Workbook
Name Scenario: Inputs!$F$8

Sheet Cover
A1: Case P: Belanou Combined Cycle Power Project, Republic of Kessara
A2: Case P companion model
A3: Units in column E; constants in column F; row totals in column G; first period in column J. Inputs: blue on yellow. Links from other sheets: green.
D4: Label | E4: Unit | F4: Constant | G4: Total
D5: Companion model for Chapters 39-45. Python mirror: model/case_p.py (source of truth).
D6: Select the scenario on the Inputs sheet (cell named Scenario):
D7: 1: FC base
D8: 2: FC banking
D9: 3: FC downside
D10: 4: Sens: availability -3 points
D11: 5: Sens: heat rate +2%
D12: 6: Sens: fixed opex +10%
D13: 7: Sens: capex +10% funded pro rata
D14: 8: Sens: COD delay 6 months, no LDs
D15: 9: Sens: base rate +200 bps (unhedged)
D16: 10: Sens: KCR devaluation 40%, 90-day lag
... D28: Sign convention: costs stored positive and subtracted explicitly.

Sheet Inputs
A1: Case P: Belanou Combined Cycle Power Project, Republic of Kessara
A2: Inputs: scenario selector, assumptions, contract terms
A3: Units in column E; constants in column F; row totals in column G; first period in column J. Inputs: blue on yellow. Links from other sheets: green.
D4: Label | E4: Unit | F4: Constant | G4: Total
D5: Scenario table: columns J-X = scenarios 1-15; semiannual rows: columns = periods; annual rows: columns = years 2015+ | J5: 2018H2 | K5: 2019H1 | L5: 2019H2 | M5: 2020H1 | N5: 2020H2 | O5: 2021H1 | P5: 2021H2 | Q5: 2022H1 | R5: 2022H2 | S5: 2023H1 | T5: 2023H2 | U5: 2024H1 | V5: 2024H2 | W5: 2025H1 | X5: 2025H2 | Y5: 2026H1 | Z5: 2026H2 | AA5: 2027H1 | AB5: 2027H2 | AC5: 2028H1 | AD5: 2028H2 | AE5: 2029H1 | AF5: 2029H2 | AG5: 2030H1 | AH5: 2030H2 | AI5: 2031H1 | AJ5: 2031H2 | AK5: 2032H1 | AL5: 2032H2 | AM5: 2033H1 | AN5: 2033H2 | AO5: 2034H1 | AP5: 2034H2 | AQ5: 2035H1 | AR5: 2035H2 | AS5: 2036H1 | AT5: 2036H2 | AU5: 2037H1 | AV5: 2037H2 | AW5: 2038H1 | AX5: 2038H2 | AY5: 2039H1 | AZ5: 2039H2 | BA5: 2040H1 | BB5: 2040H2 | BC5: 2041H1 | BD5: 2041H2 | BE5: 2042H1 | BF5: 2042H2 | BG5: 2043H1 | BH5: 2043H2 | BI5: 2044H1 | BJ5: 2044H2 | BK5: 2045H1 | BL5: 2045H2 | BM5: 2046H1 | BN5: 2046H2
B7: Scenario control
D8: Scenario selector (1-15, see table below) | E8: index | F8: 1
B9: Live scenario parameters (selected from the scenario table)
D10: Macro path (1 FC forward, 2 actual history, 3 COD re-forecast) [table] | E10: code | J10: 1 | K10: 1 | L10: 1 | M10: 1 | N10: 1 | O10: 1 | P10: 1 | Q10: 1 | R10: 1 | S10: 1 | T10: 1 | U10: 1 | V10: 1 | W10: 3 | X10: 2
D11: Construction case (1 FC budget, 2 actual) [table] | E11: code | J11: 1 | K11: 1 | L11: 1 | M11: 1 | N11: 1 | O11: 1 | P11: 1 | Q11: 1 | R11: 1 | S11: 1 | T11: 1 | U11: 1 | V11: 1 | W11: 2 | X11: 2
D12: COD delay (sensitivity) [table] | E12: months | J12: 0 | K12: 0 | L12: 0 | M12: 0 | N12: 0 | O12: 0 | P12: 0 | Q12: 6 | R12: 0 | S12: 0 | T12: 0 | U12: 0 | V12: 0 | W12: 0 | X12: 0
D13: Capex factor [table] | E13: factor | J13: 1 | K13: 1 | L13: 1 | M13: 1 | N13: 1 | O13: 1 | P13: 1.1 | Q13: 1 | R13: 1 | S13: 1 | T13: 1 | U13: 1 | V13: 1 | W13: 1 | X13: 1
D14: Availability adjustment [table] | E14: points | J14: 0 | K14: 0 | L14: -6.5 | M14: -3 | N14: 0 | O14: 0 | P14: 0 | Q14: 0 | R14: 0 | S14: 0 | T14: 0 | U14: 0 | V14: 0 | W14: 0 | X14: 0
D15: Dispatch factor when available [table] | E15: % | J15: 76.5 | K15: 72 | L15: 76.5 | M15: 76.5 | N15: 76.5 | O15: 76.5 | P15: 76.5 | Q15: 76.5 | R15: 76.5 | S15: 76.5 | T15: 76.5 | U15: 50 | V15: 76.5 | W15: 76.5 | X15: 76.5
D16: Plant heat rate factor [table] | E16: factor | J16: 1 | K16: 1 | L16: 1.015 | M16: 1 | N16: 1.02 | O16: 1 | P16: 1 | Q16: 1 | R16: 1 | S16: 1 | T16: 1 | U16: 1 | V16: 1 | W16: 1 | X16: 1
D17: Fixed opex factor [table] | E17: factor | J17: 1 | K17: 1 | L17: 1.1 | M17: 1 | N17: 1 | O17: 1.1 | P17: 1 | Q17: 1 | R17: 1 | S17: 1 | T17: 1 | U17: 1 | V17: 1 | W17: 1 | X17: 1
D18: Gas price factor [table] | E18: factor | J18: 1 | K18: 1 | L18: 1 | M18: 1 | N18: 1 | O18: 1 | P18: 1 | Q18: 1 | R18: 1 | S18: 1 | T18: 1 | U18: 1 | V18: 1.3 | W18: 1 | X18: 1
D19: Base rate shift from 2022H1 [table] | E19: % | J19: 0 | K19: 0 | L19: 0 | M19: 0 | N19: 0 | O19: 0 | P19: 0 | Q19: 0 | R19: 2 | S19: 0 | T19: 0 | U19: 0 | V19: 0 | W19: 0 | X19: 0
D20: KCR devaluation from 2022H1 [table] | E20: fraction | J20: 0 | K20: 0 | L20: 0 | M20: 0 | N20: 0 | O20: 0 | P20: 0 | Q20: 0 | R20: 0 | S20: 0.4 | T20: 0 | U20: 0 | V20: 0 | W20: 0 | X20: 0
D21: Extra days on SEKA capacity/VOM payments, 2022H1-2022H2 [table] | E21: days | J21: 0 | K21: 0 | L21: 0 | M21: 0 | N21: 0 | O21: 0 | P21: 0 | Q21: 0 | R21: 0 | S21: 90 | T21: 120 | U21: 0 | V21: 0 | W21: 0 | X21: 0
... D32: Actual 2022 dispatch path (1 = on) [table] | E32: flag | J32: 0 | K32: 0 | L32: 0 | M32: 0 | N32: 0 | O32: 0 | P32: 0 | Q32: 0 | R32: 0 | S32: 0 | T32: 0 | U32: 0 | V32: 0 | W32: 0 | X32: 1
D33: Macro path (1 FC forward, 2 actual history, 3 COD re-forecast) | E33: code | F33: =INDEX($J$10:$X$10,1,Scenario)
D34: Construction case (1 FC budget, 2 actual) | E34: code | F34: =INDEX($J$11:$X$11,1,Scenario)
D35: COD delay (sensitivity) | E35: months | F35: =INDEX($J$12:$X$12,1,Scenario)
D36: Capex factor | E36: factor | F36: =INDEX($J$13:$X$13,1,Scenario)
D37: Availability adjustment | E37: points | F37: =INDEX($J$14:$X$14,1,Scenario)
D38: Dispatch factor when available | E38: % | F38: =INDEX($J$15:$X$15,1,Scenario)
D39: Plant heat rate factor | E39: factor | F39: =INDEX($J$16:$X$16,1,Scenario)
D40: Fixed opex factor | E40: factor | F40: =INDEX($J$17:$X$17,1,Scenario)
D41: Gas price factor | E41: factor | F41: =INDEX($J$18:$X$18,1,Scenario)
D42: Base rate shift from 2022H1 | E42: % | F42: =INDEX($J$19:$X$19,1,Scenario)
D43: KCR devaluation from 2022H1 | E43: fraction | F43: =INDEX($J$20:$X$20,1,Scenario)
D44: Extra days on SEKA capacity/VOM payments, 2022H1-2022H2 | E44: days | F44: =INDEX($J$21:$X$21,1,Scenario)
D45: Offtaker crisis events (1 = on) | E45: flag | F45: =INDEX($J$22:$X$22,1,Scenario)
D46: Insurance market step-up from 2022H2 (1 = on) | E46: flag | F46: =INDEX($J$23:$X$23,1,Scenario)
D47: Repayment profile (1 FC contract, 2 COD re-sculpted) | E47: code | F47: =INDEX($J$24:$X$24,1,Scenario)
D48: Performance LD prepayment June 2022 (1 = on) | E48: flag | F48: =INDEX($J$25:$X$25,1,Scenario)
D49: Waiver and amendment 2023 (1 = on) | E49: flag | F49: =INDEX($J$26:$X$26,1,Scenario)
D50: 2025 bond refinancing (1 = on) | E50: flag | F50: =INDEX($J$27:$X$27,1,Scenario)
D51: Funding mode (1 committed amounts, 2 re-grossed pro rata) | E51: code | F51: =INDEX($J$28:$X$28,1,Scenario)
D52: Soft mini-perm sweep (1 = on) | E52: flag | F52: =INDEX($J$29:$X$29,1,Scenario)
D53: Shareholder loan share of equity | E53: fraction | F53: =INDEX($J$30:$X$30,1,Scenario)
D54: Capital charge factor | E54: factor | F54: =INDEX($J$31:$X$31,1,Scenario)
D55: Actual 2022 dispatch path (1 = on) | E55: flag | F55: =INDEX($J$32:$X$32,1,Scenario)
B56: Capital cost (USD m unless stated)
D57: EPC contract price | E57: USD m | F57: 571.84
D58: of which offshore portion | E58: USD m | F58: 489.17
D59: of which onshore portion | E59: USD m | F59: 82.67
D60: Onshore portion fixed in KCR at | E60: KCR/USD | F60: 519.4
D61: Owner's costs | E61: USD m | F61: 46.18
D62: Insurance during construction | E62: USD m | F62: 7.62
D63: Development costs reimbursed at FC | E63: USD m | F63: 21.43
D64: Development fee at FC | E64: USD m | F64: 11.2
D65: Lenders' advisors and legal | E65: USD m | F65: 8.97
D66: Contingency | E66: USD m | F66: 38.4
D67: Initial working capital (spares, fuel) | E67: USD m | F67: 5.35
D68: LNTP paid February 2018 (equity credit at FC) | E68: USD m | F68: 14.2
... D73: Policy rate, FC expectation | E73: % | F73: 13.5
B74: Senior debt terms
D75: ECA-covered tranche share | E75: fraction | F75: 0.3
D76: ABDB A-loan share | E76: fraction | F76: 0.22
D77: ABDB B-loan share | E77: fraction | F77: 0.1
D78: Commercial tranche share | E78: fraction | F78: 0.38
D79: ECA margin | E79: % | F79: 1.35
D80: A-loan margin | E80: % | F80: 3.65
D81: B-loan margin | E81: % | F81: 3.4
D82: Commercial margin to 2025 | E82: % | F82: 4.1
D83: Commercial margin 2026-2029 | E83: % | F83: 4.6
D84: Commercial margin from 2030 | E84: % | F84: 5.1
D85: ECA commitment fee | E85: % pa | F85: 0.45
D86: A-loan commitment fee | E86: % pa | F86: 0.75
... D111: Soft mini-perm sweep share (from 2027) | E111: fraction | F111: 0.5
B112: Contract terms fixed at financial close (from the FC base sizing run)
D113: Senior debt commitment (total, 4 tranches) | E113: USD m | F113: 654.63356
D114: Equity commitment (base, incl. LNTP) | E114: USD m | F114: 205.2822
B115: Plant and PPA
D116: Contracted capacity (FC) | E116: MW | F116: 588.4
D117: Contracted capacity after tests | E117: MW | F117: 581.9
D118: Guaranteed net heat rate | E118: kJ/kWh | F118: 6261
D119: Tested net heat rate | E119: kJ/kWh | F119: 6286
D120: PPA contracted heat rate | E120: kJ/kWh | F120: 6323
D121: Contracted HR degradation allowance | E121: % pa | F121: 0.1
D122: Average part-load penalty | E122: % | F122: 2.3
D123: HHV/LHV ratio | E123: factor | F123: 1.108
D124: kJ per MMBtu | E124: kJ | F124: 1055056
D125: Output degradation, non-recoverable | E125: % pa | F125: 0.15
D126: Output degradation, recoverable average | E126: % | F126: 1
D127: Heat-rate degradation, non-recoverable | E127: % pa | F127: 0.12
... D140: VOM US CPI share | E140: fraction | F140: 0.7
B141: Fuel and transport
D142: GSA gas price 2018 | E142: USD/MMBtu | F142: 5.86
D143: GSA escalation | E143: % pa | F143: 2
D144: Daily contract quantity | E144: MMBtu/d | F144: 72400
D145: Take-or-pay level | E145: fraction | F145: 0.8
D146: GTA reserved capacity | E146: MMBtu/d | F146: 96500
D147: GTA reservation charge 2018 | E147: USD/MMBtu | F147: 0.62
D148: GTA commodity charge 2018 | E148: USD/MMBtu | F148: 0.19
D149: GTA escalation | E149: % pa | F149: 1.5
B150: Operating costs (2018 prices)
D151: O&M fixed fee | E151: USD m pa | F151: 7.92
...

Sheet Time
A1: Case P: Belanou Combined Cycle Power Project, Republic of Kessara
A2: Time: semiannual operating timeline (monthly timeline on the Construction sheet)
A3: Units in column E; constants in column F; row totals in column G; first period in column J. Inputs: blue on yellow. Links from other sheets: green.
D4: Label | E4: Unit | F4: Constant | G4: Total
D5: Period ending | J5: 2018H2 | K5: 2019H1 | L5: 2019H2 | M5: 2020H1 | N5: 2020H2 | O5: 2021H1 | P5: 2021H2 | Q5: 2022H1 | R5: 2022H2 | S5: 2023H1 | T5: 2023H2 | U5: 2024H1 | V5: 2024H2 | W5: 2025H1 | X5: 2025H2 | Y5: 2026H1 | Z5: 2026H2 | AA5: 2027H1 | AB5: 2027H2 | AC5: 2028H1 | AD5: 2028H2 | AE5: 2029H1 | AF5: 2029H2 | AG5: 2030H1 | AH5: 2030H2 | AI5: 2031H1 | AJ5: 2031H2 | AK5: 2032H1 | AL5: 2032H2 | AM5: 2033H1 | AN5: 2033H2 | AO5: 2034H1 | AP5: 2034H2 | AQ5: 2035H1 | AR5: 2035H2 | AS5: 2036H1 | AT5: 2036H2 | AU5: 2037H1 | AV5: 2037H2 | AW5: 2038H1 | AX5: 2038H2 | AY5: 2039H1 | AZ5: 2039H2 | BA5: 2040H1 | BB5: 2040H2 | BC5: 2041H1 | BD5: 2041H2 | BE5: 2042H1 | BF5: 2042H2 | BG5: 2043H1 | BH5: 2043H2 | BI5: 2044H1 | BJ5: 2044H2 | BK5: 2045H1 | BL5: 2045H2 | BM5: 2046H1 | BN5: 2046H2
B7: Key dates (scenario-dependent)
D8: Commercial operation date | E8: date | F8: =IF(Inputs!$F$34<>1,Inputs!$F$191,EDATE(Inputs!$F$190,Inputs!$F$35))
D9: PPA term | E9: months | F9: =Inputs!$F$210*12
D10: PPA expiry | E10: date | F10: =EDATE(Time!$F$8,Time!$F$9)-1
D11: Construction months (NTP to COD) | E11: months | F11: =(YEAR(Time!$F$8)-YEAR(Inputs!$F$188))*12+MONTH(Time!$F$8)-MONTH(Inputs!$F$188)
D12: Period containing COD (period number) | E12: index | F12: =MATCH($F$8,$J$22:$BN$22,1)
D13: First debt service period | E13: index | F13: =Time!$F$12+1
D14: Last month of the funding period (month number) | E14: index | F14: =MATCH(INDEX($J$23:$BN$23,1,$F$12),Construction!$J$10:$BJ$10,0)
D15: Last operating period (period number) | E15: index | F15: =SUMPRODUCT($J$37:$BN$37,$J$20:$BN$20)
D16: FC FX drift per year (Kessara / US CPI expectations) | E16: factor | F16: =(1+Inputs!$F$213/100)/(1+Inputs!$F$214/100)
D17: Refinancing period (period number) | E17: index | F17: =MATCH(Inputs!$F$205,$J$23:$BN$23,0)
D18: Deferral period (period number) | E18: index | F18: =MATCH(Inputs!$F$200,$J$23:$BN$23,0)
B19: Semiannual timeline
D20: Period number | E20: index | J20: =I20+1 | K20: =J20+1 | L20: =K20+1 | M20: =L20+1 | N20: =M20+1 | O20: =N20+1 | P20: =O20+1 | Q20: =P20+1 | ... BN20: =BM20+1
D21: Months per period | E21: months | J21: =Inputs!$F$226 | K21: =Inputs!$F$226 | L21: =Inputs!$F$226 | M21: =Inputs!$F$226 | N21: =Inputs!$F$226 | O21: =Inputs!$F$226 | P21: =Inputs!$F$226 | Q21: =Inputs!$F$226 | ... BN21: =Inputs!$F$226
D22: Period start | E22: date | J22: =IF(J20=1,Inputs!$F$189,EDATE(I22,J21)) | K22: =IF(K20=1,Inputs!$F$189,EDATE(J22,K21)) | L22: =IF(L20=1,Inputs!$F$189,EDATE(K22,L21)) | M22: =IF(M20=1,Inputs!$F$189,EDATE(L22,M21)) | N22: =IF(N20=1,Inputs!$F$189,EDATE(M22,N21)) | O22: =IF(O20=1,Inputs!$F$189,EDATE(N22,O21)) | P22: =IF(P20=1,Inputs!$F$189,EDATE(O22,P21)) | Q22: =IF(Q20=1,Inputs!$F$189,EDATE(P22,Q21)) | ... BN22: =IF(BN20=1,Inputs!$F$189,EDATE(BM22,BN21))
D23: Period end | E23: date | J23: =EOMONTH(J22,J21-1) | K23: =EOMONTH(K22,K21-1) | L23: =EOMONTH(L22,L21-1) | M23: =EOMONTH(M22,M21-1) | N23: =EOMONTH(N22,N21-1) | O23: =EOMONTH(O22,O21-1) | P23: =EOMONTH(P22,P21-1) | Q23: =EOMONTH(Q22,Q21-1) | ... BN23: =EOMONTH(BN22,BN21-1)
D24: Year fraction 30/360 (months / 12) | E24: factor | J24: =J21/12 | K24: =K21/12 | L24: =L21/12 | M24: =M21/12 | N24: =N21/12 | O24: =O21/12 | P24: =P21/12 | Q24: =Q21/12 | ... BN24: =BN21/12
D25: Days in period | E25: days | J25: =J23-J22+1 | K25: =K23-K22+1 | L25: =L23-L22+1 | M25: =M23-M22+1 | N25: =N23-N22+1 | O25: =O23-O22+1 | P25: =P23-P22+1 | Q25: =Q23-Q22+1 | ... BN25: =BN23-BN22+1
D26: Calendar year | E26: year | J26: =YEAR(J22) | K26: =YEAR(K22) | L26: =YEAR(L22) | M26: =YEAR(M22) | N26: =YEAR(N22) | O26: =YEAR(O22) | P26: =YEAR(P22) | Q26: =YEAR(Q22) | ... BN26: =YEAR(BN22)
D27: Flag_FirstHalf (Jan-Jun) | E27: flag | J27: =IF(MONTH(J22)=1,1,0) | K27: =IF(MONTH(K22)=1,1,0) | L27: =IF(MONTH(L22)=1,1,0) | M27: =IF(MONTH(M22)=1,1,0) | N27: =IF(MONTH(N22)=1,1,0) | O27: =IF(MONTH(O22)=1,1,0) | P27: =IF(MONTH(P22)=1,1,0) | Q27: =IF(MONTH(Q22)=1,1,0) | ... BN27: =IF(MONTH(BN22)=1,1,0)
D28: Operations start in period | E28: date | J28: =MAX(J22,$F$8) | K28: =MAX(K22,$F$8) | L28: =MAX(L22,$F$8) | M28: =MAX(M22,$F$8) | N28: =MAX(N22,$F$8) | O28: =MAX(O22,$F$8) | P28: =MAX(P22,$F$8) | Q28: =MAX(Q22,$F$8) | ... BN28: =MAX(BN22,$F$8)
D29: Operations end in period | E29: date | J29: =MIN(J23,$F$10) | K29: =MIN(K23,$F$10) | L29: =MIN(L23,$F$10) | M29: =MIN(M23,$F$10) | N29: =MIN(N23,$F$10) | O29: =MIN(O23,$F$10) | P29: =MIN(P23,$F$10) | Q29: =MIN(Q23,$F$10) | ... BN29: =MIN(BN23,$F$10)
D30: Operating months in period | E30: months | J30: =IF(J29>=J28,(YEAR(J29)-YEAR(J28))*12+MONTH(J29)-MONTH(J28)+1,0) | K30: =IF(K29>=K28,(YEAR(K29)-YEAR(K28))*12+MONTH(K29)-MONTH(K28)+1,0) | L30: =IF(L29>=L28,(YEAR(L29)-YEAR(L28))*12+MONTH(L29)-MONTH(L28)+1,0) | M30: =IF(M29>=M28,(YEAR(M29)-YEAR(M28))*12+MONTH(M29)-MONTH(M28)+1,0) | N30: =IF(N29>=N28,(YEAR(N29)-YEAR(N28))*12+MONTH(N29)-MONTH(N28)+1,0) | O30: =IF(O29>=O28,(YEAR(O29)-YEAR(O28))*12+MONTH(O29)-MONTH(O28)+1,0) | P30: =IF(P29>=P28,(YEAR(P29)-YEAR(P28))*12+MONTH(P29)-MONTH(P28)+1,0) | Q30: =IF(Q29>=Q28,(YEAR(Q29)-YEAR(Q28))*12+MONTH(Q29)-MONTH(Q28)+1,0) | ... BN30: =IF(BN29>=BN28,(YEAR(BN29)-YEAR(BN28))*12+MONTH(BN29)-MONTH(BN28)+1,0)
D31: Operating days in period | E31: days | J31: =IF(J29>=J28,J29-J28+1,0) | K31: =IF(K29>=K28,K29-K28+1,0) | L31: =IF(L29>=L28,L29-L28+1,0) | M31: =IF(M29>=M28,M29-M28+1,0) | N31: =IF(N29>=N28,N29-N28+1,0) | O31: =IF(O29>=O28,O29-O28+1,0) | P31: =IF(P29>=P28,P29-P28+1,0) | Q31: =IF(Q29>=Q28,Q29-Q28+1,0) | ... BN31: =IF(BN29>=BN28,BN29-BN28+1,0)
D32: Operating months elapsed at period start | E32: months | J32: =MIN(MAX((YEAR(J22)-YEAR($F$8))*12+MONTH(J22)-MONTH($F$8),0),$F$9) | K32: =MIN(MAX((YEAR(K22)-YEAR($F$8))*12+MONTH(K22)-MONTH($F$8),0),$F$9) | L32: =MIN(MAX((YEAR(L22)-YEAR($F$8))*12+MONTH(L22)-MONTH($F$8),0),$F$9) | M32: =MIN(MAX((YEAR(M22)-YEAR($F$8))*12+MONTH(M22)-MONTH($F$8),0),$F$9) | N32: =MIN(MAX((YEAR(N22)-YEAR($F$8))*12+MONTH(N22)-MONTH($F$8),0),$F$9) | O32: =MIN(MAX((YEAR(O22)-YEAR($F$8))*12+MONTH(O22)-MONTH($F$8),0),$F$9) | P32: =MIN(MAX((YEAR(P22)-YEAR($F$8))*12+MONTH(P22)-MONTH($F$8),0),$F$9) | Q32: =MIN(MAX((YEAR(Q22)-YEAR($F$8))*12+MONTH(Q22)-MONTH($F$8),0),$F$9) | ... BN32: =MIN(MAX((YEAR(BN22)-YEAR($F$8))*12+MONTH(BN22)-MONTH($F$8),0),$F$9)
D33: Operating months elapsed at period end | E33: months | J33: =J32+J30 | K33: =K32+K30 | L33: =L32+L30 | M33: =M32+M30 | N33: =N32+N30 | O33: =O32+O30 | P33: =P32+P30 | Q33: =Q32+Q30 | ... BN33: =BN32+BN30
D34: Flag_CODPeriod | E34: flag | J34: =IF(J20=$F$12,1,0) | K34: =IF(K20=$F$12,1,0) | L34: =IF(L20=$F$12,1,0) | M34: =IF(M20=$F$12,1,0) | N34: =IF(N20=$F$12,1,0) | O34: =IF(O20=$F$12,1,0) | P34: =IF(P20=$F$12,1,0) | Q34: =IF(Q20=$F$12,1,0) | ... BN34: =IF(BN20=$F$12,1,0)
D35: Flag_DebtService (after COD period) | E35: flag | J35: =IF(J20>$F$12,1,0) | K35: =IF(K20>$F$12,1,0) | L35: =IF(L20>$F$12,1,0) | M35: =IF(M20>$F$12,1,0) | N35: =IF(N20>$F$12,1,0) | O35: =IF(O20>$F$12,1,0) | P35: =IF(P20>$F$12,1,0) | Q35: =IF(Q20>$F$12,1,0) | ... BN35: =IF(BN20>$F$12,1,0)
D36: Flag_Operations | E36: flag | J36: =IF(J30>0,1,0) | K36: =IF(K30>0,1,0) | L36: =IF(L30>0,1,0) | M36: =IF(M30>0,1,0) | N36: =IF(N30>0,1,0) | O36: =IF(O30>0,1,0) | P36: =IF(P30>0,1,0) | Q36: =IF(Q30>0,1,0) | ... BN36: =IF(BN30>0,1,0)
D37: Flag_LastOperatingPeriod | E37: flag | J37: =IF(AND(J30>0,K30=0),1,0) | K37: =IF(AND(K30>0,L30=0),1,0) | L37: =IF(AND(L30>0,M30=0),1,0) | M37: =IF(AND(M30>0,N30=0),1,0) | N37: =IF(AND(N30>0,O30=0),1,0) | O37: =IF(AND(O30>0,P30=0),1,0) | P37: =IF(AND(P30>0,Q30=0),1,0) | Q37: =IF(AND(Q30>0,R30=0),1,0) | ... BN37: =IF(AND(BN30>0,BO30=0),1,0)
D38: Flag_ShockPeriods | E38: flag | J38: =IF(AND(J22>=Inputs!$F$193,J22<EDATE(Inputs!$F$193,Inputs!$F$211)),1,0) | K38: =IF(AND(K22>=Inputs!$F$193,K22<EDATE(Inputs!$F$193,Inputs!$F$211)),1,0) | L38: =IF(AND(L22>=Inputs!$F$193,L22<EDATE(Inputs!$F$193,Inputs!$F$211)),1,0) | M38: =IF(AND(M22>=Inputs!$F$193,M22<EDATE(Inputs!$F$193,Inputs!$F$211)),1,0) | N38: =IF(AND(N22>=Inputs!$F$193,N22<EDATE(Inputs!$F$193,Inputs!$F$211)),1,0) | O38: =IF(AND(O22>=Inputs!$F$193,O22<EDATE(Inputs!$F$193,Inputs!$F$211)),1,0) | P38: =IF(AND(P22>=Inputs!$F$193,P22<EDATE(Inputs!$F$193,Inputs!$F$211)),1,0) | Q38: =IF(AND(Q22>=Inputs!$F$193,Q22<EDATE(Inputs!$F$193,Inputs!$F$211)),1,0) | ... BN38: =IF(AND(BN22>=Inputs!$F$193,BN22<EDATE(Inputs!$F$193,Inputs!$F$211)),1,0)
D39: Flag_FromShockStart | E39: flag | J39: =IF(J22>=Inputs!$F$193,1,0) | K39: =IF(K22>=Inputs!$F$193,1,0) | L39: =IF(L22>=Inputs!$F$193,1,0) | M39: =IF(M22>=Inputs!$F$193,1,0) | N39: =IF(N22>=Inputs!$F$193,1,0) | O39: =IF(O22>=Inputs!$F$193,1,0) | P39: =IF(P22>=Inputs!$F$193,1,0) | Q39: =IF(Q22>=Inputs!$F$193,1,0) | ... BN39: =IF(BN22>=Inputs!$F$193,1,0)
D40: Flag_TermSOFR | E40: flag | J40: =IF(J22>=Inputs!$F$196,1,0) | K40: =IF(K22>=Inputs!$F$196,1,0) | L40: =IF(L22>=Inputs!$F$196,1,0) | M40: =IF(M22>=Inputs!$F$196,1,0) | N40: =IF(N22>=Inputs!$F$196,1,0) | O40: =IF(O22>=Inputs!$F$196,1,0) | P40: =IF(P22>=Inputs!$F$196,1,0) | Q40: =IF(Q22>=Inputs!$F$196,1,0) | ... BN40: =IF(BN22>=Inputs!$F$196,1,0)
D41: Flag_InsuranceStepUp | E41: flag | J41: =IF(J22>=Inputs!$F$195,1,0) | K41: =IF(K22>=Inputs!$F$195,1,0) | L41: =IF(L22>=Inputs!$F$195,1,0) | M41: =IF(M22>=Inputs!$F$195,1,0) | N41: =IF(N22>=Inputs!$F$195,1,0) | O41: =IF(O22>=Inputs!$F$195,1,0) | P41: =IF(P22>=Inputs!$F$195,1,0) | Q41: =IF(Q22>=Inputs!$F$195,1,0) | ... BN41: =IF(BN22>=Inputs!$F$195,1,0)
D42: Flag_LDPrepayment | E42: flag | J42: =Inputs!$F$48*IF(J23=Inputs!$F$198,1,0) | K42: =Inputs!$F$48*IF(K23=Inputs!$F$198,1,0) | L42: =Inputs!$F$48*IF(L23=Inputs!$F$198,1,0) | M42: =Inputs!$F$48*IF(M23=Inputs!$F$198,1,0) | N42: =Inputs!$F$48*IF(N23=Inputs!$F$198,1,0) | O42: =Inputs!$F$48*IF(O23=Inputs!$F$198,1,0) | P42: =Inputs!$F$48*IF(P23=Inputs!$F$198,1,0) | Q42: =Inputs!$F$48*IF(Q23=Inputs!$F$198,1,0) | ... BN42: =Inputs!$F$48*IF(BN23=Inputs!$F$198,1,0)
D43: Flag_WaiverDeferral | E43: flag | J43: =Inputs!$F$49*IF(J23=Inputs!$F$200,1,0) | K43: =Inputs!$F$49*IF(K23=Inputs!$F$200,1,0) | L43: =Inputs!$F$49*IF(L23=Inputs!$F$200,1,0) | M43: =Inputs!$F$49*IF(M23=Inputs!$F$200,1,0) | N43: =Inputs!$F$49*IF(N23=Inputs!$F$200,1,0) | O43: =Inputs!$F$49*IF(O23=Inputs!$F$200,1,0) | P43: =Inputs!$F$49*IF(P23=Inputs!$F$200,1,0) | Q43: =Inputs!$F$49*IF(Q23=Inputs!$F$200,1,0) | ... BN43: =Inputs!$F$49*IF(BN23=Inputs!$F$200,1,0)
D44: Flag_MarginUplift | E44: flag | J44: =Inputs!$F$49*IF(AND(J22>=Inputs!$F$201,J23<=Inputs!$F$202),1,0) | K44: =Inputs!$F$49*IF(AND(K22>=Inputs!$F$201,K23<=Inputs!$F$202),1,0) | L44: =Inputs!$F$49*IF(AND(L22>=Inputs!$F$201,L23<=Inputs!$F$202),1,0) | M44: =Inputs!$F$49*IF(AND(M22>=Inputs!$F$201,M23<=Inputs!$F$202),1,0) | N44: =Inputs!$F$49*IF(AND(N22>=Inputs!$F$201,N23<=Inputs!$F$202),1,0) | O44: =Inputs!$F$49*IF(AND(O22>=Inputs!$F$201,O23<=Inputs!$F$202),1,0) | P44: =Inputs!$F$49*IF(AND(P22>=Inputs!$F$201,P23<=Inputs!$F$202),1,0) | Q44: =Inputs!$F$49*IF(AND(Q22>=Inputs!$F$201,Q23<=Inputs!$F$202),1,0) | ... BN44: =Inputs!$F$49*IF(AND(BN22>=Inputs!$F$201,BN23<=Inputs!$F$202),1,0)
D45: Flag_DeferredRepayment | E45: flag | J45: =Inputs!$F$49*IF(AND(J23>=Inputs!$F$203,J23<=Inputs!$F$204),1,0) | K45: =Inputs!$F$49*IF(AND(K23>=Inputs!$F$203,K23<=Inputs!$F$204),1,0) | L45: =Inputs!$F$49*IF(AND(L23>=Inputs!$F$203,L23<=Inputs!$F$204),1,0) | M45: =Inputs!$F$49*IF(AND(M23>=Inputs!$F$203,M23<=Inputs!$F$204),1,0) | N45: =Inputs!$F$49*IF(AND(N23>=Inputs!$F$203,N23<=Inputs!$F$204),1,0) | O45: =Inputs!$F$49*IF(AND(O23>=Inputs!$F$203,O23<=Inputs!$F$204),1,0) | P45: =Inputs!$F$49*IF(AND(P23>=Inputs!$F$203,P23<=Inputs!$F$204),1,0) | Q45: =Inputs!$F$49*IF(AND(Q23>=Inputs!$F$203,Q23<=Inputs!$F$204),1,0) | ... BN45: =Inputs!$F$49*IF(AND(BN23>=Inputs!$F$203,BN23<=Inputs!$F$204),1,0)
D46: Deferred repayments remaining (this and later periods) | E46: count | J46: =SUM(J45:BN45) | K46: =SUM(K45:BN45) | L46: =SUM(L45:BN45) | M46: =SUM(M45:BN45) | N46: =SUM(N45:BN45) | O46: =SUM(O45:BN45) | P46: =SUM(P45:BN45) | Q46: =SUM(Q45:BN45) | R46: =SUM(R45:BN45) | S46: =SUM(S45:BN45) | T46: =SUM(T45:BN45) | U46: =SUM(U45:BN45) | V46: =SUM(V45:BN45) | W46: =SUM(W45:BN45) | X46: =SUM(X45:BN45) | Y46: =SUM(Y45:BN45) | Z46: =SUM(Z45:BN45) | AA46: =SUM(AA45:BN45) | AB46: =SUM(AB45:BN45) | AC46: =SUM(AC45:BN45) | AD46: =SUM(AD45:BN45) | AE46: =SUM(AE45:BN45) | AF46: =SUM(AF45:BN45) | AG46: =SUM(AG45:BN45) | AH46: =SUM(AH45:BN45) | AI46: =SUM(AI45:BN45) | AJ46: =SUM(AJ45:BN45) | AK46: =SUM(AK45:BN45) | AL46: =SUM(AL45:BN45) | AM46: =SUM(AM45:BN45) | AN46: =SUM(AN45:BN45) | AO46: =SUM(AO45:BN45) | AP46: =SUM(AP45:BN45) | AQ46: =SUM(AQ45:BN45) | AR46: =SUM(AR45:BN45) | AS46: =SUM(AS45:BN45) | AT46: =SUM(AT45:BN45) | AU46: =SUM(AU45:BN45) | AV46: =SUM(AV45:BN45) | AW46: =SUM(AW45:BN45) | AX46: =SUM(AX45:BN45) | AY46: =SUM(AY45:BN45) | AZ46: =SUM(AZ45:BN45) | BA46: =SUM(BA45:BN45) | BB46: =SUM(BB45:BN45) | BC46: =SUM(BC45:BN45) | BD46: =SUM(BD45:BN45) | BE46: =SUM(BE45:BN45) | BF46: =SUM(BF45:BN45) | BG46: =SUM(BG45:BN45) | BH46: =SUM(BH45:BN45) | BI46: =SUM(BI45:BN45) | BJ46: =SUM(BJ45:BN45) | BK46: =SUM(BK45:BN45) | BL46: =SUM(BL45:BN45) | BM46: =SUM(BM45:BN45) | BN46: =SUM(BN45:BN45)
D47: Flag_Refinancing | E47: flag | J47: =Inputs!$F$50*IF(J23=Inputs!$F$205,1,0) | K47: =Inputs!$F$50*IF(K23=Inputs!$F$205,1,0) | L47: =Inputs!$F$50*IF(L23=Inputs!$F$205,1,0) | M47: =Inputs!$F$50*IF(M23=Inputs!$F$205,1,0) | N47: =Inputs!$F$50*IF(N23=Inputs!$F$205,1,0) | O47: =Inputs!$F$50*IF(O23=Inputs!$F$205,1,0) | P47: =Inputs!$F$50*IF(P23=Inputs!$F$205,1,0) | Q47: =Inputs!$F$50*IF(Q23=Inputs!$F$205,1,0) | ... BN47: =Inputs!$F$50*IF(BN23=Inputs!$F$205,1,0)
D48: Flag_AfterRefinancing | E48: flag | J48: =Inputs!$F$50*IF(J23>Inputs!$F$205,1,0) | K48: =Inputs!$F$50*IF(K23>Inputs!$F$205,1,0) | L48: =Inputs!$F$50*IF(L23>Inputs!$F$205,1,0) | M48: =Inputs!$F$50*IF(M23>Inputs!$F$205,1,0) | N48: =Inputs!$F$50*IF(N23>Inputs!$F$205,1,0) | O48: =Inputs!$F$50*IF(O23>Inputs!$F$205,1,0) | P48: =Inputs!$F$50*IF(P23>Inputs!$F$205,1,0) | Q48: =Inputs!$F$50*IF(Q23>Inputs!$F$205,1,0) | ... BN48: =Inputs!$F$50*IF(BN23>Inputs!$F$205,1,0)
D49: Flag_TestWaived | E49: flag | J49: =Inputs!$F$49*IF(AND(J23>=Inputs!$F$199,J23<=Inputs!$F$200),1,0) | K49: =Inputs!$F$49*IF(AND(K23>=Inputs!$F$199,K23<=Inputs!$F$200),1,0) | L49: =Inputs!$F$49*IF(AND(L23>=Inputs!$F$199,L23<=Inputs!$F$200),1,0) | M49: =Inputs!$F$49*IF(AND(M23>=Inputs!$F$199,M23<=Inputs!$F$200),1,0) | N49: =Inputs!$F$49*IF(AND(N23>=Inputs!$F$199,N23<=Inputs!$F$200),1,0) | O49: =Inputs!$F$49*IF(AND(O23>=Inputs!$F$199,O23<=Inputs!$F$200),1,0) | P49: =Inputs!$F$49*IF(AND(P23>=Inputs!$F$199,P23<=Inputs!$F$200),1,0) | Q49: =Inputs!$F$49*IF(AND(Q23>=Inputs!$F$199,Q23<=Inputs!$F$200),1,0) | ... BN49: =Inputs!$F$49*IF(AND(BN23>=Inputs!$F$199,BN23<=Inputs!$F$200),1,0)
D50: Flag_WaiverRegime | E50: flag | J50: =Inputs!$F$49*IF(J23>=Inputs!$F$199,1,0) | K50: =Inputs!$F$49*IF(K23>=Inputs!$F$199,1,0) | L50: =Inputs!$F$49*IF(L23>=Inputs!$F$199,1,0) | M50: =Inputs!$F$49*IF(M23>=Inputs!$F$199,1,0) | N50: =Inputs!$F$49*IF(N23>=Inputs!$F$199,1,0) | O50: =Inputs!$F$49*IF(O23>=Inputs!$F$199,1,0) | P50: =Inputs!$F$49*IF(P23>=Inputs!$F$199,1,0) | Q50: =Inputs!$F$49*IF(Q23>=Inputs!$F$199,1,0) | ... BN50: =Inputs!$F$49*IF(BN23>=Inputs!$F$199,1,0)
D51: Flag_AfterWaivedTests | E51: flag | J51: =Inputs!$F$49*IF(J23>Inputs!$F$200,1,0) | K51: =Inputs!$F$49*IF(K23>Inputs!$F$200,1,0) | L51: =Inputs!$F$49*IF(L23>Inputs!$F$200,1,0) | M51: =Inputs!$F$49*IF(M23>Inputs!$F$200,1,0) | N51: =Inputs!$F$49*IF(N23>Inputs!$F$200,1,0) | O51: =Inputs!$F$49*IF(O23>Inputs!$F$200,1,0) | P51: =Inputs!$F$49*IF(P23>Inputs!$F$200,1,0) | Q51: =Inputs!$F$49*IF(Q23>Inputs!$F$200,1,0) | ... BN51: =Inputs!$F$49*IF(BN23>Inputs!$F$200,1,0)
D52: Flag_MiniPermSweep | E52: flag | J52: =IF(J22>=Inputs!$F$206,1,0) | K52: =IF(K22>=Inputs!$F$206,1,0) | L52: =IF(L22>=Inputs!$F$206,1,0) | M52: =IF(M22>=Inputs!$F$206,1,0) | N52: =IF(N22>=Inputs!$F$206,1,0) | O52: =IF(O22>=Inputs!$F$206,1,0) | P52: =IF(P22>=Inputs!$F$206,1,0) | Q52: =IF(Q22>=Inputs!$F$206,1,0) | ... BN52: =IF(BN22>=Inputs!$F$206,1,0)
D53: Flag_SculptingPeriod (first repayment to final maturity) | E53: flag | J53: =IF(AND(J20>=$F$13,J23<=Inputs!$F$192),1,0) | K53: =IF(AND(K20>=$F$13,K23<=Inputs!$F$192),1,0) | L53: =IF(AND(L20>=$F$13,L23<=Inputs!$F$192),1,0) | M53: =IF(AND(M20>=$F$13,M23<=Inputs!$F$192),1,0) | N53: =IF(AND(N20>=$F$13,N23<=Inputs!$F$192),1,0) | O53: =IF(AND(O20>=$F$13,O23<=Inputs!$F$192),1,0) | P53: =IF(AND(P20>=$F$13,P23<=Inputs!$F$192),1,0) | Q53: =IF(AND(Q20>=$F$13,Q23<=Inputs!$F$192),1,0) | ... BN53: =IF(AND(BN20>=$F$13,BN23<=Inputs!$F$192),1,0)
D54: Flag_ReforecastProjection | E54: flag | J54: =IF(J22>=Inputs!$F$194,1,0) | K54: =IF(K22>=Inputs!$F$194,1,0) | L54: =IF(L22>=Inputs!$F$194,1,0) | M54: =IF(M22>=Inputs!$F$194,1,0) | N54: =IF(N22>=Inputs!$F$194,1,0) | O54: =IF(O22>=Inputs!$F$194,1,0) | P54: =IF(P22>=Inputs!$F$194,1,0) | Q54: =IF(Q22>=Inputs!$F$194,1,0) | ... BN54: =IF(BN22>=Inputs!$F$194,1,0)
D55: Days of late-payment interest accrual to settlement | E55: days | J55: =MAX(0,MIN(J25,Inputs!$F$197-J22)) | K55: =MAX(0,MIN(K25,Inputs!$F$197-K22)) | L55: =MAX(0,MIN(L25,Inputs!$F$197-L22)) | M55: =MAX(0,MIN(M25,Inputs!$F$197-M22)) | N55: =MAX(0,MIN(N25,Inputs!$F$197-N22)) | O55: =MAX(0,MIN(O25,Inputs!$F$197-O22)) | P55: =MAX(0,MIN(P25,Inputs!$F$197-P22)) | Q55: =MAX(0,MIN(Q25,Inputs!$F$197-Q22)) | ... BN55: =MAX(0,MIN(BN25,Inputs!$F$197-BN22))

Sheet Construction
A1: Case P: Belanou Combined Cycle Power Project, Republic of Kessara
A2: Construction: monthly uses of funds before financing costs, VAT
A3: Units in column E; constants in column F; row totals in column G; first period in column J. Inputs: blue on yellow. Links from other sheets: green.
D4: Label | E4: Unit | F4: Constant | G4: Total
D5: Month | J5: 2018-08 | K5: 2018-09 | L5: 2018-10 | M5: 2018-11 | N5: 2018-12 | O5: 2019-01 | P5: 2019-02 | Q5: 2019-03 | R5: 2019-04 | S5: 2019-05 | T5: 2019-06 | U5: 2019-07 | V5: 2019-08 | W5: 2019-09 | X5: 2019-10 | Y5: 2019-11 | Z5: 2019-12 | AA5: 2020-01 | AB5: 2020-02 | AC5: 2020-03 | AD5: 2020-04 | AE5: 2020-05 | AF5: 2020-06 | AG5: 2020-07 | AH5: 2020-08 | AI5: 2020-09 | AJ5: 2020-10 | AK5: 2020-11 | AL5: 2020-12 | AM5: 2021-01 | AN5: 2021-02 | AO5: 2021-03 | AP5: 2021-04 | AQ5: 2021-05 | AR5: 2021-06 | AS5: 2021-07 | AT5: 2021-08 | AU5: 2021-09 | AV5: 2021-10 | AW5: 2021-11 | AX5: 2021-12 | AY5: 2022-01 | AZ5: 2022-02 | BA5: 2022-03 | BB5: 2022-04 | BC5: 2022-05 | BD5: 2022-06 | BE5: 2022-07 | BF5: 2022-08 | BG5: 2022-09 | BH5: 2022-10 | BI5: 2022-11 | BJ5: 2022-12
B7: Monthly timeline (column J = August 2018)
D8: Month number | E8: index | J8: =I8+1 | K8: =J8+1 | L8: =K8+1 | M8: =L8+1 | N8: =M8+1 | O8: =N8+1 | P8: =O8+1 | Q8: =P8+1 | ... BJ8: =BI8+1
D9: Month start | E9: date | J9: =IF(J8=1,Inputs!$F$188,EDATE(I9,1)) | K9: =IF(K8=1,Inputs!$F$188,EDATE(J9,1)) | L9: =IF(L8=1,Inputs!$F$188,EDATE(K9,1)) | M9: =IF(M8=1,Inputs!$F$188,EDATE(L9,1)) | N9: =IF(N8=1,Inputs!$F$188,EDATE(M9,1)) | O9: =IF(O8=1,Inputs!$F$188,EDATE(N9,1)) | P9: =IF(P8=1,Inputs!$F$188,EDATE(O9,1)) | Q9: =IF(Q8=1,Inputs!$F$188,EDATE(P9,1)) | ... BJ9: =IF(BJ8=1,Inputs!$F$188,EDATE(BI9,1))
D10: Month end | E10: date | J10: =EOMONTH(J9,0) | K10: =EOMONTH(K9,0) | L10: =EOMONTH(L9,0) | M10: =EOMONTH(M9,0) | N10: =EOMONTH(N9,0) | O10: =EOMONTH(O9,0) | P10: =EOMONTH(P9,0) | Q10: =EOMONTH(Q9,0) | ... BJ10: =EOMONTH(BJ9,0)
D11: Days | E11: days | J11: =J10-J9+1 | K11: =K10-K9+1 | L11: =L10-L9+1 | M11: =M10-M9+1 | N11: =N10-N9+1 | O11: =O10-O9+1 | P11: =P10-P9+1 | Q11: =Q10-Q9+1 | ... BJ11: =BJ10-BJ9+1
D12: Semiannual period number | E12: index | J12: =MATCH(J9,Time!$J$22:$BN$22,1) | K12: =MATCH(K9,Time!$J$22:$BN$22,1) | L12: =MATCH(L9,Time!$J$22:$BN$22,1) | M12: =MATCH(M9,Time!$J$22:$BN$22,1) | N12: =MATCH(N9,Time!$J$22:$BN$22,1) | O12: =MATCH(O9,Time!$J$22:$BN$22,1) | P12: =MATCH(P9,Time!$J$22:$BN$22,1) | Q12: =MATCH(Q9,Time!$J$22:$BN$22,1) | ... BJ12: =MATCH(BJ9,Time!$J$22:$BN$22,1)
D13: Flag_Construction (before COD) | E13: flag | J13: =IF(J8<=Time!$F$11,1,0) | K13: =IF(K8<=Time!$F$11,1,0) | L13: =IF(L8<=Time!$F$11,1,0) | M13: =IF(M8<=Time!$F$11,1,0) | N13: =IF(N8<=Time!$F$11,1,0) | O13: =IF(O8<=Time!$F$11,1,0) | P13: =IF(P8<=Time!$F$11,1,0) | Q13: =IF(Q8<=Time!$F$11,1,0) | ... BJ13: =IF(BJ8<=Time!$F$11,1,0)
D14: Flag_FundingPeriod (to end of COD period) | E14: flag | J14: =IF(J8<=Time!$F$14,1,0) | K14: =IF(K8<=Time!$F$14,1,0) | L14: =IF(L8<=Time!$F$14,1,0) | M14: =IF(M8<=Time!$F$14,1,0) | N14: =IF(N8<=Time!$F$14,1,0) | O14: =IF(O8<=Time!$F$14,1,0) | P14: =IF(P8<=Time!$F$14,1,0) | Q14: =IF(Q8<=Time!$F$14,1,0) | ... BJ14: =IF(BJ8<=Time!$F$14,1,0)
D15: Flag_CODMonth | E15: flag | J15: =IF(J8=Time!$F$11+1,1,0) | K15: =IF(K8=Time!$F$11+1,1,0) | L15: =IF(L8=Time!$F$11+1,1,0) | M15: =IF(M8=Time!$F$11+1,1,0) | N15: =IF(N8=Time!$F$11+1,1,0) | O15: =IF(O8=Time!$F$11+1,1,0) | P15: =IF(P8=Time!$F$11+1,1,0) | Q15: =IF(Q8=Time!$F$11+1,1,0) | ... BJ15: =IF(BJ8=Time!$F$11+1,1,0)
D16: KCR per USD | E16: KCR/USD | J16: =IF(Inputs!$F$33=1,Inputs!$F$60*Time!$F$16^((J8-Inputs!$F$212)/12),INDEX(Operations!$J$11:$BN$11,1,J12)) | K16: =IF(Inputs!$F$33=1,Inputs!$F$60*Time!$F$16^((K8-Inputs!$F$212)/12),INDEX(Operations!$J$11:$BN$11,1,K12)) | L16: =IF(Inputs!$F$33=1,Inputs!$F$60*Time!$F$16^((L8-Inputs!$F$212)/12),INDEX(Operations!$J$11:$BN$11,1,L12)) | M16: =IF(Inputs!$F$33=1,Inputs!$F$60*Time!$F$16^((M8-Inputs!$F$212)/12),INDEX(Operations!$J$11:$BN$11,1,M12)) | N16: =IF(Inputs!$F$33=1,Inputs!$F$60*Time!$F$16^((N8-Inputs!$F$212)/12),INDEX(Operations!$J$11:$BN$11,1,N12)) | O16: =IF(Inputs!$F$33=1,Inputs!$F$60*Time!$F$16^((O8-Inputs!$F$212)/12),INDEX(Operations!$J$11:$BN$11,1,O12)) | P16: =IF(Inputs!$F$33=1,Inputs!$F$60*Time!$F$16^((P8-Inputs!$F$212)/12),INDEX(Operations!$J$11:$BN$11,1,P12)) | Q16: =IF(Inputs!$F$33=1,Inputs!$F$60*Time!$F$16^((Q8-Inputs!$F$212)/12),INDEX(Operations!$J$11:$BN$11,1,Q12)) | ... BJ16: =IF(Inputs!$F$33=1,Inputs!$F$60*Time!$F$16^((BJ8-Inputs!$F$212)/12),INDEX(Operations!$J$11:$BN$11,1,BJ12))
D17: Base rate (6M fixing for the half-year) | E17: % | J17: =INDEX(Operations!$J$8:$BN$8,1,J12) | K17: =INDEX(Operations!$J$8:$BN$8,1,K12) | L17: =INDEX(Operations!$J$8:$BN$8,1,L12) | M17: =INDEX(Operations!$J$8:$BN$8,1,M12) | N17: =INDEX(Operations!$J$8:$BN$8,1,N12) | O17: =INDEX(Operations!$J$8:$BN$8,1,O12) | P17: =INDEX(Operations!$J$8:$BN$8,1,P12) | Q17: =INDEX(Operations!$J$8:$BN$8,1,Q12) | ... BJ17: =INDEX(Operations!$J$8:$BN$8,1,BJ12)
D18: Kessara policy rate | E18: % | J18: =IF(Inputs!$F$33=1,Inputs!$F$73,INDEX(Inputs!$J$289:$AR$289,1,MATCH(YEAR(J9),Inputs!$J$282:$AR$282,0))) | K18: =IF(Inputs!$F$33=1,Inputs!$F$73,INDEX(Inputs!$J$289:$AR$289,1,MATCH(YEAR(K9),Inputs!$J$282:$AR$282,0))) | L18: =IF(Inputs!$F$33=1,Inputs!$F$73,INDEX(Inputs!$J$289:$AR$289,1,MATCH(YEAR(L9),Inputs!$J$282:$AR$282,0))) | M18: =IF(Inputs!$F$33=1,Inputs!$F$73,INDEX(Inputs!$J$289:$AR$289,1,MATCH(YEAR(M9),Inputs!$J$282:$AR$282,0))) | N18: =IF(Inputs!$F$33=1,Inputs!$F$73,INDEX(Inputs!$J$289:$AR$289,1,MATCH(YEAR(N9),Inputs!$J$282:$AR$282,0))) | O18: =IF(Inputs!$F$33=1,Inputs!$F$73,INDEX(Inputs!$J$289:$AR$289,1,MATCH(YEAR(O9),Inputs!$J$282:$AR$282,0))) | P18: =IF(Inputs!$F$33=1,Inputs!$F$73,INDEX(Inputs!$J$289:$AR$289,1,MATCH(YEAR(P9),Inputs!$J$282:$AR$282,0))) | Q18: =IF(Inputs!$F$33=1,Inputs!$F$73,INDEX(Inputs!$J$289:$AR$289,1,MATCH(YEAR(Q9),Inputs!$J$282:$AR$282,0))) | ... BJ18: =IF(Inputs!$F$33=1,Inputs!$F$73,INDEX(Inputs!$J$289:$AR$289,1,MATCH(YEAR(BJ9),Inputs!$J$282:$AR$282,0)))
B19: Uses before financing costs (USD m)
D20: EPC payment profile, selected | E20: % | J20: =IF(Inputs!$F$34<>1,Inputs!J306,Inputs!J305+IF(Inputs!$F$35>0,IF(J8=Inputs!$F$237,-Inputs!$F$238,0)+IF(J8=Inputs!$F$237+Inputs!$F$35,Inputs!$F$238,0),0)) | K20: =IF(Inputs!$F$34<>1,Inputs!K306,Inputs!K305+IF(Inputs!$F$35>0,IF(K8=Inputs!$F$237,-Inputs!$F$238,0)+IF(K8=Inputs!$F$237+Inputs!$F$35,Inputs!$F$238,0),0)) | L20: =IF(Inputs!$F$34<>1,Inputs!L306,Inputs!L305+IF(Inputs!$F$35>0,IF(L8=Inputs!$F$237,-Inputs!$F$238,0)+IF(L8=Inputs!$F$237+Inputs!$F$35,Inputs!$F$238,0),0)) | M20: =IF(Inputs!$F$34<>1,Inputs!M306,Inputs!M305+IF(Inputs!$F$35>0,IF(M8=Inputs!$F$237,-Inputs!$F$238,0)+IF(M8=Inputs!$F$237+Inputs!$F$35,Inputs!$F$238,0),0)) | N20: =IF(Inputs!$F$34<>1,Inputs!N306,Inputs!N305+IF(Inputs!$F$35>0,IF(N8=Inputs!$F$237,-Inputs!$F$238,0)+IF(N8=Inputs!$F$237+Inputs!$F$35,Inputs!$F$238,0),0)) | O20: =IF(Inputs!$F$34<>1,Inputs!O306,Inputs!O305+IF(Inputs!$F$35>0,IF(O8=Inputs!$F$237,-Inputs!$F$238,0)+IF(O8=Inputs!$F$237+Inputs!$F$35,Inputs!$F$238,0),0)) | P20: =IF(Inputs!$F$34<>1,Inputs!P306,Inputs!P305+IF(Inputs!$F$35>0,IF(P8=Inputs!$F$237,-Inputs!$F$238,0)+IF(P8=Inputs!$F$237+Inputs!$F$35,Inputs!$F$238,0),0)) | Q20: =IF(Inputs!$F$34<>1,Inputs!Q306,Inputs!Q305+IF(Inputs!$F$35>0,IF(Q8=Inputs!$F$237,-Inputs!$F$238,0)+IF(Q8=Inputs!$F$237+Inputs!$F$35,Inputs!$F$238,0),0)) | ... BJ20: =IF(Inputs!$F$34<>1,Inputs!BJ306,Inputs!BJ305+IF(Inputs!$F$35>0,IF(BJ8=Inputs!$F$237,-Inputs!$F$238,0)+IF(BJ8=Inputs!$F$237+Inputs!$F$35,Inputs!$F$238,0),0))
D21: EPC progress payments for contingency (FC) | E21: % | J21: =IF(J8=1,0,J20)-IF(J8=Time!$F$11,Inputs!$F$238,0) | K21: =IF(K8=1,0,K20)-IF(K8=Time!$F$11,Inputs!$F$238,0) | L21: =IF(L8=1,0,L20)-IF(L8=Time!$F$11,Inputs!$F$238,0) | M21: =IF(M8=1,0,M20)-IF(M8=Time!$F$11,Inputs!$F$238,0) | N21: =IF(N8=1,0,N20)-IF(N8=Time!$F$11,Inputs!$F$238,0) | O21: =IF(O8=1,0,O20)-IF(O8=Time!$F$11,Inputs!$F$238,0) | P21: =IF(P8=1,0,P20)-IF(P8=Time!$F$11,Inputs!$F$238,0) | Q21: =IF(Q8=1,0,Q20)-IF(Q8=Time!$F$11,Inputs!$F$238,0) | ... BJ21: =IF(BJ8=1,0,BJ20)-IF(BJ8=Time!$F$11,Inputs!$F$238,0)
D22: EPC payments | E22: USD m | G22: =SUM(J22:BJ22) | J22: =IF(Inputs!$F$34<>1,J20/100*Inputs!$F$58+J20/100*Inputs!$F$59*Inputs!$F$60/J16,Inputs!$F$57*Inputs!$F$36*J20/100) | K22: =IF(Inputs!$F$34<>1,K20/100*Inputs!$F$58+K20/100*Inputs!$F$59*Inputs!$F$60/K16,Inputs!$F$57*Inputs!$F$36*K20/100) | L22: =IF(Inputs!$F$34<>1,L20/100*Inputs!$F$58+L20/100*Inputs!$F$59*Inputs!$F$60/L16,Inputs!$F$57*Inputs!$F$36*L20/100) | M22: =IF(Inputs!$F$34<>1,M20/100*Inputs!$F$58+M20/100*Inputs!$F$59*Inputs!$F$60/M16,Inputs!$F$57*Inputs!$F$36*M20/100) | N22: =IF(Inputs!$F$34<>1,N20/100*Inputs!$F$58+N20/100*Inputs!$F$59*Inputs!$F$60/N16,Inputs!$F$57*Inputs!$F$36*N20/100) | O22: =IF(Inputs!$F$34<>1,O20/100*Inputs!$F$58+O20/100*Inputs!$F$59*Inputs!$F$60/O16,Inputs!$F$57*Inputs!$F$36*O20/100) | P22: =IF(Inputs!$F$34<>1,P20/100*Inputs!$F$58+P20/100*Inputs!$F$59*Inputs!$F$60/P16,Inputs!$F$57*Inputs!$F$36*P20/100) | Q22: =IF(Inputs!$F$34<>1,Q20/100*Inputs!$F$58+Q20/100*Inputs!$F$59*Inputs!$F$60/Q16,Inputs!$F$57*Inputs!$F$36*Q20/100) | ... BJ22: =IF(Inputs!$F$34<>1,BJ20/100*Inputs!$F$58+BJ20/100*Inputs!$F$59*Inputs!$F$60/BJ16,Inputs!$F$57*Inputs!$F$36*BJ20/100)
D23: Owner's costs | E23: USD m | G23: =SUM(J23:BJ23) | J23: =Inputs!$F$61*IF(Inputs!$F$34=1,Inputs!$F$36,1)*(Inputs!J307+IF(AND(Inputs!$F$34=1,J8>Inputs!$F$237,J8<=Time!$F$11),Inputs!$F$239,0))/100+IF(AND(Inputs!$F$34<>1,J8>=Inputs!$F$240,J8<=Inputs!$F$241),Inputs!$F$69/(Inputs!$F$241-Inputs!$F$240+1),0) | K23: =Inputs!$F$61*IF(Inputs!$F$34=1,Inputs!$F$36,1)*(Inputs!K307+IF(AND(Inputs!$F$34=1,K8>Inputs!$F$237,K8<=Time!$F$11),Inputs!$F$239,0))/100+IF(AND(Inputs!$F$34<>1,K8>=Inputs!$F$240,K8<=Inputs!$F$241),Inputs!$F$69/(Inputs!$F$241-Inputs!$F$240+1),0) | L23: =Inputs!$F$61*IF(Inputs!$F$34=1,Inputs!$F$36,1)*(Inputs!L307+IF(AND(Inputs!$F$34=1,L8>Inputs!$F$237,L8<=Time!$F$11),Inputs!$F$239,0))/100+IF(AND(Inputs!$F$34<>1,L8>=Inputs!$F$240,L8<=Inputs!$F$241),Inputs!$F$69/(Inputs!$F$241-Inputs!$F$240+1),0) | M23: =Inputs!$F$61*IF(Inputs!$F$34=1,Inputs!$F$36,1)*(Inputs!M307+IF(AND(Inputs!$F$34=1,M8>Inputs!$F$237,M8<=Time!$F$11),Inputs!$F$239,0))/100+IF(AND(Inputs!$F$34<>1,M8>=Inputs!$F$240,M8<=Inputs!$F$241),Inputs!$F$69/(Inputs!$F$241-Inputs!$F$240+1),0) | N23: =Inputs!$F$61*IF(Inputs!$F$34=1,Inputs!$F$36,1)*(Inputs!N307+IF(AND(Inputs!$F$34=1,N8>Inputs!$F$237,N8<=Time!$F$11),Inputs!$F$239,0))/100+IF(AND(Inputs!$F$34<>1,N8>=Inputs!$F$240,N8<=Inputs!$F$241),Inputs!$F$69/(Inputs!$F$241-Inputs!$F$240+1),0) | O23: =Inputs!$F$61*IF(Inputs!$F$34=1,Inputs!$F$36,1)*(Inputs!O307+IF(AND(Inputs!$F$34=1,O8>Inputs!$F$237,O8<=Time!$F$11),Inputs!$F$239,0))/100+IF(AND(Inputs!$F$34<>1,O8>=Inputs!$F$240,O8<=Inputs!$F$241),Inputs!$F$69/(Inputs!$F$241-Inputs!$F$240+1),0) | P23: =Inputs!$F$61*IF(Inputs!$F$34=1,Inputs!$F$36,1)*(Inputs!P307+IF(AND(Inputs!$F$34=1,P8>Inputs!$F$237,P8<=Time!$F$11),Inputs!$F$239,0))/100+IF(AND(Inputs!$F$34<>1,P8>=Inputs!$F$240,P8<=Inputs!$F$241),Inputs!$F$69/(Inputs!$F$241-Inputs!$F$240+1),0) | Q23: =Inputs!$F$61*IF(Inputs!$F$34=1,Inputs!$F$36,1)*(Inputs!Q307+IF(AND(Inputs!$F$34=1,Q8>Inputs!$F$237,Q8<=Time!$F$11),Inputs!$F$239,0))/100+IF(AND(Inputs!$F$34<>1,Q8>=Inputs!$F$240,Q8<=Inputs!$F$241),Inputs!$F$69/(Inputs!$F$241-Inputs!$F$240+1),0) | ... BJ23: =Inputs!$F$61*IF(Inputs!$F$34=1,Inputs!$F$36,1)*(Inputs!BJ307+IF(AND(Inputs!$F$34=1,BJ8>Inputs!$F$237,BJ8<=Time!$F$11),Inputs!$F$239,0))/100+IF(AND(Inputs!$F$34<>1,BJ8>=Inputs!$F$240,BJ8<=Inputs!$F$241),Inputs!$F$69/(Inputs!$F$241-Inputs!$F$240+1),0)
D24: Insurance during construction | E24: USD m | G24: =SUM(J24:BJ24) | J24: =Inputs!$F$62*Inputs!$F$36*(Inputs!$F$243*IF(J8=1,1,0)+(1-Inputs!$F$243)*IF(J8=Inputs!$F$242,1,0)) | K24: =Inputs!$F$62*Inputs!$F$36*(Inputs!$F$243*IF(K8=1,1,0)+(1-Inputs!$F$243)*IF(K8=Inputs!$F$242,1,0)) | L24: =Inputs!$F$62*Inputs!$F$36*(Inputs!$F$243*IF(L8=1,1,0)+(1-Inputs!$F$243)*IF(L8=Inputs!$F$242,1,0)) | M24: =Inputs!$F$62*Inputs!$F$36*(Inputs!$F$243*IF(M8=1,1,0)+(1-Inputs!$F$243)*IF(M8=Inputs!$F$242,1,0)) | N24: =Inputs!$F$62*Inputs!$F$36*(Inputs!$F$243*IF(N8=1,1,0)+(1-Inputs!$F$243)*IF(N8=Inputs!$F$242,1,0)) | O24: =Inputs!$F$62*Inputs!$F$36*(Inputs!$F$243*IF(O8=1,1,0)+(1-Inputs!$F$243)*IF(O8=Inputs!$F$242,1,0)) | P24: =Inputs!$F$62*Inputs!$F$36*(Inputs!$F$243*IF(P8=1,1,0)+(1-Inputs!$F$243)*IF(P8=Inputs!$F$242,1,0)) | Q24: =Inputs!$F$62*Inputs!$F$36*(Inputs!$F$243*IF(Q8=1,1,0)+(1-Inputs!$F$243)*IF(Q8=Inputs!$F$242,1,0)) | ... BJ24: =Inputs!$F$62*Inputs!$F$36*(Inputs!$F$243*IF(BJ8=1,1,0)+(1-Inputs!$F$243)*IF(BJ8=Inputs!$F$242,1,0))
D25: Development costs and fee | E25: USD m | G25: =SUM(J25:BJ25) | J25: =IF(J8=1,Inputs!$F$63+Inputs!$F$64,0) | K25: =IF(K8=1,Inputs!$F$63+Inputs!$F$64,0) | L25: =IF(L8=1,Inputs!$F$63+Inputs!$F$64,0) | M25: =IF(M8=1,Inputs!$F$63+Inputs!$F$64,0) | N25: =IF(N8=1,Inputs!$F$63+Inputs!$F$64,0) | O25: =IF(O8=1,Inputs!$F$63+Inputs!$F$64,0) | P25: =IF(P8=1,Inputs!$F$63+Inputs!$F$64,0) | Q25: =IF(Q8=1,Inputs!$F$63+Inputs!$F$64,0) | ... BJ25: =IF(BJ8=1,Inputs!$F$63+Inputs!$F$64,0)
D26: Lenders' advisors and legal | E26: USD m | G26: =SUM(J26:BJ26) | J26: =Inputs!$F$65*Inputs!$F$36*(Inputs!$F$244*IF(J8=1,1,0)+(1-Inputs!$F$244)/(Time!$F$11-1)*IF(AND(J8>1,J8<=Time!$F$11),1,0)) | K26: =Inputs!$F$65*Inputs!$F$36*(Inputs!$F$244*IF(K8=1,1,0)+(1-Inputs!$F$244)/(Time!$F$11-1)*IF(AND(K8>1,K8<=Time!$F$11),1,0)) | L26: =Inputs!$F$65*Inputs!$F$36*(Inputs!$F$244*IF(L8=1,1,0)+(1-Inputs!$F$244)/(Time!$F$11-1)*IF(AND(L8>1,L8<=Time!$F$11),1,0)) | M26: =Inputs!$F$65*Inputs!$F$36*(Inputs!$F$244*IF(M8=1,1,0)+(1-Inputs!$F$244)/(Time!$F$11-1)*IF(AND(M8>1,M8<=Time!$F$11),1,0)) | N26: =Inputs!$F$65*Inputs!$F$36*(Inputs!$F$244*IF(N8=1,1,0)+(1-Inputs!$F$244)/(Time!$F$11-1)*IF(AND(N8>1,N8<=Time!$F$11),1,0)) | O26: =Inputs!$F$65*Inputs!$F$36*(Inputs!$F$244*IF(O8=1,1,0)+(1-Inputs!$F$244)/(Time!$F$11-1)*IF(AND(O8>1,O8<=Time!$F$11),1,0)) | P26: =Inputs!$F$65*Inputs!$F$36*(Inputs!$F$244*IF(P8=1,1,0)+(1-Inputs!$F$244)/(Time!$F$11-1)*IF(AND(P8>1,P8<=Time!$F$11),1,0)) | Q26: =Inputs!$F$65*Inputs!$F$36*(Inputs!$F$244*IF(Q8=1,1,0)+(1-Inputs!$F$244)/(Time!$F$11-1)*IF(AND(Q8>1,Q8<=Time!$F$11),1,0)) | ... BJ26: =Inputs!$F$65*Inputs!$F$36*(Inputs!$F$244*IF(BJ8=1,1,0)+(1-Inputs!$F$244)/(Time!$F$11-1)*IF(AND(BJ8>1,BJ8<=Time!$F$11),1,0))
D27: Contingency (FC: pro rata with EPC progress payments) | E27: USD m | G27: =SUM(J27:BJ27) | J27: =IF(Inputs!$F$34=1,Inputs!$F$66*Inputs!$F$36*J21/SUM($J$21:$BJ$21),0) | K27: =IF(Inputs!$F$34=1,Inputs!$F$66*Inputs!$F$36*K21/SUM($J$21:$BJ$21),0) | L27: =IF(Inputs!$F$34=1,Inputs!$F$66*Inputs!$F$36*L21/SUM($J$21:$BJ$21),0) | M27: =IF(Inputs!$F$34=1,Inputs!$F$66*Inputs!$F$36*M21/SUM($J$21:$BJ$21),0) | N27: =IF(Inputs!$F$34=1,Inputs!$F$66*Inputs!$F$36*N21/SUM($J$21:$BJ$21),0) | O27: =IF(Inputs!$F$34=1,Inputs!$F$66*Inputs!$F$36*O21/SUM($J$21:$BJ$21),0) | P27: =IF(Inputs!$F$34=1,Inputs!$F$66*Inputs!$F$36*P21/SUM($J$21:$BJ$21),0) | Q27: =IF(Inputs!$F$34=1,Inputs!$F$66*Inputs!$F$36*Q21/SUM($J$21:$BJ$21),0) | ... BJ27: =IF(Inputs!$F$34=1,Inputs!$F$66*Inputs!$F$36*BJ21/SUM($J$21:$BJ$21),0)
D28: Initial working capital | E28: USD m | G28: =SUM(J28:BJ28) | J28: =IF(J8=Time!$F$11,Inputs!$F$67*Inputs!$F$36,0) | K28: =IF(K8=Time!$F$11,Inputs!$F$67*Inputs!$F$36,0) | L28: =IF(L8=Time!$F$11,Inputs!$F$67*Inputs!$F$36,0) | M28: =IF(M8=Time!$F$11,Inputs!$F$67*Inputs!$F$36,0) | N28: =IF(N8=Time!$F$11,Inputs!$F$67*Inputs!$F$36,0) | O28: =IF(O8=Time!$F$11,Inputs!$F$67*Inputs!$F$36,0) | P28: =IF(P8=Time!$F$11,Inputs!$F$67*Inputs!$F$36,0) | Q28: =IF(Q8=Time!$F$11,Inputs!$F$67*Inputs!$F$36,0) | ... BJ28: =IF(BJ8=Time!$F$11,Inputs!$F$67*Inputs!$F$36,0)
D29: Overrun items (actual) | E29: USD m | G29: =SUM(J29:BJ29) | J29: =IF(Inputs!$F$34<>1,Inputs!J308,0) | K29: =IF(Inputs!$F$34<>1,Inputs!K308,0) | L29: =IF(Inputs!$F$34<>1,Inputs!L308,0) | M29: =IF(Inputs!$F$34<>1,Inputs!M308,0) | N29: =IF(Inputs!$F$34<>1,Inputs!N308,0) | O29: =IF(Inputs!$F$34<>1,Inputs!O308,0) | P29: =IF(Inputs!$F$34<>1,Inputs!P308,0) | Q29: =IF(Inputs!$F$34<>1,Inputs!Q308,0) | ... BJ29: =IF(Inputs!$F$34<>1,Inputs!BJ308,0)
D30: KCR forward rate traded at financial close (covered interest parity) | E30: KCR/USD | J30: =Inputs!$F$60*((1+Inputs!$F$73/100)/(1+INDEX(Inputs!$J$291:$BN$291,1,J12)/100))^((J10-Inputs!$F$187)/Inputs!$F$248) | K30: =Inputs!$F$60*((1+Inputs!$F$73/100)/(1+INDEX(Inputs!$J$291:$BN$291,1,K12)/100))^((K10-Inputs!$F$187)/Inputs!$F$248) | L30: =Inputs!$F$60*((1+Inputs!$F$73/100)/(1+INDEX(Inputs!$J$291:$BN$291,1,L12)/100))^((L10-Inputs!$F$187)/Inputs!$F$248) | M30: =Inputs!$F$60*((1+Inputs!$F$73/100)/(1+INDEX(Inputs!$J$291:$BN$291,1,M12)/100))^((M10-Inputs!$F$187)/Inputs!$F$248) | N30: =Inputs!$F$60*((1+Inputs!$F$73/100)/(1+INDEX(Inputs!$J$291:$BN$291,1,N12)/100))^((N10-Inputs!$F$187)/Inputs!$F$248) | O30: =Inputs!$F$60*((1+Inputs!$F$73/100)/(1+INDEX(Inputs!$J$291:$BN$291,1,O12)/100))^((O10-Inputs!$F$187)/Inputs!$F$248) | P30: =Inputs!$F$60*((1+Inputs!$F$73/100)/(1+INDEX(Inputs!$J$291:$BN$291,1,P12)/100))^((P10-Inputs!$F$187)/Inputs!$F$248) | Q30: =Inputs!$F$60*((1+Inputs!$F$73/100)/(1+INDEX(Inputs!$J$291:$BN$291,1,Q12)/100))^((Q10-Inputs!$F$187)/Inputs!$F$248) | ... BJ30: =Inputs!$F$60*((1+Inputs!$F$73/100)/(1+INDEX(Inputs!$J$291:$BN$291,1,BJ12)/100))^((BJ10-Inputs!$F$187)/Inputs!$F$248)
D31: FX forward settlement on onshore EPC payments (gain to the project) | E31: USD m | G31: =SUM(J31:BJ31) | J31: =IF(Inputs!$F$34<>1,Inputs!$F$259*J34*(1/J16-1/J30),0) | K31: =IF(Inputs!$F$34<>1,Inputs!$F$259*K34*(1/K16-1/K30),0) | L31: =IF(Inputs!$F$34<>1,Inputs!$F$259*L34*(1/L16-1/L30),0) | M31: =IF(Inputs!$F$34<>1,Inputs!$F$259*M34*(1/M16-1/M30),0) | N31: =IF(Inputs!$F$34<>1,Inputs!$F$259*N34*(1/N16-1/N30),0) | O31: =IF(Inputs!$F$34<>1,Inputs!$F$259*O34*(1/O16-1/O30),0) | P31: =IF(Inputs!$F$34<>1,Inputs!$F$259*P34*(1/P16-1/P30),0) | Q31: =IF(Inputs!$F$34<>1,Inputs!$F$259*Q34*(1/Q16-1/Q30),0) | ... BJ31: =IF(Inputs!$F$34<>1,Inputs!$F$259*BJ34*(1/BJ16-1/BJ30),0)
D32: Uses before financing costs (net of FX hedge settlements) | E32: USD m | G32: =SUM(J32:BJ32) | J32: =J22+J23+J24+J25+J26+J27+J28+J29-J31 | K32: =K22+K23+K24+K25+K26+K27+K28+K29-K31 | L32: =L22+L23+L24+L25+L26+L27+L28+L29-L31 | M32: =M22+M23+M24+M25+M26+M27+M28+M29-M31 | N32: =N22+N23+N24+N25+N26+N27+N28+N29-N31 | O32: =O22+O23+O24+O25+O26+O27+O28+O29-O31 | P32: =P22+P23+P24+P25+P26+P27+P28+P29-P31 | Q32: =Q22+Q23+Q24+Q25+Q26+Q27+Q28+Q29-Q31 | ... BJ32: =BJ22+BJ23+BJ24+BJ25+BJ26+BJ27+BJ28+BJ29-BJ31
B33: VAT on onshore EPC (KCR m) and UBK VAT facility
D34: Onshore EPC payments | E34: KCR m | G34: =SUM(J34:BJ34) | J34: =J20/100*Inputs!$F$59*Inputs!$F$60*Inputs!$F$36 | K34: =K20/100*Inputs!$F$59*Inputs!$F$60*Inputs!$F$36 | L34: =L20/100*Inputs!$F$59*Inputs!$F$60*Inputs!$F$36 | M34: =M20/100*Inputs!$F$59*Inputs!$F$60*Inputs!$F$36 | N34: =N20/100*Inputs!$F$59*Inputs!$F$60*Inputs!$F$36 | O34: =O20/100*Inputs!$F$59*Inputs!$F$60*Inputs!$F$36 | P34: =P20/100*Inputs!$F$59*Inputs!$F$60*Inputs!$F$36 | Q34: =Q20/100*Inputs!$F$59*Inputs!$F$60*Inputs!$F$36 | ... BJ34: =BJ20/100*Inputs!$F$59*Inputs!$F$60*Inputs!$F$36
D35: VAT paid (drawn on the VAT facility) | E35: KCR m | G35: =SUM(J35:BJ35) | J35: =Inputs!$F$70/100*J34 | K35: =Inputs!$F$70/100*K34 | L35: =Inputs!$F$70/100*L34 | M35: =Inputs!$F$70/100*M34 | N35: =Inputs!$F$70/100*N34 | O35: =Inputs!$F$70/100*O34 | P35: =Inputs!$F$70/100*P34 | Q35: =Inputs!$F$70/100*Q34 | ... BJ35: =Inputs!$F$70/100*BJ34
D36: VAT refunds (9-month lag) repaying the facility | E36: KCR m | G36: =SUM(J36:BJ36) | J36: =SUMIFS($J$35:$BJ$35,$J$8:$BJ$8,J8-Inputs!$F$246) | K36: =SUMIFS($J$35:$BJ$35,$J$8:$BJ$8,K8-Inputs!$F$246) | L36: =SUMIFS($J$35:$BJ$35,$J$8:$BJ$8,L8-Inputs!$F$246) | M36: =SUMIFS($J$35:$BJ$35,$J$8:$BJ$8,M8-Inputs!$F$246) | N36: =SUMIFS($J$35:$BJ$35,$J$8:$BJ$8,N8-Inputs!$F$246) | O36: =SUMIFS($J$35:$BJ$35,$J$8:$BJ$8,O8-Inputs!$F$246) | P36: =SUMIFS($J$35:$BJ$35,$J$8:$BJ$8,P8-Inputs!$F$246) | Q36: =SUMIFS($J$35:$BJ$35,$J$8:$BJ$8,Q8-Inputs!$F$246) | ... BJ36: =SUMIFS($J$35:$BJ$35,$J$8:$BJ$8,BJ8-Inputs!$F$246)
D37: VAT facility balance | E37: KCR m | J37: =I37+J35-J36 | K37: =J37+K35-K36 | L37: =K37+L35-L36 | M37: =L37+M35-M36 | N37: =M37+N35-N36 | O37: =N37+O35-O36 | P37: =O37+P35-P36 | Q37: =P37+Q35-Q36 | ... BJ37: =BI37+BJ35-BJ36
D38: VAT facility interest | E38: USD m | G38: =SUM(J38:BJ38) | J38: =I37*(J18+Inputs!$F$71)/100*J11/Inputs!$F$248/J16 | K38: =J37*(K18+Inputs!$F$71)/100*K11/Inputs!$F$248/K16 | L38: =K37*(L18+Inputs!$F$71)/100*L11/Inputs!$F$248/L16 | M38: =L37*(M18+Inputs!$F$71)/100*M11/Inputs!$F$248/M16 | N38: =M37*(N18+Inputs!$F$71)/100*N11/Inputs!$F$248/N16 | O38: =N37*(O18+Inputs!$F$71)/100*O11/Inputs!$F$248/O16 | P38: =O37*(P18+Inputs!$F$71)/100*P11/Inputs!$F$248/P16 | Q38: =P37*(Q18+Inputs!$F$71)/100*Q11/Inputs!$F$248/Q16 | ... BJ38: =BI37*(BJ18+Inputs!$F$71)/100*BJ11/Inputs!$F$248/BJ16

Sheet Operations
A1: Case P: Belanou Combined Cycle Power Project, Republic of Kessara
A2: Operations: macro paths, plant, revenue, operating costs, working capital
A3: Units in column E; constants in column F; row totals in column G; first period in column J. Inputs: blue on yellow. Links from other sheets: green.
D4: Label | E4: Unit | F4: Constant | G4: Total
D5: Period ending | J5: 2018H2 | K5: 2019H1 | L5: 2019H2 | M5: 2020H1 | N5: 2020H2 | O5: 2021H1 | P5: 2021H2 | Q5: 2022H1 | R5: 2022H2 | S5: 2023H1 | T5: 2023H2 | U5: 2024H1 | V5: 2024H2 | W5: 2025H1 | X5: 2025H2 | Y5: 2026H1 | Z5: 2026H2 | AA5: 2027H1 | AB5: 2027H2 | AC5: 2028H1 | AD5: 2028H2 | AE5: 2029H1 | AF5: 2029H2 | AG5: 2030H1 | AH5: 2030H2 | AI5: 2031H1 | AJ5: 2031H2 | AK5: 2032H1 | AL5: 2032H2 | AM5: 2033H1 | AN5: 2033H2 | AO5: 2034H1 | AP5: 2034H2 | AQ5: 2035H1 | AR5: 2035H2 | AS5: 2036H1 | AT5: 2036H2 | AU5: 2037H1 | AV5: 2037H2 | AW5: 2038H1 | AX5: 2038H2 | AY5: 2039H1 | AZ5: 2039H2 | BA5: 2040H1 | BB5: 2040H2 | BC5: 2041H1 | BD5: 2041H2 | BE5: 2042H1 | BF5: 2042H2 | BG5: 2043H1 | BH5: 2043H2 | BI5: 2044H1 | BJ5: 2044H2 | BK5: 2045H1 | BL5: 2045H2 | BM5: 2046H1 | BN5: 2046H2
B7: Macro paths
D8: Base rate before sensitivity shift | E8: % | J8: =CHOOSE(Inputs!$F$33,Inputs!J291,Inputs!J292,Inputs!J293) | K8: =CHOOSE(Inputs!$F$33,Inputs!K291,Inputs!K292,Inputs!K293) | L8: =CHOOSE(Inputs!$F$33,Inputs!L291,Inputs!L292,Inputs!L293) | M8: =CHOOSE(Inputs!$F$33,Inputs!M291,Inputs!M292,Inputs!M293) | N8: =CHOOSE(Inputs!$F$33,Inputs!N291,Inputs!N292,Inputs!N293) | O8: =CHOOSE(Inputs!$F$33,Inputs!O291,Inputs!O292,Inputs!O293) | P8: =CHOOSE(Inputs!$F$33,Inputs!P291,Inputs!P292,Inputs!P293) | Q8: =CHOOSE(Inputs!$F$33,Inputs!Q291,Inputs!Q292,Inputs!Q293) | ... BN8: =CHOOSE(Inputs!$F$33,Inputs!BN291,Inputs!BN292,Inputs!BN293)
D9: Base rate (6M LIBOR / Term SOFR + CAS) | E9: % | J9: =J8+Inputs!$F$42*Time!J39 | K9: =K8+Inputs!$F$42*Time!K39 | L9: =L8+Inputs!$F$42*Time!L39 | M9: =M8+Inputs!$F$42*Time!M39 | N9: =N8+Inputs!$F$42*Time!N39 | O9: =O8+Inputs!$F$42*Time!O39 | P9: =P8+Inputs!$F$42*Time!P39 | Q9: =Q8+Inputs!$F$42*Time!Q39 | ... BN9: =BN8+Inputs!$F$42*Time!BN39
D10: KCR per USD before devaluation sensitivity | E10: KCR/USD | J10: =CHOOSE(Inputs!$F$33,Inputs!$F$60*Time!$F$16^((Time!J20-Inputs!$F$212)*Time!J24),IF(Inputs!J294>0,Inputs!J294,I10*((1+J13/100)/(1+J12/100))^Time!J24),IF(Time!J54=0,Inputs!J294,I10*Time!$F$16^Time!J24)) | K10: =CHOOSE(Inputs!$F$33,Inputs!$F$60*Time!$F$16^((Time!K20-Inputs!$F$212)*Time!K24),IF(Inputs!K294>0,Inputs!K294,J10*((1+K13/100)/(1+K12/100))^Time!K24),IF(Time!K54=0,Inputs!K294,J10*Time!$F$16^Time!K24)) | L10: =CHOOSE(Inputs!$F$33,Inputs!$F$60*Time!$F$16^((Time!L20-Inputs!$F$212)*Time!L24),IF(Inputs!L294>0,Inputs!L294,K10*((1+L13/100)/(1+L12/100))^Time!L24),IF(Time!L54=0,Inputs!L294,K10*Time!$F$16^Time!L24)) | M10: =CHOOSE(Inputs!$F$33,Inputs!$F$60*Time!$F$16^((Time!M20-Inputs!$F$212)*Time!M24),IF(Inputs!M294>0,Inputs!M294,L10*((1+M13/100)/(1+M12/100))^Time!M24),IF(Time!M54=0,Inputs!M294,L10*Time!$F$16^Time!M24)) | N10: =CHOOSE(Inputs!$F$33,Inputs!$F$60*Time!$F$16^((Time!N20-Inputs!$F$212)*Time!N24),IF(Inputs!N294>0,Inputs!N294,M10*((1+N13/100)/(1+N12/100))^Time!N24),IF(Time!N54=0,Inputs!N294,M10*Time!$F$16^Time!N24)) | O10: =CHOOSE(Inputs!$F$33,Inputs!$F$60*Time!$F$16^((Time!O20-Inputs!$F$212)*Time!O24),IF(Inputs!O294>0,Inputs!O294,N10*((1+O13/100)/(1+O12/100))^Time!O24),IF(Time!O54=0,Inputs!O294,N10*Time!$F$16^Time!O24)) | P10: =CHOOSE(Inputs!$F$33,Inputs!$F$60*Time!$F$16^((Time!P20-Inputs!$F$212)*Time!P24),IF(Inputs!P294>0,Inputs!P294,O10*((1+P13/100)/(1+P12/100))^Time!P24),IF(Time!P54=0,Inputs!P294,O10*Time!$F$16^Time!P24)) | Q10: =CHOOSE(Inputs!$F$33,Inputs!$F$60*Time!$F$16^((Time!Q20-Inputs!$F$212)*Time!Q24),IF(Inputs!Q294>0,Inputs!Q294,P10*((1+Q13/100)/(1+Q12/100))^Time!Q24),IF(Time!Q54=0,Inputs!Q294,P10*Time!$F$16^Time!Q24)) | ... BN10: =CHOOSE(Inputs!$F$33,Inputs!$F$60*Time!$F$16^((Time!BN20-Inputs!$F$212)*Time!BN24),IF(Inputs!BN294>0,Inputs!BN294,BM10*((1+BN13/100)/(1+BN12/100))^Time!BN24),IF(Time!BN54=0,Inputs!BN294,BM10*Time!$F$16^Time!BN24))
D11: KCR per USD, period average | E11: KCR/USD | J11: =J10/(1-Inputs!$F$43*Time!J39) | K11: =K10/(1-Inputs!$F$43*Time!K39) | L11: =L10/(1-Inputs!$F$43*Time!L39) | M11: =M10/(1-Inputs!$F$43*Time!M39) | N11: =N10/(1-Inputs!$F$43*Time!N39) | O11: =O10/(1-Inputs!$F$43*Time!O39) | P11: =P10/(1-Inputs!$F$43*Time!P39) | Q11: =Q10/(1-Inputs!$F$43*Time!Q39) | ... BN11: =BN10/(1-Inputs!$F$43*Time!BN39)
D12: US CPI change, current year | E12: % | J12: =CHOOSE(Inputs!$F$33,INDEX(Inputs!$J$283:$AR$283,1,MATCH((Time!J26-0),Inputs!$J$282:$AR$282,0)),INDEX(Inputs!$J$285:$AR$285,1,MATCH((Time!J26-0),Inputs!$J$282:$AR$282,0)),INDEX(Inputs!$J$287:$AR$287,1,MATCH((Time!J26-0),Inputs!$J$282:$AR$282,0))) | K12: =CHOOSE(Inputs!$F$33,INDEX(Inputs!$J$283:$AR$283,1,MATCH((Time!K26-0),Inputs!$J$282:$AR$282,0)),INDEX(Inputs!$J$285:$AR$285,1,MATCH((Time!K26-0),Inputs!$J$282:$AR$282,0)),INDEX(Inputs!$J$287:$AR$287,1,MATCH((Time!K26-0),Inputs!$J$282:$AR$282,0))) | L12: =CHOOSE(Inputs!$F$33,INDEX(Inputs!$J$283:$AR$283,1,MATCH((Time!L26-0),Inputs!$J$282:$AR$282,0)),INDEX(Inputs!$J$285:$AR$285,1,MATCH((Time!L26-0),Inputs!$J$282:$AR$282,0)),INDEX(Inputs!$J$287:$AR$287,1,MATCH((Time!L26-0),Inputs!$J$282:$AR$282,0))) | M12: =CHOOSE(Inputs!$F$33,INDEX(Inputs!$J$283:$AR$283,1,MATCH((Time!M26-0),Inputs!$J$282:$AR$282,0)),INDEX(Inputs!$J$285:$AR$285,1,MATCH((Time!M26-0),Inputs!$J$282:$AR$282,0)),INDEX(Inputs!$J$287:$AR$287,1,MATCH((Time!M26-0),Inputs!$J$282:$AR$282,0))) | N12: =CHOOSE(Inputs!$F$33,INDEX(Inputs!$J$283:$AR$283,1,MATCH((Time!N26-0),Inputs!$J$282:$AR$282,0)),INDEX(Inputs!$J$285:$AR$285,1,MATCH((Time!N26-0),Inputs!$J$282:$AR$282,0)),INDEX(Inputs!$J$287:$AR$287,1,MATCH((Time!N26-0),Inputs!$J$282:$AR$282,0))) | O12: =CHOOSE(Inputs!$F$33,INDEX(Inputs!$J$283:$AR$283,1,MATCH((Time!O26-0),Inputs!$J$282:$AR$282,0)),INDEX(Inputs!$J$285:$AR$285,1,MATCH((Time!O26-0),Inputs!$J$282:$AR$282,0)),INDEX(Inputs!$J$287:$AR$287,1,MATCH((Time!O26-0),Inputs!$J$282:$AR$282,0))) | P12: =CHOOSE(Inputs!$F$33,INDEX(Inputs!$J$283:$AR$283,1,MATCH((Time!P26-0),Inputs!$J$282:$AR$282,0)),INDEX(Inputs!$J$285:$AR$285,1,MATCH((Time!P26-0),Inputs!$J$282:$AR$282,0)),INDEX(Inputs!$J$287:$AR$287,1,MATCH((Time!P26-0),Inputs!$J$282:$AR$282,0))) | Q12: =CHOOSE(Inputs!$F$33,INDEX(Inputs!$J$283:$AR$283,1,MATCH((Time!Q26-0),Inputs!$J$282:$AR$282,0)),INDEX(Inputs!$J$285:$AR$285,1,MATCH((Time!Q26-0),Inputs!$J$282:$AR$282,0)),INDEX(Inputs!$J$287:$AR$287,1,MATCH((Time!Q26-0),Inputs!$J$282:$AR$282,0))) | ... BN12: =CHOOSE(Inputs!$F$33,INDEX(Inputs!$J$283:$AR$283,1,MATCH((Time!BN26-0),Inputs!$J$282:$AR$282,0)),INDEX(Inputs!$J$285:$AR$285,1,MATCH((Time!BN26-0),Inputs!$J$282:$AR$282,0)),INDEX(Inputs!$J$287:$AR$287,1,MATCH((Time!BN26-0),Inputs!$J$282:$AR$282,0)))
D13: Kessara CPI change, current year | E13: % | J13: =CHOOSE(Inputs!$F$33,INDEX(Inputs!$J$284:$AR$284,1,MATCH((Time!J26-0),Inputs!$J$282:$AR$282,0)),INDEX(Inputs!$J$286:$AR$286,1,MATCH((Time!J26-0),Inputs!$J$282:$AR$282,0)),INDEX(Inputs!$J$288:$AR$288,1,MATCH((Time!J26-0),Inputs!$J$282:$AR$282,0))) | K13: =CHOOSE(Inputs!$F$33,INDEX(Inputs!$J$284:$AR$284,1,MATCH((Time!K26-0),Inputs!$J$282:$AR$282,0)),INDEX(Inputs!$J$286:$AR$286,1,MATCH((Time!K26-0),Inputs!$J$282:$AR$282,0)),INDEX(Inputs!$J$288:$AR$288,1,MATCH((Time!K26-0),Inputs!$J$282:$AR$282,0))) | L13: =CHOOSE(Inputs!$F$33,INDEX(Inputs!$J$284:$AR$284,1,MATCH((Time!L26-0),Inputs!$J$282:$AR$282,0)),INDEX(Inputs!$J$286:$AR$286,1,MATCH((Time!L26-0),Inputs!$J$282:$AR$282,0)),INDEX(Inputs!$J$288:$AR$288,1,MATCH((Time!L26-0),Inputs!$J$282:$AR$282,0))) | M13: =CHOOSE(Inputs!$F$33,INDEX(Inputs!$J$284:$AR$284,1,MATCH((Time!M26-0),Inputs!$J$282:$AR$282,0)),INDEX(Inputs!$J$286:$AR$286,1,MATCH((Time!M26-0),Inputs!$J$282:$AR$282,0)),INDEX(Inputs!$J$288:$AR$288,1,MATCH((Time!M26-0),Inputs!$J$282:$AR$282,0))) | N13: =CHOOSE(Inputs!$F$33,INDEX(Inputs!$J$284:$AR$284,1,MATCH((Time!N26-0),Inputs!$J$282:$AR$282,0)),INDEX(Inputs!$J$286:$AR$286,1,MATCH((Time!N26-0),Inputs!$J$282:$AR$282,0)),INDEX(Inputs!$J$288:$AR$288,1,MATCH((Time!N26-0),Inputs!$J$282:$AR$282,0))) | O13: =CHOOSE(Inputs!$F$33,INDEX(Inputs!$J$284:$AR$284,1,MATCH((Time!O26-0),Inputs!$J$282:$AR$282,0)),INDEX(Inputs!$J$286:$AR$286,1,MATCH((Time!O26-0),Inputs!$J$282:$AR$282,0)),INDEX(Inputs!$J$288:$AR$288,1,MATCH((Time!O26-0),Inputs!$J$282:$AR$282,0))) | P13: =CHOOSE(Inputs!$F$33,INDEX(Inputs!$J$284:$AR$284,1,MATCH((Time!P26-0),Inputs!$J$282:$AR$282,0)),INDEX(Inputs!$J$286:$AR$286,1,MATCH((Time!P26-0),Inputs!$J$282:$AR$282,0)),INDEX(Inputs!$J$288:$AR$288,1,MATCH((Time!P26-0),Inputs!$J$282:$AR$282,0))) | Q13: =CHOOSE(Inputs!$F$33,INDEX(Inputs!$J$284:$AR$284,1,MATCH((Time!Q26-0),Inputs!$J$282:$AR$282,0)),INDEX(Inputs!$J$286:$AR$286,1,MATCH((Time!Q26-0),Inputs!$J$282:$AR$282,0)),INDEX(Inputs!$J$288:$AR$288,1,MATCH((Time!Q26-0),Inputs!$J$282:$AR$282,0))) | ... BN13: =CHOOSE(Inputs!$F$33,INDEX(Inputs!$J$284:$AR$284,1,MATCH((Time!BN26-0),Inputs!$J$282:$AR$282,0)),INDEX(Inputs!$J$286:$AR$286,1,MATCH((Time!BN26-0),Inputs!$J$282:$AR$282,0)),INDEX(Inputs!$J$288:$AR$288,1,MATCH((Time!BN26-0),Inputs!$J$282:$AR$282,0)))
D14: US CPI change, prior year | E14: % | J14: =CHOOSE(Inputs!$F$33,INDEX(Inputs!$J$283:$AR$283,1,MATCH((Time!J26-1),Inputs!$J$282:$AR$282,0)),INDEX(Inputs!$J$285:$AR$285,1,MATCH((Time!J26-1),Inputs!$J$282:$AR$282,0)),INDEX(Inputs!$J$287:$AR$287,1,MATCH((Time!J26-1),Inputs!$J$282:$AR$282,0))) | K14: =CHOOSE(Inputs!$F$33,INDEX(Inputs!$J$283:$AR$283,1,MATCH((Time!K26-1),Inputs!$J$282:$AR$282,0)),INDEX(Inputs!$J$285:$AR$285,1,MATCH((Time!K26-1),Inputs!$J$282:$AR$282,0)),INDEX(Inputs!$J$287:$AR$287,1,MATCH((Time!K26-1),Inputs!$J$282:$AR$282,0))) | L14: =CHOOSE(Inputs!$F$33,INDEX(Inputs!$J$283:$AR$283,1,MATCH((Time!L26-1),Inputs!$J$282:$AR$282,0)),INDEX(Inputs!$J$285:$AR$285,1,MATCH((Time!L26-1),Inputs!$J$282:$AR$282,0)),INDEX(Inputs!$J$287:$AR$287,1,MATCH((Time!L26-1),Inputs!$J$282:$AR$282,0))) | M14: =CHOOSE(Inputs!$F$33,INDEX(Inputs!$J$283:$AR$283,1,MATCH((Time!M26-1),Inputs!$J$282:$AR$282,0)),INDEX(Inputs!$J$285:$AR$285,1,MATCH((Time!M26-1),Inputs!$J$282:$AR$282,0)),INDEX(Inputs!$J$287:$AR$287,1,MATCH((Time!M26-1),Inputs!$J$282:$AR$282,0))) | N14: =CHOOSE(Inputs!$F$33,INDEX(Inputs!$J$283:$AR$283,1,MATCH((Time!N26-1),Inputs!$J$282:$AR$282,0)),INDEX(Inputs!$J$285:$AR$285,1,MATCH((Time!N26-1),Inputs!$J$282:$AR$282,0)),INDEX(Inputs!$J$287:$AR$287,1,MATCH((Time!N26-1),Inputs!$J$282:$AR$282,0))) | O14: =CHOOSE(Inputs!$F$33,INDEX(Inputs!$J$283:$AR$283,1,MATCH((Time!O26-1),Inputs!$J$282:$AR$282,0)),INDEX(Inputs!$J$285:$AR$285,1,MATCH((Time!O26-1),Inputs!$J$282:$AR$282,0)),INDEX(Inputs!$J$287:$AR$287,1,MATCH((Time!O26-1),Inputs!$J$282:$AR$282,0))) | P14: =CHOOSE(Inputs!$F$33,INDEX(Inputs!$J$283:$AR$283,1,MATCH((Time!P26-1),Inputs!$J$282:$AR$282,0)),INDEX(Inputs!$J$285:$AR$285,1,MATCH((Time!P26-1),Inputs!$J$282:$AR$282,0)),INDEX(Inputs!$J$287:$AR$287,1,MATCH((Time!P26-1),Inputs!$J$282:$AR$282,0))) | Q14: =CHOOSE(Inputs!$F$33,INDEX(Inputs!$J$283:$AR$283,1,MATCH((Time!Q26-1),Inputs!$J$282:$AR$282,0)),INDEX(Inputs!$J$285:$AR$285,1,MATCH((Time!Q26-1),Inputs!$J$282:$AR$282,0)),INDEX(Inputs!$J$287:$AR$287,1,MATCH((Time!Q26-1),Inputs!$J$282:$AR$282,0))) | ... BN14: =CHOOSE(Inputs!$F$33,INDEX(Inputs!$J$283:$AR$283,1,MATCH((Time!BN26-1),Inputs!$J$282:$AR$282,0)),INDEX(Inputs!$J$285:$AR$285,1,MATCH((Time!BN26-1),Inputs!$J$282:$AR$282,0)),INDEX(Inputs!$J$287:$AR$287,1,MATCH((Time!BN26-1),Inputs!$J$282:$AR$282,0)))
D15: Kessara CPI change, prior year | E15: % | J15: =CHOOSE(Inputs!$F$33,INDEX(Inputs!$J$284:$AR$284,1,MATCH((Time!J26-1),Inputs!$J$282:$AR$282,0)),INDEX(Inputs!$J$286:$AR$286,1,MATCH((Time!J26-1),Inputs!$J$282:$AR$282,0)),INDEX(Inputs!$J$288:$AR$288,1,MATCH((Time!J26-1),Inputs!$J$282:$AR$282,0))) | K15: =CHOOSE(Inputs!$F$33,INDEX(Inputs!$J$284:$AR$284,1,MATCH((Time!K26-1),Inputs!$J$282:$AR$282,0)),INDEX(Inputs!$J$286:$AR$286,1,MATCH((Time!K26-1),Inputs!$J$282:$AR$282,0)),INDEX(Inputs!$J$288:$AR$288,1,MATCH((Time!K26-1),Inputs!$J$282:$AR$282,0))) | L15: =CHOOSE(Inputs!$F$33,INDEX(Inputs!$J$284:$AR$284,1,MATCH((Time!L26-1),Inputs!$J$282:$AR$282,0)),INDEX(Inputs!$J$286:$AR$286,1,MATCH((Time!L26-1),Inputs!$J$282:$AR$282,0)),INDEX(Inputs!$J$288:$AR$288,1,MATCH((Time!L26-1),Inputs!$J$282:$AR$282,0))) | M15: =CHOOSE(Inputs!$F$33,INDEX(Inputs!$J$284:$AR$284,1,MATCH((Time!M26-1),Inputs!$J$282:$AR$282,0)),INDEX(Inputs!$J$286:$AR$286,1,MATCH((Time!M26-1),Inputs!$J$282:$AR$282,0)),INDEX(Inputs!$J$288:$AR$288,1,MATCH((Time!M26-1),Inputs!$J$282:$AR$282,0))) | N15: =CHOOSE(Inputs!$F$33,INDEX(Inputs!$J$284:$AR$284,1,MATCH((Time!N26-1),Inputs!$J$282:$AR$282,0)),INDEX(Inputs!$J$286:$AR$286,1,MATCH((Time!N26-1),Inputs!$J$282:$AR$282,0)),INDEX(Inputs!$J$288:$AR$288,1,MATCH((Time!N26-1),Inputs!$J$282:$AR$282,0))) | O15: =CHOOSE(Inputs!$F$33,INDEX(Inputs!$J$284:$AR$284,1,MATCH((Time!O26-1),Inputs!$J$282:$AR$282,0)),INDEX(Inputs!$J$286:$AR$286,1,MATCH((Time!O26-1),Inputs!$J$282:$AR$282,0)),INDEX(Inputs!$J$288:$AR$288,1,MATCH((Time!O26-1),Inputs!$J$282:$AR$282,0))) | P15: =CHOOSE(Inputs!$F$33,INDEX(Inputs!$J$284:$AR$284,1,MATCH((Time!P26-1),Inputs!$J$282:$AR$282,0)),INDEX(Inputs!$J$286:$AR$286,1,MATCH((Time!P26-1),Inputs!$J$282:$AR$282,0)),INDEX(Inputs!$J$288:$AR$288,1,MATCH((Time!P26-1),Inputs!$J$282:$AR$282,0))) | Q15: =CHOOSE(Inputs!$F$33,INDEX(Inputs!$J$284:$AR$284,1,MATCH((Time!Q26-1),Inputs!$J$282:$AR$282,0)),INDEX(Inputs!$J$286:$AR$286,1,MATCH((Time!Q26-1),Inputs!$J$282:$AR$282,0)),INDEX(Inputs!$J$288:$AR$288,1,MATCH((Time!Q26-1),Inputs!$J$282:$AR$282,0))) | ... BN15: =CHOOSE(Inputs!$F$33,INDEX(Inputs!$J$284:$AR$284,1,MATCH((Time!BN26-1),Inputs!$J$282:$AR$282,0)),INDEX(Inputs!$J$286:$AR$286,1,MATCH((Time!BN26-1),Inputs!$J$282:$AR$282,0)),INDEX(Inputs!$J$288:$AR$288,1,MATCH((Time!BN26-1),Inputs!$J$282:$AR$282,0)))
D16: US index, 2018 price base month | E16: index | F16: =Inputs!$F$232*(1+CHOOSE(Inputs!$F$33,INDEX(Inputs!$J$283:$AR$283,1,MATCH(Inputs!$F$230,Inputs!$J$282:$AR$282,0)),INDEX(Inputs!$J$285:$AR$285,1,MATCH(Inputs!$F$230,Inputs!$J$282:$AR$282,0)),INDEX(Inputs!$J$287:$AR$287,1,MATCH(Inputs!$F$230,Inputs!$J$282:$AR$282,0)))/100)^((12-Inputs!$F$231)/12)*(1+CHOOSE(Inputs!$F$33,INDEX(Inputs!$J$283:$AR$283,1,MATCH(Inputs!$F$230+1,Inputs!$J$282:$AR$282,0)),INDEX(Inputs!$J$285:$AR$285,1,MATCH(Inputs!$F$230+1,Inputs!$J$282:$AR$282,0)),INDEX(Inputs!$J$287:$AR$287,1,MATCH(Inputs!$F$230+1,Inputs!$J$282:$AR$282,0)))/100)*(1+CHOOSE(Inputs!$F$33,INDEX(Inputs!$J$283:$AR$283,1,MATCH(YEAR(Inputs!$F$189),Inputs!$J$282:$AR$282,0)),INDEX(Inputs!$J$285:$AR$285,1,MATCH(YEAR(Inputs!$F$189),Inputs!$J$282:$AR$282,0)),INDEX(Inputs!$J$287:$AR$287,1,MATCH(YEAR(Inputs!$F$189),Inputs!$J$282:$AR$282,0)))/100)^(Inputs!$F$235/12)
D17: US index, first cost reading | E17: index | F17: =Inputs!$F$232*(1+CHOOSE(Inputs!$F$33,INDEX(Inputs!$J$283:$AR$283,1,MATCH(Inputs!$F$230,Inputs!$J$282:$AR$282,0)),INDEX(Inputs!$J$285:$AR$285,1,MATCH(Inputs!$F$230,Inputs!$J$282:$AR$282,0)),INDEX(Inputs!$J$287:$AR$287,1,MATCH(Inputs!$F$230,Inputs!$J$282:$AR$282,0)))/100)^((12-Inputs!$F$231)/12)*(1+CHOOSE(Inputs!$F$33,INDEX(Inputs!$J$283:$AR$283,1,MATCH(Inputs!$F$230+1,Inputs!$J$282:$AR$282,0)),INDEX(Inputs!$J$285:$AR$285,1,MATCH(Inputs!$F$230+1,Inputs!$J$282:$AR$282,0)),INDEX(Inputs!$J$287:$AR$287,1,MATCH(Inputs!$F$230+1,Inputs!$J$282:$AR$282,0)))/100)*(1+CHOOSE(Inputs!$F$33,INDEX(Inputs!$J$283:$AR$283,1,MATCH(YEAR(Inputs!$F$189),Inputs!$J$282:$AR$282,0)),INDEX(Inputs!$J$285:$AR$285,1,MATCH(YEAR(Inputs!$F$189),Inputs!$J$282:$AR$282,0)),INDEX(Inputs!$J$287:$AR$287,1,MATCH(YEAR(Inputs!$F$189),Inputs!$J$282:$AR$282,0)))/100)^(Inputs!$F$233/12)
D18: US index, first tariff reading | E18: index | F18: =Inputs!$F$232*(1+CHOOSE(Inputs!$F$33,INDEX(Inputs!$J$283:$AR$283,1,MATCH(Inputs!$F$230,Inputs!$J$282:$AR$282,0)),INDEX(Inputs!$J$285:$AR$285,1,MATCH(Inputs!$F$230,Inputs!$J$282:$AR$282,0)),INDEX(Inputs!$J$287:$AR$287,1,MATCH(Inputs!$F$230,Inputs!$J$282:$AR$282,0)))/100)^((12-Inputs!$F$231)/12)*(1+CHOOSE(Inputs!$F$33,INDEX(Inputs!$J$283:$AR$283,1,MATCH(Inputs!$F$230+1,Inputs!$J$282:$AR$282,0)),INDEX(Inputs!$J$285:$AR$285,1,MATCH(Inputs!$F$230+1,Inputs!$J$282:$AR$282,0)),INDEX(Inputs!$J$287:$AR$287,1,MATCH(Inputs!$F$230+1,Inputs!$J$282:$AR$282,0)))/100)*(1+CHOOSE(Inputs!$F$33,INDEX(Inputs!$J$283:$AR$283,1,MATCH(YEAR(Inputs!$F$189),Inputs!$J$282:$AR$282,0)),INDEX(Inputs!$J$285:$AR$285,1,MATCH(YEAR(Inputs!$F$189),Inputs!$J$282:$AR$282,0)),INDEX(Inputs!$J$287:$AR$287,1,MATCH(YEAR(Inputs!$F$189),Inputs!$J$282:$AR$282,0)))/100)^(Inputs!$F$234/12)
D19: US CPI index, cost reading (Mar/Sep), Nov 2016 = 100 | E19: index | J19: =IF(Time!J20=1,$F$17,I19*IF(Time!J27=1,(1+J14/100)^(Inputs!$F$236/12)*(1+J12/100)^((Time!J21-Inputs!$F$236)/12),(1+J12/100)^Time!J24)) | K19: =IF(Time!K20=1,$F$17,J19*IF(Time!K27=1,(1+K14/100)^(Inputs!$F$236/12)*(1+K12/100)^((Time!K21-Inputs!$F$236)/12),(1+K12/100)^Time!K24)) | L19: =IF(Time!L20=1,$F$17,K19*IF(Time!L27=1,(1+L14/100)^(Inputs!$F$236/12)*(1+L12/100)^((Time!L21-Inputs!$F$236)/12),(1+L12/100)^Time!L24)) | M19: =IF(Time!M20=1,$F$17,L19*IF(Time!M27=1,(1+M14/100)^(Inputs!$F$236/12)*(1+M12/100)^((Time!M21-Inputs!$F$236)/12),(1+M12/100)^Time!M24)) | N19: =IF(Time!N20=1,$F$17,M19*IF(Time!N27=1,(1+N14/100)^(Inputs!$F$236/12)*(1+N12/100)^((Time!N21-Inputs!$F$236)/12),(1+N12/100)^Time!N24)) | O19: =IF(Time!O20=1,$F$17,N19*IF(Time!O27=1,(1+O14/100)^(Inputs!$F$236/12)*(1+O12/100)^((Time!O21-Inputs!$F$236)/12),(1+O12/100)^Time!O24)) | P19: =IF(Time!P20=1,$F$17,O19*IF(Time!P27=1,(1+P14/100)^(Inputs!$F$236/12)*(1+P12/100)^((Time!P21-Inputs!$F$236)/12),(1+P12/100)^Time!P24)) | Q19: =IF(Time!Q20=1,$F$17,P19*IF(Time!Q27=1,(1+Q14/100)^(Inputs!$F$236/12)*(1+Q12/100)^((Time!Q21-Inputs!$F$236)/12),(1+Q12/100)^Time!Q24)) | ... BN19: =IF(Time!BN20=1,$F$17,BM19*IF(Time!BN27=1,(1+BN14/100)^(Inputs!$F$236/12)*(1+BN12/100)^((Time!BN21-Inputs!$F$236)/12),(1+BN12/100)^Time!BN24))
D20: US CPI index, tariff reading (3-month lag) | E20: index | J20: =J19*(1+J12/100)^(Inputs!$F$236/12) | K20: =K19*(1+K12/100)^(Inputs!$F$236/12) | L20: =L19*(1+L12/100)^(Inputs!$F$236/12) | M20: =M19*(1+M12/100)^(Inputs!$F$236/12) | N20: =N19*(1+N12/100)^(Inputs!$F$236/12) | O20: =O19*(1+O12/100)^(Inputs!$F$236/12) | P20: =P19*(1+P12/100)^(Inputs!$F$236/12) | Q20: =Q19*(1+Q12/100)^(Inputs!$F$236/12) | ... BN20: =BN19*(1+BN12/100)^(Inputs!$F$236/12)
D21: US cost indexation factor vs 2018 prices | E21: factor | J21: =J19/$F$16 | K21: =K19/$F$16 | L21: =L19/$F$16 | M21: =M19/$F$16 | N21: =N19/$F$16 | O21: =O19/$F$16 | P21: =P19/$F$16 | Q21: =Q19/$F$16 | ... BN21: =BN19/$F$16
D22: KC index, 2018 price base month | E22: index | F22: =Inputs!$F$232*(1+CHOOSE(Inputs!$F$33,INDEX(Inputs!$J$284:$AR$284,1,MATCH(Inputs!$F$230,Inputs!$J$282:$AR$282,0)),INDEX(Inputs!$J$286:$AR$286,1,MATCH(Inputs!$F$230,Inputs!$J$282:$AR$282,0)),INDEX(Inputs!$J$288:$AR$288,1,MATCH(Inputs!$F$230,Inputs!$J$282:$AR$282,0)))/100)^((12-Inputs!$F$231)/12)*(1+CHOOSE(Inputs!$F$33,INDEX(Inputs!$J$284:$AR$284,1,MATCH(Inputs!$F$230+1,Inputs!$J$282:$AR$282,0)),INDEX(Inputs!$J$286:$AR$286,1,MATCH(Inputs!$F$230+1,Inputs!$J$282:$AR$282,0)),INDEX(Inputs!$J$288:$AR$288,1,MATCH(Inputs!$F$230+1,Inputs!$J$282:$AR$282,0)))/100)*(1+CHOOSE(Inputs!$F$33,INDEX(Inputs!$J$284:$AR$284,1,MATCH(YEAR(Inputs!$F$189),Inputs!$J$282:$AR$282,0)),INDEX(Inputs!$J$286:$AR$286,1,MATCH(YEAR(Inputs!$F$189),Inputs!$J$282:$AR$282,0)),INDEX(Inputs!$J$288:$AR$288,1,MATCH(YEAR(Inputs!$F$189),Inputs!$J$282:$AR$282,0)))/100)^(Inputs!$F$235/12)
D23: KC index, first cost reading | E23: index | F23: =Inputs!$F$232*(1+CHOOSE(Inputs!$F$33,INDEX(Inputs!$J$284:$AR$284,1,MATCH(Inputs!$F$230,Inputs!$J$282:$AR$282,0)),INDEX(Inputs!$J$286:$AR$286,1,MATCH(Inputs!$F$230,Inputs!$J$282:$AR$282,0)),INDEX(Inputs!$J$288:$AR$288,1,MATCH(Inputs!$F$230,Inputs!$J$282:$AR$282,0)))/100)^((12-Inputs!$F$231)/12)*(1+CHOOSE(Inputs!$F$33,INDEX(Inputs!$J$284:$AR$284,1,MATCH(Inputs!$F$230+1,Inputs!$J$282:$AR$282,0)),INDEX(Inputs!$J$286:$AR$286,1,MATCH(Inputs!$F$230+1,Inputs!$J$282:$AR$282,0)),INDEX(Inputs!$J$288:$AR$288,1,MATCH(Inputs!$F$230+1,Inputs!$J$282:$AR$282,0)))/100)*(1+CHOOSE(Inputs!$F$33,INDEX(Inputs!$J$284:$AR$284,1,MATCH(YEAR(Inputs!$F$189),Inputs!$J$282:$AR$282,0)),INDEX(Inputs!$J$286:$AR$286,1,MATCH(YEAR(Inputs!$F$189),Inputs!$J$282:$AR$282,0)),INDEX(Inputs!$J$288:$AR$288,1,MATCH(YEAR(Inputs!$F$189),Inputs!$J$282:$AR$282,0)))/100)^(Inputs!$F$233/12)
D24: KC index, first tariff reading | E24: index | F24: =Inputs!$F$232*(1+CHOOSE(Inputs!$F$33,INDEX(Inputs!$J$284:$AR$284,1,MATCH(Inputs!$F$230,Inputs!$J$282:$AR$282,0)),INDEX(Inputs!$J$286:$AR$286,1,MATCH(Inputs!$F$230,Inputs!$J$282:$AR$282,0)),INDEX(Inputs!$J$288:$AR$288,1,MATCH(Inputs!$F$230,Inputs!$J$282:$AR$282,0)))/100)^((12-Inputs!$F$231)/12)*(1+CHOOSE(Inputs!$F$33,INDEX(Inputs!$J$284:$AR$284,1,MATCH(Inputs!$F$230+1,Inputs!$J$282:$AR$282,0)),INDEX(Inputs!$J$286:$AR$286,1,MATCH(Inputs!$F$230+1,Inputs!$J$282:$AR$282,0)),INDEX(Inputs!$J$288:$AR$288,1,MATCH(Inputs!$F$230+1,Inputs!$J$282:$AR$282,0)))/100)*(1+CHOOSE(Inputs!$F$33,INDEX(Inputs!$J$284:$AR$284,1,MATCH(YEAR(Inputs!$F$189),Inputs!$J$282:$AR$282,0)),INDEX(Inputs!$J$286:$AR$286,1,MATCH(YEAR(Inputs!$F$189),Inputs!$J$282:$AR$282,0)),INDEX(Inputs!$J$288:$AR$288,1,MATCH(YEAR(Inputs!$F$189),Inputs!$J$282:$AR$282,0)))/100)^(Inputs!$F$234/12)
D25: Kessara CPI index, cost reading (Mar/Sep), Nov 2016 = 100 | E25: index | J25: =IF(Time!J20=1,$F$23,I25*IF(Time!J27=1,(1+J15/100)^(Inputs!$F$236/12)*(1+J13/100)^((Time!J21-Inputs!$F$236)/12),(1+J13/100)^Time!J24)) | K25: =IF(Time!K20=1,$F$23,J25*IF(Time!K27=1,(1+K15/100)^(Inputs!$F$236/12)*(1+K13/100)^((Time!K21-Inputs!$F$236)/12),(1+K13/100)^Time!K24)) | L25: =IF(Time!L20=1,$F$23,K25*IF(Time!L27=1,(1+L15/100)^(Inputs!$F$236/12)*(1+L13/100)^((Time!L21-Inputs!$F$236)/12),(1+L13/100)^Time!L24)) | M25: =IF(Time!M20=1,$F$23,L25*IF(Time!M27=1,(1+M15/100)^(Inputs!$F$236/12)*(1+M13/100)^((Time!M21-Inputs!$F$236)/12),(1+M13/100)^Time!M24)) | N25: =IF(Time!N20=1,$F$23,M25*IF(Time!N27=1,(1+N15/100)^(Inputs!$F$236/12)*(1+N13/100)^((Time!N21-Inputs!$F$236)/12),(1+N13/100)^Time!N24)) | O25: =IF(Time!O20=1,$F$23,N25*IF(Time!O27=1,(1+O15/100)^(Inputs!$F$236/12)*(1+O13/100)^((Time!O21-Inputs!$F$236)/12),(1+O13/100)^Time!O24)) | P25: =IF(Time!P20=1,$F$23,O25*IF(Time!P27=1,(1+P15/100)^(Inputs!$F$236/12)*(1+P13/100)^((Time!P21-Inputs!$F$236)/12),(1+P13/100)^Time!P24)) | Q25: =IF(Time!Q20=1,$F$23,P25*IF(Time!Q27=1,(1+Q15/100)^(Inputs!$F$236/12)*(1+Q13/100)^((Time!Q21-Inputs!$F$236)/12),(1+Q13/100)^Time!Q24)) | ... BN25: =IF(Time!BN20=1,$F$23,BM25*IF(Time!BN27=1,(1+BN15/100)^(Inputs!$F$236/12)*(1+BN13/100)^((Time!BN21-Inputs!$F$236)/12),(1+BN13/100)^Time!BN24))
D26: Kessara CPI index, tariff reading (3-month lag) | E26: index | J26: =J25*(1+J13/100)^(Inputs!$F$236/12) | K26: =K25*(1+K13/100)^(Inputs!$F$236/12) | L26: =L25*(1+L13/100)^(Inputs!$F$236/12) | M26: =M25*(1+M13/100)^(Inputs!$F$236/12) | N26: =N25*(1+N13/100)^(Inputs!$F$236/12) | O26: =O25*(1+O13/100)^(Inputs!$F$236/12) | P26: =P25*(1+P13/100)^(Inputs!$F$236/12) | Q26: =Q25*(1+Q13/100)^(Inputs!$F$236/12) | ... BN26: =BN25*(1+BN13/100)^(Inputs!$F$236/12)
D27: Kessara cost indexation factor vs 2018 prices | E27: factor | J27: =J25/$F$22 | K27: =K25/$F$22 | L27: =L25/$F$22 | M27: =M25/$F$22 | N27: =N25/$F$22 | O27: =O25/$F$22 | P27: =P25/$F$22 | Q27: =Q25/$F$22 | ... BN27: =BN25/$F$22
B28: Plant
D29: Operating year at period start | E29: OY | J29: =INT(Time!J32/12)+1 | K29: =INT(Time!K32/12)+1 | L29: =INT(Time!L32/12)+1 | M29: =INT(Time!M32/12)+1 | N29: =INT(Time!N32/12)+1 | O29: =INT(Time!O32/12)+1 | P29: =INT(Time!P32/12)+1 | Q29: =INT(Time!Q32/12)+1 | ... BN29: =INT(Time!BN32/12)+1
D30: Months in that operating year | E30: months | J30: =MIN(Time!J33,J29*12)-Time!J32 | K30: =MIN(Time!K33,K29*12)-Time!K32 | L30: =MIN(Time!L33,L29*12)-Time!L32 | M30: =MIN(Time!M33,M29*12)-Time!M32 | N30: =MIN(Time!N33,N29*12)-Time!N32 | O30: =MIN(Time!O33,O29*12)-Time!O32 | P30: =MIN(Time!P33,P29*12)-Time!P32 | Q30: =MIN(Time!Q33,Q29*12)-Time!Q32 | ... BN30: =MIN(Time!BN33,BN29*12)-Time!BN32
D31: Availability, profile (month-weighted) | E31: % | J31: =IF(Time!J30>0,(J30*INDEX(Inputs!$J$302:$Q$302,1,MOD(J29-1,Inputs!$F$220)+1)+(Time!J30-J30)*INDEX(Inputs!$J$302:$Q$302,1,MOD(J29,Inputs!$F$220)+1))/Time!J30,0) | K31: =IF(Time!K30>0,(K30*INDEX(Inputs!$J$302:$Q$302,1,MOD(K29-1,Inputs!$F$220)+1)+(Time!K30-K30)*INDEX(Inputs!$J$302:$Q$302,1,MOD(K29,Inputs!$F$220)+1))/Time!K30,0) | L31: =IF(Time!L30>0,(L30*INDEX(Inputs!$J$302:$Q$302,1,MOD(L29-1,Inputs!$F$220)+1)+(Time!L30-L30)*INDEX(Inputs!$J$302:$Q$302,1,MOD(L29,Inputs!$F$220)+1))/Time!L30,0) | M31: =IF(Time!M30>0,(M30*INDEX(Inputs!$J$302:$Q$302,1,MOD(M29-1,Inputs!$F$220)+1)+(Time!M30-M30)*INDEX(Inputs!$J$302:$Q$302,1,MOD(M29,Inputs!$F$220)+1))/Time!M30,0) | N31: =IF(Time!N30>0,(N30*INDEX(Inputs!$J$302:$Q$302,1,MOD(N29-1,Inputs!$F$220)+1)+(Time!N30-N30)*INDEX(Inputs!$J$302:$Q$302,1,MOD(N29,Inputs!$F$220)+1))/Time!N30,0) | O31: =IF(Time!O30>0,(O30*INDEX(Inputs!$J$302:$Q$302,1,MOD(O29-1,Inputs!$F$220)+1)+(Time!O30-O30)*INDEX(Inputs!$J$302:$Q$302,1,MOD(O29,Inputs!$F$220)+1))/Time!O30,0) | P31: =IF(Time!P30>0,(P30*INDEX(Inputs!$J$302:$Q$302,1,MOD(P29-1,Inputs!$F$220)+1)+(Time!P30-P30)*INDEX(Inputs!$J$302:$Q$302,1,MOD(P29,Inputs!$F$220)+1))/Time!P30,0) | Q31: =IF(Time!Q30>0,(Q30*INDEX(Inputs!$J$302:$Q$302,1,MOD(Q29-1,Inputs!$F$220)+1)+(Time!Q30-Q30)*INDEX(Inputs!$J$302:$Q$302,1,MOD(Q29,Inputs!$F$220)+1))/Time!Q30,0) | ... BN31: =IF(Time!BN30>0,(BN30*INDEX(Inputs!$J$302:$Q$302,1,MOD(BN29-1,Inputs!$F$220)+1)+(Time!BN30-BN30)*INDEX(Inputs!$J$302:$Q$302,1,MOD(BN29,Inputs!$F$220)+1))/Time!BN30,0)
D32: Availability | E32: % | J32: =IF(Time!J30>0,J31+Inputs!$F$37,0) | K32: =IF(Time!K30>0,K31+Inputs!$F$37,0) | L32: =IF(Time!L30>0,L31+Inputs!$F$37,0) | M32: =IF(Time!M30>0,M31+Inputs!$F$37,0) | N32: =IF(Time!N30>0,N31+Inputs!$F$37,0) | O32: =IF(Time!O30>0,O31+Inputs!$F$37,0) | P32: =IF(Time!P30>0,P31+Inputs!$F$37,0) | Q32: =IF(Time!Q30>0,Q31+Inputs!$F$37,0) | ... BN32: =IF(Time!BN30>0,BN31+Inputs!$F$37,0)
D33: Years since COD (period mid-point) | E33: years | J33: =IF(Time!J30>0,AVERAGE(Time!J32,Time!J33)/12,0) | K33: =IF(Time!K30>0,AVERAGE(Time!K32,Time!K33)/12,0) | L33: =IF(Time!L30>0,AVERAGE(Time!L32,Time!L33)/12,0) | M33: =IF(Time!M30>0,AVERAGE(Time!M32,Time!M33)/12,0) | N33: =IF(Time!N30>0,AVERAGE(Time!N32,Time!N33)/12,0) | O33: =IF(Time!O30>0,AVERAGE(Time!O32,Time!O33)/12,0) | P33: =IF(Time!P30>0,AVERAGE(Time!P32,Time!P33)/12,0) | Q33: =IF(Time!Q30>0,AVERAGE(Time!Q32,Time!Q33)/12,0) | ... BN33: =IF(Time!BN30>0,AVERAGE(Time!BN32,Time!BN33)/12,0)
D34: Contracted capacity | E34: MW | F34: =IF(Inputs!$F$34<>1,Inputs!$F$117,Inputs!$F$116)
D35: Plant net heat rate, new and clean | E35: kJ/kWh | F35: =IF(Inputs!$F$34<>1,Inputs!$F$119,Inputs!$F$118)
D36: Output degradation factor | E36: factor | J36: =(1-Inputs!$F$125/100*J33)*(1-Inputs!$F$126/100) | K36: =(1-Inputs!$F$125/100*K33)*(1-Inputs!$F$126/100) | L36: =(1-Inputs!$F$125/100*L33)*(1-Inputs!$F$126/100) | M36: =(1-Inputs!$F$125/100*M33)*(1-Inputs!$F$126/100) | N36: =(1-Inputs!$F$125/100*N33)*(1-Inputs!$F$126/100) | O36: =(1-Inputs!$F$125/100*O33)*(1-Inputs!$F$126/100) | P36: =(1-Inputs!$F$125/100*P33)*(1-Inputs!$F$126/100) | Q36: =(1-Inputs!$F$125/100*Q33)*(1-Inputs!$F$126/100) | ... BN36: =(1-Inputs!$F$125/100*BN33)*(1-Inputs!$F$126/100)
D37: Dispatch factor when available | E37: % | J37: =IF(AND(Inputs!$F$55=1,Inputs!J303>0),Inputs!J303,Inputs!$F$38) | K37: =IF(AND(Inputs!$F$55=1,Inputs!K303>0),Inputs!K303,Inputs!$F$38) | L37: =IF(AND(Inputs!$F$55=1,Inputs!L303>0),Inputs!L303,Inputs!$F$38) | M37: =IF(AND(Inputs!$F$55=1,Inputs!M303>0),Inputs!M303,Inputs!$F$38) | N37: =IF(AND(Inputs!$F$55=1,Inputs!N303>0),Inputs!N303,Inputs!$F$38) | O37: =IF(AND(Inputs!$F$55=1,Inputs!O303>0),Inputs!O303,Inputs!$F$38) | P37: =IF(AND(Inputs!$F$55=1,Inputs!P303>0),Inputs!P303,Inputs!$F$38) | Q37: =IF(AND(Inputs!$F$55=1,Inputs!Q303>0),Inputs!Q303,Inputs!$F$38) | ... BN37: =IF(AND(Inputs!$F$55=1,Inputs!BN303>0),Inputs!BN303,Inputs!$F$38)
D38: Net energy delivered | E38: MWh | J38: =$F$34*Inputs!$F$215*Time!J30*J32/100*J37/100*J36 | K38: =$F$34*Inputs!$F$215*Time!K30*K32/100*K37/100*K36 | L38: =$F$34*Inputs!$F$215*Time!L30*L32/100*L37/100*L36 | M38: =$F$34*Inputs!$F$215*Time!M30*M32/100*M37/100*M36 | N38: =$F$34*Inputs!$F$215*Time!N30*N32/100*N37/100*N36 | O38: =$F$34*Inputs!$F$215*Time!O30*O32/100*O37/100*O36 | P38: =$F$34*Inputs!$F$215*Time!P30*P32/100*P37/100*P36 | Q38: =$F$34*Inputs!$F$215*Time!Q30*Q32/100*Q37/100*Q36 | ... BN38: =$F$34*Inputs!$F$215*Time!BN30*BN32/100*BN37/100*BN36
D39: Plant net heat rate | E39: kJ/kWh | J39: =$F$35*(1+Inputs!$F$127/100*J33)*(1+Inputs!$F$128/100)*(1+Inputs!$F$122/100)*Inputs!$F$39 | K39: =$F$35*(1+Inputs!$F$127/100*K33)*(1+Inputs!$F$128/100)*(1+Inputs!$F$122/100)*Inputs!$F$39 | L39: =$F$35*(1+Inputs!$F$127/100*L33)*(1+Inputs!$F$128/100)*(1+Inputs!$F$122/100)*Inputs!$F$39 | M39: =$F$35*(1+Inputs!$F$127/100*M33)*(1+Inputs!$F$128/100)*(1+Inputs!$F$122/100)*Inputs!$F$39 | N39: =$F$35*(1+Inputs!$F$127/100*N33)*(1+Inputs!$F$128/100)*(1+Inputs!$F$122/100)*Inputs!$F$39 | O39: =$F$35*(1+Inputs!$F$127/100*O33)*(1+Inputs!$F$128/100)*(1+Inputs!$F$122/100)*Inputs!$F$39 | P39: =$F$35*(1+Inputs!$F$127/100*P33)*(1+Inputs!$F$128/100)*(1+Inputs!$F$122/100)*Inputs!$F$39 | Q39: =$F$35*(1+Inputs!$F$127/100*Q33)*(1+Inputs!$F$128/100)*(1+Inputs!$F$122/100)*Inputs!$F$39 | ... BN39: =$F$35*(1+Inputs!$F$127/100*BN33)*(1+Inputs!$F$128/100)*(1+Inputs!$F$122/100)*Inputs!$F$39
D40: Contracted heat rate at dispatched load | E40: kJ/kWh | J40: =Inputs!$F$120*(1+Inputs!$F$121/100*J33)*(1+Inputs!$F$122/100) | K40: =Inputs!$F$120*(1+Inputs!$F$121/100*K33)*(1+Inputs!$F$122/100) | L40: =Inputs!$F$120*(1+Inputs!$F$121/100*L33)*(1+Inputs!$F$122/100) | M40: =Inputs!$F$120*(1+Inputs!$F$121/100*M33)*(1+Inputs!$F$122/100) | N40: =Inputs!$F$120*(1+Inputs!$F$121/100*N33)*(1+Inputs!$F$122/100) | O40: =Inputs!$F$120*(1+Inputs!$F$121/100*O33)*(1+Inputs!$F$122/100) | P40: =Inputs!$F$120*(1+Inputs!$F$121/100*P33)*(1+Inputs!$F$122/100) | Q40: =Inputs!$F$120*(1+Inputs!$F$121/100*Q33)*(1+Inputs!$F$122/100) | ... BN40: =Inputs!$F$120*(1+Inputs!$F$121/100*BN33)*(1+Inputs!$F$122/100)
D41: Gas price (GCV) | E41: USD/MMBtu | J41: =Inputs!$F$142*(1+Inputs!$F$143/100)^(Time!J26-Inputs!$F$256)*Inputs!$F$41 | K41: =Inputs!$F$142*(1+Inputs!$F$143/100)^(Time!K26-Inputs!$F$256)*Inputs!$F$41 | L41: =Inputs!$F$142*(1+Inputs!$F$143/100)^(Time!L26-Inputs!$F$256)*Inputs!$F$41 | M41: =Inputs!$F$142*(1+Inputs!$F$143/100)^(Time!M26-Inputs!$F$256)*Inputs!$F$41 | N41: =Inputs!$F$142*(1+Inputs!$F$143/100)^(Time!N26-Inputs!$F$256)*Inputs!$F$41 | O41: =Inputs!$F$142*(1+Inputs!$F$143/100)^(Time!O26-Inputs!$F$256)*Inputs!$F$41 | P41: =Inputs!$F$142*(1+Inputs!$F$143/100)^(Time!P26-Inputs!$F$256)*Inputs!$F$41 | Q41: =Inputs!$F$142*(1+Inputs!$F$143/100)^(Time!Q26-Inputs!$F$256)*Inputs!$F$41 | ... BN41: =Inputs!$F$142*(1+Inputs!$F$143/100)^(Time!BN26-Inputs!$F$256)*Inputs!$F$41
D42: Gas burned | E42: MMBtu | J42: =J38*J39*(1000*Inputs!$F$123/Inputs!$F$124) | K42: =K38*K39*(1000*Inputs!$F$123/Inputs!$F$124) | L42: =L38*L39*(1000*Inputs!$F$123/Inputs!$F$124) | M42: =M38*M39*(1000*Inputs!$F$123/Inputs!$F$124) | N42: =N38*N39*(1000*Inputs!$F$123/Inputs!$F$124) | O42: =O38*O39*(1000*Inputs!$F$123/Inputs!$F$124) | P42: =P38*P39*(1000*Inputs!$F$123/Inputs!$F$124) | Q42: =Q38*Q39*(1000*Inputs!$F$123/Inputs!$F$124) | ... BN42: =BN38*BN39*(1000*Inputs!$F$123/Inputs!$F$124)
D43: Take-or-pay quantity | E43: MMBtu | J43: =Inputs!$F$145*Inputs!$F$144*Time!J31 | K43: =Inputs!$F$145*Inputs!$F$144*Time!K31 | L43: =Inputs!$F$145*Inputs!$F$144*Time!L31 | M43: =Inputs!$F$145*Inputs!$F$144*Time!M31 | N43: =Inputs!$F$145*Inputs!$F$144*Time!N31 | O43: =Inputs!$F$145*Inputs!$F$144*Time!O31 | P43: =Inputs!$F$145*Inputs!$F$144*Time!P31 | Q43: =Inputs!$F$145*Inputs!$F$144*Time!Q31 | ... BN43: =Inputs!$F$145*Inputs!$F$144*Time!BN31
B44: Revenue (USD m)
D45: Capital charge, indexed | E45: USD/kW-month | J45: =Inputs!$F$134*Inputs!$F$54*(1-Inputs!$F$135+Inputs!$F$135*J20/100) | K45: =Inputs!$F$134*Inputs!$F$54*(1-Inputs!$F$135+Inputs!$F$135*K20/100) | L45: =Inputs!$F$134*Inputs!$F$54*(1-Inputs!$F$135+Inputs!$F$135*L20/100) | M45: =Inputs!$F$134*Inputs!$F$54*(1-Inputs!$F$135+Inputs!$F$135*M20/100) | N45: =Inputs!$F$134*Inputs!$F$54*(1-Inputs!$F$135+Inputs!$F$135*N20/100) | O45: =Inputs!$F$134*Inputs!$F$54*(1-Inputs!$F$135+Inputs!$F$135*O20/100) | P45: =Inputs!$F$134*Inputs!$F$54*(1-Inputs!$F$135+Inputs!$F$135*P20/100) | Q45: =Inputs!$F$134*Inputs!$F$54*(1-Inputs!$F$135+Inputs!$F$135*Q20/100) | ... BN45: =Inputs!$F$134*Inputs!$F$54*(1-Inputs!$F$135+Inputs!$F$135*BN20/100)
D46: Fixed O&M charge, indexed | E46: USD/kW-month | J46: =Inputs!$F$136*(Inputs!$F$137*J20/100+(1-Inputs!$F$137)*J26/100*Inputs!$F$138/J11) | K46: =Inputs!$F$136*(Inputs!$F$137*K20/100+(1-Inputs!$F$137)*K26/100*Inputs!$F$138/K11) | L46: =Inputs!$F$136*(Inputs!$F$137*L20/100+(1-Inputs!$F$137)*L26/100*Inputs!$F$138/L11) | M46: =Inputs!$F$136*(Inputs!$F$137*M20/100+(1-Inputs!$F$137)*M26/100*Inputs!$F$138/M11) | N46: =Inputs!$F$136*(Inputs!$F$137*N20/100+(1-Inputs!$F$137)*N26/100*Inputs!$F$138/N11) | O46: =Inputs!$F$136*(Inputs!$F$137*O20/100+(1-Inputs!$F$137)*O26/100*Inputs!$F$138/O11) | P46: =Inputs!$F$136*(Inputs!$F$137*P20/100+(1-Inputs!$F$137)*P26/100*Inputs!$F$138/P11) | Q46: =Inputs!$F$136*(Inputs!$F$137*Q20/100+(1-Inputs!$F$137)*Q26/100*Inputs!$F$138/Q11) | ... BN46: =Inputs!$F$136*(Inputs!$F$137*BN20/100+(1-Inputs!$F$137)*BN26/100*Inputs!$F$138/BN11)
D47: Availability factor min(1, A/90%) | E47: factor | J47: =J32/Inputs!$F$133 | K47: =K32/Inputs!$F$133 | L47: =L32/Inputs!$F$133 | M47: =M32/Inputs!$F$133 | N47: =N32/Inputs!$F$133 | O47: =O32/Inputs!$F$133 | P47: =P32/Inputs!$F$133 | Q47: =Q32/Inputs!$F$133 | ... BN47: =BN32/Inputs!$F$133
D48: Capacity payment | E48: USD m | G48: =SUM(J48:BN48) | J48: =$F$34*1000*Time!J30*(J45+J46)*J47/1000000 | K48: =$F$34*1000*Time!K30*(K45+K46)*K47/1000000 | L48: =$F$34*1000*Time!L30*(L45+L46)*L47/1000000 | M48: =$F$34*1000*Time!M30*(M45+M46)*M47/1000000 | N48: =$F$34*1000*Time!N30*(N45+N46)*N47/1000000 | O48: =$F$34*1000*Time!O30*(O45+O46)*O47/1000000 | P48: =$F$34*1000*Time!P30*(P45+P46)*P47/1000000 | Q48: =$F$34*1000*Time!Q30*(Q45+Q46)*Q47/1000000 | ... BN48: =$F$34*1000*Time!BN30*(BN45+BN46)*BN47/1000000
D49: VOM charge, indexed | E49: USD/MWh | J49: =Inputs!$F$139*(Inputs!$F$140*J20/100+(1-Inputs!$F$140)*J26/100*Inputs!$F$138/J11) | K49: =Inputs!$F$139*(Inputs!$F$140*K20/100+(1-Inputs!$F$140)*K26/100*Inputs!$F$138/K11) | L49: =Inputs!$F$139*(Inputs!$F$140*L20/100+(1-Inputs!$F$140)*L26/100*Inputs!$F$138/L11) | M49: =Inputs!$F$139*(Inputs!$F$140*M20/100+(1-Inputs!$F$140)*M26/100*Inputs!$F$138/M11) | N49: =Inputs!$F$139*(Inputs!$F$140*N20/100+(1-Inputs!$F$140)*N26/100*Inputs!$F$138/N11) | O49: =Inputs!$F$139*(Inputs!$F$140*O20/100+(1-Inputs!$F$140)*O26/100*Inputs!$F$138/O11) | P49: =Inputs!$F$139*(Inputs!$F$140*P20/100+(1-Inputs!$F$140)*P26/100*Inputs!$F$138/P11) | Q49: =Inputs!$F$139*(Inputs!$F$140*Q20/100+(1-Inputs!$F$140)*Q26/100*Inputs!$F$138/Q11) | ... BN49: =Inputs!$F$139*(Inputs!$F$140*BN20/100+(1-Inputs!$F$140)*BN26/100*Inputs!$F$138/BN11)
D50: Variable O&M payment | E50: USD m | G50: =SUM(J50:BN50) | J50: =J38*J49/1000000 | K50: =K38*K49/1000000 | L50: =L38*L49/1000000 | M50: =M38*M49/1000000 | N50: =N38*N49/1000000 | O50: =O38*O49/1000000 | P50: =P38*P49/1000000 | Q50: =Q38*Q49/1000000 | ... BN50: =BN38*BN49/1000000
D51: Fuel charge (pass-through) | E51: USD m | G51: =SUM(J51:BN51) | J51: =J38*J40*(1000*Inputs!$F$123/Inputs!$F$124)*J41/1000000*0.765/(Inputs!$F$38/100) | K51: =K38*K40*(1000*Inputs!$F$123/Inputs!$F$124)*K41/1000000*0.765/(Inputs!$F$38/100) | L51: =L38*L40*(1000*Inputs!$F$123/Inputs!$F$124)*L41/1000000*0.765/(Inputs!$F$38/100) | M51: =M38*M40*(1000*Inputs!$F$123/Inputs!$F$124)*M41/1000000*0.765/(Inputs!$F$38/100) | N51: =N38*N40*(1000*Inputs!$F$123/Inputs!$F$124)*N41/1000000*0.765/(Inputs!$F$38/100) | O51: =O38*O40*(1000*Inputs!$F$123/Inputs!$F$124)*O41/1000000*0.765/(Inputs!$F$38/100) | P51: =P38*P40*(1000*Inputs!$F$123/Inputs!$F$124)*P41/1000000*0.765/(Inputs!$F$38/100) | Q51: =Q38*Q40*(1000*Inputs!$F$123/Inputs!$F$124)*Q41/1000000*0.765/(Inputs!$F$38/100) | ... BN51: =BN38*BN40*(1000*Inputs!$F$123/Inputs!$F$124)*BN41/1000000*0.765/(Inputs!$F$38/100)
D52: GTA reservation charge (pass-through) | E52: USD m | G52: =SUM(J52:BN52) | J52: =Inputs!$F$146*Time!J31*Inputs!$F$147*(1+Inputs!$F$149/100)^(Time!J26-Inputs!$F$256)/1000000 | K52: =Inputs!$F$146*Time!K31*Inputs!$F$147*(1+Inputs!$F$149/100)^(Time!K26-Inputs!$F$256)/1000000 | L52: =Inputs!$F$146*Time!L31*Inputs!$F$147*(1+Inputs!$F$149/100)^(Time!L26-Inputs!$F$256)/1000000 | M52: =Inputs!$F$146*Time!M31*Inputs!$F$147*(1+Inputs!$F$149/100)^(Time!M26-Inputs!$F$256)/1000000 | N52: =Inputs!$F$146*Time!N31*Inputs!$F$147*(1+Inputs!$F$149/100)^(Time!N26-Inputs!$F$256)/1000000 | O52: =Inputs!$F$146*Time!O31*Inputs!$F$147*(1+Inputs!$F$149/100)^(Time!O26-Inputs!$F$256)/1000000 | P52: =Inputs!$F$146*Time!P31*Inputs!$F$147*(1+Inputs!$F$149/100)^(Time!P26-Inputs!$F$256)/1000000 | Q52: =Inputs!$F$146*Time!Q31*Inputs!$F$147*(1+Inputs!$F$149/100)^(Time!Q26-Inputs!$F$256)/1000000 | ... BN52: =Inputs!$F$146*Time!BN31*Inputs!$F$147*(1+Inputs!$F$149/100)^(Time!BN26-Inputs!$F$256)/1000000
D53: GTA commodity charge (pass-through) | E53: USD m | G53: =SUM(J53:BN53) | J53: =J42*Inputs!$F$148*(1+Inputs!$F$149/100)^(Time!J26-Inputs!$F$256)/1000000 | K53: =K42*Inputs!$F$148*(1+Inputs!$F$149/100)^(Time!K26-Inputs!$F$256)/1000000 | L53: =L42*Inputs!$F$148*(1+Inputs!$F$149/100)^(Time!L26-Inputs!$F$256)/1000000 | M53: =M42*Inputs!$F$148*(1+Inputs!$F$149/100)^(Time!M26-Inputs!$F$256)/1000000 | N53: =N42*Inputs!$F$148*(1+Inputs!$F$149/100)^(Time!N26-Inputs!$F$256)/1000000 | O53: =O42*Inputs!$F$148*(1+Inputs!$F$149/100)^(Time!O26-Inputs!$F$256)/1000000 | P53: =P42*Inputs!$F$148*(1+Inputs!$F$149/100)^(Time!P26-Inputs!$F$256)/1000000 | Q53: =Q42*Inputs!$F$148*(1+Inputs!$F$149/100)^(Time!Q26-Inputs!$F$256)/1000000 | ... BN53: =BN42*Inputs!$F$148*(1+Inputs!$F$149/100)^(Time!BN26-Inputs!$F$256)/1000000
D54: Take-or-pay payment (pass-through) | E54: USD m | G54: =SUM(J54:BN54) | J54: =MAX(0,J43-J42)*J41/1000000 | K54: =MAX(0,K43-K42)*K41/1000000 | L54: =MAX(0,L43-L42)*L41/1000000 | M54: =MAX(0,M43-M42)*M41/1000000 | N54: =MAX(0,N43-N42)*N41/1000000 | O54: =MAX(0,O43-O42)*O41/1000000 | P54: =MAX(0,P43-P42)*P41/1000000 | Q54: =MAX(0,Q43-Q42)*Q41/1000000 | ... BN54: =MAX(0,BN43-BN42)*BN41/1000000
D55: Non-fuel revenue | E55: USD m | G55: =SUM(J55:BN55) | J55: =J48+J50 | K55: =K48+K50 | L55: =L48+L50 | M55: =M48+M50 | N55: =N48+N50 | O55: =O48+O50 | P55: =P48+P50 | Q55: =Q48+Q50 | ... BN55: =BN48+BN50
D56: Total revenue | E56: USD m | G56: =SUM(J56:BN56) | J56: =J55+J51+J52+J53+J54 | K56: =K55+K51+K52+K53+K54 | L56: =L55+L51+L52+L53+L54 | M56: =M55+M51+M52+M53+M54 | N56: =N55+N51+N52+N53+N54 | O56: =O55+O51+O52+O53+O54 | P56: =P55+P51+P52+P53+P54 | Q56: =Q55+Q51+Q52+Q53+Q54 | ... BN56: =BN55+BN51+BN52+BN53+BN54
D57: Late payment interest accrued (to settlement 2024-03-21) | E57: USD m | G57: =SUM(J57:BN57) | J57: =IF(Inputs!$F$45=1,AVERAGE(I89,J89)*(J9-Time!J40*Inputs!$F$98+Inputs!$F$263)/100*Time!J55/Inputs!$F$247,0) | K57: =IF(Inputs!$F$45=1,AVERAGE(J89,K89)*(K9-Time!K40*Inputs!$F$98+Inputs!$F$263)/100*Time!K55/Inputs!$F$247,0) | L57: =IF(Inputs!$F$45=1,AVERAGE(K89,L89)*(L9-Time!L40*Inputs!$F$98+Inputs!$F$263)/100*Time!L55/Inputs!$F$247,0) | M57: =IF(Inputs!$F$45=1,AVERAGE(L89,M89)*(M9-Time!M40*Inputs!$F$98+Inputs!$F$263)/100*Time!M55/Inputs!$F$247,0) | N57: =IF(Inputs!$F$45=1,AVERAGE(M89,N89)*(N9-Time!N40*Inputs!$F$98+Inputs!$F$263)/100*Time!N55/Inputs!$F$247,0) | O57: =IF(Inputs!$F$45=1,AVERAGE(N89,O89)*(O9-Time!O40*Inputs!$F$98+Inputs!$F$263)/100*Time!O55/Inputs!$F$247,0) | P57: =IF(Inputs!$F$45=1,AVERAGE(O89,P89)*(P9-Time!P40*Inputs!$F$98+Inputs!$F$263)/100*Time!P55/Inputs!$F$247,0) | Q57: =IF(Inputs!$F$45=1,AVERAGE(P89,Q89)*(Q9-Time!Q40*Inputs!$F$98+Inputs!$F$263)/100*Time!Q55/Inputs!$F$247,0) | ... BN57: =IF(Inputs!$F$45=1,AVERAGE(BM89,BN89)*(BN9-Time!BN40*Inputs!$F$98+Inputs!$F$263)/100*Time!BN55/Inputs!$F$247,0)
D58: Late payment interest received (60%, with settlement installments) | E58: USD m | G58: =SUM(J58:BN58) | J58: =Inputs!$F$264*SUM($J$57:$BN$57)*Inputs!J297 | K58: =Inputs!$F$264*SUM($J$57:$BN$57)*Inputs!K297 | L58: =Inputs!$F$264*SUM($J$57:$BN$57)*Inputs!L297 | M58: =Inputs!$F$264*SUM($J$57:$BN$57)*Inputs!M297 | N58: =Inputs!$F$264*SUM($J$57:$BN$57)*Inputs!N297 | O58: =Inputs!$F$264*SUM($J$57:$BN$57)*Inputs!O297 | P58: =Inputs!$F$264*SUM($J$57:$BN$57)*Inputs!P297 | Q58: =Inputs!$F$264*SUM($J$57:$BN$57)*Inputs!Q297 | ... BN58: =Inputs!$F$264*SUM($J$57:$BN$57)*Inputs!BN297
B59: Operating costs (USD m)
D60: O&M fixed fee | E60: USD m | G60: =SUM(J60:BN60) | J60: =Inputs!$F$151*(Inputs!$F$152*J21+(1-Inputs!$F$152)*J27*Inputs!$F$153/J11)*Time!J30/12*Inputs!$F$40 | K60: =Inputs!$F$151*(Inputs!$F$152*K21+(1-Inputs!$F$152)*K27*Inputs!$F$153/K11)*Time!K30/12*Inputs!$F$40 | L60: =Inputs!$F$151*(Inputs!$F$152*L21+(1-Inputs!$F$152)*L27*Inputs!$F$153/L11)*Time!L30/12*Inputs!$F$40 | M60: =Inputs!$F$151*(Inputs!$F$152*M21+(1-Inputs!$F$152)*M27*Inputs!$F$153/M11)*Time!M30/12*Inputs!$F$40 | N60: =Inputs!$F$151*(Inputs!$F$152*N21+(1-Inputs!$F$152)*N27*Inputs!$F$153/N11)*Time!N30/12*Inputs!$F$40 | O60: =Inputs!$F$151*(Inputs!$F$152*O21+(1-Inputs!$F$152)*O27*Inputs!$F$153/O11)*Time!O30/12*Inputs!$F$40 | P60: =Inputs!$F$151*(Inputs!$F$152*P21+(1-Inputs!$F$152)*P27*Inputs!$F$153/P11)*Time!P30/12*Inputs!$F$40 | Q60: =Inputs!$F$151*(Inputs!$F$152*Q21+(1-Inputs!$F$152)*Q27*Inputs!$F$153/Q11)*Time!Q30/12*Inputs!$F$40 | ... BN60: =Inputs!$F$151*(Inputs!$F$152*BN21+(1-Inputs!$F$152)*BN27*Inputs!$F$153/BN11)*Time!BN30/12*Inputs!$F$40
D61: O&M availability incentive | E61: USD m | G61: =SUM(J61:BN61) | J61: =IF(Time!J30>0,Inputs!$F$154*MAX(-1,MIN(1,(J32-Inputs!$F$216)/Inputs!$F$217))*J21*Time!J30/12,0) | K61: =IF(Time!K30>0,Inputs!$F$154*MAX(-1,MIN(1,(K32-Inputs!$F$216)/Inputs!$F$217))*K21*Time!K30/12,0) | L61: =IF(Time!L30>0,Inputs!$F$154*MAX(-1,MIN(1,(L32-Inputs!$F$216)/Inputs!$F$217))*L21*Time!L30/12,0) | M61: =IF(Time!M30>0,Inputs!$F$154*MAX(-1,MIN(1,(M32-Inputs!$F$216)/Inputs!$F$217))*M21*Time!M30/12,0) | N61: =IF(Time!N30>0,Inputs!$F$154*MAX(-1,MIN(1,(N32-Inputs!$F$216)/Inputs!$F$217))*N21*Time!N30/12,0) | O61: =IF(Time!O30>0,Inputs!$F$154*MAX(-1,MIN(1,(O32-Inputs!$F$216)/Inputs!$F$217))*O21*Time!O30/12,0) | P61: =IF(Time!P30>0,Inputs!$F$154*MAX(-1,MIN(1,(P32-Inputs!$F$216)/Inputs!$F$217))*P21*Time!P30/12,0) | Q61: =IF(Time!Q30>0,Inputs!$F$154*MAX(-1,MIN(1,(Q32-Inputs!$F$216)/Inputs!$F$217))*Q21*Time!Q30/12,0) | ... BN61: =IF(Time!BN30>0,Inputs!$F$154*MAX(-1,MIN(1,(BN32-Inputs!$F$216)/Inputs!$F$217))*BN21*Time!BN30/12,0)
D62: LTSA fixed fee | E62: USD m | G62: =SUM(J62:BN62) | J62: =Inputs!$F$155*J21*Time!J30/12*Inputs!$F$40 | K62: =Inputs!$F$155*K21*Time!K30/12*Inputs!$F$40 | L62: =Inputs!$F$155*L21*Time!L30/12*Inputs!$F$40 | M62: =Inputs!$F$155*M21*Time!M30/12*Inputs!$F$40 | N62: =Inputs!$F$155*N21*Time!N30/12*Inputs!$F$40 | O62: =Inputs!$F$155*O21*Time!O30/12*Inputs!$F$40 | P62: =Inputs!$F$155*P21*Time!P30/12*Inputs!$F$40 | Q62: =Inputs!$F$155*Q21*Time!Q30/12*Inputs!$F$40 | ... BN62: =Inputs!$F$155*BN21*Time!BN30/12*Inputs!$F$40
D63: Equivalent operating hours (2 GTs) | E63: EOH | J63: =IF(J31>0,1*(Inputs!$F$129*J32/J31*J37/Inputs!$F$131+Inputs!$F$130*Inputs!$F$132)*Time!J30/12,0) | K63: =IF(K31>0,1*(Inputs!$F$129*K32/K31*K37/Inputs!$F$131+Inputs!$F$130*Inputs!$F$132)*Time!K30/12,0) | L63: =IF(L31>0,1*(Inputs!$F$129*L32/L31*L37/Inputs!$F$131+Inputs!$F$130*Inputs!$F$132)*Time!L30/12,0) | M63: =IF(M31>0,1*(Inputs!$F$129*M32/M31*M37/Inputs!$F$131+Inputs!$F$130*Inputs!$F$132)*Time!M30/12,0) | N63: =IF(N31>0,1*(Inputs!$F$129*N32/N31*N37/Inputs!$F$131+Inputs!$F$130*Inputs!$F$132)*Time!N30/12,0) | O63: =IF(O31>0,1*(Inputs!$F$129*O32/O31*O37/Inputs!$F$131+Inputs!$F$130*Inputs!$F$132)*Time!O30/12,0) | P63: =IF(P31>0,1*(Inputs!$F$129*P32/P31*P37/Inputs!$F$131+Inputs!$F$130*Inputs!$F$132)*Time!P30/12,0) | Q63: =IF(Q31>0,1*(Inputs!$F$129*Q32/Q31*Q37/Inputs!$F$131+Inputs!$F$130*Inputs!$F$132)*Time!Q30/12,0) | ... BN63: =IF(BN31>0,1*(Inputs!$F$129*BN32/BN31*BN37/Inputs!$F$131+Inputs!$F$130*Inputs!$F$132)*Time!BN30/12,0)
D64: LTSA variable fee | E64: USD m | G64: =SUM(J64:BN64) | J64: =J63*Inputs!$F$156*J21/1000000 | K64: =K63*Inputs!$F$156*K21/1000000 | L64: =L63*Inputs!$F$156*L21/1000000 | M64: =M63*Inputs!$F$156*M21/1000000 | N64: =N63*Inputs!$F$156*N21/1000000 | O64: =O63*Inputs!$F$156*O21/1000000 | P64: =P63*Inputs!$F$156*P21/1000000 | Q64: =Q63*Inputs!$F$156*Q21/1000000 | ... BN64: =BN63*Inputs!$F$156*BN21/1000000
D65: Operational insurance | E65: USD m | G65: =SUM(J65:BN65) | J65: =Inputs!$F$157*J21*Time!J30/12*(1+Inputs!$F$158*Inputs!$F$46*Time!J41)*Inputs!$F$40 | K65: =Inputs!$F$157*K21*Time!K30/12*(1+Inputs!$F$158*Inputs!$F$46*Time!K41)*Inputs!$F$40 | L65: =Inputs!$F$157*L21*Time!L30/12*(1+Inputs!$F$158*Inputs!$F$46*Time!L41)*Inputs!$F$40 | M65: =Inputs!$F$157*M21*Time!M30/12*(1+Inputs!$F$158*Inputs!$F$46*Time!M41)*Inputs!$F$40 | N65: =Inputs!$F$157*N21*Time!N30/12*(1+Inputs!$F$158*Inputs!$F$46*Time!N41)*Inputs!$F$40 | O65: =Inputs!$F$157*O21*Time!O30/12*(1+Inputs!$F$158*Inputs!$F$46*Time!O41)*Inputs!$F$40 | P65: =Inputs!$F$157*P21*Time!P30/12*(1+Inputs!$F$158*Inputs!$F$46*Time!P41)*Inputs!$F$40 | Q65: =Inputs!$F$157*Q21*Time!Q30/12*(1+Inputs!$F$158*Inputs!$F$46*Time!Q41)*Inputs!$F$40 | ... BN65: =Inputs!$F$157*BN21*Time!BN30/12*(1+Inputs!$F$158*Inputs!$F$46*Time!BN41)*Inputs!$F$40
D66: G&A | E66: USD m | G66: =SUM(J66:BN66) | J66: =Inputs!$F$159*(Inputs!$F$218*J21+(1-Inputs!$F$218)*J27*Inputs!$F$153/J11)*Time!J30/12*Inputs!$F$40 | K66: =Inputs!$F$159*(Inputs!$F$218*K21+(1-Inputs!$F$218)*K27*Inputs!$F$153/K11)*Time!K30/12*Inputs!$F$40 | L66: =Inputs!$F$159*(Inputs!$F$218*L21+(1-Inputs!$F$218)*L27*Inputs!$F$153/L11)*Time!L30/12*Inputs!$F$40 | M66: =Inputs!$F$159*(Inputs!$F$218*M21+(1-Inputs!$F$218)*M27*Inputs!$F$153/M11)*Time!M30/12*Inputs!$F$40 | N66: =Inputs!$F$159*(Inputs!$F$218*N21+(1-Inputs!$F$218)*N27*Inputs!$F$153/N11)*Time!N30/12*Inputs!$F$40 | O66: =Inputs!$F$159*(Inputs!$F$218*O21+(1-Inputs!$F$218)*O27*Inputs!$F$153/O11)*Time!O30/12*Inputs!$F$40 | P66: =Inputs!$F$159*(Inputs!$F$218*P21+(1-Inputs!$F$218)*P27*Inputs!$F$153/P11)*Time!P30/12*Inputs!$F$40 | Q66: =Inputs!$F$159*(Inputs!$F$218*Q21+(1-Inputs!$F$218)*Q27*Inputs!$F$153/Q11)*Time!Q30/12*Inputs!$F$40 | ... BN66: =Inputs!$F$159*(Inputs!$F$218*BN21+(1-Inputs!$F$218)*BN27*Inputs!$F$153/BN11)*Time!BN30/12*Inputs!$F$40
D67: Land lease and permits | E67: USD m | G67: =SUM(J67:BN67) | J67: =Inputs!$F$160*J27/J11*Time!J30/12*Inputs!$F$40 | K67: =Inputs!$F$160*K27/K11*Time!K30/12*Inputs!$F$40 | L67: =Inputs!$F$160*L27/L11*Time!L30/12*Inputs!$F$40 | M67: =Inputs!$F$160*M27/M11*Time!M30/12*Inputs!$F$40 | N67: =Inputs!$F$160*N27/N11*Time!N30/12*Inputs!$F$40 | O67: =Inputs!$F$160*O27/O11*Time!O30/12*Inputs!$F$40 | P67: =Inputs!$F$160*P27/P11*Time!P30/12*Inputs!$F$40 | Q67: =Inputs!$F$160*Q27/Q11*Time!Q30/12*Inputs!$F$40 | ... BN67: =Inputs!$F$160*BN27/BN11*Time!BN30/12*Inputs!$F$40
D68: Community fund and OREK levy | E68: USD m | G68: =SUM(J68:BN68) | J68: =Inputs!$F$161/100*J55 | K68: =Inputs!$F$161/100*K55 | L68: =Inputs!$F$161/100*L55 | M68: =Inputs!$F$161/100*M55 | N68: =Inputs!$F$161/100*N55 | O68: =Inputs!$F$161/100*O55 | P68: =Inputs!$F$161/100*P55 | Q68: =Inputs!$F$161/100*Q55 | ... BN68: =Inputs!$F$161/100*BN55
D69: Variable consumables | E69: USD m | G69: =SUM(J69:BN69) | J69: =Inputs!$F$162*(Inputs!$F$219*J21+(1-Inputs!$F$219)*J27*Inputs!$F$153/J11)*J38/1000000 | K69: =Inputs!$F$162*(Inputs!$F$219*K21+(1-Inputs!$F$219)*K27*Inputs!$F$153/K11)*K38/1000000 | L69: =Inputs!$F$162*(Inputs!$F$219*L21+(1-Inputs!$F$219)*L27*Inputs!$F$153/L11)*L38/1000000 | M69: =Inputs!$F$162*(Inputs!$F$219*M21+(1-Inputs!$F$219)*M27*Inputs!$F$153/M11)*M38/1000000 | N69: =Inputs!$F$162*(Inputs!$F$219*N21+(1-Inputs!$F$219)*N27*Inputs!$F$153/N11)*N38/1000000 | O69: =Inputs!$F$162*(Inputs!$F$219*O21+(1-Inputs!$F$219)*O27*Inputs!$F$153/O11)*O38/1000000 | P69: =Inputs!$F$162*(Inputs!$F$219*P21+(1-Inputs!$F$219)*P27*Inputs!$F$153/P11)*P38/1000000 | Q69: =Inputs!$F$162*(Inputs!$F$219*Q21+(1-Inputs!$F$219)*Q27*Inputs!$F$153/Q11)*Q38/1000000 | ... BN69: =Inputs!$F$162*(Inputs!$F$219*BN21+(1-Inputs!$F$219)*BN27*Inputs!$F$153/BN11)*BN38/1000000
D70: Agency and account fees | E70: USD m | G70: =SUM(J70:BN70) | J70: =Inputs!$F$107*Time!J30/12 | K70: =Inputs!$F$107*Time!K30/12 | L70: =Inputs!$F$107*Time!L30/12 | M70: =Inputs!$F$107*Time!M30/12 | N70: =Inputs!$F$107*Time!N30/12 | O70: =Inputs!$F$107*Time!O30/12 | P70: =Inputs!$F$107*Time!P30/12 | Q70: =Inputs!$F$107*Time!Q30/12 | ... BN70: =Inputs!$F$107*Time!BN30/12
D71: ABDB PRG fee | E71: USD m | G71: =SUM(J71:BN71) | J71: =Inputs!$F$163*Time!J30/12 | K71: =Inputs!$F$163*Time!K30/12 | L71: =Inputs!$F$163*Time!L30/12 | M71: =Inputs!$F$163*Time!M30/12 | N71: =Inputs!$F$163*Time!N30/12 | O71: =Inputs!$F$163*Time!O30/12 | P71: =Inputs!$F$163*Time!P30/12 | Q71: =Inputs!$F$163*Time!Q30/12 | ... BN71: =Inputs!$F$163*Time!BN30/12
D72: Operating costs before pass-through items | E72: USD m | G72: =SUM(J72:BN72) | J72: =J60+J61+J62+J64+J65+J66+J67+J68+J69+J70+J71 | K72: =K60+K61+K62+K64+K65+K66+K67+K68+K69+K70+K71 | L72: =L60+L61+L62+L64+L65+L66+L67+L68+L69+L70+L71 | M72: =M60+M61+M62+M64+M65+M66+M67+M68+M69+M70+M71 | N72: =N60+N61+N62+N64+N65+N66+N67+N68+N69+N70+N71 | O72: =O60+O61+O62+O64+O65+O66+O67+O68+O69+O70+O71 | P72: =P60+P61+P62+P64+P65+P66+P67+P68+P69+P70+P71 | Q72: =Q60+Q61+Q62+Q64+Q65+Q66+Q67+Q68+Q69+Q70+Q71 | ... BN72: =BN60+BN61+BN62+BN64+BN65+BN66+BN67+BN68+BN69+BN70+BN71
D73: Gas purchases | E73: USD m | G73: =SUM(J73:BN73) | J73: =J42*J41/1000000 | K73: =K42*K41/1000000 | L73: =L42*L41/1000000 | M73: =M42*M41/1000000 | N73: =N42*N41/1000000 | O73: =O42*O41/1000000 | P73: =P42*P41/1000000 | Q73: =Q42*Q41/1000000 | ... BN73: =BN42*BN41/1000000
D74: Pass-through costs (gas, GTA, take-or-pay) | E74: USD m | G74: =SUM(J74:BN74) | J74: =J73+J52+J53+J54 | K74: =K73+K52+K53+K54 | L74: =L73+L52+L53+L54 | M74: =M73+M52+M53+M54 | N74: =N73+N52+N53+N54 | O74: =O73+O52+O53+O54 | P74: =P73+P52+P53+P54 | Q74: =Q73+Q52+Q53+Q54 | ... BN74: =BN73+BN52+BN53+BN54
D75: VAT facility interest after the funding period | E75: USD m | G75: =SUM(J75:BN75) | J75: =SUMIFS(Construction!$J$38:$BJ$38,Construction!$J$12:$BJ$12,Time!J20,Construction!$J$8:$BJ$8,">"&Time!$F$14) | K75: =SUMIFS(Construction!$J$38:$BJ$38,Construction!$J$12:$BJ$12,Time!K20,Construction!$J$8:$BJ$8,">"&Time!$F$14) | L75: =SUMIFS(Construction!$J$38:$BJ$38,Construction!$J$12:$BJ$12,Time!L20,Construction!$J$8:$BJ$8,">"&Time!$F$14) | M75: =SUMIFS(Construction!$J$38:$BJ$38,Construction!$J$12:$BJ$12,Time!M20,Construction!$J$8:$BJ$8,">"&Time!$F$14) | N75: =SUMIFS(Construction!$J$38:$BJ$38,Construction!$J$12:$BJ$12,Time!N20,Construction!$J$8:$BJ$8,">"&Time!$F$14) | O75: =SUMIFS(Construction!$J$38:$BJ$38,Construction!$J$12:$BJ$12,Time!O20,Construction!$J$8:$BJ$8,">"&Time!$F$14) | P75: =SUMIFS(Construction!$J$38:$BJ$38,Construction!$J$12:$BJ$12,Time!P20,Construction!$J$8:$BJ$8,">"&Time!$F$14) | Q75: =SUMIFS(Construction!$J$38:$BJ$38,Construction!$J$12:$BJ$12,Time!Q20,Construction!$J$8:$BJ$8,">"&Time!$F$14) | ... BN75: =SUMIFS(Construction!$J$38:$BJ$38,Construction!$J$12:$BJ$12,Time!BN20,Construction!$J$8:$BJ$8,">"&Time!$F$14)
D76: FX conversion losses | E76: USD m | G76: =SUM(J76:BN76) | J76: =Inputs!$F$45*Inputs!J296 | K76: =Inputs!$F$45*Inputs!K296 | L76: =Inputs!$F$45*Inputs!L296 | M76: =Inputs!$F$45*Inputs!M296 | N76: =Inputs!$F$45*Inputs!N296 | O76: =Inputs!$F$45*Inputs!O296 | P76: =Inputs!$F$45*Inputs!P296 | Q76: =Inputs!$F$45*Inputs!Q296 | ... BN76: =Inputs!$F$45*Inputs!BN296
D77: OY whose maintenance month could fall in the period | E77: OY | J77: =INT((Time!J33-Inputs!$F$221)/12)+1 | K77: =INT((Time!K33-Inputs!$F$221)/12)+1 | L77: =INT((Time!L33-Inputs!$F$221)/12)+1 | M77: =INT((Time!M33-Inputs!$F$221)/12)+1 | N77: =INT((Time!N33-Inputs!$F$221)/12)+1 | O77: =INT((Time!O33-Inputs!$F$221)/12)+1 | P77: =INT((Time!P33-Inputs!$F$221)/12)+1 | Q77: =INT((Time!Q33-Inputs!$F$221)/12)+1 | ... BN77: =INT((Time!BN33-Inputs!$F$221)/12)+1
D78: Major maintenance outside LTSA (2018 prices) | E78: USD m | J78: =IF(AND(Time!J30>0,J77>=1,J77<=Inputs!$F$222,Time!J32<(J77-1)*12+Inputs!$F$221,(J77-1)*12+Inputs!$F$221<=Time!J33),IF(MOD(J77,Inputs!$F$223)=0,Inputs!$F$164,IF(MOD(J77,Inputs!$F$224)=0,Inputs!$F$165,0)),0) | K78: =IF(AND(Time!K30>0,K77>=1,K77<=Inputs!$F$222,Time!K32<(K77-1)*12+Inputs!$F$221,(K77-1)*12+Inputs!$F$221<=Time!K33),IF(MOD(K77,Inputs!$F$223)=0,Inputs!$F$164,IF(MOD(K77,Inputs!$F$224)=0,Inputs!$F$165,0)),0) | L78: =IF(AND(Time!L30>0,L77>=1,L77<=Inputs!$F$222,Time!L32<(L77-1)*12+Inputs!$F$221,(L77-1)*12+Inputs!$F$221<=Time!L33),IF(MOD(L77,Inputs!$F$223)=0,Inputs!$F$164,IF(MOD(L77,Inputs!$F$224)=0,Inputs!$F$165,0)),0) | M78: =IF(AND(Time!M30>0,M77>=1,M77<=Inputs!$F$222,Time!M32<(M77-1)*12+Inputs!$F$221,(M77-1)*12+Inputs!$F$221<=Time!M33),IF(MOD(M77,Inputs!$F$223)=0,Inputs!$F$164,IF(MOD(M77,Inputs!$F$224)=0,Inputs!$F$165,0)),0) | N78: =IF(AND(Time!N30>0,N77>=1,N77<=Inputs!$F$222,Time!N32<(N77-1)*12+Inputs!$F$221,(N77-1)*12+Inputs!$F$221<=Time!N33),IF(MOD(N77,Inputs!$F$223)=0,Inputs!$F$164,IF(MOD(N77,Inputs!$F$224)=0,Inputs!$F$165,0)),0) | O78: =IF(AND(Time!O30>0,O77>=1,O77<=Inputs!$F$222,Time!O32<(O77-1)*12+Inputs!$F$221,(O77-1)*12+Inputs!$F$221<=Time!O33),IF(MOD(O77,Inputs!$F$223)=0,Inputs!$F$164,IF(MOD(O77,Inputs!$F$224)=0,Inputs!$F$165,0)),0) | P78: =IF(AND(Time!P30>0,P77>=1,P77<=Inputs!$F$222,Time!P32<(P77-1)*12+Inputs!$F$221,(P77-1)*12+Inputs!$F$221<=Time!P33),IF(MOD(P77,Inputs!$F$223)=0,Inputs!$F$164,IF(MOD(P77,Inputs!$F$224)=0,Inputs!$F$165,0)),0) | Q78: =IF(AND(Time!Q30>0,Q77>=1,Q77<=Inputs!$F$222,Time!Q32<(Q77-1)*12+Inputs!$F$221,(Q77-1)*12+Inputs!$F$221<=Time!Q33),IF(MOD(Q77,Inputs!$F$223)=0,Inputs!$F$164,IF(MOD(Q77,Inputs!$F$224)=0,Inputs!$F$165,0)),0) | ... BN78: =IF(AND(Time!BN30>0,BN77>=1,BN77<=Inputs!$F$222,Time!BN32<(BN77-1)*12+Inputs!$F$221,(BN77-1)*12+Inputs!$F$221<=Time!BN33),IF(MOD(BN77,Inputs!$F$223)=0,Inputs!$F$164,IF(MOD(BN77,Inputs!$F$224)=0,Inputs!$F$165,0)),0)
D79: Major maintenance spend | E79: USD m | G79: =SUM(J79:BN79) | J79: =J78*J21 | K79: =K78*K21 | L79: =L78*L21 | M79: =M78*M21 | N79: =N78*N21 | O79: =O78*O21 | P79: =P78*P21 | Q79: =Q78*Q21 | ... BN79: =BN78*BN21
D80: Months in period from the handback reserve year | E80: months | J80: =MAX(0,MIN(Time!J33,Time!$F$9)-MAX(Time!J32,(Inputs!$F$227-1)*12)) | K80: =MAX(0,MIN(Time!K33,Time!$F$9)-MAX(Time!K32,(Inputs!$F$227-1)*12)) | L80: =MAX(0,MIN(Time!L33,Time!$F$9)-MAX(Time!L32,(Inputs!$F$227-1)*12)) | M80: =MAX(0,MIN(Time!M33,Time!$F$9)-MAX(Time!M32,(Inputs!$F$227-1)*12)) | N80: =MAX(0,MIN(Time!N33,Time!$F$9)-MAX(Time!N32,(Inputs!$F$227-1)*12)) | O80: =MAX(0,MIN(Time!O33,Time!$F$9)-MAX(Time!O32,(Inputs!$F$227-1)*12)) | P80: =MAX(0,MIN(Time!P33,Time!$F$9)-MAX(Time!P32,(Inputs!$F$227-1)*12)) | Q80: =MAX(0,MIN(Time!Q33,Time!$F$9)-MAX(Time!Q32,(Inputs!$F$227-1)*12)) | ... BN80: =MAX(0,MIN(Time!BN33,Time!$F$9)-MAX(Time!BN32,(Inputs!$F$227-1)*12))
D81: Handback reserve contribution required | E81: USD m | G81: =SUM(J81:BN81) | J81: =Inputs!$F$166*J21*J80/12 | K81: =Inputs!$F$166*K21*K80/12 | L81: =Inputs!$F$166*L21*L80/12 | M81: =Inputs!$F$166*M21*M80/12 | N81: =Inputs!$F$166*N21*N80/12 | O81: =Inputs!$F$166*O21*O80/12 | P81: =Inputs!$F$166*P21*P80/12 | Q81: =Inputs!$F$166*Q21*Q80/12 | ... BN81: =Inputs!$F$166*BN21*BN80/12
D82: Handback works at PPA expiry | E82: USD m | G82: =SUM(J82:BN82) | J82: =Time!J37*SUM($J$81:$BN$81) | K82: =Time!K37*SUM($J$81:$BN$81) | L82: =Time!L37*SUM($J$81:$BN$81) | M82: =Time!M37*SUM($J$81:$BN$81) | N82: =Time!N37*SUM($J$81:$BN$81) | O82: =Time!O37*SUM($J$81:$BN$81) | P82: =Time!P37*SUM($J$81:$BN$81) | Q82: =Time!Q37*SUM($J$81:$BN$81) | ... BN82: =Time!BN37*SUM($J$81:$BN$81)
D83: Total operating costs | E83: USD m | G83: =SUM(J83:BN83) | J83: =J72+J74+J75+J76+J79+J82 | K83: =K72+K74+K75+K76+K79+K82 | L83: =L72+L74+L75+L76+L79+L82 | M83: =M72+M74+M75+M76+M79+M82 | N83: =N72+N74+N75+N76+N79+N82 | O83: =O72+O74+O75+O76+O79+O82 | P83: =P72+P74+P75+P76+P79+P82 | Q83: =Q72+Q74+Q75+Q76+Q79+Q82 | ... BN83: =BN72+BN74+BN75+BN76+BN79+BN82
D84: EBITDA | E84: USD m | G84: =SUM(J84:BN84) | J84: =J56-J83+J58 | K84: =K56-K83+K58 | L84: =L56-L83+L58 | M84: =M56-M83+M58 | N84: =N56-N83+N58 | O84: =O56-O83+O58 | P84: =P56-P83+P58 | Q84: =Q56-Q83+Q58 | ... BN84: =BN56-BN83+BN58
B85: Working capital (USD m, period-end balances)
D86: Flag: final operating period or later (working capital unwinds) | E86: flag | J86: =IF(Time!J20>=Time!$F$15,1,0) | K86: =IF(Time!K20>=Time!$F$15,1,0) | L86: =IF(Time!L20>=Time!$F$15,1,0) | M86: =IF(Time!M20>=Time!$F$15,1,0) | N86: =IF(Time!N20>=Time!$F$15,1,0) | O86: =IF(Time!O20>=Time!$F$15,1,0) | P86: =IF(Time!P20>=Time!$F$15,1,0) | Q86: =IF(Time!Q20>=Time!$F$15,1,0) | ... BN86: =IF(Time!BN20>=Time!$F$15,1,0)
D87: Extra receivable days on capacity and VOM (sensitivities) | E87: days | J87: =Inputs!$F$44*Time!J38 | K87: =Inputs!$F$44*Time!K38 | L87: =Inputs!$F$44*Time!L38 | M87: =Inputs!$F$44*Time!M38 | N87: =Inputs!$F$44*Time!N38 | O87: =Inputs!$F$44*Time!O38 | P87: =Inputs!$F$44*Time!P38 | Q87: =Inputs!$F$44*Time!Q38 | ... BN87: =Inputs!$F$44*Time!BN38
D88: Trade receivables (normal terms) | E88: USD m | J88: =(1-J86)*(J56/MAX(Time!J31,1)*Inputs!$F$168+J55/MAX(Time!J31,1)*J87) | K88: =(1-K86)*(K56/MAX(Time!K31,1)*Inputs!$F$168+K55/MAX(Time!K31,1)*K87) | L88: =(1-L86)*(L56/MAX(Time!L31,1)*Inputs!$F$168+L55/MAX(Time!L31,1)*L87) | M88: =(1-M86)*(M56/MAX(Time!M31,1)*Inputs!$F$168+M55/MAX(Time!M31,1)*M87) | N88: =(1-N86)*(N56/MAX(Time!N31,1)*Inputs!$F$168+N55/MAX(Time!N31,1)*N87) | O88: =(1-O86)*(O56/MAX(Time!O31,1)*Inputs!$F$168+O55/MAX(Time!O31,1)*O87) | P88: =(1-P86)*(P56/MAX(Time!P31,1)*Inputs!$F$168+P55/MAX(Time!P31,1)*P87) | Q88: =(1-Q86)*(Q56/MAX(Time!Q31,1)*Inputs!$F$168+Q55/MAX(Time!Q31,1)*Q87) | ... BN88: =(1-BN86)*(BN56/MAX(Time!BN31,1)*Inputs!$F$168+BN55/MAX(Time!BN31,1)*BN87)
D89: SEKA overdue receivables | E89: USD m | J89: =Inputs!$F$45*Inputs!J295 | K89: =Inputs!$F$45*Inputs!K295 | L89: =Inputs!$F$45*Inputs!L295 | M89: =Inputs!$F$45*Inputs!M295 | N89: =Inputs!$F$45*Inputs!N295 | O89: =Inputs!$F$45*Inputs!O295 | P89: =Inputs!$F$45*Inputs!P295 | Q89: =Inputs!$F$45*Inputs!Q295 | ... BN89: =Inputs!$F$45*Inputs!BN295
D90: Gas payables | E90: USD m | J90: =(1-J86)*(J73+J54)/MAX(Time!J31,1)*Inputs!$F$169 | K90: =(1-K86)*(K73+K54)/MAX(Time!K31,1)*Inputs!$F$169 | L90: =(1-L86)*(L73+L54)/MAX(Time!L31,1)*Inputs!$F$169 | M90: =(1-M86)*(M73+M54)/MAX(Time!M31,1)*Inputs!$F$169 | N90: =(1-N86)*(N73+N54)/MAX(Time!N31,1)*Inputs!$F$169 | O90: =(1-O86)*(O73+O54)/MAX(Time!O31,1)*Inputs!$F$169 | P90: =(1-P86)*(P73+P54)/MAX(Time!P31,1)*Inputs!$F$169 | Q90: =(1-Q86)*(Q73+Q54)/MAX(Time!Q31,1)*Inputs!$F$169 | ... BN90: =(1-BN86)*(BN73+BN54)/MAX(Time!BN31,1)*Inputs!$F$169
D91: GTA payables | E91: USD m | J91: =(1-J86)*(J52+J53)/MAX(Time!J31,1)*Inputs!$F$170 | K91: =(1-K86)*(K52+K53)/MAX(Time!K31,1)*Inputs!$F$170 | L91: =(1-L86)*(L52+L53)/MAX(Time!L31,1)*Inputs!$F$170 | M91: =(1-M86)*(M52+M53)/MAX(Time!M31,1)*Inputs!$F$170 | N91: =(1-N86)*(N52+N53)/MAX(Time!N31,1)*Inputs!$F$170 | O91: =(1-O86)*(O52+O53)/MAX(Time!O31,1)*Inputs!$F$170 | P91: =(1-P86)*(P52+P53)/MAX(Time!P31,1)*Inputs!$F$170 | Q91: =(1-Q86)*(Q52+Q53)/MAX(Time!Q31,1)*Inputs!$F$170 | ... BN91: =(1-BN86)*(BN52+BN53)/MAX(Time!BN31,1)*Inputs!$F$170
D92: O&M and LTSA payables | E92: USD m | J92: =(1-J86)*(J60+J61+J62+J64)/MAX(Time!J31,1)*Inputs!$F$171 | K92: =(1-K86)*(K60+K61+K62+K64)/MAX(Time!K31,1)*Inputs!$F$171 | L92: =(1-L86)*(L60+L61+L62+L64)/MAX(Time!L31,1)*Inputs!$F$171 | M92: =(1-M86)*(M60+M61+M62+M64)/MAX(Time!M31,1)*Inputs!$F$171 | N92: =(1-N86)*(N60+N61+N62+N64)/MAX(Time!N31,1)*Inputs!$F$171 | O92: =(1-O86)*(O60+O61+O62+O64)/MAX(Time!O31,1)*Inputs!$F$171 | P92: =(1-P86)*(P60+P61+P62+P64)/MAX(Time!P31,1)*Inputs!$F$171 | Q92: =(1-Q86)*(Q60+Q61+Q62+Q64)/MAX(Time!Q31,1)*Inputs!$F$171 | ... BN92: =(1-BN86)*(BN60+BN61+BN62+BN64)/MAX(Time!BN31,1)*Inputs!$F$171
D93: Other payables | E93: USD m | J93: =(1-J86)*(J65+J66+J67+J68+J69+J70+J71)/MAX(Time!J31,1)*Inputs!$F$172 | K93: =(1-K86)*(K65+K66+K67+K68+K69+K70+K71)/MAX(Time!K31,1)*Inputs!$F$172 | L93: =(1-L86)*(L65+L66+L67+L68+L69+L70+L71)/MAX(Time!L31,1)*Inputs!$F$172 | M93: =(1-M86)*(M65+M66+M67+M68+M69+M70+M71)/MAX(Time!M31,1)*Inputs!$F$172 | N93: =(1-N86)*(N65+N66+N67+N68+N69+N70+N71)/MAX(Time!N31,1)*Inputs!$F$172 | O93: =(1-O86)*(O65+O66+O67+O68+O69+O70+O71)/MAX(Time!O31,1)*Inputs!$F$172 | P93: =(1-P86)*(P65+P66+P67+P68+P69+P70+P71)/MAX(Time!P31,1)*Inputs!$F$172 | Q93: =(1-Q86)*(Q65+Q66+Q67+Q68+Q69+Q70+Q71)/MAX(Time!Q31,1)*Inputs!$F$172 | ... BN93: =(1-BN86)*(BN65+BN66+BN67+BN68+BN69+BN70+BN71)/MAX(Time!BN31,1)*Inputs!$F$172
D94: Deferred SNHK/GCK payables matching SEKA energy-charge arrears | E94: USD m | J94: =Inputs!$F$262*J89 | K94: =Inputs!$F$262*K89 | L94: =Inputs!$F$262*L89 | M94: =Inputs!$F$262*M89 | N94: =Inputs!$F$262*N89 | O94: =Inputs!$F$262*O89 | P94: =Inputs!$F$262*P89 | Q94: =Inputs!$F$262*Q89 | ... BN94: =Inputs!$F$262*BN89
D95: Net working capital (excl. spares inventory) | E95: USD m | J95: =J88+J89-J90-J91-J92-J93-J94 | K95: =K88+K89-K90-K91-K92-K93-K94 | L95: =L88+L89-L90-L91-L92-L93-L94 | M95: =M88+M89-M90-M91-M92-M93-M94 | N95: =N88+N89-N90-N91-N92-N93-N94 | O95: =O88+O89-O90-O91-O92-O93-O94 | P95: =P88+P89-P90-P91-P92-P93-P94 | Q95: =Q88+Q89-Q90-Q91-Q92-Q93-Q94 | ... BN95: =BN88+BN89-BN90-BN91-BN92-BN93-BN94
D96: Increase in net working capital | E96: USD m | G96: =SUM(J96:BN96) | J96: =J95-I95 | K96: =K95-J95 | L96: =L95-K95 | M96: =M95-L95 | N96: =N95-M95 | O96: =O95-N95 | P96: =P95-O95 | Q96: =Q95-P95 | ... BN96: =BN95-BM95
D97: Release of spares inventory at expiry | E97: USD m | G97: =SUM(J97:BN97) | J97: =Time!J37*Inputs!$F$67*Inputs!$F$36 | K97: =Time!K37*Inputs!$F$67*Inputs!$F$36 | L97: =Time!L37*Inputs!$F$67*Inputs!$F$36 | M97: =Time!M37*Inputs!$F$67*Inputs!$F$36 | N97: =Time!N37*Inputs!$F$67*Inputs!$F$36 | O97: =Time!O37*Inputs!$F$67*Inputs!$F$36 | P97: =Time!P37*Inputs!$F$67*Inputs!$F$36 | Q97: =Time!Q37*Inputs!$F$67*Inputs!$F$36 | ... BN97: =Time!BN37*Inputs!$F$67*Inputs!$F$36

Sheet Tax
A1: Case P: Belanou Combined Cycle Power Project, Republic of Kessara
A2: Tax: holiday, deferred depreciation, thin capitalization, minimum turnover tax
A3: Units in column E; constants in column F; row totals in column G; first period in column J. Inputs: blue on yellow. Links from other sheets: green.
D4: Label | E4: Unit | F4: Constant | G4: Total
D5: Period ending | J5: 2018H2 | K5: 2019H1 | L5: 2019H2 | M5: 2020H1 | N5: 2020H2 | O5: 2021H1 | P5: 2021H2 | Q5: 2022H1 | R5: 2022H2 | S5: 2023H1 | T5: 2023H2 | U5: 2024H1 | V5: 2024H2 | W5: 2025H1 | X5: 2025H2 | Y5: 2026H1 | Z5: 2026H2 | AA5: 2027H1 | AB5: 2027H2 | AC5: 2028H1 | AD5: 2028H2 | AE5: 2029H1 | AF5: 2029H2 | AG5: 2030H1 | AH5: 2030H2 | AI5: 2031H1 | AJ5: 2031H2 | AK5: 2032H1 | AL5: 2032H2 | AM5: 2033H1 | AN5: 2033H2 | AO5: 2034H1 | AP5: 2034H2 | AQ5: 2035H1 | AR5: 2035H2 | AS5: 2036H1 | AT5: 2036H2 | AU5: 2037H1 | AV5: 2037H2 | AW5: 2038H1 | AX5: 2038H2 | AY5: 2039H1 | AZ5: 2039H2 | BA5: 2040H1 | BB5: 2040H2 | BC5: 2041H1 | BD5: 2041H2 | BE5: 2042H1 | BF5: 2042H2 | BG5: 2043H1 | BH5: 2043H2 | BI5: 2044H1 | BJ5: 2044H2 | BK5: 2045H1 | BL5: 2045H2 | BM5: 2046H1 | BN5: 2046H2
D7: Holiday months (OY1-OY5) | E7: months | J7: =MAX(0,MIN(Time!J33,Inputs!$F$229*12)-MIN(Time!J32,Inputs!$F$229*12)) | K7: =MAX(0,MIN(Time!K33,Inputs!$F$229*12)-MIN(Time!K32,Inputs!$F$229*12)) | L7: =MAX(0,MIN(Time!L33,Inputs!$F$229*12)-MIN(Time!L32,Inputs!$F$229*12)) | M7: =MAX(0,MIN(Time!M33,Inputs!$F$229*12)-MIN(Time!M32,Inputs!$F$229*12)) | N7: =MAX(0,MIN(Time!N33,Inputs!$F$229*12)-MIN(Time!N32,Inputs!$F$229*12)) | O7: =MAX(0,MIN(Time!O33,Inputs!$F$229*12)-MIN(Time!O32,Inputs!$F$229*12)) | P7: =MAX(0,MIN(Time!P33,Inputs!$F$229*12)-MIN(Time!P32,Inputs!$F$229*12)) | Q7: =MAX(0,MIN(Time!Q33,Inputs!$F$229*12)-MIN(Time!Q32,Inputs!$F$229*12)) | ... BN7: =MAX(0,MIN(Time!BN33,Inputs!$F$229*12)-MIN(Time!BN32,Inputs!$F$229*12))
D8: Reduced-rate months (OY6-OY8) | E8: months | J8: =MAX(0,MIN(Time!J33,Inputs!$F$229*12)-MIN(MAX(Time!J32,Inputs!$F$229*12),Inputs!$F$229*12)) | K8: =MAX(0,MIN(Time!K33,Inputs!$F$229*12)-MIN(MAX(Time!K32,Inputs!$F$229*12),Inputs!$F$229*12)) | L8: =MAX(0,MIN(Time!L33,Inputs!$F$229*12)-MIN(MAX(Time!L32,Inputs!$F$229*12),Inputs!$F$229*12)) | M8: =MAX(0,MIN(Time!M33,Inputs!$F$229*12)-MIN(MAX(Time!M32,Inputs!$F$229*12),Inputs!$F$229*12)) | N8: =MAX(0,MIN(Time!N33,Inputs!$F$229*12)-MIN(MAX(Time!N32,Inputs!$F$229*12),Inputs!$F$229*12)) | O8: =MAX(0,MIN(Time!O33,Inputs!$F$229*12)-MIN(MAX(Time!O32,Inputs!$F$229*12),Inputs!$F$229*12)) | P8: =MAX(0,MIN(Time!P33,Inputs!$F$229*12)-MIN(MAX(Time!P32,Inputs!$F$229*12),Inputs!$F$229*12)) | Q8: =MAX(0,MIN(Time!Q33,Inputs!$F$229*12)-MIN(MAX(Time!Q32,Inputs!$F$229*12),Inputs!$F$229*12)) | ... BN8: =MAX(0,MIN(Time!BN33,Inputs!$F$229*12)-MIN(MAX(Time!BN32,Inputs!$F$229*12),Inputs!$F$229*12))
D9: Full-rate months (OY9+) | E9: months | J9: =Time!J30-J7-J8 | K9: =Time!K30-K7-K8 | L9: =Time!L30-L7-L8 | M9: =Time!M30-M7-M8 | N9: =Time!N30-N7-N8 | O9: =Time!O30-O7-O8 | P9: =Time!P30-P7-P8 | Q9: =Time!Q30-Q7-Q8 | ... BN9: =Time!BN30-BN7-BN8
D10: Tax depreciation (straight line from COD) | E10: USD m | G10: =SUM(J10:BN10) | J10: =Inputs!$F$177*Funding!$F$76/Inputs!$F$178*MAX(0,MIN(Time!J33,Inputs!$F$178)-MIN(Time!J32,Inputs!$F$178))+Inputs!$F$179*Funding!$F$76/Inputs!$F$180*MAX(0,MIN(Time!J33,Inputs!$F$180)-MIN(Time!J32,Inputs!$F$180))+Inputs!$F$181*Funding!$F$76/Inputs!$F$182*MAX(0,MIN(Time!J33,Inputs!$F$182)-MIN(Time!J32,Inputs!$F$182)) | K10: =Inputs!$F$177*Funding!$F$76/Inputs!$F$178*MAX(0,MIN(Time!K33,Inputs!$F$178)-MIN(Time!K32,Inputs!$F$178))+Inputs!$F$179*Funding!$F$76/Inputs!$F$180*MAX(0,MIN(Time!K33,Inputs!$F$180)-MIN(Time!K32,Inputs!$F$180))+Inputs!$F$181*Funding!$F$76/Inputs!$F$182*MAX(0,MIN(Time!K33,Inputs!$F$182)-MIN(Time!K32,Inputs!$F$182)) | L10: =Inputs!$F$177*Funding!$F$76/Inputs!$F$178*MAX(0,MIN(Time!L33,Inputs!$F$178)-MIN(Time!L32,Inputs!$F$178))+Inputs!$F$179*Funding!$F$76/Inputs!$F$180*MAX(0,MIN(Time!L33,Inputs!$F$180)-MIN(Time!L32,Inputs!$F$180))+Inputs!$F$181*Funding!$F$76/Inputs!$F$182*MAX(0,MIN(Time!L33,Inputs!$F$182)-MIN(Time!L32,Inputs!$F$182)) | M10: =Inputs!$F$177*Funding!$F$76/Inputs!$F$178*MAX(0,MIN(Time!M33,Inputs!$F$178)-MIN(Time!M32,Inputs!$F$178))+Inputs!$F$179*Funding!$F$76/Inputs!$F$180*MAX(0,MIN(Time!M33,Inputs!$F$180)-MIN(Time!M32,Inputs!$F$180))+Inputs!$F$181*Funding!$F$76/Inputs!$F$182*MAX(0,MIN(Time!M33,Inputs!$F$182)-MIN(Time!M32,Inputs!$F$182)) | N10: =Inputs!$F$177*Funding!$F$76/Inputs!$F$178*MAX(0,MIN(Time!N33,Inputs!$F$178)-MIN(Time!N32,Inputs!$F$178))+Inputs!$F$179*Funding!$F$76/Inputs!$F$180*MAX(0,MIN(Time!N33,Inputs!$F$180)-MIN(Time!N32,Inputs!$F$180))+Inputs!$F$181*Funding!$F$76/Inputs!$F$182*MAX(0,MIN(Time!N33,Inputs!$F$182)-MIN(Time!N32,Inputs!$F$182)) | O10: =Inputs!$F$177*Funding!$F$76/Inputs!$F$178*MAX(0,MIN(Time!O33,Inputs!$F$178)-MIN(Time!O32,Inputs!$F$178))+Inputs!$F$179*Funding!$F$76/Inputs!$F$180*MAX(0,MIN(Time!O33,Inputs!$F$180)-MIN(Time!O32,Inputs!$F$180))+Inputs!$F$181*Funding!$F$76/Inputs!$F$182*MAX(0,MIN(Time!O33,Inputs!$F$182)-MIN(Time!O32,Inputs!$F$182)) | P10: =Inputs!$F$177*Funding!$F$76/Inputs!$F$178*MAX(0,MIN(Time!P33,Inputs!$F$178)-MIN(Time!P32,Inputs!$F$178))+Inputs!$F$179*Funding!$F$76/Inputs!$F$180*MAX(0,MIN(Time!P33,Inputs!$F$180)-MIN(Time!P32,Inputs!$F$180))+Inputs!$F$181*Funding!$F$76/Inputs!$F$182*MAX(0,MIN(Time!P33,Inputs!$F$182)-MIN(Time!P32,Inputs!$F$182)) | Q10: =Inputs!$F$177*Funding!$F$76/Inputs!$F$178*MAX(0,MIN(Time!Q33,Inputs!$F$178)-MIN(Time!Q32,Inputs!$F$178))+Inputs!$F$179*Funding!$F$76/Inputs!$F$180*MAX(0,MIN(Time!Q33,Inputs!$F$180)-MIN(Time!Q32,Inputs!$F$180))+Inputs!$F$181*Funding!$F$76/Inputs!$F$182*MAX(0,MIN(Time!Q33,Inputs!$F$182)-MIN(Time!Q32,Inputs!$F$182)) | ... BN10: =Inputs!$F$177*Funding!$F$76/Inputs!$F$178*MAX(0,MIN(Time!BN33,Inputs!$F$178)-MIN(Time!BN32,Inputs!$F$178))+Inputs!$F$179*Funding!$F$76/Inputs!$F$180*MAX(0,MIN(Time!BN33,Inputs!$F$180)-MIN(Time!BN32,Inputs!$F$180))+Inputs!$F$181*Funding!$F$76/Inputs!$F$182*MAX(0,MIN(Time!BN33,Inputs!$F$182)-MIN(Time!BN32,Inputs!$F$182))
D11: Depreciation of holiday months (deemed deferred) | E11: USD m | G11: =SUM(J11:BN11) | J11: =(Inputs!$F$177*Funding!$F$76/Inputs!$F$178+Inputs!$F$179*Funding!$F$76/Inputs!$F$180)*J7+Inputs!$F$181*Funding!$F$76/Inputs!$F$182*MAX(0,MIN(Time!J33,MIN(Inputs!$F$182,Inputs!$F$229*12))-MIN(Time!J32,MIN(Inputs!$F$182,Inputs!$F$229*12))) | K11: =(Inputs!$F$177*Funding!$F$76/Inputs!$F$178+Inputs!$F$179*Funding!$F$76/Inputs!$F$180)*K7+Inputs!$F$181*Funding!$F$76/Inputs!$F$182*MAX(0,MIN(Time!K33,MIN(Inputs!$F$182,Inputs!$F$229*12))-MIN(Time!K32,MIN(Inputs!$F$182,Inputs!$F$229*12))) | L11: =(Inputs!$F$177*Funding!$F$76/Inputs!$F$178+Inputs!$F$179*Funding!$F$76/Inputs!$F$180)*L7+Inputs!$F$181*Funding!$F$76/Inputs!$F$182*MAX(0,MIN(Time!L33,MIN(Inputs!$F$182,Inputs!$F$229*12))-MIN(Time!L32,MIN(Inputs!$F$182,Inputs!$F$229*12))) | M11: =(Inputs!$F$177*Funding!$F$76/Inputs!$F$178+Inputs!$F$179*Funding!$F$76/Inputs!$F$180)*M7+Inputs!$F$181*Funding!$F$76/Inputs!$F$182*MAX(0,MIN(Time!M33,MIN(Inputs!$F$182,Inputs!$F$229*12))-MIN(Time!M32,MIN(Inputs!$F$182,Inputs!$F$229*12))) | N11: =(Inputs!$F$177*Funding!$F$76/Inputs!$F$178+Inputs!$F$179*Funding!$F$76/Inputs!$F$180)*N7+Inputs!$F$181*Funding!$F$76/Inputs!$F$182*MAX(0,MIN(Time!N33,MIN(Inputs!$F$182,Inputs!$F$229*12))-MIN(Time!N32,MIN(Inputs!$F$182,Inputs!$F$229*12))) | O11: =(Inputs!$F$177*Funding!$F$76/Inputs!$F$178+Inputs!$F$179*Funding!$F$76/Inputs!$F$180)*O7+Inputs!$F$181*Funding!$F$76/Inputs!$F$182*MAX(0,MIN(Time!O33,MIN(Inputs!$F$182,Inputs!$F$229*12))-MIN(Time!O32,MIN(Inputs!$F$182,Inputs!$F$229*12))) | P11: =(Inputs!$F$177*Funding!$F$76/Inputs!$F$178+Inputs!$F$179*Funding!$F$76/Inputs!$F$180)*P7+Inputs!$F$181*Funding!$F$76/Inputs!$F$182*MAX(0,MIN(Time!P33,MIN(Inputs!$F$182,Inputs!$F$229*12))-MIN(Time!P32,MIN(Inputs!$F$182,Inputs!$F$229*12))) | Q11: =(Inputs!$F$177*Funding!$F$76/Inputs!$F$178+Inputs!$F$179*Funding!$F$76/Inputs!$F$180)*Q7+Inputs!$F$181*Funding!$F$76/Inputs!$F$182*MAX(0,MIN(Time!Q33,MIN(Inputs!$F$182,Inputs!$F$229*12))-MIN(Time!Q32,MIN(Inputs!$F$182,Inputs!$F$229*12))) | ... BN11: =(Inputs!$F$177*Funding!$F$76/Inputs!$F$178+Inputs!$F$179*Funding!$F$76/Inputs!$F$180)*BN7+Inputs!$F$181*Funding!$F$76/Inputs!$F$182*MAX(0,MIN(Time!BN33,MIN(Inputs!$F$182,Inputs!$F$229*12))-MIN(Time!BN32,MIN(Inputs!$F$182,Inputs!$F$229*12)))
D12: Depreciation deducted currently | E12: USD m | G12: =SUM(J12:BN12) | J12: =J10-J11 | K12: =K10-K11 | L12: =L10-L11 | M12: =M10-M11 | N12: =N10-N11 | O12: =O10-O11 | P12: =P10-P11 | Q12: =Q10-Q11 | ... BN12: =BN10-BN11
D13: Shareholder loan interest accrued | E13: USD m | G13: =SUM(J13:BN13) | J13: =IF(Time!J20>=Time!$F$12,Waterfall!J33*Inputs!$F$104/100*Time!J31/Inputs!$F$248,0) | K13: =IF(Time!K20>=Time!$F$12,Waterfall!K33*Inputs!$F$104/100*Time!K31/Inputs!$F$248,0) | L13: =IF(Time!L20>=Time!$F$12,Waterfall!L33*Inputs!$F$104/100*Time!L31/Inputs!$F$248,0) | M13: =IF(Time!M20>=Time!$F$12,Waterfall!M33*Inputs!$F$104/100*Time!M31/Inputs!$F$248,0) | N13: =IF(Time!N20>=Time!$F$12,Waterfall!N33*Inputs!$F$104/100*Time!N31/Inputs!$F$248,0) | O13: =IF(Time!O20>=Time!$F$12,Waterfall!O33*Inputs!$F$104/100*Time!O31/Inputs!$F$248,0) | P13: =IF(Time!P20>=Time!$F$12,Waterfall!P33*Inputs!$F$104/100*Time!P31/Inputs!$F$248,0) | Q13: =IF(Time!Q20>=Time!$F$12,Waterfall!Q33*Inputs!$F$104/100*Time!Q31/Inputs!$F$248,0) | ... BN13: =IF(Time!BN20>=Time!$F$12,Waterfall!BN33*Inputs!$F$104/100*Time!BN31/Inputs!$F$248,0)
D14: Thin cap: deductible share = min(1, 3 x equity / SHL) | E14: fraction | J14: =IF(Waterfall!J33>0,MIN(1,Inputs!$F$183*(Waterfall!$F$32+MAX(0,Waterfall!I43))/Waterfall!J33),1) | K14: =IF(Waterfall!K33>0,MIN(1,Inputs!$F$183*(Waterfall!$F$32+MAX(0,Waterfall!J43))/Waterfall!K33),1) | L14: =IF(Waterfall!L33>0,MIN(1,Inputs!$F$183*(Waterfall!$F$32+MAX(0,Waterfall!K43))/Waterfall!L33),1) | M14: =IF(Waterfall!M33>0,MIN(1,Inputs!$F$183*(Waterfall!$F$32+MAX(0,Waterfall!L43))/Waterfall!M33),1) | N14: =IF(Waterfall!N33>0,MIN(1,Inputs!$F$183*(Waterfall!$F$32+MAX(0,Waterfall!M43))/Waterfall!N33),1) | O14: =IF(Waterfall!O33>0,MIN(1,Inputs!$F$183*(Waterfall!$F$32+MAX(0,Waterfall!N43))/Waterfall!O33),1) | P14: =IF(Waterfall!P33>0,MIN(1,Inputs!$F$183*(Waterfall!$F$32+MAX(0,Waterfall!O43))/Waterfall!P33),1) | Q14: =IF(Waterfall!Q33>0,MIN(1,Inputs!$F$183*(Waterfall!$F$32+MAX(0,Waterfall!P43))/Waterfall!Q33),1) | ... BN14: =IF(Waterfall!BN33>0,MIN(1,Inputs!$F$183*(Waterfall!$F$32+MAX(0,Waterfall!BM43))/Waterfall!BN33),1)
D15: Shareholder loan interest deductible | E15: USD m | G15: =SUM(J15:BN15) | J15: =J13*J14 | K15: =K13*K14 | L15: =L13*L14 | M15: =M13*M14 | N15: =N13*N14 | O15: =O13*O14 | P15: =P13*P14 | Q15: =Q13*Q14 | ... BN15: =BN13*BN14
D16: Senior financing costs deductible (all grandfathered) | E16: USD m | G16: =SUM(J16:BN16) | J16: =Debt!J112+Debt!J110+Debt!J104-Debt!J103 | K16: =Debt!K112+Debt!K110+Debt!K104-Debt!K103 | L16: =Debt!L112+Debt!L110+Debt!L104-Debt!L103 | M16: =Debt!M112+Debt!M110+Debt!M104-Debt!M103 | N16: =Debt!N112+Debt!N110+Debt!N104-Debt!N103 | O16: =Debt!O112+Debt!O110+Debt!O104-Debt!O103 | P16: =Debt!P112+Debt!P110+Debt!P104-Debt!P103 | Q16: =Debt!Q112+Debt!Q110+Debt!Q104-Debt!Q103 | ... BN16: =Debt!BN112+Debt!BN110+Debt!BN104-Debt!BN103
D17: Non-holiday share of operating months | E17: fraction | J17: =IF(Time!J30>0,(Time!J30-J7)/Time!J30,0) | K17: =IF(Time!K30>0,(Time!K30-K7)/Time!K30,0) | L17: =IF(Time!L30>0,(Time!L30-L7)/Time!L30,0) | M17: =IF(Time!M30>0,(Time!M30-M7)/Time!M30,0) | N17: =IF(Time!N30>0,(Time!N30-N7)/Time!N30,0) | O17: =IF(Time!O30>0,(Time!O30-O7)/Time!O30,0) | P17: =IF(Time!P30>0,(Time!P30-P7)/Time!P30,0) | Q17: =IF(Time!Q30>0,(Time!Q30-Q7)/Time!Q30,0) | ... BN17: =IF(Time!BN30>0,(Time!BN30-BN7)/Time!BN30,0)
D18: Taxable income before losses and deferred depreciation | E18: USD m | G18: =SUM(J18:BN18) | J18: =(Operations!J84-J16-J15)*J17-J12 | K18: =(Operations!K84-K16-K15)*K17-K12 | L18: =(Operations!L84-L16-L15)*L17-L12 | M18: =(Operations!M84-M16-M15)*M17-M12 | N18: =(Operations!N84-N16-N15)*N17-N12 | O18: =(Operations!O84-O16-O15)*O17-O12 | P18: =(Operations!P84-P16-P15)*P17-P12 | Q18: =(Operations!Q84-Q16-Q15)*Q17-Q12 | ... BN18: =(Operations!BN84-BN16-BN15)*BN17-BN12
D19: Tax losses used | E19: USD m | G19: =SUM(J19:BN19) | J19: =MIN(I22,MAX(0,J18)) | K19: =MIN(J22,MAX(0,K18)) | L19: =MIN(K22,MAX(0,L18)) | M19: =MIN(L22,MAX(0,M18)) | N19: =MIN(M22,MAX(0,N18)) | O19: =MIN(N22,MAX(0,O18)) | P19: =MIN(O22,MAX(0,P18)) | Q19: =MIN(P22,MAX(0,Q18)) | ... BN19: =MIN(BM22,MAX(0,BN18))
D20: Deferred depreciation used | E20: USD m | G20: =SUM(J20:BN20) | J20: =MIN(I21,MAX(0,J18-J19)) | K20: =MIN(J21,MAX(0,K18-K19)) | L20: =MIN(K21,MAX(0,L18-L19)) | M20: =MIN(L21,MAX(0,M18-M19)) | N20: =MIN(M21,MAX(0,N18-N19)) | O20: =MIN(N21,MAX(0,O18-O19)) | P20: =MIN(O21,MAX(0,P18-P19)) | Q20: =MIN(P21,MAX(0,Q18-Q19)) | ... BN20: =MIN(BM21,MAX(0,BN18-BN19))
D21: Deferred depreciation pool, closing | E21: USD m | J21: =I21+0-J20 | K21: =J21+0-K20 | L21: =K21+0-L20 | M21: =L21+0-M20 | N21: =M21+0-N20 | O21: =N21+0-O20 | P21: =O21+0-P20 | Q21: =P21+0-Q20 | ... BN21: =BM21+0-BN20
D22: Tax losses carried forward, closing | E22: USD m | J22: =I22-J19+MAX(0,-J18) | K22: =J22-K19+MAX(0,-K18) | L22: =K22-L19+MAX(0,-L18) | M22: =L22-M19+MAX(0,-M18) | N22: =M22-N19+MAX(0,-N18) | O22: =N22-O19+MAX(0,-O18) | P22: =O22-P19+MAX(0,-P18) | Q22: =P22-Q19+MAX(0,-Q18) | ... BN22: =BM22-BN19+MAX(0,-BN18)
D23: Taxable income | E23: USD m | G23: =SUM(J23:BN23) | J23: =MAX(0,J18-J19-J20) | K23: =MAX(0,K18-K19-K20) | L23: =MAX(0,L18-L19-L20) | M23: =MAX(0,M18-M19-M20) | N23: =MAX(0,N18-N19-N20) | O23: =MAX(0,O18-O19-O20) | P23: =MAX(0,P18-P19-P20) | Q23: =MAX(0,Q18-Q19-Q20) | ... BN23: =MAX(0,BN18-BN19-BN20)
D24: Applicable CIT rate (month-weighted) | E24: % | J24: =IF(J8+J9>0,(J8*Inputs!$F$175+J9*Inputs!$F$174)/(J8+J9)/100,0) | K24: =IF(K8+K9>0,(K8*Inputs!$F$175+K9*Inputs!$F$174)/(K8+K9)/100,0) | L24: =IF(L8+L9>0,(L8*Inputs!$F$175+L9*Inputs!$F$174)/(L8+L9)/100,0) | M24: =IF(M8+M9>0,(M8*Inputs!$F$175+M9*Inputs!$F$174)/(M8+M9)/100,0) | N24: =IF(N8+N9>0,(N8*Inputs!$F$175+N9*Inputs!$F$174)/(N8+N9)/100,0) | O24: =IF(O8+O9>0,(O8*Inputs!$F$175+O9*Inputs!$F$174)/(O8+O9)/100,0) | P24: =IF(P8+P9>0,(P8*Inputs!$F$175+P9*Inputs!$F$174)/(P8+P9)/100,0) | Q24: =IF(Q8+Q9>0,(Q8*Inputs!$F$175+Q9*Inputs!$F$174)/(Q8+Q9)/100,0) | ... BN24: =IF(BN8+BN9>0,(BN8*Inputs!$F$175+BN9*Inputs!$F$174)/(BN8+BN9)/100,0)
D25: Corporate income tax | E25: USD m | G25: =SUM(J25:BN25) | J25: =J23*J24 | K25: =K23*K24 | L25: =L23*L24 | M25: =M23*M24 | N25: =N23*N24 | O25: =O23*O24 | P25: =P23*P24 | Q25: =Q23*Q24 | ... BN25: =BN23*BN24
D26: Minimum turnover tax | E26: USD m | G26: =SUM(J26:BN26) | J26: =IF(Time!J30>0,Inputs!$F$176/100*Operations!J55*(J8+J9)/Time!J30,0) | K26: =IF(Time!K30>0,Inputs!$F$176/100*Operations!K55*(K8+K9)/Time!K30,0) | L26: =IF(Time!L30>0,Inputs!$F$176/100*Operations!L55*(L8+L9)/Time!L30,0) | M26: =IF(Time!M30>0,Inputs!$F$176/100*Operations!M55*(M8+M9)/Time!M30,0) | N26: =IF(Time!N30>0,Inputs!$F$176/100*Operations!N55*(N8+N9)/Time!N30,0) | O26: =IF(Time!O30>0,Inputs!$F$176/100*Operations!O55*(O8+O9)/Time!O30,0) | P26: =IF(Time!P30>0,Inputs!$F$176/100*Operations!P55*(P8+P9)/Time!P30,0) | Q26: =IF(Time!Q30>0,Inputs!$F$176/100*Operations!Q55*(Q8+Q9)/Time!Q30,0) | ... BN26: =IF(Time!BN30>0,Inputs!$F$176/100*Operations!BN55*(BN8+BN9)/Time!BN30,0)
D27: Tax paid = max(CIT, MTT) | E27: USD m | G27: =SUM(J27:BN27) | J27: =MAX(J25,J26) | K27: =MAX(K25,K26) | L27: =MAX(L25,L26) | M27: =MAX(M25,M26) | N27: =MAX(N25,N26) | O27: =MAX(O25,O26) | P27: =MAX(P25,P26) | Q27: =MAX(Q25,Q26) | ... BN27: =MAX(BN25,BN26)
D28: Thin-cap disallowance | E28: USD m | G28: =SUM(J28:BN28) | J28: =J13-J15 | K28: =K13-K15 | L28: =L13-L15 | M28: =M13-M15 | N28: =N13-N15 | O28: =O13-O15 | P28: =P13-P15 | Q28: =Q13-Q15 | ... BN28: =BN13-BN15

Sheet Funding
A1: Case P: Belanou Combined Cycle Power Project, Republic of Kessara
A2: Funding: closed-form gross-up, drawdowns by tranche, IDC, fees, equity
A3: Units in column E; constants in column F; row totals in column G; first period in column J. Inputs: blue on yellow. Links from other sheets: green.
D4: Label | E4: Unit | F4: Constant | G4: Total
D5: Month | J5: 2018-08 | K5: 2018-09 | L5: 2018-10 | M5: 2018-11 | N5: 2018-12 | O5: 2019-01 | P5: 2019-02 | Q5: 2019-03 | R5: 2019-04 | S5: 2019-05 | T5: 2019-06 | U5: 2019-07 | V5: 2019-08 | W5: 2019-09 | X5: 2019-10 | Y5: 2019-11 | Z5: 2019-12 | AA5: 2020-01 | AB5: 2020-02 | AC5: 2020-03 | AD5: 2020-04 | AE5: 2020-05 | AF5: 2020-06 | AG5: 2020-07 | AH5: 2020-08 | AI5: 2020-09 | AJ5: 2020-10 | AK5: 2020-11 | AL5: 2020-12 | AM5: 2021-01 | AN5: 2021-02 | AO5: 2021-03 | AP5: 2021-04 | AQ5: 2021-05 | AR5: 2021-06 | AS5: 2021-07 | AT5: 2021-08 | AU5: 2021-09 | AV5: 2021-10 | AW5: 2021-11 | AX5: 2021-12 | AY5: 2022-01 | AZ5: 2022-02 | BA5: 2022-03 | BB5: 2022-04 | BC5: 2022-05 | BD5: 2022-06 | BE5: 2022-07 | BF5: 2022-08 | BG5: 2022-09 | BH5: 2022-10 | BI5: 2022-11 | BJ5: 2022-12
B7: Constants
D8: Contract debt share of funding g = D/(D+E) | E8: fraction | F8: =Inputs!$F$113/(Inputs!$F$113+Inputs!$F$114)
D9: Gearing used in the closed-form gross-up | E9: fraction | F9: =IF(Inputs!$F$51<>1,Funding!$F$8,Inputs!$F$105)
D10: ECA premium gross-up denominator 1 - prem x share x g | E10: factor | F10: =1-Inputs!$F$94/100*Inputs!$F$75*Funding!$F$9
D11: First installment share of remaining profile | E11: fraction | F11: =INDEX(Debt!$J$17:$BN$17,1,Time!$F$13)/INDEX(Debt!$J$18:$BN$18,1,Time!$F$13)
D12: DSRA coefficient per USD of E balance | E12: factor | F12: =$F$11+(INDEX(Operations!$J$9:$BN$9,1,Time!$F$13)+Inputs!$F$79)/100*0.5*1
D13: DSRA coefficient per USD of A balance | E13: factor | F13: =$F$11+(INDEX(Operations!$J$9:$BN$9,1,Time!$F$13)+Inputs!$F$80)/100*0.5*1
D14: DSRA coefficient per USD of B balance | E14: factor | F14: =$F$11+(INDEX(Operations!$J$9:$BN$9,1,Time!$F$13)+Inputs!$F$81)/100*0.5*1
D15: DSRA coefficient per USD of C balance | E15: factor | F15: =$F$11+(INDEX(Operations!$J$9:$BN$9,1,Time!$F$13)+INDEX(Debt!$J$8:$BN$8,1,Time!$F$13))/100*0.5*(1/(1-Inputs!$F$93/100))+(Inputs!$F$95/100*Inputs!$F$96/100)*INDEX(Time!$J$25:$BN$25,1,Time!$F$13)/Inputs!$F$248
D16: DSRA coefficient per USD of standby balance | E16: factor | F16: =$F$11+INDEX(Debt!$J$14:$BN$14,1,Time!$F$13)
D17: DSRA constant (swap net payment) | E17: USD m | F17: =-1*INDEX(Inputs!$J$301:$BN$301,1,Time!$F$13)*(Inputs!$F$97/100*INDEX(Time!$J$24:$BN$24,1,Time!$F$13)-INDEX(Operations!$J$9:$BN$9,1,Time!$F$13)/100*INDEX(Time!$J$25:$BN$25,1,Time!$F$13)/Inputs!$F$247)
B18: Closed-form gross-up: debt balance = alpha + beta x T (FC-type cases)
D19: Blended loan rate per month (rho) | E19: factor | J19: =Inputs!$F$75*(Construction!J17+Inputs!$F$79)/100*(1/12)*1+Inputs!$F$76*(Construction!J17+Inputs!$F$80)/100*(1/12)*1+Inputs!$F$77*(Construction!J17+Inputs!$F$81)/100*(1/12)*1+Inputs!$F$78*(Construction!J17+Inputs!$F$82)/100*(1/12)*(1/(1-Inputs!$F$93/100))+Inputs!$F$78*(Inputs!$F$95/100*Inputs!$F$96/100)*Construction!J11/Inputs!$F$248 | K19: =Inputs!$F$75*(Construction!K17+Inputs!$F$79)/100*(1/12)*1+Inputs!$F$76*(Construction!K17+Inputs!$F$80)/100*(1/12)*1+Inputs!$F$77*(Construction!K17+Inputs!$F$81)/100*(1/12)*1+Inputs!$F$78*(Construction!K17+Inputs!$F$82)/100*(1/12)*(1/(1-Inputs!$F$93/100))+Inputs!$F$78*(Inputs!$F$95/100*Inputs!$F$96/100)*Construction!K11/Inputs!$F$248 | L19: =Inputs!$F$75*(Construction!L17+Inputs!$F$79)/100*(1/12)*1+Inputs!$F$76*(Construction!L17+Inputs!$F$80)/100*(1/12)*1+Inputs!$F$77*(Construction!L17+Inputs!$F$81)/100*(1/12)*1+Inputs!$F$78*(Construction!L17+Inputs!$F$82)/100*(1/12)*(1/(1-Inputs!$F$93/100))+Inputs!$F$78*(Inputs!$F$95/100*Inputs!$F$96/100)*Construction!L11/Inputs!$F$248 | M19: =Inputs!$F$75*(Construction!M17+Inputs!$F$79)/100*(1/12)*1+Inputs!$F$76*(Construction!M17+Inputs!$F$80)/100*(1/12)*1+Inputs!$F$77*(Construction!M17+Inputs!$F$81)/100*(1/12)*1+Inputs!$F$78*(Construction!M17+Inputs!$F$82)/100*(1/12)*(1/(1-Inputs!$F$93/100))+Inputs!$F$78*(Inputs!$F$95/100*Inputs!$F$96/100)*Construction!M11/Inputs!$F$248 | N19: =Inputs!$F$75*(Construction!N17+Inputs!$F$79)/100*(1/12)*1+Inputs!$F$76*(Construction!N17+Inputs!$F$80)/100*(1/12)*1+Inputs!$F$77*(Construction!N17+Inputs!$F$81)/100*(1/12)*1+Inputs!$F$78*(Construction!N17+Inputs!$F$82)/100*(1/12)*(1/(1-Inputs!$F$93/100))+Inputs!$F$78*(Inputs!$F$95/100*Inputs!$F$96/100)*Construction!N11/Inputs!$F$248 | O19: =Inputs!$F$75*(Construction!O17+Inputs!$F$79)/100*(1/12)*1+Inputs!$F$76*(Construction!O17+Inputs!$F$80)/100*(1/12)*1+Inputs!$F$77*(Construction!O17+Inputs!$F$81)/100*(1/12)*1+Inputs!$F$78*(Construction!O17+Inputs!$F$82)/100*(1/12)*(1/(1-Inputs!$F$93/100))+Inputs!$F$78*(Inputs!$F$95/100*Inputs!$F$96/100)*Construction!O11/Inputs!$F$248 | P19: =Inputs!$F$75*(Construction!P17+Inputs!$F$79)/100*(1/12)*1+Inputs!$F$76*(Construction!P17+Inputs!$F$80)/100*(1/12)*1+Inputs!$F$77*(Construction!P17+Inputs!$F$81)/100*(1/12)*1+Inputs!$F$78*(Construction!P17+Inputs!$F$82)/100*(1/12)*(1/(1-Inputs!$F$93/100))+Inputs!$F$78*(Inputs!$F$95/100*Inputs!$F$96/100)*Construction!P11/Inputs!$F$248 | Q19: =Inputs!$F$75*(Construction!Q17+Inputs!$F$79)/100*(1/12)*1+Inputs!$F$76*(Construction!Q17+Inputs!$F$80)/100*(1/12)*1+Inputs!$F$77*(Construction!Q17+Inputs!$F$81)/100*(1/12)*1+Inputs!$F$78*(Construction!Q17+Inputs!$F$82)/100*(1/12)*(1/(1-Inputs!$F$93/100))+Inputs!$F$78*(Inputs!$F$95/100*Inputs!$F$96/100)*Construction!Q11/Inputs!$F$248 | ... BJ19: =Inputs!$F$75*(Construction!BJ17+Inputs!$F$79)/100*(1/12)*1+Inputs!$F$76*(Construction!BJ17+Inputs!$F$80)/100*(1/12)*1+Inputs!$F$77*(Construction!BJ17+Inputs!$F$81)/100*(1/12)*1+Inputs!$F$78*(Construction!BJ17+Inputs!$F$82)/100*(1/12)*(1/(1-Inputs!$F$93/100))+Inputs!$F$78*(Inputs!$F$95/100*Inputs!$F$96/100)*Construction!BJ11/Inputs!$F$248
D20: Blended commitment fee per month (kappa) | E20: factor | J20: =Inputs!$F$75*Inputs!$F$85/100*Construction!J11/Inputs!$F$247+Inputs!$F$76*Inputs!$F$86/100*Construction!J11/Inputs!$F$247+Inputs!$F$77*Inputs!$F$87/100*Construction!J11/Inputs!$F$247+Inputs!$F$78*(Inputs!$F$88/100*Inputs!$F$82)/100*Construction!J11/Inputs!$F$247 | K20: =Inputs!$F$75*Inputs!$F$85/100*Construction!K11/Inputs!$F$247+Inputs!$F$76*Inputs!$F$86/100*Construction!K11/Inputs!$F$247+Inputs!$F$77*Inputs!$F$87/100*Construction!K11/Inputs!$F$247+Inputs!$F$78*(Inputs!$F$88/100*Inputs!$F$82)/100*Construction!K11/Inputs!$F$247 | L20: =Inputs!$F$75*Inputs!$F$85/100*Construction!L11/Inputs!$F$247+Inputs!$F$76*Inputs!$F$86/100*Construction!L11/Inputs!$F$247+Inputs!$F$77*Inputs!$F$87/100*Construction!L11/Inputs!$F$247+Inputs!$F$78*(Inputs!$F$88/100*Inputs!$F$82)/100*Construction!L11/Inputs!$F$247 | M20: =Inputs!$F$75*Inputs!$F$85/100*Construction!M11/Inputs!$F$247+Inputs!$F$76*Inputs!$F$86/100*Construction!M11/Inputs!$F$247+Inputs!$F$77*Inputs!$F$87/100*Construction!M11/Inputs!$F$247+Inputs!$F$78*(Inputs!$F$88/100*Inputs!$F$82)/100*Construction!M11/Inputs!$F$247 | N20: =Inputs!$F$75*Inputs!$F$85/100*Construction!N11/Inputs!$F$247+Inputs!$F$76*Inputs!$F$86/100*Construction!N11/Inputs!$F$247+Inputs!$F$77*Inputs!$F$87/100*Construction!N11/Inputs!$F$247+Inputs!$F$78*(Inputs!$F$88/100*Inputs!$F$82)/100*Construction!N11/Inputs!$F$247 | O20: =Inputs!$F$75*Inputs!$F$85/100*Construction!O11/Inputs!$F$247+Inputs!$F$76*Inputs!$F$86/100*Construction!O11/Inputs!$F$247+Inputs!$F$77*Inputs!$F$87/100*Construction!O11/Inputs!$F$247+Inputs!$F$78*(Inputs!$F$88/100*Inputs!$F$82)/100*Construction!O11/Inputs!$F$247 | P20: =Inputs!$F$75*Inputs!$F$85/100*Construction!P11/Inputs!$F$247+Inputs!$F$76*Inputs!$F$86/100*Construction!P11/Inputs!$F$247+Inputs!$F$77*Inputs!$F$87/100*Construction!P11/Inputs!$F$247+Inputs!$F$78*(Inputs!$F$88/100*Inputs!$F$82)/100*Construction!P11/Inputs!$F$247 | Q20: =Inputs!$F$75*Inputs!$F$85/100*Construction!Q11/Inputs!$F$247+Inputs!$F$76*Inputs!$F$86/100*Construction!Q11/Inputs!$F$247+Inputs!$F$77*Inputs!$F$87/100*Construction!Q11/Inputs!$F$247+Inputs!$F$78*(Inputs!$F$88/100*Inputs!$F$82)/100*Construction!Q11/Inputs!$F$247 | ... BJ20: =Inputs!$F$75*Inputs!$F$85/100*Construction!BJ11/Inputs!$F$247+Inputs!$F$76*Inputs!$F$86/100*Construction!BJ11/Inputs!$F$247+Inputs!$F$77*Inputs!$F$87/100*Construction!BJ11/Inputs!$F$247+Inputs!$F$78*(Inputs!$F$88/100*Inputs!$F$82)/100*Construction!BJ11/Inputs!$F$247
D21: Costs independent of facility size | E21: USD m | J21: =Construction!J14*(Construction!J32+Construction!J38+Inputs!$F$107/12+-1*Inputs!J309*(Inputs!$F$97/100/12-Construction!J17/100*Construction!J11/Inputs!$F$247)+Inputs!$F$99*Inputs!$F$100/100*Construction!J11/Inputs!$F$247+Construction!J15*$F$17) | K21: =Construction!K14*(Construction!K32+Construction!K38+Inputs!$F$107/12+-1*Inputs!K309*(Inputs!$F$97/100/12-Construction!K17/100*Construction!K11/Inputs!$F$247)+Inputs!$F$99*Inputs!$F$100/100*Construction!K11/Inputs!$F$247+Construction!K15*$F$17) | L21: =Construction!L14*(Construction!L32+Construction!L38+Inputs!$F$107/12+-1*Inputs!L309*(Inputs!$F$97/100/12-Construction!L17/100*Construction!L11/Inputs!$F$247)+Inputs!$F$99*Inputs!$F$100/100*Construction!L11/Inputs!$F$247+Construction!L15*$F$17) | M21: =Construction!M14*(Construction!M32+Construction!M38+Inputs!$F$107/12+-1*Inputs!M309*(Inputs!$F$97/100/12-Construction!M17/100*Construction!M11/Inputs!$F$247)+Inputs!$F$99*Inputs!$F$100/100*Construction!M11/Inputs!$F$247+Construction!M15*$F$17) | N21: =Construction!N14*(Construction!N32+Construction!N38+Inputs!$F$107/12+-1*Inputs!N309*(Inputs!$F$97/100/12-Construction!N17/100*Construction!N11/Inputs!$F$247)+Inputs!$F$99*Inputs!$F$100/100*Construction!N11/Inputs!$F$247+Construction!N15*$F$17) | O21: =Construction!O14*(Construction!O32+Construction!O38+Inputs!$F$107/12+-1*Inputs!O309*(Inputs!$F$97/100/12-Construction!O17/100*Construction!O11/Inputs!$F$247)+Inputs!$F$99*Inputs!$F$100/100*Construction!O11/Inputs!$F$247+Construction!O15*$F$17) | P21: =Construction!P14*(Construction!P32+Construction!P38+Inputs!$F$107/12+-1*Inputs!P309*(Inputs!$F$97/100/12-Construction!P17/100*Construction!P11/Inputs!$F$247)+Inputs!$F$99*Inputs!$F$100/100*Construction!P11/Inputs!$F$247+Construction!P15*$F$17) | Q21: =Construction!Q14*(Construction!Q32+Construction!Q38+Inputs!$F$107/12+-1*Inputs!Q309*(Inputs!$F$97/100/12-Construction!Q17/100*Construction!Q11/Inputs!$F$247)+Inputs!$F$99*Inputs!$F$100/100*Construction!Q11/Inputs!$F$247+Construction!Q15*$F$17) | ... BJ21: =Construction!BJ14*(Construction!BJ32+Construction!BJ38+Inputs!$F$107/12+-1*Inputs!BJ309*(Inputs!$F$97/100/12-Construction!BJ17/100*Construction!BJ11/Inputs!$F$247)+Inputs!$F$99*Inputs!$F$100/100*Construction!BJ11/Inputs!$F$247+Construction!BJ15*$F$17)
D22: Balance, constant part (alpha) | E22: USD m | J22: =I22+Construction!J14*$F$9/$F$10*(J21+(J19-J20)*I22) | K22: =J22+Construction!K14*$F$9/$F$10*(K21+(K19-K20)*J22) | L22: =K22+Construction!L14*$F$9/$F$10*(L21+(L19-L20)*K22) | M22: =L22+Construction!M14*$F$9/$F$10*(M21+(M19-M20)*L22) | N22: =M22+Construction!N14*$F$9/$F$10*(N21+(N19-N20)*M22) | O22: =N22+Construction!O14*$F$9/$F$10*(O21+(O19-O20)*N22) | P22: =O22+Construction!P14*$F$9/$F$10*(P21+(P19-P20)*O22) | Q22: =P22+Construction!Q14*$F$9/$F$10*(Q21+(Q19-Q20)*P22) | ... BJ22: =BI22+Construction!BJ14*$F$9/$F$10*(BJ21+(BJ19-BJ20)*BI22)
D23: Balance per USD of total funding (beta) | E23: factor | J23: =I23+Construction!J14*$F$9/$F$10*(J19*I23+J20*($F$9-I23)+IF(Construction!J8=1,$F$9*(Inputs!$F$75*Inputs!$F$89/100+Inputs!$F$76*Inputs!$F$90/100+Inputs!$F$77*Inputs!$F$91/100+Inputs!$F$78*Inputs!$F$92/100),0)+Construction!J15*$F$9*(Inputs!$F$75*$F$12+Inputs!$F$76*$F$13+Inputs!$F$77*$F$14+Inputs!$F$78*$F$15)) | K23: =J23+Construction!K14*$F$9/$F$10*(K19*J23+K20*($F$9-J23)+IF(Construction!K8=1,$F$9*(Inputs!$F$75*Inputs!$F$89/100+Inputs!$F$76*Inputs!$F$90/100+Inputs!$F$77*Inputs!$F$91/100+Inputs!$F$78*Inputs!$F$92/100),0)+Construction!K15*$F$9*(Inputs!$F$75*$F$12+Inputs!$F$76*$F$13+Inputs!$F$77*$F$14+Inputs!$F$78*$F$15)) | L23: =K23+Construction!L14*$F$9/$F$10*(L19*K23+L20*($F$9-K23)+IF(Construction!L8=1,$F$9*(Inputs!$F$75*Inputs!$F$89/100+Inputs!$F$76*Inputs!$F$90/100+Inputs!$F$77*Inputs!$F$91/100+Inputs!$F$78*Inputs!$F$92/100),0)+Construction!L15*$F$9*(Inputs!$F$75*$F$12+Inputs!$F$76*$F$13+Inputs!$F$77*$F$14+Inputs!$F$78*$F$15)) | M23: =L23+Construction!M14*$F$9/$F$10*(M19*L23+M20*($F$9-L23)+IF(Construction!M8=1,$F$9*(Inputs!$F$75*Inputs!$F$89/100+Inputs!$F$76*Inputs!$F$90/100+Inputs!$F$77*Inputs!$F$91/100+Inputs!$F$78*Inputs!$F$92/100),0)+Construction!M15*$F$9*(Inputs!$F$75*$F$12+Inputs!$F$76*$F$13+Inputs!$F$77*$F$14+Inputs!$F$78*$F$15)) | N23: =M23+Construction!N14*$F$9/$F$10*(N19*M23+N20*($F$9-M23)+IF(Construction!N8=1,$F$9*(Inputs!$F$75*Inputs!$F$89/100+Inputs!$F$76*Inputs!$F$90/100+Inputs!$F$77*Inputs!$F$91/100+Inputs!$F$78*Inputs!$F$92/100),0)+Construction!N15*$F$9*(Inputs!$F$75*$F$12+Inputs!$F$76*$F$13+Inputs!$F$77*$F$14+Inputs!$F$78*$F$15)) | O23: =N23+Construction!O14*$F$9/$F$10*(O19*N23+O20*($F$9-N23)+IF(Construction!O8=1,$F$9*(Inputs!$F$75*Inputs!$F$89/100+Inputs!$F$76*Inputs!$F$90/100+Inputs!$F$77*Inputs!$F$91/100+Inputs!$F$78*Inputs!$F$92/100),0)+Construction!O15*$F$9*(Inputs!$F$75*$F$12+Inputs!$F$76*$F$13+Inputs!$F$77*$F$14+Inputs!$F$78*$F$15)) | P23: =O23+Construction!P14*$F$9/$F$10*(P19*O23+P20*($F$9-O23)+IF(Construction!P8=1,$F$9*(Inputs!$F$75*Inputs!$F$89/100+Inputs!$F$76*Inputs!$F$90/100+Inputs!$F$77*Inputs!$F$91/100+Inputs!$F$78*Inputs!$F$92/100),0)+Construction!P15*$F$9*(Inputs!$F$75*$F$12+Inputs!$F$76*$F$13+Inputs!$F$77*$F$14+Inputs!$F$78*$F$15)) | Q23: =P23+Construction!Q14*$F$9/$F$10*(Q19*P23+Q20*($F$9-P23)+IF(Construction!Q8=1,$F$9*(Inputs!$F$75*Inputs!$F$89/100+Inputs!$F$76*Inputs!$F$90/100+Inputs!$F$77*Inputs!$F$91/100+Inputs!$F$78*Inputs!$F$92/100),0)+Construction!Q15*$F$9*(Inputs!$F$75*$F$12+Inputs!$F$76*$F$13+Inputs!$F$77*$F$14+Inputs!$F$78*$F$15)) | ... BJ23: =BI23+Construction!BJ14*$F$9/$F$10*(BJ19*BI23+BJ20*($F$9-BI23)+IF(Construction!BJ8=1,$F$9*(Inputs!$F$75*Inputs!$F$89/100+Inputs!$F$76*Inputs!$F$90/100+Inputs!$F$77*Inputs!$F$91/100+Inputs!$F$78*Inputs!$F$92/100),0)+Construction!BJ15*$F$9*(Inputs!$F$75*$F$12+Inputs!$F$76*$F$13+Inputs!$F$77*$F$14+Inputs!$F$78*$F$15))
D24: Total funding requirement at this gearing, closed form T = alpha/(g - beta) | E24: USD m | F24: =INDEX(Funding!$J$22:$BJ$22,1,Time!$F$14)/(Funding!$F$9-INDEX(Funding!$J$23:$BJ$23,1,Time!$F$14))
D25: Senior debt (committed tranches) | E25: USD m | F25: =IF(Inputs!$F$51<>1,Funding!$F$8*Funding!$F$24,Inputs!$F$113)
D26: Debt share of monthly funding | E26: fraction | F26: =(Inputs!$F$113-SUM($J$44:$BJ$44))/(Inputs!$F$113+Inputs!$F$114-SUM($J$44:$BJ$44))
B27: Monthly funding schedule (USD m)
D28: ECA-covered tranche: opening balance | E28: USD m | J28: =I61 | K28: =J61 | L28: =K61 | M28: =L61 | N28: =M61 | O28: =N61 | P28: =O61 | Q28: =P61 | ... BJ28: =BI61
D29: ABDB A-loan: opening balance | E29: USD m | J29: =I62 | K29: =J62 | L29: =K62 | M29: =L62 | N29: =M62 | O29: =N62 | P29: =O62 | Q29: =P62 | ... BJ29: =BI62
D30: ABDB B-loan: opening balance | E30: USD m | J30: =I63 | K30: =J63 | L30: =K63 | M30: =L63 | N30: =M63 | O30: =N63 | P30: =O63 | Q30: =P63 | ... BJ30: =BI63
D31: Commercial tranche: opening balance | E31: USD m | J31: =I64 | K31: =J64 | L31: =K64 | M31: =L64 | N31: =M64 | O31: =N64 | P31: =O64 | Q31: =P64 | ... BJ31: =BI64
D32: Standby facility: opening balance | E32: USD m | J32: =I65 | K32: =J65 | L32: =K65 | M32: =L65 | N32: =M65 | O32: =N65 | P32: =O65 | Q32: =P65 | ... BJ32: =BI65
D33: ECA-covered tranche: interest | E33: USD m | G33: =SUM(J33:BJ33) | J33: =Construction!J14*J28*(Construction!J17+Inputs!$F$79)/100*(1/12)*1 | K33: =Construction!K14*K28*(Construction!K17+Inputs!$F$79)/100*(1/12)*1 | L33: =Construction!L14*L28*(Construction!L17+Inputs!$F$79)/100*(1/12)*1 | M33: =Construction!M14*M28*(Construction!M17+Inputs!$F$79)/100*(1/12)*1 | N33: =Construction!N14*N28*(Construction!N17+Inputs!$F$79)/100*(1/12)*1 | O33: =Construction!O14*O28*(Construction!O17+Inputs!$F$79)/100*(1/12)*1 | P33: =Construction!P14*P28*(Construction!P17+Inputs!$F$79)/100*(1/12)*1 | Q33: =Construction!Q14*Q28*(Construction!Q17+Inputs!$F$79)/100*(1/12)*1 | ... BJ33: =Construction!BJ14*BJ28*(Construction!BJ17+Inputs!$F$79)/100*(1/12)*1
D34: ABDB A-loan: interest | E34: USD m | G34: =SUM(J34:BJ34) | J34: =Construction!J14*J29*(Construction!J17+Inputs!$F$80)/100*(1/12)*1 | K34: =Construction!K14*K29*(Construction!K17+Inputs!$F$80)/100*(1/12)*1 | L34: =Construction!L14*L29*(Construction!L17+Inputs!$F$80)/100*(1/12)*1 | M34: =Construction!M14*M29*(Construction!M17+Inputs!$F$80)/100*(1/12)*1 | N34: =Construction!N14*N29*(Construction!N17+Inputs!$F$80)/100*(1/12)*1 | O34: =Construction!O14*O29*(Construction!O17+Inputs!$F$80)/100*(1/12)*1 | P34: =Construction!P14*P29*(Construction!P17+Inputs!$F$80)/100*(1/12)*1 | Q34: =Construction!Q14*Q29*(Construction!Q17+Inputs!$F$80)/100*(1/12)*1 | ... BJ34: =Construction!BJ14*BJ29*(Construction!BJ17+Inputs!$F$80)/100*(1/12)*1
D35: ABDB B-loan: interest | E35: USD m | G35: =SUM(J35:BJ35) | J35: =Construction!J14*J30*(Construction!J17+Inputs!$F$81)/100*(1/12)*1 | K35: =Construction!K14*K30*(Construction!K17+Inputs!$F$81)/100*(1/12)*1 | L35: =Construction!L14*L30*(Construction!L17+Inputs!$F$81)/100*(1/12)*1 | M35: =Construction!M14*M30*(Construction!M17+Inputs!$F$81)/100*(1/12)*1 | N35: =Construction!N14*N30*(Construction!N17+Inputs!$F$81)/100*(1/12)*1 | O35: =Construction!O14*O30*(Construction!O17+Inputs!$F$81)/100*(1/12)*1 | P35: =Construction!P14*P30*(Construction!P17+Inputs!$F$81)/100*(1/12)*1 | Q35: =Construction!Q14*Q30*(Construction!Q17+Inputs!$F$81)/100*(1/12)*1 | ... BJ35: =Construction!BJ14*BJ30*(Construction!BJ17+Inputs!$F$81)/100*(1/12)*1
D36: Commercial tranche: interest | E36: USD m | G36: =SUM(J36:BJ36) | J36: =Construction!J14*J31*(Construction!J17+Inputs!$F$82)/100*(1/12)*(1/(1-Inputs!$F$93/100)) | K36: =Construction!K14*K31*(Construction!K17+Inputs!$F$82)/100*(1/12)*(1/(1-Inputs!$F$93/100)) | L36: =Construction!L14*L31*(Construction!L17+Inputs!$F$82)/100*(1/12)*(1/(1-Inputs!$F$93/100)) | M36: =Construction!M14*M31*(Construction!M17+Inputs!$F$82)/100*(1/12)*(1/(1-Inputs!$F$93/100)) | N36: =Construction!N14*N31*(Construction!N17+Inputs!$F$82)/100*(1/12)*(1/(1-Inputs!$F$93/100)) | O36: =Construction!O14*O31*(Construction!O17+Inputs!$F$82)/100*(1/12)*(1/(1-Inputs!$F$93/100)) | P36: =Construction!P14*P31*(Construction!P17+Inputs!$F$82)/100*(1/12)*(1/(1-Inputs!$F$93/100)) | Q36: =Construction!Q14*Q31*(Construction!Q17+Inputs!$F$82)/100*(1/12)*(1/(1-Inputs!$F$93/100)) | ... BJ36: =Construction!BJ14*BJ31*(Construction!BJ17+Inputs!$F$82)/100*(1/12)*(1/(1-Inputs!$F$93/100))
D37: Standby facility: interest | E37: USD m | G37: =SUM(J37:BJ37) | J37: =Construction!J14*J32*(Inputs!$F$102*(Construction!J17+Inputs!$F$82+Inputs!$F$101)/(1-Inputs!$F$93/100)+(1-Inputs!$F$102)*(Construction!J17+Inputs!$F$80+Inputs!$F$101))/100*Construction!J11/Inputs!$F$247 | K37: =Construction!K14*K32*(Inputs!$F$102*(Construction!K17+Inputs!$F$82+Inputs!$F$101)/(1-Inputs!$F$93/100)+(1-Inputs!$F$102)*(Construction!K17+Inputs!$F$80+Inputs!$F$101))/100*Construction!K11/Inputs!$F$247 | L37: =Construction!L14*L32*(Inputs!$F$102*(Construction!L17+Inputs!$F$82+Inputs!$F$101)/(1-Inputs!$F$93/100)+(1-Inputs!$F$102)*(Construction!L17+Inputs!$F$80+Inputs!$F$101))/100*Construction!L11/Inputs!$F$247 | M37: =Construction!M14*M32*(Inputs!$F$102*(Construction!M17+Inputs!$F$82+Inputs!$F$101)/(1-Inputs!$F$93/100)+(1-Inputs!$F$102)*(Construction!M17+Inputs!$F$80+Inputs!$F$101))/100*Construction!M11/Inputs!$F$247 | N37: =Construction!N14*N32*(Inputs!$F$102*(Construction!N17+Inputs!$F$82+Inputs!$F$101)/(1-Inputs!$F$93/100)+(1-Inputs!$F$102)*(Construction!N17+Inputs!$F$80+Inputs!$F$101))/100*Construction!N11/Inputs!$F$247 | O37: =Construction!O14*O32*(Inputs!$F$102*(Construction!O17+Inputs!$F$82+Inputs!$F$101)/(1-Inputs!$F$93/100)+(1-Inputs!$F$102)*(Construction!O17+Inputs!$F$80+Inputs!$F$101))/100*Construction!O11/Inputs!$F$247 | P37: =Construction!P14*P32*(Inputs!$F$102*(Construction!P17+Inputs!$F$82+Inputs!$F$101)/(1-Inputs!$F$93/100)+(1-Inputs!$F$102)*(Construction!P17+Inputs!$F$80+Inputs!$F$101))/100*Construction!P11/Inputs!$F$247 | Q37: =Construction!Q14*Q32*(Inputs!$F$102*(Construction!Q17+Inputs!$F$82+Inputs!$F$101)/(1-Inputs!$F$93/100)+(1-Inputs!$F$102)*(Construction!Q17+Inputs!$F$80+Inputs!$F$101))/100*Construction!Q11/Inputs!$F$247 | ... BJ37: =Construction!BJ14*BJ32*(Inputs!$F$102*(Construction!BJ17+Inputs!$F$82+Inputs!$F$101)/(1-Inputs!$F$93/100)+(1-Inputs!$F$102)*(Construction!BJ17+Inputs!$F$80+Inputs!$F$101))/100*Construction!BJ11/Inputs!$F$247
D38: PRI premium on commercial tranche | E38: USD m | G38: =SUM(J38:BJ38) | J38: =Construction!J14*(Inputs!$F$95/100*Inputs!$F$96/100)*J31*Construction!J11/Inputs!$F$248 | K38: =Construction!K14*(Inputs!$F$95/100*Inputs!$F$96/100)*K31*Construction!K11/Inputs!$F$248 | L38: =Construction!L14*(Inputs!$F$95/100*Inputs!$F$96/100)*L31*Construction!L11/Inputs!$F$248 | M38: =Construction!M14*(Inputs!$F$95/100*Inputs!$F$96/100)*M31*Construction!M11/Inputs!$F$248 | N38: =Construction!N14*(Inputs!$F$95/100*Inputs!$F$96/100)*N31*Construction!N11/Inputs!$F$248 | O38: =Construction!O14*(Inputs!$F$95/100*Inputs!$F$96/100)*O31*Construction!O11/Inputs!$F$248 | P38: =Construction!P14*(Inputs!$F$95/100*Inputs!$F$96/100)*P31*Construction!P11/Inputs!$F$248 | Q38: =Construction!Q14*(Inputs!$F$95/100*Inputs!$F$96/100)*Q31*Construction!Q11/Inputs!$F$248 | ... BJ38: =Construction!BJ14*(Inputs!$F$95/100*Inputs!$F$96/100)*BJ31*Construction!BJ11/Inputs!$F$248
D39: Swap net payment | E39: USD m | G39: =SUM(J39:BJ39) | J39: =-1*Construction!J14*Inputs!J309*(Inputs!$F$97/100/12-Construction!J17/100*Construction!J11/Inputs!$F$247) | K39: =-1*Construction!K14*Inputs!K309*(Inputs!$F$97/100/12-Construction!K17/100*Construction!K11/Inputs!$F$247) | L39: =-1*Construction!L14*Inputs!L309*(Inputs!$F$97/100/12-Construction!L17/100*Construction!L11/Inputs!$F$247) | M39: =-1*Construction!M14*Inputs!M309*(Inputs!$F$97/100/12-Construction!M17/100*Construction!M11/Inputs!$F$247) | N39: =-1*Construction!N14*Inputs!N309*(Inputs!$F$97/100/12-Construction!N17/100*Construction!N11/Inputs!$F$247) | O39: =-1*Construction!O14*Inputs!O309*(Inputs!$F$97/100/12-Construction!O17/100*Construction!O11/Inputs!$F$247) | P39: =-1*Construction!P14*Inputs!P309*(Inputs!$F$97/100/12-Construction!P17/100*Construction!P11/Inputs!$F$247) | Q39: =-1*Construction!Q14*Inputs!Q309*(Inputs!$F$97/100/12-Construction!Q17/100*Construction!Q11/Inputs!$F$247) | ... BJ39: =-1*Construction!BJ14*Inputs!BJ309*(Inputs!$F$97/100/12-Construction!BJ17/100*Construction!BJ11/Inputs!$F$247)
D40: Commitment fees, senior tranches | E40: USD m | G40: =SUM(J40:BJ40) | J40: =Construction!J14*((Inputs!$F$75*$F$25-J28)*Inputs!$F$85/100+(Inputs!$F$76*$F$25-J29)*Inputs!$F$86/100+(Inputs!$F$77*$F$25-J30)*Inputs!$F$87/100+(Inputs!$F$78*$F$25-J31)*(Inputs!$F$88/100*Inputs!$F$82)/100)*Construction!J11/Inputs!$F$247 | K40: =Construction!K14*((Inputs!$F$75*$F$25-K28)*Inputs!$F$85/100+(Inputs!$F$76*$F$25-K29)*Inputs!$F$86/100+(Inputs!$F$77*$F$25-K30)*Inputs!$F$87/100+(Inputs!$F$78*$F$25-K31)*(Inputs!$F$88/100*Inputs!$F$82)/100)*Construction!K11/Inputs!$F$247 | L40: =Construction!L14*((Inputs!$F$75*$F$25-L28)*Inputs!$F$85/100+(Inputs!$F$76*$F$25-L29)*Inputs!$F$86/100+(Inputs!$F$77*$F$25-L30)*Inputs!$F$87/100+(Inputs!$F$78*$F$25-L31)*(Inputs!$F$88/100*Inputs!$F$82)/100)*Construction!L11/Inputs!$F$247 | M40: =Construction!M14*((Inputs!$F$75*$F$25-M28)*Inputs!$F$85/100+(Inputs!$F$76*$F$25-M29)*Inputs!$F$86/100+(Inputs!$F$77*$F$25-M30)*Inputs!$F$87/100+(Inputs!$F$78*$F$25-M31)*(Inputs!$F$88/100*Inputs!$F$82)/100)*Construction!M11/Inputs!$F$247 | N40: =Construction!N14*((Inputs!$F$75*$F$25-N28)*Inputs!$F$85/100+(Inputs!$F$76*$F$25-N29)*Inputs!$F$86/100+(Inputs!$F$77*$F$25-N30)*Inputs!$F$87/100+(Inputs!$F$78*$F$25-N31)*(Inputs!$F$88/100*Inputs!$F$82)/100)*Construction!N11/Inputs!$F$247 | O40: =Construction!O14*((Inputs!$F$75*$F$25-O28)*Inputs!$F$85/100+(Inputs!$F$76*$F$25-O29)*Inputs!$F$86/100+(Inputs!$F$77*$F$25-O30)*Inputs!$F$87/100+(Inputs!$F$78*$F$25-O31)*(Inputs!$F$88/100*Inputs!$F$82)/100)*Construction!O11/Inputs!$F$247 | P40: =Construction!P14*((Inputs!$F$75*$F$25-P28)*Inputs!$F$85/100+(Inputs!$F$76*$F$25-P29)*Inputs!$F$86/100+(Inputs!$F$77*$F$25-P30)*Inputs!$F$87/100+(Inputs!$F$78*$F$25-P31)*(Inputs!$F$88/100*Inputs!$F$82)/100)*Construction!P11/Inputs!$F$247 | Q40: =Construction!Q14*((Inputs!$F$75*$F$25-Q28)*Inputs!$F$85/100+(Inputs!$F$76*$F$25-Q29)*Inputs!$F$86/100+(Inputs!$F$77*$F$25-Q30)*Inputs!$F$87/100+(Inputs!$F$78*$F$25-Q31)*(Inputs!$F$88/100*Inputs!$F$82)/100)*Construction!Q11/Inputs!$F$247 | ... BJ40: =Construction!BJ14*((Inputs!$F$75*$F$25-BJ28)*Inputs!$F$85/100+(Inputs!$F$76*$F$25-BJ29)*Inputs!$F$86/100+(Inputs!$F$77*$F$25-BJ30)*Inputs!$F$87/100+(Inputs!$F$78*$F$25-BJ31)*(Inputs!$F$88/100*Inputs!$F$82)/100)*Construction!BJ11/Inputs!$F$247
D41: Commitment fee, standby facility | E41: USD m | G41: =SUM(J41:BJ41) | J41: =Construction!J14*(Inputs!$F$99-J32)*Inputs!$F$100/100*Construction!J11/Inputs!$F$247 | K41: =Construction!K14*(Inputs!$F$99-K32)*Inputs!$F$100/100*Construction!K11/Inputs!$F$247 | L41: =Construction!L14*(Inputs!$F$99-L32)*Inputs!$F$100/100*Construction!L11/Inputs!$F$247 | M41: =Construction!M14*(Inputs!$F$99-M32)*Inputs!$F$100/100*Construction!M11/Inputs!$F$247 | N41: =Construction!N14*(Inputs!$F$99-N32)*Inputs!$F$100/100*Construction!N11/Inputs!$F$247 | O41: =Construction!O14*(Inputs!$F$99-O32)*Inputs!$F$100/100*Construction!O11/Inputs!$F$247 | P41: =Construction!P14*(Inputs!$F$99-P32)*Inputs!$F$100/100*Construction!P11/Inputs!$F$247 | Q41: =Construction!Q14*(Inputs!$F$99-Q32)*Inputs!$F$100/100*Construction!Q11/Inputs!$F$247 | ... BJ41: =Construction!BJ14*(Inputs!$F$99-BJ32)*Inputs!$F$100/100*Construction!BJ11/Inputs!$F$247
D42: Upfront and arrangement fees | E42: USD m | G42: =SUM(J42:BJ42) | J42: =IF(Construction!J8=1,Inputs!$F$75*$F$25*Inputs!$F$89/100+Inputs!$F$76*$F$25*Inputs!$F$90/100+Inputs!$F$77*$F$25*Inputs!$F$91/100+Inputs!$F$78*$F$25*Inputs!$F$92/100,0) | K42: =IF(Construction!K8=1,Inputs!$F$75*$F$25*Inputs!$F$89/100+Inputs!$F$76*$F$25*Inputs!$F$90/100+Inputs!$F$77*$F$25*Inputs!$F$91/100+Inputs!$F$78*$F$25*Inputs!$F$92/100,0) | L42: =IF(Construction!L8=1,Inputs!$F$75*$F$25*Inputs!$F$89/100+Inputs!$F$76*$F$25*Inputs!$F$90/100+Inputs!$F$77*$F$25*Inputs!$F$91/100+Inputs!$F$78*$F$25*Inputs!$F$92/100,0) | M42: =IF(Construction!M8=1,Inputs!$F$75*$F$25*Inputs!$F$89/100+Inputs!$F$76*$F$25*Inputs!$F$90/100+Inputs!$F$77*$F$25*Inputs!$F$91/100+Inputs!$F$78*$F$25*Inputs!$F$92/100,0) | N42: =IF(Construction!N8=1,Inputs!$F$75*$F$25*Inputs!$F$89/100+Inputs!$F$76*$F$25*Inputs!$F$90/100+Inputs!$F$77*$F$25*Inputs!$F$91/100+Inputs!$F$78*$F$25*Inputs!$F$92/100,0) | O42: =IF(Construction!O8=1,Inputs!$F$75*$F$25*Inputs!$F$89/100+Inputs!$F$76*$F$25*Inputs!$F$90/100+Inputs!$F$77*$F$25*Inputs!$F$91/100+Inputs!$F$78*$F$25*Inputs!$F$92/100,0) | P42: =IF(Construction!P8=1,Inputs!$F$75*$F$25*Inputs!$F$89/100+Inputs!$F$76*$F$25*Inputs!$F$90/100+Inputs!$F$77*$F$25*Inputs!$F$91/100+Inputs!$F$78*$F$25*Inputs!$F$92/100,0) | Q42: =IF(Construction!Q8=1,Inputs!$F$75*$F$25*Inputs!$F$89/100+Inputs!$F$76*$F$25*Inputs!$F$90/100+Inputs!$F$77*$F$25*Inputs!$F$91/100+Inputs!$F$78*$F$25*Inputs!$F$92/100,0) | ... BJ42: =IF(Construction!BJ8=1,Inputs!$F$75*$F$25*Inputs!$F$89/100+Inputs!$F$76*$F$25*Inputs!$F$90/100+Inputs!$F$77*$F$25*Inputs!$F$91/100+Inputs!$F$78*$F$25*Inputs!$F$92/100,0)
D43: Agency fees during construction | E43: USD m | G43: =SUM(J43:BJ43) | J43: =Construction!J14*Inputs!$F$107/12 | K43: =Construction!K14*Inputs!$F$107/12 | L43: =Construction!L14*Inputs!$F$107/12 | M43: =Construction!M14*Inputs!$F$107/12 | N43: =Construction!N14*Inputs!$F$107/12 | O43: =Construction!O14*Inputs!$F$107/12 | P43: =Construction!P14*Inputs!$F$107/12 | Q43: =Construction!Q14*Inputs!$F$107/12 | ... BJ43: =Construction!BJ14*Inputs!$F$107/12
D44: DSRA initial funding (COD month) | E44: USD m | G44: =SUM(J44:BJ44) | J44: =Construction!J15*IF(Inputs!$F$34=1,$F$12*Inputs!$F$75*$F$25+$F$13*Inputs!$F$76*$F$25+$F$14*Inputs!$F$77*$F$25+$F$15*Inputs!$F$78*$F$25+$F$17,$F$12*J28+$F$13*J29+$F$14*J30+$F$15*J31+$F$16*J32+$F$17) | K44: =Construction!K15*IF(Inputs!$F$34=1,$F$12*Inputs!$F$75*$F$25+$F$13*Inputs!$F$76*$F$25+$F$14*Inputs!$F$77*$F$25+$F$15*Inputs!$F$78*$F$25+$F$17,$F$12*K28+$F$13*K29+$F$14*K30+$F$15*K31+$F$16*K32+$F$17) | L44: =Construction!L15*IF(Inputs!$F$34=1,$F$12*Inputs!$F$75*$F$25+$F$13*Inputs!$F$76*$F$25+$F$14*Inputs!$F$77*$F$25+$F$15*Inputs!$F$78*$F$25+$F$17,$F$12*L28+$F$13*L29+$F$14*L30+$F$15*L31+$F$16*L32+$F$17) | M44: =Construction!M15*IF(Inputs!$F$34=1,$F$12*Inputs!$F$75*$F$25+$F$13*Inputs!$F$76*$F$25+$F$14*Inputs!$F$77*$F$25+$F$15*Inputs!$F$78*$F$25+$F$17,$F$12*M28+$F$13*M29+$F$14*M30+$F$15*M31+$F$16*M32+$F$17) | N44: =Construction!N15*IF(Inputs!$F$34=1,$F$12*Inputs!$F$75*$F$25+$F$13*Inputs!$F$76*$F$25+$F$14*Inputs!$F$77*$F$25+$F$15*Inputs!$F$78*$F$25+$F$17,$F$12*N28+$F$13*N29+$F$14*N30+$F$15*N31+$F$16*N32+$F$17) | O44: =Construction!O15*IF(Inputs!$F$34=1,$F$12*Inputs!$F$75*$F$25+$F$13*Inputs!$F$76*$F$25+$F$14*Inputs!$F$77*$F$25+$F$15*Inputs!$F$78*$F$25+$F$17,$F$12*O28+$F$13*O29+$F$14*O30+$F$15*O31+$F$16*O32+$F$17) | P44: =Construction!P15*IF(Inputs!$F$34=1,$F$12*Inputs!$F$75*$F$25+$F$13*Inputs!$F$76*$F$25+$F$14*Inputs!$F$77*$F$25+$F$15*Inputs!$F$78*$F$25+$F$17,$F$12*P28+$F$13*P29+$F$14*P30+$F$15*P31+$F$16*P32+$F$17) | Q44: =Construction!Q15*IF(Inputs!$F$34=1,$F$12*Inputs!$F$75*$F$25+$F$13*Inputs!$F$76*$F$25+$F$14*Inputs!$F$77*$F$25+$F$15*Inputs!$F$78*$F$25+$F$17,$F$12*Q28+$F$13*Q29+$F$14*Q30+$F$15*Q31+$F$16*Q32+$F$17) | ... BJ44: =Construction!BJ15*IF(Inputs!$F$34=1,$F$12*Inputs!$F$75*$F$25+$F$13*Inputs!$F$76*$F$25+$F$14*Inputs!$F$77*$F$25+$F$15*Inputs!$F$78*$F$25+$F$17,$F$12*BJ28+$F$13*BJ29+$F$14*BJ30+$F$15*BJ31+$F$16*BJ32+$F$17)
D45: Uses before ECA premium | E45: USD m | J45: =Construction!J14*(Construction!J32+Construction!J38)+J33+J34+J35+J36+J37+J38+J39+J40+J41+J42+J43+J44 | K45: =Construction!K14*(Construction!K32+Construction!K38)+K33+K34+K35+K36+K37+K38+K39+K40+K41+K42+K43+K44 | L45: =Construction!L14*(Construction!L32+Construction!L38)+L33+L34+L35+L36+L37+L38+L39+L40+L41+L42+L43+L44 | M45: =Construction!M14*(Construction!M32+Construction!M38)+M33+M34+M35+M36+M37+M38+M39+M40+M41+M42+M43+M44 | N45: =Construction!N14*(Construction!N32+Construction!N38)+N33+N34+N35+N36+N37+N38+N39+N40+N41+N42+N43+N44 | O45: =Construction!O14*(Construction!O32+Construction!O38)+O33+O34+O35+O36+O37+O38+O39+O40+O41+O42+O43+O44 | P45: =Construction!P14*(Construction!P32+Construction!P38)+P33+P34+P35+P36+P37+P38+P39+P40+P41+P42+P43+P44 | Q45: =Construction!Q14*(Construction!Q32+Construction!Q38)+Q33+Q34+Q35+Q36+Q37+Q38+Q39+Q40+Q41+Q42+Q43+Q44 | ... BJ45: =Construction!BJ14*(Construction!BJ32+Construction!BJ38)+BJ33+BJ34+BJ35+BJ36+BJ37+BJ38+BJ39+BJ40+BJ41+BJ42+BJ43+BJ44
D46: Headroom on committed senior tranches | E46: USD m | J46: =$F$25-J28-J29-J30-J31 | K46: =$F$25-K28-K29-K30-K31 | L46: =$F$25-L28-L29-L30-L31 | M46: =$F$25-M28-M29-M30-M31 | N46: =$F$25-N28-N29-N30-N31 | O46: =$F$25-O28-O29-O30-O31 | P46: =$F$25-P28-P29-P30-P31 | Q46: =$F$25-Q28-Q29-Q30-Q31 | ... BJ46: =$F$25-BJ28-BJ29-BJ30-BJ31
D47: Senior tranche drawdown (pro rata) | E47: USD m | G47: =SUM(J47:BJ47) | J47: =MIN(($F$26*(J45-J44)+J44)/(1-Inputs!$F$94/100*Inputs!$F$75*$F$26),J46) | K47: =MIN(($F$26*(K45-K44)+K44)/(1-Inputs!$F$94/100*Inputs!$F$75*$F$26),K46) | L47: =MIN(($F$26*(L45-L44)+L44)/(1-Inputs!$F$94/100*Inputs!$F$75*$F$26),L46) | M47: =MIN(($F$26*(M45-M44)+M44)/(1-Inputs!$F$94/100*Inputs!$F$75*$F$26),M46) | N47: =MIN(($F$26*(N45-N44)+N44)/(1-Inputs!$F$94/100*Inputs!$F$75*$F$26),N46) | O47: =MIN(($F$26*(O45-O44)+O44)/(1-Inputs!$F$94/100*Inputs!$F$75*$F$26),O46) | P47: =MIN(($F$26*(P45-P44)+P44)/(1-Inputs!$F$94/100*Inputs!$F$75*$F$26),P46) | Q47: =MIN(($F$26*(Q45-Q44)+Q44)/(1-Inputs!$F$94/100*Inputs!$F$75*$F$26),Q46) | ... BJ47: =MIN(($F$26*(BJ45-BJ44)+BJ44)/(1-Inputs!$F$94/100*Inputs!$F$75*$F$26),BJ46)
D48: ECA premium (financed) | E48: USD m | G48: =SUM(J48:BJ48) | J48: =Inputs!$F$94/100*Inputs!$F$75*J47 | K48: =Inputs!$F$94/100*Inputs!$F$75*K47 | L48: =Inputs!$F$94/100*Inputs!$F$75*L47 | M48: =Inputs!$F$94/100*Inputs!$F$75*M47 | N48: =Inputs!$F$94/100*Inputs!$F$75*N47 | O48: =Inputs!$F$94/100*Inputs!$F$75*O47 | P48: =Inputs!$F$94/100*Inputs!$F$75*P47 | Q48: =Inputs!$F$94/100*Inputs!$F$75*Q47 | ... BJ48: =Inputs!$F$94/100*Inputs!$F$75*BJ47
D49: Total uses of funds | E49: USD m | G49: =SUM(J49:BJ49) | J49: =J45+J48 | K49: =K45+K48 | L49: =L45+L48 | M49: =M45+M48 | N49: =N45+N48 | O49: =O45+O48 | P49: =P45+P48 | Q49: =Q45+Q48 | ... BJ49: =BJ45+BJ48
D50: Funded pro rata from committed debt and equity | E50: USD m | G50: =SUM(J50:BJ50) | J50: =J49 | K50: =K49 | L50: =L49 | M50: =M49 | N50: =N49 | O50: =O49 | P50: =P49 | Q50: =Q49 | ... BJ50: =BJ49
D51: Remaining uses after committed facilities | E51: USD m | J51: =J49-J50 | K51: =K49-K50 | L51: =L49-L50 | M51: =M49-M50 | N51: =N49-N50 | O51: =O49-O50 | P51: =P49-P50 | Q51: =Q49-Q50 | ... BJ51: =BJ49-BJ50
D52: Delay LDs and DSU proceeds received | E52: USD m | G52: =SUM(J52:BJ52) | J52: =IF(AND(Inputs!$F$34<>1,Construction!J8=Inputs!$F$245),Inputs!$F$265+Inputs!$F$266,0) | K52: =IF(AND(Inputs!$F$34<>1,Construction!K8=Inputs!$F$245),Inputs!$F$265+Inputs!$F$266,0) | L52: =IF(AND(Inputs!$F$34<>1,Construction!L8=Inputs!$F$245),Inputs!$F$265+Inputs!$F$266,0) | M52: =IF(AND(Inputs!$F$34<>1,Construction!M8=Inputs!$F$245),Inputs!$F$265+Inputs!$F$266,0) | N52: =IF(AND(Inputs!$F$34<>1,Construction!N8=Inputs!$F$245),Inputs!$F$265+Inputs!$F$266,0) | O52: =IF(AND(Inputs!$F$34<>1,Construction!O8=Inputs!$F$245),Inputs!$F$265+Inputs!$F$266,0) | P52: =IF(AND(Inputs!$F$34<>1,Construction!P8=Inputs!$F$245),Inputs!$F$265+Inputs!$F$266,0) | Q52: =IF(AND(Inputs!$F$34<>1,Construction!Q8=Inputs!$F$245),Inputs!$F$265+Inputs!$F$266,0) | ... BJ52: =IF(AND(Inputs!$F$34<>1,Construction!BJ8=Inputs!$F$245),Inputs!$F$265+Inputs!$F$266,0)
D53: LD and DSU proceeds applied | E53: USD m | G53: =SUM(J53:BJ53) | J53: =MIN(J51,I54+J52) | K53: =MIN(K51,J54+K52) | L53: =MIN(L51,K54+L52) | M53: =MIN(M51,L54+M52) | N53: =MIN(N51,M54+N52) | O53: =MIN(O51,N54+O52) | P53: =MIN(P51,O54+P52) | Q53: =MIN(Q51,P54+Q52) | ... BJ53: =MIN(BJ51,BI54+BJ52)
D54: LD and DSU proceeds held (Proceeds Account) | E54: USD m | J54: =I54+J52-J53 | K54: =J54+K52-K53 | L54: =K54+L52-L53 | M54: =L54+M52-M53 | N54: =M54+N52-N53 | O54: =N54+O52-O53 | P54: =O54+P52-P53 | Q54: =P54+Q52-Q53 | ... BJ54: =BI54+BJ52-BJ53
D55: Standby facility drawdown (75%) | E55: USD m | G55: =SUM(J55:BJ55) | J55: =Inputs!$F$249*(J51-J53) | K55: =Inputs!$F$249*(K51-K53) | L55: =Inputs!$F$249*(L51-L53) | M55: =Inputs!$F$249*(M51-M53) | N55: =Inputs!$F$249*(N51-N53) | O55: =Inputs!$F$249*(O51-O53) | P55: =Inputs!$F$249*(P51-P53) | Q55: =Inputs!$F$249*(Q51-Q53) | ... BJ55: =Inputs!$F$249*(BJ51-BJ53)
D56: Contingent equity (25%) | E56: USD m | G56: =SUM(J56:BJ56) | J56: =(1-Inputs!$F$249)*(J51-J53) | K56: =(1-Inputs!$F$249)*(K51-K53) | L56: =(1-Inputs!$F$249)*(L51-L53) | M56: =(1-Inputs!$F$249)*(M51-M53) | N56: =(1-Inputs!$F$249)*(N51-N53) | O56: =(1-Inputs!$F$249)*(O51-O53) | P56: =(1-Inputs!$F$249)*(P51-P53) | Q56: =(1-Inputs!$F$249)*(Q51-Q53) | ... BJ56: =(1-Inputs!$F$249)*(BJ51-BJ53)
D57: ECA-covered tranche: drawdown | E57: USD m | G57: =SUM(J57:BJ57) | J57: =Inputs!$F$75*J47 | K57: =Inputs!$F$75*K47 | L57: =Inputs!$F$75*L47 | M57: =Inputs!$F$75*M47 | N57: =Inputs!$F$75*N47 | O57: =Inputs!$F$75*O47 | P57: =Inputs!$F$75*P47 | Q57: =Inputs!$F$75*Q47 | ... BJ57: =Inputs!$F$75*BJ47
D58: ABDB A-loan: drawdown | E58: USD m | G58: =SUM(J58:BJ58) | J58: =Inputs!$F$76*J47 | K58: =Inputs!$F$76*K47 | L58: =Inputs!$F$76*L47 | M58: =Inputs!$F$76*M47 | N58: =Inputs!$F$76*N47 | O58: =Inputs!$F$76*O47 | P58: =Inputs!$F$76*P47 | Q58: =Inputs!$F$76*Q47 | ... BJ58: =Inputs!$F$76*BJ47
D59: ABDB B-loan: drawdown | E59: USD m | G59: =SUM(J59:BJ59) | J59: =Inputs!$F$77*J47 | K59: =Inputs!$F$77*K47 | L59: =Inputs!$F$77*L47 | M59: =Inputs!$F$77*M47 | N59: =Inputs!$F$77*N47 | O59: =Inputs!$F$77*O47 | P59: =Inputs!$F$77*P47 | Q59: =Inputs!$F$77*Q47 | ... BJ59: =Inputs!$F$77*BJ47
D60: Commercial tranche: drawdown | E60: USD m | G60: =SUM(J60:BJ60) | J60: =Inputs!$F$78*J47 | K60: =Inputs!$F$78*K47 | L60: =Inputs!$F$78*L47 | M60: =Inputs!$F$78*M47 | N60: =Inputs!$F$78*N47 | O60: =Inputs!$F$78*O47 | P60: =Inputs!$F$78*P47 | Q60: =Inputs!$F$78*Q47 | ... BJ60: =Inputs!$F$78*BJ47
D61: ECA-covered tranche: closing balance | E61: USD m | J61: =J28+J57 | K61: =K28+K57 | L61: =L28+L57 | M61: =M28+M57 | N61: =N28+N57 | O61: =O28+O57 | P61: =P28+P57 | Q61: =Q28+Q57 | ... BJ61: =BJ28+BJ57
D62: ABDB A-loan: closing balance | E62: USD m | J62: =J29+J58 | K62: =K29+K58 | L62: =L29+L58 | M62: =M29+M58 | N62: =N29+N58 | O62: =O29+O58 | P62: =P29+P58 | Q62: =Q29+Q58 | ... BJ62: =BJ29+BJ58
D63: ABDB B-loan: closing balance | E63: USD m | J63: =J30+J59 | K63: =K30+K59 | L63: =L30+L59 | M63: =M30+M59 | N63: =N30+N59 | O63: =O30+O59 | P63: =P30+P59 | Q63: =Q30+Q59 | ... BJ63: =BJ30+BJ59
D64: Commercial tranche: closing balance | E64: USD m | J64: =J31+J60 | K64: =K31+K60 | L64: =L31+L60 | M64: =M31+M60 | N64: =N31+N60 | O64: =O31+O60 | P64: =P31+P60 | Q64: =Q31+Q60 | ... BJ64: =BJ31+BJ60
D65: Standby facility: closing balance | E65: USD m | J65: =J32+J55 | K65: =K32+K55 | L65: =L32+L55 | M65: =M32+M55 | N65: =N32+N55 | O65: =O32+O55 | P65: =P32+P55 | Q65: =Q32+Q55 | ... BJ65: =BJ32+BJ55
B66: Equity (USD m)
D67: Equity contributions (incl. LNTP credit in month 1) | E67: USD m | G67: =SUM(J67:BJ67) | J67: =J50-J47+J56 | K67: =K50-K47+K56 | L67: =L50-L47+L56 | M67: =M50-M47+M56 | N67: =N50-N47+N56 | O67: =O50-O47+O56 | P67: =P50-P47+P56 | Q67: =Q50-Q47+Q56 | ... BJ67: =BJ50-BJ47+BJ56
D68: Equity contributed in cash | E68: USD m | G68: =SUM(J68:BJ68) | J68: =J67-IF(Construction!J8=1,Inputs!$F$68,0) | K68: =K67-IF(Construction!K8=1,Inputs!$F$68,0) | L68: =L67-IF(Construction!L8=1,Inputs!$F$68,0) | M68: =M67-IF(Construction!M8=1,Inputs!$F$68,0) | N68: =N67-IF(Construction!N8=1,Inputs!$F$68,0) | O68: =O67-IF(Construction!O8=1,Inputs!$F$68,0) | P68: =P67-IF(Construction!P8=1,Inputs!$F$68,0) | Q68: =Q67-IF(Construction!Q8=1,Inputs!$F$68,0) | ... BJ68: =BJ67-IF(Construction!BJ8=1,Inputs!$F$68,0)
D69: Share capital | E69: USD m | G69: =SUM(J69:BJ69) | J69: =(1-Inputs!$F$53)*J67 | K69: =(1-Inputs!$F$53)*K67 | L69: =(1-Inputs!$F$53)*L67 | M69: =(1-Inputs!$F$53)*M67 | N69: =(1-Inputs!$F$53)*N67 | O69: =(1-Inputs!$F$53)*O67 | P69: =(1-Inputs!$F$53)*P67 | Q69: =(1-Inputs!$F$53)*Q67 | ... BJ69: =(1-Inputs!$F$53)*BJ67
D70: Shareholder loans advanced | E70: USD m | G70: =SUM(J70:BJ70) | J70: =Inputs!$F$53*J67 | K70: =Inputs!$F$53*K67 | L70: =Inputs!$F$53*L67 | M70: =Inputs!$F$53*M67 | N70: =Inputs!$F$53*N67 | O70: =Inputs!$F$53*O67 | P70: =Inputs!$F$53*P67 | Q70: =Inputs!$F$53*Q67 | ... BJ70: =Inputs!$F$53*BJ67
D71: Shareholder loan interest capitalized (to COD) | E71: USD m | G71: =SUM(J71:BJ71) | J71: =IF(Construction!J8<=Time!$F$11,I72*Inputs!$F$104/100*Construction!J11/Inputs!$F$248,0) | K71: =IF(Construction!K8<=Time!$F$11,J72*Inputs!$F$104/100*Construction!K11/Inputs!$F$248,0) | L71: =IF(Construction!L8<=Time!$F$11,K72*Inputs!$F$104/100*Construction!L11/Inputs!$F$248,0) | M71: =IF(Construction!M8<=Time!$F$11,L72*Inputs!$F$104/100*Construction!M11/Inputs!$F$248,0) | N71: =IF(Construction!N8<=Time!$F$11,M72*Inputs!$F$104/100*Construction!N11/Inputs!$F$248,0) | O71: =IF(Construction!O8<=Time!$F$11,N72*Inputs!$F$104/100*Construction!O11/Inputs!$F$248,0) | P71: =IF(Construction!P8<=Time!$F$11,O72*Inputs!$F$104/100*Construction!P11/Inputs!$F$248,0) | Q71: =IF(Construction!Q8<=Time!$F$11,P72*Inputs!$F$104/100*Construction!Q11/Inputs!$F$248,0) | ... BJ71: =IF(Construction!BJ8<=Time!$F$11,BI72*Inputs!$F$104/100*Construction!BJ11/Inputs!$F$248,0)
D72: Shareholder loan balance | E72: USD m | J72: =I72+J71+J70 | K72: =J72+K71+K70 | L72: =K72+L71+L70 | M72: =L72+M71+M70 | N72: =M72+N71+N70 | O72: =N72+O71+O70 | P72: =O72+P71+P70 | Q72: =P72+Q71+Q70 | ... BJ72: =BI72+BJ71+BJ70
D73: Total debt drawdowns (incl. standby) | E73: USD m | G73: =SUM(J73:BJ73) | J73: =J47+J55 | K73: =K47+K55 | L73: =L47+L55 | M73: =M47+M55 | N73: =N47+N55 | O73: =O47+O55 | P73: =P47+P55 | Q73: =Q47+Q55 | ... BJ73: =BJ47+BJ55
D74: Financing costs (IDC, fees, premium, VAT interest) | E74: USD m | G74: =SUM(J74:BJ74) | J74: =J33+J34+J35+J36+J37+J38+J39+J40+J41+J42+J43+J48+Construction!J14*Construction!J38 | K74: =K33+K34+K35+K36+K37+K38+K39+K40+K41+K42+K43+K48+Construction!K14*Construction!K38 | L74: =L33+L34+L35+L36+L37+L38+L39+L40+L41+L42+L43+L48+Construction!L14*Construction!L38 | M74: =M33+M34+M35+M36+M37+M38+M39+M40+M41+M42+M43+M48+Construction!M14*Construction!M38 | N74: =N33+N34+N35+N36+N37+N38+N39+N40+N41+N42+N43+N48+Construction!N14*Construction!N38 | O74: =O33+O34+O35+O36+O37+O38+O39+O40+O41+O42+O43+O48+Construction!O14*Construction!O38 | P74: =P33+P34+P35+P36+P37+P38+P39+P40+P41+P42+P43+P48+Construction!P14*Construction!P38 | Q74: =Q33+Q34+Q35+Q36+Q37+Q38+Q39+Q40+Q41+Q42+Q43+Q48+Construction!Q14*Construction!Q38 | ... BJ74: =BJ33+BJ34+BJ35+BJ36+BJ37+BJ38+BJ39+BJ40+BJ41+BJ42+BJ43+BJ48+Construction!BJ14*Construction!BJ38
D75: Total funding requirement (sum of uses) | E75: USD m | F75: =SUM(Funding!$J$49:$BJ$49)
D76: Capitalized cost (book and tax) | E76: USD m | F76: =SUM(Funding!$J$49:$BJ$49)-SUM(Funding!$J$44:$BJ$44)-SUM(Construction!$J$28:$BJ$28)+SUM(Funding!$J$71:$BJ$71)-SUM(Funding!$J$52:$BJ$52)-Inputs!$F$48*Inputs!$F$267

Sheet Debt
A1: Case P: Belanou Combined Cycle Power Project, Republic of Kessara
A2: Debt: tranches, scheduled repayment, waiver, refinancing, swap, sculpting
A3: Units in column E; constants in column F; row totals in column G; first period in column J. Inputs: blue on yellow. Links from other sheets: green.
D4: Label | E4: Unit | F4: Constant | G4: Total
D5: Period ending | J5: 2018H2 | K5: 2019H1 | L5: 2019H2 | M5: 2020H1 | N5: 2020H2 | O5: 2021H1 | P5: 2021H2 | Q5: 2022H1 | R5: 2022H2 | S5: 2023H1 | T5: 2023H2 | U5: 2024H1 | V5: 2024H2 | W5: 2025H1 | X5: 2025H2 | Y5: 2026H1 | Z5: 2026H2 | AA5: 2027H1 | AB5: 2027H2 | AC5: 2028H1 | AD5: 2028H2 | AE5: 2029H1 | AF5: 2029H2 | AG5: 2030H1 | AH5: 2030H2 | AI5: 2031H1 | AJ5: 2031H2 | AK5: 2032H1 | AL5: 2032H2 | AM5: 2033H1 | AN5: 2033H2 | AO5: 2034H1 | AP5: 2034H2 | AQ5: 2035H1 | AR5: 2035H2 | AS5: 2036H1 | AT5: 2036H2 | AU5: 2037H1 | AV5: 2037H2 | AW5: 2038H1 | AX5: 2038H2 | AY5: 2039H1 | AZ5: 2039H2 | BA5: 2040H1 | BB5: 2040H2 | BC5: 2041H1 | BD5: 2041H2 | BE5: 2042H1 | BF5: 2042H2 | BG5: 2043H1 | BH5: 2043H2 | BI5: 2044H1 | BJ5: 2044H2 | BK5: 2045H1 | BL5: 2045H2 | BM5: 2046H1 | BN5: 2046H2
B7: Rates
D8: Commercial margin (step-ups) | E8: % | J8: =IF(Time!J22<Inputs!$F$207,Inputs!$F$82,IF(Time!J22<Inputs!$F$208,Inputs!$F$83,Inputs!$F$84)) | K8: =IF(Time!K22<Inputs!$F$207,Inputs!$F$82,IF(Time!K22<Inputs!$F$208,Inputs!$F$83,Inputs!$F$84)) | L8: =IF(Time!L22<Inputs!$F$207,Inputs!$F$82,IF(Time!L22<Inputs!$F$208,Inputs!$F$83,Inputs!$F$84)) | M8: =IF(Time!M22<Inputs!$F$207,Inputs!$F$82,IF(Time!M22<Inputs!$F$208,Inputs!$F$83,Inputs!$F$84)) | N8: =IF(Time!N22<Inputs!$F$207,Inputs!$F$82,IF(Time!N22<Inputs!$F$208,Inputs!$F$83,Inputs!$F$84)) | O8: =IF(Time!O22<Inputs!$F$207,Inputs!$F$82,IF(Time!O22<Inputs!$F$208,Inputs!$F$83,Inputs!$F$84)) | P8: =IF(Time!P22<Inputs!$F$207,Inputs!$F$82,IF(Time!P22<Inputs!$F$208,Inputs!$F$83,Inputs!$F$84)) | Q8: =IF(Time!Q22<Inputs!$F$207,Inputs!$F$82,IF(Time!Q22<Inputs!$F$208,Inputs!$F$83,Inputs!$F$84)) | ... BN8: =IF(Time!BN22<Inputs!$F$207,Inputs!$F$82,IF(Time!BN22<Inputs!$F$208,Inputs!$F$83,Inputs!$F$84))
D9: Waiver margin uplift | E9: % | J9: =Time!J44*Inputs!$F$269 | K9: =Time!K44*Inputs!$F$269 | L9: =Time!L44*Inputs!$F$269 | M9: =Time!M44*Inputs!$F$269 | N9: =Time!N44*Inputs!$F$269 | O9: =Time!O44*Inputs!$F$269 | P9: =Time!P44*Inputs!$F$269 | Q9: =Time!Q44*Inputs!$F$269 | ... BN9: =Time!BN44*Inputs!$F$269
D10: ECA-covered tranche: rate per period | E10: factor | J10: =(Operations!J9+Inputs!$F$79+J9)/100*0.5 | K10: =(Operations!K9+Inputs!$F$79+K9)/100*0.5 | L10: =(Operations!L9+Inputs!$F$79+L9)/100*0.5 | M10: =(Operations!M9+Inputs!$F$79+M9)/100*0.5 | N10: =(Operations!N9+Inputs!$F$79+N9)/100*0.5 | O10: =(Operations!O9+Inputs!$F$79+O9)/100*0.5 | P10: =(Operations!P9+Inputs!$F$79+P9)/100*0.5 | Q10: =(Operations!Q9+Inputs!$F$79+Q9)/100*0.5 | ... BN10: =(Operations!BN9+Inputs!$F$79+BN9)/100*0.5
D11: ABDB A-loan: rate per period | E11: factor | J11: =(Operations!J9+Inputs!$F$80+J9)/100*0.5 | K11: =(Operations!K9+Inputs!$F$80+K9)/100*0.5 | L11: =(Operations!L9+Inputs!$F$80+L9)/100*0.5 | M11: =(Operations!M9+Inputs!$F$80+M9)/100*0.5 | N11: =(Operations!N9+Inputs!$F$80+N9)/100*0.5 | O11: =(Operations!O9+Inputs!$F$80+O9)/100*0.5 | P11: =(Operations!P9+Inputs!$F$80+P9)/100*0.5 | Q11: =(Operations!Q9+Inputs!$F$80+Q9)/100*0.5 | ... BN11: =(Operations!BN9+Inputs!$F$80+BN9)/100*0.5
D12: ABDB B-loan: rate per period | E12: factor | J12: =(Operations!J9+Inputs!$F$81+J9)/100*0.5 | K12: =(Operations!K9+Inputs!$F$81+K9)/100*0.5 | L12: =(Operations!L9+Inputs!$F$81+L9)/100*0.5 | M12: =(Operations!M9+Inputs!$F$81+M9)/100*0.5 | N12: =(Operations!N9+Inputs!$F$81+N9)/100*0.5 | O12: =(Operations!O9+Inputs!$F$81+O9)/100*0.5 | P12: =(Operations!P9+Inputs!$F$81+P9)/100*0.5 | Q12: =(Operations!Q9+Inputs!$F$81+Q9)/100*0.5 | ... BN12: =(Operations!BN9+Inputs!$F$81+BN9)/100*0.5
D13: Commercial tranche: rate per period | E13: factor | J13: =(Operations!J9+J8+J9)/100*0.5/(1-Inputs!$F$93/100) | K13: =(Operations!K9+K8+K9)/100*0.5/(1-Inputs!$F$93/100) | L13: =(Operations!L9+L8+L9)/100*0.5/(1-Inputs!$F$93/100) | M13: =(Operations!M9+M8+M9)/100*0.5/(1-Inputs!$F$93/100) | N13: =(Operations!N9+N8+N9)/100*0.5/(1-Inputs!$F$93/100) | O13: =(Operations!O9+O8+O9)/100*0.5/(1-Inputs!$F$93/100) | P13: =(Operations!P9+P8+P9)/100*0.5/(1-Inputs!$F$93/100) | Q13: =(Operations!Q9+Q8+Q9)/100*0.5/(1-Inputs!$F$93/100) | ... BN13: =(Operations!BN9+BN8+BN9)/100*0.5/(1-Inputs!$F$93/100)
D14: Standby facility: rate per period | E14: factor | J14: =(Inputs!$F$102*(Operations!J9+J8+Inputs!$F$101+J9)/(1-Inputs!$F$93/100)+(1-Inputs!$F$102)*(Operations!J9+Inputs!$F$80+Inputs!$F$101+J9))/100*Time!J25/Inputs!$F$247 | K14: =(Inputs!$F$102*(Operations!K9+K8+Inputs!$F$101+K9)/(1-Inputs!$F$93/100)+(1-Inputs!$F$102)*(Operations!K9+Inputs!$F$80+Inputs!$F$101+K9))/100*Time!K25/Inputs!$F$247 | L14: =(Inputs!$F$102*(Operations!L9+L8+Inputs!$F$101+L9)/(1-Inputs!$F$93/100)+(1-Inputs!$F$102)*(Operations!L9+Inputs!$F$80+Inputs!$F$101+L9))/100*Time!L25/Inputs!$F$247 | M14: =(Inputs!$F$102*(Operations!M9+M8+Inputs!$F$101+M9)/(1-Inputs!$F$93/100)+(1-Inputs!$F$102)*(Operations!M9+Inputs!$F$80+Inputs!$F$101+M9))/100*Time!M25/Inputs!$F$247 | N14: =(Inputs!$F$102*(Operations!N9+N8+Inputs!$F$101+N9)/(1-Inputs!$F$93/100)+(1-Inputs!$F$102)*(Operations!N9+Inputs!$F$80+Inputs!$F$101+N9))/100*Time!N25/Inputs!$F$247 | O14: =(Inputs!$F$102*(Operations!O9+O8+Inputs!$F$101+O9)/(1-Inputs!$F$93/100)+(1-Inputs!$F$102)*(Operations!O9+Inputs!$F$80+Inputs!$F$101+O9))/100*Time!O25/Inputs!$F$247 | P14: =(Inputs!$F$102*(Operations!P9+P8+Inputs!$F$101+P9)/(1-Inputs!$F$93/100)+(1-Inputs!$F$102)*(Operations!P9+Inputs!$F$80+Inputs!$F$101+P9))/100*Time!P25/Inputs!$F$247 | Q14: =(Inputs!$F$102*(Operations!Q9+Q8+Inputs!$F$101+Q9)/(1-Inputs!$F$93/100)+(1-Inputs!$F$102)*(Operations!Q9+Inputs!$F$80+Inputs!$F$101+Q9))/100*Time!Q25/Inputs!$F$247 | ... BN14: =(Inputs!$F$102*(Operations!BN9+BN8+Inputs!$F$101+BN9)/(1-Inputs!$F$93/100)+(1-Inputs!$F$102)*(Operations!BN9+Inputs!$F$80+Inputs!$F$101+BN9))/100*Time!BN25/Inputs!$F$247
D15: 2025 project bond: rate per period | E15: factor | J15: =Inputs!$F$271/100*Time!J24 | K15: =Inputs!$F$271/100*Time!K24 | L15: =Inputs!$F$271/100*Time!L24 | M15: =Inputs!$F$271/100*Time!M24 | N15: =Inputs!$F$271/100*Time!N24 | O15: =Inputs!$F$271/100*Time!O24 | P15: =Inputs!$F$271/100*Time!P24 | Q15: =Inputs!$F$271/100*Time!Q24 | ... BN15: =Inputs!$F$271/100*Time!BN24
B16: Contract repayment profile
D17: Repayment profile, selected | E17: fraction | J17: =IF(Inputs!$F$47=1,Inputs!J298,Inputs!J299) | K17: =IF(Inputs!$F$47=1,Inputs!K298,Inputs!K299) | L17: =IF(Inputs!$F$47=1,Inputs!L298,Inputs!L299) | M17: =IF(Inputs!$F$47=1,Inputs!M298,Inputs!M299) | N17: =IF(Inputs!$F$47=1,Inputs!N298,Inputs!N299) | O17: =IF(Inputs!$F$47=1,Inputs!O298,Inputs!O299) | P17: =IF(Inputs!$F$47=1,Inputs!P298,Inputs!P299) | Q17: =IF(Inputs!$F$47=1,Inputs!Q298,Inputs!Q299) | ... BN17: =IF(Inputs!$F$47=1,Inputs!BN298,Inputs!BN299)
D18: Remaining profile (this and later installments) | E18: fraction | J18: =SUM(J17:BN17) | K18: =SUM(K17:BN17) | L18: =SUM(L17:BN17) | M18: =SUM(M17:BN17) | N18: =SUM(N17:BN17) | O18: =SUM(O17:BN17) | P18: =SUM(P17:BN17) | Q18: =SUM(Q17:BN17) | R18: =SUM(R17:BN17) | S18: =SUM(S17:BN17) | T18: =SUM(T17:BN17) | U18: =SUM(U17:BN17) | V18: =SUM(V17:BN17) | W18: =SUM(W17:BN17) | X18: =SUM(X17:BN17) | Y18: =SUM(Y17:BN17) | Z18: =SUM(Z17:BN17) | AA18: =SUM(AA17:BN17) | AB18: =SUM(AB17:BN17) | AC18: =SUM(AC17:BN17) | AD18: =SUM(AD17:BN17) | AE18: =SUM(AE17:BN17) | AF18: =SUM(AF17:BN17) | AG18: =SUM(AG17:BN17) | AH18: =SUM(AH17:BN17) | AI18: =SUM(AI17:BN17) | AJ18: =SUM(AJ17:BN17) | AK18: =SUM(AK17:BN17) | AL18: =SUM(AL17:BN17) | AM18: =SUM(AM17:BN17) | AN18: =SUM(AN17:BN17) | AO18: =SUM(AO17:BN17) | AP18: =SUM(AP17:BN17) | AQ18: =SUM(AQ17:BN17) | AR18: =SUM(AR17:BN17) | AS18: =SUM(AS17:BN17) | AT18: =SUM(AT17:BN17) | AU18: =SUM(AU17:BN17) | AV18: =SUM(AV17:BN17) | AW18: =SUM(AW17:BN17) | AX18: =SUM(AX17:BN17) | AY18: =SUM(AY17:BN17) | AZ18: =SUM(AZ17:BN17) | BA18: =SUM(BA17:BN17) | BB18: =SUM(BB17:BN17) | BC18: =SUM(BC17:BN17) | BD18: =SUM(BD17:BN17) | BE18: =SUM(BE17:BN17) | BF18: =SUM(BF17:BN17) | BG18: =SUM(BG17:BN17) | BH18: =SUM(BH17:BN17) | BI18: =SUM(BI17:BN17) | BJ18: =SUM(BJ17:BN17) | BK18: =SUM(BK17:BN17) | BL18: =SUM(BL17:BN17) | BM18: =SUM(BM17:BN17) | BN18: =SUM(BN17:BN17)
D19: Installment share of remaining balance | E19: fraction | J19: =IF(J18>Inputs!$F$253,J17/J18,0) | K19: =IF(K18>Inputs!$F$253,K17/K18,0) | L19: =IF(L18>Inputs!$F$253,L17/L18,0) | M19: =IF(M18>Inputs!$F$253,M17/M18,0) | N19: =IF(N18>Inputs!$F$253,N17/N18,0) | O19: =IF(O18>Inputs!$F$253,O17/O18,0) | P19: =IF(P18>Inputs!$F$253,P17/P18,0) | Q19: =IF(Q18>Inputs!$F$253,Q17/Q18,0) | ... BN19: =IF(BN18>Inputs!$F$253,BN17/BN18,0)
B20: ECA-covered tranche
D21: Opening balance | E21: USD m | J21: =Time!J35*I33 | K21: =Time!K35*J33 | L21: =Time!L35*K33 | M21: =Time!M35*L33 | N21: =Time!N35*M33 | O21: =Time!O35*N33 | P21: =Time!P35*O33 | Q21: =Time!Q35*P33 | ... BN21: =Time!BN35*BM33
D22: Deferred principal, opening | E22: USD m | J22: =I30 | K22: =J30 | L22: =K30 | M22: =L30 | N22: =M30 | O22: =N30 | P22: =O30 | Q22: =P30 | ... BN22: =BM30
D23: Interest (incl. WHT gross-up where applicable) | E23: USD m | G23: =SUM(J23:BN23) | J23: =J21*J10 | K23: =K21*K10 | L23: =L21*L10 | M23: =M21*M10 | N23: =N21*N10 | O23: =O21*O10 | P23: =P21*P10 | Q23: =Q21*Q10 | ... BN23: =BN21*BN10
D24: Scheduled principal per profile | E24: USD m | G24: =SUM(J24:BN24) | J24: =Time!J35*(J21-J22)*J19 | K24: =Time!K35*(K21-K22)*K19 | L24: =Time!L35*(L21-L22)*L19 | M24: =Time!M35*(M21-M22)*M19 | N24: =Time!N35*(N21-N22)*N19 | O24: =Time!O35*(O21-O22)*O19 | P24: =Time!P35*(P21-P22)*P19 | Q24: =Time!Q35*(Q21-Q22)*Q19 | ... BN24: =Time!BN35*(BN21-BN22)*BN19
D25: Principal deferred under the waiver | E25: USD m | G25: =SUM(J25:BN25) | J25: =Time!J43*Inputs!$F$270*J24 | K25: =Time!K43*Inputs!$F$270*K24 | L25: =Time!L43*Inputs!$F$270*L24 | M25: =Time!M43*Inputs!$F$270*M24 | N25: =Time!N43*Inputs!$F$270*N24 | O25: =Time!O43*Inputs!$F$270*O24 | P25: =Time!P43*Inputs!$F$270*P24 | Q25: =Time!Q43*Inputs!$F$270*Q24 | ... BN25: =Time!BN43*Inputs!$F$270*BN24
D26: Deferred principal repaid (equal parts over the remaining repayment dates) | E26: USD m | G26: =SUM(J26:BN26) | J26: =IF(Time!J46>0,Time!J45*J22/Time!J46,0) | K26: =IF(Time!K46>0,Time!K45*K22/Time!K46,0) | L26: =IF(Time!L46>0,Time!L45*L22/Time!L46,0) | M26: =IF(Time!M46>0,Time!M45*M22/Time!M46,0) | N26: =IF(Time!N46>0,Time!N45*N22/Time!N46,0) | O26: =IF(Time!O46>0,Time!O45*O22/Time!O46,0) | P26: =IF(Time!P46>0,Time!P45*P22/Time!P46,0) | Q26: =IF(Time!Q46>0,Time!Q45*Q22/Time!Q46,0) | ... BN26: =IF(Time!BN46>0,Time!BN45*BN22/Time!BN46,0)
D27: Principal paid | E27: USD m | G27: =SUM(J27:BN27) | J27: =J24-J25+J26 | K27: =K24-K25+K26 | L27: =L24-L25+L26 | M27: =M24-M25+M26 | N27: =N24-N25+N26 | O27: =O24-O25+O26 | P27: =P24-P25+P26 | Q27: =Q24-Q25+Q26 | ... BN27: =BN24-BN25+BN26
D28: Performance LD prepayment | E28: USD m | G28: =SUM(J28:BN28) | J28: =Time!J42*Inputs!$F$267*(J21-J27)/(J21-J27+J35-J41+J49-J55+J63-J69+J77-J83+Inputs!$F$253) | K28: =Time!K42*Inputs!$F$267*(K21-K27)/(K21-K27+K35-K41+K49-K55+K63-K69+K77-K83+Inputs!$F$253) | L28: =Time!L42*Inputs!$F$267*(L21-L27)/(L21-L27+L35-L41+L49-L55+L63-L69+L77-L83+Inputs!$F$253) | M28: =Time!M42*Inputs!$F$267*(M21-M27)/(M21-M27+M35-M41+M49-M55+M63-M69+M77-M83+Inputs!$F$253) | N28: =Time!N42*Inputs!$F$267*(N21-N27)/(N21-N27+N35-N41+N49-N55+N63-N69+N77-N83+Inputs!$F$253) | O28: =Time!O42*Inputs!$F$267*(O21-O27)/(O21-O27+O35-O41+O49-O55+O63-O69+O77-O83+Inputs!$F$253) | P28: =Time!P42*Inputs!$F$267*(P21-P27)/(P21-P27+P35-P41+P49-P55+P63-P69+P77-P83+Inputs!$F$253) | Q28: =Time!Q42*Inputs!$F$267*(Q21-Q27)/(Q21-Q27+Q35-Q41+Q49-Q55+Q63-Q69+Q77-Q83+Inputs!$F$253) | ... BN28: =Time!BN42*Inputs!$F$267*(BN21-BN27)/(BN21-BN27+BN35-BN41+BN49-BN55+BN63-BN69+BN77-BN83+Inputs!$F$253)
D29: Refinanced (not refinanced: stays in place) | E29: USD m | G29: =SUM(J29:BN29) | J29: =Time!J47*0 | K29: =Time!K47*0 | L29: =Time!L47*0 | M29: =Time!M47*0 | N29: =Time!N47*0 | O29: =Time!O47*0 | P29: =Time!P47*0 | Q29: =Time!Q47*0 | ... BN29: =Time!BN47*0
D30: Deferred principal, closing | E30: USD m | J30: =J22+J25-J26 | K30: =K22+K25-K26 | L30: =L22+L25-L26 | M30: =M22+M25-M26 | N30: =N22+N25-N26 | O30: =O22+O25-O26 | P30: =P22+P25-P26 | Q30: =Q22+Q25-Q26 | ... BN30: =BN22+BN25-BN26
D31: Balance after scheduled payment, LDs and refinancing | E31: USD m | J31: =J21-J27-J28-J29 | K31: =K21-K27-K28-K29 | L31: =L21-L27-L28-L29 | M31: =M21-M27-M28-M29 | N31: =N21-N27-N28-N29 | O31: =O21-O27-O28-O29 | P31: =P21-P27-P28-P29 | Q31: =Q21-Q27-Q28-Q29 | ... BN31: =BN21-BN27-BN28-BN29
D32: Cash sweep prepayment | E32: USD m | G32: =SUM(J32:BN32) | J32: =Waterfall!J28*J31/(J31+J45+J59+J73+J87+Inputs!$F$253) | K32: =Waterfall!K28*K31/(K31+K45+K59+K73+K87+Inputs!$F$253) | L32: =Waterfall!L28*L31/(L31+L45+L59+L73+L87+Inputs!$F$253) | M32: =Waterfall!M28*M31/(M31+M45+M59+M73+M87+Inputs!$F$253) | N32: =Waterfall!N28*N31/(N31+N45+N59+N73+N87+Inputs!$F$253) | O32: =Waterfall!O28*O31/(O31+O45+O59+O73+O87+Inputs!$F$253) | P32: =Waterfall!P28*P31/(P31+P45+P59+P73+P87+Inputs!$F$253) | Q32: =Waterfall!Q28*Q31/(Q31+Q45+Q59+Q73+Q87+Inputs!$F$253) | ... BN32: =Waterfall!BN28*BN31/(BN31+BN45+BN59+BN73+BN87+Inputs!$F$253)
D33: Closing balance | E33: USD m | J33: =IF(Time!J34=1,INDEX(Funding!$J$61:$BJ$61,1,Time!$F$14),Time!J35*(J31-J32)) | K33: =IF(Time!K34=1,INDEX(Funding!$J$61:$BJ$61,1,Time!$F$14),Time!K35*(K31-K32)) | L33: =IF(Time!L34=1,INDEX(Funding!$J$61:$BJ$61,1,Time!$F$14),Time!L35*(L31-L32)) | M33: =IF(Time!M34=1,INDEX(Funding!$J$61:$BJ$61,1,Time!$F$14),Time!M35*(M31-M32)) | N33: =IF(Time!N34=1,INDEX(Funding!$J$61:$BJ$61,1,Time!$F$14),Time!N35*(N31-N32)) | O33: =IF(Time!O34=1,INDEX(Funding!$J$61:$BJ$61,1,Time!$F$14),Time!O35*(O31-O32)) | P33: =IF(Time!P34=1,INDEX(Funding!$J$61:$BJ$61,1,Time!$F$14),Time!P35*(P31-P32)) | Q33: =IF(Time!Q34=1,INDEX(Funding!$J$61:$BJ$61,1,Time!$F$14),Time!Q35*(Q31-Q32)) | ... BN33: =IF(Time!BN34=1,INDEX(Funding!$J$61:$BJ$61,1,Time!$F$14),Time!BN35*(BN31-BN32))
B34: ABDB A-loan
D35: Opening balance | E35: USD m | J35: =Time!J35*I47 | K35: =Time!K35*J47 | L35: =Time!L35*K47 | M35: =Time!M35*L47 | N35: =Time!N35*M47 | O35: =Time!O35*N47 | P35: =Time!P35*O47 | Q35: =Time!Q35*P47 | ... BN35: =Time!BN35*BM47
D36: Deferred principal, opening | E36: USD m | J36: =I44 | K36: =J44 | L36: =K44 | M36: =L44 | N36: =M44 | O36: =N44 | P36: =O44 | Q36: =P44 | ... BN36: =BM44
D37: Interest (incl. WHT gross-up where applicable) | E37: USD m | G37: =SUM(J37:BN37) | J37: =J35*J11 | K37: =K35*K11 | L37: =L35*L11 | M37: =M35*M11 | N37: =N35*N11 | O37: =O35*O11 | P37: =P35*P11 | Q37: =Q35*Q11 | ... BN37: =BN35*BN11
D38: Scheduled principal per profile | E38: USD m | G38: =SUM(J38:BN38) | J38: =Time!J35*(J35-J36)*J19 | K38: =Time!K35*(K35-K36)*K19 | L38: =Time!L35*(L35-L36)*L19 | M38: =Time!M35*(M35-M36)*M19 | N38: =Time!N35*(N35-N36)*N19 | O38: =Time!O35*(O35-O36)*O19 | P38: =Time!P35*(P35-P36)*P19 | Q38: =Time!Q35*(Q35-Q36)*Q19 | ... BN38: =Time!BN35*(BN35-BN36)*BN19
D39: Principal deferred under the waiver | E39: USD m | G39: =SUM(J39:BN39) | J39: =Time!J43*Inputs!$F$270*J38 | K39: =Time!K43*Inputs!$F$270*K38 | L39: =Time!L43*Inputs!$F$270*L38 | M39: =Time!M43*Inputs!$F$270*M38 | N39: =Time!N43*Inputs!$F$270*N38 | O39: =Time!O43*Inputs!$F$270*O38 | P39: =Time!P43*Inputs!$F$270*P38 | Q39: =Time!Q43*Inputs!$F$270*Q38 | ... BN39: =Time!BN43*Inputs!$F$270*BN38
D40: Deferred principal repaid (equal parts over the remaining repayment dates) | E40: USD m | G40: =SUM(J40:BN40) | J40: =IF(Time!J46>0,Time!J45*J36/Time!J46,0) | K40: =IF(Time!K46>0,Time!K45*K36/Time!K46,0) | L40: =IF(Time!L46>0,Time!L45*L36/Time!L46,0) | M40: =IF(Time!M46>0,Time!M45*M36/Time!M46,0) | N40: =IF(Time!N46>0,Time!N45*N36/Time!N46,0) | O40: =IF(Time!O46>0,Time!O45*O36/Time!O46,0) | P40: =IF(Time!P46>0,Time!P45*P36/Time!P46,0) | Q40: =IF(Time!Q46>0,Time!Q45*Q36/Time!Q46,0) | ... BN40: =IF(Time!BN46>0,Time!BN45*BN36/Time!BN46,0)
D41: Principal paid | E41: USD m | G41: =SUM(J41:BN41) | J41: =J38-J39+J40 | K41: =K38-K39+K40 | L41: =L38-L39+L40 | M41: =M38-M39+M40 | N41: =N38-N39+N40 | O41: =O38-O39+O40 | P41: =P38-P39+P40 | Q41: =Q38-Q39+Q40 | ... BN41: =BN38-BN39+BN40
D42: Performance LD prepayment | E42: USD m | G42: =SUM(J42:BN42) | J42: =Time!J42*Inputs!$F$267*(J35-J41)/(J21-J27+J35-J41+J49-J55+J63-J69+J77-J83+Inputs!$F$253) | K42: =Time!K42*Inputs!$F$267*(K35-K41)/(K21-K27+K35-K41+K49-K55+K63-K69+K77-K83+Inputs!$F$253) | L42: =Time!L42*Inputs!$F$267*(L35-L41)/(L21-L27+L35-L41+L49-L55+L63-L69+L77-L83+Inputs!$F$253) | M42: =Time!M42*Inputs!$F$267*(M35-M41)/(M21-M27+M35-M41+M49-M55+M63-M69+M77-M83+Inputs!$F$253) | N42: =Time!N42*Inputs!$F$267*(N35-N41)/(N21-N27+N35-N41+N49-N55+N63-N69+N77-N83+Inputs!$F$253) | O42: =Time!O42*Inputs!$F$267*(O35-O41)/(O21-O27+O35-O41+O49-O55+O63-O69+O77-O83+Inputs!$F$253) | P42: =Time!P42*Inputs!$F$267*(P35-P41)/(P21-P27+P35-P41+P49-P55+P63-P69+P77-P83+Inputs!$F$253) | Q42: =Time!Q42*Inputs!$F$267*(Q35-Q41)/(Q21-Q27+Q35-Q41+Q49-Q55+Q63-Q69+Q77-Q83+Inputs!$F$253) | ... BN42: =Time!BN42*Inputs!$F$267*(BN35-BN41)/(BN21-BN27+BN35-BN41+BN49-BN55+BN63-BN69+BN77-BN83+Inputs!$F$253)
D43: Refinanced (not refinanced: stays in place) | E43: USD m | G43: =SUM(J43:BN43) | J43: =Time!J47*0 | K43: =Time!K47*0 | L43: =Time!L47*0 | M43: =Time!M47*0 | N43: =Time!N47*0 | O43: =Time!O47*0 | P43: =Time!P47*0 | Q43: =Time!Q47*0 | ... BN43: =Time!BN47*0
D44: Deferred principal, closing | E44: USD m | J44: =J36+J39-J40 | K44: =K36+K39-K40 | L44: =L36+L39-L40 | M44: =M36+M39-M40 | N44: =N36+N39-N40 | O44: =O36+O39-O40 | P44: =P36+P39-P40 | Q44: =Q36+Q39-Q40 | ... BN44: =BN36+BN39-BN40
D45: Balance after scheduled payment, LDs and refinancing | E45: USD m | J45: =J35-J41-J42-J43 | K45: =K35-K41-K42-K43 | L45: =L35-L41-L42-L43 | M45: =M35-M41-M42-M43 | N45: =N35-N41-N42-N43 | O45: =O35-O41-O42-O43 | P45: =P35-P41-P42-P43 | Q45: =Q35-Q41-Q42-Q43 | ... BN45: =BN35-BN41-BN42-BN43
D46: Cash sweep prepayment | E46: USD m | G46: =SUM(J46:BN46) | J46: =Waterfall!J28*J45/(J31+J45+J59+J73+J87+Inputs!$F$253) | K46: =Waterfall!K28*K45/(K31+K45+K59+K73+K87+Inputs!$F$253) | L46: =Waterfall!L28*L45/(L31+L45+L59+L73+L87+Inputs!$F$253) | M46: =Waterfall!M28*M45/(M31+M45+M59+M73+M87+Inputs!$F$253) | N46: =Waterfall!N28*N45/(N31+N45+N59+N73+N87+Inputs!$F$253) | O46: =Waterfall!O28*O45/(O31+O45+O59+O73+O87+Inputs!$F$253) | P46: =Waterfall!P28*P45/(P31+P45+P59+P73+P87+Inputs!$F$253) | Q46: =Waterfall!Q28*Q45/(Q31+Q45+Q59+Q73+Q87+Inputs!$F$253) | ... BN46: =Waterfall!BN28*BN45/(BN31+BN45+BN59+BN73+BN87+Inputs!$F$253)
D47: Closing balance | E47: USD m | J47: =IF(Time!J34=1,INDEX(Funding!$J$62:$BJ$62,1,Time!$F$14),Time!J35*(J45-J46)) | K47: =IF(Time!K34=1,INDEX(Funding!$J$62:$BJ$62,1,Time!$F$14),Time!K35*(K45-K46)) | L47: =IF(Time!L34=1,INDEX(Funding!$J$62:$BJ$62,1,Time!$F$14),Time!L35*(L45-L46)) | M47: =IF(Time!M34=1,INDEX(Funding!$J$62:$BJ$62,1,Time!$F$14),Time!M35*(M45-M46)) | N47: =IF(Time!N34=1,INDEX(Funding!$J$62:$BJ$62,1,Time!$F$14),Time!N35*(N45-N46)) | O47: =IF(Time!O34=1,INDEX(Funding!$J$62:$BJ$62,1,Time!$F$14),Time!O35*(O45-O46)) | P47: =IF(Time!P34=1,INDEX(Funding!$J$62:$BJ$62,1,Time!$F$14),Time!P35*(P45-P46)) | Q47: =IF(Time!Q34=1,INDEX(Funding!$J$62:$BJ$62,1,Time!$F$14),Time!Q35*(Q45-Q46)) | ... BN47: =IF(Time!BN34=1,INDEX(Funding!$J$62:$BJ$62,1,Time!$F$14),Time!BN35*(BN45-BN46))
B48: ABDB B-loan
D49: Opening balance | E49: USD m | J49: =Time!J35*I61 | K49: =Time!K35*J61 | L49: =Time!L35*K61 | M49: =Time!M35*L61 | N49: =Time!N35*M61 | O49: =Time!O35*N61 | P49: =Time!P35*O61 | Q49: =Time!Q35*P61 | ... BN49: =Time!BN35*BM61
D50: Deferred principal, opening | E50: USD m | J50: =I58 | K50: =J58 | L50: =K58 | M50: =L58 | N50: =M58 | O50: =N58 | P50: =O58 | Q50: =P58 | ... BN50: =BM58
D51: Interest (incl. WHT gross-up where applicable) | E51: USD m | G51: =SUM(J51:BN51) | J51: =J49*J12 | K51: =K49*K12 | L51: =L49*L12 | M51: =M49*M12 | N51: =N49*N12 | O51: =O49*O12 | P51: =P49*P12 | Q51: =Q49*Q12 | ... BN51: =BN49*BN12
D52: Scheduled principal per profile | E52: USD m | G52: =SUM(J52:BN52) | J52: =Time!J35*(J49-J50)*J19 | K52: =Time!K35*(K49-K50)*K19 | L52: =Time!L35*(L49-L50)*L19 | M52: =Time!M35*(M49-M50)*M19 | N52: =Time!N35*(N49-N50)*N19 | O52: =Time!O35*(O49-O50)*O19 | P52: =Time!P35*(P49-P50)*P19 | Q52: =Time!Q35*(Q49-Q50)*Q19 | ... BN52: =Time!BN35*(BN49-BN50)*BN19
D53: Principal deferred under the waiver | E53: USD m | G53: =SUM(J53:BN53) | J53: =Time!J43*Inputs!$F$270*J52 | K53: =Time!K43*Inputs!$F$270*K52 | L53: =Time!L43*Inputs!$F$270*L52 | M53: =Time!M43*Inputs!$F$270*M52 | N53: =Time!N43*Inputs!$F$270*N52 | O53: =Time!O43*Inputs!$F$270*O52 | P53: =Time!P43*Inputs!$F$270*P52 | Q53: =Time!Q43*Inputs!$F$270*Q52 | ... BN53: =Time!BN43*Inputs!$F$270*BN52
D54: Deferred principal repaid (equal parts over the remaining repayment dates) | E54: USD m | G54: =SUM(J54:BN54) | J54: =IF(Time!J46>0,Time!J45*J50/Time!J46,0) | K54: =IF(Time!K46>0,Time!K45*K50/Time!K46,0) | L54: =IF(Time!L46>0,Time!L45*L50/Time!L46,0) | M54: =IF(Time!M46>0,Time!M45*M50/Time!M46,0) | N54: =IF(Time!N46>0,Time!N45*N50/Time!N46,0) | O54: =IF(Time!O46>0,Time!O45*O50/Time!O46,0) | P54: =IF(Time!P46>0,Time!P45*P50/Time!P46,0) | Q54: =IF(Time!Q46>0,Time!Q45*Q50/Time!Q46,0) | ... BN54: =IF(Time!BN46>0,Time!BN45*BN50/Time!BN46,0)
D55: Principal paid | E55: USD m | G55: =SUM(J55:BN55) | J55: =J52-J53+J54 | K55: =K52-K53+K54 | L55: =L52-L53+L54 | M55: =M52-M53+M54 | N55: =N52-N53+N54 | O55: =O52-O53+O54 | P55: =P52-P53+P54 | Q55: =Q52-Q53+Q54 | ... BN55: =BN52-BN53+BN54
D56: Performance LD prepayment | E56: USD m | G56: =SUM(J56:BN56) | J56: =Time!J42*Inputs!$F$267*(J49-J55)/(J21-J27+J35-J41+J49-J55+J63-J69+J77-J83+Inputs!$F$253) | K56: =Time!K42*Inputs!$F$267*(K49-K55)/(K21-K27+K35-K41+K49-K55+K63-K69+K77-K83+Inputs!$F$253) | L56: =Time!L42*Inputs!$F$267*(L49-L55)/(L21-L27+L35-L41+L49-L55+L63-L69+L77-L83+Inputs!$F$253) | M56: =Time!M42*Inputs!$F$267*(M49-M55)/(M21-M27+M35-M41+M49-M55+M63-M69+M77-M83+Inputs!$F$253) | N56: =Time!N42*Inputs!$F$267*(N49-N55)/(N21-N27+N35-N41+N49-N55+N63-N69+N77-N83+Inputs!$F$253) | O56: =Time!O42*Inputs!$F$267*(O49-O55)/(O21-O27+O35-O41+O49-O55+O63-O69+O77-O83+Inputs!$F$253) | P56: =Time!P42*Inputs!$F$267*(P49-P55)/(P21-P27+P35-P41+P49-P55+P63-P69+P77-P83+Inputs!$F$253) | Q56: =Time!Q42*Inputs!$F$267*(Q49-Q55)/(Q21-Q27+Q35-Q41+Q49-Q55+Q63-Q69+Q77-Q83+Inputs!$F$253) | ... BN56: =Time!BN42*Inputs!$F$267*(BN49-BN55)/(BN21-BN27+BN35-BN41+BN49-BN55+BN63-BN69+BN77-BN83+Inputs!$F$253)
D57: Refinanced (prepaid from bond proceeds) | E57: USD m | G57: =SUM(J57:BN57) | J57: =Time!J47*(J49-J55-J56) | K57: =Time!K47*(K49-K55-K56) | L57: =Time!L47*(L49-L55-L56) | M57: =Time!M47*(M49-M55-M56) | N57: =Time!N47*(N49-N55-N56) | O57: =Time!O47*(O49-O55-O56) | P57: =Time!P47*(P49-P55-P56) | Q57: =Time!Q47*(Q49-Q55-Q56) | ... BN57: =Time!BN47*(BN49-BN55-BN56)
D58: Deferred principal, closing | E58: USD m | J58: =(1-Time!J47)*(J50+J53-J54) | K58: =(1-Time!K47)*(K50+K53-K54) | L58: =(1-Time!L47)*(L50+L53-L54) | M58: =(1-Time!M47)*(M50+M53-M54) | N58: =(1-Time!N47)*(N50+N53-N54) | O58: =(1-Time!O47)*(O50+O53-O54) | P58: =(1-Time!P47)*(P50+P53-P54) | Q58: =(1-Time!Q47)*(Q50+Q53-Q54) | ... BN58: =(1-Time!BN47)*(BN50+BN53-BN54)
D59: Balance after scheduled payment, LDs and refinancing | E59: USD m | J59: =J49-J55-J56-J57 | K59: =K49-K55-K56-K57 | L59: =L49-L55-L56-L57 | M59: =M49-M55-M56-M57 | N59: =N49-N55-N56-N57 | O59: =O49-O55-O56-O57 | P59: =P49-P55-P56-P57 | Q59: =Q49-Q55-Q56-Q57 | ... BN59: =BN49-BN55-BN56-BN57
D60: Cash sweep prepayment | E60: USD m | G60: =SUM(J60:BN60) | J60: =Waterfall!J28*J59/(J31+J45+J59+J73+J87+Inputs!$F$253) | K60: =Waterfall!K28*K59/(K31+K45+K59+K73+K87+Inputs!$F$253) | L60: =Waterfall!L28*L59/(L31+L45+L59+L73+L87+Inputs!$F$253) | M60: =Waterfall!M28*M59/(M31+M45+M59+M73+M87+Inputs!$F$253) | N60: =Waterfall!N28*N59/(N31+N45+N59+N73+N87+Inputs!$F$253) | O60: =Waterfall!O28*O59/(O31+O45+O59+O73+O87+Inputs!$F$253) | P60: =Waterfall!P28*P59/(P31+P45+P59+P73+P87+Inputs!$F$253) | Q60: =Waterfall!Q28*Q59/(Q31+Q45+Q59+Q73+Q87+Inputs!$F$253) | ... BN60: =Waterfall!BN28*BN59/(BN31+BN45+BN59+BN73+BN87+Inputs!$F$253)
D61: Closing balance | E61: USD m | J61: =IF(Time!J34=1,INDEX(Funding!$J$63:$BJ$63,1,Time!$F$14),Time!J35*(J59-J60)) | K61: =IF(Time!K34=1,INDEX(Funding!$J$63:$BJ$63,1,Time!$F$14),Time!K35*(K59-K60)) | L61: =IF(Time!L34=1,INDEX(Funding!$J$63:$BJ$63,1,Time!$F$14),Time!L35*(L59-L60)) | M61: =IF(Time!M34=1,INDEX(Funding!$J$63:$BJ$63,1,Time!$F$14),Time!M35*(M59-M60)) | N61: =IF(Time!N34=1,INDEX(Funding!$J$63:$BJ$63,1,Time!$F$14),Time!N35*(N59-N60)) | O61: =IF(Time!O34=1,INDEX(Funding!$J$63:$BJ$63,1,Time!$F$14),Time!O35*(O59-O60)) | P61: =IF(Time!P34=1,INDEX(Funding!$J$63:$BJ$63,1,Time!$F$14),Time!P35*(P59-P60)) | Q61: =IF(Time!Q34=1,INDEX(Funding!$J$63:$BJ$63,1,Time!$F$14),Time!Q35*(Q59-Q60)) | ... BN61: =IF(Time!BN34=1,INDEX(Funding!$J$63:$BJ$63,1,Time!$F$14),Time!BN35*(BN59-BN60))
B62: Commercial tranche
D63: Opening balance | E63: USD m | J63: =Time!J35*I75 | K63: =Time!K35*J75 | L63: =Time!L35*K75 | M63: =Time!M35*L75 | N63: =Time!N35*M75 | O63: =Time!O35*N75 | P63: =Time!P35*O75 | Q63: =Time!Q35*P75 | ... BN63: =Time!BN35*BM75
D64: Deferred principal, opening | E64: USD m | J64: =I72 | K64: =J72 | L64: =K72 | M64: =L72 | N64: =M72 | O64: =N72 | P64: =O72 | Q64: =P72 | ... BN64: =BM72
D65: Interest (incl. WHT gross-up where applicable) | E65: USD m | G65: =SUM(J65:BN65) | J65: =J63*J13 | K65: =K63*K13 | L65: =L63*L13 | M65: =M63*M13 | N65: =N63*N13 | O65: =O63*O13 | P65: =P63*P13 | Q65: =Q63*Q13 | ... BN65: =BN63*BN13
D66: Scheduled principal per profile | E66: USD m | G66: =SUM(J66:BN66) | J66: =Time!J35*(J63-J64)*J19 | K66: =Time!K35*(K63-K64)*K19 | L66: =Time!L35*(L63-L64)*L19 | M66: =Time!M35*(M63-M64)*M19 | N66: =Time!N35*(N63-N64)*N19 | O66: =Time!O35*(O63-O64)*O19 | P66: =Time!P35*(P63-P64)*P19 | Q66: =Time!Q35*(Q63-Q64)*Q19 | ... BN66: =Time!BN35*(BN63-BN64)*BN19
D67: Principal deferred under the waiver | E67: USD m | G67: =SUM(J67:BN67) | J67: =Time!J43*Inputs!$F$270*J66 | K67: =Time!K43*Inputs!$F$270*K66 | L67: =Time!L43*Inputs!$F$270*L66 | M67: =Time!M43*Inputs!$F$270*M66 | N67: =Time!N43*Inputs!$F$270*N66 | O67: =Time!O43*Inputs!$F$270*O66 | P67: =Time!P43*Inputs!$F$270*P66 | Q67: =Time!Q43*Inputs!$F$270*Q66 | ... BN67: =Time!BN43*Inputs!$F$270*BN66
D68: Deferred principal repaid (equal parts over the remaining repayment dates) | E68: USD m | G68: =SUM(J68:BN68) | J68: =IF(Time!J46>0,Time!J45*J64/Time!J46,0) | K68: =IF(Time!K46>0,Time!K45*K64/Time!K46,0) | L68: =IF(Time!L46>0,Time!L45*L64/Time!L46,0) | M68: =IF(Time!M46>0,Time!M45*M64/Time!M46,0) | N68: =IF(Time!N46>0,Time!N45*N64/Time!N46,0) | O68: =IF(Time!O46>0,Time!O45*O64/Time!O46,0) | P68: =IF(Time!P46>0,Time!P45*P64/Time!P46,0) | Q68: =IF(Time!Q46>0,Time!Q45*Q64/Time!Q46,0) | ... BN68: =IF(Time!BN46>0,Time!BN45*BN64/Time!BN46,0)
D69: Principal paid | E69: USD m | G69: =SUM(J69:BN69) | J69: =J66-J67+J68 | K69: =K66-K67+K68 | L69: =L66-L67+L68 | M69: =M66-M67+M68 | N69: =N66-N67+N68 | O69: =O66-O67+O68 | P69: =P66-P67+P68 | Q69: =Q66-Q67+Q68 | ... BN69: =BN66-BN67+BN68
D70: Performance LD prepayment | E70: USD m | G70: =SUM(J70:BN70) | J70: =Time!J42*Inputs!$F$267*(J63-J69)/(J21-J27+J35-J41+J49-J55+J63-J69+J77-J83+Inputs!$F$253) | K70: =Time!K42*Inputs!$F$267*(K63-K69)/(K21-K27+K35-K41+K49-K55+K63-K69+K77-K83+Inputs!$F$253) | L70: =Time!L42*Inputs!$F$267*(L63-L69)/(L21-L27+L35-L41+L49-L55+L63-L69+L77-L83+Inputs!$F$253) | M70: =Time!M42*Inputs!$F$267*(M63-M69)/(M21-M27+M35-M41+M49-M55+M63-M69+M77-M83+Inputs!$F$253) | N70: =Time!N42*Inputs!$F$267*(N63-N69)/(N21-N27+N35-N41+N49-N55+N63-N69+N77-N83+Inputs!$F$253) | O70: =Time!O42*Inputs!$F$267*(O63-O69)/(O21-O27+O35-O41+O49-O55+O63-O69+O77-O83+Inputs!$F$253) | P70: =Time!P42*Inputs!$F$267*(P63-P69)/(P21-P27+P35-P41+P49-P55+P63-P69+P77-P83+Inputs!$F$253) | Q70: =Time!Q42*Inputs!$F$267*(Q63-Q69)/(Q21-Q27+Q35-Q41+Q49-Q55+Q63-Q69+Q77-Q83+Inputs!$F$253) | ... BN70: =Time!BN42*Inputs!$F$267*(BN63-BN69)/(BN21-BN27+BN35-BN41+BN49-BN55+BN63-BN69+BN77-BN83+Inputs!$F$253)
D71: Refinanced (prepaid from bond proceeds) | E71: USD m | G71: =SUM(J71:BN71) | J71: =Time!J47*(J63-J69-J70) | K71: =Time!K47*(K63-K69-K70) | L71: =Time!L47*(L63-L69-L70) | M71: =Time!M47*(M63-M69-M70) | N71: =Time!N47*(N63-N69-N70) | O71: =Time!O47*(O63-O69-O70) | P71: =Time!P47*(P63-P69-P70) | Q71: =Time!Q47*(Q63-Q69-Q70) | ... BN71: =Time!BN47*(BN63-BN69-BN70)
D72: Deferred principal, closing | E72: USD m | J72: =(1-Time!J47)*(J64+J67-J68) | K72: =(1-Time!K47)*(K64+K67-K68) | L72: =(1-Time!L47)*(L64+L67-L68) | M72: =(1-Time!M47)*(M64+M67-M68) | N72: =(1-Time!N47)*(N64+N67-N68) | O72: =(1-Time!O47)*(O64+O67-O68) | P72: =(1-Time!P47)*(P64+P67-P68) | Q72: =(1-Time!Q47)*(Q64+Q67-Q68) | ... BN72: =(1-Time!BN47)*(BN64+BN67-BN68)
D73: Balance after scheduled payment, LDs and refinancing | E73: USD m | J73: =J63-J69-J70-J71 | K73: =K63-K69-K70-K71 | L73: =L63-L69-L70-L71 | M73: =M63-M69-M70-M71 | N73: =N63-N69-N70-N71 | O73: =O63-O69-O70-O71 | P73: =P63-P69-P70-P71 | Q73: =Q63-Q69-Q70-Q71 | ... BN73: =BN63-BN69-BN70-BN71
D74: Cash sweep prepayment | E74: USD m | G74: =SUM(J74:BN74) | J74: =Waterfall!J28*J73/(J31+J45+J59+J73+J87+Inputs!$F$253)+Waterfall!J29 | K74: =Waterfall!K28*K73/(K31+K45+K59+K73+K87+Inputs!$F$253)+Waterfall!K29 | L74: =Waterfall!L28*L73/(L31+L45+L59+L73+L87+Inputs!$F$253)+Waterfall!L29 | M74: =Waterfall!M28*M73/(M31+M45+M59+M73+M87+Inputs!$F$253)+Waterfall!M29 | N74: =Waterfall!N28*N73/(N31+N45+N59+N73+N87+Inputs!$F$253)+Waterfall!N29 | O74: =Waterfall!O28*O73/(O31+O45+O59+O73+O87+Inputs!$F$253)+Waterfall!O29 | P74: =Waterfall!P28*P73/(P31+P45+P59+P73+P87+Inputs!$F$253)+Waterfall!P29 | Q74: =Waterfall!Q28*Q73/(Q31+Q45+Q59+Q73+Q87+Inputs!$F$253)+Waterfall!Q29 | ... BN74: =Waterfall!BN28*BN73/(BN31+BN45+BN59+BN73+BN87+Inputs!$F$253)+Waterfall!BN29
