Workbook

Sheet Cover
A1: Case P: Belanou Combined Cycle Power Project, Republic of Kessara
A2: Case P companion model
A3: Units in column E; constants in column F; row totals in column G; first period in column J. Inputs: blue on yellow. Links from other sheets: green.
D4: Label | E4: Unit | F4: Constant | G4: Total
D5: Companion model for Chapters 39-45. Python mirror: model/case_p.py (source of truth).
D6: Select the scenario on the Inputs sheet (cell named Scenario):
D7: 1: FC base
D8: 2: FC banking
D9: 3: FC downside
D10: 4: Sens: availability -3 points
D11: 5: Sens: heat rate +2%
D12: 6: Sens: fixed opex +10%
D13: 7: Sens: capex +10% funded pro rata
D14: 8: Sens: COD delay 6 months, no LDs
D15: 9: Sens: base rate +200 bps (unhedged)
D16: 10: Sens: KCR devaluation 40%, 90-day lag
... D28: Sign convention: costs stored positive and subtracted explicitly.

Sheet Inputs
A1: Case P: Belanou Combined Cycle Power Project, Republic of Kessara
A2: Inputs: scenario selector, assumptions, contract terms
A3: Units in column E; constants in column F; row totals in column G; first period in column J. Inputs: blue on yellow. Links from other sheets: green.
D4: Label | E4: Unit | F4: Constant | G4: Total
D5: Scenario table: columns J-X = scenarios 1-15; semiannual rows: columns = periods; annual rows: columns = years 2015+ | J5: 2018H2 | K5: 2019H1 | L5: 2019H2 | M5: 2020H1 | N5: 2020H2 | O5: 2021H1 | P5: 2021H2 | Q5: 2022H1 | R5: 2022H2 | S5: 2023H1 | T5: 2023H2 | U5: 2024H1 | V5: 2024H2 | W5: 2025H1 | X5: 2025H2 | Y5: 2026H1 | Z5: 2026H2 | AA5: 2027H1 | AB5: 2027H2 | AC5: 2028H1 | AD5: 2028H2 | AE5: 2029H1 | AF5: 2029H2 | AG5: 2030H1 | AH5: 2030H2 | AI5: 2031H1 | AJ5: 2031H2 | AK5: 2032H1 | AL5: 2032H2 | AM5: 2033H1 | AN5: 2033H2 | AO5: 2034H1 | AP5: 2034H2 | AQ5: 2035H1 | AR5: 2035H2 | AS5: 2036H1 | AT5: 2036H2 | AU5: 2037H1 | AV5: 2037H2 | AW5: 2038H1 | AX5: 2038H2 | AY5: 2039H1 | AZ5: 2039H2 | BA5: 2040H1 | BB5: 2040H2 | BC5: 2041H1 | BD5: 2041H2 | BE5: 2042H1 | BF5: 2042H2 | BG5: 2043H1 | BH5: 2043H2 | BI5: 2044H1 | BJ5: 2044H2 | BK5: 2045H1 | BL5: 2045H2 | BM5: 2046H1 | BN5: 2046H2
B7: Scenario control
D8: Scenario selector (1-15, see table below) | E8: index | F8: 7
B9: Live scenario parameters (selected from the scenario table)
D10: Macro path (1 FC forward, 2 actual history, 3 COD re-forecast) [table] | E10: code | J10: 1 | K10: 1 | L10: 1 | M10: 1 | N10: 1 | O10: 1 | P10: 1 | Q10: 1 | R10: 1 | S10: 1 | T10: 1 | U10: 1 | V10: 1 | W10: 3 | X10: 2
D11: Construction case (1 FC budget, 2 actual) [table] | E11: code | J11: 1 | K11: 1 | L11: 1 | M11: 1 | N11: 1 | O11: 1 | P11: 1 | Q11: 1 | R11: 1 | S11: 1 | T11: 1 | U11: 1 | V11: 1 | W11: 2 | X11: 2
D12: COD delay (sensitivity) [table] | E12: months | J12: 0 | K12: 0 | L12: 0 | M12: 0 | N12: 0 | O12: 0 | P12: 0 | Q12: 6 | R12: 0 | S12: 0 | T12: 0 | U12: 0 | V12: 0 | W12: 0 | X12: 0
D13: Capex factor [table] | E13: factor | J13: 1 | K13: 1 | L13: 1 | M13: 1 | N13: 1 | O13: 1 | P13: 1.1 | Q13: 1 | R13: 1 | S13: 1 | T13: 1 | U13: 1 | V13: 1 | W13: 1 | X13: 1
D14: Availability adjustment [table] | E14: points | J14: 0 | K14: 0 | L14: -6.5 | M14: -3 | N14: 0 | O14: 0 | P14: 0 | Q14: 0 | R14: 0 | S14: 0 | T14: 0 | U14: 0 | V14: 0 | W14: 0 | X14: 0
D15: Dispatch factor when available [table] | E15: % | J15: 76.5 | K15: 72 | L15: 76.5 | M15: 76.5 | N15: 76.5 | O15: 76.5 | P15: 76.5 | Q15: 76.5 | R15: 76.5 | S15: 76.5 | T15: 76.5 | U15: 50 | V15: 76.5 | W15: 76.5 | X15: 76.5
D16: Plant heat rate factor [table] | E16: factor | J16: 1 | K16: 1 | L16: 1.015 | M16: 1 | N16: 1.02 | O16: 1 | P16: 1 | Q16: 1 | R16: 1 | S16: 1 | T16: 1 | U16: 1 | V16: 1 | W16: 1 | X16: 1
D17: Fixed opex factor [table] | E17: factor | J17: 1 | K17: 1 | L17: 1.1 | M17: 1 | N17: 1 | O17: 1.1 | P17: 1 | Q17: 1 | R17: 1 | S17: 1 | T17: 1 | U17: 1 | V17: 1 | W17: 1 | X17: 1
D18: Gas price factor [table] | E18: factor | J18: 1 | K18: 1 | L18: 1 | M18: 1 | N18: 1 | O18: 1 | P18: 1 | Q18: 1 | R18: 1 | S18: 1 | T18: 1 | U18: 1 | V18: 1.3 | W18: 1 | X18: 1
D19: Base rate shift from 2022H1 [table] | E19: % | J19: 0 | K19: 0 | L19: 0 | M19: 0 | N19: 0 | O19: 0 | P19: 0 | Q19: 0 | R19: 2 | S19: 0 | T19: 0 | U19: 0 | V19: 0 | W19: 0 | X19: 0
D20: KCR devaluation from 2022H1 [table] | E20: fraction | J20: 0 | K20: 0 | L20: 0 | M20: 0 | N20: 0 | O20: 0 | P20: 0 | Q20: 0 | R20: 0 | S20: 0.4 | T20: 0 | U20: 0 | V20: 0 | W20: 0 | X20: 0
D21: Extra days on SEKA capacity/VOM payments, 2022H1-2022H2 [table] | E21: days | J21: 0 | K21: 0 | L21: 0 | M21: 0 | N21: 0 | O21: 0 | P21: 0 | Q21: 0 | R21: 0 | S21: 90 | T21: 120 | U21: 0 | V21: 0 | W21: 0 | X21: 0
... D31: Capital charge factor [table] | E31: factor | J31: 1 | K31: 1 | L31: 1 | M31: 1 | N31: 1 | O31: 1 | P31: 1 | Q31: 1 | R31: 1 | S31: 1 | T31: 1 | U31: 1 | V31: 1 | W31: 1 | X31: 1
D32: Macro path (1 FC forward, 2 actual history, 3 COD re-forecast) | E32: code | F32: =INDEX($J$10:$X$10,1,Scenario) -> 1
D33: Construction case (1 FC budget, 2 actual) | E33: code | F33: =INDEX($J$11:$X$11,1,Scenario) -> 1
D34: COD delay (sensitivity) | E34: months | F34: =INDEX($J$12:$X$12,1,Scenario) -> 0
D35: Capex factor | E35: factor | F35: =INDEX($J$13:$X$13,1,Scenario) -> 1.1
D36: Availability adjustment | E36: points | F36: =INDEX($J$14:$X$14,1,Scenario) -> 0
D37: Dispatch factor when available | E37: % | F37: =INDEX($J$15:$X$15,1,Scenario) -> 76.5
D38: Plant heat rate factor | E38: factor | F38: =INDEX($J$16:$X$16,1,Scenario) -> 1
D39: Fixed opex factor | E39: factor | F39: =INDEX($J$17:$X$17,1,Scenario) -> 1
D40: Gas price factor | E40: factor | F40: =INDEX($J$18:$X$18,1,Scenario) -> 1
D41: Base rate shift from 2022H1 | E41: % | F41: =INDEX($J$19:$X$19,1,Scenario) -> 0
D42: KCR devaluation from 2022H1 | E42: fraction | F42: =INDEX($J$20:$X$20,1,Scenario) -> 0
D43: Extra days on SEKA capacity/VOM payments, 2022H1-2022H2 | E43: days | F43: =INDEX($J$21:$X$21,1,Scenario) -> 0
D44: Offtaker crisis events (1 = on) | E44: flag | F44: =INDEX($J$22:$X$22,1,Scenario) -> 0
D45: Insurance market step-up from 2022H2 (1 = on) | E45: flag | F45: =INDEX($J$23:$X$23,1,Scenario) -> 0
D46: Repayment profile (1 FC contract, 2 COD re-sculpted) | E46: code | F46: =INDEX($J$24:$X$24,1,Scenario) -> 1
D47: Performance LD prepayment June 2022 (1 = on) | E47: flag | F47: =INDEX($J$25:$X$25,1,Scenario) -> 0
D48: Waiver and amendment 2023 (1 = on) | E48: flag | F48: =INDEX($J$26:$X$26,1,Scenario) -> 0
D49: 2025 bond refinancing (1 = on) | E49: flag | F49: =INDEX($J$27:$X$27,1,Scenario) -> 0
D50: Funding mode (1 committed amounts, 2 re-grossed pro rata) | E50: code | F50: =INDEX($J$28:$X$28,1,Scenario) -> 2
D51: Soft mini-perm sweep (1 = on) | E51: flag | F51: =INDEX($J$29:$X$29,1,Scenario) -> 1
D52: Shareholder loan share of equity | E52: fraction | F52: =INDEX($J$30:$X$30,1,Scenario) -> 0.8
D53: Capital charge factor | E53: factor | F53: =INDEX($J$31:$X$31,1,Scenario) -> 1
B54: Capital cost (USD m unless stated)
D55: EPC contract price | E55: USD m | F55: 571.84
D56: of which offshore portion | E56: USD m | F56: 489.17
D57: of which onshore portion | E57: USD m | F57: 82.67
D58: Onshore portion fixed in KCR at | E58: KCR/USD | F58: 519.4
D59: Owner's costs | E59: USD m | F59: 46.18
D60: Insurance during construction | E60: USD m | F60: 7.62
D61: Development costs reimbursed at FC | E61: USD m | F61: 21.43
D62: Development fee at FC | E62: USD m | F62: 11.2
D63: Lenders' advisors and legal | E63: USD m | F63: 8.97
D64: Contingency | E64: USD m | F64: 38.4
D65: Initial working capital (spares, fuel) | E65: USD m | F65: 5.35
D66: LNTP paid February 2018 (equity credit at FC) | E66: USD m | F66: 14.2
... D71: Policy rate, FC expectation | E71: % | F71: 13.5
B72: Senior debt terms
D73: ECA-covered tranche share | E73: fraction | F73: 0.3
D74: ABDB A-loan share | E74: fraction | F74: 0.22
D75: ABDB B-loan share | E75: fraction | F75: 0.1
D76: Commercial tranche share | E76: fraction | F76: 0.38
D77: ECA margin | E77: % | F77: 1.35
D78: A-loan margin | E78: % | F78: 3.65
D79: B-loan margin | E79: % | F79: 3.4
D80: Commercial margin to 2025 | E80: % | F80: 4.1
D81: Commercial margin 2026-2029 | E81: % | F81: 4.6
D82: Commercial margin from 2030 | E82: % | F82: 5.1
D83: ECA commitment fee | E83: % pa | F83: 0.45
D84: A-loan commitment fee | E84: % pa | F84: 0.75
... D109: Soft mini-perm sweep share (from 2027) | E109: fraction | F109: 0.5
B110: Contract terms fixed at financial close (from the FC base sizing run)
D111: Senior debt commitment (total, 4 tranches) | E111: USD m | F111: 633.25598
D112: Equity commitment (base, incl. LNTP) | E112: USD m | F112: 221.83377
B113: Plant and PPA
D114: Contracted capacity (FC) | E114: MW | F114: 588.4
D115: Contracted capacity after tests | E115: MW | F115: 581.9
D116: Guaranteed net heat rate | E116: kJ/kWh | F116: 6261
D117: Tested net heat rate | E117: kJ/kWh | F117: 6286
D118: PPA contracted heat rate | E118: kJ/kWh | F118: 6323
D119: Contracted HR degradation allowance | E119: % pa | F119: 0.1
D120: Average part-load penalty | E120: % | F120: 2.3
D121: HHV/LHV ratio | E121: factor | F121: 1.108
D122: kJ per MMBtu | E122: kJ | F122: 1055056
D123: Output degradation, non-recoverable | E123: % pa | F123: 0.15
D124: Output degradation, recoverable average | E124: % | F124: 1
D125: Heat-rate degradation, non-recoverable | E125: % pa | F125: 0.12
... D137: VOM US CPI share | E137: fraction | F137: 0.7
B138: Fuel and transport
D139: GSA gas price 2018 | E139: USD/MMBtu | F139: 5.86
D140: GSA escalation | E140: % pa | F140: 2
D141: Daily contract quantity | E141: MMBtu/d | F141: 72400
D142: Take-or-pay level | E142: fraction | F142: 0.8
D143: GTA reserved capacity | E143: MMBtu/d | F143: 96500
D144: GTA reservation charge 2018 | E144: USD/MMBtu | F144: 0.62
D145: GTA commodity charge 2018 | E145: USD/MMBtu | F145: 0.19
D146: GTA escalation | E146: % pa | F146: 1.5
B147: Operating costs (2018 prices)
D148: O&M fixed fee | E148: USD m pa | F148: 7.92
D149: O&M USD share | E149: fraction | F149: 0.65
...

Sheet Time
A1: Case P: Belanou Combined Cycle Power Project, Republic of Kessara
A2: Time: semiannual operating timeline (monthly timeline on the Construction sheet)
A3: Units in column E; constants in column F; row totals in column G; first period in column J. Inputs: blue on yellow. Links from other sheets: green.
D4: Label | E4: Unit | F4: Constant | G4: Total
D5: Period ending | J5: 2018H2 | K5: 2019H1 | L5: 2019H2 | M5: 2020H1 | N5: 2020H2 | O5: 2021H1 | P5: 2021H2 | Q5: 2022H1 | R5: 2022H2 | S5: 2023H1 | T5: 2023H2 | U5: 2024H1 | V5: 2024H2 | W5: 2025H1 | X5: 2025H2 | Y5: 2026H1 | Z5: 2026H2 | AA5: 2027H1 | AB5: 2027H2 | AC5: 2028H1 | AD5: 2028H2 | AE5: 2029H1 | AF5: 2029H2 | AG5: 2030H1 | AH5: 2030H2 | AI5: 2031H1 | AJ5: 2031H2 | AK5: 2032H1 | AL5: 2032H2 | AM5: 2033H1 | AN5: 2033H2 | AO5: 2034H1 | AP5: 2034H2 | AQ5: 2035H1 | AR5: 2035H2 | AS5: 2036H1 | AT5: 2036H2 | AU5: 2037H1 | AV5: 2037H2 | AW5: 2038H1 | AX5: 2038H2 | AY5: 2039H1 | AZ5: 2039H2 | BA5: 2040H1 | BB5: 2040H2 | BC5: 2041H1 | BD5: 2041H2 | BE5: 2042H1 | BF5: 2042H2 | BG5: 2043H1 | BH5: 2043H2 | BI5: 2044H1 | BJ5: 2044H2 | BK5: 2045H1 | BL5: 2045H2 | BM5: 2046H1 | BN5: 2046H2
B7: Key dates (scenario-dependent)
D8: Commercial operation date | E8: date | F8: =IF(Inputs!$F$33=2,DATE(2021,12,1),EDATE(DATE(2021,5,1),Inputs!$F$34)) -> 44317
D9: PPA expiry | E9: date | F9: =EDATE(Time!$F$8,300)-1 -> 53447
D10: Construction months (NTP to COD) | E10: months | F10: =(YEAR(Time!$F$8)-2018)*12+MONTH(Time!$F$8)-8 -> 33
D11: Period containing COD (period number) | E11: index | F11: =(YEAR(Time!$F$8)-2018)*2+IF(MONTH(Time!$F$8)<=6,0,1) -> 6
D12: First debt service period | E12: index | F12: =Time!$F$11+1 -> 7
D13: Last month of the funding period (month number) | E13: index | F13: =(YEAR(Time!$F$8)-2018)*12+IF(MONTH(Time!$F$8)<=6,6,12)-7 -> 35
D14: Last operating period (period number) | E14: index | F14: =SUMPRODUCT($J$32:$BN$32,$J$17:$BN$17) -> 56
D15: FC FX drift (Kessara 7.5% / US 2.2%) | E15: factor | F15: =1.075/1.022 -> 1.0518591
B16: Semiannual timeline
D17: Period number | E17: index | J17: =1 -> 1 | K17: =2 -> 2 | L17: =3 -> 3 | M17: =4 -> 4 | N17: =5 -> 5 | O17: =6 -> 6 | P17: =7 -> 7 | Q17: =8 -> 8 | R17: =9 -> 9 | S17: =10 -> 10 | T17: =11 -> 11 | U17: =12 -> 12 | V17: =13 -> 13 | W17: =14 -> 14 | X17: =15 -> 15 | Y17: =16 -> 16 | Z17: =17 -> 17 | AA17: =18 -> 18 | AB17: =19 -> 19 | AC17: =20 -> 20 | AD17: =21 -> 21 | AE17: =22 -> 22 | AF17: =23 -> 23 | AG17: =24 -> 24 | AH17: =25 -> 25 | AI17: =26 -> 26 | AJ17: =27 -> 27 | AK17: =28 -> 28 | AL17: =29 -> 29 | AM17: =30 -> 30 | AN17: =31 -> 31 | AO17: =32 -> 32 | AP17: =33 -> 33 | AQ17: =34 -> 34 | AR17: =35 -> 35 | AS17: =36 -> 36 | AT17: =37 -> 37 | AU17: =38 -> 38 | AV17: =39 -> 39 | AW17: =40 -> 40 | AX17: =41 -> 41 | AY17: =42 -> 42 | AZ17: =43 -> 43 | BA17: =44 -> 44 | BB17: =45 -> 45 | BC17: =46 -> 46 | BD17: =47 -> 47 | BE17: =48 -> 48 | BF17: =49 -> 49 | BG17: =50 -> 50 | BH17: =51 -> 51 | BI17: =52 -> 52 | BJ17: =53 -> 53 | BK17: =54 -> 54 | BL17: =55 -> 55 | BM17: =56 -> 56 | BN17: =57 -> 57
D18: Period start | E18: date | J18: =DATE(2018,7,1) -> 43282 | K18: =EDATE(J18,6) -> 43466 | L18: =EDATE(K18,6) -> 43647 | M18: =EDATE(L18,6) -> 43831 | N18: =EDATE(M18,6) -> 44013 | O18: =EDATE(N18,6) -> 44197 | P18: =EDATE(O18,6) -> 44378 | Q18: =EDATE(P18,6) -> 44562 | R18: =EDATE(Q18,6) -> 44743 | ... BN18: =EDATE(BM18,6) -> 53509
D19: Period end | E19: date | J19: =EOMONTH(J18,5) -> 43465 | K19: =EOMONTH(K18,5) -> 43646 | L19: =EOMONTH(L18,5) -> 43830 | M19: =EOMONTH(M18,5) -> 44012 | N19: =EOMONTH(N18,5) -> 44196 | O19: =EOMONTH(O18,5) -> 44377 | P19: =EOMONTH(P18,5) -> 44561 | Q19: =EOMONTH(Q18,5) -> 44742 | ... BN19: =EOMONTH(BN18,5) -> 53692
D20: Days in period | E20: days | J20: =J19-J18+1 -> 184 | K20: =K19-K18+1 -> 181 | L20: =L19-L18+1 -> 184 | M20: =M19-M18+1 -> 182 | N20: =N19-N18+1 -> 184 | O20: =O19-O18+1 -> 181 | P20: =P19-P18+1 -> 184 | Q20: =Q19-Q18+1 -> 181 | ... BN20: =BN19-BN18+1 -> 184
D21: Calendar year | E21: year | J21: =YEAR(J18) -> 2018 | K21: =YEAR(K18) -> 2019 | L21: =YEAR(L18) -> 2019 | M21: =YEAR(M18) -> 2020 | N21: =YEAR(N18) -> 2020 | O21: =YEAR(O18) -> 2021 | P21: =YEAR(P18) -> 2021 | Q21: =YEAR(Q18) -> 2022 | ... BN21: =YEAR(BN18) -> 2046
D22: Half (1 = Jan-Jun) | E22: index | J22: =IF(MONTH(J18)=1,1,2) -> 2 | K22: =IF(MONTH(K18)=1,1,2) -> 1 | L22: =IF(MONTH(L18)=1,1,2) -> 2 | M22: =IF(MONTH(M18)=1,1,2) -> 1 | N22: =IF(MONTH(N18)=1,1,2) -> 2 | O22: =IF(MONTH(O18)=1,1,2) -> 1 | P22: =IF(MONTH(P18)=1,1,2) -> 2 | Q22: =IF(MONTH(Q18)=1,1,2) -> 1 | ... BN22: =IF(MONTH(BN18)=1,1,2) -> 2
D23: Operations start in period | E23: date | J23: =MAX(J18,$F$8) -> 44317 | K23: =MAX(K18,$F$8) -> 44317 | L23: =MAX(L18,$F$8) -> 44317 | M23: =MAX(M18,$F$8) -> 44317 | N23: =MAX(N18,$F$8) -> 44317 | O23: =MAX(O18,$F$8) -> 44317 | P23: =MAX(P18,$F$8) -> 44378 | Q23: =MAX(Q18,$F$8) -> 44562 | ... BN23: =MAX(BN18,$F$8) -> 53509
D24: Operations end in period | E24: date | J24: =MIN(J19,$F$9) -> 43465 | K24: =MIN(K19,$F$9) -> 43646 | L24: =MIN(L19,$F$9) -> 43830 | M24: =MIN(M19,$F$9) -> 44012 | N24: =MIN(N19,$F$9) -> 44196 | O24: =MIN(O19,$F$9) -> 44377 | P24: =MIN(P19,$F$9) -> 44561 | Q24: =MIN(Q19,$F$9) -> 44742 | ... BN24: =MIN(BN19,$F$9) -> 53447
D25: Operating months in period | E25: months | J25: =IF(J24>=J23,(YEAR(J24)-YEAR(J23))*12+MONTH(J24)-MONTH(J23)+1,0) -> 0 | K25: =IF(K24>=K23,(YEAR(K24)-YEAR(K23))*12+MONTH(K24)-MONTH(K23)+1,0) -> 0 | L25: =IF(L24>=L23,(YEAR(L24)-YEAR(L23))*12+MONTH(L24)-MONTH(L23)+1,0) -> 0 | M25: =IF(M24>=M23,(YEAR(M24)-YEAR(M23))*12+MONTH(M24)-MONTH(M23)+1,0) -> 0 | N25: =IF(N24>=N23,(YEAR(N24)-YEAR(N23))*12+MONTH(N24)-MONTH(N23)+1,0) -> 0 | O25: =IF(O24>=O23,(YEAR(O24)-YEAR(O23))*12+MONTH(O24)-MONTH(O23)+1,0) -> 2 | P25: =IF(P24>=P23,(YEAR(P24)-YEAR(P23))*12+MONTH(P24)-MONTH(P23)+1,0) -> 6 | Q25: =IF(Q24>=Q23,(YEAR(Q24)-YEAR(Q23))*12+MONTH(Q24)-MONTH(Q23)+1,0) -> 6 | ... BN25: =IF(BN24>=BN23,(YEAR(BN24)-YEAR(BN23))*12+MONTH(BN24)-MONTH(BN23)+1,0) -> 0
D26: Operating days in period | E26: days | J26: =IF(J24>=J23,J24-J23+1,0) -> 0 | K26: =IF(K24>=K23,K24-K23+1,0) -> 0 | L26: =IF(L24>=L23,L24-L23+1,0) -> 0 | M26: =IF(M24>=M23,M24-M23+1,0) -> 0 | N26: =IF(N24>=N23,N24-N23+1,0) -> 0 | O26: =IF(O24>=O23,O24-O23+1,0) -> 61 | P26: =IF(P24>=P23,P24-P23+1,0) -> 184 | Q26: =IF(Q24>=Q23,Q24-Q23+1,0) -> 181 | ... BN26: =IF(BN24>=BN23,BN24-BN23+1,0) -> 0
D27: Operating months elapsed at period start | E27: months | J27: =MIN(MAX((YEAR(J18)-YEAR($F$8))*12+MONTH(J18)-MONTH($F$8),0),300) -> 0 | K27: =MIN(MAX((YEAR(K18)-YEAR($F$8))*12+MONTH(K18)-MONTH($F$8),0),300) -> 0 | L27: =MIN(MAX((YEAR(L18)-YEAR($F$8))*12+MONTH(L18)-MONTH($F$8),0),300) -> 0 | M27: =MIN(MAX((YEAR(M18)-YEAR($F$8))*12+MONTH(M18)-MONTH($F$8),0),300) -> 0 | N27: =MIN(MAX((YEAR(N18)-YEAR($F$8))*12+MONTH(N18)-MONTH($F$8),0),300) -> 0 | O27: =MIN(MAX((YEAR(O18)-YEAR($F$8))*12+MONTH(O18)-MONTH($F$8),0),300) -> 0 | P27: =MIN(MAX((YEAR(P18)-YEAR($F$8))*12+MONTH(P18)-MONTH($F$8),0),300) -> 2 | Q27: =MIN(MAX((YEAR(Q18)-YEAR($F$8))*12+MONTH(Q18)-MONTH($F$8),0),300) -> 8 | ... BN27: =MIN(MAX((YEAR(BN18)-YEAR($F$8))*12+MONTH(BN18)-MONTH($F$8),0),300) -> 300
D28: Operating months elapsed at period end | E28: months | J28: =J27+J25 -> 0 | K28: =K27+K25 -> 0 | L28: =L27+L25 -> 0 | M28: =M27+M25 -> 0 | N28: =N27+N25 -> 0 | O28: =O27+O25 -> 2 | P28: =P27+P25 -> 8 | Q28: =Q27+Q25 -> 14 | ... BN28: =BN27+BN25 -> 300
D29: Flag_CODPeriod | E29: flag | J29: =IF(J17=$F$11,1,0) -> 0 | K29: =IF(K17=$F$11,1,0) -> 0 | L29: =IF(L17=$F$11,1,0) -> 0 | M29: =IF(M17=$F$11,1,0) -> 0 | N29: =IF(N17=$F$11,1,0) -> 0 | O29: =IF(O17=$F$11,1,0) -> 1 | P29: =IF(P17=$F$11,1,0) -> 0 | Q29: =IF(Q17=$F$11,1,0) -> 0 | ... BN29: =IF(BN17=$F$11,1,0) -> 0
D30: Flag_DebtService (after COD period) | E30: flag | J30: =IF(J17>$F$11,1,0) -> 0 | K30: =IF(K17>$F$11,1,0) -> 0 | L30: =IF(L17>$F$11,1,0) -> 0 | M30: =IF(M17>$F$11,1,0) -> 0 | N30: =IF(N17>$F$11,1,0) -> 0 | O30: =IF(O17>$F$11,1,0) -> 0 | P30: =IF(P17>$F$11,1,0) -> 1 | Q30: =IF(Q17>$F$11,1,0) -> 1 | ... BN30: =IF(BN17>$F$11,1,0) -> 1
D31: Flag_Operations | E31: flag | J31: =IF(J25>0,1,0) -> 0 | K31: =IF(K25>0,1,0) -> 0 | L31: =IF(L25>0,1,0) -> 0 | M31: =IF(M25>0,1,0) -> 0 | N31: =IF(N25>0,1,0) -> 0 | O31: =IF(O25>0,1,0) -> 1 | P31: =IF(P25>0,1,0) -> 1 | Q31: =IF(Q25>0,1,0) -> 1 | ... BN31: =IF(BN25>0,1,0) -> 0
D32: Flag_LastOperatingPeriod | E32: flag | J32: =IF(AND(J25>0,K25=0),1,0) -> 0 | K32: =IF(AND(K25>0,L25=0),1,0) -> 0 | L32: =IF(AND(L25>0,M25=0),1,0) -> 0 | M32: =IF(AND(M25>0,N25=0),1,0) -> 0 | N32: =IF(AND(N25>0,O25=0),1,0) -> 0 | O32: =IF(AND(O25>0,P25=0),1,0) -> 0 | P32: =IF(AND(P25>0,Q25=0),1,0) -> 0 | Q32: =IF(AND(Q25>0,R25=0),1,0) -> 0 | ... BM32: =IF(AND(BM25>0,BN25=0),1,0) -> 1 | BN32: =IF(AND(BN25>0,0=0),1,0) -> 0
D33: Flag_ShockPeriods (2022H1-2022H2) | E33: flag | J33: =IF(AND(J17>=8,J17<=9),1,0) -> 0 | K33: =IF(AND(K17>=8,K17<=9),1,0) -> 0 | L33: =IF(AND(L17>=8,L17<=9),1,0) -> 0 | M33: =IF(AND(M17>=8,M17<=9),1,0) -> 0 | N33: =IF(AND(N17>=8,N17<=9),1,0) -> 0 | O33: =IF(AND(O17>=8,O17<=9),1,0) -> 0 | P33: =IF(AND(P17>=8,P17<=9),1,0) -> 0 | Q33: =IF(AND(Q17>=8,Q17<=9),1,0) -> 1 | ... BN33: =IF(AND(BN17>=8,BN17<=9),1,0) -> 0
D34: Flag from 2022H1 | E34: flag | J34: =IF(J17>=8,1,0) -> 0 | K34: =IF(K17>=8,1,0) -> 0 | L34: =IF(L17>=8,1,0) -> 0 | M34: =IF(M17>=8,1,0) -> 0 | N34: =IF(N17>=8,1,0) -> 0 | O34: =IF(O17>=8,1,0) -> 0 | P34: =IF(P17>=8,1,0) -> 0 | Q34: =IF(Q17>=8,1,0) -> 1 | ... BN34: =IF(BN17>=8,1,0) -> 1

Sheet Construction
A1: Case P: Belanou Combined Cycle Power Project, Republic of Kessara
A2: Construction: monthly uses of funds before financing costs, VAT
A3: Units in column E; constants in column F; row totals in column G; first period in column J. Inputs: blue on yellow. Links from other sheets: green.
D4: Label | E4: Unit | F4: Constant | G4: Total
D5: Month | J5: 2018-08 | K5: 2018-09 | L5: 2018-10 | M5: 2018-11 | N5: 2018-12 | O5: 2019-01 | P5: 2019-02 | Q5: 2019-03 | R5: 2019-04 | S5: 2019-05 | T5: 2019-06 | U5: 2019-07 | V5: 2019-08 | W5: 2019-09 | X5: 2019-10 | Y5: 2019-11 | Z5: 2019-12 | AA5: 2020-01 | AB5: 2020-02 | AC5: 2020-03 | AD5: 2020-04 | AE5: 2020-05 | AF5: 2020-06 | AG5: 2020-07 | AH5: 2020-08 | AI5: 2020-09 | AJ5: 2020-10 | AK5: 2020-11 | AL5: 2020-12 | AM5: 2021-01 | AN5: 2021-02 | AO5: 2021-03 | AP5: 2021-04 | AQ5: 2021-05 | AR5: 2021-06 | AS5: 2021-07 | AT5: 2021-08 | AU5: 2021-09 | AV5: 2021-10 | AW5: 2021-11 | AX5: 2021-12 | AY5: 2022-01 | AZ5: 2022-02 | BA5: 2022-03 | BB5: 2022-04 | BC5: 2022-05 | BD5: 2022-06 | BE5: 2022-07 | BF5: 2022-08 | BG5: 2022-09 | BH5: 2022-10 | BI5: 2022-11 | BJ5: 2022-12
B7: Monthly timeline (column J = August 2018)
D8: Month number | E8: index | J8: =1 -> 1 | K8: =2 -> 2 | L8: =3 -> 3 | M8: =4 -> 4 | N8: =5 -> 5 | O8: =6 -> 6 | P8: =7 -> 7 | Q8: =8 -> 8 | R8: =9 -> 9 | S8: =10 -> 10 | T8: =11 -> 11 | U8: =12 -> 12 | V8: =13 -> 13 | W8: =14 -> 14 | X8: =15 -> 15 | Y8: =16 -> 16 | Z8: =17 -> 17 | AA8: =18 -> 18 | AB8: =19 -> 19 | AC8: =20 -> 20 | AD8: =21 -> 21 | AE8: =22 -> 22 | AF8: =23 -> 23 | AG8: =24 -> 24 | AH8: =25 -> 25 | AI8: =26 -> 26 | AJ8: =27 -> 27 | AK8: =28 -> 28 | AL8: =29 -> 29 | AM8: =30 -> 30 | AN8: =31 -> 31 | AO8: =32 -> 32 | AP8: =33 -> 33 | AQ8: =34 -> 34 | AR8: =35 -> 35 | AS8: =36 -> 36 | AT8: =37 -> 37 | AU8: =38 -> 38 | AV8: =39 -> 39 | AW8: =40 -> 40 | AX8: =41 -> 41 | AY8: =42 -> 42 | AZ8: =43 -> 43 | BA8: =44 -> 44 | BB8: =45 -> 45 | BC8: =46 -> 46 | BD8: =47 -> 47 | BE8: =48 -> 48 | BF8: =49 -> 49 | BG8: =50 -> 50 | BH8: =51 -> 51 | BI8: =52 -> 52 | BJ8: =53 -> 53
D9: Month start | E9: date | J9: =DATE(2018,8,1) -> 43313 | K9: =EDATE(J9,1) -> 43344 | L9: =EDATE(K9,1) -> 43374 | M9: =EDATE(L9,1) -> 43405 | N9: =EDATE(M9,1) -> 43435 | O9: =EDATE(N9,1) -> 43466 | P9: =EDATE(O9,1) -> 43497 | Q9: =EDATE(P9,1) -> 43525 | R9: =EDATE(Q9,1) -> 43556 | ... BJ9: =EDATE(BI9,1) -> 44896
D10: Month end | E10: date | J10: =EOMONTH(J9,0) -> 43343 | K10: =EOMONTH(K9,0) -> 43373 | L10: =EOMONTH(L9,0) -> 43404 | M10: =EOMONTH(M9,0) -> 43434 | N10: =EOMONTH(N9,0) -> 43465 | O10: =EOMONTH(O9,0) -> 43496 | P10: =EOMONTH(P9,0) -> 43524 | Q10: =EOMONTH(Q9,0) -> 43555 | ... BJ10: =EOMONTH(BJ9,0) -> 44926
D11: Days | E11: days | J11: =J10-J9+1 -> 31 | K11: =K10-K9+1 -> 30 | L11: =L10-L9+1 -> 31 | M11: =M10-M9+1 -> 30 | N11: =N10-N9+1 -> 31 | O11: =O10-O9+1 -> 31 | P11: =P10-P9+1 -> 28 | Q11: =Q10-Q9+1 -> 31 | ... BJ11: =BJ10-BJ9+1 -> 31
D12: Semiannual period number | E12: index | J12: =(YEAR(J9)-2018)*2+IF(MONTH(J9)<=6,0,1) -> 1 | K12: =(YEAR(K9)-2018)*2+IF(MONTH(K9)<=6,0,1) -> 1 | L12: =(YEAR(L9)-2018)*2+IF(MONTH(L9)<=6,0,1) -> 1 | M12: =(YEAR(M9)-2018)*2+IF(MONTH(M9)<=6,0,1) -> 1 | N12: =(YEAR(N9)-2018)*2+IF(MONTH(N9)<=6,0,1) -> 1 | O12: =(YEAR(O9)-2018)*2+IF(MONTH(O9)<=6,0,1) -> 2 | P12: =(YEAR(P9)-2018)*2+IF(MONTH(P9)<=6,0,1) -> 2 | Q12: =(YEAR(Q9)-2018)*2+IF(MONTH(Q9)<=6,0,1) -> 2 | ... BJ12: =(YEAR(BJ9)-2018)*2+IF(MONTH(BJ9)<=6,0,1) -> 9
D13: Flag_Construction (before COD) | E13: flag | J13: =IF(J8<=Time!$F$10,1,0) -> 1 | K13: =IF(K8<=Time!$F$10,1,0) -> 1 | L13: =IF(L8<=Time!$F$10,1,0) -> 1 | M13: =IF(M8<=Time!$F$10,1,0) -> 1 | N13: =IF(N8<=Time!$F$10,1,0) -> 1 | O13: =IF(O8<=Time!$F$10,1,0) -> 1 | P13: =IF(P8<=Time!$F$10,1,0) -> 1 | Q13: =IF(Q8<=Time!$F$10,1,0) -> 1 | ... BJ13: =IF(BJ8<=Time!$F$10,1,0) -> 0
D14: Flag_FundingPeriod (to end of COD period) | E14: flag | J14: =IF(J8<=Time!$F$13,1,0) -> 1 | K14: =IF(K8<=Time!$F$13,1,0) -> 1 | L14: =IF(L8<=Time!$F$13,1,0) -> 1 | M14: =IF(M8<=Time!$F$13,1,0) -> 1 | N14: =IF(N8<=Time!$F$13,1,0) -> 1 | O14: =IF(O8<=Time!$F$13,1,0) -> 1 | P14: =IF(P8<=Time!$F$13,1,0) -> 1 | Q14: =IF(Q8<=Time!$F$13,1,0) -> 1 | ... BJ14: =IF(BJ8<=Time!$F$13,1,0) -> 0
D15: Flag_CODMonth | E15: flag | J15: =IF(J8=Time!$F$10+1,1,0) -> 0 | K15: =IF(K8=Time!$F$10+1,1,0) -> 0 | L15: =IF(L8=Time!$F$10+1,1,0) -> 0 | M15: =IF(M8=Time!$F$10+1,1,0) -> 0 | N15: =IF(N8=Time!$F$10+1,1,0) -> 0 | O15: =IF(O8=Time!$F$10+1,1,0) -> 0 | P15: =IF(P8=Time!$F$10+1,1,0) -> 0 | Q15: =IF(Q8=Time!$F$10+1,1,0) -> 0 | ... BJ15: =IF(BJ8=Time!$F$10+1,1,0) -> 0
D16: KCR per USD | E16: KCR/USD | J16: =IF(Inputs!$F$32=1,Inputs!$F$58*Time!$F$15^((J8-0.5)/12),INDEX(Operations!$J$11:$BN$11,1,J12)) -> 520.49534 | K16: =IF(Inputs!$F$32=1,Inputs!$F$58*Time!$F$15^((K8-0.5)/12),INDEX(Operations!$J$11:$BN$11,1,K12)) -> 522.69295 | L16: =IF(Inputs!$F$32=1,Inputs!$F$58*Time!$F$15^((L8-0.5)/12),INDEX(Operations!$J$11:$BN$11,1,L12)) -> 524.89984 | M16: =IF(Inputs!$F$32=1,Inputs!$F$58*Time!$F$15^((M8-0.5)/12),INDEX(Operations!$J$11:$BN$11,1,M12)) -> 527.11605 | N16: =IF(Inputs!$F$32=1,Inputs!$F$58*Time!$F$15^((N8-0.5)/12),INDEX(Operations!$J$11:$BN$11,1,N12)) -> 529.34161 | O16: =IF(Inputs!$F$32=1,Inputs!$F$58*Time!$F$15^((O8-0.5)/12),INDEX(Operations!$J$11:$BN$11,1,O12)) -> 531.57657 | P16: =IF(Inputs!$F$32=1,Inputs!$F$58*Time!$F$15^((P8-0.5)/12),INDEX(Operations!$J$11:$BN$11,1,P12)) -> 533.82097 | Q16: =IF(Inputs!$F$32=1,Inputs!$F$58*Time!$F$15^((Q8-0.5)/12),INDEX(Operations!$J$11:$BN$11,1,Q12)) -> 536.07484 | ... BJ16: =IF(Inputs!$F$32=1,Inputs!$F$58*Time!$F$15^((BJ8-0.5)/12),INDEX(Operations!$J$11:$BN$11,1,BJ12)) -> 647.98702
D17: Base rate (6M fixing for the half-year) | E17: % | J17: =INDEX(Operations!$J$8:$BN$8,1,J12) -> 2.52 | K17: =INDEX(Operations!$J$8:$BN$8,1,K12) -> 2.52 | L17: =INDEX(Operations!$J$8:$BN$8,1,L12) -> 2.52 | M17: =INDEX(Operations!$J$8:$BN$8,1,M12) -> 2.52 | N17: =INDEX(Operations!$J$8:$BN$8,1,N12) -> 2.52 | O17: =INDEX(Operations!$J$8:$BN$8,1,O12) -> 2.79 | P17: =INDEX(Operations!$J$8:$BN$8,1,P12) -> 2.79 | Q17: =INDEX(Operations!$J$8:$BN$8,1,Q12) -> 2.79 | ... BJ17: =INDEX(Operations!$J$8:$BN$8,1,BJ12) -> 3.11
D18: Kessara policy rate | E18: % | J18: =IF(Inputs!$F$32=1,Inputs!$F$71,INDEX(Inputs!$J$210:$AR$210,1,YEAR(J9)-2014)) -> 13.5 | K18: =IF(Inputs!$F$32=1,Inputs!$F$71,INDEX(Inputs!$J$210:$AR$210,1,YEAR(K9)-2014)) -> 13.5 | L18: =IF(Inputs!$F$32=1,Inputs!$F$71,INDEX(Inputs!$J$210:$AR$210,1,YEAR(L9)-2014)) -> 13.5 | M18: =IF(Inputs!$F$32=1,Inputs!$F$71,INDEX(Inputs!$J$210:$AR$210,1,YEAR(M9)-2014)) -> 13.5 | N18: =IF(Inputs!$F$32=1,Inputs!$F$71,INDEX(Inputs!$J$210:$AR$210,1,YEAR(N9)-2014)) -> 13.5 | O18: =IF(Inputs!$F$32=1,Inputs!$F$71,INDEX(Inputs!$J$210:$AR$210,1,YEAR(O9)-2014)) -> 13.5 | P18: =IF(Inputs!$F$32=1,Inputs!$F$71,INDEX(Inputs!$J$210:$AR$210,1,YEAR(P9)-2014)) -> 13.5 | Q18: =IF(Inputs!$F$32=1,Inputs!$F$71,INDEX(Inputs!$J$210:$AR$210,1,YEAR(Q9)-2014)) -> 13.5 | ... BJ18: =IF(Inputs!$F$32=1,Inputs!$F$71,INDEX(Inputs!$J$210:$AR$210,1,YEAR(BJ9)-2014)) -> 13.5
B19: Uses before financing costs (USD m)
D20: EPC payment profile, selected | E20: % | J20: =IF(Inputs!$F$33=2,Inputs!J226,Inputs!J225+IF(Inputs!$F$34>0,IF(J8=33,-7.5,0)+IF(J8=33+Inputs!$F$34,7.5,0),0)) -> 10 | K20: =IF(Inputs!$F$33=2,Inputs!K226,Inputs!K225+IF(Inputs!$F$34>0,IF(K8=33,-7.5,0)+IF(K8=33+Inputs!$F$34,7.5,0),0)) -> 0.0108 | L20: =IF(Inputs!$F$33=2,Inputs!L226,Inputs!L225+IF(Inputs!$F$34>0,IF(L8=33,-7.5,0)+IF(L8=33+Inputs!$F$34,7.5,0),0)) -> 0.1133 | M20: =IF(Inputs!$F$33=2,Inputs!M226,Inputs!M225+IF(Inputs!$F$34>0,IF(M8=33,-7.5,0)+IF(M8=33+Inputs!$F$34,7.5,0),0)) -> 0.3239 | N20: =IF(Inputs!$F$33=2,Inputs!N226,Inputs!N225+IF(Inputs!$F$34>0,IF(N8=33,-7.5,0)+IF(N8=33+Inputs!$F$34,7.5,0),0)) -> 0.6294 | O20: =IF(Inputs!$F$33=2,Inputs!O226,Inputs!O225+IF(Inputs!$F$34>0,IF(O8=33,-7.5,0)+IF(O8=33+Inputs!$F$34,7.5,0),0)) -> 1.0114 | P20: =IF(Inputs!$F$33=2,Inputs!P226,Inputs!P225+IF(Inputs!$F$34>0,IF(P8=33,-7.5,0)+IF(P8=33+Inputs!$F$34,7.5,0),0)) -> 1.4496 | Q20: =IF(Inputs!$F$33=2,Inputs!Q226,Inputs!Q225+IF(Inputs!$F$34>0,IF(Q8=33,-7.5,0)+IF(Q8=33+Inputs!$F$34,7.5,0),0)) -> 1.9236 | ... BJ20: =IF(Inputs!$F$33=2,Inputs!BJ226,Inputs!BJ225+IF(Inputs!$F$34>0,IF(BJ8=33,-7.5,0)+IF(BJ8=33+Inputs!$F$34,7.5,0),0)) -> 0
D21: EPC progress payments for contingency (FC) | E21: % | J21: =IF(J8=1,0,J20)-IF(J8=Time!$F$10,7.5,0) -> 0 | K21: =IF(K8=1,0,K20)-IF(K8=Time!$F$10,7.5,0) -> 0.0108 | L21: =IF(L8=1,0,L20)-IF(L8=Time!$F$10,7.5,0) -> 0.1133 | M21: =IF(M8=1,0,M20)-IF(M8=Time!$F$10,7.5,0) -> 0.3239 | N21: =IF(N8=1,0,N20)-IF(N8=Time!$F$10,7.5,0) -> 0.6294 | O21: =IF(O8=1,0,O20)-IF(O8=Time!$F$10,7.5,0) -> 1.0114 | P21: =IF(P8=1,0,P20)-IF(P8=Time!$F$10,7.5,0) -> 1.4496 | Q21: =IF(Q8=1,0,Q20)-IF(Q8=Time!$F$10,7.5,0) -> 1.9236 | ... BJ21: =IF(BJ8=1,0,BJ20)-IF(BJ8=Time!$F$10,7.5,0) -> 0
D22: EPC payments | E22: USD m | G22: =SUM(J22:BJ22) -> 629.024 | J22: =IF(Inputs!$F$33=2,J20/100*Inputs!$F$56+J20/100*Inputs!$F$57*Inputs!$F$58/J16,Inputs!$F$55*Inputs!$F$35*J20/100) -> 62.9024 | K22: =IF(Inputs!$F$33=2,K20/100*Inputs!$F$56+K20/100*Inputs!$F$57*Inputs!$F$58/K16,Inputs!$F$55*Inputs!$F$35*K20/100) -> 0.067934592 | L22: =IF(Inputs!$F$33=2,L20/100*Inputs!$F$56+L20/100*Inputs!$F$57*Inputs!$F$58/L16,Inputs!$F$55*Inputs!$F$35*L20/100) -> 0.71268419 | M22: =IF(Inputs!$F$33=2,M20/100*Inputs!$F$56+M20/100*Inputs!$F$57*Inputs!$F$58/M16,Inputs!$F$55*Inputs!$F$35*M20/100) -> 2.0374087 | N22: =IF(Inputs!$F$33=2,N20/100*Inputs!$F$56+N20/100*Inputs!$F$57*Inputs!$F$58/N16,Inputs!$F$55*Inputs!$F$35*N20/100) -> 3.9590771 | O22: =IF(Inputs!$F$33=2,O20/100*Inputs!$F$56+O20/100*Inputs!$F$57*Inputs!$F$58/O16,Inputs!$F$55*Inputs!$F$35*O20/100) -> 6.3619487 | P22: =IF(Inputs!$F$33=2,P20/100*Inputs!$F$56+P20/100*Inputs!$F$57*Inputs!$F$58/P16,Inputs!$F$55*Inputs!$F$35*P20/100) -> 9.1183319 | Q22: =IF(Inputs!$F$33=2,Q20/100*Inputs!$F$56+Q20/100*Inputs!$F$57*Inputs!$F$58/Q16,Inputs!$F$55*Inputs!$F$35*Q20/100) -> 12.099906 | ... BJ22: =IF(Inputs!$F$33=2,BJ20/100*Inputs!$F$56+BJ20/100*Inputs!$F$57*Inputs!$F$58/BJ16,Inputs!$F$55*Inputs!$F$35*BJ20/100) -> 0
D23: Owner's costs | E23: USD m | G23: =SUM(J23:BJ23) -> 50.798 | J23: =Inputs!$F$59*IF(Inputs!$F$33=1,Inputs!$F$35,1)*(Inputs!J227+IF(AND(Inputs!$F$33=1,J8>33,J8<=Time!$F$10),2.75,0))/100+IF(AND(Inputs!$F$33=2,J8>=34,J8<=40),Inputs!$F$67/7,0) -> 6.09576 | K23: =Inputs!$F$59*IF(Inputs!$F$33=1,Inputs!$F$35,1)*(Inputs!K227+IF(AND(Inputs!$F$33=1,K8>33,K8<=Time!$F$10),2.75,0))/100+IF(AND(Inputs!$F$33=2,K8>=34,K8<=40),Inputs!$F$67/7,0) -> 1.396945 | L23: =Inputs!$F$59*IF(Inputs!$F$33=1,Inputs!$F$35,1)*(Inputs!L227+IF(AND(Inputs!$F$33=1,L8>33,L8<=Time!$F$10),2.75,0))/100+IF(AND(Inputs!$F$33=2,L8>=34,L8<=40),Inputs!$F$67/7,0) -> 1.396945 | M23: =Inputs!$F$59*IF(Inputs!$F$33=1,Inputs!$F$35,1)*(Inputs!M227+IF(AND(Inputs!$F$33=1,M8>33,M8<=Time!$F$10),2.75,0))/100+IF(AND(Inputs!$F$33=2,M8>=34,M8<=40),Inputs!$F$67/7,0) -> 1.396945 | N23: =Inputs!$F$59*IF(Inputs!$F$33=1,Inputs!$F$35,1)*(Inputs!N227+IF(AND(Inputs!$F$33=1,N8>33,N8<=Time!$F$10),2.75,0))/100+IF(AND(Inputs!$F$33=2,N8>=34,N8<=40),Inputs!$F$67/7,0) -> 1.396945 | O23: =Inputs!$F$59*IF(Inputs!$F$33=1,Inputs!$F$35,1)*(Inputs!O227+IF(AND(Inputs!$F$33=1,O8>33,O8<=Time!$F$10),2.75,0))/100+IF(AND(Inputs!$F$33=2,O8>=34,O8<=40),Inputs!$F$67/7,0) -> 1.396945 | P23: =Inputs!$F$59*IF(Inputs!$F$33=1,Inputs!$F$35,1)*(Inputs!P227+IF(AND(Inputs!$F$33=1,P8>33,P8<=Time!$F$10),2.75,0))/100+IF(AND(Inputs!$F$33=2,P8>=34,P8<=40),Inputs!$F$67/7,0) -> 1.396945 | Q23: =Inputs!$F$59*IF(Inputs!$F$33=1,Inputs!$F$35,1)*(Inputs!Q227+IF(AND(Inputs!$F$33=1,Q8>33,Q8<=Time!$F$10),2.75,0))/100+IF(AND(Inputs!$F$33=2,Q8>=34,Q8<=40),Inputs!$F$67/7,0) -> 1.396945 | ... BJ23: =Inputs!$F$59*IF(Inputs!$F$33=1,Inputs!$F$35,1)*(Inputs!BJ227+IF(AND(Inputs!$F$33=1,BJ8>33,BJ8<=Time!$F$10),2.75,0))/100+IF(AND(Inputs!$F$33=2,BJ8>=34,BJ8<=40),Inputs!$F$67/7,0) -> 0
D24: Insurance during construction | E24: USD m | G24: =SUM(J24:BJ24) -> 8.382 | J24: =Inputs!$F$60*Inputs!$F$35*(0.85*IF(J8=1,1,0)+0.15*IF(J8=18,1,0)) -> 7.1247 | K24: =Inputs!$F$60*Inputs!$F$35*(0.85*IF(K8=1,1,0)+0.15*IF(K8=18,1,0)) -> 0 | L24: =Inputs!$F$60*Inputs!$F$35*(0.85*IF(L8=1,1,0)+0.15*IF(L8=18,1,0)) -> 0 | M24: =Inputs!$F$60*Inputs!$F$35*(0.85*IF(M8=1,1,0)+0.15*IF(M8=18,1,0)) -> 0 | N24: =Inputs!$F$60*Inputs!$F$35*(0.85*IF(N8=1,1,0)+0.15*IF(N8=18,1,0)) -> 0 | O24: =Inputs!$F$60*Inputs!$F$35*(0.85*IF(O8=1,1,0)+0.15*IF(O8=18,1,0)) -> 0 | P24: =Inputs!$F$60*Inputs!$F$35*(0.85*IF(P8=1,1,0)+0.15*IF(P8=18,1,0)) -> 0 | Q24: =Inputs!$F$60*Inputs!$F$35*(0.85*IF(Q8=1,1,0)+0.15*IF(Q8=18,1,0)) -> 0 | ... BJ24: =Inputs!$F$60*Inputs!$F$35*(0.85*IF(BJ8=1,1,0)+0.15*IF(BJ8=18,1,0)) -> 0
D25: Development costs and fee | E25: USD m | G25: =SUM(J25:BJ25) -> 32.63 | J25: =IF(J8=1,Inputs!$F$61+Inputs!$F$62,0) -> 32.63 | K25: =IF(K8=1,Inputs!$F$61+Inputs!$F$62,0) -> 0 | L25: =IF(L8=1,Inputs!$F$61+Inputs!$F$62,0) -> 0 | M25: =IF(M8=1,Inputs!$F$61+Inputs!$F$62,0) -> 0 | N25: =IF(N8=1,Inputs!$F$61+Inputs!$F$62,0) -> 0 | O25: =IF(O8=1,Inputs!$F$61+Inputs!$F$62,0) -> 0 | P25: =IF(P8=1,Inputs!$F$61+Inputs!$F$62,0) -> 0 | Q25: =IF(Q8=1,Inputs!$F$61+Inputs!$F$62,0) -> 0 | ... BJ25: =IF(BJ8=1,Inputs!$F$61+Inputs!$F$62,0) -> 0
D26: Lenders' advisors and legal | E26: USD m | G26: =SUM(J26:BJ26) -> 9.867 | J26: =Inputs!$F$63*Inputs!$F$35*(0.7*IF(J8=1,1,0)+0.3/(Time!$F$10-1)*IF(AND(J8>=2,J8<=Time!$F$10),1,0)) -> 6.9069 | K26: =Inputs!$F$63*Inputs!$F$35*(0.7*IF(K8=1,1,0)+0.3/(Time!$F$10-1)*IF(AND(K8>=2,K8<=Time!$F$10),1,0)) -> 0.092503125 | L26: =Inputs!$F$63*Inputs!$F$35*(0.7*IF(L8=1,1,0)+0.3/(Time!$F$10-1)*IF(AND(L8>=2,L8<=Time!$F$10),1,0)) -> 0.092503125 | M26: =Inputs!$F$63*Inputs!$F$35*(0.7*IF(M8=1,1,0)+0.3/(Time!$F$10-1)*IF(AND(M8>=2,M8<=Time!$F$10),1,0)) -> 0.092503125 | N26: =Inputs!$F$63*Inputs!$F$35*(0.7*IF(N8=1,1,0)+0.3/(Time!$F$10-1)*IF(AND(N8>=2,N8<=Time!$F$10),1,0)) -> 0.092503125 | O26: =Inputs!$F$63*Inputs!$F$35*(0.7*IF(O8=1,1,0)+0.3/(Time!$F$10-1)*IF(AND(O8>=2,O8<=Time!$F$10),1,0)) -> 0.092503125 | P26: =Inputs!$F$63*Inputs!$F$35*(0.7*IF(P8=1,1,0)+0.3/(Time!$F$10-1)*IF(AND(P8>=2,P8<=Time!$F$10),1,0)) -> 0.092503125 | Q26: =Inputs!$F$63*Inputs!$F$35*(0.7*IF(Q8=1,1,0)+0.3/(Time!$F$10-1)*IF(AND(Q8>=2,Q8<=Time!$F$10),1,0)) -> 0.092503125 | ... BJ26: =Inputs!$F$63*Inputs!$F$35*(0.7*IF(BJ8=1,1,0)+0.3/(Time!$F$10-1)*IF(AND(BJ8>=2,BJ8<=Time!$F$10),1,0)) -> 0
D27: Contingency (FC: pro rata with EPC progress payments) | E27: USD m | G27: =SUM(J27:BJ27) -> 42.24 | J27: =IF(Inputs!$F$33=1,Inputs!$F$64*Inputs!$F$35*J21/SUM($J$21:$BJ$21),0) -> 0 | K27: =IF(Inputs!$F$33=1,Inputs!$F$64*Inputs!$F$35*K21/SUM($J$21:$BJ$21),0) -> 0.0055296 | L27: =IF(Inputs!$F$33=1,Inputs!$F$64*Inputs!$F$35*L21/SUM($J$21:$BJ$21),0) -> 0.0580096 | M27: =IF(Inputs!$F$33=1,Inputs!$F$64*Inputs!$F$35*M21/SUM($J$21:$BJ$21),0) -> 0.1658368 | N27: =IF(Inputs!$F$33=1,Inputs!$F$64*Inputs!$F$35*N21/SUM($J$21:$BJ$21),0) -> 0.3222528 | O27: =IF(Inputs!$F$33=1,Inputs!$F$64*Inputs!$F$35*O21/SUM($J$21:$BJ$21),0) -> 0.5178368 | P27: =IF(Inputs!$F$33=1,Inputs!$F$64*Inputs!$F$35*P21/SUM($J$21:$BJ$21),0) -> 0.7421952 | Q27: =IF(Inputs!$F$33=1,Inputs!$F$64*Inputs!$F$35*Q21/SUM($J$21:$BJ$21),0) -> 0.9848832 | ... BJ27: =IF(Inputs!$F$33=1,Inputs!$F$64*Inputs!$F$35*BJ21/SUM($J$21:$BJ$21),0) -> 0
D28: Initial working capital | E28: USD m | G28: =SUM(J28:BJ28) -> 5.885 | J28: =IF(J8=Time!$F$10,Inputs!$F$65*Inputs!$F$35,0) -> 0 | K28: =IF(K8=Time!$F$10,Inputs!$F$65*Inputs!$F$35,0) -> 0 | L28: =IF(L8=Time!$F$10,Inputs!$F$65*Inputs!$F$35,0) -> 0 | M28: =IF(M8=Time!$F$10,Inputs!$F$65*Inputs!$F$35,0) -> 0 | N28: =IF(N8=Time!$F$10,Inputs!$F$65*Inputs!$F$35,0) -> 0 | O28: =IF(O8=Time!$F$10,Inputs!$F$65*Inputs!$F$35,0) -> 0 | P28: =IF(P8=Time!$F$10,Inputs!$F$65*Inputs!$F$35,0) -> 0 | Q28: =IF(Q8=Time!$F$10,Inputs!$F$65*Inputs!$F$35,0) -> 0 | ... BJ28: =IF(BJ8=Time!$F$10,Inputs!$F$65*Inputs!$F$35,0) -> 0
D29: Overrun items (actual) | E29: USD m | G29: =SUM(J29:BJ29) -> 0 | J29: =IF(Inputs!$F$33=2,Inputs!J228,0) -> 0 | K29: =IF(Inputs!$F$33=2,Inputs!K228,0) -> 0 | L29: =IF(Inputs!$F$33=2,Inputs!L228,0) -> 0 | M29: =IF(Inputs!$F$33=2,Inputs!M228,0) -> 0 | N29: =IF(Inputs!$F$33=2,Inputs!N228,0) -> 0 | O29: =IF(Inputs!$F$33=2,Inputs!O228,0) -> 0 | P29: =IF(Inputs!$F$33=2,Inputs!P228,0) -> 0 | Q29: =IF(Inputs!$F$33=2,Inputs!Q228,0) -> 0 | ... BJ29: =IF(Inputs!$F$33=2,Inputs!BJ228,0) -> 0
D30: Uses before financing costs | E30: USD m | G30: =SUM(J30:BJ30) -> 778.826 | J30: =J22+J23+J24+J25+J26+J27+J28+J29 -> 115.65976 | K30: =K22+K23+K24+K25+K26+K27+K28+K29 -> 1.5629123 | L30: =L22+L23+L24+L25+L26+L27+L28+L29 -> 2.2601419 | M30: =M22+M23+M24+M25+M26+M27+M28+M29 -> 3.6926937 | N30: =N22+N23+N24+N25+N26+N27+N28+N29 -> 5.770778 | O30: =O22+O23+O24+O25+O26+O27+O28+O29 -> 8.3692337 | P30: =P22+P23+P24+P25+P26+P27+P28+P29 -> 11.349975 | Q30: =Q22+Q23+Q24+Q25+Q26+Q27+Q28+Q29 -> 14.574237 | ... BJ30: =BJ22+BJ23+BJ24+BJ25+BJ26+BJ27+BJ28+BJ29 -> 0
B31: VAT on onshore EPC (KCR m) and UBK VAT facility
D32: Onshore EPC payments | E32: KCR m | G32: =SUM(J32:BJ32) -> 47232.678 | J32: =J20/100*Inputs!$F$57*Inputs!$F$58*Inputs!$F$35 -> 4723.2678 | K32: =K20/100*Inputs!$F$57*Inputs!$F$58*Inputs!$F$35 -> 5.1011292 | L32: =L20/100*Inputs!$F$57*Inputs!$F$58*Inputs!$F$35 -> 53.514624 | M32: =M20/100*Inputs!$F$57*Inputs!$F$58*Inputs!$F$35 -> 152.98664 | N32: =N20/100*Inputs!$F$57*Inputs!$F$58*Inputs!$F$35 -> 297.28247 | O32: =O20/100*Inputs!$F$57*Inputs!$F$58*Inputs!$F$35 -> 477.7113 | P32: =P20/100*Inputs!$F$57*Inputs!$F$58*Inputs!$F$35 -> 684.6849 | Q32: =Q20/100*Inputs!$F$57*Inputs!$F$58*Inputs!$F$35 -> 908.56779 | ... BJ32: =BJ20/100*Inputs!$F$57*Inputs!$F$58*Inputs!$F$35 -> 0
D33: VAT paid (drawn on the VAT facility) | E33: KCR m | G33: =SUM(J33:BJ33) -> 8501.882 | J33: =Inputs!$F$68/100*J32 -> 850.1882 | K33: =Inputs!$F$68/100*K32 -> 0.91820326 | L33: =Inputs!$F$68/100*L32 -> 9.6326323 | M33: =Inputs!$F$68/100*M32 -> 27.537596 | N33: =Inputs!$F$68/100*N32 -> 53.510845 | O33: =Inputs!$F$68/100*O32 -> 85.988035 | P33: =Inputs!$F$68/100*P32 -> 123.24328 | Q33: =Inputs!$F$68/100*Q32 -> 163.5422 | ... BJ33: =Inputs!$F$68/100*BJ32 -> 0
D34: VAT refunds (9-month lag) repaying the facility | E34: KCR m | G34: =SUM(J34:BJ34) -> 8501.882 | J34: =0 -> 0 | K34: =0 -> 0 | L34: =0 -> 0 | M34: =0 -> 0 | N34: =0 -> 0 | O34: =0 -> 0 | P34: =0 -> 0 | Q34: =0 -> 0 | R34: =0 -> 0 | S34: =J33 -> 850.1882 | T34: =K33 -> 0.91820326 | U34: =L33 -> 9.6326323 | V34: =M33 -> 27.537596 | W34: =N33 -> 53.510845 | X34: =O33 -> 85.988035 | Y34: =P33 -> 123.24328 | Z34: =Q33 -> 163.5422 | ... BJ34: =BA33 -> 0
D35: VAT facility balance | E35: KCR m | J35: =0+J33-J34 -> 850.1882 | K35: =J35+K33-K34 -> 851.1064 | L35: =K35+L33-L34 -> 860.73904 | M35: =L35+M33-M34 -> 888.27663 | N35: =M35+N33-N34 -> 941.78748 | O35: =N35+O33-O34 -> 1027.7755 | P35: =O35+P33-P34 -> 1151.0188 | Q35: =P35+Q33-Q34 -> 1314.561 | R35: =Q35+R33-R34 -> 1519.7369 | ... BJ35: =BI35+BJ33-BJ34 -> 0
D36: VAT facility interest | E36: USD m | G36: =SUM(J36:BJ36) -> 1.7983538 | J36: =0*(J18+Inputs!$F$69)/100*J11/365/J16 -> 0 | K36: =J35*(K18+Inputs!$F$69)/100*K11/365/K16 -> 0.021390297 | L36: =K35*(L18+Inputs!$F$69)/100*L11/365/L16 -> 0.022034146 | M36: =L35*(M18+Inputs!$F$69)/100*M11/365/M16 -> 0.021474034 | N36: =M35*(N18+Inputs!$F$69)/100*N11/365/N16 -> 0.022803474 | O36: =N35*(O18+Inputs!$F$69)/100*O11/365/O16 -> 0.024075532 | P36: =O35*(P18+Inputs!$F$69)/100*P11/365/P16 -> 0.023631309 | Q36: =P35*(Q18+Inputs!$F$69)/100*Q11/365/Q16 -> 0.029177347 | R36: =Q35*(R18+Inputs!$F$69)/100*R11/365/R16 -> 0.032112483 | ... BJ36: =BI35*(BJ18+Inputs!$F$69)/100*BJ11/365/BJ16 -> 0

Sheet Operations
A1: Case P: Belanou Combined Cycle Power Project, Republic of Kessara
A2: Operations: macro paths, plant, revenue, operating costs, working capital
A3: Units in column E; constants in column F; row totals in column G; first period in column J. Inputs: blue on yellow. Links from other sheets: green.
D4: Label | E4: Unit | F4: Constant | G4: Total
D5: Period ending | J5: 2018H2 | K5: 2019H1 | L5: 2019H2 | M5: 2020H1 | N5: 2020H2 | O5: 2021H1 | P5: 2021H2 | Q5: 2022H1 | R5: 2022H2 | S5: 2023H1 | T5: 2023H2 | U5: 2024H1 | V5: 2024H2 | W5: 2025H1 | X5: 2025H2 | Y5: 2026H1 | Z5: 2026H2 | AA5: 2027H1 | AB5: 2027H2 | AC5: 2028H1 | AD5: 2028H2 | AE5: 2029H1 | AF5: 2029H2 | AG5: 2030H1 | AH5: 2030H2 | AI5: 2031H1 | AJ5: 2031H2 | AK5: 2032H1 | AL5: 2032H2 | AM5: 2033H1 | AN5: 2033H2 | AO5: 2034H1 | AP5: 2034H2 | AQ5: 2035H1 | AR5: 2035H2 | AS5: 2036H1 | AT5: 2036H2 | AU5: 2037H1 | AV5: 2037H2 | AW5: 2038H1 | AX5: 2038H2 | AY5: 2039H1 | AZ5: 2039H2 | BA5: 2040H1 | BB5: 2040H2 | BC5: 2041H1 | BD5: 2041H2 | BE5: 2042H1 | BF5: 2042H2 | BG5: 2043H1 | BH5: 2043H2 | BI5: 2044H1 | BJ5: 2044H2 | BK5: 2045H1 | BL5: 2045H2 | BM5: 2046H1 | BN5: 2046H2
B7: Macro paths
D8: Base rate before sensitivity shift | E8: % | J8: =CHOOSE(Inputs!$F$32,Inputs!J212,Inputs!J213,Inputs!J214) -> 2.52 | K8: =CHOOSE(Inputs!$F$32,Inputs!K212,Inputs!K213,Inputs!K214) -> 2.79 | L8: =CHOOSE(Inputs!$F$32,Inputs!L212,Inputs!L213,Inputs!L214) -> 2.94 | M8: =CHOOSE(Inputs!$F$32,Inputs!M212,Inputs!M213,Inputs!M214) -> 3.02 | N8: =CHOOSE(Inputs!$F$32,Inputs!N212,Inputs!N213,Inputs!N214) -> 3.06 | O8: =CHOOSE(Inputs!$F$32,Inputs!O212,Inputs!O213,Inputs!O214) -> 3.09 | P8: =CHOOSE(Inputs!$F$32,Inputs!P212,Inputs!P213,Inputs!P214) -> 3.09 | Q8: =CHOOSE(Inputs!$F$32,Inputs!Q212,Inputs!Q213,Inputs!Q214) -> 3.11 | ... BN8: =CHOOSE(Inputs!$F$32,Inputs!BN212,Inputs!BN213,Inputs!BN214) -> 3.12
D9: Base rate (6M LIBOR / Term SOFR + CAS) | E9: % | J9: =J8+Inputs!$F$41*Time!J34 -> 2.52 | K9: =K8+Inputs!$F$41*Time!K34 -> 2.79 | L9: =L8+Inputs!$F$41*Time!L34 -> 2.94 | M9: =M8+Inputs!$F$41*Time!M34 -> 3.02 | N9: =N8+Inputs!$F$41*Time!N34 -> 3.06 | O9: =O8+Inputs!$F$41*Time!O34 -> 3.09 | P9: =P8+Inputs!$F$41*Time!P34 -> 3.09 | Q9: =Q8+Inputs!$F$41*Time!Q34 -> 3.11 | ... BN9: =BN8+Inputs!$F$41*Time!BN34 -> 3.12
D10: KCR per USD before devaluation sensitivity | E10: KCR/USD | J10: =CHOOSE(Inputs!$F$32,Inputs!$F$58*Time!$F$15^((Time!J17-0.5)/2),Inputs!J215,Inputs!J215) -> 526.00677 | K10: =CHOOSE(Inputs!$F$32,Inputs!$F$58*Time!$F$15^((Time!K17-0.5)/2),Inputs!K215,Inputs!K215) -> 539.47351 | L10: =CHOOSE(Inputs!$F$32,Inputs!$F$58*Time!$F$15^((Time!L17-0.5)/2),Inputs!L215,Inputs!L215) -> 553.28501 | M10: =CHOOSE(Inputs!$F$32,Inputs!$F$58*Time!$F$15^((Time!M17-0.5)/2),Inputs!M215,Inputs!M215) -> 567.45012 | N10: =CHOOSE(Inputs!$F$32,Inputs!$F$58*Time!$F$15^((Time!N17-0.5)/2),Inputs!N215,Inputs!N215) -> 581.97787 | O10: =CHOOSE(Inputs!$F$32,Inputs!$F$58*Time!$F$15^((Time!O17-0.5)/2),Inputs!O215,Inputs!O215) -> 596.87757 | P10: =CHOOSE(Inputs!$F$32,Inputs!$F$58*Time!$F$15^((Time!P17-0.5)/2),Inputs!P215,Inputs!P215) -> 612.15872 | Q10: =CHOOSE(Inputs!$F$32,Inputs!$F$58*Time!$F$15^((Time!Q17-0.5)/2),Inputs!Q215,P10*Time!$F$15^0.5) -> 627.8311 | R10: =CHOOSE(Inputs!$F$32,Inputs!$F$58*Time!$F$15^((Time!R17-0.5)/2),Inputs!R215,Q10*Time!$F$15^0.5) -> 643.90472 | S10: =CHOOSE(Inputs!$F$32,Inputs!$F$58*Time!$F$15^((Time!S17-0.5)/2),Inputs!S215,R10*Time!$F$15^0.5) -> 660.38986 | T10: =CHOOSE(Inputs!$F$32,Inputs!$F$58*Time!$F$15^((Time!T17-0.5)/2),Inputs!T215,S10*Time!$F$15^0.5) -> 677.29704 | U10: =CHOOSE(Inputs!$F$32,Inputs!$F$58*Time!$F$15^((Time!U17-0.5)/2),Inputs!U215,T10*Time!$F$15^0.5) -> 694.63708 | V10: =CHOOSE(Inputs!$F$32,Inputs!$F$58*Time!$F$15^((Time!V17-0.5)/2),Inputs!V215,U10*Time!$F$15^0.5) -> 712.42106 | W10: =CHOOSE(Inputs!$F$32,Inputs!$F$58*Time!$F$15^((Time!W17-0.5)/2),Inputs!W215,V10*Time!$F$15^0.5) -> 730.66034 | X10: =CHOOSE(Inputs!$F$32,Inputs!$F$58*Time!$F$15^((Time!X17-0.5)/2),Inputs!X215,W10*Time!$F$15^0.5) -> 749.36657 | ... Z10: =CHOOSE(Inputs!$F$32,Inputs!$F$58*Time!$F$15^((Time!Z17-0.5)/2),Inputs!Z215,Y10*Time!$F$15^0.5) -> 788.22805 | AA10: =CHOOSE(Inputs!$F$32,Inputs!$F$58*Time!$F$15^((Time!AA17-0.5)/2),Z10*((1+AA13/100)/(1+AA12/100))^0.5,Z10*Time!$F$15^0.5) -> 808.40812 | AB10: =CHOOSE(Inputs!$F$32,Inputs!$F$58*Time!$F$15^((Time!AB17-0.5)/2),AA10*((1+AB13/100)/(1+AB12/100))^0.5,AA10*Time!$F$15^0.5) -> 829.10485 | AC10: =CHOOSE(Inputs!$F$32,Inputs!$F$58*Time!$F$15^((Time!AC17-0.5)/2),AB10*((1+AC13/100)/(1+AC12/100))^0.5,AB10*Time!$F$15^0.5) -> 850.33144 | AD10: =CHOOSE(Inputs!$F$32,Inputs!$F$58*Time!$F$15^((Time!AD17-0.5)/2),AC10*((1+AD13/100)/(1+AD12/100))^0.5,AC10*Time!$F$15^0.5) -> 872.10148 | AE10: =CHOOSE(Inputs!$F$32,Inputs!$F$58*Time!$F$15^((Time!AE17-0.5)/2),AD10*((1+AE13/100)/(1+AE12/100))^0.5,AD10*Time!$F$15^0.5) -> 894.42886 | AF10: =CHOOSE(Inputs!$F$32,Inputs!$F$58*Time!$F$15^((Time!AF17-0.5)/2),AE10*((1+AF13/100)/(1+AF12/100))^0.5,AE10*Time!$F$15^0.5) -> 917.32787 | AG10: =CHOOSE(Inputs!$F$32,Inputs!$F$58*Time!$F$15^((Time!AG17-0.5)/2),AF10*((1+AG13/100)/(1+AG12/100))^0.5,AF10*Time!$F$15^0.5) -> 940.81314 | AH10: =CHOOSE(Inputs!$F$32,Inputs!$F$58*Time!$F$15^((Time!AH17-0.5)/2),AG10*((1+AH13/100)/(1+AH12/100))^0.5,AG10*Time!$F$15^0.5) -> 964.89967 | ... BN10: =CHOOSE(Inputs!$F$32,Inputs!$F$58*Time!$F$15^((Time!BN17-0.5)/2),BM10*((1+BN13/100)/(1+BN12/100))^0.5,BM10*Time!$F$15^0.5) -> 2166.7223
D11: KCR per USD, period average | E11: KCR/USD | J11: =J10/(1-Inputs!$F$42*Time!J34) -> 526.00677 | K11: =K10/(1-Inputs!$F$42*Time!K34) -> 539.47351 | L11: =L10/(1-Inputs!$F$42*Time!L34) -> 553.28501 | M11: =M10/(1-Inputs!$F$42*Time!M34) -> 567.45012 | N11: =N10/(1-Inputs!$F$42*Time!N34) -> 581.97787 | O11: =O10/(1-Inputs!$F$42*Time!O34) -> 596.87757 | P11: =P10/(1-Inputs!$F$42*Time!P34) -> 612.15872 | Q11: =Q10/(1-Inputs!$F$42*Time!Q34) -> 627.8311 | ... BN11: =BN10/(1-Inputs!$F$42*Time!BN34) -> 2166.7223
D12: US CPI change, current year | E12: % | J12: =CHOOSE(Inputs!$F$32,INDEX(Inputs!$J$204:$AR$204,1,(Time!J21-0)-2014),INDEX(Inputs!$J$206:$AR$206,1,(Time!J21-0)-2014),INDEX(Inputs!$J$208:$AR$208,1,(Time!J21-0)-2014)) -> 2.2 | K12: =CHOOSE(Inputs!$F$32,INDEX(Inputs!$J$204:$AR$204,1,(Time!K21-0)-2014),INDEX(Inputs!$J$206:$AR$206,1,(Time!K21-0)-2014),INDEX(Inputs!$J$208:$AR$208,1,(Time!K21-0)-2014)) -> 2.2 | L12: =CHOOSE(Inputs!$F$32,INDEX(Inputs!$J$204:$AR$204,1,(Time!L21-0)-2014),INDEX(Inputs!$J$206:$AR$206,1,(Time!L21-0)-2014),INDEX(Inputs!$J$208:$AR$208,1,(Time!L21-0)-2014)) -> 2.2 | M12: =CHOOSE(Inputs!$F$32,INDEX(Inputs!$J$204:$AR$204,1,(Time!M21-0)-2014),INDEX(Inputs!$J$206:$AR$206,1,(Time!M21-0)-2014),INDEX(Inputs!$J$208:$AR$208,1,(Time!M21-0)-2014)) -> 2.2 | N12: =CHOOSE(Inputs!$F$32,INDEX(Inputs!$J$204:$AR$204,1,(Time!N21-0)-2014),INDEX(Inputs!$J$206:$AR$206,1,(Time!N21-0)-2014),INDEX(Inputs!$J$208:$AR$208,1,(Time!N21-0)-2014)) -> 2.2 | O12: =CHOOSE(Inputs!$F$32,INDEX(Inputs!$J$204:$AR$204,1,(Time!O21-0)-2014),INDEX(Inputs!$J$206:$AR$206,1,(Time!O21-0)-2014),INDEX(Inputs!$J$208:$AR$208,1,(Time!O21-0)-2014)) -> 2.2 | P12: =CHOOSE(Inputs!$F$32,INDEX(Inputs!$J$204:$AR$204,1,(Time!P21-0)-2014),INDEX(Inputs!$J$206:$AR$206,1,(Time!P21-0)-2014),INDEX(Inputs!$J$208:$AR$208,1,(Time!P21-0)-2014)) -> 2.2 | Q12: =CHOOSE(Inputs!$F$32,INDEX(Inputs!$J$204:$AR$204,1,(Time!Q21-0)-2014),INDEX(Inputs!$J$206:$AR$206,1,(Time!Q21-0)-2014),INDEX(Inputs!$J$208:$AR$208,1,(Time!Q21-0)-2014)) -> 2.2 | ... BN12: =CHOOSE(Inputs!$F$32,INDEX(Inputs!$J$204:$AR$204,1,(Time!BN21-0)-2014),INDEX(Inputs!$J$206:$AR$206,1,(Time!BN21-0)-2014),INDEX(Inputs!$J$208:$AR$208,1,(Time!BN21-0)-2014)) -> 2.2
D13: Kessara CPI change, current year | E13: % | J13: =CHOOSE(Inputs!$F$32,INDEX(Inputs!$J$205:$AR$205,1,(Time!J21-0)-2014),INDEX(Inputs!$J$207:$AR$207,1,(Time!J21-0)-2014),INDEX(Inputs!$J$209:$AR$209,1,(Time!J21-0)-2014)) -> 7.5 | K13: =CHOOSE(Inputs!$F$32,INDEX(Inputs!$J$205:$AR$205,1,(Time!K21-0)-2014),INDEX(Inputs!$J$207:$AR$207,1,(Time!K21-0)-2014),INDEX(Inputs!$J$209:$AR$209,1,(Time!K21-0)-2014)) -> 7.5 | L13: =CHOOSE(Inputs!$F$32,INDEX(Inputs!$J$205:$AR$205,1,(Time!L21-0)-2014),INDEX(Inputs!$J$207:$AR$207,1,(Time!L21-0)-2014),INDEX(Inputs!$J$209:$AR$209,1,(Time!L21-0)-2014)) -> 7.5 | M13: =CHOOSE(Inputs!$F$32,INDEX(Inputs!$J$205:$AR$205,1,(Time!M21-0)-2014),INDEX(Inputs!$J$207:$AR$207,1,(Time!M21-0)-2014),INDEX(Inputs!$J$209:$AR$209,1,(Time!M21-0)-2014)) -> 7.5 | N13: =CHOOSE(Inputs!$F$32,INDEX(Inputs!$J$205:$AR$205,1,(Time!N21-0)-2014),INDEX(Inputs!$J$207:$AR$207,1,(Time!N21-0)-2014),INDEX(Inputs!$J$209:$AR$209,1,(Time!N21-0)-2014)) -> 7.5 | O13: =CHOOSE(Inputs!$F$32,INDEX(Inputs!$J$205:$AR$205,1,(Time!O21-0)-2014),INDEX(Inputs!$J$207:$AR$207,1,(Time!O21-0)-2014),INDEX(Inputs!$J$209:$AR$209,1,(Time!O21-0)-2014)) -> 7.5 | P13: =CHOOSE(Inputs!$F$32,INDEX(Inputs!$J$205:$AR$205,1,(Time!P21-0)-2014),INDEX(Inputs!$J$207:$AR$207,1,(Time!P21-0)-2014),INDEX(Inputs!$J$209:$AR$209,1,(Time!P21-0)-2014)) -> 7.5 | Q13: =CHOOSE(Inputs!$F$32,INDEX(Inputs!$J$205:$AR$205,1,(Time!Q21-0)-2014),INDEX(Inputs!$J$207:$AR$207,1,(Time!Q21-0)-2014),INDEX(Inputs!$J$209:$AR$209,1,(Time!Q21-0)-2014)) -> 7.5 | ... BN13: =CHOOSE(Inputs!$F$32,INDEX(Inputs!$J$205:$AR$205,1,(Time!BN21-0)-2014),INDEX(Inputs!$J$207:$AR$207,1,(Time!BN21-0)-2014),INDEX(Inputs!$J$209:$AR$209,1,(Time!BN21-0)-2014)) -> 7.5
D14: US CPI change, prior year | E14: % | J14: =CHOOSE(Inputs!$F$32,INDEX(Inputs!$J$204:$AR$204,1,(Time!J21-1)-2014),INDEX(Inputs!$J$206:$AR$206,1,(Time!J21-1)-2014),INDEX(Inputs!$J$208:$AR$208,1,(Time!J21-1)-2014)) -> 2.1 | K14: =CHOOSE(Inputs!$F$32,INDEX(Inputs!$J$204:$AR$204,1,(Time!K21-1)-2014),INDEX(Inputs!$J$206:$AR$206,1,(Time!K21-1)-2014),INDEX(Inputs!$J$208:$AR$208,1,(Time!K21-1)-2014)) -> 2.2 | L14: =CHOOSE(Inputs!$F$32,INDEX(Inputs!$J$204:$AR$204,1,(Time!L21-1)-2014),INDEX(Inputs!$J$206:$AR$206,1,(Time!L21-1)-2014),INDEX(Inputs!$J$208:$AR$208,1,(Time!L21-1)-2014)) -> 2.2 | M14: =CHOOSE(Inputs!$F$32,INDEX(Inputs!$J$204:$AR$204,1,(Time!M21-1)-2014),INDEX(Inputs!$J$206:$AR$206,1,(Time!M21-1)-2014),INDEX(Inputs!$J$208:$AR$208,1,(Time!M21-1)-2014)) -> 2.2 | N14: =CHOOSE(Inputs!$F$32,INDEX(Inputs!$J$204:$AR$204,1,(Time!N21-1)-2014),INDEX(Inputs!$J$206:$AR$206,1,(Time!N21-1)-2014),INDEX(Inputs!$J$208:$AR$208,1,(Time!N21-1)-2014)) -> 2.2 | O14: =CHOOSE(Inputs!$F$32,INDEX(Inputs!$J$204:$AR$204,1,(Time!O21-1)-2014),INDEX(Inputs!$J$206:$AR$206,1,(Time!O21-1)-2014),INDEX(Inputs!$J$208:$AR$208,1,(Time!O21-1)-2014)) -> 2.2 | P14: =CHOOSE(Inputs!$F$32,INDEX(Inputs!$J$204:$AR$204,1,(Time!P21-1)-2014),INDEX(Inputs!$J$206:$AR$206,1,(Time!P21-1)-2014),INDEX(Inputs!$J$208:$AR$208,1,(Time!P21-1)-2014)) -> 2.2 | Q14: =CHOOSE(Inputs!$F$32,INDEX(Inputs!$J$204:$AR$204,1,(Time!Q21-1)-2014),INDEX(Inputs!$J$206:$AR$206,1,(Time!Q21-1)-2014),INDEX(Inputs!$J$208:$AR$208,1,(Time!Q21-1)-2014)) -> 2.2 | ... BN14: =CHOOSE(Inputs!$F$32,INDEX(Inputs!$J$204:$AR$204,1,(Time!BN21-1)-2014),INDEX(Inputs!$J$206:$AR$206,1,(Time!BN21-1)-2014),INDEX(Inputs!$J$208:$AR$208,1,(Time!BN21-1)-2014)) -> 2.2
D15: Kessara CPI change, prior year | E15: % | J15: =CHOOSE(Inputs!$F$32,INDEX(Inputs!$J$205:$AR$205,1,(Time!J21-1)-2014),INDEX(Inputs!$J$207:$AR$207,1,(Time!J21-1)-2014),INDEX(Inputs!$J$209:$AR$209,1,(Time!J21-1)-2014)) -> 8.1 | K15: =CHOOSE(Inputs!$F$32,INDEX(Inputs!$J$205:$AR$205,1,(Time!K21-1)-2014),INDEX(Inputs!$J$207:$AR$207,1,(Time!K21-1)-2014),INDEX(Inputs!$J$209:$AR$209,1,(Time!K21-1)-2014)) -> 7.5 | L15: =CHOOSE(Inputs!$F$32,INDEX(Inputs!$J$205:$AR$205,1,(Time!L21-1)-2014),INDEX(Inputs!$J$207:$AR$207,1,(Time!L21-1)-2014),INDEX(Inputs!$J$209:$AR$209,1,(Time!L21-1)-2014)) -> 7.5 | M15: =CHOOSE(Inputs!$F$32,INDEX(Inputs!$J$205:$AR$205,1,(Time!M21-1)-2014),INDEX(Inputs!$J$207:$AR$207,1,(Time!M21-1)-2014),INDEX(Inputs!$J$209:$AR$209,1,(Time!M21-1)-2014)) -> 7.5 | N15: =CHOOSE(Inputs!$F$32,INDEX(Inputs!$J$205:$AR$205,1,(Time!N21-1)-2014),INDEX(Inputs!$J$207:$AR$207,1,(Time!N21-1)-2014),INDEX(Inputs!$J$209:$AR$209,1,(Time!N21-1)-2014)) -> 7.5 | O15: =CHOOSE(Inputs!$F$32,INDEX(Inputs!$J$205:$AR$205,1,(Time!O21-1)-2014),INDEX(Inputs!$J$207:$AR$207,1,(Time!O21-1)-2014),INDEX(Inputs!$J$209:$AR$209,1,(Time!O21-1)-2014)) -> 7.5 | P15: =CHOOSE(Inputs!$F$32,INDEX(Inputs!$J$205:$AR$205,1,(Time!P21-1)-2014),INDEX(Inputs!$J$207:$AR$207,1,(Time!P21-1)-2014),INDEX(Inputs!$J$209:$AR$209,1,(Time!P21-1)-2014)) -> 7.5 | Q15: =CHOOSE(Inputs!$F$32,INDEX(Inputs!$J$205:$AR$205,1,(Time!Q21-1)-2014),INDEX(Inputs!$J$207:$AR$207,1,(Time!Q21-1)-2014),INDEX(Inputs!$J$209:$AR$209,1,(Time!Q21-1)-2014)) -> 7.5 | ... BN15: =CHOOSE(Inputs!$F$32,INDEX(Inputs!$J$205:$AR$205,1,(Time!BN21-1)-2014),INDEX(Inputs!$J$207:$AR$207,1,(Time!BN21-1)-2014),INDEX(Inputs!$J$209:$AR$209,1,(Time!BN21-1)-2014)) -> 7.5
D16: US index, June 2018 (2018 price base) | E16: index | F16: =100*(1+CHOOSE(Inputs!$F$32,INDEX(Inputs!$J$204:$AR$204,1,2016-2014),INDEX(Inputs!$J$206:$AR$206,1,2016-2014),INDEX(Inputs!$J$208:$AR$208,1,2016-2014))/100)^(1/12)*(1+CHOOSE(Inputs!$F$32,INDEX(Inputs!$J$204:$AR$204,1,2017-2014),INDEX(Inputs!$J$206:$AR$206,1,2017-2014),INDEX(Inputs!$J$208:$AR$208,1,2017-2014))/100)*(1+CHOOSE(Inputs!$F$32,INDEX(Inputs!$J$204:$AR$204,1,2018-2014),INDEX(Inputs!$J$206:$AR$206,1,2018-2014),INDEX(Inputs!$J$208:$AR$208,1,2018-2014))/100)^(6/12) -> 103.32815
D17: US CPI index, cost reading (Mar/Sep), Nov 2016 = 100 | E17: index | J17: =100*(1+CHOOSE(Inputs!$F$32,INDEX(Inputs!$J$204:$AR$204,1,2016-2014),INDEX(Inputs!$J$206:$AR$206,1,2016-2014),INDEX(Inputs!$J$208:$AR$208,1,2016-2014))/100)^(1/12)*(1+CHOOSE(Inputs!$F$32,INDEX(Inputs!$J$204:$AR$204,1,2017-2014),INDEX(Inputs!$J$206:$AR$206,1,2017-2014),INDEX(Inputs!$J$208:$AR$208,1,2017-2014))/100)*(1+CHOOSE(Inputs!$F$32,INDEX(Inputs!$J$204:$AR$204,1,2018-2014),INDEX(Inputs!$J$206:$AR$206,1,2018-2014),INDEX(Inputs!$J$208:$AR$208,1,2018-2014))/100)^(9/12) -> 103.89182 | K17: =J17*IF(Time!K22=1,(1+K14/100)^0.25*(1+K12/100)^0.25,(1+K12/100)^0.5) -> 105.02842 | L17: =K17*IF(Time!L22=1,(1+L14/100)^0.25*(1+L12/100)^0.25,(1+L12/100)^0.5) -> 106.17744 | M17: =L17*IF(Time!M22=1,(1+M14/100)^0.25*(1+M12/100)^0.25,(1+M12/100)^0.5) -> 107.33904 | N17: =M17*IF(Time!N22=1,(1+N14/100)^0.25*(1+N12/100)^0.25,(1+N12/100)^0.5) -> 108.51335 | O17: =N17*IF(Time!O22=1,(1+O14/100)^0.25*(1+O12/100)^0.25,(1+O12/100)^0.5) -> 109.7005 | P17: =O17*IF(Time!P22=1,(1+P14/100)^0.25*(1+P12/100)^0.25,(1+P12/100)^0.5) -> 110.90064 | Q17: =P17*IF(Time!Q22=1,(1+Q14/100)^0.25*(1+Q12/100)^0.25,(1+Q12/100)^0.5) -> 112.11391 | R17: =Q17*IF(Time!R22=1,(1+R14/100)^0.25*(1+R12/100)^0.25,(1+R12/100)^0.5) -> 113.34045 | ... BN17: =BM17*IF(Time!BN22=1,(1+BN14/100)^0.25*(1+BN12/100)^0.25,(1+BN12/100)^0.5) -> 191.07614
D18: US CPI index, tariff reading (3-month lag) | E18: index | J18: =100*(1+CHOOSE(Inputs!$F$32,INDEX(Inputs!$J$204:$AR$204,1,2016-2014),INDEX(Inputs!$J$206:$AR$206,1,2016-2014),INDEX(Inputs!$J$208:$AR$208,1,2016-2014))/100)^(1/12)*(1+CHOOSE(Inputs!$F$32,INDEX(Inputs!$J$204:$AR$204,1,2017-2014),INDEX(Inputs!$J$206:$AR$206,1,2017-2014),INDEX(Inputs!$J$208:$AR$208,1,2017-2014))/100)*(1+CHOOSE(Inputs!$F$32,INDEX(Inputs!$J$204:$AR$204,1,2018-2014),INDEX(Inputs!$J$206:$AR$206,1,2018-2014),INDEX(Inputs!$J$208:$AR$208,1,2018-2014))/100)^(3/12) -> 102.76753 | K18: =J17 -> 103.89182 | L18: =K17 -> 105.02842 | M18: =L17 -> 106.17744 | N18: =M17 -> 107.33904 | O18: =N17 -> 108.51335 | P18: =O17 -> 109.7005 | Q18: =P17 -> 110.90064 | R18: =Q17 -> 112.11391 | ... BN18: =BM17 -> 189.00835
D19: US cost indexation factor vs 2018 prices | E19: factor | J19: =J17/$F$16 -> 1.0054552 | K19: =K17/$F$16 -> 1.016455 | L19: =L17/$F$16 -> 1.0275752 | M19: =M17/$F$16 -> 1.038817 | N19: =N17/$F$16 -> 1.0501819 | O19: =O17/$F$16 -> 1.061671 | P19: =P17/$F$16 -> 1.0732859 | Q19: =Q17/$F$16 -> 1.0850278 | ... BN19: =BN17/$F$16 -> 1.8492167
D20: KC index, June 2018 (2018 price base) | E20: index | F20: =100*(1+CHOOSE(Inputs!$F$32,INDEX(Inputs!$J$205:$AR$205,1,2016-2014),INDEX(Inputs!$J$207:$AR$207,1,2016-2014),INDEX(Inputs!$J$209:$AR$209,1,2016-2014))/100)^(1/12)*(1+CHOOSE(Inputs!$F$32,INDEX(Inputs!$J$205:$AR$205,1,2017-2014),INDEX(Inputs!$J$207:$AR$207,1,2017-2014),INDEX(Inputs!$J$209:$AR$209,1,2017-2014))/100)*(1+CHOOSE(Inputs!$F$32,INDEX(Inputs!$J$205:$AR$205,1,2018-2014),INDEX(Inputs!$J$207:$AR$207,1,2018-2014),INDEX(Inputs!$J$209:$AR$209,1,2018-2014))/100)^(6/12) -> 112.92273
D21: Kessara CPI index, cost reading (Mar/Sep), Nov 2016 = 100 | E21: index | J21: =100*(1+CHOOSE(Inputs!$F$32,INDEX(Inputs!$J$205:$AR$205,1,2016-2014),INDEX(Inputs!$J$207:$AR$207,1,2016-2014),INDEX(Inputs!$J$209:$AR$209,1,2016-2014))/100)^(1/12)*(1+CHOOSE(Inputs!$F$32,INDEX(Inputs!$J$205:$AR$205,1,2017-2014),INDEX(Inputs!$J$207:$AR$207,1,2017-2014),INDEX(Inputs!$J$209:$AR$209,1,2017-2014))/100)*(1+CHOOSE(Inputs!$F$32,INDEX(Inputs!$J$205:$AR$205,1,2018-2014),INDEX(Inputs!$J$207:$AR$207,1,2018-2014),INDEX(Inputs!$J$209:$AR$209,1,2018-2014))/100)^(9/12) -> 114.98296 | K21: =J21*IF(Time!K22=1,(1+K15/100)^0.25*(1+K13/100)^0.25,(1+K13/100)^0.5) -> 119.21687 | L21: =K21*IF(Time!L22=1,(1+L15/100)^0.25*(1+L13/100)^0.25,(1+L13/100)^0.5) -> 123.60668 | M21: =L21*IF(Time!M22=1,(1+M15/100)^0.25*(1+M13/100)^0.25,(1+M13/100)^0.5) -> 128.15814 | N21: =M21*IF(Time!N22=1,(1+N15/100)^0.25*(1+N13/100)^0.25,(1+N13/100)^0.5) -> 132.87718 | O21: =N21*IF(Time!O22=1,(1+O15/100)^0.25*(1+O13/100)^0.25,(1+O13/100)^0.5) -> 137.77 | P21: =O21*IF(Time!P22=1,(1+P15/100)^0.25*(1+P13/100)^0.25,(1+P13/100)^0.5) -> 142.84297 | Q21: =P21*IF(Time!Q22=1,(1+Q15/100)^0.25*(1+Q13/100)^0.25,(1+Q13/100)^0.5) -> 148.10275 | R21: =Q21*IF(Time!R22=1,(1+R15/100)^0.25*(1+R13/100)^0.25,(1+R13/100)^0.5) -> 153.5562 | ... BN21: =BM21*IF(Time!BN22=1,(1+BN15/100)^0.25*(1+BN13/100)^0.25,(1+BN13/100)^0.5) -> 871.10496
D22: Kessara CPI index, tariff reading (3-month lag) | E22: index | J22: =100*(1+CHOOSE(Inputs!$F$32,INDEX(Inputs!$J$205:$AR$205,1,2016-2014),INDEX(Inputs!$J$207:$AR$207,1,2016-2014),INDEX(Inputs!$J$209:$AR$209,1,2016-2014))/100)^(1/12)*(1+CHOOSE(Inputs!$F$32,INDEX(Inputs!$J$205:$AR$205,1,2017-2014),INDEX(Inputs!$J$207:$AR$207,1,2017-2014),INDEX(Inputs!$J$209:$AR$209,1,2017-2014))/100)*(1+CHOOSE(Inputs!$F$32,INDEX(Inputs!$J$205:$AR$205,1,2018-2014),INDEX(Inputs!$J$207:$AR$207,1,2018-2014),INDEX(Inputs!$J$209:$AR$209,1,2018-2014))/100)^(3/12) -> 110.89941 | K22: =J21 -> 114.98296 | L22: =K21 -> 119.21687 | M22: =L21 -> 123.60668 | N22: =M21 -> 128.15814 | O22: =N21 -> 132.87718 | P22: =O21 -> 137.77 | Q22: =P21 -> 142.84297 | R22: =Q21 -> 148.10275 | ... BN22: =BM21 -> 840.16822
D23: Kessara cost indexation factor vs 2018 prices | E23: factor | J23: =J21/$F$20 -> 1.0182446 | K23: =K21/$F$20 -> 1.0557385 | L23: =L21/$F$20 -> 1.0946129 | M23: =M21/$F$20 -> 1.1349189 | N23: =N21/$F$20 -> 1.1767089 | O23: =O21/$F$20 -> 1.2200378 | P23: =P21/$F$20 -> 1.2649621 | Q23: =Q21/$F$20 -> 1.3115406 | ... BN23: =BN21/$F$20 -> 7.7141684
B24: Plant
D25: Operating year at period start | E25: OY | J25: =INT(Time!J27/12)+1 -> 1 | K25: =INT(Time!K27/12)+1 -> 1 | L25: =INT(Time!L27/12)+1 -> 1 | M25: =INT(Time!M27/12)+1 -> 1 | N25: =INT(Time!N27/12)+1 -> 1 | O25: =INT(Time!O27/12)+1 -> 1 | P25: =INT(Time!P27/12)+1 -> 1 | Q25: =INT(Time!Q27/12)+1 -> 1 | ... BN25: =INT(Time!BN27/12)+1 -> 26
D26: Months in that operating year | E26: months | J26: =MIN(Time!J28,J25*12)-Time!J27 -> 0 | K26: =MIN(Time!K28,K25*12)-Time!K27 -> 0 | L26: =MIN(Time!L28,L25*12)-Time!L27 -> 0 | M26: =MIN(Time!M28,M25*12)-Time!M27 -> 0 | N26: =MIN(Time!N28,N25*12)-Time!N27 -> 0 | O26: =MIN(Time!O28,O25*12)-Time!O27 -> 2 | P26: =MIN(Time!P28,P25*12)-Time!P27 -> 6 | Q26: =MIN(Time!Q28,Q25*12)-Time!Q27 -> 4 | ... BN26: =MIN(Time!BN28,BN25*12)-Time!BN27 -> 0
D27: Availability, profile (month-weighted) | E27: % | J27: =IF(Time!J25>0,(J26*INDEX(Inputs!$J$223:$Q$223,1,MOD(J25-1,8)+1)+(Time!J25-J26)*INDEX(Inputs!$J$223:$Q$223,1,MOD(J25,8)+1))/Time!J25,0) -> 0 | K27: =IF(Time!K25>0,(K26*INDEX(Inputs!$J$223:$Q$223,1,MOD(K25-1,8)+1)+(Time!K25-K26)*INDEX(Inputs!$J$223:$Q$223,1,MOD(K25,8)+1))/Time!K25,0) -> 0 | L27: =IF(Time!L25>0,(L26*INDEX(Inputs!$J$223:$Q$223,1,MOD(L25-1,8)+1)+(Time!L25-L26)*INDEX(Inputs!$J$223:$Q$223,1,MOD(L25,8)+1))/Time!L25,0) -> 0 | M27: =IF(Time!M25>0,(M26*INDEX(Inputs!$J$223:$Q$223,1,MOD(M25-1,8)+1)+(Time!M25-M26)*INDEX(Inputs!$J$223:$Q$223,1,MOD(M25,8)+1))/Time!M25,0) -> 0 | N27: =IF(Time!N25>0,(N26*INDEX(Inputs!$J$223:$Q$223,1,MOD(N25-1,8)+1)+(Time!N25-N26)*INDEX(Inputs!$J$223:$Q$223,1,MOD(N25,8)+1))/Time!N25,0) -> 0 | O27: =IF(Time!O25>0,(O26*INDEX(Inputs!$J$223:$Q$223,1,MOD(O25-1,8)+1)+(Time!O25-O26)*INDEX(Inputs!$J$223:$Q$223,1,MOD(O25,8)+1))/Time!O25,0) -> 93.8 | P27: =IF(Time!P25>0,(P26*INDEX(Inputs!$J$223:$Q$223,1,MOD(P25-1,8)+1)+(Time!P25-P26)*INDEX(Inputs!$J$223:$Q$223,1,MOD(P25,8)+1))/Time!P25,0) -> 93.8 | Q27: =IF(Time!Q25>0,(Q26*INDEX(Inputs!$J$223:$Q$223,1,MOD(Q25-1,8)+1)+(Time!Q25-Q26)*INDEX(Inputs!$J$223:$Q$223,1,MOD(Q25,8)+1))/Time!Q25,0) -> 93.5 | ... BN27: =IF(Time!BN25>0,(BN26*INDEX(Inputs!$J$223:$Q$223,1,MOD(BN25-1,8)+1)+(Time!BN25-BN26)*INDEX(Inputs!$J$223:$Q$223,1,MOD(BN25,8)+1))/Time!BN25,0) -> 0
D28: Availability | E28: % | J28: =IF(Time!J25>0,J27+Inputs!$F$36,0) -> 0 | K28: =IF(Time!K25>0,K27+Inputs!$F$36,0) -> 0 | L28: =IF(Time!L25>0,L27+Inputs!$F$36,0) -> 0 | M28: =IF(Time!M25>0,M27+Inputs!$F$36,0) -> 0 | N28: =IF(Time!N25>0,N27+Inputs!$F$36,0) -> 0 | O28: =IF(Time!O25>0,O27+Inputs!$F$36,0) -> 93.8 | P28: =IF(Time!P25>0,P27+Inputs!$F$36,0) -> 93.8 | Q28: =IF(Time!Q25>0,Q27+Inputs!$F$36,0) -> 93.5 | ... BN28: =IF(Time!BN25>0,BN27+Inputs!$F$36,0) -> 0
D29: Years since COD (period mid-point) | E29: years | J29: =IF(Time!J25>0,(Time!J27+Time!J28)/24,0) -> 0 | K29: =IF(Time!K25>0,(Time!K27+Time!K28)/24,0) -> 0 | L29: =IF(Time!L25>0,(Time!L27+Time!L28)/24,0) -> 0 | M29: =IF(Time!M25>0,(Time!M27+Time!M28)/24,0) -> 0 | N29: =IF(Time!N25>0,(Time!N27+Time!N28)/24,0) -> 0 | O29: =IF(Time!O25>0,(Time!O27+Time!O28)/24,0) -> 0.083333333 | P29: =IF(Time!P25>0,(Time!P27+Time!P28)/24,0) -> 0.41666667 | Q29: =IF(Time!Q25>0,(Time!Q27+Time!Q28)/24,0) -> 0.91666667 | ... BN29: =IF(Time!BN25>0,(Time!BN27+Time!BN28)/24,0) -> 0
D30: Contracted capacity | E30: MW | F30: =IF(Inputs!$F$33=2,Inputs!$F$115,Inputs!$F$114) -> 588.4
D31: Plant net heat rate, new and clean | E31: kJ/kWh | F31: =IF(Inputs!$F$33=2,Inputs!$F$117,Inputs!$F$116) -> 6261
D32: Output degradation factor | E32: factor | J32: =(1-Inputs!$F$123/100*J29)*(1-Inputs!$F$124/100) -> 0.99 | K32: =(1-Inputs!$F$123/100*K29)*(1-Inputs!$F$124/100) -> 0.99 | L32: =(1-Inputs!$F$123/100*L29)*(1-Inputs!$F$124/100) -> 0.99 | M32: =(1-Inputs!$F$123/100*M29)*(1-Inputs!$F$124/100) -> 0.99 | N32: =(1-Inputs!$F$123/100*N29)*(1-Inputs!$F$124/100) -> 0.99 | O32: =(1-Inputs!$F$123/100*O29)*(1-Inputs!$F$124/100) -> 0.98987625 | P32: =(1-Inputs!$F$123/100*P29)*(1-Inputs!$F$124/100) -> 0.98938125 | Q32: =(1-Inputs!$F$123/100*Q29)*(1-Inputs!$F$124/100) -> 0.98863875 | ... BN32: =(1-Inputs!$F$123/100*BN29)*(1-Inputs!$F$124/100) -> 0.99
D33: Net energy delivered | E33: MWh | J33: =$F$30*730*Time!J25*J28/100*Inputs!$F$37/100*J32 -> 0 | K33: =$F$30*730*Time!K25*K28/100*Inputs!$F$37/100*K32 -> 0 | L33: =$F$30*730*Time!L25*L28/100*Inputs!$F$37/100*L32 -> 0 | M33: =$F$30*730*Time!M25*M28/100*Inputs!$F$37/100*M32 -> 0 | N33: =$F$30*730*Time!N25*N28/100*Inputs!$F$37/100*N32 -> 0 | O33: =$F$30*730*Time!O25*O28/100*Inputs!$F$37/100*O32 -> 610197.88 | P33: =$F$30*730*Time!P25*P28/100*Inputs!$F$37/100*P32 -> 1829678.2 | Q33: =$F$30*730*Time!Q25*Q28/100*Inputs!$F$37/100*Q32 -> 1822457.7 | ... BN33: =$F$30*730*Time!BN25*BN28/100*Inputs!$F$37/100*BN32 -> 0
D34: Plant net heat rate | E34: kJ/kWh | J34: =$F$31*(1+Inputs!$F$125/100*J29)*(1+Inputs!$F$126/100)*(1+Inputs!$F$120/100)*Inputs!$F$38 -> 6456.243 | K34: =$F$31*(1+Inputs!$F$125/100*K29)*(1+Inputs!$F$126/100)*(1+Inputs!$F$120/100)*Inputs!$F$38 -> 6456.243 | L34: =$F$31*(1+Inputs!$F$125/100*L29)*(1+Inputs!$F$126/100)*(1+Inputs!$F$120/100)*Inputs!$F$38 -> 6456.243 | M34: =$F$31*(1+Inputs!$F$125/100*M29)*(1+Inputs!$F$126/100)*(1+Inputs!$F$120/100)*Inputs!$F$38 -> 6456.243 | N34: =$F$31*(1+Inputs!$F$125/100*N29)*(1+Inputs!$F$126/100)*(1+Inputs!$F$120/100)*Inputs!$F$38 -> 6456.243 | O34: =$F$31*(1+Inputs!$F$125/100*O29)*(1+Inputs!$F$126/100)*(1+Inputs!$F$120/100)*Inputs!$F$38 -> 6456.8886 | P34: =$F$31*(1+Inputs!$F$125/100*P29)*(1+Inputs!$F$126/100)*(1+Inputs!$F$120/100)*Inputs!$F$38 -> 6459.4711 | Q34: =$F$31*(1+Inputs!$F$125/100*Q29)*(1+Inputs!$F$126/100)*(1+Inputs!$F$120/100)*Inputs!$F$38 -> 6463.3449 | ... BN34: =$F$31*(1+Inputs!$F$125/100*BN29)*(1+Inputs!$F$126/100)*(1+Inputs!$F$120/100)*Inputs!$F$38 -> 6456.243
D35: Contracted heat rate at dispatched load | E35: kJ/kWh | J35: =Inputs!$F$118*(1+Inputs!$F$119/100*J29)*(1+Inputs!$F$120/100) -> 6468.429 | K35: =Inputs!$F$118*(1+Inputs!$F$119/100*K29)*(1+Inputs!$F$120/100) -> 6468.429 | L35: =Inputs!$F$118*(1+Inputs!$F$119/100*L29)*(1+Inputs!$F$120/100) -> 6468.429 | M35: =Inputs!$F$118*(1+Inputs!$F$119/100*M29)*(1+Inputs!$F$120/100) -> 6468.429 | N35: =Inputs!$F$118*(1+Inputs!$F$119/100*N29)*(1+Inputs!$F$120/100) -> 6468.429 | O35: =Inputs!$F$118*(1+Inputs!$F$119/100*O29)*(1+Inputs!$F$120/100) -> 6468.968 | P35: =Inputs!$F$118*(1+Inputs!$F$119/100*P29)*(1+Inputs!$F$120/100) -> 6471.1242 | Q35: =Inputs!$F$118*(1+Inputs!$F$119/100*Q29)*(1+Inputs!$F$120/100) -> 6474.3584 | ... BN35: =Inputs!$F$118*(1+Inputs!$F$119/100*BN29)*(1+Inputs!$F$120/100) -> 6468.429
D36: Gas price (GCV) | E36: USD/MMBtu | J36: =Inputs!$F$139*(1+Inputs!$F$140/100)^(Time!J21-2018)*Inputs!$F$40 -> 5.86 | K36: =Inputs!$F$139*(1+Inputs!$F$140/100)^(Time!K21-2018)*Inputs!$F$40 -> 5.9772 | L36: =Inputs!$F$139*(1+Inputs!$F$140/100)^(Time!L21-2018)*Inputs!$F$40 -> 5.9772 | M36: =Inputs!$F$139*(1+Inputs!$F$140/100)^(Time!M21-2018)*Inputs!$F$40 -> 6.096744 | N36: =Inputs!$F$139*(1+Inputs!$F$140/100)^(Time!N21-2018)*Inputs!$F$40 -> 6.096744 | O36: =Inputs!$F$139*(1+Inputs!$F$140/100)^(Time!O21-2018)*Inputs!$F$40 -> 6.2186789 | P36: =Inputs!$F$139*(1+Inputs!$F$140/100)^(Time!P21-2018)*Inputs!$F$40 -> 6.2186789 | Q36: =Inputs!$F$139*(1+Inputs!$F$140/100)^(Time!Q21-2018)*Inputs!$F$40 -> 6.3430525 | ... BN36: =Inputs!$F$139*(1+Inputs!$F$140/100)^(Time!BN21-2018)*Inputs!$F$40 -> 10.202402
D37: Gas burned | E37: MMBtu | J37: =J33*J34*(1000*Inputs!$F$121/Inputs!$F$122) -> 0 | K37: =K33*K34*(1000*Inputs!$F$121/Inputs!$F$122) -> 0 | L37: =L33*L34*(1000*Inputs!$F$121/Inputs!$F$122) -> 0 | M37: =M33*M34*(1000*Inputs!$F$121/Inputs!$F$122) -> 0 | N37: =N33*N34*(1000*Inputs!$F$121/Inputs!$F$122) -> 0 | O37: =O33*O34*(1000*Inputs!$F$121/Inputs!$F$122) -> 4137692.8 | P37: =P33*P34*(1000*Inputs!$F$121/Inputs!$F$122) -> 12411833 | Q37: =Q33*Q34*(1000*Inputs!$F$121/Inputs!$F$122) -> 12370266 | ... BN37: =BN33*BN34*(1000*Inputs!$F$121/Inputs!$F$122) -> 0
D38: Take-or-pay quantity | E38: MMBtu | J38: =Inputs!$F$142*Inputs!$F$141*Time!J26 -> 0 | K38: =Inputs!$F$142*Inputs!$F$141*Time!K26 -> 0 | L38: =Inputs!$F$142*Inputs!$F$141*Time!L26 -> 0 | M38: =Inputs!$F$142*Inputs!$F$141*Time!M26 -> 0 | N38: =Inputs!$F$142*Inputs!$F$141*Time!N26 -> 0 | O38: =Inputs!$F$142*Inputs!$F$141*Time!O26 -> 3533120 | P38: =Inputs!$F$142*Inputs!$F$141*Time!P26 -> 10657280 | Q38: =Inputs!$F$142*Inputs!$F$141*Time!Q26 -> 10483520 | ... BN38: =Inputs!$F$142*Inputs!$F$141*Time!BN26 -> 0
B39: Revenue (USD m)
D40: Capital charge, indexed | E40: USD/kW-month | J40: =Inputs!$F$131*Inputs!$F$53*(1-Inputs!$F$132+Inputs!$F$132*J18/100) -> 14.439483 | K40: =Inputs!$F$131*Inputs!$F$53*(1-Inputs!$F$132+Inputs!$F$132*K18/100) -> 14.471773 | L40: =Inputs!$F$131*Inputs!$F$53*(1-Inputs!$F$132+Inputs!$F$132*L18/100) -> 14.504416 | M40: =Inputs!$F$131*Inputs!$F$53*(1-Inputs!$F$132+Inputs!$F$132*M18/100) -> 14.537416 | N40: =Inputs!$F$131*Inputs!$F$53*(1-Inputs!$F$132+Inputs!$F$132*N18/100) -> 14.570777 | O40: =Inputs!$F$131*Inputs!$F$53*(1-Inputs!$F$132+Inputs!$F$132*O18/100) -> 14.604503 | P40: =Inputs!$F$131*Inputs!$F$53*(1-Inputs!$F$132+Inputs!$F$132*P18/100) -> 14.638598 | Q40: =Inputs!$F$131*Inputs!$F$53*(1-Inputs!$F$132+Inputs!$F$132*Q18/100) -> 14.673066 | ... BN40: =Inputs!$F$131*Inputs!$F$53*(1-Inputs!$F$132+Inputs!$F$132*BN18/100) -> 16.91632
D41: Fixed O&M charge, indexed | E41: USD/kW-month | J41: =Inputs!$F$133*(Inputs!$F$134*J18/100+(1-Inputs!$F$134)*J22/100*Inputs!$F$135/J11) -> 2.3275027 | K41: =Inputs!$F$133*(Inputs!$F$134*K18/100+(1-Inputs!$F$134)*K22/100*Inputs!$F$135/K11) -> 2.352966 | L41: =Inputs!$F$133*(Inputs!$F$134*L18/100+(1-Inputs!$F$134)*L22/100*Inputs!$F$135/L11) -> 2.3787078 | M41: =Inputs!$F$133*(Inputs!$F$134*M18/100+(1-Inputs!$F$134)*M22/100*Inputs!$F$135/M11) -> 2.4047312 | N41: =Inputs!$F$133*(Inputs!$F$134*N18/100+(1-Inputs!$F$134)*N22/100*Inputs!$F$135/N11) -> 2.4310394 | O41: =Inputs!$F$133*(Inputs!$F$134*O18/100+(1-Inputs!$F$134)*O22/100*Inputs!$F$135/O11) -> 2.4576353 | P41: =Inputs!$F$133*(Inputs!$F$134*P18/100+(1-Inputs!$F$134)*P22/100*Inputs!$F$135/P11) -> 2.4845222 | Q41: =Inputs!$F$133*(Inputs!$F$134*Q18/100+(1-Inputs!$F$134)*Q22/100*Inputs!$F$135/Q11) -> 2.5117033 | ... BN41: =Inputs!$F$133*(Inputs!$F$134*BN18/100+(1-Inputs!$F$134)*BN22/100*Inputs!$F$135/BN11) -> 4.2807048
D42: Availability factor min(1, A/90%) | E42: factor | J42: =MIN(1,J28/Inputs!$F$130) -> 0 | K42: =MIN(1,K28/Inputs!$F$130) -> 0 | L42: =MIN(1,L28/Inputs!$F$130) -> 0 | M42: =MIN(1,M28/Inputs!$F$130) -> 0 | N42: =MIN(1,N28/Inputs!$F$130) -> 0 | O42: =MIN(1,O28/Inputs!$F$130) -> 1 | P42: =MIN(1,P28/Inputs!$F$130) -> 1 | Q42: =MIN(1,Q28/Inputs!$F$130) -> 1 | ... BN42: =MIN(1,BN28/Inputs!$F$130) -> 0
D43: Capacity payment | E43: USD m | G43: =SUM(J43:BN43) -> 3334.8082 | J43: =$F$30*1000*Time!J25*(J40+J41)*J42/1000000 -> 0 | K43: =$F$30*1000*Time!K25*(K40+K41)*K42/1000000 -> 0 | L43: =$F$30*1000*Time!L25*(L40+L41)*L42/1000000 -> 0 | M43: =$F$30*1000*Time!M25*(M40+M41)*M42/1000000 -> 0 | N43: =$F$30*1000*Time!N25*(N40+N41)*N42/1000000 -> 0 | O43: =$F$30*1000*Time!O25*(O40+O41)*O42/1000000 -> 20.078725 | P43: =$F$30*1000*Time!P25*(P40+P41)*P42/1000000 -> 60.451465 | Q43: =$F$30*1000*Time!Q25*(Q40+Q41)*Q42/1000000 -> 60.669111 | ... BN43: =$F$30*1000*Time!BN25*(BN40+BN41)*BN42/1000000 -> 0
D44: VOM charge, indexed | E44: USD/MWh | J44: =Inputs!$F$136*(Inputs!$F$137*J18/100+(1-Inputs!$F$137)*J22/100*Inputs!$F$135/J11) -> 3.9055795 | K44: =Inputs!$F$136*(Inputs!$F$137*K18/100+(1-Inputs!$F$137)*K22/100*Inputs!$F$135/K11) -> 3.9483072 | L44: =Inputs!$F$136*(Inputs!$F$137*L18/100+(1-Inputs!$F$137)*L22/100*Inputs!$F$135/L11) -> 3.9915023 | M44: =Inputs!$F$136*(Inputs!$F$137*M18/100+(1-Inputs!$F$137)*M22/100*Inputs!$F$135/M11) -> 4.03517 | N44: =Inputs!$F$136*(Inputs!$F$137*N18/100+(1-Inputs!$F$137)*N22/100*Inputs!$F$135/N11) -> 4.0793153 | O44: =Inputs!$F$136*(Inputs!$F$137*O18/100+(1-Inputs!$F$137)*O22/100*Inputs!$F$135/O11) -> 4.1239437 | P44: =Inputs!$F$136*(Inputs!$F$137*P18/100+(1-Inputs!$F$137)*P22/100*Inputs!$F$135/P11) -> 4.1690603 | Q44: =Inputs!$F$136*(Inputs!$F$137*Q18/100+(1-Inputs!$F$137)*Q22/100*Inputs!$F$135/Q11) -> 4.2146705 | ... BN44: =Inputs!$F$136*(Inputs!$F$137*BN18/100+(1-Inputs!$F$137)*BN22/100*Inputs!$F$135/BN11) -> 7.1830778
D45: Variable O&M payment | E45: USD m | G45: =SUM(J45:BN45) -> 485.81175 | J45: =J33*J44/1000000 -> 0 | K45: =K33*K44/1000000 -> 0 | L45: =L33*L44/1000000 -> 0 | M45: =M33*M44/1000000 -> 0 | N45: =N33*N44/1000000 -> 0 | O45: =O33*O44/1000000 -> 2.5164217 | P45: =P33*P44/1000000 -> 7.6280389 | Q45: =Q33*Q44/1000000 -> 7.6810585 | ... BN45: =BN33*BN44/1000000 -> 0
D46: Fuel charge (pass-through) | E46: USD m | G46: =SUM(J46:BN46) -> 4886.8261 | J46: =J33*J35*(1000*Inputs!$F$121/Inputs!$F$122)*J36/1000000 -> 0 | K46: =K33*K35*(1000*Inputs!$F$121/Inputs!$F$122)*K36/1000000 -> 0 | L46: =L33*L35*(1000*Inputs!$F$121/Inputs!$F$122)*L36/1000000 -> 0 | M46: =M33*M35*(1000*Inputs!$F$121/Inputs!$F$122)*M36/1000000 -> 0 | N46: =N33*N35*(1000*Inputs!$F$121/Inputs!$F$122)*N36/1000000 -> 0 | O46: =O33*O35*(1000*Inputs!$F$121/Inputs!$F$122)*O36/1000000 -> 25.77912 | P46: =P33*P35*(1000*Inputs!$F$121/Inputs!$F$122)*P36/1000000 -> 77.32445 | Q46: =Q33*Q35*(1000*Inputs!$F$121/Inputs!$F$122)*Q36/1000000 -> 78.598949 | ... BN46: =BN33*BN35*(1000*Inputs!$F$121/Inputs!$F$122)*BN36/1000000 -> 0
D47: GTA reservation charge (pass-through) | E47: USD m | G47: =SUM(J47:BN47) -> 690.34673 | J47: =Inputs!$F$143*Time!J26*Inputs!$F$144*(1+Inputs!$F$146/100)^(Time!J21-2018)/1000000 -> 0 | K47: =Inputs!$F$143*Time!K26*Inputs!$F$144*(1+Inputs!$F$146/100)^(Time!K21-2018)/1000000 -> 0 | L47: =Inputs!$F$143*Time!L26*Inputs!$F$144*(1+Inputs!$F$146/100)^(Time!L21-2018)/1000000 -> 0 | M47: =Inputs!$F$143*Time!M26*Inputs!$F$144*(1+Inputs!$F$146/100)^(Time!M21-2018)/1000000 -> 0 | N47: =Inputs!$F$143*Time!N26*Inputs!$F$144*(1+Inputs!$F$146/100)^(Time!N21-2018)/1000000 -> 0 | O47: =Inputs!$F$143*Time!O26*Inputs!$F$144*(1+Inputs!$F$146/100)^(Time!O21-2018)/1000000 -> 3.8163392 | P47: =Inputs!$F$143*Time!P26*Inputs!$F$144*(1+Inputs!$F$146/100)^(Time!P21-2018)/1000000 -> 11.51158 | Q47: =Inputs!$F$143*Time!Q26*Inputs!$F$144*(1+Inputs!$F$146/100)^(Time!Q21-2018)/1000000 -> 11.49375 | ... BN47: =Inputs!$F$143*Time!BN26*Inputs!$F$144*(1+Inputs!$F$146/100)^(Time!BN21-2018)/1000000 -> 0
D48: GTA commodity charge (pass-through) | E48: USD m | G48: =SUM(J48:BN48) -> 146.42954 | J48: =J37*Inputs!$F$145*(1+Inputs!$F$146/100)^(Time!J21-2018)/1000000 -> 0 | K48: =K37*Inputs!$F$145*(1+Inputs!$F$146/100)^(Time!K21-2018)/1000000 -> 0 | L48: =L37*Inputs!$F$145*(1+Inputs!$F$146/100)^(Time!L21-2018)/1000000 -> 0 | M48: =M37*Inputs!$F$145*(1+Inputs!$F$146/100)^(Time!M21-2018)/1000000 -> 0 | N48: =N37*Inputs!$F$145*(1+Inputs!$F$146/100)^(Time!N21-2018)/1000000 -> 0 | O48: =O37*Inputs!$F$145*(1+Inputs!$F$146/100)^(Time!O21-2018)/1000000 -> 0.82207222 | P48: =P37*Inputs!$F$145*(1+Inputs!$F$146/100)^(Time!P21-2018)/1000000 -> 2.4659693 | Q48: =Q37*Inputs!$F$145*(1+Inputs!$F$146/100)^(Time!Q21-2018)/1000000 -> 2.4945763 | ... BN48: =BN37*Inputs!$F$145*(1+Inputs!$F$146/100)^(Time!BN21-2018)/1000000 -> 0
D49: Take-or-pay payment (pass-through) | E49: USD m | G49: =SUM(J49:BN49) -> 0 | J49: =MAX(0,J38-J37)*J36/1000000 -> 0 | K49: =MAX(0,K38-K37)*K36/1000000 -> 0 | L49: =MAX(0,L38-L37)*L36/1000000 -> 0 | M49: =MAX(0,M38-M37)*M36/1000000 -> 0 | N49: =MAX(0,N38-N37)*N36/1000000 -> 0 | O49: =MAX(0,O38-O37)*O36/1000000 -> 0 | P49: =MAX(0,P38-P37)*P36/1000000 -> 0 | Q49: =MAX(0,Q38-Q37)*Q36/1000000 -> 0 | ... BN49: =MAX(0,BN38-BN37)*BN36/1000000 -> 0
D50: Non-fuel revenue | E50: USD m | G50: =SUM(J50:BN50) -> 3820.6199 | J50: =J43+J45 -> 0 | K50: =K43+K45 -> 0 | L50: =L43+L45 -> 0 | M50: =M43+M45 -> 0 | N50: =N43+N45 -> 0 | O50: =O43+O45 -> 22.595146 | P50: =P43+P45 -> 68.079504 | Q50: =Q43+Q45 -> 68.350169 | ... BN50: =BN43+BN45 -> 0
D51: Total revenue | E51: USD m | G51: =SUM(J51:BN51) -> 9544.2224 | J51: =J50+J46+J47+J48+J49 -> 0 | K51: =K50+K46+K47+K48+K49 -> 0 | L51: =L50+L46+L47+L48+L49 -> 0 | M51: =M50+M46+M47+M48+M49 -> 0 | N51: =N50+N46+N47+N48+N49 -> 0 | O51: =O50+O46+O47+O48+O49 -> 53.012678 | P51: =P50+P46+P47+P48+P49 -> 159.3815 | Q51: =Q50+Q46+Q47+Q48+Q49 -> 160.93744 | ... BN51: =BN50+BN46+BN47+BN48+BN49 -> 0
D52: Late payment interest accrued (to settlement 2024-03-21) | E52: USD m | G52: =SUM(J52:BN52) -> 0 | J52: =IF(Inputs!$F$44=1,(0+J84)/2*(J9-IF(Time!J17>=10,Inputs!$F$96,0)+Inputs!$F$184)/100*MAX(0,MIN(Time!J20,DATE(2024,3,21)-Time!J18))/360,0) -> 0 | K52: =IF(Inputs!$F$44=1,(J84+K84)/2*(K9-IF(Time!K17>=10,Inputs!$F$96,0)+Inputs!$F$184)/100*MAX(0,MIN(Time!K20,DATE(2024,3,21)-Time!K18))/360,0) -> 0 | L52: =IF(Inputs!$F$44=1,(K84+L84)/2*(L9-IF(Time!L17>=10,Inputs!$F$96,0)+Inputs!$F$184)/100*MAX(0,MIN(Time!L20,DATE(2024,3,21)-Time!L18))/360,0) -> 0 | M52: =IF(Inputs!$F$44=1,(L84+M84)/2*(M9-IF(Time!M17>=10,Inputs!$F$96,0)+Inputs!$F$184)/100*MAX(0,MIN(Time!M20,DATE(2024,3,21)-Time!M18))/360,0) -> 0 | N52: =IF(Inputs!$F$44=1,(M84+N84)/2*(N9-IF(Time!N17>=10,Inputs!$F$96,0)+Inputs!$F$184)/100*MAX(0,MIN(Time!N20,DATE(2024,3,21)-Time!N18))/360,0) -> 0 | O52: =IF(Inputs!$F$44=1,(N84+O84)/2*(O9-IF(Time!O17>=10,Inputs!$F$96,0)+Inputs!$F$184)/100*MAX(0,MIN(Time!O20,DATE(2024,3,21)-Time!O18))/360,0) -> 0 | P52: =IF(Inputs!$F$44=1,(O84+P84)/2*(P9-IF(Time!P17>=10,Inputs!$F$96,0)+Inputs!$F$184)/100*MAX(0,MIN(Time!P20,DATE(2024,3,21)-Time!P18))/360,0) -> 0 | Q52: =IF(Inputs!$F$44=1,(P84+Q84)/2*(Q9-IF(Time!Q17>=10,Inputs!$F$96,0)+Inputs!$F$184)/100*MAX(0,MIN(Time!Q20,DATE(2024,3,21)-Time!Q18))/360,0) -> 0 | R52: =IF(Inputs!$F$44=1,(Q84+R84)/2*(R9-IF(Time!R17>=10,Inputs!$F$96,0)+Inputs!$F$184)/100*MAX(0,MIN(Time!R20,DATE(2024,3,21)-Time!R18))/360,0) -> 0 | ... BN52: =IF(Inputs!$F$44=1,(BM84+BN84)/2*(BN9-IF(Time!BN17>=10,Inputs!$F$96,0)+Inputs!$F$184)/100*MAX(0,MIN(Time!BN20,DATE(2024,3,21)-Time!BN18))/360,0) -> 0
D53: Late payment interest received (60%, with settlement installments) | E53: USD m | G53: =SUM(J53:BN53) -> 0 | J53: =Inputs!$F$185*SUM($J$52:$BN$52)*Inputs!J218 -> 0 | K53: =Inputs!$F$185*SUM($J$52:$BN$52)*Inputs!K218 -> 0 | L53: =Inputs!$F$185*SUM($J$52:$BN$52)*Inputs!L218 -> 0 | M53: =Inputs!$F$185*SUM($J$52:$BN$52)*Inputs!M218 -> 0 | N53: =Inputs!$F$185*SUM($J$52:$BN$52)*Inputs!N218 -> 0 | O53: =Inputs!$F$185*SUM($J$52:$BN$52)*Inputs!O218 -> 0 | P53: =Inputs!$F$185*SUM($J$52:$BN$52)*Inputs!P218 -> 0 | Q53: =Inputs!$F$185*SUM($J$52:$BN$52)*Inputs!Q218 -> 0 | ... BN53: =Inputs!$F$185*SUM($J$52:$BN$52)*Inputs!BN218 -> 0
B54: Operating costs (USD m)
D55: O&M fixed fee | E55: USD m | G55: =SUM(J55:BN55) -> 279.35964 | J55: =Inputs!$F$148*(Inputs!$F$149*J19+(1-Inputs!$F$149)*J23*Inputs!$F$150/J11)*Time!J25/12*Inputs!$F$39 -> 0 | K55: =Inputs!$F$148*(Inputs!$F$149*K19+(1-Inputs!$F$149)*K23*Inputs!$F$150/K11)*Time!K25/12*Inputs!$F$39 -> 0 | L55: =Inputs!$F$148*(Inputs!$F$149*L19+(1-Inputs!$F$149)*L23*Inputs!$F$150/L11)*Time!L25/12*Inputs!$F$39 -> 0 | M55: =Inputs!$F$148*(Inputs!$F$149*M19+(1-Inputs!$F$149)*M23*Inputs!$F$150/M11)*Time!M25/12*Inputs!$F$39 -> 0 | N55: =Inputs!$F$148*(Inputs!$F$149*N19+(1-Inputs!$F$149)*N23*Inputs!$F$150/N11)*Time!N25/12*Inputs!$F$39 -> 0 | O55: =Inputs!$F$148*(Inputs!$F$149*O19+(1-Inputs!$F$149)*O23*Inputs!$F$150/O11)*Time!O25/12*Inputs!$F$39 -> 1.3989505 | P55: =Inputs!$F$148*(Inputs!$F$149*P19+(1-Inputs!$F$149)*P23*Inputs!$F$150/P11)*Time!P25/12*Inputs!$F$39 -> 4.2427656 | Q55: =Inputs!$F$148*(Inputs!$F$149*Q19+(1-Inputs!$F$149)*Q23*Inputs!$F$150/Q11)*Time!Q25/12*Inputs!$F$39 -> 4.2891821 | ... BN55: =Inputs!$F$148*(Inputs!$F$149*BN19+(1-Inputs!$F$149)*BN23*Inputs!$F$150/BN11)*Time!BN25/12*Inputs!$F$39 -> 0
D56: O&M availability incentive | E56: USD m | G56: =SUM(J56:BN56) -> 4.1079836 | J56: =IF(Time!J25>0,Inputs!$F$151*MAX(-1,MIN(1,(J28-92)/3))*J19*Time!J25/12,0) -> 0 | K56: =IF(Time!K25>0,Inputs!$F$151*MAX(-1,MIN(1,(K28-92)/3))*K19*Time!K25/12,0) -> 0 | L56: =IF(Time!L25>0,Inputs!$F$151*MAX(-1,MIN(1,(L28-92)/3))*L19*Time!L25/12,0) -> 0 | M56: =IF(Time!M25>0,Inputs!$F$151*MAX(-1,MIN(1,(M28-92)/3))*M19*Time!M25/12,0) -> 0 | N56: =IF(Time!N25>0,Inputs!$F$151*MAX(-1,MIN(1,(N28-92)/3))*N19*Time!N25/12,0) -> 0 | O56: =IF(Time!O25>0,Inputs!$F$151*MAX(-1,MIN(1,(O28-92)/3))*O19*Time!O25/12,0) -> 0.063700261 | P56: =IF(Time!P25>0,Inputs!$F$151*MAX(-1,MIN(1,(P28-92)/3))*P19*Time!P25/12,0) -> 0.19319146 | Q56: =IF(Time!Q25>0,Inputs!$F$151*MAX(-1,MIN(1,(Q28-92)/3))*Q19*Time!Q25/12,0) -> 0.16275417 | ... BN56: =IF(Time!BN25>0,Inputs!$F$151*MAX(-1,MIN(1,(BN28-92)/3))*BN19*Time!BN25/12,0) -> 0
D57: LTSA fixed fee | E57: USD m | G57: =SUM(J57:BN57) -> 93.283313 | J57: =Inputs!$F$152*J19*Time!J25/12*Inputs!$F$39 -> 0 | K57: =Inputs!$F$152*K19*Time!K25/12*Inputs!$F$39 -> 0 | L57: =Inputs!$F$152*L19*Time!L25/12*Inputs!$F$39 -> 0 | M57: =Inputs!$F$152*M19*Time!M25/12*Inputs!$F$39 -> 0 | N57: =Inputs!$F$152*N19*Time!N25/12*Inputs!$F$39 -> 0 | O57: =Inputs!$F$152*O19*Time!O25/12*Inputs!$F$39 -> 0.46713525 | P57: =Inputs!$F$152*P19*Time!P25/12*Inputs!$F$39 -> 1.4167373 | Q57: =Inputs!$F$152*Q19*Time!Q25/12*Inputs!$F$39 -> 1.4322367 | ... BN57: =Inputs!$F$152*BN19*Time!BN25/12*Inputs!$F$39 -> 0
D58: Equivalent operating hours (2 GTs) | E58: EOH | J58: =IF(J27>0,2*(Inputs!$F$127*J28/J27+Inputs!$F$128*Inputs!$F$129)*Time!J25/12,0) -> 0 | K58: =IF(K27>0,2*(Inputs!$F$127*K28/K27+Inputs!$F$128*Inputs!$F$129)*Time!K25/12,0) -> 0 | L58: =IF(L27>0,2*(Inputs!$F$127*L28/L27+Inputs!$F$128*Inputs!$F$129)*Time!L25/12,0) -> 0 | M58: =IF(M27>0,2*(Inputs!$F$127*M28/M27+Inputs!$F$128*Inputs!$F$129)*Time!M25/12,0) -> 0 | N58: =IF(N27>0,2*(Inputs!$F$127*N28/N27+Inputs!$F$128*Inputs!$F$129)*Time!N25/12,0) -> 0 | O58: =IF(O27>0,2*(Inputs!$F$127*O28/O27+Inputs!$F$128*Inputs!$F$129)*Time!O25/12,0) -> 2813 | P58: =IF(P27>0,2*(Inputs!$F$127*P28/P27+Inputs!$F$128*Inputs!$F$129)*Time!P25/12,0) -> 8439 | Q58: =IF(Q27>0,2*(Inputs!$F$127*Q28/Q27+Inputs!$F$128*Inputs!$F$129)*Time!Q25/12,0) -> 8439 | ... BN58: =IF(BN27>0,2*(Inputs!$F$127*BN28/BN27+Inputs!$F$128*Inputs!$F$129)*Time!BN25/12,0) -> 0
D59: LTSA variable fee | E59: USD m | G59: =SUM(J59:BN59) -> 289.83931 | J59: =J58*Inputs!$F$153*J19/1000000 -> 0 | K59: =K58*Inputs!$F$153*K19/1000000 -> 0 | L59: =L58*Inputs!$F$153*L19/1000000 -> 0 | M59: =M58*Inputs!$F$153*M19/1000000 -> 0 | N59: =N58*Inputs!$F$153*N19/1000000 -> 0 | O59: =O58*Inputs!$F$153*O19/1000000 -> 1.4514296 | P59: =P58*Inputs!$F$153*P19/1000000 -> 4.4019253 | Q59: =Q58*Inputs!$F$153*Q19/1000000 -> 4.450083 | ... BN59: =BN58*Inputs!$F$153*BN19/1000000 -> 0
D60: Operational insurance | E60: USD m | G60: =SUM(J60:BN60) -> 154.41215 | J60: =Inputs!$F$154*J19*Time!J25/12*(1+Inputs!$F$155*Inputs!$F$45*IF(Time!J17>=9,1,0))*Inputs!$F$39 -> 0 | K60: =Inputs!$F$154*K19*Time!K25/12*(1+Inputs!$F$155*Inputs!$F$45*IF(Time!K17>=9,1,0))*Inputs!$F$39 -> 0 | L60: =Inputs!$F$154*L19*Time!L25/12*(1+Inputs!$F$155*Inputs!$F$45*IF(Time!L17>=9,1,0))*Inputs!$F$39 -> 0 | M60: =Inputs!$F$154*M19*Time!M25/12*(1+Inputs!$F$155*Inputs!$F$45*IF(Time!M17>=9,1,0))*Inputs!$F$39 -> 0 | N60: =Inputs!$F$154*N19*Time!N25/12*(1+Inputs!$F$155*Inputs!$F$45*IF(Time!N17>=9,1,0))*Inputs!$F$39 -> 0 | O60: =Inputs!$F$154*O19*Time!O25/12*(1+Inputs!$F$155*Inputs!$F$45*IF(Time!O17>=9,1,0))*Inputs!$F$39 -> 0.77325039 | P60: =Inputs!$F$154*P19*Time!P25/12*(1+Inputs!$F$155*Inputs!$F$45*IF(Time!P17>=9,1,0))*Inputs!$F$39 -> 2.3451296 | Q60: =Inputs!$F$154*Q19*Time!Q25/12*(1+Inputs!$F$155*Inputs!$F$45*IF(Time!Q17>=9,1,0))*Inputs!$F$39 -> 2.3707857 | ... BN60: =Inputs!$F$154*BN19*Time!BN25/12*(1+Inputs!$F$155*Inputs!$F$45*IF(Time!BN17>=9,1,0))*Inputs!$F$39 -> 0
D61: G&A | E61: USD m | G61: =SUM(J61:BN61) -> 112.08276 | J61: =Inputs!$F$156*(0.5*J19+0.5*J23*Inputs!$F$150/J11)*Time!J25/12*Inputs!$F$39 -> 0 | K61: =Inputs!$F$156*(0.5*K19+0.5*K23*Inputs!$F$150/K11)*Time!K25/12*Inputs!$F$39 -> 0 | L61: =Inputs!$F$156*(0.5*L19+0.5*L23*Inputs!$F$150/L11)*Time!L25/12*Inputs!$F$39 -> 0 | M61: =Inputs!$F$156*(0.5*M19+0.5*M23*Inputs!$F$150/M11)*Time!M25/12*Inputs!$F$39 -> 0 | N61: =Inputs!$F$156*(0.5*N19+0.5*N23*Inputs!$F$150/N11)*Time!N25/12*Inputs!$F$39 -> 0 | O61: =Inputs!$F$156*(0.5*O19+0.5*O23*Inputs!$F$150/O11)*Time!O25/12*Inputs!$F$39 -> 0.5612773 | P61: =Inputs!$F$156*(0.5*P19+0.5*P23*Inputs!$F$150/P11)*Time!P25/12*Inputs!$F$39 -> 1.7022533 | Q61: =Inputs!$F$156*(0.5*Q19+0.5*Q23*Inputs!$F$150/Q11)*Time!Q25/12*Inputs!$F$39 -> 1.7208762 | ... BN61: =Inputs!$F$156*(0.5*BN19+0.5*BN23*Inputs!$F$150/BN11)*Time!BN25/12*Inputs!$F$39 -> 0
D62: Land lease and permits | E62: USD m | G62: =SUM(J62:BN62) -> 25.034903 | J62: =Inputs!$F$157*J23/J11*Time!J25/12*Inputs!$F$39 -> 0 | K62: =Inputs!$F$157*K23/K11*Time!K25/12*Inputs!$F$39 -> 0 | L62: =Inputs!$F$157*L23/L11*Time!L25/12*Inputs!$F$39 -> 0 | M62: =Inputs!$F$157*M23/M11*Time!M25/12*Inputs!$F$39 -> 0 | N62: =Inputs!$F$157*N23/N11*Time!N25/12*Inputs!$F$39 -> 0 | O62: =Inputs!$F$157*O23/O11*Time!O25/12*Inputs!$F$39 -> 0.12536739 | P62: =Inputs!$F$157*P23/P11*Time!P25/12*Inputs!$F$39 -> 0.38021679 | Q62: =Inputs!$F$157*Q23/Q11*Time!Q25/12*Inputs!$F$39 -> 0.38437642 | ... BN62: =Inputs!$F$157*BN23/BN11*Time!BN25/12*Inputs!$F$39 -> 0
D63: Community fund and OREK levy | E63: USD m | G63: =SUM(J63:BN63) -> 21.01341 | J63: =Inputs!$F$158/100*J50 -> 0 | K63: =Inputs!$F$158/100*K50 -> 0 | L63: =Inputs!$F$158/100*L50 -> 0 | M63: =Inputs!$F$158/100*M50 -> 0 | N63: =Inputs!$F$158/100*N50 -> 0 | O63: =Inputs!$F$158/100*O50 -> 0.12427331 | P63: =Inputs!$F$158/100*P50 -> 0.37443727 | Q63: =Inputs!$F$158/100*Q50 -> 0.37592593 | ... BN63: =Inputs!$F$158/100*BN50 -> 0
D64: Variable consumables | E64: USD m | G64: =SUM(J64:BN64) -> 134.8703 | J64: =Inputs!$F$159*(0.7*J19+0.3*J23*Inputs!$F$150/J11)*J33/1000000 -> 0 | K64: =Inputs!$F$159*(0.7*K19+0.3*K23*Inputs!$F$150/K11)*K33/1000000 -> 0 | L64: =Inputs!$F$159*(0.7*L19+0.3*L23*Inputs!$F$150/L11)*L33/1000000 -> 0 | M64: =Inputs!$F$159*(0.7*M19+0.3*M23*Inputs!$F$150/M11)*M33/1000000 -> 0 | N64: =Inputs!$F$159*(0.7*N19+0.3*N23*Inputs!$F$150/N11)*N33/1000000 -> 0 | O64: =Inputs!$F$159*(0.7*O19+0.3*O23*Inputs!$F$150/O11)*O33/1000000 -> 0.69860507 | P64: =Inputs!$F$159*(0.7*P19+0.3*P23*Inputs!$F$150/P11)*P33/1000000 -> 2.1176842 | Q64: =Inputs!$F$159*(0.7*Q19+0.3*Q23*Inputs!$F$150/Q11)*Q33/1000000 -> 2.1324035 | ... BN64: =Inputs!$F$159*(0.7*BN19+0.3*BN23*Inputs!$F$150/BN11)*BN33/1000000 -> 0
D65: Agency and account fees | E65: USD m | G65: =SUM(J65:BN65) -> 6.375 | J65: =Inputs!$F$105*Time!J25/12 -> 0 | K65: =Inputs!$F$105*Time!K25/12 -> 0 | L65: =Inputs!$F$105*Time!L25/12 -> 0 | M65: =Inputs!$F$105*Time!M25/12 -> 0 | N65: =Inputs!$F$105*Time!N25/12 -> 0 | O65: =Inputs!$F$105*Time!O25/12 -> 0.0425 | P65: =Inputs!$F$105*Time!P25/12 -> 0.1275 | Q65: =Inputs!$F$105*Time!Q25/12 -> 0.1275 | ... BN65: =Inputs!$F$105*Time!BN25/12 -> 0
D66: ABDB PRG fee | E66: USD m | G66: =SUM(J66:BN66) -> 7.78125 | J66: =Inputs!$F$160*Time!J25/12 -> 0 | K66: =Inputs!$F$160*Time!K25/12 -> 0 | L66: =Inputs!$F$160*Time!L25/12 -> 0 | M66: =Inputs!$F$160*Time!M25/12 -> 0 | N66: =Inputs!$F$160*Time!N25/12 -> 0 | O66: =Inputs!$F$160*Time!O25/12 -> 0.051875 | P66: =Inputs!$F$160*Time!P25/12 -> 0.155625 | Q66: =Inputs!$F$160*Time!Q25/12 -> 0.155625 | ... BN66: =Inputs!$F$160*Time!BN25/12 -> 0
D67: Operating costs before pass-through items | E67: USD m | G67: =SUM(J67:BN67) -> 1128.16 | J67: =J55+J56+J57+J59+J60+J61+J62+J63+J64+J65+J66 -> 0 | K67: =K55+K56+K57+K59+K60+K61+K62+K63+K64+K65+K66 -> 0 | L67: =L55+L56+L57+L59+L60+L61+L62+L63+L64+L65+L66 -> 0 | M67: =M55+M56+M57+M59+M60+M61+M62+M63+M64+M65+M66 -> 0 | N67: =N55+N56+N57+N59+N60+N61+N62+N63+N64+N65+N66 -> 0 | O67: =O55+O56+O57+O59+O60+O61+O62+O63+O64+O65+O66 -> 5.758364 | P67: =P55+P56+P57+P59+P60+P61+P62+P63+P64+P65+P66 -> 17.457466 | Q67: =Q55+Q56+Q57+Q59+Q60+Q61+Q62+Q63+Q64+Q65+Q66 -> 17.601749 | ... BN67: =BN55+BN56+BN57+BN59+BN60+BN61+BN62+BN63+BN64+BN65+BN66 -> 0
D68: Gas purchases | E68: USD m | G68: =SUM(J68:BN68) -> 4890.5537 | J68: =J37*J36/1000000 -> 0 | K68: =K37*K36/1000000 -> 0 | L68: =L37*L36/1000000 -> 0 | M68: =M37*M36/1000000 -> 0 | N68: =N37*N36/1000000 -> 0 | O68: =O37*O36/1000000 -> 25.730983 | P68: =P37*P36/1000000 -> 77.185206 | Q68: =Q37*Q36/1000000 -> 78.465244 | ... BN68: =BN37*BN36/1000000 -> 0
D69: Pass-through costs (gas, GTA, take-or-pay) | E69: USD m | G69: =SUM(J69:BN69) -> 5727.3299 | J69: =J68+J47+J48+J49 -> 0 | K69: =K68+K47+K48+K49 -> 0 | L69: =L68+L47+L48+L49 -> 0 | M69: =M68+M47+M48+M49 -> 0 | N69: =N68+N47+N48+N49 -> 0 | O69: =O68+O47+O48+O49 -> 30.369394 | P69: =P68+P47+P48+P49 -> 91.162756 | Q69: =Q68+Q47+Q48+Q49 -> 92.453571 | ... BN69: =BN68+BN47+BN48+BN49 -> 0
D70: VAT facility interest after the funding period | E70: USD m | G70: =SUM(J70:BN70) -> 0.12253688 | J70: =SUMIFS(Construction!$J$36:$BJ$36,Construction!$J$12:$BJ$12,Time!J17,Construction!$J$8:$BJ$8,">"&Time!$F$13) -> 0 | K70: =SUMIFS(Construction!$J$36:$BJ$36,Construction!$J$12:$BJ$12,Time!K17,Construction!$J$8:$BJ$8,">"&Time!$F$13) -> 0 | L70: =SUMIFS(Construction!$J$36:$BJ$36,Construction!$J$12:$BJ$12,Time!L17,Construction!$J$8:$BJ$8,">"&Time!$F$13) -> 0 | M70: =SUMIFS(Construction!$J$36:$BJ$36,Construction!$J$12:$BJ$12,Time!M17,Construction!$J$8:$BJ$8,">"&Time!$F$13) -> 0 | N70: =SUMIFS(Construction!$J$36:$BJ$36,Construction!$J$12:$BJ$12,Time!N17,Construction!$J$8:$BJ$8,">"&Time!$F$13) -> 0 | O70: =SUMIFS(Construction!$J$36:$BJ$36,Construction!$J$12:$BJ$12,Time!O17,Construction!$J$8:$BJ$8,">"&Time!$F$13) -> 0 | P70: =SUMIFS(Construction!$J$36:$BJ$36,Construction!$J$12:$BJ$12,Time!P17,Construction!$J$8:$BJ$8,">"&Time!$F$13) -> 0.10851031 | Q70: =SUMIFS(Construction!$J$36:$BJ$36,Construction!$J$12:$BJ$12,Time!Q17,Construction!$J$8:$BJ$8,">"&Time!$F$13) -> 0.014026572 | ... BN70: =SUMIFS(Construction!$J$36:$BJ$36,Construction!$J$12:$BJ$12,Time!BN17,Construction!$J$8:$BJ$8,">"&Time!$F$13) -> 0
D71: FX conversion losses | E71: USD m | G71: =SUM(J71:BN71) -> 0 | J71: =Inputs!$F$44*Inputs!J217 -> 0 | K71: =Inputs!$F$44*Inputs!K217 -> 0 | L71: =Inputs!$F$44*Inputs!L217 -> 0 | M71: =Inputs!$F$44*Inputs!M217 -> 0 | N71: =Inputs!$F$44*Inputs!N217 -> 0 | O71: =Inputs!$F$44*Inputs!O217 -> 0 | P71: =Inputs!$F$44*Inputs!P217 -> 0 | Q71: =Inputs!$F$44*Inputs!Q217 -> 0 | ... BN71: =Inputs!$F$44*Inputs!BN217 -> 0
D72: OY whose month 7 could fall in the period | E72: OY | J72: =INT((Time!J28-7)/12)+1 -> 0 | K72: =INT((Time!K28-7)/12)+1 -> 0 | L72: =INT((Time!L28-7)/12)+1 -> 0 | M72: =INT((Time!M28-7)/12)+1 -> 0 | N72: =INT((Time!N28-7)/12)+1 -> 0 | O72: =INT((Time!O28-7)/12)+1 -> 0 | P72: =INT((Time!P28-7)/12)+1 -> 1 | Q72: =INT((Time!Q28-7)/12)+1 -> 1 | ... BN72: =INT((Time!BN28-7)/12)+1 -> 25
D73: Major maintenance outside LTSA (2018 prices) | E73: USD m | J73: =IF(AND(Time!J25>0,J72>=1,J72<=24,Time!J27<(J72-1)*12+7,(J72-1)*12+7<=Time!J28),IF(MOD(J72,8)=0,Inputs!$F$161,IF(MOD(J72,4)=0,Inputs!$F$162,0)),0) -> 0 | K73: =IF(AND(Time!K25>0,K72>=1,K72<=24,Time!K27<(K72-1)*12+7,(K72-1)*12+7<=Time!K28),IF(MOD(K72,8)=0,Inputs!$F$161,IF(MOD(K72,4)=0,Inputs!$F$162,0)),0) -> 0 | L73: =IF(AND(Time!L25>0,L72>=1,L72<=24,Time!L27<(L72-1)*12+7,(L72-1)*12+7<=Time!L28),IF(MOD(L72,8)=0,Inputs!$F$161,IF(MOD(L72,4)=0,Inputs!$F$162,0)),0) -> 0 | M73: =IF(AND(Time!M25>0,M72>=1,M72<=24,Time!M27<(M72-1)*12+7,(M72-1)*12+7<=Time!M28),IF(MOD(M72,8)=0,Inputs!$F$161,IF(MOD(M72,4)=0,Inputs!$F$162,0)),0) -> 0 | N73: =IF(AND(Time!N25>0,N72>=1,N72<=24,Time!N27<(N72-1)*12+7,(N72-1)*12+7<=Time!N28),IF(MOD(N72,8)=0,Inputs!$F$161,IF(MOD(N72,4)=0,Inputs!$F$162,0)),0) -> 0 | O73: =IF(AND(Time!O25>0,O72>=1,O72<=24,Time!O27<(O72-1)*12+7,(O72-1)*12+7<=Time!O28),IF(MOD(O72,8)=0,Inputs!$F$161,IF(MOD(O72,4)=0,Inputs!$F$162,0)),0) -> 0 | P73: =IF(AND(Time!P25>0,P72>=1,P72<=24,Time!P27<(P72-1)*12+7,(P72-1)*12+7<=Time!P28),IF(MOD(P72,8)=0,Inputs!$F$161,IF(MOD(P72,4)=0,Inputs!$F$162,0)),0) -> 0 | Q73: =IF(AND(Time!Q25>0,Q72>=1,Q72<=24,Time!Q27<(Q72-1)*12+7,(Q72-1)*12+7<=Time!Q28),IF(MOD(Q72,8)=0,Inputs!$F$161,IF(MOD(Q72,4)=0,Inputs!$F$162,0)),0) -> 0 | ... BN73: =IF(AND(Time!BN25>0,BN72>=1,BN72<=24,Time!BN27<(BN72-1)*12+7,(BN72-1)*12+7<=Time!BN28),IF(MOD(BN72,8)=0,Inputs!$F$161,IF(MOD(BN72,4)=0,Inputs!$F$162,0)),0) -> 0
D74: Major maintenance spend | E74: USD m | G74: =SUM(J74:BN74) -> 51.698065 | J74: =J73*J19 -> 0 | K74: =K73*K19 -> 0 | L74: =L73*L19 -> 0 | M74: =M73*M19 -> 0 | N74: =N73*N19 -> 0 | O74: =O73*O19 -> 0 | P74: =P73*P19 -> 0 | Q74: =Q73*Q19 -> 0 | ... BN74: =BN73*BN19 -> 0
D75: Months in period from OY20 | E75: months | J75: =MAX(0,MIN(Time!J28,300)-MAX(Time!J27,228)) -> 0 | K75: =MAX(0,MIN(Time!K28,300)-MAX(Time!K27,228)) -> 0 | L75: =MAX(0,MIN(Time!L28,300)-MAX(Time!L27,228)) -> 0 | M75: =MAX(0,MIN(Time!M28,300)-MAX(Time!M27,228)) -> 0 | N75: =MAX(0,MIN(Time!N28,300)-MAX(Time!N27,228)) -> 0 | O75: =MAX(0,MIN(Time!O28,300)-MAX(Time!O27,228)) -> 0 | P75: =MAX(0,MIN(Time!P28,300)-MAX(Time!P27,228)) -> 0 | Q75: =MAX(0,MIN(Time!Q28,300)-MAX(Time!Q27,228)) -> 0 | ... BN75: =MAX(0,MIN(Time!BN28,300)-MAX(Time!BN27,228)) -> 0
D76: Handback reserve contribution required | E76: USD m | G76: =SUM(J76:BN76) -> 19.06919 | J76: =Inputs!$F$163*J19*J75/12 -> 0 | K76: =Inputs!$F$163*K19*K75/12 -> 0 | L76: =Inputs!$F$163*L19*L75/12 -> 0 | M76: =Inputs!$F$163*M19*M75/12 -> 0 | N76: =Inputs!$F$163*N19*N75/12 -> 0 | O76: =Inputs!$F$163*O19*O75/12 -> 0 | P76: =Inputs!$F$163*P19*P75/12 -> 0 | Q76: =Inputs!$F$163*Q19*Q75/12 -> 0 | ... BN76: =Inputs!$F$163*BN19*BN75/12 -> 0
D77: Handback works at PPA expiry | E77: USD m | G77: =SUM(J77:BN77) -> 19.06919 | J77: =Time!J32*SUM($J$76:$BN$76) -> 0 | K77: =Time!K32*SUM($J$76:$BN$76) -> 0 | L77: =Time!L32*SUM($J$76:$BN$76) -> 0 | M77: =Time!M32*SUM($J$76:$BN$76) -> 0 | N77: =Time!N32*SUM($J$76:$BN$76) -> 0 | O77: =Time!O32*SUM($J$76:$BN$76) -> 0 | P77: =Time!P32*SUM($J$76:$BN$76) -> 0 | Q77: =Time!Q32*SUM($J$76:$BN$76) -> 0 | ... BN77: =Time!BN32*SUM($J$76:$BN$76) -> 0
D78: Total operating costs | E78: USD m | G78: =SUM(J78:BN78) -> 6926.3797 | J78: =J67+J69+J70+J71+J74+J77 -> 0 | K78: =K67+K69+K70+K71+K74+K77 -> 0 | L78: =L67+L69+L70+L71+L74+L77 -> 0 | M78: =M67+M69+M70+M71+M74+M77 -> 0 | N78: =N67+N69+N70+N71+N74+N77 -> 0 | O78: =O67+O69+O70+O71+O74+O77 -> 36.127758 | P78: =P67+P69+P70+P71+P74+P77 -> 108.72873 | Q78: =Q67+Q69+Q70+Q71+Q74+Q77 -> 110.06935 | ... BN78: =BN67+BN69+BN70+BN71+BN74+BN77 -> 0
D79: EBITDA | E79: USD m | G79: =SUM(J79:BN79) -> 2617.8426 | J79: =J51-J78+J53 -> 0 | K79: =K51-K78+K53 -> 0 | L79: =L51-L78+L53 -> 0 | M79: =M51-M78+M53 -> 0 | N79: =N51-N78+N53 -> 0 | O79: =O51-O78+O53 -> 16.884919 | P79: =P51-P78+P53 -> 50.652771 | Q79: =Q51-Q78+Q53 -> 50.868098 | ... BN79: =BN51-BN78+BN53 -> 0
B80: Working capital (USD m, period-end balances)
D81: Flag: final operating period or later (working capital unwinds) | E81: flag | J81: =IF(Time!J17>=Time!$F$14,1,0) -> 0 | K81: =IF(Time!K17>=Time!$F$14,1,0) -> 0 | L81: =IF(Time!L17>=Time!$F$14,1,0) -> 0 | M81: =IF(Time!M17>=Time!$F$14,1,0) -> 0 | N81: =IF(Time!N17>=Time!$F$14,1,0) -> 0 | O81: =IF(Time!O17>=Time!$F$14,1,0) -> 0 | P81: =IF(Time!P17>=Time!$F$14,1,0) -> 0 | Q81: =IF(Time!Q17>=Time!$F$14,1,0) -> 0 | ... BN81: =IF(Time!BN17>=Time!$F$14,1,0) -> 1
D82: Extra receivable days on capacity and VOM (sensitivities) | E82: days | J82: =Inputs!$F$43*Time!J33 -> 0 | K82: =Inputs!$F$43*Time!K33 -> 0 | L82: =Inputs!$F$43*Time!L33 -> 0 | M82: =Inputs!$F$43*Time!M33 -> 0 | N82: =Inputs!$F$43*Time!N33 -> 0 | O82: =Inputs!$F$43*Time!O33 -> 0 | P82: =Inputs!$F$43*Time!P33 -> 0 | Q82: =Inputs!$F$43*Time!Q33 -> 0 | ... BN82: =Inputs!$F$43*Time!BN33 -> 0
D83: Trade receivables (normal terms) | E83: USD m | J83: =(1-J81)*(J51/MAX(Time!J26,1)*Inputs!$F$165+J50/MAX(Time!J26,1)*J82) -> 0 | K83: =(1-K81)*(K51/MAX(Time!K26,1)*Inputs!$F$165+K50/MAX(Time!K26,1)*K82) -> 0 | L83: =(1-L81)*(L51/MAX(Time!L26,1)*Inputs!$F$165+L50/MAX(Time!L26,1)*L82) -> 0 | M83: =(1-M81)*(M51/MAX(Time!M26,1)*Inputs!$F$165+M50/MAX(Time!M26,1)*M82) -> 0 | N83: =(1-N81)*(N51/MAX(Time!N26,1)*Inputs!$F$165+N50/MAX(Time!N26,1)*N82) -> 0 | O83: =(1-O81)*(O51/MAX(Time!O26,1)*Inputs!$F$165+O50/MAX(Time!O26,1)*O82) -> 39.107713 | P83: =(1-P81)*(P51/MAX(Time!P26,1)*Inputs!$F$165+P50/MAX(Time!P26,1)*P82) -> 38.979172 | Q83: =(1-Q81)*(Q51/MAX(Time!Q26,1)*Inputs!$F$165+Q50/MAX(Time!Q26,1)*Q82) -> 40.012072 | ... BN83: =(1-BN81)*(BN51/MAX(Time!BN26,1)*Inputs!$F$165+BN50/MAX(Time!BN26,1)*BN82) -> 0
D84: SEKA overdue receivables | E84: USD m | J84: =Inputs!$F$44*Inputs!J216 -> 0 | K84: =Inputs!$F$44*Inputs!K216 -> 0 | L84: =Inputs!$F$44*Inputs!L216 -> 0 | M84: =Inputs!$F$44*Inputs!M216 -> 0 | N84: =Inputs!$F$44*Inputs!N216 -> 0 | O84: =Inputs!$F$44*Inputs!O216 -> 0 | P84: =Inputs!$F$44*Inputs!P216 -> 0 | Q84: =Inputs!$F$44*Inputs!Q216 -> 0 | ... BN84: =Inputs!$F$44*Inputs!BN216 -> 0
D85: Gas payables | E85: USD m | J85: =(1-J81)*(J68+J49)/MAX(Time!J26,1)*Inputs!$F$166 -> 0 | K85: =(1-K81)*(K68+K49)/MAX(Time!K26,1)*Inputs!$F$166 -> 0 | L85: =(1-L81)*(L68+L49)/MAX(Time!L26,1)*Inputs!$F$166 -> 0 | M85: =(1-M81)*(M68+M49)/MAX(Time!M26,1)*Inputs!$F$166 -> 0 | N85: =(1-N81)*(N68+N49)/MAX(Time!N26,1)*Inputs!$F$166 -> 0 | O85: =(1-O81)*(O68+O49)/MAX(Time!O26,1)*Inputs!$F$166 -> 18.981873 | P85: =(1-P81)*(P68+P49)/MAX(Time!P26,1)*Inputs!$F$166 -> 18.876817 | Q85: =(1-Q81)*(Q68+Q49)/MAX(Time!Q26,1)*Inputs!$F$166 -> 19.507934 | ... BN85: =(1-BN81)*(BN68+BN49)/MAX(Time!BN26,1)*Inputs!$F$166 -> 0
D86: GTA payables | E86: USD m | J86: =(1-J81)*(J47+J48)/MAX(Time!J26,1)*Inputs!$F$167 -> 0 | K86: =(1-K81)*(K47+K48)/MAX(Time!K26,1)*Inputs!$F$167 -> 0 | L86: =(1-L81)*(L47+L48)/MAX(Time!L26,1)*Inputs!$F$167 -> 0 | M86: =(1-M81)*(M47+M48)/MAX(Time!M26,1)*Inputs!$F$167 -> 0 | N86: =(1-N81)*(N47+N48)/MAX(Time!N26,1)*Inputs!$F$167 -> 0 | O86: =(1-O81)*(O47+O48)/MAX(Time!O26,1)*Inputs!$F$167 -> 2.2811859 | P86: =(1-P81)*(P47+P48)/MAX(Time!P26,1)*Inputs!$F$167 -> 2.2789483 | Q86: =(1-Q81)*(Q47+Q48)/MAX(Time!Q26,1)*Inputs!$F$167 -> 2.3185071 | ... BN86: =(1-BN81)*(BN47+BN48)/MAX(Time!BN26,1)*Inputs!$F$167 -> 0
D87: O&M and LTSA payables | E87: USD m | J87: =(1-J81)*(J55+J56+J57+J59)/MAX(Time!J26,1)*Inputs!$F$168 -> 0 | K87: =(1-K81)*(K55+K56+K57+K59)/MAX(Time!K26,1)*Inputs!$F$168 -> 0 | L87: =(1-L81)*(L55+L56+L57+L59)/MAX(Time!L26,1)*Inputs!$F$168 -> 0 | M87: =(1-M81)*(M55+M56+M57+M59)/MAX(Time!M26,1)*Inputs!$F$168 -> 0 | N87: =(1-N81)*(N55+N56+N57+N59)/MAX(Time!N26,1)*Inputs!$F$168 -> 0 | O87: =(1-O81)*(O55+O56+O57+O59)/MAX(Time!O26,1)*Inputs!$F$168 -> 1.6628929 | P87: =(1-P81)*(P55+P56+P57+P59)/MAX(Time!P26,1)*Inputs!$F$168 -> 1.6719489 | Q87: =(1-Q81)*(Q55+Q56+Q57+Q59)/MAX(Time!Q26,1)*Inputs!$F$168 -> 1.7128601 | ... BN87: =(1-BN81)*(BN55+BN56+BN57+BN59)/MAX(Time!BN26,1)*Inputs!$F$168 -> 0
D88: Other payables | E88: USD m | J88: =(1-J81)*(J60+J61+J62+J63+J64+J65+J66)/MAX(Time!J26,1)*Inputs!$F$169 -> 0 | K88: =(1-K81)*(K60+K61+K62+K63+K64+K65+K66)/MAX(Time!K26,1)*Inputs!$F$169 -> 0 | L88: =(1-L81)*(L60+L61+L62+L63+L64+L65+L66)/MAX(Time!L26,1)*Inputs!$F$169 -> 0 | M88: =(1-M81)*(M60+M61+M62+M63+M64+M65+M66)/MAX(Time!M26,1)*Inputs!$F$169 -> 0 | N88: =(1-N81)*(N60+N61+N62+N63+N64+N65+N66)/MAX(Time!N26,1)*Inputs!$F$169 -> 0 | O88: =(1-O81)*(O60+O61+O62+O63+O64+O65+O66)/MAX(Time!O26,1)*Inputs!$F$169 -> 1.1690894 | P88: =(1-P81)*(P60+P61+P62+P63+P64+P65+P66)/MAX(Time!P26,1)*Inputs!$F$169 -> 1.1743771 | Q88: =(1-Q81)*(Q60+Q61+Q62+Q63+Q64+Q65+Q66)/MAX(Time!Q26,1)*Inputs!$F$169 -> 1.2045568 | ... BN88: =(1-BN81)*(BN60+BN61+BN62+BN63+BN64+BN65+BN66)/MAX(Time!BN26,1)*Inputs!$F$169 -> 0
D89: Deferred SNHK/GCK payables matching SEKA energy-charge arrears | E89: USD m | J89: =Inputs!$F$183*J84 -> 0 | K89: =Inputs!$F$183*K84 -> 0 | L89: =Inputs!$F$183*L84 -> 0 | M89: =Inputs!$F$183*M84 -> 0 | N89: =Inputs!$F$183*N84 -> 0 | O89: =Inputs!$F$183*O84 -> 0 | P89: =Inputs!$F$183*P84 -> 0 | Q89: =Inputs!$F$183*Q84 -> 0 | ... BN89: =Inputs!$F$183*BN84 -> 0
D90: Net working capital (excl. spares inventory) | E90: USD m | J90: =J83+J84-J85-J86-J87-J88-J89 -> 0 | K90: =K83+K84-K85-K86-K87-K88-K89 -> 0 | L90: =L83+L84-L85-L86-L87-L88-L89 -> 0 | M90: =M83+M84-M85-M86-M87-M88-M89 -> 0 | N90: =N83+N84-N85-N86-N87-N88-N89 -> 0 | O90: =O83+O84-O85-O86-O87-O88-O89 -> 15.012672 | P90: =P83+P84-P85-P86-P87-P88-P89 -> 14.977081 | Q90: =Q83+Q84-Q85-Q86-Q87-Q88-Q89 -> 15.268214 | ... BN90: =BN83+BN84-BN85-BN86-BN87-BN88-BN89 -> 0
D91: Increase in net working capital | E91: USD m | G91: =SUM(J91:BN91) -> 0 | J91: =J90-0 -> 0 | K91: =K90-J90 -> 0 | L91: =L90-K90 -> 0 | M91: =M90-L90 -> 0 | N91: =N90-M90 -> 0 | O91: =O90-N90 -> 15.012672 | P91: =P90-O90 -> -0.035591104 | Q91: =Q90-P90 -> 0.29113303 | R91: =R90-Q90 -> -0.19330016 | ... BN91: =BN90-BM90 -> 0
D92: Release of spares inventory at expiry | E92: USD m | G92: =SUM(J92:BN92) -> 5.885 | J92: =Time!J32*Inputs!$F$65*Inputs!$F$35 -> 0 | K92: =Time!K32*Inputs!$F$65*Inputs!$F$35 -> 0 | L92: =Time!L32*Inputs!$F$65*Inputs!$F$35 -> 0 | M92: =Time!M32*Inputs!$F$65*Inputs!$F$35 -> 0 | N92: =Time!N32*Inputs!$F$65*Inputs!$F$35 -> 0 | O92: =Time!O32*Inputs!$F$65*Inputs!$F$35 -> 0 | P92: =Time!P32*Inputs!$F$65*Inputs!$F$35 -> 0 | Q92: =Time!Q32*Inputs!$F$65*Inputs!$F$35 -> 0 | ... BN92: =Time!BN32*Inputs!$F$65*Inputs!$F$35 -> 0

Sheet Tax
A1: Case P: Belanou Combined Cycle Power Project, Republic of Kessara
A2: Tax: holiday, deferred depreciation, thin capitalization, minimum turnover tax
A3: Units in column E; constants in column F; row totals in column G; first period in column J. Inputs: blue on yellow. Links from other sheets: green.
D4: Label | E4: Unit | F4: Constant | G4: Total
D5: Period ending | J5: 2018H2 | K5: 2019H1 | L5: 2019H2 | M5: 2020H1 | N5: 2020H2 | O5: 2021H1 | P5: 2021H2 | Q5: 2022H1 | R5: 2022H2 | S5: 2023H1 | T5: 2023H2 | U5: 2024H1 | V5: 2024H2 | W5: 2025H1 | X5: 2025H2 | Y5: 2026H1 | Z5: 2026H2 | AA5: 2027H1 | AB5: 2027H2 | AC5: 2028H1 | AD5: 2028H2 | AE5: 2029H1 | AF5: 2029H2 | AG5: 2030H1 | AH5: 2030H2 | AI5: 2031H1 | AJ5: 2031H2 | AK5: 2032H1 | AL5: 2032H2 | AM5: 2033H1 | AN5: 2033H2 | AO5: 2034H1 | AP5: 2034H2 | AQ5: 2035H1 | AR5: 2035H2 | AS5: 2036H1 | AT5: 2036H2 | AU5: 2037H1 | AV5: 2037H2 | AW5: 2038H1 | AX5: 2038H2 | AY5: 2039H1 | AZ5: 2039H2 | BA5: 2040H1 | BB5: 2040H2 | BC5: 2041H1 | BD5: 2041H2 | BE5: 2042H1 | BF5: 2042H2 | BG5: 2043H1 | BH5: 2043H2 | BI5: 2044H1 | BJ5: 2044H2 | BK5: 2045H1 | BL5: 2045H2 | BM5: 2046H1 | BN5: 2046H2
D7: Holiday months (OY1-OY5) | E7: months | J7: =MAX(0,MIN(Time!J28,60)-MIN(Time!J27,60)) -> 0 | K7: =MAX(0,MIN(Time!K28,60)-MIN(Time!K27,60)) -> 0 | L7: =MAX(0,MIN(Time!L28,60)-MIN(Time!L27,60)) -> 0 | M7: =MAX(0,MIN(Time!M28,60)-MIN(Time!M27,60)) -> 0 | N7: =MAX(0,MIN(Time!N28,60)-MIN(Time!N27,60)) -> 0 | O7: =MAX(0,MIN(Time!O28,60)-MIN(Time!O27,60)) -> 2 | P7: =MAX(0,MIN(Time!P28,60)-MIN(Time!P27,60)) -> 6 | Q7: =MAX(0,MIN(Time!Q28,60)-MIN(Time!Q27,60)) -> 6 | ... BN7: =MAX(0,MIN(Time!BN28,60)-MIN(Time!BN27,60)) -> 0
D8: Reduced-rate months (OY6-OY8) | E8: months | J8: =MAX(0,MIN(Time!J28,96)-MIN(MAX(Time!J27,60),96)) -> 0 | K8: =MAX(0,MIN(Time!K28,96)-MIN(MAX(Time!K27,60),96)) -> 0 | L8: =MAX(0,MIN(Time!L28,96)-MIN(MAX(Time!L27,60),96)) -> 0 | M8: =MAX(0,MIN(Time!M28,96)-MIN(MAX(Time!M27,60),96)) -> 0 | N8: =MAX(0,MIN(Time!N28,96)-MIN(MAX(Time!N27,60),96)) -> 0 | O8: =MAX(0,MIN(Time!O28,96)-MIN(MAX(Time!O27,60),96)) -> 0 | P8: =MAX(0,MIN(Time!P28,96)-MIN(MAX(Time!P27,60),96)) -> 0 | Q8: =MAX(0,MIN(Time!Q28,96)-MIN(MAX(Time!Q27,60),96)) -> 0 | ... BN8: =MAX(0,MIN(Time!BN28,96)-MIN(MAX(Time!BN27,60),96)) -> 0
D9: Full-rate months (OY9+) | E9: months | J9: =Time!J25-J7-J8 -> 0 | K9: =Time!K25-K7-K8 -> 0 | L9: =Time!L25-L7-L8 -> 0 | M9: =Time!M25-M7-M8 -> 0 | N9: =Time!N25-N7-N8 -> 0 | O9: =Time!O25-O7-O8 -> 0 | P9: =Time!P25-P7-P8 -> 0 | Q9: =Time!Q25-Q7-Q8 -> 0 | ... BN9: =Time!BN25-BN7-BN8 -> 0
D10: Tax depreciation (straight line from COD) | E10: USD m | G10: =SUM(J10:BN10) -> 916.09922 | J10: =Inputs!$F$174*Funding!$F$76/Inputs!$F$175*MAX(0,MIN(Time!J28,Inputs!$F$175)-MIN(Time!J27,Inputs!$F$175))+Inputs!$F$176*Funding!$F$76/Inputs!$F$177*MAX(0,MIN(Time!J28,Inputs!$F$177)-MIN(Time!J27,Inputs!$F$177))+Inputs!$F$178*Funding!$F$76/Inputs!$F$179*MAX(0,MIN(Time!J28,Inputs!$F$179)-MIN(Time!J27,Inputs!$F$179)) -> 0 | K10: =Inputs!$F$174*Funding!$F$76/Inputs!$F$175*MAX(0,MIN(Time!K28,Inputs!$F$175)-MIN(Time!K27,Inputs!$F$175))+Inputs!$F$176*Funding!$F$76/Inputs!$F$177*MAX(0,MIN(Time!K28,Inputs!$F$177)-MIN(Time!K27,Inputs!$F$177))+Inputs!$F$178*Funding!$F$76/Inputs!$F$179*MAX(0,MIN(Time!K28,Inputs!$F$179)-MIN(Time!K27,Inputs!$F$179)) -> 0 | L10: =Inputs!$F$174*Funding!$F$76/Inputs!$F$175*MAX(0,MIN(Time!L28,Inputs!$F$175)-MIN(Time!L27,Inputs!$F$175))+Inputs!$F$176*Funding!$F$76/Inputs!$F$177*MAX(0,MIN(Time!L28,Inputs!$F$177)-MIN(Time!L27,Inputs!$F$177))+Inputs!$F$178*Funding!$F$76/Inputs!$F$179*MAX(0,MIN(Time!L28,Inputs!$F$179)-MIN(Time!L27,Inputs!$F$179)) -> 0 | M10: =Inputs!$F$174*Funding!$F$76/Inputs!$F$175*MAX(0,MIN(Time!M28,Inputs!$F$175)-MIN(Time!M27,Inputs!$F$175))+Inputs!$F$176*Funding!$F$76/Inputs!$F$177*MAX(0,MIN(Time!M28,Inputs!$F$177)-MIN(Time!M27,Inputs!$F$177))+Inputs!$F$178*Funding!$F$76/Inputs!$F$179*MAX(0,MIN(Time!M28,Inputs!$F$179)-MIN(Time!M27,Inputs!$F$179)) -> 0 | N10: =Inputs!$F$174*Funding!$F$76/Inputs!$F$175*MAX(0,MIN(Time!N28,Inputs!$F$175)-MIN(Time!N27,Inputs!$F$175))+Inputs!$F$176*Funding!$F$76/Inputs!$F$177*MAX(0,MIN(Time!N28,Inputs!$F$177)-MIN(Time!N27,Inputs!$F$177))+Inputs!$F$178*Funding!$F$76/Inputs!$F$179*MAX(0,MIN(Time!N28,Inputs!$F$179)-MIN(Time!N27,Inputs!$F$179)) -> 0 | O10: =Inputs!$F$174*Funding!$F$76/Inputs!$F$175*MAX(0,MIN(Time!O28,Inputs!$F$175)-MIN(Time!O27,Inputs!$F$175))+Inputs!$F$176*Funding!$F$76/Inputs!$F$177*MAX(0,MIN(Time!O28,Inputs!$F$177)-MIN(Time!O27,Inputs!$F$177))+Inputs!$F$178*Funding!$F$76/Inputs!$F$179*MAX(0,MIN(Time!O28,Inputs!$F$179)-MIN(Time!O27,Inputs!$F$179)) -> 8.244893 | P10: =Inputs!$F$174*Funding!$F$76/Inputs!$F$175*MAX(0,MIN(Time!P28,Inputs!$F$175)-MIN(Time!P27,Inputs!$F$175))+Inputs!$F$176*Funding!$F$76/Inputs!$F$177*MAX(0,MIN(Time!P28,Inputs!$F$177)-MIN(Time!P27,Inputs!$F$177))+Inputs!$F$178*Funding!$F$76/Inputs!$F$179*MAX(0,MIN(Time!P28,Inputs!$F$179)-MIN(Time!P27,Inputs!$F$179)) -> 24.734679 | Q10: =Inputs!$F$174*Funding!$F$76/Inputs!$F$175*MAX(0,MIN(Time!Q28,Inputs!$F$175)-MIN(Time!Q27,Inputs!$F$175))+Inputs!$F$176*Funding!$F$76/Inputs!$F$177*MAX(0,MIN(Time!Q28,Inputs!$F$177)-MIN(Time!Q27,Inputs!$F$177))+Inputs!$F$178*Funding!$F$76/Inputs!$F$179*MAX(0,MIN(Time!Q28,Inputs!$F$179)-MIN(Time!Q27,Inputs!$F$179)) -> 24.734679 | ... BN10: =Inputs!$F$174*Funding!$F$76/Inputs!$F$175*MAX(0,MIN(Time!BN28,Inputs!$F$175)-MIN(Time!BN27,Inputs!$F$175))+Inputs!$F$176*Funding!$F$76/Inputs!$F$177*MAX(0,MIN(Time!BN28,Inputs!$F$177)-MIN(Time!BN27,Inputs!$F$177))+Inputs!$F$178*Funding!$F$76/Inputs!$F$179*MAX(0,MIN(Time!BN28,Inputs!$F$179)-MIN(Time!BN27,Inputs!$F$179)) -> 0
D11: Depreciation of holiday months (deemed deferred) | E11: USD m | G11: =SUM(J11:BN11) -> 247.34679 | J11: =(Inputs!$F$174*Funding!$F$76/Inputs!$F$175+Inputs!$F$176*Funding!$F$76/Inputs!$F$177+Inputs!$F$178*Funding!$F$76/Inputs!$F$179)*J7 -> 0 | K11: =(Inputs!$F$174*Funding!$F$76/Inputs!$F$175+Inputs!$F$176*Funding!$F$76/Inputs!$F$177+Inputs!$F$178*Funding!$F$76/Inputs!$F$179)*K7 -> 0 | L11: =(Inputs!$F$174*Funding!$F$76/Inputs!$F$175+Inputs!$F$176*Funding!$F$76/Inputs!$F$177+Inputs!$F$178*Funding!$F$76/Inputs!$F$179)*L7 -> 0 | M11: =(Inputs!$F$174*Funding!$F$76/Inputs!$F$175+Inputs!$F$176*Funding!$F$76/Inputs!$F$177+Inputs!$F$178*Funding!$F$76/Inputs!$F$179)*M7 -> 0 | N11: =(Inputs!$F$174*Funding!$F$76/Inputs!$F$175+Inputs!$F$176*Funding!$F$76/Inputs!$F$177+Inputs!$F$178*Funding!$F$76/Inputs!$F$179)*N7 -> 0 | O11: =(Inputs!$F$174*Funding!$F$76/Inputs!$F$175+Inputs!$F$176*Funding!$F$76/Inputs!$F$177+Inputs!$F$178*Funding!$F$76/Inputs!$F$179)*O7 -> 8.244893 | P11: =(Inputs!$F$174*Funding!$F$76/Inputs!$F$175+Inputs!$F$176*Funding!$F$76/Inputs!$F$177+Inputs!$F$178*Funding!$F$76/Inputs!$F$179)*P7 -> 24.734679 | Q11: =(Inputs!$F$174*Funding!$F$76/Inputs!$F$175+Inputs!$F$176*Funding!$F$76/Inputs!$F$177+Inputs!$F$178*Funding!$F$76/Inputs!$F$179)*Q7 -> 24.734679 | ... BN11: =(Inputs!$F$174*Funding!$F$76/Inputs!$F$175+Inputs!$F$176*Funding!$F$76/Inputs!$F$177+Inputs!$F$178*Funding!$F$76/Inputs!$F$179)*BN7 -> 0
D12: Depreciation deducted currently | E12: USD m | G12: =SUM(J12:BN12) -> 668.75243 | J12: =J10-J11 -> 0 | K12: =K10-K11 -> 0 | L12: =L10-L11 -> 0 | M12: =M10-M11 -> 0 | N12: =N10-N11 -> 0 | O12: =O10-O11 -> 0 | P12: =P10-P11 -> 0 | Q12: =Q10-Q11 -> 0 | ... BN12: =BN10-BN11 -> 0
D13: Shareholder loan interest accrued | E13: USD m | G13: =SUM(J13:BN13) -> 345.25404 | J13: =IF(Time!J17>=Time!$F$11,Waterfall!J33*Inputs!$F$102/100*Time!J26/365,0) -> 0 | K13: =IF(Time!K17>=Time!$F$11,Waterfall!K33*Inputs!$F$102/100*Time!K26/365,0) -> 0 | L13: =IF(Time!L17>=Time!$F$11,Waterfall!L33*Inputs!$F$102/100*Time!L26/365,0) -> 0 | M13: =IF(Time!M17>=Time!$F$11,Waterfall!M33*Inputs!$F$102/100*Time!M26/365,0) -> 0 | N13: =IF(Time!N17>=Time!$F$11,Waterfall!N33*Inputs!$F$102/100*Time!N26/365,0) -> 0 | O13: =IF(Time!O17>=Time!$F$11,Waterfall!O33*Inputs!$F$102/100*Time!O26/365,0) -> 3.5046385 | P13: =IF(Time!P17>=Time!$F$11,Waterfall!P33*Inputs!$F$102/100*Time!P26/365,0) -> 10.739207 | Q13: =IF(Time!Q17>=Time!$F$11,Waterfall!Q33*Inputs!$F$102/100*Time!Q26/365,0) -> 10.532497 | ... BN13: =IF(Time!BN17>=Time!$F$11,Waterfall!BN33*Inputs!$F$102/100*Time!BN26/365,0) -> 0
D14: Thin cap: deductible share = min(1, 3 x equity / SHL) | E14: fraction | J14: =IF(Waterfall!J33>0,MIN(1,Inputs!$F$180*(Waterfall!$F$32+MAX(0,0))/Waterfall!J33),1) -> 1 | K14: =IF(Waterfall!K33>0,MIN(1,Inputs!$F$180*(Waterfall!$F$32+MAX(0,Waterfall!J43))/Waterfall!K33),1) -> 1 | L14: =IF(Waterfall!L33>0,MIN(1,Inputs!$F$180*(Waterfall!$F$32+MAX(0,Waterfall!K43))/Waterfall!L33),1) -> 1 | M14: =IF(Waterfall!M33>0,MIN(1,Inputs!$F$180*(Waterfall!$F$32+MAX(0,Waterfall!L43))/Waterfall!M33),1) -> 1 | N14: =IF(Waterfall!N33>0,MIN(1,Inputs!$F$180*(Waterfall!$F$32+MAX(0,Waterfall!M43))/Waterfall!N33),1) -> 1 | O14: =IF(Waterfall!O33>0,MIN(1,Inputs!$F$180*(Waterfall!$F$32+MAX(0,Waterfall!N43))/Waterfall!O33),1) -> 0.66032997 | P14: =IF(Waterfall!P33>0,MIN(1,Inputs!$F$180*(Waterfall!$F$32+MAX(0,Waterfall!O43))/Waterfall!P33),1) -> 0.77182045 | Q14: =IF(Waterfall!Q33>0,MIN(1,Inputs!$F$180*(Waterfall!$F$32+MAX(0,Waterfall!P43))/Waterfall!Q33),1) -> 0.81722852 | R14: =IF(Waterfall!R33>0,MIN(1,Inputs!$F$180*(Waterfall!$F$32+MAX(0,Waterfall!Q43))/Waterfall!R33),1) -> 0.8706944 | ... BN14: =IF(Waterfall!BN33>0,MIN(1,Inputs!$F$180*(Waterfall!$F$32+MAX(0,Waterfall!BM43))/Waterfall!BN33),1) -> 1
D15: Shareholder loan interest deductible | E15: USD m | G15: =SUM(J15:BN15) -> 337.53466 | J15: =J13*J14 -> 0 | K15: =K13*K14 -> 0 | L15: =L13*L14 -> 0 | M15: =M13*M14 -> 0 | N15: =N13*N14 -> 0 | O15: =O13*O14 -> 2.3142179 | P15: =P13*P14 -> 8.2887398 | Q15: =Q13*Q14 -> 8.6074572 | ... BN15: =BN13*BN14 -> 0
D16: Senior financing costs deductible (all grandfathered) | E16: USD m | G16: =SUM(J16:BN16) -> 350.35696 | J16: =Debt!J119+Debt!J117+Debt!J111-Debt!J110 -> 0 | K16: =Debt!K119+Debt!K117+Debt!K111-Debt!K110 -> 0 | L16: =Debt!L119+Debt!L117+Debt!L111-Debt!L110 -> 0 | M16: =Debt!M119+Debt!M117+Debt!M111-Debt!M110 -> 0 | N16: =Debt!N119+Debt!N117+Debt!N111-Debt!N110 -> 0 | O16: =Debt!O119+Debt!O117+Debt!O111-Debt!O110 -> 0 | P16: =Debt!P119+Debt!P117+Debt!P111-Debt!P110 -> 23.876799 | Q16: =Debt!Q119+Debt!Q117+Debt!Q111-Debt!Q110 -> 23.052927 | ... BN16: =Debt!BN119+Debt!BN117+Debt!BN111-Debt!BN110 -> 0
D17: Non-holiday share of operating months | E17: fraction | J17: =IF(Time!J25>0,(Time!J25-J7)/Time!J25,0) -> 0 | K17: =IF(Time!K25>0,(Time!K25-K7)/Time!K25,0) -> 0 | L17: =IF(Time!L25>0,(Time!L25-L7)/Time!L25,0) -> 0 | M17: =IF(Time!M25>0,(Time!M25-M7)/Time!M25,0) -> 0 | N17: =IF(Time!N25>0,(Time!N25-N7)/Time!N25,0) -> 0 | O17: =IF(Time!O25>0,(Time!O25-O7)/Time!O25,0) -> 0 | P17: =IF(Time!P25>0,(Time!P25-P7)/Time!P25,0) -> 0 | Q17: =IF(Time!Q25>0,(Time!Q25-Q7)/Time!Q25,0) -> 0 | ... BN17: =IF(Time!BN25>0,(Time!BN25-BN7)/Time!BN25,0) -> 0
D18: Taxable income before losses and deferred depreciation | E18: USD m | G18: =SUM(J18:BN18) -> 1055.0128 | J18: =(Operations!J79-J16-J15)*J17-J12 -> 0 | K18: =(Operations!K79-K16-K15)*K17-K12 -> 0 | L18: =(Operations!L79-L16-L15)*L17-L12 -> 0 | M18: =(Operations!M79-M16-M15)*M17-M12 -> 0 | N18: =(Operations!N79-N16-N15)*N17-N12 -> 0 | O18: =(Operations!O79-O16-O15)*O17-O12 -> 0 | P18: =(Operations!P79-P16-P15)*P17-P12 -> 0 | Q18: =(Operations!Q79-Q16-Q15)*Q17-Q12 -> 0 | ... BN18: =(Operations!BN79-BN16-BN15)*BN17-BN12 -> 0
D19: Tax losses used | E19: USD m | G19: =SUM(J19:BN19) -> 7.8693862 | J19: =MIN(0,MAX(0,J18)) -> 0 | K19: =MIN(J22,MAX(0,K18)) -> 0 | L19: =MIN(K22,MAX(0,L18)) -> 0 | M19: =MIN(L22,MAX(0,M18)) -> 0 | N19: =MIN(M22,MAX(0,N18)) -> 0 | O19: =MIN(N22,MAX(0,O18)) -> 0 | P19: =MIN(O22,MAX(0,P18)) -> 0 | Q19: =MIN(P22,MAX(0,Q18)) -> 0 | R19: =MIN(Q22,MAX(0,R18)) -> 0 | ... BN19: =MIN(BM22,MAX(0,BN18)) -> 0
D20: Deferred depreciation used | E20: USD m | G20: =SUM(J20:BN20) -> 247.34679 | J20: =MIN(0,MAX(0,J18-J19)) -> 0 | K20: =MIN(J21,MAX(0,K18-K19)) -> 0 | L20: =MIN(K21,MAX(0,L18-L19)) -> 0 | M20: =MIN(L21,MAX(0,M18-M19)) -> 0 | N20: =MIN(M21,MAX(0,N18-N19)) -> 0 | O20: =MIN(N21,MAX(0,O18-O19)) -> 0 | P20: =MIN(O21,MAX(0,P18-P19)) -> 0 | Q20: =MIN(P21,MAX(0,Q18-Q19)) -> 0 | R20: =MIN(Q21,MAX(0,R18-R19)) -> 0 | ... BN20: =MIN(BM21,MAX(0,BN18-BN19)) -> 0
D21: Deferred depreciation pool, closing | E21: USD m | J21: =0+J11-J20 -> 0 | K21: =J21+K11-K20 -> 0 | L21: =K21+L11-L20 -> 0 | M21: =L21+M11-M20 -> 0 | N21: =M21+N11-N20 -> 0 | O21: =N21+O11-O20 -> 8.244893 | P21: =O21+P11-P20 -> 32.979572 | Q21: =P21+Q11-Q20 -> 57.714251 | R21: =Q21+R11-R20 -> 82.44893 | ... BN21: =BM21+BN11-BN20 -> 0
D22: Tax losses carried forward, closing | E22: USD m | J22: =0-J19+MAX(0,-J18) -> 0 | K22: =J22-K19+MAX(0,-K18) -> 0 | L22: =K22-L19+MAX(0,-L18) -> 0 | M22: =L22-M19+MAX(0,-M18) -> 0 | N22: =M22-N19+MAX(0,-N18) -> 0 | O22: =N22-O19+MAX(0,-O18) -> 0 | P22: =O22-P19+MAX(0,-P18) -> 0 | Q22: =P22-Q19+MAX(0,-Q18) -> 0 | R22: =Q22-R19+MAX(0,-R18) -> 0 | ... BN22: =BM22-BN19+MAX(0,-BN18) -> 0
D23: Taxable income | E23: USD m | G23: =SUM(J23:BN23) -> 807.666 | J23: =MAX(0,J18-J19-J20) -> 0 | K23: =MAX(0,K18-K19-K20) -> 0 | L23: =MAX(0,L18-L19-L20) -> 0 | M23: =MAX(0,M18-M19-M20) -> 0 | N23: =MAX(0,N18-N19-N20) -> 0 | O23: =MAX(0,O18-O19-O20) -> 0 | P23: =MAX(0,P18-P19-P20) -> 0 | Q23: =MAX(0,Q18-Q19-Q20) -> 0 | ... BN23: =MAX(0,BN18-BN19-BN20) -> 0
D24: Applicable CIT rate (month-weighted) | E24: % | J24: =IF(J8+J9>0,(J8*Inputs!$F$172+J9*Inputs!$F$171)/(J8+J9)/100,0) -> 0 | K24: =IF(K8+K9>0,(K8*Inputs!$F$172+K9*Inputs!$F$171)/(K8+K9)/100,0) -> 0 | L24: =IF(L8+L9>0,(L8*Inputs!$F$172+L9*Inputs!$F$171)/(L8+L9)/100,0) -> 0 | M24: =IF(M8+M9>0,(M8*Inputs!$F$172+M9*Inputs!$F$171)/(M8+M9)/100,0) -> 0 | N24: =IF(N8+N9>0,(N8*Inputs!$F$172+N9*Inputs!$F$171)/(N8+N9)/100,0) -> 0 | O24: =IF(O8+O9>0,(O8*Inputs!$F$172+O9*Inputs!$F$171)/(O8+O9)/100,0) -> 0 | P24: =IF(P8+P9>0,(P8*Inputs!$F$172+P9*Inputs!$F$171)/(P8+P9)/100,0) -> 0 | Q24: =IF(Q8+Q9>0,(Q8*Inputs!$F$172+Q9*Inputs!$F$171)/(Q8+Q9)/100,0) -> 0 | ... BN24: =IF(BN8+BN9>0,(BN8*Inputs!$F$172+BN9*Inputs!$F$171)/(BN8+BN9)/100,0) -> 0
D25: Corporate income tax | E25: USD m | G25: =SUM(J25:BN25) -> 242.2998 | J25: =J23*J24 -> 0 | K25: =K23*K24 -> 0 | L25: =L23*L24 -> 0 | M25: =M23*M24 -> 0 | N25: =N23*N24 -> 0 | O25: =O23*O24 -> 0 | P25: =P23*P24 -> 0 | Q25: =Q23*Q24 -> 0 | ... BN25: =BN23*BN24 -> 0
D26: Minimum turnover tax | E26: USD m | G26: =SUM(J26:BN26) -> 15.639465 | J26: =IF(Time!J25>0,Inputs!$F$173/100*Operations!J50*(J8+J9)/Time!J25,0) -> 0 | K26: =IF(Time!K25>0,Inputs!$F$173/100*Operations!K50*(K8+K9)/Time!K25,0) -> 0 | L26: =IF(Time!L25>0,Inputs!$F$173/100*Operations!L50*(L8+L9)/Time!L25,0) -> 0 | M26: =IF(Time!M25>0,Inputs!$F$173/100*Operations!M50*(M8+M9)/Time!M25,0) -> 0 | N26: =IF(Time!N25>0,Inputs!$F$173/100*Operations!N50*(N8+N9)/Time!N25,0) -> 0 | O26: =IF(Time!O25>0,Inputs!$F$173/100*Operations!O50*(O8+O9)/Time!O25,0) -> 0 | P26: =IF(Time!P25>0,Inputs!$F$173/100*Operations!P50*(P8+P9)/Time!P25,0) -> 0 | Q26: =IF(Time!Q25>0,Inputs!$F$173/100*Operations!Q50*(Q8+Q9)/Time!Q25,0) -> 0 | ... BN26: =IF(Time!BN25>0,Inputs!$F$173/100*Operations!BN50*(BN8+BN9)/Time!BN25,0) -> 0
D27: Tax paid = max(CIT, MTT) | E27: USD m | G27: =SUM(J27:BN27) -> 249.85285 | J27: =MAX(J25,J26) -> 0 | K27: =MAX(K25,K26) -> 0 | L27: =MAX(L25,L26) -> 0 | M27: =MAX(M25,M26) -> 0 | N27: =MAX(N25,N26) -> 0 | O27: =MAX(O25,O26) -> 0 | P27: =MAX(P25,P26) -> 0 | Q27: =MAX(Q25,Q26) -> 0 | ... BN27: =MAX(BN25,BN26) -> 0
D28: Thin-cap disallowance | E28: USD m | G28: =SUM(J28:BN28) -> 7.7193821 | J28: =J13-J15 -> 0 | K28: =K13-K15 -> 0 | L28: =L13-L15 -> 0 | M28: =M13-M15 -> 0 | N28: =N13-N15 -> 0 | O28: =O13-O15 -> 1.1904207 | P28: =P13-P15 -> 2.4504675 | Q28: =Q13-Q15 -> 1.9250401 | ... BN28: =BN13-BN15 -> 0

Sheet Funding
A1: Case P: Belanou Combined Cycle Power Project, Republic of Kessara
A2: Funding: closed-form gross-up, drawdowns by tranche, IDC, fees, equity
A3: Units in column E; constants in column F; row totals in column G; first period in column J. Inputs: blue on yellow. Links from other sheets: green.
D4: Label | E4: Unit | F4: Constant | G4: Total
D5: Month | J5: 2018-08 | K5: 2018-09 | L5: 2018-10 | M5: 2018-11 | N5: 2018-12 | O5: 2019-01 | P5: 2019-02 | Q5: 2019-03 | R5: 2019-04 | S5: 2019-05 | T5: 2019-06 | U5: 2019-07 | V5: 2019-08 | W5: 2019-09 | X5: 2019-10 | Y5: 2019-11 | Z5: 2019-12 | AA5: 2020-01 | AB5: 2020-02 | AC5: 2020-03 | AD5: 2020-04 | AE5: 2020-05 | AF5: 2020-06 | AG5: 2020-07 | AH5: 2020-08 | AI5: 2020-09 | AJ5: 2020-10 | AK5: 2020-11 | AL5: 2020-12 | AM5: 2021-01 | AN5: 2021-02 | AO5: 2021-03 | AP5: 2021-04 | AQ5: 2021-05 | AR5: 2021-06 | AS5: 2021-07 | AT5: 2021-08 | AU5: 2021-09 | AV5: 2021-10 | AW5: 2021-11 | AX5: 2021-12 | AY5: 2022-01 | AZ5: 2022-02 | BA5: 2022-03 | BB5: 2022-04 | BC5: 2022-05 | BD5: 2022-06 | BE5: 2022-07 | BF5: 2022-08 | BG5: 2022-09 | BH5: 2022-10 | BI5: 2022-11 | BJ5: 2022-12
B7: Constants
D8: Contract debt share of funding g = D/(D+E) | E8: fraction | F8: =Inputs!$F$111/(Inputs!$F$111+Inputs!$F$112) -> 0.74057253
D9: Gearing used in the closed-form gross-up | E9: fraction | F9: =IF(Inputs!$F$50=2,Funding!$F$8,Inputs!$F$103) -> 0.74057253
D10: ECA premium gross-up denominator 1 - prem x share x g | E10: factor | F10: =1-Inputs!$F$92/100*Inputs!$F$73*Funding!$F$9 -> 0.97589436
D11: First installment share of remaining profile | E11: fraction | F11: =INDEX(Debt!$J$17:$BN$17,1,Time!$F$12)/INDEX(Debt!$J$18:$BN$18,1,Time!$F$12) -> 0.024460432
D12: DSRA coefficient per USD of E balance | E12: factor | F12: =$F$11+(INDEX(Operations!$J$9:$BN$9,1,Time!$F$12)+Inputs!$F$77)/100*INDEX(Time!$J$20:$BN$20,1,Time!$F$12)/360*1 -> 0.047153765
D13: DSRA coefficient per USD of A balance | E13: factor | F13: =$F$11+(INDEX(Operations!$J$9:$BN$9,1,Time!$F$12)+Inputs!$F$78)/100*INDEX(Time!$J$20:$BN$20,1,Time!$F$12)/360*1 -> 0.058909321
D14: DSRA coefficient per USD of B balance | E14: factor | F14: =$F$11+(INDEX(Operations!$J$9:$BN$9,1,Time!$F$12)+Inputs!$F$79)/100*INDEX(Time!$J$20:$BN$20,1,Time!$F$12)/360*1 -> 0.057631543
D15: DSRA coefficient per USD of C balance | E15: factor | F15: =$F$11+(INDEX(Operations!$J$9:$BN$9,1,Time!$F$12)+INDEX(Debt!$J$8:$BN$8,1,Time!$F$12))/100*INDEX(Time!$J$20:$BN$20,1,Time!$F$12)/360*(1/(1-Inputs!$F$91/100))+(Inputs!$F$93/100*Inputs!$F$94/100)*INDEX(Time!$J$20:$BN$20,1,Time!$F$12)/365 -> 0.070510065
D16: DSRA coefficient per USD of standby balance | E16: factor | F16: =$F$11+INDEX(Debt!$J$14:$BN$14,1,Time!$F$12) -> 0.06410221
D17: DSRA constant (swap net payment) | E17: USD m | F17: =INDEX(Inputs!$J$222:$BN$222,1,Time!$F$12)*(Inputs!$F$95/100*0.5-INDEX(Operations!$J$9:$BN$9,1,Time!$F$12)/100*INDEX(Time!$J$20:$BN$20,1,Time!$F$12)/360) -> -0.53615673
B18: Closed-form gross-up: debt balance = alpha + beta x T (FC-type cases)
D19: Blended loan rate per month (rho) | E19: factor | J19: =Inputs!$F$73*(Construction!J17+Inputs!$F$77)/100*Construction!J11/360*1+Inputs!$F$74*(Construction!J17+Inputs!$F$78)/100*Construction!J11/360*1+Inputs!$F$75*(Construction!J17+Inputs!$F$79)/100*Construction!J11/360*1+Inputs!$F$76*(Construction!J17+Inputs!$F$80)/100*Construction!J11/360*(1/(1-Inputs!$F$91/100))+Inputs!$F$76*(Inputs!$F$93/100*Inputs!$F$94/100)*Construction!J11/365 -> 0.0054193369 | K19: =Inputs!$F$73*(Construction!K17+Inputs!$F$77)/100*Construction!K11/360*1+Inputs!$F$74*(Construction!K17+Inputs!$F$78)/100*Construction!K11/360*1+Inputs!$F$75*(Construction!K17+Inputs!$F$79)/100*Construction!K11/360*1+Inputs!$F$76*(Construction!K17+Inputs!$F$80)/100*Construction!K11/360*(1/(1-Inputs!$F$91/100))+Inputs!$F$76*(Inputs!$F$93/100*Inputs!$F$94/100)*Construction!K11/365 -> 0.0052445195 | L19: =Inputs!$F$73*(Construction!L17+Inputs!$F$77)/100*Construction!L11/360*1+Inputs!$F$74*(Construction!L17+Inputs!$F$78)/100*Construction!L11/360*1+Inputs!$F$75*(Construction!L17+Inputs!$F$79)/100*Construction!L11/360*1+Inputs!$F$76*(Construction!L17+Inputs!$F$80)/100*Construction!L11/360*(1/(1-Inputs!$F$91/100))+Inputs!$F$76*(Inputs!$F$93/100*Inputs!$F$94/100)*Construction!L11/365 -> 0.0054193369 | M19: =Inputs!$F$73*(Construction!M17+Inputs!$F$77)/100*Construction!M11/360*1+Inputs!$F$74*(Construction!M17+Inputs!$F$78)/100*Construction!M11/360*1+Inputs!$F$75*(Construction!M17+Inputs!$F$79)/100*Construction!M11/360*1+Inputs!$F$76*(Construction!M17+Inputs!$F$80)/100*Construction!M11/360*(1/(1-Inputs!$F$91/100))+Inputs!$F$76*(Inputs!$F$93/100*Inputs!$F$94/100)*Construction!M11/365 -> 0.0052445195 | N19: =Inputs!$F$73*(Construction!N17+Inputs!$F$77)/100*Construction!N11/360*1+Inputs!$F$74*(Construction!N17+Inputs!$F$78)/100*Construction!N11/360*1+Inputs!$F$75*(Construction!N17+Inputs!$F$79)/100*Construction!N11/360*1+Inputs!$F$76*(Construction!N17+Inputs!$F$80)/100*Construction!N11/360*(1/(1-Inputs!$F$91/100))+Inputs!$F$76*(Inputs!$F$93/100*Inputs!$F$94/100)*Construction!N11/365 -> 0.0054193369 | O19: =Inputs!$F$73*(Construction!O17+Inputs!$F$77)/100*Construction!O11/360*1+Inputs!$F$74*(Construction!O17+Inputs!$F$78)/100*Construction!O11/360*1+Inputs!$F$75*(Construction!O17+Inputs!$F$79)/100*Construction!O11/360*1+Inputs!$F$76*(Construction!O17+Inputs!$F$80)/100*Construction!O11/360*(1/(1-Inputs!$F$91/100))+Inputs!$F$76*(Inputs!$F$93/100*Inputs!$F$94/100)*Construction!O11/365 -> 0.0056616535 | P19: =Inputs!$F$73*(Construction!P17+Inputs!$F$77)/100*Construction!P11/360*1+Inputs!$F$74*(Construction!P17+Inputs!$F$78)/100*Construction!P11/360*1+Inputs!$F$75*(Construction!P17+Inputs!$F$79)/100*Construction!P11/360*1+Inputs!$F$76*(Construction!P17+Inputs!$F$80)/100*Construction!P11/360*(1/(1-Inputs!$F$91/100))+Inputs!$F$76*(Inputs!$F$93/100*Inputs!$F$94/100)*Construction!P11/365 -> 0.0051137516 | Q19: =Inputs!$F$73*(Construction!Q17+Inputs!$F$77)/100*Construction!Q11/360*1+Inputs!$F$74*(Construction!Q17+Inputs!$F$78)/100*Construction!Q11/360*1+Inputs!$F$75*(Construction!Q17+Inputs!$F$79)/100*Construction!Q11/360*1+Inputs!$F$76*(Construction!Q17+Inputs!$F$80)/100*Construction!Q11/360*(1/(1-Inputs!$F$91/100))+Inputs!$F$76*(Inputs!$F$93/100*Inputs!$F$94/100)*Construction!Q11/365 -> 0.0056616535 | ... BJ19: =Inputs!$F$73*(Construction!BJ17+Inputs!$F$77)/100*Construction!BJ11/360*1+Inputs!$F$74*(Construction!BJ17+Inputs!$F$78)/100*Construction!BJ11/360*1+Inputs!$F$75*(Construction!BJ17+Inputs!$F$79)/100*Construction!BJ11/360*1+Inputs!$F$76*(Construction!BJ17+Inputs!$F$80)/100*Construction!BJ11/360*(1/(1-Inputs!$F$91/100))+Inputs!$F$76*(Inputs!$F$93/100*Inputs!$F$94/100)*Construction!BJ11/365 -> 0.0059488436
D20: Blended commitment fee per month (kappa) | E20: factor | J20: =Inputs!$F$73*Inputs!$F$83/100*Construction!J11/360+Inputs!$F$74*Inputs!$F$84/100*Construction!J11/360+Inputs!$F$75*Inputs!$F$85/100*Construction!J11/360+Inputs!$F$76*(Inputs!$F$86/100*Inputs!$F$80)/100*Construction!J11/360 -> 0.00086817222 | K20: =Inputs!$F$73*Inputs!$F$83/100*Construction!K11/360+Inputs!$F$74*Inputs!$F$84/100*Construction!K11/360+Inputs!$F$75*Inputs!$F$85/100*Construction!K11/360+Inputs!$F$76*(Inputs!$F$86/100*Inputs!$F$80)/100*Construction!K11/360 -> 0.00084016667 | L20: =Inputs!$F$73*Inputs!$F$83/100*Construction!L11/360+Inputs!$F$74*Inputs!$F$84/100*Construction!L11/360+Inputs!$F$75*Inputs!$F$85/100*Construction!L11/360+Inputs!$F$76*(Inputs!$F$86/100*Inputs!$F$80)/100*Construction!L11/360 -> 0.00086817222 | M20: =Inputs!$F$73*Inputs!$F$83/100*Construction!M11/360+Inputs!$F$74*Inputs!$F$84/100*Construction!M11/360+Inputs!$F$75*Inputs!$F$85/100*Construction!M11/360+Inputs!$F$76*(Inputs!$F$86/100*Inputs!$F$80)/100*Construction!M11/360 -> 0.00084016667 | N20: =Inputs!$F$73*Inputs!$F$83/100*Construction!N11/360+Inputs!$F$74*Inputs!$F$84/100*Construction!N11/360+Inputs!$F$75*Inputs!$F$85/100*Construction!N11/360+Inputs!$F$76*(Inputs!$F$86/100*Inputs!$F$80)/100*Construction!N11/360 -> 0.00086817222 | O20: =Inputs!$F$73*Inputs!$F$83/100*Construction!O11/360+Inputs!$F$74*Inputs!$F$84/100*Construction!O11/360+Inputs!$F$75*Inputs!$F$85/100*Construction!O11/360+Inputs!$F$76*(Inputs!$F$86/100*Inputs!$F$80)/100*Construction!O11/360 -> 0.00086817222 | P20: =Inputs!$F$73*Inputs!$F$83/100*Construction!P11/360+Inputs!$F$74*Inputs!$F$84/100*Construction!P11/360+Inputs!$F$75*Inputs!$F$85/100*Construction!P11/360+Inputs!$F$76*(Inputs!$F$86/100*Inputs!$F$80)/100*Construction!P11/360 -> 0.00078415556 | Q20: =Inputs!$F$73*Inputs!$F$83/100*Construction!Q11/360+Inputs!$F$74*Inputs!$F$84/100*Construction!Q11/360+Inputs!$F$75*Inputs!$F$85/100*Construction!Q11/360+Inputs!$F$76*(Inputs!$F$86/100*Inputs!$F$80)/100*Construction!Q11/360 -> 0.00086817222 | ... BJ20: =Inputs!$F$73*Inputs!$F$83/100*Construction!BJ11/360+Inputs!$F$74*Inputs!$F$84/100*Construction!BJ11/360+Inputs!$F$75*Inputs!$F$85/100*Construction!BJ11/360+Inputs!$F$76*(Inputs!$F$86/100*Inputs!$F$80)/100*Construction!BJ11/360 -> 0.00086817222
D21: Costs independent of facility size | E21: USD m | J21: =Construction!J14*(Construction!J30+Construction!J36+Inputs!$F$105/12+Inputs!J229*(Inputs!$F$95/100/12-Construction!J17/100*Construction!J11/360)+Inputs!$F$97*Inputs!$F$98/100*Construction!J11/360+Construction!J15*$F$17) -> 115.70478 | K21: =Construction!K14*(Construction!K30+Construction!K36+Inputs!$F$105/12+Inputs!K229*(Inputs!$F$95/100/12-Construction!K17/100*Construction!K11/360)+Inputs!$F$97*Inputs!$F$98/100*Construction!K11/360+Construction!K15*$F$17) -> 1.6541862 | L21: =Construction!L14*(Construction!L30+Construction!L36+Inputs!$F$105/12+Inputs!L229*(Inputs!$F$95/100/12-Construction!L17/100*Construction!L11/360)+Inputs!$F$97*Inputs!$F$98/100*Construction!L11/360+Construction!L15*$F$17) -> 2.3482069 | M21: =Construction!M14*(Construction!M30+Construction!M36+Inputs!$F$105/12+Inputs!M229*(Inputs!$F$95/100/12-Construction!M17/100*Construction!M11/360)+Inputs!$F$97*Inputs!$F$98/100*Construction!M11/360+Construction!M15*$F$17) -> 3.7852497 | N21: =Construction!N14*(Construction!N30+Construction!N36+Inputs!$F$105/12+Inputs!N229*(Inputs!$F$95/100/12-Construction!N17/100*Construction!N11/360)+Inputs!$F$97*Inputs!$F$98/100*Construction!N11/360+Construction!N15*$F$17) -> 5.8609143 | O21: =Construction!O14*(Construction!O30+Construction!O36+Inputs!$F$105/12+Inputs!O229*(Inputs!$F$95/100/12-Construction!O17/100*Construction!O11/360)+Inputs!$F$97*Inputs!$F$98/100*Construction!O11/360+Construction!O15*$F$17) -> 8.4426947 | P21: =Construction!P14*(Construction!P30+Construction!P36+Inputs!$F$105/12+Inputs!P229*(Inputs!$F$95/100/12-Construction!P17/100*Construction!P11/360)+Inputs!$F$97*Inputs!$F$98/100*Construction!P11/360+Construction!P15*$F$17) -> 11.441251 | Q21: =Construction!Q14*(Construction!Q30+Construction!Q36+Inputs!$F$105/12+Inputs!Q229*(Inputs!$F$95/100/12-Construction!Q17/100*Construction!Q11/360)+Inputs!$F$97*Inputs!$F$98/100*Construction!Q11/360+Construction!Q15*$F$17) -> 14.653451 | ... BJ21: =Construction!BJ14*(Construction!BJ30+Construction!BJ36+Inputs!$F$105/12+Inputs!BJ229*(Inputs!$F$95/100/12-Construction!BJ17/100*Construction!BJ11/360)+Inputs!$F$97*Inputs!$F$98/100*Construction!BJ11/360+Construction!BJ15*$F$17) -> 0
D22: Balance, constant part (alpha) | E22: USD m | J22: =0+Construction!J14*$F$9/$F$10*(J21+(J19-J20)*0) -> 87.804359 | K22: =J22+Construction!K14*$F$9/$F$10*(K21+(K19-K20)*J22) -> 89.353134 | L22: =K22+Construction!L14*$F$9/$F$10*(L21+(L19-L20)*K22) -> 91.443708 | M22: =L22+Construction!M14*$F$9/$F$10*(M21+(M19-M20)*L22) -> 94.621836 | N22: =M22+Construction!N14*$F$9/$F$10*(N21+(N19-N20)*M22) -> 99.396279 | O22: =N22+Construction!O14*$F$9/$F$10*(O21+(O19-O20)*N22) -> 106.16471 | P22: =O22+Construction!P14*$F$9/$F$10*(P21+(P19-P20)*O22) -> 115.1959 | Q22: =P22+Construction!Q14*$F$9/$F$10*(Q21+(Q19-Q20)*P22) -> 126.73493 | R22: =Q22+Construction!R14*$F$9/$F$10*(R21+(R19-R20)*Q22) -> 140.83694 | ... BJ22: =BI22+Construction!BJ14*$F$9/$F$10*(BJ21+(BJ19-BJ20)*BI22) -> 635.88242
D23: Balance per USD of total funding (beta) | E23: factor | J23: =0+Construction!J14*$F$9/$F$10*(J19*0+J20*($F$9-0)+IF(Construction!J8=1,$F$9*(Inputs!$F$73*Inputs!$F$87/100+Inputs!$F$74*Inputs!$F$88/100+Inputs!$F$75*Inputs!$F$89/100+Inputs!$F$76*Inputs!$F$90/100),0)+Construction!J15*$F$9*(Inputs!$F$73*$F$12+Inputs!$F$74*$F$13+Inputs!$F$75*$F$14+Inputs!$F$76*$F$15)) -> 0.0093224685 | K23: =J23+Construction!K14*$F$9/$F$10*(K19*J23+K20*($F$9-J23)+IF(Construction!K8=1,$F$9*(Inputs!$F$73*Inputs!$F$87/100+Inputs!$F$74*Inputs!$F$88/100+Inputs!$F$75*Inputs!$F$89/100+Inputs!$F$76*Inputs!$F$90/100),0)+Construction!K15*$F$9*(Inputs!$F$73*$F$12+Inputs!$F$74*$F$13+Inputs!$F$75*$F$14+Inputs!$F$76*$F$15)) -> 0.0098257965 | L23: =K23+Construction!L14*$F$9/$F$10*(L19*K23+L20*($F$9-K23)+IF(Construction!L8=1,$F$9*(Inputs!$F$73*Inputs!$F$87/100+Inputs!$F$74*Inputs!$F$88/100+Inputs!$F$75*Inputs!$F$89/100+Inputs!$F$76*Inputs!$F$90/100),0)+Construction!L15*$F$9*(Inputs!$F$73*$F$12+Inputs!$F$74*$F$13+Inputs!$F$75*$F$14+Inputs!$F$76*$F$15)) -> 0.01034764 | M23: =L23+Construction!M14*$F$9/$F$10*(M19*L23+M20*($F$9-L23)+IF(Construction!M8=1,$F$9*(Inputs!$F$73*Inputs!$F$87/100+Inputs!$F$74*Inputs!$F$88/100+Inputs!$F$75*Inputs!$F$89/100+Inputs!$F$76*Inputs!$F$90/100),0)+Construction!M15*$F$9*(Inputs!$F$73*$F$12+Inputs!$F$74*$F$13+Inputs!$F$75*$F$14+Inputs!$F$76*$F$15)) -> 0.010854395 | N23: =M23+Construction!N14*$F$9/$F$10*(N19*M23+N20*($F$9-M23)+IF(Construction!N8=1,$F$9*(Inputs!$F$73*Inputs!$F$87/100+Inputs!$F$74*Inputs!$F$88/100+Inputs!$F$75*Inputs!$F$89/100+Inputs!$F$76*Inputs!$F$90/100),0)+Construction!N15*$F$9*(Inputs!$F$73*$F$12+Inputs!$F$74*$F$13+Inputs!$F$75*$F$14+Inputs!$F$76*$F$15)) -> 0.011379791 | O23: =N23+Construction!O14*$F$9/$F$10*(O19*N23+O20*($F$9-N23)+IF(Construction!O8=1,$F$9*(Inputs!$F$73*Inputs!$F$87/100+Inputs!$F$74*Inputs!$F$88/100+Inputs!$F$75*Inputs!$F$89/100+Inputs!$F$76*Inputs!$F$90/100),0)+Construction!O15*$F$9*(Inputs!$F$73*$F$12+Inputs!$F$74*$F$13+Inputs!$F$75*$F$14+Inputs!$F$76*$F$15)) -> 0.011909095 | P23: =O23+Construction!P14*$F$9/$F$10*(P19*O23+P20*($F$9-O23)+IF(Construction!P8=1,$F$9*(Inputs!$F$73*Inputs!$F$87/100+Inputs!$F$74*Inputs!$F$88/100+Inputs!$F$75*Inputs!$F$89/100+Inputs!$F$76*Inputs!$F$90/100),0)+Construction!P15*$F$9*(Inputs!$F$73*$F$12+Inputs!$F$74*$F$13+Inputs!$F$75*$F$14+Inputs!$F$76*$F$15)) -> 0.012388915 | Q23: =P23+Construction!Q14*$F$9/$F$10*(Q19*P23+Q20*($F$9-P23)+IF(Construction!Q8=1,$F$9*(Inputs!$F$73*Inputs!$F$87/100+Inputs!$F$74*Inputs!$F$88/100+Inputs!$F$75*Inputs!$F$89/100+Inputs!$F$76*Inputs!$F$90/100),0)+Construction!Q15*$F$9*(Inputs!$F$73*$F$12+Inputs!$F$74*$F$13+Inputs!$F$75*$F$14+Inputs!$F$76*$F$15)) -> 0.012921889 | R23: =Q23+Construction!R14*$F$9/$F$10*(R19*Q23+R20*($F$9-Q23)+IF(Construction!R8=1,$F$9*(Inputs!$F$73*Inputs!$F$87/100+Inputs!$F$74*Inputs!$F$88/100+Inputs!$F$75*Inputs!$F$89/100+Inputs!$F$76*Inputs!$F$90/100),0)+Construction!R15*$F$9*(Inputs!$F$73*$F$12+Inputs!$F$74*$F$13+Inputs!$F$75*$F$14+Inputs!$F$76*$F$15)) -> 0.013439547 | ... BJ23: =BI23+Construction!BJ14*$F$9/$F$10*(BJ19*BI23+BJ20*($F$9-BI23)+IF(Construction!BJ8=1,$F$9*(Inputs!$F$73*Inputs!$F$87/100+Inputs!$F$74*Inputs!$F$88/100+Inputs!$F$75*Inputs!$F$89/100+Inputs!$F$76*Inputs!$F$90/100),0)+Construction!BJ15*$F$9*(Inputs!$F$73*$F$12+Inputs!$F$74*$F$13+Inputs!$F$75*$F$14+Inputs!$F$76*$F$15)) -> 0.06152471
D24: Total funding requirement at this gearing, closed form T = alpha/(g - beta) | E24: USD m | F24: =INDEX(Funding!$J$22:$BJ$22,1,Time!$F$13)/(Funding!$F$9-INDEX(Funding!$J$23:$BJ$23,1,Time!$F$13)) -> 936.43245
D25: Senior debt (committed tranches) | E25: USD m | F25: =IF(Inputs!$F$50=2,Funding!$F$8*Funding!$F$24,Inputs!$F$111) -> 693.49615
D26: Debt share of monthly funding | E26: fraction | F26: =Funding!$F$8 -> 0.74057253
B27: Monthly funding schedule (USD m)
D28: ECA-covered tranche: opening balance | E28: USD m | J28: =0 -> 0 | K28: =J61 -> 28.960266 | L28: =K61 -> 29.566298 | M28: =L61 -> 30.340072 | N28: =M61 -> 31.435873 | O28: =N61 -> 33.015805 | P28: =O61 -> 35.195033 | Q28: =P61 -> 38.039183 | R28: =Q61 -> 41.650622 | ... BJ28: =BI61 -> 208.04885
D29: ABDB A-loan: opening balance | E29: USD m | J29: =0 -> 0 | K29: =J62 -> 21.237529 | L29: =K62 -> 21.681952 | M29: =L62 -> 22.249386 | N29: =M62 -> 23.052974 | O29: =N62 -> 24.211591 | P29: =O62 -> 25.809691 | Q29: =P62 -> 27.895401 | R29: =Q62 -> 30.54379 | ... BJ29: =BI62 -> 152.56915
D30: ABDB B-loan: opening balance | E30: USD m | J30: =0 -> 0 | K30: =J63 -> 9.6534221 | L30: =K63 -> 9.8554328 | M30: =L63 -> 10.113357 | N30: =M63 -> 10.478624 | O30: =N63 -> 11.005268 | P30: =O63 -> 11.731678 | Q30: =P63 -> 12.679728 | R30: =Q63 -> 13.883541 | ... BJ30: =BI63 -> 69.349615
D31: Commercial tranche: opening balance | E31: USD m | J31: =0 -> 0 | K31: =J64 -> 36.683004 | L31: =K64 -> 37.450645 | M31: =L64 -> 38.430758 | N31: =M64 -> 39.818773 | O31: =N64 -> 41.82002 | P31: =O64 -> 44.580375 | Q31: =P64 -> 48.182966 | R31: =Q64 -> 52.757455 | ... BJ31: =BI64 -> 263.52854
D32: Standby facility: opening balance | E32: USD m | J32: =0 -> 0 | K32: =J65 -> 0 | L32: =K65 -> 0 | M32: =L65 -> 0 | N32: =M65 -> 0 | O32: =N65 -> 0 | P32: =O65 -> 0 | Q32: =P65 -> 0 | R32: =Q65 -> 0 | ... BJ32: =BI65 -> 4.7295501e-14
D33: ECA-covered tranche: interest | E33: USD m | G33: =SUM(J33:BJ33) -> 13.575177 | J33: =Construction!J14*J28*(Construction!J17+Inputs!$F$77)/100*Construction!J11/360*1 -> 0 | K33: =Construction!K14*K28*(Construction!K17+Inputs!$F$77)/100*Construction!K11/360*1 -> 0.093396859 | L33: =Construction!L14*L28*(Construction!L17+Inputs!$F$77)/100*Construction!L11/360*1 -> 0.09852969 | M33: =Construction!M14*M28*(Construction!M17+Inputs!$F$77)/100*Construction!M11/360*1 -> 0.097846733 | N33: =Construction!N14*N28*(Construction!N17+Inputs!$F$77)/100*Construction!N11/360*1 -> 0.10476005 | O33: =Construction!O14*O28*(Construction!O17+Inputs!$F$77)/100*Construction!O11/360*1 -> 0.11770135 | P33: =Construction!P14*P28*(Construction!P17+Inputs!$F$77)/100*Construction!P11/360*1 -> 0.11332801 | Q33: =Construction!Q14*Q28*(Construction!Q17+Inputs!$F$77)/100*Construction!Q11/360*1 -> 0.13560969 | ... BJ33: =Construction!BJ14*BJ28*(Construction!BJ17+Inputs!$F$77)/100*Construction!BJ11/360*1 -> 0
D34: ABDB A-loan: interest | E34: USD m | G34: =SUM(J34:BJ34) -> 15.205877 | J34: =Construction!J14*J29*(Construction!J17+Inputs!$F$78)/100*Construction!J11/360*1 -> 0 | K34: =Construction!K14*K29*(Construction!K17+Inputs!$F$78)/100*Construction!K11/360*1 -> 0.10919629 | L34: =Construction!L14*L29*(Construction!L17+Inputs!$F$78)/100*Construction!L11/360*1 -> 0.11519742 | M34: =Construction!M14*M29*(Construction!M17+Inputs!$F$78)/100*Construction!M11/360*1 -> 0.11439893 | N34: =Construction!N14*N29*(Construction!N17+Inputs!$F$78)/100*Construction!N11/360*1 -> 0.12248173 | O34: =Construction!O14*O29*(Construction!O17+Inputs!$F$78)/100*Construction!O11/360*1 -> 0.13426672 | P34: =Construction!P14*P29*(Construction!P17+Inputs!$F$78)/100*Construction!P11/360*1 -> 0.12927787 | Q34: =Construction!Q14*Q29*(Construction!Q17+Inputs!$F$78)/100*Construction!Q11/360*1 -> 0.1546955 | ... BJ34: =Construction!BJ14*BJ29*(Construction!BJ17+Inputs!$F$78)/100*Construction!BJ11/360*1 -> 0
D35: ABDB B-loan: interest | E35: USD m | G35: =SUM(J35:BJ35) -> 6.6523382 | J35: =Construction!J14*J30*(Construction!J17+Inputs!$F$79)/100*Construction!J11/360*1 -> 0 | K35: =Construction!K14*K30*(Construction!K17+Inputs!$F$79)/100*Construction!K11/360*1 -> 0.047623549 | L35: =Construction!L14*L30*(Construction!L17+Inputs!$F$79)/100*Construction!L11/360*1 -> 0.050240806 | M35: =Construction!M14*M30*(Construction!M17+Inputs!$F$79)/100*Construction!M11/360*1 -> 0.049892563 | N35: =Construction!N14*N30*(Construction!N17+Inputs!$F$79)/100*Construction!N11/360*1 -> 0.053417698 | O35: =Construction!O14*O30*(Construction!O17+Inputs!$F$79)/100*Construction!O11/360*1 -> 0.058661138 | P35: =Construction!P14*P30*(Construction!P17+Inputs!$F$79)/100*Construction!P11/360*1 -> 0.05648151 | Q35: =Construction!Q14*Q30*(Construction!Q17+Inputs!$F$79)/100*Construction!Q11/360*1 -> 0.067586471 | ... BJ35: =Construction!BJ14*BJ30*(Construction!BJ17+Inputs!$F$79)/100*Construction!BJ11/360*1 -> 0
D36: Commercial tranche: interest | E36: USD m | G36: =SUM(J36:BJ36) -> 31.154622 | J36: =Construction!J14*J31*(Construction!J17+Inputs!$F$80)/100*Construction!J11/360*(1/(1-Inputs!$F$91/100)) -> 0 | K36: =Construction!K14*K31*(Construction!K17+Inputs!$F$80)/100*Construction!K11/360*(1/(1-Inputs!$F$91/100)) -> 0.22485323 | L36: =Construction!L14*L31*(Construction!L17+Inputs!$F$80)/100*Construction!L11/360*(1/(1-Inputs!$F$91/100)) -> 0.23721053 | M36: =Construction!M14*M31*(Construction!M17+Inputs!$F$80)/100*Construction!M11/360*(1/(1-Inputs!$F$91/100)) -> 0.23556631 | N36: =Construction!N14*N31*(Construction!N17+Inputs!$F$80)/100*Construction!N11/360*(1/(1-Inputs!$F$91/100)) -> 0.25221014 | O36: =Construction!O14*O31*(Construction!O17+Inputs!$F$80)/100*Construction!O11/360*(1/(1-Inputs!$F$91/100)) -> 0.27568945 | P36: =Construction!P14*P31*(Construction!P17+Inputs!$F$80)/100*Construction!P11/360*(1/(1-Inputs!$F$91/100)) -> 0.26544586 | Q36: =Construction!Q14*Q31*(Construction!Q17+Inputs!$F$80)/100*Construction!Q11/360*(1/(1-Inputs!$F$91/100)) -> 0.31763579 | ... BJ36: =Construction!BJ14*BJ31*(Construction!BJ17+Inputs!$F$80)/100*Construction!BJ11/360*(1/(1-Inputs!$F$91/100)) -> 0
D37: Standby facility: interest | E37: USD m | G37: =SUM(J37:BJ37) -> 0 | J37: =Construction!J14*J32*(Inputs!$F$100*(Construction!J17+Inputs!$F$80+Inputs!$F$99)/(1-Inputs!$F$91/100)+(1-Inputs!$F$100)*(Construction!J17+Inputs!$F$78+Inputs!$F$99))/100*Construction!J11/360 -> 0 | K37: =Construction!K14*K32*(Inputs!$F$100*(Construction!K17+Inputs!$F$80+Inputs!$F$99)/(1-Inputs!$F$91/100)+(1-Inputs!$F$100)*(Construction!K17+Inputs!$F$78+Inputs!$F$99))/100*Construction!K11/360 -> 0 | L37: =Construction!L14*L32*(Inputs!$F$100*(Construction!L17+Inputs!$F$80+Inputs!$F$99)/(1-Inputs!$F$91/100)+(1-Inputs!$F$100)*(Construction!L17+Inputs!$F$78+Inputs!$F$99))/100*Construction!L11/360 -> 0 | M37: =Construction!M14*M32*(Inputs!$F$100*(Construction!M17+Inputs!$F$80+Inputs!$F$99)/(1-Inputs!$F$91/100)+(1-Inputs!$F$100)*(Construction!M17+Inputs!$F$78+Inputs!$F$99))/100*Construction!M11/360 -> 0 | N37: =Construction!N14*N32*(Inputs!$F$100*(Construction!N17+Inputs!$F$80+Inputs!$F$99)/(1-Inputs!$F$91/100)+(1-Inputs!$F$100)*(Construction!N17+Inputs!$F$78+Inputs!$F$99))/100*Construction!N11/360 -> 0 | O37: =Construction!O14*O32*(Inputs!$F$100*(Construction!O17+Inputs!$F$80+Inputs!$F$99)/(1-Inputs!$F$91/100)+(1-Inputs!$F$100)*(Construction!O17+Inputs!$F$78+Inputs!$F$99))/100*Construction!O11/360 -> 0 | P37: =Construction!P14*P32*(Inputs!$F$100*(Construction!P17+Inputs!$F$80+Inputs!$F$99)/(1-Inputs!$F$91/100)+(1-Inputs!$F$100)*(Construction!P17+Inputs!$F$78+Inputs!$F$99))/100*Construction!P11/360 -> 0 | Q37: =Construction!Q14*Q32*(Inputs!$F$100*(Construction!Q17+Inputs!$F$80+Inputs!$F$99)/(1-Inputs!$F$91/100)+(1-Inputs!$F$100)*(Construction!Q17+Inputs!$F$78+Inputs!$F$99))/100*Construction!Q11/360 -> 0 | ... BJ37: =Construction!BJ14*BJ32*(Inputs!$F$100*(Construction!BJ17+Inputs!$F$80+Inputs!$F$99)/(1-Inputs!$F$91/100)+(1-Inputs!$F$100)*(Construction!BJ17+Inputs!$F$78+Inputs!$F$99))/100*Construction!BJ11/360 -> 0
D38: PRI premium on commercial tranche | E38: USD m | G38: =SUM(J38:BJ38) -> 4.0253554 | J38: =Construction!J14*(Inputs!$F$93/100*Inputs!$F$94/100)*J31*Construction!J11/365 -> 0 | K38: =Construction!K14*(Inputs!$F$93/100*Inputs!$F$94/100)*K31*Construction!K11/365 -> 0.031205679 | L38: =Construction!L14*(Inputs!$F$93/100*Inputs!$F$94/100)*L31*Construction!L11/365 -> 0.032920656 | M38: =Construction!M14*(Inputs!$F$93/100*Inputs!$F$94/100)*M31*Construction!M11/365 -> 0.032692467 | N38: =Construction!N14*(Inputs!$F$93/100*Inputs!$F$94/100)*N31*Construction!N11/365 -> 0.035002338 | O38: =Construction!O14*(Inputs!$F$93/100*Inputs!$F$94/100)*O31*Construction!O11/365 -> 0.036761516 | P38: =Construction!P14*(Inputs!$F$93/100*Inputs!$F$94/100)*P31*Construction!P11/365 -> 0.035395596 | Q38: =Construction!Q14*(Inputs!$F$93/100*Inputs!$F$94/100)*Q31*Construction!Q11/365 -> 0.042354807 | ... BJ38: =Construction!BJ14*(Inputs!$F$93/100*Inputs!$F$94/100)*BJ31*Construction!BJ11/365 -> 0
D39: Swap net payment | E39: USD m | G39: =SUM(J39:BJ39) -> -0.78015439 | J39: =Construction!J14*Inputs!J229*(Inputs!$F$95/100/12-Construction!J17/100*Construction!J11/360) -> 0 | K39: =Construction!K14*Inputs!K229*(Inputs!$F$95/100/12-Construction!K17/100*Construction!K11/360) -> 0.025633627 | L39: =Construction!L14*Inputs!L229*(Inputs!$F$95/100/12-Construction!L17/100*Construction!L11/360) -> 0.021014144 | M39: =Construction!M14*Inputs!M229*(Inputs!$F$95/100/12-Construction!M17/100*Construction!M11/360) -> 0.026832031 | N39: =Construction!N14*Inputs!N229*(Inputs!$F$95/100/12-Construction!N17/100*Construction!N11/360) -> 0.022316213 | O39: =Construction!O14*Inputs!O229*(Inputs!$F$95/100/12-Construction!O17/100*Construction!O11/360) -> 0.004368853 | P39: =Construction!P14*Inputs!P229*(Inputs!$F$95/100/12-Construction!P17/100*Construction!P11/360) -> 0.024927526 | Q39: =Construction!Q14*Inputs!Q229*(Inputs!$F$95/100/12-Construction!Q17/100*Construction!Q11/360) -> 0.00501953 | ... BJ39: =Construction!BJ14*Inputs!BJ229*(Inputs!$F$95/100/12-Construction!BJ17/100*Construction!BJ11/360) -> 0
D40: Commitment fees, senior tranches | E40: USD m | G40: =SUM(J40:BJ40) -> 10.222095 | J40: =Construction!J14*((Inputs!$F$73*$F$25-J28)*Inputs!$F$83/100+(Inputs!$F$74*$F$25-J29)*Inputs!$F$84/100+(Inputs!$F$75*$F$25-J30)*Inputs!$F$85/100+(Inputs!$F$76*$F$25-J31)*(Inputs!$F$86/100*Inputs!$F$80)/100)*Construction!J11/360 -> 0.60207409 | K40: =Construction!K14*((Inputs!$F$73*$F$25-K28)*Inputs!$F$83/100+(Inputs!$F$74*$F$25-K29)*Inputs!$F$84/100+(Inputs!$F$75*$F$25-K30)*Inputs!$F$85/100+(Inputs!$F$76*$F$25-K31)*(Inputs!$F$86/100*Inputs!$F$80)/100)*Construction!K11/360 -> 0.50154751 | L40: =Construction!L14*((Inputs!$F$73*$F$25-L28)*Inputs!$F$83/100+(Inputs!$F$74*$F$25-L29)*Inputs!$F$84/100+(Inputs!$F$75*$F$25-L30)*Inputs!$F$85/100+(Inputs!$F$76*$F$25-L31)*(Inputs!$F$86/100*Inputs!$F$80)/100)*Construction!L11/360 -> 0.51651196 | M40: =Construction!M14*((Inputs!$F$73*$F$25-M28)*Inputs!$F$83/100+(Inputs!$F$74*$F$25-M29)*Inputs!$F$84/100+(Inputs!$F$75*$F$25-M30)*Inputs!$F$85/100+(Inputs!$F$76*$F$25-M31)*(Inputs!$F$86/100*Inputs!$F$80)/100)*Construction!M11/360 -> 0.49768329 | N40: =Construction!N14*((Inputs!$F$73*$F$25-N28)*Inputs!$F$83/100+(Inputs!$F$74*$F$25-N29)*Inputs!$F$84/100+(Inputs!$F$75*$F$25-N30)*Inputs!$F$85/100+(Inputs!$F$76*$F$25-N31)*(Inputs!$F$86/100*Inputs!$F$80)/100)*Construction!N11/360 -> 0.51110159 | O40: =Construction!O14*((Inputs!$F$73*$F$25-O28)*Inputs!$F$83/100+(Inputs!$F$74*$F$25-O29)*Inputs!$F$84/100+(Inputs!$F$75*$F$25-O30)*Inputs!$F$85/100+(Inputs!$F$76*$F$25-O31)*(Inputs!$F$86/100*Inputs!$F$80)/100)*Construction!O11/360 -> 0.50652941 | P40: =Construction!P14*((Inputs!$F$73*$F$25-P28)*Inputs!$F$83/100+(Inputs!$F$74*$F$25-P29)*Inputs!$F$84/100+(Inputs!$F$75*$F$25-P30)*Inputs!$F$85/100+(Inputs!$F$76*$F$25-P31)*(Inputs!$F$86/100*Inputs!$F$80)/100)*Construction!P11/360 -> 0.45181426 | Q40: =Construction!Q14*((Inputs!$F$73*$F$25-Q28)*Inputs!$F$83/100+(Inputs!$F$74*$F$25-Q29)*Inputs!$F$84/100+(Inputs!$F$75*$F$25-Q30)*Inputs!$F$85/100+(Inputs!$F$76*$F$25-Q31)*(Inputs!$F$86/100*Inputs!$F$80)/100)*Construction!Q11/360 -> 0.49199222 | ... BJ40: =Construction!BJ14*((Inputs!$F$73*$F$25-BJ28)*Inputs!$F$83/100+(Inputs!$F$74*$F$25-BJ29)*Inputs!$F$84/100+(Inputs!$F$75*$F$25-BJ30)*Inputs!$F$85/100+(Inputs!$F$76*$F$25-BJ31)*(Inputs!$F$86/100*Inputs!$F$80)/100)*Construction!BJ11/360 -> 0
D41: Commitment fee, standby facility | E41: USD m | G41: =SUM(J41:BJ41) -> 0.8165 | J41: =Construction!J14*(Inputs!$F$97-J32)*Inputs!$F$98/100*Construction!J11/360 -> 0.023766667 | K41: =Construction!K14*(Inputs!$F$97-K32)*Inputs!$F$98/100*Construction!K11/360 -> 0.023 | L41: =Construction!L14*(Inputs!$F$97-L32)*Inputs!$F$98/100*Construction!L11/360 -> 0.023766667 | M41: =Construction!M14*(Inputs!$F$97-M32)*Inputs!$F$98/100*Construction!M11/360 -> 0.023 | N41: =Construction!N14*(Inputs!$F$97-N32)*Inputs!$F$98/100*Construction!N11/360 -> 0.023766667 | O41: =Construction!O14*(Inputs!$F$97-O32)*Inputs!$F$98/100*Construction!O11/360 -> 0.023766667 | P41: =Construction!P14*(Inputs!$F$97-P32)*Inputs!$F$98/100*Construction!P11/360 -> 0.021466667 | Q41: =Construction!Q14*(Inputs!$F$97-Q32)*Inputs!$F$98/100*Construction!Q11/360 -> 0.023766667 | ... BJ41: =Construction!BJ14*(Inputs!$F$97-BJ32)*Inputs!$F$98/100*Construction!BJ11/360 -> 0
D42: Upfront and arrangement fees | E42: USD m | G42: =SUM(J42:BJ42) -> 10.901759 | J42: =IF(Construction!J8=1,Inputs!$F$73*$F$25*Inputs!$F$87/100+Inputs!$F$74*$F$25*Inputs!$F$88/100+Inputs!$F$75*$F$25*Inputs!$F$89/100+Inputs!$F$76*$F$25*Inputs!$F$90/100,0) -> 10.901759 | K42: =IF(Construction!K8=1,Inputs!$F$73*$F$25*Inputs!$F$87/100+Inputs!$F$74*$F$25*Inputs!$F$88/100+Inputs!$F$75*$F$25*Inputs!$F$89/100+Inputs!$F$76*$F$25*Inputs!$F$90/100,0) -> 0 | L42: =IF(Construction!L8=1,Inputs!$F$73*$F$25*Inputs!$F$87/100+Inputs!$F$74*$F$25*Inputs!$F$88/100+Inputs!$F$75*$F$25*Inputs!$F$89/100+Inputs!$F$76*$F$25*Inputs!$F$90/100,0) -> 0 | M42: =IF(Construction!M8=1,Inputs!$F$73*$F$25*Inputs!$F$87/100+Inputs!$F$74*$F$25*Inputs!$F$88/100+Inputs!$F$75*$F$25*Inputs!$F$89/100+Inputs!$F$76*$F$25*Inputs!$F$90/100,0) -> 0 | N42: =IF(Construction!N8=1,Inputs!$F$73*$F$25*Inputs!$F$87/100+Inputs!$F$74*$F$25*Inputs!$F$88/100+Inputs!$F$75*$F$25*Inputs!$F$89/100+Inputs!$F$76*$F$25*Inputs!$F$90/100,0) -> 0 | O42: =IF(Construction!O8=1,Inputs!$F$73*$F$25*Inputs!$F$87/100+Inputs!$F$74*$F$25*Inputs!$F$88/100+Inputs!$F$75*$F$25*Inputs!$F$89/100+Inputs!$F$76*$F$25*Inputs!$F$90/100,0) -> 0 | P42: =IF(Construction!P8=1,Inputs!$F$73*$F$25*Inputs!$F$87/100+Inputs!$F$74*$F$25*Inputs!$F$88/100+Inputs!$F$75*$F$25*Inputs!$F$89/100+Inputs!$F$76*$F$25*Inputs!$F$90/100,0) -> 0 | Q42: =IF(Construction!Q8=1,Inputs!$F$73*$F$25*Inputs!$F$87/100+Inputs!$F$74*$F$25*Inputs!$F$88/100+Inputs!$F$75*$F$25*Inputs!$F$89/100+Inputs!$F$76*$F$25*Inputs!$F$90/100,0) -> 0 | ... BJ42: =IF(Construction!BJ8=1,Inputs!$F$73*$F$25*Inputs!$F$87/100+Inputs!$F$74*$F$25*Inputs!$F$88/100+Inputs!$F$75*$F$25*Inputs!$F$89/100+Inputs!$F$76*$F$25*Inputs!$F$90/100,0) -> 0
D43: Agency fees during construction | E43: USD m | G43: =SUM(J43:BJ43) -> 0.74375 | J43: =Construction!J14*Inputs!$F$105/12 -> 0.02125 | K43: =Construction!K14*Inputs!$F$105/12 -> 0.02125 | L43: =Construction!L14*Inputs!$F$105/12 -> 0.02125 | M43: =Construction!M14*Inputs!$F$105/12 -> 0.02125 | N43: =Construction!N14*Inputs!$F$105/12 -> 0.02125 | O43: =Construction!O14*Inputs!$F$105/12 -> 0.02125 | P43: =Construction!P14*Inputs!$F$105/12 -> 0.02125 | Q43: =Construction!Q14*Inputs!$F$105/12 -> 0.02125 | ... BJ43: =Construction!BJ14*Inputs!$F$105/12 -> 0
D44: DSRA initial funding (COD month) | E44: USD m | G44: =SUM(J44:BJ44) -> 40.840015 | J44: =Construction!J15*IF(Inputs!$F$33=1,$F$12*Inputs!$F$73*$F$25+$F$13*Inputs!$F$74*$F$25+$F$14*Inputs!$F$75*$F$25+$F$15*Inputs!$F$76*$F$25+$F$17,$F$12*J28+$F$13*J29+$F$14*J30+$F$15*J31+$F$16*J32+$F$17) -> 0 | K44: =Construction!K15*IF(Inputs!$F$33=1,$F$12*Inputs!$F$73*$F$25+$F$13*Inputs!$F$74*$F$25+$F$14*Inputs!$F$75*$F$25+$F$15*Inputs!$F$76*$F$25+$F$17,$F$12*K28+$F$13*K29+$F$14*K30+$F$15*K31+$F$16*K32+$F$17) -> 0 | L44: =Construction!L15*IF(Inputs!$F$33=1,$F$12*Inputs!$F$73*$F$25+$F$13*Inputs!$F$74*$F$25+$F$14*Inputs!$F$75*$F$25+$F$15*Inputs!$F$76*$F$25+$F$17,$F$12*L28+$F$13*L29+$F$14*L30+$F$15*L31+$F$16*L32+$F$17) -> 0 | M44: =Construction!M15*IF(Inputs!$F$33=1,$F$12*Inputs!$F$73*$F$25+$F$13*Inputs!$F$74*$F$25+$F$14*Inputs!$F$75*$F$25+$F$15*Inputs!$F$76*$F$25+$F$17,$F$12*M28+$F$13*M29+$F$14*M30+$F$15*M31+$F$16*M32+$F$17) -> 0 | N44: =Construction!N15*IF(Inputs!$F$33=1,$F$12*Inputs!$F$73*$F$25+$F$13*Inputs!$F$74*$F$25+$F$14*Inputs!$F$75*$F$25+$F$15*Inputs!$F$76*$F$25+$F$17,$F$12*N28+$F$13*N29+$F$14*N30+$F$15*N31+$F$16*N32+$F$17) -> 0 | O44: =Construction!O15*IF(Inputs!$F$33=1,$F$12*Inputs!$F$73*$F$25+$F$13*Inputs!$F$74*$F$25+$F$14*Inputs!$F$75*$F$25+$F$15*Inputs!$F$76*$F$25+$F$17,$F$12*O28+$F$13*O29+$F$14*O30+$F$15*O31+$F$16*O32+$F$17) -> 0 | P44: =Construction!P15*IF(Inputs!$F$33=1,$F$12*Inputs!$F$73*$F$25+$F$13*Inputs!$F$74*$F$25+$F$14*Inputs!$F$75*$F$25+$F$15*Inputs!$F$76*$F$25+$F$17,$F$12*P28+$F$13*P29+$F$14*P30+$F$15*P31+$F$16*P32+$F$17) -> 0 | Q44: =Construction!Q15*IF(Inputs!$F$33=1,$F$12*Inputs!$F$73*$F$25+$F$13*Inputs!$F$74*$F$25+$F$14*Inputs!$F$75*$F$25+$F$15*Inputs!$F$76*$F$25+$F$17,$F$12*Q28+$F$13*Q29+$F$14*Q30+$F$15*Q31+$F$16*Q32+$F$17) -> 0 | ... BJ44: =Construction!BJ15*IF(Inputs!$F$33=1,$F$12*Inputs!$F$73*$F$25+$F$13*Inputs!$F$74*$F$25+$F$14*Inputs!$F$75*$F$25+$F$15*Inputs!$F$76*$F$25+$F$17,$F$12*BJ28+$F$13*BJ29+$F$14*BJ30+$F$15*BJ31+$F$16*BJ32+$F$17) -> 0
D45: Uses before ECA premium | E45: USD m | J45: =Construction!J14*(Construction!J30+Construction!J36)+J33+J34+J35+J36+J37+J38+J39+J40+J41+J42+J43+J44 -> 127.20861 | K45: =Construction!K14*(Construction!K30+Construction!K36)+K33+K34+K35+K36+K37+K38+K39+K40+K41+K42+K43+K44 -> 2.6620094 | L45: =Construction!L14*(Construction!L30+Construction!L36)+L33+L34+L35+L36+L37+L38+L39+L40+L41+L42+L43+L44 -> 3.3988179 | M45: =Construction!M14*(Construction!M30+Construction!M36)+M33+M34+M35+M36+M37+M38+M39+M40+M41+M42+M43+M44 -> 4.81333 | N45: =Construction!N14*(Construction!N30+Construction!N36)+N33+N34+N35+N36+N37+N38+N39+N40+N41+N42+N43+N44 -> 6.9398879 | O45: =Construction!O14*(Construction!O30+Construction!O36)+O33+O34+O35+O36+O37+O38+O39+O40+O41+O42+O43+O44 -> 9.5723043 | P45: =Construction!P14*(Construction!P30+Construction!P36)+P33+P34+P35+P36+P37+P38+P39+P40+P41+P42+P43+P44 -> 12.492994 | Q45: =Construction!Q14*(Construction!Q30+Construction!Q36)+Q33+Q34+Q35+Q36+Q37+Q38+Q39+Q40+Q41+Q42+Q43+Q44 -> 15.863325 | ... BJ45: =Construction!BJ14*(Construction!BJ30+Construction!BJ36)+BJ33+BJ34+BJ35+BJ36+BJ37+BJ38+BJ39+BJ40+BJ41+BJ42+BJ43+BJ44 -> 0
D46: Headroom on committed senior tranches | E46: USD m | J46: =$F$25-J28-J29-J30-J31 -> 693.49615 | K46: =$F$25-K28-K29-K30-K31 -> 596.96193 | L46: =$F$25-L28-L29-L30-L31 -> 594.94182 | M46: =$F$25-M28-M29-M30-M31 -> 592.36258 | N46: =$F$25-N28-N29-N30-N31 -> 588.70991 | O46: =$F$25-O28-O29-O30-O31 -> 583.44347 | P46: =$F$25-P28-P29-P30-P31 -> 576.17937 | Q46: =$F$25-Q28-Q29-Q30-Q31 -> 566.69887 | ... BJ46: =$F$25-BJ28-BJ29-BJ30-BJ31 -> 0
D47: Senior tranche drawdown (pro rata) | E47: USD m | G47: =SUM(J47:BJ47) -> 693.49615 | J47: =MIN($F$26*J45/(1-Inputs!$F$92/100*Inputs!$F$73*$F$26),J46) -> 96.534221 | K47: =MIN($F$26*K45/(1-Inputs!$F$92/100*Inputs!$F$73*$F$26),K46) -> 2.020107 | L47: =MIN($F$26*L45/(1-Inputs!$F$92/100*Inputs!$F$73*$F$26),L46) -> 2.5792456 | M47: =MIN($F$26*M45/(1-Inputs!$F$92/100*Inputs!$F$73*$F$26),M46) -> 3.6526699 | N47: =MIN($F$26*N45/(1-Inputs!$F$92/100*Inputs!$F$73*$F$26),N46) -> 5.2664412 | O47: =MIN($F$26*O45/(1-Inputs!$F$92/100*Inputs!$F$73*$F$26),O46) -> 7.2640912 | P47: =MIN($F$26*P45/(1-Inputs!$F$92/100*Inputs!$F$73*$F$26),P46) -> 9.4805016 | Q47: =MIN($F$26*Q45/(1-Inputs!$F$92/100*Inputs!$F$73*$F$26),Q46) -> 12.03813 | ... BJ47: =MIN($F$26*BJ45/(1-Inputs!$F$92/100*Inputs!$F$73*$F$26),BJ46) -> 0
D48: ECA premium (financed) | E48: USD m | G48: =SUM(J48:BJ48) -> 22.5733 | J48: =Inputs!$F$92/100*Inputs!$F$73*J47 -> 3.1421889 | K48: =Inputs!$F$92/100*Inputs!$F$73*K47 -> 0.065754482 | L48: =Inputs!$F$92/100*Inputs!$F$73*L47 -> 0.083954443 | M48: =Inputs!$F$92/100*Inputs!$F$73*M47 -> 0.11889441 | N48: =Inputs!$F$92/100*Inputs!$F$73*N47 -> 0.17142266 | O48: =Inputs!$F$92/100*Inputs!$F$73*O47 -> 0.23644617 | P48: =Inputs!$F$92/100*Inputs!$F$73*P47 -> 0.30859033 | Q48: =Inputs!$F$92/100*Inputs!$F$73*Q47 -> 0.39184112 | ... BJ48: =Inputs!$F$92/100*Inputs!$F$73*BJ47 -> 0
D49: Total uses of funds | E49: USD m | G49: =SUM(J49:BJ49) -> 936.43245 | J49: =J45+J48 -> 130.3508 | K49: =K45+K48 -> 2.7277638 | L49: =L45+L48 -> 3.4827724 | M49: =M45+M48 -> 4.9322244 | N49: =N45+N48 -> 7.1113105 | O49: =O45+O48 -> 9.8087505 | P49: =P45+P48 -> 12.801584 | Q49: =Q45+Q48 -> 16.255166 | ... BJ49: =BJ45+BJ48 -> 0
D50: Funded pro rata from committed debt and equity | E50: USD m | G50: =SUM(J50:BJ50) -> 936.43245 | J50: =J47/$F$26 -> 130.3508 | K50: =K47/$F$26 -> 2.7277638 | L50: =L47/$F$26 -> 3.4827724 | M50: =M47/$F$26 -> 4.9322244 | N50: =N47/$F$26 -> 7.1113105 | O50: =O47/$F$26 -> 9.8087505 | P50: =P47/$F$26 -> 12.801584 | Q50: =Q47/$F$26 -> 16.255166 | ... BJ50: =BJ47/$F$26 -> 0
D51: Remaining uses after committed facilities | E51: USD m | J51: =J49-J50 -> 0 | K51: =K49-K50 -> 0 | L51: =L49-L50 -> 0 | M51: =M49-M50 -> 0 | N51: =N49-N50 -> 0 | O51: =O49-O50 -> 0 | P51: =P49-P50 -> 0 | Q51: =Q49-Q50 -> 0 | ... BJ51: =BJ49-BJ50 -> 0
D52: Delay LDs and DSU proceeds received | E52: USD m | G52: =SUM(J52:BJ52) -> 0 | J52: =IF(AND(Inputs!$F$33=2,Construction!J8=40),Inputs!$F$186+Inputs!$F$187,0) -> 0 | K52: =IF(AND(Inputs!$F$33=2,Construction!K8=40),Inputs!$F$186+Inputs!$F$187,0) -> 0 | L52: =IF(AND(Inputs!$F$33=2,Construction!L8=40),Inputs!$F$186+Inputs!$F$187,0) -> 0 | M52: =IF(AND(Inputs!$F$33=2,Construction!M8=40),Inputs!$F$186+Inputs!$F$187,0) -> 0 | N52: =IF(AND(Inputs!$F$33=2,Construction!N8=40),Inputs!$F$186+Inputs!$F$187,0) -> 0 | O52: =IF(AND(Inputs!$F$33=2,Construction!O8=40),Inputs!$F$186+Inputs!$F$187,0) -> 0 | P52: =IF(AND(Inputs!$F$33=2,Construction!P8=40),Inputs!$F$186+Inputs!$F$187,0) -> 0 | Q52: =IF(AND(Inputs!$F$33=2,Construction!Q8=40),Inputs!$F$186+Inputs!$F$187,0) -> 0 | ... BJ52: =IF(AND(Inputs!$F$33=2,Construction!BJ8=40),Inputs!$F$186+Inputs!$F$187,0) -> 0
D53: LD and DSU proceeds applied | E53: USD m | G53: =SUM(J53:BJ53) -> 0 | J53: =MIN(J51,0+J52) -> 0 | K53: =MIN(K51,J54+K52) -> 0 | L53: =MIN(L51,K54+L52) -> 0 | M53: =MIN(M51,L54+M52) -> 0 | N53: =MIN(N51,M54+N52) -> 0 | O53: =MIN(O51,N54+O52) -> 0 | P53: =MIN(P51,O54+P52) -> 0 | Q53: =MIN(Q51,P54+Q52) -> 0 | R53: =MIN(R51,Q54+R52) -> 0 | ... BJ53: =MIN(BJ51,BI54+BJ52) -> 0
D54: LD and DSU proceeds held (Proceeds Account) | E54: USD m | J54: =0+J52-J53 -> 0 | K54: =J54+K52-K53 -> 0 | L54: =K54+L52-L53 -> 0 | M54: =L54+M52-M53 -> 0 | N54: =M54+N52-N53 -> 0 | O54: =N54+O52-O53 -> 0 | P54: =O54+P52-P53 -> 0 | Q54: =P54+Q52-Q53 -> 0 | R54: =Q54+R52-R53 -> 0 | ... BJ54: =BI54+BJ52-BJ53 -> 0
D55: Standby facility drawdown (75%) | E55: USD m | G55: =SUM(J55:BJ55) -> 4.7295501e-14 | J55: =0.75*(J51-J53) -> 0 | K55: =0.75*(K51-K53) -> 0 | L55: =0.75*(L51-L53) -> 0 | M55: =0.75*(M51-M53) -> 0 | N55: =0.75*(N51-N53) -> 0 | O55: =0.75*(O51-O53) -> 0 | P55: =0.75*(P51-P53) -> 0 | Q55: =0.75*(Q51-Q53) -> 0 | ... BJ55: =0.75*(BJ51-BJ53) -> 0
D56: Contingent equity (25%) | E56: USD m | G56: =SUM(J56:BJ56) -> 1.5765167e-14 | J56: =0.25*(J51-J53) -> 0 | K56: =0.25*(K51-K53) -> 0 | L56: =0.25*(L51-L53) -> 0 | M56: =0.25*(M51-M53) -> 0 | N56: =0.25*(N51-N53) -> 0 | O56: =0.25*(O51-O53) -> 0 | P56: =0.25*(P51-P53) -> 0 | Q56: =0.25*(Q51-Q53) -> 0 | ... BJ56: =0.25*(BJ51-BJ53) -> 0
D57: ECA-covered tranche: drawdown | E57: USD m | G57: =SUM(J57:BJ57) -> 208.04885 | J57: =Inputs!$F$73*J47 -> 28.960266 | K57: =Inputs!$F$73*K47 -> 0.60603209 | L57: =Inputs!$F$73*L47 -> 0.77377367 | M57: =Inputs!$F$73*M47 -> 1.095801 | N57: =Inputs!$F$73*N47 -> 1.5799324 | O57: =Inputs!$F$73*O47 -> 2.1792273 | P57: =Inputs!$F$73*P47 -> 2.8441505 | Q57: =Inputs!$F$73*Q47 -> 3.6114389 | ... BJ57: =Inputs!$F$73*BJ47 -> 0
D58: ABDB A-loan: drawdown | E58: USD m | G58: =SUM(J58:BJ58) -> 152.56915 | J58: =Inputs!$F$74*J47 -> 21.237529 | K58: =Inputs!$F$74*K47 -> 0.44442353 | L58: =Inputs!$F$74*L47 -> 0.56743402 | M58: =Inputs!$F$74*M47 -> 0.80358738 | N58: =Inputs!$F$74*N47 -> 1.1586171 | O58: =Inputs!$F$74*O47 -> 1.5981001 | P58: =Inputs!$F$74*P47 -> 2.0857103 | Q58: =Inputs!$F$74*Q47 -> 2.6483885 | ... BJ58: =Inputs!$F$74*BJ47 -> 0
D59: ABDB B-loan: drawdown | E59: USD m | G59: =SUM(J59:BJ59) -> 69.349615 | J59: =Inputs!$F$75*J47 -> 9.6534221 | K59: =Inputs!$F$75*K47 -> 0.2020107 | L59: =Inputs!$F$75*L47 -> 0.25792456 | M59: =Inputs!$F$75*M47 -> 0.36526699 | N59: =Inputs!$F$75*N47 -> 0.52664412 | O59: =Inputs!$F$75*O47 -> 0.72640912 | P59: =Inputs!$F$75*P47 -> 0.94805016 | Q59: =Inputs!$F$75*Q47 -> 1.203813 | ... BJ59: =Inputs!$F$75*BJ47 -> 0
D60: Commercial tranche: drawdown | E60: USD m | G60: =SUM(J60:BJ60) -> 263.52854 | J60: =Inputs!$F$76*J47 -> 36.683004 | K60: =Inputs!$F$76*K47 -> 0.76764065 | L60: =Inputs!$F$76*L47 -> 0.98011331 | M60: =Inputs!$F$76*M47 -> 1.3880146 | N60: =Inputs!$F$76*N47 -> 2.0012477 | O60: =Inputs!$F$76*O47 -> 2.7603546 | P60: =Inputs!$F$76*P47 -> 3.6025906 | Q60: =Inputs!$F$76*Q47 -> 4.5744892 | ... BJ60: =Inputs!$F$76*BJ47 -> 0
D61: ECA-covered tranche: closing balance | E61: USD m | J61: =J28+J57 -> 28.960266 | K61: =K28+K57 -> 29.566298 | L61: =L28+L57 -> 30.340072 | M61: =M28+M57 -> 31.435873 | N61: =N28+N57 -> 33.015805 | O61: =O28+O57 -> 35.195033 | P61: =P28+P57 -> 38.039183 | Q61: =Q28+Q57 -> 41.650622 | ... BJ61: =BJ28+BJ57 -> 208.04885
D62: ABDB A-loan: closing balance | E62: USD m | J62: =J29+J58 -> 21.237529 | K62: =K29+K58 -> 21.681952 | L62: =L29+L58 -> 22.249386 | M62: =M29+M58 -> 23.052974 | N62: =N29+N58 -> 24.211591 | O62: =O29+O58 -> 25.809691 | P62: =P29+P58 -> 27.895401 | Q62: =Q29+Q58 -> 30.54379 | ... BJ62: =BJ29+BJ58 -> 152.56915
D63: ABDB B-loan: closing balance | E63: USD m | J63: =J30+J59 -> 9.6534221 | K63: =K30+K59 -> 9.8554328 | L63: =L30+L59 -> 10.113357 | M63: =M30+M59 -> 10.478624 | N63: =N30+N59 -> 11.005268 | O63: =O30+O59 -> 11.731678 | P63: =P30+P59 -> 12.679728 | Q63: =Q30+Q59 -> 13.883541 | ... BJ63: =BJ30+BJ59 -> 69.349615
D64: Commercial tranche: closing balance | E64: USD m | J64: =J31+J60 -> 36.683004 | K64: =K31+K60 -> 37.450645 | L64: =L31+L60 -> 38.430758 | M64: =M31+M60 -> 39.818773 | N64: =N31+N60 -> 41.82002 | O64: =O31+O60 -> 44.580375 | P64: =P31+P60 -> 48.182966 | Q64: =Q31+Q60 -> 52.757455 | ... BJ64: =BJ31+BJ60 -> 263.52854
D65: Standby facility: closing balance | E65: USD m | J65: =J32+J55 -> 0 | K65: =K32+K55 -> 0 | L65: =L32+L55 -> 0 | M65: =M32+M55 -> 0 | N65: =N32+N55 -> 0 | O65: =O32+O55 -> 0 | P65: =P32+P55 -> 0 | Q65: =Q32+Q55 -> 0 | ... BJ65: =BJ32+BJ55 -> 4.7295501e-14
B66: Equity (USD m)
D67: Equity contributions (incl. LNTP credit in month 1) | E67: USD m | G67: =SUM(J67:BJ67) -> 242.9363 | J67: =J50-J47+J56 -> 33.816578 | K67: =K50-K47+K56 -> 0.70765687 | L67: =L50-L47+L56 -> 0.90352682 | M67: =M50-M47+M56 -> 1.2795545 | N67: =N50-N47+N56 -> 1.8448693 | O67: =O50-O47+O56 -> 2.5446593 | P67: =P50-P47+P56 -> 3.3210826 | Q67: =Q50-Q47+Q56 -> 4.2170366 | ... BJ67: =BJ50-BJ47+BJ56 -> 0
D68: Equity contributed in cash | E68: USD m | G68: =SUM(J68:BJ68) -> 228.7363 | J68: =J67-IF(Construction!J8=1,Inputs!$F$66,0) -> 19.616578 | K68: =K67-IF(Construction!K8=1,Inputs!$F$66,0) -> 0.70765687 | L68: =L67-IF(Construction!L8=1,Inputs!$F$66,0) -> 0.90352682 | M68: =M67-IF(Construction!M8=1,Inputs!$F$66,0) -> 1.2795545 | N68: =N67-IF(Construction!N8=1,Inputs!$F$66,0) -> 1.8448693 | O68: =O67-IF(Construction!O8=1,Inputs!$F$66,0) -> 2.5446593 | P68: =P67-IF(Construction!P8=1,Inputs!$F$66,0) -> 3.3210826 | Q68: =Q67-IF(Construction!Q8=1,Inputs!$F$66,0) -> 4.2170366 | ... BJ68: =BJ67-IF(Construction!BJ8=1,Inputs!$F$66,0) -> 0
D69: Share capital | E69: USD m | G69: =SUM(J69:BJ69) -> 48.58726 | J69: =(1-Inputs!$F$52)*J67 -> 6.7633156 | K69: =(1-Inputs!$F$52)*K67 -> 0.14153137 | L69: =(1-Inputs!$F$52)*L67 -> 0.18070536 | M69: =(1-Inputs!$F$52)*M67 -> 0.2559109 | N69: =(1-Inputs!$F$52)*N67 -> 0.36897386 | O69: =(1-Inputs!$F$52)*O67 -> 0.50893186 | P69: =(1-Inputs!$F$52)*P67 -> 0.66421651 | Q69: =(1-Inputs!$F$52)*Q67 -> 0.84340732 | ... BJ69: =(1-Inputs!$F$52)*BJ67 -> 0
D70: Shareholder loans advanced | E70: USD m | G70: =SUM(J70:BJ70) -> 194.34904 | J70: =Inputs!$F$52*J67 -> 27.053262 | K70: =Inputs!$F$52*K67 -> 0.5661255 | L70: =Inputs!$F$52*L67 -> 0.72282146 | M70: =Inputs!$F$52*M67 -> 1.0236436 | N70: =Inputs!$F$52*N67 -> 1.4758954 | O70: =Inputs!$F$52*O67 -> 2.0357274 | P70: =Inputs!$F$52*P67 -> 2.6568661 | Q70: =Inputs!$F$52*Q67 -> 3.3736293 | ... BJ70: =Inputs!$F$52*BJ67 -> 0
D71: Shareholder loan interest capitalized (to COD) | E71: USD m | G71: =SUM(J71:BJ71) -> 26.391783 | J71: =IF(Construction!J8<=Time!$F$10,0*Inputs!$F$102/100*Construction!J11/365,0) -> 0 | K71: =IF(Construction!K8<=Time!$F$10,J72*Inputs!$F$102/100*Construction!K11/365,0) -> 0.2112378 | L71: =IF(Construction!L8<=Time!$F$10,K72*Inputs!$F$102/100*Construction!L11/365,0) -> 0.22455121 | M71: =IF(Construction!M8<=Time!$F$10,L72*Inputs!$F$102/100*Construction!M11/365,0) -> 0.22470492 | N71: =IF(Construction!N8<=Time!$F$10,M72*Inputs!$F$102/100*Construction!N11/365,0) -> 0.24226737 | O71: =IF(Construction!O8<=Time!$F$10,N72*Inputs!$F$102/100*Construction!O11/365,0) -> 0.25613036 | P71: =IF(Construction!P8<=Time!$F$10,O72*Inputs!$F$102/100*Construction!P11/365,0) -> 0.24804586 | Q71: =IF(Construction!Q8<=Time!$F$10,P72*Inputs!$F$102/100*Construction!Q11/365,0) -> 0.29806046 | R71: =IF(Construction!R8<=Time!$F$10,Q72*Inputs!$F$102/100*Construction!R11/365,0) -> 0.31711496 | ... BJ71: =IF(Construction!BJ8<=Time!$F$10,BI72*Inputs!$F$102/100*Construction!BJ11/365,0) -> 0
D72: Shareholder loan balance | E72: USD m | J72: =0+J71+J70 -> 27.053262 | K72: =J72+K71+K70 -> 27.830626 | L72: =K72+L71+L70 -> 28.777998 | M72: =L72+M71+M70 -> 30.026347 | N72: =M72+N71+N70 -> 31.74451 | O72: =N72+O71+O70 -> 34.036367 | P72: =O72+P71+P70 -> 36.941279 | Q72: =P72+Q71+Q70 -> 40.612969 | R72: =Q72+R71+R70 -> 45.017956 | ... BJ72: =BI72+BJ71+BJ70 -> 220.74082
D73: Total debt drawdowns (incl. standby) | E73: USD m | G73: =SUM(J73:BJ73) -> 693.49615 | J73: =J47+J55 -> 96.534221 | K73: =K47+K55 -> 2.020107 | L73: =L47+L55 -> 2.5792456 | M73: =M47+M55 -> 3.6526699 | N73: =N47+N55 -> 5.2664412 | O73: =O47+O55 -> 7.2640912 | P73: =P47+P55 -> 9.4805016 | Q73: =Q47+Q55 -> 12.03813 | ... BJ73: =BJ47+BJ55 -> 0
D74: Financing costs (IDC, fees, premium, VAT interest) | E74: USD m | G74: =SUM(J74:BJ74) -> 116.76644 | J74: =J33+J34+J35+J36+J37+J38+J39+J40+J41+J42+J43+J48+Construction!J14*Construction!J36 -> 14.691039 | K74: =K33+K34+K35+K36+K37+K38+K39+K40+K41+K42+K43+K48+Construction!K14*Construction!K36 -> 1.1648515 | L74: =L33+L34+L35+L36+L37+L38+L39+L40+L41+L42+L43+L48+Construction!L14*Construction!L36 -> 1.2226305 | M74: =M33+M34+M35+M36+M37+M38+M39+M40+M41+M42+M43+M48+Construction!M14*Construction!M36 -> 1.2395308 | N74: =N33+N34+N35+N36+N37+N38+N39+N40+N41+N42+N43+N48+Construction!N14*Construction!N36 -> 1.3405326 | O74: =O33+O34+O35+O36+O37+O38+O39+O40+O41+O42+O43+O48+Construction!O14*Construction!O36 -> 1.4395168 | P74: =P33+P34+P35+P36+P37+P38+P39+P40+P41+P42+P43+P48+Construction!P14*Construction!P36 -> 1.4516089 | Q74: =Q33+Q34+Q35+Q36+Q37+Q38+Q39+Q40+Q41+Q42+Q43+Q48+Construction!Q14*Construction!Q36 -> 1.6809291 | ... BJ74: =BJ33+BJ34+BJ35+BJ36+BJ37+BJ38+BJ39+BJ40+BJ41+BJ42+BJ43+BJ48+Construction!BJ14*Construction!BJ36 -> 0
D75: Total funding requirement (sum of uses) | E75: USD m | F75: =SUM(Funding!$J$49:$BJ$49) -> 936.43245
D76: Capitalized cost (book and tax) | E76: USD m | F76: =SUM(Funding!$J$49:$BJ$49)-SUM(Funding!$J$44:$BJ$44)-SUM(Construction!$J$28:$BJ$28)+SUM(Funding!$J$71:$BJ$71)-SUM(Funding!$J$52:$BJ$52)-Inputs!$F$47*Inputs!$F$188 -> 916.09922

Sheet Debt
A1: Case P: Belanou Combined Cycle Power Project, Republic of Kessara
A2: Debt: tranches, scheduled repayment, waiver, refinancing, swap, sculpting
A3: Units in column E; constants in column F; row totals in column G; first period in column J. Inputs: blue on yellow. Links from other sheets: green.
D4: Label | E4: Unit | F4: Constant | G4: Total
D5: Period ending | J5: 2018H2 | K5: 2019H1 | L5: 2019H2 | M5: 2020H1 | N5: 2020H2 | O5: 2021H1 | P5: 2021H2 | Q5: 2022H1 | R5: 2022H2 | S5: 2023H1 | T5: 2023H2 | U5: 2024H1 | V5: 2024H2 | W5: 2025H1 | X5: 2025H2 | Y5: 2026H1 | Z5: 2026H2 | AA5: 2027H1 | AB5: 2027H2 | AC5: 2028H1 | AD5: 2028H2 | AE5: 2029H1 | AF5: 2029H2 | AG5: 2030H1 | AH5: 2030H2 | AI5: 2031H1 | AJ5: 2031H2 | AK5: 2032H1 | AL5: 2032H2 | AM5: 2033H1 | AN5: 2033H2 | AO5: 2034H1 | AP5: 2034H2 | AQ5: 2035H1 | AR5: 2035H2 | AS5: 2036H1 | AT5: 2036H2 | AU5: 2037H1 | AV5: 2037H2 | AW5: 2038H1 | AX5: 2038H2 | AY5: 2039H1 | AZ5: 2039H2 | BA5: 2040H1 | BB5: 2040H2 | BC5: 2041H1 | BD5: 2041H2 | BE5: 2042H1 | BF5: 2042H2 | BG5: 2043H1 | BH5: 2043H2 | BI5: 2044H1 | BJ5: 2044H2 | BK5: 2045H1 | BL5: 2045H2 | BM5: 2046H1 | BN5: 2046H2
B7: Rates
D8: Commercial margin (step-ups) | E8: % | J8: =IF(Time!J21<=2025,Inputs!$F$80,IF(Time!J21<=2029,Inputs!$F$81,Inputs!$F$82)) -> 4.1 | K8: =IF(Time!K21<=2025,Inputs!$F$80,IF(Time!K21<=2029,Inputs!$F$81,Inputs!$F$82)) -> 4.1 | L8: =IF(Time!L21<=2025,Inputs!$F$80,IF(Time!L21<=2029,Inputs!$F$81,Inputs!$F$82)) -> 4.1 | M8: =IF(Time!M21<=2025,Inputs!$F$80,IF(Time!M21<=2029,Inputs!$F$81,Inputs!$F$82)) -> 4.1 | N8: =IF(Time!N21<=2025,Inputs!$F$80,IF(Time!N21<=2029,Inputs!$F$81,Inputs!$F$82)) -> 4.1 | O8: =IF(Time!O21<=2025,Inputs!$F$80,IF(Time!O21<=2029,Inputs!$F$81,Inputs!$F$82)) -> 4.1 | P8: =IF(Time!P21<=2025,Inputs!$F$80,IF(Time!P21<=2029,Inputs!$F$81,Inputs!$F$82)) -> 4.1 | Q8: =IF(Time!Q21<=2025,Inputs!$F$80,IF(Time!Q21<=2029,Inputs!$F$81,Inputs!$F$82)) -> 4.1 | ... BN8: =IF(Time!BN21<=2025,Inputs!$F$80,IF(Time!BN21<=2029,Inputs!$F$81,Inputs!$F$82)) -> 5.1
D9: Waiver margin uplift | E9: % | J9: =Inputs!$F$48*IF(AND(Time!J17>=11,Time!J17<=13),Inputs!$F$190,0) -> 0 | K9: =Inputs!$F$48*IF(AND(Time!K17>=11,Time!K17<=13),Inputs!$F$190,0) -> 0 | L9: =Inputs!$F$48*IF(AND(Time!L17>=11,Time!L17<=13),Inputs!$F$190,0) -> 0 | M9: =Inputs!$F$48*IF(AND(Time!M17>=11,Time!M17<=13),Inputs!$F$190,0) -> 0 | N9: =Inputs!$F$48*IF(AND(Time!N17>=11,Time!N17<=13),Inputs!$F$190,0) -> 0 | O9: =Inputs!$F$48*IF(AND(Time!O17>=11,Time!O17<=13),Inputs!$F$190,0) -> 0 | P9: =Inputs!$F$48*IF(AND(Time!P17>=11,Time!P17<=13),Inputs!$F$190,0) -> 0 | Q9: =Inputs!$F$48*IF(AND(Time!Q17>=11,Time!Q17<=13),Inputs!$F$190,0) -> 0 | ... BN9: =Inputs!$F$48*IF(AND(Time!BN17>=11,Time!BN17<=13),Inputs!$F$190,0) -> 0
D10: ECA-covered tranche: rate per period | E10: factor | J10: =(Operations!J9+Inputs!$F$77+J9)/100*Time!J20/360 -> 0.01978 | K10: =(Operations!K9+Inputs!$F$77+K9)/100*Time!K20/360 -> 0.020815 | L10: =(Operations!L9+Inputs!$F$77+L9)/100*Time!L20/360 -> 0.021926667 | M10: =(Operations!M9+Inputs!$F$77+M9)/100*Time!M20/360 -> 0.022092778 | N10: =(Operations!N9+Inputs!$F$77+N9)/100*Time!N20/360 -> 0.02254 | O10: =(Operations!O9+Inputs!$F$77+O9)/100*Time!O20/360 -> 0.022323333 | P10: =(Operations!P9+Inputs!$F$77+P9)/100*Time!P20/360 -> 0.022693333 | Q10: =(Operations!Q9+Inputs!$F$77+Q9)/100*Time!Q20/360 -> 0.022423889 | ... BN10: =(Operations!BN9+Inputs!$F$77+BN9)/100*Time!BN20/360 -> 0.022846667
D11: ABDB A-loan: rate per period | E11: factor | J11: =(Operations!J9+Inputs!$F$78+J9)/100*Time!J20/360 -> 0.031535556 | K11: =(Operations!K9+Inputs!$F$78+K9)/100*Time!K20/360 -> 0.032378889 | L11: =(Operations!L9+Inputs!$F$78+L9)/100*Time!L20/360 -> 0.033682222 | M11: =(Operations!M9+Inputs!$F$78+M9)/100*Time!M20/360 -> 0.033720556 | N11: =(Operations!N9+Inputs!$F$78+N9)/100*Time!N20/360 -> 0.034295556 | O11: =(Operations!O9+Inputs!$F$78+O9)/100*Time!O20/360 -> 0.033887222 | P11: =(Operations!P9+Inputs!$F$78+P9)/100*Time!P20/360 -> 0.034448889 | Q11: =(Operations!Q9+Inputs!$F$78+Q9)/100*Time!Q20/360 -> 0.033987778 | ... BN11: =(Operations!BN9+Inputs!$F$78+BN9)/100*Time!BN20/360 -> 0.034602222
D12: ABDB B-loan: rate per period | E12: factor | J12: =(Operations!J9+Inputs!$F$79+J9)/100*Time!J20/360 -> 0.030257778 | K12: =(Operations!K9+Inputs!$F$79+K9)/100*Time!K20/360 -> 0.031121944 | L12: =(Operations!L9+Inputs!$F$79+L9)/100*Time!L20/360 -> 0.032404444 | M12: =(Operations!M9+Inputs!$F$79+M9)/100*Time!M20/360 -> 0.032456667 | N12: =(Operations!N9+Inputs!$F$79+N9)/100*Time!N20/360 -> 0.033017778 | O12: =(Operations!O9+Inputs!$F$79+O9)/100*Time!O20/360 -> 0.032630278 | P12: =(Operations!P9+Inputs!$F$79+P9)/100*Time!P20/360 -> 0.033171111 | Q12: =(Operations!Q9+Inputs!$F$79+Q9)/100*Time!Q20/360 -> 0.032730833 | ... BN12: =(Operations!BN9+Inputs!$F$79+BN9)/100*Time!BN20/360 -> 0.033324444
D13: Commercial tranche: rate per period | E13: factor | J13: =(Operations!J9+J8+J9)/100*Time!J20/360/(1-Inputs!$F$91/100) -> 0.037595062 | K13: =(Operations!K9+K8+K9)/100*Time!K20/360/(1-Inputs!$F$91/100) -> 0.038490432 | L13: =(Operations!L9+L8+L9)/100*Time!L20/360/(1-Inputs!$F$91/100) -> 0.039980247 | M13: =(Operations!M9+M8+M9)/100*Time!M20/360/(1-Inputs!$F$91/100) -> 0.039995062 | N13: =(Operations!N9+N8+N9)/100*Time!N20/360/(1-Inputs!$F$91/100) -> 0.040661728 | O13: =(Operations!O9+O8+O9)/100*Time!O20/360/(1-Inputs!$F$91/100) -> 0.040166358 | P13: =(Operations!P9+P8+P9)/100*Time!P20/360/(1-Inputs!$F$91/100) -> 0.040832099 | Q13: =(Operations!Q9+Q8+Q9)/100*Time!Q20/360/(1-Inputs!$F$91/100) -> 0.040278086 | ... BN13: =(Operations!BN9+BN8+BN9)/100*Time!BN20/360/(1-Inputs!$F$91/100) -> 0.046681481
D14: Standby facility: rate per period | E14: factor | J14: =(Inputs!$F$100*(Operations!J9+J8+Inputs!$F$99+J9)/(1-Inputs!$F$91/100)+(1-Inputs!$F$100)*(Operations!J9+Inputs!$F$78+Inputs!$F$99+J9))/100*Time!J20/360 -> 0.036534222 | K14: =(Inputs!$F$100*(Operations!K9+K8+Inputs!$F$99+K9)/(1-Inputs!$F$91/100)+(1-Inputs!$F$100)*(Operations!K9+Inputs!$F$78+Inputs!$F$99+K9))/100*Time!K20/360 -> 0.037386556 | L14: =(Inputs!$F$100*(Operations!L9+L8+Inputs!$F$99+L9)/(1-Inputs!$F$91/100)+(1-Inputs!$F$100)*(Operations!L9+Inputs!$F$78+Inputs!$F$99+L9))/100*Time!L20/360 -> 0.038824 | M14: =(Inputs!$F$100*(Operations!M9+M8+Inputs!$F$99+M9)/(1-Inputs!$F$91/100)+(1-Inputs!$F$100)*(Operations!M9+Inputs!$F$78+Inputs!$F$99+M9))/100*Time!M20/360 -> 0.038833407 | N14: =(Inputs!$F$100*(Operations!N9+N8+Inputs!$F$99+N9)/(1-Inputs!$F$91/100)+(1-Inputs!$F$100)*(Operations!N9+Inputs!$F$78+Inputs!$F$99+N9))/100*Time!N20/360 -> 0.039478222 | O14: =(Inputs!$F$100*(Operations!O9+O8+Inputs!$F$99+O9)/(1-Inputs!$F$91/100)+(1-Inputs!$F$100)*(Operations!O9+Inputs!$F$78+Inputs!$F$99+O9))/100*Time!O20/360 -> 0.038995444 | P14: =(Inputs!$F$100*(Operations!P9+P8+Inputs!$F$99+P9)/(1-Inputs!$F$91/100)+(1-Inputs!$F$100)*(Operations!P9+Inputs!$F$78+Inputs!$F$99+P9))/100*Time!P20/360 -> 0.039641778 | Q14: =(Inputs!$F$100*(Operations!Q9+Q8+Inputs!$F$99+Q9)/(1-Inputs!$F$91/100)+(1-Inputs!$F$100)*(Operations!Q9+Inputs!$F$78+Inputs!$F$99+Q9))/100*Time!Q20/360 -> 0.039102704 | ... BN14: =(Inputs!$F$100*(Operations!BN9+BN8+Inputs!$F$99+BN9)/(1-Inputs!$F$91/100)+(1-Inputs!$F$100)*(Operations!BN9+Inputs!$F$78+Inputs!$F$99+BN9))/100*Time!BN20/360 -> 0.043212741
D15: 2025 project bond: rate per period | E15: factor | J15: =Inputs!$F$192/100*0.5 -> 0.039375 | K15: =Inputs!$F$192/100*0.5 -> 0.039375 | L15: =Inputs!$F$192/100*0.5 -> 0.039375 | M15: =Inputs!$F$192/100*0.5 -> 0.039375 | N15: =Inputs!$F$192/100*0.5 -> 0.039375 | O15: =Inputs!$F$192/100*0.5 -> 0.039375 | P15: =Inputs!$F$192/100*0.5 -> 0.039375 | Q15: =Inputs!$F$192/100*0.5 -> 0.039375 | ... BN15: =Inputs!$F$192/100*0.5 -> 0.039375
B16: Contract repayment profile
D17: Repayment profile, selected | E17: fraction | J17: =IF(Inputs!$F$46=1,Inputs!J219,Inputs!J220) -> 0 | K17: =IF(Inputs!$F$46=1,Inputs!K219,Inputs!K220) -> 0 | L17: =IF(Inputs!$F$46=1,Inputs!L219,Inputs!L220) -> 0 | M17: =IF(Inputs!$F$46=1,Inputs!M219,Inputs!M220) -> 0 | N17: =IF(Inputs!$F$46=1,Inputs!N219,Inputs!N220) -> 0 | O17: =IF(Inputs!$F$46=1,Inputs!O219,Inputs!O220) -> 0 | P17: =IF(Inputs!$F$46=1,Inputs!P219,Inputs!P220) -> 0.024460432 | Q17: =IF(Inputs!$F$46=1,Inputs!Q219,Inputs!Q220) -> 0.02549564 | ... BN17: =IF(Inputs!$F$46=1,Inputs!BN219,Inputs!BN220) -> 0
D18: Remaining profile (this and later installments) | E18: fraction | J18: =SUM(J17:BN17) -> 1 | K18: =SUM(K17:BN17) -> 1 | L18: =SUM(L17:BN17) -> 1 | M18: =SUM(M17:BN17) -> 1 | N18: =SUM(N17:BN17) -> 1 | O18: =SUM(O17:BN17) -> 1 | P18: =SUM(P17:BN17) -> 1 | Q18: =SUM(Q17:BN17) -> 0.97553957 | R18: =SUM(R17:BN17) -> 0.95004393 | S18: =SUM(S17:BN17) -> 0.92329241 | T18: =SUM(T17:BN17) -> 0.89575256 | U18: =SUM(U17:BN17) -> 0.86694589 | V18: =SUM(V17:BN17) -> 0.83722053 | W18: =SUM(W17:BN17) -> 0.80555322 | X18: =SUM(X17:BN17) -> 0.77291787 | Y18: =SUM(Y17:BN17) -> 0.7411884 | Z18: =SUM(Z17:BN17) -> 0.709444 | AA18: =SUM(AA17:BN17) -> 0.6763845 | AB18: =SUM(AB17:BN17) -> 0.64236024 | AC18: =SUM(AC17:BN17) -> 0.60671049 | AD18: =SUM(AD17:BN17) -> 0.56987972 | AE18: =SUM(AE17:BN17) -> 0.52966321 | AF18: =SUM(AF17:BN17) -> 0.48771816 | AG18: =SUM(AG17:BN17) -> 0.44430162 | AH18: =SUM(AH17:BN17) -> 0.40007478 | AI18: =SUM(AI17:BN17) -> 0.35362768 | AJ18: =SUM(AJ17:BN17) -> 0.30581678 | AK18: =SUM(AK17:BN17) -> 0.25569769 | AL18: =SUM(AL17:BN17) -> 0.20395632 | AM18: =SUM(AM17:BN17) -> 0.14909295 | AN18: =SUM(AN17:BN17) -> 0.093089243 | AO18: =SUM(AO17:BN17) -> 0.04688685 | AP18: =SUM(AP17:BN17) -> 0 | AQ18: =SUM(AQ17:BN17) -> 0 | AR18: =SUM(AR17:BN17) -> 0 | AS18: =SUM(AS17:BN17) -> 0 | AT18: =SUM(AT17:BN17) -> 0 | AU18: =SUM(AU17:BN17) -> 0 | AV18: =SUM(AV17:BN17) -> 0 | AW18: =SUM(AW17:BN17) -> 0 | AX18: =SUM(AX17:BN17) -> 0 | AY18: =SUM(AY17:BN17) -> 0 | AZ18: =SUM(AZ17:BN17) -> 0 | BA18: =SUM(BA17:BN17) -> 0 | BB18: =SUM(BB17:BN17) -> 0 | BC18: =SUM(BC17:BN17) -> 0 | BD18: =SUM(BD17:BN17) -> 0 | BE18: =SUM(BE17:BN17) -> 0 | BF18: =SUM(BF17:BN17) -> 0 | BG18: =SUM(BG17:BN17) -> 0 | BH18: =SUM(BH17:BN17) -> 0 | BI18: =SUM(BI17:BN17) -> 0 | BJ18: =SUM(BJ17:BN17) -> 0 | BK18: =SUM(BK17:BN17) -> 0 | BL18: =SUM(BL17:BN17) -> 0 | BM18: =SUM(BM17:BN17) -> 0 | BN18: =SUM(BN17:BN17) -> 0
D19: Installment share of remaining balance | E19: fraction | J19: =IF(J18>0.000000000001,J17/J18,0) -> 0 | K19: =IF(K18>0.000000000001,K17/K18,0) -> 0 | L19: =IF(L18>0.000000000001,L17/L18,0) -> 0 | M19: =IF(M18>0.000000000001,M17/M18,0) -> 0 | N19: =IF(N18>0.000000000001,N17/N18,0) -> 0 | O19: =IF(O18>0.000000000001,O17/O18,0) -> 0 | P19: =IF(P18>0.000000000001,P17/P18,0) -> 0.024460432 | Q19: =IF(Q18>0.000000000001,Q17/Q18,0) -> 0.026134911 | ... BN19: =IF(BN18>0.000000000001,BN17/BN18,0) -> 0
D20: Flag_Refinancing (2025H1) | E20: flag | J20: =Inputs!$F$49*IF(Time!J17=15,1,0) -> 0 | K20: =Inputs!$F$49*IF(Time!K17=15,1,0) -> 0 | L20: =Inputs!$F$49*IF(Time!L17=15,1,0) -> 0 | M20: =Inputs!$F$49*IF(Time!M17=15,1,0) -> 0 | N20: =Inputs!$F$49*IF(Time!N17=15,1,0) -> 0 | O20: =Inputs!$F$49*IF(Time!O17=15,1,0) -> 0 | P20: =Inputs!$F$49*IF(Time!P17=15,1,0) -> 0 | Q20: =Inputs!$F$49*IF(Time!Q17=15,1,0) -> 0 | ... BN20: =Inputs!$F$49*IF(Time!BN17=15,1,0) -> 0
D21: Flag_Waiver deferral (2023H2) | E21: flag | J21: =Inputs!$F$48*IF(Time!J17=11,1,0) -> 0 | K21: =Inputs!$F$48*IF(Time!K17=11,1,0) -> 0 | L21: =Inputs!$F$48*IF(Time!L17=11,1,0) -> 0 | M21: =Inputs!$F$48*IF(Time!M17=11,1,0) -> 0 | N21: =Inputs!$F$48*IF(Time!N17=11,1,0) -> 0 | O21: =Inputs!$F$48*IF(Time!O17=11,1,0) -> 0 | P21: =Inputs!$F$48*IF(Time!P17=11,1,0) -> 0 | Q21: =Inputs!$F$48*IF(Time!Q17=11,1,0) -> 0 | ... BN21: =Inputs!$F$48*IF(Time!BN17=11,1,0) -> 0
D22: Flag_Deferred repayment (2024H1-2025H2) | E22: flag | J22: =Inputs!$F$48*IF(AND(Time!J17>=12,Time!J17<=15),1,0) -> 0 | K22: =Inputs!$F$48*IF(AND(Time!K17>=12,Time!K17<=15),1,0) -> 0 | L22: =Inputs!$F$48*IF(AND(Time!L17>=12,Time!L17<=15),1,0) -> 0 | M22: =Inputs!$F$48*IF(AND(Time!M17>=12,Time!M17<=15),1,0) -> 0 | N22: =Inputs!$F$48*IF(AND(Time!N17>=12,Time!N17<=15),1,0) -> 0 | O22: =Inputs!$F$48*IF(AND(Time!O17>=12,Time!O17<=15),1,0) -> 0 | P22: =Inputs!$F$48*IF(AND(Time!P17>=12,Time!P17<=15),1,0) -> 0 | Q22: =Inputs!$F$48*IF(AND(Time!Q17>=12,Time!Q17<=15),1,0) -> 0 | ... BN22: =Inputs!$F$48*IF(AND(Time!BN17>=12,Time!BN17<=15),1,0) -> 0
D23: Flag_LD prepayment (2022H1) | E23: flag | J23: =Inputs!$F$47*IF(Time!J17=8,1,0) -> 0 | K23: =Inputs!$F$47*IF(Time!K17=8,1,0) -> 0 | L23: =Inputs!$F$47*IF(Time!L17=8,1,0) -> 0 | M23: =Inputs!$F$47*IF(Time!M17=8,1,0) -> 0 | N23: =Inputs!$F$47*IF(Time!N17=8,1,0) -> 0 | O23: =Inputs!$F$47*IF(Time!O17=8,1,0) -> 0 | P23: =Inputs!$F$47*IF(Time!P17=8,1,0) -> 0 | Q23: =Inputs!$F$47*IF(Time!Q17=8,1,0) -> 0 | ... BN23: =Inputs!$F$47*IF(Time!BN17=8,1,0) -> 0
B24: ECA-covered tranche
D25: Opening balance | E25: USD m | J25: =Time!J30*0 -> 0 | K25: =Time!K30*J38 -> 0 | L25: =Time!L30*K38 -> 0 | M25: =Time!M30*L38 -> 0 | N25: =Time!N30*M38 -> 0 | O25: =Time!O30*N38 -> 0 | P25: =Time!P30*O38 -> 208.04885 | Q25: =Time!Q30*P38 -> 202.95988 | R25: =Time!R30*Q38 -> 197.65554 | ... BN25: =Time!BN30*BM38 -> 0
D26: Deferred principal, opening | E26: USD m | J26: =0 -> 0 | K26: =J35 -> 0 | L26: =K35 -> 0 | M26: =L35 -> 0 | N26: =M35 -> 0 | O26: =N35 -> 0 | P26: =O35 -> 0 | Q26: =P35 -> 0 | R26: =Q35 -> 0 | ... BN26: =BM35 -> 0
D27: Interest (incl. WHT gross-up where applicable) | E27: USD m | G27: =SUM(J27:BN27) -> 71.875052 | J27: =J25*J10 -> 0 | K27: =K25*K10 -> 0 | L27: =L25*L10 -> 0 | M27: =M25*M10 -> 0 | N27: =N25*N10 -> 0 | O27: =O25*O10 -> 0 | P27: =P25*P10 -> 4.7213218 | Q27: =Q25*Q10 -> 4.5511498 | ... BN27: =BN25*BN10 -> 0
D28: Scheduled principal per profile | E28: USD m | G28: =SUM(J28:BN28) -> 208.04885 | J28: =Time!J30*(J25-J26)*J19 -> 0 | K28: =Time!K30*(K25-K26)*K19 -> 0 | L28: =Time!L30*(L25-L26)*L19 -> 0 | M28: =Time!M30*(M25-M26)*M19 -> 0 | N28: =Time!N30*(N25-N26)*N19 -> 0 | O28: =Time!O30*(O25-O26)*O19 -> 0 | P28: =Time!P30*(P25-P26)*P19 -> 5.0889647 | Q28: =Time!Q30*(Q25-Q26)*Q19 -> 5.3043384 | ... BN28: =Time!BN30*(BN25-BN26)*BN19 -> 0
D29: Principal deferred under the waiver | E29: USD m | G29: =SUM(J29:BN29) -> 0 | J29: =J21*Inputs!$F$191*J28 -> 0 | K29: =K21*Inputs!$F$191*K28 -> 0 | L29: =L21*Inputs!$F$191*L28 -> 0 | M29: =M21*Inputs!$F$191*M28 -> 0 | N29: =N21*Inputs!$F$191*N28 -> 0 | O29: =O21*Inputs!$F$191*O28 -> 0 | P29: =P21*Inputs!$F$191*P28 -> 0 | Q29: =Q21*Inputs!$F$191*Q28 -> 0 | ... BN29: =BN21*Inputs!$F$191*BN28 -> 0
D30: Deferred amount at 2023-12-31 | E30: USD m | F30: =$T$29 -> 0
D31: Deferred principal repaid | E31: USD m | G31: =SUM(J31:BN31) -> 0 | J31: =0 -> 0 | K31: =0 -> 0 | L31: =0 -> 0 | M31: =0 -> 0 | N31: =0 -> 0 | O31: =0 -> 0 | P31: =0 -> 0 | Q31: =0 -> 0 | ... T31: =0 -> 0 | U31: =U22*MIN($F$30/4,U26) -> 0 | V31: =V22*MIN($F$30/4,V26) -> 0 | W31: =W22*MIN($F$30/4,W26) -> 0 | X31: =X22*MIN($F$30/4,X26) -> 0 | Y31: =0 -> 0 | Z31: =0 -> 0 | AA31: =0 -> 0 | AB31: =0 -> 0 | AC31: =0 -> 0 | AD31: =0 -> 0 | AE31: =0 -> 0 | AF31: =0 -> 0 | ... BN31: =0 -> 0
D32: Principal paid | E32: USD m | G32: =SUM(J32:BN32) -> 208.04885 | J32: =J28-J29+J31 -> 0 | K32: =K28-K29+K31 -> 0 | L32: =L28-L29+L31 -> 0 | M32: =M28-M29+M31 -> 0 | N32: =N28-N29+N31 -> 0 | O32: =O28-O29+O31 -> 0 | P32: =P28-P29+P31 -> 5.0889647 | Q32: =Q28-Q29+Q31 -> 5.3043384 | ... BN32: =BN28-BN29+BN31 -> 0
D33: Performance LD prepayment | E33: USD m | G33: =SUM(J33:BN33) -> 0 | J33: =J23*Inputs!$F$188*(J25-J32)/(J25-J32+J40-J47+J55-J62+J70-J77+J85-J92+0.000000001) -> 0 | K33: =K23*Inputs!$F$188*(K25-K32)/(K25-K32+K40-K47+K55-K62+K70-K77+K85-K92+0.000000001) -> 0 | L33: =L23*Inputs!$F$188*(L25-L32)/(L25-L32+L40-L47+L55-L62+L70-L77+L85-L92+0.000000001) -> 0 | M33: =M23*Inputs!$F$188*(M25-M32)/(M25-M32+M40-M47+M55-M62+M70-M77+M85-M92+0.000000001) -> 0 | N33: =N23*Inputs!$F$188*(N25-N32)/(N25-N32+N40-N47+N55-N62+N70-N77+N85-N92+0.000000001) -> 0 | O33: =O23*Inputs!$F$188*(O25-O32)/(O25-O32+O40-O47+O55-O62+O70-O77+O85-O92+0.000000001) -> 0 | P33: =P23*Inputs!$F$188*(P25-P32)/(P25-P32+P40-P47+P55-P62+P70-P77+P85-P92+0.000000001) -> 0 | Q33: =Q23*Inputs!$F$188*(Q25-Q32)/(Q25-Q32+Q40-Q47+Q55-Q62+Q70-Q77+Q85-Q92+0.000000001) -> 0 | ... BN33: =BN23*Inputs!$F$188*(BN25-BN32)/(BN25-BN32+BN40-BN47+BN55-BN62+BN70-BN77+BN85-BN92+0.000000001) -> 0
D34: Refinanced (prepaid from bond proceeds) | E34: USD m | G34: =SUM(J34:BN34) -> 0 | J34: =0 -> 0 | K34: =0 -> 0 | L34: =0 -> 0 | M34: =0 -> 0 | N34: =0 -> 0 | O34: =0 -> 0 | P34: =0 -> 0 | Q34: =0 -> 0 | ... BN34: =0 -> 0
D35: Deferred principal, closing | E35: USD m | J35: =J26+J29-J31 -> 0 | K35: =K26+K29-K31 -> 0 | L35: =L26+L29-L31 -> 0 | M35: =M26+M29-M31 -> 0 | N35: =N26+N29-N31 -> 0 | O35: =O26+O29-O31 -> 0 | P35: =P26+P29-P31 -> 0 | Q35: =Q26+Q29-Q31 -> 0 | ... BN35: =BN26+BN29-BN31 -> 0
D36: Balance after scheduled payment, LDs and refinancing | E36: USD m | J36: =J25-J32-J33-J34 -> 0 | K36: =K25-K32-K33-K34 -> 0 | L36: =L25-L32-L33-L34 -> 0 | M36: =M25-M32-M33-M34 -> 0 | N36: =N25-N32-N33-N34 -> 0 | O36: =O25-O32-O33-O34 -> 0 | P36: =P25-P32-P33-P34 -> 202.95988 | Q36: =Q25-Q32-Q33-Q34 -> 197.65554 | ... BN36: =BN25-BN32-BN33-BN34 -> 0
D37: Cash sweep prepayment | E37: USD m | G37: =SUM(J37:BN37) -> 0 | J37: =Waterfall!J28*J36/(J36+J51+J66+J81+J96+0.000000001) -> 0 | K37: =Waterfall!K28*K36/(K36+K51+K66+K81+K96+0.000000001) -> 0 | L37: =Waterfall!L28*L36/(L36+L51+L66+L81+L96+0.000000001) -> 0 | M37: =Waterfall!M28*M36/(M36+M51+M66+M81+M96+0.000000001) -> 0 | N37: =Waterfall!N28*N36/(N36+N51+N66+N81+N96+0.000000001) -> 0 | O37: =Waterfall!O28*O36/(O36+O51+O66+O81+O96+0.000000001) -> 0 | P37: =Waterfall!P28*P36/(P36+P51+P66+P81+P96+0.000000001) -> 0 | Q37: =Waterfall!Q28*Q36/(Q36+Q51+Q66+Q81+Q96+0.000000001) -> 0 | ... BN37: =Waterfall!BN28*BN36/(BN36+BN51+BN66+BN81+BN96+0.000000001) -> 0
D38: Closing balance | E38: USD m | J38: =IF(Time!J29=1,INDEX(Funding!$J$61:$BJ$61,1,Time!$F$13),Time!J30*(J36-J37)) -> 0 | K38: =IF(Time!K29=1,INDEX(Funding!$J$61:$BJ$61,1,Time!$F$13),Time!K30*(K36-K37)) -> 0 | L38: =IF(Time!L29=1,INDEX(Funding!$J$61:$BJ$61,1,Time!$F$13),Time!L30*(L36-L37)) -> 0 | M38: =IF(Time!M29=1,INDEX(Funding!$J$61:$BJ$61,1,Time!$F$13),Time!M30*(M36-M37)) -> 0 | N38: =IF(Time!N29=1,INDEX(Funding!$J$61:$BJ$61,1,Time!$F$13),Time!N30*(N36-N37)) -> 0 | O38: =IF(Time!O29=1,INDEX(Funding!$J$61:$BJ$61,1,Time!$F$13),Time!O30*(O36-O37)) -> 208.04885 | P38: =IF(Time!P29=1,INDEX(Funding!$J$61:$BJ$61,1,Time!$F$13),Time!P30*(P36-P37)) -> 202.95988 | Q38: =IF(Time!Q29=1,INDEX(Funding!$J$61:$BJ$61,1,Time!$F$13),Time!Q30*(Q36-Q37)) -> 197.65554 | ... BN38: =IF(Time!BN29=1,INDEX(Funding!$J$61:$BJ$61,1,Time!$F$13),Time!BN30*(BN36-BN37)) -> 0
B39: ABDB A-loan
D40: Opening balance | E40: USD m | J40: =Time!J30*0 -> 0 | K40: =Time!K30*J53 -> 0 | L40: =Time!L30*K53 -> 0 | M40: =Time!M30*L53 -> 0 | N40: =Time!N30*M53 -> 0 | O40: =Time!O30*N53 -> 0 | P40: =Time!P30*O53 -> 152.56915 | Q40: =Time!Q30*P53 -> 148.83725 | R40: =Time!R30*Q53 -> 144.9474 | ... BN40: =Time!BN30*BM53 -> 0
D41: Deferred principal, opening | E41: USD m | J41: =0 -> 0 | K41: =J50 -> 0 | L41: =K50 -> 0 | M41: =L50 -> 0 | N41: =M50 -> 0 | O41: =N50 -> 0 | P41: =O50 -> 0 | Q41: =P50 -> 0 | R41: =Q50 -> 0 | ... BN41: =BM50 -> 0
D42: Interest (incl. WHT gross-up where applicable) | E42: USD m | G42: =SUM(J42:BN42) -> 79.84871 | J42: =J40*J11 -> 0 | K42: =K40*K11 -> 0 | L42: =L40*L11 -> 0 | M42: =M40*M11 -> 0 | N42: =N40*N11 -> 0 | O42: =O40*O11 -> 0 | P42: =P40*P11 -> 5.2558378 | Q42: =Q40*Q11 -> 5.0586472 | ... BN42: =BN40*BN11 -> 0
D43: Scheduled principal per profile | E43: USD m | G43: =SUM(J43:BN43) -> 152.56915 | J43: =Time!J30*(J40-J41)*J19 -> 0 | K43: =Time!K30*(K40-K41)*K19 -> 0 | L43: =Time!L30*(L40-L41)*L19 -> 0 | M43: =Time!M30*(M40-M41)*M19 -> 0 | N43: =Time!N30*(N40-N41)*N19 -> 0 | O43: =Time!O30*(O40-O41)*O19 -> 0 | P43: =Time!P30*(P40-P41)*P19 -> 3.7319074 | Q43: =Time!Q30*(Q40-Q41)*Q19 -> 3.8898482 | ... BN43: =Time!BN30*(BN40-BN41)*BN19 -> 0
D44: Principal deferred under the waiver | E44: USD m | G44: =SUM(J44:BN44) -> 0 | J44: =J21*Inputs!$F$191*J43 -> 0 | K44: =K21*Inputs!$F$191*K43 -> 0 | L44: =L21*Inputs!$F$191*L43 -> 0 | M44: =M21*Inputs!$F$191*M43 -> 0 | N44: =N21*Inputs!$F$191*N43 -> 0 | O44: =O21*Inputs!$F$191*O43 -> 0 | P44: =P21*Inputs!$F$191*P43 -> 0 | Q44: =Q21*Inputs!$F$191*Q43 -> 0 | ... BN44: =BN21*Inputs!$F$191*BN43 -> 0
D45: Deferred amount at 2023-12-31 | E45: USD m | F45: =$T$44 -> 0
D46: Deferred principal repaid | E46: USD m | G46: =SUM(J46:BN46) -> 0 | J46: =0 -> 0 | K46: =0 -> 0 | L46: =0 -> 0 | M46: =0 -> 0 | N46: =0 -> 0 | O46: =0 -> 0 | P46: =0 -> 0 | Q46: =0 -> 0 | ... T46: =0 -> 0 | U46: =U22*MIN($F$45/4,U41) -> 0 | V46: =V22*MIN($F$45/4,V41) -> 0 | W46: =W22*MIN($F$45/4,W41) -> 0 | X46: =X22*MIN($F$45/4,X41) -> 0 | Y46: =0 -> 0 | Z46: =0 -> 0 | AA46: =0 -> 0 | AB46: =0 -> 0 | AC46: =0 -> 0 | AD46: =0 -> 0 | AE46: =0 -> 0 | AF46: =0 -> 0 | ... BN46: =0 -> 0
D47: Principal paid | E47: USD m | G47: =SUM(J47:BN47) -> 152.56915 | J47: =J43-J44+J46 -> 0 | K47: =K43-K44+K46 -> 0 | L47: =L43-L44+L46 -> 0 | M47: =M43-M44+M46 -> 0 | N47: =N43-N44+N46 -> 0 | O47: =O43-O44+O46 -> 0 | P47: =P43-P44+P46 -> 3.7319074 | Q47: =Q43-Q44+Q46 -> 3.8898482 | ... BN47: =BN43-BN44+BN46 -> 0
D48: Performance LD prepayment | E48: USD m | G48: =SUM(J48:BN48) -> 0 | J48: =J23*Inputs!$F$188*(J40-J47)/(J25-J32+J40-J47+J55-J62+J70-J77+J85-J92+0.000000001) -> 0 | K48: =K23*Inputs!$F$188*(K40-K47)/(K25-K32+K40-K47+K55-K62+K70-K77+K85-K92+0.000000001) -> 0 | L48: =L23*Inputs!$F$188*(L40-L47)/(L25-L32+L40-L47+L55-L62+L70-L77+L85-L92+0.000000001) -> 0 | M48: =M23*Inputs!$F$188*(M40-M47)/(M25-M32+M40-M47+M55-M62+M70-M77+M85-M92+0.000000001) -> 0 | N48: =N23*Inputs!$F$188*(N40-N47)/(N25-N32+N40-N47+N55-N62+N70-N77+N85-N92+0.000000001) -> 0 | O48: =O23*Inputs!$F$188*(O40-O47)/(O25-O32+O40-O47+O55-O62+O70-O77+O85-O92+0.000000001) -> 0 | P48: =P23*Inputs!$F$188*(P40-P47)/(P25-P32+P40-P47+P55-P62+P70-P77+P85-P92+0.000000001) -> 0 | Q48: =Q23*Inputs!$F$188*(Q40-Q47)/(Q25-Q32+Q40-Q47+Q55-Q62+Q70-Q77+Q85-Q92+0.000000001) -> 0 | ... BN48: =BN23*Inputs!$F$188*(BN40-BN47)/(BN25-BN32+BN40-BN47+BN55-BN62+BN70-BN77+BN85-BN92+0.000000001) -> 0
D49: Refinanced (prepaid from bond proceeds) | E49: USD m | G49: =SUM(J49:BN49) -> 0 | J49: =0 -> 0 | K49: =0 -> 0 | L49: =0 -> 0 | M49: =0 -> 0 | N49: =0 -> 0 | O49: =0 -> 0 | P49: =0 -> 0 | Q49: =0 -> 0 | ... BN49: =0 -> 0
D50: Deferred principal, closing | E50: USD m | J50: =J41+J44-J46 -> 0 | K50: =K41+K44-K46 -> 0 | L50: =L41+L44-L46 -> 0 | M50: =M41+M44-M46 -> 0 | N50: =N41+N44-N46 -> 0 | O50: =O41+O44-O46 -> 0 | P50: =P41+P44-P46 -> 0 | Q50: =Q41+Q44-Q46 -> 0 | ... BN50: =BN41+BN44-BN46 -> 0
D51: Balance after scheduled payment, LDs and refinancing | E51: USD m | J51: =J40-J47-J48-J49 -> 0 | K51: =K40-K47-K48-K49 -> 0 | L51: =L40-L47-L48-L49 -> 0 | M51: =M40-M47-M48-M49 -> 0 | N51: =N40-N47-N48-N49 -> 0 | O51: =O40-O47-O48-O49 -> 0 | P51: =P40-P47-P48-P49 -> 148.83725 | Q51: =Q40-Q47-Q48-Q49 -> 144.9474 | ... BN51: =BN40-BN47-BN48-BN49 -> 0
D52: Cash sweep prepayment | E52: USD m | G52: =SUM(J52:BN52) -> 0 | J52: =Waterfall!J28*J51/(J36+J51+J66+J81+J96+0.000000001) -> 0 | K52: =Waterfall!K28*K51/(K36+K51+K66+K81+K96+0.000000001) -> 0 | L52: =Waterfall!L28*L51/(L36+L51+L66+L81+L96+0.000000001) -> 0 | M52: =Waterfall!M28*M51/(M36+M51+M66+M81+M96+0.000000001) -> 0 | N52: =Waterfall!N28*N51/(N36+N51+N66+N81+N96+0.000000001) -> 0 | O52: =Waterfall!O28*O51/(O36+O51+O66+O81+O96+0.000000001) -> 0 | P52: =Waterfall!P28*P51/(P36+P51+P66+P81+P96+0.000000001) -> 0 | Q52: =Waterfall!Q28*Q51/(Q36+Q51+Q66+Q81+Q96+0.000000001) -> 0 | ... BN52: =Waterfall!BN28*BN51/(BN36+BN51+BN66+BN81+BN96+0.000000001) -> 0
D53: Closing balance | E53: USD m | J53: =IF(Time!J29=1,INDEX(Funding!$J$62:$BJ$62,1,Time!$F$13),Time!J30*(J51-J52)) -> 0 | K53: =IF(Time!K29=1,INDEX(Funding!$J$62:$BJ$62,1,Time!$F$13),Time!K30*(K51-K52)) -> 0 | L53: =IF(Time!L29=1,INDEX(Funding!$J$62:$BJ$62,1,Time!$F$13),Time!L30*(L51-L52)) -> 0 | M53: =IF(Time!M29=1,INDEX(Funding!$J$62:$BJ$62,1,Time!$F$13),Time!M30*(M51-M52)) -> 0 | N53: =IF(Time!N29=1,INDEX(Funding!$J$62:$BJ$62,1,Time!$F$13),Time!N30*(N51-N52)) -> 0 | O53: =IF(Time!O29=1,INDEX(Funding!$J$62:$BJ$62,1,Time!$F$13),Time!O30*(O51-O52)) -> 152.56915 | P53: =IF(Time!P29=1,INDEX(Funding!$J$62:$BJ$62,1,Time!$F$13),Time!P30*(P51-P52)) -> 148.83725 | Q53: =IF(Time!Q29=1,INDEX(Funding!$J$62:$BJ$62,1,Time!$F$13),Time!Q30*(Q51-Q52)) -> 144.9474 | ... BN53: =IF(Time!BN29=1,INDEX(Funding!$J$62:$BJ$62,1,Time!$F$13),Time!BN30*(BN51-BN52)) -> 0
B54: ABDB B-loan
D55: Opening balance | E55: USD m | J55: =Time!J30*0 -> 0 | K55: =Time!K30*J68 -> 0 | L55: =Time!L30*K68 -> 0 | M55: =Time!M30*L68 -> 0 | N55: =Time!N30*M68 -> 0 | O55: =Time!O30*N68 -> 0 | P55: =Time!P30*O68 -> 69.349615 | Q55: =Time!Q30*P68 -> 67.653293 | R55: =Time!R30*Q68 -> 65.885181 | ... BN55: =Time!BN30*BM68 -> 0
D56: Deferred principal, opening | E56: USD m | J56: =0 -> 0 | K56: =J65 -> 0 | L56: =K65 -> 0 | M56: =L65 -> 0 | N56: =M65 -> 0 | O56: =N65 -> 0 | P56: =O65 -> 0 | Q56: =P65 -> 0 | R56: =Q65 -> 0 | ... BN56: =BM65 -> 0
D57: Interest (incl. WHT gross-up where applicable) | E57: USD m | G57: =SUM(J57:BN57) -> 34.953942 | J57: =J55*J12 -> 0 | K57: =K55*K12 -> 0 | L57: =L55*L12 -> 0 | M57: =M55*M12 -> 0 | N57: =N55*N12 -> 0 | O57: =O55*O12 -> 0 | P57: =P55*P12 -> 2.3004038 | Q57: =Q55*Q12 -> 2.2143487 | ... BN57: =BN55*BN12 -> 0
D58: Scheduled principal per profile | E58: USD m | G58: =SUM(J58:BN58) -> 69.349615 | J58: =Time!J30*(J55-J56)*J19 -> 0 | K58: =Time!K30*(K55-K56)*K19 -> 0 | L58: =Time!L30*(L55-L56)*L19 -> 0 | M58: =Time!M30*(M55-M56)*M19 -> 0 | N58: =Time!N30*(N55-N56)*N19 -> 0 | O58: =Time!O30*(O55-O56)*O19 -> 0 | P58: =Time!P30*(P55-P56)*P19 -> 1.6963216 | Q58: =Time!Q30*(Q55-Q56)*Q19 -> 1.7681128 | ... BN58: =Time!BN30*(BN55-BN56)*BN19 -> 0
D59: Principal deferred under the waiver | E59: USD m | G59: =SUM(J59:BN59) -> 0 | J59: =J21*Inputs!$F$191*J58 -> 0 | K59: =K21*Inputs!$F$191*K58 -> 0 | L59: =L21*Inputs!$F$191*L58 -> 0 | M59: =M21*Inputs!$F$191*M58 -> 0 | N59: =N21*Inputs!$F$191*N58 -> 0 | O59: =O21*Inputs!$F$191*O58 -> 0 | P59: =P21*Inputs!$F$191*P58 -> 0 | Q59: =Q21*Inputs!$F$191*Q58 -> 0 | ... BN59: =BN21*Inputs!$F$191*BN58 -> 0
D60: Deferred amount at 2023-12-31 | E60: USD m | F60: =$T$59 -> 0
D61: Deferred principal repaid | E61: USD m | G61: =SUM(J61:BN61) -> 0 | J61: =0 -> 0 | K61: =0 -> 0 | L61: =0 -> 0 | M61: =0 -> 0 | N61: =0 -> 0 | O61: =0 -> 0 | P61: =0 -> 0 | Q61: =0 -> 0 | ... T61: =0 -> 0 | U61: =U22*MIN($F$60/4,U56) -> 0 | V61: =V22*MIN($F$60/4,V56) -> 0 | W61: =W22*MIN($F$60/4,W56) -> 0 | X61: =X22*MIN($F$60/4,X56) -> 0 | Y61: =0 -> 0 | Z61: =0 -> 0 | AA61: =0 -> 0 | AB61: =0 -> 0 | AC61: =0 -> 0 | AD61: =0 -> 0 | AE61: =0 -> 0 | AF61: =0 -> 0 | ... BN61: =0 -> 0
D62: Principal paid | E62: USD m | G62: =SUM(J62:BN62) -> 69.349615 | J62: =J58-J59+J61 -> 0 | K62: =K58-K59+K61 -> 0 | L62: =L58-L59+L61 -> 0 | M62: =M58-M59+M61 -> 0 | N62: =N58-N59+N61 -> 0 | O62: =O58-O59+O61 -> 0 | P62: =P58-P59+P61 -> 1.6963216 | Q62: =Q58-Q59+Q61 -> 1.7681128 | ... BN62: =BN58-BN59+BN61 -> 0
D63: Performance LD prepayment | E63: USD m | G63: =SUM(J63:BN63) -> 0 | J63: =J23*Inputs!$F$188*(J55-J62)/(J25-J32+J40-J47+J55-J62+J70-J77+J85-J92+0.000000001) -> 0 | K63: =K23*Inputs!$F$188*(K55-K62)/(K25-K32+K40-K47+K55-K62+K70-K77+K85-K92+0.000000001) -> 0 | L63: =L23*Inputs!$F$188*(L55-L62)/(L25-L32+L40-L47+L55-L62+L70-L77+L85-L92+0.000000001) -> 0 | M63: =M23*Inputs!$F$188*(M55-M62)/(M25-M32+M40-M47+M55-M62+M70-M77+M85-M92+0.000000001) -> 0 | N63: =N23*Inputs!$F$188*(N55-N62)/(N25-N32+N40-N47+N55-N62+N70-N77+N85-N92+0.000000001) -> 0 | O63: =O23*Inputs!$F$188*(O55-O62)/(O25-O32+O40-O47+O55-O62+O70-O77+O85-O92+0.000000001) -> 0 | P63: =P23*Inputs!$F$188*(P55-P62)/(P25-P32+P40-P47+P55-P62+P70-P77+P85-P92+0.000000001) -> 0 | Q63: =Q23*Inputs!$F$188*(Q55-Q62)/(Q25-Q32+Q40-Q47+Q55-Q62+Q70-Q77+Q85-Q92+0.000000001) -> 0 | ... BN63: =BN23*Inputs!$F$188*(BN55-BN62)/(BN25-BN32+BN40-BN47+BN55-BN62+BN70-BN77+BN85-BN92+0.000000001) -> 0
D64: Refinanced (prepaid from bond proceeds) | E64: USD m | G64: =SUM(J64:BN64) -> 0 | J64: =J20*(J55-J62-J63) -> 0 | K64: =K20*(K55-K62-K63) -> 0 | L64: =L20*(L55-L62-L63) -> 0 | M64: =M20*(M55-M62-M63) -> 0 | N64: =N20*(N55-N62-N63) -> 0 | O64: =O20*(O55-O62-O63) -> 0 | P64: =P20*(P55-P62-P63) -> 0 | Q64: =Q20*(Q55-Q62-Q63) -> 0 | ... BN64: =BN20*(BN55-BN62-BN63) -> 0
D65: Deferred principal, closing | E65: USD m | J65: =IF(J20=1,0,1)*(J56+J59-J61) -> 0 | K65: =IF(K20=1,0,1)*(K56+K59-K61) -> 0 | L65: =IF(L20=1,0,1)*(L56+L59-L61) -> 0 | M65: =IF(M20=1,0,1)*(M56+M59-M61) -> 0 | N65: =IF(N20=1,0,1)*(N56+N59-N61) -> 0 | O65: =IF(O20=1,0,1)*(O56+O59-O61) -> 0 | P65: =IF(P20=1,0,1)*(P56+P59-P61) -> 0 | Q65: =IF(Q20=1,0,1)*(Q56+Q59-Q61) -> 0 | ... BN65: =IF(BN20=1,0,1)*(BN56+BN59-BN61) -> 0
D66: Balance after scheduled payment, LDs and refinancing | E66: USD m | J66: =J55-J62-J63-J64 -> 0 | K66: =K55-K62-K63-K64 -> 0 | L66: =L55-L62-L63-L64 -> 0 | M66: =M55-M62-M63-M64 -> 0 | N66: =N55-N62-N63-N64 -> 0 | O66: =O55-O62-O63-O64 -> 0 | P66: =P55-P62-P63-P64 -> 67.653293 | Q66: =Q55-Q62-Q63-Q64 -> 65.885181 | ... BN66: =BN55-BN62-BN63-BN64 -> 0
D67: Cash sweep prepayment | E67: USD m | G67: =SUM(J67:BN67) -> 0 | J67: =Waterfall!J28*J66/(J36+J51+J66+J81+J96+0.000000001) -> 0 | K67: =Waterfall!K28*K66/(K36+K51+K66+K81+K96+0.000000001) -> 0 | L67: =Waterfall!L28*L66/(L36+L51+L66+L81+L96+0.000000001) -> 0 | M67: =Waterfall!M28*M66/(M36+M51+M66+M81+M96+0.000000001) -> 0 | N67: =Waterfall!N28*N66/(N36+N51+N66+N81+N96+0.000000001) -> 0 | O67: =Waterfall!O28*O66/(O36+O51+O66+O81+O96+0.000000001) -> 0 | P67: =Waterfall!P28*P66/(P36+P51+P66+P81+P96+0.000000001) -> 0 | Q67: =Waterfall!Q28*Q66/(Q36+Q51+Q66+Q81+Q96+0.000000001) -> 0 | ... BN67: =Waterfall!BN28*BN66/(BN36+BN51+BN66+BN81+BN96+0.000000001) -> 0
D68: Closing balance | E68: USD m | J68: =IF(Time!J29=1,INDEX(Funding!$J$63:$BJ$63,1,Time!$F$13),Time!J30*(J66-J67)) -> 0 | K68: =IF(Time!K29=1,INDEX(Funding!$J$63:$BJ$63,1,Time!$F$13),Time!K30*(K66-K67)) -> 0 | L68: =IF(Time!L29=1,INDEX(Funding!$J$63:$BJ$63,1,Time!$F$13),Time!L30*(L66-L67)) -> 0 | M68: =IF(Time!M29=1,INDEX(Funding!$J$63:$BJ$63,1,Time!$F$13),Time!M30*(M66-M67)) -> 0 | N68: =IF(Time!N29=1,INDEX(Funding!$J$63:$BJ$63,1,Time!$F$13),Time!N30*(N66-N67)) -> 0 | O68: =IF(Time!O29=1,INDEX(Funding!$J$63:$BJ$63,1,Time!$F$13),Time!O30*(O66-O67)) -> 69.349615 | P68: =IF(Time!P29=1,INDEX(Funding!$J$63:$BJ$63,1,Time!$F$13),Time!P30*(P66-P67)) -> 67.653293 | Q68: =IF(Time!Q29=1,INDEX(Funding!$J$63:$BJ$63,1,Time!$F$13),Time!Q30*(Q66-Q67)) -> 65.885181 | ... BN68: =IF(Time!BN29=1,INDEX(Funding!$J$63:$BJ$63,1,Time!$F$13),Time!BN30*(BN66-BN67)) -> 0
B69: Commercial tranche
D70: Opening balance | E70: USD m | J70: =Time!J30*0 -> 0 | K70: =Time!K30*J83 -> 0 | L70: =Time!L30*K83 -> 0 | M70: =Time!M30*L83 -> 0 | N70: =Time!N30*M83 -> 0 | O70: =Time!O30*N83 -> 0 | P70: =Time!P30*O83 -> 263.52854 | Q70: =Time!Q30*P83 -> 257.08252 | R70: =Time!R30*Q83 -> 250.36369 | ... BN70: =Time!BN30*BM83 -> 0
D71: Deferred principal, opening | E71: USD m | J71: =0 -> 0 | K71: =J80 -> 0 | L71: =K80 -> 0 | M71: =L80 -> 0 | N71: =M80 -> 0 | O71: =N80 -> 0 | P71: =O80 -> 0 | Q71: =P80 -> 0 | R71: =Q80 -> 0 | ... BN71: =BM80 -> 0
D72: Interest (incl. WHT gross-up where applicable) | E72: USD m | G72: =SUM(J72:BN72) -> 153.16262 | J72: =J70*J13 -> 0 | K72: =K70*K13 -> 0 | L72: =L70*L13 -> 0 | M72: =M70*M13 -> 0 | N72: =N70*N13 -> 0 | O72: =O70*O13 -> 0 | P72: =P70*P13 -> 10.760423 | Q72: =Q70*Q13 -> 10.354792 | ... BN72: =BN70*BN13 -> 0
D73: Scheduled principal per profile | E73: USD m | G73: =SUM(J73:BN73) -> 178.63635 | J73: =Time!J30*(J70-J71)*J19 -> 0 | K73: =Time!K30*(K70-K71)*K19 -> 0 | L73: =Time!L30*(L70-L71)*L19 -> 0 | M73: =Time!M30*(M70-M71)*M19 -> 0 | N73: =Time!N30*(N70-N71)*N19 -> 0 | O73: =Time!O30*(O70-O71)*O19 -> 0 | P73: =Time!P30*(P70-P71)*P19 -> 6.4460219 | Q73: =Time!Q30*(Q70-Q71)*Q19 -> 6.7188287 | ... BN73: =Time!BN30*(BN70-BN71)*BN19 -> 0
D74: Principal deferred under the waiver | E74: USD m | G74: =SUM(J74:BN74) -> 0 | J74: =J21*Inputs!$F$191*J73 -> 0 | K74: =K21*Inputs!$F$191*K73 -> 0 | L74: =L21*Inputs!$F$191*L73 -> 0 | M74: =M21*Inputs!$F$191*M73 -> 0 | N74: =N21*Inputs!$F$191*N73 -> 0 | O74: =O21*Inputs!$F$191*O73 -> 0 | P74: =P21*Inputs!$F$191*P73 -> 0 | Q74: =Q21*Inputs!$F$191*Q73 -> 0 | ... BN74: =BN21*Inputs!$F$191*BN73 -> 0
D75: Deferred amount at 2023-12-31 | E75: USD m | F75: =$T$74 -> 0
D76: Deferred principal repaid | E76: USD m | G76: =SUM(J76:BN76) -> 0 | J76: =0 -> 0 | K76: =0 -> 0 | L76: =0 -> 0 | M76: =0 -> 0 | N76: =0 -> 0 | O76: =0 -> 0 | P76: =0 -> 0 | Q76: =0 -> 0 | ... T76: =0 -> 0 | U76: =U22*MIN($F$75/4,U71) -> 0 | V76: =V22*MIN($F$75/4,V71) -> 0 | W76: =W22*MIN($F$75/4,W71) -> 0 | X76: =X22*MIN($F$75/4,X71) -> 0 | Y76: =0 -> 0 | Z76: =0 -> 0 | AA76: =0 -> 0 | AB76: =0 -> 0 | AC76: =0 -> 0 | AD76: =0 -> 0 | AE76: =0 -> 0 | AF76: =0 -> 0 | ... BN76: =0 -> 0
D77: Principal paid | E77: USD m | G77: =SUM(J77:BN77) -> 178.63635 | J77: =J73-J74+J76 -> 0 | K77: =K73-K74+K76 -> 0 | L77: =L73-L74+L76 -> 0 | M77: =M73-M74+M76 -> 0 | N77: =N73-N74+N76 -> 0 | O77: =O73-O74+O76 -> 0 | P77: =P73-P74+P76 -> 6.4460219 | Q77: =Q73-Q74+Q76 -> 6.7188287 | ... BN77: =BN73-BN74+BN76 -> 0
D78: Performance LD prepayment | E78: USD m | G78: =SUM(J78:BN78) -> 0 | J78: =J23*Inputs!$F$188*(J70-J77)/(J25-J32+J40-J47+J55-J62+J70-J77+J85-J92+0.000000001) -> 0 | K78: =K23*Inputs!$F$188*(K70-K77)/(K25-K32+K40-K47+K55-K62+K70-K77+K85-K92+0.000000001) -> 0 | L78: =L23*Inputs!$F$188*(L70-L77)/(L25-L32+L40-L47+L55-L62+L70-L77+L85-L92+0.000000001) -> 0 | M78: =M23*Inputs!$F$188*(M70-M77)/(M25-M32+M40-M47+M55-M62+M70-M77+M85-M92+0.000000001) -> 0 | N78: =N23*Inputs!$F$188*(N70-N77)/(N25-N32+N40-N47+N55-N62+N70-N77+N85-N92+0.000000001) -> 0 | O78: =O23*Inputs!$F$188*(O70-O77)/(O25-O32+O40-O47+O55-O62+O70-O77+O85-O92+0.000000001) -> 0 | P78: =P23*Inputs!$F$188*(P70-P77)/(P25-P32+P40-P47+P55-P62+P70-P77+P85-P92+0.000000001) -> 0 | Q78: =Q23*Inputs!$F$188*(Q70-Q77)/(Q25-Q32+Q40-Q47+Q55-Q62+Q70-Q77+Q85-Q92+0.000000001) -> 0 | ... BN78: =BN23*Inputs!$F$188*(BN70-BN77)/(BN25-BN32+BN40-BN47+BN55-BN62+BN70-BN77+BN85-BN92+0.000000001) -> 0
D79: Refinanced (prepaid from bond proceeds) | E79: USD m | G79: =SUM(J79:BN79) -> 0 | J79: =J20*(J70-J77-J78) -> 0 | K79: =K20*(K70-K77-K78) -> 0 | L79: =L20*(L70-L77-L78) -> 0 | M79: =M20*(M70-M77-M78) -> 0 | N79: =N20*(N70-N77-N78) -> 0 | O79: =O20*(O70-O77-O78) -> 0 | P79: =P20*(P70-P77-P78) -> 0 | Q79: =Q20*(Q70-Q77-Q78) -> 0 | ... BN79: =BN20*(BN70-BN77-BN78) -> 0
D80: Deferred principal, closing | E80: USD m | J80: =IF(J20=1,0,1)*(J71+J74-J76) -> 0 | K80: =IF(K20=1,0,1)*(K71+K74-K76) -> 0 | L80: =IF(L20=1,0,1)*(L71+L74-L76) -> 0 | M80: =IF(M20=1,0,1)*(M71+M74-M76) -> 0 | N80: =IF(N20=1,0,1)*(N71+N74-N76) -> 0 | O80: =IF(O20=1,0,1)*(O71+O74-O76) -> 0 | P80: =IF(P20=1,0,1)*(P71+P74-P76) -> 0 | Q80: =IF(Q20=1,0,1)*(Q71+Q74-Q76) -> 0 | ... BN80: =IF(BN20=1,0,1)*(BN71+BN74-BN76) -> 0
D81: Balance after scheduled payment, LDs and refinancing | E81: USD m | J81: =J70-J77-J78-J79 -> 0 | K81: =K70-K77-K78-K79 -> 0 | L81: =L70-L77-L78-L79 -> 0 | M81: =M70-M77-M78-M79 -> 0 | N81: =N70-N77-N78-N79 -> 0 | O81: =O70-O77-O78-O79 -> 0 | P81: =P70-P77-P78-P79 -> 257.08252 | Q81: =Q70-Q77-Q78-Q79 -> 250.36369 | ... BN81: =BN70-BN77-BN78-BN79 -> 0
D82: Cash sweep prepayment | E82: USD m | G82: =SUM(J82:BN82) -> 84.892187 | J82: =Waterfall!J28*J81/(J36+J51+J66+J81+J96+0.000000001)+Waterfall!J29 -> 0 | K82: =Waterfall!K28*K81/(K36+K51+K66+K81+K96+0.000000001)+Waterfall!K29 -> 0 | L82: =Waterfall!L28*L81/(L36+L51+L66+L81+L96+0.000000001)+Waterfall!L29 -> 0 | M82: =Waterfall!M28*M81/(M36+M51+M66+M81+M96+0.000000001)+Waterfall!M29 -> 0 | N82: =Waterfall!N28*N81/(N36+N51+N66+N81+N96+0.000000001)+Waterfall!N29 -> 0 | O82: =Waterfall!O28*O81/(O36+O51+O66+O81+O96+0.000000001)+Waterfall!O29 -> 0 | P82: =Waterfall!P28*P81/(P36+P51+P66+P81+P96+0.000000001)+Waterfall!P29 -> 0 | Q82: =Waterfall!Q28*Q81/(Q36+Q51+Q66+Q81+Q96+0.000000001)+Waterfall!Q29 -> 0 | ... BN82: =Waterfall!BN28*BN81/(BN36+BN51+BN66+BN81+BN96+0.000000001)+Waterfall!BN29 -> 0
D83: Closing balance | E83: USD m | J83: =IF(Time!J29=1,INDEX(Funding!$J$64:$BJ$64,1,Time!$F$13),Time!J30*(J81-J82)) -> 0 | K83: =IF(Time!K29=1,INDEX(Funding!$J$64:$BJ$64,1,Time!$F$13),Time!K30*(K81-K82)) -> 0 | L83: =IF(Time!L29=1,INDEX(Funding!$J$64:$BJ$64,1,Time!$F$13),Time!L30*(L81-L82)) -> 0 | M83: =IF(Time!M29=1,INDEX(Funding!$J$64:$BJ$64,1,Time!$F$13),Time!M30*(M81-M82)) -> 0 | N83: =IF(Time!N29=1,INDEX(Funding!$J$64:$BJ$64,1,Time!$F$13),Time!N30*(N81-N82)) -> 0 | O83: =IF(Time!O29=1,INDEX(Funding!$J$64:$BJ$64,1,Time!$F$13),Time!O30*(O81-O82)) -> 263.52854 | P83: =IF(Time!P29=1,INDEX(Funding!$J$64:$BJ$64,1,Time!$F$13),Time!P30*(P81-P82)) -> 257.08252 | Q83: =IF(Time!Q29=1,INDEX(Funding!$J$64:$BJ$64,1,Time!$F$13),Time!Q30*(Q81-Q82)) -> 250.36369 | ... BN83: =IF(Time!BN29=1,INDEX(Funding!$J$64:$BJ$64,1,Time!$F$13),Time!BN30*(BN81-BN82)) -> 0
B84: Standby facility
