Workbook
Name Scenario: Inputs!$F$8

Sheet Cover
A1: Case P: Belanou Combined Cycle Power Project, Republic of Kessara
A2: Case P companion model
A3: Units in column E; constants in column F; row totals in column G; first period in column J. Inputs: blue on yellow. Links from other sheets: green.
D4: Label | E4: Unit | F4: Constant | G4: Total
D5: Companion model for Chapters 39-45. Python mirror: model/case_p.py (source of truth).
D6: Select the scenario on the Inputs sheet (cell named Scenario):
D7: 1: FC base
D8: 2: FC banking
D9: 3: FC downside
D10: 4: Sens: availability -3 points
D11: 5: Sens: heat rate +2%
D12: 6: Sens: fixed opex +10%
D13: 7: Sens: capex +10% funded pro rata
D14: 8: Sens: COD delay 6 months, no LDs
D15: 9: Sens: base rate +200 bps (unhedged)
D16: 10: Sens: KCR devaluation 40%, 90-day lag
... D21: 15: Actual history
D22: Master check (0 = all pass) | F22: =Checks!$F$19
D23: Circularity: none. IDC/fee/premium/DSRA gross-up is solved in closed form on the Funding sheet
D24: (balance = alpha + beta x T; T = alpha/(g - beta)). Sculpting with tax uses the contractual
D25: repayment profile on Inputs; the Debt sheet recomputes the sculpted profile live and the
D26: Checks sheet reports the difference (Python iterates the profile to convergence, tolerance USD 1,000).
D27: Sheets: Cover, Inputs, Time, Construction, Operations, Tax, Funding, Debt, Reserves, Waterfall, Financials, Ratios, Returns, Checks, Outputs
D28: Sign convention: costs stored positive and subtracted explicitly.
D31: Build-along file Ch40_funding.xlsx: the companion model at the end of Chapter 40 (u09 Section 0.4 rows of Chapters 39 to 40; model version 1.4).
D32: Provisional rows: Construction row 38 (VAT facility interest), replaced by its formula in Chapter 41. They hold FC base (Scenario 1) values pasted in input color.
D33: Reconciles on Scenario 1 only (the provisional rows hold Scenario 1 values); other scenarios reconcile from Ch42_waterfall.xlsx.
D34: Next file: Ch41_operations.xlsx.
D35: Verification: model/build/verification.md.

Sheet Inputs
A1: Case P: Belanou Combined Cycle Power Project, Republic of Kessara
A2: Inputs: scenario selector, assumptions, contract terms
A3: Units in column E; constants in column F; row totals in column G; first period in column J. Inputs: blue on yellow. Links from other sheets: green.
D4: Label | E4: Unit | F4: Constant | G4: Total
D5: Scenario table: columns J-X = scenarios 1-15; semiannual rows: columns = periods; annual rows: columns = years 2015+ | J5: 2018H2 | K5: 2019H1 | L5: 2019H2 | M5: 2020H1 | N5: 2020H2 | O5: 2021H1 | P5: 2021H2 | Q5: 2022H1 | R5: 2022H2 | S5: 2023H1 | T5: 2023H2 | U5: 2024H1 | V5: 2024H2 | W5: 2025H1 | X5: 2025H2 | Y5: 2026H1 | Z5: 2026H2 | AA5: 2027H1 | AB5: 2027H2 | AC5: 2028H1 | AD5: 2028H2 | AE5: 2029H1 | AF5: 2029H2 | AG5: 2030H1 | AH5: 2030H2 | AI5: 2031H1 | AJ5: 2031H2 | AK5: 2032H1 | AL5: 2032H2 | AM5: 2033H1 | AN5: 2033H2 | AO5: 2034H1 | AP5: 2034H2 | AQ5: 2035H1 | AR5: 2035H2 | AS5: 2036H1 | AT5: 2036H2 | AU5: 2037H1 | AV5: 2037H2 | AW5: 2038H1 | AX5: 2038H2 | AY5: 2039H1 | AZ5: 2039H2 | BA5: 2040H1 | BB5: 2040H2 | BC5: 2041H1 | BD5: 2041H2 | BE5: 2042H1 | BF5: 2042H2 | BG5: 2043H1 | BH5: 2043H2 | BI5: 2044H1 | BJ5: 2044H2 | BK5: 2045H1 | BL5: 2045H2 | BM5: 2046H1 | BN5: 2046H2
B7: Scenario control
D8: Scenario selector (1-15, see table below) | E8: index | F8: 1
B9: Live scenario parameters (selected from the scenario table)
D10: Macro path (1 FC forward, 2 actual history, 3 COD re-forecast) [table] | E10: code | J10: 1 | K10: 1 | L10: 1 | M10: 1 | N10: 1 | O10: 1 | P10: 1 | Q10: 1 | R10: 1 | S10: 1 | T10: 1 | U10: 1 | V10: 1 | W10: 3 | X10: 2
D11: Construction case (1 FC budget, 2 actual) [table] | E11: code | J11: 1 | K11: 1 | L11: 1 | M11: 1 | N11: 1 | O11: 1 | P11: 1 | Q11: 1 | R11: 1 | S11: 1 | T11: 1 | U11: 1 | V11: 1 | W11: 2 | X11: 2
D12: COD delay (sensitivity) [table] | E12: months | J12: 0 | K12: 0 | L12: 0 | M12: 0 | N12: 0 | O12: 0 | P12: 0 | Q12: 6 | R12: 0 | S12: 0 | T12: 0 | U12: 0 | V12: 0 | W12: 0 | X12: 0
D13: Capex factor [table] | E13: factor | J13: 1 | K13: 1 | L13: 1 | M13: 1 | N13: 1 | O13: 1 | P13: 1.1 | Q13: 1 | R13: 1 | S13: 1 | T13: 1 | U13: 1 | V13: 1 | W13: 1 | X13: 1
D14: Availability adjustment [table] | E14: points | J14: 0 | K14: 0 | L14: -6.5 | M14: -3 | N14: 0 | O14: 0 | P14: 0 | Q14: 0 | R14: 0 | S14: 0 | T14: 0 | U14: 0 | V14: 0 | W14: 0 | X14: 0
D15: Dispatch factor when available [table] | E15: % | J15: 76.5 | K15: 72 | L15: 76.5 | M15: 76.5 | N15: 76.5 | O15: 76.5 | P15: 76.5 | Q15: 76.5 | R15: 76.5 | S15: 76.5 | T15: 76.5 | U15: 50 | V15: 76.5 | W15: 76.5 | X15: 76.5
D16: Plant heat rate factor [table] | E16: factor | J16: 1 | K16: 1 | L16: 1.015 | M16: 1 | N16: 1.02 | O16: 1 | P16: 1 | Q16: 1 | R16: 1 | S16: 1 | T16: 1 | U16: 1 | V16: 1 | W16: 1 | X16: 1
D17: Fixed opex factor [table] | E17: factor | J17: 1 | K17: 1 | L17: 1.1 | M17: 1 | N17: 1 | O17: 1.1 | P17: 1 | Q17: 1 | R17: 1 | S17: 1 | T17: 1 | U17: 1 | V17: 1 | W17: 1 | X17: 1
D18: Gas price factor [table] | E18: factor | J18: 1 | K18: 1 | L18: 1 | M18: 1 | N18: 1 | O18: 1 | P18: 1 | Q18: 1 | R18: 1 | S18: 1 | T18: 1 | U18: 1 | V18: 1.3 | W18: 1 | X18: 1
D19: Base rate shift from 2022H1 [table] | E19: % | J19: 0 | K19: 0 | L19: 0 | M19: 0 | N19: 0 | O19: 0 | P19: 0 | Q19: 0 | R19: 2 | S19: 0 | T19: 0 | U19: 0 | V19: 0 | W19: 0 | X19: 0
D20: KCR devaluation from 2022H1 [table] | E20: fraction | J20: 0 | K20: 0 | L20: 0 | M20: 0 | N20: 0 | O20: 0 | P20: 0 | Q20: 0 | R20: 0 | S20: 0.4 | T20: 0 | U20: 0 | V20: 0 | W20: 0 | X20: 0
D21: Extra days on SEKA capacity/VOM payments, 2022H1-2022H2 [table] | E21: days | J21: 0 | K21: 0 | L21: 0 | M21: 0 | N21: 0 | O21: 0 | P21: 0 | Q21: 0 | R21: 0 | S21: 90 | T21: 120 | U21: 0 | V21: 0 | W21: 0 | X21: 0
... D32: Actual 2022 dispatch path (1 = on) [table] | E32: flag | J32: 0 | K32: 0 | L32: 0 | M32: 0 | N32: 0 | O32: 0 | P32: 0 | Q32: 0 | R32: 0 | S32: 0 | T32: 0 | U32: 0 | V32: 0 | W32: 0 | X32: 1
D33: Macro path (1 FC forward, 2 actual history, 3 COD re-forecast) | E33: code | F33: =INDEX($J$10:$X$10,1,Scenario)
D34: Construction case (1 FC budget, 2 actual) | E34: code | F34: =INDEX($J$11:$X$11,1,Scenario)
D35: COD delay (sensitivity) | E35: months | F35: =INDEX($J$12:$X$12,1,Scenario)
D36: Capex factor | E36: factor | F36: =INDEX($J$13:$X$13,1,Scenario)
D37: Availability adjustment | E37: points | F37: =INDEX($J$14:$X$14,1,Scenario)
D38: Dispatch factor when available | E38: % | F38: =INDEX($J$15:$X$15,1,Scenario)
D39: Plant heat rate factor | E39: factor | F39: =INDEX($J$16:$X$16,1,Scenario)
D40: Fixed opex factor | E40: factor | F40: =INDEX($J$17:$X$17,1,Scenario)
D41: Gas price factor | E41: factor | F41: =INDEX($J$18:$X$18,1,Scenario)
D42: Base rate shift from 2022H1 | E42: % | F42: =INDEX($J$19:$X$19,1,Scenario)
D43: KCR devaluation from 2022H1 | E43: fraction | F43: =INDEX($J$20:$X$20,1,Scenario)
D44: Extra days on SEKA capacity/VOM payments, 2022H1-2022H2 | E44: days | F44: =INDEX($J$21:$X$21,1,Scenario)
D45: Offtaker crisis events (1 = on) | E45: flag | F45: =INDEX($J$22:$X$22,1,Scenario)
D46: Insurance market step-up from 2022H2 (1 = on) | E46: flag | F46: =INDEX($J$23:$X$23,1,Scenario)
D47: Repayment profile (1 FC contract, 2 COD re-sculpted) | E47: code | F47: =INDEX($J$24:$X$24,1,Scenario)
D48: Performance LD prepayment June 2022 (1 = on) | E48: flag | F48: =INDEX($J$25:$X$25,1,Scenario)
D49: Waiver and amendment 2023 (1 = on) | E49: flag | F49: =INDEX($J$26:$X$26,1,Scenario)
D50: 2025 bond refinancing (1 = on) | E50: flag | F50: =INDEX($J$27:$X$27,1,Scenario)
D51: Funding mode (1 committed amounts, 2 re-grossed pro rata) | E51: code | F51: =INDEX($J$28:$X$28,1,Scenario)
D52: Soft mini-perm sweep (1 = on) | E52: flag | F52: =INDEX($J$29:$X$29,1,Scenario)
D53: Shareholder loan share of equity | E53: fraction | F53: =INDEX($J$30:$X$30,1,Scenario)
D54: Capital charge factor | E54: factor | F54: =INDEX($J$31:$X$31,1,Scenario)
D55: Actual 2022 dispatch path (1 = on) | E55: flag | F55: =INDEX($J$32:$X$32,1,Scenario)
B56: Capital cost (USD m unless stated)
D57: EPC contract price | E57: USD m | F57: 571.84
D58: of which offshore portion | E58: USD m | F58: 489.17
D59: of which onshore portion | E59: USD m | F59: 82.67
D60: Onshore portion fixed in KCR at | E60: KCR/USD | F60: 519.4
D61: Owner's costs | E61: USD m | F61: 46.18
D62: Insurance during construction | E62: USD m | F62: 7.62
D63: Development costs reimbursed at FC | E63: USD m | F63: 21.43
D64: Development fee at FC | E64: USD m | F64: 11.2
D65: Lenders' advisors and legal | E65: USD m | F65: 8.97
D66: Contingency | E66: USD m | F66: 38.4
D67: Initial working capital (spares, fuel) | E67: USD m | F67: 5.35
D68: LNTP paid February 2018 (equity credit at FC) | E68: USD m | F68: 14.2
... D73: Policy rate, FC expectation | E73: % | F73: 13.5
B74: Senior debt terms
D75: ECA-covered tranche share | E75: fraction | F75: 0.3
D76: ABDB A-loan share | E76: fraction | F76: 0.22
D77: ABDB B-loan share | E77: fraction | F77: 0.1
D78: Commercial tranche share | E78: fraction | F78: 0.38
D79: ECA margin | E79: % | F79: 1.35
D80: A-loan margin | E80: % | F80: 3.65
D81: B-loan margin | E81: % | F81: 3.4
D82: Commercial margin to 2025 | E82: % | F82: 4.1
D83: Commercial margin 2026-2029 | E83: % | F83: 4.6
D84: Commercial margin from 2030 | E84: % | F84: 5.1
D85: ECA commitment fee | E85: % pa | F85: 0.45
D86: A-loan commitment fee | E86: % pa | F86: 0.75
... D107: Agency and account fees | E107: USD m pa | F107: 0.255
B112: Contract terms fixed at financial close (from the FC base sizing run)
D113: Senior debt commitment (total, 4 tranches) | E113: USD m | F113: 633.25598
D114: Equity commitment (base, incl. LNTP) | E114: USD m | F114: 221.83377
B185: Timing and event dates (all dates are inputs; flags on the Time sheet read them)
D186: LNTP payment date | E186: date | F186: 43136
D187: Financial close | E187: date | F187: 43298
D188: Notice to proceed (Month 1 start) | E188: date | F188: 43313
D189: First semiannual period start | E189: date | F189: 43282
D190: COD, FC base | E190: date | F190: 44317
D191: COD, actual | E191: date | F191: 44531
D192: Final maturity, bank debt | E192: date | F192: 49125
D193: Start of devaluation, payment-delay and base-rate sensitivities | E193: date | F193: 44562
D194: COD re-forecast: first projected period | E194: date | F194: 44562
D195: Insurance step-up from | E195: date | F195: 44743
D196: Loans switch to Term SOFR + CAS | E196: date | F196: 44927
D197: Arrears settlement agreement | E197: date | F197: 45372
... D208: Commercial margin step 2 from | E208: date | F208: 47484
B209: Structural constants (FAST: no numbers inside calculation formulas)
D210: PPA term | E210: years | F210: 25
D211: Length of the shock sensitivities | E211: months | F211: 12
D212: Mid-period offset for FC FX drift | E212: periods | F212: 0.5
D213: FC Kessara CPI expectation | E213: % | F213: 7.5
D214: FC US CPI expectation | E214: % | F214: 2.2
D226: Months per operating period | E226: months | F226: 6
D237: FC EPC payment months | E237: months | F237: 33
D238: Taking-over payment | E238: % of EPC price | F238: 7.5
D239: Owner's cost rate per extra month (FC delay sensitivity) | E239: % | F239: 2.75
D240: Actual extension window: first month | E240: month | F240: 34
...

Sheet Time
A1: Case P: Belanou Combined Cycle Power Project, Republic of Kessara
A2: Time: semiannual operating timeline (monthly timeline on the Construction sheet)
A3: Units in column E; constants in column F; row totals in column G; first period in column J. Inputs: blue on yellow. Links from other sheets: green.
D4: Label | E4: Unit | F4: Constant | G4: Total
D5: Period ending | J5: 2018H2 | K5: 2019H1 | L5: 2019H2 | M5: 2020H1 | N5: 2020H2 | O5: 2021H1 | P5: 2021H2 | Q5: 2022H1 | R5: 2022H2 | S5: 2023H1 | T5: 2023H2 | U5: 2024H1 | V5: 2024H2 | W5: 2025H1 | X5: 2025H2 | Y5: 2026H1 | Z5: 2026H2 | AA5: 2027H1 | AB5: 2027H2 | AC5: 2028H1 | AD5: 2028H2 | AE5: 2029H1 | AF5: 2029H2 | AG5: 2030H1 | AH5: 2030H2 | AI5: 2031H1 | AJ5: 2031H2 | AK5: 2032H1 | AL5: 2032H2 | AM5: 2033H1 | AN5: 2033H2 | AO5: 2034H1 | AP5: 2034H2 | AQ5: 2035H1 | AR5: 2035H2 | AS5: 2036H1 | AT5: 2036H2 | AU5: 2037H1 | AV5: 2037H2 | AW5: 2038H1 | AX5: 2038H2 | AY5: 2039H1 | AZ5: 2039H2 | BA5: 2040H1 | BB5: 2040H2 | BC5: 2041H1 | BD5: 2041H2 | BE5: 2042H1 | BF5: 2042H2 | BG5: 2043H1 | BH5: 2043H2 | BI5: 2044H1 | BJ5: 2044H2 | BK5: 2045H1 | BL5: 2045H2 | BM5: 2046H1 | BN5: 2046H2
B7: Key dates (scenario-dependent)
D8: Commercial operation date | E8: date | F8: =IF(Inputs!$F$34<>1,Inputs!$F$191,EDATE(Inputs!$F$190,Inputs!$F$35))
D9: PPA term | E9: months | F9: =Inputs!$F$210*12
D10: PPA expiry | E10: date | F10: =EDATE(Time!$F$8,Time!$F$9)-1
D11: Construction months (NTP to COD) | E11: months | F11: =(YEAR(Time!$F$8)-YEAR(Inputs!$F$188))*12+MONTH(Time!$F$8)-MONTH(Inputs!$F$188)
D12: Period containing COD (period number) | E12: index | F12: =MATCH($F$8,$J$22:$BN$22,1)
D13: First debt service period | E13: index | F13: =Time!$F$12+1
D14: Last month of the funding period (month number) | E14: index | F14: =MATCH(INDEX($J$23:$BN$23,1,$F$12),Construction!$J$10:$BJ$10,0)
D15: Last operating period (period number) | E15: index | F15: =SUMPRODUCT($J$37:$BN$37,$J$20:$BN$20)
D16: FC FX drift per year (Kessara / US CPI expectations) | E16: factor | F16: =(1+Inputs!$F$213/100)/(1+Inputs!$F$214/100)
D17: Refinancing period (period number) | E17: index | F17: =MATCH(Inputs!$F$205,$J$23:$BN$23,0)
D18: Deferral period (period number) | E18: index | F18: =MATCH(Inputs!$F$200,$J$23:$BN$23,0)
B19: Semiannual timeline
D20: Period number | E20: index | J20: =I20+1 | K20: =J20+1 | L20: =K20+1 | M20: =L20+1 | N20: =M20+1 | O20: =N20+1 | P20: =O20+1 | Q20: =P20+1 | ... BN20: =BM20+1
D21: Months per period | E21: months | J21: =Inputs!$F$226 | K21: =Inputs!$F$226 | L21: =Inputs!$F$226 | M21: =Inputs!$F$226 | N21: =Inputs!$F$226 | O21: =Inputs!$F$226 | P21: =Inputs!$F$226 | Q21: =Inputs!$F$226 | ... BN21: =Inputs!$F$226
D22: Period start | E22: date | J22: =IF(J20=1,Inputs!$F$189,EDATE(I22,J21)) | K22: =IF(K20=1,Inputs!$F$189,EDATE(J22,K21)) | L22: =IF(L20=1,Inputs!$F$189,EDATE(K22,L21)) | M22: =IF(M20=1,Inputs!$F$189,EDATE(L22,M21)) | N22: =IF(N20=1,Inputs!$F$189,EDATE(M22,N21)) | O22: =IF(O20=1,Inputs!$F$189,EDATE(N22,O21)) | P22: =IF(P20=1,Inputs!$F$189,EDATE(O22,P21)) | Q22: =IF(Q20=1,Inputs!$F$189,EDATE(P22,Q21)) | ... BN22: =IF(BN20=1,Inputs!$F$189,EDATE(BM22,BN21))
D23: Period end | E23: date | J23: =EOMONTH(J22,J21-1) | K23: =EOMONTH(K22,K21-1) | L23: =EOMONTH(L22,L21-1) | M23: =EOMONTH(M22,M21-1) | N23: =EOMONTH(N22,N21-1) | O23: =EOMONTH(O22,O21-1) | P23: =EOMONTH(P22,P21-1) | Q23: =EOMONTH(Q22,Q21-1) | ... BN23: =EOMONTH(BN22,BN21-1)
D24: Year fraction 30/360 (months / 12) | E24: factor | J24: =J21/12 | K24: =K21/12 | L24: =L21/12 | M24: =M21/12 | N24: =N21/12 | O24: =O21/12 | P24: =P21/12 | Q24: =Q21/12 | ... BN24: =BN21/12
D25: Days in period | E25: days | J25: =J23-J22+1 | K25: =K23-K22+1 | L25: =L23-L22+1 | M25: =M23-M22+1 | N25: =N23-N22+1 | O25: =O23-O22+1 | P25: =P23-P22+1 | Q25: =Q23-Q22+1 | ... BN25: =BN23-BN22+1
D26: Calendar year | E26: year | J26: =YEAR(J22) | K26: =YEAR(K22) | L26: =YEAR(L22) | M26: =YEAR(M22) | N26: =YEAR(N22) | O26: =YEAR(O22) | P26: =YEAR(P22) | Q26: =YEAR(Q22) | ... BN26: =YEAR(BN22)
D27: Flag_FirstHalf (Jan-Jun) | E27: flag | J27: =IF(MONTH(J22)=1,1,0) | K27: =IF(MONTH(K22)=1,1,0) | L27: =IF(MONTH(L22)=1,1,0) | M27: =IF(MONTH(M22)=1,1,0) | N27: =IF(MONTH(N22)=1,1,0) | O27: =IF(MONTH(O22)=1,1,0) | P27: =IF(MONTH(P22)=1,1,0) | Q27: =IF(MONTH(Q22)=1,1,0) | ... BN27: =IF(MONTH(BN22)=1,1,0)
D28: Operations start in period | E28: date | J28: =MAX(J22,$F$8) | K28: =MAX(K22,$F$8) | L28: =MAX(L22,$F$8) | M28: =MAX(M22,$F$8) | N28: =MAX(N22,$F$8) | O28: =MAX(O22,$F$8) | P28: =MAX(P22,$F$8) | Q28: =MAX(Q22,$F$8) | ... BN28: =MAX(BN22,$F$8)
D29: Operations end in period | E29: date | J29: =MIN(J23,$F$10) | K29: =MIN(K23,$F$10) | L29: =MIN(L23,$F$10) | M29: =MIN(M23,$F$10) | N29: =MIN(N23,$F$10) | O29: =MIN(O23,$F$10) | P29: =MIN(P23,$F$10) | Q29: =MIN(Q23,$F$10) | ... BN29: =MIN(BN23,$F$10)
D30: Operating months in period | E30: months | J30: =IF(J29>=J28,(YEAR(J29)-YEAR(J28))*12+MONTH(J29)-MONTH(J28)+1,0) | K30: =IF(K29>=K28,(YEAR(K29)-YEAR(K28))*12+MONTH(K29)-MONTH(K28)+1,0) | L30: =IF(L29>=L28,(YEAR(L29)-YEAR(L28))*12+MONTH(L29)-MONTH(L28)+1,0) | M30: =IF(M29>=M28,(YEAR(M29)-YEAR(M28))*12+MONTH(M29)-MONTH(M28)+1,0) | N30: =IF(N29>=N28,(YEAR(N29)-YEAR(N28))*12+MONTH(N29)-MONTH(N28)+1,0) | O30: =IF(O29>=O28,(YEAR(O29)-YEAR(O28))*12+MONTH(O29)-MONTH(O28)+1,0) | P30: =IF(P29>=P28,(YEAR(P29)-YEAR(P28))*12+MONTH(P29)-MONTH(P28)+1,0) | Q30: =IF(Q29>=Q28,(YEAR(Q29)-YEAR(Q28))*12+MONTH(Q29)-MONTH(Q28)+1,0) | ... BN30: =IF(BN29>=BN28,(YEAR(BN29)-YEAR(BN28))*12+MONTH(BN29)-MONTH(BN28)+1,0)
D31: Operating days in period | E31: days | J31: =IF(J29>=J28,J29-J28+1,0) | K31: =IF(K29>=K28,K29-K28+1,0) | L31: =IF(L29>=L28,L29-L28+1,0) | M31: =IF(M29>=M28,M29-M28+1,0) | N31: =IF(N29>=N28,N29-N28+1,0) | O31: =IF(O29>=O28,O29-O28+1,0) | P31: =IF(P29>=P28,P29-P28+1,0) | Q31: =IF(Q29>=Q28,Q29-Q28+1,0) | ... BN31: =IF(BN29>=BN28,BN29-BN28+1,0)
D32: Operating months elapsed at period start | E32: months | J32: =MIN(MAX((YEAR(J22)-YEAR($F$8))*12+MONTH(J22)-MONTH($F$8),0),$F$9) | K32: =MIN(MAX((YEAR(K22)-YEAR($F$8))*12+MONTH(K22)-MONTH($F$8),0),$F$9) | L32: =MIN(MAX((YEAR(L22)-YEAR($F$8))*12+MONTH(L22)-MONTH($F$8),0),$F$9) | M32: =MIN(MAX((YEAR(M22)-YEAR($F$8))*12+MONTH(M22)-MONTH($F$8),0),$F$9) | N32: =MIN(MAX((YEAR(N22)-YEAR($F$8))*12+MONTH(N22)-MONTH($F$8),0),$F$9) | O32: =MIN(MAX((YEAR(O22)-YEAR($F$8))*12+MONTH(O22)-MONTH($F$8),0),$F$9) | P32: =MIN(MAX((YEAR(P22)-YEAR($F$8))*12+MONTH(P22)-MONTH($F$8),0),$F$9) | Q32: =MIN(MAX((YEAR(Q22)-YEAR($F$8))*12+MONTH(Q22)-MONTH($F$8),0),$F$9) | ... BN32: =MIN(MAX((YEAR(BN22)-YEAR($F$8))*12+MONTH(BN22)-MONTH($F$8),0),$F$9)
D33: Operating months elapsed at period end | E33: months | J33: =J32+J30 | K33: =K32+K30 | L33: =L32+L30 | M33: =M32+M30 | N33: =N32+N30 | O33: =O32+O30 | P33: =P32+P30 | Q33: =Q32+Q30 | ... BN33: =BN32+BN30
D34: Flag_CODPeriod | E34: flag | J34: =IF(J20=$F$12,1,0) | K34: =IF(K20=$F$12,1,0) | L34: =IF(L20=$F$12,1,0) | M34: =IF(M20=$F$12,1,0) | N34: =IF(N20=$F$12,1,0) | O34: =IF(O20=$F$12,1,0) | P34: =IF(P20=$F$12,1,0) | Q34: =IF(Q20=$F$12,1,0) | ... BN34: =IF(BN20=$F$12,1,0)
D35: Flag_DebtService (after COD period) | E35: flag | J35: =IF(J20>$F$12,1,0) | K35: =IF(K20>$F$12,1,0) | L35: =IF(L20>$F$12,1,0) | M35: =IF(M20>$F$12,1,0) | N35: =IF(N20>$F$12,1,0) | O35: =IF(O20>$F$12,1,0) | P35: =IF(P20>$F$12,1,0) | Q35: =IF(Q20>$F$12,1,0) | ... BN35: =IF(BN20>$F$12,1,0)
D36: Flag_Operations | E36: flag | J36: =IF(J30>0,1,0) | K36: =IF(K30>0,1,0) | L36: =IF(L30>0,1,0) | M36: =IF(M30>0,1,0) | N36: =IF(N30>0,1,0) | O36: =IF(O30>0,1,0) | P36: =IF(P30>0,1,0) | Q36: =IF(Q30>0,1,0) | ... BN36: =IF(BN30>0,1,0)
D37: Flag_LastOperatingPeriod | E37: flag | J37: =IF(AND(J30>0,K30=0),1,0) | K37: =IF(AND(K30>0,L30=0),1,0) | L37: =IF(AND(L30>0,M30=0),1,0) | M37: =IF(AND(M30>0,N30=0),1,0) | N37: =IF(AND(N30>0,O30=0),1,0) | O37: =IF(AND(O30>0,P30=0),1,0) | P37: =IF(AND(P30>0,Q30=0),1,0) | Q37: =IF(AND(Q30>0,R30=0),1,0) | ... BN37: =IF(AND(BN30>0,BO30=0),1,0)
D38: Flag_ShockPeriods | E38: flag | J38: =IF(AND(J22>=Inputs!$F$193,J22<EDATE(Inputs!$F$193,Inputs!$F$211)),1,0) | K38: =IF(AND(K22>=Inputs!$F$193,K22<EDATE(Inputs!$F$193,Inputs!$F$211)),1,0) | L38: =IF(AND(L22>=Inputs!$F$193,L22<EDATE(Inputs!$F$193,Inputs!$F$211)),1,0) | M38: =IF(AND(M22>=Inputs!$F$193,M22<EDATE(Inputs!$F$193,Inputs!$F$211)),1,0) | N38: =IF(AND(N22>=Inputs!$F$193,N22<EDATE(Inputs!$F$193,Inputs!$F$211)),1,0) | O38: =IF(AND(O22>=Inputs!$F$193,O22<EDATE(Inputs!$F$193,Inputs!$F$211)),1,0) | P38: =IF(AND(P22>=Inputs!$F$193,P22<EDATE(Inputs!$F$193,Inputs!$F$211)),1,0) | Q38: =IF(AND(Q22>=Inputs!$F$193,Q22<EDATE(Inputs!$F$193,Inputs!$F$211)),1,0) | ... BN38: =IF(AND(BN22>=Inputs!$F$193,BN22<EDATE(Inputs!$F$193,Inputs!$F$211)),1,0)
D39: Flag_FromShockStart | E39: flag | J39: =IF(J22>=Inputs!$F$193,1,0) | K39: =IF(K22>=Inputs!$F$193,1,0) | L39: =IF(L22>=Inputs!$F$193,1,0) | M39: =IF(M22>=Inputs!$F$193,1,0) | N39: =IF(N22>=Inputs!$F$193,1,0) | O39: =IF(O22>=Inputs!$F$193,1,0) | P39: =IF(P22>=Inputs!$F$193,1,0) | Q39: =IF(Q22>=Inputs!$F$193,1,0) | ... BN39: =IF(BN22>=Inputs!$F$193,1,0)
D40: Flag_TermSOFR | E40: flag | J40: =IF(J22>=Inputs!$F$196,1,0) | K40: =IF(K22>=Inputs!$F$196,1,0) | L40: =IF(L22>=Inputs!$F$196,1,0) | M40: =IF(M22>=Inputs!$F$196,1,0) | N40: =IF(N22>=Inputs!$F$196,1,0) | O40: =IF(O22>=Inputs!$F$196,1,0) | P40: =IF(P22>=Inputs!$F$196,1,0) | Q40: =IF(Q22>=Inputs!$F$196,1,0) | ... BN40: =IF(BN22>=Inputs!$F$196,1,0)
D41: Flag_InsuranceStepUp | E41: flag | J41: =IF(J22>=Inputs!$F$195,1,0) | K41: =IF(K22>=Inputs!$F$195,1,0) | L41: =IF(L22>=Inputs!$F$195,1,0) | M41: =IF(M22>=Inputs!$F$195,1,0) | N41: =IF(N22>=Inputs!$F$195,1,0) | O41: =IF(O22>=Inputs!$F$195,1,0) | P41: =IF(P22>=Inputs!$F$195,1,0) | Q41: =IF(Q22>=Inputs!$F$195,1,0) | ... BN41: =IF(BN22>=Inputs!$F$195,1,0)
D42: Flag_LDPrepayment | E42: flag | J42: =Inputs!$F$48*IF(J23=Inputs!$F$198,1,0) | K42: =Inputs!$F$48*IF(K23=Inputs!$F$198,1,0) | L42: =Inputs!$F$48*IF(L23=Inputs!$F$198,1,0) | M42: =Inputs!$F$48*IF(M23=Inputs!$F$198,1,0) | N42: =Inputs!$F$48*IF(N23=Inputs!$F$198,1,0) | O42: =Inputs!$F$48*IF(O23=Inputs!$F$198,1,0) | P42: =Inputs!$F$48*IF(P23=Inputs!$F$198,1,0) | Q42: =Inputs!$F$48*IF(Q23=Inputs!$F$198,1,0) | ... BN42: =Inputs!$F$48*IF(BN23=Inputs!$F$198,1,0)
D43: Flag_WaiverDeferral | E43: flag | J43: =Inputs!$F$49*IF(J23=Inputs!$F$200,1,0) | K43: =Inputs!$F$49*IF(K23=Inputs!$F$200,1,0) | L43: =Inputs!$F$49*IF(L23=Inputs!$F$200,1,0) | M43: =Inputs!$F$49*IF(M23=Inputs!$F$200,1,0) | N43: =Inputs!$F$49*IF(N23=Inputs!$F$200,1,0) | O43: =Inputs!$F$49*IF(O23=Inputs!$F$200,1,0) | P43: =Inputs!$F$49*IF(P23=Inputs!$F$200,1,0) | Q43: =Inputs!$F$49*IF(Q23=Inputs!$F$200,1,0) | ... BN43: =Inputs!$F$49*IF(BN23=Inputs!$F$200,1,0)
D44: Flag_MarginUplift | E44: flag | J44: =Inputs!$F$49*IF(AND(J22>=Inputs!$F$201,J23<=Inputs!$F$202),1,0) | K44: =Inputs!$F$49*IF(AND(K22>=Inputs!$F$201,K23<=Inputs!$F$202),1,0) | L44: =Inputs!$F$49*IF(AND(L22>=Inputs!$F$201,L23<=Inputs!$F$202),1,0) | M44: =Inputs!$F$49*IF(AND(M22>=Inputs!$F$201,M23<=Inputs!$F$202),1,0) | N44: =Inputs!$F$49*IF(AND(N22>=Inputs!$F$201,N23<=Inputs!$F$202),1,0) | O44: =Inputs!$F$49*IF(AND(O22>=Inputs!$F$201,O23<=Inputs!$F$202),1,0) | P44: =Inputs!$F$49*IF(AND(P22>=Inputs!$F$201,P23<=Inputs!$F$202),1,0) | Q44: =Inputs!$F$49*IF(AND(Q22>=Inputs!$F$201,Q23<=Inputs!$F$202),1,0) | ... BN44: =Inputs!$F$49*IF(AND(BN22>=Inputs!$F$201,BN23<=Inputs!$F$202),1,0)
D45: Flag_DeferredRepayment | E45: flag | J45: =Inputs!$F$49*IF(AND(J23>=Inputs!$F$203,J23<=Inputs!$F$204),1,0) | K45: =Inputs!$F$49*IF(AND(K23>=Inputs!$F$203,K23<=Inputs!$F$204),1,0) | L45: =Inputs!$F$49*IF(AND(L23>=Inputs!$F$203,L23<=Inputs!$F$204),1,0) | M45: =Inputs!$F$49*IF(AND(M23>=Inputs!$F$203,M23<=Inputs!$F$204),1,0) | N45: =Inputs!$F$49*IF(AND(N23>=Inputs!$F$203,N23<=Inputs!$F$204),1,0) | O45: =Inputs!$F$49*IF(AND(O23>=Inputs!$F$203,O23<=Inputs!$F$204),1,0) | P45: =Inputs!$F$49*IF(AND(P23>=Inputs!$F$203,P23<=Inputs!$F$204),1,0) | Q45: =Inputs!$F$49*IF(AND(Q23>=Inputs!$F$203,Q23<=Inputs!$F$204),1,0) | ... BN45: =Inputs!$F$49*IF(AND(BN23>=Inputs!$F$203,BN23<=Inputs!$F$204),1,0)
D46: Deferred repayments remaining (this and later periods) | E46: count | J46: =SUM(J45:BN45) | K46: =SUM(K45:BN45) | L46: =SUM(L45:BN45) | M46: =SUM(M45:BN45) | N46: =SUM(N45:BN45) | O46: =SUM(O45:BN45) | P46: =SUM(P45:BN45) | Q46: =SUM(Q45:BN45) | R46: =SUM(R45:BN45) | S46: =SUM(S45:BN45) | T46: =SUM(T45:BN45) | U46: =SUM(U45:BN45) | V46: =SUM(V45:BN45) | W46: =SUM(W45:BN45) | X46: =SUM(X45:BN45) | Y46: =SUM(Y45:BN45) | Z46: =SUM(Z45:BN45) | AA46: =SUM(AA45:BN45) | AB46: =SUM(AB45:BN45) | AC46: =SUM(AC45:BN45) | AD46: =SUM(AD45:BN45) | AE46: =SUM(AE45:BN45) | AF46: =SUM(AF45:BN45) | AG46: =SUM(AG45:BN45) | AH46: =SUM(AH45:BN45) | AI46: =SUM(AI45:BN45) | AJ46: =SUM(AJ45:BN45) | AK46: =SUM(AK45:BN45) | AL46: =SUM(AL45:BN45) | AM46: =SUM(AM45:BN45) | AN46: =SUM(AN45:BN45) | AO46: =SUM(AO45:BN45) | AP46: =SUM(AP45:BN45) | AQ46: =SUM(AQ45:BN45) | AR46: =SUM(AR45:BN45) | AS46: =SUM(AS45:BN45) | AT46: =SUM(AT45:BN45) | AU46: =SUM(AU45:BN45) | AV46: =SUM(AV45:BN45) | AW46: =SUM(AW45:BN45) | AX46: =SUM(AX45:BN45) | AY46: =SUM(AY45:BN45) | AZ46: =SUM(AZ45:BN45) | BA46: =SUM(BA45:BN45) | BB46: =SUM(BB45:BN45) | BC46: =SUM(BC45:BN45) | BD46: =SUM(BD45:BN45) | BE46: =SUM(BE45:BN45) | BF46: =SUM(BF45:BN45) | BG46: =SUM(BG45:BN45) | BH46: =SUM(BH45:BN45) | BI46: =SUM(BI45:BN45) | BJ46: =SUM(BJ45:BN45) | BK46: =SUM(BK45:BN45) | BL46: =SUM(BL45:BN45) | BM46: =SUM(BM45:BN45) | BN46: =SUM(BN45:BN45)
D47: Flag_Refinancing | E47: flag | J47: =Inputs!$F$50*IF(J23=Inputs!$F$205,1,0) | K47: =Inputs!$F$50*IF(K23=Inputs!$F$205,1,0) | L47: =Inputs!$F$50*IF(L23=Inputs!$F$205,1,0) | M47: =Inputs!$F$50*IF(M23=Inputs!$F$205,1,0) | N47: =Inputs!$F$50*IF(N23=Inputs!$F$205,1,0) | O47: =Inputs!$F$50*IF(O23=Inputs!$F$205,1,0) | P47: =Inputs!$F$50*IF(P23=Inputs!$F$205,1,0) | Q47: =Inputs!$F$50*IF(Q23=Inputs!$F$205,1,0) | ... BN47: =Inputs!$F$50*IF(BN23=Inputs!$F$205,1,0)
D48: Flag_AfterRefinancing | E48: flag | J48: =Inputs!$F$50*IF(J23>Inputs!$F$205,1,0) | K48: =Inputs!$F$50*IF(K23>Inputs!$F$205,1,0) | L48: =Inputs!$F$50*IF(L23>Inputs!$F$205,1,0) | M48: =Inputs!$F$50*IF(M23>Inputs!$F$205,1,0) | N48: =Inputs!$F$50*IF(N23>Inputs!$F$205,1,0) | O48: =Inputs!$F$50*IF(O23>Inputs!$F$205,1,0) | P48: =Inputs!$F$50*IF(P23>Inputs!$F$205,1,0) | Q48: =Inputs!$F$50*IF(Q23>Inputs!$F$205,1,0) | ... BN48: =Inputs!$F$50*IF(BN23>Inputs!$F$205,1,0)
D49: Flag_TestWaived | E49: flag | J49: =Inputs!$F$49*IF(AND(J23>=Inputs!$F$199,J23<=Inputs!$F$200),1,0) | K49: =Inputs!$F$49*IF(AND(K23>=Inputs!$F$199,K23<=Inputs!$F$200),1,0) | L49: =Inputs!$F$49*IF(AND(L23>=Inputs!$F$199,L23<=Inputs!$F$200),1,0) | M49: =Inputs!$F$49*IF(AND(M23>=Inputs!$F$199,M23<=Inputs!$F$200),1,0) | N49: =Inputs!$F$49*IF(AND(N23>=Inputs!$F$199,N23<=Inputs!$F$200),1,0) | O49: =Inputs!$F$49*IF(AND(O23>=Inputs!$F$199,O23<=Inputs!$F$200),1,0) | P49: =Inputs!$F$49*IF(AND(P23>=Inputs!$F$199,P23<=Inputs!$F$200),1,0) | Q49: =Inputs!$F$49*IF(AND(Q23>=Inputs!$F$199,Q23<=Inputs!$F$200),1,0) | ... BN49: =Inputs!$F$49*IF(AND(BN23>=Inputs!$F$199,BN23<=Inputs!$F$200),1,0)
D50: Flag_WaiverRegime | E50: flag | J50: =Inputs!$F$49*IF(J23>=Inputs!$F$199,1,0) | K50: =Inputs!$F$49*IF(K23>=Inputs!$F$199,1,0) | L50: =Inputs!$F$49*IF(L23>=Inputs!$F$199,1,0) | M50: =Inputs!$F$49*IF(M23>=Inputs!$F$199,1,0) | N50: =Inputs!$F$49*IF(N23>=Inputs!$F$199,1,0) | O50: =Inputs!$F$49*IF(O23>=Inputs!$F$199,1,0) | P50: =Inputs!$F$49*IF(P23>=Inputs!$F$199,1,0) | Q50: =Inputs!$F$49*IF(Q23>=Inputs!$F$199,1,0) | ... BN50: =Inputs!$F$49*IF(BN23>=Inputs!$F$199,1,0)
D51: Flag_AfterWaivedTests | E51: flag | J51: =Inputs!$F$49*IF(J23>Inputs!$F$200,1,0) | K51: =Inputs!$F$49*IF(K23>Inputs!$F$200,1,0) | L51: =Inputs!$F$49*IF(L23>Inputs!$F$200,1,0) | M51: =Inputs!$F$49*IF(M23>Inputs!$F$200,1,0) | N51: =Inputs!$F$49*IF(N23>Inputs!$F$200,1,0) | O51: =Inputs!$F$49*IF(O23>Inputs!$F$200,1,0) | P51: =Inputs!$F$49*IF(P23>Inputs!$F$200,1,0) | Q51: =Inputs!$F$49*IF(Q23>Inputs!$F$200,1,0) | ... BN51: =Inputs!$F$49*IF(BN23>Inputs!$F$200,1,0)
D52: Flag_MiniPermSweep | E52: flag | J52: =IF(J22>=Inputs!$F$206,1,0) | K52: =IF(K22>=Inputs!$F$206,1,0) | L52: =IF(L22>=Inputs!$F$206,1,0) | M52: =IF(M22>=Inputs!$F$206,1,0) | N52: =IF(N22>=Inputs!$F$206,1,0) | O52: =IF(O22>=Inputs!$F$206,1,0) | P52: =IF(P22>=Inputs!$F$206,1,0) | Q52: =IF(Q22>=Inputs!$F$206,1,0) | ... BN52: =IF(BN22>=Inputs!$F$206,1,0)
D53: Flag_SculptingPeriod (first repayment to final maturity) | E53: flag | J53: =IF(AND(J20>=$F$13,J23<=Inputs!$F$192),1,0) | K53: =IF(AND(K20>=$F$13,K23<=Inputs!$F$192),1,0) | L53: =IF(AND(L20>=$F$13,L23<=Inputs!$F$192),1,0) | M53: =IF(AND(M20>=$F$13,M23<=Inputs!$F$192),1,0) | N53: =IF(AND(N20>=$F$13,N23<=Inputs!$F$192),1,0) | O53: =IF(AND(O20>=$F$13,O23<=Inputs!$F$192),1,0) | P53: =IF(AND(P20>=$F$13,P23<=Inputs!$F$192),1,0) | Q53: =IF(AND(Q20>=$F$13,Q23<=Inputs!$F$192),1,0) | ... BN53: =IF(AND(BN20>=$F$13,BN23<=Inputs!$F$192),1,0)
D54: Flag_ReforecastProjection | E54: flag | J54: =IF(J22>=Inputs!$F$194,1,0) | K54: =IF(K22>=Inputs!$F$194,1,0) | L54: =IF(L22>=Inputs!$F$194,1,0) | M54: =IF(M22>=Inputs!$F$194,1,0) | N54: =IF(N22>=Inputs!$F$194,1,0) | O54: =IF(O22>=Inputs!$F$194,1,0) | P54: =IF(P22>=Inputs!$F$194,1,0) | Q54: =IF(Q22>=Inputs!$F$194,1,0) | ... BN54: =IF(BN22>=Inputs!$F$194,1,0)
D55: Days of late-payment interest accrual to settlement | E55: days | J55: =MAX(0,MIN(J25,Inputs!$F$197-J22)) | K55: =MAX(0,MIN(K25,Inputs!$F$197-K22)) | L55: =MAX(0,MIN(L25,Inputs!$F$197-L22)) | M55: =MAX(0,MIN(M25,Inputs!$F$197-M22)) | N55: =MAX(0,MIN(N25,Inputs!$F$197-N22)) | O55: =MAX(0,MIN(O25,Inputs!$F$197-O22)) | P55: =MAX(0,MIN(P25,Inputs!$F$197-P22)) | Q55: =MAX(0,MIN(Q25,Inputs!$F$197-Q22)) | ... BN55: =MAX(0,MIN(BN25,Inputs!$F$197-BN22))

Sheet Construction
A1: Case P: Belanou Combined Cycle Power Project, Republic of Kessara
A2: Construction: monthly uses of funds before financing costs, VAT
A3: Units in column E; constants in column F; row totals in column G; first period in column J. Inputs: blue on yellow. Links from other sheets: green.
D4: Label | E4: Unit | F4: Constant | G4: Total
D5: Month | J5: 2018-08 | K5: 2018-09 | L5: 2018-10 | M5: 2018-11 | N5: 2018-12 | O5: 2019-01 | P5: 2019-02 | Q5: 2019-03 | R5: 2019-04 | S5: 2019-05 | T5: 2019-06 | U5: 2019-07 | V5: 2019-08 | W5: 2019-09 | X5: 2019-10 | Y5: 2019-11 | Z5: 2019-12 | AA5: 2020-01 | AB5: 2020-02 | AC5: 2020-03 | AD5: 2020-04 | AE5: 2020-05 | AF5: 2020-06 | AG5: 2020-07 | AH5: 2020-08 | AI5: 2020-09 | AJ5: 2020-10 | AK5: 2020-11 | AL5: 2020-12 | AM5: 2021-01 | AN5: 2021-02 | AO5: 2021-03 | AP5: 2021-04 | AQ5: 2021-05 | AR5: 2021-06 | AS5: 2021-07 | AT5: 2021-08 | AU5: 2021-09 | AV5: 2021-10 | AW5: 2021-11 | AX5: 2021-12 | AY5: 2022-01 | AZ5: 2022-02 | BA5: 2022-03 | BB5: 2022-04 | BC5: 2022-05 | BD5: 2022-06 | BE5: 2022-07 | BF5: 2022-08 | BG5: 2022-09 | BH5: 2022-10 | BI5: 2022-11 | BJ5: 2022-12
B7: Monthly timeline (column J = August 2018)
D8: Month number | E8: index | J8: =I8+1 | K8: =J8+1 | L8: =K8+1 | M8: =L8+1 | N8: =M8+1 | O8: =N8+1 | P8: =O8+1 | Q8: =P8+1 | ... BJ8: =BI8+1
D9: Month start | E9: date | J9: =IF(J8=1,Inputs!$F$188,EDATE(I9,1)) | K9: =IF(K8=1,Inputs!$F$188,EDATE(J9,1)) | L9: =IF(L8=1,Inputs!$F$188,EDATE(K9,1)) | M9: =IF(M8=1,Inputs!$F$188,EDATE(L9,1)) | N9: =IF(N8=1,Inputs!$F$188,EDATE(M9,1)) | O9: =IF(O8=1,Inputs!$F$188,EDATE(N9,1)) | P9: =IF(P8=1,Inputs!$F$188,EDATE(O9,1)) | Q9: =IF(Q8=1,Inputs!$F$188,EDATE(P9,1)) | ... BJ9: =IF(BJ8=1,Inputs!$F$188,EDATE(BI9,1))
D10: Month end | E10: date | J10: =EOMONTH(J9,0) | K10: =EOMONTH(K9,0) | L10: =EOMONTH(L9,0) | M10: =EOMONTH(M9,0) | N10: =EOMONTH(N9,0) | O10: =EOMONTH(O9,0) | P10: =EOMONTH(P9,0) | Q10: =EOMONTH(Q9,0) | ... BJ10: =EOMONTH(BJ9,0)
D11: Days | E11: days | J11: =J10-J9+1 | K11: =K10-K9+1 | L11: =L10-L9+1 | M11: =M10-M9+1 | N11: =N10-N9+1 | O11: =O10-O9+1 | P11: =P10-P9+1 | Q11: =Q10-Q9+1 | ... BJ11: =BJ10-BJ9+1
D12: Semiannual period number | E12: index | J12: =MATCH(J9,Time!$J$22:$BN$22,1) | K12: =MATCH(K9,Time!$J$22:$BN$22,1) | L12: =MATCH(L9,Time!$J$22:$BN$22,1) | M12: =MATCH(M9,Time!$J$22:$BN$22,1) | N12: =MATCH(N9,Time!$J$22:$BN$22,1) | O12: =MATCH(O9,Time!$J$22:$BN$22,1) | P12: =MATCH(P9,Time!$J$22:$BN$22,1) | Q12: =MATCH(Q9,Time!$J$22:$BN$22,1) | ... BJ12: =MATCH(BJ9,Time!$J$22:$BN$22,1)
D13: Flag_Construction (before COD) | E13: flag | J13: =IF(J8<=Time!$F$11,1,0) | K13: =IF(K8<=Time!$F$11,1,0) | L13: =IF(L8<=Time!$F$11,1,0) | M13: =IF(M8<=Time!$F$11,1,0) | N13: =IF(N8<=Time!$F$11,1,0) | O13: =IF(O8<=Time!$F$11,1,0) | P13: =IF(P8<=Time!$F$11,1,0) | Q13: =IF(Q8<=Time!$F$11,1,0) | ... BJ13: =IF(BJ8<=Time!$F$11,1,0)
D14: Flag_FundingPeriod (to end of COD period) | E14: flag | J14: =IF(J8<=Time!$F$14,1,0) | K14: =IF(K8<=Time!$F$14,1,0) | L14: =IF(L8<=Time!$F$14,1,0) | M14: =IF(M8<=Time!$F$14,1,0) | N14: =IF(N8<=Time!$F$14,1,0) | O14: =IF(O8<=Time!$F$14,1,0) | P14: =IF(P8<=Time!$F$14,1,0) | Q14: =IF(Q8<=Time!$F$14,1,0) | ... BJ14: =IF(BJ8<=Time!$F$14,1,0)
D15: Flag_CODMonth | E15: flag | J15: =IF(J8=Time!$F$11+1,1,0) | K15: =IF(K8=Time!$F$11+1,1,0) | L15: =IF(L8=Time!$F$11+1,1,0) | M15: =IF(M8=Time!$F$11+1,1,0) | N15: =IF(N8=Time!$F$11+1,1,0) | O15: =IF(O8=Time!$F$11+1,1,0) | P15: =IF(P8=Time!$F$11+1,1,0) | Q15: =IF(Q8=Time!$F$11+1,1,0) | ... BJ15: =IF(BJ8=Time!$F$11+1,1,0)
D16: KCR per USD | E16: KCR/USD | J16: =IF(Inputs!$F$33=1,Inputs!$F$60*Time!$F$16^((J8-Inputs!$F$212)/12),INDEX(Operations!$J$11:$BN$11,1,J12)) | K16: =IF(Inputs!$F$33=1,Inputs!$F$60*Time!$F$16^((K8-Inputs!$F$212)/12),INDEX(Operations!$J$11:$BN$11,1,K12)) | L16: =IF(Inputs!$F$33=1,Inputs!$F$60*Time!$F$16^((L8-Inputs!$F$212)/12),INDEX(Operations!$J$11:$BN$11,1,L12)) | M16: =IF(Inputs!$F$33=1,Inputs!$F$60*Time!$F$16^((M8-Inputs!$F$212)/12),INDEX(Operations!$J$11:$BN$11,1,M12)) | N16: =IF(Inputs!$F$33=1,Inputs!$F$60*Time!$F$16^((N8-Inputs!$F$212)/12),INDEX(Operations!$J$11:$BN$11,1,N12)) | O16: =IF(Inputs!$F$33=1,Inputs!$F$60*Time!$F$16^((O8-Inputs!$F$212)/12),INDEX(Operations!$J$11:$BN$11,1,O12)) | P16: =IF(Inputs!$F$33=1,Inputs!$F$60*Time!$F$16^((P8-Inputs!$F$212)/12),INDEX(Operations!$J$11:$BN$11,1,P12)) | Q16: =IF(Inputs!$F$33=1,Inputs!$F$60*Time!$F$16^((Q8-Inputs!$F$212)/12),INDEX(Operations!$J$11:$BN$11,1,Q12)) | ... BJ16: =IF(Inputs!$F$33=1,Inputs!$F$60*Time!$F$16^((BJ8-Inputs!$F$212)/12),INDEX(Operations!$J$11:$BN$11,1,BJ12))
D17: Base rate (6M fixing for the half-year) | E17: % | J17: =INDEX(Operations!$J$8:$BN$8,1,J12) | K17: =INDEX(Operations!$J$8:$BN$8,1,K12) | L17: =INDEX(Operations!$J$8:$BN$8,1,L12) | M17: =INDEX(Operations!$J$8:$BN$8,1,M12) | N17: =INDEX(Operations!$J$8:$BN$8,1,N12) | O17: =INDEX(Operations!$J$8:$BN$8,1,O12) | P17: =INDEX(Operations!$J$8:$BN$8,1,P12) | Q17: =INDEX(Operations!$J$8:$BN$8,1,Q12) | ... BJ17: =INDEX(Operations!$J$8:$BN$8,1,BJ12)
D18: Kessara policy rate | E18: % | J18: =IF(Inputs!$F$33=1,Inputs!$F$73,INDEX(Inputs!$J$289:$AR$289,1,MATCH(YEAR(J9),Inputs!$J$282:$AR$282,0))) | K18: =IF(Inputs!$F$33=1,Inputs!$F$73,INDEX(Inputs!$J$289:$AR$289,1,MATCH(YEAR(K9),Inputs!$J$282:$AR$282,0))) | L18: =IF(Inputs!$F$33=1,Inputs!$F$73,INDEX(Inputs!$J$289:$AR$289,1,MATCH(YEAR(L9),Inputs!$J$282:$AR$282,0))) | M18: =IF(Inputs!$F$33=1,Inputs!$F$73,INDEX(Inputs!$J$289:$AR$289,1,MATCH(YEAR(M9),Inputs!$J$282:$AR$282,0))) | N18: =IF(Inputs!$F$33=1,Inputs!$F$73,INDEX(Inputs!$J$289:$AR$289,1,MATCH(YEAR(N9),Inputs!$J$282:$AR$282,0))) | O18: =IF(Inputs!$F$33=1,Inputs!$F$73,INDEX(Inputs!$J$289:$AR$289,1,MATCH(YEAR(O9),Inputs!$J$282:$AR$282,0))) | P18: =IF(Inputs!$F$33=1,Inputs!$F$73,INDEX(Inputs!$J$289:$AR$289,1,MATCH(YEAR(P9),Inputs!$J$282:$AR$282,0))) | Q18: =IF(Inputs!$F$33=1,Inputs!$F$73,INDEX(Inputs!$J$289:$AR$289,1,MATCH(YEAR(Q9),Inputs!$J$282:$AR$282,0))) | ... BJ18: =IF(Inputs!$F$33=1,Inputs!$F$73,INDEX(Inputs!$J$289:$AR$289,1,MATCH(YEAR(BJ9),Inputs!$J$282:$AR$282,0)))
B19: Uses before financing costs (USD m)
D20: EPC payment profile, selected | E20: % | J20: =IF(Inputs!$F$34<>1,Inputs!J306,Inputs!J305+IF(Inputs!$F$35>0,IF(J8=Inputs!$F$237,-Inputs!$F$238,0)+IF(J8=Inputs!$F$237+Inputs!$F$35,Inputs!$F$238,0),0)) | K20: =IF(Inputs!$F$34<>1,Inputs!K306,Inputs!K305+IF(Inputs!$F$35>0,IF(K8=Inputs!$F$237,-Inputs!$F$238,0)+IF(K8=Inputs!$F$237+Inputs!$F$35,Inputs!$F$238,0),0)) | L20: =IF(Inputs!$F$34<>1,Inputs!L306,Inputs!L305+IF(Inputs!$F$35>0,IF(L8=Inputs!$F$237,-Inputs!$F$238,0)+IF(L8=Inputs!$F$237+Inputs!$F$35,Inputs!$F$238,0),0)) | M20: =IF(Inputs!$F$34<>1,Inputs!M306,Inputs!M305+IF(Inputs!$F$35>0,IF(M8=Inputs!$F$237,-Inputs!$F$238,0)+IF(M8=Inputs!$F$237+Inputs!$F$35,Inputs!$F$238,0),0)) | N20: =IF(Inputs!$F$34<>1,Inputs!N306,Inputs!N305+IF(Inputs!$F$35>0,IF(N8=Inputs!$F$237,-Inputs!$F$238,0)+IF(N8=Inputs!$F$237+Inputs!$F$35,Inputs!$F$238,0),0)) | O20: =IF(Inputs!$F$34<>1,Inputs!O306,Inputs!O305+IF(Inputs!$F$35>0,IF(O8=Inputs!$F$237,-Inputs!$F$238,0)+IF(O8=Inputs!$F$237+Inputs!$F$35,Inputs!$F$238,0),0)) | P20: =IF(Inputs!$F$34<>1,Inputs!P306,Inputs!P305+IF(Inputs!$F$35>0,IF(P8=Inputs!$F$237,-Inputs!$F$238,0)+IF(P8=Inputs!$F$237+Inputs!$F$35,Inputs!$F$238,0),0)) | Q20: =IF(Inputs!$F$34<>1,Inputs!Q306,Inputs!Q305+IF(Inputs!$F$35>0,IF(Q8=Inputs!$F$237,-Inputs!$F$238,0)+IF(Q8=Inputs!$F$237+Inputs!$F$35,Inputs!$F$238,0),0)) | ... BJ20: =IF(Inputs!$F$34<>1,Inputs!BJ306,Inputs!BJ305+IF(Inputs!$F$35>0,IF(BJ8=Inputs!$F$237,-Inputs!$F$238,0)+IF(BJ8=Inputs!$F$237+Inputs!$F$35,Inputs!$F$238,0),0))
D21: EPC progress payments for contingency (FC) | E21: % | J21: =IF(J8=1,0,J20)-IF(J8=Time!$F$11,Inputs!$F$238,0) | K21: =IF(K8=1,0,K20)-IF(K8=Time!$F$11,Inputs!$F$238,0) | L21: =IF(L8=1,0,L20)-IF(L8=Time!$F$11,Inputs!$F$238,0) | M21: =IF(M8=1,0,M20)-IF(M8=Time!$F$11,Inputs!$F$238,0) | N21: =IF(N8=1,0,N20)-IF(N8=Time!$F$11,Inputs!$F$238,0) | O21: =IF(O8=1,0,O20)-IF(O8=Time!$F$11,Inputs!$F$238,0) | P21: =IF(P8=1,0,P20)-IF(P8=Time!$F$11,Inputs!$F$238,0) | Q21: =IF(Q8=1,0,Q20)-IF(Q8=Time!$F$11,Inputs!$F$238,0) | ... BJ21: =IF(BJ8=1,0,BJ20)-IF(BJ8=Time!$F$11,Inputs!$F$238,0)
D22: EPC payments | E22: USD m | G22: =SUM(J22:BJ22) | J22: =IF(Inputs!$F$34<>1,J20/100*Inputs!$F$58+J20/100*Inputs!$F$59*Inputs!$F$60/J16,Inputs!$F$57*Inputs!$F$36*J20/100) | K22: =IF(Inputs!$F$34<>1,K20/100*Inputs!$F$58+K20/100*Inputs!$F$59*Inputs!$F$60/K16,Inputs!$F$57*Inputs!$F$36*K20/100) | L22: =IF(Inputs!$F$34<>1,L20/100*Inputs!$F$58+L20/100*Inputs!$F$59*Inputs!$F$60/L16,Inputs!$F$57*Inputs!$F$36*L20/100) | M22: =IF(Inputs!$F$34<>1,M20/100*Inputs!$F$58+M20/100*Inputs!$F$59*Inputs!$F$60/M16,Inputs!$F$57*Inputs!$F$36*M20/100) | N22: =IF(Inputs!$F$34<>1,N20/100*Inputs!$F$58+N20/100*Inputs!$F$59*Inputs!$F$60/N16,Inputs!$F$57*Inputs!$F$36*N20/100) | O22: =IF(Inputs!$F$34<>1,O20/100*Inputs!$F$58+O20/100*Inputs!$F$59*Inputs!$F$60/O16,Inputs!$F$57*Inputs!$F$36*O20/100) | P22: =IF(Inputs!$F$34<>1,P20/100*Inputs!$F$58+P20/100*Inputs!$F$59*Inputs!$F$60/P16,Inputs!$F$57*Inputs!$F$36*P20/100) | Q22: =IF(Inputs!$F$34<>1,Q20/100*Inputs!$F$58+Q20/100*Inputs!$F$59*Inputs!$F$60/Q16,Inputs!$F$57*Inputs!$F$36*Q20/100) | ... BJ22: =IF(Inputs!$F$34<>1,BJ20/100*Inputs!$F$58+BJ20/100*Inputs!$F$59*Inputs!$F$60/BJ16,Inputs!$F$57*Inputs!$F$36*BJ20/100)
D23: Owner's costs | E23: USD m | G23: =SUM(J23:BJ23) | J23: =Inputs!$F$61*IF(Inputs!$F$34=1,Inputs!$F$36,1)*(Inputs!J307+IF(AND(Inputs!$F$34=1,J8>Inputs!$F$237,J8<=Time!$F$11),Inputs!$F$239,0))/100+IF(AND(Inputs!$F$34<>1,J8>=Inputs!$F$240,J8<=Inputs!$F$241),Inputs!$F$69/(Inputs!$F$241-Inputs!$F$240+1),0) | K23: =Inputs!$F$61*IF(Inputs!$F$34=1,Inputs!$F$36,1)*(Inputs!K307+IF(AND(Inputs!$F$34=1,K8>Inputs!$F$237,K8<=Time!$F$11),Inputs!$F$239,0))/100+IF(AND(Inputs!$F$34<>1,K8>=Inputs!$F$240,K8<=Inputs!$F$241),Inputs!$F$69/(Inputs!$F$241-Inputs!$F$240+1),0) | L23: =Inputs!$F$61*IF(Inputs!$F$34=1,Inputs!$F$36,1)*(Inputs!L307+IF(AND(Inputs!$F$34=1,L8>Inputs!$F$237,L8<=Time!$F$11),Inputs!$F$239,0))/100+IF(AND(Inputs!$F$34<>1,L8>=Inputs!$F$240,L8<=Inputs!$F$241),Inputs!$F$69/(Inputs!$F$241-Inputs!$F$240+1),0) | M23: =Inputs!$F$61*IF(Inputs!$F$34=1,Inputs!$F$36,1)*(Inputs!M307+IF(AND(Inputs!$F$34=1,M8>Inputs!$F$237,M8<=Time!$F$11),Inputs!$F$239,0))/100+IF(AND(Inputs!$F$34<>1,M8>=Inputs!$F$240,M8<=Inputs!$F$241),Inputs!$F$69/(Inputs!$F$241-Inputs!$F$240+1),0) | N23: =Inputs!$F$61*IF(Inputs!$F$34=1,Inputs!$F$36,1)*(Inputs!N307+IF(AND(Inputs!$F$34=1,N8>Inputs!$F$237,N8<=Time!$F$11),Inputs!$F$239,0))/100+IF(AND(Inputs!$F$34<>1,N8>=Inputs!$F$240,N8<=Inputs!$F$241),Inputs!$F$69/(Inputs!$F$241-Inputs!$F$240+1),0) | O23: =Inputs!$F$61*IF(Inputs!$F$34=1,Inputs!$F$36,1)*(Inputs!O307+IF(AND(Inputs!$F$34=1,O8>Inputs!$F$237,O8<=Time!$F$11),Inputs!$F$239,0))/100+IF(AND(Inputs!$F$34<>1,O8>=Inputs!$F$240,O8<=Inputs!$F$241),Inputs!$F$69/(Inputs!$F$241-Inputs!$F$240+1),0) | P23: =Inputs!$F$61*IF(Inputs!$F$34=1,Inputs!$F$36,1)*(Inputs!P307+IF(AND(Inputs!$F$34=1,P8>Inputs!$F$237,P8<=Time!$F$11),Inputs!$F$239,0))/100+IF(AND(Inputs!$F$34<>1,P8>=Inputs!$F$240,P8<=Inputs!$F$241),Inputs!$F$69/(Inputs!$F$241-Inputs!$F$240+1),0) | Q23: =Inputs!$F$61*IF(Inputs!$F$34=1,Inputs!$F$36,1)*(Inputs!Q307+IF(AND(Inputs!$F$34=1,Q8>Inputs!$F$237,Q8<=Time!$F$11),Inputs!$F$239,0))/100+IF(AND(Inputs!$F$34<>1,Q8>=Inputs!$F$240,Q8<=Inputs!$F$241),Inputs!$F$69/(Inputs!$F$241-Inputs!$F$240+1),0) | ... BJ23: =Inputs!$F$61*IF(Inputs!$F$34=1,Inputs!$F$36,1)*(Inputs!BJ307+IF(AND(Inputs!$F$34=1,BJ8>Inputs!$F$237,BJ8<=Time!$F$11),Inputs!$F$239,0))/100+IF(AND(Inputs!$F$34<>1,BJ8>=Inputs!$F$240,BJ8<=Inputs!$F$241),Inputs!$F$69/(Inputs!$F$241-Inputs!$F$240+1),0)
D24: Insurance during construction | E24: USD m | G24: =SUM(J24:BJ24) | J24: =Inputs!$F$62*Inputs!$F$36*(Inputs!$F$243*IF(J8=1,1,0)+(1-Inputs!$F$243)*IF(J8=Inputs!$F$242,1,0)) | K24: =Inputs!$F$62*Inputs!$F$36*(Inputs!$F$243*IF(K8=1,1,0)+(1-Inputs!$F$243)*IF(K8=Inputs!$F$242,1,0)) | L24: =Inputs!$F$62*Inputs!$F$36*(Inputs!$F$243*IF(L8=1,1,0)+(1-Inputs!$F$243)*IF(L8=Inputs!$F$242,1,0)) | M24: =Inputs!$F$62*Inputs!$F$36*(Inputs!$F$243*IF(M8=1,1,0)+(1-Inputs!$F$243)*IF(M8=Inputs!$F$242,1,0)) | N24: =Inputs!$F$62*Inputs!$F$36*(Inputs!$F$243*IF(N8=1,1,0)+(1-Inputs!$F$243)*IF(N8=Inputs!$F$242,1,0)) | O24: =Inputs!$F$62*Inputs!$F$36*(Inputs!$F$243*IF(O8=1,1,0)+(1-Inputs!$F$243)*IF(O8=Inputs!$F$242,1,0)) | P24: =Inputs!$F$62*Inputs!$F$36*(Inputs!$F$243*IF(P8=1,1,0)+(1-Inputs!$F$243)*IF(P8=Inputs!$F$242,1,0)) | Q24: =Inputs!$F$62*Inputs!$F$36*(Inputs!$F$243*IF(Q8=1,1,0)+(1-Inputs!$F$243)*IF(Q8=Inputs!$F$242,1,0)) | ... BJ24: =Inputs!$F$62*Inputs!$F$36*(Inputs!$F$243*IF(BJ8=1,1,0)+(1-Inputs!$F$243)*IF(BJ8=Inputs!$F$242,1,0))
D25: Development costs and fee | E25: USD m | G25: =SUM(J25:BJ25) | J25: =IF(J8=1,Inputs!$F$63+Inputs!$F$64,0) | K25: =IF(K8=1,Inputs!$F$63+Inputs!$F$64,0) | L25: =IF(L8=1,Inputs!$F$63+Inputs!$F$64,0) | M25: =IF(M8=1,Inputs!$F$63+Inputs!$F$64,0) | N25: =IF(N8=1,Inputs!$F$63+Inputs!$F$64,0) | O25: =IF(O8=1,Inputs!$F$63+Inputs!$F$64,0) | P25: =IF(P8=1,Inputs!$F$63+Inputs!$F$64,0) | Q25: =IF(Q8=1,Inputs!$F$63+Inputs!$F$64,0) | ... BJ25: =IF(BJ8=1,Inputs!$F$63+Inputs!$F$64,0)
D26: Lenders' advisors and legal | E26: USD m | G26: =SUM(J26:BJ26) | J26: =Inputs!$F$65*Inputs!$F$36*(Inputs!$F$244*IF(J8=1,1,0)+(1-Inputs!$F$244)/(Time!$F$11-1)*IF(AND(J8>1,J8<=Time!$F$11),1,0)) | K26: =Inputs!$F$65*Inputs!$F$36*(Inputs!$F$244*IF(K8=1,1,0)+(1-Inputs!$F$244)/(Time!$F$11-1)*IF(AND(K8>1,K8<=Time!$F$11),1,0)) | L26: =Inputs!$F$65*Inputs!$F$36*(Inputs!$F$244*IF(L8=1,1,0)+(1-Inputs!$F$244)/(Time!$F$11-1)*IF(AND(L8>1,L8<=Time!$F$11),1,0)) | M26: =Inputs!$F$65*Inputs!$F$36*(Inputs!$F$244*IF(M8=1,1,0)+(1-Inputs!$F$244)/(Time!$F$11-1)*IF(AND(M8>1,M8<=Time!$F$11),1,0)) | N26: =Inputs!$F$65*Inputs!$F$36*(Inputs!$F$244*IF(N8=1,1,0)+(1-Inputs!$F$244)/(Time!$F$11-1)*IF(AND(N8>1,N8<=Time!$F$11),1,0)) | O26: =Inputs!$F$65*Inputs!$F$36*(Inputs!$F$244*IF(O8=1,1,0)+(1-Inputs!$F$244)/(Time!$F$11-1)*IF(AND(O8>1,O8<=Time!$F$11),1,0)) | P26: =Inputs!$F$65*Inputs!$F$36*(Inputs!$F$244*IF(P8=1,1,0)+(1-Inputs!$F$244)/(Time!$F$11-1)*IF(AND(P8>1,P8<=Time!$F$11),1,0)) | Q26: =Inputs!$F$65*Inputs!$F$36*(Inputs!$F$244*IF(Q8=1,1,0)+(1-Inputs!$F$244)/(Time!$F$11-1)*IF(AND(Q8>1,Q8<=Time!$F$11),1,0)) | ... BJ26: =Inputs!$F$65*Inputs!$F$36*(Inputs!$F$244*IF(BJ8=1,1,0)+(1-Inputs!$F$244)/(Time!$F$11-1)*IF(AND(BJ8>1,BJ8<=Time!$F$11),1,0))
D27: Contingency (FC: pro rata with EPC progress payments) | E27: USD m | G27: =SUM(J27:BJ27) | J27: =IF(Inputs!$F$34=1,Inputs!$F$66*Inputs!$F$36*J21/SUM($J$21:$BJ$21),0) | K27: =IF(Inputs!$F$34=1,Inputs!$F$66*Inputs!$F$36*K21/SUM($J$21:$BJ$21),0) | L27: =IF(Inputs!$F$34=1,Inputs!$F$66*Inputs!$F$36*L21/SUM($J$21:$BJ$21),0) | M27: =IF(Inputs!$F$34=1,Inputs!$F$66*Inputs!$F$36*M21/SUM($J$21:$BJ$21),0) | N27: =IF(Inputs!$F$34=1,Inputs!$F$66*Inputs!$F$36*N21/SUM($J$21:$BJ$21),0) | O27: =IF(Inputs!$F$34=1,Inputs!$F$66*Inputs!$F$36*O21/SUM($J$21:$BJ$21),0) | P27: =IF(Inputs!$F$34=1,Inputs!$F$66*Inputs!$F$36*P21/SUM($J$21:$BJ$21),0) | Q27: =IF(Inputs!$F$34=1,Inputs!$F$66*Inputs!$F$36*Q21/SUM($J$21:$BJ$21),0) | ... BJ27: =IF(Inputs!$F$34=1,Inputs!$F$66*Inputs!$F$36*BJ21/SUM($J$21:$BJ$21),0)
D28: Initial working capital | E28: USD m | G28: =SUM(J28:BJ28) | J28: =IF(J8=Time!$F$11,Inputs!$F$67*Inputs!$F$36,0) | K28: =IF(K8=Time!$F$11,Inputs!$F$67*Inputs!$F$36,0) | L28: =IF(L8=Time!$F$11,Inputs!$F$67*Inputs!$F$36,0) | M28: =IF(M8=Time!$F$11,Inputs!$F$67*Inputs!$F$36,0) | N28: =IF(N8=Time!$F$11,Inputs!$F$67*Inputs!$F$36,0) | O28: =IF(O8=Time!$F$11,Inputs!$F$67*Inputs!$F$36,0) | P28: =IF(P8=Time!$F$11,Inputs!$F$67*Inputs!$F$36,0) | Q28: =IF(Q8=Time!$F$11,Inputs!$F$67*Inputs!$F$36,0) | ... BJ28: =IF(BJ8=Time!$F$11,Inputs!$F$67*Inputs!$F$36,0)
D29: Overrun items (actual) | E29: USD m | G29: =SUM(J29:BJ29) | J29: =IF(Inputs!$F$34<>1,Inputs!J308,0) | K29: =IF(Inputs!$F$34<>1,Inputs!K308,0) | L29: =IF(Inputs!$F$34<>1,Inputs!L308,0) | M29: =IF(Inputs!$F$34<>1,Inputs!M308,0) | N29: =IF(Inputs!$F$34<>1,Inputs!N308,0) | O29: =IF(Inputs!$F$34<>1,Inputs!O308,0) | P29: =IF(Inputs!$F$34<>1,Inputs!P308,0) | Q29: =IF(Inputs!$F$34<>1,Inputs!Q308,0) | ... BJ29: =IF(Inputs!$F$34<>1,Inputs!BJ308,0)
D30: KCR forward rate traded at financial close (covered interest parity) | E30: KCR/USD | J30: =Inputs!$F$60*((1+Inputs!$F$73/100)/(1+INDEX(Inputs!$J$291:$BN$291,1,J12)/100))^((J10-Inputs!$F$187)/Inputs!$F$248) | K30: =Inputs!$F$60*((1+Inputs!$F$73/100)/(1+INDEX(Inputs!$J$291:$BN$291,1,K12)/100))^((K10-Inputs!$F$187)/Inputs!$F$248) | L30: =Inputs!$F$60*((1+Inputs!$F$73/100)/(1+INDEX(Inputs!$J$291:$BN$291,1,L12)/100))^((L10-Inputs!$F$187)/Inputs!$F$248) | M30: =Inputs!$F$60*((1+Inputs!$F$73/100)/(1+INDEX(Inputs!$J$291:$BN$291,1,M12)/100))^((M10-Inputs!$F$187)/Inputs!$F$248) | N30: =Inputs!$F$60*((1+Inputs!$F$73/100)/(1+INDEX(Inputs!$J$291:$BN$291,1,N12)/100))^((N10-Inputs!$F$187)/Inputs!$F$248) | O30: =Inputs!$F$60*((1+Inputs!$F$73/100)/(1+INDEX(Inputs!$J$291:$BN$291,1,O12)/100))^((O10-Inputs!$F$187)/Inputs!$F$248) | P30: =Inputs!$F$60*((1+Inputs!$F$73/100)/(1+INDEX(Inputs!$J$291:$BN$291,1,P12)/100))^((P10-Inputs!$F$187)/Inputs!$F$248) | Q30: =Inputs!$F$60*((1+Inputs!$F$73/100)/(1+INDEX(Inputs!$J$291:$BN$291,1,Q12)/100))^((Q10-Inputs!$F$187)/Inputs!$F$248) | ... BJ30: =Inputs!$F$60*((1+Inputs!$F$73/100)/(1+INDEX(Inputs!$J$291:$BN$291,1,BJ12)/100))^((BJ10-Inputs!$F$187)/Inputs!$F$248)
D31: FX forward settlement on onshore EPC payments (gain to the project) | E31: USD m | G31: =SUM(J31:BJ31) | J31: =IF(Inputs!$F$34<>1,Inputs!$F$259*J34*(1/J16-1/J30),0) | K31: =IF(Inputs!$F$34<>1,Inputs!$F$259*K34*(1/K16-1/K30),0) | L31: =IF(Inputs!$F$34<>1,Inputs!$F$259*L34*(1/L16-1/L30),0) | M31: =IF(Inputs!$F$34<>1,Inputs!$F$259*M34*(1/M16-1/M30),0) | N31: =IF(Inputs!$F$34<>1,Inputs!$F$259*N34*(1/N16-1/N30),0) | O31: =IF(Inputs!$F$34<>1,Inputs!$F$259*O34*(1/O16-1/O30),0) | P31: =IF(Inputs!$F$34<>1,Inputs!$F$259*P34*(1/P16-1/P30),0) | Q31: =IF(Inputs!$F$34<>1,Inputs!$F$259*Q34*(1/Q16-1/Q30),0) | ... BJ31: =IF(Inputs!$F$34<>1,Inputs!$F$259*BJ34*(1/BJ16-1/BJ30),0)
D32: Uses before financing costs (net of FX hedge settlements) | E32: USD m | G32: =SUM(J32:BJ32) | J32: =J22+J23+J24+J25+J26+J27+J28+J29-J31 | K32: =K22+K23+K24+K25+K26+K27+K28+K29-K31 | L32: =L22+L23+L24+L25+L26+L27+L28+L29-L31 | M32: =M22+M23+M24+M25+M26+M27+M28+M29-M31 | N32: =N22+N23+N24+N25+N26+N27+N28+N29-N31 | O32: =O22+O23+O24+O25+O26+O27+O28+O29-O31 | P32: =P22+P23+P24+P25+P26+P27+P28+P29-P31 | Q32: =Q22+Q23+Q24+Q25+Q26+Q27+Q28+Q29-Q31 | ... BJ32: =BJ22+BJ23+BJ24+BJ25+BJ26+BJ27+BJ28+BJ29-BJ31
B33: VAT on onshore EPC (KCR m) and UBK VAT facility
D34: Onshore EPC payments | E34: KCR m | G34: =SUM(J34:BJ34) | J34: =J20/100*Inputs!$F$59*Inputs!$F$60*Inputs!$F$36 | K34: =K20/100*Inputs!$F$59*Inputs!$F$60*Inputs!$F$36 | L34: =L20/100*Inputs!$F$59*Inputs!$F$60*Inputs!$F$36 | M34: =M20/100*Inputs!$F$59*Inputs!$F$60*Inputs!$F$36 | N34: =N20/100*Inputs!$F$59*Inputs!$F$60*Inputs!$F$36 | O34: =O20/100*Inputs!$F$59*Inputs!$F$60*Inputs!$F$36 | P34: =P20/100*Inputs!$F$59*Inputs!$F$60*Inputs!$F$36 | Q34: =Q20/100*Inputs!$F$59*Inputs!$F$60*Inputs!$F$36 | ... BJ34: =BJ20/100*Inputs!$F$59*Inputs!$F$60*Inputs!$F$36
D38: VAT facility interest (provisional: pasted FC base values; replaced by formulas in Chapter 41) | E38: USD m | G38: =SUM(J38:BJ38) | J38: 0 | K38: 0.019445724 | L38: 0.020031042 | M38: 0.019521849 | N38: 0.020730431 | O38: 0.021886847 | P38: 0.021483009 | Q38: 0.026524861 | R38: 0.029193167 | S38: 0.03472798 | T38: 0.020173501 | U38: 0.027221871 | V38: 0.034171697 | W38: 0.040050802 | X38: 0.048562472 | Y38: 0.053634492 | Z38: 0.061715048 | AA38: 0.067224136 | AB38: 0.067139513 | AC38: 0.075210485 | AD38: 0.074945696 | AE38: 0.078407122 | AF38: 0.075558839 | AG38: 0.076471171 | AH38: 0.073642649 | AI38: 0.067436164 | AJ38: 0.064722764 | AK38: 0.057019429 | AL38: 0.05246833 | AM38: 0.045588345 | AN38: 0.03479697 | AO38: 0.031542811 | AP38: 0.02411303 | AQ38: 0.032090256 | AR38: 0.026017431 | AS38: 0.022569579 | AT38: 0.019139376 | AU38: 0.016021961 | AV38: 0.014747477 | AW38: 0.013168905 | AX38: 0.012998434 | AY38: 0.012751429 | AZ38: 0 | BA38: 0 | BB38: 0 | BC38: 0 | BD38: 0 | BE38: 0 | BF38: 0 | BG38: 0 | BH38: 0 | BI38: 0 | BJ38: 0

Sheet Operations
A1: Case P: Belanou Combined Cycle Power Project, Republic of Kessara
A2: Operations: macro paths, plant, revenue, operating costs, working capital
A3: Units in column E; constants in column F; row totals in column G; first period in column J. Inputs: blue on yellow. Links from other sheets: green.
D4: Label | E4: Unit | F4: Constant | G4: Total
D5: Period ending | J5: 2018H2 | K5: 2019H1 | L5: 2019H2 | M5: 2020H1 | N5: 2020H2 | O5: 2021H1 | P5: 2021H2 | Q5: 2022H1 | R5: 2022H2 | S5: 2023H1 | T5: 2023H2 | U5: 2024H1 | V5: 2024H2 | W5: 2025H1 | X5: 2025H2 | Y5: 2026H1 | Z5: 2026H2 | AA5: 2027H1 | AB5: 2027H2 | AC5: 2028H1 | AD5: 2028H2 | AE5: 2029H1 | AF5: 2029H2 | AG5: 2030H1 | AH5: 2030H2 | AI5: 2031H1 | AJ5: 2031H2 | AK5: 2032H1 | AL5: 2032H2 | AM5: 2033H1 | AN5: 2033H2 | AO5: 2034H1 | AP5: 2034H2 | AQ5: 2035H1 | AR5: 2035H2 | AS5: 2036H1 | AT5: 2036H2 | AU5: 2037H1 | AV5: 2037H2 | AW5: 2038H1 | AX5: 2038H2 | AY5: 2039H1 | AZ5: 2039H2 | BA5: 2040H1 | BB5: 2040H2 | BC5: 2041H1 | BD5: 2041H2 | BE5: 2042H1 | BF5: 2042H2 | BG5: 2043H1 | BH5: 2043H2 | BI5: 2044H1 | BJ5: 2044H2 | BK5: 2045H1 | BL5: 2045H2 | BM5: 2046H1 | BN5: 2046H2
B7: Macro paths
D8: Base rate before sensitivity shift | E8: % | J8: =CHOOSE(Inputs!$F$33,Inputs!J291,Inputs!J292,Inputs!J293) | K8: =CHOOSE(Inputs!$F$33,Inputs!K291,Inputs!K292,Inputs!K293) | L8: =CHOOSE(Inputs!$F$33,Inputs!L291,Inputs!L292,Inputs!L293) | M8: =CHOOSE(Inputs!$F$33,Inputs!M291,Inputs!M292,Inputs!M293) | N8: =CHOOSE(Inputs!$F$33,Inputs!N291,Inputs!N292,Inputs!N293) | O8: =CHOOSE(Inputs!$F$33,Inputs!O291,Inputs!O292,Inputs!O293) | P8: =CHOOSE(Inputs!$F$33,Inputs!P291,Inputs!P292,Inputs!P293) | Q8: =CHOOSE(Inputs!$F$33,Inputs!Q291,Inputs!Q292,Inputs!Q293) | ... BN8: =CHOOSE(Inputs!$F$33,Inputs!BN291,Inputs!BN292,Inputs!BN293)
D9: Base rate (6M LIBOR / Term SOFR + CAS) | E9: % | J9: =J8+Inputs!$F$42*Time!J39 | K9: =K8+Inputs!$F$42*Time!K39 | L9: =L8+Inputs!$F$42*Time!L39 | M9: =M8+Inputs!$F$42*Time!M39 | N9: =N8+Inputs!$F$42*Time!N39 | O9: =O8+Inputs!$F$42*Time!O39 | P9: =P8+Inputs!$F$42*Time!P39 | Q9: =Q8+Inputs!$F$42*Time!Q39 | ... BN9: =BN8+Inputs!$F$42*Time!BN39
D10: KCR per USD before devaluation sensitivity | E10: KCR/USD | J10: =CHOOSE(Inputs!$F$33,Inputs!$F$60*Time!$F$16^((Time!J20-Inputs!$F$212)*Time!J24),IF(Inputs!J294>0,Inputs!J294,I10*((1+J13/100)/(1+J12/100))^Time!J24),IF(Time!J54=0,Inputs!J294,I10*Time!$F$16^Time!J24)) | K10: =CHOOSE(Inputs!$F$33,Inputs!$F$60*Time!$F$16^((Time!K20-Inputs!$F$212)*Time!K24),IF(Inputs!K294>0,Inputs!K294,J10*((1+K13/100)/(1+K12/100))^Time!K24),IF(Time!K54=0,Inputs!K294,J10*Time!$F$16^Time!K24)) | L10: =CHOOSE(Inputs!$F$33,Inputs!$F$60*Time!$F$16^((Time!L20-Inputs!$F$212)*Time!L24),IF(Inputs!L294>0,Inputs!L294,K10*((1+L13/100)/(1+L12/100))^Time!L24),IF(Time!L54=0,Inputs!L294,K10*Time!$F$16^Time!L24)) | M10: =CHOOSE(Inputs!$F$33,Inputs!$F$60*Time!$F$16^((Time!M20-Inputs!$F$212)*Time!M24),IF(Inputs!M294>0,Inputs!M294,L10*((1+M13/100)/(1+M12/100))^Time!M24),IF(Time!M54=0,Inputs!M294,L10*Time!$F$16^Time!M24)) | N10: =CHOOSE(Inputs!$F$33,Inputs!$F$60*Time!$F$16^((Time!N20-Inputs!$F$212)*Time!N24),IF(Inputs!N294>0,Inputs!N294,M10*((1+N13/100)/(1+N12/100))^Time!N24),IF(Time!N54=0,Inputs!N294,M10*Time!$F$16^Time!N24)) | O10: =CHOOSE(Inputs!$F$33,Inputs!$F$60*Time!$F$16^((Time!O20-Inputs!$F$212)*Time!O24),IF(Inputs!O294>0,Inputs!O294,N10*((1+O13/100)/(1+O12/100))^Time!O24),IF(Time!O54=0,Inputs!O294,N10*Time!$F$16^Time!O24)) | P10: =CHOOSE(Inputs!$F$33,Inputs!$F$60*Time!$F$16^((Time!P20-Inputs!$F$212)*Time!P24),IF(Inputs!P294>0,Inputs!P294,O10*((1+P13/100)/(1+P12/100))^Time!P24),IF(Time!P54=0,Inputs!P294,O10*Time!$F$16^Time!P24)) | Q10: =CHOOSE(Inputs!$F$33,Inputs!$F$60*Time!$F$16^((Time!Q20-Inputs!$F$212)*Time!Q24),IF(Inputs!Q294>0,Inputs!Q294,P10*((1+Q13/100)/(1+Q12/100))^Time!Q24),IF(Time!Q54=0,Inputs!Q294,P10*Time!$F$16^Time!Q24)) | ... BN10: =CHOOSE(Inputs!$F$33,Inputs!$F$60*Time!$F$16^((Time!BN20-Inputs!$F$212)*Time!BN24),IF(Inputs!BN294>0,Inputs!BN294,BM10*((1+BN13/100)/(1+BN12/100))^Time!BN24),IF(Time!BN54=0,Inputs!BN294,BM10*Time!$F$16^Time!BN24))
D11: KCR per USD, period average | E11: KCR/USD | J11: =J10/(1-Inputs!$F$43*Time!J39) | K11: =K10/(1-Inputs!$F$43*Time!K39) | L11: =L10/(1-Inputs!$F$43*Time!L39) | M11: =M10/(1-Inputs!$F$43*Time!M39) | N11: =N10/(1-Inputs!$F$43*Time!N39) | O11: =O10/(1-Inputs!$F$43*Time!O39) | P11: =P10/(1-Inputs!$F$43*Time!P39) | Q11: =Q10/(1-Inputs!$F$43*Time!Q39) | ... BN11: =BN10/(1-Inputs!$F$43*Time!BN39)
D12: US CPI change, current year | E12: % | J12: =CHOOSE(Inputs!$F$33,INDEX(Inputs!$J$283:$AR$283,1,MATCH((Time!J26-0),Inputs!$J$282:$AR$282,0)),INDEX(Inputs!$J$285:$AR$285,1,MATCH((Time!J26-0),Inputs!$J$282:$AR$282,0)),INDEX(Inputs!$J$287:$AR$287,1,MATCH((Time!J26-0),Inputs!$J$282:$AR$282,0))) | K12: =CHOOSE(Inputs!$F$33,INDEX(Inputs!$J$283:$AR$283,1,MATCH((Time!K26-0),Inputs!$J$282:$AR$282,0)),INDEX(Inputs!$J$285:$AR$285,1,MATCH((Time!K26-0),Inputs!$J$282:$AR$282,0)),INDEX(Inputs!$J$287:$AR$287,1,MATCH((Time!K26-0),Inputs!$J$282:$AR$282,0))) | L12: =CHOOSE(Inputs!$F$33,INDEX(Inputs!$J$283:$AR$283,1,MATCH((Time!L26-0),Inputs!$J$282:$AR$282,0)),INDEX(Inputs!$J$285:$AR$285,1,MATCH((Time!L26-0),Inputs!$J$282:$AR$282,0)),INDEX(Inputs!$J$287:$AR$287,1,MATCH((Time!L26-0),Inputs!$J$282:$AR$282,0))) | M12: =CHOOSE(Inputs!$F$33,INDEX(Inputs!$J$283:$AR$283,1,MATCH((Time!M26-0),Inputs!$J$282:$AR$282,0)),INDEX(Inputs!$J$285:$AR$285,1,MATCH((Time!M26-0),Inputs!$J$282:$AR$282,0)),INDEX(Inputs!$J$287:$AR$287,1,MATCH((Time!M26-0),Inputs!$J$282:$AR$282,0))) | N12: =CHOOSE(Inputs!$F$33,INDEX(Inputs!$J$283:$AR$283,1,MATCH((Time!N26-0),Inputs!$J$282:$AR$282,0)),INDEX(Inputs!$J$285:$AR$285,1,MATCH((Time!N26-0),Inputs!$J$282:$AR$282,0)),INDEX(Inputs!$J$287:$AR$287,1,MATCH((Time!N26-0),Inputs!$J$282:$AR$282,0))) | O12: =CHOOSE(Inputs!$F$33,INDEX(Inputs!$J$283:$AR$283,1,MATCH((Time!O26-0),Inputs!$J$282:$AR$282,0)),INDEX(Inputs!$J$285:$AR$285,1,MATCH((Time!O26-0),Inputs!$J$282:$AR$282,0)),INDEX(Inputs!$J$287:$AR$287,1,MATCH((Time!O26-0),Inputs!$J$282:$AR$282,0))) | P12: =CHOOSE(Inputs!$F$33,INDEX(Inputs!$J$283:$AR$283,1,MATCH((Time!P26-0),Inputs!$J$282:$AR$282,0)),INDEX(Inputs!$J$285:$AR$285,1,MATCH((Time!P26-0),Inputs!$J$282:$AR$282,0)),INDEX(Inputs!$J$287:$AR$287,1,MATCH((Time!P26-0),Inputs!$J$282:$AR$282,0))) | Q12: =CHOOSE(Inputs!$F$33,INDEX(Inputs!$J$283:$AR$283,1,MATCH((Time!Q26-0),Inputs!$J$282:$AR$282,0)),INDEX(Inputs!$J$285:$AR$285,1,MATCH((Time!Q26-0),Inputs!$J$282:$AR$282,0)),INDEX(Inputs!$J$287:$AR$287,1,MATCH((Time!Q26-0),Inputs!$J$282:$AR$282,0))) | ... BN12: =CHOOSE(Inputs!$F$33,INDEX(Inputs!$J$283:$AR$283,1,MATCH((Time!BN26-0),Inputs!$J$282:$AR$282,0)),INDEX(Inputs!$J$285:$AR$285,1,MATCH((Time!BN26-0),Inputs!$J$282:$AR$282,0)),INDEX(Inputs!$J$287:$AR$287,1,MATCH((Time!BN26-0),Inputs!$J$282:$AR$282,0)))
D13: Kessara CPI change, current year | E13: % | J13: =CHOOSE(Inputs!$F$33,INDEX(Inputs!$J$284:$AR$284,1,MATCH((Time!J26-0),Inputs!$J$282:$AR$282,0)),INDEX(Inputs!$J$286:$AR$286,1,MATCH((Time!J26-0),Inputs!$J$282:$AR$282,0)),INDEX(Inputs!$J$288:$AR$288,1,MATCH((Time!J26-0),Inputs!$J$282:$AR$282,0))) | K13: =CHOOSE(Inputs!$F$33,INDEX(Inputs!$J$284:$AR$284,1,MATCH((Time!K26-0),Inputs!$J$282:$AR$282,0)),INDEX(Inputs!$J$286:$AR$286,1,MATCH((Time!K26-0),Inputs!$J$282:$AR$282,0)),INDEX(Inputs!$J$288:$AR$288,1,MATCH((Time!K26-0),Inputs!$J$282:$AR$282,0))) | L13: =CHOOSE(Inputs!$F$33,INDEX(Inputs!$J$284:$AR$284,1,MATCH((Time!L26-0),Inputs!$J$282:$AR$282,0)),INDEX(Inputs!$J$286:$AR$286,1,MATCH((Time!L26-0),Inputs!$J$282:$AR$282,0)),INDEX(Inputs!$J$288:$AR$288,1,MATCH((Time!L26-0),Inputs!$J$282:$AR$282,0))) | M13: =CHOOSE(Inputs!$F$33,INDEX(Inputs!$J$284:$AR$284,1,MATCH((Time!M26-0),Inputs!$J$282:$AR$282,0)),INDEX(Inputs!$J$286:$AR$286,1,MATCH((Time!M26-0),Inputs!$J$282:$AR$282,0)),INDEX(Inputs!$J$288:$AR$288,1,MATCH((Time!M26-0),Inputs!$J$282:$AR$282,0))) | N13: =CHOOSE(Inputs!$F$33,INDEX(Inputs!$J$284:$AR$284,1,MATCH((Time!N26-0),Inputs!$J$282:$AR$282,0)),INDEX(Inputs!$J$286:$AR$286,1,MATCH((Time!N26-0),Inputs!$J$282:$AR$282,0)),INDEX(Inputs!$J$288:$AR$288,1,MATCH((Time!N26-0),Inputs!$J$282:$AR$282,0))) | O13: =CHOOSE(Inputs!$F$33,INDEX(Inputs!$J$284:$AR$284,1,MATCH((Time!O26-0),Inputs!$J$282:$AR$282,0)),INDEX(Inputs!$J$286:$AR$286,1,MATCH((Time!O26-0),Inputs!$J$282:$AR$282,0)),INDEX(Inputs!$J$288:$AR$288,1,MATCH((Time!O26-0),Inputs!$J$282:$AR$282,0))) | P13: =CHOOSE(Inputs!$F$33,INDEX(Inputs!$J$284:$AR$284,1,MATCH((Time!P26-0),Inputs!$J$282:$AR$282,0)),INDEX(Inputs!$J$286:$AR$286,1,MATCH((Time!P26-0),Inputs!$J$282:$AR$282,0)),INDEX(Inputs!$J$288:$AR$288,1,MATCH((Time!P26-0),Inputs!$J$282:$AR$282,0))) | Q13: =CHOOSE(Inputs!$F$33,INDEX(Inputs!$J$284:$AR$284,1,MATCH((Time!Q26-0),Inputs!$J$282:$AR$282,0)),INDEX(Inputs!$J$286:$AR$286,1,MATCH((Time!Q26-0),Inputs!$J$282:$AR$282,0)),INDEX(Inputs!$J$288:$AR$288,1,MATCH((Time!Q26-0),Inputs!$J$282:$AR$282,0))) | ... BN13: =CHOOSE(Inputs!$F$33,INDEX(Inputs!$J$284:$AR$284,1,MATCH((Time!BN26-0),Inputs!$J$282:$AR$282,0)),INDEX(Inputs!$J$286:$AR$286,1,MATCH((Time!BN26-0),Inputs!$J$282:$AR$282,0)),INDEX(Inputs!$J$288:$AR$288,1,MATCH((Time!BN26-0),Inputs!$J$282:$AR$282,0)))
D14: US CPI change, prior year | E14: % | J14: =CHOOSE(Inputs!$F$33,INDEX(Inputs!$J$283:$AR$283,1,MATCH((Time!J26-1),Inputs!$J$282:$AR$282,0)),INDEX(Inputs!$J$285:$AR$285,1,MATCH((Time!J26-1),Inputs!$J$282:$AR$282,0)),INDEX(Inputs!$J$287:$AR$287,1,MATCH((Time!J26-1),Inputs!$J$282:$AR$282,0))) | K14: =CHOOSE(Inputs!$F$33,INDEX(Inputs!$J$283:$AR$283,1,MATCH((Time!K26-1),Inputs!$J$282:$AR$282,0)),INDEX(Inputs!$J$285:$AR$285,1,MATCH((Time!K26-1),Inputs!$J$282:$AR$282,0)),INDEX(Inputs!$J$287:$AR$287,1,MATCH((Time!K26-1),Inputs!$J$282:$AR$282,0))) | L14: =CHOOSE(Inputs!$F$33,INDEX(Inputs!$J$283:$AR$283,1,MATCH((Time!L26-1),Inputs!$J$282:$AR$282,0)),INDEX(Inputs!$J$285:$AR$285,1,MATCH((Time!L26-1),Inputs!$J$282:$AR$282,0)),INDEX(Inputs!$J$287:$AR$287,1,MATCH((Time!L26-1),Inputs!$J$282:$AR$282,0))) | M14: =CHOOSE(Inputs!$F$33,INDEX(Inputs!$J$283:$AR$283,1,MATCH((Time!M26-1),Inputs!$J$282:$AR$282,0)),INDEX(Inputs!$J$285:$AR$285,1,MATCH((Time!M26-1),Inputs!$J$282:$AR$282,0)),INDEX(Inputs!$J$287:$AR$287,1,MATCH((Time!M26-1),Inputs!$J$282:$AR$282,0))) | N14: =CHOOSE(Inputs!$F$33,INDEX(Inputs!$J$283:$AR$283,1,MATCH((Time!N26-1),Inputs!$J$282:$AR$282,0)),INDEX(Inputs!$J$285:$AR$285,1,MATCH((Time!N26-1),Inputs!$J$282:$AR$282,0)),INDEX(Inputs!$J$287:$AR$287,1,MATCH((Time!N26-1),Inputs!$J$282:$AR$282,0))) | O14: =CHOOSE(Inputs!$F$33,INDEX(Inputs!$J$283:$AR$283,1,MATCH((Time!O26-1),Inputs!$J$282:$AR$282,0)),INDEX(Inputs!$J$285:$AR$285,1,MATCH((Time!O26-1),Inputs!$J$282:$AR$282,0)),INDEX(Inputs!$J$287:$AR$287,1,MATCH((Time!O26-1),Inputs!$J$282:$AR$282,0))) | P14: =CHOOSE(Inputs!$F$33,INDEX(Inputs!$J$283:$AR$283,1,MATCH((Time!P26-1),Inputs!$J$282:$AR$282,0)),INDEX(Inputs!$J$285:$AR$285,1,MATCH((Time!P26-1),Inputs!$J$282:$AR$282,0)),INDEX(Inputs!$J$287:$AR$287,1,MATCH((Time!P26-1),Inputs!$J$282:$AR$282,0))) | Q14: =CHOOSE(Inputs!$F$33,INDEX(Inputs!$J$283:$AR$283,1,MATCH((Time!Q26-1),Inputs!$J$282:$AR$282,0)),INDEX(Inputs!$J$285:$AR$285,1,MATCH((Time!Q26-1),Inputs!$J$282:$AR$282,0)),INDEX(Inputs!$J$287:$AR$287,1,MATCH((Time!Q26-1),Inputs!$J$282:$AR$282,0))) | ... BN14: =CHOOSE(Inputs!$F$33,INDEX(Inputs!$J$283:$AR$283,1,MATCH((Time!BN26-1),Inputs!$J$282:$AR$282,0)),INDEX(Inputs!$J$285:$AR$285,1,MATCH((Time!BN26-1),Inputs!$J$282:$AR$282,0)),INDEX(Inputs!$J$287:$AR$287,1,MATCH((Time!BN26-1),Inputs!$J$282:$AR$282,0)))
D15: Kessara CPI change, prior year | E15: % | J15: =CHOOSE(Inputs!$F$33,INDEX(Inputs!$J$284:$AR$284,1,MATCH((Time!J26-1),Inputs!$J$282:$AR$282,0)),INDEX(Inputs!$J$286:$AR$286,1,MATCH((Time!J26-1),Inputs!$J$282:$AR$282,0)),INDEX(Inputs!$J$288:$AR$288,1,MATCH((Time!J26-1),Inputs!$J$282:$AR$282,0))) | K15: =CHOOSE(Inputs!$F$33,INDEX(Inputs!$J$284:$AR$284,1,MATCH((Time!K26-1),Inputs!$J$282:$AR$282,0)),INDEX(Inputs!$J$286:$AR$286,1,MATCH((Time!K26-1),Inputs!$J$282:$AR$282,0)),INDEX(Inputs!$J$288:$AR$288,1,MATCH((Time!K26-1),Inputs!$J$282:$AR$282,0))) | L15: =CHOOSE(Inputs!$F$33,INDEX(Inputs!$J$284:$AR$284,1,MATCH((Time!L26-1),Inputs!$J$282:$AR$282,0)),INDEX(Inputs!$J$286:$AR$286,1,MATCH((Time!L26-1),Inputs!$J$282:$AR$282,0)),INDEX(Inputs!$J$288:$AR$288,1,MATCH((Time!L26-1),Inputs!$J$282:$AR$282,0))) | M15: =CHOOSE(Inputs!$F$33,INDEX(Inputs!$J$284:$AR$284,1,MATCH((Time!M26-1),Inputs!$J$282:$AR$282,0)),INDEX(Inputs!$J$286:$AR$286,1,MATCH((Time!M26-1),Inputs!$J$282:$AR$282,0)),INDEX(Inputs!$J$288:$AR$288,1,MATCH((Time!M26-1),Inputs!$J$282:$AR$282,0))) | N15: =CHOOSE(Inputs!$F$33,INDEX(Inputs!$J$284:$AR$284,1,MATCH((Time!N26-1),Inputs!$J$282:$AR$282,0)),INDEX(Inputs!$J$286:$AR$286,1,MATCH((Time!N26-1),Inputs!$J$282:$AR$282,0)),INDEX(Inputs!$J$288:$AR$288,1,MATCH((Time!N26-1),Inputs!$J$282:$AR$282,0))) | O15: =CHOOSE(Inputs!$F$33,INDEX(Inputs!$J$284:$AR$284,1,MATCH((Time!O26-1),Inputs!$J$282:$AR$282,0)),INDEX(Inputs!$J$286:$AR$286,1,MATCH((Time!O26-1),Inputs!$J$282:$AR$282,0)),INDEX(Inputs!$J$288:$AR$288,1,MATCH((Time!O26-1),Inputs!$J$282:$AR$282,0))) | P15: =CHOOSE(Inputs!$F$33,INDEX(Inputs!$J$284:$AR$284,1,MATCH((Time!P26-1),Inputs!$J$282:$AR$282,0)),INDEX(Inputs!$J$286:$AR$286,1,MATCH((Time!P26-1),Inputs!$J$282:$AR$282,0)),INDEX(Inputs!$J$288:$AR$288,1,MATCH((Time!P26-1),Inputs!$J$282:$AR$282,0))) | Q15: =CHOOSE(Inputs!$F$33,INDEX(Inputs!$J$284:$AR$284,1,MATCH((Time!Q26-1),Inputs!$J$282:$AR$282,0)),INDEX(Inputs!$J$286:$AR$286,1,MATCH((Time!Q26-1),Inputs!$J$282:$AR$282,0)),INDEX(Inputs!$J$288:$AR$288,1,MATCH((Time!Q26-1),Inputs!$J$282:$AR$282,0))) | ... BN15: =CHOOSE(Inputs!$F$33,INDEX(Inputs!$J$284:$AR$284,1,MATCH((Time!BN26-1),Inputs!$J$282:$AR$282,0)),INDEX(Inputs!$J$286:$AR$286,1,MATCH((Time!BN26-1),Inputs!$J$282:$AR$282,0)),INDEX(Inputs!$J$288:$AR$288,1,MATCH((Time!BN26-1),Inputs!$J$282:$AR$282,0)))

Sheet Funding
A1: Case P: Belanou Combined Cycle Power Project, Republic of Kessara
A2: Funding: closed-form gross-up, drawdowns by tranche, IDC, fees, equity
A3: Units in column E; constants in column F; row totals in column G; first period in column J. Inputs: blue on yellow. Links from other sheets: green.
D4: Label | E4: Unit | F4: Constant | G4: Total
D5: Month | J5: 2018-08 | K5: 2018-09 | L5: 2018-10 | M5: 2018-11 | N5: 2018-12 | O5: 2019-01 | P5: 2019-02 | Q5: 2019-03 | R5: 2019-04 | S5: 2019-05 | T5: 2019-06 | U5: 2019-07 | V5: 2019-08 | W5: 2019-09 | X5: 2019-10 | Y5: 2019-11 | Z5: 2019-12 | AA5: 2020-01 | AB5: 2020-02 | AC5: 2020-03 | AD5: 2020-04 | AE5: 2020-05 | AF5: 2020-06 | AG5: 2020-07 | AH5: 2020-08 | AI5: 2020-09 | AJ5: 2020-10 | AK5: 2020-11 | AL5: 2020-12 | AM5: 2021-01 | AN5: 2021-02 | AO5: 2021-03 | AP5: 2021-04 | AQ5: 2021-05 | AR5: 2021-06 | AS5: 2021-07 | AT5: 2021-08 | AU5: 2021-09 | AV5: 2021-10 | AW5: 2021-11 | AX5: 2021-12 | AY5: 2022-01 | AZ5: 2022-02 | BA5: 2022-03 | BB5: 2022-04 | BC5: 2022-05 | BD5: 2022-06 | BE5: 2022-07 | BF5: 2022-08 | BG5: 2022-09 | BH5: 2022-10 | BI5: 2022-11 | BJ5: 2022-12
B7: Constants
D8: Contract debt share of funding g = D/(D+E) | E8: fraction | F8: =Inputs!$F$113/(Inputs!$F$113+Inputs!$F$114)
D9: Gearing used in the closed-form gross-up | E9: fraction | F9: =IF(Inputs!$F$51<>1,Funding!$F$8,Inputs!$F$105)
D10: ECA premium gross-up denominator 1 - prem x share x g | E10: factor | F10: =1-Inputs!$F$94/100*Inputs!$F$75*Funding!$F$9
D11: First installment share of remaining profile | E11: fraction | F11: =INDEX(Debt!$J$17:$BN$17,1,Time!$F$13)/INDEX(Debt!$J$18:$BN$18,1,Time!$F$13)
D12: DSRA coefficient per USD of E balance | E12: factor | F12: =$F$11+(INDEX(Operations!$J$9:$BN$9,1,Time!$F$13)+Inputs!$F$79)/100*INDEX(Time!$J$25:$BN$25,1,Time!$F$13)/Inputs!$F$247*1
D13: DSRA coefficient per USD of A balance | E13: factor | F13: =$F$11+(INDEX(Operations!$J$9:$BN$9,1,Time!$F$13)+Inputs!$F$80)/100*INDEX(Time!$J$25:$BN$25,1,Time!$F$13)/Inputs!$F$247*1
D14: DSRA coefficient per USD of B balance | E14: factor | F14: =$F$11+(INDEX(Operations!$J$9:$BN$9,1,Time!$F$13)+Inputs!$F$81)/100*INDEX(Time!$J$25:$BN$25,1,Time!$F$13)/Inputs!$F$247*1
D15: DSRA coefficient per USD of C balance | E15: factor | F15: =$F$11+(INDEX(Operations!$J$9:$BN$9,1,Time!$F$13)+INDEX(Debt!$J$8:$BN$8,1,Time!$F$13))/100*INDEX(Time!$J$25:$BN$25,1,Time!$F$13)/Inputs!$F$247*(1/(1-Inputs!$F$93/100))+(Inputs!$F$95/100*Inputs!$F$96/100)*INDEX(Time!$J$25:$BN$25,1,Time!$F$13)/Inputs!$F$248
D16: DSRA coefficient per USD of standby balance | E16: factor | F16: =$F$11+INDEX(Debt!$J$14:$BN$14,1,Time!$F$13)
D17: DSRA constant (swap net payment) | E17: USD m | F17: =INDEX(Inputs!$J$301:$BN$301,1,Time!$F$13)*(Inputs!$F$97/100*INDEX(Time!$J$24:$BN$24,1,Time!$F$13)-INDEX(Operations!$J$9:$BN$9,1,Time!$F$13)/100*INDEX(Time!$J$25:$BN$25,1,Time!$F$13)/Inputs!$F$247)
B18: Closed-form gross-up: debt balance = alpha + beta x T (FC-type cases)
D19: Blended loan rate per month (rho) | E19: factor | J19: =Inputs!$F$75*(Construction!J17+Inputs!$F$79)/100*Construction!J11/Inputs!$F$247*1+Inputs!$F$76*(Construction!J17+Inputs!$F$80)/100*Construction!J11/Inputs!$F$247*1+Inputs!$F$77*(Construction!J17+Inputs!$F$81)/100*Construction!J11/Inputs!$F$247*1+Inputs!$F$78*(Construction!J17+Inputs!$F$82)/100*Construction!J11/Inputs!$F$247*(1/(1-Inputs!$F$93/100))+Inputs!$F$78*(Inputs!$F$95/100*Inputs!$F$96/100)*Construction!J11/Inputs!$F$248 | K19: =Inputs!$F$75*(Construction!K17+Inputs!$F$79)/100*Construction!K11/Inputs!$F$247*1+Inputs!$F$76*(Construction!K17+Inputs!$F$80)/100*Construction!K11/Inputs!$F$247*1+Inputs!$F$77*(Construction!K17+Inputs!$F$81)/100*Construction!K11/Inputs!$F$247*1+Inputs!$F$78*(Construction!K17+Inputs!$F$82)/100*Construction!K11/Inputs!$F$247*(1/(1-Inputs!$F$93/100))+Inputs!$F$78*(Inputs!$F$95/100*Inputs!$F$96/100)*Construction!K11/Inputs!$F$248 | L19: =Inputs!$F$75*(Construction!L17+Inputs!$F$79)/100*Construction!L11/Inputs!$F$247*1+Inputs!$F$76*(Construction!L17+Inputs!$F$80)/100*Construction!L11/Inputs!$F$247*1+Inputs!$F$77*(Construction!L17+Inputs!$F$81)/100*Construction!L11/Inputs!$F$247*1+Inputs!$F$78*(Construction!L17+Inputs!$F$82)/100*Construction!L11/Inputs!$F$247*(1/(1-Inputs!$F$93/100))+Inputs!$F$78*(Inputs!$F$95/100*Inputs!$F$96/100)*Construction!L11/Inputs!$F$248 | M19: =Inputs!$F$75*(Construction!M17+Inputs!$F$79)/100*Construction!M11/Inputs!$F$247*1+Inputs!$F$76*(Construction!M17+Inputs!$F$80)/100*Construction!M11/Inputs!$F$247*1+Inputs!$F$77*(Construction!M17+Inputs!$F$81)/100*Construction!M11/Inputs!$F$247*1+Inputs!$F$78*(Construction!M17+Inputs!$F$82)/100*Construction!M11/Inputs!$F$247*(1/(1-Inputs!$F$93/100))+Inputs!$F$78*(Inputs!$F$95/100*Inputs!$F$96/100)*Construction!M11/Inputs!$F$248 | N19: =Inputs!$F$75*(Construction!N17+Inputs!$F$79)/100*Construction!N11/Inputs!$F$247*1+Inputs!$F$76*(Construction!N17+Inputs!$F$80)/100*Construction!N11/Inputs!$F$247*1+Inputs!$F$77*(Construction!N17+Inputs!$F$81)/100*Construction!N11/Inputs!$F$247*1+Inputs!$F$78*(Construction!N17+Inputs!$F$82)/100*Construction!N11/Inputs!$F$247*(1/(1-Inputs!$F$93/100))+Inputs!$F$78*(Inputs!$F$95/100*Inputs!$F$96/100)*Construction!N11/Inputs!$F$248 | O19: =Inputs!$F$75*(Construction!O17+Inputs!$F$79)/100*Construction!O11/Inputs!$F$247*1+Inputs!$F$76*(Construction!O17+Inputs!$F$80)/100*Construction!O11/Inputs!$F$247*1+Inputs!$F$77*(Construction!O17+Inputs!$F$81)/100*Construction!O11/Inputs!$F$247*1+Inputs!$F$78*(Construction!O17+Inputs!$F$82)/100*Construction!O11/Inputs!$F$247*(1/(1-Inputs!$F$93/100))+Inputs!$F$78*(Inputs!$F$95/100*Inputs!$F$96/100)*Construction!O11/Inputs!$F$248 | P19: =Inputs!$F$75*(Construction!P17+Inputs!$F$79)/100*Construction!P11/Inputs!$F$247*1+Inputs!$F$76*(Construction!P17+Inputs!$F$80)/100*Construction!P11/Inputs!$F$247*1+Inputs!$F$77*(Construction!P17+Inputs!$F$81)/100*Construction!P11/Inputs!$F$247*1+Inputs!$F$78*(Construction!P17+Inputs!$F$82)/100*Construction!P11/Inputs!$F$247*(1/(1-Inputs!$F$93/100))+Inputs!$F$78*(Inputs!$F$95/100*Inputs!$F$96/100)*Construction!P11/Inputs!$F$248 | Q19: =Inputs!$F$75*(Construction!Q17+Inputs!$F$79)/100*Construction!Q11/Inputs!$F$247*1+Inputs!$F$76*(Construction!Q17+Inputs!$F$80)/100*Construction!Q11/Inputs!$F$247*1+Inputs!$F$77*(Construction!Q17+Inputs!$F$81)/100*Construction!Q11/Inputs!$F$247*1+Inputs!$F$78*(Construction!Q17+Inputs!$F$82)/100*Construction!Q11/Inputs!$F$247*(1/(1-Inputs!$F$93/100))+Inputs!$F$78*(Inputs!$F$95/100*Inputs!$F$96/100)*Construction!Q11/Inputs!$F$248 | ... BJ19: =Inputs!$F$75*(Construction!BJ17+Inputs!$F$79)/100*Construction!BJ11/Inputs!$F$247*1+Inputs!$F$76*(Construction!BJ17+Inputs!$F$80)/100*Construction!BJ11/Inputs!$F$247*1+Inputs!$F$77*(Construction!BJ17+Inputs!$F$81)/100*Construction!BJ11/Inputs!$F$247*1+Inputs!$F$78*(Construction!BJ17+Inputs!$F$82)/100*Construction!BJ11/Inputs!$F$247*(1/(1-Inputs!$F$93/100))+Inputs!$F$78*(Inputs!$F$95/100*Inputs!$F$96/100)*Construction!BJ11/Inputs!$F$248
D20: Blended commitment fee per month (kappa) | E20: factor | J20: =Inputs!$F$75*Inputs!$F$85/100*Construction!J11/Inputs!$F$247+Inputs!$F$76*Inputs!$F$86/100*Construction!J11/Inputs!$F$247+Inputs!$F$77*Inputs!$F$87/100*Construction!J11/Inputs!$F$247+Inputs!$F$78*(Inputs!$F$88/100*Inputs!$F$82)/100*Construction!J11/Inputs!$F$247 | K20: =Inputs!$F$75*Inputs!$F$85/100*Construction!K11/Inputs!$F$247+Inputs!$F$76*Inputs!$F$86/100*Construction!K11/Inputs!$F$247+Inputs!$F$77*Inputs!$F$87/100*Construction!K11/Inputs!$F$247+Inputs!$F$78*(Inputs!$F$88/100*Inputs!$F$82)/100*Construction!K11/Inputs!$F$247 | L20: =Inputs!$F$75*Inputs!$F$85/100*Construction!L11/Inputs!$F$247+Inputs!$F$76*Inputs!$F$86/100*Construction!L11/Inputs!$F$247+Inputs!$F$77*Inputs!$F$87/100*Construction!L11/Inputs!$F$247+Inputs!$F$78*(Inputs!$F$88/100*Inputs!$F$82)/100*Construction!L11/Inputs!$F$247 | M20: =Inputs!$F$75*Inputs!$F$85/100*Construction!M11/Inputs!$F$247+Inputs!$F$76*Inputs!$F$86/100*Construction!M11/Inputs!$F$247+Inputs!$F$77*Inputs!$F$87/100*Construction!M11/Inputs!$F$247+Inputs!$F$78*(Inputs!$F$88/100*Inputs!$F$82)/100*Construction!M11/Inputs!$F$247 | N20: =Inputs!$F$75*Inputs!$F$85/100*Construction!N11/Inputs!$F$247+Inputs!$F$76*Inputs!$F$86/100*Construction!N11/Inputs!$F$247+Inputs!$F$77*Inputs!$F$87/100*Construction!N11/Inputs!$F$247+Inputs!$F$78*(Inputs!$F$88/100*Inputs!$F$82)/100*Construction!N11/Inputs!$F$247 | O20: =Inputs!$F$75*Inputs!$F$85/100*Construction!O11/Inputs!$F$247+Inputs!$F$76*Inputs!$F$86/100*Construction!O11/Inputs!$F$247+Inputs!$F$77*Inputs!$F$87/100*Construction!O11/Inputs!$F$247+Inputs!$F$78*(Inputs!$F$88/100*Inputs!$F$82)/100*Construction!O11/Inputs!$F$247 | P20: =Inputs!$F$75*Inputs!$F$85/100*Construction!P11/Inputs!$F$247+Inputs!$F$76*Inputs!$F$86/100*Construction!P11/Inputs!$F$247+Inputs!$F$77*Inputs!$F$87/100*Construction!P11/Inputs!$F$247+Inputs!$F$78*(Inputs!$F$88/100*Inputs!$F$82)/100*Construction!P11/Inputs!$F$247 | Q20: =Inputs!$F$75*Inputs!$F$85/100*Construction!Q11/Inputs!$F$247+Inputs!$F$76*Inputs!$F$86/100*Construction!Q11/Inputs!$F$247+Inputs!$F$77*Inputs!$F$87/100*Construction!Q11/Inputs!$F$247+Inputs!$F$78*(Inputs!$F$88/100*Inputs!$F$82)/100*Construction!Q11/Inputs!$F$247 | ... BJ20: =Inputs!$F$75*Inputs!$F$85/100*Construction!BJ11/Inputs!$F$247+Inputs!$F$76*Inputs!$F$86/100*Construction!BJ11/Inputs!$F$247+Inputs!$F$77*Inputs!$F$87/100*Construction!BJ11/Inputs!$F$247+Inputs!$F$78*(Inputs!$F$88/100*Inputs!$F$82)/100*Construction!BJ11/Inputs!$F$247
D21: Costs independent of facility size | E21: USD m | J21: =Construction!J14*(Construction!J32+Construction!J38+Inputs!$F$107/12+Inputs!J309*(Inputs!$F$97/100/12-Construction!J17/100*Construction!J11/Inputs!$F$247)+Inputs!$F$99*Inputs!$F$100/100*Construction!J11/Inputs!$F$247+Construction!J15*$F$17) | K21: =Construction!K14*(Construction!K32+Construction!K38+Inputs!$F$107/12+Inputs!K309*(Inputs!$F$97/100/12-Construction!K17/100*Construction!K11/Inputs!$F$247)+Inputs!$F$99*Inputs!$F$100/100*Construction!K11/Inputs!$F$247+Construction!K15*$F$17) | L21: =Construction!L14*(Construction!L32+Construction!L38+Inputs!$F$107/12+Inputs!L309*(Inputs!$F$97/100/12-Construction!L17/100*Construction!L11/Inputs!$F$247)+Inputs!$F$99*Inputs!$F$100/100*Construction!L11/Inputs!$F$247+Construction!L15*$F$17) | M21: =Construction!M14*(Construction!M32+Construction!M38+Inputs!$F$107/12+Inputs!M309*(Inputs!$F$97/100/12-Construction!M17/100*Construction!M11/Inputs!$F$247)+Inputs!$F$99*Inputs!$F$100/100*Construction!M11/Inputs!$F$247+Construction!M15*$F$17) | N21: =Construction!N14*(Construction!N32+Construction!N38+Inputs!$F$107/12+Inputs!N309*(Inputs!$F$97/100/12-Construction!N17/100*Construction!N11/Inputs!$F$247)+Inputs!$F$99*Inputs!$F$100/100*Construction!N11/Inputs!$F$247+Construction!N15*$F$17) | O21: =Construction!O14*(Construction!O32+Construction!O38+Inputs!$F$107/12+Inputs!O309*(Inputs!$F$97/100/12-Construction!O17/100*Construction!O11/Inputs!$F$247)+Inputs!$F$99*Inputs!$F$100/100*Construction!O11/Inputs!$F$247+Construction!O15*$F$17) | P21: =Construction!P14*(Construction!P32+Construction!P38+Inputs!$F$107/12+Inputs!P309*(Inputs!$F$97/100/12-Construction!P17/100*Construction!P11/Inputs!$F$247)+Inputs!$F$99*Inputs!$F$100/100*Construction!P11/Inputs!$F$247+Construction!P15*$F$17) | Q21: =Construction!Q14*(Construction!Q32+Construction!Q38+Inputs!$F$107/12+Inputs!Q309*(Inputs!$F$97/100/12-Construction!Q17/100*Construction!Q11/Inputs!$F$247)+Inputs!$F$99*Inputs!$F$100/100*Construction!Q11/Inputs!$F$247+Construction!Q15*$F$17) | ... BJ21: =Construction!BJ14*(Construction!BJ32+Construction!BJ38+Inputs!$F$107/12+Inputs!BJ309*(Inputs!$F$97/100/12-Construction!BJ17/100*Construction!BJ11/Inputs!$F$247)+Inputs!$F$99*Inputs!$F$100/100*Construction!BJ11/Inputs!$F$247+Construction!BJ15*$F$17)
D22: Balance, constant part (alpha) | E22: USD m | J22: =I22+Construction!J14*$F$9/$F$10*(J21+(J19-J20)*I22) | K22: =J22+Construction!K14*$F$9/$F$10*(K21+(K19-K20)*J22) | L22: =K22+Construction!L14*$F$9/$F$10*(L21+(L19-L20)*K22) | M22: =L22+Construction!M14*$F$9/$F$10*(M21+(M19-M20)*L22) | N22: =M22+Construction!N14*$F$9/$F$10*(N21+(N19-N20)*M22) | O22: =N22+Construction!O14*$F$9/$F$10*(O21+(O19-O20)*N22) | P22: =O22+Construction!P14*$F$9/$F$10*(P21+(P19-P20)*O22) | Q22: =P22+Construction!Q14*$F$9/$F$10*(Q21+(Q19-Q20)*P22) | ... BJ22: =BI22+Construction!BJ14*$F$9/$F$10*(BJ21+(BJ19-BJ20)*BI22)
D23: Balance per USD of total funding (beta) | E23: factor | J23: =I23+Construction!J14*$F$9/$F$10*(J19*I23+J20*($F$9-I23)+IF(Construction!J8=1,$F$9*(Inputs!$F$75*Inputs!$F$89/100+Inputs!$F$76*Inputs!$F$90/100+Inputs!$F$77*Inputs!$F$91/100+Inputs!$F$78*Inputs!$F$92/100),0)+Construction!J15*$F$9*(Inputs!$F$75*$F$12+Inputs!$F$76*$F$13+Inputs!$F$77*$F$14+Inputs!$F$78*$F$15)) | K23: =J23+Construction!K14*$F$9/$F$10*(K19*J23+K20*($F$9-J23)+IF(Construction!K8=1,$F$9*(Inputs!$F$75*Inputs!$F$89/100+Inputs!$F$76*Inputs!$F$90/100+Inputs!$F$77*Inputs!$F$91/100+Inputs!$F$78*Inputs!$F$92/100),0)+Construction!K15*$F$9*(Inputs!$F$75*$F$12+Inputs!$F$76*$F$13+Inputs!$F$77*$F$14+Inputs!$F$78*$F$15)) | L23: =K23+Construction!L14*$F$9/$F$10*(L19*K23+L20*($F$9-K23)+IF(Construction!L8=1,$F$9*(Inputs!$F$75*Inputs!$F$89/100+Inputs!$F$76*Inputs!$F$90/100+Inputs!$F$77*Inputs!$F$91/100+Inputs!$F$78*Inputs!$F$92/100),0)+Construction!L15*$F$9*(Inputs!$F$75*$F$12+Inputs!$F$76*$F$13+Inputs!$F$77*$F$14+Inputs!$F$78*$F$15)) | M23: =L23+Construction!M14*$F$9/$F$10*(M19*L23+M20*($F$9-L23)+IF(Construction!M8=1,$F$9*(Inputs!$F$75*Inputs!$F$89/100+Inputs!$F$76*Inputs!$F$90/100+Inputs!$F$77*Inputs!$F$91/100+Inputs!$F$78*Inputs!$F$92/100),0)+Construction!M15*$F$9*(Inputs!$F$75*$F$12+Inputs!$F$76*$F$13+Inputs!$F$77*$F$14+Inputs!$F$78*$F$15)) | N23: =M23+Construction!N14*$F$9/$F$10*(N19*M23+N20*($F$9-M23)+IF(Construction!N8=1,$F$9*(Inputs!$F$75*Inputs!$F$89/100+Inputs!$F$76*Inputs!$F$90/100+Inputs!$F$77*Inputs!$F$91/100+Inputs!$F$78*Inputs!$F$92/100),0)+Construction!N15*$F$9*(Inputs!$F$75*$F$12+Inputs!$F$76*$F$13+Inputs!$F$77*$F$14+Inputs!$F$78*$F$15)) | O23: =N23+Construction!O14*$F$9/$F$10*(O19*N23+O20*($F$9-N23)+IF(Construction!O8=1,$F$9*(Inputs!$F$75*Inputs!$F$89/100+Inputs!$F$76*Inputs!$F$90/100+Inputs!$F$77*Inputs!$F$91/100+Inputs!$F$78*Inputs!$F$92/100),0)+Construction!O15*$F$9*(Inputs!$F$75*$F$12+Inputs!$F$76*$F$13+Inputs!$F$77*$F$14+Inputs!$F$78*$F$15)) | P23: =O23+Construction!P14*$F$9/$F$10*(P19*O23+P20*($F$9-O23)+IF(Construction!P8=1,$F$9*(Inputs!$F$75*Inputs!$F$89/100+Inputs!$F$76*Inputs!$F$90/100+Inputs!$F$77*Inputs!$F$91/100+Inputs!$F$78*Inputs!$F$92/100),0)+Construction!P15*$F$9*(Inputs!$F$75*$F$12+Inputs!$F$76*$F$13+Inputs!$F$77*$F$14+Inputs!$F$78*$F$15)) | Q23: =P23+Construction!Q14*$F$9/$F$10*(Q19*P23+Q20*($F$9-P23)+IF(Construction!Q8=1,$F$9*(Inputs!$F$75*Inputs!$F$89/100+Inputs!$F$76*Inputs!$F$90/100+Inputs!$F$77*Inputs!$F$91/100+Inputs!$F$78*Inputs!$F$92/100),0)+Construction!Q15*$F$9*(Inputs!$F$75*$F$12+Inputs!$F$76*$F$13+Inputs!$F$77*$F$14+Inputs!$F$78*$F$15)) | ... BJ23: =BI23+Construction!BJ14*$F$9/$F$10*(BJ19*BI23+BJ20*($F$9-BI23)+IF(Construction!BJ8=1,$F$9*(Inputs!$F$75*Inputs!$F$89/100+Inputs!$F$76*Inputs!$F$90/100+Inputs!$F$77*Inputs!$F$91/100+Inputs!$F$78*Inputs!$F$92/100),0)+Construction!BJ15*$F$9*(Inputs!$F$75*$F$12+Inputs!$F$76*$F$13+Inputs!$F$77*$F$14+Inputs!$F$78*$F$15))
D24: Total funding requirement at this gearing, closed form T = alpha/(g - beta) | E24: USD m | F24: =INDEX(Funding!$J$22:$BJ$22,1,Time!$F$14)/(Funding!$F$9-INDEX(Funding!$J$23:$BJ$23,1,Time!$F$14))
D25: Senior debt (committed tranches) | E25: USD m | F25: =IF(Inputs!$F$51<>1,Funding!$F$8*Funding!$F$24,Inputs!$F$113)
D26: Debt share of monthly funding | E26: fraction | F26: =$F$8
B27: Monthly funding schedule (USD m)
D28: ECA-covered tranche: opening balance | E28: USD m | J28: =I61 | K28: =J61 | L28: =K61 | M28: =L61 | N28: =M61 | O28: =N61 | P28: =O61 | Q28: =P61 | ... BJ28: =BI61
D29: ABDB A-loan: opening balance | E29: USD m | J29: =I62 | K29: =J62 | L29: =K62 | M29: =L62 | N29: =M62 | O29: =N62 | P29: =O62 | Q29: =P62 | ... BJ29: =BI62
D30: ABDB B-loan: opening balance | E30: USD m | J30: =I63 | K30: =J63 | L30: =K63 | M30: =L63 | N30: =M63 | O30: =N63 | P30: =O63 | Q30: =P63 | ... BJ30: =BI63
D31: Commercial tranche: opening balance | E31: USD m | J31: =I64 | K31: =J64 | L31: =K64 | M31: =L64 | N31: =M64 | O31: =N64 | P31: =O64 | Q31: =P64 | ... BJ31: =BI64
D32: Standby facility: opening balance | E32: USD m | J32: =I65 | K32: =J65 | L32: =K65 | M32: =L65 | N32: =M65 | O32: =N65 | P32: =O65 | Q32: =P65 | ... BJ32: =BI65
D33: ECA-covered tranche: interest | E33: USD m | G33: =SUM(J33:BJ33) | J33: =Construction!J14*J28*(Construction!J17+Inputs!$F$79)/100*Construction!J11/Inputs!$F$247*1 | K33: =Construction!K14*K28*(Construction!K17+Inputs!$F$79)/100*Construction!K11/Inputs!$F$247*1 | L33: =Construction!L14*L28*(Construction!L17+Inputs!$F$79)/100*Construction!L11/Inputs!$F$247*1 | M33: =Construction!M14*M28*(Construction!M17+Inputs!$F$79)/100*Construction!M11/Inputs!$F$247*1 | N33: =Construction!N14*N28*(Construction!N17+Inputs!$F$79)/100*Construction!N11/Inputs!$F$247*1 | O33: =Construction!O14*O28*(Construction!O17+Inputs!$F$79)/100*Construction!O11/Inputs!$F$247*1 | P33: =Construction!P14*P28*(Construction!P17+Inputs!$F$79)/100*Construction!P11/Inputs!$F$247*1 | Q33: =Construction!Q14*Q28*(Construction!Q17+Inputs!$F$79)/100*Construction!Q11/Inputs!$F$247*1 | ... BJ33: =Construction!BJ14*BJ28*(Construction!BJ17+Inputs!$F$79)/100*Construction!BJ11/Inputs!$F$247*1
D34: ABDB A-loan: interest | E34: USD m | G34: =SUM(J34:BJ34) | J34: =Construction!J14*J29*(Construction!J17+Inputs!$F$80)/100*Construction!J11/Inputs!$F$247*1 | K34: =Construction!K14*K29*(Construction!K17+Inputs!$F$80)/100*Construction!K11/Inputs!$F$247*1 | L34: =Construction!L14*L29*(Construction!L17+Inputs!$F$80)/100*Construction!L11/Inputs!$F$247*1 | M34: =Construction!M14*M29*(Construction!M17+Inputs!$F$80)/100*Construction!M11/Inputs!$F$247*1 | N34: =Construction!N14*N29*(Construction!N17+Inputs!$F$80)/100*Construction!N11/Inputs!$F$247*1 | O34: =Construction!O14*O29*(Construction!O17+Inputs!$F$80)/100*Construction!O11/Inputs!$F$247*1 | P34: =Construction!P14*P29*(Construction!P17+Inputs!$F$80)/100*Construction!P11/Inputs!$F$247*1 | Q34: =Construction!Q14*Q29*(Construction!Q17+Inputs!$F$80)/100*Construction!Q11/Inputs!$F$247*1 | ... BJ34: =Construction!BJ14*BJ29*(Construction!BJ17+Inputs!$F$80)/100*Construction!BJ11/Inputs!$F$247*1
D35: ABDB B-loan: interest | E35: USD m | G35: =SUM(J35:BJ35) | J35: =Construction!J14*J30*(Construction!J17+Inputs!$F$81)/100*Construction!J11/Inputs!$F$247*1 | K35: =Construction!K14*K30*(Construction!K17+Inputs!$F$81)/100*Construction!K11/Inputs!$F$247*1 | L35: =Construction!L14*L30*(Construction!L17+Inputs!$F$81)/100*Construction!L11/Inputs!$F$247*1 | M35: =Construction!M14*M30*(Construction!M17+Inputs!$F$81)/100*Construction!M11/Inputs!$F$247*1 | N35: =Construction!N14*N30*(Construction!N17+Inputs!$F$81)/100*Construction!N11/Inputs!$F$247*1 | O35: =Construction!O14*O30*(Construction!O17+Inputs!$F$81)/100*Construction!O11/Inputs!$F$247*1 | P35: =Construction!P14*P30*(Construction!P17+Inputs!$F$81)/100*Construction!P11/Inputs!$F$247*1 | Q35: =Construction!Q14*Q30*(Construction!Q17+Inputs!$F$81)/100*Construction!Q11/Inputs!$F$247*1 | ... BJ35: =Construction!BJ14*BJ30*(Construction!BJ17+Inputs!$F$81)/100*Construction!BJ11/Inputs!$F$247*1
D36: Commercial tranche: interest | E36: USD m | G36: =SUM(J36:BJ36) | J36: =Construction!J14*J31*(Construction!J17+Inputs!$F$82)/100*Construction!J11/Inputs!$F$247*(1/(1-Inputs!$F$93/100)) | K36: =Construction!K14*K31*(Construction!K17+Inputs!$F$82)/100*Construction!K11/Inputs!$F$247*(1/(1-Inputs!$F$93/100)) | L36: =Construction!L14*L31*(Construction!L17+Inputs!$F$82)/100*Construction!L11/Inputs!$F$247*(1/(1-Inputs!$F$93/100)) | M36: =Construction!M14*M31*(Construction!M17+Inputs!$F$82)/100*Construction!M11/Inputs!$F$247*(1/(1-Inputs!$F$93/100)) | N36: =Construction!N14*N31*(Construction!N17+Inputs!$F$82)/100*Construction!N11/Inputs!$F$247*(1/(1-Inputs!$F$93/100)) | O36: =Construction!O14*O31*(Construction!O17+Inputs!$F$82)/100*Construction!O11/Inputs!$F$247*(1/(1-Inputs!$F$93/100)) | P36: =Construction!P14*P31*(Construction!P17+Inputs!$F$82)/100*Construction!P11/Inputs!$F$247*(1/(1-Inputs!$F$93/100)) | Q36: =Construction!Q14*Q31*(Construction!Q17+Inputs!$F$82)/100*Construction!Q11/Inputs!$F$247*(1/(1-Inputs!$F$93/100)) | ... BJ36: =Construction!BJ14*BJ31*(Construction!BJ17+Inputs!$F$82)/100*Construction!BJ11/Inputs!$F$247*(1/(1-Inputs!$F$93/100))
D37: Standby facility: interest | E37: USD m | G37: =SUM(J37:BJ37) | J37: =Construction!J14*J32*(Inputs!$F$102*(Construction!J17+Inputs!$F$82+Inputs!$F$101)/(1-Inputs!$F$93/100)+(1-Inputs!$F$102)*(Construction!J17+Inputs!$F$80+Inputs!$F$101))/100*Construction!J11/Inputs!$F$247 | K37: =Construction!K14*K32*(Inputs!$F$102*(Construction!K17+Inputs!$F$82+Inputs!$F$101)/(1-Inputs!$F$93/100)+(1-Inputs!$F$102)*(Construction!K17+Inputs!$F$80+Inputs!$F$101))/100*Construction!K11/Inputs!$F$247 | L37: =Construction!L14*L32*(Inputs!$F$102*(Construction!L17+Inputs!$F$82+Inputs!$F$101)/(1-Inputs!$F$93/100)+(1-Inputs!$F$102)*(Construction!L17+Inputs!$F$80+Inputs!$F$101))/100*Construction!L11/Inputs!$F$247 | M37: =Construction!M14*M32*(Inputs!$F$102*(Construction!M17+Inputs!$F$82+Inputs!$F$101)/(1-Inputs!$F$93/100)+(1-Inputs!$F$102)*(Construction!M17+Inputs!$F$80+Inputs!$F$101))/100*Construction!M11/Inputs!$F$247 | N37: =Construction!N14*N32*(Inputs!$F$102*(Construction!N17+Inputs!$F$82+Inputs!$F$101)/(1-Inputs!$F$93/100)+(1-Inputs!$F$102)*(Construction!N17+Inputs!$F$80+Inputs!$F$101))/100*Construction!N11/Inputs!$F$247 | O37: =Construction!O14*O32*(Inputs!$F$102*(Construction!O17+Inputs!$F$82+Inputs!$F$101)/(1-Inputs!$F$93/100)+(1-Inputs!$F$102)*(Construction!O17+Inputs!$F$80+Inputs!$F$101))/100*Construction!O11/Inputs!$F$247 | P37: =Construction!P14*P32*(Inputs!$F$102*(Construction!P17+Inputs!$F$82+Inputs!$F$101)/(1-Inputs!$F$93/100)+(1-Inputs!$F$102)*(Construction!P17+Inputs!$F$80+Inputs!$F$101))/100*Construction!P11/Inputs!$F$247 | Q37: =Construction!Q14*Q32*(Inputs!$F$102*(Construction!Q17+Inputs!$F$82+Inputs!$F$101)/(1-Inputs!$F$93/100)+(1-Inputs!$F$102)*(Construction!Q17+Inputs!$F$80+Inputs!$F$101))/100*Construction!Q11/Inputs!$F$247 | ... BJ37: =Construction!BJ14*BJ32*(Inputs!$F$102*(Construction!BJ17+Inputs!$F$82+Inputs!$F$101)/(1-Inputs!$F$93/100)+(1-Inputs!$F$102)*(Construction!BJ17+Inputs!$F$80+Inputs!$F$101))/100*Construction!BJ11/Inputs!$F$247
D38: PRI premium on commercial tranche | E38: USD m | G38: =SUM(J38:BJ38) | J38: =Construction!J14*(Inputs!$F$95/100*Inputs!$F$96/100)*J31*Construction!J11/Inputs!$F$248 | K38: =Construction!K14*(Inputs!$F$95/100*Inputs!$F$96/100)*K31*Construction!K11/Inputs!$F$248 | L38: =Construction!L14*(Inputs!$F$95/100*Inputs!$F$96/100)*L31*Construction!L11/Inputs!$F$248 | M38: =Construction!M14*(Inputs!$F$95/100*Inputs!$F$96/100)*M31*Construction!M11/Inputs!$F$248 | N38: =Construction!N14*(Inputs!$F$95/100*Inputs!$F$96/100)*N31*Construction!N11/Inputs!$F$248 | O38: =Construction!O14*(Inputs!$F$95/100*Inputs!$F$96/100)*O31*Construction!O11/Inputs!$F$248 | P38: =Construction!P14*(Inputs!$F$95/100*Inputs!$F$96/100)*P31*Construction!P11/Inputs!$F$248 | Q38: =Construction!Q14*(Inputs!$F$95/100*Inputs!$F$96/100)*Q31*Construction!Q11/Inputs!$F$248 | ... BJ38: =Construction!BJ14*(Inputs!$F$95/100*Inputs!$F$96/100)*BJ31*Construction!BJ11/Inputs!$F$248
D39: Swap net payment | E39: USD m | G39: =SUM(J39:BJ39) | J39: =Construction!J14*Inputs!J309*(Inputs!$F$97/100/12-Construction!J17/100*Construction!J11/Inputs!$F$247) | K39: =Construction!K14*Inputs!K309*(Inputs!$F$97/100/12-Construction!K17/100*Construction!K11/Inputs!$F$247) | L39: =Construction!L14*Inputs!L309*(Inputs!$F$97/100/12-Construction!L17/100*Construction!L11/Inputs!$F$247) | M39: =Construction!M14*Inputs!M309*(Inputs!$F$97/100/12-Construction!M17/100*Construction!M11/Inputs!$F$247) | N39: =Construction!N14*Inputs!N309*(Inputs!$F$97/100/12-Construction!N17/100*Construction!N11/Inputs!$F$247) | O39: =Construction!O14*Inputs!O309*(Inputs!$F$97/100/12-Construction!O17/100*Construction!O11/Inputs!$F$247) | P39: =Construction!P14*Inputs!P309*(Inputs!$F$97/100/12-Construction!P17/100*Construction!P11/Inputs!$F$247) | Q39: =Construction!Q14*Inputs!Q309*(Inputs!$F$97/100/12-Construction!Q17/100*Construction!Q11/Inputs!$F$247) | ... BJ39: =Construction!BJ14*Inputs!BJ309*(Inputs!$F$97/100/12-Construction!BJ17/100*Construction!BJ11/Inputs!$F$247)
D40: Commitment fees, senior tranches | E40: USD m | G40: =SUM(J40:BJ40) | J40: =Construction!J14*((Inputs!$F$75*$F$25-J28)*Inputs!$F$85/100+(Inputs!$F$76*$F$25-J29)*Inputs!$F$86/100+(Inputs!$F$77*$F$25-J30)*Inputs!$F$87/100+(Inputs!$F$78*$F$25-J31)*(Inputs!$F$88/100*Inputs!$F$82)/100)*Construction!J11/Inputs!$F$247 | K40: =Construction!K14*((Inputs!$F$75*$F$25-K28)*Inputs!$F$85/100+(Inputs!$F$76*$F$25-K29)*Inputs!$F$86/100+(Inputs!$F$77*$F$25-K30)*Inputs!$F$87/100+(Inputs!$F$78*$F$25-K31)*(Inputs!$F$88/100*Inputs!$F$82)/100)*Construction!K11/Inputs!$F$247 | L40: =Construction!L14*((Inputs!$F$75*$F$25-L28)*Inputs!$F$85/100+(Inputs!$F$76*$F$25-L29)*Inputs!$F$86/100+(Inputs!$F$77*$F$25-L30)*Inputs!$F$87/100+(Inputs!$F$78*$F$25-L31)*(Inputs!$F$88/100*Inputs!$F$82)/100)*Construction!L11/Inputs!$F$247 | M40: =Construction!M14*((Inputs!$F$75*$F$25-M28)*Inputs!$F$85/100+(Inputs!$F$76*$F$25-M29)*Inputs!$F$86/100+(Inputs!$F$77*$F$25-M30)*Inputs!$F$87/100+(Inputs!$F$78*$F$25-M31)*(Inputs!$F$88/100*Inputs!$F$82)/100)*Construction!M11/Inputs!$F$247 | N40: =Construction!N14*((Inputs!$F$75*$F$25-N28)*Inputs!$F$85/100+(Inputs!$F$76*$F$25-N29)*Inputs!$F$86/100+(Inputs!$F$77*$F$25-N30)*Inputs!$F$87/100+(Inputs!$F$78*$F$25-N31)*(Inputs!$F$88/100*Inputs!$F$82)/100)*Construction!N11/Inputs!$F$247 | O40: =Construction!O14*((Inputs!$F$75*$F$25-O28)*Inputs!$F$85/100+(Inputs!$F$76*$F$25-O29)*Inputs!$F$86/100+(Inputs!$F$77*$F$25-O30)*Inputs!$F$87/100+(Inputs!$F$78*$F$25-O31)*(Inputs!$F$88/100*Inputs!$F$82)/100)*Construction!O11/Inputs!$F$247 | P40: =Construction!P14*((Inputs!$F$75*$F$25-P28)*Inputs!$F$85/100+(Inputs!$F$76*$F$25-P29)*Inputs!$F$86/100+(Inputs!$F$77*$F$25-P30)*Inputs!$F$87/100+(Inputs!$F$78*$F$25-P31)*(Inputs!$F$88/100*Inputs!$F$82)/100)*Construction!P11/Inputs!$F$247 | Q40: =Construction!Q14*((Inputs!$F$75*$F$25-Q28)*Inputs!$F$85/100+(Inputs!$F$76*$F$25-Q29)*Inputs!$F$86/100+(Inputs!$F$77*$F$25-Q30)*Inputs!$F$87/100+(Inputs!$F$78*$F$25-Q31)*(Inputs!$F$88/100*Inputs!$F$82)/100)*Construction!Q11/Inputs!$F$247 | ... BJ40: =Construction!BJ14*((Inputs!$F$75*$F$25-BJ28)*Inputs!$F$85/100+(Inputs!$F$76*$F$25-BJ29)*Inputs!$F$86/100+(Inputs!$F$77*$F$25-BJ30)*Inputs!$F$87/100+(Inputs!$F$78*$F$25-BJ31)*(Inputs!$F$88/100*Inputs!$F$82)/100)*Construction!BJ11/Inputs!$F$247
D41: Commitment fee, standby facility | E41: USD m | G41: =SUM(J41:BJ41) | J41: =Construction!J14*(Inputs!$F$99-J32)*Inputs!$F$100/100*Construction!J11/Inputs!$F$247 | K41: =Construction!K14*(Inputs!$F$99-K32)*Inputs!$F$100/100*Construction!K11/Inputs!$F$247 | L41: =Construction!L14*(Inputs!$F$99-L32)*Inputs!$F$100/100*Construction!L11/Inputs!$F$247 | M41: =Construction!M14*(Inputs!$F$99-M32)*Inputs!$F$100/100*Construction!M11/Inputs!$F$247 | N41: =Construction!N14*(Inputs!$F$99-N32)*Inputs!$F$100/100*Construction!N11/Inputs!$F$247 | O41: =Construction!O14*(Inputs!$F$99-O32)*Inputs!$F$100/100*Construction!O11/Inputs!$F$247 | P41: =Construction!P14*(Inputs!$F$99-P32)*Inputs!$F$100/100*Construction!P11/Inputs!$F$247 | Q41: =Construction!Q14*(Inputs!$F$99-Q32)*Inputs!$F$100/100*Construction!Q11/Inputs!$F$247 | ... BJ41: =Construction!BJ14*(Inputs!$F$99-BJ32)*Inputs!$F$100/100*Construction!BJ11/Inputs!$F$247
D42: Upfront and arrangement fees | E42: USD m | G42: =SUM(J42:BJ42) | J42: =IF(Construction!J8=1,Inputs!$F$75*$F$25*Inputs!$F$89/100+Inputs!$F$76*$F$25*Inputs!$F$90/100+Inputs!$F$77*$F$25*Inputs!$F$91/100+Inputs!$F$78*$F$25*Inputs!$F$92/100,0) | K42: =IF(Construction!K8=1,Inputs!$F$75*$F$25*Inputs!$F$89/100+Inputs!$F$76*$F$25*Inputs!$F$90/100+Inputs!$F$77*$F$25*Inputs!$F$91/100+Inputs!$F$78*$F$25*Inputs!$F$92/100,0) | L42: =IF(Construction!L8=1,Inputs!$F$75*$F$25*Inputs!$F$89/100+Inputs!$F$76*$F$25*Inputs!$F$90/100+Inputs!$F$77*$F$25*Inputs!$F$91/100+Inputs!$F$78*$F$25*Inputs!$F$92/100,0) | M42: =IF(Construction!M8=1,Inputs!$F$75*$F$25*Inputs!$F$89/100+Inputs!$F$76*$F$25*Inputs!$F$90/100+Inputs!$F$77*$F$25*Inputs!$F$91/100+Inputs!$F$78*$F$25*Inputs!$F$92/100,0) | N42: =IF(Construction!N8=1,Inputs!$F$75*$F$25*Inputs!$F$89/100+Inputs!$F$76*$F$25*Inputs!$F$90/100+Inputs!$F$77*$F$25*Inputs!$F$91/100+Inputs!$F$78*$F$25*Inputs!$F$92/100,0) | O42: =IF(Construction!O8=1,Inputs!$F$75*$F$25*Inputs!$F$89/100+Inputs!$F$76*$F$25*Inputs!$F$90/100+Inputs!$F$77*$F$25*Inputs!$F$91/100+Inputs!$F$78*$F$25*Inputs!$F$92/100,0) | P42: =IF(Construction!P8=1,Inputs!$F$75*$F$25*Inputs!$F$89/100+Inputs!$F$76*$F$25*Inputs!$F$90/100+Inputs!$F$77*$F$25*Inputs!$F$91/100+Inputs!$F$78*$F$25*Inputs!$F$92/100,0) | Q42: =IF(Construction!Q8=1,Inputs!$F$75*$F$25*Inputs!$F$89/100+Inputs!$F$76*$F$25*Inputs!$F$90/100+Inputs!$F$77*$F$25*Inputs!$F$91/100+Inputs!$F$78*$F$25*Inputs!$F$92/100,0) | ... BJ42: =IF(Construction!BJ8=1,Inputs!$F$75*$F$25*Inputs!$F$89/100+Inputs!$F$76*$F$25*Inputs!$F$90/100+Inputs!$F$77*$F$25*Inputs!$F$91/100+Inputs!$F$78*$F$25*Inputs!$F$92/100,0)
D43: Agency fees during construction | E43: USD m | G43: =SUM(J43:BJ43) | J43: =Construction!J14*Inputs!$F$107/12 | K43: =Construction!K14*Inputs!$F$107/12 | L43: =Construction!L14*Inputs!$F$107/12 | M43: =Construction!M14*Inputs!$F$107/12 | N43: =Construction!N14*Inputs!$F$107/12 | O43: =Construction!O14*Inputs!$F$107/12 | P43: =Construction!P14*Inputs!$F$107/12 | Q43: =Construction!Q14*Inputs!$F$107/12 | ... BJ43: =Construction!BJ14*Inputs!$F$107/12
D44: DSRA initial funding (COD month) | E44: USD m | G44: =SUM(J44:BJ44) | J44: =Construction!J15*IF(Inputs!$F$34=1,$F$12*Inputs!$F$75*$F$25+$F$13*Inputs!$F$76*$F$25+$F$14*Inputs!$F$77*$F$25+$F$15*Inputs!$F$78*$F$25+$F$17,$F$12*J28+$F$13*J29+$F$14*J30+$F$15*J31+$F$16*J32+$F$17) | K44: =Construction!K15*IF(Inputs!$F$34=1,$F$12*Inputs!$F$75*$F$25+$F$13*Inputs!$F$76*$F$25+$F$14*Inputs!$F$77*$F$25+$F$15*Inputs!$F$78*$F$25+$F$17,$F$12*K28+$F$13*K29+$F$14*K30+$F$15*K31+$F$16*K32+$F$17) | L44: =Construction!L15*IF(Inputs!$F$34=1,$F$12*Inputs!$F$75*$F$25+$F$13*Inputs!$F$76*$F$25+$F$14*Inputs!$F$77*$F$25+$F$15*Inputs!$F$78*$F$25+$F$17,$F$12*L28+$F$13*L29+$F$14*L30+$F$15*L31+$F$16*L32+$F$17) | M44: =Construction!M15*IF(Inputs!$F$34=1,$F$12*Inputs!$F$75*$F$25+$F$13*Inputs!$F$76*$F$25+$F$14*Inputs!$F$77*$F$25+$F$15*Inputs!$F$78*$F$25+$F$17,$F$12*M28+$F$13*M29+$F$14*M30+$F$15*M31+$F$16*M32+$F$17) | N44: =Construction!N15*IF(Inputs!$F$34=1,$F$12*Inputs!$F$75*$F$25+$F$13*Inputs!$F$76*$F$25+$F$14*Inputs!$F$77*$F$25+$F$15*Inputs!$F$78*$F$25+$F$17,$F$12*N28+$F$13*N29+$F$14*N30+$F$15*N31+$F$16*N32+$F$17) | O44: =Construction!O15*IF(Inputs!$F$34=1,$F$12*Inputs!$F$75*$F$25+$F$13*Inputs!$F$76*$F$25+$F$14*Inputs!$F$77*$F$25+$F$15*Inputs!$F$78*$F$25+$F$17,$F$12*O28+$F$13*O29+$F$14*O30+$F$15*O31+$F$16*O32+$F$17) | P44: =Construction!P15*IF(Inputs!$F$34=1,$F$12*Inputs!$F$75*$F$25+$F$13*Inputs!$F$76*$F$25+$F$14*Inputs!$F$77*$F$25+$F$15*Inputs!$F$78*$F$25+$F$17,$F$12*P28+$F$13*P29+$F$14*P30+$F$15*P31+$F$16*P32+$F$17) | Q44: =Construction!Q15*IF(Inputs!$F$34=1,$F$12*Inputs!$F$75*$F$25+$F$13*Inputs!$F$76*$F$25+$F$14*Inputs!$F$77*$F$25+$F$15*Inputs!$F$78*$F$25+$F$17,$F$12*Q28+$F$13*Q29+$F$14*Q30+$F$15*Q31+$F$16*Q32+$F$17) | ... BJ44: =Construction!BJ15*IF(Inputs!$F$34=1,$F$12*Inputs!$F$75*$F$25+$F$13*Inputs!$F$76*$F$25+$F$14*Inputs!$F$77*$F$25+$F$15*Inputs!$F$78*$F$25+$F$17,$F$12*BJ28+$F$13*BJ29+$F$14*BJ30+$F$15*BJ31+$F$16*BJ32+$F$17)
D45: Uses before ECA premium | E45: USD m | J45: =Construction!J14*(Construction!J32+Construction!J38)+J33+J34+J35+J36+J37+J38+J39+J40+J41+J42+J43+J44 | K45: =Construction!K14*(Construction!K32+Construction!K38)+K33+K34+K35+K36+K37+K38+K39+K40+K41+K42+K43+K44 | L45: =Construction!L14*(Construction!L32+Construction!L38)+L33+L34+L35+L36+L37+L38+L39+L40+L41+L42+L43+L44 | M45: =Construction!M14*(Construction!M32+Construction!M38)+M33+M34+M35+M36+M37+M38+M39+M40+M41+M42+M43+M44 | N45: =Construction!N14*(Construction!N32+Construction!N38)+N33+N34+N35+N36+N37+N38+N39+N40+N41+N42+N43+N44 | O45: =Construction!O14*(Construction!O32+Construction!O38)+O33+O34+O35+O36+O37+O38+O39+O40+O41+O42+O43+O44 | P45: =Construction!P14*(Construction!P32+Construction!P38)+P33+P34+P35+P36+P37+P38+P39+P40+P41+P42+P43+P44 | Q45: =Construction!Q14*(Construction!Q32+Construction!Q38)+Q33+Q34+Q35+Q36+Q37+Q38+Q39+Q40+Q41+Q42+Q43+Q44 | ... BJ45: =Construction!BJ14*(Construction!BJ32+Construction!BJ38)+BJ33+BJ34+BJ35+BJ36+BJ37+BJ38+BJ39+BJ40+BJ41+BJ42+BJ43+BJ44
D46: Headroom on committed senior tranches | E46: USD m | J46: =$F$25-J28-J29-J30-J31 | K46: =$F$25-K28-K29-K30-K31 | L46: =$F$25-L28-L29-L30-L31 | M46: =$F$25-M28-M29-M30-M31 | N46: =$F$25-N28-N29-N30-N31 | O46: =$F$25-O28-O29-O30-O31 | P46: =$F$25-P28-P29-P30-P31 | Q46: =$F$25-Q28-Q29-Q30-Q31 | ... BJ46: =$F$25-BJ28-BJ29-BJ30-BJ31
D47: Senior tranche drawdown (pro rata) | E47: USD m | G47: =SUM(J47:BJ47) | J47: =MIN($F$26*J45/(1-Inputs!$F$94/100*Inputs!$F$75*$F$26),J46) | K47: =MIN($F$26*K45/(1-Inputs!$F$94/100*Inputs!$F$75*$F$26),K46) | L47: =MIN($F$26*L45/(1-Inputs!$F$94/100*Inputs!$F$75*$F$26),L46) | M47: =MIN($F$26*M45/(1-Inputs!$F$94/100*Inputs!$F$75*$F$26),M46) | N47: =MIN($F$26*N45/(1-Inputs!$F$94/100*Inputs!$F$75*$F$26),N46) | O47: =MIN($F$26*O45/(1-Inputs!$F$94/100*Inputs!$F$75*$F$26),O46) | P47: =MIN($F$26*P45/(1-Inputs!$F$94/100*Inputs!$F$75*$F$26),P46) | Q47: =MIN($F$26*Q45/(1-Inputs!$F$94/100*Inputs!$F$75*$F$26),Q46) | ... BJ47: =MIN($F$26*BJ45/(1-Inputs!$F$94/100*Inputs!$F$75*$F$26),BJ46)
D48: ECA premium (financed) | E48: USD m | G48: =SUM(J48:BJ48) | J48: =Inputs!$F$94/100*Inputs!$F$75*J47 | K48: =Inputs!$F$94/100*Inputs!$F$75*K47 | L48: =Inputs!$F$94/100*Inputs!$F$75*L47 | M48: =Inputs!$F$94/100*Inputs!$F$75*M47 | N48: =Inputs!$F$94/100*Inputs!$F$75*N47 | O48: =Inputs!$F$94/100*Inputs!$F$75*O47 | P48: =Inputs!$F$94/100*Inputs!$F$75*P47 | Q48: =Inputs!$F$94/100*Inputs!$F$75*Q47 | ... BJ48: =Inputs!$F$94/100*Inputs!$F$75*BJ47
D49: Total uses of funds | E49: USD m | G49: =SUM(J49:BJ49) | J49: =J45+J48 | K49: =K45+K48 | L49: =L45+L48 | M49: =M45+M48 | N49: =N45+N48 | O49: =O45+O48 | P49: =P45+P48 | Q49: =Q45+Q48 | ... BJ49: =BJ45+BJ48
D50: Funded pro rata from committed debt and equity | E50: USD m | G50: =SUM(J50:BJ50) | J50: =J47/$F$26 | K50: =K47/$F$26 | L50: =L47/$F$26 | M50: =M47/$F$26 | N50: =N47/$F$26 | O50: =O47/$F$26 | P50: =P47/$F$26 | Q50: =Q47/$F$26 | ... BJ50: =BJ47/$F$26
D51: Remaining uses after committed facilities | E51: USD m | J51: =J49-J50 | K51: =K49-K50 | L51: =L49-L50 | M51: =M49-M50 | N51: =N49-N50 | O51: =O49-O50 | P51: =P49-P50 | Q51: =Q49-Q50 | ... BJ51: =BJ49-BJ50
D52: Delay LDs and DSU proceeds received | E52: USD m | G52: =SUM(J52:BJ52) | J52: =IF(AND(Inputs!$F$34<>1,Construction!J8=Inputs!$F$245),Inputs!$F$265+Inputs!$F$266,0) | K52: =IF(AND(Inputs!$F$34<>1,Construction!K8=Inputs!$F$245),Inputs!$F$265+Inputs!$F$266,0) | L52: =IF(AND(Inputs!$F$34<>1,Construction!L8=Inputs!$F$245),Inputs!$F$265+Inputs!$F$266,0) | M52: =IF(AND(Inputs!$F$34<>1,Construction!M8=Inputs!$F$245),Inputs!$F$265+Inputs!$F$266,0) | N52: =IF(AND(Inputs!$F$34<>1,Construction!N8=Inputs!$F$245),Inputs!$F$265+Inputs!$F$266,0) | O52: =IF(AND(Inputs!$F$34<>1,Construction!O8=Inputs!$F$245),Inputs!$F$265+Inputs!$F$266,0) | P52: =IF(AND(Inputs!$F$34<>1,Construction!P8=Inputs!$F$245),Inputs!$F$265+Inputs!$F$266,0) | Q52: =IF(AND(Inputs!$F$34<>1,Construction!Q8=Inputs!$F$245),Inputs!$F$265+Inputs!$F$266,0) | ... BJ52: =IF(AND(Inputs!$F$34<>1,Construction!BJ8=Inputs!$F$245),Inputs!$F$265+Inputs!$F$266,0)
D53: LD and DSU proceeds applied | E53: USD m | G53: =SUM(J53:BJ53) | J53: =MIN(J51,I54+J52) | K53: =MIN(K51,J54+K52) | L53: =MIN(L51,K54+L52) | M53: =MIN(M51,L54+M52) | N53: =MIN(N51,M54+N52) | O53: =MIN(O51,N54+O52) | P53: =MIN(P51,O54+P52) | Q53: =MIN(Q51,P54+Q52) | ... BJ53: =MIN(BJ51,BI54+BJ52)
D54: LD and DSU proceeds held (Proceeds Account) | E54: USD m | J54: =I54+J52-J53 | K54: =J54+K52-K53 | L54: =K54+L52-L53 | M54: =L54+M52-M53 | N54: =M54+N52-N53 | O54: =N54+O52-O53 | P54: =O54+P52-P53 | Q54: =P54+Q52-Q53 | ... BJ54: =BI54+BJ52-BJ53
D55: Standby facility drawdown (75%) | E55: USD m | G55: =SUM(J55:BJ55) | J55: =Inputs!$F$249*(J51-J53) | K55: =Inputs!$F$249*(K51-K53) | L55: =Inputs!$F$249*(L51-L53) | M55: =Inputs!$F$249*(M51-M53) | N55: =Inputs!$F$249*(N51-N53) | O55: =Inputs!$F$249*(O51-O53) | P55: =Inputs!$F$249*(P51-P53) | Q55: =Inputs!$F$249*(Q51-Q53) | ... BJ55: =Inputs!$F$249*(BJ51-BJ53)
D56: Contingent equity (25%) | E56: USD m | G56: =SUM(J56:BJ56) | J56: =(1-Inputs!$F$249)*(J51-J53) | K56: =(1-Inputs!$F$249)*(K51-K53) | L56: =(1-Inputs!$F$249)*(L51-L53) | M56: =(1-Inputs!$F$249)*(M51-M53) | N56: =(1-Inputs!$F$249)*(N51-N53) | O56: =(1-Inputs!$F$249)*(O51-O53) | P56: =(1-Inputs!$F$249)*(P51-P53) | Q56: =(1-Inputs!$F$249)*(Q51-Q53) | ... BJ56: =(1-Inputs!$F$249)*(BJ51-BJ53)
D57: ECA-covered tranche: drawdown | E57: USD m | G57: =SUM(J57:BJ57) | J57: =Inputs!$F$75*J47 | K57: =Inputs!$F$75*K47 | L57: =Inputs!$F$75*L47 | M57: =Inputs!$F$75*M47 | N57: =Inputs!$F$75*N47 | O57: =Inputs!$F$75*O47 | P57: =Inputs!$F$75*P47 | Q57: =Inputs!$F$75*Q47 | ... BJ57: =Inputs!$F$75*BJ47
D58: ABDB A-loan: drawdown | E58: USD m | G58: =SUM(J58:BJ58) | J58: =Inputs!$F$76*J47 | K58: =Inputs!$F$76*K47 | L58: =Inputs!$F$76*L47 | M58: =Inputs!$F$76*M47 | N58: =Inputs!$F$76*N47 | O58: =Inputs!$F$76*O47 | P58: =Inputs!$F$76*P47 | Q58: =Inputs!$F$76*Q47 | ... BJ58: =Inputs!$F$76*BJ47
D59: ABDB B-loan: drawdown | E59: USD m | G59: =SUM(J59:BJ59) | J59: =Inputs!$F$77*J47 | K59: =Inputs!$F$77*K47 | L59: =Inputs!$F$77*L47 | M59: =Inputs!$F$77*M47 | N59: =Inputs!$F$77*N47 | O59: =Inputs!$F$77*O47 | P59: =Inputs!$F$77*P47 | Q59: =Inputs!$F$77*Q47 | ... BJ59: =Inputs!$F$77*BJ47
D60: Commercial tranche: drawdown | E60: USD m | G60: =SUM(J60:BJ60) | J60: =Inputs!$F$78*J47 | K60: =Inputs!$F$78*K47 | L60: =Inputs!$F$78*L47 | M60: =Inputs!$F$78*M47 | N60: =Inputs!$F$78*N47 | O60: =Inputs!$F$78*O47 | P60: =Inputs!$F$78*P47 | Q60: =Inputs!$F$78*Q47 | ... BJ60: =Inputs!$F$78*BJ47
D61: ECA-covered tranche: closing balance | E61: USD m | J61: =J28+J57 | K61: =K28+K57 | L61: =L28+L57 | M61: =M28+M57 | N61: =N28+N57 | O61: =O28+O57 | P61: =P28+P57 | Q61: =Q28+Q57 | ... BJ61: =BJ28+BJ57
D62: ABDB A-loan: closing balance | E62: USD m | J62: =J29+J58 | K62: =K29+K58 | L62: =L29+L58 | M62: =M29+M58 | N62: =N29+N58 | O62: =O29+O58 | P62: =P29+P58 | Q62: =Q29+Q58 | ... BJ62: =BJ29+BJ58
D63: ABDB B-loan: closing balance | E63: USD m | J63: =J30+J59 | K63: =K30+K59 | L63: =L30+L59 | M63: =M30+M59 | N63: =N30+N59 | O63: =O30+O59 | P63: =P30+P59 | Q63: =Q30+Q59 | ... BJ63: =BJ30+BJ59
D64: Commercial tranche: closing balance | E64: USD m | J64: =J31+J60 | K64: =K31+K60 | L64: =L31+L60 | M64: =M31+M60 | N64: =N31+N60 | O64: =O31+O60 | P64: =P31+P60 | Q64: =Q31+Q60 | ... BJ64: =BJ31+BJ60
D65: Standby facility: closing balance | E65: USD m | J65: =J32+J55 | K65: =K32+K55 | L65: =L32+L55 | M65: =M32+M55 | N65: =N32+N55 | O65: =O32+O55 | P65: =P32+P55 | Q65: =Q32+Q55 | ... BJ65: =BJ32+BJ55
B66: Equity (USD m)
D67: Equity contributions (incl. LNTP credit in month 1) | E67: USD m | G67: =SUM(J67:BJ67) | J67: =J50-J47+J56 | K67: =K50-K47+K56 | L67: =L50-L47+L56 | M67: =M50-M47+M56 | N67: =N50-N47+N56 | O67: =O50-O47+O56 | P67: =P50-P47+P56 | Q67: =Q50-Q47+Q56 | ... BJ67: =BJ50-BJ47+BJ56
D68: Equity contributed in cash | E68: USD m | G68: =SUM(J68:BJ68) | J68: =J67-IF(Construction!J8=1,Inputs!$F$68,0) | K68: =K67-IF(Construction!K8=1,Inputs!$F$68,0) | L68: =L67-IF(Construction!L8=1,Inputs!$F$68,0) | M68: =M67-IF(Construction!M8=1,Inputs!$F$68,0) | N68: =N67-IF(Construction!N8=1,Inputs!$F$68,0) | O68: =O67-IF(Construction!O8=1,Inputs!$F$68,0) | P68: =P67-IF(Construction!P8=1,Inputs!$F$68,0) | Q68: =Q67-IF(Construction!Q8=1,Inputs!$F$68,0) | ... BJ68: =BJ67-IF(Construction!BJ8=1,Inputs!$F$68,0)
D69: Share capital | E69: USD m | G69: =SUM(J69:BJ69) | J69: =(1-Inputs!$F$53)*J67 | K69: =(1-Inputs!$F$53)*K67 | L69: =(1-Inputs!$F$53)*L67 | M69: =(1-Inputs!$F$53)*M67 | N69: =(1-Inputs!$F$53)*N67 | O69: =(1-Inputs!$F$53)*O67 | P69: =(1-Inputs!$F$53)*P67 | Q69: =(1-Inputs!$F$53)*Q67 | ... BJ69: =(1-Inputs!$F$53)*BJ67
D70: Shareholder loans advanced | E70: USD m | G70: =SUM(J70:BJ70) | J70: =Inputs!$F$53*J67 | K70: =Inputs!$F$53*K67 | L70: =Inputs!$F$53*L67 | M70: =Inputs!$F$53*M67 | N70: =Inputs!$F$53*N67 | O70: =Inputs!$F$53*O67 | P70: =Inputs!$F$53*P67 | Q70: =Inputs!$F$53*Q67 | ... BJ70: =Inputs!$F$53*BJ67
D71: Shareholder loan interest capitalized (to COD) | E71: USD m | G71: =SUM(J71:BJ71) | J71: =IF(Construction!J8<=Time!$F$11,I72*Inputs!$F$104/100*Construction!J11/Inputs!$F$248,0) | K71: =IF(Construction!K8<=Time!$F$11,J72*Inputs!$F$104/100*Construction!K11/Inputs!$F$248,0) | L71: =IF(Construction!L8<=Time!$F$11,K72*Inputs!$F$104/100*Construction!L11/Inputs!$F$248,0) | M71: =IF(Construction!M8<=Time!$F$11,L72*Inputs!$F$104/100*Construction!M11/Inputs!$F$248,0) | N71: =IF(Construction!N8<=Time!$F$11,M72*Inputs!$F$104/100*Construction!N11/Inputs!$F$248,0) | O71: =IF(Construction!O8<=Time!$F$11,N72*Inputs!$F$104/100*Construction!O11/Inputs!$F$248,0) | P71: =IF(Construction!P8<=Time!$F$11,O72*Inputs!$F$104/100*Construction!P11/Inputs!$F$248,0) | Q71: =IF(Construction!Q8<=Time!$F$11,P72*Inputs!$F$104/100*Construction!Q11/Inputs!$F$248,0) | ... BJ71: =IF(Construction!BJ8<=Time!$F$11,BI72*Inputs!$F$104/100*Construction!BJ11/Inputs!$F$248,0)
D72: Shareholder loan balance | E72: USD m | J72: =I72+J71+J70 | K72: =J72+K71+K70 | L72: =K72+L71+L70 | M72: =L72+M71+M70 | N72: =M72+N71+N70 | O72: =N72+O71+O70 | P72: =O72+P71+P70 | Q72: =P72+Q71+Q70 | ... BJ72: =BI72+BJ71+BJ70
D73: Total debt drawdowns (incl. standby) | E73: USD m | G73: =SUM(J73:BJ73) | J73: =J47+J55 | K73: =K47+K55 | L73: =L47+L55 | M73: =M47+M55 | N73: =N47+N55 | O73: =O47+O55 | P73: =P47+P55 | Q73: =Q47+Q55 | ... BJ73: =BJ47+BJ55
D74: Financing costs (IDC, fees, premium, VAT interest) | E74: USD m | G74: =SUM(J74:BJ74) | J74: =J33+J34+J35+J36+J37+J38+J39+J40+J41+J42+J43+J48+Construction!J14*Construction!J38 | K74: =K33+K34+K35+K36+K37+K38+K39+K40+K41+K42+K43+K48+Construction!K14*Construction!K38 | L74: =L33+L34+L35+L36+L37+L38+L39+L40+L41+L42+L43+L48+Construction!L14*Construction!L38 | M74: =M33+M34+M35+M36+M37+M38+M39+M40+M41+M42+M43+M48+Construction!M14*Construction!M38 | N74: =N33+N34+N35+N36+N37+N38+N39+N40+N41+N42+N43+N48+Construction!N14*Construction!N38 | O74: =O33+O34+O35+O36+O37+O38+O39+O40+O41+O42+O43+O48+Construction!O14*Construction!O38 | P74: =P33+P34+P35+P36+P37+P38+P39+P40+P41+P42+P43+P48+Construction!P14*Construction!P38 | Q74: =Q33+Q34+Q35+Q36+Q37+Q38+Q39+Q40+Q41+Q42+Q43+Q48+Construction!Q14*Construction!Q38 | ... BJ74: =BJ33+BJ34+BJ35+BJ36+BJ37+BJ38+BJ39+BJ40+BJ41+BJ42+BJ43+BJ48+Construction!BJ14*Construction!BJ38
D75: Total funding requirement (sum of uses) | E75: USD m | F75: =SUM(Funding!$J$49:$BJ$49)
D76: Capitalized cost (book and tax) | E76: USD m | F76: =SUM(Funding!$J$49:$BJ$49)-SUM(Funding!$J$44:$BJ$44)-SUM(Construction!$J$28:$BJ$28)+SUM(Funding!$J$71:$BJ$71)-SUM(Funding!$J$52:$BJ$52)-Inputs!$F$48*Inputs!$F$267

Sheet Debt
A1: Case P: Belanou Combined Cycle Power Project, Republic of Kessara
A2: Debt: tranches, scheduled repayment, waiver, refinancing, swap, sculpting
A3: Units in column E; constants in column F; row totals in column G; first period in column J. Inputs: blue on yellow. Links from other sheets: green.
D4: Label | E4: Unit | F4: Constant | G4: Total
D5: Period ending | J5: 2018H2 | K5: 2019H1 | L5: 2019H2 | M5: 2020H1 | N5: 2020H2 | O5: 2021H1 | P5: 2021H2 | Q5: 2022H1 | R5: 2022H2 | S5: 2023H1 | T5: 2023H2 | U5: 2024H1 | V5: 2024H2 | W5: 2025H1 | X5: 2025H2 | Y5: 2026H1 | Z5: 2026H2 | AA5: 2027H1 | AB5: 2027H2 | AC5: 2028H1 | AD5: 2028H2 | AE5: 2029H1 | AF5: 2029H2 | AG5: 2030H1 | AH5: 2030H2 | AI5: 2031H1 | AJ5: 2031H2 | AK5: 2032H1 | AL5: 2032H2 | AM5: 2033H1 | AN5: 2033H2 | AO5: 2034H1 | AP5: 2034H2 | AQ5: 2035H1 | AR5: 2035H2 | AS5: 2036H1 | AT5: 2036H2 | AU5: 2037H1 | AV5: 2037H2 | AW5: 2038H1 | AX5: 2038H2 | AY5: 2039H1 | AZ5: 2039H2 | BA5: 2040H1 | BB5: 2040H2 | BC5: 2041H1 | BD5: 2041H2 | BE5: 2042H1 | BF5: 2042H2 | BG5: 2043H1 | BH5: 2043H2 | BI5: 2044H1 | BJ5: 2044H2 | BK5: 2045H1 | BL5: 2045H2 | BM5: 2046H1 | BN5: 2046H2
B7: Rates
D8: Commercial margin (step-ups) | E8: % | J8: =IF(Time!J22<Inputs!$F$207,Inputs!$F$82,IF(Time!J22<Inputs!$F$208,Inputs!$F$83,Inputs!$F$84)) | K8: =IF(Time!K22<Inputs!$F$207,Inputs!$F$82,IF(Time!K22<Inputs!$F$208,Inputs!$F$83,Inputs!$F$84)) | L8: =IF(Time!L22<Inputs!$F$207,Inputs!$F$82,IF(Time!L22<Inputs!$F$208,Inputs!$F$83,Inputs!$F$84)) | M8: =IF(Time!M22<Inputs!$F$207,Inputs!$F$82,IF(Time!M22<Inputs!$F$208,Inputs!$F$83,Inputs!$F$84)) | N8: =IF(Time!N22<Inputs!$F$207,Inputs!$F$82,IF(Time!N22<Inputs!$F$208,Inputs!$F$83,Inputs!$F$84)) | O8: =IF(Time!O22<Inputs!$F$207,Inputs!$F$82,IF(Time!O22<Inputs!$F$208,Inputs!$F$83,Inputs!$F$84)) | P8: =IF(Time!P22<Inputs!$F$207,Inputs!$F$82,IF(Time!P22<Inputs!$F$208,Inputs!$F$83,Inputs!$F$84)) | Q8: =IF(Time!Q22<Inputs!$F$207,Inputs!$F$82,IF(Time!Q22<Inputs!$F$208,Inputs!$F$83,Inputs!$F$84)) | ... BN8: =IF(Time!BN22<Inputs!$F$207,Inputs!$F$82,IF(Time!BN22<Inputs!$F$208,Inputs!$F$83,Inputs!$F$84))
D9: Waiver margin uplift | E9: % | J9: =Time!J44*Inputs!$F$269 | K9: =Time!K44*Inputs!$F$269 | L9: =Time!L44*Inputs!$F$269 | M9: =Time!M44*Inputs!$F$269 | N9: =Time!N44*Inputs!$F$269 | O9: =Time!O44*Inputs!$F$269 | P9: =Time!P44*Inputs!$F$269 | Q9: =Time!Q44*Inputs!$F$269 | ... BN9: =Time!BN44*Inputs!$F$269
D10: ECA-covered tranche: rate per period | E10: factor | J10: =(Operations!J9+Inputs!$F$79+J9)/100*Time!J25/Inputs!$F$247 | K10: =(Operations!K9+Inputs!$F$79+K9)/100*Time!K25/Inputs!$F$247 | L10: =(Operations!L9+Inputs!$F$79+L9)/100*Time!L25/Inputs!$F$247 | M10: =(Operations!M9+Inputs!$F$79+M9)/100*Time!M25/Inputs!$F$247 | N10: =(Operations!N9+Inputs!$F$79+N9)/100*Time!N25/Inputs!$F$247 | O10: =(Operations!O9+Inputs!$F$79+O9)/100*Time!O25/Inputs!$F$247 | P10: =(Operations!P9+Inputs!$F$79+P9)/100*Time!P25/Inputs!$F$247 | Q10: =(Operations!Q9+Inputs!$F$79+Q9)/100*Time!Q25/Inputs!$F$247 | ... BN10: =(Operations!BN9+Inputs!$F$79+BN9)/100*Time!BN25/Inputs!$F$247
D11: ABDB A-loan: rate per period | E11: factor | J11: =(Operations!J9+Inputs!$F$80+J9)/100*Time!J25/Inputs!$F$247 | K11: =(Operations!K9+Inputs!$F$80+K9)/100*Time!K25/Inputs!$F$247 | L11: =(Operations!L9+Inputs!$F$80+L9)/100*Time!L25/Inputs!$F$247 | M11: =(Operations!M9+Inputs!$F$80+M9)/100*Time!M25/Inputs!$F$247 | N11: =(Operations!N9+Inputs!$F$80+N9)/100*Time!N25/Inputs!$F$247 | O11: =(Operations!O9+Inputs!$F$80+O9)/100*Time!O25/Inputs!$F$247 | P11: =(Operations!P9+Inputs!$F$80+P9)/100*Time!P25/Inputs!$F$247 | Q11: =(Operations!Q9+Inputs!$F$80+Q9)/100*Time!Q25/Inputs!$F$247 | ... BN11: =(Operations!BN9+Inputs!$F$80+BN9)/100*Time!BN25/Inputs!$F$247
D12: ABDB B-loan: rate per period | E12: factor | J12: =(Operations!J9+Inputs!$F$81+J9)/100*Time!J25/Inputs!$F$247 | K12: =(Operations!K9+Inputs!$F$81+K9)/100*Time!K25/Inputs!$F$247 | L12: =(Operations!L9+Inputs!$F$81+L9)/100*Time!L25/Inputs!$F$247 | M12: =(Operations!M9+Inputs!$F$81+M9)/100*Time!M25/Inputs!$F$247 | N12: =(Operations!N9+Inputs!$F$81+N9)/100*Time!N25/Inputs!$F$247 | O12: =(Operations!O9+Inputs!$F$81+O9)/100*Time!O25/Inputs!$F$247 | P12: =(Operations!P9+Inputs!$F$81+P9)/100*Time!P25/Inputs!$F$247 | Q12: =(Operations!Q9+Inputs!$F$81+Q9)/100*Time!Q25/Inputs!$F$247 | ... BN12: =(Operations!BN9+Inputs!$F$81+BN9)/100*Time!BN25/Inputs!$F$247
D13: Commercial tranche: rate per period | E13: factor | J13: =(Operations!J9+J8+J9)/100*Time!J25/Inputs!$F$247/(1-Inputs!$F$93/100) | K13: =(Operations!K9+K8+K9)/100*Time!K25/Inputs!$F$247/(1-Inputs!$F$93/100) | L13: =(Operations!L9+L8+L9)/100*Time!L25/Inputs!$F$247/(1-Inputs!$F$93/100) | M13: =(Operations!M9+M8+M9)/100*Time!M25/Inputs!$F$247/(1-Inputs!$F$93/100) | N13: =(Operations!N9+N8+N9)/100*Time!N25/Inputs!$F$247/(1-Inputs!$F$93/100) | O13: =(Operations!O9+O8+O9)/100*Time!O25/Inputs!$F$247/(1-Inputs!$F$93/100) | P13: =(Operations!P9+P8+P9)/100*Time!P25/Inputs!$F$247/(1-Inputs!$F$93/100) | Q13: =(Operations!Q9+Q8+Q9)/100*Time!Q25/Inputs!$F$247/(1-Inputs!$F$93/100) | ... BN13: =(Operations!BN9+BN8+BN9)/100*Time!BN25/Inputs!$F$247/(1-Inputs!$F$93/100)
D14: Standby facility: rate per period | E14: factor | J14: =(Inputs!$F$102*(Operations!J9+J8+Inputs!$F$101+J9)/(1-Inputs!$F$93/100)+(1-Inputs!$F$102)*(Operations!J9+Inputs!$F$80+Inputs!$F$101+J9))/100*Time!J25/Inputs!$F$247 | K14: =(Inputs!$F$102*(Operations!K9+K8+Inputs!$F$101+K9)/(1-Inputs!$F$93/100)+(1-Inputs!$F$102)*(Operations!K9+Inputs!$F$80+Inputs!$F$101+K9))/100*Time!K25/Inputs!$F$247 | L14: =(Inputs!$F$102*(Operations!L9+L8+Inputs!$F$101+L9)/(1-Inputs!$F$93/100)+(1-Inputs!$F$102)*(Operations!L9+Inputs!$F$80+Inputs!$F$101+L9))/100*Time!L25/Inputs!$F$247 | M14: =(Inputs!$F$102*(Operations!M9+M8+Inputs!$F$101+M9)/(1-Inputs!$F$93/100)+(1-Inputs!$F$102)*(Operations!M9+Inputs!$F$80+Inputs!$F$101+M9))/100*Time!M25/Inputs!$F$247 | N14: =(Inputs!$F$102*(Operations!N9+N8+Inputs!$F$101+N9)/(1-Inputs!$F$93/100)+(1-Inputs!$F$102)*(Operations!N9+Inputs!$F$80+Inputs!$F$101+N9))/100*Time!N25/Inputs!$F$247 | O14: =(Inputs!$F$102*(Operations!O9+O8+Inputs!$F$101+O9)/(1-Inputs!$F$93/100)+(1-Inputs!$F$102)*(Operations!O9+Inputs!$F$80+Inputs!$F$101+O9))/100*Time!O25/Inputs!$F$247 | P14: =(Inputs!$F$102*(Operations!P9+P8+Inputs!$F$101+P9)/(1-Inputs!$F$93/100)+(1-Inputs!$F$102)*(Operations!P9+Inputs!$F$80+Inputs!$F$101+P9))/100*Time!P25/Inputs!$F$247 | Q14: =(Inputs!$F$102*(Operations!Q9+Q8+Inputs!$F$101+Q9)/(1-Inputs!$F$93/100)+(1-Inputs!$F$102)*(Operations!Q9+Inputs!$F$80+Inputs!$F$101+Q9))/100*Time!Q25/Inputs!$F$247 | ... BN14: =(Inputs!$F$102*(Operations!BN9+BN8+Inputs!$F$101+BN9)/(1-Inputs!$F$93/100)+(1-Inputs!$F$102)*(Operations!BN9+Inputs!$F$80+Inputs!$F$101+BN9))/100*Time!BN25/Inputs!$F$247
D15: 2025 project bond: rate per period | E15: factor | J15: =Inputs!$F$271/100*Time!J24 | K15: =Inputs!$F$271/100*Time!K24 | L15: =Inputs!$F$271/100*Time!L24 | M15: =Inputs!$F$271/100*Time!M24 | N15: =Inputs!$F$271/100*Time!N24 | O15: =Inputs!$F$271/100*Time!O24 | P15: =Inputs!$F$271/100*Time!P24 | Q15: =Inputs!$F$271/100*Time!Q24 | ... BN15: =Inputs!$F$271/100*Time!BN24
B16: Contract repayment profile
D17: Repayment profile, selected | E17: fraction | J17: =IF(Inputs!$F$47=1,Inputs!J298,Inputs!J299) | K17: =IF(Inputs!$F$47=1,Inputs!K298,Inputs!K299) | L17: =IF(Inputs!$F$47=1,Inputs!L298,Inputs!L299) | M17: =IF(Inputs!$F$47=1,Inputs!M298,Inputs!M299) | N17: =IF(Inputs!$F$47=1,Inputs!N298,Inputs!N299) | O17: =IF(Inputs!$F$47=1,Inputs!O298,Inputs!O299) | P17: =IF(Inputs!$F$47=1,Inputs!P298,Inputs!P299) | Q17: =IF(Inputs!$F$47=1,Inputs!Q298,Inputs!Q299) | ... BN17: =IF(Inputs!$F$47=1,Inputs!BN298,Inputs!BN299)
D18: Remaining profile (this and later installments) | E18: fraction | J18: =SUM(J17:BN17) | K18: =SUM(K17:BN17) | L18: =SUM(L17:BN17) | M18: =SUM(M17:BN17) | N18: =SUM(N17:BN17) | O18: =SUM(O17:BN17) | P18: =SUM(P17:BN17) | Q18: =SUM(Q17:BN17) | R18: =SUM(R17:BN17) | S18: =SUM(S17:BN17) | T18: =SUM(T17:BN17) | U18: =SUM(U17:BN17) | V18: =SUM(V17:BN17) | W18: =SUM(W17:BN17) | X18: =SUM(X17:BN17) | Y18: =SUM(Y17:BN17) | Z18: =SUM(Z17:BN17) | AA18: =SUM(AA17:BN17) | AB18: =SUM(AB17:BN17) | AC18: =SUM(AC17:BN17) | AD18: =SUM(AD17:BN17) | AE18: =SUM(AE17:BN17) | AF18: =SUM(AF17:BN17) | AG18: =SUM(AG17:BN17) | AH18: =SUM(AH17:BN17) | AI18: =SUM(AI17:BN17) | AJ18: =SUM(AJ17:BN17) | AK18: =SUM(AK17:BN17) | AL18: =SUM(AL17:BN17) | AM18: =SUM(AM17:BN17) | AN18: =SUM(AN17:BN17) | AO18: =SUM(AO17:BN17) | AP18: =SUM(AP17:BN17) | AQ18: =SUM(AQ17:BN17) | AR18: =SUM(AR17:BN17) | AS18: =SUM(AS17:BN17) | AT18: =SUM(AT17:BN17) | AU18: =SUM(AU17:BN17) | AV18: =SUM(AV17:BN17) | AW18: =SUM(AW17:BN17) | AX18: =SUM(AX17:BN17) | AY18: =SUM(AY17:BN17) | AZ18: =SUM(AZ17:BN17) | BA18: =SUM(BA17:BN17) | BB18: =SUM(BB17:BN17) | BC18: =SUM(BC17:BN17) | BD18: =SUM(BD17:BN17) | BE18: =SUM(BE17:BN17) | BF18: =SUM(BF17:BN17) | BG18: =SUM(BG17:BN17) | BH18: =SUM(BH17:BN17) | BI18: =SUM(BI17:BN17) | BJ18: =SUM(BJ17:BN17) | BK18: =SUM(BK17:BN17) | BL18: =SUM(BL17:BN17) | BM18: =SUM(BM17:BN17) | BN18: =SUM(BN17:BN17)
D19: Installment share of remaining balance | E19: fraction | J19: =IF(J18>Inputs!$F$253,J17/J18,0) | K19: =IF(K18>Inputs!$F$253,K17/K18,0) | L19: =IF(L18>Inputs!$F$253,L17/L18,0) | M19: =IF(M18>Inputs!$F$253,M17/M18,0) | N19: =IF(N18>Inputs!$F$253,N17/N18,0) | O19: =IF(O18>Inputs!$F$253,O17/O18,0) | P19: =IF(P18>Inputs!$F$253,P17/P18,0) | Q19: =IF(Q18>Inputs!$F$253,Q17/Q18,0) | ... BN19: =IF(BN18>Inputs!$F$253,BN17/BN18,0)

Sheet Checks
A1: Case P: Belanou Combined Cycle Power Project, Republic of Kessara
A2: Checks: every check shows 0 when passing
A3: Units in column E; constants in column F; row totals in column G; first period in column J. Inputs: blue on yellow. Links from other sheets: green.
D4: Label | E4: Unit | F4: Constant | G4: Total
D7: Sources less uses (construction) | E7: check | F7: =IF(ABS(SUM(Funding!$J$73:$BJ$73)+SUM(Funding!$J$67:$BJ$67)+SUM(Funding!$J$53:$BJ$53)-SUM(Funding!$J$49:$BJ$49))<=Inputs!$F$254,0,SUM(Funding!$J$73:$BJ$73)+SUM(Funding!$J$67:$BJ$67)+SUM(Funding!$J$53:$BJ$53)-SUM(Funding!$J$49:$BJ$49))
D8: Committed debt drawn in full (FC-type), USD m | E8: check | F8: =IF(Inputs!$F$34=1,IF(ABS(SUM(Funding!$J$47:$BJ$47)-Funding!$F$25)<=Inputs!$F$254,0,SUM(Funding!$J$47:$BJ$47)-Funding!$F$25),0)
D9: Closed-form T less live T (re-grossed cases), USD m | E9: check | F9: =IF(Inputs!$F$51<>1,IF(ABS(Funding!$F$24-Funding!$F$75)<=Inputs!$F$254,0,Funding!$F$24-Funding!$F$75),0)
D16: Standby and contingent equity within commitments | E16: check | F16: =IF(AND(SUM(Funding!$J$55:$BJ$55)<=Inputs!$F$99+Inputs!$F$254,SUM(Funding!$J$56:$BJ$56)<=Inputs!$F$103+Inputs!$F$254),0,1)
D17: ECA tranche within cap | E17: check | F17: =IF(Inputs!$F$75*Funding!$F$25<=Inputs!$F$251,0,1)
D19: Sum of checks (0 = all pass) | E19: check | F19: =ABS($F$7)+ABS($F$8)+ABS($F$9)+ABS($F$16)+ABS($F$17)+ABS($F$20)+ABS($F$21)
D20: Time: operating months sum to the PPA term | E20: check | F20: =SUM(Time!$J$30:$BN$30)-Time!$F$9
D21: Construction flags sum to construction months | E21: check | F21: =SUM(Construction!$J$13:$BJ$13)-Time!$F$11
