Workbook

Sheet Cover
D1: Case T: Merrick Link toll road PPP | Cover
D3: Case T reference model: the Merrick Link toll road PPP, State of Brannock, Commonwealth of Ardmore.
D4: Model version 1.0; story as of October 3, 2026. Currency: Ardmore dollar (ARD), millions, nominal.
D5: Python mirror: model/case_t.py (source of truth); verification: model/case_t_verification.md.
D7: How to use: choose the scenario in Inputs!F (named range Scenario):
D8: 1 = Bid base (Pellow traffic), locked financing
D9: 2 = Banking case (Ridgeway traffic), live debt sizing
D10: 3 = Downside traffic, locked financing
D11: 4 = Actual history to 2026H1, then Ridgeway 2023 case; restructuring at 2023-12-31
D12: 5 = Restructuring case: actual history to 2023H2, Ridgeway 2023 case from 2024 (live notes sculpting)
D13: 6 = Retender valuation at 2022-06-30 (actual to 2022H1, retender traffic case after)
D14: 7 = Sensitivity: traffic -10%
... D39: subtracted; tables show negatives in parentheses.

Sheet Inputs
D1: Case T: Merrick Link toll road PPP | Inputs
D2: Units: ARD millions unless stated. Inputs blue on yellow; links green; calculations black.
D3: Period end | E3: date | J3: =Time!J8 -> 42185 | K3: =Time!K8 -> 42277 | L3: =Time!L8 -> 42369 | M3: =Time!M8 -> 42460 | N3: =Time!N8 -> 42551 | O3: =Time!O8 -> 42643 | P3: =Time!P8 -> 42735 | Q3: =Time!Q8 -> 42825 | ... DB3: =Time!DB8 -> 58256
D5: Switches
D6: Scenario (1-13, see Cover) | E6: # | F6: 4
D7: Contribution option (1 = bid, 2 = solved for 11.4% on banking) | E7: # | F7: 1
D8: Circuit breaker (1 = live circular links, 0 = cut) | E8: flag | F8: 1
D9: Test tolerance | E9: ARD m | F9: 1e-06
D10: Large number for MIN helper rows | E10: # | F10: 1000000000000
D12: Dates
D13: Financial close | E13: date | F13: 42151
D14: End of first model period | E14: date | F14: 42185
D15: Scheduled completion and end of construction funding | E15: date | F15: 43555
D16: Scheduled opening | E16: date | F16: 43555
D17: Actual opening | E17: date | F17: 43591
D18: Concession expiry (original) | E18: date | F18: 56030
D19: Concession expiry (extended 2023) | E19: date | F19: 58221
D20: Restructuring (model date) | E20: date | F20: 45291
D21: Senior first repayment | E21: date | F21: 44377
D22: Senior final repayment | E22: date | F22: 54423
D23: Bank margin step-up date | E23: date | F23: 43978
D24: Bank mini-perm maturity (refinancing or A&E date) | E24: date | F24: 44708
... D42: PSC: contribution payment date | E42: date | F42: 43555
D44: Conventions
D45: Days per year (ACT/365) | E45: days | F45: 365
D46: Days per year (30/360) | E46: days | F46: 360
D47: Average days per month (period length in months) | E47: days | F47: 30.4
D48: Defects period | E48: months | F48: 24
D49: Handback funding window | E49: months | F49: 60
D50: Bridge draws: last construction months | E50: months | F50: 18
D51: Toll escalation month (July 1) | E51: # | F51: 7
D52: Toll rounding (decimal places) | E52: # | F52: 4
D53: Last year of the 3% escalation floor (July 1) | E53: year | F53: 2029
D54: CPI-only escalation from (restructured) | E54: year | F54: 2024
D55: Traffic growth band 1 ends | E55: year | F55: 2030
D56: Traffic growth band 2 ends | E56: year | F56: 2040
... D65: ARD per ARD million | E65: # | F65: 1000000
D67: Construction costs
D68: D&C contract price (lump sum) | E68: ARD m | F68: 1684.3
D69: Retention released at completion | E69: % | F69: 0.025
D70: Retention released at end of defects period | E70: % | F70: 0.025
D71: Development and bid costs reimbursed (at close) | E71: ARD m | F71: 41.2
D72: Project company costs during construction (flat by day) | E72: ARD m | F72: 37.8
D73: Insurance during construction | E73: ARD m | F73: 12.6
D74: Insurance share paid at close | E74: % | F74: 0.8
D75: Independent certifier (flat by day) | E75: ARD m | F75: 3.4
D76: Lenders' advisors and legal (flat by day) | E76: ARD m | F76: 9.7
D77: Contingency (pro rata with D&C) | E77: ARD m | F77: 52.4
D78: Delay LDs received (actual) | E78: ARD m | F78: 10.26
D80: State contribution and bridge
D81: State construction contribution (bid) | E81: ARD m | F81: 287.4
D82: Contribution for 11.4% on banking (solved by Python mirror) | E82: ARD m | F82: 537.71626
D83: Bridge margin over ABBR | E83: % | F83: 0.016
D84: Bridge upfront fee | E84: % | F84: 0.01
D86: Equity and sizing
D87: Equity share of funding requirement net of contribution | E87: % | F87: 0.22
D88: Share capital share of equity | E88: % | F88: 0.15
D89: Shareholder loan rate | E89: % | F89: 0.1025
D90: Bid target equity IRR (nominal post-tax) | E90: % | F90: 0.114
D91: Senior sculpting / minimum DSCR, banking | E91: x | F91: 1.5
D92: Minimum DSCR, downside | E92: x | F92: 1.15
D93: Minimum LLCR, banking | E93: x | F93: 1.55
D94: Senior cap, % of funding net of contribution | E94: % | F94: 0.55
D95: Ramp-up interest account target DSCR | E95: x | F95: 1.5
D96: Senior split: bank | E96: % | F96: 0.45
D97: Senior split: bonds | E97: % | F97: 0.55
D99: Senior debt terms
D100: Bank swap fixed rate | E100: %pa | F100: 3.48
D101: Market swap rate at 2023-12-31 | E101: %pa | F101: 4.36
D102: Bank margin to 2020-05-27 | E102: %pa | F102: 2.35
D103: Bank margin 2020-05-27 to 2022-05-27 | E103: %pa | F103: 2.6
D104: Base-case refinancing margin from 2022-05-27 | E104: %pa | F104: 2.25
D105: Amend-and-extend margin from 2022-05-27 (actual) | E105: %pa | F105: 3.25
D106: Base-case refinancing fee | E106: % | F106: 0.0125
D107: Amend-and-extend fee | E107: % | F107: 0.005
D108: Bank upfront fee | E108: % | F108: 0.0185
D109: Bank commitment fee | E109: % | F109: 0.0095
D110: Bond coupon | E110: % | F110: 0.0485
D111: Bond escrow earnings rate | E111: % | F111: 0.021
... D115: DSRA months of debt service | E115: months | F115: 6
D117: NILO loan
D118: NILO fixed rate | E118: % | F118: 0.0306
D119: NILO PIK rate to 2030 (restructured) | E119: % | F119: 0.01
D120: NILO maximum share of eligible costs | E120: % | F120: 0.33
D121: NILO application fee | E121: % | F121: 0.001
D122: Combined senior plus NILO minimum DSCR (banking) | E122: x | F122: 1.25
D124: Tolls, traffic and revenue
D125: Car toll per km, June 2014 prices | E125: ARD/km | F125: 0.1525
D126: Escalation floor to 2030 | E126: % | F126: 0.03
D127: Average trip length | E127: km | F127: 23.8
D128: Revenue leakage | E128: % | F128: 0.018
D129: Vehicle mix: car (original) | E129: %pa | F129: 79.4
D130: Vehicle mix: light commercial (original) | E130: %pa | F130: 9
D131: Vehicle mix: heavy (original) | E131: %pa | F131: 11.6
D132: Vehicle mix: car (from 2024) | E132: %pa | F132: 77.6
D133: Vehicle mix: light commercial (from 2024) | E133: %pa | F133: 8.6
D134: Vehicle mix: heavy (from 2024) | E134: %pa | F134: 13.8
D135: Class multiplier: light commercial | E135: factor | F135: 1.6
D136: Class multiplier: heavy (original) | E136: factor | F136: 2.85
... D138: Class multiplier: car | E138: factor | F138: 1
...

Sheet Time
D1: Case T: Merrick Link toll road PPP | Time
D2: Units: ARD millions unless stated. Inputs blue on yellow; links green; calculations black.
D3: Period end | E3: date | J3: =J8 -> 42185 | K3: =K8 -> 42277 | L3: =L8 -> 42369 | M3: =M8 -> 42460 | N3: =N8 -> 42551 | O3: =O8 -> 42643 | P3: =P8 -> 42735 | Q3: =Q8 -> 42825 | ... DB3: =DB8 -> 58256
D5: Timeline
D6: Period number | E6: # | J6: =I6+1 -> 1 | K6: =J6+1 -> 2 | L6: =K6+1 -> 3 | M6: =L6+1 -> 4 | N6: =M6+1 -> 5 | O6: =N6+1 -> 6 | P6: =O6+1 -> 7 | Q6: =P6+1 -> 8 | ... DB6: =DA6+1 -> 97
D7: Period start | E7: date | J7: =IF(J6=1,Inputs!$F$13,I8) -> 42151 | K7: =IF(K6=1,Inputs!$F$13,J8) -> 42185 | L7: =IF(L6=1,Inputs!$F$13,K8) -> 42277 | M7: =IF(M6=1,Inputs!$F$13,L8) -> 42369 | N7: =IF(N6=1,Inputs!$F$13,M8) -> 42460 | O7: =IF(O6=1,Inputs!$F$13,N8) -> 42551 | P7: =IF(P6=1,Inputs!$F$13,O8) -> 42643 | Q7: =IF(Q6=1,Inputs!$F$13,P8) -> 42735 | ... DB7: =IF(DB6=1,Inputs!$F$13,DA8) -> 58075
D8: Period end | E8: date | J8: =IF(J6=1,Inputs!$F$14,EOMONTH(I8,IF(I8<=Inputs!$F$15,3,6))) -> 42185 | K8: =IF(K6=1,Inputs!$F$14,EOMONTH(J8,IF(J8<=Inputs!$F$15,3,6))) -> 42277 | L8: =IF(L6=1,Inputs!$F$14,EOMONTH(K8,IF(K8<=Inputs!$F$15,3,6))) -> 42369 | M8: =IF(M6=1,Inputs!$F$14,EOMONTH(L8,IF(L8<=Inputs!$F$15,3,6))) -> 42460 | N8: =IF(N6=1,Inputs!$F$14,EOMONTH(M8,IF(M8<=Inputs!$F$15,3,6))) -> 42551 | O8: =IF(O6=1,Inputs!$F$14,EOMONTH(N8,IF(N8<=Inputs!$F$15,3,6))) -> 42643 | P8: =IF(P6=1,Inputs!$F$14,EOMONTH(O8,IF(O8<=Inputs!$F$15,3,6))) -> 42735 | Q8: =IF(Q6=1,Inputs!$F$14,EOMONTH(P8,IF(P8<=Inputs!$F$15,3,6))) -> 42825 | ... DB8: =IF(DB6=1,Inputs!$F$14,EOMONTH(DA8,IF(DA8<=Inputs!$F$15,3,6))) -> 58256
D9: Days in period | E9: days | J9: =J8-J7 -> 34 | K9: =K8-K7 -> 92 | L9: =L8-L7 -> 92 | M9: =M8-M7 -> 91 | N9: =N8-N7 -> 91 | O9: =O8-O7 -> 92 | P9: =P8-P7 -> 92 | Q9: =Q8-Q7 -> 90 | ... DB9: =DB8-DB7 -> 181
D10: Days in period (30/360) | E10: days | J10: =Inputs!$F$46*(YEAR(J8)-YEAR(J7))+30*(MONTH(J8)-MONTH(J7))+MIN(DAY(J8),30)-MIN(DAY(J7),30) -> 33 | K10: =Inputs!$F$46*(YEAR(K8)-YEAR(K7))+30*(MONTH(K8)-MONTH(K7))+MIN(DAY(K8),30)-MIN(DAY(K7),30) -> 90 | L10: =Inputs!$F$46*(YEAR(L8)-YEAR(L7))+30*(MONTH(L8)-MONTH(L7))+MIN(DAY(L8),30)-MIN(DAY(L7),30) -> 90 | M10: =Inputs!$F$46*(YEAR(M8)-YEAR(M7))+30*(MONTH(M8)-MONTH(M7))+MIN(DAY(M8),30)-MIN(DAY(M7),30) -> 90 | N10: =Inputs!$F$46*(YEAR(N8)-YEAR(N7))+30*(MONTH(N8)-MONTH(N7))+MIN(DAY(N8),30)-MIN(DAY(N7),30) -> 90 | O10: =Inputs!$F$46*(YEAR(O8)-YEAR(O7))+30*(MONTH(O8)-MONTH(O7))+MIN(DAY(O8),30)-MIN(DAY(O7),30) -> 90 | P10: =Inputs!$F$46*(YEAR(P8)-YEAR(P7))+30*(MONTH(P8)-MONTH(P7))+MIN(DAY(P8),30)-MIN(DAY(P7),30) -> 90 | Q10: =Inputs!$F$46*(YEAR(Q8)-YEAR(Q7))+30*(MONTH(Q8)-MONTH(Q7))+MIN(DAY(Q8),30)-MIN(DAY(Q7),30) -> 90 | ... DB10: =Inputs!$F$46*(YEAR(DB8)-YEAR(DB7))+30*(MONTH(DB8)-MONTH(DB7))+MIN(DAY(DB8),30)-MIN(DAY(DB7),30) -> 180
D11: Calendar year | E11: year | J11: =YEAR(J8) -> 2015 | K11: =YEAR(K8) -> 2015 | L11: =YEAR(L8) -> 2015 | M11: =YEAR(M8) -> 2016 | N11: =YEAR(N8) -> 2016 | O11: =YEAR(O8) -> 2016 | P11: =YEAR(P8) -> 2016 | Q11: =YEAR(Q8) -> 2017 | ... DB11: =YEAR(DB8) -> 2059
D12: Half (1 = Jan-Jun, 2 = Jul-Dec) | E12: # | J12: =IF(MONTH(J8)<=6,1,2) -> 1 | K12: =IF(MONTH(K8)<=6,1,2) -> 2 | L12: =IF(MONTH(L8)<=6,1,2) -> 2 | M12: =IF(MONTH(M8)<=6,1,2) -> 1 | N12: =IF(MONTH(N8)<=6,1,2) -> 1 | O12: =IF(MONTH(O8)<=6,1,2) -> 2 | P12: =IF(MONTH(P8)<=6,1,2) -> 2 | Q12: =IF(MONTH(Q8)<=6,1,2) -> 1 | ... DB12: =IF(MONTH(DB8)<=6,1,2) -> 1
D13: Half-year code | E13: code | J13: =J11*Inputs!$F$63+J12 -> 20151 | K13: =K11*Inputs!$F$63+K12 -> 20152 | L13: =L11*Inputs!$F$63+L12 -> 20152 | M13: =M11*Inputs!$F$63+M12 -> 20161 | N13: =N11*Inputs!$F$63+N12 -> 20161 | O13: =O11*Inputs!$F$63+O12 -> 20162 | P13: =P11*Inputs!$F$63+P12 -> 20162 | Q13: =Q11*Inputs!$F$63+Q12 -> 20171 | ... DB13: =DB11*Inputs!$F$63+DB12 -> 20591
D14: Months in period | E14: # | J14: =ROUND(J9/Inputs!$F$47,0) -> 1 | K14: =ROUND(K9/Inputs!$F$47,0) -> 3 | L14: =ROUND(L9/Inputs!$F$47,0) -> 3 | M14: =ROUND(M9/Inputs!$F$47,0) -> 3 | N14: =ROUND(N9/Inputs!$F$47,0) -> 3 | O14: =ROUND(O9/Inputs!$F$47,0) -> 3 | P14: =ROUND(P9/Inputs!$F$47,0) -> 3 | Q14: =ROUND(Q9/Inputs!$F$47,0) -> 3 | ... DB14: =ROUND(DB9/Inputs!$F$47,0) -> 6
D15: Key dates for the selected scenario
D16: Opening date | E16: date | F16: =IF(Inputs!$F$213=1,Inputs!$F$17,Inputs!$F$16) -> 43591
D17: Concession expiry | E17: date | F17: =IF(Inputs!$F$215=1,Inputs!$F$19,Inputs!$F$18) -> 58221
D18: Construction days (close to scheduled completion) | E18: days | F18: =Inputs!$F$15-Inputs!$F$13 -> 1404
D19: Flags
D20: Flag_Construction | E20: flag | J20: =IF(J8<=Inputs!$F$15,1,0) -> 1 | K20: =IF(K8<=Inputs!$F$15,1,0) -> 1 | L20: =IF(L8<=Inputs!$F$15,1,0) -> 1 | M20: =IF(M8<=Inputs!$F$15,1,0) -> 1 | N20: =IF(N8<=Inputs!$F$15,1,0) -> 1 | O20: =IF(O8<=Inputs!$F$15,1,0) -> 1 | P20: =IF(P8<=Inputs!$F$15,1,0) -> 1 | Q20: =IF(Q8<=Inputs!$F$15,1,0) -> 1 | ... DB20: =IF(DB8<=Inputs!$F$15,1,0) -> 0
D21: Flag_FirstPostConstruction | E21: flag | J21: =IF(AND(I20=1,J20=0),1,0) -> 0 | K21: =IF(AND(J20=1,K20=0),1,0) -> 0 | L21: =IF(AND(K20=1,L20=0),1,0) -> 0 | M21: =IF(AND(L20=1,M20=0),1,0) -> 0 | N21: =IF(AND(M20=1,N20=0),1,0) -> 0 | O21: =IF(AND(N20=1,O20=0),1,0) -> 0 | P21: =IF(AND(O20=1,P20=0),1,0) -> 0 | Q21: =IF(AND(P20=1,Q20=0),1,0) -> 0 | ... DB21: =IF(AND(DA20=1,DB20=0),1,0) -> 0
D22: Flag_BridgeDraw (last six construction quarters) | E22: flag | J22: =IF(AND(J20=1,J8>EDATE(Inputs!$F$15,-Inputs!$F$50)),1,0) -> 0 | K22: =IF(AND(K20=1,K8>EDATE(Inputs!$F$15,-Inputs!$F$50)),1,0) -> 0 | L22: =IF(AND(L20=1,L8>EDATE(Inputs!$F$15,-Inputs!$F$50)),1,0) -> 0 | M22: =IF(AND(M20=1,M8>EDATE(Inputs!$F$15,-Inputs!$F$50)),1,0) -> 0 | N22: =IF(AND(N20=1,N8>EDATE(Inputs!$F$15,-Inputs!$F$50)),1,0) -> 0 | O22: =IF(AND(O20=1,O8>EDATE(Inputs!$F$15,-Inputs!$F$50)),1,0) -> 0 | P22: =IF(AND(P20=1,P8>EDATE(Inputs!$F$15,-Inputs!$F$50)),1,0) -> 0 | Q22: =IF(AND(Q20=1,Q8>EDATE(Inputs!$F$15,-Inputs!$F$50)),1,0) -> 0 | ... DB22: =IF(AND(DB20=1,DB8>EDATE(Inputs!$F$15,-Inputs!$F$50)),1,0) -> 0
D23: Flag_PostRestructuring | E23: flag | J23: =IF(AND(Inputs!$F$215=1,J8>Inputs!$F$20),1,0) -> 0 | K23: =IF(AND(Inputs!$F$215=1,K8>Inputs!$F$20),1,0) -> 0 | L23: =IF(AND(Inputs!$F$215=1,L8>Inputs!$F$20),1,0) -> 0 | M23: =IF(AND(Inputs!$F$215=1,M8>Inputs!$F$20),1,0) -> 0 | N23: =IF(AND(Inputs!$F$215=1,N8>Inputs!$F$20),1,0) -> 0 | O23: =IF(AND(Inputs!$F$215=1,O8>Inputs!$F$20),1,0) -> 0 | P23: =IF(AND(Inputs!$F$215=1,P8>Inputs!$F$20),1,0) -> 0 | Q23: =IF(AND(Inputs!$F$215=1,Q8>Inputs!$F$20),1,0) -> 0 | ... DB23: =IF(AND(Inputs!$F$215=1,DB8>Inputs!$F$20),1,0) -> 1
D24: Applicable concession expiry | E24: date | J24: =IF(J23=1,Inputs!$F$19,Inputs!$F$18) -> 56030 | K24: =IF(K23=1,Inputs!$F$19,Inputs!$F$18) -> 56030 | L24: =IF(L23=1,Inputs!$F$19,Inputs!$F$18) -> 56030 | M24: =IF(M23=1,Inputs!$F$19,Inputs!$F$18) -> 56030 | N24: =IF(N23=1,Inputs!$F$19,Inputs!$F$18) -> 56030 | O24: =IF(O23=1,Inputs!$F$19,Inputs!$F$18) -> 56030 | P24: =IF(P23=1,Inputs!$F$19,Inputs!$F$18) -> 56030 | Q24: =IF(Q23=1,Inputs!$F$19,Inputs!$F$18) -> 56030 | ... DB24: =IF(DB23=1,Inputs!$F$19,Inputs!$F$18) -> 58221
D25: Operating days | E25: days | J25: =MAX(0,MIN(J8,$F$17)-MAX(J7,$F$16)) -> 0 | K25: =MAX(0,MIN(K8,$F$17)-MAX(K7,$F$16)) -> 0 | L25: =MAX(0,MIN(L8,$F$17)-MAX(L7,$F$16)) -> 0 | M25: =MAX(0,MIN(M8,$F$17)-MAX(M7,$F$16)) -> 0 | N25: =MAX(0,MIN(N8,$F$17)-MAX(N7,$F$16)) -> 0 | O25: =MAX(0,MIN(O8,$F$17)-MAX(O7,$F$16)) -> 0 | P25: =MAX(0,MIN(P8,$F$17)-MAX(P7,$F$16)) -> 0 | Q25: =MAX(0,MIN(Q8,$F$17)-MAX(Q7,$F$16)) -> 0 | ... DB25: =MAX(0,MIN(DB8,$F$17)-MAX(DB7,$F$16)) -> 146
D26: Flag_Operations | E26: flag | J26: =IF(J25>0,1,0) -> 0 | K26: =IF(K25>0,1,0) -> 0 | L26: =IF(L25>0,1,0) -> 0 | M26: =IF(M25>0,1,0) -> 0 | N26: =IF(N25>0,1,0) -> 0 | O26: =IF(O25>0,1,0) -> 0 | P26: =IF(P25>0,1,0) -> 0 | Q26: =IF(Q25>0,1,0) -> 0 | ... DB26: =IF(DB25>0,1,0) -> 1
D27: Flag_OpeningPeriod | E27: flag | J27: =IF(AND(J7<$F$16,$F$16<=J8),1,0) -> 0 | K27: =IF(AND(K7<$F$16,$F$16<=K8),1,0) -> 0 | L27: =IF(AND(L7<$F$16,$F$16<=L8),1,0) -> 0 | M27: =IF(AND(M7<$F$16,$F$16<=M8),1,0) -> 0 | N27: =IF(AND(N7<$F$16,$F$16<=N8),1,0) -> 0 | O27: =IF(AND(O7<$F$16,$F$16<=O8),1,0) -> 0 | P27: =IF(AND(P7<$F$16,$F$16<=P8),1,0) -> 0 | Q27: =IF(AND(Q7<$F$16,$F$16<=Q8),1,0) -> 0 | ... DB27: =IF(AND(DB7<$F$16,$F$16<=DB8),1,0) -> 0
D28: Flag_FinalPeriod (concession expiry) | E28: flag | J28: =IF(AND(J7<$F$17,$F$17<=J8),1,0) -> 0 | K28: =IF(AND(K7<$F$17,$F$17<=K8),1,0) -> 0 | L28: =IF(AND(L7<$F$17,$F$17<=L8),1,0) -> 0 | M28: =IF(AND(M7<$F$17,$F$17<=M8),1,0) -> 0 | N28: =IF(AND(N7<$F$17,$F$17<=N8),1,0) -> 0 | O28: =IF(AND(O7<$F$17,$F$17<=O8),1,0) -> 0 | P28: =IF(AND(P7<$F$17,$F$17<=P8),1,0) -> 0 | Q28: =IF(AND(Q7<$F$17,$F$17<=Q8),1,0) -> 0 | ... DB28: =IF(AND(DB7<$F$17,$F$17<=DB8),1,0) -> 1
D29: Remaining concession days from period start | E29: days | J29: =MAX(0,J24-MAX(J7,$F$16)) -> 12439 | K29: =MAX(0,K24-MAX(K7,$F$16)) -> 12439 | L29: =MAX(0,L24-MAX(L7,$F$16)) -> 12439 | M29: =MAX(0,M24-MAX(M7,$F$16)) -> 12439 | N29: =MAX(0,N24-MAX(N7,$F$16)) -> 12439 | O29: =MAX(0,O24-MAX(O7,$F$16)) -> 12439 | P29: =MAX(0,P24-MAX(P7,$F$16)) -> 12439 | Q29: =MAX(0,Q24-MAX(Q7,$F$16)) -> 12439 | ... DB29: =MAX(0,DB24-MAX(DB7,$F$16)) -> 146
D30: Flag_Repayment (senior, original) | E30: flag | J30: =IF(AND(J8>=Inputs!$F$21,J8<=Inputs!$F$22),1,0) -> 0 | K30: =IF(AND(K8>=Inputs!$F$21,K8<=Inputs!$F$22),1,0) -> 0 | L30: =IF(AND(L8>=Inputs!$F$21,L8<=Inputs!$F$22),1,0) -> 0 | M30: =IF(AND(M8>=Inputs!$F$21,M8<=Inputs!$F$22),1,0) -> 0 | N30: =IF(AND(N8>=Inputs!$F$21,N8<=Inputs!$F$22),1,0) -> 0 | O30: =IF(AND(O8>=Inputs!$F$21,O8<=Inputs!$F$22),1,0) -> 0 | P30: =IF(AND(P8>=Inputs!$F$21,P8<=Inputs!$F$22),1,0) -> 0 | Q30: =IF(AND(Q8>=Inputs!$F$21,Q8<=Inputs!$F$22),1,0) -> 0 | ... DB30: =IF(AND(DB8>=Inputs!$F$21,DB8<=Inputs!$F$22),1,0) -> 0
D31: Flag_FirstRepayment | E31: flag | J31: =IF(AND(J30=1,I30=0),1,0) -> 0 | K31: =IF(AND(K30=1,J30=0),1,0) -> 0 | L31: =IF(AND(L30=1,K30=0),1,0) -> 0 | M31: =IF(AND(M30=1,L30=0),1,0) -> 0 | N31: =IF(AND(N30=1,M30=0),1,0) -> 0 | O31: =IF(AND(O30=1,N30=0),1,0) -> 0 | P31: =IF(AND(P30=1,O30=0),1,0) -> 0 | Q31: =IF(AND(Q30=1,P30=0),1,0) -> 0 | ... DB31: =IF(AND(DB30=1,DA30=0),1,0) -> 0
D32: Flag_RampUp (operations before first repayment) | E32: flag | J32: =IF(AND(J26=1,J8<Inputs!$F$21),1,0) -> 0 | K32: =IF(AND(K26=1,K8<Inputs!$F$21),1,0) -> 0 | L32: =IF(AND(L26=1,L8<Inputs!$F$21),1,0) -> 0 | M32: =IF(AND(M26=1,M8<Inputs!$F$21),1,0) -> 0 | N32: =IF(AND(N26=1,N8<Inputs!$F$21),1,0) -> 0 | O32: =IF(AND(O26=1,O8<Inputs!$F$21),1,0) -> 0 | P32: =IF(AND(P26=1,P8<Inputs!$F$21),1,0) -> 0 | Q32: =IF(AND(Q26=1,Q8<Inputs!$F$21),1,0) -> 0 | ... DB32: =IF(AND(DB26=1,DB8<Inputs!$F$21),1,0) -> 0
D33: Flag_BeforeFirstRepayment | E33: flag | J33: =IF(J8<Inputs!$F$21,1,0) -> 1 | K33: =IF(K8<Inputs!$F$21,1,0) -> 1 | L33: =IF(L8<Inputs!$F$21,1,0) -> 1 | M33: =IF(M8<Inputs!$F$21,1,0) -> 1 | N33: =IF(N8<Inputs!$F$21,1,0) -> 1 | O33: =IF(O8<Inputs!$F$21,1,0) -> 1 | P33: =IF(P8<Inputs!$F$21,1,0) -> 1 | Q33: =IF(Q8<Inputs!$F$21,1,0) -> 1 | ... DB33: =IF(DB8<Inputs!$F$21,1,0) -> 0
D34: Flag_Standstill | E34: flag | J34: =IF(AND(Inputs!$F$213=1,J8>=Inputs!$F$21,J8<=Inputs!$F$20),1,0) -> 0 | K34: =IF(AND(Inputs!$F$213=1,K8>=Inputs!$F$21,K8<=Inputs!$F$20),1,0) -> 0 | L34: =IF(AND(Inputs!$F$213=1,L8>=Inputs!$F$21,L8<=Inputs!$F$20),1,0) -> 0 | M34: =IF(AND(Inputs!$F$213=1,M8>=Inputs!$F$21,M8<=Inputs!$F$20),1,0) -> 0 | N34: =IF(AND(Inputs!$F$213=1,N8>=Inputs!$F$21,N8<=Inputs!$F$20),1,0) -> 0 | O34: =IF(AND(Inputs!$F$213=1,O8>=Inputs!$F$21,O8<=Inputs!$F$20),1,0) -> 0 | P34: =IF(AND(Inputs!$F$213=1,P8>=Inputs!$F$21,P8<=Inputs!$F$20),1,0) -> 0 | Q34: =IF(AND(Inputs!$F$213=1,Q8>=Inputs!$F$21,Q8<=Inputs!$F$20),1,0) -> 0 | ... DB34: =IF(AND(Inputs!$F$213=1,DB8>=Inputs!$F$21,DB8<=Inputs!$F$20),1,0) -> 0
D35: Flag_Restructuring | E35: flag | J35: =IF(AND(Inputs!$F$215=1,J8=Inputs!$F$20),1,0) -> 0 | K35: =IF(AND(Inputs!$F$215=1,K8=Inputs!$F$20),1,0) -> 0 | L35: =IF(AND(Inputs!$F$215=1,L8=Inputs!$F$20),1,0) -> 0 | M35: =IF(AND(Inputs!$F$215=1,M8=Inputs!$F$20),1,0) -> 0 | N35: =IF(AND(Inputs!$F$215=1,N8=Inputs!$F$20),1,0) -> 0 | O35: =IF(AND(Inputs!$F$215=1,O8=Inputs!$F$20),1,0) -> 0 | P35: =IF(AND(Inputs!$F$215=1,P8=Inputs!$F$20),1,0) -> 0 | Q35: =IF(AND(Inputs!$F$215=1,Q8=Inputs!$F$20),1,0) -> 0 | ... DB35: =IF(AND(Inputs!$F$215=1,DB8=Inputs!$F$20),1,0) -> 0
D36: Flag_FirstNotesPeriod | E36: flag | J36: =IF(AND(J23=1,I35=1),1,0) -> 0 | K36: =IF(AND(K23=1,J35=1),1,0) -> 0 | L36: =IF(AND(L23=1,K35=1),1,0) -> 0 | M36: =IF(AND(M23=1,L35=1),1,0) -> 0 | N36: =IF(AND(N23=1,M35=1),1,0) -> 0 | O36: =IF(AND(O23=1,N35=1),1,0) -> 0 | P36: =IF(AND(P23=1,O35=1),1,0) -> 0 | Q36: =IF(AND(Q23=1,P35=1),1,0) -> 0 | ... DB36: =IF(AND(DB23=1,DA35=1),1,0) -> 0
D37: Flag_NotesRepayment | E37: flag | J37: =IF(AND(J23=1,J8<=Inputs!$F$32),1,0) -> 0 | K37: =IF(AND(K23=1,K8<=Inputs!$F$32),1,0) -> 0 | L37: =IF(AND(L23=1,L8<=Inputs!$F$32),1,0) -> 0 | M37: =IF(AND(M23=1,M8<=Inputs!$F$32),1,0) -> 0 | N37: =IF(AND(N23=1,N8<=Inputs!$F$32),1,0) -> 0 | O37: =IF(AND(O23=1,O8<=Inputs!$F$32),1,0) -> 0 | P37: =IF(AND(P23=1,P8<=Inputs!$F$32),1,0) -> 0 | Q37: =IF(AND(Q23=1,Q8<=Inputs!$F$32),1,0) -> 0 | ... DB37: =IF(AND(DB23=1,DB8<=Inputs!$F$32),1,0) -> 0
D38: Flag_NotesSweep | E38: flag | J38: =IF(AND(J23=1,J8<=Inputs!$F$33),1,0) -> 0 | K38: =IF(AND(K23=1,K8<=Inputs!$F$33),1,0) -> 0 | L38: =IF(AND(L23=1,L8<=Inputs!$F$33),1,0) -> 0 | M38: =IF(AND(M23=1,M8<=Inputs!$F$33),1,0) -> 0 | N38: =IF(AND(N23=1,N8<=Inputs!$F$33),1,0) -> 0 | O38: =IF(AND(O23=1,O8<=Inputs!$F$33),1,0) -> 0 | P38: =IF(AND(P23=1,P8<=Inputs!$F$33),1,0) -> 0 | Q38: =IF(AND(Q23=1,Q8<=Inputs!$F$33),1,0) -> 0 | ... DB38: =IF(AND(DB23=1,DB8<=Inputs!$F$33),1,0) -> 0
D39: Flag_ActualTraffic | E39: flag | J39: =IF(AND(Inputs!$F$213=1,J26=1,J8<=Inputs!$F$214),1,0) -> 0 | K39: =IF(AND(Inputs!$F$213=1,K26=1,K8<=Inputs!$F$214),1,0) -> 0 | L39: =IF(AND(Inputs!$F$213=1,L26=1,L8<=Inputs!$F$214),1,0) -> 0 | M39: =IF(AND(Inputs!$F$213=1,M26=1,M8<=Inputs!$F$214),1,0) -> 0 | N39: =IF(AND(Inputs!$F$213=1,N26=1,N8<=Inputs!$F$214),1,0) -> 0 | O39: =IF(AND(Inputs!$F$213=1,O26=1,O8<=Inputs!$F$214),1,0) -> 0 | P39: =IF(AND(Inputs!$F$213=1,P26=1,P8<=Inputs!$F$214),1,0) -> 0 | Q39: =IF(AND(Inputs!$F$213=1,Q26=1,Q8<=Inputs!$F$214),1,0) -> 0 | ... DB39: =IF(AND(Inputs!$F$213=1,DB26=1,DB8<=Inputs!$F$214),1,0) -> 0
D40: Share of period before margin step | E40: factor | J40: =MIN(1,MAX(0,(MIN(J8,Inputs!$F$23)-J7)/J9)) -> 1 | K40: =MIN(1,MAX(0,(MIN(K8,Inputs!$F$23)-K7)/K9)) -> 1 | L40: =MIN(1,MAX(0,(MIN(L8,Inputs!$F$23)-L7)/L9)) -> 1 | M40: =MIN(1,MAX(0,(MIN(M8,Inputs!$F$23)-M7)/M9)) -> 1 | N40: =MIN(1,MAX(0,(MIN(N8,Inputs!$F$23)-N7)/N9)) -> 1 | O40: =MIN(1,MAX(0,(MIN(O8,Inputs!$F$23)-O7)/O9)) -> 1 | P40: =MIN(1,MAX(0,(MIN(P8,Inputs!$F$23)-P7)/P9)) -> 1 | Q40: =MIN(1,MAX(0,(MIN(Q8,Inputs!$F$23)-Q7)/Q9)) -> 1 | ... DB40: =MIN(1,MAX(0,(MIN(DB8,Inputs!$F$23)-DB7)/DB9)) -> 0
D41: Share of period before mini-perm maturity | E41: factor | J41: =MIN(1,MAX(0,(MIN(J8,Inputs!$F$24)-J7)/J9)) -> 1 | K41: =MIN(1,MAX(0,(MIN(K8,Inputs!$F$24)-K7)/K9)) -> 1 | L41: =MIN(1,MAX(0,(MIN(L8,Inputs!$F$24)-L7)/L9)) -> 1 | M41: =MIN(1,MAX(0,(MIN(M8,Inputs!$F$24)-M7)/M9)) -> 1 | N41: =MIN(1,MAX(0,(MIN(N8,Inputs!$F$24)-N7)/N9)) -> 1 | O41: =MIN(1,MAX(0,(MIN(O8,Inputs!$F$24)-O7)/O9)) -> 1 | P41: =MIN(1,MAX(0,(MIN(P8,Inputs!$F$24)-P7)/P9)) -> 1 | Q41: =MIN(1,MAX(0,(MIN(Q8,Inputs!$F$24)-Q7)/Q9)) -> 1 | ... DB41: =MIN(1,MAX(0,(MIN(DB8,Inputs!$F$24)-DB7)/DB9)) -> 0
D42: Flag_MiniPermMaturity | E42: flag | J42: =IF(AND(J7<Inputs!$F$24,Inputs!$F$24<=J8),1,0) -> 0 | K42: =IF(AND(K7<Inputs!$F$24,Inputs!$F$24<=K8),1,0) -> 0 | L42: =IF(AND(L7<Inputs!$F$24,Inputs!$F$24<=L8),1,0) -> 0 | M42: =IF(AND(M7<Inputs!$F$24,Inputs!$F$24<=M8),1,0) -> 0 | N42: =IF(AND(N7<Inputs!$F$24,Inputs!$F$24<=N8),1,0) -> 0 | O42: =IF(AND(O7<Inputs!$F$24,Inputs!$F$24<=O8),1,0) -> 0 | P42: =IF(AND(P7<Inputs!$F$24,Inputs!$F$24<=P8),1,0) -> 0 | Q42: =IF(AND(Q7<Inputs!$F$24,Inputs!$F$24<=Q8),1,0) -> 0 | ... DB42: =IF(AND(DB7<Inputs!$F$24,Inputs!$F$24<=DB8),1,0) -> 0
D43: Flag_Hedged | E43: flag | J43: =IF(J8<=Inputs!$F$25,1,0) -> 1 | K43: =IF(K8<=Inputs!$F$25,1,0) -> 1 | L43: =IF(L8<=Inputs!$F$25,1,0) -> 1 | M43: =IF(M8<=Inputs!$F$25,1,0) -> 1 | N43: =IF(N8<=Inputs!$F$25,1,0) -> 1 | O43: =IF(O8<=Inputs!$F$25,1,0) -> 1 | P43: =IF(P8<=Inputs!$F$25,1,0) -> 1 | Q43: =IF(Q8<=Inputs!$F$25,1,0) -> 1 | ... DB43: =IF(DB8<=Inputs!$F$25,1,0) -> 0
D44: Flag_DSCRTest | E44: flag | J44: =IF(AND(J26=1,J8>=Inputs!$F$34),1,0) -> 0 | K44: =IF(AND(K26=1,K8>=Inputs!$F$34),1,0) -> 0 | L44: =IF(AND(L26=1,L8>=Inputs!$F$34),1,0) -> 0 | M44: =IF(AND(M26=1,M8>=Inputs!$F$34),1,0) -> 0 | N44: =IF(AND(N26=1,N8>=Inputs!$F$34),1,0) -> 0 | O44: =IF(AND(O26=1,O8>=Inputs!$F$34),1,0) -> 0 | P44: =IF(AND(P26=1,P8>=Inputs!$F$34),1,0) -> 0 | Q44: =IF(AND(Q26=1,Q8>=Inputs!$F$34),1,0) -> 0 | ... DB44: =IF(AND(DB26=1,DB8>=Inputs!$F$34),1,0) -> 1
D45: Flag_DefaultTest | E45: flag | J45: =IF(J8>=Inputs!$F$35,1,0) -> 0 | K45: =IF(K8>=Inputs!$F$35,1,0) -> 0 | L45: =IF(L8>=Inputs!$F$35,1,0) -> 0 | M45: =IF(M8>=Inputs!$F$35,1,0) -> 0 | N45: =IF(N8>=Inputs!$F$35,1,0) -> 0 | O45: =IF(O8>=Inputs!$F$35,1,0) -> 0 | P45: =IF(P8>=Inputs!$F$35,1,0) -> 0 | Q45: =IF(Q8>=Inputs!$F$35,1,0) -> 0 | ... DB45: =IF(DB8>=Inputs!$F$35,1,0) -> 1
D46: Flag_RetentionRelease | E46: flag | J46: =IF(AND(J7<EDATE($F$16,Inputs!$F$48),EDATE($F$16,Inputs!$F$48)<=J8),1,0) -> 0 | K46: =IF(AND(K7<EDATE($F$16,Inputs!$F$48),EDATE($F$16,Inputs!$F$48)<=K8),1,0) -> 0 | L46: =IF(AND(L7<EDATE($F$16,Inputs!$F$48),EDATE($F$16,Inputs!$F$48)<=L8),1,0) -> 0 | M46: =IF(AND(M7<EDATE($F$16,Inputs!$F$48),EDATE($F$16,Inputs!$F$48)<=M8),1,0) -> 0 | N46: =IF(AND(N7<EDATE($F$16,Inputs!$F$48),EDATE($F$16,Inputs!$F$48)<=N8),1,0) -> 0 | O46: =IF(AND(O7<EDATE($F$16,Inputs!$F$48),EDATE($F$16,Inputs!$F$48)<=O8),1,0) -> 0 | P46: =IF(AND(P7<EDATE($F$16,Inputs!$F$48),EDATE($F$16,Inputs!$F$48)<=P8),1,0) -> 0 | Q46: =IF(AND(Q7<EDATE($F$16,Inputs!$F$48),EDATE($F$16,Inputs!$F$48)<=Q8),1,0) -> 0 | ... DB46: =IF(AND(DB7<EDATE($F$16,Inputs!$F$48),EDATE($F$16,Inputs!$F$48)<=DB8),1,0) -> 0
D47: Flag_NILORepayment | E47: flag | J47: =IF(Inputs!$F$215=1,IF(AND(J8>=Inputs!$F$29,J8<=Inputs!$F$30),1,0),IF(AND(J8>=Inputs!$F$27,J8<=Inputs!$F$28),1,0)) -> 0 | K47: =IF(Inputs!$F$215=1,IF(AND(K8>=Inputs!$F$29,K8<=Inputs!$F$30),1,0),IF(AND(K8>=Inputs!$F$27,K8<=Inputs!$F$28),1,0)) -> 0 | L47: =IF(Inputs!$F$215=1,IF(AND(L8>=Inputs!$F$29,L8<=Inputs!$F$30),1,0),IF(AND(L8>=Inputs!$F$27,L8<=Inputs!$F$28),1,0)) -> 0 | M47: =IF(Inputs!$F$215=1,IF(AND(M8>=Inputs!$F$29,M8<=Inputs!$F$30),1,0),IF(AND(M8>=Inputs!$F$27,M8<=Inputs!$F$28),1,0)) -> 0 | N47: =IF(Inputs!$F$215=1,IF(AND(N8>=Inputs!$F$29,N8<=Inputs!$F$30),1,0),IF(AND(N8>=Inputs!$F$27,N8<=Inputs!$F$28),1,0)) -> 0 | O47: =IF(Inputs!$F$215=1,IF(AND(O8>=Inputs!$F$29,O8<=Inputs!$F$30),1,0),IF(AND(O8>=Inputs!$F$27,O8<=Inputs!$F$28),1,0)) -> 0 | P47: =IF(Inputs!$F$215=1,IF(AND(P8>=Inputs!$F$29,P8<=Inputs!$F$30),1,0),IF(AND(P8>=Inputs!$F$27,P8<=Inputs!$F$28),1,0)) -> 0 | Q47: =IF(Inputs!$F$215=1,IF(AND(Q8>=Inputs!$F$29,Q8<=Inputs!$F$30),1,0),IF(AND(Q8>=Inputs!$F$27,Q8<=Inputs!$F$28),1,0)) -> 0 | ... DB47: =IF(Inputs!$F$215=1,IF(AND(DB8>=Inputs!$F$29,DB8<=Inputs!$F$30),1,0),IF(AND(DB8>=Inputs!$F$27,DB8<=Inputs!$F$28),1,0)) -> 0
D48: Flag_NILOFirstRepayment | E48: flag | J48: =IF(AND(J47=1,I47=0),1,0) -> 0 | K48: =IF(AND(K47=1,J47=0),1,0) -> 0 | L48: =IF(AND(L47=1,K47=0),1,0) -> 0 | M48: =IF(AND(M47=1,L47=0),1,0) -> 0 | N48: =IF(AND(N47=1,M47=0),1,0) -> 0 | O48: =IF(AND(O47=1,N47=0),1,0) -> 0 | P48: =IF(AND(P47=1,O47=0),1,0) -> 0 | Q48: =IF(AND(Q47=1,P47=0),1,0) -> 0 | ... DB48: =IF(AND(DB47=1,DA47=0),1,0) -> 0
D49: Flag_NILOScheduleStart | E49: flag | J49: =IF(Inputs!$F$215=1,J36,J21) -> 0 | K49: =IF(Inputs!$F$215=1,K36,K21) -> 0 | L49: =IF(Inputs!$F$215=1,L36,L21) -> 0 | M49: =IF(Inputs!$F$215=1,M36,M21) -> 0 | N49: =IF(Inputs!$F$215=1,N36,N21) -> 0 | O49: =IF(Inputs!$F$215=1,O36,O21) -> 0 | P49: =IF(Inputs!$F$215=1,P36,P21) -> 0 | Q49: =IF(Inputs!$F$215=1,Q36,Q21) -> 0 | ... DB49: =IF(Inputs!$F$215=1,DB36,DB21) -> 0
D50: NILO interest rate | E50: % | J50: =IF(AND(J23=1,J8<=Inputs!$F$31),Inputs!$F$119,Inputs!$F$118) -> 0.0306 | K50: =IF(AND(K23=1,K8<=Inputs!$F$31),Inputs!$F$119,Inputs!$F$118) -> 0.0306 | L50: =IF(AND(L23=1,L8<=Inputs!$F$31),Inputs!$F$119,Inputs!$F$118) -> 0.0306 | M50: =IF(AND(M23=1,M8<=Inputs!$F$31),Inputs!$F$119,Inputs!$F$118) -> 0.0306 | N50: =IF(AND(N23=1,N8<=Inputs!$F$31),Inputs!$F$119,Inputs!$F$118) -> 0.0306 | O50: =IF(AND(O23=1,O8<=Inputs!$F$31),Inputs!$F$119,Inputs!$F$118) -> 0.0306 | P50: =IF(AND(P23=1,P8<=Inputs!$F$31),Inputs!$F$119,Inputs!$F$118) -> 0.0306 | Q50: =IF(AND(Q23=1,Q8<=Inputs!$F$31),Inputs!$F$119,Inputs!$F$118) -> 0.0306 | ... DB50: =IF(AND(DB23=1,DB8<=Inputs!$F$31),Inputs!$F$119,Inputs!$F$118) -> 0.0306
D51: NILO interest paid in cash (share) | E51: factor | J51: =IF(AND(J23=1,J8<=Inputs!$F$31),0,1-MIN(1,MAX(0,(MIN(J8,Inputs!$F$26)-J7)/J9))) -> 0 | K51: =IF(AND(K23=1,K8<=Inputs!$F$31),0,1-MIN(1,MAX(0,(MIN(K8,Inputs!$F$26)-K7)/K9))) -> 0 | L51: =IF(AND(L23=1,L8<=Inputs!$F$31),0,1-MIN(1,MAX(0,(MIN(L8,Inputs!$F$26)-L7)/L9))) -> 0 | M51: =IF(AND(M23=1,M8<=Inputs!$F$31),0,1-MIN(1,MAX(0,(MIN(M8,Inputs!$F$26)-M7)/M9))) -> 0 | N51: =IF(AND(N23=1,N8<=Inputs!$F$31),0,1-MIN(1,MAX(0,(MIN(N8,Inputs!$F$26)-N7)/N9))) -> 0 | O51: =IF(AND(O23=1,O8<=Inputs!$F$31),0,1-MIN(1,MAX(0,(MIN(O8,Inputs!$F$26)-O7)/O9))) -> 0 | P51: =IF(AND(P23=1,P8<=Inputs!$F$31),0,1-MIN(1,MAX(0,(MIN(P8,Inputs!$F$26)-P7)/P9))) -> 0 | Q51: =IF(AND(Q23=1,Q8<=Inputs!$F$31),0,1-MIN(1,MAX(0,(MIN(Q8,Inputs!$F$26)-Q7)/Q9))) -> 0 | ... DB51: =IF(AND(DB23=1,DB8<=Inputs!$F$31),0,1-MIN(1,MAX(0,(MIN(DB8,Inputs!$F$26)-DB7)/DB9))) -> 1
D52: Flag_SwapRemaining (after 2023-12-31) | E52: flag | J52: =IF(AND(J8>Inputs!$F$20,J43=1),1,0) -> 0 | K52: =IF(AND(K8>Inputs!$F$20,K43=1),1,0) -> 0 | L52: =IF(AND(L8>Inputs!$F$20,L43=1),1,0) -> 0 | M52: =IF(AND(M8>Inputs!$F$20,M43=1),1,0) -> 0 | N52: =IF(AND(N8>Inputs!$F$20,N43=1),1,0) -> 0 | O52: =IF(AND(O8>Inputs!$F$20,O43=1),1,0) -> 0 | P52: =IF(AND(P8>Inputs!$F$20,P43=1),1,0) -> 0 | Q52: =IF(AND(Q8>Inputs!$F$20,Q43=1),1,0) -> 0 | ... DB52: =IF(AND(DB8>Inputs!$F$20,DB43=1),1,0) -> 0
D53: Macro
D54: 6-month ABBR | E54: %pa | J54: =IFERROR(INDEX(Inputs!$J$259:$AG$259,MATCH(J13,Inputs!$J$258:$AG$258,0)),Inputs!$F$260) -> 2.31 | K54: =IFERROR(INDEX(Inputs!$J$259:$AG$259,MATCH(K13,Inputs!$J$258:$AG$258,0)),Inputs!$F$260) -> 2.18 | L54: =IFERROR(INDEX(Inputs!$J$259:$AG$259,MATCH(L13,Inputs!$J$258:$AG$258,0)),Inputs!$F$260) -> 2.18 | M54: =IFERROR(INDEX(Inputs!$J$259:$AG$259,MATCH(M13,Inputs!$J$258:$AG$258,0)),Inputs!$F$260) -> 2.02 | N54: =IFERROR(INDEX(Inputs!$J$259:$AG$259,MATCH(N13,Inputs!$J$258:$AG$258,0)),Inputs!$F$260) -> 2.02 | O54: =IFERROR(INDEX(Inputs!$J$259:$AG$259,MATCH(O13,Inputs!$J$258:$AG$258,0)),Inputs!$F$260) -> 1.84 | P54: =IFERROR(INDEX(Inputs!$J$259:$AG$259,MATCH(P13,Inputs!$J$258:$AG$258,0)),Inputs!$F$260) -> 1.84 | Q54: =IFERROR(INDEX(Inputs!$J$259:$AG$259,MATCH(Q13,Inputs!$J$258:$AG$258,0)),Inputs!$F$260) -> 1.79 | ... DB54: =IFERROR(INDEX(Inputs!$J$259:$AG$259,MATCH(DB13,Inputs!$J$258:$AG$258,0)),Inputs!$F$260) -> 3.5
D55: Ardmore CPI change for the year (selected path) | E55: %pa | J55: =IF(Inputs!$F$216=1,INDEX(Inputs!$J$257:$BE$257,MATCH(J11,Inputs!$J$255:$BE$255,0)),INDEX(Inputs!$J$256:$BE$256,MATCH(J11,Inputs!$J$255:$BE$255,0))) -> 1.6 | K55: =IF(Inputs!$F$216=1,INDEX(Inputs!$J$257:$BE$257,MATCH(K11,Inputs!$J$255:$BE$255,0)),INDEX(Inputs!$J$256:$BE$256,MATCH(K11,Inputs!$J$255:$BE$255,0))) -> 1.6 | L55: =IF(Inputs!$F$216=1,INDEX(Inputs!$J$257:$BE$257,MATCH(L11,Inputs!$J$255:$BE$255,0)),INDEX(Inputs!$J$256:$BE$256,MATCH(L11,Inputs!$J$255:$BE$255,0))) -> 1.6 | M55: =IF(Inputs!$F$216=1,INDEX(Inputs!$J$257:$BE$257,MATCH(M11,Inputs!$J$255:$BE$255,0)),INDEX(Inputs!$J$256:$BE$256,MATCH(M11,Inputs!$J$255:$BE$255,0))) -> 1.4 | N55: =IF(Inputs!$F$216=1,INDEX(Inputs!$J$257:$BE$257,MATCH(N11,Inputs!$J$255:$BE$255,0)),INDEX(Inputs!$J$256:$BE$256,MATCH(N11,Inputs!$J$255:$BE$255,0))) -> 1.4 | O55: =IF(Inputs!$F$216=1,INDEX(Inputs!$J$257:$BE$257,MATCH(O11,Inputs!$J$255:$BE$255,0)),INDEX(Inputs!$J$256:$BE$256,MATCH(O11,Inputs!$J$255:$BE$255,0))) -> 1.4 | P55: =IF(Inputs!$F$216=1,INDEX(Inputs!$J$257:$BE$257,MATCH(P11,Inputs!$J$255:$BE$255,0)),INDEX(Inputs!$J$256:$BE$256,MATCH(P11,Inputs!$J$255:$BE$255,0))) -> 1.4 | Q55: =IF(Inputs!$F$216=1,INDEX(Inputs!$J$257:$BE$257,MATCH(Q11,Inputs!$J$255:$BE$255,0)),INDEX(Inputs!$J$256:$BE$256,MATCH(Q11,Inputs!$J$255:$BE$255,0))) -> 1.9 | ... DB55: =IF(Inputs!$F$216=1,INDEX(Inputs!$J$257:$BE$257,MATCH(DB11,Inputs!$J$255:$BE$255,0)),INDEX(Inputs!$J$256:$BE$256,MATCH(DB11,Inputs!$J$255:$BE$255,0))) -> 2.5
D56: CPI factor (2015 = 1.0) | E56: factor | J56: =IF(J6=1,1,I56*IF(J11>I11,1+J55/100,1)) -> 1 | K56: =IF(K6=1,1,J56*IF(K11>J11,1+K55/100,1)) -> 1 | L56: =IF(L6=1,1,K56*IF(L11>K11,1+L55/100,1)) -> 1 | M56: =IF(M6=1,1,L56*IF(M11>L11,1+M55/100,1)) -> 1.014 | N56: =IF(N6=1,1,M56*IF(N11>M11,1+N55/100,1)) -> 1.014 | O56: =IF(O6=1,1,N56*IF(O11>N11,1+O55/100,1)) -> 1.014 | P56: =IF(P6=1,1,O56*IF(P11>O11,1+P55/100,1)) -> 1.014 | Q56: =IF(Q6=1,1,P56*IF(Q11>P11,1+Q55/100,1)) -> 1.033266 | ... DB56: =IF(DB6=1,1,DA56*IF(DB11>DA11,1+DB55/100,1)) -> 3.0976154
D57: CPI factor 2023 (2015 = 1.0) | E57: factor | F57: =IF(Inputs!$F$216=1,EXP(SUMPRODUCT((Inputs!$J$255:$BE$255>=Inputs!$F$61)*(Inputs!$J$255:$BE$255<=Inputs!$F$62)*LN(1+Inputs!$J$257:$BE$257/100))),EXP(SUMPRODUCT((Inputs!$J$255:$BE$255>=Inputs!$F$61)*(Inputs!$J$255:$BE$255<=Inputs!$F$62)*LN(1+Inputs!$J$256:$BE$256/100)))) -> 1.2598586
D58: Flag_TollEscalation (contains July 1) | E58: flag | J58: =IF(AND(J7<DATE(J11,Inputs!$F$51,1),DATE(J11,Inputs!$F$51,1)<=J8),1,0) -> 0 | K58: =IF(AND(K7<DATE(K11,Inputs!$F$51,1),DATE(K11,Inputs!$F$51,1)<=K8),1,0) -> 1 | L58: =IF(AND(L7<DATE(L11,Inputs!$F$51,1),DATE(L11,Inputs!$F$51,1)<=L8),1,0) -> 0 | M58: =IF(AND(M7<DATE(M11,Inputs!$F$51,1),DATE(M11,Inputs!$F$51,1)<=M8),1,0) -> 0 | N58: =IF(AND(N7<DATE(N11,Inputs!$F$51,1),DATE(N11,Inputs!$F$51,1)<=N8),1,0) -> 0 | O58: =IF(AND(O7<DATE(O11,Inputs!$F$51,1),DATE(O11,Inputs!$F$51,1)<=O8),1,0) -> 1 | P58: =IF(AND(P7<DATE(P11,Inputs!$F$51,1),DATE(P11,Inputs!$F$51,1)<=P8),1,0) -> 0 | Q58: =IF(AND(Q7<DATE(Q11,Inputs!$F$51,1),DATE(Q11,Inputs!$F$51,1)<=Q8),1,0) -> 0 | ... DB58: =IF(AND(DB7<DATE(DB11,Inputs!$F$51,1),DATE(DB11,Inputs!$F$51,1)<=DB8),1,0) -> 0
D59: Toll escalation factor | E59: factor | J59: =IF(OR(Inputs!$F$220=1,AND(Inputs!$F$215=1,J11>=Inputs!$F$54),J11>Inputs!$F$53),1+J55/100,MAX(1+J55/100,1+Inputs!$F$126)) -> 1.03 | K59: =IF(OR(Inputs!$F$220=1,AND(Inputs!$F$215=1,K11>=Inputs!$F$54),K11>Inputs!$F$53),1+K55/100,MAX(1+K55/100,1+Inputs!$F$126)) -> 1.03 | L59: =IF(OR(Inputs!$F$220=1,AND(Inputs!$F$215=1,L11>=Inputs!$F$54),L11>Inputs!$F$53),1+L55/100,MAX(1+L55/100,1+Inputs!$F$126)) -> 1.03 | M59: =IF(OR(Inputs!$F$220=1,AND(Inputs!$F$215=1,M11>=Inputs!$F$54),M11>Inputs!$F$53),1+M55/100,MAX(1+M55/100,1+Inputs!$F$126)) -> 1.03 | N59: =IF(OR(Inputs!$F$220=1,AND(Inputs!$F$215=1,N11>=Inputs!$F$54),N11>Inputs!$F$53),1+N55/100,MAX(1+N55/100,1+Inputs!$F$126)) -> 1.03 | O59: =IF(OR(Inputs!$F$220=1,AND(Inputs!$F$215=1,O11>=Inputs!$F$54),O11>Inputs!$F$53),1+O55/100,MAX(1+O55/100,1+Inputs!$F$126)) -> 1.03 | P59: =IF(OR(Inputs!$F$220=1,AND(Inputs!$F$215=1,P11>=Inputs!$F$54),P11>Inputs!$F$53),1+P55/100,MAX(1+P55/100,1+Inputs!$F$126)) -> 1.03 | Q59: =IF(OR(Inputs!$F$220=1,AND(Inputs!$F$215=1,Q11>=Inputs!$F$54),Q11>Inputs!$F$53),1+Q55/100,MAX(1+Q55/100,1+Inputs!$F$126)) -> 1.03 | ... DB59: =IF(OR(Inputs!$F$220=1,AND(Inputs!$F$215=1,DB11>=Inputs!$F$54),DB11>Inputs!$F$53),1+DB55/100,MAX(1+DB55/100,1+Inputs!$F$126)) -> 1.025
D60: Car toll per km | E60: ARD/km | J60: =IF(J6=1,IF(J58=1,ROUND(Inputs!$F$125*J59,Inputs!$F$52),Inputs!$F$125),IF(J58=1,ROUND(I60*J59,Inputs!$F$52),I60)) -> 0.1525 | K60: =IF(K6=1,IF(K58=1,ROUND(Inputs!$F$125*K59,Inputs!$F$52),Inputs!$F$125),IF(K58=1,ROUND(J60*K59,Inputs!$F$52),J60)) -> 0.1571 | L60: =IF(L6=1,IF(L58=1,ROUND(Inputs!$F$125*L59,Inputs!$F$52),Inputs!$F$125),IF(L58=1,ROUND(K60*L59,Inputs!$F$52),K60)) -> 0.1571 | M60: =IF(M6=1,IF(M58=1,ROUND(Inputs!$F$125*M59,Inputs!$F$52),Inputs!$F$125),IF(M58=1,ROUND(L60*M59,Inputs!$F$52),L60)) -> 0.1571 | N60: =IF(N6=1,IF(N58=1,ROUND(Inputs!$F$125*N59,Inputs!$F$52),Inputs!$F$125),IF(N58=1,ROUND(M60*N59,Inputs!$F$52),M60)) -> 0.1571 | O60: =IF(O6=1,IF(O58=1,ROUND(Inputs!$F$125*O59,Inputs!$F$52),Inputs!$F$125),IF(O58=1,ROUND(N60*O59,Inputs!$F$52),N60)) -> 0.1618 | P60: =IF(P6=1,IF(P58=1,ROUND(Inputs!$F$125*P59,Inputs!$F$52),Inputs!$F$125),IF(P58=1,ROUND(O60*P59,Inputs!$F$52),O60)) -> 0.1618 | Q60: =IF(Q6=1,IF(Q58=1,ROUND(Inputs!$F$125*Q59,Inputs!$F$52),Inputs!$F$125),IF(Q58=1,ROUND(P60*Q59,Inputs!$F$52),P60)) -> 0.1618 | ... DB60: =IF(DB6=1,IF(DB58=1,ROUND(Inputs!$F$125*DB59,Inputs!$F$52),Inputs!$F$125),IF(DB58=1,ROUND(DA60*DB59,Inputs!$F$52),DA60)) -> 0.5102

Sheet Construction
D1: Case T: Merrick Link toll road PPP | Construction
D2: Units: ARD millions unless stated. Inputs blue on yellow; links green; calculations black.
D3: Period end | E3: date | J3: =Time!J8 -> 42185 | K3: =Time!K8 -> 42277 | L3: =Time!L8 -> 42369 | M3: =Time!M8 -> 42460 | N3: =Time!N8 -> 42551 | O3: =Time!O8 -> 42643 | P3: =Time!P8 -> 42735 | Q3: =Time!Q8 -> 42825 | ... DB3: =Time!DB8 -> 58256
D5: Construction costs (paid at period end)
D6: D&C contract payments (incl. 5% retention at completion) | E6: ARD m | G6: =SUM(J6:DB6) -> 1684.3 | J6: =Inputs!$F$68*Inputs!J267+IF(Time!J8=Inputs!$F$15,Inputs!$F$68*(Inputs!$F$69+Inputs!$F$70),0) -> 2.7487776 | K6: =Inputs!$F$68*Inputs!K267+IF(Time!K8=Inputs!$F$15,Inputs!$F$68*(Inputs!$F$69+Inputs!$F$70),0) -> 21.656729 | L6: =Inputs!$F$68*Inputs!L267+IF(Time!L8=Inputs!$F$15,Inputs!$F$68*(Inputs!$F$69+Inputs!$F$70),0) -> 52.144244 | M6: =Inputs!$F$68*Inputs!M267+IF(Time!M8=Inputs!$F$15,Inputs!$F$68*(Inputs!$F$69+Inputs!$F$70),0) -> 87.622339 | N6: =Inputs!$F$68*Inputs!N267+IF(Time!N8=Inputs!$F$15,Inputs!$F$68*(Inputs!$F$69+Inputs!$F$70),0) -> 122.59683 | O6: =Inputs!$F$68*Inputs!O267+IF(Time!O8=Inputs!$F$15,Inputs!$F$68*(Inputs!$F$69+Inputs!$F$70),0) -> 152.67337 | P6: =Inputs!$F$68*Inputs!P267+IF(Time!P8=Inputs!$F$15,Inputs!$F$68*(Inputs!$F$69+Inputs!$F$70),0) -> 174.5558 | Q6: =Inputs!$F$68*Inputs!Q267+IF(Time!Q8=Inputs!$F$15,Inputs!$F$68*(Inputs!$F$69+Inputs!$F$70),0) -> 186.04609 | ... DB6: =Inputs!$F$68*Inputs!DB267+IF(Time!DB8=Inputs!$F$15,Inputs!$F$68*(Inputs!$F$69+Inputs!$F$70),0) -> 0
D7: Development and bid costs | E7: ARD m | G7: =SUM(J7:DB7) -> 41.2 | J7: =IF(Time!J6=1,Inputs!$F$71,0) -> 41.2 | K7: =IF(Time!K6=1,Inputs!$F$71,0) -> 0 | L7: =IF(Time!L6=1,Inputs!$F$71,0) -> 0 | M7: =IF(Time!M6=1,Inputs!$F$71,0) -> 0 | N7: =IF(Time!N6=1,Inputs!$F$71,0) -> 0 | O7: =IF(Time!O6=1,Inputs!$F$71,0) -> 0 | P7: =IF(Time!P6=1,Inputs!$F$71,0) -> 0 | Q7: =IF(Time!Q6=1,Inputs!$F$71,0) -> 0 | ... DB7: =IF(Time!DB6=1,Inputs!$F$71,0) -> 0
D8: Project company costs | E8: ARD m | G8: =SUM(J8:DB8) -> 37.8 | J8: =Inputs!$F$72*Time!J9/Time!$F$18*Time!J20 -> 0.91538462 | K8: =Inputs!$F$72*Time!K9/Time!$F$18*Time!K20 -> 2.4769231 | L8: =Inputs!$F$72*Time!L9/Time!$F$18*Time!L20 -> 2.4769231 | M8: =Inputs!$F$72*Time!M9/Time!$F$18*Time!M20 -> 2.45 | N8: =Inputs!$F$72*Time!N9/Time!$F$18*Time!N20 -> 2.45 | O8: =Inputs!$F$72*Time!O9/Time!$F$18*Time!O20 -> 2.4769231 | P8: =Inputs!$F$72*Time!P9/Time!$F$18*Time!P20 -> 2.4769231 | Q8: =Inputs!$F$72*Time!Q9/Time!$F$18*Time!Q20 -> 2.4230769 | ... DB8: =Inputs!$F$72*Time!DB9/Time!$F$18*Time!DB20 -> 0
D9: Insurance during construction | E9: ARD m | G9: =SUM(J9:DB9) -> 12.6 | J9: =IF(Time!J6=1,Inputs!$F$73*Inputs!$F$74,IF(Time!J8=Inputs!$F$37,Inputs!$F$73*(1-Inputs!$F$74),0)) -> 10.08 | K9: =IF(Time!K6=1,Inputs!$F$73*Inputs!$F$74,IF(Time!K8=Inputs!$F$37,Inputs!$F$73*(1-Inputs!$F$74),0)) -> 0 | L9: =IF(Time!L6=1,Inputs!$F$73*Inputs!$F$74,IF(Time!L8=Inputs!$F$37,Inputs!$F$73*(1-Inputs!$F$74),0)) -> 0 | M9: =IF(Time!M6=1,Inputs!$F$73*Inputs!$F$74,IF(Time!M8=Inputs!$F$37,Inputs!$F$73*(1-Inputs!$F$74),0)) -> 0 | N9: =IF(Time!N6=1,Inputs!$F$73*Inputs!$F$74,IF(Time!N8=Inputs!$F$37,Inputs!$F$73*(1-Inputs!$F$74),0)) -> 0 | O9: =IF(Time!O6=1,Inputs!$F$73*Inputs!$F$74,IF(Time!O8=Inputs!$F$37,Inputs!$F$73*(1-Inputs!$F$74),0)) -> 0 | P9: =IF(Time!P6=1,Inputs!$F$73*Inputs!$F$74,IF(Time!P8=Inputs!$F$37,Inputs!$F$73*(1-Inputs!$F$74),0)) -> 0 | Q9: =IF(Time!Q6=1,Inputs!$F$73*Inputs!$F$74,IF(Time!Q8=Inputs!$F$37,Inputs!$F$73*(1-Inputs!$F$74),0)) -> 0 | ... DB9: =IF(Time!DB6=1,Inputs!$F$73*Inputs!$F$74,IF(Time!DB8=Inputs!$F$37,Inputs!$F$73*(1-Inputs!$F$74),0)) -> 0
D10: Independent certifier | E10: ARD m | G10: =SUM(J10:DB10) -> 3.4 | J10: =Inputs!$F$75*Time!J9/Time!$F$18*Time!J20 -> 0.082336182 | K10: =Inputs!$F$75*Time!K9/Time!$F$18*Time!K20 -> 0.22279202 | L10: =Inputs!$F$75*Time!L9/Time!$F$18*Time!L20 -> 0.22279202 | M10: =Inputs!$F$75*Time!M9/Time!$F$18*Time!M20 -> 0.22037037 | N10: =Inputs!$F$75*Time!N9/Time!$F$18*Time!N20 -> 0.22037037 | O10: =Inputs!$F$75*Time!O9/Time!$F$18*Time!O20 -> 0.22279202 | P10: =Inputs!$F$75*Time!P9/Time!$F$18*Time!P20 -> 0.22279202 | Q10: =Inputs!$F$75*Time!Q9/Time!$F$18*Time!Q20 -> 0.21794872 | ... DB10: =Inputs!$F$75*Time!DB9/Time!$F$18*Time!DB20 -> 0
D11: Lenders' advisors and legal | E11: ARD m | G11: =SUM(J11:DB11) -> 9.7 | J11: =Inputs!$F$76*Time!J9/Time!$F$18*Time!J20 -> 0.23490028 | K11: =Inputs!$F$76*Time!K9/Time!$F$18*Time!K20 -> 0.63561254 | L11: =Inputs!$F$76*Time!L9/Time!$F$18*Time!L20 -> 0.63561254 | M11: =Inputs!$F$76*Time!M9/Time!$F$18*Time!M20 -> 0.6287037 | N11: =Inputs!$F$76*Time!N9/Time!$F$18*Time!N20 -> 0.6287037 | O11: =Inputs!$F$76*Time!O9/Time!$F$18*Time!O20 -> 0.63561254 | P11: =Inputs!$F$76*Time!P9/Time!$F$18*Time!P20 -> 0.63561254 | Q11: =Inputs!$F$76*Time!Q9/Time!$F$18*Time!Q20 -> 0.62179487 | ... DB11: =Inputs!$F$76*Time!DB9/Time!$F$18*Time!DB20 -> 0
D12: Contingency | E12: ARD m | G12: =SUM(J12:DB12) -> 52.4 | J12: =Inputs!$F$77*Inputs!J267/SUM(Inputs!$J$267:$DB$267) -> 0.090017684 | K12: =Inputs!$F$77*Inputs!K267/SUM(Inputs!$J$267:$DB$267) -> 0.70922021 | L12: =Inputs!$F$77*Inputs!L267/SUM(Inputs!$J$267:$DB$267) -> 1.7076333 | M12: =Inputs!$F$77*Inputs!M267/SUM(Inputs!$J$267:$DB$267) -> 2.8694792 | N12: =Inputs!$F$77*Inputs!N267/SUM(Inputs!$J$267:$DB$267) -> 4.0148328 | O12: =Inputs!$F$77*Inputs!O267/SUM(Inputs!$J$267:$DB$267) -> 4.9997874 | P12: =Inputs!$F$77*Inputs!P267/SUM(Inputs!$J$267:$DB$267) -> 5.7163987 | Q12: =Inputs!$F$77*Inputs!Q267/SUM(Inputs!$J$267:$DB$267) -> 6.0926859 | ... DB12: =Inputs!$F$77*Inputs!DB267/SUM(Inputs!$J$267:$DB$267) -> 0
D13: Total construction costs before financing | E13: ARD m | G13: =SUM(J13:DB13) -> 1841.4 | J13: =J6+J7+J8+J9+J10+J11+J12 -> 55.351416 | K13: =K6+K7+K8+K9+K10+K11+K12 -> 25.701277 | L13: =L6+L7+L8+L9+L10+L11+L12 -> 57.187205 | M13: =M6+M7+M8+M9+M10+M11+M12 -> 93.790892 | N13: =N6+N7+N8+N9+N10+N11+N12 -> 129.91074 | O13: =O6+O7+O8+O9+O10+O11+O12 -> 161.00849 | P13: =P6+P7+P8+P9+P10+P11+P12 -> 183.60753 | Q13: =Q6+Q7+Q8+Q9+Q10+Q11+Q12 -> 195.4016 | ... DB13: =DB6+DB7+DB8+DB9+DB10+DB11+DB12 -> 0
D14: Retention deposited at completion (released after defects period) | E14: ARD m | G14: =SUM(J14:DB14) -> 42.1075 | J14: =IF(Time!J8=Inputs!$F$15,Inputs!$F$68*Inputs!$F$70,0) -> 0 | K14: =IF(Time!K8=Inputs!$F$15,Inputs!$F$68*Inputs!$F$70,0) -> 0 | L14: =IF(Time!L8=Inputs!$F$15,Inputs!$F$68*Inputs!$F$70,0) -> 0 | M14: =IF(Time!M8=Inputs!$F$15,Inputs!$F$68*Inputs!$F$70,0) -> 0 | N14: =IF(Time!N8=Inputs!$F$15,Inputs!$F$68*Inputs!$F$70,0) -> 0 | O14: =IF(Time!O8=Inputs!$F$15,Inputs!$F$68*Inputs!$F$70,0) -> 0 | P14: =IF(Time!P8=Inputs!$F$15,Inputs!$F$68*Inputs!$F$70,0) -> 0 | Q14: =IF(Time!Q8=Inputs!$F$15,Inputs!$F$68*Inputs!$F$70,0) -> 0 | ... DB14: =IF(Time!DB8=Inputs!$F$15,Inputs!$F$68*Inputs!$F$70,0) -> 0

Sheet Operations
D1: Case T: Merrick Link toll road PPP | Operations
D2: Units: ARD millions unless stated. Inputs blue on yellow; links green; calculations black.
D3: Period end | E3: date | J3: =Time!J8 -> 42185 | K3: =Time!K8 -> 42277 | L3: =Time!L8 -> 42369 | M3: =Time!M8 -> 42460 | N3: =Time!N8 -> 42551 | O3: =Time!O8 -> 42643 | P3: =Time!P8 -> 42735 | Q3: =Time!Q8 -> 42825 | ... DB3: =Time!DB8 -> 58256
D5: Traffic
D6: Growth rate for the year | E6: %pa | J6: =IF(Time!J11<=Inputs!$F$55,Inputs!$F$243,IF(Time!J11<=Inputs!$F$56,Inputs!$F$244,Inputs!$F$245)) -> 2.6 | K6: =IF(Time!K11<=Inputs!$F$55,Inputs!$F$243,IF(Time!K11<=Inputs!$F$56,Inputs!$F$244,Inputs!$F$245)) -> 2.6 | L6: =IF(Time!L11<=Inputs!$F$55,Inputs!$F$243,IF(Time!L11<=Inputs!$F$56,Inputs!$F$244,Inputs!$F$245)) -> 2.6 | M6: =IF(Time!M11<=Inputs!$F$55,Inputs!$F$243,IF(Time!M11<=Inputs!$F$56,Inputs!$F$244,Inputs!$F$245)) -> 2.6 | N6: =IF(Time!N11<=Inputs!$F$55,Inputs!$F$243,IF(Time!N11<=Inputs!$F$56,Inputs!$F$244,Inputs!$F$245)) -> 2.6 | O6: =IF(Time!O11<=Inputs!$F$55,Inputs!$F$243,IF(Time!O11<=Inputs!$F$56,Inputs!$F$244,Inputs!$F$245)) -> 2.6 | P6: =IF(Time!P11<=Inputs!$F$55,Inputs!$F$243,IF(Time!P11<=Inputs!$F$56,Inputs!$F$244,Inputs!$F$245)) -> 2.6 | Q6: =IF(Time!Q11<=Inputs!$F$55,Inputs!$F$243,IF(Time!Q11<=Inputs!$F$56,Inputs!$F$244,Inputs!$F$245)) -> 2.6 | ... DB6: =IF(Time!DB11<=Inputs!$F$55,Inputs!$F$243,IF(Time!DB11<=Inputs!$F$56,Inputs!$F$244,Inputs!$F$245)) -> 0.9
D7: Underlying traffic level | E7: k/day | J7: =IF(Time!J11<=Inputs!$F$242,Inputs!$F$241/(1+Inputs!$F$243/100)^(Inputs!$F$242-Time!J11),I7*IF(Time!J11>Time!I11,1+J6/100,1)) -> 34.69211 | K7: =IF(Time!K11<=Inputs!$F$242,Inputs!$F$241/(1+Inputs!$F$243/100)^(Inputs!$F$242-Time!K11),J7*IF(Time!K11>Time!J11,1+K6/100,1)) -> 34.69211 | L7: =IF(Time!L11<=Inputs!$F$242,Inputs!$F$241/(1+Inputs!$F$243/100)^(Inputs!$F$242-Time!L11),K7*IF(Time!L11>Time!K11,1+L6/100,1)) -> 34.69211 | M7: =IF(Time!M11<=Inputs!$F$242,Inputs!$F$241/(1+Inputs!$F$243/100)^(Inputs!$F$242-Time!M11),L7*IF(Time!M11>Time!L11,1+M6/100,1)) -> 35.594105 | N7: =IF(Time!N11<=Inputs!$F$242,Inputs!$F$241/(1+Inputs!$F$243/100)^(Inputs!$F$242-Time!N11),M7*IF(Time!N11>Time!M11,1+N6/100,1)) -> 35.594105 | O7: =IF(Time!O11<=Inputs!$F$242,Inputs!$F$241/(1+Inputs!$F$243/100)^(Inputs!$F$242-Time!O11),N7*IF(Time!O11>Time!N11,1+O6/100,1)) -> 35.594105 | P7: =IF(Time!P11<=Inputs!$F$242,Inputs!$F$241/(1+Inputs!$F$243/100)^(Inputs!$F$242-Time!P11),O7*IF(Time!P11>Time!O11,1+P6/100,1)) -> 35.594105 | Q7: =IF(Time!Q11<=Inputs!$F$242,Inputs!$F$241/(1+Inputs!$F$243/100)^(Inputs!$F$242-Time!Q11),P7*IF(Time!Q11>Time!P11,1+Q6/100,1)) -> 36.519551 | ... DB7: =IF(Time!DB11<=Inputs!$F$242,Inputs!$F$241/(1+Inputs!$F$243/100)^(Inputs!$F$242-Time!DB11),DA7*IF(Time!DB11>Time!DA11,1+DB6/100,1)) -> 72.252198
D8: Ramp-up table year | E8: year | J8: =MAX(Inputs!$F$57,MIN(Inputs!$F$58,Time!J11-Inputs!$F$219)) -> 2019 | K8: =MAX(Inputs!$F$57,MIN(Inputs!$F$58,Time!K11-Inputs!$F$219)) -> 2019 | L8: =MAX(Inputs!$F$57,MIN(Inputs!$F$58,Time!L11-Inputs!$F$219)) -> 2019 | M8: =MAX(Inputs!$F$57,MIN(Inputs!$F$58,Time!M11-Inputs!$F$219)) -> 2019 | N8: =MAX(Inputs!$F$57,MIN(Inputs!$F$58,Time!N11-Inputs!$F$219)) -> 2019 | O8: =MAX(Inputs!$F$57,MIN(Inputs!$F$58,Time!O11-Inputs!$F$219)) -> 2019 | P8: =MAX(Inputs!$F$57,MIN(Inputs!$F$58,Time!P11-Inputs!$F$219)) -> 2019 | Q8: =MAX(Inputs!$F$57,MIN(Inputs!$F$58,Time!Q11-Inputs!$F$219)) -> 2019 | ... DB8: =MAX(Inputs!$F$57,MIN(Inputs!$F$58,Time!DB11-Inputs!$F$219)) -> 2023
D9: Ramp-up factor | E9: factor | J9: =CHOOSE(J8-Inputs!$F$57+1,Inputs!$F$248,Inputs!$F$249,Inputs!$F$250,Inputs!$F$251,Inputs!$F$252) -> 1 | K9: =CHOOSE(K8-Inputs!$F$57+1,Inputs!$F$248,Inputs!$F$249,Inputs!$F$250,Inputs!$F$251,Inputs!$F$252) -> 1 | L9: =CHOOSE(L8-Inputs!$F$57+1,Inputs!$F$248,Inputs!$F$249,Inputs!$F$250,Inputs!$F$251,Inputs!$F$252) -> 1 | M9: =CHOOSE(M8-Inputs!$F$57+1,Inputs!$F$248,Inputs!$F$249,Inputs!$F$250,Inputs!$F$251,Inputs!$F$252) -> 1 | N9: =CHOOSE(N8-Inputs!$F$57+1,Inputs!$F$248,Inputs!$F$249,Inputs!$F$250,Inputs!$F$251,Inputs!$F$252) -> 1 | O9: =CHOOSE(O8-Inputs!$F$57+1,Inputs!$F$248,Inputs!$F$249,Inputs!$F$250,Inputs!$F$251,Inputs!$F$252) -> 1 | P9: =CHOOSE(P8-Inputs!$F$57+1,Inputs!$F$248,Inputs!$F$249,Inputs!$F$250,Inputs!$F$251,Inputs!$F$252) -> 1 | Q9: =CHOOSE(Q8-Inputs!$F$57+1,Inputs!$F$248,Inputs!$F$249,Inputs!$F$250,Inputs!$F$251,Inputs!$F$252) -> 1 | ... DB9: =CHOOSE(DB8-Inputs!$F$57+1,Inputs!$F$248,Inputs!$F$249,Inputs!$F$250,Inputs!$F$251,Inputs!$F$252) -> 1
D10: Heavy-vehicle uplift factor | E10: factor | J10: =IF(Time!J11>=Inputs!$F$59,1+Inputs!$F$246/100,1) -> 1 | K10: =IF(Time!K11>=Inputs!$F$59,1+Inputs!$F$246/100,1) -> 1 | L10: =IF(Time!L11>=Inputs!$F$59,1+Inputs!$F$246/100,1) -> 1 | M10: =IF(Time!M11>=Inputs!$F$59,1+Inputs!$F$246/100,1) -> 1 | N10: =IF(Time!N11>=Inputs!$F$59,1+Inputs!$F$246/100,1) -> 1 | O10: =IF(Time!O11>=Inputs!$F$59,1+Inputs!$F$246/100,1) -> 1 | P10: =IF(Time!P11>=Inputs!$F$59,1+Inputs!$F$246/100,1) -> 1 | Q10: =IF(Time!Q11>=Inputs!$F$59,1+Inputs!$F$246/100,1) -> 1 | ... DB10: =IF(Time!DB11>=Inputs!$F$59,1+Inputs!$F$246/100,1) -> 1.024
D11: Forecast traffic | E11: k/day | J11: =J7*J9*J10*Inputs!$F$218 -> 34.69211 | K11: =K7*K9*K10*Inputs!$F$218 -> 34.69211 | L11: =L7*L9*L10*Inputs!$F$218 -> 34.69211 | M11: =M7*M9*M10*Inputs!$F$218 -> 35.594105 | N11: =N7*N9*N10*Inputs!$F$218 -> 35.594105 | O11: =O7*O9*O10*Inputs!$F$218 -> 35.594105 | P11: =P7*P9*P10*Inputs!$F$218 -> 35.594105 | Q11: =Q7*Q9*Q10*Inputs!$F$218 -> 36.519551 | ... DB11: =DB7*DB9*DB10*Inputs!$F$218 -> 73.986251
D12: Actual traffic | E12: k/day | J12: =IFERROR(INDEX(Inputs!$J$262:$X$262,MATCH(Time!J13,Inputs!$J$261:$X$261,0)),0) -> 0 | K12: =IFERROR(INDEX(Inputs!$J$262:$X$262,MATCH(Time!K13,Inputs!$J$261:$X$261,0)),0) -> 0 | L12: =IFERROR(INDEX(Inputs!$J$262:$X$262,MATCH(Time!L13,Inputs!$J$261:$X$261,0)),0) -> 0 | M12: =IFERROR(INDEX(Inputs!$J$262:$X$262,MATCH(Time!M13,Inputs!$J$261:$X$261,0)),0) -> 0 | N12: =IFERROR(INDEX(Inputs!$J$262:$X$262,MATCH(Time!N13,Inputs!$J$261:$X$261,0)),0) -> 0 | O12: =IFERROR(INDEX(Inputs!$J$262:$X$262,MATCH(Time!O13,Inputs!$J$261:$X$261,0)),0) -> 0 | P12: =IFERROR(INDEX(Inputs!$J$262:$X$262,MATCH(Time!P13,Inputs!$J$261:$X$261,0)),0) -> 0 | Q12: =IFERROR(INDEX(Inputs!$J$262:$X$262,MATCH(Time!Q13,Inputs!$J$261:$X$261,0)),0) -> 0 | ... DB12: =IFERROR(INDEX(Inputs!$J$262:$X$262,MATCH(Time!DB13,Inputs!$J$261:$X$261,0)),0) -> 0
D13: Traffic used (average daily trips) | E13: k/day | J13: =IF(Time!J39=1,J12,J11)*Time!J26 -> 0 | K13: =IF(Time!K39=1,K12,K11)*Time!K26 -> 0 | L13: =IF(Time!L39=1,L12,L11)*Time!L26 -> 0 | M13: =IF(Time!M39=1,M12,M11)*Time!M26 -> 0 | N13: =IF(Time!N39=1,N12,N11)*Time!N26 -> 0 | O13: =IF(Time!O39=1,O12,O11)*Time!O26 -> 0 | P13: =IF(Time!P39=1,P12,P11)*Time!P26 -> 0 | Q13: =IF(Time!Q39=1,Q12,Q11)*Time!Q26 -> 0 | ... DB13: =IF(Time!DB39=1,DB12,DB11)*Time!DB26 -> 73.986251
D14: Toll revenue
D15: Weighted class multiplier, original | E15: factor | F15: =((Inputs!$F$129-Inputs!$F$224)*Inputs!$F$138+Inputs!$F$130*Inputs!$F$135+(Inputs!$F$131+Inputs!$F$224)*Inputs!$F$136)/100 -> 1.2686
D16: Weighted class multiplier, from 2024 (restructured) | E16: factor | F16: =(Inputs!$F$132*Inputs!$F$138+Inputs!$F$133*Inputs!$F$135+Inputs!$F$134*Inputs!$F$137)/100 -> 1.2448
D17: Weighted class multiplier | E17: factor | J17: =IF(Time!J23=1,$F$16,$F$15) -> 1.2686 | K17: =IF(Time!K23=1,$F$16,$F$15) -> 1.2686 | L17: =IF(Time!L23=1,$F$16,$F$15) -> 1.2686 | M17: =IF(Time!M23=1,$F$16,$F$15) -> 1.2686 | N17: =IF(Time!N23=1,$F$16,$F$15) -> 1.2686 | O17: =IF(Time!O23=1,$F$16,$F$15) -> 1.2686 | P17: =IF(Time!P23=1,$F$16,$F$15) -> 1.2686 | Q17: =IF(Time!Q23=1,$F$16,$F$15) -> 1.2686 | ... DB17: =IF(Time!DB23=1,$F$16,$F$15) -> 1.2448
D18: Gross toll revenue | E18: ARD m | G18: =SUM(J18:DB18) -> 8675.2587 | J18: =J13*Inputs!$F$64*Time!J25*Inputs!$F$127*Time!J60*J17/Inputs!$F$65 -> 0 | K18: =K13*Inputs!$F$64*Time!K25*Inputs!$F$127*Time!K60*K17/Inputs!$F$65 -> 0 | L18: =L13*Inputs!$F$64*Time!L25*Inputs!$F$127*Time!L60*L17/Inputs!$F$65 -> 0 | M18: =M13*Inputs!$F$64*Time!M25*Inputs!$F$127*Time!M60*M17/Inputs!$F$65 -> 0 | N18: =N13*Inputs!$F$64*Time!N25*Inputs!$F$127*Time!N60*N17/Inputs!$F$65 -> 0 | O18: =O13*Inputs!$F$64*Time!O25*Inputs!$F$127*Time!O60*O17/Inputs!$F$65 -> 0 | P18: =P13*Inputs!$F$64*Time!P25*Inputs!$F$127*Time!P60*P17/Inputs!$F$65 -> 0 | Q18: =Q13*Inputs!$F$64*Time!Q25*Inputs!$F$127*Time!Q60*Q17/Inputs!$F$65 -> 0 | ... DB18: =DB13*Inputs!$F$64*Time!DB25*Inputs!$F$127*Time!DB60*DB17/Inputs!$F$65 -> 163.27544
D19: Revenue leakage | E19: ARD m | G19: =SUM(J19:DB19) -> 156.15466 | J19: =J18*Inputs!$F$128 -> 0 | K19: =K18*Inputs!$F$128 -> 0 | L19: =L18*Inputs!$F$128 -> 0 | M19: =M18*Inputs!$F$128 -> 0 | N19: =N18*Inputs!$F$128 -> 0 | O19: =O18*Inputs!$F$128 -> 0 | P19: =P18*Inputs!$F$128 -> 0 | Q19: =Q18*Inputs!$F$128 -> 0 | ... DB19: =DB18*Inputs!$F$128 -> 2.9389579
D20: Net toll revenue | E20: ARD m | G20: =SUM(J20:DB20) -> 8519.1041 | J20: =J18-J19 -> 0 | K20: =K18-K19 -> 0 | L20: =L18-L19 -> 0 | M20: =M18-M19 -> 0 | N20: =N18-N19 -> 0 | O20: =O18-O19 -> 0 | P20: =P18-P19 -> 0 | Q20: =Q18-Q19 -> 0 | ... DB20: =DB18-DB19 -> 160.33648
D21: Delay liquidated damages received | E21: ARD m | G21: =SUM(J21:DB21) -> 10.26 | J21: =IF(AND(Inputs!$F$213=1,Time!J27=1),Inputs!$F$78,0) -> 0 | K21: =IF(AND(Inputs!$F$213=1,Time!K27=1),Inputs!$F$78,0) -> 0 | L21: =IF(AND(Inputs!$F$213=1,Time!L27=1),Inputs!$F$78,0) -> 0 | M21: =IF(AND(Inputs!$F$213=1,Time!M27=1),Inputs!$F$78,0) -> 0 | N21: =IF(AND(Inputs!$F$213=1,Time!N27=1),Inputs!$F$78,0) -> 0 | O21: =IF(AND(Inputs!$F$213=1,Time!O27=1),Inputs!$F$78,0) -> 0 | P21: =IF(AND(Inputs!$F$213=1,Time!P27=1),Inputs!$F$78,0) -> 0 | Q21: =IF(AND(Inputs!$F$213=1,Time!Q27=1),Inputs!$F$78,0) -> 0 | ... DB21: =IF(AND(Inputs!$F$213=1,Time!DB27=1),Inputs!$F$78,0) -> 0
D22: Operating costs
D23: Cost factor (CPI x operating days / 365 x opex factor) | E23: factor | J23: =Time!J56*Time!J25/Inputs!$F$45*Inputs!$F$221 -> 0 | K23: =Time!K56*Time!K25/Inputs!$F$45*Inputs!$F$221 -> 0 | L23: =Time!L56*Time!L25/Inputs!$F$45*Inputs!$F$221 -> 0 | M23: =Time!M56*Time!M25/Inputs!$F$45*Inputs!$F$221 -> 0 | N23: =Time!N56*Time!N25/Inputs!$F$45*Inputs!$F$221 -> 0 | O23: =Time!O56*Time!O25/Inputs!$F$45*Inputs!$F$221 -> 0 | P23: =Time!P56*Time!P25/Inputs!$F$45*Inputs!$F$221 -> 0 | Q23: =Time!Q56*Time!Q25/Inputs!$F$45*Inputs!$F$221 -> 0 | ... DB23: =Time!DB56*Time!DB25/Inputs!$F$45*Inputs!$F$221 -> 1.2390462
D24: Corvus fixed O&M | E24: ARD m | G24: =SUM(J24:DB24) -> 858.3272 | J24: =Inputs!$F$141*J23*IF(Time!J23=1,1-Inputs!$F$142,1) -> 0 | K24: =Inputs!$F$141*K23*IF(Time!K23=1,1-Inputs!$F$142,1) -> 0 | L24: =Inputs!$F$141*L23*IF(Time!L23=1,1-Inputs!$F$142,1) -> 0 | M24: =Inputs!$F$141*M23*IF(Time!M23=1,1-Inputs!$F$142,1) -> 0 | N24: =Inputs!$F$141*N23*IF(Time!N23=1,1-Inputs!$F$142,1) -> 0 | O24: =Inputs!$F$141*O23*IF(Time!O23=1,1-Inputs!$F$142,1) -> 0 | P24: =Inputs!$F$141*P23*IF(Time!P23=1,1-Inputs!$F$142,1) -> 0 | Q24: =Inputs!$F$141*Q23*IF(Time!Q23=1,1-Inputs!$F$142,1) -> 0 | ... DB24: =Inputs!$F$141*DB23*IF(Time!DB23=1,1-Inputs!$F$142,1) -> 13.496682
D25: Tolling back office, fixed | E25: ARD m | G25: =SUM(J25:DB25) -> 168.41401 | J25: =Inputs!$F$144*J23 -> 0 | K25: =Inputs!$F$144*K23 -> 0 | L25: =Inputs!$F$144*L23 -> 0 | M25: =Inputs!$F$144*M23 -> 0 | N25: =Inputs!$F$144*N23 -> 0 | O25: =Inputs!$F$144*O23 -> 0 | P25: =Inputs!$F$144*P23 -> 0 | Q25: =Inputs!$F$144*Q23 -> 0 | ... DB25: =Inputs!$F$144*DB23 -> 2.6639493
D26: Tolling back office, variable | E26: ARD m | G26: =SUM(J26:DB26) -> 528.18445 | J26: =Inputs!$F$143*J20*Inputs!$F$221 -> 0 | K26: =Inputs!$F$143*K20*Inputs!$F$221 -> 0 | L26: =Inputs!$F$143*L20*Inputs!$F$221 -> 0 | M26: =Inputs!$F$143*M20*Inputs!$F$221 -> 0 | N26: =Inputs!$F$143*N20*Inputs!$F$221 -> 0 | O26: =Inputs!$F$143*O20*Inputs!$F$221 -> 0 | P26: =Inputs!$F$143*P20*Inputs!$F$221 -> 0 | Q26: =Inputs!$F$143*Q20*Inputs!$F$221 -> 0 | ... DB26: =Inputs!$F$143*DB20*Inputs!$F$221 -> 9.940862
D27: Insurance | E27: ARD m | G27: =SUM(J27:DB27) -> 263.19584 | J27: =Inputs!$F$145*J23 -> 0 | K27: =Inputs!$F$145*K23 -> 0 | L27: =Inputs!$F$145*L23 -> 0 | M27: =Inputs!$F$145*M23 -> 0 | N27: =Inputs!$F$145*N23 -> 0 | O27: =Inputs!$F$145*O23 -> 0 | P27: =Inputs!$F$145*P23 -> 0 | Q27: =Inputs!$F$145*Q23 -> 0 | ... DB27: =Inputs!$F$145*DB23 -> 4.1631952
D28: Project company costs | E28: ARD m | G28: =SUM(J28:DB28) -> 212.27998 | J28: =Inputs!$F$146*J23 -> 0 | K28: =Inputs!$F$146*K23 -> 0 | L28: =Inputs!$F$146*L23 -> 0 | M28: =Inputs!$F$146*M23 -> 0 | N28: =Inputs!$F$146*N23 -> 0 | O28: =Inputs!$F$146*O23 -> 0 | P28: =Inputs!$F$146*P23 -> 0 | Q28: =Inputs!$F$146*Q23 -> 0 | ... DB28: =Inputs!$F$146*DB23 -> 3.3578151
D29: Total operating costs | E29: ARD m | G29: =SUM(J29:DB29) -> 2030.4015 | J29: =J24+J25+J26+J27+J28 -> 0 | K29: =K24+K25+K26+K27+K28 -> 0 | L29: =L24+L25+L26+L27+L28 -> 0 | M29: =M24+M25+M26+M27+M28 -> 0 | N29: =N24+N25+N26+N27+N28 -> 0 | O29: =O24+O25+O26+O27+O28 -> 0 | P29: =P24+P25+P26+P27+P28 -> 0 | Q29: =Q24+Q25+Q26+Q27+Q28 -> 0 | ... DB29: =DB24+DB25+DB26+DB27+DB28 -> 33.622504
D30: State revenue share | E30: ARD m | G30: =SUM(J30:DB30) -> 0 | J30: =IF(Time!J23=1,Inputs!$F$176*MAX(0,J20-Inputs!$F$177*Time!J56/Time!$F$57*Time!J25/Inputs!$F$45),0) -> 0 | K30: =IF(Time!K23=1,Inputs!$F$176*MAX(0,K20-Inputs!$F$177*Time!K56/Time!$F$57*Time!K25/Inputs!$F$45),0) -> 0 | L30: =IF(Time!L23=1,Inputs!$F$176*MAX(0,L20-Inputs!$F$177*Time!L56/Time!$F$57*Time!L25/Inputs!$F$45),0) -> 0 | M30: =IF(Time!M23=1,Inputs!$F$176*MAX(0,M20-Inputs!$F$177*Time!M56/Time!$F$57*Time!M25/Inputs!$F$45),0) -> 0 | N30: =IF(Time!N23=1,Inputs!$F$176*MAX(0,N20-Inputs!$F$177*Time!N56/Time!$F$57*Time!N25/Inputs!$F$45),0) -> 0 | O30: =IF(Time!O23=1,Inputs!$F$176*MAX(0,O20-Inputs!$F$177*Time!O56/Time!$F$57*Time!O25/Inputs!$F$45),0) -> 0 | P30: =IF(Time!P23=1,Inputs!$F$176*MAX(0,P20-Inputs!$F$177*Time!P56/Time!$F$57*Time!P25/Inputs!$F$45),0) -> 0 | Q30: =IF(Time!Q23=1,Inputs!$F$176*MAX(0,Q20-Inputs!$F$177*Time!Q56/Time!$F$57*Time!Q25/Inputs!$F$45),0) -> 0 | ... DB30: =IF(Time!DB23=1,Inputs!$F$176*MAX(0,DB20-Inputs!$F$177*Time!DB56/Time!$F$57*Time!DB25/Inputs!$F$45),0) -> 0
D31: Restructuring costs | E31: ARD m | G31: =SUM(J31:DB31) -> 21.6 | J31: =IF(AND(Time!J39=1,Time!J8>=Inputs!$F$38,Time!J8<=Inputs!$F$20),Inputs!$F$161/Inputs!$F$162,0) -> 0 | K31: =IF(AND(Time!K39=1,Time!K8>=Inputs!$F$38,Time!K8<=Inputs!$F$20),Inputs!$F$161/Inputs!$F$162,0) -> 0 | L31: =IF(AND(Time!L39=1,Time!L8>=Inputs!$F$38,Time!L8<=Inputs!$F$20),Inputs!$F$161/Inputs!$F$162,0) -> 0 | M31: =IF(AND(Time!M39=1,Time!M8>=Inputs!$F$38,Time!M8<=Inputs!$F$20),Inputs!$F$161/Inputs!$F$162,0) -> 0 | N31: =IF(AND(Time!N39=1,Time!N8>=Inputs!$F$38,Time!N8<=Inputs!$F$20),Inputs!$F$161/Inputs!$F$162,0) -> 0 | O31: =IF(AND(Time!O39=1,Time!O8>=Inputs!$F$38,Time!O8<=Inputs!$F$20),Inputs!$F$161/Inputs!$F$162,0) -> 0 | P31: =IF(AND(Time!P39=1,Time!P8>=Inputs!$F$38,Time!P8<=Inputs!$F$20),Inputs!$F$161/Inputs!$F$162,0) -> 0 | Q31: =IF(AND(Time!Q39=1,Time!Q8>=Inputs!$F$38,Time!Q8<=Inputs!$F$20),Inputs!$F$161/Inputs!$F$162,0) -> 0 | ... DB31: =IF(AND(Time!DB39=1,Time!DB8>=Inputs!$F$38,Time!DB8<=Inputs!$F$20),Inputs!$F$161/Inputs!$F$162,0) -> 0
D32: EBITDA | E32: ARD m | G32: =SUM(J32:DB32) -> 6477.3626 | J32: =J20+J21-J29-J30-J31 -> 0 | K32: =K20+K21-K29-K30-K31 -> 0 | L32: =L20+L21-L29-L30-L31 -> 0 | M32: =M20+M21-M29-M30-M31 -> 0 | N32: =N20+N21-N29-N30-N31 -> 0 | O32: =O20+O21-O29-O30-O31 -> 0 | P32: =P20+P21-P29-P30-P31 -> 0 | Q32: =Q20+Q21-Q29-Q30-Q31 -> 0 | ... DB32: =DB20+DB21-DB29-DB30-DB31 -> 126.71398
D33: Lifecycle and handback
D34: Operating year (H2 periods) | E34: # | J34: =IF(AND(Time!J12=2,Time!J26=1,Time!J8<=Time!$F$17),Time!J11-Inputs!$F$60,0) -> 0 | K34: =IF(AND(Time!K12=2,Time!K26=1,Time!K8<=Time!$F$17),Time!K11-Inputs!$F$60,0) -> 0 | L34: =IF(AND(Time!L12=2,Time!L26=1,Time!L8<=Time!$F$17),Time!L11-Inputs!$F$60,0) -> 0 | M34: =IF(AND(Time!M12=2,Time!M26=1,Time!M8<=Time!$F$17),Time!M11-Inputs!$F$60,0) -> 0 | N34: =IF(AND(Time!N12=2,Time!N26=1,Time!N8<=Time!$F$17),Time!N11-Inputs!$F$60,0) -> 0 | O34: =IF(AND(Time!O12=2,Time!O26=1,Time!O8<=Time!$F$17),Time!O11-Inputs!$F$60,0) -> 0 | P34: =IF(AND(Time!P12=2,Time!P26=1,Time!P8<=Time!$F$17),Time!P11-Inputs!$F$60,0) -> 0 | Q34: =IF(AND(Time!Q12=2,Time!Q26=1,Time!Q8<=Time!$F$17),Time!Q11-Inputs!$F$60,0) -> 0 | ... DB34: =IF(AND(Time!DB12=2,Time!DB26=1,Time!DB8<=Time!$F$17),Time!DB11-Inputs!$F$60,0) -> 0
D35: Lifecycle works (2015 prices) | E35: ARD m | G35: =SUM(J35:DB35) -> 265.1 | J35: =IF(J34>0,Inputs!$F$147*IF(MOD(J34,Inputs!$F$148)=0,1,0)+Inputs!$F$149*IF(MOD(J34,Inputs!$F$150)=0,1,0)+Inputs!$F$151*IF(MOD(J34,Inputs!$F$152)=0,1,0),0) -> 0 | K35: =IF(K34>0,Inputs!$F$147*IF(MOD(K34,Inputs!$F$148)=0,1,0)+Inputs!$F$149*IF(MOD(K34,Inputs!$F$150)=0,1,0)+Inputs!$F$151*IF(MOD(K34,Inputs!$F$152)=0,1,0),0) -> 0 | L35: =IF(L34>0,Inputs!$F$147*IF(MOD(L34,Inputs!$F$148)=0,1,0)+Inputs!$F$149*IF(MOD(L34,Inputs!$F$150)=0,1,0)+Inputs!$F$151*IF(MOD(L34,Inputs!$F$152)=0,1,0),0) -> 0 | M35: =IF(M34>0,Inputs!$F$147*IF(MOD(M34,Inputs!$F$148)=0,1,0)+Inputs!$F$149*IF(MOD(M34,Inputs!$F$150)=0,1,0)+Inputs!$F$151*IF(MOD(M34,Inputs!$F$152)=0,1,0),0) -> 0 | N35: =IF(N34>0,Inputs!$F$147*IF(MOD(N34,Inputs!$F$148)=0,1,0)+Inputs!$F$149*IF(MOD(N34,Inputs!$F$150)=0,1,0)+Inputs!$F$151*IF(MOD(N34,Inputs!$F$152)=0,1,0),0) -> 0 | O35: =IF(O34>0,Inputs!$F$147*IF(MOD(O34,Inputs!$F$148)=0,1,0)+Inputs!$F$149*IF(MOD(O34,Inputs!$F$150)=0,1,0)+Inputs!$F$151*IF(MOD(O34,Inputs!$F$152)=0,1,0),0) -> 0 | P35: =IF(P34>0,Inputs!$F$147*IF(MOD(P34,Inputs!$F$148)=0,1,0)+Inputs!$F$149*IF(MOD(P34,Inputs!$F$150)=0,1,0)+Inputs!$F$151*IF(MOD(P34,Inputs!$F$152)=0,1,0),0) -> 0 | Q35: =IF(Q34>0,Inputs!$F$147*IF(MOD(Q34,Inputs!$F$148)=0,1,0)+Inputs!$F$149*IF(MOD(Q34,Inputs!$F$150)=0,1,0)+Inputs!$F$151*IF(MOD(Q34,Inputs!$F$152)=0,1,0),0) -> 0 | ... DB35: =IF(DB34>0,Inputs!$F$147*IF(MOD(DB34,Inputs!$F$148)=0,1,0)+Inputs!$F$149*IF(MOD(DB34,Inputs!$F$150)=0,1,0)+Inputs!$F$151*IF(MOD(DB34,Inputs!$F$152)=0,1,0),0) -> 0
D36: Lifecycle works (nominal), paid from the MMRA | E36: ARD m | G36: =SUM(J36:DB36) -> 550.67763 | J36: =J35*Time!J56*Inputs!$F$222 -> 0 | K36: =K35*Time!K56*Inputs!$F$222 -> 0 | L36: =L35*Time!L56*Inputs!$F$222 -> 0 | M36: =M35*Time!M56*Inputs!$F$222 -> 0 | N36: =N35*Time!N56*Inputs!$F$222 -> 0 | O36: =O35*Time!O56*Inputs!$F$222 -> 0 | P36: =P35*Time!P56*Inputs!$F$222 -> 0 | Q36: =Q35*Time!Q56*Inputs!$F$222 -> 0 | ... DB36: =DB35*Time!DB56*Inputs!$F$222 -> 0
D37: Lifecycle reserve contribution (next six periods / 6) | E37: ARD m | G37: =SUM(J37:DB37) -> 550.67763 | J37: =SUM(K36:P36)/Inputs!$F$153 -> 0 | K37: =SUM(L36:Q36)/Inputs!$F$153 -> 0 | L37: =SUM(M36:R36)/Inputs!$F$153 -> 0 | M37: =SUM(N36:S36)/Inputs!$F$153 -> 0 | N37: =SUM(O36:T36)/Inputs!$F$153 -> 0 | O37: =SUM(P36:U36)/Inputs!$F$153 -> 0 | P37: =SUM(Q36:V36)/Inputs!$F$153 -> 0 | Q37: =SUM(R36:W36)/Inputs!$F$153 -> 0 | ... DB37: =SUM(DC36:DH36)/Inputs!$F$153 -> 0
D38: Flag_HandbackFunding | E38: flag | J38: =IF(AND(Time!J26=1,Time!J7>=EDATE(Time!$F$17,-Inputs!$F$49)),1,0) -> 0 | K38: =IF(AND(Time!K26=1,Time!K7>=EDATE(Time!$F$17,-Inputs!$F$49)),1,0) -> 0 | L38: =IF(AND(Time!L26=1,Time!L7>=EDATE(Time!$F$17,-Inputs!$F$49)),1,0) -> 0 | M38: =IF(AND(Time!M26=1,Time!M7>=EDATE(Time!$F$17,-Inputs!$F$49)),1,0) -> 0 | N38: =IF(AND(Time!N26=1,Time!N7>=EDATE(Time!$F$17,-Inputs!$F$49)),1,0) -> 0 | O38: =IF(AND(Time!O26=1,Time!O7>=EDATE(Time!$F$17,-Inputs!$F$49)),1,0) -> 0 | P38: =IF(AND(Time!P26=1,Time!P7>=EDATE(Time!$F$17,-Inputs!$F$49)),1,0) -> 0 | Q38: =IF(AND(Time!Q26=1,Time!Q7>=EDATE(Time!$F$17,-Inputs!$F$49)),1,0) -> 0 | ... DB38: =IF(AND(Time!DB26=1,Time!DB7>=EDATE(Time!$F$17,-Inputs!$F$49)),1,0) -> 1
D39: Handback reserve contribution | E39: ARD m | G39: =SUM(J39:DB39) -> 124.14388 | J39: =Inputs!$F$154*Time!J56*Inputs!$F$222/Inputs!$F$155*J38 -> 0 | K39: =Inputs!$F$154*Time!K56*Inputs!$F$222/Inputs!$F$155*K38 -> 0 | L39: =Inputs!$F$154*Time!L56*Inputs!$F$222/Inputs!$F$155*L38 -> 0 | M39: =Inputs!$F$154*Time!M56*Inputs!$F$222/Inputs!$F$155*M38 -> 0 | N39: =Inputs!$F$154*Time!N56*Inputs!$F$222/Inputs!$F$155*N38 -> 0 | O39: =Inputs!$F$154*Time!O56*Inputs!$F$222/Inputs!$F$155*O38 -> 0 | P39: =Inputs!$F$154*Time!P56*Inputs!$F$222/Inputs!$F$155*P38 -> 0 | Q39: =Inputs!$F$154*Time!Q56*Inputs!$F$222/Inputs!$F$155*Q38 -> 0 | ... DB39: =Inputs!$F$154*Time!DB56*Inputs!$F$222/Inputs!$F$155*DB38 -> 13.195842
D40: Working capital
D41: Toll receivables | E41: ARD m | J41: =IF(AND(Time!J26=1,Time!J28=0),J20/Time!J25*Inputs!$F$156,0) -> 0 | K41: =IF(AND(Time!K26=1,Time!K28=0),K20/Time!K25*Inputs!$F$156,0) -> 0 | L41: =IF(AND(Time!L26=1,Time!L28=0),L20/Time!L25*Inputs!$F$156,0) -> 0 | M41: =IF(AND(Time!M26=1,Time!M28=0),M20/Time!M25*Inputs!$F$156,0) -> 0 | N41: =IF(AND(Time!N26=1,Time!N28=0),N20/Time!N25*Inputs!$F$156,0) -> 0 | O41: =IF(AND(Time!O26=1,Time!O28=0),O20/Time!O25*Inputs!$F$156,0) -> 0 | P41: =IF(AND(Time!P26=1,Time!P28=0),P20/Time!P25*Inputs!$F$156,0) -> 0 | Q41: =IF(AND(Time!Q26=1,Time!Q28=0),Q20/Time!Q25*Inputs!$F$156,0) -> 0 | ... DB41: =IF(AND(Time!DB26=1,Time!DB28=0),DB20/Time!DB25*Inputs!$F$156,0) -> 0
D42: Operating payables | E42: ARD m | J42: =IF(AND(Time!J26=1,Time!J28=0),J29/Time!J25*Inputs!$F$157,0) -> 0 | K42: =IF(AND(Time!K26=1,Time!K28=0),K29/Time!K25*Inputs!$F$157,0) -> 0 | L42: =IF(AND(Time!L26=1,Time!L28=0),L29/Time!L25*Inputs!$F$157,0) -> 0 | M42: =IF(AND(Time!M26=1,Time!M28=0),M29/Time!M25*Inputs!$F$157,0) -> 0 | N42: =IF(AND(Time!N26=1,Time!N28=0),N29/Time!N25*Inputs!$F$157,0) -> 0 | O42: =IF(AND(Time!O26=1,Time!O28=0),O29/Time!O25*Inputs!$F$157,0) -> 0 | P42: =IF(AND(Time!P26=1,Time!P28=0),P29/Time!P25*Inputs!$F$157,0) -> 0 | Q42: =IF(AND(Time!Q26=1,Time!Q28=0),Q29/Time!Q25*Inputs!$F$157,0) -> 0 | ... DB42: =IF(AND(Time!DB26=1,Time!DB28=0),DB29/Time!DB25*Inputs!$F$157,0) -> 0
D43: Net working capital | E43: ARD m | J43: =J41-J42 -> 0 | K43: =K41-K42 -> 0 | L43: =L41-L42 -> 0 | M43: =M41-M42 -> 0 | N43: =N41-N42 -> 0 | O43: =O41-O42 -> 0 | P43: =P41-P42 -> 0 | Q43: =Q41-Q42 -> 0 | ... DB43: =DB41-DB42 -> 0
D44: Increase in working capital | E44: ARD m | G44: =SUM(J44:DB44) -> 0 | J44: =J43-I43 -> 0 | K44: =K43-J43 -> 0 | L44: =L43-K43 -> 0 | M44: =M43-L43 -> 0 | N44: =N43-M43 -> 0 | O44: =O43-N43 -> 0 | P44: =P43-O43 -> 0 | Q44: =Q43-P43 -> 0 | ... DB44: =DB43-DA43 -> -8.4657642
D45: Interchange upgrade capex (from the upgrade account) | E45: ARD m | G45: =SUM(J45:DB45) -> 78.3 | J45: =IF(AND(Inputs!$F$215=1,Time!J8>=Inputs!$F$39,Time!J8<=Inputs!$F$40),Inputs!$F$172/Inputs!$F$173,0) -> 0 | K45: =IF(AND(Inputs!$F$215=1,Time!K8>=Inputs!$F$39,Time!K8<=Inputs!$F$40),Inputs!$F$172/Inputs!$F$173,0) -> 0 | L45: =IF(AND(Inputs!$F$215=1,Time!L8>=Inputs!$F$39,Time!L8<=Inputs!$F$40),Inputs!$F$172/Inputs!$F$173,0) -> 0 | M45: =IF(AND(Inputs!$F$215=1,Time!M8>=Inputs!$F$39,Time!M8<=Inputs!$F$40),Inputs!$F$172/Inputs!$F$173,0) -> 0 | N45: =IF(AND(Inputs!$F$215=1,Time!N8>=Inputs!$F$39,Time!N8<=Inputs!$F$40),Inputs!$F$172/Inputs!$F$173,0) -> 0 | O45: =IF(AND(Inputs!$F$215=1,Time!O8>=Inputs!$F$39,Time!O8<=Inputs!$F$40),Inputs!$F$172/Inputs!$F$173,0) -> 0 | P45: =IF(AND(Inputs!$F$215=1,Time!P8>=Inputs!$F$39,Time!P8<=Inputs!$F$40),Inputs!$F$172/Inputs!$F$173,0) -> 0 | Q45: =IF(AND(Inputs!$F$215=1,Time!Q8>=Inputs!$F$39,Time!Q8<=Inputs!$F$40),Inputs!$F$172/Inputs!$F$173,0) -> 0 | ... DB45: =IF(AND(Inputs!$F$215=1,Time!DB8>=Inputs!$F$39,Time!DB8<=Inputs!$F$40),Inputs!$F$172/Inputs!$F$173,0) -> 0
D46: Cash flow available for debt service
D47: Tax paid | E47: ARD m | G47: =SUM(J47:DB47) -> 983.83964 | J47: =Tax!J23 -> 0 | K47: =Tax!K23 -> 0 | L47: =Tax!L23 -> 0 | M47: =Tax!M23 -> 0 | N47: =Tax!N23 -> 0 | O47: =Tax!O23 -> 0 | P47: =Tax!P23 -> 0 | Q47: =Tax!Q23 -> 0 | ... DB47: =Tax!DB23 -> 0
D48: CFADS | E48: ARD m | G48: =SUM(J48:DB48) -> 4818.7014 | J48: =(J32-J44-J47-J37-J39)*(1-Time!J20) -> 0 | K48: =(K32-K44-K47-K37-K39)*(1-Time!K20) -> 0 | L48: =(L32-L44-L47-L37-L39)*(1-Time!L20) -> 0 | M48: =(M32-M44-M47-M37-M39)*(1-Time!M20) -> 0 | N48: =(N32-N44-N47-N37-N39)*(1-Time!N20) -> 0 | O48: =(O32-O44-O47-O37-O39)*(1-Time!O20) -> 0 | P48: =(P32-P44-P47-P37-P39)*(1-Time!P20) -> 0 | Q48: =(Q32-Q44-Q47-Q37-Q39)*(1-Time!Q20) -> 0 | ... DB48: =(DB32-DB44-DB47-DB37-DB39)*(1-Time!DB20) -> 121.9839

Sheet Tax
D1: Case T: Merrick Link toll road PPP | Tax
D2: Units: ARD millions unless stated. Inputs blue on yellow; links green; calculations black.
D3: Period end | E3: date | J3: =Time!J8 -> 42185 | K3: =Time!K8 -> 42277 | L3: =Time!L8 -> 42369 | M3: =Time!M8 -> 42460 | N3: =Time!N8 -> 42551 | O3: =Time!O8 -> 42643 | P3: =Time!P8 -> 42735 | Q3: =Time!Q8 -> 42825 | ... DB3: =Time!DB8 -> 58256
D5: Tax cost base of the concession asset
D6: Opening tax written-down value | E6: ARD m | J6: =I11 -> 0 | K6: =J11 -> 73.414541 | L6: =K11 -> 104.99317 | M6: =L11 -> 168.75744 | N6: =M11 -> 270.51178 | O6: =N11 -> 410.61034 | P6: =O11 -> 584.71411 | Q6: =P11 -> 782.99668 | ... DB6: =DA11 -> 16.083795
D7: Additions (capitalized cost less contribution plus upgrade) | E7: ARD m | G7: =SUM(J7:DB7) -> 1915.5053 | J7: =Funding!J41-Funding!J39+Operations!J45 -> 73.414541 | K7: =Funding!K41-Funding!K39+Operations!K45 -> 31.578625 | L7: =Funding!L41-Funding!L39+Operations!L45 -> 63.764276 | M7: =Funding!M41-Funding!M39+Operations!M45 -> 101.75434 | N7: =Funding!N41-Funding!N39+Operations!N45 -> 140.09856 | O7: =Funding!O41-Funding!O39+Operations!O45 -> 174.10377 | P7: =Funding!P41-Funding!P39+Operations!P45 -> 198.28257 | Q7: =Funding!Q41-Funding!Q39+Operations!Q45 -> 211.6284 | ... DB7: =Funding!DB41-Funding!DB39+Operations!DB45 -> 0
D8: Tax amortization (straight line over remaining term) | E8: ARD m | G8: =SUM(J8:DB8) -> 1673.7071 | J8: =IF(Time!J29>0,J6*Time!J25/Time!J29,0) -> 0 | K8: =IF(Time!K29>0,K6*Time!K25/Time!K29,0) -> 0 | L8: =IF(Time!L29>0,L6*Time!L25/Time!L29,0) -> 0 | M8: =IF(Time!M29>0,M6*Time!M25/Time!M29,0) -> 0 | N8: =IF(Time!N29>0,N6*Time!N25/Time!N29,0) -> 0 | O8: =IF(Time!O29>0,O6*Time!O25/Time!O29,0) -> 0 | P8: =IF(Time!P29>0,P6*Time!P25/Time!P29,0) -> 0 | Q8: =IF(Time!Q29>0,Q6*Time!Q25/Time!Q29,0) -> 0 | ... DB8: =IF(Time!DB29>0,DB6*Time!DB25/Time!DB29,0) -> 16.083795
D9: Value before forgiveness | E9: ARD m | J9: =J6+J7-J8 -> 73.414541 | K9: =K6+K7-K8 -> 104.99317 | L9: =L6+L7-L8 -> 168.75744 | M9: =M6+M7-M8 -> 270.51178 | N9: =N6+N7-N8 -> 410.61034 | O9: =O6+O7-O8 -> 584.71411 | P9: =P6+P7-P8 -> 782.99668 | Q9: =Q6+Q7-Q8 -> 994.62508 | ... DB9: =DB6+DB7-DB8 -> 0
D10: Debt forgiveness applied to cost base | E10: ARD m | G10: =SUM(J10:DB10) -> 241.79816 | J10: =MIN(J19-J20,J9) -> 0 | K10: =MIN(K19-K20,K9) -> 0 | L10: =MIN(L19-L20,L9) -> 0 | M10: =MIN(M19-M20,M9) -> 0 | N10: =MIN(N19-N20,N9) -> 0 | O10: =MIN(O19-O20,O9) -> 0 | P10: =MIN(P19-P20,P9) -> 0 | Q10: =MIN(Q19-Q20,Q9) -> 0 | ... DB10: =MIN(DB19-DB20,DB9) -> 0
D11: Closing tax written-down value | E11: ARD m | J11: =J9-J10 -> 73.414541 | K11: =K9-K10 -> 104.99317 | L11: =L9-L10 -> 168.75744 | M11: =M9-M10 -> 270.51178 | N11: =N9-N10 -> 410.61034 | O11: =O9-O10 -> 584.71411 | P11: =P9-P10 -> 782.99668 | Q11: =Q9-Q10 -> 994.62508 | ... DB11: =DB9-DB10 -> 0
D12: Taxable income
D13: NILO interest accrued (deductible) | E13: ARD m | G13: =SUM(J13:DB13) -> 503.83999 | J13: =Debt!J97*(1-Time!J20) -> 0 | K13: =Debt!K97*(1-Time!K20) -> 0 | L13: =Debt!L97*(1-Time!L20) -> 0 | M13: =Debt!M97*(1-Time!M20) -> 0 | N13: =Debt!N97*(1-Time!N20) -> 0 | O13: =Debt!O97*(1-Time!O20) -> 0 | P13: =Debt!P97*(1-Time!P20) -> 0 | Q13: =Debt!Q97*(1-Time!Q20) -> 0 | ... DB13: =Debt!DB97*(1-Time!DB20) -> 5.0901589e-13
D14: Shareholder loan interest accrued (deductible) | E14: ARD m | G14: =SUM(J14:DB14) -> 281.98031 | J14: =Waterfall!J54*(1-Time!J20) -> 0 | K14: =Waterfall!K54*(1-Time!K20) -> 0 | L14: =Waterfall!L54*(1-Time!L20) -> 0 | M14: =Waterfall!M54*(1-Time!M20) -> 0 | N14: =Waterfall!N54*(1-Time!N20) -> 0 | O14: =Waterfall!O54*(1-Time!O20) -> 0 | P14: =Waterfall!P54*(1-Time!P20) -> 0 | Q14: =Waterfall!Q54*(1-Time!Q20) -> 0 | ... DB14: =Waterfall!DB54*(1-Time!DB20) -> 0
D15: Taxable income before losses | E15: ARD m | G15: =SUM(J15:DB15) -> 2623.282 | J15: =(Operations!J32-Operations!J36-Reserves!J22-J8-Debt!J64-J13-J14-Debt!J65)*(1-Time!J20) -> 0 | K15: =(Operations!K32-Operations!K36-Reserves!K22-K8-Debt!K64-K13-K14-Debt!K65)*(1-Time!K20) -> 0 | L15: =(Operations!L32-Operations!L36-Reserves!L22-L8-Debt!L64-L13-L14-Debt!L65)*(1-Time!L20) -> 0 | M15: =(Operations!M32-Operations!M36-Reserves!M22-M8-Debt!M64-M13-M14-Debt!M65)*(1-Time!M20) -> 0 | N15: =(Operations!N32-Operations!N36-Reserves!N22-N8-Debt!N64-N13-N14-Debt!N65)*(1-Time!N20) -> 0 | O15: =(Operations!O32-Operations!O36-Reserves!O22-O8-Debt!O64-O13-O14-Debt!O65)*(1-Time!O20) -> 0 | P15: =(Operations!P32-Operations!P36-Reserves!P22-P8-Debt!P64-P13-P14-Debt!P65)*(1-Time!P20) -> 0 | Q15: =(Operations!Q32-Operations!Q36-Reserves!Q22-Q8-Debt!Q64-Q13-Q14-Debt!Q65)*(1-Time!Q20) -> 0 | ... DB15: =(Operations!DB32-Operations!DB36-Reserves!DB22-DB8-Debt!DB64-DB13-DB14-Debt!DB65)*(1-Time!DB20) -> -13.513692
D16: Tax losses brought forward | E16: ARD m | J16: =I21 -> 0 | K16: =J21 -> 0 | L16: =K21 -> 0 | M16: =L21 -> 0 | N16: =M21 -> 0 | O16: =N21 -> 0 | P16: =O21 -> 0 | Q16: =P21 -> 0 | ... DB16: =DA21 -> 0
D17: Losses used | E17: ARD m | G17: =SUM(J17:DB17) -> 167.51578 | J17: =MIN(J16,MAX(0,J15)) -> 0 | K17: =MIN(K16,MAX(0,K15)) -> 0 | L17: =MIN(L16,MAX(0,L15)) -> 0 | M17: =MIN(M16,MAX(0,M15)) -> 0 | N17: =MIN(N16,MAX(0,N15)) -> 0 | O17: =MIN(O16,MAX(0,O15)) -> 0 | P17: =MIN(P16,MAX(0,P15)) -> 0 | Q17: =MIN(Q16,MAX(0,Q15)) -> 0 | ... DB17: =MIN(DB16,MAX(0,DB15)) -> 0
D18: Losses added | E18: ARD m | G18: =SUM(J18:DB18) -> 823.69926 | J18: =MAX(0,-J15) -> 0 | K18: =MAX(0,-K15) -> 0 | L18: =MAX(0,-L15) -> 0 | M18: =MAX(0,-M15) -> 0 | N18: =MAX(0,-N15) -> 0 | O18: =MAX(0,-O15) -> 0 | P18: =MAX(0,-P15) -> 0 | Q18: =MAX(0,-Q15) -> 0 | ... DB18: =MAX(0,-DB15) -> 13.513692
D19: Forgiven commercial debt (cancelled claims plus shareholder loans) | E19: ARD m | G19: =SUM(J19:DB19) -> 884.46795 | J19: =Time!J35*(Debt!J79+Debt!J80) -> 0 | K19: =Time!K35*(Debt!K79+Debt!K80) -> 0 | L19: =Time!L35*(Debt!L79+Debt!L80) -> 0 | M19: =Time!M35*(Debt!M79+Debt!M80) -> 0 | N19: =Time!N35*(Debt!N79+Debt!N80) -> 0 | O19: =Time!O35*(Debt!O79+Debt!O80) -> 0 | P19: =Time!P35*(Debt!P79+Debt!P80) -> 0 | Q19: =Time!Q35*(Debt!Q79+Debt!Q80) -> 0 | ... DB19: =Time!DB35*(Debt!DB79+Debt!DB80) -> 0
D20: Forgiveness applied to losses | E20: ARD m | G20: =SUM(J20:DB20) -> 642.66979 | J20: =MIN(J19,J16-J17+J18) -> 0 | K20: =MIN(K19,K16-K17+K18) -> 0 | L20: =MIN(L19,L16-L17+L18) -> 0 | M20: =MIN(M19,M16-M17+M18) -> 0 | N20: =MIN(N19,N16-N17+N18) -> 0 | O20: =MIN(O19,O16-O17+O18) -> 0 | P20: =MIN(P19,P16-P17+P18) -> 0 | Q20: =MIN(Q19,Q16-Q17+Q18) -> 0 | ... DB20: =MIN(DB19,DB16-DB17+DB18) -> 0
D21: Tax losses carried forward | E21: ARD m | J21: =J16-J17+J18-J20 -> 0 | K21: =K16-K17+K18-K20 -> 0 | L21: =L16-L17+L18-L20 -> 0 | M21: =M16-M17+M18-M20 -> 0 | N21: =N16-N17+N18-N20 -> 0 | O21: =O16-O17+O18-O20 -> 0 | P21: =P16-P17+P18-P20 -> 0 | Q21: =Q16-Q17+Q18-Q20 -> 0 | ... DB21: =DB16-DB17+DB18-DB20 -> 13.513692
D22: Taxable income after losses | E22: ARD m | G22: =SUM(J22:DB22) -> 3279.4655 | J22: =MAX(0,J15)-J17 -> 0 | K22: =MAX(0,K15)-K17 -> 0 | L22: =MAX(0,L15)-L17 -> 0 | M22: =MAX(0,M15)-M17 -> 0 | N22: =MAX(0,N15)-N17 -> 0 | O22: =MAX(0,O15)-O17 -> 0 | P22: =MAX(0,P15)-P17 -> 0 | Q22: =MAX(0,Q15)-Q17 -> 0 | ... DB22: =MAX(0,DB15)-DB17 -> 0
D23: Tax paid | E23: ARD m | G23: =SUM(J23:DB23) -> 983.83964 | J23: =Inputs!$F$158*J22 -> 0 | K23: =Inputs!$F$158*K22 -> 0 | L23: =Inputs!$F$158*L22 -> 0 | M23: =Inputs!$F$158*M22 -> 0 | N23: =Inputs!$F$158*N22 -> 0 | O23: =Inputs!$F$158*O22 -> 0 | P23: =Inputs!$F$158*P22 -> 0 | Q23: =Inputs!$F$158*Q22 -> 0 | ... DB23: =Inputs!$F$158*DB22 -> 0

Sheet Funding
D1: Case T: Merrick Link toll road PPP | Funding
D2: Units: ARD millions unless stated. Inputs blue on yellow; links green; calculations black.
D3: Period end | E3: date | J3: =Time!J8 -> 42185 | K3: =Time!K8 -> 42277 | L3: =Time!L8 -> 42369 | M3: =Time!M8 -> 42460 | N3: =Time!N8 -> 42551 | O3: =Time!O8 -> 42643 | P3: =Time!P8 -> 42735 | Q3: =Time!Q8 -> 42825 | ... DB3: =Time!DB8 -> 58256
D5: Commitments
D6: Bank mini-perm commitment | E6: ARD m | F6: =Inputs!$F$96*Debt!$F$26 -> 396.95858
D7: Bond face value (fully funded at close into escrow) | E7: ARD m | F7: =Inputs!$F$97*Debt!$F$26 -> 485.17159
D8: Uses of funds
D9: Construction costs | E9: ARD m | G9: =SUM(J9:DB9) -> 1841.4 | J9: =Construction!J13 -> 55.351416 | K9: =Construction!K13 -> 25.701277 | L9: =Construction!L13 -> 57.187205 | M9: =Construction!M13 -> 93.790892 | N9: =Construction!N13 -> 129.91074 | O9: =Construction!O13 -> 161.00849 | P9: =Construction!P13 -> 183.60753 | Q9: =Construction!Q13 -> 195.4016 | ... DB9: =Construction!DB13 -> 0
D10: Upfront fees (bank, bond issue, NILO, bridge) | E10: ARD m | G10: =SUM(J10:DB10) -> 16.503927 | J10: =IF(Time!J6=1,Inputs!$F$108*$F$6+Inputs!$F$112*$F$7+Inputs!$F$121*Debt!$F$28+Inputs!$F$84*Inputs!$F$227,0) -> 16.503927 | K10: =IF(Time!K6=1,Inputs!$F$108*$F$6+Inputs!$F$112*$F$7+Inputs!$F$121*Debt!$F$28+Inputs!$F$84*Inputs!$F$227,0) -> 0 | L10: =IF(Time!L6=1,Inputs!$F$108*$F$6+Inputs!$F$112*$F$7+Inputs!$F$121*Debt!$F$28+Inputs!$F$84*Inputs!$F$227,0) -> 0 | M10: =IF(Time!M6=1,Inputs!$F$108*$F$6+Inputs!$F$112*$F$7+Inputs!$F$121*Debt!$F$28+Inputs!$F$84*Inputs!$F$227,0) -> 0 | N10: =IF(Time!N6=1,Inputs!$F$108*$F$6+Inputs!$F$112*$F$7+Inputs!$F$121*Debt!$F$28+Inputs!$F$84*Inputs!$F$227,0) -> 0 | O10: =IF(Time!O6=1,Inputs!$F$108*$F$6+Inputs!$F$112*$F$7+Inputs!$F$121*Debt!$F$28+Inputs!$F$84*Inputs!$F$227,0) -> 0 | P10: =IF(Time!P6=1,Inputs!$F$108*$F$6+Inputs!$F$112*$F$7+Inputs!$F$121*Debt!$F$28+Inputs!$F$84*Inputs!$F$227,0) -> 0 | Q10: =IF(Time!Q6=1,Inputs!$F$108*$F$6+Inputs!$F$112*$F$7+Inputs!$F$121*Debt!$F$28+Inputs!$F$84*Inputs!$F$227,0) -> 0 | ... DB10: =IF(Time!DB6=1,Inputs!$F$108*$F$6+Inputs!$F$112*$F$7+Inputs!$F$121*Debt!$F$28+Inputs!$F$84*Inputs!$F$227,0) -> 0
D11: Bank interest during construction | E11: ARD m | G11: =SUM(J11:DB11) -> 37.9294 | J11: =Debt!J43*Time!J20 -> 0 | K11: =Debt!K43*Time!K20 -> 0 | L11: =Debt!L43*Time!L20 -> 0 | M11: =Debt!M43*Time!M20 -> 0 | N11: =Debt!N43*Time!N20 -> 0 | O11: =Debt!O43*Time!O20 -> 0.075326408 | P11: =Debt!P43*Time!P20 -> 0.79185685 | Q11: =Debt!Q43*Time!Q20 -> 1.5752662 | ... DB11: =Debt!DB43*Time!DB20 -> 0
D12: Bank commitment fee | E12: ARD m | G12: =SUM(J12:DB12) -> 8.3252397 | J12: =Inputs!$F$109*($F$6-Debt!J42)*Time!J9/Inputs!$F$45*Time!J20 -> 0.35128115 | K12: =Inputs!$F$109*($F$6-Debt!K42)*Time!K9/Inputs!$F$45*Time!K20 -> 0.95052547 | L12: =Inputs!$F$109*($F$6-Debt!L42)*Time!L9/Inputs!$F$45*Time!L20 -> 0.95052547 | M12: =Inputs!$F$109*($F$6-Debt!M42)*Time!M9/Inputs!$F$45*Time!M20 -> 0.94019367 | N12: =Inputs!$F$109*($F$6-Debt!N42)*Time!N9/Inputs!$F$45*Time!N20 -> 0.94019367 | O12: =Inputs!$F$109*($F$6-Debt!O42)*Time!O9/Inputs!$F$45*Time!O20 -> 0.93825101 | P12: =Inputs!$F$109*($F$6-Debt!P42)*Time!P9/Inputs!$F$45*Time!P20 -> 0.82149219 | Q12: =Inputs!$F$109*($F$6-Debt!Q42)*Time!Q9/Inputs!$F$45*Time!Q20 -> 0.67317183 | ... DB12: =Inputs!$F$109*($F$6-Debt!DB42)*Time!DB9/Inputs!$F$45*Time!DB20 -> 0
D13: Bond interest during construction | E13: ARD m | G13: =SUM(J13:DB13) -> 90.397576 | J13: =Debt!J50*Time!J20 -> 2.156992 | K13: =Debt!K50*Time!K20 -> 5.8827056 | L13: =Debt!L50*Time!L20 -> 5.8827056 | M13: =Debt!M50*Time!M20 -> 5.8827056 | N13: =Debt!N50*Time!N20 -> 5.8827056 | O13: =Debt!O50*Time!O20 -> 5.8827056 | P13: =Debt!P50*Time!P20 -> 5.8827056 | Q13: =Debt!Q50*Time!Q20 -> 5.8827056 | ... DB13: =Debt!DB50*Time!DB20 -> 0
D14: Bond escrow: opening | E14: ARD m | J14: =IF(Time!J6=1,$F$7,I16) -> 485.17159 | K14: =IF(Time!K6=1,$F$7,J16) -> 485.17159 | L14: =IF(Time!L6=1,$F$7,K16) -> 485.17159 | M14: =IF(Time!M6=1,$F$7,L16) -> 485.17159 | N14: =IF(Time!N6=1,$F$7,M16) -> 485.17159 | O14: =IF(Time!O6=1,$F$7,N16) -> 478.90641 | P14: =IF(Time!P6=1,$F$7,O16) -> 419.30983 | Q14: =IF(Time!Q6=1,$F$7,P16) -> 351.2391 | ... DB14: =IF(Time!DB6=1,$F$7,DA16) -> 0
D15: Bond escrow earnings (deducted) | E15: ARD m | G15: =SUM(J15:DB15) -> 22.492753 | J15: =J14*Inputs!$F$111*Time!J9/Inputs!$F$45*Time!J20 -> 0.94907539 | K15: =K14*Inputs!$F$111*Time!K9/Inputs!$F$45*Time!K20 -> 2.5680863 | L15: =L14*Inputs!$F$111*Time!L9/Inputs!$F$45*Time!L20 -> 2.5680863 | M15: =M14*Inputs!$F$111*Time!M9/Inputs!$F$45*Time!M20 -> 2.5401724 | N15: =N14*Inputs!$F$111*Time!N9/Inputs!$F$45*Time!N20 -> 2.5401724 | O15: =O14*Inputs!$F$111*Time!O9/Inputs!$F$45*Time!O20 -> 2.5349238 | P15: =P14*Inputs!$F$111*Time!P9/Inputs!$F$45*Time!P20 -> 2.2194701 | Q15: =Q14*Inputs!$F$111*Time!Q9/Inputs!$F$45*Time!Q20 -> 1.8187449 | ... DB15: =DB14*Inputs!$F$111*Time!DB9/Inputs!$F$45*Time!DB20 -> 0
D16: Bond escrow: closing | E16: ARD m | J16: =J14-J36 -> 485.17159 | K16: =K14-K36 -> 485.17159 | L16: =L14-L36 -> 485.17159 | M16: =M14-M36 -> 485.17159 | N16: =N14-N36 -> 478.90641 | O16: =O14-O36 -> 419.30983 | P16: =P14-P36 -> 351.2391 | Q16: =Q14-Q36 -> 278.54469 | ... DB16: =DB14-DB36 -> 0
D17: Contribution bridge: opening | E17: ARD m | J17: =I40 -> 0 | K17: =J40 -> 0 | L17: =K40 -> 0 | M17: =L40 -> 0 | N17: =M40 -> 0 | O17: =N40 -> 0 | P17: =O40 -> 0 | Q17: =P40 -> 0 | ... DB17: =DA40 -> 0
D18: Bridge interest | E18: ARD m | G18: =SUM(J18:DB18) -> 8.1272408 | J18: =J17*(Time!J54/100+Inputs!$F$83)*MAX(0,MIN(Time!J8,Time!$F$16)-Time!J7)/Inputs!$F$45 -> 0 | K18: =K17*(Time!K54/100+Inputs!$F$83)*MAX(0,MIN(Time!K8,Time!$F$16)-Time!K7)/Inputs!$F$45 -> 0 | L18: =L17*(Time!L54/100+Inputs!$F$83)*MAX(0,MIN(Time!L8,Time!$F$16)-Time!L7)/Inputs!$F$45 -> 0 | M18: =M17*(Time!M54/100+Inputs!$F$83)*MAX(0,MIN(Time!M8,Time!$F$16)-Time!M7)/Inputs!$F$45 -> 0 | N18: =N17*(Time!N54/100+Inputs!$F$83)*MAX(0,MIN(Time!N8,Time!$F$16)-Time!N7)/Inputs!$F$45 -> 0 | O18: =O17*(Time!O54/100+Inputs!$F$83)*MAX(0,MIN(Time!O8,Time!$F$16)-Time!O7)/Inputs!$F$45 -> 0 | P18: =P17*(Time!P54/100+Inputs!$F$83)*MAX(0,MIN(Time!P8,Time!$F$16)-Time!P7)/Inputs!$F$45 -> 0 | Q18: =Q17*(Time!Q54/100+Inputs!$F$83)*MAX(0,MIN(Time!Q8,Time!$F$16)-Time!Q7)/Inputs!$F$45 -> 0 | ... DB18: =DB17*(Time!DB54/100+Inputs!$F$83)*MAX(0,MIN(Time!DB8,Time!$F$16)-Time!DB7)/Inputs!$F$45 -> 0
D19: Bridge interest during construction | E19: ARD m | G19: =SUM(J19:DB19) -> 7.2031514 | J19: =J18*Time!J20 -> 0 | K19: =K18*Time!K20 -> 0 | L19: =L18*Time!L20 -> 0 | M19: =M18*Time!M20 -> 0 | N19: =N18*Time!N20 -> 0 | O19: =O18*Time!O20 -> 0 | P19: =P18*Time!P20 -> 0 | Q19: =Q18*Time!Q20 -> 0 | ... DB19: =DB18*Time!DB20 -> 0
D20: Bridge interest after completion (paid from operations) | E20: ARD m | G20: =SUM(J20:DB20) -> 0.92408942 | J20: =J18*(1-Time!J20) -> 0 | K20: =K18*(1-Time!K20) -> 0 | L20: =L18*(1-Time!L20) -> 0 | M20: =M18*(1-Time!M20) -> 0 | N20: =N18*(1-Time!N20) -> 0 | O20: =O18*(1-Time!O20) -> 0 | P20: =P18*(1-Time!P20) -> 0 | Q20: =Q18*(1-Time!Q20) -> 0 | ... DB20: =DB18*(1-Time!DB20) -> 0
D21: DSRA initial funding | E21: ARD m | G21: =SUM(J21:DB21) -> 13.887642 | J21: =IF(Time!J8=Inputs!$F$15,Reserves!J7,0) -> 0 | K21: =IF(Time!K8=Inputs!$F$15,Reserves!K7,0) -> 0 | L21: =IF(Time!L8=Inputs!$F$15,Reserves!L7,0) -> 0 | M21: =IF(Time!M8=Inputs!$F$15,Reserves!M7,0) -> 0 | N21: =IF(Time!N8=Inputs!$F$15,Reserves!N7,0) -> 0 | O21: =IF(Time!O8=Inputs!$F$15,Reserves!O7,0) -> 0 | P21: =IF(Time!P8=Inputs!$F$15,Reserves!P7,0) -> 0 | Q21: =IF(Time!Q8=Inputs!$F$15,Reserves!Q7,0) -> 0 | ... DB21: =IF(Time!DB8=Inputs!$F$15,Reserves!DB7,0) -> 0
D22: Ramp-up interest account funding | E22: ARD m | G22: =SUM(J22:DB22) -> 20.225926 | J22: =IF(Time!J8=Inputs!$F$15,SUM(Debt!$J$39:$DB$39),0) -> 0 | K22: =IF(Time!K8=Inputs!$F$15,SUM(Debt!$J$39:$DB$39),0) -> 0 | L22: =IF(Time!L8=Inputs!$F$15,SUM(Debt!$J$39:$DB$39),0) -> 0 | M22: =IF(Time!M8=Inputs!$F$15,SUM(Debt!$J$39:$DB$39),0) -> 0 | N22: =IF(Time!N8=Inputs!$F$15,SUM(Debt!$J$39:$DB$39),0) -> 0 | O22: =IF(Time!O8=Inputs!$F$15,SUM(Debt!$J$39:$DB$39),0) -> 0 | P22: =IF(Time!P8=Inputs!$F$15,SUM(Debt!$J$39:$DB$39),0) -> 0 | Q22: =IF(Time!Q8=Inputs!$F$15,SUM(Debt!$J$39:$DB$39),0) -> 0 | ... DB22: =IF(Time!DB8=Inputs!$F$15,SUM(Debt!$J$39:$DB$39),0) -> 0
D23: Total uses | E23: ARD m | G23: =SUM(J23:DB23) -> 2013.3801 | J23: =(J9+J10+J11+J12+J13-J15+J19+J21+J22)*Time!J20 -> 73.414541 | K23: =(K9+K10+K11+K12+K13-K15+K19+K21+K22)*Time!K20 -> 29.966422 | L23: =(L9+L10+L11+L12+L13-L15+L19+L21+L22)*Time!L20 -> 61.452349 | M23: =(M9+M10+M11+M12+M13-M15+M19+M21+M22)*Time!M20 -> 98.073619 | N23: =(N9+N10+N11+N12+N13-N15+N19+N21+N22)*Time!N20 -> 134.19346 | O23: =(O9+O10+O11+O12+O13-O15+O19+O21+O22)*Time!O20 -> 165.36985 | P23: =(P9+P10+P11+P12+P13-P15+P19+P21+P22)*Time!P20 -> 188.88411 | Q23: =(Q9+Q10+Q11+Q12+Q13-Q15+Q19+Q21+Q22)*Time!Q20 -> 201.714 | ... DB23: =(DB9+DB10+DB11+DB12+DB13-DB15+DB19+DB21+DB22)*Time!DB20 -> 0
D24: Total uses (eligible costs) | E24: ARD m | F24: =SUM($J$23:$DB$23) -> 2013.3801
D25: Funding requirement net of the state contribution | E25: ARD m | F25: =$F$24-Inputs!$F$227 -> 1725.9801
D26: Sources of funds (equity first, then debt pro rata; bridge in the last six quarters)
D27: Equity drawn | E27: ARD m | G27: =SUM(J27:DB27) -> 379.71562 | J27: =MIN(J23,MAX(0,Debt!$F$29-I28))*Time!J20 -> 73.414541 | K27: =MIN(K23,MAX(0,Debt!$F$29-J28))*Time!K20 -> 29.966422 | L27: =MIN(L23,MAX(0,Debt!$F$29-K28))*Time!L20 -> 61.452349 | M27: =MIN(M23,MAX(0,Debt!$F$29-L28))*Time!M20 -> 98.073619 | N27: =MIN(N23,MAX(0,Debt!$F$29-M28))*Time!N20 -> 116.80869 | O27: =MIN(O23,MAX(0,Debt!$F$29-N28))*Time!O20 -> 0 | P27: =MIN(P23,MAX(0,Debt!$F$29-O28))*Time!P20 -> 0 | Q27: =MIN(Q23,MAX(0,Debt!$F$29-P28))*Time!Q20 -> 0 | ... DB27: =MIN(DB23,MAX(0,Debt!$F$29-DA28))*Time!DB20 -> 0
D28: Cumulative equity | E28: ARD m | J28: =I28+J27 -> 73.414541 | K28: =J28+K27 -> 103.38096 | L28: =K28+L27 -> 164.83331 | M28: =L28+M27 -> 262.90693 | N28: =M28+N27 -> 379.71562 | O28: =N28+O27 -> 379.71562 | P28: =O28+P27 -> 379.71562 | Q28: =P28+Q27 -> 379.71562 | ... DB28: =DA28+DB27 -> 379.71562
D29: Funding need after equity | E29: ARD m | G29: =SUM(J29:DB29) -> 1633.6645 | J29: =J23-J27 -> 0 | K29: =K23-K27 -> 0 | L29: =L23-L27 -> 0 | M29: =M23-M27 -> 0 | N29: =N23-N27 -> 17.38477 | O29: =O23-O27 -> 165.36985 | P29: =P23-P27 -> 188.88411 | Q29: =Q23-Q27 -> 201.714 | ... DB29: =DB23-DB27 -> 0
D30: Need in the bridge draw quarters | E30: ARD m | F30: =SUMPRODUCT($J$29:$DB$29,Time!$J$22:$DB$22) -> 662.7535
D31: Bridge drawn | E31: ARD m | G31: =SUM(J31:DB31) -> 287.4 | J31: =IF(AND(Time!J22=1,$F$30<>0),Inputs!$F$227*J29/$F$30,0) -> 0 | K31: =IF(AND(Time!K22=1,$F$30<>0),Inputs!$F$227*K29/$F$30,0) -> 0 | L31: =IF(AND(Time!L22=1,$F$30<>0),Inputs!$F$227*L29/$F$30,0) -> 0 | M31: =IF(AND(Time!M22=1,$F$30<>0),Inputs!$F$227*M29/$F$30,0) -> 0 | N31: =IF(AND(Time!N22=1,$F$30<>0),Inputs!$F$227*N29/$F$30,0) -> 0 | O31: =IF(AND(Time!O22=1,$F$30<>0),Inputs!$F$227*O29/$F$30,0) -> 0 | P31: =IF(AND(Time!P22=1,$F$30<>0),Inputs!$F$227*P29/$F$30,0) -> 0 | Q31: =IF(AND(Time!Q22=1,$F$30<>0),Inputs!$F$227*Q29/$F$30,0) -> 0 | ... DB31: =IF(AND(Time!DB22=1,$F$30<>0),Inputs!$F$227*DB29/$F$30,0) -> 0
D32: Debt drawn (senior plus NILO) | E32: ARD m | G32: =SUM(J32:DB32) -> 1346.2645 | J32: =J29-J31 -> 0 | K32: =K29-K31 -> 0 | L32: =L29-L31 -> 0 | M32: =M29-M31 -> 0 | N32: =N29-N31 -> 17.38477 | O32: =O29-O31 -> 165.36985 | P32: =P29-P31 -> 188.88411 | Q32: =Q29-Q31 -> 201.714 | ... DB32: =DB29-DB31 -> 0
D33: Senior drawn | E33: ARD m | G33: =SUM(J33:DB33) -> 882.13017 | J33: =IF(Debt!$F$26+Debt!$F$28=0,0,J32*Debt!$F$26/(Debt!$F$26+Debt!$F$28)) -> 0 | K33: =IF(Debt!$F$26+Debt!$F$28=0,0,K32*Debt!$F$26/(Debt!$F$26+Debt!$F$28)) -> 0 | L33: =IF(Debt!$F$26+Debt!$F$28=0,0,L32*Debt!$F$26/(Debt!$F$26+Debt!$F$28)) -> 0 | M33: =IF(Debt!$F$26+Debt!$F$28=0,0,M32*Debt!$F$26/(Debt!$F$26+Debt!$F$28)) -> 0 | N33: =IF(Debt!$F$26+Debt!$F$28=0,0,N32*Debt!$F$26/(Debt!$F$26+Debt!$F$28)) -> 11.391246 | O33: =IF(Debt!$F$26+Debt!$F$28=0,0,O32*Debt!$F$26/(Debt!$F$26+Debt!$F$28)) -> 108.35741 | P33: =IF(Debt!$F$26+Debt!$F$28=0,0,P32*Debt!$F$26/(Debt!$F$26+Debt!$F$28)) -> 123.76496 | Q33: =IF(Debt!$F$26+Debt!$F$28=0,0,Q32*Debt!$F$26/(Debt!$F$26+Debt!$F$28)) -> 132.17165 | ... DB33: =IF(Debt!$F$26+Debt!$F$28=0,0,DB32*Debt!$F$26/(Debt!$F$26+Debt!$F$28)) -> 0
D34: NILO drawn | E34: ARD m | G34: =SUM(J34:DB34) -> 464.13432 | J34: =J32-J33 -> 0 | K34: =K32-K33 -> 0 | L34: =L32-L33 -> 0 | M34: =M32-M33 -> 0 | N34: =N32-N33 -> 5.9935237 | O34: =O32-O33 -> 57.012439 | P34: =P32-P33 -> 65.119149 | Q34: =Q32-Q33 -> 69.542345 | ... DB34: =DB32-DB33 -> 0
D35: Bank drawn | E35: ARD m | G35: =SUM(J35:DB35) -> 396.95858 | J35: =Inputs!$F$96*J33 -> 0 | K35: =Inputs!$F$96*K33 -> 0 | L35: =Inputs!$F$96*L33 -> 0 | M35: =Inputs!$F$96*M33 -> 0 | N35: =Inputs!$F$96*N33 -> 5.1260606 | O35: =Inputs!$F$96*O33 -> 48.760834 | P35: =Inputs!$F$96*P33 -> 55.694233 | Q35: =Inputs!$F$96*Q33 -> 59.477244 | ... DB35: =Inputs!$F$96*DB33 -> 0
D36: Bond escrow released | E36: ARD m | G36: =SUM(J36:DB36) -> 485.17159 | J36: =Inputs!$F$97*J33 -> 0 | K36: =Inputs!$F$97*K33 -> 0 | L36: =Inputs!$F$97*L33 -> 0 | M36: =Inputs!$F$97*M33 -> 0 | N36: =Inputs!$F$97*N33 -> 6.2651852 | O36: =Inputs!$F$97*O33 -> 59.596575 | P36: =Inputs!$F$97*P33 -> 68.070729 | Q36: =Inputs!$F$97*Q33 -> 72.69441 | ... DB36: =Inputs!$F$97*DB33 -> 0
D37: Equity: share capital | E37: ARD m | G37: =SUM(J37:DB37) -> 56.957344 | J37: =Inputs!$F$88*J27 -> 11.012181 | K37: =Inputs!$F$88*K27 -> 4.4949633 | L37: =Inputs!$F$88*L27 -> 9.2178524 | M37: =Inputs!$F$88*M27 -> 14.711043 | N37: =Inputs!$F$88*N27 -> 17.521304 | O37: =Inputs!$F$88*O27 -> 0 | P37: =Inputs!$F$88*P27 -> 0 | Q37: =Inputs!$F$88*Q27 -> 0 | ... DB37: =Inputs!$F$88*DB27 -> 0
D38: Equity: shareholder loans | E38: ARD m | G38: =SUM(J38:DB38) -> 322.75828 | J38: =J27-J37 -> 62.40236 | K38: =K27-K37 -> 25.471459 | L38: =L27-L37 -> 52.234497 | M38: =M27-M37 -> 83.362576 | N38: =N27-N37 -> 99.287389 | O38: =O27-O37 -> 0 | P38: =P27-P37 -> 0 | Q38: =Q27-Q37 -> 0 | ... DB38: =DB27-DB37 -> 0
D39: State contribution received (repays the bridge) | E39: ARD m | G39: =SUM(J39:DB39) -> 287.4 | J39: =Inputs!$F$227*Time!J27 -> 0 | K39: =Inputs!$F$227*Time!K27 -> 0 | L39: =Inputs!$F$227*Time!L27 -> 0 | M39: =Inputs!$F$227*Time!M27 -> 0 | N39: =Inputs!$F$227*Time!N27 -> 0 | O39: =Inputs!$F$227*Time!O27 -> 0 | P39: =Inputs!$F$227*Time!P27 -> 0 | Q39: =Inputs!$F$227*Time!Q27 -> 0 | ... DB39: =Inputs!$F$227*Time!DB27 -> 0
D40: Contribution bridge: closing | E40: ARD m | J40: =J17+J31-J39 -> 0 | K40: =K17+K31-K39 -> 0 | L40: =L17+L31-L39 -> 0 | M40: =M17+M31-M39 -> 0 | N40: =N17+N31-N39 -> 0 | O40: =O17+O31-O39 -> 0 | P40: =P17+P31-P39 -> 0 | Q40: =Q17+Q31-Q39 -> 0 | ... DB40: =DB17+DB31-DB39 -> 0
D41: Capitalized cost (uses less reserves plus capitalized NILO and SHL interest) | E41: ARD m | G41: =SUM(J41:DB41) -> 2124.6053 | J41: =(J23-J21-J22+Debt!J97+Waterfall!J54)*Time!J20 -> 73.414541 | K41: =(K23-K21-K22+Debt!K97+Waterfall!K54)*Time!K20 -> 31.578625 | L41: =(L23-L21-L22+Debt!L97+Waterfall!L54)*Time!L20 -> 63.764276 | M41: =(M23-M21-M22+Debt!M97+Waterfall!M54)*Time!M20 -> 101.75434 | N41: =(N23-N21-N22+Debt!N97+Waterfall!N54)*Time!N20 -> 140.09856 | O41: =(O23-O21-O22+Debt!O97+Waterfall!O54)*Time!O20 -> 174.10377 | P41: =(P23-P21-P22+Debt!P97+Waterfall!P54)*Time!P20 -> 198.28257 | Q41: =(Q23-Q21-Q22+Debt!Q97+Waterfall!Q54)*Time!Q20 -> 211.6284 | ... DB41: =(DB23-DB21-DB22+Debt!DB97+Waterfall!DB54)*Time!DB20 -> 0
D42: Sources less uses | E42: ARD m | G42: =SUM(J42:DB42) -> 0 | J42: =J27+J31+J32-J23 -> 0 | K42: =K27+K31+K32-K23 -> 0 | L42: =L27+L31+L32-L23 -> 0 | M42: =M27+M31+M32-M23 -> 0 | N42: =N27+N31+N32-N23 -> 0 | O42: =O27+O31+O32-O23 -> 0 | P42: =P27+P31+P32-P23 -> 0 | Q42: =Q27+Q31+Q32-Q23 -> 0 | ... DB42: =DB27+DB31+DB32-DB23 -> 0

Sheet Debt
D1: Case T: Merrick Link toll road PPP | Debt
D2: Units: ARD millions unless stated. Inputs blue on yellow; links green; calculations black.
D3: Period end | E3: date | J3: =Time!J8 -> 42185 | K3: =Time!K8 -> 42277 | L3: =Time!L8 -> 42369 | M3: =Time!M8 -> 42460 | N3: =Time!N8 -> 42551 | O3: =Time!O8 -> 42643 | P3: =Time!P8 -> 42735 | Q3: =Time!Q8 -> 42825 | ... DB3: =Time!DB8 -> 58256
D5: Rates
D6: Bank margin after the mini-perm maturity | E6: %pa | F6: =IF(Inputs!$F$213=1,Inputs!$F$105,Inputs!$F$104+Inputs!$F$223) -> 3.25
D7: Bank margin (day-weighted) | E7: %pa | J7: =Inputs!$F$102*Time!J40+Inputs!$F$103*(Time!J41-Time!J40)+$F$6*(1-Time!J41) -> 2.35 | K7: =Inputs!$F$102*Time!K40+Inputs!$F$103*(Time!K41-Time!K40)+$F$6*(1-Time!K41) -> 2.35 | L7: =Inputs!$F$102*Time!L40+Inputs!$F$103*(Time!L41-Time!L40)+$F$6*(1-Time!L41) -> 2.35 | M7: =Inputs!$F$102*Time!M40+Inputs!$F$103*(Time!M41-Time!M40)+$F$6*(1-Time!M41) -> 2.35 | N7: =Inputs!$F$102*Time!N40+Inputs!$F$103*(Time!N41-Time!N40)+$F$6*(1-Time!N41) -> 2.35 | O7: =Inputs!$F$102*Time!O40+Inputs!$F$103*(Time!O41-Time!O40)+$F$6*(1-Time!O41) -> 2.35 | P7: =Inputs!$F$102*Time!P40+Inputs!$F$103*(Time!P41-Time!P40)+$F$6*(1-Time!P41) -> 2.35 | Q7: =Inputs!$F$102*Time!Q40+Inputs!$F$103*(Time!Q41-Time!Q40)+$F$6*(1-Time!Q41) -> 2.35 | ... DB7: =Inputs!$F$102*Time!DB40+Inputs!$F$103*(Time!DB41-Time!DB40)+$F$6*(1-Time!DB41) -> 3.25
D8: Bank all-in rate | E8: % | J8: =(IF(Time!J43=1,Inputs!$F$100,Time!J54)+J7)/100 -> 0.0583 | K8: =(IF(Time!K43=1,Inputs!$F$100,Time!K54)+K7)/100 -> 0.0583 | L8: =(IF(Time!L43=1,Inputs!$F$100,Time!L54)+L7)/100 -> 0.0583 | M8: =(IF(Time!M43=1,Inputs!$F$100,Time!M54)+M7)/100 -> 0.0583 | N8: =(IF(Time!N43=1,Inputs!$F$100,Time!N54)+N7)/100 -> 0.0583 | O8: =(IF(Time!O43=1,Inputs!$F$100,Time!O54)+O7)/100 -> 0.0583 | P8: =(IF(Time!P43=1,Inputs!$F$100,Time!P54)+P7)/100 -> 0.0583 | Q8: =(IF(Time!Q43=1,Inputs!$F$100,Time!Q54)+Q7)/100 -> 0.0583 | ... DB8: =(IF(Time!DB43=1,Inputs!$F$100,Time!DB54)+DB7)/100 -> 0.0675
D9: Senior blended period rate | E9: % | J9: =Inputs!$F$96*J8*Time!J9/Inputs!$F$45+Inputs!$F$97*Inputs!$F$110*Time!J10/Inputs!$F$46 -> 0.0048890166 | K9: =Inputs!$F$96*K8*Time!K9/Inputs!$F$45+Inputs!$F$97*Inputs!$F$110*Time!K10/Inputs!$F$46 -> 0.013281408 | L9: =Inputs!$F$96*L8*Time!L9/Inputs!$F$45+Inputs!$F$97*Inputs!$F$110*Time!L10/Inputs!$F$46 -> 0.013281408 | M9: =Inputs!$F$96*M8*Time!M9/Inputs!$F$45+Inputs!$F$97*Inputs!$F$110*Time!M10/Inputs!$F$46 -> 0.013209531 | N9: =Inputs!$F$96*N8*Time!N9/Inputs!$F$45+Inputs!$F$97*Inputs!$F$110*Time!N10/Inputs!$F$46 -> 0.013209531 | O9: =Inputs!$F$96*O8*Time!O9/Inputs!$F$45+Inputs!$F$97*Inputs!$F$110*Time!O10/Inputs!$F$46 -> 0.013281408 | P9: =Inputs!$F$96*P8*Time!P9/Inputs!$F$45+Inputs!$F$97*Inputs!$F$110*Time!P10/Inputs!$F$46 -> 0.013281408 | Q9: =Inputs!$F$96*Q8*Time!Q9/Inputs!$F$45+Inputs!$F$97*Inputs!$F$110*Time!Q10/Inputs!$F$46 -> 0.013137654 | ... DB9: =Inputs!$F$96*DB8*Time!DB9/Inputs!$F$45+Inputs!$F$97*Inputs!$F$110*Time!DB10/Inputs!$F$46 -> 0.028400171
D10: Notes period rate | E10: % | J10: =Inputs!$F$166*Time!J10/Inputs!$F$46 -> 0.004675 | K10: =Inputs!$F$166*Time!K10/Inputs!$F$46 -> 0.01275 | L10: =Inputs!$F$166*Time!L10/Inputs!$F$46 -> 0.01275 | M10: =Inputs!$F$166*Time!M10/Inputs!$F$46 -> 0.01275 | N10: =Inputs!$F$166*Time!N10/Inputs!$F$46 -> 0.01275 | O10: =Inputs!$F$166*Time!O10/Inputs!$F$46 -> 0.01275 | P10: =Inputs!$F$166*Time!P10/Inputs!$F$46 -> 0.01275 | Q10: =Inputs!$F$166*Time!Q10/Inputs!$F$46 -> 0.01275 | ... DB10: =Inputs!$F$166*Time!DB10/Inputs!$F$46 -> 0.0255
D11: Senior sizing (live in Scenario 2)
D12: Discount factor from 2021-01-01 at the senior rate | E12: factor | J12: =IF(Time!J30=1,IF(Time!I30=1,I12,1)/(1+J9),0) -> 0 | K12: =IF(Time!K30=1,IF(Time!J30=1,J12,1)/(1+K9),0) -> 0 | L12: =IF(Time!L30=1,IF(Time!K30=1,K12,1)/(1+L9),0) -> 0 | M12: =IF(Time!M30=1,IF(Time!L30=1,L12,1)/(1+M9),0) -> 0 | N12: =IF(Time!N30=1,IF(Time!M30=1,M12,1)/(1+N9),0) -> 0 | O12: =IF(Time!O30=1,IF(Time!N30=1,N12,1)/(1+O9),0) -> 0 | P12: =IF(Time!P30=1,IF(Time!O30=1,O12,1)/(1+P9),0) -> 0 | Q12: =IF(Time!Q30=1,IF(Time!P30=1,P12,1)/(1+Q9),0) -> 0 | ... DB12: =IF(Time!DB30=1,IF(Time!DA30=1,DA12,1)/(1+DB9),0) -> 0
D13: CFADS | E13: ARD m | G13: =SUM(J13:DB13) -> 4818.7014 | J13: =Operations!J48 -> 0 | K13: =Operations!K48 -> 0 | L13: =Operations!L48 -> 0 | M13: =Operations!M48 -> 0 | N13: =Operations!N48 -> 0 | O13: =Operations!O48 -> 0 | P13: =Operations!P48 -> 0 | Q13: =Operations!Q48 -> 0 | ... DB13: =Operations!DB48 -> 121.9839
D14: PV of CFADS over the repayment periods | E14: ARD m | F14: =SUMPRODUCT($J$13:$DB$13,$J$12:$DB$12,Time!$J$30:$DB$30) -> 1221.7802
D15: Capacity: 55% of funding requirement net of contribution | E15: ARD m | F15: =Inputs!$F$94*Funding!$F$25 -> 949.28906
D16: Capacity: sculpted at 1.50x (PV / 1.50) | E16: ARD m | F16: =$F$14/Inputs!$F$91 -> 814.52016
D17: Capacity: LLCR 1.55x | E17: ARD m | F17: =$F$14/Inputs!$F$93 -> 788.24531
D18: Interest-only capacity at 1.50x | E18: ARD m | J18: =IF(AND(Time!J30=1,J9>0),J13/(Inputs!$F$91*J9),Inputs!$F$10) -> 1000000000000 | K18: =IF(AND(Time!K30=1,K9>0),K13/(Inputs!$F$91*K9),Inputs!$F$10) -> 1000000000000 | L18: =IF(AND(Time!L30=1,L9>0),L13/(Inputs!$F$91*L9),Inputs!$F$10) -> 1000000000000 | M18: =IF(AND(Time!M30=1,M9>0),M13/(Inputs!$F$91*M9),Inputs!$F$10) -> 1000000000000 | N18: =IF(AND(Time!N30=1,N9>0),N13/(Inputs!$F$91*N9),Inputs!$F$10) -> 1000000000000 | O18: =IF(AND(Time!O30=1,O9>0),O13/(Inputs!$F$91*O9),Inputs!$F$10) -> 1000000000000 | P18: =IF(AND(Time!P30=1,P9>0),P13/(Inputs!$F$91*P9),Inputs!$F$10) -> 1000000000000 | Q18: =IF(AND(Time!Q30=1,Q9>0),Q13/(Inputs!$F$91*Q9),Inputs!$F$10) -> 1000000000000 | ... DB18: =IF(AND(Time!DB30=1,DB9>0),DB13/(Inputs!$F$91*DB9),Inputs!$F$10) -> 1000000000000
D19: Capacity: interest cover 1.50x in every repayment period | E19: ARD m | F19: =MIN($J$18:$DB$18) -> 446.15696
D20: Downside interest-only capacity at 1.15x | E20: ARD m | J20: =IF(AND(Time!J30=1,J9>0),Inputs!J275/(Inputs!$F$92*J9),Inputs!$F$10) -> 1000000000000 | K20: =IF(AND(Time!K30=1,K9>0),Inputs!K275/(Inputs!$F$92*K9),Inputs!$F$10) -> 1000000000000 | L20: =IF(AND(Time!L30=1,L9>0),Inputs!L275/(Inputs!$F$92*L9),Inputs!$F$10) -> 1000000000000 | M20: =IF(AND(Time!M30=1,M9>0),Inputs!M275/(Inputs!$F$92*M9),Inputs!$F$10) -> 1000000000000 | N20: =IF(AND(Time!N30=1,N9>0),Inputs!N275/(Inputs!$F$92*N9),Inputs!$F$10) -> 1000000000000 | O20: =IF(AND(Time!O30=1,O9>0),Inputs!O275/(Inputs!$F$92*O9),Inputs!$F$10) -> 1000000000000 | P20: =IF(AND(Time!P30=1,P9>0),Inputs!P275/(Inputs!$F$92*P9),Inputs!$F$10) -> 1000000000000 | Q20: =IF(AND(Time!Q30=1,Q9>0),Inputs!Q275/(Inputs!$F$92*Q9),Inputs!$F$10) -> 1000000000000 | ... DB20: =IF(AND(Time!DB30=1,DB9>0),Inputs!DB275/(Inputs!$F$92*DB9),Inputs!$F$10) -> 1000000000000
D21: Capacity: downside interest cover 1.15x | E21: ARD m | F21: =MIN($J$20:$DB$20) -> 888.95503
D22: Senior debt, live sizing (lesser of the constraints) | E22: ARD m | F22: =MIN($F$15,$F$16,$F$17,$F$19,$F$21) -> 446.15696
D23: Binding constraint (1 gearing, 2 sculpt, 3 LLCR, 4 interest cover, 5 downside) | E23: # | F23: =IF($F$22=$F$15,1,IF($F$22=$F$16,2,IF($F$22=$F$17,3,IF($F$22=$F$19,4,5)))) -> 4
D24: Live sizing active (Live and Circ) | E24: flag | F24: =IF(AND(Inputs!$F$8=1,Inputs!$F$225=1),1,0) -> 0
D25: Live restructured sculpting active | E25: flag | F25: =IF(AND(Inputs!$F$8=1,Inputs!$F$226=1),1,0) -> 0
D26: Senior debt applied | E26: ARD m | F26: =IF($F$24=1,$F$22,Inputs!$F$269) -> 882.13017
D27: NILO, live (remainder, capped at 33% of eligible costs) | E27: ARD m | F27: =MIN(Funding!$F$25-Inputs!$F$87*Funding!$F$25-$F$22,Inputs!$F$120*Funding!$F$24) -> 664.41544
D28: NILO applied | E28: ARD m | F28: =IF($F$24=1,$F$27,Inputs!$F$270) -> 464.13432
D29: Equity applied | E29: ARD m | F29: =IF($F$24=1,Funding!$F$25-$F$26-$F$28,Inputs!$F$271) -> 379.71562
D30: Senior sculpting: DS = MAX(interest, CFADS / s) from June 2021
D31: Scheduled balance: opening | E31: ARD m | J31: =IF(Time!J21=1,$F$26,I36) -> 0 | K31: =IF(Time!K21=1,$F$26,J36) -> 0 | L31: =IF(Time!L21=1,$F$26,K36) -> 0 | M31: =IF(Time!M21=1,$F$26,L36) -> 0 | N31: =IF(Time!N21=1,$F$26,M36) -> 0 | O31: =IF(Time!O21=1,$F$26,N36) -> 0 | P31: =IF(Time!P21=1,$F$26,O36) -> 0 | Q31: =IF(Time!Q21=1,$F$26,P36) -> 0 | ... DB31: =IF(Time!DB21=1,$F$26,DA36) -> -20.115541
D32: Scheduled interest | E32: ARD m | G32: =SUM(J32:DB32) -> 1161.7833 | J32: =J31*J9 -> 0 | K32: =K31*K9 -> 0 | L32: =L31*L9 -> 0 | M32: =M31*M9 -> 0 | N32: =N31*N9 -> 0 | O32: =O31*O9 -> 0 | P32: =P31*P9 -> 0 | Q32: =Q31*Q9 -> 0 | ... DB32: =DB31*DB9 -> -0.5712848
D33: Flag_InterestOnly (interest above CFADS / s) | E33: flag | J33: =IF(AND(Time!J30=1,J32>J13/$F$37),1,0) -> 0 | K33: =IF(AND(Time!K30=1,K32>K13/$F$37),1,0) -> 0 | L33: =IF(AND(Time!L30=1,L32>L13/$F$37),1,0) -> 0 | M33: =IF(AND(Time!M30=1,M32>M13/$F$37),1,0) -> 0 | N33: =IF(AND(Time!N30=1,N32>N13/$F$37),1,0) -> 0 | O33: =IF(AND(Time!O30=1,O32>O13/$F$37),1,0) -> 0 | P33: =IF(AND(Time!P30=1,P32>P13/$F$37),1,0) -> 0 | Q33: =IF(AND(Time!Q30=1,Q32>Q13/$F$37),1,0) -> 0 | ... DB33: =IF(AND(Time!DB30=1,DB32>DB13/$F$37),1,0) -> 0
D34: Scheduled debt service | E34: ARD m | G34: =SUM(J34:DB34) -> 1993.6655 | J34: =IF(Time!J30=1,MAX(J32,J13/$F$37),0) -> 0 | K34: =IF(Time!K30=1,MAX(K32,K13/$F$37),0) -> 0 | L34: =IF(Time!L30=1,MAX(L32,L13/$F$37),0) -> 0 | M34: =IF(Time!M30=1,MAX(M32,M13/$F$37),0) -> 0 | N34: =IF(Time!N30=1,MAX(N32,N13/$F$37),0) -> 0 | O34: =IF(Time!O30=1,MAX(O32,O13/$F$37),0) -> 0 | P34: =IF(Time!P30=1,MAX(P32,P13/$F$37),0) -> 0 | Q34: =IF(Time!Q30=1,MAX(Q32,Q13/$F$37),0) -> 0 | ... DB34: =IF(Time!DB30=1,MAX(DB32,DB13/$F$37),0) -> 0
D35: Scheduled principal (live) | E35: ARD m | G35: =SUM(J35:DB35) -> 902.24571 | J35: =IF(Time!J30=1,J34-J32,0) -> 0 | K35: =IF(Time!K30=1,K34-K32,0) -> 0 | L35: =IF(Time!L30=1,L34-L32,0) -> 0 | M35: =IF(Time!M30=1,M34-M32,0) -> 0 | N35: =IF(Time!N30=1,N34-N32,0) -> 0 | O35: =IF(Time!O30=1,O34-O32,0) -> 0 | P35: =IF(Time!P30=1,P34-P32,0) -> 0 | Q35: =IF(Time!Q30=1,Q34-Q32,0) -> 0 | ... DB35: =IF(Time!DB30=1,DB34-DB32,0) -> 0
D36: Scheduled balance: closing | E36: ARD m | J36: =J31-J35 -> 0 | K36: =K31-K35 -> 0 | L36: =L31-L35 -> 0 | M36: =M31-M35 -> 0 | N36: =N31-N35 -> 0 | O36: =O31-O35 -> 0 | P36: =P31-P35 -> 0 | Q36: =Q31-Q35 -> 0 | ... DB36: =DB31-DB35 -> -20.115541
D37: Sculpting divisor s (fixed point) | E37: x | F37: =IF($F$24=1,IFERROR(MAX(Inputs!$F$9,SUMPRODUCT($J$13:$DB$13*$J$12:$DB$12*Time!$J$30:$DB$30*(1-$J$33:$DB$33))/($F$26-SUMPRODUCT($J$32:$DB$32*$J$12:$DB$12*$J$33:$DB$33))),Inputs!$F$91),Inputs!$F$91) -> 1.5
D38: Ramp-up interest account release (live) | E38: ARD m | G38: =SUM(J38:DB38) -> 44.431098 | J38: =IF(Time!J32=1,MAX(0,J32-J13/Inputs!$F$95),0) -> 0 | K38: =IF(Time!K32=1,MAX(0,K32-K13/Inputs!$F$95),0) -> 0 | L38: =IF(Time!L32=1,MAX(0,L32-L13/Inputs!$F$95),0) -> 0 | M38: =IF(Time!M32=1,MAX(0,M32-M13/Inputs!$F$95),0) -> 0 | N38: =IF(Time!N32=1,MAX(0,N32-N13/Inputs!$F$95),0) -> 0 | O38: =IF(Time!O32=1,MAX(0,O32-O13/Inputs!$F$95),0) -> 0 | P38: =IF(Time!P32=1,MAX(0,P32-P13/Inputs!$F$95),0) -> 0 | Q38: =IF(Time!Q32=1,MAX(0,Q32-Q13/Inputs!$F$95),0) -> 0 | ... DB38: =IF(Time!DB32=1,MAX(0,DB32-DB13/Inputs!$F$95),0) -> 0
D39: Ramp-up interest account release (applied) | E39: ARD m | G39: =SUM(J39:DB39) -> 20.225926 | J39: =IF($F$24=1,J38,Inputs!J273) -> 0 | K39: =IF($F$24=1,K38,Inputs!K273) -> 0 | L39: =IF($F$24=1,L38,Inputs!L273) -> 0 | M39: =IF($F$24=1,M38,Inputs!M273) -> 0 | N39: =IF($F$24=1,N38,Inputs!N273) -> 0 | O39: =IF($F$24=1,O38,Inputs!O273) -> 0 | P39: =IF($F$24=1,P38,Inputs!P273) -> 0 | Q39: =IF($F$24=1,Q38,Inputs!Q273) -> 0 | ... DB39: =IF($F$24=1,DB38,Inputs!DB273) -> 0
D40: Scheduled senior principal (applied) | E40: ARD m | G40: =SUM(J40:DB40) -> 882.13017 | J40: =IF($F$24=1,J35,Inputs!J272) -> 0 | K40: =IF($F$24=1,K35,Inputs!K272) -> 0 | L40: =IF($F$24=1,L35,Inputs!L272) -> 0 | M40: =IF($F$24=1,M35,Inputs!M272) -> 0 | N40: =IF($F$24=1,N35,Inputs!N272) -> 0 | O40: =IF($F$24=1,O35,Inputs!O272) -> 0 | P40: =IF($F$24=1,P35,Inputs!P272) -> 0 | Q40: =IF($F$24=1,Q35,Inputs!Q272) -> 0 | ... DB40: =IF($F$24=1,DB35,Inputs!DB272) -> 0
D41: Bank mini-perm
D42: Opening balance | E42: ARD m | J42: =I47 -> 0 | K42: =J47 -> 0 | L42: =K47 -> 0 | M42: =L47 -> 0 | N42: =M47 -> 0 | O42: =N47 -> 5.1260606 | P42: =O47 -> 53.886895 | Q42: =P47 -> 109.58113 | ... DB42: =DA47 -> 0
D43: Interest | E43: ARD m | G43: =SUM(J43:DB43) -> 154.36363 | J43: =J42*J8*Time!J9/Inputs!$F$45 -> 0 | K43: =K42*K8*Time!K9/Inputs!$F$45 -> 0 | L43: =L42*L8*Time!L9/Inputs!$F$45 -> 0 | M43: =M42*M8*Time!M9/Inputs!$F$45 -> 0 | N43: =N42*N8*Time!N9/Inputs!$F$45 -> 0 | O43: =O42*O8*Time!O9/Inputs!$F$45 -> 0.075326408 | P43: =P42*P8*Time!P9/Inputs!$F$45 -> 0.79185685 | Q43: =Q42*Q8*Time!Q9/Inputs!$F$45 -> 1.5752662 | ... DB43: =DB42*DB8*Time!DB9/Inputs!$F$45 -> 0
D44: Interest due from operations | E44: ARD m | G44: =SUM(J44:DB44) -> 116.43423 | J44: =J43*(1-Time!J20) -> 0 | K44: =K43*(1-Time!K20) -> 0 | L44: =L43*(1-Time!L20) -> 0 | M44: =M43*(1-Time!M20) -> 0 | N44: =N43*(1-Time!N20) -> 0 | O44: =O43*(1-Time!O20) -> 0 | P44: =P43*(1-Time!P20) -> 0 | Q44: =Q43*(1-Time!Q20) -> 0 | ... DB44: =DB43*(1-Time!DB20) -> 0
D45: Principal due | E45: ARD m | G45: =SUM(J45:DB45) -> 0 | J45: =IF(OR(Time!J20=1,Time!J34=1,Time!J23=1),0,MIN(Inputs!$F$96*J40,J42)) -> 0 | K45: =IF(OR(Time!K20=1,Time!K34=1,Time!K23=1),0,MIN(Inputs!$F$96*K40,K42)) -> 0 | L45: =IF(OR(Time!L20=1,Time!L34=1,Time!L23=1),0,MIN(Inputs!$F$96*L40,L42)) -> 0 | M45: =IF(OR(Time!M20=1,Time!M34=1,Time!M23=1),0,MIN(Inputs!$F$96*M40,M42)) -> 0 | N45: =IF(OR(Time!N20=1,Time!N34=1,Time!N23=1),0,MIN(Inputs!$F$96*N40,N42)) -> 0 | O45: =IF(OR(Time!O20=1,Time!O34=1,Time!O23=1),0,MIN(Inputs!$F$96*O40,O42)) -> 0 | P45: =IF(OR(Time!P20=1,Time!P34=1,Time!P23=1),0,MIN(Inputs!$F$96*P40,P42)) -> 0 | Q45: =IF(OR(Time!Q20=1,Time!Q34=1,Time!Q23=1),0,MIN(Inputs!$F$96*Q40,Q42)) -> 0 | ... DB45: =IF(OR(Time!DB20=1,Time!DB34=1,Time!DB23=1),0,MIN(Inputs!$F$96*DB40,DB42)) -> 0
D46: Closing balance before restructuring | E46: ARD m | J46: =J42+Funding!J35-Waterfall!J20-Waterfall!J31 -> 0 | K46: =K42+Funding!K35-Waterfall!K20-Waterfall!K31 -> 0 | L46: =L42+Funding!L35-Waterfall!L20-Waterfall!L31 -> 0 | M46: =M42+Funding!M35-Waterfall!M20-Waterfall!M31 -> 0 | N46: =N42+Funding!N35-Waterfall!N20-Waterfall!N31 -> 5.1260606 | O46: =O42+Funding!O35-Waterfall!O20-Waterfall!O31 -> 53.886895 | P46: =P42+Funding!P35-Waterfall!P20-Waterfall!P31 -> 109.58113 | Q46: =Q42+Funding!Q35-Waterfall!Q20-Waterfall!Q31 -> 169.05837 | ... DB46: =DB42+Funding!DB35-Waterfall!DB20-Waterfall!DB31 -> 0
D47: Closing balance | E47: ARD m | J47: =IF(Time!J35=1,0,J46) -> 0 | K47: =IF(Time!K35=1,0,K46) -> 0 | L47: =IF(Time!L35=1,0,L46) -> 0 | M47: =IF(Time!M35=1,0,M46) -> 0 | N47: =IF(Time!N35=1,0,N46) -> 5.1260606 | O47: =IF(Time!O35=1,0,O46) -> 53.886895 | P47: =IF(Time!P35=1,0,P46) -> 109.58113 | Q47: =IF(Time!Q35=1,0,Q46) -> 169.05837 | ... DB47: =IF(Time!DB35=1,0,DB46) -> 0
D48: Revenue bonds
D49: Opening balance | E49: ARD m | J49: =IF(Time!J6=1,Funding!$F$7,I54) -> 485.17159 | K49: =IF(Time!K6=1,Funding!$F$7,J54) -> 485.17159 | L49: =IF(Time!L6=1,Funding!$F$7,K54) -> 485.17159 | M49: =IF(Time!M6=1,Funding!$F$7,L54) -> 485.17159 | N49: =IF(Time!N6=1,Funding!$F$7,M54) -> 485.17159 | O49: =IF(Time!O6=1,Funding!$F$7,N54) -> 485.17159 | P49: =IF(Time!P6=1,Funding!$F$7,O54) -> 485.17159 | Q49: =IF(Time!Q6=1,Funding!$F$7,P54) -> 485.17159 | ... DB49: =IF(Time!DB6=1,Funding!$F$7,DA54) -> 0
D50: Interest (30/360) | E50: ARD m | G50: =SUM(J50:DB50) -> 200.97607 | J50: =J49*Inputs!$F$110*Time!J10/Inputs!$F$46 -> 2.156992 | K50: =K49*Inputs!$F$110*Time!K10/Inputs!$F$46 -> 5.8827056 | L50: =L49*Inputs!$F$110*Time!L10/Inputs!$F$46 -> 5.8827056 | M50: =M49*Inputs!$F$110*Time!M10/Inputs!$F$46 -> 5.8827056 | N50: =N49*Inputs!$F$110*Time!N10/Inputs!$F$46 -> 5.8827056 | O50: =O49*Inputs!$F$110*Time!O10/Inputs!$F$46 -> 5.8827056 | P50: =P49*Inputs!$F$110*Time!P10/Inputs!$F$46 -> 5.8827056 | Q50: =Q49*Inputs!$F$110*Time!Q10/Inputs!$F$46 -> 5.8827056 | ... DB50: =DB49*Inputs!$F$110*Time!DB10/Inputs!$F$46 -> 0
D51: Interest due from operations | E51: ARD m | G51: =SUM(J51:DB51) -> 110.57849 | J51: =J50*(1-Time!J20) -> 0 | K51: =K50*(1-Time!K20) -> 0 | L51: =L50*(1-Time!L20) -> 0 | M51: =M50*(1-Time!M20) -> 0 | N51: =N50*(1-Time!N20) -> 0 | O51: =O50*(1-Time!O20) -> 0 | P51: =P50*(1-Time!P20) -> 0 | Q51: =Q50*(1-Time!Q20) -> 0 | ... DB51: =DB50*(1-Time!DB20) -> 0
D52: Principal due | E52: ARD m | G52: =SUM(J52:DB52) -> 0 | J52: =IF(OR(Time!J20=1,Time!J34=1,Time!J23=1),0,MIN(Inputs!$F$97*J40,J49)) -> 0 | K52: =IF(OR(Time!K20=1,Time!K34=1,Time!K23=1),0,MIN(Inputs!$F$97*K40,K49)) -> 0 | L52: =IF(OR(Time!L20=1,Time!L34=1,Time!L23=1),0,MIN(Inputs!$F$97*L40,L49)) -> 0 | M52: =IF(OR(Time!M20=1,Time!M34=1,Time!M23=1),0,MIN(Inputs!$F$97*M40,M49)) -> 0 | N52: =IF(OR(Time!N20=1,Time!N34=1,Time!N23=1),0,MIN(Inputs!$F$97*N40,N49)) -> 0 | O52: =IF(OR(Time!O20=1,Time!O34=1,Time!O23=1),0,MIN(Inputs!$F$97*O40,O49)) -> 0 | P52: =IF(OR(Time!P20=1,Time!P34=1,Time!P23=1),0,MIN(Inputs!$F$97*P40,P49)) -> 0 | Q52: =IF(OR(Time!Q20=1,Time!Q34=1,Time!Q23=1),0,MIN(Inputs!$F$97*Q40,Q49)) -> 0 | ... DB52: =IF(OR(Time!DB20=1,Time!DB34=1,Time!DB23=1),0,MIN(Inputs!$F$97*DB40,DB49)) -> 0
D53: Closing balance before restructuring | E53: ARD m | J53: =J49-Waterfall!J21-Waterfall!J32 -> 485.17159 | K53: =K49-Waterfall!K21-Waterfall!K32 -> 485.17159 | L53: =L49-Waterfall!L21-Waterfall!L32 -> 485.17159 | M53: =M49-Waterfall!M21-Waterfall!M32 -> 485.17159 | N53: =N49-Waterfall!N21-Waterfall!N32 -> 485.17159 | O53: =O49-Waterfall!O21-Waterfall!O32 -> 485.17159 | P53: =P49-Waterfall!P21-Waterfall!P32 -> 485.17159 | Q53: =Q49-Waterfall!Q21-Waterfall!Q32 -> 485.17159 | ... DB53: =DB49-Waterfall!DB21-Waterfall!DB32 -> 0
D54: Closing balance | E54: ARD m | J54: =IF(Time!J35=1,0,J53) -> 485.17159 | K54: =IF(Time!K35=1,0,K53) -> 485.17159 | L54: =IF(Time!L35=1,0,L53) -> 485.17159 | M54: =IF(Time!M35=1,0,M53) -> 485.17159 | N54: =IF(Time!N35=1,0,N53) -> 485.17159 | O54: =IF(Time!O35=1,0,O53) -> 485.17159 | P54: =IF(Time!P35=1,0,P53) -> 485.17159 | Q54: =IF(Time!Q35=1,0,Q53) -> 485.17159 | ... DB54: =IF(Time!DB35=1,0,DB53) -> 0
D55: Senior arrears (interest unpaid under the standstill)
D56: Bank arrears: opening | E56: ARD m | J56: =I60 -> 0 | K56: =J60 -> 0 | L56: =K60 -> 0 | M56: =L60 -> 0 | N56: =M60 -> 0 | O56: =N60 -> 0 | P56: =O60 -> 0 | Q56: =P60 -> 0 | ... DB56: =DA60 -> 0
D57: Bond arrears: opening | E57: ARD m | J57: =I61 -> 0 | K57: =J61 -> 0 | L57: =K61 -> 0 | M57: =L61 -> 0 | N57: =M61 -> 0 | O57: =N61 -> 0 | P57: =O61 -> 0 | Q57: =P61 -> 0 | ... DB57: =DA61 -> 0
D58: Bank arrears: closing before restructuring | E58: ARD m | J58: =(J56+J44-Waterfall!J16*Waterfall!J18)*(1-Time!J20) -> 0 | K58: =(K56+K44-Waterfall!K16*Waterfall!K18)*(1-Time!K20) -> 0 | L58: =(L56+L44-Waterfall!L16*Waterfall!L18)*(1-Time!L20) -> 0 | M58: =(M56+M44-Waterfall!M16*Waterfall!M18)*(1-Time!M20) -> 0 | N58: =(N56+N44-Waterfall!N16*Waterfall!N18)*(1-Time!N20) -> 0 | O58: =(O56+O44-Waterfall!O16*Waterfall!O18)*(1-Time!O20) -> 0 | P58: =(P56+P44-Waterfall!P16*Waterfall!P18)*(1-Time!P20) -> 0 | Q58: =(Q56+Q44-Waterfall!Q16*Waterfall!Q18)*(1-Time!Q20) -> 0 | ... DB58: =(DB56+DB44-Waterfall!DB16*Waterfall!DB18)*(1-Time!DB20) -> 0
D59: Bond arrears: closing before restructuring | E59: ARD m | J59: =(J57+J51-Waterfall!J16*Waterfall!J19)*(1-Time!J20) -> 0 | K59: =(K57+K51-Waterfall!K16*Waterfall!K19)*(1-Time!K20) -> 0 | L59: =(L57+L51-Waterfall!L16*Waterfall!L19)*(1-Time!L20) -> 0 | M59: =(M57+M51-Waterfall!M16*Waterfall!M19)*(1-Time!M20) -> 0 | N59: =(N57+N51-Waterfall!N16*Waterfall!N19)*(1-Time!N20) -> 0 | O59: =(O57+O51-Waterfall!O16*Waterfall!O19)*(1-Time!O20) -> 0 | P59: =(P57+P51-Waterfall!P16*Waterfall!P19)*(1-Time!P20) -> 0 | Q59: =(Q57+Q51-Waterfall!Q16*Waterfall!Q19)*(1-Time!Q20) -> 0 | ... DB59: =(DB57+DB51-Waterfall!DB16*Waterfall!DB19)*(1-Time!DB20) -> 0
D60: Bank arrears: closing | E60: ARD m | J60: =IF(Time!J35=1,0,J58) -> 0 | K60: =IF(Time!K35=1,0,K58) -> 0 | L60: =IF(Time!L35=1,0,L58) -> 0 | M60: =IF(Time!M35=1,0,M58) -> 0 | N60: =IF(Time!N35=1,0,N58) -> 0 | O60: =IF(Time!O35=1,0,O58) -> 0 | P60: =IF(Time!P35=1,0,P58) -> 0 | Q60: =IF(Time!Q35=1,0,Q58) -> 0 | ... DB60: =IF(Time!DB35=1,0,DB58) -> 0
D61: Bond arrears: closing | E61: ARD m | J61: =IF(Time!J35=1,0,J59) -> 0 | K61: =IF(Time!K35=1,0,K59) -> 0 | L61: =IF(Time!L35=1,0,L59) -> 0 | M61: =IF(Time!M35=1,0,M59) -> 0 | N61: =IF(Time!N35=1,0,N59) -> 0 | O61: =IF(Time!O35=1,0,O59) -> 0 | P61: =IF(Time!P35=1,0,P59) -> 0 | Q61: =IF(Time!Q35=1,0,Q59) -> 0 | ... DB61: =IF(Time!DB35=1,0,DB59) -> 0
D62: Debt service due (all senior)
D63: Restructured notes interest due (30/360) | E63: ARD m | G63: =SUM(J63:DB63) -> 489.86005 | J63: =J93*J10 -> 0 | K63: =K93*K10 -> 0 | L63: =L93*L10 -> 0 | M63: =M93*M10 -> 0 | N63: =N93*N10 -> 0 | O63: =O93*O10 -> 0 | P63: =P93*P10 -> 0 | Q63: =Q93*Q10 -> 0 | ... DB63: =DB93*DB10 -> 0
D64: Senior interest due | E64: ARD m | G64: =SUM(J64:DB64) -> 716.87277 | J64: =J44+J51+J63 -> 0 | K64: =K44+K51+K63 -> 0 | L64: =L44+L51+L63 -> 0 | M64: =M44+M51+M63 -> 0 | N64: =N44+N51+N63 -> 0 | O64: =O44+O51+O63 -> 0 | P64: =P44+P51+P63 -> 0 | Q64: =Q44+Q51+Q63 -> 0 | ... DB64: =DB44+DB51+DB63 -> 0
D65: Refinancing / A&E fee and post-completion bridge interest | E65: ARD m | G65: =SUM(J65:DB65) -> 2.8589037 | J65: =IF(Inputs!$F$213=1,Inputs!$F$107,Inputs!$F$106)*J42*Time!J42+Funding!J20 -> 0 | K65: =IF(Inputs!$F$213=1,Inputs!$F$107,Inputs!$F$106)*K42*Time!K42+Funding!K20 -> 0 | L65: =IF(Inputs!$F$213=1,Inputs!$F$107,Inputs!$F$106)*L42*Time!L42+Funding!L20 -> 0 | M65: =IF(Inputs!$F$213=1,Inputs!$F$107,Inputs!$F$106)*M42*Time!M42+Funding!M20 -> 0 | N65: =IF(Inputs!$F$213=1,Inputs!$F$107,Inputs!$F$106)*N42*Time!N42+Funding!N20 -> 0 | O65: =IF(Inputs!$F$213=1,Inputs!$F$107,Inputs!$F$106)*O42*Time!O42+Funding!O20 -> 0 | P65: =IF(Inputs!$F$213=1,Inputs!$F$107,Inputs!$F$106)*P42*Time!P42+Funding!P20 -> 0 | Q65: =IF(Inputs!$F$213=1,Inputs!$F$107,Inputs!$F$106)*Q42*Time!Q42+Funding!Q20 -> 0 | ... DB65: =IF(Inputs!$F$213=1,Inputs!$F$107,Inputs!$F$106)*DB42*Time!DB42+Funding!DB20 -> 0
D66: Notes principal due | E66: ARD m | G66: =SUM(J66:DB66) -> 447.43887 | J66: =IF(Time!J23=1,MIN(J91,J93),0) -> 0 | K66: =IF(Time!K23=1,MIN(K91,K93),0) -> 0 | L66: =IF(Time!L23=1,MIN(L91,L93),0) -> 0 | M66: =IF(Time!M23=1,MIN(M91,M93),0) -> 0 | N66: =IF(Time!N23=1,MIN(N91,N93),0) -> 0 | O66: =IF(Time!O23=1,MIN(O91,O93),0) -> 0 | P66: =IF(Time!P23=1,MIN(P91,P93),0) -> 0 | Q66: =IF(Time!Q23=1,MIN(Q91,Q93),0) -> 0 | ... DB66: =IF(Time!DB23=1,MIN(DB91,DB93),0) -> 0
D67: Senior principal due | E67: ARD m | G67: =SUM(J67:DB67) -> 447.43887 | J67: =J45+J52+J66 -> 0 | K67: =K45+K52+K66 -> 0 | L67: =L45+L52+L66 -> 0 | M67: =M45+M52+M66 -> 0 | N67: =N45+N52+N66 -> 0 | O67: =O45+O52+O66 -> 0 | P67: =P45+P52+P66 -> 0 | Q67: =Q45+Q52+Q66 -> 0 | ... DB67: =DB45+DB52+DB66 -> 0
D68: Scheduled senior cash debt service (covenant basis) | E68: ARD m | G68: =SUM(J68:DB68) -> 1144.0857 | J68: =J64+(Inputs!$F$96+Inputs!$F$97)*J40*(1-Time!J23)*(1-Time!J20)+J66-J39 -> 0 | K68: =K64+(Inputs!$F$96+Inputs!$F$97)*K40*(1-Time!K23)*(1-Time!K20)+K66-K39 -> 0 | L68: =L64+(Inputs!$F$96+Inputs!$F$97)*L40*(1-Time!L23)*(1-Time!L20)+L66-L39 -> 0 | M68: =M64+(Inputs!$F$96+Inputs!$F$97)*M40*(1-Time!M23)*(1-Time!M20)+M66-M39 -> 0 | N68: =N64+(Inputs!$F$96+Inputs!$F$97)*N40*(1-Time!N23)*(1-Time!N20)+N66-N39 -> 0 | O68: =O64+(Inputs!$F$96+Inputs!$F$97)*O40*(1-Time!O23)*(1-Time!O20)+O66-O39 -> 0 | P68: =P64+(Inputs!$F$96+Inputs!$F$97)*P40*(1-Time!P23)*(1-Time!P20)+P66-P39 -> 0 | Q68: =Q64+(Inputs!$F$96+Inputs!$F$97)*Q40*(1-Time!Q23)*(1-Time!Q20)+Q66-Q39 -> 0 | ... DB68: =DB64+(Inputs!$F$96+Inputs!$F$97)*DB40*(1-Time!DB23)*(1-Time!DB20)+DB66-DB39 -> 0
D69: Restructuring at 2023-12-31
D70: Original scheduled senior balance (swap notional basis) | E70: ARD m | J70: =IF(Time!J21=1,$F$26,I70-I40) -> 0 | K70: =IF(Time!K21=1,$F$26,J70-J40) -> 0 | L70: =IF(Time!L21=1,$F$26,K70-K40) -> 0 | M70: =IF(Time!M21=1,$F$26,L70-L40) -> 0 | N70: =IF(Time!N21=1,$F$26,M70-M40) -> 0 | O70: =IF(Time!O21=1,$F$26,N70-N40) -> 0 | P70: =IF(Time!P21=1,$F$26,O70-O40) -> 0 | Q70: =IF(Time!Q21=1,$F$26,P70-P40) -> 0 | ... DB70: =IF(Time!DB21=1,$F$26,DA70-DA40) -> 2.1174174e-12
D71: Swap discount factor at 4.36% | E71: factor | J71: =IF(Time!J52=1,IF(Time!I52=1,I71,1)/(1+Inputs!$F$101/100*Time!J9/Inputs!$F$45),0) -> 0 | K71: =IF(Time!K52=1,IF(Time!J52=1,J71,1)/(1+Inputs!$F$101/100*Time!K9/Inputs!$F$45),0) -> 0 | L71: =IF(Time!L52=1,IF(Time!K52=1,K71,1)/(1+Inputs!$F$101/100*Time!L9/Inputs!$F$45),0) -> 0 | M71: =IF(Time!M52=1,IF(Time!L52=1,L71,1)/(1+Inputs!$F$101/100*Time!M9/Inputs!$F$45),0) -> 0 | N71: =IF(Time!N52=1,IF(Time!M52=1,M71,1)/(1+Inputs!$F$101/100*Time!N9/Inputs!$F$45),0) -> 0 | O71: =IF(Time!O52=1,IF(Time!N52=1,N71,1)/(1+Inputs!$F$101/100*Time!O9/Inputs!$F$45),0) -> 0 | P71: =IF(Time!P52=1,IF(Time!O52=1,O71,1)/(1+Inputs!$F$101/100*Time!P9/Inputs!$F$45),0) -> 0 | Q71: =IF(Time!Q52=1,IF(Time!P52=1,P71,1)/(1+Inputs!$F$101/100*Time!Q9/Inputs!$F$45),0) -> 0 | ... DB71: =IF(Time!DB52=1,IF(Time!DA52=1,DA71,1)/(1+Inputs!$F$101/100*Time!DB9/Inputs!$F$45),0) -> 0
D72: PV of swap net receipts (market less fixed) | E72: ARD m | G72: =SUM(J72:DB72) -> 31.154782 | J72: =Time!J52*(Inputs!$F$101-Inputs!$F$100)/100*Inputs!$F$96*J70*Time!J9/Inputs!$F$45*J71 -> 0 | K72: =Time!K52*(Inputs!$F$101-Inputs!$F$100)/100*Inputs!$F$96*K70*Time!K9/Inputs!$F$45*K71 -> 0 | L72: =Time!L52*(Inputs!$F$101-Inputs!$F$100)/100*Inputs!$F$96*L70*Time!L9/Inputs!$F$45*L71 -> 0 | M72: =Time!M52*(Inputs!$F$101-Inputs!$F$100)/100*Inputs!$F$96*M70*Time!M9/Inputs!$F$45*M71 -> 0 | N72: =Time!N52*(Inputs!$F$101-Inputs!$F$100)/100*Inputs!$F$96*N70*Time!N9/Inputs!$F$45*N71 -> 0 | O72: =Time!O52*(Inputs!$F$101-Inputs!$F$100)/100*Inputs!$F$96*O70*Time!O9/Inputs!$F$45*O71 -> 0 | P72: =Time!P52*(Inputs!$F$101-Inputs!$F$100)/100*Inputs!$F$96*P70*Time!P9/Inputs!$F$45*P71 -> 0 | Q72: =Time!Q52*(Inputs!$F$101-Inputs!$F$100)/100*Inputs!$F$96*Q70*Time!Q9/Inputs!$F$45*Q71 -> 0 | ... DB72: =Time!DB52*(Inputs!$F$101-Inputs!$F$100)/100*Inputs!$F$96*DB70*Time!DB9/Inputs!$F$45*DB71 -> 0
D73: Swap mark-to-market at 2023-12-31 (owed to the concessionaire) | E73: ARD m | F73: =SUM($J$72:$DB$72) -> 31.154782
D74: Senior claims: principal plus arrears | E74: ARD m | G74: =SUM(J74:DB74) -> 840.26859 | J74: =Time!J35*(J46+J53+J58+J59) -> 0 | K74: =Time!K35*(K46+K53+K58+K59) -> 0 | L74: =Time!L35*(L46+L53+L58+L59) -> 0 | M74: =Time!M35*(M46+M53+M58+M59) -> 0 | N74: =Time!N35*(N46+N53+N58+N59) -> 0 | O74: =Time!O35*(O46+O53+O58+O59) -> 0 | P74: =Time!P35*(P46+P53+P58+P59) -> 0 | Q74: =Time!Q35*(Q46+Q53+Q58+Q59) -> 0 | ... DB74: =Time!DB35*(DB46+DB53+DB58+DB59) -> 0
D75: Swap termination value set off | E75: ARD m | G75: =SUM(J75:DB75) -> 31.154782 | J75: =Time!J35*$F$73 -> 0 | K75: =Time!K35*$F$73 -> 0 | L75: =Time!L35*$F$73 -> 0 | M75: =Time!M35*$F$73 -> 0 | N75: =Time!N35*$F$73 -> 0 | O75: =Time!O35*$F$73 -> 0 | P75: =Time!P35*$F$73 -> 0 | Q75: =Time!Q35*$F$73 -> 0 | ... DB75: =Time!DB35*$F$73 -> 0
D76: Senior claims net of set-off | E76: ARD m | G76: =SUM(J76:DB76) -> 809.11381 | J76: =J74-J75 -> 0 | K76: =K74-K75 -> 0 | L76: =L74-L75 -> 0 | M76: =M74-M75 -> 0 | N76: =N74-N75 -> 0 | O76: =O74-O75 -> 0 | P76: =P74-P75 -> 0 | Q76: =Q74-Q75 -> 0 | ... DB76: =DB74-DB75 -> 0
D77: Restructured Senior Notes issued (76%) | E77: ARD m | G77: =SUM(J77:DB77) -> 614.9265 | J77: =Inputs!$F$163*J76 -> 0 | K77: =Inputs!$F$163*K76 -> 0 | L77: =Inputs!$F$163*L76 -> 0 | M77: =Inputs!$F$163*M76 -> 0 | N77: =Inputs!$F$163*N76 -> 0 | O77: =Inputs!$F$163*O76 -> 0 | P77: =Inputs!$F$163*P76 -> 0 | Q77: =Inputs!$F$163*Q76 -> 0 | ... DB77: =Inputs!$F$163*DB76 -> 0
D78: Claims converted to equity (10%) | E78: ARD m | G78: =SUM(J78:DB78) -> 80.911381 | J78: =Inputs!$F$165*J76 -> 0 | K78: =Inputs!$F$165*K76 -> 0 | L78: =Inputs!$F$165*L76 -> 0 | M78: =Inputs!$F$165*M76 -> 0 | N78: =Inputs!$F$165*N76 -> 0 | O78: =Inputs!$F$165*O76 -> 0 | P78: =Inputs!$F$165*P76 -> 0 | Q78: =Inputs!$F$165*Q76 -> 0 | ... DB78: =Inputs!$F$165*DB76 -> 0
D79: Claims cancelled (14%) | E79: ARD m | G79: =SUM(J79:DB79) -> 113.27593 | J79: =Inputs!$F$164*J76 -> 0 | K79: =Inputs!$F$164*K76 -> 0 | L79: =Inputs!$F$164*L76 -> 0 | M79: =Inputs!$F$164*M76 -> 0 | N79: =Inputs!$F$164*N76 -> 0 | O79: =Inputs!$F$164*O76 -> 0 | P79: =Inputs!$F$164*P76 -> 0 | Q79: =Inputs!$F$164*Q76 -> 0 | ... DB79: =Inputs!$F$164*DB76 -> 0
D80: Shareholder loans written off | E80: ARD m | G80: =SUM(J80:DB80) -> 771.19202 | J80: =Time!J35*Waterfall!J58 -> 0 | K80: =Time!K35*Waterfall!K58 -> 0 | L80: =Time!L35*Waterfall!L58 -> 0 | M80: =Time!M35*Waterfall!M58 -> 0 | N80: =Time!N35*Waterfall!N58 -> 0 | O80: =Time!O35*Waterfall!O58 -> 0 | P80: =Time!P35*Waterfall!P58 -> 0 | Q80: =Time!Q35*Waterfall!Q58 -> 0 | ... DB80: =Time!DB35*Waterfall!DB58 -> 0
D81: Notes face value | E81: ARD m | F81: =SUM($J$77:$DB$77) -> 614.9265
D82: Restructured notes sculpting (live in Scenario 5)
D83: Discount factor at the notes rate | E83: factor | J83: =IF(Time!J37=1,IF(Time!I37=1,I83,1)/(1+J10),0) -> 0 | K83: =IF(Time!K37=1,IF(Time!J37=1,J83,1)/(1+K10),0) -> 0 | L83: =IF(Time!L37=1,IF(Time!K37=1,K83,1)/(1+L10),0) -> 0 | M83: =IF(Time!M37=1,IF(Time!L37=1,L83,1)/(1+M10),0) -> 0 | N83: =IF(Time!N37=1,IF(Time!M37=1,M83,1)/(1+N10),0) -> 0 | O83: =IF(Time!O37=1,IF(Time!N37=1,N83,1)/(1+O10),0) -> 0 | P83: =IF(Time!P37=1,IF(Time!O37=1,O83,1)/(1+P10),0) -> 0 | Q83: =IF(Time!Q37=1,IF(Time!P37=1,P83,1)/(1+Q10),0) -> 0 | ... DB83: =IF(Time!DB37=1,IF(Time!DA37=1,DA83,1)/(1+DB10),0) -> 0
D84: Scheduled notes balance: opening | E84: ARD m | J84: =IF(Time!J36=1,$F$81,I89) -> 0 | K84: =IF(Time!K36=1,$F$81,J89) -> 0 | L84: =IF(Time!L36=1,$F$81,K89) -> 0 | M84: =IF(Time!M36=1,$F$81,L89) -> 0 | N84: =IF(Time!N36=1,$F$81,M89) -> 0 | O84: =IF(Time!O36=1,$F$81,N89) -> 0 | P84: =IF(Time!P36=1,$F$81,O89) -> 0 | Q84: =IF(Time!Q36=1,$F$81,P89) -> 0 | ... DB84: =IF(Time!DB36=1,$F$81,DA89) -> -2514.762
D85: Scheduled notes interest | E85: ARD m | G85: =SUM(J85:DB85) -> -1354.267 | J85: =J84*J10 -> 0 | K85: =K84*K10 -> 0 | L85: =L84*L10 -> 0 | M85: =M84*M10 -> 0 | N85: =N84*N10 -> 0 | O85: =O84*O10 -> 0 | P85: =P84*P10 -> 0 | Q85: =Q84*Q10 -> 0 | ... DB85: =DB84*DB10 -> -64.126431
D86: Flag_InterestOnly (notes) | E86: flag | J86: =IF(AND(Time!J37=1,J85>J13/$F$90),1,0) -> 0 | K86: =IF(AND(Time!K37=1,K85>K13/$F$90),1,0) -> 0 | L86: =IF(AND(Time!L37=1,L85>L13/$F$90),1,0) -> 0 | M86: =IF(AND(Time!M37=1,M85>M13/$F$90),1,0) -> 0 | N86: =IF(AND(Time!N37=1,N85>N13/$F$90),1,0) -> 0 | O86: =IF(AND(Time!O37=1,O85>O13/$F$90),1,0) -> 0 | P86: =IF(AND(Time!P37=1,P85>P13/$F$90),1,0) -> 0 | Q86: =IF(AND(Time!Q37=1,Q85>Q13/$F$90),1,0) -> 0 | ... DB86: =IF(AND(Time!DB37=1,DB85>DB13/$F$90),1,0) -> 0
D87: Scheduled notes debt service | E87: ARD m | G87: =SUM(J87:DB87) -> 2609.0651 | J87: =IF(Time!J37=1,MAX(J85,J13/$F$90),0) -> 0 | K87: =IF(Time!K37=1,MAX(K85,K13/$F$90),0) -> 0 | L87: =IF(Time!L37=1,MAX(L85,L13/$F$90),0) -> 0 | M87: =IF(Time!M37=1,MAX(M85,M13/$F$90),0) -> 0 | N87: =IF(Time!N37=1,MAX(N85,N13/$F$90),0) -> 0 | O87: =IF(Time!O37=1,MAX(O85,O13/$F$90),0) -> 0 | P87: =IF(Time!P37=1,MAX(P85,P13/$F$90),0) -> 0 | Q87: =IF(Time!Q37=1,MAX(Q85,Q13/$F$90),0) -> 0 | ... DB87: =IF(Time!DB37=1,MAX(DB85,DB13/$F$90),0) -> 0
D88: Scheduled notes principal (live) | E88: ARD m | G88: =SUM(J88:DB88) -> 3129.6885 | J88: =IF(Time!J37=1,J87-J85,0) -> 0 | K88: =IF(Time!K37=1,K87-K85,0) -> 0 | L88: =IF(Time!L37=1,L87-L85,0) -> 0 | M88: =IF(Time!M37=1,M87-M85,0) -> 0 | N88: =IF(Time!N37=1,N87-N85,0) -> 0 | O88: =IF(Time!O37=1,O87-O85,0) -> 0 | P88: =IF(Time!P37=1,P87-P85,0) -> 0 | Q88: =IF(Time!Q37=1,Q87-Q85,0) -> 0 | ... DB88: =IF(Time!DB37=1,DB87-DB85,0) -> 0
D89: Scheduled notes balance: closing | E89: ARD m | J89: =J84-J88 -> 0 | K89: =K84-K88 -> 0 | L89: =L84-L88 -> 0 | M89: =M84-M88 -> 0 | N89: =N84-N88 -> 0 | O89: =O84-O88 -> 0 | P89: =P84-P88 -> 0 | Q89: =Q84-Q88 -> 0 | ... DB89: =DB84-DB88 -> -2514.762
D90: Notes sculpting divisor (fixed point) | E90: x | F90: =IF(AND($F$25=1,$F$81>0),IFERROR(MAX(Inputs!$F$9,SUMPRODUCT($J$13:$DB$13*$J$83:$DB$83*Time!$J$37:$DB$37*(1-$J$86:$DB$86))/($F$81-SUMPRODUCT($J$85:$DB$85*$J$83:$DB$83*$J$86:$DB$86))),Inputs!$F$167),Inputs!$F$167) -> 1.3
D91: Scheduled notes principal (applied) | E91: ARD m | G91: =SUM(J91:DB91) -> 614.9265 | J91: =IF($F$25=1,J88,Inputs!J277) -> 0 | K91: =IF($F$25=1,K88,Inputs!K277) -> 0 | L91: =IF($F$25=1,L88,Inputs!L277) -> 0 | M91: =IF($F$25=1,M88,Inputs!M277) -> 0 | N91: =IF($F$25=1,N88,Inputs!N277) -> 0 | O91: =IF($F$25=1,O88,Inputs!O277) -> 0 | P91: =IF($F$25=1,P88,Inputs!P277) -> 0 | Q91: =IF($F$25=1,Q88,Inputs!Q277) -> 0 | ... DB91: =IF($F$25=1,DB88,Inputs!DB277) -> 0
D92: Restructured Senior Notes
D93: Opening balance | E93: ARD m | J93: =I94 -> 0 | K93: =J94 -> 0 | L93: =K94 -> 0 | M93: =L94 -> 0 | N93: =M94 -> 0 | O93: =N94 -> 0 | P93: =O94 -> 0 | Q93: =P94 -> 0 | ... DB93: =DA94 -> 0
D94: Closing balance | E94: ARD m | J94: =IF(Time!J35=1,J77,J93-Waterfall!J22-Waterfall!J38) -> 0 | K94: =IF(Time!K35=1,K77,K93-Waterfall!K22-Waterfall!K38) -> 0 | L94: =IF(Time!L35=1,L77,L93-Waterfall!L22-Waterfall!L38) -> 0 | M94: =IF(Time!M35=1,M77,M93-Waterfall!M22-Waterfall!M38) -> 0 | N94: =IF(Time!N35=1,N77,N93-Waterfall!N22-Waterfall!N38) -> 0 | O94: =IF(Time!O35=1,O77,O93-Waterfall!O22-Waterfall!O38) -> 0 | P94: =IF(Time!P35=1,P77,P93-Waterfall!P22-Waterfall!P38) -> 0 | Q94: =IF(Time!Q35=1,Q77,Q93-Waterfall!Q22-Waterfall!Q38) -> 0 | ... DB94: =IF(Time!DB35=1,DB77,DB93-Waterfall!DB22-Waterfall!DB38) -> 0
D95: NILO loan
D96: Opening balance | E96: ARD m | J96: =I102 -> 0 | K96: =J102 -> 0 | L96: =K102 -> 0 | M96: =L102 -> 0 | N96: =M102 -> 0 | O96: =N102 -> 5.9935237 | P96: =O102 -> 63.05219 | Q96: =P102 -> 128.65765 | ... DB96: =DA102 -> 3.3544723e-11
D97: Interest accrued (cash and capitalized) | E97: ARD m | G97: =SUM(J97:DB97) -> 527.72529 | J97: =J96*Time!J50*Time!J9/Inputs!$F$45 -> 0 | K97: =K96*Time!K50*Time!K9/Inputs!$F$45 -> 0 | L97: =L96*Time!L50*Time!L9/Inputs!$F$45 -> 0 | M97: =M96*Time!M50*Time!M9/Inputs!$F$45 -> 0 | N97: =N96*Time!N50*Time!N9/Inputs!$F$45 -> 0 | O97: =O96*Time!O50*Time!O9/Inputs!$F$45 -> 0.04622731 | P97: =P96*Time!P50*Time!P9/Inputs!$F$45 -> 0.48631376 | Q97: =Q96*Time!Q50*Time!Q9/Inputs!$F$45 -> 0.97074842 | ... DB97: =DB96*Time!DB50*Time!DB9/Inputs!$F$45 -> 5.0901589e-13
D98: Cash interest due | E98: ARD m | G98: =SUM(J98:DB98) -> 387.17962 | J98: =J97*Time!J51*(1-Time!J20) -> 0 | K98: =K97*Time!K51*(1-Time!K20) -> 0 | L98: =L97*Time!L51*(1-Time!L20) -> 0 | M98: =M97*Time!M51*(1-Time!M20) -> 0 | N98: =N97*Time!N51*(1-Time!N20) -> 0 | O98: =O97*Time!O51*(1-Time!O20) -> 0 | P98: =P97*Time!P51*(1-Time!P20) -> 0 | Q98: =Q97*Time!Q51*(1-Time!Q20) -> 0 | ... DB98: =DB97*Time!DB51*(1-Time!DB20) -> 5.0901589e-13
D99: Principal due | E99: ARD m | G99: =SUM(J99:DB99) -> 604.67999 | J99: =MIN(J116,J96+J97-J98)*(1-Time!J20) -> 0 | K99: =MIN(K116,K96+K97-K98)*(1-Time!K20) -> 0 | L99: =MIN(L116,L96+L97-L98)*(1-Time!L20) -> 0 | M99: =MIN(M116,M96+M97-M98)*(1-Time!M20) -> 0 | N99: =MIN(N116,N96+N97-N98)*(1-Time!N20) -> 0 | O99: =MIN(O116,O96+O97-O98)*(1-Time!O20) -> 0 | P99: =MIN(P116,P96+P97-P98)*(1-Time!P20) -> 0 | Q99: =MIN(Q116,Q96+Q97-Q98)*(1-Time!Q20) -> 0 | ... DB99: =MIN(DB116,DB96+DB97-DB98)*(1-Time!DB20) -> 0
D100: Total due incl. shortfall brought forward | E100: ARD m | G100: =SUM(J100:DB100) -> 991.85961 | J100: =J98+J99+I101 -> 0 | K100: =K98+K99+J101 -> 0 | L100: =L98+L99+K101 -> 0 | M100: =M98+M99+L101 -> 0 | N100: =N98+N99+M101 -> 0 | O100: =O98+O99+N101 -> 0 | P100: =P98+P99+O101 -> 0 | Q100: =Q98+Q99+P101 -> 0 | ... DB100: =DB98+DB99+DA101 -> 5.0901589e-13
D101: Shortfall carried forward | E101: ARD m | J101: =J100-Waterfall!J35 -> 0 | K101: =K100-Waterfall!K35 -> 0 | L101: =L100-Waterfall!L35 -> 0 | M101: =M100-Waterfall!M35 -> 0 | N101: =N100-Waterfall!N35 -> 0 | O101: =O100-Waterfall!O35 -> 0 | P101: =P100-Waterfall!P35 -> 0 | Q101: =Q100-Waterfall!Q35 -> 0 | ... DB101: =DB100-Waterfall!DB35 -> 0
...

Sheet Reserves
D1: Case T: Merrick Link toll road PPP | Reserves
D2: Units: ARD millions unless stated. Inputs blue on yellow; links green; calculations black.
D3: Period end | E3: date | J3: =Time!J8 -> 42185 | K3: =Time!K8 -> 42277 | L3: =Time!L8 -> 42369 | M3: =Time!M8 -> 42460 | N3: =Time!N8 -> 42551 | O3: =Time!O8 -> 42643 | P3: =Time!P8 -> 42735 | Q3: =Time!Q8 -> 42825 | ... DB3: =Time!DB8 -> 58256
D5: Debt service reserve account (six months of scheduled senior cash debt service)
D6: Next period scheduled cash debt service | E6: ARD m | J6: =IF(Time!K14=0,0,(Debt!J42+Funding!J35-Waterfall!J20)*Debt!K8*Time!K9/Inputs!$F$45+(Debt!J49-Waterfall!J21)*Inputs!$F$110*Time!K10/Inputs!$F$46+(Debt!J93-Waterfall!J22)*Debt!K10+IF(Time!K34=1,0,IF(Time!K23=1,MIN(Debt!K91,Debt!J93-Waterfall!J22),MIN(Inputs!$F$96*Debt!K40,Debt!J42+Funding!J35-Waterfall!J20)+MIN(Inputs!$F$97*Debt!K40,Debt!J49-Waterfall!J21)))-Debt!K39) -> 5.8827056 | K6: =IF(Time!L14=0,0,(Debt!K42+Funding!K35-Waterfall!K20)*Debt!L8*Time!L9/Inputs!$F$45+(Debt!K49-Waterfall!K21)*Inputs!$F$110*Time!L10/Inputs!$F$46+(Debt!K93-Waterfall!K22)*Debt!L10+IF(Time!L34=1,0,IF(Time!L23=1,MIN(Debt!L91,Debt!K93-Waterfall!K22),MIN(Inputs!$F$96*Debt!L40,Debt!K42+Funding!K35-Waterfall!K20)+MIN(Inputs!$F$97*Debt!L40,Debt!K49-Waterfall!K21)))-Debt!L39) -> 5.8827056 | L6: =IF(Time!M14=0,0,(Debt!L42+Funding!L35-Waterfall!L20)*Debt!M8*Time!M9/Inputs!$F$45+(Debt!L49-Waterfall!L21)*Inputs!$F$110*Time!M10/Inputs!$F$46+(Debt!L93-Waterfall!L22)*Debt!M10+IF(Time!M34=1,0,IF(Time!M23=1,MIN(Debt!M91,Debt!L93-Waterfall!L22),MIN(Inputs!$F$96*Debt!M40,Debt!L42+Funding!L35-Waterfall!L20)+MIN(Inputs!$F$97*Debt!M40,Debt!L49-Waterfall!L21)))-Debt!M39) -> 5.8827056 | M6: =IF(Time!N14=0,0,(Debt!M42+Funding!M35-Waterfall!M20)*Debt!N8*Time!N9/Inputs!$F$45+(Debt!M49-Waterfall!M21)*Inputs!$F$110*Time!N10/Inputs!$F$46+(Debt!M93-Waterfall!M22)*Debt!N10+IF(Time!N34=1,0,IF(Time!N23=1,MIN(Debt!N91,Debt!M93-Waterfall!M22),MIN(Inputs!$F$96*Debt!N40,Debt!M42+Funding!M35-Waterfall!M20)+MIN(Inputs!$F$97*Debt!N40,Debt!M49-Waterfall!M21)))-Debt!N39) -> 5.8827056 | N6: =IF(Time!O14=0,0,(Debt!N42+Funding!N35-Waterfall!N20)*Debt!O8*Time!O9/Inputs!$F$45+(Debt!N49-Waterfall!N21)*Inputs!$F$110*Time!O10/Inputs!$F$46+(Debt!N93-Waterfall!N22)*Debt!O10+IF(Time!O34=1,0,IF(Time!O23=1,MIN(Debt!O91,Debt!N93-Waterfall!N22),MIN(Inputs!$F$96*Debt!O40,Debt!N42+Funding!N35-Waterfall!N20)+MIN(Inputs!$F$97*Debt!O40,Debt!N49-Waterfall!N21)))-Debt!O39) -> 5.958032 | O6: =IF(Time!P14=0,0,(Debt!O42+Funding!O35-Waterfall!O20)*Debt!P8*Time!P9/Inputs!$F$45+(Debt!O49-Waterfall!O21)*Inputs!$F$110*Time!P10/Inputs!$F$46+(Debt!O93-Waterfall!O22)*Debt!P10+IF(Time!P34=1,0,IF(Time!P23=1,MIN(Debt!P91,Debt!O93-Waterfall!O22),MIN(Inputs!$F$96*Debt!P40,Debt!O42+Funding!O35-Waterfall!O20)+MIN(Inputs!$F$97*Debt!P40,Debt!O49-Waterfall!O21)))-Debt!P39) -> 6.6745624 | P6: =IF(Time!Q14=0,0,(Debt!P42+Funding!P35-Waterfall!P20)*Debt!Q8*Time!Q9/Inputs!$F$45+(Debt!P49-Waterfall!P21)*Inputs!$F$110*Time!Q10/Inputs!$F$46+(Debt!P93-Waterfall!P22)*Debt!Q10+IF(Time!Q34=1,0,IF(Time!Q23=1,MIN(Debt!Q91,Debt!P93-Waterfall!P22),MIN(Inputs!$F$96*Debt!Q40,Debt!P42+Funding!P35-Waterfall!P20)+MIN(Inputs!$F$97*Debt!Q40,Debt!P49-Waterfall!P21)))-Debt!Q39) -> 7.4579718 | Q6: =IF(Time!R14=0,0,(Debt!Q42+Funding!Q35-Waterfall!Q20)*Debt!R8*Time!R9/Inputs!$F$45+(Debt!Q49-Waterfall!Q21)*Inputs!$F$110*Time!R10/Inputs!$F$46+(Debt!Q93-Waterfall!Q22)*Debt!R10+IF(Time!R34=1,0,IF(Time!R23=1,MIN(Debt!R91,Debt!Q93-Waterfall!Q22),MIN(Inputs!$F$96*Debt!R40,Debt!Q42+Funding!Q35-Waterfall!Q20)+MIN(Inputs!$F$97*Debt!R40,Debt!Q49-Waterfall!Q21)))-Debt!R39) -> 8.3399806 | ... DB6: =IF(Time!DC14=0,0,(Debt!DB42+Funding!DB35-Waterfall!DB20)*Debt!DC8*Time!DC9/Inputs!$F$45+(Debt!DB49-Waterfall!DB21)*Inputs!$F$110*Time!DC10/Inputs!$F$46+(Debt!DB93-Waterfall!DB22)*Debt!DC10+IF(Time!DC34=1,0,IF(Time!DC23=1,MIN(Debt!DC91,Debt!DB93-Waterfall!DB22),MIN(Inputs!$F$96*Debt!DC40,Debt!DB42+Funding!DB35-Waterfall!DB20)+MIN(Inputs!$F$97*Debt!DC40,Debt!DB49-Waterfall!DB21)))-Debt!DC39) -> 0
D7: DSRA target | E7: ARD m | J7: =IF(Time!J20=1,IF(Time!J8=Inputs!$F$15,J6*Inputs!$F$115/Time!K14,0),IF(Time!J35=1,0,IF(Time!K14=0,0,J6*Inputs!$F$115/Time!K14))) -> 0 | K7: =IF(Time!K20=1,IF(Time!K8=Inputs!$F$15,K6*Inputs!$F$115/Time!L14,0),IF(Time!K35=1,0,IF(Time!L14=0,0,K6*Inputs!$F$115/Time!L14))) -> 0 | L7: =IF(Time!L20=1,IF(Time!L8=Inputs!$F$15,L6*Inputs!$F$115/Time!M14,0),IF(Time!L35=1,0,IF(Time!M14=0,0,L6*Inputs!$F$115/Time!M14))) -> 0 | M7: =IF(Time!M20=1,IF(Time!M8=Inputs!$F$15,M6*Inputs!$F$115/Time!N14,0),IF(Time!M35=1,0,IF(Time!N14=0,0,M6*Inputs!$F$115/Time!N14))) -> 0 | N7: =IF(Time!N20=1,IF(Time!N8=Inputs!$F$15,N6*Inputs!$F$115/Time!O14,0),IF(Time!N35=1,0,IF(Time!O14=0,0,N6*Inputs!$F$115/Time!O14))) -> 0 | O7: =IF(Time!O20=1,IF(Time!O8=Inputs!$F$15,O6*Inputs!$F$115/Time!P14,0),IF(Time!O35=1,0,IF(Time!P14=0,0,O6*Inputs!$F$115/Time!P14))) -> 0 | P7: =IF(Time!P20=1,IF(Time!P8=Inputs!$F$15,P6*Inputs!$F$115/Time!Q14,0),IF(Time!P35=1,0,IF(Time!Q14=0,0,P6*Inputs!$F$115/Time!Q14))) -> 0 | Q7: =IF(Time!Q20=1,IF(Time!Q8=Inputs!$F$15,Q6*Inputs!$F$115/Time!R14,0),IF(Time!Q35=1,0,IF(Time!R14=0,0,Q6*Inputs!$F$115/Time!R14))) -> 0 | ... DB7: =IF(Time!DB20=1,IF(Time!DB8=Inputs!$F$15,DB6*Inputs!$F$115/Time!DC14,0),IF(Time!DB35=1,0,IF(Time!DC14=0,0,DB6*Inputs!$F$115/Time!DC14))) -> 0
D8: DSRA: opening | E8: ARD m | J8: =I13 -> 0 | K8: =J13 -> 0 | L8: =K13 -> 0 | M8: =L13 -> 0 | N8: =M13 -> 0 | O8: =N13 -> 0 | P8: =O13 -> 0 | Q8: =P13 -> 0 | ... DB8: =DA13 -> 0
D9: DSRA after draws | E9: ARD m | J9: =J8-Waterfall!J23 -> 0 | K9: =K8-Waterfall!K23 -> 0 | L9: =L8-Waterfall!L23 -> 0 | M9: =M8-Waterfall!M23 -> 0 | N9: =N8-Waterfall!N23 -> 0 | O9: =O8-Waterfall!O23 -> 0 | P9: =P8-Waterfall!P23 -> 0 | Q9: =Q8-Waterfall!Q23 -> 0 | ... DB9: =DB8-Waterfall!DB23 -> 0
D10: Shortfall against target | E10: ARD m | J10: =J7-J9 -> 0 | K10: =K7-K9 -> 0 | L10: =L7-L9 -> 0 | M10: =M7-M9 -> 0 | N10: =N7-N9 -> 0 | O10: =O7-O9 -> 0 | P10: =P7-P9 -> 0 | Q10: =Q7-Q9 -> 0 | ... DB10: =DB7-DB9 -> 0
D11: Top-up from cash flow | E11: ARD m | G11: =SUM(J11:DB11) -> 83.099685 | J11: =MIN(MAX(0,Waterfall!J24),MAX(0,J10))*(1-Time!J20) -> 0 | K11: =MIN(MAX(0,Waterfall!K24),MAX(0,K10))*(1-Time!K20) -> 0 | L11: =MIN(MAX(0,Waterfall!L24),MAX(0,L10))*(1-Time!L20) -> 0 | M11: =MIN(MAX(0,Waterfall!M24),MAX(0,M10))*(1-Time!M20) -> 0 | N11: =MIN(MAX(0,Waterfall!N24),MAX(0,N10))*(1-Time!N20) -> 0 | O11: =MIN(MAX(0,Waterfall!O24),MAX(0,O10))*(1-Time!O20) -> 0 | P11: =MIN(MAX(0,Waterfall!P24),MAX(0,P10))*(1-Time!P20) -> 0 | Q11: =MIN(MAX(0,Waterfall!Q24),MAX(0,Q10))*(1-Time!Q20) -> 0 | ... DB11: =MIN(MAX(0,Waterfall!DB24),MAX(0,DB10))*(1-Time!DB20) -> 0
D12: Release of excess | E12: ARD m | G12: =SUM(J12:DB12) -> 79.839946 | J12: =MAX(0,-J10)*(1-Time!J20) -> 0 | K12: =MAX(0,-K10)*(1-Time!K20) -> 0 | L12: =MAX(0,-L10)*(1-Time!L20) -> 0 | M12: =MAX(0,-M10)*(1-Time!M20) -> 0 | N12: =MAX(0,-N10)*(1-Time!N20) -> 0 | O12: =MAX(0,-O10)*(1-Time!O20) -> 0 | P12: =MAX(0,-P10)*(1-Time!P20) -> 0 | Q12: =MAX(0,-Q10)*(1-Time!Q20) -> 0 | ... DB12: =MAX(0,-DB10)*(1-Time!DB20) -> 0
D13: DSRA: closing | E13: ARD m | J13: =IF(Time!J20=1,J8+Funding!J21,J9+J11-J12) -> 0 | K13: =IF(Time!K20=1,K8+Funding!K21,K9+K11-K12) -> 0 | L13: =IF(Time!L20=1,L8+Funding!L21,L9+L11-L12) -> 0 | M13: =IF(Time!M20=1,M8+Funding!M21,M9+M11-M12) -> 0 | N13: =IF(Time!N20=1,N8+Funding!N21,N9+N11-N12) -> 0 | O13: =IF(Time!O20=1,O8+Funding!O21,O9+O11-O12) -> 0 | P13: =IF(Time!P20=1,P8+Funding!P21,P9+P11-P12) -> 0 | Q13: =IF(Time!Q20=1,Q8+Funding!Q21,Q9+Q11-Q12) -> 0 | ... DB13: =IF(Time!DB20=1,DB8+Funding!DB21,DB9+DB11-DB12) -> 0
D14: Ramp-up interest account
D15: Opening | E15: ARD m | J15: =I16 -> 0 | K15: =J16 -> 0 | L15: =K16 -> 0 | M15: =L16 -> 0 | N15: =M16 -> 0 | O15: =N16 -> 0 | P15: =O16 -> 0 | Q15: =P16 -> 0 | ... DB15: =DA16 -> 0
D16: Closing | E16: ARD m | J16: =J15+Funding!J22-Debt!J39 -> 0 | K16: =K15+Funding!K22-Debt!K39 -> 0 | L16: =L15+Funding!L22-Debt!L39 -> 0 | M16: =M15+Funding!M22-Debt!M39 -> 0 | N16: =N15+Funding!N22-Debt!N39 -> 0 | O16: =O15+Funding!O22-Debt!O39 -> 0 | P16: =P15+Funding!P22-Debt!P39 -> 0 | Q16: =Q15+Funding!Q22-Debt!Q39 -> 0 | ... DB16: =DB15+Funding!DB22-Debt!DB39 -> 0
D17: Lifecycle reserve (MMRA)
D18: Opening | E18: ARD m | J18: =I19 -> 0 | K18: =J19 -> 0 | L18: =K19 -> 0 | M18: =L19 -> 0 | N18: =M19 -> 0 | O18: =N19 -> 0 | P18: =O19 -> 0 | Q18: =P19 -> 0 | ... DB18: =DA19 -> 0
D19: Closing | E19: ARD m | J19: =J18+Operations!J37-Operations!J36 -> 0 | K19: =K18+Operations!K37-Operations!K36 -> 0 | L19: =L18+Operations!L37-Operations!L36 -> 0 | M19: =M18+Operations!M37-Operations!M36 -> 0 | N19: =N18+Operations!N37-Operations!N36 -> 0 | O19: =O18+Operations!O37-Operations!O36 -> 0 | P19: =P18+Operations!P37-Operations!P36 -> 0 | Q19: =Q18+Operations!Q37-Operations!Q36 -> 0 | ... DB19: =DB18+Operations!DB37-Operations!DB36 -> 0
D20: Handback reserve
D21: Opening | E21: ARD m | J21: =I23 -> 0 | K21: =J23 -> 0 | L21: =K23 -> 0 | M21: =L23 -> 0 | N21: =M23 -> 0 | O21: =N23 -> 0 | P21: =O23 -> 0 | Q21: =P23 -> 0 | ... DB21: =DA23 -> 110.94803
D22: Handback works at expiry | E22: ARD m | G22: =SUM(J22:DB22) -> 124.14388 | J22: =(J21+Operations!J39)*Time!J28 -> 0 | K22: =(K21+Operations!K39)*Time!K28 -> 0 | L22: =(L21+Operations!L39)*Time!L28 -> 0 | M22: =(M21+Operations!M39)*Time!M28 -> 0 | N22: =(N21+Operations!N39)*Time!N28 -> 0 | O22: =(O21+Operations!O39)*Time!O28 -> 0 | P22: =(P21+Operations!P39)*Time!P28 -> 0 | Q22: =(Q21+Operations!Q39)*Time!Q28 -> 0 | ... DB22: =(DB21+Operations!DB39)*Time!DB28 -> 124.14388
D23: Closing | E23: ARD m | J23: =J21+Operations!J39-J22 -> 0 | K23: =K21+Operations!K39-K22 -> 0 | L23: =L21+Operations!L39-L22 -> 0 | M23: =M21+Operations!M39-M22 -> 0 | N23: =N21+Operations!N39-N22 -> 0 | O23: =O21+Operations!O39-O22 -> 0 | P23: =P21+Operations!P39-P22 -> 0 | Q23: =Q21+Operations!Q39-Q22 -> 0 | ... DB23: =DB21+Operations!DB39-DB22 -> 0
D24: Retention account
D25: Opening | E25: ARD m | J25: =I27 -> 0 | K25: =J27 -> 0 | L25: =K27 -> 0 | M25: =L27 -> 0 | N25: =M27 -> 0 | O25: =N27 -> 0 | P25: =O27 -> 0 | Q25: =P27 -> 0 | ... DB25: =DA27 -> 0
D26: Released to the D&C contractor | E26: ARD m | G26: =SUM(J26:DB26) -> 42.1075 | J26: =J25*Time!J46 -> 0 | K26: =K25*Time!K46 -> 0 | L26: =L25*Time!L46 -> 0 | M26: =M25*Time!M46 -> 0 | N26: =N25*Time!N46 -> 0 | O26: =O25*Time!O46 -> 0 | P26: =P25*Time!P46 -> 0 | Q26: =Q25*Time!Q46 -> 0 | ... DB26: =DB25*Time!DB46 -> 0
D27: Closing | E27: ARD m | J27: =J25+Construction!J14-J26 -> 0 | K27: =K25+Construction!K14-K26 -> 0 | L27: =L25+Construction!L14-L26 -> 0 | M27: =M25+Construction!M14-M26 -> 0 | N27: =N25+Construction!N14-N26 -> 0 | O27: =O25+Construction!O14-O26 -> 0 | P27: =P25+Construction!P14-P26 -> 0 | Q27: =Q25+Construction!Q14-Q26 -> 0 | ... DB27: =DB25+Construction!DB14-DB26 -> 0
D28: Interchange upgrade account (state new money)
D29: Opening | E29: ARD m | J29: =I30 -> 0 | K29: =J30 -> 0 | L29: =K30 -> 0 | M29: =L30 -> 0 | N29: =M30 -> 0 | O29: =N30 -> 0 | P29: =O30 -> 0 | Q29: =P30 -> 0 | ... DB29: =DA30 -> 0
D30: Closing | E30: ARD m | J30: =J29-Operations!J45+Time!J35*Inputs!$F$172 -> 0 | K30: =K29-Operations!K45+Time!K35*Inputs!$F$172 -> 0 | L30: =L29-Operations!L45+Time!L35*Inputs!$F$172 -> 0 | M30: =M29-Operations!M45+Time!M35*Inputs!$F$172 -> 0 | N30: =N29-Operations!N45+Time!N35*Inputs!$F$172 -> 0 | O30: =O29-Operations!O45+Time!O35*Inputs!$F$172 -> 0 | P30: =P29-Operations!P45+Time!P35*Inputs!$F$172 -> 0 | Q30: =Q29-Operations!Q45+Time!Q35*Inputs!$F$172 -> 0 | ... DB30: =DB29-Operations!DB45+Time!DB35*Inputs!$F$172 -> 0

Sheet Waterfall
D1: Case T: Merrick Link toll road PPP | Waterfall
D2: Units: ARD millions unless stated. Inputs blue on yellow; links green; calculations black.
D3: Period end | E3: date | J3: =Time!J8 -> 42185 | K3: =Time!K8 -> 42277 | L3: =Time!L8 -> 42369 | M3: =Time!M8 -> 42460 | N3: =Time!N8 -> 42551 | O3: =Time!O8 -> 42643 | P3: =Time!P8 -> 42735 | Q3: =Time!Q8 -> 42825 | ... DB3: =Time!DB8 -> 58256
D5: Cash available
D6: Cash account (locked-up cash) brought forward | E6: ARD m | J6: =I51 -> 0 | K6: =J51 -> 0 | L6: =K51 -> 0 | M6: =L51 -> 0 | N6: =M51 -> 0 | O6: =N51 -> 0 | P6: =O51 -> 0 | Q6: =P51 -> 0 | ... DB6: =DA51 -> 0
D7: CFADS | E7: ARD m | G7: =SUM(J7:DB7) -> 4818.7014 | J7: =Operations!J48 -> 0 | K7: =Operations!K48 -> 0 | L7: =Operations!L48 -> 0 | M7: =Operations!M48 -> 0 | N7: =Operations!N48 -> 0 | O7: =Operations!O48 -> 0 | P7: =Operations!P48 -> 0 | Q7: =Operations!Q48 -> 0 | ... DB7: =Operations!DB48 -> 121.9839
D8: Ramp-up interest account release | E8: ARD m | G8: =SUM(J8:DB8) -> 20.225926 | J8: =Debt!J39 -> 0 | K8: =Debt!K39 -> 0 | L8: =Debt!L39 -> 0 | M8: =Debt!M39 -> 0 | N8: =Debt!N39 -> 0 | O8: =Debt!O39 -> 0 | P8: =Debt!P39 -> 0 | Q8: =Debt!Q39 -> 0 | ... DB8: =Debt!DB39 -> 0
D9: Sponsor support loans | E9: ARD m | G9: =SUM(J9:DB9) -> 45 | J9: =Inputs!$F$213*IFERROR(INDEX(Inputs!$J$264:$K$264,MATCH(Time!J13,Inputs!$J$263:$K$263,0)),0) -> 0 | K9: =Inputs!$F$213*IFERROR(INDEX(Inputs!$J$264:$K$264,MATCH(Time!K13,Inputs!$J$263:$K$263,0)),0) -> 0 | L9: =Inputs!$F$213*IFERROR(INDEX(Inputs!$J$264:$K$264,MATCH(Time!L13,Inputs!$J$263:$K$263,0)),0) -> 0 | M9: =Inputs!$F$213*IFERROR(INDEX(Inputs!$J$264:$K$264,MATCH(Time!M13,Inputs!$J$263:$K$263,0)),0) -> 0 | N9: =Inputs!$F$213*IFERROR(INDEX(Inputs!$J$264:$K$264,MATCH(Time!N13,Inputs!$J$263:$K$263,0)),0) -> 0 | O9: =Inputs!$F$213*IFERROR(INDEX(Inputs!$J$264:$K$264,MATCH(Time!O13,Inputs!$J$263:$K$263,0)),0) -> 0 | P9: =Inputs!$F$213*IFERROR(INDEX(Inputs!$J$264:$K$264,MATCH(Time!P13,Inputs!$J$263:$K$263,0)),0) -> 0 | Q9: =Inputs!$F$213*IFERROR(INDEX(Inputs!$J$264:$K$264,MATCH(Time!Q13,Inputs!$J$263:$K$263,0)),0) -> 0 | ... DB9: =Inputs!$F$213*IFERROR(INDEX(Inputs!$J$264:$K$264,MATCH(Time!DB13,Inputs!$J$263:$K$263,0)),0) -> 0
D10: Cash available for senior debt service | E10: ARD m | J10: =(J6+J7+J8+J9)*(1-Time!J20) -> 0 | K10: =(K6+K7+K8+K9)*(1-Time!K20) -> 0 | L10: =(L6+L7+L8+L9)*(1-Time!L20) -> 0 | M10: =(M6+M7+M8+M9)*(1-Time!M20) -> 0 | N10: =(N6+N7+N8+N9)*(1-Time!N20) -> 0 | O10: =(O6+O7+O8+O9)*(1-Time!O20) -> 0 | P10: =(P6+P7+P8+P9)*(1-Time!P20) -> 0 | Q10: =(Q6+Q7+Q8+Q9)*(1-Time!Q20) -> 0 | ... DB10: =(DB6+DB7+DB8+DB9)*(1-Time!DB20) -> 121.9839
D11: 1. Senior fees, interest (including arrears) and principal
D12: Senior arrears brought forward | E12: ARD m | J12: =Debt!J56+Debt!J57 -> 0 | K12: =Debt!K56+Debt!K57 -> 0 | L12: =Debt!L56+Debt!L57 -> 0 | M12: =Debt!M56+Debt!M57 -> 0 | N12: =Debt!N56+Debt!N57 -> 0 | O12: =Debt!O56+Debt!O57 -> 0 | P12: =Debt!P56+Debt!P57 -> 0 | Q12: =Debt!Q56+Debt!Q57 -> 0 | ... DB12: =Debt!DB56+Debt!DB57 -> 0
D13: Senior amounts due | E13: ARD m | G13: =SUM(J13:DB13) -> 1167.1705 | J13: =(Debt!J65+Debt!J64+J12+Debt!J67)*(1-Time!J20) -> 0 | K13: =(Debt!K65+Debt!K64+K12+Debt!K67)*(1-Time!K20) -> 0 | L13: =(Debt!L65+Debt!L64+L12+Debt!L67)*(1-Time!L20) -> 0 | M13: =(Debt!M65+Debt!M64+M12+Debt!M67)*(1-Time!M20) -> 0 | N13: =(Debt!N65+Debt!N64+N12+Debt!N67)*(1-Time!N20) -> 0 | O13: =(Debt!O65+Debt!O64+O12+Debt!O67)*(1-Time!O20) -> 0 | P13: =(Debt!P65+Debt!P64+P12+Debt!P67)*(1-Time!P20) -> 0 | Q13: =(Debt!Q65+Debt!Q64+Q12+Debt!Q67)*(1-Time!Q20) -> 0 | ... DB13: =(Debt!DB65+Debt!DB64+DB12+Debt!DB67)*(1-Time!DB20) -> 0
D14: Senior amounts paid (cash plus DSRA) | E14: ARD m | G14: =SUM(J14:DB14) -> 1167.1705 | J14: =MIN(J13,MAX(0,J10)+Reserves!J8)*(1-Time!J20) -> 0 | K14: =MIN(K13,MAX(0,K10)+Reserves!K8)*(1-Time!K20) -> 0 | L14: =MIN(L13,MAX(0,L10)+Reserves!L8)*(1-Time!L20) -> 0 | M14: =MIN(M13,MAX(0,M10)+Reserves!M8)*(1-Time!M20) -> 0 | N14: =MIN(N13,MAX(0,N10)+Reserves!N8)*(1-Time!N20) -> 0 | O14: =MIN(O13,MAX(0,O10)+Reserves!O8)*(1-Time!O20) -> 0 | P14: =MIN(P13,MAX(0,P10)+Reserves!P8)*(1-Time!P20) -> 0 | Q14: =MIN(Q13,MAX(0,Q10)+Reserves!Q8)*(1-Time!Q20) -> 0 | ... DB14: =MIN(DB13,MAX(0,DB10)+Reserves!DB8)*(1-Time!DB20) -> 0
D15: Fees paid | E15: ARD m | G15: =SUM(J15:DB15) -> 2.8589037 | J15: =MIN(Debt!J65,J14)*(1-Time!J20) -> 0 | K15: =MIN(Debt!K65,K14)*(1-Time!K20) -> 0 | L15: =MIN(Debt!L65,L14)*(1-Time!L20) -> 0 | M15: =MIN(Debt!M65,M14)*(1-Time!M20) -> 0 | N15: =MIN(Debt!N65,N14)*(1-Time!N20) -> 0 | O15: =MIN(Debt!O65,O14)*(1-Time!O20) -> 0 | P15: =MIN(Debt!P65,P14)*(1-Time!P20) -> 0 | Q15: =MIN(Debt!Q65,Q14)*(1-Time!Q20) -> 0 | ... DB15: =MIN(Debt!DB65,DB14)*(1-Time!DB20) -> 0
D16: Interest paid | E16: ARD m | G16: =SUM(J16:DB16) -> 716.87277 | J16: =MIN(Debt!J64+J12,J14-J15) -> 0 | K16: =MIN(Debt!K64+K12,K14-K15) -> 0 | L16: =MIN(Debt!L64+L12,L14-L15) -> 0 | M16: =MIN(Debt!M64+M12,M14-M15) -> 0 | N16: =MIN(Debt!N64+N12,N14-N15) -> 0 | O16: =MIN(Debt!O64+O12,O14-O15) -> 0 | P16: =MIN(Debt!P64+P12,P14-P15) -> 0 | Q16: =MIN(Debt!Q64+Q12,Q14-Q15) -> 0 | ... DB16: =MIN(Debt!DB64+DB12,DB14-DB15) -> 0
D17: Principal paid | E17: ARD m | G17: =SUM(J17:DB17) -> 447.43887 | J17: =J14-J15-J16 -> 0 | K17: =K14-K15-K16 -> 0 | L17: =L14-L15-L16 -> 0 | M17: =M14-M15-M16 -> 0 | N17: =N14-N15-N16 -> 0 | O17: =O14-O15-O16 -> 0 | P17: =P14-P15-P16 -> 0 | Q17: =Q14-Q15-Q16 -> 0 | ... DB17: =DB14-DB15-DB16 -> 0
D18: Bank share of interest paid | E18: factor | J18: =IF(Debt!J64+J12>0,(Debt!J44+Debt!J56)/(Debt!J64+J12),0) -> 0 | K18: =IF(Debt!K64+K12>0,(Debt!K44+Debt!K56)/(Debt!K64+K12),0) -> 0 | L18: =IF(Debt!L64+L12>0,(Debt!L44+Debt!L56)/(Debt!L64+L12),0) -> 0 | M18: =IF(Debt!M64+M12>0,(Debt!M44+Debt!M56)/(Debt!M64+M12),0) -> 0 | N18: =IF(Debt!N64+N12>0,(Debt!N44+Debt!N56)/(Debt!N64+N12),0) -> 0 | O18: =IF(Debt!O64+O12>0,(Debt!O44+Debt!O56)/(Debt!O64+O12),0) -> 0 | P18: =IF(Debt!P64+P12>0,(Debt!P44+Debt!P56)/(Debt!P64+P12),0) -> 0 | Q18: =IF(Debt!Q64+Q12>0,(Debt!Q44+Debt!Q56)/(Debt!Q64+Q12),0) -> 0 | ... DB18: =IF(Debt!DB64+DB12>0,(Debt!DB44+Debt!DB56)/(Debt!DB64+DB12),0) -> 0
D19: Bond share of interest paid | E19: factor | J19: =IF(Debt!J64+J12>0,(Debt!J51+Debt!J57)/(Debt!J64+J12),0) -> 0 | K19: =IF(Debt!K64+K12>0,(Debt!K51+Debt!K57)/(Debt!K64+K12),0) -> 0 | L19: =IF(Debt!L64+L12>0,(Debt!L51+Debt!L57)/(Debt!L64+L12),0) -> 0 | M19: =IF(Debt!M64+M12>0,(Debt!M51+Debt!M57)/(Debt!M64+M12),0) -> 0 | N19: =IF(Debt!N64+N12>0,(Debt!N51+Debt!N57)/(Debt!N64+N12),0) -> 0 | O19: =IF(Debt!O64+O12>0,(Debt!O51+Debt!O57)/(Debt!O64+O12),0) -> 0 | P19: =IF(Debt!P64+P12>0,(Debt!P51+Debt!P57)/(Debt!P64+P12),0) -> 0 | Q19: =IF(Debt!Q64+Q12>0,(Debt!Q51+Debt!Q57)/(Debt!Q64+Q12),0) -> 0 | ... DB19: =IF(Debt!DB64+DB12>0,(Debt!DB51+Debt!DB57)/(Debt!DB64+DB12),0) -> 0
D20: Bank principal paid | E20: ARD m | G20: =SUM(J20:DB20) -> 0 | J20: =IF(Debt!J67>0,J17*Debt!J45/Debt!J67,0) -> 0 | K20: =IF(Debt!K67>0,K17*Debt!K45/Debt!K67,0) -> 0 | L20: =IF(Debt!L67>0,L17*Debt!L45/Debt!L67,0) -> 0 | M20: =IF(Debt!M67>0,M17*Debt!M45/Debt!M67,0) -> 0 | N20: =IF(Debt!N67>0,N17*Debt!N45/Debt!N67,0) -> 0 | O20: =IF(Debt!O67>0,O17*Debt!O45/Debt!O67,0) -> 0 | P20: =IF(Debt!P67>0,P17*Debt!P45/Debt!P67,0) -> 0 | Q20: =IF(Debt!Q67>0,Q17*Debt!Q45/Debt!Q67,0) -> 0 | ... DB20: =IF(Debt!DB67>0,DB17*Debt!DB45/Debt!DB67,0) -> 0
D21: Bond principal paid | E21: ARD m | G21: =SUM(J21:DB21) -> 0 | J21: =IF(Debt!J67>0,J17*Debt!J52/Debt!J67,0) -> 0 | K21: =IF(Debt!K67>0,K17*Debt!K52/Debt!K67,0) -> 0 | L21: =IF(Debt!L67>0,L17*Debt!L52/Debt!L67,0) -> 0 | M21: =IF(Debt!M67>0,M17*Debt!M52/Debt!M67,0) -> 0 | N21: =IF(Debt!N67>0,N17*Debt!N52/Debt!N67,0) -> 0 | O21: =IF(Debt!O67>0,O17*Debt!O52/Debt!O67,0) -> 0 | P21: =IF(Debt!P67>0,P17*Debt!P52/Debt!P67,0) -> 0 | Q21: =IF(Debt!Q67>0,Q17*Debt!Q52/Debt!Q67,0) -> 0 | ... DB21: =IF(Debt!DB67>0,DB17*Debt!DB52/Debt!DB67,0) -> 0
D22: Notes principal paid | E22: ARD m | G22: =SUM(J22:DB22) -> 447.43887 | J22: =IF(Debt!J67>0,J17*Debt!J66/Debt!J67,0) -> 0 | K22: =IF(Debt!K67>0,K17*Debt!K66/Debt!K67,0) -> 0 | L22: =IF(Debt!L67>0,L17*Debt!L66/Debt!L67,0) -> 0 | M22: =IF(Debt!M67>0,M17*Debt!M66/Debt!M67,0) -> 0 | N22: =IF(Debt!N67>0,N17*Debt!N66/Debt!N67,0) -> 0 | O22: =IF(Debt!O67>0,O17*Debt!O66/Debt!O67,0) -> 0 | P22: =IF(Debt!P67>0,P17*Debt!P66/Debt!P67,0) -> 0 | Q22: =IF(Debt!Q67>0,Q17*Debt!Q66/Debt!Q67,0) -> 0 | ... DB22: =IF(Debt!DB67>0,DB17*Debt!DB66/Debt!DB67,0) -> 0
D23: DSRA drawn | E23: ARD m | G23: =SUM(J23:DB23) -> 17.147382 | J23: =MAX(0,J14-MAX(0,J10)) -> 0 | K23: =MAX(0,K14-MAX(0,K10)) -> 0 | L23: =MAX(0,L14-MAX(0,L10)) -> 0 | M23: =MAX(0,M14-MAX(0,M10)) -> 0 | N23: =MAX(0,N14-MAX(0,N10)) -> 0 | O23: =MAX(0,O14-MAX(0,O10)) -> 0 | P23: =MAX(0,P14-MAX(0,P10)) -> 0 | Q23: =MAX(0,Q14-MAX(0,Q10)) -> 0 | ... DB23: =MAX(0,DB14-MAX(0,DB10)) -> 0
D24: Cash after senior debt service | E24: ARD m | J24: =J10-J14+J23 -> 0 | K24: =K10-K14+K23 -> 0 | L24: =L10-L14+L23 -> 0 | M24: =M10-M14+M23 -> 0 | N24: =N10-N14+N23 -> 0 | O24: =O10-O14+O23 -> 0 | P24: =P10-P14+P23 -> 0 | Q24: =Q10-Q14+Q23 -> 0 | ... DB24: =DB10-DB14+DB23 -> 121.9839
D25: 2. DSRA top-up or release
D26: Cash after DSRA | E26: ARD m | J26: =J24-Reserves!J11+Reserves!J12 -> 0 | K26: =K24-Reserves!K11+Reserves!K12 -> 0 | L26: =L24-Reserves!L11+Reserves!L12 -> 0 | M26: =M24-Reserves!M11+Reserves!M12 -> 0 | N26: =N24-Reserves!N11+Reserves!N12 -> 0 | O26: =O24-Reserves!O11+Reserves!O12 -> 0 | P26: =P24-Reserves!P11+Reserves!P12 -> 0 | Q26: =Q24-Reserves!Q11+Reserves!Q12 -> 0 | ... DB26: =DB24-Reserves!DB11+Reserves!DB12 -> 121.9839
D27: 3. Standstill cash sweep (100% to senior principal)
D28: Bank balance after scheduled principal | E28: ARD m | J28: =Debt!J42-J20 -> 0 | K28: =Debt!K42-K20 -> 0 | L28: =Debt!L42-L20 -> 0 | M28: =Debt!M42-M20 -> 0 | N28: =Debt!N42-N20 -> 0 | O28: =Debt!O42-O20 -> 5.1260606 | P28: =Debt!P42-P20 -> 53.886895 | Q28: =Debt!Q42-Q20 -> 109.58113 | ... DB28: =Debt!DB42-DB20 -> 0
D29: Bond balance after scheduled principal | E29: ARD m | J29: =Debt!J49-J21 -> 485.17159 | K29: =Debt!K49-K21 -> 485.17159 | L29: =Debt!L49-L21 -> 485.17159 | M29: =Debt!M49-M21 -> 485.17159 | N29: =Debt!N49-N21 -> 485.17159 | O29: =Debt!O49-O21 -> 485.17159 | P29: =Debt!P49-P21 -> 485.17159 | Q29: =Debt!Q49-Q21 -> 485.17159 | ... DB29: =Debt!DB49-DB21 -> 0
D30: Standstill sweep | E30: ARD m | G30: =SUM(J30:DB30) -> 41.861577 | J30: =Time!J34*MIN(MAX(0,J26),J28+J29) -> 0 | K30: =Time!K34*MIN(MAX(0,K26),K28+K29) -> 0 | L30: =Time!L34*MIN(MAX(0,L26),L28+L29) -> 0 | M30: =Time!M34*MIN(MAX(0,M26),M28+M29) -> 0 | N30: =Time!N34*MIN(MAX(0,N26),N28+N29) -> 0 | O30: =Time!O34*MIN(MAX(0,O26),O28+O29) -> 0 | P30: =Time!P34*MIN(MAX(0,P26),P28+P29) -> 0 | Q30: =Time!Q34*MIN(MAX(0,Q26),Q28+Q29) -> 0 | ... DB30: =Time!DB34*MIN(MAX(0,DB26),DB28+DB29) -> 0
D31: Standstill sweep to bank | E31: ARD m | G31: =SUM(J31:DB31) -> 18.83771 | J31: =IF(J30>0,J30*J28/(J28+J29),0) -> 0 | K31: =IF(K30>0,K30*K28/(K28+K29),0) -> 0 | L31: =IF(L30>0,L30*L28/(L28+L29),0) -> 0 | M31: =IF(M30>0,M30*M28/(M28+M29),0) -> 0 | N31: =IF(N30>0,N30*N28/(N28+N29),0) -> 0 | O31: =IF(O30>0,O30*O28/(O28+O29),0) -> 0 | P31: =IF(P30>0,P30*P28/(P28+P29),0) -> 0 | Q31: =IF(Q30>0,Q30*Q28/(Q28+Q29),0) -> 0 | ... DB31: =IF(DB30>0,DB30*DB28/(DB28+DB29),0) -> 0
D32: Standstill sweep to bonds | E32: ARD m | G32: =SUM(J32:DB32) -> 23.023867 | J32: =J30-J31 -> 0 | K32: =K30-K31 -> 0 | L32: =L30-L31 -> 0 | M32: =M30-M31 -> 0 | N32: =N30-N31 -> 0 | O32: =O30-O31 -> 0 | P32: =P30-P31 -> 0 | Q32: =Q30-Q31 -> 0 | ... DB32: =DB30-DB31 -> 0
D33: Cash after standstill sweep | E33: ARD m | J33: =J26-J30 -> 0 | K33: =K26-K30 -> 0 | L33: =L26-L30 -> 0 | M33: =M26-M30 -> 0 | N33: =N26-N30 -> 0 | O33: =O26-O30 -> 0 | P33: =P26-P30 -> 0 | Q33: =Q26-Q30 -> 0 | ... DB33: =DB26-DB30 -> 121.9839
D34: 4. NILO debt service
D35: NILO paid | E35: ARD m | G35: =SUM(J35:DB35) -> 991.85961 | J35: =MIN(Debt!J100,MAX(0,J33))*(1-Time!J20) -> 0 | K35: =MIN(Debt!K100,MAX(0,K33))*(1-Time!K20) -> 0 | L35: =MIN(Debt!L100,MAX(0,L33))*(1-Time!L20) -> 0 | M35: =MIN(Debt!M100,MAX(0,M33))*(1-Time!M20) -> 0 | N35: =MIN(Debt!N100,MAX(0,N33))*(1-Time!N20) -> 0 | O35: =MIN(Debt!O100,MAX(0,O33))*(1-Time!O20) -> 0 | P35: =MIN(Debt!P100,MAX(0,P33))*(1-Time!P20) -> 0 | Q35: =MIN(Debt!Q100,MAX(0,Q33))*(1-Time!Q20) -> 0 | ... DB35: =MIN(Debt!DB100,MAX(0,DB33))*(1-Time!DB20) -> 5.0901589e-13
D36: Cash after NILO | E36: ARD m | J36: =J33-J35 -> 0 | K36: =K33-K35 -> 0 | L36: =L33-L35 -> 0 | M36: =M33-M35 -> 0 | N36: =N33-N35 -> 0 | O36: =O33-O35 -> 0 | P36: =P33-P35 -> 0 | Q36: =Q33-Q35 -> 0 | ... DB36: =DB33-DB35 -> 121.9839
D37: 5. Notes cash sweep (50% to 2030)
D38: Notes cash sweep | E38: ARD m | G38: =SUM(J38:DB38) -> 167.48763 | J38: =Time!J38*MIN(Inputs!$F$168*MAX(0,J36),Debt!J93-J22) -> 0 | K38: =Time!K38*MIN(Inputs!$F$168*MAX(0,K36),Debt!K93-K22) -> 0 | L38: =Time!L38*MIN(Inputs!$F$168*MAX(0,L36),Debt!L93-L22) -> 0 | M38: =Time!M38*MIN(Inputs!$F$168*MAX(0,M36),Debt!M93-M22) -> 0 | N38: =Time!N38*MIN(Inputs!$F$168*MAX(0,N36),Debt!N93-N22) -> 0 | O38: =Time!O38*MIN(Inputs!$F$168*MAX(0,O36),Debt!O93-O22) -> 0 | P38: =Time!P38*MIN(Inputs!$F$168*MAX(0,P36),Debt!P93-P22) -> 0 | Q38: =Time!Q38*MIN(Inputs!$F$168*MAX(0,Q36),Debt!Q93-Q22) -> 0 | ... DB38: =Time!DB38*MIN(Inputs!$F$168*MAX(0,DB36),Debt!DB93-DB22) -> 0
D39: Cash available for distribution | E39: ARD m | J39: =J36-J38 -> 0 | K39: =K36-K38 -> 0 | L39: =L36-L38 -> 0 | M39: =M36-M38 -> 0 | N39: =N36-N38 -> 0 | O39: =O36-O38 -> 0 | P39: =P36-P38 -> 0 | Q39: =Q36-Q38 -> 0 | ... DB39: =DB36-DB38 -> 121.9839
D40: 6. Distribution tests
D41: Senior DSCR, period | E41: x | J41: =IF(Debt!J68>Inputs!$F$9,J7/Debt!J68,0) -> 0 | K41: =IF(Debt!K68>Inputs!$F$9,K7/Debt!K68,0) -> 0 | L41: =IF(Debt!L68>Inputs!$F$9,L7/Debt!L68,0) -> 0 | M41: =IF(Debt!M68>Inputs!$F$9,M7/Debt!M68,0) -> 0 | N41: =IF(Debt!N68>Inputs!$F$9,N7/Debt!N68,0) -> 0 | O41: =IF(Debt!O68>Inputs!$F$9,O7/Debt!O68,0) -> 0 | P41: =IF(Debt!P68>Inputs!$F$9,P7/Debt!P68,0) -> 0 | Q41: =IF(Debt!Q68>Inputs!$F$9,Q7/Debt!Q68,0) -> 0 | ... DB41: =IF(Debt!DB68>Inputs!$F$9,DB7/Debt!DB68,0) -> 0
D42: Historic CFADS (12 months; 6 months at the first test) | E42: ARD m | J42: =IF(OR(Time!J36=1,Time!I44=0),J7,J7+I7) -> 0 | K42: =IF(OR(Time!K36=1,Time!J44=0),K7,K7+J7) -> 0 | L42: =IF(OR(Time!L36=1,Time!K44=0),L7,L7+K7) -> 0 | M42: =IF(OR(Time!M36=1,Time!L44=0),M7,M7+L7) -> 0 | N42: =IF(OR(Time!N36=1,Time!M44=0),N7,N7+M7) -> 0 | O42: =IF(OR(Time!O36=1,Time!N44=0),O7,O7+N7) -> 0 | P42: =IF(OR(Time!P36=1,Time!O44=0),P7,P7+O7) -> 0 | Q42: =IF(OR(Time!Q36=1,Time!P44=0),Q7,Q7+P7) -> 0 | ... DB42: =IF(OR(Time!DB36=1,Time!DA44=0),DB7,DB7+DA7) -> 239.49099
D43: Historic scheduled debt service | E43: ARD m | J43: =IF(OR(Time!J36=1,Time!I44=0),Debt!J68,Debt!J68+Debt!I68) -> 0 | K43: =IF(OR(Time!K36=1,Time!J44=0),Debt!K68,Debt!K68+Debt!J68) -> 0 | L43: =IF(OR(Time!L36=1,Time!K44=0),Debt!L68,Debt!L68+Debt!K68) -> 0 | M43: =IF(OR(Time!M36=1,Time!L44=0),Debt!M68,Debt!M68+Debt!L68) -> 0 | N43: =IF(OR(Time!N36=1,Time!M44=0),Debt!N68,Debt!N68+Debt!M68) -> 0 | O43: =IF(OR(Time!O36=1,Time!N44=0),Debt!O68,Debt!O68+Debt!N68) -> 0 | P43: =IF(OR(Time!P36=1,Time!O44=0),Debt!P68,Debt!P68+Debt!O68) -> 0 | Q43: =IF(OR(Time!Q36=1,Time!P44=0),Debt!Q68,Debt!Q68+Debt!P68) -> 0 | ... DB43: =IF(OR(Time!DB36=1,Time!DA44=0),Debt!DB68,Debt!DB68+Debt!DA68) -> 0
D44: Senior DSCR, historic (covenant) | E44: x | J44: =IF(AND(Time!J44=1,J43>Inputs!$F$9),J42/J43,0) -> 0 | K44: =IF(AND(Time!K44=1,K43>Inputs!$F$9),K42/K43,0) -> 0 | L44: =IF(AND(Time!L44=1,L43>Inputs!$F$9),L42/L43,0) -> 0 | M44: =IF(AND(Time!M44=1,M43>Inputs!$F$9),M42/M43,0) -> 0 | N44: =IF(AND(Time!N44=1,N43>Inputs!$F$9),N42/N43,0) -> 0 | O44: =IF(AND(Time!O44=1,O43>Inputs!$F$9),O42/O43,0) -> 0 | P44: =IF(AND(Time!P44=1,P43>Inputs!$F$9),P42/P43,0) -> 0 | Q44: =IF(AND(Time!Q44=1,Q43>Inputs!$F$9),Q42/Q43,0) -> 0 | ... DB44: =IF(AND(Time!DB44=1,DB43>Inputs!$F$9),DB42/DB43,0) -> 0
D45: Lock-up test failed | E45: flag | J45: =IF(AND(Time!J44=1,J43>Inputs!$F$9,J44<Inputs!$F$113),1,0) -> 0 | K45: =IF(AND(Time!K44=1,K43>Inputs!$F$9,K44<Inputs!$F$113),1,0) -> 0 | L45: =IF(AND(Time!L44=1,L43>Inputs!$F$9,L44<Inputs!$F$113),1,0) -> 0 | M45: =IF(AND(Time!M44=1,M43>Inputs!$F$9,M44<Inputs!$F$113),1,0) -> 0 | N45: =IF(AND(Time!N44=1,N43>Inputs!$F$9,N44<Inputs!$F$113),1,0) -> 0 | O45: =IF(AND(Time!O44=1,O43>Inputs!$F$9,O44<Inputs!$F$113),1,0) -> 0 | P45: =IF(AND(Time!P44=1,P43>Inputs!$F$9,P44<Inputs!$F$113),1,0) -> 0 | Q45: =IF(AND(Time!Q44=1,Q43>Inputs!$F$9,Q44<Inputs!$F$113),1,0) -> 0 | ... DB45: =IF(AND(Time!DB44=1,DB43>Inputs!$F$9,DB44<Inputs!$F$113),1,0) -> 0
D46: Default test failed | E46: flag | J46: =IF(AND(Time!J45=1,J43>Inputs!$F$9,J44<Inputs!$F$114),1,0) -> 0 | K46: =IF(AND(Time!K45=1,K43>Inputs!$F$9,K44<Inputs!$F$114),1,0) -> 0 | L46: =IF(AND(Time!L45=1,L43>Inputs!$F$9,L44<Inputs!$F$114),1,0) -> 0 | M46: =IF(AND(Time!M45=1,M43>Inputs!$F$9,M44<Inputs!$F$114),1,0) -> 0 | N46: =IF(AND(Time!N45=1,N43>Inputs!$F$9,N44<Inputs!$F$114),1,0) -> 0 | O46: =IF(AND(Time!O45=1,O43>Inputs!$F$9,O44<Inputs!$F$114),1,0) -> 0 | P46: =IF(AND(Time!P45=1,P43>Inputs!$F$9,P44<Inputs!$F$114),1,0) -> 0 | Q46: =IF(AND(Time!Q45=1,Q43>Inputs!$F$9,Q44<Inputs!$F$114),1,0) -> 0 | ... DB46: =IF(AND(Time!DB45=1,DB43>Inputs!$F$9,DB44<Inputs!$F$114),1,0) -> 0
D47: Event of default continuing | E47: flag | J47: =IF(AND(Time!J20=0,Time!J23=0,OR(I47=1,J46=1)),1,0) -> 0 | K47: =IF(AND(Time!K20=0,Time!K23=0,OR(J47=1,K46=1)),1,0) -> 0 | L47: =IF(AND(Time!L20=0,Time!L23=0,OR(K47=1,L46=1)),1,0) -> 0 | M47: =IF(AND(Time!M20=0,Time!M23=0,OR(L47=1,M46=1)),1,0) -> 0 | N47: =IF(AND(Time!N20=0,Time!N23=0,OR(M47=1,N46=1)),1,0) -> 0 | O47: =IF(AND(Time!O20=0,Time!O23=0,OR(N47=1,O46=1)),1,0) -> 0 | P47: =IF(AND(Time!P20=0,Time!P23=0,OR(O47=1,P46=1)),1,0) -> 0 | Q47: =IF(AND(Time!Q20=0,Time!Q23=0,OR(P47=1,Q46=1)),1,0) -> 0 | ... DB47: =IF(AND(Time!DB20=0,Time!DB23=0,OR(DA47=1,DB46=1)),1,0) -> 0
D48: Distributions blocked | E48: flag | J48: =IF(OR(Time!J20=1,Time!J28=1),0,IF(OR(Time!J33=1,J45=1,Reserves!J13<Reserves!J7-Inputs!$F$9,J47=1,Time!J34=1,Debt!J101>Inputs!$F$9,Debt!J58+Debt!J59>Inputs!$F$9),1,0)) -> 0 | K48: =IF(OR(Time!K20=1,Time!K28=1),0,IF(OR(Time!K33=1,K45=1,Reserves!K13<Reserves!K7-Inputs!$F$9,K47=1,Time!K34=1,Debt!K101>Inputs!$F$9,Debt!K58+Debt!K59>Inputs!$F$9),1,0)) -> 0 | L48: =IF(OR(Time!L20=1,Time!L28=1),0,IF(OR(Time!L33=1,L45=1,Reserves!L13<Reserves!L7-Inputs!$F$9,L47=1,Time!L34=1,Debt!L101>Inputs!$F$9,Debt!L58+Debt!L59>Inputs!$F$9),1,0)) -> 0 | M48: =IF(OR(Time!M20=1,Time!M28=1),0,IF(OR(Time!M33=1,M45=1,Reserves!M13<Reserves!M7-Inputs!$F$9,M47=1,Time!M34=1,Debt!M101>Inputs!$F$9,Debt!M58+Debt!M59>Inputs!$F$9),1,0)) -> 0 | N48: =IF(OR(Time!N20=1,Time!N28=1),0,IF(OR(Time!N33=1,N45=1,Reserves!N13<Reserves!N7-Inputs!$F$9,N47=1,Time!N34=1,Debt!N101>Inputs!$F$9,Debt!N58+Debt!N59>Inputs!$F$9),1,0)) -> 0 | O48: =IF(OR(Time!O20=1,Time!O28=1),0,IF(OR(Time!O33=1,O45=1,Reserves!O13<Reserves!O7-Inputs!$F$9,O47=1,Time!O34=1,Debt!O101>Inputs!$F$9,Debt!O58+Debt!O59>Inputs!$F$9),1,0)) -> 0 | P48: =IF(OR(Time!P20=1,Time!P28=1),0,IF(OR(Time!P33=1,P45=1,Reserves!P13<Reserves!P7-Inputs!$F$9,P47=1,Time!P34=1,Debt!P101>Inputs!$F$9,Debt!P58+Debt!P59>Inputs!$F$9),1,0)) -> 0 | Q48: =IF(OR(Time!Q20=1,Time!Q28=1),0,IF(OR(Time!Q33=1,Q45=1,Reserves!Q13<Reserves!Q7-Inputs!$F$9,Q47=1,Time!Q34=1,Debt!Q101>Inputs!$F$9,Debt!Q58+Debt!Q59>Inputs!$F$9),1,0)) -> 0 | ... DB48: =IF(OR(Time!DB20=1,Time!DB28=1),0,IF(OR(Time!DB33=1,DB45=1,Reserves!DB13<Reserves!DB7-Inputs!$F$9,DB47=1,Time!DB34=1,Debt!DB101>Inputs!$F$9,Debt!DB58+Debt!DB59>Inputs!$F$9),1,0)) -> 0
D49: Distributions to equity | E49: ARD m | G49: =SUM(J49:DB49) -> 2571.1356 | J49: =IF(J48=1,0,MAX(0,J39))*(1-Time!J20) -> 0 | K49: =IF(K48=1,0,MAX(0,K39))*(1-Time!K20) -> 0 | L49: =IF(L48=1,0,MAX(0,L39))*(1-Time!L20) -> 0 | M49: =IF(M48=1,0,MAX(0,M39))*(1-Time!M20) -> 0 | N49: =IF(N48=1,0,MAX(0,N39))*(1-Time!N20) -> 0 | O49: =IF(O48=1,0,MAX(0,O39))*(1-Time!O20) -> 0 | P49: =IF(P48=1,0,MAX(0,P39))*(1-Time!P20) -> 0 | Q49: =IF(Q48=1,0,MAX(0,Q39))*(1-Time!Q20) -> 0 | ... DB49: =IF(DB48=1,0,MAX(0,DB39))*(1-Time!DB20) -> 121.9839
D50: State reserve top-up received | E50: ARD m | G50: =SUM(J50:DB50) -> 41.7 | J50: =Inputs!$F$174*Time!J35 -> 0 | K50: =Inputs!$F$174*Time!K35 -> 0 | L50: =Inputs!$F$174*Time!L35 -> 0 | M50: =Inputs!$F$174*Time!M35 -> 0 | N50: =Inputs!$F$174*Time!N35 -> 0 | O50: =Inputs!$F$174*Time!O35 -> 0 | P50: =Inputs!$F$174*Time!P35 -> 0 | Q50: =Inputs!$F$174*Time!Q35 -> 0 | ... DB50: =Inputs!$F$174*Time!DB35 -> 0
D51: Cash account carried forward | E51: ARD m | J51: =(J39-J49+J50)*(1-Time!J20) -> 0 | K51: =(K39-K49+K50)*(1-Time!K20) -> 0 | L51: =(L39-L49+L50)*(1-Time!L20) -> 0 | M51: =(M39-M49+M50)*(1-Time!M20) -> 0 | N51: =(N39-N49+N50)*(1-Time!N20) -> 0 | O51: =(O39-O49+O50)*(1-Time!O20) -> 0 | P51: =(P39-P49+P50)*(1-Time!P20) -> 0 | Q51: =(Q39-Q49+Q50)*(1-Time!Q20) -> 0 | ... DB51: =(DB39-DB49+DB50)*(1-Time!DB20) -> 0
D52: Shareholder loans and dividends
D53: Shareholder loans: opening (incl. capitalized interest) | E53: ARD m | J53: =I59 -> 0 | K53: =J59 -> 62.40236 | L53: =K59 -> 89.486022 | M53: =L59 -> 144.03245 | N53: =M59 -> 231.07574 | O53: =N59 -> 336.26822 | P53: =O59 -> 344.95592 | Q53: =P59 -> 353.86807 | ... DB53: =DA59 -> 0
D54: Shareholder loan interest accrued | E54: ARD m | G54: =SUM(J54:DB54) -> 403.43374 | J54: =J53*Inputs!$F$89*Time!J9/Inputs!$F$45 -> 0 | K54: =K53*Inputs!$F$89*Time!K9/Inputs!$F$45 -> 1.6122034 | L54: =L53*Inputs!$F$89*Time!L9/Inputs!$F$45 -> 2.3119265 | M54: =M53*Inputs!$F$89*Time!M9/Inputs!$F$45 -> 3.6807196 | N54: =N53*Inputs!$F$89*Time!N9/Inputs!$F$45 -> 5.9050931 | O54: =O53*Inputs!$F$89*Time!O9/Inputs!$F$45 -> 8.6876968 | P54: =P53*Inputs!$F$89*Time!P9/Inputs!$F$45 -> 8.9121488 | Q54: =Q53*Inputs!$F$89*Time!Q9/Inputs!$F$45 -> 8.9436519 | ... DB54: =DB53*Inputs!$F$89*Time!DB9/Inputs!$F$45 -> 0
D55: Shareholder loans outstanding before payment | E55: ARD m | J55: =J53+J54+J9+Funding!J38 -> 62.40236 | K55: =K53+K54+K9+Funding!K38 -> 89.486022 | L55: =L53+L54+L9+Funding!L38 -> 144.03245 | M55: =M53+M54+M9+Funding!M38 -> 231.07574 | N55: =N53+N54+N9+Funding!N38 -> 336.26822 | O55: =O53+O54+O9+Funding!O38 -> 344.95592 | P55: =P53+P54+P9+Funding!P38 -> 353.86807 | Q55: =Q53+Q54+Q9+Funding!Q38 -> 362.81172 | ... DB55: =DB53+DB54+DB9+Funding!DB38 -> 0
D56: Paid on shareholder loans | E56: ARD m | G56: =SUM(J56:DB56) -> 0 | J56: =MIN(J49,J55) -> 0 | K56: =MIN(K49,K55) -> 0 | L56: =MIN(L49,L55) -> 0 | M56: =MIN(M49,M55) -> 0 | N56: =MIN(N49,N55) -> 0 | O56: =MIN(O49,O55) -> 0 | P56: =MIN(P49,P55) -> 0 | Q56: =MIN(Q49,Q55) -> 0 | ... DB56: =MIN(DB49,DB55) -> 0
D57: Dividends | E57: ARD m | G57: =SUM(J57:DB57) -> 2571.1356 | J57: =J49-J56 -> 0 | K57: =K49-K56 -> 0 | L57: =L49-L56 -> 0 | M57: =M49-M56 -> 0 | N57: =N49-N56 -> 0 | O57: =O49-O56 -> 0 | P57: =P49-P56 -> 0 | Q57: =Q49-Q56 -> 0 | ... DB57: =DB49-DB56 -> 121.9839
D58: Shareholder loans: closing before restructuring | E58: ARD m | J58: =J55-J56 -> 62.40236 | K58: =K55-K56 -> 89.486022 | L58: =L55-L56 -> 144.03245 | M58: =M55-M56 -> 231.07574 | N58: =N55-N56 -> 336.26822 | O58: =O55-O56 -> 344.95592 | P58: =P55-P56 -> 353.86807 | Q58: =Q55-Q56 -> 362.81172 | ... DB58: =DB55-DB56 -> 0
D59: Shareholder loans: closing | E59: ARD m | J59: =IF(Time!J35=1,0,J58) -> 62.40236 | K59: =IF(Time!K35=1,0,K58) -> 89.486022 | L59: =IF(Time!L35=1,0,L58) -> 144.03245 | M59: =IF(Time!M35=1,0,M58) -> 231.07574 | N59: =IF(Time!N35=1,0,N58) -> 336.26822 | O59: =IF(Time!O35=1,0,O58) -> 344.95592 | P59: =IF(Time!P35=1,0,P58) -> 353.86807 | Q59: =IF(Time!Q35=1,0,Q58) -> 362.81172 | ... DB59: =IF(Time!DB35=1,0,DB58) -> 0
D60: Equity cash flows
D61: Original sponsors' cash flow | E61: ARD m | G61: =SUM(J61:DB61) -> -424.71562 | J61: =IF(Time!J20=1,-Funding!J27,IF(Time!J23=1,0,J49-J9)) -> -73.414541 | K61: =IF(Time!K20=1,-Funding!K27,IF(Time!K23=1,0,K49-K9)) -> -29.966422 | L61: =IF(Time!L20=1,-Funding!L27,IF(Time!L23=1,0,L49-L9)) -> -61.452349 | M61: =IF(Time!M20=1,-Funding!M27,IF(Time!M23=1,0,M49-M9)) -> -98.073619 | N61: =IF(Time!N20=1,-Funding!N27,IF(Time!N23=1,0,N49-N9)) -> -116.80869 | O61: =IF(Time!O20=1,-Funding!O27,IF(Time!O23=1,0,O49-O9)) -> 0 | P61: =IF(Time!P20=1,-Funding!P27,IF(Time!P23=1,0,P49-P9)) -> 0 | Q61: =IF(Time!Q20=1,-Funding!Q27,IF(Time!Q23=1,0,Q49-Q9)) -> 0 | ... DB61: =IF(Time!DB20=1,-Funding!DB27,IF(Time!DB23=1,0,DB49-DB9)) -> 0
D62: New equity cash flow (creditors 85%, state 15%) | E62: ARD m | G62: =SUM(J62:DB62) -> 2451.1356 | J62: =IF(Time!J23=1,J49,0)-Inputs!$F$171*Time!J35 -> 0 | K62: =IF(Time!K23=1,K49,0)-Inputs!$F$171*Time!K35 -> 0 | L62: =IF(Time!L23=1,L49,0)-Inputs!$F$171*Time!L35 -> 0 | M62: =IF(Time!M23=1,M49,0)-Inputs!$F$171*Time!M35 -> 0 | N62: =IF(Time!N23=1,N49,0)-Inputs!$F$171*Time!N35 -> 0 | O62: =IF(Time!O23=1,O49,0)-Inputs!$F$171*Time!O35 -> 0 | P62: =IF(Time!P23=1,P49,0)-Inputs!$F$171*Time!P35 -> 0 | Q62: =IF(Time!Q23=1,Q49,0)-Inputs!$F$171*Time!Q35 -> 0 | ... DB62: =IF(Time!DB23=1,DB49,0)-Inputs!$F$171*Time!DB35 -> 121.9839

Sheet Financials
D1: Case T: Merrick Link toll road PPP | Financials
D2: Units: ARD millions unless stated. Inputs blue on yellow; links green; calculations black.
D3: Period end | E3: date | J3: =Time!J8 -> 42185 | K3: =Time!K8 -> 42277 | L3: =Time!L8 -> 42369 | M3: =Time!M8 -> 42460 | N3: =Time!N8 -> 42551 | O3: =Time!O8 -> 42643 | P3: =Time!P8 -> 42735 | Q3: =Time!Q8 -> 42825 | ... DB3: =Time!DB8 -> 58256
D5: Income statement
D6: Book amortization of the concession asset | E6: ARD m | G6: =SUM(J6:DB6) -> 1915.5053 | J6: =IF(Time!J29>0,I7*Time!J25/Time!J29,0) -> 0 | K6: =IF(Time!K29>0,J7*Time!K25/Time!K29,0) -> 0 | L6: =IF(Time!L29>0,K7*Time!L25/Time!L29,0) -> 0 | M6: =IF(Time!M29>0,L7*Time!M25/Time!M29,0) -> 0 | N6: =IF(Time!N29>0,M7*Time!N25/Time!N29,0) -> 0 | O6: =IF(Time!O29>0,N7*Time!O25/Time!O29,0) -> 0 | P6: =IF(Time!P29>0,O7*Time!P25/Time!P29,0) -> 0 | Q6: =IF(Time!Q29>0,P7*Time!Q25/Time!Q29,0) -> 0 | ... DB6: =IF(Time!DB29>0,DA7*Time!DB25/Time!DB29,0) -> 18.814076
D7: Concession intangible: net book value | E7: ARD m | J7: =I7+Tax!J7-J6 -> 73.414541 | K7: =J7+Tax!K7-K6 -> 104.99317 | L7: =K7+Tax!L7-L6 -> 168.75744 | M7: =L7+Tax!M7-M6 -> 270.51178 | N7: =M7+Tax!N7-N6 -> 410.61034 | O7: =N7+Tax!O7-O6 -> 584.71411 | P7: =O7+Tax!P7-P6 -> 782.99668 | Q7: =P7+Tax!Q7-Q6 -> 994.62508 | ... DB7: =DA7+Tax!DB7-DB6 -> 0
D8: Restructuring gain (cancelled claims and swap termination) | E8: ARD m | G8: =SUM(J8:DB8) -> 144.43072 | J8: =Debt!J79+Debt!J75 -> 0 | K8: =Debt!K79+Debt!K75 -> 0 | L8: =Debt!L79+Debt!L75 -> 0 | M8: =Debt!M79+Debt!M75 -> 0 | N8: =Debt!N79+Debt!N75 -> 0 | O8: =Debt!O79+Debt!O75 -> 0 | P8: =Debt!P79+Debt!P75 -> 0 | Q8: =Debt!Q79+Debt!Q75 -> 0 | ... DB8: =Debt!DB79+Debt!DB75 -> 0
D9: Net income | E9: ARD m | G9: =SUM(J9:DB9) -> 1542.0749 | J9: =(Operations!J32-Operations!J36-Reserves!J22-J6-Debt!J64-Tax!J13-Tax!J14-Debt!J65-Tax!J23)*(1-Time!J20)+J8 -> 0 | K9: =(Operations!K32-Operations!K36-Reserves!K22-K6-Debt!K64-Tax!K13-Tax!K14-Debt!K65-Tax!K23)*(1-Time!K20)+K8 -> 0 | L9: =(Operations!L32-Operations!L36-Reserves!L22-L6-Debt!L64-Tax!L13-Tax!L14-Debt!L65-Tax!L23)*(1-Time!L20)+L8 -> 0 | M9: =(Operations!M32-Operations!M36-Reserves!M22-M6-Debt!M64-Tax!M13-Tax!M14-Debt!M65-Tax!M23)*(1-Time!M20)+M8 -> 0 | N9: =(Operations!N32-Operations!N36-Reserves!N22-N6-Debt!N64-Tax!N13-Tax!N14-Debt!N65-Tax!N23)*(1-Time!N20)+N8 -> 0 | O9: =(Operations!O32-Operations!O36-Reserves!O22-O6-Debt!O64-Tax!O13-Tax!O14-Debt!O65-Tax!O23)*(1-Time!O20)+O8 -> 0 | P9: =(Operations!P32-Operations!P36-Reserves!P22-P6-Debt!P64-Tax!P13-Tax!P14-Debt!P65-Tax!P23)*(1-Time!P20)+P8 -> 0 | Q9: =(Operations!Q32-Operations!Q36-Reserves!Q22-Q6-Debt!Q64-Tax!Q13-Tax!Q14-Debt!Q65-Tax!Q23)*(1-Time!Q20)+Q8 -> 0 | ... DB9: =(Operations!DB32-Operations!DB36-Reserves!DB22-DB6-Debt!DB64-Tax!DB13-Tax!DB14-Debt!DB65-Tax!DB23)*(1-Time!DB20)+DB8 -> -16.243973
D10: Balance sheet
D11: Total assets | E11: ARD m | J11: =J7+Operations!J41+Funding!J16+Reserves!J13+Reserves!J16+Reserves!J19+Reserves!J23+Reserves!J27+Reserves!J30+Waterfall!J51 -> 558.58613 | K11: =K7+Operations!K41+Funding!K16+Reserves!K13+Reserves!K16+Reserves!K19+Reserves!K23+Reserves!K27+Reserves!K30+Waterfall!K51 -> 590.16476 | L11: =L7+Operations!L41+Funding!L16+Reserves!L13+Reserves!L16+Reserves!L19+Reserves!L23+Reserves!L27+Reserves!L30+Waterfall!L51 -> 653.92904 | M11: =M7+Operations!M41+Funding!M16+Reserves!M13+Reserves!M16+Reserves!M19+Reserves!M23+Reserves!M27+Reserves!M30+Waterfall!M51 -> 755.68337 | N11: =N7+Operations!N41+Funding!N16+Reserves!N13+Reserves!N16+Reserves!N19+Reserves!N23+Reserves!N27+Reserves!N30+Waterfall!N51 -> 889.51674 | O11: =O7+Operations!O41+Funding!O16+Reserves!O13+Reserves!O16+Reserves!O19+Reserves!O23+Reserves!O27+Reserves!O30+Waterfall!O51 -> 1004.0239 | P11: =P7+Operations!P41+Funding!P16+Reserves!P13+Reserves!P16+Reserves!P19+Reserves!P23+Reserves!P27+Reserves!P30+Waterfall!P51 -> 1134.2358 | Q11: =Q7+Operations!Q41+Funding!Q16+Reserves!Q13+Reserves!Q16+Reserves!Q19+Reserves!Q23+Reserves!Q27+Reserves!Q30+Waterfall!Q51 -> 1273.1698 | ... DB11: =DB7+Operations!DB41+Funding!DB16+Reserves!DB13+Reserves!DB16+Reserves!DB19+Reserves!DB23+Reserves!DB27+Reserves!DB30+Waterfall!DB51 -> 0
D12: Total liabilities | E12: ARD m | J12: =Debt!J47+Debt!J54+Debt!J60+Debt!J61+Debt!J94+Debt!J102+Funding!J40+Operations!J42+Waterfall!J59+Reserves!J27 -> 547.57395 | K12: =Debt!K47+Debt!K54+Debt!K60+Debt!K61+Debt!K94+Debt!K102+Funding!K40+Operations!K42+Waterfall!K59+Reserves!K27 -> 574.65762 | L12: =Debt!L47+Debt!L54+Debt!L60+Debt!L61+Debt!L94+Debt!L102+Funding!L40+Operations!L42+Waterfall!L59+Reserves!L27 -> 629.20404 | M12: =Debt!M47+Debt!M54+Debt!M60+Debt!M61+Debt!M94+Debt!M102+Funding!M40+Operations!M42+Waterfall!M59+Reserves!M27 -> 716.24733 | N12: =Debt!N47+Debt!N54+Debt!N60+Debt!N61+Debt!N94+Debt!N102+Funding!N40+Operations!N42+Waterfall!N59+Reserves!N27 -> 832.5594 | O12: =Debt!O47+Debt!O54+Debt!O60+Debt!O61+Debt!O94+Debt!O102+Funding!O40+Operations!O42+Waterfall!O59+Reserves!O27 -> 947.0666 | P12: =Debt!P47+Debt!P54+Debt!P60+Debt!P61+Debt!P94+Debt!P102+Funding!P40+Operations!P42+Waterfall!P59+Reserves!P27 -> 1077.2784 | Q12: =Debt!Q47+Debt!Q54+Debt!Q60+Debt!Q61+Debt!Q94+Debt!Q102+Funding!Q40+Operations!Q42+Waterfall!Q59+Reserves!Q27 -> 1216.2124 | ... DB12: =Debt!DB47+Debt!DB54+Debt!DB60+Debt!DB61+Debt!DB94+Debt!DB102+Funding!DB40+Operations!DB42+Waterfall!DB59+Reserves!DB27 -> 3.3544723e-11
D13: Share capital | E13: ARD m | J13: =I13+Funding!J37+Debt!J78+Inputs!$F$171*Time!J35 -> 11.012181 | K13: =J13+Funding!K37+Debt!K78+Inputs!$F$171*Time!K35 -> 15.507144 | L13: =K13+Funding!L37+Debt!L78+Inputs!$F$171*Time!L35 -> 24.724997 | M13: =L13+Funding!M37+Debt!M78+Inputs!$F$171*Time!M35 -> 39.43604 | N13: =M13+Funding!N37+Debt!N78+Inputs!$F$171*Time!N35 -> 56.957344 | O13: =N13+Funding!O37+Debt!O78+Inputs!$F$171*Time!O35 -> 56.957344 | P13: =O13+Funding!P37+Debt!P78+Inputs!$F$171*Time!P35 -> 56.957344 | Q13: =P13+Funding!Q37+Debt!Q78+Inputs!$F$171*Time!Q35 -> 56.957344 | ... DB13: =DA13+Funding!DB37+Debt!DB78+Inputs!$F$171*Time!DB35 -> 257.86872
D14: Shareholder loans forgiven (equity reserve) | E14: ARD m | J14: =I14+Debt!J80 -> 0 | K14: =J14+Debt!K80 -> 0 | L14: =K14+Debt!L80 -> 0 | M14: =L14+Debt!M80 -> 0 | N14: =M14+Debt!N80 -> 0 | O14: =N14+Debt!O80 -> 0 | P14: =O14+Debt!P80 -> 0 | Q14: =P14+Debt!Q80 -> 0 | ... DB14: =DA14+Debt!DB80 -> 771.19202
D15: Retained earnings | E15: ARD m | J15: =I15+J9-Waterfall!J57 -> 0 | K15: =J15+K9-Waterfall!K57 -> 0 | L15: =K15+L9-Waterfall!L57 -> 0 | M15: =L15+M9-Waterfall!M57 -> 0 | N15: =M15+N9-Waterfall!N57 -> 0 | O15: =N15+O9-Waterfall!O57 -> 0 | P15: =O15+P9-Waterfall!P57 -> 0 | Q15: =P15+Q9-Waterfall!Q57 -> 0 | ... DB15: =DA15+DB9-Waterfall!DB57 -> -1029.0607
D16: Total equity | E16: ARD m | J16: =J13+J14+J15 -> 11.012181 | K16: =K13+K14+K15 -> 15.507144 | L16: =L13+L14+L15 -> 24.724997 | M16: =M13+M14+M15 -> 39.43604 | N16: =N13+N14+N15 -> 56.957344 | O16: =O13+O14+O15 -> 56.957344 | P16: =P13+P14+P15 -> 56.957344 | Q16: =Q13+Q14+Q15 -> 56.957344 | ... DB16: =DB13+DB14+DB15 -> -3.2514436e-11
D17: Balance check (assets less liabilities less equity) | E17: ARD m | J17: =ROUND(J11-J12-J16,6) -> 0 | K17: =ROUND(K11-K12-K16,6) -> 0 | L17: =ROUND(L11-L12-L16,6) -> 0 | M17: =ROUND(M11-M12-M16,6) -> 0 | N17: =ROUND(N11-N12-N16,6) -> 0 | O17: =ROUND(O11-O12-O16,6) -> 0 | P17: =ROUND(P11-P12-P16,6) -> 0 | Q17: =ROUND(Q11-Q12-Q16,6) -> 0 | ... DB17: =ROUND(DB11-DB12-DB16,6) -> 0

Sheet Ratios
D1: Case T: Merrick Link toll road PPP | Ratios
D2: Units: ARD millions unless stated. Inputs blue on yellow; links green; calculations black.
D3: Period end | E3: date | J3: =Time!J8 -> 42185 | K3: =Time!K8 -> 42277 | L3: =Time!L8 -> 42369 | M3: =Time!M8 -> 42460 | N3: =Time!N8 -> 42551 | O3: =Time!O8 -> 42643 | P3: =Time!P8 -> 42735 | Q3: =Time!Q8 -> 42825 | ... DB3: =Time!DB8 -> 58256
D5: Senior ratios (original debt, repayment periods)
D6: DSCR, repayment periods | E6: x | J6: =IF(AND(Time!J30=1,Debt!J68>Inputs!$F$9),Waterfall!J7/Debt!J68,"") | K6: =IF(AND(Time!K30=1,Debt!K68>Inputs!$F$9),Waterfall!K7/Debt!K68,"") | L6: =IF(AND(Time!L30=1,Debt!L68>Inputs!$F$9),Waterfall!L7/Debt!L68,"") | M6: =IF(AND(Time!M30=1,Debt!M68>Inputs!$F$9),Waterfall!M7/Debt!M68,"") | N6: =IF(AND(Time!N30=1,Debt!N68>Inputs!$F$9),Waterfall!N7/Debt!N68,"") | O6: =IF(AND(Time!O30=1,Debt!O68>Inputs!$F$9),Waterfall!O7/Debt!O68,"") | P6: =IF(AND(Time!P30=1,Debt!P68>Inputs!$F$9),Waterfall!P7/Debt!P68,"") | Q6: =IF(AND(Time!Q30=1,Debt!Q68>Inputs!$F$9),Waterfall!Q7/Debt!Q68,"") | ... DB6: =IF(AND(Time!DB30=1,Debt!DB68>Inputs!$F$9),Waterfall!DB7/Debt!DB68,"")
D7: Minimum DSCR, repayment periods | E7: x | F7: =IF(COUNT($J$6:$DB$6)>0,MIN($J$6:$DB$6),0) -> 0.75865837
D8: Average DSCR, repayment periods | E8: x | F8: =IF(COUNT($J$6:$DB$6)>0,AVERAGE($J$6:$DB$6),0) -> 2.8705404
D9: DSCR, ramp-up periods | E9: x | J9: =IF(AND(Time!J32=1,Debt!J68>Inputs!$F$9),Waterfall!J7/Debt!J68,"") | K9: =IF(AND(Time!K32=1,Debt!K68>Inputs!$F$9),Waterfall!K7/Debt!K68,"") | L9: =IF(AND(Time!L32=1,Debt!L68>Inputs!$F$9),Waterfall!L7/Debt!L68,"") | M9: =IF(AND(Time!M32=1,Debt!M68>Inputs!$F$9),Waterfall!M7/Debt!M68,"") | N9: =IF(AND(Time!N32=1,Debt!N68>Inputs!$F$9),Waterfall!N7/Debt!N68,"") | O9: =IF(AND(Time!O32=1,Debt!O68>Inputs!$F$9),Waterfall!O7/Debt!O68,"") | P9: =IF(AND(Time!P32=1,Debt!P68>Inputs!$F$9),Waterfall!P7/Debt!P68,"") | Q9: =IF(AND(Time!Q32=1,Debt!Q68>Inputs!$F$9),Waterfall!Q7/Debt!Q68,"") | ... DB9: =IF(AND(Time!DB32=1,Debt!DB68>Inputs!$F$9),Waterfall!DB7/Debt!DB68,"")
D10: Minimum DSCR, ramp-up | E10: x | F10: =IF(COUNT($J$9:$DB$9)>0,MIN($J$9:$DB$9),0) -> 0.46617243
D11: Senior plus NILO DSCR | E11: x | J11: =IF(AND(Time!J30=1,Time!J47=1,Debt!J68+Debt!J98+Debt!J99>Inputs!$F$9),Waterfall!J7/(Debt!J68+Debt!J98+Debt!J99),"") | K11: =IF(AND(Time!K30=1,Time!K47=1,Debt!K68+Debt!K98+Debt!K99>Inputs!$F$9),Waterfall!K7/(Debt!K68+Debt!K98+Debt!K99),"") | L11: =IF(AND(Time!L30=1,Time!L47=1,Debt!L68+Debt!L98+Debt!L99>Inputs!$F$9),Waterfall!L7/(Debt!L68+Debt!L98+Debt!L99),"") | M11: =IF(AND(Time!M30=1,Time!M47=1,Debt!M68+Debt!M98+Debt!M99>Inputs!$F$9),Waterfall!M7/(Debt!M68+Debt!M98+Debt!M99),"") | N11: =IF(AND(Time!N30=1,Time!N47=1,Debt!N68+Debt!N98+Debt!N99>Inputs!$F$9),Waterfall!N7/(Debt!N68+Debt!N98+Debt!N99),"") | O11: =IF(AND(Time!O30=1,Time!O47=1,Debt!O68+Debt!O98+Debt!O99>Inputs!$F$9),Waterfall!O7/(Debt!O68+Debt!O98+Debt!O99),"") | P11: =IF(AND(Time!P30=1,Time!P47=1,Debt!P68+Debt!P98+Debt!P99>Inputs!$F$9),Waterfall!P7/(Debt!P68+Debt!P98+Debt!P99),"") | Q11: =IF(AND(Time!Q30=1,Time!Q47=1,Debt!Q68+Debt!Q98+Debt!Q99>Inputs!$F$9),Waterfall!Q7/(Debt!Q68+Debt!Q98+Debt!Q99),"") | ... DB11: =IF(AND(Time!DB30=1,Time!DB47=1,Debt!DB68+Debt!DB98+Debt!DB99>Inputs!$F$9),Waterfall!DB7/(Debt!DB68+Debt!DB98+Debt!DB99),"")
D12: Minimum senior plus NILO DSCR | E12: x | F12: =IF(COUNT($J$11:$DB$11)>0,MIN($J$11:$DB$11),0) -> 1.8293126
D13: Discount factor from 2021-01-01 (all periods) | E13: factor | J13: =IF(Time!J8>=Inputs!$F$21,IF(I13>0,I13,1)/(1+Debt!J9),0) -> 0 | K13: =IF(Time!K8>=Inputs!$F$21,IF(J13>0,J13,1)/(1+Debt!K9),0) -> 0 | L13: =IF(Time!L8>=Inputs!$F$21,IF(K13>0,K13,1)/(1+Debt!L9),0) -> 0 | M13: =IF(Time!M8>=Inputs!$F$21,IF(L13>0,L13,1)/(1+Debt!M9),0) -> 0 | N13: =IF(Time!N8>=Inputs!$F$21,IF(M13>0,M13,1)/(1+Debt!N9),0) -> 0 | O13: =IF(Time!O8>=Inputs!$F$21,IF(N13>0,N13,1)/(1+Debt!O9),0) -> 0 | P13: =IF(Time!P8>=Inputs!$F$21,IF(O13>0,O13,1)/(1+Debt!P9),0) -> 0 | Q13: =IF(Time!Q8>=Inputs!$F$21,IF(P13>0,P13,1)/(1+Debt!Q9),0) -> 0 | ... DB13: =IF(Time!DB8>=Inputs!$F$21,IF(DA13>0,DA13,1)/(1+Debt!DB9),0) -> 0.11520678
D14: LLCR | E14: x | J14: =IF(AND(Time!J30=1,Debt!J42+Debt!J49>Inputs!$F$9),SUMPRODUCT(Waterfall!J$7:$DB$7,J$13:$DB$13,Time!J$30:$DB$30)/(J13*(1+Debt!J9))/(Debt!J42+Debt!J49),"") | K14: =IF(AND(Time!K30=1,Debt!K42+Debt!K49>Inputs!$F$9),SUMPRODUCT(Waterfall!K$7:$DB$7,K$13:$DB$13,Time!K$30:$DB$30)/(K13*(1+Debt!K9))/(Debt!K42+Debt!K49),"") | L14: =IF(AND(Time!L30=1,Debt!L42+Debt!L49>Inputs!$F$9),SUMPRODUCT(Waterfall!L$7:$DB$7,L$13:$DB$13,Time!L$30:$DB$30)/(L13*(1+Debt!L9))/(Debt!L42+Debt!L49),"") | M14: =IF(AND(Time!M30=1,Debt!M42+Debt!M49>Inputs!$F$9),SUMPRODUCT(Waterfall!M$7:$DB$7,M$13:$DB$13,Time!M$30:$DB$30)/(M13*(1+Debt!M9))/(Debt!M42+Debt!M49),"") | N14: =IF(AND(Time!N30=1,Debt!N42+Debt!N49>Inputs!$F$9),SUMPRODUCT(Waterfall!N$7:$DB$7,N$13:$DB$13,Time!N$30:$DB$30)/(N13*(1+Debt!N9))/(Debt!N42+Debt!N49),"") | O14: =IF(AND(Time!O30=1,Debt!O42+Debt!O49>Inputs!$F$9),SUMPRODUCT(Waterfall!O$7:$DB$7,O$13:$DB$13,Time!O$30:$DB$30)/(O13*(1+Debt!O9))/(Debt!O42+Debt!O49),"") | P14: =IF(AND(Time!P30=1,Debt!P42+Debt!P49>Inputs!$F$9),SUMPRODUCT(Waterfall!P$7:$DB$7,P$13:$DB$13,Time!P$30:$DB$30)/(P13*(1+Debt!P9))/(Debt!P42+Debt!P49),"") | Q14: =IF(AND(Time!Q30=1,Debt!Q42+Debt!Q49>Inputs!$F$9),SUMPRODUCT(Waterfall!Q$7:$DB$7,Q$13:$DB$13,Time!Q$30:$DB$30)/(Q13*(1+Debt!Q9))/(Debt!Q42+Debt!Q49),"") | ... DB14: =IF(AND(Time!DB30=1,Debt!DB42+Debt!DB49>Inputs!$F$9),SUMPRODUCT(Waterfall!DB$7:$DB$7,DB$13:$DB$13,Time!DB$30:$DB$30)/(DB13*(1+Debt!DB9))/(Debt!DB42+Debt!DB49),"")
D15: LLCR at the first repayment period | E15: x | F15: =SUMPRODUCT($J$14:$DB$14,Time!$J$31:$DB$31) -> 1.385034
D16: Minimum LLCR | E16: x | F16: =IF(COUNT($J$14:$DB$14)>0,MIN($J$14:$DB$14),0) -> 1.385034
D17: PLCR at the first repayment period | E17: x | F17: =IFERROR(SUMPRODUCT(Waterfall!$J$7:$DB$7,$J$13:$DB$13,Time!$J$26:$DB$26)/SUMPRODUCT(Debt!$J$42:$DB$42+Debt!$J$49:$DB$49,Time!$J$31:$DB$31),0) -> 1.7137495
D18: Notes DSCR | E18: x | J18: =IF(AND(Time!J37=1,Debt!J68>Inputs!$F$9),Waterfall!J7/Debt!J68,"") | K18: =IF(AND(Time!K37=1,Debt!K68>Inputs!$F$9),Waterfall!K7/Debt!K68,"") | L18: =IF(AND(Time!L37=1,Debt!L68>Inputs!$F$9),Waterfall!L7/Debt!L68,"") | M18: =IF(AND(Time!M37=1,Debt!M68>Inputs!$F$9),Waterfall!M7/Debt!M68,"") | N18: =IF(AND(Time!N37=1,Debt!N68>Inputs!$F$9),Waterfall!N7/Debt!N68,"") | O18: =IF(AND(Time!O37=1,Debt!O68>Inputs!$F$9),Waterfall!O7/Debt!O68,"") | P18: =IF(AND(Time!P37=1,Debt!P68>Inputs!$F$9),Waterfall!P7/Debt!P68,"") | Q18: =IF(AND(Time!Q37=1,Debt!Q68>Inputs!$F$9),Waterfall!Q7/Debt!Q68,"") | ... DB18: =IF(AND(Time!DB37=1,Debt!DB68>Inputs!$F$9),Waterfall!DB7/Debt!DB68,"")
D19: Minimum notes DSCR | E19: x | F19: =IF(COUNT($J$18:$DB$18)>0,MIN($J$18:$DB$18),0) -> 1.9513098
D20: Average notes DSCR | E20: x | F20: =IF(COUNT($J$18:$DB$18)>0,AVERAGE($J$18:$DB$18),0) -> 3.2840018
D21: Lock-up periods after the first repayment date | E21: # | F21: =SUMPRODUCT(Waterfall!$J$48:$DB$48,Time!$J$26:$DB$26,1-Time!$J$33:$DB$33) -> 6
D22: DSRA drawn in total | E22: ARD m | F22: =SUM(Waterfall!$J$23:$DB$23) -> 17.147382
D23: Senior debt, % of funding net of contribution | E23: % | F23: =IFERROR(Debt!$F$26/Funding!$F$25,0) -> 0.51108942
D24: NILO, % of funding net of contribution | E24: % | F24: =IFERROR(Debt!$F$28/Funding!$F$25,0) -> 0.26891058
D25: Equity, % of funding net of contribution | E25: % | F25: =IFERROR(Debt!$F$29/Funding!$F$25,0) -> 0.22
D26: NILO, % of eligible costs | E26: % | F26: =IFERROR(Debt!$F$28/Funding!$F$24,0) -> 0.23052493

Sheet Returns
D1: Case T: Merrick Link toll road PPP | Returns
D2: Units: ARD millions unless stated. Inputs blue on yellow; links green; calculations black.
D3: Period end | E3: date | J3: =Time!J8 -> 42185 | K3: =Time!K8 -> 42277 | L3: =Time!L8 -> 42369 | M3: =Time!M8 -> 42460 | N3: =Time!N8 -> 42551 | O3: =Time!O8 -> 42643 | P3: =Time!P8 -> 42735 | Q3: =Time!Q8 -> 42825 | ... DB3: =Time!DB8 -> 58256
D5: Original sponsors' equity
D6: Equity cash flow | E6: ARD m | G6: =SUM(J6:DB6) -> -424.71562 | J6: =Waterfall!J61 -> -73.414541 | K6: =Waterfall!K61 -> -29.966422 | L6: =Waterfall!L61 -> -61.452349 | M6: =Waterfall!M61 -> -98.073619 | N6: =Waterfall!N61 -> -116.80869 | O6: =Waterfall!O61 -> 0 | P6: =Waterfall!P61 -> 0 | Q6: =Waterfall!Q61 -> 0 | ... DB6: =Waterfall!DB61 -> 0
D7: Equity IRR (XIRR on period-end dates) | E7: % | F7: =IFERROR(XIRR($J$6:$DB$6,Time!$J$8:$DB$8),"n/a") -> n/a
D8: Equity NPV at 11.4% at financial close | E8: ARD m | F8: =SUMPRODUCT($J$6:$DB$6/(1+Inputs!$F$90)^((Time!$J$8:$DB$8-Inputs!$F$13)/Inputs!$F$45)) -> -375.12703
D9: Equity invested (incl. sponsor support) | E9: ARD m | F9: =SUM(Funding!$J$27:$DB$27)+SUM(Waterfall!$J$9:$DB$9) -> 424.71562
D10: Project cash flow (post-tax, before financing)
D11: Project cash flow | E11: ARD m | G11: =SUM(J11:DB11) -> 3186.4014 | J11: =-Construction!J13+Funding!J39+Waterfall!J7*(1-Time!J20)-Operations!J45 -> -55.351416 | K11: =-Construction!K13+Funding!K39+Waterfall!K7*(1-Time!K20)-Operations!K45 -> -25.701277 | L11: =-Construction!L13+Funding!L39+Waterfall!L7*(1-Time!L20)-Operations!L45 -> -57.187205 | M11: =-Construction!M13+Funding!M39+Waterfall!M7*(1-Time!M20)-Operations!M45 -> -93.790892 | N11: =-Construction!N13+Funding!N39+Waterfall!N7*(1-Time!N20)-Operations!N45 -> -129.91074 | O11: =-Construction!O13+Funding!O39+Waterfall!O7*(1-Time!O20)-Operations!O45 -> -161.00849 | P11: =-Construction!P13+Funding!P39+Waterfall!P7*(1-Time!P20)-Operations!P45 -> -183.60753 | Q11: =-Construction!Q13+Funding!Q39+Waterfall!Q7*(1-Time!Q20)-Operations!Q45 -> -195.4016 | ... DB11: =-Construction!DB13+Funding!DB39+Waterfall!DB7*(1-Time!DB20)-Operations!DB45 -> 121.9839
D12: Project IRR, post-tax | E12: % | F12: =IFERROR(XIRR($J$11:$DB$11,Time!$J$8:$DB$8),"n/a") -> 0.04541178
D13: Project cash flow before tax | E13: ARD m | G13: =SUM(J13:DB13) -> 4170.2411 | J13: =J11+Tax!J23 -> -55.351416 | K13: =K11+Tax!K23 -> -25.701277 | L13: =L11+Tax!L23 -> -57.187205 | M13: =M11+Tax!M23 -> -93.790892 | N13: =N11+Tax!N23 -> -129.91074 | O13: =O11+Tax!O23 -> -161.00849 | P13: =P11+Tax!P23 -> -183.60753 | Q13: =Q11+Tax!Q23 -> -195.4016 | ... DB13: =DB11+Tax!DB23 -> 121.9839
D14: Project IRR, pre-tax | E14: % | F14: =IFERROR(XIRR($J$13:$DB$13,Time!$J$8:$DB$8),"n/a") -> 0.051938212
D15: Termination values at 2022-06-30
D16: NPV at 11.4% of distributions after 2022-06-30 (authority-default equity compensation when run on the bid base) | E16: ARD m | F16: =SUMPRODUCT((Time!$J$8:$DB$8>Inputs!$F$36)*Waterfall!$J$49:$DB$49/(1+Inputs!$F$90)^((Time!$J$8:$DB$8-Inputs!$F$36)/Inputs!$F$45)) -> 308.96858
D17: Pre-tax unlevered cash flow (retender valuation) | E17: ARD m | G17: =SUM(J17:DB17) -> 5824.1411 | J17: =Operations!J32-Operations!J44-Operations!J36-Reserves!J22+Operations!J31 -> 0 | K17: =Operations!K32-Operations!K44-Operations!K36-Reserves!K22+Operations!K31 -> 0 | L17: =Operations!L32-Operations!L44-Operations!L36-Reserves!L22+Operations!L31 -> 0 | M17: =Operations!M32-Operations!M44-Operations!M36-Reserves!M22+Operations!M31 -> 0 | N17: =Operations!N32-Operations!N44-Operations!N36-Reserves!N22+Operations!N31 -> 0 | O17: =Operations!O32-Operations!O44-Operations!O36-Reserves!O22+Operations!O31 -> 0 | P17: =Operations!P32-Operations!P44-Operations!P36-Reserves!P22+Operations!P31 -> 0 | Q17: =Operations!Q32-Operations!Q44-Operations!Q36-Reserves!Q22+Operations!Q31 -> 0 | ... DB17: =Operations!DB32-Operations!DB44-Operations!DB36-Reserves!DB22+Operations!DB31 -> 11.035868
D18: Estimated fair value at 2022-06-30 (run in Scenario 6) | E18: ARD m | F18: =SUMPRODUCT((Time!$J$8:$DB$8>Inputs!$F$36)*$J$17:$DB$17/(1+Inputs!$F$180)^((Time!$J$8:$DB$8-Inputs!$F$36)/Inputs!$F$45)) -> 1155.5107
D19: Concessionaire-default compensation (fair value less retendering costs) | E19: ARD m | F19: =$F$18-Inputs!$F$181 -> 1143.0107
D20: Senior claims at 2022-06-30 (principal plus arrears) | E20: ARD m | F20: =SUMPRODUCT((Time!$J$8:$DB$8=Inputs!$F$36)*(Debt!$J$47:$DB$47+Debt!$J$54:$DB$54+Debt!$J$60:$DB$60+Debt!$J$61:$DB$61)) -> 859.91747
D21: NILO outstanding at 2022-06-30 | E21: ARD m | F21: =SUMPRODUCT((Time!$J$8:$DB$8=Inputs!$F$36)*Debt!$J$102:$DB$102) -> 538.6915
D22: Equity contributed less distributions to 2022-06-30 | E22: ARD m | F22: =SUMPRODUCT((Time!$J$8:$DB$8<=Inputs!$F$36)*(Funding!$J$27:$DB$27+Waterfall!$J$9:$DB$9-Waterfall!$J$49:$DB$49)) -> 424.71562
D23: Prolonged force majeure compensation | E23: ARD m | F23: =$F$20+$F$21+$F$22 -> 1823.3246
D24: Restructuring valuation (run in Scenario 5)
D25: New equity value at the plan rate (14.0%) | E25: ARD m | F25: =SUMPRODUCT((Time!$J$8:$DB$8>Inputs!$F$20)*Waterfall!$J$49:$DB$49/(1+Inputs!$F$178)^((Time!$J$8:$DB$8-Inputs!$F$20)/Inputs!$F$45)) -> 275.95987
D26: Flag_NotesRepaid | E26: flag | J26: =IF(AND(Inputs!$F$215=1,Time!J8>Inputs!$F$20,Debt!J93<=Inputs!$F$9),1,0) -> 0 | K26: =IF(AND(Inputs!$F$215=1,Time!K8>Inputs!$F$20,Debt!K93<=Inputs!$F$9),1,0) -> 0 | L26: =IF(AND(Inputs!$F$215=1,Time!L8>Inputs!$F$20,Debt!L93<=Inputs!$F$9),1,0) -> 0 | M26: =IF(AND(Inputs!$F$215=1,Time!M8>Inputs!$F$20,Debt!M93<=Inputs!$F$9),1,0) -> 0 | N26: =IF(AND(Inputs!$F$215=1,Time!N8>Inputs!$F$20,Debt!N93<=Inputs!$F$9),1,0) -> 0 | O26: =IF(AND(Inputs!$F$215=1,Time!O8>Inputs!$F$20,Debt!O93<=Inputs!$F$9),1,0) -> 0 | P26: =IF(AND(Inputs!$F$215=1,Time!P8>Inputs!$F$20,Debt!P93<=Inputs!$F$9),1,0) -> 0 | Q26: =IF(AND(Inputs!$F$215=1,Time!Q8>Inputs!$F$20,Debt!Q93<=Inputs!$F$9),1,0) -> 0 | ... DB26: =IF(AND(Inputs!$F$215=1,Time!DB8>Inputs!$F$20,Debt!DB93<=Inputs!$F$9),1,0) -> 1
D27: Warrants: 3% of distributions after the notes are repaid | E27: ARD m | F27: =Inputs!$F$175*SUMPRODUCT($J$26:$DB$26*Waterfall!$J$49:$DB$49/(1+Inputs!$F$178)^((Time!$J$8:$DB$8-Inputs!$F$20)/Inputs!$F$45)) -> 0.61677949
D28: Equity value to senior creditors (85%) | E28: ARD m | F28: =Inputs!$F$169*($F$25-$F$27) -> 234.04163
D29: Equity value to the state (15%) | E29: ARD m | F29: =Inputs!$F$170*($F$25-$F$27) -> 41.301464
D30: State money in excess of plan value (implied capital grant) | E30: ARD m | F30: =Inputs!$F$171-$F$29 -> 78.698536
D31: Payments to noteholders | E31: ARD m | G31: =SUM(J31:DB31) -> 1104.7865 | J31: =IF(Time!J23=1,Waterfall!J16+Waterfall!J22+Waterfall!J38,0) -> 0 | K31: =IF(Time!K23=1,Waterfall!K16+Waterfall!K22+Waterfall!K38,0) -> 0 | L31: =IF(Time!L23=1,Waterfall!L16+Waterfall!L22+Waterfall!L38,0) -> 0 | M31: =IF(Time!M23=1,Waterfall!M16+Waterfall!M22+Waterfall!M38,0) -> 0 | N31: =IF(Time!N23=1,Waterfall!N16+Waterfall!N22+Waterfall!N38,0) -> 0 | O31: =IF(Time!O23=1,Waterfall!O16+Waterfall!O22+Waterfall!O38,0) -> 0 | P31: =IF(Time!P23=1,Waterfall!P16+Waterfall!P22+Waterfall!P38,0) -> 0 | Q31: =IF(Time!Q23=1,Waterfall!Q16+Waterfall!Q22+Waterfall!Q38,0) -> 0 | ... DB31: =IF(Time!DB23=1,Waterfall!DB16+Waterfall!DB22+Waterfall!DB38,0) -> 0
D32: Notes market value at the 7.50% yield | E32: ARD m | F32: =SUMPRODUCT((Time!$J$8:$DB$8>Inputs!$F$20)*$J$31:$DB$31/(1+Inputs!$F$179)^((Time!$J$8:$DB$8-Inputs!$F$20)/Inputs!$F$45)) -> 499.79799
D33: Senior claims net of set-off | E33: ARD m | F33: =SUM(Debt!$J$76:$DB$76) -> 809.11381
D34: Senior recovery (notes at market plus equity at plan value) | E34: % | F34: =IF($F$33>0,($F$32+$F$28)/$F$33,0) -> 0.90696711
D35: Senior recovery with notes at par | E35: % | F35: =IF($F$33>0,(Debt!$F$81+$F$28)/$F$33,0) -> 1.0492567
D36: NILO claim at 2023-12-31 | E36: ARD m | F36: =SUMPRODUCT(Time!$J$35:$DB$35,Debt!$J$102:$DB$102) -> 563.8675
D37: PV of NILO receipts at 3.06% | E37: ARD m | F37: =SUMPRODUCT((Time!$J$8:$DB$8>Inputs!$F$20)*Waterfall!$J$35:$DB$35/(1+Inputs!$F$118)^((Time!$J$8:$DB$8-Inputs!$F$20)/Inputs!$F$45)) -> 491.27769
D38: NILO recovery in PV terms | E38: % | F38: =IF($F$36>0,$F$37/$F$36,0) -> 0.87126442
D39: Public sector comparator and value for money (PV at 2012-12-31)
D40: Risk-adjusted PSC | E40: ARD m | F40: =Inputs!$F$185+Inputs!$F$186+Inputs!$F$187+Inputs!$F$188+Inputs!$F$189+Inputs!$F$190+Inputs!$F$191 -> 384.2
D41: Raw PSC (before risk and competitive neutrality) | E41: ARD m | F41: =Inputs!$F$185+Inputs!$F$186+Inputs!$F$187 -> 143.4
D42: Discount factor, contribution date to PV date | E42: factor | F42: =(1+Inputs!$F$184)^(-(Inputs!$F$42-Inputs!$F$41)/Inputs!$F$45) -> 0.66096569
D43: PPP reference project cost | E43: ARD m | F43: =Inputs!$F$192*$F$42+Inputs!$F$193+Inputs!$F$194 -> 345.39593
D44: PPP cost at the winning bid | E44: ARD m | F44: =Inputs!$F$81*$F$42+Inputs!$F$193+Inputs!$F$194 -> 264.36154
D45: Value for money, reference | E45: ARD m | F45: =$F$40-$F$43 -> 38.804066
D46: Value for money, reference, % of risk-adjusted PSC | E46: % | F46: =$F$45/$F$40 -> 0.10099965
D47: Value for money, winning bid | E47: ARD m | F47: =$F$40-$F$44 -> 119.83846
D48: Value for money, winning bid, % of risk-adjusted PSC | E48: % | F48: =$F$47/$F$40 -> 0.31191687

Sheet Checks
D1: Case T: Merrick Link toll road PPP | Checks
D5: Integrity checks (0 = pass)
D6: Sources equal uses in every construction period | E6: ARD m | F6: =ROUND(SUMPRODUCT(ABS(Funding!$J$42:$DB$42)),6) -> 0
D7: Total sources at close equal total uses | E7: ARD m | F7: =ROUND(Debt!$F$29+Debt!$F$26+Debt!$F$28+Inputs!$F$227-Funding!$F$24,6) -> 0
D8: Equity drawn equals equity commitment | E8: ARD m | F8: =ROUND(SUM(Funding!$J$27:$DB$27)-Debt!$F$29,6) -> 0
D9: Bond escrow fully used at completion | E9: ARD m | F9: =ROUND(SUMPRODUCT(Funding!$J$16:$DB$16,Time!$J$21:$DB$21),6) -> 0
D10: Bridge repaid at opening | E10: ARD m | F10: =ROUND(SUMPRODUCT(ABS(Funding!$J$40:$DB$40)*Time!$J$26:$DB$26),6) -> 0
D11: Balance sheet balances | E11: ARD m | F11: =ROUND(SUMPRODUCT(ABS(Financials!$J$17:$DB$17)),6) -> 0
D12: Live senior schedule repays by 2048 (Scenario 2) | E12: ARD m | F12: =IF(Debt!$F$24=1,ROUND(SUMPRODUCT(Debt!$J$36:$DB$36,Time!$J$30:$DB$30*(Time!$J$8:$DB$8=Inputs!$F$22)),6),0) -> 0
D13: Live sizing equals locked financing (Scenario 2, bid contribution) | E13: ARD m | F13: =IF(AND(Debt!$F$24=1,Inputs!$F$7=1),ROUND(ABS(Debt!$F$22-Inputs!$F$269)+SUMPRODUCT(ABS(Debt!$J$35:$DB$35-Inputs!$J$272:$DB$272))+SUMPRODUCT(ABS(Debt!$J$38:$DB$38-Inputs!$J$273:$DB$273))+SUMPRODUCT(ABS(Debt!$J$111:$DB$111-Inputs!$J$274:$DB$274)),3),0) -> 0
D14: Live notes schedule equals locked (Scenario 5) | E14: ARD m | F14: =IF(Debt!$F$25=1,ROUND(SUMPRODUCT(ABS(Debt!$J$88:$DB$88-Inputs!$J$277:$DB$277))+SUMPRODUCT(ABS(Debt!$J$111:$DB$111-Inputs!$J$278:$DB$278)),3),0) -> 0
D15: Senior debt repaid by concession expiry | E15: ARD m | F15: =ROUND(SUMPRODUCT((Debt!$J$47:$DB$47+Debt!$J$54:$DB$54+Debt!$J$94:$DB$94)*Time!$J$28:$DB$28),6) -> 0
D16: NILO repaid by concession expiry | E16: ARD m | F16: =ROUND(SUMPRODUCT(Debt!$J$102:$DB$102*Time!$J$28:$DB$28),6) -> 0
D17: Reserves never negative | E17: ARD m | F17: =ROUND(-MIN(0,MIN(Reserves!$J$13:$DB$13),MIN(Reserves!$J$19:$DB$19),MIN(Reserves!$J$23:$DB$23),MIN(Reserves!$J$16:$DB$16),MIN(Reserves!$J$30:$DB$30)),6) -> 0
D18: Ramp-up account fully used | E18: ARD m | F18: =ROUND(SUMPRODUCT(Reserves!$J$16:$DB$16,Time!$J$31:$DB$31),6) -> 0
D19: Cash account never negative | E19: ARD m | F19: =ROUND(-MIN(0,MIN(Waterfall!$J$51:$DB$51)),6) -> 0
D20: NILO within 33% of eligible costs | E20: ARD m | F20: =ROUND(MAX(0,Debt!$F$28-Inputs!$F$120*Funding!$F$24),6) -> 0
D21: Equity at least 22% of funding net of contribution | E21: ARD m | F21: =ROUND(MAX(0,Inputs!$F$87*Funding!$F$25-Debt!$F$29),6) -> 0
D22: Restructuring: notes plus converted plus cancelled equal net claims | E22: ARD m | F22: =ROUND(SUM(Debt!$J$77:$DB$77)+SUM(Debt!$J$78:$DB$78)+SUM(Debt!$J$79:$DB$79)-SUM(Debt!$J$76:$DB$76),6) -> 0
D23: All checks | E23: ARD m | F23: =ABS($F$6)+ABS($F$7)+ABS($F$8)+ABS($F$9)+ABS($F$10)+ABS($F$11)+ABS($F$12)+ABS($F$13)+ABS($F$14)+ABS($F$15)+ABS($F$16)+ABS($F$17)+ABS($F$18)+ABS($F$19)+ABS($F$20)+ABS($F$21)+ABS($F$22) -> 0

Sheet Outputs
D1: Case T: Merrick Link toll road PPP | Outputs
D5: Dashboard (selected scenario)
D6: Scenario | E6: # | F6: =Inputs!$F$6 -> 4
D7: Total uses | E7: ARD m | F7: =Funding!$F$24 -> 2013.3801
D8: Funding requirement net of contribution | E8: ARD m | F8: =Funding!$F$25 -> 1725.9801
D9: Senior debt (bank plus bonds) | E9: ARD m | F9: =Debt!$F$26 -> 882.13017
D10: Bank mini-perm | E10: ARD m | F10: =Funding!$F$6 -> 396.95858
D11: Revenue bonds | E11: ARD m | F11: =Funding!$F$7 -> 485.17159
D12: NILO loan | E12: ARD m | F12: =Debt!$F$28 -> 464.13432
D13: Equity | E13: ARD m | F13: =Debt!$F$29 -> 379.71562
D14: Binding sizing constraint | E14: # | F14: =Debt!$F$23 -> 4
D15: Senior sculpting divisor | E15: x | F15: =Debt!$F$37 -> 1.5
D16: Senior IDC net of escrow income plus bridge interest | E16: ARD m | F16: =SUM(Funding!$J$11:$DB$11)+SUM(Funding!$J$13:$DB$13)-SUM(Funding!$J$15:$DB$15)+SUM(Funding!$J$19:$DB$19) -> 113.03737
D17: Upfront and commitment fees | E17: ARD m | F17: =SUM(Funding!$J$10:$DB$10)+SUM(Funding!$J$12:$DB$12) -> 24.829167
D18: DSRA initial funding | E18: ARD m | F18: =SUM(Funding!$J$21:$DB$21) -> 13.887642
D19: Ramp-up interest account | E19: ARD m | F19: =SUM(Funding!$J$22:$DB$22) -> 20.225926
D20: Minimum senior DSCR (repayment periods) | E20: x | F20: =Ratios!$F$7 -> 0.75865837
D21: Average senior DSCR | E21: x | F21: =Ratios!$F$8 -> 2.8705404
D22: Minimum senior plus NILO DSCR | E22: x | F22: =Ratios!$F$12 -> 1.8293126
D23: LLCR at first repayment | E23: x | F23: =Ratios!$F$15 -> 1.385034
D24: PLCR at first repayment | E24: x | F24: =Ratios!$F$17 -> 1.7137495
D25: Equity IRR | E25: % | F25: =Returns!$F$7 -> n/a
D26: Equity NPV at 11.4% | E26: ARD m | F26: =Returns!$F$8 -> -375.12703
D27: Project IRR post-tax | E27: % | F27: =Returns!$F$12 -> 0.04541178
D28: Value for money, winning bid | E28: ARD m | F28: =Returns!$F$47 -> 119.83846
D29: All checks (0 = pass) | E29: ARD m | F29: =Checks!$F$23 -> 0
