Workbook

Sheet Inputs
A1: Llano Pardo Solar (fictional; Illustrative): Chapter 13 practice files
A2: Inputs: Chapter 1 Exhibits 1.4 and 1.6 (u01 Section 1.A.3 to 1.A.6); USD thousand
A3: Column D label, E unit, F value or scalar, G row total; first period in column J. Inputs: blue on yellow. Links: green. Checks: 0 when passing.
D6: Check tolerance | E6: USD k | F6: 0.5
D7: P50 energy, 2018 (operating year 1) | E7: MWh | F7: 134724
D8: Degradation (compounding) | E8: % pa | F8: 0.005
D9: PPA tariff (flat nominal) | E9: USD/MWh | F9: 58.2
D10: Operating costs, 2018 | E10: USD k | F10: 1085
D11: Operating cost escalation | E11: % pa | F11: 0.02
D12: Tax depreciation (62,721 / 20) | E12: USD k pa | F12: 3136
D13: Corporate income tax | E13: % | F13: 0.25
D14: Senior debt at COD | E14: USD k | F14: 48809
D15: Interest rate (fixed all-in, on the opening balance) | E15: % pa | F15: 0.054
D16: First operating year | E16: year | F16: 2018
D17: Last repayment year | E17: year | F17: 2035
D18: k: CFADS / debt service, pasted from Goal Seek (closing debt 2035 = 0 by changing k) | E18: x | F18: 1.3807397

Sheet Calc
A1: Llano Pardo Solar (fictional; Illustrative): Chapter 13 practice files
A2: Calc: annual projection 2018 to 2037 (columns J to AC); sculpted debt service = CFADS / k
A3: Column D label, E unit, F value or scalar, G row total; first period in column J. Inputs: blue on yellow. Links: green. Checks: 0 when passing.
J5: 2018 | K5: 2019 | L5: 2020 | M5: 2021 | N5: 2022 | O5: 2023 | P5: 2024 | Q5: 2025 | R5: 2026 | S5: 2027 | T5: 2028 | U5: 2029 | V5: 2030 | W5: 2031 | X5: 2032 | Y5: 2033 | Z5: 2034 | AA5: 2035 | AB5: 2036 | AC5: 2037
D6: Year counter | E6: index | J6: =I6+1 | K6: =J6+1 | L6: =K6+1 | M6: =L6+1 | N6: =M6+1 | O6: =N6+1 | P6: =O6+1 | Q6: =P6+1 | ... AC6: =AB6+1
D7: Year | E7: year | J7: =Inputs!$F$16+J6-1 | K7: =Inputs!$F$16+K6-1 | L7: =Inputs!$F$16+L6-1 | M7: =Inputs!$F$16+M6-1 | N7: =Inputs!$F$16+N6-1 | O7: =Inputs!$F$16+O6-1 | P7: =Inputs!$F$16+P6-1 | Q7: =Inputs!$F$16+Q6-1 | ... AC7: =Inputs!$F$16+AC6-1
D8: Operating year | E8: OY | J8: =J7-Inputs!$F$16+1 | K8: =K7-Inputs!$F$16+1 | L8: =L7-Inputs!$F$16+1 | M8: =M7-Inputs!$F$16+1 | N8: =N7-Inputs!$F$16+1 | O8: =O7-Inputs!$F$16+1 | P8: =P7-Inputs!$F$16+1 | Q8: =Q7-Inputs!$F$16+1 | ... AC8: =AC7-Inputs!$F$16+1
D9: Flag_Repayment (2018 to 2035) | E9: flag | J9: =IF(J7<=Inputs!$F$17,1,0) | K9: =IF(K7<=Inputs!$F$17,1,0) | L9: =IF(L7<=Inputs!$F$17,1,0) | M9: =IF(M7<=Inputs!$F$17,1,0) | N9: =IF(N7<=Inputs!$F$17,1,0) | O9: =IF(O7<=Inputs!$F$17,1,0) | P9: =IF(P7<=Inputs!$F$17,1,0) | Q9: =IF(Q7<=Inputs!$F$17,1,0) | ... AC9: =IF(AC7<=Inputs!$F$17,1,0)
D10: Energy | E10: MWh | G10: =SUM(J10:AC10) | J10: =Inputs!$F$7*(1-Inputs!$F$8)^(J8-1) | K10: =Inputs!$F$7*(1-Inputs!$F$8)^(K8-1) | L10: =Inputs!$F$7*(1-Inputs!$F$8)^(L8-1) | M10: =Inputs!$F$7*(1-Inputs!$F$8)^(M8-1) | N10: =Inputs!$F$7*(1-Inputs!$F$8)^(N8-1) | O10: =Inputs!$F$7*(1-Inputs!$F$8)^(O8-1) | P10: =Inputs!$F$7*(1-Inputs!$F$8)^(P8-1) | Q10: =Inputs!$F$7*(1-Inputs!$F$8)^(Q8-1) | ... AC10: =Inputs!$F$7*(1-Inputs!$F$8)^(AC8-1)
D11: Revenue | E11: USD k | G11: =SUM(J11:AC11) | J11: =J10*Inputs!$F$9/1000 | K11: =K10*Inputs!$F$9/1000 | L11: =L10*Inputs!$F$9/1000 | M11: =M10*Inputs!$F$9/1000 | N11: =N10*Inputs!$F$9/1000 | O11: =O10*Inputs!$F$9/1000 | P11: =P10*Inputs!$F$9/1000 | Q11: =Q10*Inputs!$F$9/1000 | ... AC11: =AC10*Inputs!$F$9/1000
D12: Operating costs | E12: USD k | G12: =SUM(J12:AC12) | J12: =Inputs!$F$10*(1+Inputs!$F$11)^(J8-1) | K12: =Inputs!$F$10*(1+Inputs!$F$11)^(K8-1) | L12: =Inputs!$F$10*(1+Inputs!$F$11)^(L8-1) | M12: =Inputs!$F$10*(1+Inputs!$F$11)^(M8-1) | N12: =Inputs!$F$10*(1+Inputs!$F$11)^(N8-1) | O12: =Inputs!$F$10*(1+Inputs!$F$11)^(O8-1) | P12: =Inputs!$F$10*(1+Inputs!$F$11)^(P8-1) | Q12: =Inputs!$F$10*(1+Inputs!$F$11)^(Q8-1) | ... AC12: =Inputs!$F$10*(1+Inputs!$F$11)^(AC8-1)
D13: Debt, opening | E13: USD k | J13: =IF(J8=1,Inputs!$F$14,I21) | K13: =IF(K8=1,Inputs!$F$14,J21) | L13: =IF(L8=1,Inputs!$F$14,K21) | M13: =IF(M8=1,Inputs!$F$14,L21) | N13: =IF(N8=1,Inputs!$F$14,M21) | O13: =IF(O8=1,Inputs!$F$14,N21) | P13: =IF(P8=1,Inputs!$F$14,O21) | Q13: =IF(Q8=1,Inputs!$F$14,P21) | ... AC13: =IF(AC8=1,Inputs!$F$14,AB21)
D14: Interest | E14: USD k | G14: =SUM(J14:AC14) | J14: =J13*Inputs!$F$15 | K14: =K13*Inputs!$F$15 | L14: =L13*Inputs!$F$15 | M14: =M13*Inputs!$F$15 | N14: =N13*Inputs!$F$15 | O14: =O13*Inputs!$F$15 | P14: =P13*Inputs!$F$15 | Q14: =Q13*Inputs!$F$15 | ... AC14: =AC13*Inputs!$F$15
D15: Taxable income | E15: USD k | G15: =SUM(J15:AC15) | J15: =J11-J12-Inputs!$F$12-J14 | K15: =K11-K12-Inputs!$F$12-K14 | L15: =L11-L12-Inputs!$F$12-L14 | M15: =M11-M12-Inputs!$F$12-M14 | N15: =N11-N12-Inputs!$F$12-N14 | O15: =O11-O12-Inputs!$F$12-O14 | P15: =P11-P12-Inputs!$F$12-P14 | Q15: =Q11-Q12-Inputs!$F$12-Q14 | ... AC15: =AC11-AC12-Inputs!$F$12-AC14
D16: Tax (none negative in the base case; checked) | E16: USD k | G16: =SUM(J16:AC16) | J16: =MAX(0,J15)*Inputs!$F$13 | K16: =MAX(0,K15)*Inputs!$F$13 | L16: =MAX(0,L15)*Inputs!$F$13 | M16: =MAX(0,M15)*Inputs!$F$13 | N16: =MAX(0,N15)*Inputs!$F$13 | O16: =MAX(0,O15)*Inputs!$F$13 | P16: =MAX(0,P15)*Inputs!$F$13 | Q16: =MAX(0,Q15)*Inputs!$F$13 | ... AC16: =MAX(0,AC15)*Inputs!$F$13
D17: CFADS | E17: USD k | G17: =SUM(J17:AC17) | J17: =J11-J12-J16 | K17: =K11-K12-K16 | L17: =L11-L12-L16 | M17: =M11-M12-M16 | N17: =N11-N12-N16 | O17: =O11-O12-O16 | P17: =P11-P12-P16 | Q17: =Q11-Q12-Q16 | ... AC17: =AC11-AC12-AC16
D18: Debt service = CFADS / k in repayment years | E18: USD k | G18: =SUM(J18:AC18) | J18: =J9*J17/Inputs!$F$18 | K18: =K9*K17/Inputs!$F$18 | L18: =L9*L17/Inputs!$F$18 | M18: =M9*M17/Inputs!$F$18 | N18: =N9*N17/Inputs!$F$18 | O18: =O9*O17/Inputs!$F$18 | P18: =P9*P17/Inputs!$F$18 | Q18: =Q9*Q17/Inputs!$F$18 | ... AC18: =AC9*AC17/Inputs!$F$18
D19: Principal | E19: USD k | G19: =SUM(J19:AC19) | J19: =J18-J14 | K19: =K18-K14 | L19: =L18-L14 | M19: =M18-M14 | N19: =N18-N14 | O19: =O18-O14 | P19: =P18-P14 | Q19: =Q18-Q14 | ... AC19: =AC18-AC14
D20: DSCR | E20: x | J20: =IF(J18>0,J17/J18,0) | K20: =IF(K18>0,K17/K18,0) | L20: =IF(L18>0,L17/L18,0) | M20: =IF(M18>0,M17/M18,0) | N20: =IF(N18>0,N17/N18,0) | O20: =IF(O18>0,O17/O18,0) | P20: =IF(P18>0,P17/P18,0) | Q20: =IF(Q18>0,Q17/Q18,0) | ... AC20: =IF(AC18>0,AC17/AC18,0)
D21: Debt, closing | E21: USD k | J21: =J13-J19 | K21: =K13-K19 | L21: =L13-L19 | M21: =M13-M19 | N21: =N13-N19 | O21: =O13-O19 | P21: =P13-P19 | Q21: =Q13-Q19 | ... AC21: =AC13-AC19
D22: Closing debt in the last repayment year | E22: USD k | F22: =INDEX(J21:AC21,1,MATCH(Inputs!$F$17,J7:AC7,0))

Sheet Checks
A1: Llano Pardo Solar (fictional; Illustrative): Chapter 13 practice files
A2: Checks: 0 when passing
A3: Column D label, E unit, F value or scalar, G row total; first period in column J. Inputs: blue on yellow. Links: green. Checks: 0 when passing.
D7: Goal-seek k repays the debt by the last repayment year | E7: check | F7: =--(ABS(Calc!F22)>Inputs!$F$6)
D8: Principal sums to the debt at COD | E8: check | F8: =--(ABS(Calc!G19-Inputs!$F$14)>Inputs!$F$6)
D9: No negative taxable income (no losses to carry forward) | E9: check | F9: =--(MIN(Calc!J15:AC15)<0)
D10: No debt after the last repayment year | E10: check | F10: =--(SUMPRODUCT((Calc!J7:AC7>Inputs!$F$17)*ABS(Calc!J21:AC21))>Inputs!$F$6)
D12: Master check (0 = all pass) | F12: =SUM(F7:F10)
