Workbook

Sheet Cover
A1: Case P: Belanou Combined Cycle Power Project, Republic of Kessara
A2: Case P companion model
A3: Units in column E; constants in column F; row totals in column G; first period in column J. Inputs: blue on yellow. Links from other sheets: green.
D4: Label | E4: Unit | F4: Constant | G4: Total
D5: Companion model for Chapters 39-45. Python mirror: model/case_p.py (source of truth).
D6: Select the scenario on the Inputs sheet (cell named Scenario):
D7: 1: FC base
D8: 2: FC banking
D9: 3: FC downside
D10: 4: Sens: availability -3 points
D11: 5: Sens: heat rate +2%
D12: 6: Sens: fixed opex +10%
D13: 7: Sens: capex +10% funded pro rata
D14: 8: Sens: COD delay 6 months, no LDs
D15: 9: Sens: base rate +200 bps (unhedged)
D16: 10: Sens: KCR devaluation 40%, 90-day lag
... D21: 15: Actual history
D22: Master check (0 = all pass) | F22: =Checks!$F$19 -> 0
D23: Circularity: none. IDC/fee/premium/DSRA gross-up is solved in closed form on the Funding sheet
D24: (balance = alpha + beta x T; T = alpha/(g - beta)). Sculpting with tax uses the contractual
D25: repayment profile on Inputs; the Debt sheet recomputes the sculpted profile live and the
D26: Checks sheet reports the difference (Python iterates the profile to convergence, tolerance USD 1,000).
D27: Sheets: Cover, Inputs, Time, Construction, Operations, Tax, Funding, Debt, Reserves, Waterfall, Financials, Ratios, Returns, Checks, Outputs
D28: Sign convention: costs stored positive and subtracted explicitly.
D29: Monte Carlo (Inputs F311): the draw table is pasted from case_p.py (seed 20180717, P-F42 parameters); the per-run results beside it are pasted from the mirror with a stamp (no native data table: one could not be generated and verified without macros).

Sheet Inputs
A1: Case P: Belanou Combined Cycle Power Project, Republic of Kessara
A2: Inputs: scenario selector, assumptions, contract terms
A3: Units in column E; constants in column F; row totals in column G; first period in column J. Inputs: blue on yellow. Links from other sheets: green.
D4: Label | E4: Unit | F4: Constant | G4: Total
D5: Scenario table: columns J-X = scenarios 1-15; semiannual rows: columns = periods; annual rows: columns = years 2015+ | J5: 2018H2 | K5: 2019H1 | L5: 2019H2 | M5: 2020H1 | N5: 2020H2 | O5: 2021H1 | P5: 2021H2 | Q5: 2022H1 | R5: 2022H2 | S5: 2023H1 | T5: 2023H2 | U5: 2024H1 | V5: 2024H2 | W5: 2025H1 | X5: 2025H2 | Y5: 2026H1 | Z5: 2026H2 | AA5: 2027H1 | AB5: 2027H2 | AC5: 2028H1 | AD5: 2028H2 | AE5: 2029H1 | AF5: 2029H2 | AG5: 2030H1 | AH5: 2030H2 | AI5: 2031H1 | AJ5: 2031H2 | AK5: 2032H1 | AL5: 2032H2 | AM5: 2033H1 | AN5: 2033H2 | AO5: 2034H1 | AP5: 2034H2 | AQ5: 2035H1 | AR5: 2035H2 | AS5: 2036H1 | AT5: 2036H2 | AU5: 2037H1 | AV5: 2037H2 | AW5: 2038H1 | AX5: 2038H2 | AY5: 2039H1 | AZ5: 2039H2 | BA5: 2040H1 | BB5: 2040H2 | BC5: 2041H1 | BD5: 2041H2 | BE5: 2042H1 | BF5: 2042H2 | BG5: 2043H1 | BH5: 2043H2 | BI5: 2044H1 | BJ5: 2044H2 | BK5: 2045H1 | BL5: 2045H2 | BM5: 2046H1 | BN5: 2046H2
B7: Scenario control
D8: Scenario selector (1-15, see table below) | E8: index | F8: 6
B9: Live scenario parameters (selected from the scenario table)
D10: Macro path (1 FC forward, 2 actual history, 3 COD re-forecast) [table] | E10: code | J10: 1 | K10: 1 | L10: 1 | M10: 1 | N10: 1 | O10: 1 | P10: 1 | Q10: 1 | R10: 1 | S10: 1 | T10: 1 | U10: 1 | V10: 1 | W10: 3 | X10: 2
D11: Construction case (1 FC budget, 2 actual) [table] | E11: code | J11: 1 | K11: 1 | L11: 1 | M11: 1 | N11: 1 | O11: 1 | P11: 1 | Q11: 1 | R11: 1 | S11: 1 | T11: 1 | U11: 1 | V11: 1 | W11: 2 | X11: 2
D12: COD delay (sensitivity) [table] | E12: months | J12: 0 | K12: 0 | L12: 0 | M12: 0 | N12: 0 | O12: 0 | P12: 0 | Q12: 6 | R12: 0 | S12: 0 | T12: 0 | U12: 0 | V12: 0 | W12: 0 | X12: 0
D13: Capex factor [table] | E13: factor | J13: 1 | K13: 1 | L13: 1 | M13: 1 | N13: 1 | O13: 1 | P13: 1.1 | Q13: 1 | R13: 1 | S13: 1 | T13: 1 | U13: 1 | V13: 1 | W13: 1 | X13: 1
D14: Availability adjustment [table] | E14: points | J14: 0 | K14: 0 | L14: -6.5 | M14: -3 | N14: 0 | O14: 0 | P14: 0 | Q14: 0 | R14: 0 | S14: 0 | T14: 0 | U14: 0 | V14: 0 | W14: 0 | X14: 0
D15: Dispatch factor when available [table] | E15: % | J15: 76.5 | K15: 72 | L15: 76.5 | M15: 76.5 | N15: 76.5 | O15: 76.5 | P15: 76.5 | Q15: 76.5 | R15: 76.5 | S15: 76.5 | T15: 76.5 | U15: 50 | V15: 76.5 | W15: 76.5 | X15: 76.5
D16: Plant heat rate factor [table] | E16: factor | J16: 1 | K16: 1 | L16: 1.015 | M16: 1 | N16: 1.02 | O16: 1 | P16: 1 | Q16: 1 | R16: 1 | S16: 1 | T16: 1 | U16: 1 | V16: 1 | W16: 1 | X16: 1
D17: Fixed opex factor [table] | E17: factor | J17: 1 | K17: 1 | L17: 1.1 | M17: 1 | N17: 1 | O17: 1.1 | P17: 1 | Q17: 1 | R17: 1 | S17: 1 | T17: 1 | U17: 1 | V17: 1 | W17: 1 | X17: 1
D18: Gas price factor [table] | E18: factor | J18: 1 | K18: 1 | L18: 1 | M18: 1 | N18: 1 | O18: 1 | P18: 1 | Q18: 1 | R18: 1 | S18: 1 | T18: 1 | U18: 1 | V18: 1.3 | W18: 1 | X18: 1
D19: Base rate shift from 2022H1 [table] | E19: % | J19: 0 | K19: 0 | L19: 0 | M19: 0 | N19: 0 | O19: 0 | P19: 0 | Q19: 0 | R19: 2 | S19: 0 | T19: 0 | U19: 0 | V19: 0 | W19: 0 | X19: 0
D20: KCR devaluation from 2022H1 [table] | E20: fraction | J20: 0 | K20: 0 | L20: 0 | M20: 0 | N20: 0 | O20: 0 | P20: 0 | Q20: 0 | R20: 0 | S20: 0.4 | T20: 0 | U20: 0 | V20: 0 | W20: 0 | X20: 0
D21: Extra days on SEKA capacity/VOM payments, 2022H1-2022H2 [table] | E21: days | J21: 0 | K21: 0 | L21: 0 | M21: 0 | N21: 0 | O21: 0 | P21: 0 | Q21: 0 | R21: 0 | S21: 90 | T21: 120 | U21: 0 | V21: 0 | W21: 0 | X21: 0
... D32: Actual 2022 dispatch path (1 = on) [table] | E32: flag | J32: 0 | K32: 0 | L32: 0 | M32: 0 | N32: 0 | O32: 0 | P32: 0 | Q32: 0 | R32: 0 | S32: 0 | T32: 0 | U32: 0 | V32: 0 | W32: 0 | X32: 1
D33: Macro path (1 FC forward, 2 actual history, 3 COD re-forecast) | E33: code | F33: =INDEX($J$10:$X$10,1,Scenario) -> 1
D34: Construction case (1 FC budget, 2 actual) | E34: code | F34: =INDEX($J$11:$X$11,1,Scenario) -> 1
D35: COD delay (sensitivity) | E35: months | F35: =INDEX($J$12:$X$12,1,Scenario) -> 0
D36: Capex factor | E36: factor | F36: =INDEX($J$13:$X$13,1,Scenario) -> 1
D37: Availability adjustment | E37: points | F37: =INDEX($J$14:$X$14,1,Scenario) -> 0
D38: Dispatch factor when available | E38: % | F38: =INDEX($J$15:$X$15,1,Scenario) -> 76.5
D39: Plant heat rate factor | E39: factor | F39: =INDEX($J$16:$X$16,1,Scenario) -> 1
D40: Fixed opex factor | E40: factor | F40: =INDEX($J$17:$X$17,1,Scenario) -> 1.1
D41: Gas price factor | E41: factor | F41: =INDEX($J$18:$X$18,1,Scenario) -> 1
D42: Base rate shift from 2022H1 | E42: % | F42: =INDEX($J$19:$X$19,1,Scenario) -> 0
D43: KCR devaluation from 2022H1 | E43: fraction | F43: =INDEX($J$20:$X$20,1,Scenario) -> 0
D44: Extra days on SEKA capacity/VOM payments, 2022H1-2022H2 | E44: days | F44: =INDEX($J$21:$X$21,1,Scenario) -> 0
D45: Offtaker crisis events (1 = on) | E45: flag | F45: =INDEX($J$22:$X$22,1,Scenario) -> 0
D46: Insurance market step-up from 2022H2 (1 = on) | E46: flag | F46: =INDEX($J$23:$X$23,1,Scenario) -> 0
D47: Repayment profile (1 FC contract, 2 COD re-sculpted) | E47: code | F47: =INDEX($J$24:$X$24,1,Scenario) -> 1
D48: Performance LD prepayment June 2022 (1 = on) | E48: flag | F48: =INDEX($J$25:$X$25,1,Scenario) -> 0
D49: Waiver and amendment 2023 (1 = on) | E49: flag | F49: =INDEX($J$26:$X$26,1,Scenario) -> 0
D50: 2025 bond refinancing (1 = on) | E50: flag | F50: =INDEX($J$27:$X$27,1,Scenario) -> 0
D51: Funding mode (1 committed amounts, 2 re-grossed pro rata) | E51: code | F51: =INDEX($J$28:$X$28,1,Scenario) -> 1
D52: Soft mini-perm sweep (1 = on) | E52: flag | F52: =INDEX($J$29:$X$29,1,Scenario) -> 1
D53: Shareholder loan share of equity | E53: fraction | F53: =INDEX($J$30:$X$30,1,Scenario) -> 0.8
D54: Capital charge factor | E54: factor | F54: =INDEX($J$31:$X$31,1,Scenario) -> 1
D55: Actual 2022 dispatch path (1 = on) | E55: flag | F55: =INDEX($J$32:$X$32,1,Scenario) -> 0
B56: Capital cost (USD m unless stated)
D57: EPC contract price | E57: USD m | F57: 571.84
D58: of which offshore portion | E58: USD m | F58: 489.17
D59: of which onshore portion | E59: USD m | F59: 82.67
D60: Onshore portion fixed in KCR at | E60: KCR/USD | F60: 519.4
D61: Owner's costs | E61: USD m | F61: 46.18
D62: Insurance during construction | E62: USD m | F62: 7.62
D63: Development costs reimbursed at FC | E63: USD m | F63: 21.43
D64: Development fee at FC | E64: USD m | F64: 11.2
D65: Lenders' advisors and legal | E65: USD m | F65: 8.97
D66: Contingency | E66: USD m | F66: 38.4
D67: Initial working capital (spares, fuel) | E67: USD m | F67: 5.35
D68: LNTP paid February 2018 (equity credit at FC) | E68: USD m | F68: 14.2
... D73: Policy rate, FC expectation | E73: % | F73: 13.5
B74: Senior debt terms
D75: ECA-covered tranche share | E75: fraction | F75: 0.3
D76: ABDB A-loan share | E76: fraction | F76: 0.22
D77: ABDB B-loan share | E77: fraction | F77: 0.1
D78: Commercial tranche share | E78: fraction | F78: 0.38
D79: ECA margin | E79: % | F79: 1.35
D80: A-loan margin | E80: % | F80: 3.65
D81: B-loan margin | E81: % | F81: 3.4
D82: Commercial margin to 2025 | E82: % | F82: 4.1
D83: Commercial margin 2026-2029 | E83: % | F83: 4.6
D84: Commercial margin from 2030 | E84: % | F84: 5.1
D85: ECA commitment fee | E85: % pa | F85: 0.45
D86: A-loan commitment fee | E86: % pa | F86: 0.75
... D111: Soft mini-perm sweep share (from 2027) | E111: fraction | F111: 0.5
B112: Contract terms fixed at financial close (from the FC base sizing run)
D113: Senior debt commitment (total, 4 tranches) | E113: USD m | F113: 629.94967
D114: Equity commitment (base, incl. LNTP) | E114: USD m | F114: 224.60222
B115: Plant and PPA
D116: Contracted capacity (FC) | E116: MW | F116: 588.4
D117: Contracted capacity after tests | E117: MW | F117: 581.9
D118: Guaranteed net heat rate | E118: kJ/kWh | F118: 6261
D119: Tested net heat rate | E119: kJ/kWh | F119: 6286
D120: PPA contracted heat rate | E120: kJ/kWh | F120: 6323
D121: Contracted HR degradation allowance | E121: % pa | F121: 0.1
D122: Average part-load penalty | E122: % | F122: 2.3
D123: HHV/LHV ratio | E123: factor | F123: 1.108
D124: kJ per MMBtu | E124: kJ | F124: 1055056
D125: Output degradation, non-recoverable | E125: % pa | F125: 0.15
D126: Output degradation, recoverable average | E126: % | F126: 1
D127: Heat-rate degradation, non-recoverable | E127: % pa | F127: 0.12
... D140: VOM US CPI share | E140: fraction | F140: 0.7
B141: Fuel and transport
D142: GSA gas price 2018 | E142: USD/MMBtu | F142: 5.86
D143: GSA escalation | E143: % pa | F143: 2
D144: Daily contract quantity | E144: MMBtu/d | F144: 72400
D145: Take-or-pay level | E145: fraction | F145: 0.8
D146: GTA reserved capacity | E146: MMBtu/d | F146: 96500
D147: GTA reservation charge 2018 | E147: USD/MMBtu | F147: 0.62
D148: GTA commodity charge 2018 | E148: USD/MMBtu | F148: 0.19
D149: GTA escalation | E149: % pa | F149: 1.5
B150: Operating costs (2018 prices)
D151: O&M fixed fee | E151: USD m pa | F151: 7.92
...

Sheet Time
A1: Case P: Belanou Combined Cycle Power Project, Republic of Kessara
A2: Time: semiannual operating timeline (monthly timeline on the Construction sheet)
A3: Units in column E; constants in column F; row totals in column G; first period in column J. Inputs: blue on yellow. Links from other sheets: green.
D4: Label | E4: Unit | F4: Constant | G4: Total
D5: Period ending | J5: 2018H2 | K5: 2019H1 | L5: 2019H2 | M5: 2020H1 | N5: 2020H2 | O5: 2021H1 | P5: 2021H2 | Q5: 2022H1 | R5: 2022H2 | S5: 2023H1 | T5: 2023H2 | U5: 2024H1 | V5: 2024H2 | W5: 2025H1 | X5: 2025H2 | Y5: 2026H1 | Z5: 2026H2 | AA5: 2027H1 | AB5: 2027H2 | AC5: 2028H1 | AD5: 2028H2 | AE5: 2029H1 | AF5: 2029H2 | AG5: 2030H1 | AH5: 2030H2 | AI5: 2031H1 | AJ5: 2031H2 | AK5: 2032H1 | AL5: 2032H2 | AM5: 2033H1 | AN5: 2033H2 | AO5: 2034H1 | AP5: 2034H2 | AQ5: 2035H1 | AR5: 2035H2 | AS5: 2036H1 | AT5: 2036H2 | AU5: 2037H1 | AV5: 2037H2 | AW5: 2038H1 | AX5: 2038H2 | AY5: 2039H1 | AZ5: 2039H2 | BA5: 2040H1 | BB5: 2040H2 | BC5: 2041H1 | BD5: 2041H2 | BE5: 2042H1 | BF5: 2042H2 | BG5: 2043H1 | BH5: 2043H2 | BI5: 2044H1 | BJ5: 2044H2 | BK5: 2045H1 | BL5: 2045H2 | BM5: 2046H1 | BN5: 2046H2
B7: Key dates (scenario-dependent)
D8: Commercial operation date | E8: date | F8: =IF(Inputs!$F$34<>1,Inputs!$F$191,EDATE(Inputs!$F$190,Inputs!$F$35)) -> 44317
D9: PPA term | E9: months | F9: =Inputs!$F$210*12 -> 300
D10: PPA expiry | E10: date | F10: =EDATE(Time!$F$8,Time!$F$9)-1 -> 53447
D11: Construction months (NTP to COD) | E11: months | F11: =(YEAR(Time!$F$8)-YEAR(Inputs!$F$188))*12+MONTH(Time!$F$8)-MONTH(Inputs!$F$188) -> 33
D12: Period containing COD (period number) | E12: index | F12: =MATCH($F$8,$J$22:$BN$22,1) -> 6
D13: First debt service period | E13: index | F13: =Time!$F$12+1 -> 7
D14: Last month of the funding period (month number) | E14: index | F14: =MATCH(INDEX($J$23:$BN$23,1,$F$12),Construction!$J$10:$BJ$10,0) -> 35
D15: Last operating period (period number) | E15: index | F15: =SUMPRODUCT($J$37:$BN$37,$J$20:$BN$20) -> 56
D16: FC FX drift per year (Kessara / US CPI expectations; Monte Carlo draw when active) | E16: factor | F16: =IF(Inputs!$F$312=1,INDEX(Inputs!$AL$313:$AL$1312,Inputs!$F$311),(1+Inputs!$F$213/100)/(1+Inputs!$F$214/100)) -> 1.0518591
D17: Refinancing period (period number) | E17: index | F17: =MATCH(Inputs!$F$205,$J$23:$BN$23,0) -> 14
D18: Deferral period (period number) | E18: index | F18: =MATCH(Inputs!$F$200,$J$23:$BN$23,0) -> 11
B19: Semiannual timeline
D20: Period number | E20: index | J20: =I20+1 -> 1 | K20: =J20+1 -> 2 | L20: =K20+1 -> 3 | M20: =L20+1 -> 4 | N20: =M20+1 -> 5 | O20: =N20+1 -> 6 | P20: =O20+1 -> 7 | Q20: =P20+1 -> 8 | ... BN20: =BM20+1 -> 57
D21: Months per period | E21: months | J21: =Inputs!$F$226 -> 6 | K21: =Inputs!$F$226 -> 6 | L21: =Inputs!$F$226 -> 6 | M21: =Inputs!$F$226 -> 6 | N21: =Inputs!$F$226 -> 6 | O21: =Inputs!$F$226 -> 6 | P21: =Inputs!$F$226 -> 6 | Q21: =Inputs!$F$226 -> 6 | ... BN21: =Inputs!$F$226 -> 6
D22: Period start | E22: date | J22: =IF(J20=1,Inputs!$F$189,EDATE(I22,J21)) -> 43282 | K22: =IF(K20=1,Inputs!$F$189,EDATE(J22,K21)) -> 43466 | L22: =IF(L20=1,Inputs!$F$189,EDATE(K22,L21)) -> 43647 | M22: =IF(M20=1,Inputs!$F$189,EDATE(L22,M21)) -> 43831 | N22: =IF(N20=1,Inputs!$F$189,EDATE(M22,N21)) -> 44013 | O22: =IF(O20=1,Inputs!$F$189,EDATE(N22,O21)) -> 44197 | P22: =IF(P20=1,Inputs!$F$189,EDATE(O22,P21)) -> 44378 | Q22: =IF(Q20=1,Inputs!$F$189,EDATE(P22,Q21)) -> 44562 | ... BN22: =IF(BN20=1,Inputs!$F$189,EDATE(BM22,BN21)) -> 53509
D23: Period end | E23: date | J23: =EOMONTH(J22,J21-1) -> 43465 | K23: =EOMONTH(K22,K21-1) -> 43646 | L23: =EOMONTH(L22,L21-1) -> 43830 | M23: =EOMONTH(M22,M21-1) -> 44012 | N23: =EOMONTH(N22,N21-1) -> 44196 | O23: =EOMONTH(O22,O21-1) -> 44377 | P23: =EOMONTH(P22,P21-1) -> 44561 | Q23: =EOMONTH(Q22,Q21-1) -> 44742 | ... BN23: =EOMONTH(BN22,BN21-1) -> 53692
D24: Year fraction 30/360 (months / 12) | E24: factor | J24: =J21/12 -> 0.5 | K24: =K21/12 -> 0.5 | L24: =L21/12 -> 0.5 | M24: =M21/12 -> 0.5 | N24: =N21/12 -> 0.5 | O24: =O21/12 -> 0.5 | P24: =P21/12 -> 0.5 | Q24: =Q21/12 -> 0.5 | ... BN24: =BN21/12 -> 0.5
D25: Days in period | E25: days | J25: =J23-J22+1 -> 184 | K25: =K23-K22+1 -> 181 | L25: =L23-L22+1 -> 184 | M25: =M23-M22+1 -> 182 | N25: =N23-N22+1 -> 184 | O25: =O23-O22+1 -> 181 | P25: =P23-P22+1 -> 184 | Q25: =Q23-Q22+1 -> 181 | ... BN25: =BN23-BN22+1 -> 184
D26: Calendar year | E26: year | J26: =YEAR(J22) -> 2018 | K26: =YEAR(K22) -> 2019 | L26: =YEAR(L22) -> 2019 | M26: =YEAR(M22) -> 2020 | N26: =YEAR(N22) -> 2020 | O26: =YEAR(O22) -> 2021 | P26: =YEAR(P22) -> 2021 | Q26: =YEAR(Q22) -> 2022 | ... BN26: =YEAR(BN22) -> 2046
D27: Flag_FirstHalf (Jan-Jun) | E27: flag | J27: =IF(MONTH(J22)=1,1,0) -> 0 | K27: =IF(MONTH(K22)=1,1,0) -> 1 | L27: =IF(MONTH(L22)=1,1,0) -> 0 | M27: =IF(MONTH(M22)=1,1,0) -> 1 | N27: =IF(MONTH(N22)=1,1,0) -> 0 | O27: =IF(MONTH(O22)=1,1,0) -> 1 | P27: =IF(MONTH(P22)=1,1,0) -> 0 | Q27: =IF(MONTH(Q22)=1,1,0) -> 1 | ... BN27: =IF(MONTH(BN22)=1,1,0) -> 0
D28: Operations start in period | E28: date | J28: =MAX(J22,$F$8) -> 44317 | K28: =MAX(K22,$F$8) -> 44317 | L28: =MAX(L22,$F$8) -> 44317 | M28: =MAX(M22,$F$8) -> 44317 | N28: =MAX(N22,$F$8) -> 44317 | O28: =MAX(O22,$F$8) -> 44317 | P28: =MAX(P22,$F$8) -> 44378 | Q28: =MAX(Q22,$F$8) -> 44562 | ... BN28: =MAX(BN22,$F$8) -> 53509
D29: Operations end in period | E29: date | J29: =MIN(J23,$F$10) -> 43465 | K29: =MIN(K23,$F$10) -> 43646 | L29: =MIN(L23,$F$10) -> 43830 | M29: =MIN(M23,$F$10) -> 44012 | N29: =MIN(N23,$F$10) -> 44196 | O29: =MIN(O23,$F$10) -> 44377 | P29: =MIN(P23,$F$10) -> 44561 | Q29: =MIN(Q23,$F$10) -> 44742 | ... BN29: =MIN(BN23,$F$10) -> 53447
D30: Operating months in period | E30: months | J30: =IF(J29>=J28,(YEAR(J29)-YEAR(J28))*12+MONTH(J29)-MONTH(J28)+1,0) -> 0 | K30: =IF(K29>=K28,(YEAR(K29)-YEAR(K28))*12+MONTH(K29)-MONTH(K28)+1,0) -> 0 | L30: =IF(L29>=L28,(YEAR(L29)-YEAR(L28))*12+MONTH(L29)-MONTH(L28)+1,0) -> 0 | M30: =IF(M29>=M28,(YEAR(M29)-YEAR(M28))*12+MONTH(M29)-MONTH(M28)+1,0) -> 0 | N30: =IF(N29>=N28,(YEAR(N29)-YEAR(N28))*12+MONTH(N29)-MONTH(N28)+1,0) -> 0 | O30: =IF(O29>=O28,(YEAR(O29)-YEAR(O28))*12+MONTH(O29)-MONTH(O28)+1,0) -> 2 | P30: =IF(P29>=P28,(YEAR(P29)-YEAR(P28))*12+MONTH(P29)-MONTH(P28)+1,0) -> 6 | Q30: =IF(Q29>=Q28,(YEAR(Q29)-YEAR(Q28))*12+MONTH(Q29)-MONTH(Q28)+1,0) -> 6 | ... BN30: =IF(BN29>=BN28,(YEAR(BN29)-YEAR(BN28))*12+MONTH(BN29)-MONTH(BN28)+1,0) -> 0
D31: Operating days in period | E31: days | J31: =IF(J29>=J28,J29-J28+1,0) -> 0 | K31: =IF(K29>=K28,K29-K28+1,0) -> 0 | L31: =IF(L29>=L28,L29-L28+1,0) -> 0 | M31: =IF(M29>=M28,M29-M28+1,0) -> 0 | N31: =IF(N29>=N28,N29-N28+1,0) -> 0 | O31: =IF(O29>=O28,O29-O28+1,0) -> 61 | P31: =IF(P29>=P28,P29-P28+1,0) -> 184 | Q31: =IF(Q29>=Q28,Q29-Q28+1,0) -> 181 | ... BN31: =IF(BN29>=BN28,BN29-BN28+1,0) -> 0
D32: Operating months elapsed at period start | E32: months | J32: =MIN(MAX((YEAR(J22)-YEAR($F$8))*12+MONTH(J22)-MONTH($F$8),0),$F$9) -> 0 | K32: =MIN(MAX((YEAR(K22)-YEAR($F$8))*12+MONTH(K22)-MONTH($F$8),0),$F$9) -> 0 | L32: =MIN(MAX((YEAR(L22)-YEAR($F$8))*12+MONTH(L22)-MONTH($F$8),0),$F$9) -> 0 | M32: =MIN(MAX((YEAR(M22)-YEAR($F$8))*12+MONTH(M22)-MONTH($F$8),0),$F$9) -> 0 | N32: =MIN(MAX((YEAR(N22)-YEAR($F$8))*12+MONTH(N22)-MONTH($F$8),0),$F$9) -> 0 | O32: =MIN(MAX((YEAR(O22)-YEAR($F$8))*12+MONTH(O22)-MONTH($F$8),0),$F$9) -> 0 | P32: =MIN(MAX((YEAR(P22)-YEAR($F$8))*12+MONTH(P22)-MONTH($F$8),0),$F$9) -> 2 | Q32: =MIN(MAX((YEAR(Q22)-YEAR($F$8))*12+MONTH(Q22)-MONTH($F$8),0),$F$9) -> 8 | ... BN32: =MIN(MAX((YEAR(BN22)-YEAR($F$8))*12+MONTH(BN22)-MONTH($F$8),0),$F$9) -> 300
D33: Operating months elapsed at period end | E33: months | J33: =J32+J30 -> 0 | K33: =K32+K30 -> 0 | L33: =L32+L30 -> 0 | M33: =M32+M30 -> 0 | N33: =N32+N30 -> 0 | O33: =O32+O30 -> 2 | P33: =P32+P30 -> 8 | Q33: =Q32+Q30 -> 14 | ... BN33: =BN32+BN30 -> 300
D34: Flag_CODPeriod | E34: flag | J34: =IF(J20=$F$12,1,0) -> 0 | K34: =IF(K20=$F$12,1,0) -> 0 | L34: =IF(L20=$F$12,1,0) -> 0 | M34: =IF(M20=$F$12,1,0) -> 0 | N34: =IF(N20=$F$12,1,0) -> 0 | O34: =IF(O20=$F$12,1,0) -> 1 | P34: =IF(P20=$F$12,1,0) -> 0 | Q34: =IF(Q20=$F$12,1,0) -> 0 | ... BN34: =IF(BN20=$F$12,1,0) -> 0
D35: Flag_DebtService (after COD period) | E35: flag | J35: =IF(J20>$F$12,1,0) -> 0 | K35: =IF(K20>$F$12,1,0) -> 0 | L35: =IF(L20>$F$12,1,0) -> 0 | M35: =IF(M20>$F$12,1,0) -> 0 | N35: =IF(N20>$F$12,1,0) -> 0 | O35: =IF(O20>$F$12,1,0) -> 0 | P35: =IF(P20>$F$12,1,0) -> 1 | Q35: =IF(Q20>$F$12,1,0) -> 1 | ... BN35: =IF(BN20>$F$12,1,0) -> 1
D36: Flag_Operations | E36: flag | J36: =IF(J30>0,1,0) -> 0 | K36: =IF(K30>0,1,0) -> 0 | L36: =IF(L30>0,1,0) -> 0 | M36: =IF(M30>0,1,0) -> 0 | N36: =IF(N30>0,1,0) -> 0 | O36: =IF(O30>0,1,0) -> 1 | P36: =IF(P30>0,1,0) -> 1 | Q36: =IF(Q30>0,1,0) -> 1 | ... BN36: =IF(BN30>0,1,0) -> 0
D37: Flag_LastOperatingPeriod | E37: flag | J37: =IF(AND(J30>0,K30=0),1,0) -> 0 | K37: =IF(AND(K30>0,L30=0),1,0) -> 0 | L37: =IF(AND(L30>0,M30=0),1,0) -> 0 | M37: =IF(AND(M30>0,N30=0),1,0) -> 0 | N37: =IF(AND(N30>0,O30=0),1,0) -> 0 | O37: =IF(AND(O30>0,P30=0),1,0) -> 0 | P37: =IF(AND(P30>0,Q30=0),1,0) -> 0 | Q37: =IF(AND(Q30>0,R30=0),1,0) -> 0 | ... BN37: =IF(AND(BN30>0,BO30=0),1,0) -> 0
D38: Flag_ShockPeriods | E38: flag | J38: =IF(AND(J22>=Inputs!$F$193,J22<EDATE(Inputs!$F$193,Inputs!$F$211)),1,0) -> 0 | K38: =IF(AND(K22>=Inputs!$F$193,K22<EDATE(Inputs!$F$193,Inputs!$F$211)),1,0) -> 0 | L38: =IF(AND(L22>=Inputs!$F$193,L22<EDATE(Inputs!$F$193,Inputs!$F$211)),1,0) -> 0 | M38: =IF(AND(M22>=Inputs!$F$193,M22<EDATE(Inputs!$F$193,Inputs!$F$211)),1,0) -> 0 | N38: =IF(AND(N22>=Inputs!$F$193,N22<EDATE(Inputs!$F$193,Inputs!$F$211)),1,0) -> 0 | O38: =IF(AND(O22>=Inputs!$F$193,O22<EDATE(Inputs!$F$193,Inputs!$F$211)),1,0) -> 0 | P38: =IF(AND(P22>=Inputs!$F$193,P22<EDATE(Inputs!$F$193,Inputs!$F$211)),1,0) -> 0 | Q38: =IF(AND(Q22>=Inputs!$F$193,Q22<EDATE(Inputs!$F$193,Inputs!$F$211)),1,0) -> 1 | ... BN38: =IF(AND(BN22>=Inputs!$F$193,BN22<EDATE(Inputs!$F$193,Inputs!$F$211)),1,0) -> 0
D39: Flag_FromShockStart | E39: flag | J39: =IF(J22>=Inputs!$F$193,1,0) -> 0 | K39: =IF(K22>=Inputs!$F$193,1,0) -> 0 | L39: =IF(L22>=Inputs!$F$193,1,0) -> 0 | M39: =IF(M22>=Inputs!$F$193,1,0) -> 0 | N39: =IF(N22>=Inputs!$F$193,1,0) -> 0 | O39: =IF(O22>=Inputs!$F$193,1,0) -> 0 | P39: =IF(P22>=Inputs!$F$193,1,0) -> 0 | Q39: =IF(Q22>=Inputs!$F$193,1,0) -> 1 | ... BN39: =IF(BN22>=Inputs!$F$193,1,0) -> 1
D40: Flag_TermSOFR | E40: flag | J40: =IF(J22>=Inputs!$F$196,1,0) -> 0 | K40: =IF(K22>=Inputs!$F$196,1,0) -> 0 | L40: =IF(L22>=Inputs!$F$196,1,0) -> 0 | M40: =IF(M22>=Inputs!$F$196,1,0) -> 0 | N40: =IF(N22>=Inputs!$F$196,1,0) -> 0 | O40: =IF(O22>=Inputs!$F$196,1,0) -> 0 | P40: =IF(P22>=Inputs!$F$196,1,0) -> 0 | Q40: =IF(Q22>=Inputs!$F$196,1,0) -> 0 | ... BN40: =IF(BN22>=Inputs!$F$196,1,0) -> 1
D41: Flag_InsuranceStepUp | E41: flag | J41: =IF(J22>=Inputs!$F$195,1,0) -> 0 | K41: =IF(K22>=Inputs!$F$195,1,0) -> 0 | L41: =IF(L22>=Inputs!$F$195,1,0) -> 0 | M41: =IF(M22>=Inputs!$F$195,1,0) -> 0 | N41: =IF(N22>=Inputs!$F$195,1,0) -> 0 | O41: =IF(O22>=Inputs!$F$195,1,0) -> 0 | P41: =IF(P22>=Inputs!$F$195,1,0) -> 0 | Q41: =IF(Q22>=Inputs!$F$195,1,0) -> 0 | ... BN41: =IF(BN22>=Inputs!$F$195,1,0) -> 1
D42: Flag_LDPrepayment | E42: flag | J42: =Inputs!$F$48*IF(J23=Inputs!$F$198,1,0) -> 0 | K42: =Inputs!$F$48*IF(K23=Inputs!$F$198,1,0) -> 0 | L42: =Inputs!$F$48*IF(L23=Inputs!$F$198,1,0) -> 0 | M42: =Inputs!$F$48*IF(M23=Inputs!$F$198,1,0) -> 0 | N42: =Inputs!$F$48*IF(N23=Inputs!$F$198,1,0) -> 0 | O42: =Inputs!$F$48*IF(O23=Inputs!$F$198,1,0) -> 0 | P42: =Inputs!$F$48*IF(P23=Inputs!$F$198,1,0) -> 0 | Q42: =Inputs!$F$48*IF(Q23=Inputs!$F$198,1,0) -> 0 | ... BN42: =Inputs!$F$48*IF(BN23=Inputs!$F$198,1,0) -> 0
D43: Flag_WaiverDeferral | E43: flag | J43: =Inputs!$F$49*IF(J23=Inputs!$F$200,1,0) -> 0 | K43: =Inputs!$F$49*IF(K23=Inputs!$F$200,1,0) -> 0 | L43: =Inputs!$F$49*IF(L23=Inputs!$F$200,1,0) -> 0 | M43: =Inputs!$F$49*IF(M23=Inputs!$F$200,1,0) -> 0 | N43: =Inputs!$F$49*IF(N23=Inputs!$F$200,1,0) -> 0 | O43: =Inputs!$F$49*IF(O23=Inputs!$F$200,1,0) -> 0 | P43: =Inputs!$F$49*IF(P23=Inputs!$F$200,1,0) -> 0 | Q43: =Inputs!$F$49*IF(Q23=Inputs!$F$200,1,0) -> 0 | ... BN43: =Inputs!$F$49*IF(BN23=Inputs!$F$200,1,0) -> 0
D44: Flag_MarginUplift | E44: flag | J44: =Inputs!$F$49*IF(AND(J22>=Inputs!$F$201,J23<=Inputs!$F$202),1,0) -> 0 | K44: =Inputs!$F$49*IF(AND(K22>=Inputs!$F$201,K23<=Inputs!$F$202),1,0) -> 0 | L44: =Inputs!$F$49*IF(AND(L22>=Inputs!$F$201,L23<=Inputs!$F$202),1,0) -> 0 | M44: =Inputs!$F$49*IF(AND(M22>=Inputs!$F$201,M23<=Inputs!$F$202),1,0) -> 0 | N44: =Inputs!$F$49*IF(AND(N22>=Inputs!$F$201,N23<=Inputs!$F$202),1,0) -> 0 | O44: =Inputs!$F$49*IF(AND(O22>=Inputs!$F$201,O23<=Inputs!$F$202),1,0) -> 0 | P44: =Inputs!$F$49*IF(AND(P22>=Inputs!$F$201,P23<=Inputs!$F$202),1,0) -> 0 | Q44: =Inputs!$F$49*IF(AND(Q22>=Inputs!$F$201,Q23<=Inputs!$F$202),1,0) -> 0 | ... BN44: =Inputs!$F$49*IF(AND(BN22>=Inputs!$F$201,BN23<=Inputs!$F$202),1,0) -> 0
D45: Flag_DeferredRepayment | E45: flag | J45: =Inputs!$F$49*IF(AND(J23>=Inputs!$F$203,J23<=Inputs!$F$204),1,0) -> 0 | K45: =Inputs!$F$49*IF(AND(K23>=Inputs!$F$203,K23<=Inputs!$F$204),1,0) -> 0 | L45: =Inputs!$F$49*IF(AND(L23>=Inputs!$F$203,L23<=Inputs!$F$204),1,0) -> 0 | M45: =Inputs!$F$49*IF(AND(M23>=Inputs!$F$203,M23<=Inputs!$F$204),1,0) -> 0 | N45: =Inputs!$F$49*IF(AND(N23>=Inputs!$F$203,N23<=Inputs!$F$204),1,0) -> 0 | O45: =Inputs!$F$49*IF(AND(O23>=Inputs!$F$203,O23<=Inputs!$F$204),1,0) -> 0 | P45: =Inputs!$F$49*IF(AND(P23>=Inputs!$F$203,P23<=Inputs!$F$204),1,0) -> 0 | Q45: =Inputs!$F$49*IF(AND(Q23>=Inputs!$F$203,Q23<=Inputs!$F$204),1,0) -> 0 | ... BN45: =Inputs!$F$49*IF(AND(BN23>=Inputs!$F$203,BN23<=Inputs!$F$204),1,0) -> 0
D46: Deferred repayments remaining (this and later periods) | E46: count | J46: =SUM(J45:BN45) -> 0 | K46: =SUM(K45:BN45) -> 0 | L46: =SUM(L45:BN45) -> 0 | M46: =SUM(M45:BN45) -> 0 | N46: =SUM(N45:BN45) -> 0 | O46: =SUM(O45:BN45) -> 0 | P46: =SUM(P45:BN45) -> 0 | Q46: =SUM(Q45:BN45) -> 0 | R46: =SUM(R45:BN45) -> 0 | S46: =SUM(S45:BN45) -> 0 | T46: =SUM(T45:BN45) -> 0 | U46: =SUM(U45:BN45) -> 0 | V46: =SUM(V45:BN45) -> 0 | W46: =SUM(W45:BN45) -> 0 | X46: =SUM(X45:BN45) -> 0 | Y46: =SUM(Y45:BN45) -> 0 | Z46: =SUM(Z45:BN45) -> 0 | AA46: =SUM(AA45:BN45) -> 0 | AB46: =SUM(AB45:BN45) -> 0 | AC46: =SUM(AC45:BN45) -> 0 | AD46: =SUM(AD45:BN45) -> 0 | AE46: =SUM(AE45:BN45) -> 0 | AF46: =SUM(AF45:BN45) -> 0 | AG46: =SUM(AG45:BN45) -> 0 | AH46: =SUM(AH45:BN45) -> 0 | AI46: =SUM(AI45:BN45) -> 0 | AJ46: =SUM(AJ45:BN45) -> 0 | AK46: =SUM(AK45:BN45) -> 0 | AL46: =SUM(AL45:BN45) -> 0 | AM46: =SUM(AM45:BN45) -> 0 | AN46: =SUM(AN45:BN45) -> 0 | AO46: =SUM(AO45:BN45) -> 0 | AP46: =SUM(AP45:BN45) -> 0 | AQ46: =SUM(AQ45:BN45) -> 0 | AR46: =SUM(AR45:BN45) -> 0 | AS46: =SUM(AS45:BN45) -> 0 | AT46: =SUM(AT45:BN45) -> 0 | AU46: =SUM(AU45:BN45) -> 0 | AV46: =SUM(AV45:BN45) -> 0 | AW46: =SUM(AW45:BN45) -> 0 | AX46: =SUM(AX45:BN45) -> 0 | AY46: =SUM(AY45:BN45) -> 0 | AZ46: =SUM(AZ45:BN45) -> 0 | BA46: =SUM(BA45:BN45) -> 0 | BB46: =SUM(BB45:BN45) -> 0 | BC46: =SUM(BC45:BN45) -> 0 | BD46: =SUM(BD45:BN45) -> 0 | BE46: =SUM(BE45:BN45) -> 0 | BF46: =SUM(BF45:BN45) -> 0 | BG46: =SUM(BG45:BN45) -> 0 | BH46: =SUM(BH45:BN45) -> 0 | BI46: =SUM(BI45:BN45) -> 0 | BJ46: =SUM(BJ45:BN45) -> 0 | BK46: =SUM(BK45:BN45) -> 0 | BL46: =SUM(BL45:BN45) -> 0 | BM46: =SUM(BM45:BN45) -> 0 | BN46: =SUM(BN45:BN45) -> 0
D47: Flag_Refinancing | E47: flag | J47: =Inputs!$F$50*IF(J23=Inputs!$F$205,1,0) -> 0 | K47: =Inputs!$F$50*IF(K23=Inputs!$F$205,1,0) -> 0 | L47: =Inputs!$F$50*IF(L23=Inputs!$F$205,1,0) -> 0 | M47: =Inputs!$F$50*IF(M23=Inputs!$F$205,1,0) -> 0 | N47: =Inputs!$F$50*IF(N23=Inputs!$F$205,1,0) -> 0 | O47: =Inputs!$F$50*IF(O23=Inputs!$F$205,1,0) -> 0 | P47: =Inputs!$F$50*IF(P23=Inputs!$F$205,1,0) -> 0 | Q47: =Inputs!$F$50*IF(Q23=Inputs!$F$205,1,0) -> 0 | ... BN47: =Inputs!$F$50*IF(BN23=Inputs!$F$205,1,0) -> 0
D48: Flag_AfterRefinancing | E48: flag | J48: =Inputs!$F$50*IF(J23>Inputs!$F$205,1,0) -> 0 | K48: =Inputs!$F$50*IF(K23>Inputs!$F$205,1,0) -> 0 | L48: =Inputs!$F$50*IF(L23>Inputs!$F$205,1,0) -> 0 | M48: =Inputs!$F$50*IF(M23>Inputs!$F$205,1,0) -> 0 | N48: =Inputs!$F$50*IF(N23>Inputs!$F$205,1,0) -> 0 | O48: =Inputs!$F$50*IF(O23>Inputs!$F$205,1,0) -> 0 | P48: =Inputs!$F$50*IF(P23>Inputs!$F$205,1,0) -> 0 | Q48: =Inputs!$F$50*IF(Q23>Inputs!$F$205,1,0) -> 0 | ... BN48: =Inputs!$F$50*IF(BN23>Inputs!$F$205,1,0) -> 0
D49: Flag_TestWaived | E49: flag | J49: =Inputs!$F$49*IF(AND(J23>=Inputs!$F$199,J23<=Inputs!$F$200),1,0) -> 0 | K49: =Inputs!$F$49*IF(AND(K23>=Inputs!$F$199,K23<=Inputs!$F$200),1,0) -> 0 | L49: =Inputs!$F$49*IF(AND(L23>=Inputs!$F$199,L23<=Inputs!$F$200),1,0) -> 0 | M49: =Inputs!$F$49*IF(AND(M23>=Inputs!$F$199,M23<=Inputs!$F$200),1,0) -> 0 | N49: =Inputs!$F$49*IF(AND(N23>=Inputs!$F$199,N23<=Inputs!$F$200),1,0) -> 0 | O49: =Inputs!$F$49*IF(AND(O23>=Inputs!$F$199,O23<=Inputs!$F$200),1,0) -> 0 | P49: =Inputs!$F$49*IF(AND(P23>=Inputs!$F$199,P23<=Inputs!$F$200),1,0) -> 0 | Q49: =Inputs!$F$49*IF(AND(Q23>=Inputs!$F$199,Q23<=Inputs!$F$200),1,0) -> 0 | ... BN49: =Inputs!$F$49*IF(AND(BN23>=Inputs!$F$199,BN23<=Inputs!$F$200),1,0) -> 0
D50: Flag_WaiverRegime | E50: flag | J50: =Inputs!$F$49*IF(J23>=Inputs!$F$199,1,0) -> 0 | K50: =Inputs!$F$49*IF(K23>=Inputs!$F$199,1,0) -> 0 | L50: =Inputs!$F$49*IF(L23>=Inputs!$F$199,1,0) -> 0 | M50: =Inputs!$F$49*IF(M23>=Inputs!$F$199,1,0) -> 0 | N50: =Inputs!$F$49*IF(N23>=Inputs!$F$199,1,0) -> 0 | O50: =Inputs!$F$49*IF(O23>=Inputs!$F$199,1,0) -> 0 | P50: =Inputs!$F$49*IF(P23>=Inputs!$F$199,1,0) -> 0 | Q50: =Inputs!$F$49*IF(Q23>=Inputs!$F$199,1,0) -> 0 | ... BN50: =Inputs!$F$49*IF(BN23>=Inputs!$F$199,1,0) -> 0
D51: Flag_AfterWaivedTests | E51: flag | J51: =Inputs!$F$49*IF(J23>Inputs!$F$200,1,0) -> 0 | K51: =Inputs!$F$49*IF(K23>Inputs!$F$200,1,0) -> 0 | L51: =Inputs!$F$49*IF(L23>Inputs!$F$200,1,0) -> 0 | M51: =Inputs!$F$49*IF(M23>Inputs!$F$200,1,0) -> 0 | N51: =Inputs!$F$49*IF(N23>Inputs!$F$200,1,0) -> 0 | O51: =Inputs!$F$49*IF(O23>Inputs!$F$200,1,0) -> 0 | P51: =Inputs!$F$49*IF(P23>Inputs!$F$200,1,0) -> 0 | Q51: =Inputs!$F$49*IF(Q23>Inputs!$F$200,1,0) -> 0 | ... BN51: =Inputs!$F$49*IF(BN23>Inputs!$F$200,1,0) -> 0
D52: Flag_MiniPermSweep | E52: flag | J52: =IF(J22>=Inputs!$F$206,1,0) -> 0 | K52: =IF(K22>=Inputs!$F$206,1,0) -> 0 | L52: =IF(L22>=Inputs!$F$206,1,0) -> 0 | M52: =IF(M22>=Inputs!$F$206,1,0) -> 0 | N52: =IF(N22>=Inputs!$F$206,1,0) -> 0 | O52: =IF(O22>=Inputs!$F$206,1,0) -> 0 | P52: =IF(P22>=Inputs!$F$206,1,0) -> 0 | Q52: =IF(Q22>=Inputs!$F$206,1,0) -> 0 | ... BN52: =IF(BN22>=Inputs!$F$206,1,0) -> 1
D53: Flag_SculptingPeriod (first repayment to final maturity) | E53: flag | J53: =IF(AND(J20>=$F$13,J23<=Inputs!$F$192),1,0) -> 0 | K53: =IF(AND(K20>=$F$13,K23<=Inputs!$F$192),1,0) -> 0 | L53: =IF(AND(L20>=$F$13,L23<=Inputs!$F$192),1,0) -> 0 | M53: =IF(AND(M20>=$F$13,M23<=Inputs!$F$192),1,0) -> 0 | N53: =IF(AND(N20>=$F$13,N23<=Inputs!$F$192),1,0) -> 0 | O53: =IF(AND(O20>=$F$13,O23<=Inputs!$F$192),1,0) -> 0 | P53: =IF(AND(P20>=$F$13,P23<=Inputs!$F$192),1,0) -> 1 | Q53: =IF(AND(Q20>=$F$13,Q23<=Inputs!$F$192),1,0) -> 1 | ... BN53: =IF(AND(BN20>=$F$13,BN23<=Inputs!$F$192),1,0) -> 0
D54: Flag_ReforecastProjection | E54: flag | J54: =IF(J22>=Inputs!$F$194,1,0) -> 0 | K54: =IF(K22>=Inputs!$F$194,1,0) -> 0 | L54: =IF(L22>=Inputs!$F$194,1,0) -> 0 | M54: =IF(M22>=Inputs!$F$194,1,0) -> 0 | N54: =IF(N22>=Inputs!$F$194,1,0) -> 0 | O54: =IF(O22>=Inputs!$F$194,1,0) -> 0 | P54: =IF(P22>=Inputs!$F$194,1,0) -> 0 | Q54: =IF(Q22>=Inputs!$F$194,1,0) -> 1 | ... BN54: =IF(BN22>=Inputs!$F$194,1,0) -> 1
D55: Days of late-payment interest accrual to settlement | E55: days | J55: =MAX(0,MIN(J25,Inputs!$F$197-J22)) -> 184 | K55: =MAX(0,MIN(K25,Inputs!$F$197-K22)) -> 181 | L55: =MAX(0,MIN(L25,Inputs!$F$197-L22)) -> 184 | M55: =MAX(0,MIN(M25,Inputs!$F$197-M22)) -> 182 | N55: =MAX(0,MIN(N25,Inputs!$F$197-N22)) -> 184 | O55: =MAX(0,MIN(O25,Inputs!$F$197-O22)) -> 181 | P55: =MAX(0,MIN(P25,Inputs!$F$197-P22)) -> 184 | Q55: =MAX(0,MIN(Q25,Inputs!$F$197-Q22)) -> 181 | ... BN55: =MAX(0,MIN(BN25,Inputs!$F$197-BN22)) -> 0

Sheet Construction
A1: Case P: Belanou Combined Cycle Power Project, Republic of Kessara
A2: Construction: monthly uses of funds before financing costs, VAT
A3: Units in column E; constants in column F; row totals in column G; first period in column J. Inputs: blue on yellow. Links from other sheets: green.
D4: Label | E4: Unit | F4: Constant | G4: Total
D5: Month | J5: 2018-08 | K5: 2018-09 | L5: 2018-10 | M5: 2018-11 | N5: 2018-12 | O5: 2019-01 | P5: 2019-02 | Q5: 2019-03 | R5: 2019-04 | S5: 2019-05 | T5: 2019-06 | U5: 2019-07 | V5: 2019-08 | W5: 2019-09 | X5: 2019-10 | Y5: 2019-11 | Z5: 2019-12 | AA5: 2020-01 | AB5: 2020-02 | AC5: 2020-03 | AD5: 2020-04 | AE5: 2020-05 | AF5: 2020-06 | AG5: 2020-07 | AH5: 2020-08 | AI5: 2020-09 | AJ5: 2020-10 | AK5: 2020-11 | AL5: 2020-12 | AM5: 2021-01 | AN5: 2021-02 | AO5: 2021-03 | AP5: 2021-04 | AQ5: 2021-05 | AR5: 2021-06 | AS5: 2021-07 | AT5: 2021-08 | AU5: 2021-09 | AV5: 2021-10 | AW5: 2021-11 | AX5: 2021-12 | AY5: 2022-01 | AZ5: 2022-02 | BA5: 2022-03 | BB5: 2022-04 | BC5: 2022-05 | BD5: 2022-06 | BE5: 2022-07 | BF5: 2022-08 | BG5: 2022-09 | BH5: 2022-10 | BI5: 2022-11 | BJ5: 2022-12
B7: Monthly timeline (column J = August 2018)
D8: Month number | E8: index | J8: =I8+1 -> 1 | K8: =J8+1 -> 2 | L8: =K8+1 -> 3 | M8: =L8+1 -> 4 | N8: =M8+1 -> 5 | O8: =N8+1 -> 6 | P8: =O8+1 -> 7 | Q8: =P8+1 -> 8 | ... BJ8: =BI8+1 -> 53
D9: Month start | E9: date | J9: =IF(J8=1,Inputs!$F$188,EDATE(I9,1)) -> 43313 | K9: =IF(K8=1,Inputs!$F$188,EDATE(J9,1)) -> 43344 | L9: =IF(L8=1,Inputs!$F$188,EDATE(K9,1)) -> 43374 | M9: =IF(M8=1,Inputs!$F$188,EDATE(L9,1)) -> 43405 | N9: =IF(N8=1,Inputs!$F$188,EDATE(M9,1)) -> 43435 | O9: =IF(O8=1,Inputs!$F$188,EDATE(N9,1)) -> 43466 | P9: =IF(P8=1,Inputs!$F$188,EDATE(O9,1)) -> 43497 | Q9: =IF(Q8=1,Inputs!$F$188,EDATE(P9,1)) -> 43525 | ... BJ9: =IF(BJ8=1,Inputs!$F$188,EDATE(BI9,1)) -> 44896
D10: Month end | E10: date | J10: =EOMONTH(J9,0) -> 43343 | K10: =EOMONTH(K9,0) -> 43373 | L10: =EOMONTH(L9,0) -> 43404 | M10: =EOMONTH(M9,0) -> 43434 | N10: =EOMONTH(N9,0) -> 43465 | O10: =EOMONTH(O9,0) -> 43496 | P10: =EOMONTH(P9,0) -> 43524 | Q10: =EOMONTH(Q9,0) -> 43555 | ... BJ10: =EOMONTH(BJ9,0) -> 44926
D11: Days | E11: days | J11: =J10-J9+1 -> 31 | K11: =K10-K9+1 -> 30 | L11: =L10-L9+1 -> 31 | M11: =M10-M9+1 -> 30 | N11: =N10-N9+1 -> 31 | O11: =O10-O9+1 -> 31 | P11: =P10-P9+1 -> 28 | Q11: =Q10-Q9+1 -> 31 | ... BJ11: =BJ10-BJ9+1 -> 31
D12: Semiannual period number | E12: index | J12: =MATCH(J9,Time!$J$22:$BN$22,1) -> 1 | K12: =MATCH(K9,Time!$J$22:$BN$22,1) -> 1 | L12: =MATCH(L9,Time!$J$22:$BN$22,1) -> 1 | M12: =MATCH(M9,Time!$J$22:$BN$22,1) -> 1 | N12: =MATCH(N9,Time!$J$22:$BN$22,1) -> 1 | O12: =MATCH(O9,Time!$J$22:$BN$22,1) -> 2 | P12: =MATCH(P9,Time!$J$22:$BN$22,1) -> 2 | Q12: =MATCH(Q9,Time!$J$22:$BN$22,1) -> 2 | ... BJ12: =MATCH(BJ9,Time!$J$22:$BN$22,1) -> 9
D13: Flag_Construction (before COD) | E13: flag | J13: =IF(J8<=Time!$F$11,1,0) -> 1 | K13: =IF(K8<=Time!$F$11,1,0) -> 1 | L13: =IF(L8<=Time!$F$11,1,0) -> 1 | M13: =IF(M8<=Time!$F$11,1,0) -> 1 | N13: =IF(N8<=Time!$F$11,1,0) -> 1 | O13: =IF(O8<=Time!$F$11,1,0) -> 1 | P13: =IF(P8<=Time!$F$11,1,0) -> 1 | Q13: =IF(Q8<=Time!$F$11,1,0) -> 1 | ... BJ13: =IF(BJ8<=Time!$F$11,1,0) -> 0
D14: Flag_FundingPeriod (to end of COD period) | E14: flag | J14: =IF(J8<=Time!$F$14,1,0) -> 1 | K14: =IF(K8<=Time!$F$14,1,0) -> 1 | L14: =IF(L8<=Time!$F$14,1,0) -> 1 | M14: =IF(M8<=Time!$F$14,1,0) -> 1 | N14: =IF(N8<=Time!$F$14,1,0) -> 1 | O14: =IF(O8<=Time!$F$14,1,0) -> 1 | P14: =IF(P8<=Time!$F$14,1,0) -> 1 | Q14: =IF(Q8<=Time!$F$14,1,0) -> 1 | ... BJ14: =IF(BJ8<=Time!$F$14,1,0) -> 0
D15: Flag_CODMonth | E15: flag | J15: =IF(J8=Time!$F$11+1,1,0) -> 0 | K15: =IF(K8=Time!$F$11+1,1,0) -> 0 | L15: =IF(L8=Time!$F$11+1,1,0) -> 0 | M15: =IF(M8=Time!$F$11+1,1,0) -> 0 | N15: =IF(N8=Time!$F$11+1,1,0) -> 0 | O15: =IF(O8=Time!$F$11+1,1,0) -> 0 | P15: =IF(P8=Time!$F$11+1,1,0) -> 0 | Q15: =IF(Q8=Time!$F$11+1,1,0) -> 0 | ... BJ15: =IF(BJ8=Time!$F$11+1,1,0) -> 0
D16: KCR per USD | E16: KCR/USD | J16: =IF(Inputs!$F$33=1,Inputs!$F$60*Time!$F$16^((J8-Inputs!$F$212)/12),INDEX(Operations!$J$11:$BN$11,1,J12)) -> 520.49534 | K16: =IF(Inputs!$F$33=1,Inputs!$F$60*Time!$F$16^((K8-Inputs!$F$212)/12),INDEX(Operations!$J$11:$BN$11,1,K12)) -> 522.69295 | L16: =IF(Inputs!$F$33=1,Inputs!$F$60*Time!$F$16^((L8-Inputs!$F$212)/12),INDEX(Operations!$J$11:$BN$11,1,L12)) -> 524.89984 | M16: =IF(Inputs!$F$33=1,Inputs!$F$60*Time!$F$16^((M8-Inputs!$F$212)/12),INDEX(Operations!$J$11:$BN$11,1,M12)) -> 527.11605 | N16: =IF(Inputs!$F$33=1,Inputs!$F$60*Time!$F$16^((N8-Inputs!$F$212)/12),INDEX(Operations!$J$11:$BN$11,1,N12)) -> 529.34161 | O16: =IF(Inputs!$F$33=1,Inputs!$F$60*Time!$F$16^((O8-Inputs!$F$212)/12),INDEX(Operations!$J$11:$BN$11,1,O12)) -> 531.57657 | P16: =IF(Inputs!$F$33=1,Inputs!$F$60*Time!$F$16^((P8-Inputs!$F$212)/12),INDEX(Operations!$J$11:$BN$11,1,P12)) -> 533.82097 | Q16: =IF(Inputs!$F$33=1,Inputs!$F$60*Time!$F$16^((Q8-Inputs!$F$212)/12),INDEX(Operations!$J$11:$BN$11,1,Q12)) -> 536.07484 | ... BJ16: =IF(Inputs!$F$33=1,Inputs!$F$60*Time!$F$16^((BJ8-Inputs!$F$212)/12),INDEX(Operations!$J$11:$BN$11,1,BJ12)) -> 647.98702
D17: Base rate (6M fixing for the half-year) | E17: % | J17: =INDEX(Operations!$J$8:$BN$8,1,J12) -> 2.52 | K17: =INDEX(Operations!$J$8:$BN$8,1,K12) -> 2.52 | L17: =INDEX(Operations!$J$8:$BN$8,1,L12) -> 2.52 | M17: =INDEX(Operations!$J$8:$BN$8,1,M12) -> 2.52 | N17: =INDEX(Operations!$J$8:$BN$8,1,N12) -> 2.52 | O17: =INDEX(Operations!$J$8:$BN$8,1,O12) -> 2.79 | P17: =INDEX(Operations!$J$8:$BN$8,1,P12) -> 2.79 | Q17: =INDEX(Operations!$J$8:$BN$8,1,Q12) -> 2.79 | ... BJ17: =INDEX(Operations!$J$8:$BN$8,1,BJ12) -> 3.11
D18: Kessara policy rate | E18: % | J18: =IF(Inputs!$F$33=1,Inputs!$F$73,INDEX(Inputs!$J$289:$AR$289,1,MATCH(YEAR(J9),Inputs!$J$282:$AR$282,0))) -> 13.5 | K18: =IF(Inputs!$F$33=1,Inputs!$F$73,INDEX(Inputs!$J$289:$AR$289,1,MATCH(YEAR(K9),Inputs!$J$282:$AR$282,0))) -> 13.5 | L18: =IF(Inputs!$F$33=1,Inputs!$F$73,INDEX(Inputs!$J$289:$AR$289,1,MATCH(YEAR(L9),Inputs!$J$282:$AR$282,0))) -> 13.5 | M18: =IF(Inputs!$F$33=1,Inputs!$F$73,INDEX(Inputs!$J$289:$AR$289,1,MATCH(YEAR(M9),Inputs!$J$282:$AR$282,0))) -> 13.5 | N18: =IF(Inputs!$F$33=1,Inputs!$F$73,INDEX(Inputs!$J$289:$AR$289,1,MATCH(YEAR(N9),Inputs!$J$282:$AR$282,0))) -> 13.5 | O18: =IF(Inputs!$F$33=1,Inputs!$F$73,INDEX(Inputs!$J$289:$AR$289,1,MATCH(YEAR(O9),Inputs!$J$282:$AR$282,0))) -> 13.5 | P18: =IF(Inputs!$F$33=1,Inputs!$F$73,INDEX(Inputs!$J$289:$AR$289,1,MATCH(YEAR(P9),Inputs!$J$282:$AR$282,0))) -> 13.5 | Q18: =IF(Inputs!$F$33=1,Inputs!$F$73,INDEX(Inputs!$J$289:$AR$289,1,MATCH(YEAR(Q9),Inputs!$J$282:$AR$282,0))) -> 13.5 | ... BJ18: =IF(Inputs!$F$33=1,Inputs!$F$73,INDEX(Inputs!$J$289:$AR$289,1,MATCH(YEAR(BJ9),Inputs!$J$282:$AR$282,0))) -> 13.5
B19: Uses before financing costs (USD m)
D20: EPC payment profile, selected | E20: % | J20: =IF(Inputs!$F$34<>1,Inputs!J306,Inputs!J305+IF(Inputs!$F$35>0,IF(J8=Inputs!$F$237,-Inputs!$F$238,0)+IF(J8=Inputs!$F$237+Inputs!$F$35,Inputs!$F$238,0),0)) -> 10 | K20: =IF(Inputs!$F$34<>1,Inputs!K306,Inputs!K305+IF(Inputs!$F$35>0,IF(K8=Inputs!$F$237,-Inputs!$F$238,0)+IF(K8=Inputs!$F$237+Inputs!$F$35,Inputs!$F$238,0),0)) -> 0.0108 | L20: =IF(Inputs!$F$34<>1,Inputs!L306,Inputs!L305+IF(Inputs!$F$35>0,IF(L8=Inputs!$F$237,-Inputs!$F$238,0)+IF(L8=Inputs!$F$237+Inputs!$F$35,Inputs!$F$238,0),0)) -> 0.1133 | M20: =IF(Inputs!$F$34<>1,Inputs!M306,Inputs!M305+IF(Inputs!$F$35>0,IF(M8=Inputs!$F$237,-Inputs!$F$238,0)+IF(M8=Inputs!$F$237+Inputs!$F$35,Inputs!$F$238,0),0)) -> 0.3239 | N20: =IF(Inputs!$F$34<>1,Inputs!N306,Inputs!N305+IF(Inputs!$F$35>0,IF(N8=Inputs!$F$237,-Inputs!$F$238,0)+IF(N8=Inputs!$F$237+Inputs!$F$35,Inputs!$F$238,0),0)) -> 0.6294 | O20: =IF(Inputs!$F$34<>1,Inputs!O306,Inputs!O305+IF(Inputs!$F$35>0,IF(O8=Inputs!$F$237,-Inputs!$F$238,0)+IF(O8=Inputs!$F$237+Inputs!$F$35,Inputs!$F$238,0),0)) -> 1.0114 | P20: =IF(Inputs!$F$34<>1,Inputs!P306,Inputs!P305+IF(Inputs!$F$35>0,IF(P8=Inputs!$F$237,-Inputs!$F$238,0)+IF(P8=Inputs!$F$237+Inputs!$F$35,Inputs!$F$238,0),0)) -> 1.4496 | Q20: =IF(Inputs!$F$34<>1,Inputs!Q306,Inputs!Q305+IF(Inputs!$F$35>0,IF(Q8=Inputs!$F$237,-Inputs!$F$238,0)+IF(Q8=Inputs!$F$237+Inputs!$F$35,Inputs!$F$238,0),0)) -> 1.9236 | ... BJ20: =IF(Inputs!$F$34<>1,Inputs!BJ306,Inputs!BJ305+IF(Inputs!$F$35>0,IF(BJ8=Inputs!$F$237,-Inputs!$F$238,0)+IF(BJ8=Inputs!$F$237+Inputs!$F$35,Inputs!$F$238,0),0)) -> 0
D21: EPC progress payments for contingency (FC) | E21: % | J21: =IF(J8=1,0,J20)-IF(J8=Time!$F$11,Inputs!$F$238,0) -> 0 | K21: =IF(K8=1,0,K20)-IF(K8=Time!$F$11,Inputs!$F$238,0) -> 0.0108 | L21: =IF(L8=1,0,L20)-IF(L8=Time!$F$11,Inputs!$F$238,0) -> 0.1133 | M21: =IF(M8=1,0,M20)-IF(M8=Time!$F$11,Inputs!$F$238,0) -> 0.3239 | N21: =IF(N8=1,0,N20)-IF(N8=Time!$F$11,Inputs!$F$238,0) -> 0.6294 | O21: =IF(O8=1,0,O20)-IF(O8=Time!$F$11,Inputs!$F$238,0) -> 1.0114 | P21: =IF(P8=1,0,P20)-IF(P8=Time!$F$11,Inputs!$F$238,0) -> 1.4496 | Q21: =IF(Q8=1,0,Q20)-IF(Q8=Time!$F$11,Inputs!$F$238,0) -> 1.9236 | ... BJ21: =IF(BJ8=1,0,BJ20)-IF(BJ8=Time!$F$11,Inputs!$F$238,0) -> 0
D22: EPC payments | E22: USD m | G22: =SUM(J22:BJ22) -> 571.84 | J22: =IF(Inputs!$F$34<>1,J20/100*Inputs!$F$58+J20/100*Inputs!$F$59*Inputs!$F$60/J16,Inputs!$F$57*Inputs!$F$36*J20/100) -> 57.184 | K22: =IF(Inputs!$F$34<>1,K20/100*Inputs!$F$58+K20/100*Inputs!$F$59*Inputs!$F$60/K16,Inputs!$F$57*Inputs!$F$36*K20/100) -> 0.06175872 | L22: =IF(Inputs!$F$34<>1,L20/100*Inputs!$F$58+L20/100*Inputs!$F$59*Inputs!$F$60/L16,Inputs!$F$57*Inputs!$F$36*L20/100) -> 0.64789472 | M22: =IF(Inputs!$F$34<>1,M20/100*Inputs!$F$58+M20/100*Inputs!$F$59*Inputs!$F$60/M16,Inputs!$F$57*Inputs!$F$36*M20/100) -> 1.8521898 | N22: =IF(Inputs!$F$34<>1,N20/100*Inputs!$F$58+N20/100*Inputs!$F$59*Inputs!$F$60/N16,Inputs!$F$57*Inputs!$F$36*N20/100) -> 3.599161 | O22: =IF(Inputs!$F$34<>1,O20/100*Inputs!$F$58+O20/100*Inputs!$F$59*Inputs!$F$60/O16,Inputs!$F$57*Inputs!$F$36*O20/100) -> 5.7835898 | P22: =IF(Inputs!$F$34<>1,P20/100*Inputs!$F$58+P20/100*Inputs!$F$59*Inputs!$F$60/P16,Inputs!$F$57*Inputs!$F$36*P20/100) -> 8.2893926 | Q22: =IF(Inputs!$F$34<>1,Q20/100*Inputs!$F$58+Q20/100*Inputs!$F$59*Inputs!$F$60/Q16,Inputs!$F$57*Inputs!$F$36*Q20/100) -> 10.999914 | ... BJ22: =IF(Inputs!$F$34<>1,BJ20/100*Inputs!$F$58+BJ20/100*Inputs!$F$59*Inputs!$F$60/BJ16,Inputs!$F$57*Inputs!$F$36*BJ20/100) -> 0
D23: Owner's costs | E23: USD m | G23: =SUM(J23:BJ23) -> 46.18 | J23: =Inputs!$F$61*IF(Inputs!$F$34=1,Inputs!$F$36,1)*(Inputs!J307+IF(AND(Inputs!$F$34=1,J8>Inputs!$F$237,J8<=Time!$F$11),Inputs!$F$239,0))/100+IF(AND(Inputs!$F$34<>1,J8>=Inputs!$F$240,J8<=Inputs!$F$241),Inputs!$F$69/(Inputs!$F$241-Inputs!$F$240+1),0) -> 5.5416 | K23: =Inputs!$F$61*IF(Inputs!$F$34=1,Inputs!$F$36,1)*(Inputs!K307+IF(AND(Inputs!$F$34=1,K8>Inputs!$F$237,K8<=Time!$F$11),Inputs!$F$239,0))/100+IF(AND(Inputs!$F$34<>1,K8>=Inputs!$F$240,K8<=Inputs!$F$241),Inputs!$F$69/(Inputs!$F$241-Inputs!$F$240+1),0) -> 1.26995 | L23: =Inputs!$F$61*IF(Inputs!$F$34=1,Inputs!$F$36,1)*(Inputs!L307+IF(AND(Inputs!$F$34=1,L8>Inputs!$F$237,L8<=Time!$F$11),Inputs!$F$239,0))/100+IF(AND(Inputs!$F$34<>1,L8>=Inputs!$F$240,L8<=Inputs!$F$241),Inputs!$F$69/(Inputs!$F$241-Inputs!$F$240+1),0) -> 1.26995 | M23: =Inputs!$F$61*IF(Inputs!$F$34=1,Inputs!$F$36,1)*(Inputs!M307+IF(AND(Inputs!$F$34=1,M8>Inputs!$F$237,M8<=Time!$F$11),Inputs!$F$239,0))/100+IF(AND(Inputs!$F$34<>1,M8>=Inputs!$F$240,M8<=Inputs!$F$241),Inputs!$F$69/(Inputs!$F$241-Inputs!$F$240+1),0) -> 1.26995 | N23: =Inputs!$F$61*IF(Inputs!$F$34=1,Inputs!$F$36,1)*(Inputs!N307+IF(AND(Inputs!$F$34=1,N8>Inputs!$F$237,N8<=Time!$F$11),Inputs!$F$239,0))/100+IF(AND(Inputs!$F$34<>1,N8>=Inputs!$F$240,N8<=Inputs!$F$241),Inputs!$F$69/(Inputs!$F$241-Inputs!$F$240+1),0) -> 1.26995 | O23: =Inputs!$F$61*IF(Inputs!$F$34=1,Inputs!$F$36,1)*(Inputs!O307+IF(AND(Inputs!$F$34=1,O8>Inputs!$F$237,O8<=Time!$F$11),Inputs!$F$239,0))/100+IF(AND(Inputs!$F$34<>1,O8>=Inputs!$F$240,O8<=Inputs!$F$241),Inputs!$F$69/(Inputs!$F$241-Inputs!$F$240+1),0) -> 1.26995 | P23: =Inputs!$F$61*IF(Inputs!$F$34=1,Inputs!$F$36,1)*(Inputs!P307+IF(AND(Inputs!$F$34=1,P8>Inputs!$F$237,P8<=Time!$F$11),Inputs!$F$239,0))/100+IF(AND(Inputs!$F$34<>1,P8>=Inputs!$F$240,P8<=Inputs!$F$241),Inputs!$F$69/(Inputs!$F$241-Inputs!$F$240+1),0) -> 1.26995 | Q23: =Inputs!$F$61*IF(Inputs!$F$34=1,Inputs!$F$36,1)*(Inputs!Q307+IF(AND(Inputs!$F$34=1,Q8>Inputs!$F$237,Q8<=Time!$F$11),Inputs!$F$239,0))/100+IF(AND(Inputs!$F$34<>1,Q8>=Inputs!$F$240,Q8<=Inputs!$F$241),Inputs!$F$69/(Inputs!$F$241-Inputs!$F$240+1),0) -> 1.26995 | ... BJ23: =Inputs!$F$61*IF(Inputs!$F$34=1,Inputs!$F$36,1)*(Inputs!BJ307+IF(AND(Inputs!$F$34=1,BJ8>Inputs!$F$237,BJ8<=Time!$F$11),Inputs!$F$239,0))/100+IF(AND(Inputs!$F$34<>1,BJ8>=Inputs!$F$240,BJ8<=Inputs!$F$241),Inputs!$F$69/(Inputs!$F$241-Inputs!$F$240+1),0) -> 0
D24: Insurance during construction | E24: USD m | G24: =SUM(J24:BJ24) -> 7.62 | J24: =Inputs!$F$62*Inputs!$F$36*(Inputs!$F$243*IF(J8=1,1,0)+(1-Inputs!$F$243)*IF(J8=Inputs!$F$242,1,0)) -> 6.477 | K24: =Inputs!$F$62*Inputs!$F$36*(Inputs!$F$243*IF(K8=1,1,0)+(1-Inputs!$F$243)*IF(K8=Inputs!$F$242,1,0)) -> 0 | L24: =Inputs!$F$62*Inputs!$F$36*(Inputs!$F$243*IF(L8=1,1,0)+(1-Inputs!$F$243)*IF(L8=Inputs!$F$242,1,0)) -> 0 | M24: =Inputs!$F$62*Inputs!$F$36*(Inputs!$F$243*IF(M8=1,1,0)+(1-Inputs!$F$243)*IF(M8=Inputs!$F$242,1,0)) -> 0 | N24: =Inputs!$F$62*Inputs!$F$36*(Inputs!$F$243*IF(N8=1,1,0)+(1-Inputs!$F$243)*IF(N8=Inputs!$F$242,1,0)) -> 0 | O24: =Inputs!$F$62*Inputs!$F$36*(Inputs!$F$243*IF(O8=1,1,0)+(1-Inputs!$F$243)*IF(O8=Inputs!$F$242,1,0)) -> 0 | P24: =Inputs!$F$62*Inputs!$F$36*(Inputs!$F$243*IF(P8=1,1,0)+(1-Inputs!$F$243)*IF(P8=Inputs!$F$242,1,0)) -> 0 | Q24: =Inputs!$F$62*Inputs!$F$36*(Inputs!$F$243*IF(Q8=1,1,0)+(1-Inputs!$F$243)*IF(Q8=Inputs!$F$242,1,0)) -> 0 | ... BJ24: =Inputs!$F$62*Inputs!$F$36*(Inputs!$F$243*IF(BJ8=1,1,0)+(1-Inputs!$F$243)*IF(BJ8=Inputs!$F$242,1,0)) -> 0
D25: Development costs and fee | E25: USD m | G25: =SUM(J25:BJ25) -> 32.63 | J25: =IF(J8=1,Inputs!$F$63+Inputs!$F$64,0) -> 32.63 | K25: =IF(K8=1,Inputs!$F$63+Inputs!$F$64,0) -> 0 | L25: =IF(L8=1,Inputs!$F$63+Inputs!$F$64,0) -> 0 | M25: =IF(M8=1,Inputs!$F$63+Inputs!$F$64,0) -> 0 | N25: =IF(N8=1,Inputs!$F$63+Inputs!$F$64,0) -> 0 | O25: =IF(O8=1,Inputs!$F$63+Inputs!$F$64,0) -> 0 | P25: =IF(P8=1,Inputs!$F$63+Inputs!$F$64,0) -> 0 | Q25: =IF(Q8=1,Inputs!$F$63+Inputs!$F$64,0) -> 0 | ... BJ25: =IF(BJ8=1,Inputs!$F$63+Inputs!$F$64,0) -> 0
D26: Lenders' advisors and legal | E26: USD m | G26: =SUM(J26:BJ26) -> 8.97 | J26: =Inputs!$F$65*Inputs!$F$36*(Inputs!$F$244*IF(J8=1,1,0)+(1-Inputs!$F$244)/(Time!$F$11-1)*IF(AND(J8>1,J8<=Time!$F$11),1,0)) -> 6.279 | K26: =Inputs!$F$65*Inputs!$F$36*(Inputs!$F$244*IF(K8=1,1,0)+(1-Inputs!$F$244)/(Time!$F$11-1)*IF(AND(K8>1,K8<=Time!$F$11),1,0)) -> 0.08409375 | L26: =Inputs!$F$65*Inputs!$F$36*(Inputs!$F$244*IF(L8=1,1,0)+(1-Inputs!$F$244)/(Time!$F$11-1)*IF(AND(L8>1,L8<=Time!$F$11),1,0)) -> 0.08409375 | M26: =Inputs!$F$65*Inputs!$F$36*(Inputs!$F$244*IF(M8=1,1,0)+(1-Inputs!$F$244)/(Time!$F$11-1)*IF(AND(M8>1,M8<=Time!$F$11),1,0)) -> 0.08409375 | N26: =Inputs!$F$65*Inputs!$F$36*(Inputs!$F$244*IF(N8=1,1,0)+(1-Inputs!$F$244)/(Time!$F$11-1)*IF(AND(N8>1,N8<=Time!$F$11),1,0)) -> 0.08409375 | O26: =Inputs!$F$65*Inputs!$F$36*(Inputs!$F$244*IF(O8=1,1,0)+(1-Inputs!$F$244)/(Time!$F$11-1)*IF(AND(O8>1,O8<=Time!$F$11),1,0)) -> 0.08409375 | P26: =Inputs!$F$65*Inputs!$F$36*(Inputs!$F$244*IF(P8=1,1,0)+(1-Inputs!$F$244)/(Time!$F$11-1)*IF(AND(P8>1,P8<=Time!$F$11),1,0)) -> 0.08409375 | Q26: =Inputs!$F$65*Inputs!$F$36*(Inputs!$F$244*IF(Q8=1,1,0)+(1-Inputs!$F$244)/(Time!$F$11-1)*IF(AND(Q8>1,Q8<=Time!$F$11),1,0)) -> 0.08409375 | ... BJ26: =Inputs!$F$65*Inputs!$F$36*(Inputs!$F$244*IF(BJ8=1,1,0)+(1-Inputs!$F$244)/(Time!$F$11-1)*IF(AND(BJ8>1,BJ8<=Time!$F$11),1,0)) -> 0
D27: Contingency (FC: pro rata with EPC progress payments) | E27: USD m | G27: =SUM(J27:BJ27) -> 38.4 | J27: =IF(Inputs!$F$34=1,Inputs!$F$66*Inputs!$F$36*J21/SUM($J$21:$BJ$21),0) -> 0 | K27: =IF(Inputs!$F$34=1,Inputs!$F$66*Inputs!$F$36*K21/SUM($J$21:$BJ$21),0) -> 0.0050269091 | L27: =IF(Inputs!$F$34=1,Inputs!$F$66*Inputs!$F$36*L21/SUM($J$21:$BJ$21),0) -> 0.052736 | M27: =IF(Inputs!$F$34=1,Inputs!$F$66*Inputs!$F$36*M21/SUM($J$21:$BJ$21),0) -> 0.15076073 | N27: =IF(Inputs!$F$34=1,Inputs!$F$66*Inputs!$F$36*N21/SUM($J$21:$BJ$21),0) -> 0.29295709 | O27: =IF(Inputs!$F$34=1,Inputs!$F$66*Inputs!$F$36*O21/SUM($J$21:$BJ$21),0) -> 0.47076073 | P27: =IF(Inputs!$F$34=1,Inputs!$F$66*Inputs!$F$36*P21/SUM($J$21:$BJ$21),0) -> 0.67472291 | Q27: =IF(Inputs!$F$34=1,Inputs!$F$66*Inputs!$F$36*Q21/SUM($J$21:$BJ$21),0) -> 0.89534836 | ... BJ27: =IF(Inputs!$F$34=1,Inputs!$F$66*Inputs!$F$36*BJ21/SUM($J$21:$BJ$21),0) -> 0
D28: Initial working capital | E28: USD m | G28: =SUM(J28:BJ28) -> 5.35 | J28: =IF(J8=Time!$F$11,Inputs!$F$67*Inputs!$F$36,0) -> 0 | K28: =IF(K8=Time!$F$11,Inputs!$F$67*Inputs!$F$36,0) -> 0 | L28: =IF(L8=Time!$F$11,Inputs!$F$67*Inputs!$F$36,0) -> 0 | M28: =IF(M8=Time!$F$11,Inputs!$F$67*Inputs!$F$36,0) -> 0 | N28: =IF(N8=Time!$F$11,Inputs!$F$67*Inputs!$F$36,0) -> 0 | O28: =IF(O8=Time!$F$11,Inputs!$F$67*Inputs!$F$36,0) -> 0 | P28: =IF(P8=Time!$F$11,Inputs!$F$67*Inputs!$F$36,0) -> 0 | Q28: =IF(Q8=Time!$F$11,Inputs!$F$67*Inputs!$F$36,0) -> 0 | ... BJ28: =IF(BJ8=Time!$F$11,Inputs!$F$67*Inputs!$F$36,0) -> 0
D29: Overrun items (actual) | E29: USD m | G29: =SUM(J29:BJ29) -> 0 | J29: =IF(Inputs!$F$34<>1,Inputs!J308,0) -> 0 | K29: =IF(Inputs!$F$34<>1,Inputs!K308,0) -> 0 | L29: =IF(Inputs!$F$34<>1,Inputs!L308,0) -> 0 | M29: =IF(Inputs!$F$34<>1,Inputs!M308,0) -> 0 | N29: =IF(Inputs!$F$34<>1,Inputs!N308,0) -> 0 | O29: =IF(Inputs!$F$34<>1,Inputs!O308,0) -> 0 | P29: =IF(Inputs!$F$34<>1,Inputs!P308,0) -> 0 | Q29: =IF(Inputs!$F$34<>1,Inputs!Q308,0) -> 0 | ... BJ29: =IF(Inputs!$F$34<>1,Inputs!BJ308,0) -> 0
D30: KCR forward rate traded at financial close (covered interest parity) | E30: KCR/USD | J30: =Inputs!$F$60*((1+Inputs!$F$73/100)/(1+INDEX(Inputs!$J$291:$BN$291,1,J12)/100))^((J10-Inputs!$F$187)/Inputs!$F$248) -> 525.95633 | K30: =Inputs!$F$60*((1+Inputs!$F$73/100)/(1+INDEX(Inputs!$J$291:$BN$291,1,K12)/100))^((K10-Inputs!$F$187)/Inputs!$F$248) -> 530.37314 | L30: =Inputs!$F$60*((1+Inputs!$F$73/100)/(1+INDEX(Inputs!$J$291:$BN$291,1,L12)/100))^((L10-Inputs!$F$187)/Inputs!$F$248) -> 534.97614 | M30: =Inputs!$F$60*((1+Inputs!$F$73/100)/(1+INDEX(Inputs!$J$291:$BN$291,1,M12)/100))^((M10-Inputs!$F$187)/Inputs!$F$248) -> 539.46869 | N30: =Inputs!$F$60*((1+Inputs!$F$73/100)/(1+INDEX(Inputs!$J$291:$BN$291,1,N12)/100))^((N10-Inputs!$F$187)/Inputs!$F$248) -> 544.15062 | O30: =Inputs!$F$60*((1+Inputs!$F$73/100)/(1+INDEX(Inputs!$J$291:$BN$291,1,O12)/100))^((O10-Inputs!$F$187)/Inputs!$F$248) -> 548.09063 | P30: =Inputs!$F$60*((1+Inputs!$F$73/100)/(1+INDEX(Inputs!$J$291:$BN$291,1,P12)/100))^((P10-Inputs!$F$187)/Inputs!$F$248) -> 552.27383 | Q30: =Inputs!$F$60*((1+Inputs!$F$73/100)/(1+INDEX(Inputs!$J$291:$BN$291,1,Q12)/100))^((Q10-Inputs!$F$187)/Inputs!$F$248) -> 556.94247 | ... BJ30: =Inputs!$F$60*((1+Inputs!$F$73/100)/(1+INDEX(Inputs!$J$291:$BN$291,1,BJ12)/100))^((BJ10-Inputs!$F$187)/Inputs!$F$248) -> 797.02768
D31: FX forward settlement on onshore EPC payments (gain to the project) | E31: USD m | G31: =SUM(J31:BJ31) -> 0 | J31: =IF(Inputs!$F$34<>1,Inputs!$F$259*J34*(1/J16-1/J30),0) -> 0 | K31: =IF(Inputs!$F$34<>1,Inputs!$F$259*K34*(1/K16-1/K30),0) -> 0 | L31: =IF(Inputs!$F$34<>1,Inputs!$F$259*L34*(1/L16-1/L30),0) -> 0 | M31: =IF(Inputs!$F$34<>1,Inputs!$F$259*M34*(1/M16-1/M30),0) -> 0 | N31: =IF(Inputs!$F$34<>1,Inputs!$F$259*N34*(1/N16-1/N30),0) -> 0 | O31: =IF(Inputs!$F$34<>1,Inputs!$F$259*O34*(1/O16-1/O30),0) -> 0 | P31: =IF(Inputs!$F$34<>1,Inputs!$F$259*P34*(1/P16-1/P30),0) -> 0 | Q31: =IF(Inputs!$F$34<>1,Inputs!$F$259*Q34*(1/Q16-1/Q30),0) -> 0 | ... BJ31: =IF(Inputs!$F$34<>1,Inputs!$F$259*BJ34*(1/BJ16-1/BJ30),0) -> 0
D32: Uses before financing costs (net of FX hedge settlements) | E32: USD m | G32: =SUM(J32:BJ32) -> 710.99 | J32: =J22+J23+J24+J25+J26+J27+J28+J29-J31 -> 108.1116 | K32: =K22+K23+K24+K25+K26+K27+K28+K29-K31 -> 1.4208294 | L32: =L22+L23+L24+L25+L26+L27+L28+L29-L31 -> 2.0546745 | M32: =M22+M23+M24+M25+M26+M27+M28+M29-M31 -> 3.3569942 | N32: =N22+N23+N24+N25+N26+N27+N28+N29-N31 -> 5.2461618 | O32: =O22+O23+O24+O25+O26+O27+O28+O29-O31 -> 7.6083942 | P32: =P22+P23+P24+P25+P26+P27+P28+P29-P31 -> 10.318159 | Q32: =Q22+Q23+Q24+Q25+Q26+Q27+Q28+Q29-Q31 -> 13.249306 | ... BJ32: =BJ22+BJ23+BJ24+BJ25+BJ26+BJ27+BJ28+BJ29-BJ31 -> 0
B33: VAT on onshore EPC (KCR m) and UBK VAT facility
D34: Onshore EPC payments | E34: KCR m | G34: =SUM(J34:BJ34) -> 42938.798 | J34: =J20/100*Inputs!$F$59*Inputs!$F$60*Inputs!$F$36 -> 4293.8798 | K34: =K20/100*Inputs!$F$59*Inputs!$F$60*Inputs!$F$36 -> 4.6373902 | L34: =L20/100*Inputs!$F$59*Inputs!$F$60*Inputs!$F$36 -> 48.649658 | M34: =M20/100*Inputs!$F$59*Inputs!$F$60*Inputs!$F$36 -> 139.07877 | N34: =N20/100*Inputs!$F$59*Inputs!$F$60*Inputs!$F$36 -> 270.25679 | O34: =O20/100*Inputs!$F$59*Inputs!$F$60*Inputs!$F$36 -> 434.283 | P34: =P20/100*Inputs!$F$59*Inputs!$F$60*Inputs!$F$36 -> 622.44082 | Q34: =Q20/100*Inputs!$F$59*Inputs!$F$60*Inputs!$F$36 -> 825.97072 | ... BJ34: =BJ20/100*Inputs!$F$59*Inputs!$F$60*Inputs!$F$36 -> 0
D35: VAT paid (drawn on the VAT facility) | E35: KCR m | G35: =SUM(J35:BJ35) -> 7728.9836 | J35: =Inputs!$F$70/100*J34 -> 772.89836 | K35: =Inputs!$F$70/100*K34 -> 0.83473023 | L35: =Inputs!$F$70/100*L34 -> 8.7569385 | M35: =Inputs!$F$70/100*M34 -> 25.034178 | N35: =Inputs!$F$70/100*N34 -> 48.646223 | O35: =Inputs!$F$70/100*O34 -> 78.170941 | P35: =Inputs!$F$70/100*P34 -> 112.03935 | Q35: =Inputs!$F$70/100*Q34 -> 148.67473 | ... BJ35: =Inputs!$F$70/100*BJ34 -> 0
D36: VAT refunds (9-month lag) repaying the facility | E36: KCR m | G36: =SUM(J36:BJ36) -> 7728.9836 | J36: =SUMIFS($J$35:$BJ$35,$J$8:$BJ$8,J8-Inputs!$F$246) -> 0 | K36: =SUMIFS($J$35:$BJ$35,$J$8:$BJ$8,K8-Inputs!$F$246) -> 0 | L36: =SUMIFS($J$35:$BJ$35,$J$8:$BJ$8,L8-Inputs!$F$246) -> 0 | M36: =SUMIFS($J$35:$BJ$35,$J$8:$BJ$8,M8-Inputs!$F$246) -> 0 | N36: =SUMIFS($J$35:$BJ$35,$J$8:$BJ$8,N8-Inputs!$F$246) -> 0 | O36: =SUMIFS($J$35:$BJ$35,$J$8:$BJ$8,O8-Inputs!$F$246) -> 0 | P36: =SUMIFS($J$35:$BJ$35,$J$8:$BJ$8,P8-Inputs!$F$246) -> 0 | Q36: =SUMIFS($J$35:$BJ$35,$J$8:$BJ$8,Q8-Inputs!$F$246) -> 0 | ... BJ36: =SUMIFS($J$35:$BJ$35,$J$8:$BJ$8,BJ8-Inputs!$F$246) -> 0
D37: VAT facility balance | E37: KCR m | J37: =I37+J35-J36 -> 772.89836 | K37: =J37+K35-K36 -> 773.73309 | L37: =K37+L35-L36 -> 782.49003 | M37: =L37+M35-M36 -> 807.52421 | N37: =M37+N35-N36 -> 856.17043 | O37: =N37+O35-O36 -> 934.34137 | P37: =O37+P35-P36 -> 1046.3807 | Q37: =P37+Q35-Q36 -> 1195.0555 | ... BJ37: =BI37+BJ35-BJ36 -> 0
D38: VAT facility interest | E38: USD m | G38: =SUM(J38:BJ38) -> 1.6348671 | J38: =I37*(J18+Inputs!$F$71)/100*J11/Inputs!$F$248/J16 -> 0 | K38: =J37*(K18+Inputs!$F$71)/100*K11/Inputs!$F$248/K16 -> 0.019445724 | L38: =K37*(L18+Inputs!$F$71)/100*L11/Inputs!$F$248/L16 -> 0.020031042 | M38: =L37*(M18+Inputs!$F$71)/100*M11/Inputs!$F$248/M16 -> 0.019521849 | N38: =M37*(N18+Inputs!$F$71)/100*N11/Inputs!$F$248/N16 -> 0.020730431 | O38: =N37*(O18+Inputs!$F$71)/100*O11/Inputs!$F$248/O16 -> 0.021886847 | P38: =O37*(P18+Inputs!$F$71)/100*P11/Inputs!$F$248/P16 -> 0.021483009 | Q38: =P37*(Q18+Inputs!$F$71)/100*Q11/Inputs!$F$248/Q16 -> 0.026524861 | ... BJ38: =BI37*(BJ18+Inputs!$F$71)/100*BJ11/Inputs!$F$248/BJ16 -> 0

Sheet Operations
A1: Case P: Belanou Combined Cycle Power Project, Republic of Kessara
A2: Operations: macro paths, plant, revenue, operating costs, working capital
A3: Units in column E; constants in column F; row totals in column G; first period in column J. Inputs: blue on yellow. Links from other sheets: green.
D4: Label | E4: Unit | F4: Constant | G4: Total
D5: Period ending | J5: 2018H2 | K5: 2019H1 | L5: 2019H2 | M5: 2020H1 | N5: 2020H2 | O5: 2021H1 | P5: 2021H2 | Q5: 2022H1 | R5: 2022H2 | S5: 2023H1 | T5: 2023H2 | U5: 2024H1 | V5: 2024H2 | W5: 2025H1 | X5: 2025H2 | Y5: 2026H1 | Z5: 2026H2 | AA5: 2027H1 | AB5: 2027H2 | AC5: 2028H1 | AD5: 2028H2 | AE5: 2029H1 | AF5: 2029H2 | AG5: 2030H1 | AH5: 2030H2 | AI5: 2031H1 | AJ5: 2031H2 | AK5: 2032H1 | AL5: 2032H2 | AM5: 2033H1 | AN5: 2033H2 | AO5: 2034H1 | AP5: 2034H2 | AQ5: 2035H1 | AR5: 2035H2 | AS5: 2036H1 | AT5: 2036H2 | AU5: 2037H1 | AV5: 2037H2 | AW5: 2038H1 | AX5: 2038H2 | AY5: 2039H1 | AZ5: 2039H2 | BA5: 2040H1 | BB5: 2040H2 | BC5: 2041H1 | BD5: 2041H2 | BE5: 2042H1 | BF5: 2042H2 | BG5: 2043H1 | BH5: 2043H2 | BI5: 2044H1 | BJ5: 2044H2 | BK5: 2045H1 | BL5: 2045H2 | BM5: 2046H1 | BN5: 2046H2
B7: Macro paths
D8: Base rate before sensitivity shift | E8: % | J8: =CHOOSE(Inputs!$F$33,Inputs!J291,Inputs!J292,Inputs!J293) -> 2.52 | K8: =CHOOSE(Inputs!$F$33,Inputs!K291,Inputs!K292,Inputs!K293) -> 2.79 | L8: =CHOOSE(Inputs!$F$33,Inputs!L291,Inputs!L292,Inputs!L293) -> 2.94 | M8: =CHOOSE(Inputs!$F$33,Inputs!M291,Inputs!M292,Inputs!M293) -> 3.02 | N8: =CHOOSE(Inputs!$F$33,Inputs!N291,Inputs!N292,Inputs!N293) -> 3.06 | O8: =CHOOSE(Inputs!$F$33,Inputs!O291,Inputs!O292,Inputs!O293) -> 3.09 | P8: =CHOOSE(Inputs!$F$33,Inputs!P291,Inputs!P292,Inputs!P293) -> 3.09 | Q8: =CHOOSE(Inputs!$F$33,Inputs!Q291,Inputs!Q292,Inputs!Q293) -> 3.11 | ... BN8: =CHOOSE(Inputs!$F$33,Inputs!BN291,Inputs!BN292,Inputs!BN293) -> 3.12
D9: Base rate (6M LIBOR / Term SOFR + CAS) | E9: % | J9: =J8+Inputs!$F$42*Time!J39 -> 2.52 | K9: =K8+Inputs!$F$42*Time!K39 -> 2.79 | L9: =L8+Inputs!$F$42*Time!L39 -> 2.94 | M9: =M8+Inputs!$F$42*Time!M39 -> 3.02 | N9: =N8+Inputs!$F$42*Time!N39 -> 3.06 | O9: =O8+Inputs!$F$42*Time!O39 -> 3.09 | P9: =P8+Inputs!$F$42*Time!P39 -> 3.09 | Q9: =Q8+Inputs!$F$42*Time!Q39 -> 3.11 | ... BN9: =BN8+Inputs!$F$42*Time!BN39 -> 3.12
D10: KCR per USD before devaluation sensitivity | E10: KCR/USD | J10: =CHOOSE(Inputs!$F$33,Inputs!$F$60*Time!$F$16^((Time!J20-Inputs!$F$212)*Time!J24),IF(Inputs!J294>0,Inputs!J294,I10*((1+J13/100)/(1+J12/100))^Time!J24),IF(Time!J54=0,Inputs!J294,I10*Time!$F$16^Time!J24)) -> 526.00677 | K10: =CHOOSE(Inputs!$F$33,Inputs!$F$60*Time!$F$16^((Time!K20-Inputs!$F$212)*Time!K24),IF(Inputs!K294>0,Inputs!K294,J10*((1+K13/100)/(1+K12/100))^Time!K24),IF(Time!K54=0,Inputs!K294,J10*Time!$F$16^Time!K24)) -> 539.47351 | L10: =CHOOSE(Inputs!$F$33,Inputs!$F$60*Time!$F$16^((Time!L20-Inputs!$F$212)*Time!L24),IF(Inputs!L294>0,Inputs!L294,K10*((1+L13/100)/(1+L12/100))^Time!L24),IF(Time!L54=0,Inputs!L294,K10*Time!$F$16^Time!L24)) -> 553.28501 | M10: =CHOOSE(Inputs!$F$33,Inputs!$F$60*Time!$F$16^((Time!M20-Inputs!$F$212)*Time!M24),IF(Inputs!M294>0,Inputs!M294,L10*((1+M13/100)/(1+M12/100))^Time!M24),IF(Time!M54=0,Inputs!M294,L10*Time!$F$16^Time!M24)) -> 567.45012 | N10: =CHOOSE(Inputs!$F$33,Inputs!$F$60*Time!$F$16^((Time!N20-Inputs!$F$212)*Time!N24),IF(Inputs!N294>0,Inputs!N294,M10*((1+N13/100)/(1+N12/100))^Time!N24),IF(Time!N54=0,Inputs!N294,M10*Time!$F$16^Time!N24)) -> 581.97787 | O10: =CHOOSE(Inputs!$F$33,Inputs!$F$60*Time!$F$16^((Time!O20-Inputs!$F$212)*Time!O24),IF(Inputs!O294>0,Inputs!O294,N10*((1+O13/100)/(1+O12/100))^Time!O24),IF(Time!O54=0,Inputs!O294,N10*Time!$F$16^Time!O24)) -> 596.87757 | P10: =CHOOSE(Inputs!$F$33,Inputs!$F$60*Time!$F$16^((Time!P20-Inputs!$F$212)*Time!P24),IF(Inputs!P294>0,Inputs!P294,O10*((1+P13/100)/(1+P12/100))^Time!P24),IF(Time!P54=0,Inputs!P294,O10*Time!$F$16^Time!P24)) -> 612.15872 | Q10: =CHOOSE(Inputs!$F$33,Inputs!$F$60*Time!$F$16^((Time!Q20-Inputs!$F$212)*Time!Q24),IF(Inputs!Q294>0,Inputs!Q294,P10*((1+Q13/100)/(1+Q12/100))^Time!Q24),IF(Time!Q54=0,Inputs!Q294,P10*Time!$F$16^Time!Q24)) -> 627.8311 | ... BN10: =CHOOSE(Inputs!$F$33,Inputs!$F$60*Time!$F$16^((Time!BN20-Inputs!$F$212)*Time!BN24),IF(Inputs!BN294>0,Inputs!BN294,BM10*((1+BN13/100)/(1+BN12/100))^Time!BN24),IF(Time!BN54=0,Inputs!BN294,BM10*Time!$F$16^Time!BN24)) -> 2166.7223
D11: KCR per USD, period average | E11: KCR/USD | J11: =J10/(1-Inputs!$F$43*Time!J39) -> 526.00677 | K11: =K10/(1-Inputs!$F$43*Time!K39) -> 539.47351 | L11: =L10/(1-Inputs!$F$43*Time!L39) -> 553.28501 | M11: =M10/(1-Inputs!$F$43*Time!M39) -> 567.45012 | N11: =N10/(1-Inputs!$F$43*Time!N39) -> 581.97787 | O11: =O10/(1-Inputs!$F$43*Time!O39) -> 596.87757 | P11: =P10/(1-Inputs!$F$43*Time!P39) -> 612.15872 | Q11: =Q10/(1-Inputs!$F$43*Time!Q39) -> 627.8311 | ... BN11: =BN10/(1-Inputs!$F$43*Time!BN39) -> 2166.7223
D12: US CPI change, current year | E12: % | J12: =CHOOSE(Inputs!$F$33,INDEX(Inputs!$J$283:$AR$283,1,MATCH((Time!J26-0),Inputs!$J$282:$AR$282,0)),INDEX(Inputs!$J$285:$AR$285,1,MATCH((Time!J26-0),Inputs!$J$282:$AR$282,0)),INDEX(Inputs!$J$287:$AR$287,1,MATCH((Time!J26-0),Inputs!$J$282:$AR$282,0))) -> 2.2 | K12: =CHOOSE(Inputs!$F$33,INDEX(Inputs!$J$283:$AR$283,1,MATCH((Time!K26-0),Inputs!$J$282:$AR$282,0)),INDEX(Inputs!$J$285:$AR$285,1,MATCH((Time!K26-0),Inputs!$J$282:$AR$282,0)),INDEX(Inputs!$J$287:$AR$287,1,MATCH((Time!K26-0),Inputs!$J$282:$AR$282,0))) -> 2.2 | L12: =CHOOSE(Inputs!$F$33,INDEX(Inputs!$J$283:$AR$283,1,MATCH((Time!L26-0),Inputs!$J$282:$AR$282,0)),INDEX(Inputs!$J$285:$AR$285,1,MATCH((Time!L26-0),Inputs!$J$282:$AR$282,0)),INDEX(Inputs!$J$287:$AR$287,1,MATCH((Time!L26-0),Inputs!$J$282:$AR$282,0))) -> 2.2 | M12: =CHOOSE(Inputs!$F$33,INDEX(Inputs!$J$283:$AR$283,1,MATCH((Time!M26-0),Inputs!$J$282:$AR$282,0)),INDEX(Inputs!$J$285:$AR$285,1,MATCH((Time!M26-0),Inputs!$J$282:$AR$282,0)),INDEX(Inputs!$J$287:$AR$287,1,MATCH((Time!M26-0),Inputs!$J$282:$AR$282,0))) -> 2.2 | N12: =CHOOSE(Inputs!$F$33,INDEX(Inputs!$J$283:$AR$283,1,MATCH((Time!N26-0),Inputs!$J$282:$AR$282,0)),INDEX(Inputs!$J$285:$AR$285,1,MATCH((Time!N26-0),Inputs!$J$282:$AR$282,0)),INDEX(Inputs!$J$287:$AR$287,1,MATCH((Time!N26-0),Inputs!$J$282:$AR$282,0))) -> 2.2 | O12: =CHOOSE(Inputs!$F$33,INDEX(Inputs!$J$283:$AR$283,1,MATCH((Time!O26-0),Inputs!$J$282:$AR$282,0)),INDEX(Inputs!$J$285:$AR$285,1,MATCH((Time!O26-0),Inputs!$J$282:$AR$282,0)),INDEX(Inputs!$J$287:$AR$287,1,MATCH((Time!O26-0),Inputs!$J$282:$AR$282,0))) -> 2.2 | P12: =CHOOSE(Inputs!$F$33,INDEX(Inputs!$J$283:$AR$283,1,MATCH((Time!P26-0),Inputs!$J$282:$AR$282,0)),INDEX(Inputs!$J$285:$AR$285,1,MATCH((Time!P26-0),Inputs!$J$282:$AR$282,0)),INDEX(Inputs!$J$287:$AR$287,1,MATCH((Time!P26-0),Inputs!$J$282:$AR$282,0))) -> 2.2 | Q12: =CHOOSE(Inputs!$F$33,INDEX(Inputs!$J$283:$AR$283,1,MATCH((Time!Q26-0),Inputs!$J$282:$AR$282,0)),INDEX(Inputs!$J$285:$AR$285,1,MATCH((Time!Q26-0),Inputs!$J$282:$AR$282,0)),INDEX(Inputs!$J$287:$AR$287,1,MATCH((Time!Q26-0),Inputs!$J$282:$AR$282,0))) -> 2.2 | ... BN12: =CHOOSE(Inputs!$F$33,INDEX(Inputs!$J$283:$AR$283,1,MATCH((Time!BN26-0),Inputs!$J$282:$AR$282,0)),INDEX(Inputs!$J$285:$AR$285,1,MATCH((Time!BN26-0),Inputs!$J$282:$AR$282,0)),INDEX(Inputs!$J$287:$AR$287,1,MATCH((Time!BN26-0),Inputs!$J$282:$AR$282,0))) -> 2.2
D13: Kessara CPI change, current year | E13: % | J13: =CHOOSE(Inputs!$F$33,INDEX(Inputs!$J$284:$AR$284,1,MATCH((Time!J26-0),Inputs!$J$282:$AR$282,0)),INDEX(Inputs!$J$286:$AR$286,1,MATCH((Time!J26-0),Inputs!$J$282:$AR$282,0)),INDEX(Inputs!$J$288:$AR$288,1,MATCH((Time!J26-0),Inputs!$J$282:$AR$282,0))) -> 7.5 | K13: =CHOOSE(Inputs!$F$33,INDEX(Inputs!$J$284:$AR$284,1,MATCH((Time!K26-0),Inputs!$J$282:$AR$282,0)),INDEX(Inputs!$J$286:$AR$286,1,MATCH((Time!K26-0),Inputs!$J$282:$AR$282,0)),INDEX(Inputs!$J$288:$AR$288,1,MATCH((Time!K26-0),Inputs!$J$282:$AR$282,0))) -> 7.5 | L13: =CHOOSE(Inputs!$F$33,INDEX(Inputs!$J$284:$AR$284,1,MATCH((Time!L26-0),Inputs!$J$282:$AR$282,0)),INDEX(Inputs!$J$286:$AR$286,1,MATCH((Time!L26-0),Inputs!$J$282:$AR$282,0)),INDEX(Inputs!$J$288:$AR$288,1,MATCH((Time!L26-0),Inputs!$J$282:$AR$282,0))) -> 7.5 | M13: =CHOOSE(Inputs!$F$33,INDEX(Inputs!$J$284:$AR$284,1,MATCH((Time!M26-0),Inputs!$J$282:$AR$282,0)),INDEX(Inputs!$J$286:$AR$286,1,MATCH((Time!M26-0),Inputs!$J$282:$AR$282,0)),INDEX(Inputs!$J$288:$AR$288,1,MATCH((Time!M26-0),Inputs!$J$282:$AR$282,0))) -> 7.5 | N13: =CHOOSE(Inputs!$F$33,INDEX(Inputs!$J$284:$AR$284,1,MATCH((Time!N26-0),Inputs!$J$282:$AR$282,0)),INDEX(Inputs!$J$286:$AR$286,1,MATCH((Time!N26-0),Inputs!$J$282:$AR$282,0)),INDEX(Inputs!$J$288:$AR$288,1,MATCH((Time!N26-0),Inputs!$J$282:$AR$282,0))) -> 7.5 | O13: =CHOOSE(Inputs!$F$33,INDEX(Inputs!$J$284:$AR$284,1,MATCH((Time!O26-0),Inputs!$J$282:$AR$282,0)),INDEX(Inputs!$J$286:$AR$286,1,MATCH((Time!O26-0),Inputs!$J$282:$AR$282,0)),INDEX(Inputs!$J$288:$AR$288,1,MATCH((Time!O26-0),Inputs!$J$282:$AR$282,0))) -> 7.5 | P13: =CHOOSE(Inputs!$F$33,INDEX(Inputs!$J$284:$AR$284,1,MATCH((Time!P26-0),Inputs!$J$282:$AR$282,0)),INDEX(Inputs!$J$286:$AR$286,1,MATCH((Time!P26-0),Inputs!$J$282:$AR$282,0)),INDEX(Inputs!$J$288:$AR$288,1,MATCH((Time!P26-0),Inputs!$J$282:$AR$282,0))) -> 7.5 | Q13: =CHOOSE(Inputs!$F$33,INDEX(Inputs!$J$284:$AR$284,1,MATCH((Time!Q26-0),Inputs!$J$282:$AR$282,0)),INDEX(Inputs!$J$286:$AR$286,1,MATCH((Time!Q26-0),Inputs!$J$282:$AR$282,0)),INDEX(Inputs!$J$288:$AR$288,1,MATCH((Time!Q26-0),Inputs!$J$282:$AR$282,0))) -> 7.5 | ... BN13: =CHOOSE(Inputs!$F$33,INDEX(Inputs!$J$284:$AR$284,1,MATCH((Time!BN26-0),Inputs!$J$282:$AR$282,0)),INDEX(Inputs!$J$286:$AR$286,1,MATCH((Time!BN26-0),Inputs!$J$282:$AR$282,0)),INDEX(Inputs!$J$288:$AR$288,1,MATCH((Time!BN26-0),Inputs!$J$282:$AR$282,0))) -> 7.5
D14: US CPI change, prior year | E14: % | J14: =CHOOSE(Inputs!$F$33,INDEX(Inputs!$J$283:$AR$283,1,MATCH((Time!J26-1),Inputs!$J$282:$AR$282,0)),INDEX(Inputs!$J$285:$AR$285,1,MATCH((Time!J26-1),Inputs!$J$282:$AR$282,0)),INDEX(Inputs!$J$287:$AR$287,1,MATCH((Time!J26-1),Inputs!$J$282:$AR$282,0))) -> 2.1 | K14: =CHOOSE(Inputs!$F$33,INDEX(Inputs!$J$283:$AR$283,1,MATCH((Time!K26-1),Inputs!$J$282:$AR$282,0)),INDEX(Inputs!$J$285:$AR$285,1,MATCH((Time!K26-1),Inputs!$J$282:$AR$282,0)),INDEX(Inputs!$J$287:$AR$287,1,MATCH((Time!K26-1),Inputs!$J$282:$AR$282,0))) -> 2.2 | L14: =CHOOSE(Inputs!$F$33,INDEX(Inputs!$J$283:$AR$283,1,MATCH((Time!L26-1),Inputs!$J$282:$AR$282,0)),INDEX(Inputs!$J$285:$AR$285,1,MATCH((Time!L26-1),Inputs!$J$282:$AR$282,0)),INDEX(Inputs!$J$287:$AR$287,1,MATCH((Time!L26-1),Inputs!$J$282:$AR$282,0))) -> 2.2 | M14: =CHOOSE(Inputs!$F$33,INDEX(Inputs!$J$283:$AR$283,1,MATCH((Time!M26-1),Inputs!$J$282:$AR$282,0)),INDEX(Inputs!$J$285:$AR$285,1,MATCH((Time!M26-1),Inputs!$J$282:$AR$282,0)),INDEX(Inputs!$J$287:$AR$287,1,MATCH((Time!M26-1),Inputs!$J$282:$AR$282,0))) -> 2.2 | N14: =CHOOSE(Inputs!$F$33,INDEX(Inputs!$J$283:$AR$283,1,MATCH((Time!N26-1),Inputs!$J$282:$AR$282,0)),INDEX(Inputs!$J$285:$AR$285,1,MATCH((Time!N26-1),Inputs!$J$282:$AR$282,0)),INDEX(Inputs!$J$287:$AR$287,1,MATCH((Time!N26-1),Inputs!$J$282:$AR$282,0))) -> 2.2 | O14: =CHOOSE(Inputs!$F$33,INDEX(Inputs!$J$283:$AR$283,1,MATCH((Time!O26-1),Inputs!$J$282:$AR$282,0)),INDEX(Inputs!$J$285:$AR$285,1,MATCH((Time!O26-1),Inputs!$J$282:$AR$282,0)),INDEX(Inputs!$J$287:$AR$287,1,MATCH((Time!O26-1),Inputs!$J$282:$AR$282,0))) -> 2.2 | P14: =CHOOSE(Inputs!$F$33,INDEX(Inputs!$J$283:$AR$283,1,MATCH((Time!P26-1),Inputs!$J$282:$AR$282,0)),INDEX(Inputs!$J$285:$AR$285,1,MATCH((Time!P26-1),Inputs!$J$282:$AR$282,0)),INDEX(Inputs!$J$287:$AR$287,1,MATCH((Time!P26-1),Inputs!$J$282:$AR$282,0))) -> 2.2 | Q14: =CHOOSE(Inputs!$F$33,INDEX(Inputs!$J$283:$AR$283,1,MATCH((Time!Q26-1),Inputs!$J$282:$AR$282,0)),INDEX(Inputs!$J$285:$AR$285,1,MATCH((Time!Q26-1),Inputs!$J$282:$AR$282,0)),INDEX(Inputs!$J$287:$AR$287,1,MATCH((Time!Q26-1),Inputs!$J$282:$AR$282,0))) -> 2.2 | ... BN14: =CHOOSE(Inputs!$F$33,INDEX(Inputs!$J$283:$AR$283,1,MATCH((Time!BN26-1),Inputs!$J$282:$AR$282,0)),INDEX(Inputs!$J$285:$AR$285,1,MATCH((Time!BN26-1),Inputs!$J$282:$AR$282,0)),INDEX(Inputs!$J$287:$AR$287,1,MATCH((Time!BN26-1),Inputs!$J$282:$AR$282,0))) -> 2.2
D15: Kessara CPI change, prior year | E15: % | J15: =CHOOSE(Inputs!$F$33,INDEX(Inputs!$J$284:$AR$284,1,MATCH((Time!J26-1),Inputs!$J$282:$AR$282,0)),INDEX(Inputs!$J$286:$AR$286,1,MATCH((Time!J26-1),Inputs!$J$282:$AR$282,0)),INDEX(Inputs!$J$288:$AR$288,1,MATCH((Time!J26-1),Inputs!$J$282:$AR$282,0))) -> 8.1 | K15: =CHOOSE(Inputs!$F$33,INDEX(Inputs!$J$284:$AR$284,1,MATCH((Time!K26-1),Inputs!$J$282:$AR$282,0)),INDEX(Inputs!$J$286:$AR$286,1,MATCH((Time!K26-1),Inputs!$J$282:$AR$282,0)),INDEX(Inputs!$J$288:$AR$288,1,MATCH((Time!K26-1),Inputs!$J$282:$AR$282,0))) -> 7.5 | L15: =CHOOSE(Inputs!$F$33,INDEX(Inputs!$J$284:$AR$284,1,MATCH((Time!L26-1),Inputs!$J$282:$AR$282,0)),INDEX(Inputs!$J$286:$AR$286,1,MATCH((Time!L26-1),Inputs!$J$282:$AR$282,0)),INDEX(Inputs!$J$288:$AR$288,1,MATCH((Time!L26-1),Inputs!$J$282:$AR$282,0))) -> 7.5 | M15: =CHOOSE(Inputs!$F$33,INDEX(Inputs!$J$284:$AR$284,1,MATCH((Time!M26-1),Inputs!$J$282:$AR$282,0)),INDEX(Inputs!$J$286:$AR$286,1,MATCH((Time!M26-1),Inputs!$J$282:$AR$282,0)),INDEX(Inputs!$J$288:$AR$288,1,MATCH((Time!M26-1),Inputs!$J$282:$AR$282,0))) -> 7.5 | N15: =CHOOSE(Inputs!$F$33,INDEX(Inputs!$J$284:$AR$284,1,MATCH((Time!N26-1),Inputs!$J$282:$AR$282,0)),INDEX(Inputs!$J$286:$AR$286,1,MATCH((Time!N26-1),Inputs!$J$282:$AR$282,0)),INDEX(Inputs!$J$288:$AR$288,1,MATCH((Time!N26-1),Inputs!$J$282:$AR$282,0))) -> 7.5 | O15: =CHOOSE(Inputs!$F$33,INDEX(Inputs!$J$284:$AR$284,1,MATCH((Time!O26-1),Inputs!$J$282:$AR$282,0)),INDEX(Inputs!$J$286:$AR$286,1,MATCH((Time!O26-1),Inputs!$J$282:$AR$282,0)),INDEX(Inputs!$J$288:$AR$288,1,MATCH((Time!O26-1),Inputs!$J$282:$AR$282,0))) -> 7.5 | P15: =CHOOSE(Inputs!$F$33,INDEX(Inputs!$J$284:$AR$284,1,MATCH((Time!P26-1),Inputs!$J$282:$AR$282,0)),INDEX(Inputs!$J$286:$AR$286,1,MATCH((Time!P26-1),Inputs!$J$282:$AR$282,0)),INDEX(Inputs!$J$288:$AR$288,1,MATCH((Time!P26-1),Inputs!$J$282:$AR$282,0))) -> 7.5 | Q15: =CHOOSE(Inputs!$F$33,INDEX(Inputs!$J$284:$AR$284,1,MATCH((Time!Q26-1),Inputs!$J$282:$AR$282,0)),INDEX(Inputs!$J$286:$AR$286,1,MATCH((Time!Q26-1),Inputs!$J$282:$AR$282,0)),INDEX(Inputs!$J$288:$AR$288,1,MATCH((Time!Q26-1),Inputs!$J$282:$AR$282,0))) -> 7.5 | ... BN15: =CHOOSE(Inputs!$F$33,INDEX(Inputs!$J$284:$AR$284,1,MATCH((Time!BN26-1),Inputs!$J$282:$AR$282,0)),INDEX(Inputs!$J$286:$AR$286,1,MATCH((Time!BN26-1),Inputs!$J$282:$AR$282,0)),INDEX(Inputs!$J$288:$AR$288,1,MATCH((Time!BN26-1),Inputs!$J$282:$AR$282,0))) -> 7.5
D16: US index, 2018 price base month | E16: index | F16: =Inputs!$F$232*(1+CHOOSE(Inputs!$F$33,INDEX(Inputs!$J$283:$AR$283,1,MATCH(Inputs!$F$230,Inputs!$J$282:$AR$282,0)),INDEX(Inputs!$J$285:$AR$285,1,MATCH(Inputs!$F$230,Inputs!$J$282:$AR$282,0)),INDEX(Inputs!$J$287:$AR$287,1,MATCH(Inputs!$F$230,Inputs!$J$282:$AR$282,0)))/100)^((12-Inputs!$F$231)/12)*(1+CHOOSE(Inputs!$F$33,INDEX(Inputs!$J$283:$AR$283,1,MATCH(Inputs!$F$230+1,Inputs!$J$282:$AR$282,0)),INDEX(Inputs!$J$285:$AR$285,1,MATCH(Inputs!$F$230+1,Inputs!$J$282:$AR$282,0)),INDEX(Inputs!$J$287:$AR$287,1,MATCH(Inputs!$F$230+1,Inputs!$J$282:$AR$282,0)))/100)*(1+CHOOSE(Inputs!$F$33,INDEX(Inputs!$J$283:$AR$283,1,MATCH(YEAR(Inputs!$F$189),Inputs!$J$282:$AR$282,0)),INDEX(Inputs!$J$285:$AR$285,1,MATCH(YEAR(Inputs!$F$189),Inputs!$J$282:$AR$282,0)),INDEX(Inputs!$J$287:$AR$287,1,MATCH(YEAR(Inputs!$F$189),Inputs!$J$282:$AR$282,0)))/100)^(Inputs!$F$235/12) -> 103.32815
D17: US index, first cost reading | E17: index | F17: =Inputs!$F$232*(1+CHOOSE(Inputs!$F$33,INDEX(Inputs!$J$283:$AR$283,1,MATCH(Inputs!$F$230,Inputs!$J$282:$AR$282,0)),INDEX(Inputs!$J$285:$AR$285,1,MATCH(Inputs!$F$230,Inputs!$J$282:$AR$282,0)),INDEX(Inputs!$J$287:$AR$287,1,MATCH(Inputs!$F$230,Inputs!$J$282:$AR$282,0)))/100)^((12-Inputs!$F$231)/12)*(1+CHOOSE(Inputs!$F$33,INDEX(Inputs!$J$283:$AR$283,1,MATCH(Inputs!$F$230+1,Inputs!$J$282:$AR$282,0)),INDEX(Inputs!$J$285:$AR$285,1,MATCH(Inputs!$F$230+1,Inputs!$J$282:$AR$282,0)),INDEX(Inputs!$J$287:$AR$287,1,MATCH(Inputs!$F$230+1,Inputs!$J$282:$AR$282,0)))/100)*(1+CHOOSE(Inputs!$F$33,INDEX(Inputs!$J$283:$AR$283,1,MATCH(YEAR(Inputs!$F$189),Inputs!$J$282:$AR$282,0)),INDEX(Inputs!$J$285:$AR$285,1,MATCH(YEAR(Inputs!$F$189),Inputs!$J$282:$AR$282,0)),INDEX(Inputs!$J$287:$AR$287,1,MATCH(YEAR(Inputs!$F$189),Inputs!$J$282:$AR$282,0)))/100)^(Inputs!$F$233/12) -> 103.89182
D18: US index, first tariff reading | E18: index | F18: =Inputs!$F$232*(1+CHOOSE(Inputs!$F$33,INDEX(Inputs!$J$283:$AR$283,1,MATCH(Inputs!$F$230,Inputs!$J$282:$AR$282,0)),INDEX(Inputs!$J$285:$AR$285,1,MATCH(Inputs!$F$230,Inputs!$J$282:$AR$282,0)),INDEX(Inputs!$J$287:$AR$287,1,MATCH(Inputs!$F$230,Inputs!$J$282:$AR$282,0)))/100)^((12-Inputs!$F$231)/12)*(1+CHOOSE(Inputs!$F$33,INDEX(Inputs!$J$283:$AR$283,1,MATCH(Inputs!$F$230+1,Inputs!$J$282:$AR$282,0)),INDEX(Inputs!$J$285:$AR$285,1,MATCH(Inputs!$F$230+1,Inputs!$J$282:$AR$282,0)),INDEX(Inputs!$J$287:$AR$287,1,MATCH(Inputs!$F$230+1,Inputs!$J$282:$AR$282,0)))/100)*(1+CHOOSE(Inputs!$F$33,INDEX(Inputs!$J$283:$AR$283,1,MATCH(YEAR(Inputs!$F$189),Inputs!$J$282:$AR$282,0)),INDEX(Inputs!$J$285:$AR$285,1,MATCH(YEAR(Inputs!$F$189),Inputs!$J$282:$AR$282,0)),INDEX(Inputs!$J$287:$AR$287,1,MATCH(YEAR(Inputs!$F$189),Inputs!$J$282:$AR$282,0)))/100)^(Inputs!$F$234/12) -> 102.76753
D19: US CPI index, cost reading (Mar/Sep), Nov 2016 = 100 | E19: index | J19: =IF(Time!J20=1,$F$17,I19*IF(Time!J27=1,(1+J14/100)^(Inputs!$F$236/12)*(1+J12/100)^((Time!J21-Inputs!$F$236)/12),(1+J12/100)^Time!J24)) -> 103.89182 | K19: =IF(Time!K20=1,$F$17,J19*IF(Time!K27=1,(1+K14/100)^(Inputs!$F$236/12)*(1+K12/100)^((Time!K21-Inputs!$F$236)/12),(1+K12/100)^Time!K24)) -> 105.02842 | L19: =IF(Time!L20=1,$F$17,K19*IF(Time!L27=1,(1+L14/100)^(Inputs!$F$236/12)*(1+L12/100)^((Time!L21-Inputs!$F$236)/12),(1+L12/100)^Time!L24)) -> 106.17744 | M19: =IF(Time!M20=1,$F$17,L19*IF(Time!M27=1,(1+M14/100)^(Inputs!$F$236/12)*(1+M12/100)^((Time!M21-Inputs!$F$236)/12),(1+M12/100)^Time!M24)) -> 107.33904 | N19: =IF(Time!N20=1,$F$17,M19*IF(Time!N27=1,(1+N14/100)^(Inputs!$F$236/12)*(1+N12/100)^((Time!N21-Inputs!$F$236)/12),(1+N12/100)^Time!N24)) -> 108.51335 | O19: =IF(Time!O20=1,$F$17,N19*IF(Time!O27=1,(1+O14/100)^(Inputs!$F$236/12)*(1+O12/100)^((Time!O21-Inputs!$F$236)/12),(1+O12/100)^Time!O24)) -> 109.7005 | P19: =IF(Time!P20=1,$F$17,O19*IF(Time!P27=1,(1+P14/100)^(Inputs!$F$236/12)*(1+P12/100)^((Time!P21-Inputs!$F$236)/12),(1+P12/100)^Time!P24)) -> 110.90064 | Q19: =IF(Time!Q20=1,$F$17,P19*IF(Time!Q27=1,(1+Q14/100)^(Inputs!$F$236/12)*(1+Q12/100)^((Time!Q21-Inputs!$F$236)/12),(1+Q12/100)^Time!Q24)) -> 112.11391 | ... BN19: =IF(Time!BN20=1,$F$17,BM19*IF(Time!BN27=1,(1+BN14/100)^(Inputs!$F$236/12)*(1+BN12/100)^((Time!BN21-Inputs!$F$236)/12),(1+BN12/100)^Time!BN24)) -> 191.07614
D20: US CPI index, tariff reading (3-month lag) | E20: index | J20: =IF(Time!J20=1,$F$18,I19) -> 102.76753 | K20: =IF(Time!K20=1,$F$18,J19) -> 103.89182 | L20: =IF(Time!L20=1,$F$18,K19) -> 105.02842 | M20: =IF(Time!M20=1,$F$18,L19) -> 106.17744 | N20: =IF(Time!N20=1,$F$18,M19) -> 107.33904 | O20: =IF(Time!O20=1,$F$18,N19) -> 108.51335 | P20: =IF(Time!P20=1,$F$18,O19) -> 109.7005 | Q20: =IF(Time!Q20=1,$F$18,P19) -> 110.90064 | ... BN20: =IF(Time!BN20=1,$F$18,BM19) -> 189.00835
D21: US cost indexation factor vs 2018 prices | E21: factor | J21: =J19/$F$16 -> 1.0054552 | K21: =K19/$F$16 -> 1.016455 | L21: =L19/$F$16 -> 1.0275752 | M21: =M19/$F$16 -> 1.038817 | N21: =N19/$F$16 -> 1.0501819 | O21: =O19/$F$16 -> 1.061671 | P21: =P19/$F$16 -> 1.0732859 | Q21: =Q19/$F$16 -> 1.0850278 | ... BN21: =BN19/$F$16 -> 1.8492167
D22: KC index, 2018 price base month | E22: index | F22: =Inputs!$F$232*(1+CHOOSE(Inputs!$F$33,INDEX(Inputs!$J$284:$AR$284,1,MATCH(Inputs!$F$230,Inputs!$J$282:$AR$282,0)),INDEX(Inputs!$J$286:$AR$286,1,MATCH(Inputs!$F$230,Inputs!$J$282:$AR$282,0)),INDEX(Inputs!$J$288:$AR$288,1,MATCH(Inputs!$F$230,Inputs!$J$282:$AR$282,0)))/100)^((12-Inputs!$F$231)/12)*(1+CHOOSE(Inputs!$F$33,INDEX(Inputs!$J$284:$AR$284,1,MATCH(Inputs!$F$230+1,Inputs!$J$282:$AR$282,0)),INDEX(Inputs!$J$286:$AR$286,1,MATCH(Inputs!$F$230+1,Inputs!$J$282:$AR$282,0)),INDEX(Inputs!$J$288:$AR$288,1,MATCH(Inputs!$F$230+1,Inputs!$J$282:$AR$282,0)))/100)*(1+CHOOSE(Inputs!$F$33,INDEX(Inputs!$J$284:$AR$284,1,MATCH(YEAR(Inputs!$F$189),Inputs!$J$282:$AR$282,0)),INDEX(Inputs!$J$286:$AR$286,1,MATCH(YEAR(Inputs!$F$189),Inputs!$J$282:$AR$282,0)),INDEX(Inputs!$J$288:$AR$288,1,MATCH(YEAR(Inputs!$F$189),Inputs!$J$282:$AR$282,0)))/100)^(Inputs!$F$235/12) -> 112.92273
D23: KC index, first cost reading | E23: index | F23: =Inputs!$F$232*(1+CHOOSE(Inputs!$F$33,INDEX(Inputs!$J$284:$AR$284,1,MATCH(Inputs!$F$230,Inputs!$J$282:$AR$282,0)),INDEX(Inputs!$J$286:$AR$286,1,MATCH(Inputs!$F$230,Inputs!$J$282:$AR$282,0)),INDEX(Inputs!$J$288:$AR$288,1,MATCH(Inputs!$F$230,Inputs!$J$282:$AR$282,0)))/100)^((12-Inputs!$F$231)/12)*(1+CHOOSE(Inputs!$F$33,INDEX(Inputs!$J$284:$AR$284,1,MATCH(Inputs!$F$230+1,Inputs!$J$282:$AR$282,0)),INDEX(Inputs!$J$286:$AR$286,1,MATCH(Inputs!$F$230+1,Inputs!$J$282:$AR$282,0)),INDEX(Inputs!$J$288:$AR$288,1,MATCH(Inputs!$F$230+1,Inputs!$J$282:$AR$282,0)))/100)*(1+CHOOSE(Inputs!$F$33,INDEX(Inputs!$J$284:$AR$284,1,MATCH(YEAR(Inputs!$F$189),Inputs!$J$282:$AR$282,0)),INDEX(Inputs!$J$286:$AR$286,1,MATCH(YEAR(Inputs!$F$189),Inputs!$J$282:$AR$282,0)),INDEX(Inputs!$J$288:$AR$288,1,MATCH(YEAR(Inputs!$F$189),Inputs!$J$282:$AR$282,0)))/100)^(Inputs!$F$233/12) -> 114.98296
D24: KC index, first tariff reading | E24: index | F24: =Inputs!$F$232*(1+CHOOSE(Inputs!$F$33,INDEX(Inputs!$J$284:$AR$284,1,MATCH(Inputs!$F$230,Inputs!$J$282:$AR$282,0)),INDEX(Inputs!$J$286:$AR$286,1,MATCH(Inputs!$F$230,Inputs!$J$282:$AR$282,0)),INDEX(Inputs!$J$288:$AR$288,1,MATCH(Inputs!$F$230,Inputs!$J$282:$AR$282,0)))/100)^((12-Inputs!$F$231)/12)*(1+CHOOSE(Inputs!$F$33,INDEX(Inputs!$J$284:$AR$284,1,MATCH(Inputs!$F$230+1,Inputs!$J$282:$AR$282,0)),INDEX(Inputs!$J$286:$AR$286,1,MATCH(Inputs!$F$230+1,Inputs!$J$282:$AR$282,0)),INDEX(Inputs!$J$288:$AR$288,1,MATCH(Inputs!$F$230+1,Inputs!$J$282:$AR$282,0)))/100)*(1+CHOOSE(Inputs!$F$33,INDEX(Inputs!$J$284:$AR$284,1,MATCH(YEAR(Inputs!$F$189),Inputs!$J$282:$AR$282,0)),INDEX(Inputs!$J$286:$AR$286,1,MATCH(YEAR(Inputs!$F$189),Inputs!$J$282:$AR$282,0)),INDEX(Inputs!$J$288:$AR$288,1,MATCH(YEAR(Inputs!$F$189),Inputs!$J$282:$AR$282,0)))/100)^(Inputs!$F$234/12) -> 110.89941
D25: Kessara CPI index, cost reading (Mar/Sep), Nov 2016 = 100 | E25: index | J25: =IF(Time!J20=1,$F$23,I25*IF(Time!J27=1,(1+J15/100)^(Inputs!$F$236/12)*(1+J13/100)^((Time!J21-Inputs!$F$236)/12),(1+J13/100)^Time!J24)) -> 114.98296 | K25: =IF(Time!K20=1,$F$23,J25*IF(Time!K27=1,(1+K15/100)^(Inputs!$F$236/12)*(1+K13/100)^((Time!K21-Inputs!$F$236)/12),(1+K13/100)^Time!K24)) -> 119.21687 | L25: =IF(Time!L20=1,$F$23,K25*IF(Time!L27=1,(1+L15/100)^(Inputs!$F$236/12)*(1+L13/100)^((Time!L21-Inputs!$F$236)/12),(1+L13/100)^Time!L24)) -> 123.60668 | M25: =IF(Time!M20=1,$F$23,L25*IF(Time!M27=1,(1+M15/100)^(Inputs!$F$236/12)*(1+M13/100)^((Time!M21-Inputs!$F$236)/12),(1+M13/100)^Time!M24)) -> 128.15814 | N25: =IF(Time!N20=1,$F$23,M25*IF(Time!N27=1,(1+N15/100)^(Inputs!$F$236/12)*(1+N13/100)^((Time!N21-Inputs!$F$236)/12),(1+N13/100)^Time!N24)) -> 132.87718 | O25: =IF(Time!O20=1,$F$23,N25*IF(Time!O27=1,(1+O15/100)^(Inputs!$F$236/12)*(1+O13/100)^((Time!O21-Inputs!$F$236)/12),(1+O13/100)^Time!O24)) -> 137.77 | P25: =IF(Time!P20=1,$F$23,O25*IF(Time!P27=1,(1+P15/100)^(Inputs!$F$236/12)*(1+P13/100)^((Time!P21-Inputs!$F$236)/12),(1+P13/100)^Time!P24)) -> 142.84297 | Q25: =IF(Time!Q20=1,$F$23,P25*IF(Time!Q27=1,(1+Q15/100)^(Inputs!$F$236/12)*(1+Q13/100)^((Time!Q21-Inputs!$F$236)/12),(1+Q13/100)^Time!Q24)) -> 148.10275 | ... BN25: =IF(Time!BN20=1,$F$23,BM25*IF(Time!BN27=1,(1+BN15/100)^(Inputs!$F$236/12)*(1+BN13/100)^((Time!BN21-Inputs!$F$236)/12),(1+BN13/100)^Time!BN24)) -> 871.10496
D26: Kessara CPI index, tariff reading (3-month lag) | E26: index | J26: =IF(Time!J20=1,$F$24,I25) -> 110.89941 | K26: =IF(Time!K20=1,$F$24,J25) -> 114.98296 | L26: =IF(Time!L20=1,$F$24,K25) -> 119.21687 | M26: =IF(Time!M20=1,$F$24,L25) -> 123.60668 | N26: =IF(Time!N20=1,$F$24,M25) -> 128.15814 | O26: =IF(Time!O20=1,$F$24,N25) -> 132.87718 | P26: =IF(Time!P20=1,$F$24,O25) -> 137.77 | Q26: =IF(Time!Q20=1,$F$24,P25) -> 142.84297 | ... BN26: =IF(Time!BN20=1,$F$24,BM25) -> 840.16822
D27: Kessara cost indexation factor vs 2018 prices | E27: factor | J27: =J25/$F$22 -> 1.0182446 | K27: =K25/$F$22 -> 1.0557385 | L27: =L25/$F$22 -> 1.0946129 | M27: =M25/$F$22 -> 1.1349189 | N27: =N25/$F$22 -> 1.1767089 | O27: =O25/$F$22 -> 1.2200378 | P27: =P25/$F$22 -> 1.2649621 | Q27: =Q25/$F$22 -> 1.3115406 | ... BN27: =BN25/$F$22 -> 7.7141684
B28: Plant
D29: Operating year at period start | E29: OY | J29: =INT(Time!J32/12)+1 -> 1 | K29: =INT(Time!K32/12)+1 -> 1 | L29: =INT(Time!L32/12)+1 -> 1 | M29: =INT(Time!M32/12)+1 -> 1 | N29: =INT(Time!N32/12)+1 -> 1 | O29: =INT(Time!O32/12)+1 -> 1 | P29: =INT(Time!P32/12)+1 -> 1 | Q29: =INT(Time!Q32/12)+1 -> 1 | ... BN29: =INT(Time!BN32/12)+1 -> 26
D30: Months in that operating year | E30: months | J30: =MIN(Time!J33,J29*12)-Time!J32 -> 0 | K30: =MIN(Time!K33,K29*12)-Time!K32 -> 0 | L30: =MIN(Time!L33,L29*12)-Time!L32 -> 0 | M30: =MIN(Time!M33,M29*12)-Time!M32 -> 0 | N30: =MIN(Time!N33,N29*12)-Time!N32 -> 0 | O30: =MIN(Time!O33,O29*12)-Time!O32 -> 2 | P30: =MIN(Time!P33,P29*12)-Time!P32 -> 6 | Q30: =MIN(Time!Q33,Q29*12)-Time!Q32 -> 4 | ... BN30: =MIN(Time!BN33,BN29*12)-Time!BN32 -> 0
D31: Availability, profile (month-weighted; plus the Monte Carlo shock for the operating year when active) | E31: % | J31: =IF(Time!J30>0,(J30*INDEX(Inputs!$J$302:$Q$302,1,MOD(J29-1,Inputs!$F$220)+1)+(Time!J30-J30)*INDEX(Inputs!$J$302:$Q$302,1,MOD(J29,Inputs!$F$220)+1))/Time!J30+IF(Inputs!$F$312=1,(J30*INDEX(Inputs!$J$313:$AI$1312,Inputs!$F$311,J29)+(Time!J30-J30)*IF(J29+1<=Inputs!$F$1321,INDEX(Inputs!$J$313:$AI$1312,Inputs!$F$311,J29+1),0))/Time!J30,0),0) -> 0 | K31: =IF(Time!K30>0,(K30*INDEX(Inputs!$J$302:$Q$302,1,MOD(K29-1,Inputs!$F$220)+1)+(Time!K30-K30)*INDEX(Inputs!$J$302:$Q$302,1,MOD(K29,Inputs!$F$220)+1))/Time!K30+IF(Inputs!$F$312=1,(K30*INDEX(Inputs!$J$313:$AI$1312,Inputs!$F$311,K29)+(Time!K30-K30)*IF(K29+1<=Inputs!$F$1321,INDEX(Inputs!$J$313:$AI$1312,Inputs!$F$311,K29+1),0))/Time!K30,0),0) -> 0 | L31: =IF(Time!L30>0,(L30*INDEX(Inputs!$J$302:$Q$302,1,MOD(L29-1,Inputs!$F$220)+1)+(Time!L30-L30)*INDEX(Inputs!$J$302:$Q$302,1,MOD(L29,Inputs!$F$220)+1))/Time!L30+IF(Inputs!$F$312=1,(L30*INDEX(Inputs!$J$313:$AI$1312,Inputs!$F$311,L29)+(Time!L30-L30)*IF(L29+1<=Inputs!$F$1321,INDEX(Inputs!$J$313:$AI$1312,Inputs!$F$311,L29+1),0))/Time!L30,0),0) -> 0 | M31: =IF(Time!M30>0,(M30*INDEX(Inputs!$J$302:$Q$302,1,MOD(M29-1,Inputs!$F$220)+1)+(Time!M30-M30)*INDEX(Inputs!$J$302:$Q$302,1,MOD(M29,Inputs!$F$220)+1))/Time!M30+IF(Inputs!$F$312=1,(M30*INDEX(Inputs!$J$313:$AI$1312,Inputs!$F$311,M29)+(Time!M30-M30)*IF(M29+1<=Inputs!$F$1321,INDEX(Inputs!$J$313:$AI$1312,Inputs!$F$311,M29+1),0))/Time!M30,0),0) -> 0 | N31: =IF(Time!N30>0,(N30*INDEX(Inputs!$J$302:$Q$302,1,MOD(N29-1,Inputs!$F$220)+1)+(Time!N30-N30)*INDEX(Inputs!$J$302:$Q$302,1,MOD(N29,Inputs!$F$220)+1))/Time!N30+IF(Inputs!$F$312=1,(N30*INDEX(Inputs!$J$313:$AI$1312,Inputs!$F$311,N29)+(Time!N30-N30)*IF(N29+1<=Inputs!$F$1321,INDEX(Inputs!$J$313:$AI$1312,Inputs!$F$311,N29+1),0))/Time!N30,0),0) -> 0 | O31: =IF(Time!O30>0,(O30*INDEX(Inputs!$J$302:$Q$302,1,MOD(O29-1,Inputs!$F$220)+1)+(Time!O30-O30)*INDEX(Inputs!$J$302:$Q$302,1,MOD(O29,Inputs!$F$220)+1))/Time!O30+IF(Inputs!$F$312=1,(O30*INDEX(Inputs!$J$313:$AI$1312,Inputs!$F$311,O29)+(Time!O30-O30)*IF(O29+1<=Inputs!$F$1321,INDEX(Inputs!$J$313:$AI$1312,Inputs!$F$311,O29+1),0))/Time!O30,0),0) -> 93.8 | P31: =IF(Time!P30>0,(P30*INDEX(Inputs!$J$302:$Q$302,1,MOD(P29-1,Inputs!$F$220)+1)+(Time!P30-P30)*INDEX(Inputs!$J$302:$Q$302,1,MOD(P29,Inputs!$F$220)+1))/Time!P30+IF(Inputs!$F$312=1,(P30*INDEX(Inputs!$J$313:$AI$1312,Inputs!$F$311,P29)+(Time!P30-P30)*IF(P29+1<=Inputs!$F$1321,INDEX(Inputs!$J$313:$AI$1312,Inputs!$F$311,P29+1),0))/Time!P30,0),0) -> 93.8 | Q31: =IF(Time!Q30>0,(Q30*INDEX(Inputs!$J$302:$Q$302,1,MOD(Q29-1,Inputs!$F$220)+1)+(Time!Q30-Q30)*INDEX(Inputs!$J$302:$Q$302,1,MOD(Q29,Inputs!$F$220)+1))/Time!Q30+IF(Inputs!$F$312=1,(Q30*INDEX(Inputs!$J$313:$AI$1312,Inputs!$F$311,Q29)+(Time!Q30-Q30)*IF(Q29+1<=Inputs!$F$1321,INDEX(Inputs!$J$313:$AI$1312,Inputs!$F$311,Q29+1),0))/Time!Q30,0),0) -> 93.5 | ... BN31: =IF(Time!BN30>0,(BN30*INDEX(Inputs!$J$302:$Q$302,1,MOD(BN29-1,Inputs!$F$220)+1)+(Time!BN30-BN30)*INDEX(Inputs!$J$302:$Q$302,1,MOD(BN29,Inputs!$F$220)+1))/Time!BN30+IF(Inputs!$F$312=1,(BN30*INDEX(Inputs!$J$313:$AI$1312,Inputs!$F$311,BN29)+(Time!BN30-BN30)*IF(BN29+1<=Inputs!$F$1321,INDEX(Inputs!$J$313:$AI$1312,Inputs!$F$311,BN29+1),0))/Time!BN30,0),0) -> 0
D32: Availability | E32: % | J32: =IF(Time!J30>0,J31+Inputs!$F$37,0) -> 0 | K32: =IF(Time!K30>0,K31+Inputs!$F$37,0) -> 0 | L32: =IF(Time!L30>0,L31+Inputs!$F$37,0) -> 0 | M32: =IF(Time!M30>0,M31+Inputs!$F$37,0) -> 0 | N32: =IF(Time!N30>0,N31+Inputs!$F$37,0) -> 0 | O32: =IF(Time!O30>0,O31+Inputs!$F$37,0) -> 93.8 | P32: =IF(Time!P30>0,P31+Inputs!$F$37,0) -> 93.8 | Q32: =IF(Time!Q30>0,Q31+Inputs!$F$37,0) -> 93.5 | ... BN32: =IF(Time!BN30>0,BN31+Inputs!$F$37,0) -> 0
D33: Years since COD (period mid-point) | E33: years | J33: =IF(Time!J30>0,AVERAGE(Time!J32,Time!J33)/12,0) -> 0 | K33: =IF(Time!K30>0,AVERAGE(Time!K32,Time!K33)/12,0) -> 0 | L33: =IF(Time!L30>0,AVERAGE(Time!L32,Time!L33)/12,0) -> 0 | M33: =IF(Time!M30>0,AVERAGE(Time!M32,Time!M33)/12,0) -> 0 | N33: =IF(Time!N30>0,AVERAGE(Time!N32,Time!N33)/12,0) -> 0 | O33: =IF(Time!O30>0,AVERAGE(Time!O32,Time!O33)/12,0) -> 0.083333333 | P33: =IF(Time!P30>0,AVERAGE(Time!P32,Time!P33)/12,0) -> 0.41666667 | Q33: =IF(Time!Q30>0,AVERAGE(Time!Q32,Time!Q33)/12,0) -> 0.91666667 | ... BN33: =IF(Time!BN30>0,AVERAGE(Time!BN32,Time!BN33)/12,0) -> 0
D34: Contracted capacity | E34: MW | F34: =IF(Inputs!$F$34<>1,Inputs!$F$117,Inputs!$F$116) -> 588.4
D35: Plant net heat rate, new and clean | E35: kJ/kWh | F35: =IF(Inputs!$F$34<>1,Inputs!$F$119,Inputs!$F$118) -> 6261
D36: Output degradation factor | E36: factor | J36: =(1-Inputs!$F$125/100*J33)*(1-Inputs!$F$126/100) -> 0.99 | K36: =(1-Inputs!$F$125/100*K33)*(1-Inputs!$F$126/100) -> 0.99 | L36: =(1-Inputs!$F$125/100*L33)*(1-Inputs!$F$126/100) -> 0.99 | M36: =(1-Inputs!$F$125/100*M33)*(1-Inputs!$F$126/100) -> 0.99 | N36: =(1-Inputs!$F$125/100*N33)*(1-Inputs!$F$126/100) -> 0.99 | O36: =(1-Inputs!$F$125/100*O33)*(1-Inputs!$F$126/100) -> 0.98987625 | P36: =(1-Inputs!$F$125/100*P33)*(1-Inputs!$F$126/100) -> 0.98938125 | Q36: =(1-Inputs!$F$125/100*Q33)*(1-Inputs!$F$126/100) -> 0.98863875 | ... BN36: =(1-Inputs!$F$125/100*BN33)*(1-Inputs!$F$126/100) -> 0.99
D37: Dispatch factor when available | E37: % | J37: =IF(Inputs!$F$312=1,INDEX(Inputs!$AJ$313:$AJ$1312,Inputs!$F$311),IF(AND(Inputs!$F$55=1,Inputs!J303>0),Inputs!J303,Inputs!$F$38)) -> 76.5 | K37: =IF(Inputs!$F$312=1,INDEX(Inputs!$AJ$313:$AJ$1312,Inputs!$F$311),IF(AND(Inputs!$F$55=1,Inputs!K303>0),Inputs!K303,Inputs!$F$38)) -> 76.5 | L37: =IF(Inputs!$F$312=1,INDEX(Inputs!$AJ$313:$AJ$1312,Inputs!$F$311),IF(AND(Inputs!$F$55=1,Inputs!L303>0),Inputs!L303,Inputs!$F$38)) -> 76.5 | M37: =IF(Inputs!$F$312=1,INDEX(Inputs!$AJ$313:$AJ$1312,Inputs!$F$311),IF(AND(Inputs!$F$55=1,Inputs!M303>0),Inputs!M303,Inputs!$F$38)) -> 76.5 | N37: =IF(Inputs!$F$312=1,INDEX(Inputs!$AJ$313:$AJ$1312,Inputs!$F$311),IF(AND(Inputs!$F$55=1,Inputs!N303>0),Inputs!N303,Inputs!$F$38)) -> 76.5 | O37: =IF(Inputs!$F$312=1,INDEX(Inputs!$AJ$313:$AJ$1312,Inputs!$F$311),IF(AND(Inputs!$F$55=1,Inputs!O303>0),Inputs!O303,Inputs!$F$38)) -> 76.5 | P37: =IF(Inputs!$F$312=1,INDEX(Inputs!$AJ$313:$AJ$1312,Inputs!$F$311),IF(AND(Inputs!$F$55=1,Inputs!P303>0),Inputs!P303,Inputs!$F$38)) -> 76.5 | Q37: =IF(Inputs!$F$312=1,INDEX(Inputs!$AJ$313:$AJ$1312,Inputs!$F$311),IF(AND(Inputs!$F$55=1,Inputs!Q303>0),Inputs!Q303,Inputs!$F$38)) -> 76.5 | ... BN37: =IF(Inputs!$F$312=1,INDEX(Inputs!$AJ$313:$AJ$1312,Inputs!$F$311),IF(AND(Inputs!$F$55=1,Inputs!BN303>0),Inputs!BN303,Inputs!$F$38)) -> 76.5
D38: Net energy delivered | E38: MWh | J38: =$F$34*Inputs!$F$215*Time!J30*J32/100*J37/100*J36 -> 0 | K38: =$F$34*Inputs!$F$215*Time!K30*K32/100*K37/100*K36 -> 0 | L38: =$F$34*Inputs!$F$215*Time!L30*L32/100*L37/100*L36 -> 0 | M38: =$F$34*Inputs!$F$215*Time!M30*M32/100*M37/100*M36 -> 0 | N38: =$F$34*Inputs!$F$215*Time!N30*N32/100*N37/100*N36 -> 0 | O38: =$F$34*Inputs!$F$215*Time!O30*O32/100*O37/100*O36 -> 610197.88 | P38: =$F$34*Inputs!$F$215*Time!P30*P32/100*P37/100*P36 -> 1829678.2 | Q38: =$F$34*Inputs!$F$215*Time!Q30*Q32/100*Q37/100*Q36 -> 1822457.7 | ... BN38: =$F$34*Inputs!$F$215*Time!BN30*BN32/100*BN37/100*BN36 -> 0
D39: Plant net heat rate | E39: kJ/kWh | J39: =$F$35*(1+IF(Inputs!$F$312=1,INDEX(Inputs!$AK$313:$AK$1312,Inputs!$F$311),Inputs!$F$127)/100*J33)*(1+Inputs!$F$128/100)*(1+Inputs!$F$122/100)*Inputs!$F$39 -> 6456.243 | K39: =$F$35*(1+IF(Inputs!$F$312=1,INDEX(Inputs!$AK$313:$AK$1312,Inputs!$F$311),Inputs!$F$127)/100*K33)*(1+Inputs!$F$128/100)*(1+Inputs!$F$122/100)*Inputs!$F$39 -> 6456.243 | L39: =$F$35*(1+IF(Inputs!$F$312=1,INDEX(Inputs!$AK$313:$AK$1312,Inputs!$F$311),Inputs!$F$127)/100*L33)*(1+Inputs!$F$128/100)*(1+Inputs!$F$122/100)*Inputs!$F$39 -> 6456.243 | M39: =$F$35*(1+IF(Inputs!$F$312=1,INDEX(Inputs!$AK$313:$AK$1312,Inputs!$F$311),Inputs!$F$127)/100*M33)*(1+Inputs!$F$128/100)*(1+Inputs!$F$122/100)*Inputs!$F$39 -> 6456.243 | N39: =$F$35*(1+IF(Inputs!$F$312=1,INDEX(Inputs!$AK$313:$AK$1312,Inputs!$F$311),Inputs!$F$127)/100*N33)*(1+Inputs!$F$128/100)*(1+Inputs!$F$122/100)*Inputs!$F$39 -> 6456.243 | O39: =$F$35*(1+IF(Inputs!$F$312=1,INDEX(Inputs!$AK$313:$AK$1312,Inputs!$F$311),Inputs!$F$127)/100*O33)*(1+Inputs!$F$128/100)*(1+Inputs!$F$122/100)*Inputs!$F$39 -> 6456.8886 | P39: =$F$35*(1+IF(Inputs!$F$312=1,INDEX(Inputs!$AK$313:$AK$1312,Inputs!$F$311),Inputs!$F$127)/100*P33)*(1+Inputs!$F$128/100)*(1+Inputs!$F$122/100)*Inputs!$F$39 -> 6459.4711 | Q39: =$F$35*(1+IF(Inputs!$F$312=1,INDEX(Inputs!$AK$313:$AK$1312,Inputs!$F$311),Inputs!$F$127)/100*Q33)*(1+Inputs!$F$128/100)*(1+Inputs!$F$122/100)*Inputs!$F$39 -> 6463.3449 | ... BN39: =$F$35*(1+IF(Inputs!$F$312=1,INDEX(Inputs!$AK$313:$AK$1312,Inputs!$F$311),Inputs!$F$127)/100*BN33)*(1+Inputs!$F$128/100)*(1+Inputs!$F$122/100)*Inputs!$F$39 -> 6456.243
D40: Contracted heat rate at dispatched load | E40: kJ/kWh | J40: =Inputs!$F$120*(1+Inputs!$F$121/100*J33)*(1+Inputs!$F$122/100) -> 6468.429 | K40: =Inputs!$F$120*(1+Inputs!$F$121/100*K33)*(1+Inputs!$F$122/100) -> 6468.429 | L40: =Inputs!$F$120*(1+Inputs!$F$121/100*L33)*(1+Inputs!$F$122/100) -> 6468.429 | M40: =Inputs!$F$120*(1+Inputs!$F$121/100*M33)*(1+Inputs!$F$122/100) -> 6468.429 | N40: =Inputs!$F$120*(1+Inputs!$F$121/100*N33)*(1+Inputs!$F$122/100) -> 6468.429 | O40: =Inputs!$F$120*(1+Inputs!$F$121/100*O33)*(1+Inputs!$F$122/100) -> 6468.968 | P40: =Inputs!$F$120*(1+Inputs!$F$121/100*P33)*(1+Inputs!$F$122/100) -> 6471.1242 | Q40: =Inputs!$F$120*(1+Inputs!$F$121/100*Q33)*(1+Inputs!$F$122/100) -> 6474.3584 | ... BN40: =Inputs!$F$120*(1+Inputs!$F$121/100*BN33)*(1+Inputs!$F$122/100) -> 6468.429
D41: Gas price (GCV) | E41: USD/MMBtu | J41: =Inputs!$F$142*(1+Inputs!$F$143/100)^(Time!J26-Inputs!$F$256)*Inputs!$F$41 -> 5.86 | K41: =Inputs!$F$142*(1+Inputs!$F$143/100)^(Time!K26-Inputs!$F$256)*Inputs!$F$41 -> 5.9772 | L41: =Inputs!$F$142*(1+Inputs!$F$143/100)^(Time!L26-Inputs!$F$256)*Inputs!$F$41 -> 5.9772 | M41: =Inputs!$F$142*(1+Inputs!$F$143/100)^(Time!M26-Inputs!$F$256)*Inputs!$F$41 -> 6.096744 | N41: =Inputs!$F$142*(1+Inputs!$F$143/100)^(Time!N26-Inputs!$F$256)*Inputs!$F$41 -> 6.096744 | O41: =Inputs!$F$142*(1+Inputs!$F$143/100)^(Time!O26-Inputs!$F$256)*Inputs!$F$41 -> 6.2186789 | P41: =Inputs!$F$142*(1+Inputs!$F$143/100)^(Time!P26-Inputs!$F$256)*Inputs!$F$41 -> 6.2186789 | Q41: =Inputs!$F$142*(1+Inputs!$F$143/100)^(Time!Q26-Inputs!$F$256)*Inputs!$F$41 -> 6.3430525 | ... BN41: =Inputs!$F$142*(1+Inputs!$F$143/100)^(Time!BN26-Inputs!$F$256)*Inputs!$F$41 -> 10.202402
D42: Gas burned | E42: MMBtu | J42: =J38*J39*(1000*Inputs!$F$123/Inputs!$F$124) -> 0 | K42: =K38*K39*(1000*Inputs!$F$123/Inputs!$F$124) -> 0 | L42: =L38*L39*(1000*Inputs!$F$123/Inputs!$F$124) -> 0 | M42: =M38*M39*(1000*Inputs!$F$123/Inputs!$F$124) -> 0 | N42: =N38*N39*(1000*Inputs!$F$123/Inputs!$F$124) -> 0 | O42: =O38*O39*(1000*Inputs!$F$123/Inputs!$F$124) -> 4137692.8 | P42: =P38*P39*(1000*Inputs!$F$123/Inputs!$F$124) -> 12411833 | Q42: =Q38*Q39*(1000*Inputs!$F$123/Inputs!$F$124) -> 12370266 | ... BN42: =BN38*BN39*(1000*Inputs!$F$123/Inputs!$F$124) -> 0
D43: Take-or-pay quantity | E43: MMBtu | J43: =Inputs!$F$145*Inputs!$F$144*Time!J31 -> 0 | K43: =Inputs!$F$145*Inputs!$F$144*Time!K31 -> 0 | L43: =Inputs!$F$145*Inputs!$F$144*Time!L31 -> 0 | M43: =Inputs!$F$145*Inputs!$F$144*Time!M31 -> 0 | N43: =Inputs!$F$145*Inputs!$F$144*Time!N31 -> 0 | O43: =Inputs!$F$145*Inputs!$F$144*Time!O31 -> 3533120 | P43: =Inputs!$F$145*Inputs!$F$144*Time!P31 -> 10657280 | Q43: =Inputs!$F$145*Inputs!$F$144*Time!Q31 -> 10483520 | ... BN43: =Inputs!$F$145*Inputs!$F$144*Time!BN31 -> 0
B44: Revenue (USD m)
D45: Capital charge, indexed | E45: USD/kW-month | J45: =Inputs!$F$134*Inputs!$F$54*(1-Inputs!$F$135+Inputs!$F$135*J20/100) -> 14.439483 | K45: =Inputs!$F$134*Inputs!$F$54*(1-Inputs!$F$135+Inputs!$F$135*K20/100) -> 14.471773 | L45: =Inputs!$F$134*Inputs!$F$54*(1-Inputs!$F$135+Inputs!$F$135*L20/100) -> 14.504416 | M45: =Inputs!$F$134*Inputs!$F$54*(1-Inputs!$F$135+Inputs!$F$135*M20/100) -> 14.537416 | N45: =Inputs!$F$134*Inputs!$F$54*(1-Inputs!$F$135+Inputs!$F$135*N20/100) -> 14.570777 | O45: =Inputs!$F$134*Inputs!$F$54*(1-Inputs!$F$135+Inputs!$F$135*O20/100) -> 14.604503 | P45: =Inputs!$F$134*Inputs!$F$54*(1-Inputs!$F$135+Inputs!$F$135*P20/100) -> 14.638598 | Q45: =Inputs!$F$134*Inputs!$F$54*(1-Inputs!$F$135+Inputs!$F$135*Q20/100) -> 14.673066 | ... BN45: =Inputs!$F$134*Inputs!$F$54*(1-Inputs!$F$135+Inputs!$F$135*BN20/100) -> 16.91632
D46: Fixed O&M charge, indexed | E46: USD/kW-month | J46: =Inputs!$F$136*(Inputs!$F$137*J20/100+(1-Inputs!$F$137)*J26/100*Inputs!$F$138/J11) -> 2.3275027 | K46: =Inputs!$F$136*(Inputs!$F$137*K20/100+(1-Inputs!$F$137)*K26/100*Inputs!$F$138/K11) -> 2.352966 | L46: =Inputs!$F$136*(Inputs!$F$137*L20/100+(1-Inputs!$F$137)*L26/100*Inputs!$F$138/L11) -> 2.3787078 | M46: =Inputs!$F$136*(Inputs!$F$137*M20/100+(1-Inputs!$F$137)*M26/100*Inputs!$F$138/M11) -> 2.4047312 | N46: =Inputs!$F$136*(Inputs!$F$137*N20/100+(1-Inputs!$F$137)*N26/100*Inputs!$F$138/N11) -> 2.4310394 | O46: =Inputs!$F$136*(Inputs!$F$137*O20/100+(1-Inputs!$F$137)*O26/100*Inputs!$F$138/O11) -> 2.4576353 | P46: =Inputs!$F$136*(Inputs!$F$137*P20/100+(1-Inputs!$F$137)*P26/100*Inputs!$F$138/P11) -> 2.4845222 | Q46: =Inputs!$F$136*(Inputs!$F$137*Q20/100+(1-Inputs!$F$137)*Q26/100*Inputs!$F$138/Q11) -> 2.5117033 | ... BN46: =Inputs!$F$136*(Inputs!$F$137*BN20/100+(1-Inputs!$F$137)*BN26/100*Inputs!$F$138/BN11) -> 4.2807048
D47: Availability factor min(1, A/90%) | E47: factor | J47: =MIN(1,J32/Inputs!$F$133) -> 0 | K47: =MIN(1,K32/Inputs!$F$133) -> 0 | L47: =MIN(1,L32/Inputs!$F$133) -> 0 | M47: =MIN(1,M32/Inputs!$F$133) -> 0 | N47: =MIN(1,N32/Inputs!$F$133) -> 0 | O47: =MIN(1,O32/Inputs!$F$133) -> 1 | P47: =MIN(1,P32/Inputs!$F$133) -> 1 | Q47: =MIN(1,Q32/Inputs!$F$133) -> 1 | ... BN47: =MIN(1,BN32/Inputs!$F$133) -> 0
D48: Capacity payment | E48: USD m | G48: =SUM(J48:BN48) -> 3334.8082 | J48: =$F$34*1000*Time!J30*(J45+J46)*J47/1000000 -> 0 | K48: =$F$34*1000*Time!K30*(K45+K46)*K47/1000000 -> 0 | L48: =$F$34*1000*Time!L30*(L45+L46)*L47/1000000 -> 0 | M48: =$F$34*1000*Time!M30*(M45+M46)*M47/1000000 -> 0 | N48: =$F$34*1000*Time!N30*(N45+N46)*N47/1000000 -> 0 | O48: =$F$34*1000*Time!O30*(O45+O46)*O47/1000000 -> 20.078725 | P48: =$F$34*1000*Time!P30*(P45+P46)*P47/1000000 -> 60.451465 | Q48: =$F$34*1000*Time!Q30*(Q45+Q46)*Q47/1000000 -> 60.669111 | ... BN48: =$F$34*1000*Time!BN30*(BN45+BN46)*BN47/1000000 -> 0
D49: VOM charge, indexed | E49: USD/MWh | J49: =Inputs!$F$139*(Inputs!$F$140*J20/100+(1-Inputs!$F$140)*J26/100*Inputs!$F$138/J11) -> 3.9055795 | K49: =Inputs!$F$139*(Inputs!$F$140*K20/100+(1-Inputs!$F$140)*K26/100*Inputs!$F$138/K11) -> 3.9483072 | L49: =Inputs!$F$139*(Inputs!$F$140*L20/100+(1-Inputs!$F$140)*L26/100*Inputs!$F$138/L11) -> 3.9915023 | M49: =Inputs!$F$139*(Inputs!$F$140*M20/100+(1-Inputs!$F$140)*M26/100*Inputs!$F$138/M11) -> 4.03517 | N49: =Inputs!$F$139*(Inputs!$F$140*N20/100+(1-Inputs!$F$140)*N26/100*Inputs!$F$138/N11) -> 4.0793153 | O49: =Inputs!$F$139*(Inputs!$F$140*O20/100+(1-Inputs!$F$140)*O26/100*Inputs!$F$138/O11) -> 4.1239437 | P49: =Inputs!$F$139*(Inputs!$F$140*P20/100+(1-Inputs!$F$140)*P26/100*Inputs!$F$138/P11) -> 4.1690603 | Q49: =Inputs!$F$139*(Inputs!$F$140*Q20/100+(1-Inputs!$F$140)*Q26/100*Inputs!$F$138/Q11) -> 4.2146705 | ... BN49: =Inputs!$F$139*(Inputs!$F$140*BN20/100+(1-Inputs!$F$140)*BN26/100*Inputs!$F$138/BN11) -> 7.1830778
D50: Variable O&M payment | E50: USD m | G50: =SUM(J50:BN50) -> 485.81175 | J50: =J38*J49/1000000 -> 0 | K50: =K38*K49/1000000 -> 0 | L50: =L38*L49/1000000 -> 0 | M50: =M38*M49/1000000 -> 0 | N50: =N38*N49/1000000 -> 0 | O50: =O38*O49/1000000 -> 2.5164217 | P50: =P38*P49/1000000 -> 7.6280389 | Q50: =Q38*Q49/1000000 -> 7.6810585 | ... BN50: =BN38*BN49/1000000 -> 0
D51: Fuel charge (pass-through) | E51: USD m | G51: =SUM(J51:BN51) -> 4886.8261 | J51: =J38*J40*(1000*Inputs!$F$123/Inputs!$F$124)*J41/1000000 -> 0 | K51: =K38*K40*(1000*Inputs!$F$123/Inputs!$F$124)*K41/1000000 -> 0 | L51: =L38*L40*(1000*Inputs!$F$123/Inputs!$F$124)*L41/1000000 -> 0 | M51: =M38*M40*(1000*Inputs!$F$123/Inputs!$F$124)*M41/1000000 -> 0 | N51: =N38*N40*(1000*Inputs!$F$123/Inputs!$F$124)*N41/1000000 -> 0 | O51: =O38*O40*(1000*Inputs!$F$123/Inputs!$F$124)*O41/1000000 -> 25.77912 | P51: =P38*P40*(1000*Inputs!$F$123/Inputs!$F$124)*P41/1000000 -> 77.32445 | Q51: =Q38*Q40*(1000*Inputs!$F$123/Inputs!$F$124)*Q41/1000000 -> 78.598949 | ... BN51: =BN38*BN40*(1000*Inputs!$F$123/Inputs!$F$124)*BN41/1000000 -> 0
D52: GTA reservation charge (pass-through) | E52: USD m | G52: =SUM(J52:BN52) -> 690.34673 | J52: =Inputs!$F$146*Time!J31*Inputs!$F$147*(1+Inputs!$F$149/100)^(Time!J26-Inputs!$F$256)/1000000 -> 0 | K52: =Inputs!$F$146*Time!K31*Inputs!$F$147*(1+Inputs!$F$149/100)^(Time!K26-Inputs!$F$256)/1000000 -> 0 | L52: =Inputs!$F$146*Time!L31*Inputs!$F$147*(1+Inputs!$F$149/100)^(Time!L26-Inputs!$F$256)/1000000 -> 0 | M52: =Inputs!$F$146*Time!M31*Inputs!$F$147*(1+Inputs!$F$149/100)^(Time!M26-Inputs!$F$256)/1000000 -> 0 | N52: =Inputs!$F$146*Time!N31*Inputs!$F$147*(1+Inputs!$F$149/100)^(Time!N26-Inputs!$F$256)/1000000 -> 0 | O52: =Inputs!$F$146*Time!O31*Inputs!$F$147*(1+Inputs!$F$149/100)^(Time!O26-Inputs!$F$256)/1000000 -> 3.8163392 | P52: =Inputs!$F$146*Time!P31*Inputs!$F$147*(1+Inputs!$F$149/100)^(Time!P26-Inputs!$F$256)/1000000 -> 11.51158 | Q52: =Inputs!$F$146*Time!Q31*Inputs!$F$147*(1+Inputs!$F$149/100)^(Time!Q26-Inputs!$F$256)/1000000 -> 11.49375 | ... BN52: =Inputs!$F$146*Time!BN31*Inputs!$F$147*(1+Inputs!$F$149/100)^(Time!BN26-Inputs!$F$256)/1000000 -> 0
D53: GTA commodity charge (pass-through) | E53: USD m | G53: =SUM(J53:BN53) -> 146.42954 | J53: =J42*Inputs!$F$148*(1+Inputs!$F$149/100)^(Time!J26-Inputs!$F$256)/1000000 -> 0 | K53: =K42*Inputs!$F$148*(1+Inputs!$F$149/100)^(Time!K26-Inputs!$F$256)/1000000 -> 0 | L53: =L42*Inputs!$F$148*(1+Inputs!$F$149/100)^(Time!L26-Inputs!$F$256)/1000000 -> 0 | M53: =M42*Inputs!$F$148*(1+Inputs!$F$149/100)^(Time!M26-Inputs!$F$256)/1000000 -> 0 | N53: =N42*Inputs!$F$148*(1+Inputs!$F$149/100)^(Time!N26-Inputs!$F$256)/1000000 -> 0 | O53: =O42*Inputs!$F$148*(1+Inputs!$F$149/100)^(Time!O26-Inputs!$F$256)/1000000 -> 0.82207222 | P53: =P42*Inputs!$F$148*(1+Inputs!$F$149/100)^(Time!P26-Inputs!$F$256)/1000000 -> 2.4659693 | Q53: =Q42*Inputs!$F$148*(1+Inputs!$F$149/100)^(Time!Q26-Inputs!$F$256)/1000000 -> 2.4945763 | ... BN53: =BN42*Inputs!$F$148*(1+Inputs!$F$149/100)^(Time!BN26-Inputs!$F$256)/1000000 -> 0
D54: Take-or-pay payment (pass-through) | E54: USD m | G54: =SUM(J54:BN54) -> 0 | J54: =MAX(0,J43-J42)*J41/1000000 -> 0 | K54: =MAX(0,K43-K42)*K41/1000000 -> 0 | L54: =MAX(0,L43-L42)*L41/1000000 -> 0 | M54: =MAX(0,M43-M42)*M41/1000000 -> 0 | N54: =MAX(0,N43-N42)*N41/1000000 -> 0 | O54: =MAX(0,O43-O42)*O41/1000000 -> 0 | P54: =MAX(0,P43-P42)*P41/1000000 -> 0 | Q54: =MAX(0,Q43-Q42)*Q41/1000000 -> 0 | ... BN54: =MAX(0,BN43-BN42)*BN41/1000000 -> 0
D55: Non-fuel revenue | E55: USD m | G55: =SUM(J55:BN55) -> 3820.6199 | J55: =J48+J50 -> 0 | K55: =K48+K50 -> 0 | L55: =L48+L50 -> 0 | M55: =M48+M50 -> 0 | N55: =N48+N50 -> 0 | O55: =O48+O50 -> 22.595146 | P55: =P48+P50 -> 68.079504 | Q55: =Q48+Q50 -> 68.350169 | ... BN55: =BN48+BN50 -> 0
D56: Total revenue | E56: USD m | G56: =SUM(J56:BN56) -> 9544.2224 | J56: =J55+J51+J52+J53+J54 -> 0 | K56: =K55+K51+K52+K53+K54 -> 0 | L56: =L55+L51+L52+L53+L54 -> 0 | M56: =M55+M51+M52+M53+M54 -> 0 | N56: =N55+N51+N52+N53+N54 -> 0 | O56: =O55+O51+O52+O53+O54 -> 53.012678 | P56: =P55+P51+P52+P53+P54 -> 159.3815 | Q56: =Q55+Q51+Q52+Q53+Q54 -> 160.93744 | ... BN56: =BN55+BN51+BN52+BN53+BN54 -> 0
D57: Late payment interest accrued (to settlement 2024-03-21) | E57: USD m | G57: =SUM(J57:BN57) -> 0 | J57: =IF(Inputs!$F$45=1,AVERAGE(I89,J89)*(J9-Time!J40*Inputs!$F$98+Inputs!$F$263)/100*Time!J55/Inputs!$F$247,0) -> 0 | K57: =IF(Inputs!$F$45=1,AVERAGE(J89,K89)*(K9-Time!K40*Inputs!$F$98+Inputs!$F$263)/100*Time!K55/Inputs!$F$247,0) -> 0 | L57: =IF(Inputs!$F$45=1,AVERAGE(K89,L89)*(L9-Time!L40*Inputs!$F$98+Inputs!$F$263)/100*Time!L55/Inputs!$F$247,0) -> 0 | M57: =IF(Inputs!$F$45=1,AVERAGE(L89,M89)*(M9-Time!M40*Inputs!$F$98+Inputs!$F$263)/100*Time!M55/Inputs!$F$247,0) -> 0 | N57: =IF(Inputs!$F$45=1,AVERAGE(M89,N89)*(N9-Time!N40*Inputs!$F$98+Inputs!$F$263)/100*Time!N55/Inputs!$F$247,0) -> 0 | O57: =IF(Inputs!$F$45=1,AVERAGE(N89,O89)*(O9-Time!O40*Inputs!$F$98+Inputs!$F$263)/100*Time!O55/Inputs!$F$247,0) -> 0 | P57: =IF(Inputs!$F$45=1,AVERAGE(O89,P89)*(P9-Time!P40*Inputs!$F$98+Inputs!$F$263)/100*Time!P55/Inputs!$F$247,0) -> 0 | Q57: =IF(Inputs!$F$45=1,AVERAGE(P89,Q89)*(Q9-Time!Q40*Inputs!$F$98+Inputs!$F$263)/100*Time!Q55/Inputs!$F$247,0) -> 0 | ... BN57: =IF(Inputs!$F$45=1,AVERAGE(BM89,BN89)*(BN9-Time!BN40*Inputs!$F$98+Inputs!$F$263)/100*Time!BN55/Inputs!$F$247,0) -> 0
D58: Late payment interest received (60%, with settlement installments) | E58: USD m | G58: =SUM(J58:BN58) -> 0 | J58: =Inputs!$F$264*SUM($J$57:$BN$57)*Inputs!J297 -> 0 | K58: =Inputs!$F$264*SUM($J$57:$BN$57)*Inputs!K297 -> 0 | L58: =Inputs!$F$264*SUM($J$57:$BN$57)*Inputs!L297 -> 0 | M58: =Inputs!$F$264*SUM($J$57:$BN$57)*Inputs!M297 -> 0 | N58: =Inputs!$F$264*SUM($J$57:$BN$57)*Inputs!N297 -> 0 | O58: =Inputs!$F$264*SUM($J$57:$BN$57)*Inputs!O297 -> 0 | P58: =Inputs!$F$264*SUM($J$57:$BN$57)*Inputs!P297 -> 0 | Q58: =Inputs!$F$264*SUM($J$57:$BN$57)*Inputs!Q297 -> 0 | ... BN58: =Inputs!$F$264*SUM($J$57:$BN$57)*Inputs!BN297 -> 0
B59: Operating costs (USD m)
D60: O&M fixed fee | E60: USD m | G60: =SUM(J60:BN60) -> 307.2956 | J60: =Inputs!$F$151*(Inputs!$F$152*J21+(1-Inputs!$F$152)*J27*Inputs!$F$153/J11)*Time!J30/12*Inputs!$F$40 -> 0 | K60: =Inputs!$F$151*(Inputs!$F$152*K21+(1-Inputs!$F$152)*K27*Inputs!$F$153/K11)*Time!K30/12*Inputs!$F$40 -> 0 | L60: =Inputs!$F$151*(Inputs!$F$152*L21+(1-Inputs!$F$152)*L27*Inputs!$F$153/L11)*Time!L30/12*Inputs!$F$40 -> 0 | M60: =Inputs!$F$151*(Inputs!$F$152*M21+(1-Inputs!$F$152)*M27*Inputs!$F$153/M11)*Time!M30/12*Inputs!$F$40 -> 0 | N60: =Inputs!$F$151*(Inputs!$F$152*N21+(1-Inputs!$F$152)*N27*Inputs!$F$153/N11)*Time!N30/12*Inputs!$F$40 -> 0 | O60: =Inputs!$F$151*(Inputs!$F$152*O21+(1-Inputs!$F$152)*O27*Inputs!$F$153/O11)*Time!O30/12*Inputs!$F$40 -> 1.5388455 | P60: =Inputs!$F$151*(Inputs!$F$152*P21+(1-Inputs!$F$152)*P27*Inputs!$F$153/P11)*Time!P30/12*Inputs!$F$40 -> 4.6670421 | Q60: =Inputs!$F$151*(Inputs!$F$152*Q21+(1-Inputs!$F$152)*Q27*Inputs!$F$153/Q11)*Time!Q30/12*Inputs!$F$40 -> 4.7181003 | ... BN60: =Inputs!$F$151*(Inputs!$F$152*BN21+(1-Inputs!$F$152)*BN27*Inputs!$F$153/BN11)*Time!BN30/12*Inputs!$F$40 -> 0
D61: O&M availability incentive | E61: USD m | G61: =SUM(J61:BN61) -> 4.1079836 | J61: =IF(Time!J30>0,Inputs!$F$154*MAX(-1,MIN(1,(J32-Inputs!$F$216)/Inputs!$F$217))*J21*Time!J30/12,0) -> 0 | K61: =IF(Time!K30>0,Inputs!$F$154*MAX(-1,MIN(1,(K32-Inputs!$F$216)/Inputs!$F$217))*K21*Time!K30/12,0) -> 0 | L61: =IF(Time!L30>0,Inputs!$F$154*MAX(-1,MIN(1,(L32-Inputs!$F$216)/Inputs!$F$217))*L21*Time!L30/12,0) -> 0 | M61: =IF(Time!M30>0,Inputs!$F$154*MAX(-1,MIN(1,(M32-Inputs!$F$216)/Inputs!$F$217))*M21*Time!M30/12,0) -> 0 | N61: =IF(Time!N30>0,Inputs!$F$154*MAX(-1,MIN(1,(N32-Inputs!$F$216)/Inputs!$F$217))*N21*Time!N30/12,0) -> 0 | O61: =IF(Time!O30>0,Inputs!$F$154*MAX(-1,MIN(1,(O32-Inputs!$F$216)/Inputs!$F$217))*O21*Time!O30/12,0) -> 0.063700261 | P61: =IF(Time!P30>0,Inputs!$F$154*MAX(-1,MIN(1,(P32-Inputs!$F$216)/Inputs!$F$217))*P21*Time!P30/12,0) -> 0.19319146 | Q61: =IF(Time!Q30>0,Inputs!$F$154*MAX(-1,MIN(1,(Q32-Inputs!$F$216)/Inputs!$F$217))*Q21*Time!Q30/12,0) -> 0.16275417 | ... BN61: =IF(Time!BN30>0,Inputs!$F$154*MAX(-1,MIN(1,(BN32-Inputs!$F$216)/Inputs!$F$217))*BN21*Time!BN30/12,0) -> 0
D62: LTSA fixed fee | E62: USD m | G62: =SUM(J62:BN62) -> 102.61164 | J62: =Inputs!$F$155*J21*Time!J30/12*Inputs!$F$40 -> 0 | K62: =Inputs!$F$155*K21*Time!K30/12*Inputs!$F$40 -> 0 | L62: =Inputs!$F$155*L21*Time!L30/12*Inputs!$F$40 -> 0 | M62: =Inputs!$F$155*M21*Time!M30/12*Inputs!$F$40 -> 0 | N62: =Inputs!$F$155*N21*Time!N30/12*Inputs!$F$40 -> 0 | O62: =Inputs!$F$155*O21*Time!O30/12*Inputs!$F$40 -> 0.51384877 | P62: =Inputs!$F$155*P21*Time!P30/12*Inputs!$F$40 -> 1.5584111 | Q62: =Inputs!$F$155*Q21*Time!Q30/12*Inputs!$F$40 -> 1.5754603 | ... BN62: =Inputs!$F$155*BN21*Time!BN30/12*Inputs!$F$40 -> 0
D63: Equivalent operating hours (2 GTs) | E63: EOH | J63: =IF(J31>0,Inputs!$F$258*(Inputs!$F$129*J32/J31*J37/Inputs!$F$131+Inputs!$F$130*Inputs!$F$132)*Time!J30/12,0) -> 0 | K63: =IF(K31>0,Inputs!$F$258*(Inputs!$F$129*K32/K31*K37/Inputs!$F$131+Inputs!$F$130*Inputs!$F$132)*Time!K30/12,0) -> 0 | L63: =IF(L31>0,Inputs!$F$258*(Inputs!$F$129*L32/L31*L37/Inputs!$F$131+Inputs!$F$130*Inputs!$F$132)*Time!L30/12,0) -> 0 | M63: =IF(M31>0,Inputs!$F$258*(Inputs!$F$129*M32/M31*M37/Inputs!$F$131+Inputs!$F$130*Inputs!$F$132)*Time!M30/12,0) -> 0 | N63: =IF(N31>0,Inputs!$F$258*(Inputs!$F$129*N32/N31*N37/Inputs!$F$131+Inputs!$F$130*Inputs!$F$132)*Time!N30/12,0) -> 0 | O63: =IF(O31>0,Inputs!$F$258*(Inputs!$F$129*O32/O31*O37/Inputs!$F$131+Inputs!$F$130*Inputs!$F$132)*Time!O30/12,0) -> 2813 | P63: =IF(P31>0,Inputs!$F$258*(Inputs!$F$129*P32/P31*P37/Inputs!$F$131+Inputs!$F$130*Inputs!$F$132)*Time!P30/12,0) -> 8439 | Q63: =IF(Q31>0,Inputs!$F$258*(Inputs!$F$129*Q32/Q31*Q37/Inputs!$F$131+Inputs!$F$130*Inputs!$F$132)*Time!Q30/12,0) -> 8439 | ... BN63: =IF(BN31>0,Inputs!$F$258*(Inputs!$F$129*BN32/BN31*BN37/Inputs!$F$131+Inputs!$F$130*Inputs!$F$132)*Time!BN30/12,0) -> 0
D64: LTSA variable fee | E64: USD m | G64: =SUM(J64:BN64) -> 289.83931 | J64: =J63*Inputs!$F$156*J21/1000000 -> 0 | K64: =K63*Inputs!$F$156*K21/1000000 -> 0 | L64: =L63*Inputs!$F$156*L21/1000000 -> 0 | M64: =M63*Inputs!$F$156*M21/1000000 -> 0 | N64: =N63*Inputs!$F$156*N21/1000000 -> 0 | O64: =O63*Inputs!$F$156*O21/1000000 -> 1.4514296 | P64: =P63*Inputs!$F$156*P21/1000000 -> 4.4019253 | Q64: =Q63*Inputs!$F$156*Q21/1000000 -> 4.450083 | ... BN64: =BN63*Inputs!$F$156*BN21/1000000 -> 0
D65: Operational insurance | E65: USD m | G65: =SUM(J65:BN65) -> 169.85337 | J65: =Inputs!$F$157*J21*Time!J30/12*(1+Inputs!$F$158*Inputs!$F$46*Time!J41)*Inputs!$F$40 -> 0 | K65: =Inputs!$F$157*K21*Time!K30/12*(1+Inputs!$F$158*Inputs!$F$46*Time!K41)*Inputs!$F$40 -> 0 | L65: =Inputs!$F$157*L21*Time!L30/12*(1+Inputs!$F$158*Inputs!$F$46*Time!L41)*Inputs!$F$40 -> 0 | M65: =Inputs!$F$157*M21*Time!M30/12*(1+Inputs!$F$158*Inputs!$F$46*Time!M41)*Inputs!$F$40 -> 0 | N65: =Inputs!$F$157*N21*Time!N30/12*(1+Inputs!$F$158*Inputs!$F$46*Time!N41)*Inputs!$F$40 -> 0 | O65: =Inputs!$F$157*O21*Time!O30/12*(1+Inputs!$F$158*Inputs!$F$46*Time!O41)*Inputs!$F$40 -> 0.85057543 | P65: =Inputs!$F$157*P21*Time!P30/12*(1+Inputs!$F$158*Inputs!$F$46*Time!P41)*Inputs!$F$40 -> 2.5796426 | Q65: =Inputs!$F$157*Q21*Time!Q30/12*(1+Inputs!$F$158*Inputs!$F$46*Time!Q41)*Inputs!$F$40 -> 2.6078643 | ... BN65: =Inputs!$F$157*BN21*Time!BN30/12*(1+Inputs!$F$158*Inputs!$F$46*Time!BN41)*Inputs!$F$40 -> 0
D66: G&A | E66: USD m | G66: =SUM(J66:BN66) -> 123.29103 | J66: =Inputs!$F$159*(Inputs!$F$218*J21+(1-Inputs!$F$218)*J27*Inputs!$F$153/J11)*Time!J30/12*Inputs!$F$40 -> 0 | K66: =Inputs!$F$159*(Inputs!$F$218*K21+(1-Inputs!$F$218)*K27*Inputs!$F$153/K11)*Time!K30/12*Inputs!$F$40 -> 0 | L66: =Inputs!$F$159*(Inputs!$F$218*L21+(1-Inputs!$F$218)*L27*Inputs!$F$153/L11)*Time!L30/12*Inputs!$F$40 -> 0 | M66: =Inputs!$F$159*(Inputs!$F$218*M21+(1-Inputs!$F$218)*M27*Inputs!$F$153/M11)*Time!M30/12*Inputs!$F$40 -> 0 | N66: =Inputs!$F$159*(Inputs!$F$218*N21+(1-Inputs!$F$218)*N27*Inputs!$F$153/N11)*Time!N30/12*Inputs!$F$40 -> 0 | O66: =Inputs!$F$159*(Inputs!$F$218*O21+(1-Inputs!$F$218)*O27*Inputs!$F$153/O11)*Time!O30/12*Inputs!$F$40 -> 0.61740503 | P66: =Inputs!$F$159*(Inputs!$F$218*P21+(1-Inputs!$F$218)*P27*Inputs!$F$153/P11)*Time!P30/12*Inputs!$F$40 -> 1.8724786 | Q66: =Inputs!$F$159*(Inputs!$F$218*Q21+(1-Inputs!$F$218)*Q27*Inputs!$F$153/Q11)*Time!Q30/12*Inputs!$F$40 -> 1.8929638 | ... BN66: =Inputs!$F$159*(Inputs!$F$218*BN21+(1-Inputs!$F$218)*BN27*Inputs!$F$153/BN11)*Time!BN30/12*Inputs!$F$40 -> 0
D67: Land lease and permits | E67: USD m | G67: =SUM(J67:BN67) -> 27.538393 | J67: =Inputs!$F$160*J27/J11*Time!J30/12*Inputs!$F$40 -> 0 | K67: =Inputs!$F$160*K27/K11*Time!K30/12*Inputs!$F$40 -> 0 | L67: =Inputs!$F$160*L27/L11*Time!L30/12*Inputs!$F$40 -> 0 | M67: =Inputs!$F$160*M27/M11*Time!M30/12*Inputs!$F$40 -> 0 | N67: =Inputs!$F$160*N27/N11*Time!N30/12*Inputs!$F$40 -> 0 | O67: =Inputs!$F$160*O27/O11*Time!O30/12*Inputs!$F$40 -> 0.13790413 | P67: =Inputs!$F$160*P27/P11*Time!P30/12*Inputs!$F$40 -> 0.41823847 | Q67: =Inputs!$F$160*Q27/Q11*Time!Q30/12*Inputs!$F$40 -> 0.42281406 | ... BN67: =Inputs!$F$160*BN27/BN11*Time!BN30/12*Inputs!$F$40 -> 0
D68: Community fund and OREK levy | E68: USD m | G68: =SUM(J68:BN68) -> 21.01341 | J68: =Inputs!$F$161/100*J55 -> 0 | K68: =Inputs!$F$161/100*K55 -> 0 | L68: =Inputs!$F$161/100*L55 -> 0 | M68: =Inputs!$F$161/100*M55 -> 0 | N68: =Inputs!$F$161/100*N55 -> 0 | O68: =Inputs!$F$161/100*O55 -> 0.12427331 | P68: =Inputs!$F$161/100*P55 -> 0.37443727 | Q68: =Inputs!$F$161/100*Q55 -> 0.37592593 | ... BN68: =Inputs!$F$161/100*BN55 -> 0
D69: Variable consumables | E69: USD m | G69: =SUM(J69:BN69) -> 134.8703 | J69: =Inputs!$F$162*(Inputs!$F$219*J21+(1-Inputs!$F$219)*J27*Inputs!$F$153/J11)*J38/1000000 -> 0 | K69: =Inputs!$F$162*(Inputs!$F$219*K21+(1-Inputs!$F$219)*K27*Inputs!$F$153/K11)*K38/1000000 -> 0 | L69: =Inputs!$F$162*(Inputs!$F$219*L21+(1-Inputs!$F$219)*L27*Inputs!$F$153/L11)*L38/1000000 -> 0 | M69: =Inputs!$F$162*(Inputs!$F$219*M21+(1-Inputs!$F$219)*M27*Inputs!$F$153/M11)*M38/1000000 -> 0 | N69: =Inputs!$F$162*(Inputs!$F$219*N21+(1-Inputs!$F$219)*N27*Inputs!$F$153/N11)*N38/1000000 -> 0 | O69: =Inputs!$F$162*(Inputs!$F$219*O21+(1-Inputs!$F$219)*O27*Inputs!$F$153/O11)*O38/1000000 -> 0.69860507 | P69: =Inputs!$F$162*(Inputs!$F$219*P21+(1-Inputs!$F$219)*P27*Inputs!$F$153/P11)*P38/1000000 -> 2.1176842 | Q69: =Inputs!$F$162*(Inputs!$F$219*Q21+(1-Inputs!$F$219)*Q27*Inputs!$F$153/Q11)*Q38/1000000 -> 2.1324035 | ... BN69: =Inputs!$F$162*(Inputs!$F$219*BN21+(1-Inputs!$F$219)*BN27*Inputs!$F$153/BN11)*BN38/1000000 -> 0
D70: Agency and account fees | E70: USD m | G70: =SUM(J70:BN70) -> 6.375 | J70: =Inputs!$F$107*Time!J30/12 -> 0 | K70: =Inputs!$F$107*Time!K30/12 -> 0 | L70: =Inputs!$F$107*Time!L30/12 -> 0 | M70: =Inputs!$F$107*Time!M30/12 -> 0 | N70: =Inputs!$F$107*Time!N30/12 -> 0 | O70: =Inputs!$F$107*Time!O30/12 -> 0.0425 | P70: =Inputs!$F$107*Time!P30/12 -> 0.1275 | Q70: =Inputs!$F$107*Time!Q30/12 -> 0.1275 | ... BN70: =Inputs!$F$107*Time!BN30/12 -> 0
D71: ABDB PRG fee | E71: USD m | G71: =SUM(J71:BN71) -> 7.78125 | J71: =Inputs!$F$163*Time!J30/12 -> 0 | K71: =Inputs!$F$163*Time!K30/12 -> 0 | L71: =Inputs!$F$163*Time!L30/12 -> 0 | M71: =Inputs!$F$163*Time!M30/12 -> 0 | N71: =Inputs!$F$163*Time!N30/12 -> 0 | O71: =Inputs!$F$163*Time!O30/12 -> 0.051875 | P71: =Inputs!$F$163*Time!P30/12 -> 0.155625 | Q71: =Inputs!$F$163*Time!Q30/12 -> 0.155625 | ... BN71: =Inputs!$F$163*Time!BN30/12 -> 0
D72: Operating costs before pass-through items | E72: USD m | G72: =SUM(J72:BN72) -> 1194.5773 | J72: =J60+J61+J62+J64+J65+J66+J67+J68+J69+J70+J71 -> 0 | K72: =K60+K61+K62+K64+K65+K66+K67+K68+K69+K70+K71 -> 0 | L72: =L60+L61+L62+L64+L65+L66+L67+L68+L69+L70+L71 -> 0 | M72: =M60+M61+M62+M64+M65+M66+M67+M68+M69+M70+M71 -> 0 | N72: =N60+N61+N62+N64+N65+N66+N67+N68+N69+N70+N71 -> 0 | O72: =O60+O61+O62+O64+O65+O66+O67+O68+O69+O70+O71 -> 6.0909621 | P72: =P60+P61+P62+P64+P65+P66+P67+P68+P69+P70+P71 -> 18.466176 | Q72: =Q60+Q61+Q62+Q64+Q65+Q66+Q67+Q68+Q69+Q70+Q71 -> 18.621494 | ... BN72: =BN60+BN61+BN62+BN64+BN65+BN66+BN67+BN68+BN69+BN70+BN71 -> 0
D73: Gas purchases | E73: USD m | G73: =SUM(J73:BN73) -> 4890.5537 | J73: =J42*J41/1000000 -> 0 | K73: =K42*K41/1000000 -> 0 | L73: =L42*L41/1000000 -> 0 | M73: =M42*M41/1000000 -> 0 | N73: =N42*N41/1000000 -> 0 | O73: =O42*O41/1000000 -> 25.730983 | P73: =P42*P41/1000000 -> 77.185206 | Q73: =Q42*Q41/1000000 -> 78.465244 | ... BN73: =BN42*BN41/1000000 -> 0
D74: Pass-through costs (gas, GTA, take-or-pay) | E74: USD m | G74: =SUM(J74:BN74) -> 5727.3299 | J74: =J73+J52+J53+J54 -> 0 | K74: =K73+K52+K53+K54 -> 0 | L74: =L73+L52+L53+L54 -> 0 | M74: =M73+M52+M53+M54 -> 0 | N74: =N73+N52+N53+N54 -> 0 | O74: =O73+O52+O53+O54 -> 30.369394 | P74: =P73+P52+P53+P54 -> 91.162756 | Q74: =Q73+Q52+Q53+Q54 -> 92.453571 | ... BN74: =BN73+BN52+BN53+BN54 -> 0
D75: VAT facility interest after the funding period | E75: USD m | G75: =SUM(J75:BN75) -> 0.11139716 | J75: =SUMIFS(Construction!$J$38:$BJ$38,Construction!$J$12:$BJ$12,Time!J20,Construction!$J$8:$BJ$8,">"&Time!$F$14) -> 0 | K75: =SUMIFS(Construction!$J$38:$BJ$38,Construction!$J$12:$BJ$12,Time!K20,Construction!$J$8:$BJ$8,">"&Time!$F$14) -> 0 | L75: =SUMIFS(Construction!$J$38:$BJ$38,Construction!$J$12:$BJ$12,Time!L20,Construction!$J$8:$BJ$8,">"&Time!$F$14) -> 0 | M75: =SUMIFS(Construction!$J$38:$BJ$38,Construction!$J$12:$BJ$12,Time!M20,Construction!$J$8:$BJ$8,">"&Time!$F$14) -> 0 | N75: =SUMIFS(Construction!$J$38:$BJ$38,Construction!$J$12:$BJ$12,Time!N20,Construction!$J$8:$BJ$8,">"&Time!$F$14) -> 0 | O75: =SUMIFS(Construction!$J$38:$BJ$38,Construction!$J$12:$BJ$12,Time!O20,Construction!$J$8:$BJ$8,">"&Time!$F$14) -> 0 | P75: =SUMIFS(Construction!$J$38:$BJ$38,Construction!$J$12:$BJ$12,Time!P20,Construction!$J$8:$BJ$8,">"&Time!$F$14) -> 0.098645733 | Q75: =SUMIFS(Construction!$J$38:$BJ$38,Construction!$J$12:$BJ$12,Time!Q20,Construction!$J$8:$BJ$8,">"&Time!$F$14) -> 0.012751429 | ... BN75: =SUMIFS(Construction!$J$38:$BJ$38,Construction!$J$12:$BJ$12,Time!BN20,Construction!$J$8:$BJ$8,">"&Time!$F$14) -> 0
D76: FX conversion losses | E76: USD m | G76: =SUM(J76:BN76) -> 0 | J76: =Inputs!$F$45*Inputs!J296 -> 0 | K76: =Inputs!$F$45*Inputs!K296 -> 0 | L76: =Inputs!$F$45*Inputs!L296 -> 0 | M76: =Inputs!$F$45*Inputs!M296 -> 0 | N76: =Inputs!$F$45*Inputs!N296 -> 0 | O76: =Inputs!$F$45*Inputs!O296 -> 0 | P76: =Inputs!$F$45*Inputs!P296 -> 0 | Q76: =Inputs!$F$45*Inputs!Q296 -> 0 | ... BN76: =Inputs!$F$45*Inputs!BN296 -> 0
D77: OY whose maintenance month could fall in the period | E77: OY | J77: =INT((Time!J33-Inputs!$F$221)/12)+1 -> 0 | K77: =INT((Time!K33-Inputs!$F$221)/12)+1 -> 0 | L77: =INT((Time!L33-Inputs!$F$221)/12)+1 -> 0 | M77: =INT((Time!M33-Inputs!$F$221)/12)+1 -> 0 | N77: =INT((Time!N33-Inputs!$F$221)/12)+1 -> 0 | O77: =INT((Time!O33-Inputs!$F$221)/12)+1 -> 0 | P77: =INT((Time!P33-Inputs!$F$221)/12)+1 -> 1 | Q77: =INT((Time!Q33-Inputs!$F$221)/12)+1 -> 1 | ... BN77: =INT((Time!BN33-Inputs!$F$221)/12)+1 -> 25
D78: Major maintenance outside LTSA (2018 prices) | E78: USD m | J78: =IF(AND(Time!J30>0,J77>=1,J77<=Inputs!$F$222,Time!J32<(J77-1)*12+Inputs!$F$221,(J77-1)*12+Inputs!$F$221<=Time!J33),IF(MOD(J77,Inputs!$F$223)=0,Inputs!$F$164,IF(MOD(J77,Inputs!$F$224)=0,Inputs!$F$165,0)),0) -> 0 | K78: =IF(AND(Time!K30>0,K77>=1,K77<=Inputs!$F$222,Time!K32<(K77-1)*12+Inputs!$F$221,(K77-1)*12+Inputs!$F$221<=Time!K33),IF(MOD(K77,Inputs!$F$223)=0,Inputs!$F$164,IF(MOD(K77,Inputs!$F$224)=0,Inputs!$F$165,0)),0) -> 0 | L78: =IF(AND(Time!L30>0,L77>=1,L77<=Inputs!$F$222,Time!L32<(L77-1)*12+Inputs!$F$221,(L77-1)*12+Inputs!$F$221<=Time!L33),IF(MOD(L77,Inputs!$F$223)=0,Inputs!$F$164,IF(MOD(L77,Inputs!$F$224)=0,Inputs!$F$165,0)),0) -> 0 | M78: =IF(AND(Time!M30>0,M77>=1,M77<=Inputs!$F$222,Time!M32<(M77-1)*12+Inputs!$F$221,(M77-1)*12+Inputs!$F$221<=Time!M33),IF(MOD(M77,Inputs!$F$223)=0,Inputs!$F$164,IF(MOD(M77,Inputs!$F$224)=0,Inputs!$F$165,0)),0) -> 0 | N78: =IF(AND(Time!N30>0,N77>=1,N77<=Inputs!$F$222,Time!N32<(N77-1)*12+Inputs!$F$221,(N77-1)*12+Inputs!$F$221<=Time!N33),IF(MOD(N77,Inputs!$F$223)=0,Inputs!$F$164,IF(MOD(N77,Inputs!$F$224)=0,Inputs!$F$165,0)),0) -> 0 | O78: =IF(AND(Time!O30>0,O77>=1,O77<=Inputs!$F$222,Time!O32<(O77-1)*12+Inputs!$F$221,(O77-1)*12+Inputs!$F$221<=Time!O33),IF(MOD(O77,Inputs!$F$223)=0,Inputs!$F$164,IF(MOD(O77,Inputs!$F$224)=0,Inputs!$F$165,0)),0) -> 0 | P78: =IF(AND(Time!P30>0,P77>=1,P77<=Inputs!$F$222,Time!P32<(P77-1)*12+Inputs!$F$221,(P77-1)*12+Inputs!$F$221<=Time!P33),IF(MOD(P77,Inputs!$F$223)=0,Inputs!$F$164,IF(MOD(P77,Inputs!$F$224)=0,Inputs!$F$165,0)),0) -> 0 | Q78: =IF(AND(Time!Q30>0,Q77>=1,Q77<=Inputs!$F$222,Time!Q32<(Q77-1)*12+Inputs!$F$221,(Q77-1)*12+Inputs!$F$221<=Time!Q33),IF(MOD(Q77,Inputs!$F$223)=0,Inputs!$F$164,IF(MOD(Q77,Inputs!$F$224)=0,Inputs!$F$165,0)),0) -> 0 | ... BN78: =IF(AND(Time!BN30>0,BN77>=1,BN77<=Inputs!$F$222,Time!BN32<(BN77-1)*12+Inputs!$F$221,(BN77-1)*12+Inputs!$F$221<=Time!BN33),IF(MOD(BN77,Inputs!$F$223)=0,Inputs!$F$164,IF(MOD(BN77,Inputs!$F$224)=0,Inputs!$F$165,0)),0) -> 0
D79: Major maintenance spend | E79: USD m | G79: =SUM(J79:BN79) -> 51.698065 | J79: =J78*J21 -> 0 | K79: =K78*K21 -> 0 | L79: =L78*L21 -> 0 | M79: =M78*M21 -> 0 | N79: =N78*N21 -> 0 | O79: =O78*O21 -> 0 | P79: =P78*P21 -> 0 | Q79: =Q78*Q21 -> 0 | ... BN79: =BN78*BN21 -> 0
D80: Months in period from the handback reserve year | E80: months | J80: =MAX(0,MIN(Time!J33,Time!$F$9)-MAX(Time!J32,(Inputs!$F$227-1)*12)) -> 0 | K80: =MAX(0,MIN(Time!K33,Time!$F$9)-MAX(Time!K32,(Inputs!$F$227-1)*12)) -> 0 | L80: =MAX(0,MIN(Time!L33,Time!$F$9)-MAX(Time!L32,(Inputs!$F$227-1)*12)) -> 0 | M80: =MAX(0,MIN(Time!M33,Time!$F$9)-MAX(Time!M32,(Inputs!$F$227-1)*12)) -> 0 | N80: =MAX(0,MIN(Time!N33,Time!$F$9)-MAX(Time!N32,(Inputs!$F$227-1)*12)) -> 0 | O80: =MAX(0,MIN(Time!O33,Time!$F$9)-MAX(Time!O32,(Inputs!$F$227-1)*12)) -> 0 | P80: =MAX(0,MIN(Time!P33,Time!$F$9)-MAX(Time!P32,(Inputs!$F$227-1)*12)) -> 0 | Q80: =MAX(0,MIN(Time!Q33,Time!$F$9)-MAX(Time!Q32,(Inputs!$F$227-1)*12)) -> 0 | ... BN80: =MAX(0,MIN(Time!BN33,Time!$F$9)-MAX(Time!BN32,(Inputs!$F$227-1)*12)) -> 0
D81: Handback reserve contribution required | E81: USD m | G81: =SUM(J81:BN81) -> 19.06919 | J81: =Inputs!$F$166*J21*J80/12 -> 0 | K81: =Inputs!$F$166*K21*K80/12 -> 0 | L81: =Inputs!$F$166*L21*L80/12 -> 0 | M81: =Inputs!$F$166*M21*M80/12 -> 0 | N81: =Inputs!$F$166*N21*N80/12 -> 0 | O81: =Inputs!$F$166*O21*O80/12 -> 0 | P81: =Inputs!$F$166*P21*P80/12 -> 0 | Q81: =Inputs!$F$166*Q21*Q80/12 -> 0 | ... BN81: =Inputs!$F$166*BN21*BN80/12 -> 0
D82: Handback works at PPA expiry | E82: USD m | G82: =SUM(J82:BN82) -> 19.06919 | J82: =Time!J37*SUM($J$81:$BN$81) -> 0 | K82: =Time!K37*SUM($J$81:$BN$81) -> 0 | L82: =Time!L37*SUM($J$81:$BN$81) -> 0 | M82: =Time!M37*SUM($J$81:$BN$81) -> 0 | N82: =Time!N37*SUM($J$81:$BN$81) -> 0 | O82: =Time!O37*SUM($J$81:$BN$81) -> 0 | P82: =Time!P37*SUM($J$81:$BN$81) -> 0 | Q82: =Time!Q37*SUM($J$81:$BN$81) -> 0 | ... BN82: =Time!BN37*SUM($J$81:$BN$81) -> 0
D83: Total operating costs | E83: USD m | G83: =SUM(J83:BN83) -> 6992.7859 | J83: =J72+J74+J75+J76+J79+J82 -> 0 | K83: =K72+K74+K75+K76+K79+K82 -> 0 | L83: =L72+L74+L75+L76+L79+L82 -> 0 | M83: =M72+M74+M75+M76+M79+M82 -> 0 | N83: =N72+N74+N75+N76+N79+N82 -> 0 | O83: =O72+O74+O75+O76+O79+O82 -> 36.460356 | P83: =P72+P74+P75+P76+P79+P82 -> 109.72758 | Q83: =Q72+Q74+Q75+Q76+Q79+Q82 -> 111.08782 | ... BN83: =BN72+BN74+BN75+BN76+BN79+BN82 -> 0
D84: EBITDA | E84: USD m | G84: =SUM(J84:BN84) -> 2551.4365 | J84: =J56-J83+J58 -> 0 | K84: =K56-K83+K58 -> 0 | L84: =L56-L83+L58 -> 0 | M84: =M56-M83+M58 -> 0 | N84: =N56-N83+N58 -> 0 | O84: =O56-O83+O58 -> 16.552321 | P84: =P56-P83+P58 -> 49.653926 | Q84: =Q56-Q83+Q58 -> 49.849628 | ... BN84: =BN56-BN83+BN58 -> 0
B85: Working capital (USD m, period-end balances)
D86: Flag: final operating period or later (working capital unwinds) | E86: flag | J86: =IF(Time!J20>=Time!$F$15,1,0) -> 0 | K86: =IF(Time!K20>=Time!$F$15,1,0) -> 0 | L86: =IF(Time!L20>=Time!$F$15,1,0) -> 0 | M86: =IF(Time!M20>=Time!$F$15,1,0) -> 0 | N86: =IF(Time!N20>=Time!$F$15,1,0) -> 0 | O86: =IF(Time!O20>=Time!$F$15,1,0) -> 0 | P86: =IF(Time!P20>=Time!$F$15,1,0) -> 0 | Q86: =IF(Time!Q20>=Time!$F$15,1,0) -> 0 | ... BN86: =IF(Time!BN20>=Time!$F$15,1,0) -> 1
D87: Extra receivable days on capacity and VOM (sensitivities) | E87: days | J87: =Inputs!$F$44*Time!J38 -> 0 | K87: =Inputs!$F$44*Time!K38 -> 0 | L87: =Inputs!$F$44*Time!L38 -> 0 | M87: =Inputs!$F$44*Time!M38 -> 0 | N87: =Inputs!$F$44*Time!N38 -> 0 | O87: =Inputs!$F$44*Time!O38 -> 0 | P87: =Inputs!$F$44*Time!P38 -> 0 | Q87: =Inputs!$F$44*Time!Q38 -> 0 | ... BN87: =Inputs!$F$44*Time!BN38 -> 0
D88: Trade receivables (normal terms) | E88: USD m | J88: =(1-J86)*(J56/MAX(Time!J31,1)*Inputs!$F$168+J55/MAX(Time!J31,1)*J87) -> 0 | K88: =(1-K86)*(K56/MAX(Time!K31,1)*Inputs!$F$168+K55/MAX(Time!K31,1)*K87) -> 0 | L88: =(1-L86)*(L56/MAX(Time!L31,1)*Inputs!$F$168+L55/MAX(Time!L31,1)*L87) -> 0 | M88: =(1-M86)*(M56/MAX(Time!M31,1)*Inputs!$F$168+M55/MAX(Time!M31,1)*M87) -> 0 | N88: =(1-N86)*(N56/MAX(Time!N31,1)*Inputs!$F$168+N55/MAX(Time!N31,1)*N87) -> 0 | O88: =(1-O86)*(O56/MAX(Time!O31,1)*Inputs!$F$168+O55/MAX(Time!O31,1)*O87) -> 39.107713 | P88: =(1-P86)*(P56/MAX(Time!P31,1)*Inputs!$F$168+P55/MAX(Time!P31,1)*P87) -> 38.979172 | Q88: =(1-Q86)*(Q56/MAX(Time!Q31,1)*Inputs!$F$168+Q55/MAX(Time!Q31,1)*Q87) -> 40.012072 | ... BN88: =(1-BN86)*(BN56/MAX(Time!BN31,1)*Inputs!$F$168+BN55/MAX(Time!BN31,1)*BN87) -> 0
D89: SEKA overdue receivables | E89: USD m | J89: =Inputs!$F$45*Inputs!J295 -> 0 | K89: =Inputs!$F$45*Inputs!K295 -> 0 | L89: =Inputs!$F$45*Inputs!L295 -> 0 | M89: =Inputs!$F$45*Inputs!M295 -> 0 | N89: =Inputs!$F$45*Inputs!N295 -> 0 | O89: =Inputs!$F$45*Inputs!O295 -> 0 | P89: =Inputs!$F$45*Inputs!P295 -> 0 | Q89: =Inputs!$F$45*Inputs!Q295 -> 0 | ... BN89: =Inputs!$F$45*Inputs!BN295 -> 0
D90: Gas payables | E90: USD m | J90: =(1-J86)*(J73+J54)/MAX(Time!J31,1)*Inputs!$F$169 -> 0 | K90: =(1-K86)*(K73+K54)/MAX(Time!K31,1)*Inputs!$F$169 -> 0 | L90: =(1-L86)*(L73+L54)/MAX(Time!L31,1)*Inputs!$F$169 -> 0 | M90: =(1-M86)*(M73+M54)/MAX(Time!M31,1)*Inputs!$F$169 -> 0 | N90: =(1-N86)*(N73+N54)/MAX(Time!N31,1)*Inputs!$F$169 -> 0 | O90: =(1-O86)*(O73+O54)/MAX(Time!O31,1)*Inputs!$F$169 -> 18.981873 | P90: =(1-P86)*(P73+P54)/MAX(Time!P31,1)*Inputs!$F$169 -> 18.876817 | Q90: =(1-Q86)*(Q73+Q54)/MAX(Time!Q31,1)*Inputs!$F$169 -> 19.507934 | ... BN90: =(1-BN86)*(BN73+BN54)/MAX(Time!BN31,1)*Inputs!$F$169 -> 0
D91: GTA payables | E91: USD m | J91: =(1-J86)*(J52+J53)/MAX(Time!J31,1)*Inputs!$F$170 -> 0 | K91: =(1-K86)*(K52+K53)/MAX(Time!K31,1)*Inputs!$F$170 -> 0 | L91: =(1-L86)*(L52+L53)/MAX(Time!L31,1)*Inputs!$F$170 -> 0 | M91: =(1-M86)*(M52+M53)/MAX(Time!M31,1)*Inputs!$F$170 -> 0 | N91: =(1-N86)*(N52+N53)/MAX(Time!N31,1)*Inputs!$F$170 -> 0 | O91: =(1-O86)*(O52+O53)/MAX(Time!O31,1)*Inputs!$F$170 -> 2.2811859 | P91: =(1-P86)*(P52+P53)/MAX(Time!P31,1)*Inputs!$F$170 -> 2.2789483 | Q91: =(1-Q86)*(Q52+Q53)/MAX(Time!Q31,1)*Inputs!$F$170 -> 2.3185071 | ... BN91: =(1-BN86)*(BN52+BN53)/MAX(Time!BN31,1)*Inputs!$F$170 -> 0
D92: O&M and LTSA payables | E92: USD m | J92: =(1-J86)*(J60+J61+J62+J64)/MAX(Time!J31,1)*Inputs!$F$171 -> 0 | K92: =(1-K86)*(K60+K61+K62+K64)/MAX(Time!K31,1)*Inputs!$F$171 -> 0 | L92: =(1-L86)*(L60+L61+L62+L64)/MAX(Time!L31,1)*Inputs!$F$171 -> 0 | M92: =(1-M86)*(M60+M61+M62+M64)/MAX(Time!M31,1)*Inputs!$F$171 -> 0 | N92: =(1-N86)*(N60+N61+N62+N64)/MAX(Time!N31,1)*Inputs!$F$171 -> 0 | O92: =(1-O86)*(O60+O61+O62+O64)/MAX(Time!O31,1)*Inputs!$F$171 -> 1.7546676 | P92: =(1-P86)*(P60+P61+P62+P64)/MAX(Time!P31,1)*Inputs!$F$171 -> 1.7642234 | Q92: =(1-Q86)*(Q60+Q61+Q62+Q64)/MAX(Time!Q31,1)*Inputs!$F$171 -> 1.8076903 | ... BN92: =(1-BN86)*(BN60+BN61+BN62+BN64)/MAX(Time!BN31,1)*Inputs!$F$171 -> 0
D93: Other payables | E93: USD m | J93: =(1-J86)*(J65+J66+J67+J68+J69+J70+J71)/MAX(Time!J31,1)*Inputs!$F$172 -> 0 | K93: =(1-K86)*(K65+K66+K67+K68+K69+K70+K71)/MAX(Time!K31,1)*Inputs!$F$172 -> 0 | L93: =(1-L86)*(L65+L66+L67+L68+L69+L70+L71)/MAX(Time!L31,1)*Inputs!$F$172 -> 0 | M93: =(1-M86)*(M65+M66+M67+M68+M69+M70+M71)/MAX(Time!M31,1)*Inputs!$F$172 -> 0 | N93: =(1-N86)*(N65+N66+N67+N68+N69+N70+N71)/MAX(Time!N31,1)*Inputs!$F$172 -> 0 | O93: =(1-O86)*(O65+O66+O67+O68+O69+O70+O71)/MAX(Time!O31,1)*Inputs!$F$172 -> 1.2408875 | P93: =(1-P86)*(P65+P66+P67+P68+P69+P70+P71)/MAX(Time!P31,1)*Inputs!$F$172 -> 1.2465662 | Q93: =(1-Q86)*(Q65+Q66+Q67+Q68+Q69+Q70+Q71)/MAX(Time!Q31,1)*Inputs!$F$172 -> 1.2787453 | ... BN93: =(1-BN86)*(BN65+BN66+BN67+BN68+BN69+BN70+BN71)/MAX(Time!BN31,1)*Inputs!$F$172 -> 0
D94: Deferred SNHK/GCK payables matching SEKA energy-charge arrears | E94: USD m | J94: =Inputs!$F$262*J89 -> 0 | K94: =Inputs!$F$262*K89 -> 0 | L94: =Inputs!$F$262*L89 -> 0 | M94: =Inputs!$F$262*M89 -> 0 | N94: =Inputs!$F$262*N89 -> 0 | O94: =Inputs!$F$262*O89 -> 0 | P94: =Inputs!$F$262*P89 -> 0 | Q94: =Inputs!$F$262*Q89 -> 0 | ... BN94: =Inputs!$F$262*BN89 -> 0
D95: Net working capital (excl. spares inventory) | E95: USD m | J95: =J88+J89-J90-J91-J92-J93-J94 -> 0 | K95: =K88+K89-K90-K91-K92-K93-K94 -> 0 | L95: =L88+L89-L90-L91-L92-L93-L94 -> 0 | M95: =M88+M89-M90-M91-M92-M93-M94 -> 0 | N95: =N88+N89-N90-N91-N92-N93-N94 -> 0 | O95: =O88+O89-O90-O91-O92-O93-O94 -> 14.849099 | P95: =P88+P89-P90-P91-P92-P93-P94 -> 14.812617 | Q95: =Q88+Q89-Q90-Q91-Q92-Q93-Q94 -> 15.099195 | ... BN95: =BN88+BN89-BN90-BN91-BN92-BN93-BN94 -> 0
D96: Increase in net working capital | E96: USD m | G96: =SUM(J96:BN96) -> 0 | J96: =J95-I95 -> 0 | K96: =K95-J95 -> 0 | L96: =L95-K95 -> 0 | M96: =M95-L95 -> 0 | N96: =N95-M95 -> 0 | O96: =O95-N95 -> 14.849099 | P96: =P95-O95 -> -0.036481908 | Q96: =Q95-P95 -> 0.28657804 | ... BN96: =BN95-BM95 -> 0
D97: Release of spares inventory at expiry | E97: USD m | G97: =SUM(J97:BN97) -> 5.35 | J97: =Time!J37*Inputs!$F$67*Inputs!$F$36 -> 0 | K97: =Time!K37*Inputs!$F$67*Inputs!$F$36 -> 0 | L97: =Time!L37*Inputs!$F$67*Inputs!$F$36 -> 0 | M97: =Time!M37*Inputs!$F$67*Inputs!$F$36 -> 0 | N97: =Time!N37*Inputs!$F$67*Inputs!$F$36 -> 0 | O97: =Time!O37*Inputs!$F$67*Inputs!$F$36 -> 0 | P97: =Time!P37*Inputs!$F$67*Inputs!$F$36 -> 0 | Q97: =Time!Q37*Inputs!$F$67*Inputs!$F$36 -> 0 | ... BN97: =Time!BN37*Inputs!$F$67*Inputs!$F$36 -> 0
D98: Fuel pass-through test: fuel charge less gas purchases (= heat-rate headroom margin) | E98: USD m | G98: =SUM(J98:BN98) -> -3.7275126 | J98: =J51-J73 -> 0 | K98: =K51-K73 -> 0 | L98: =L51-L73 -> 0 | M98: =M51-M73 -> 0 | N98: =N51-N73 -> 0 | O98: =O51-O73 -> 0.048136886 | P98: =P51-P73 -> 0.13924387 | Q98: =Q51-Q73 -> 0.13370432 | ... BN98: =BN51-BN73 -> 0
D99: GTA pass-through test (0 in every period) | E99: USD m | G99: =SUM(J99:BN99) -> 0 | J99: =J52+J53-(J74-J73-J54) -> 0 | K99: =K52+K53-(K74-K73-K54) -> 0 | L99: =L52+L53-(L74-L73-L54) -> 0 | M99: =M52+M53-(M74-M73-M54) -> 0 | N99: =N52+N53-(N74-N73-N54) -> 0 | O99: =O52+O53-(O74-O73-O54) -> 0 | P99: =P52+P53-(P74-P73-P54) -> 0 | Q99: =Q52+Q53-(Q74-Q73-Q54) -> 0 | ... BN99: =BN52+BN53-(BN74-BN73-BN54) -> 0

Sheet Tax
A1: Case P: Belanou Combined Cycle Power Project, Republic of Kessara
A2: Tax: holiday, deferred depreciation, thin capitalization, minimum turnover tax
A3: Units in column E; constants in column F; row totals in column G; first period in column J. Inputs: blue on yellow. Links from other sheets: green.
D4: Label | E4: Unit | F4: Constant | G4: Total
D5: Period ending | J5: 2018H2 | K5: 2019H1 | L5: 2019H2 | M5: 2020H1 | N5: 2020H2 | O5: 2021H1 | P5: 2021H2 | Q5: 2022H1 | R5: 2022H2 | S5: 2023H1 | T5: 2023H2 | U5: 2024H1 | V5: 2024H2 | W5: 2025H1 | X5: 2025H2 | Y5: 2026H1 | Z5: 2026H2 | AA5: 2027H1 | AB5: 2027H2 | AC5: 2028H1 | AD5: 2028H2 | AE5: 2029H1 | AF5: 2029H2 | AG5: 2030H1 | AH5: 2030H2 | AI5: 2031H1 | AJ5: 2031H2 | AK5: 2032H1 | AL5: 2032H2 | AM5: 2033H1 | AN5: 2033H2 | AO5: 2034H1 | AP5: 2034H2 | AQ5: 2035H1 | AR5: 2035H2 | AS5: 2036H1 | AT5: 2036H2 | AU5: 2037H1 | AV5: 2037H2 | AW5: 2038H1 | AX5: 2038H2 | AY5: 2039H1 | AZ5: 2039H2 | BA5: 2040H1 | BB5: 2040H2 | BC5: 2041H1 | BD5: 2041H2 | BE5: 2042H1 | BF5: 2042H2 | BG5: 2043H1 | BH5: 2043H2 | BI5: 2044H1 | BJ5: 2044H2 | BK5: 2045H1 | BL5: 2045H2 | BM5: 2046H1 | BN5: 2046H2
D7: Holiday months (OY1-OY5) | E7: months | J7: =MAX(0,MIN(Time!J33,Inputs!$F$228*12)-MIN(Time!J32,Inputs!$F$228*12)) -> 0 | K7: =MAX(0,MIN(Time!K33,Inputs!$F$228*12)-MIN(Time!K32,Inputs!$F$228*12)) -> 0 | L7: =MAX(0,MIN(Time!L33,Inputs!$F$228*12)-MIN(Time!L32,Inputs!$F$228*12)) -> 0 | M7: =MAX(0,MIN(Time!M33,Inputs!$F$228*12)-MIN(Time!M32,Inputs!$F$228*12)) -> 0 | N7: =MAX(0,MIN(Time!N33,Inputs!$F$228*12)-MIN(Time!N32,Inputs!$F$228*12)) -> 0 | O7: =MAX(0,MIN(Time!O33,Inputs!$F$228*12)-MIN(Time!O32,Inputs!$F$228*12)) -> 2 | P7: =MAX(0,MIN(Time!P33,Inputs!$F$228*12)-MIN(Time!P32,Inputs!$F$228*12)) -> 6 | Q7: =MAX(0,MIN(Time!Q33,Inputs!$F$228*12)-MIN(Time!Q32,Inputs!$F$228*12)) -> 6 | ... BN7: =MAX(0,MIN(Time!BN33,Inputs!$F$228*12)-MIN(Time!BN32,Inputs!$F$228*12)) -> 0
D8: Reduced-rate months (OY6-OY8) | E8: months | J8: =MAX(0,MIN(Time!J33,Inputs!$F$229*12)-MIN(MAX(Time!J32,Inputs!$F$228*12),Inputs!$F$229*12)) -> 0 | K8: =MAX(0,MIN(Time!K33,Inputs!$F$229*12)-MIN(MAX(Time!K32,Inputs!$F$228*12),Inputs!$F$229*12)) -> 0 | L8: =MAX(0,MIN(Time!L33,Inputs!$F$229*12)-MIN(MAX(Time!L32,Inputs!$F$228*12),Inputs!$F$229*12)) -> 0 | M8: =MAX(0,MIN(Time!M33,Inputs!$F$229*12)-MIN(MAX(Time!M32,Inputs!$F$228*12),Inputs!$F$229*12)) -> 0 | N8: =MAX(0,MIN(Time!N33,Inputs!$F$229*12)-MIN(MAX(Time!N32,Inputs!$F$228*12),Inputs!$F$229*12)) -> 0 | O8: =MAX(0,MIN(Time!O33,Inputs!$F$229*12)-MIN(MAX(Time!O32,Inputs!$F$228*12),Inputs!$F$229*12)) -> 0 | P8: =MAX(0,MIN(Time!P33,Inputs!$F$229*12)-MIN(MAX(Time!P32,Inputs!$F$228*12),Inputs!$F$229*12)) -> 0 | Q8: =MAX(0,MIN(Time!Q33,Inputs!$F$229*12)-MIN(MAX(Time!Q32,Inputs!$F$228*12),Inputs!$F$229*12)) -> 0 | ... BN8: =MAX(0,MIN(Time!BN33,Inputs!$F$229*12)-MIN(MAX(Time!BN32,Inputs!$F$228*12),Inputs!$F$229*12)) -> 0
D9: Full-rate months (OY9+) | E9: months | J9: =Time!J30-J7-J8 -> 0 | K9: =Time!K30-K7-K8 -> 0 | L9: =Time!L30-L7-L8 -> 0 | M9: =Time!M30-M7-M8 -> 0 | N9: =Time!N30-N7-N8 -> 0 | O9: =Time!O30-O7-O8 -> 0 | P9: =Time!P30-P7-P8 -> 0 | Q9: =Time!Q30-Q7-Q8 -> 0 | ... BN9: =Time!BN30-BN7-BN8 -> 0
D10: Tax depreciation (straight line from COD) | E10: USD m | G10: =SUM(J10:BN10) -> 836.45256 | J10: =Inputs!$F$177*Funding!$F$76/Inputs!$F$178*MAX(0,MIN(Time!J33,Inputs!$F$178)-MIN(Time!J32,Inputs!$F$178))+Inputs!$F$179*Funding!$F$76/Inputs!$F$180*MAX(0,MIN(Time!J33,Inputs!$F$180)-MIN(Time!J32,Inputs!$F$180))+Inputs!$F$181*Funding!$F$76/Inputs!$F$182*MAX(0,MIN(Time!J33,Inputs!$F$182)-MIN(Time!J32,Inputs!$F$182)) -> 0 | K10: =Inputs!$F$177*Funding!$F$76/Inputs!$F$178*MAX(0,MIN(Time!K33,Inputs!$F$178)-MIN(Time!K32,Inputs!$F$178))+Inputs!$F$179*Funding!$F$76/Inputs!$F$180*MAX(0,MIN(Time!K33,Inputs!$F$180)-MIN(Time!K32,Inputs!$F$180))+Inputs!$F$181*Funding!$F$76/Inputs!$F$182*MAX(0,MIN(Time!K33,Inputs!$F$182)-MIN(Time!K32,Inputs!$F$182)) -> 0 | L10: =Inputs!$F$177*Funding!$F$76/Inputs!$F$178*MAX(0,MIN(Time!L33,Inputs!$F$178)-MIN(Time!L32,Inputs!$F$178))+Inputs!$F$179*Funding!$F$76/Inputs!$F$180*MAX(0,MIN(Time!L33,Inputs!$F$180)-MIN(Time!L32,Inputs!$F$180))+Inputs!$F$181*Funding!$F$76/Inputs!$F$182*MAX(0,MIN(Time!L33,Inputs!$F$182)-MIN(Time!L32,Inputs!$F$182)) -> 0 | M10: =Inputs!$F$177*Funding!$F$76/Inputs!$F$178*MAX(0,MIN(Time!M33,Inputs!$F$178)-MIN(Time!M32,Inputs!$F$178))+Inputs!$F$179*Funding!$F$76/Inputs!$F$180*MAX(0,MIN(Time!M33,Inputs!$F$180)-MIN(Time!M32,Inputs!$F$180))+Inputs!$F$181*Funding!$F$76/Inputs!$F$182*MAX(0,MIN(Time!M33,Inputs!$F$182)-MIN(Time!M32,Inputs!$F$182)) -> 0 | N10: =Inputs!$F$177*Funding!$F$76/Inputs!$F$178*MAX(0,MIN(Time!N33,Inputs!$F$178)-MIN(Time!N32,Inputs!$F$178))+Inputs!$F$179*Funding!$F$76/Inputs!$F$180*MAX(0,MIN(Time!N33,Inputs!$F$180)-MIN(Time!N32,Inputs!$F$180))+Inputs!$F$181*Funding!$F$76/Inputs!$F$182*MAX(0,MIN(Time!N33,Inputs!$F$182)-MIN(Time!N32,Inputs!$F$182)) -> 0 | O10: =Inputs!$F$177*Funding!$F$76/Inputs!$F$178*MAX(0,MIN(Time!O33,Inputs!$F$178)-MIN(Time!O32,Inputs!$F$178))+Inputs!$F$179*Funding!$F$76/Inputs!$F$180*MAX(0,MIN(Time!O33,Inputs!$F$180)-MIN(Time!O32,Inputs!$F$180))+Inputs!$F$181*Funding!$F$76/Inputs!$F$182*MAX(0,MIN(Time!O33,Inputs!$F$182)-MIN(Time!O32,Inputs!$F$182)) -> 7.5280731 | P10: =Inputs!$F$177*Funding!$F$76/Inputs!$F$178*MAX(0,MIN(Time!P33,Inputs!$F$178)-MIN(Time!P32,Inputs!$F$178))+Inputs!$F$179*Funding!$F$76/Inputs!$F$180*MAX(0,MIN(Time!P33,Inputs!$F$180)-MIN(Time!P32,Inputs!$F$180))+Inputs!$F$181*Funding!$F$76/Inputs!$F$182*MAX(0,MIN(Time!P33,Inputs!$F$182)-MIN(Time!P32,Inputs!$F$182)) -> 22.584219 | Q10: =Inputs!$F$177*Funding!$F$76/Inputs!$F$178*MAX(0,MIN(Time!Q33,Inputs!$F$178)-MIN(Time!Q32,Inputs!$F$178))+Inputs!$F$179*Funding!$F$76/Inputs!$F$180*MAX(0,MIN(Time!Q33,Inputs!$F$180)-MIN(Time!Q32,Inputs!$F$180))+Inputs!$F$181*Funding!$F$76/Inputs!$F$182*MAX(0,MIN(Time!Q33,Inputs!$F$182)-MIN(Time!Q32,Inputs!$F$182)) -> 22.584219 | ... BN10: =Inputs!$F$177*Funding!$F$76/Inputs!$F$178*MAX(0,MIN(Time!BN33,Inputs!$F$178)-MIN(Time!BN32,Inputs!$F$178))+Inputs!$F$179*Funding!$F$76/Inputs!$F$180*MAX(0,MIN(Time!BN33,Inputs!$F$180)-MIN(Time!BN32,Inputs!$F$180))+Inputs!$F$181*Funding!$F$76/Inputs!$F$182*MAX(0,MIN(Time!BN33,Inputs!$F$182)-MIN(Time!BN32,Inputs!$F$182)) -> 0
D11: Depreciation of holiday months (deemed deferred) | E11: USD m | G11: =SUM(J11:BN11) -> 225.84219 | J11: =(Inputs!$F$177*Funding!$F$76/Inputs!$F$178+Inputs!$F$179*Funding!$F$76/Inputs!$F$180)*J7+Inputs!$F$181*Funding!$F$76/Inputs!$F$182*MAX(0,MIN(Time!J33,MIN(Inputs!$F$182,Inputs!$F$228*12))-MIN(Time!J32,MIN(Inputs!$F$182,Inputs!$F$228*12))) -> 0 | K11: =(Inputs!$F$177*Funding!$F$76/Inputs!$F$178+Inputs!$F$179*Funding!$F$76/Inputs!$F$180)*K7+Inputs!$F$181*Funding!$F$76/Inputs!$F$182*MAX(0,MIN(Time!K33,MIN(Inputs!$F$182,Inputs!$F$228*12))-MIN(Time!K32,MIN(Inputs!$F$182,Inputs!$F$228*12))) -> 0 | L11: =(Inputs!$F$177*Funding!$F$76/Inputs!$F$178+Inputs!$F$179*Funding!$F$76/Inputs!$F$180)*L7+Inputs!$F$181*Funding!$F$76/Inputs!$F$182*MAX(0,MIN(Time!L33,MIN(Inputs!$F$182,Inputs!$F$228*12))-MIN(Time!L32,MIN(Inputs!$F$182,Inputs!$F$228*12))) -> 0 | M11: =(Inputs!$F$177*Funding!$F$76/Inputs!$F$178+Inputs!$F$179*Funding!$F$76/Inputs!$F$180)*M7+Inputs!$F$181*Funding!$F$76/Inputs!$F$182*MAX(0,MIN(Time!M33,MIN(Inputs!$F$182,Inputs!$F$228*12))-MIN(Time!M32,MIN(Inputs!$F$182,Inputs!$F$228*12))) -> 0 | N11: =(Inputs!$F$177*Funding!$F$76/Inputs!$F$178+Inputs!$F$179*Funding!$F$76/Inputs!$F$180)*N7+Inputs!$F$181*Funding!$F$76/Inputs!$F$182*MAX(0,MIN(Time!N33,MIN(Inputs!$F$182,Inputs!$F$228*12))-MIN(Time!N32,MIN(Inputs!$F$182,Inputs!$F$228*12))) -> 0 | O11: =(Inputs!$F$177*Funding!$F$76/Inputs!$F$178+Inputs!$F$179*Funding!$F$76/Inputs!$F$180)*O7+Inputs!$F$181*Funding!$F$76/Inputs!$F$182*MAX(0,MIN(Time!O33,MIN(Inputs!$F$182,Inputs!$F$228*12))-MIN(Time!O32,MIN(Inputs!$F$182,Inputs!$F$228*12))) -> 7.5280731 | P11: =(Inputs!$F$177*Funding!$F$76/Inputs!$F$178+Inputs!$F$179*Funding!$F$76/Inputs!$F$180)*P7+Inputs!$F$181*Funding!$F$76/Inputs!$F$182*MAX(0,MIN(Time!P33,MIN(Inputs!$F$182,Inputs!$F$228*12))-MIN(Time!P32,MIN(Inputs!$F$182,Inputs!$F$228*12))) -> 22.584219 | Q11: =(Inputs!$F$177*Funding!$F$76/Inputs!$F$178+Inputs!$F$179*Funding!$F$76/Inputs!$F$180)*Q7+Inputs!$F$181*Funding!$F$76/Inputs!$F$182*MAX(0,MIN(Time!Q33,MIN(Inputs!$F$182,Inputs!$F$228*12))-MIN(Time!Q32,MIN(Inputs!$F$182,Inputs!$F$228*12))) -> 22.584219 | ... BN11: =(Inputs!$F$177*Funding!$F$76/Inputs!$F$178+Inputs!$F$179*Funding!$F$76/Inputs!$F$180)*BN7+Inputs!$F$181*Funding!$F$76/Inputs!$F$182*MAX(0,MIN(Time!BN33,MIN(Inputs!$F$182,Inputs!$F$228*12))-MIN(Time!BN32,MIN(Inputs!$F$182,Inputs!$F$228*12))) -> 0
D12: Depreciation deducted currently | E12: USD m | G12: =SUM(J12:BN12) -> 610.61037 | J12: =J10-J11 -> 0 | K12: =K10-K11 -> 0 | L12: =L10-L11 -> 0 | M12: =M10-M11 -> 0 | N12: =N10-N11 -> 0 | O12: =O10-O11 -> 0 | P12: =P10-P11 -> 0 | Q12: =Q10-Q11 -> 0 | ... BN12: =BN10-BN11 -> 0
D13: Shareholder loan interest accrued | E13: USD m | G13: =SUM(J13:BN13) -> 222.68721 | J13: =IF(Time!J20>=Time!$F$12,Waterfall!J33*Inputs!$F$104/100*Time!J31/Inputs!$F$248,0) -> 0 | K13: =IF(Time!K20>=Time!$F$12,Waterfall!K33*Inputs!$F$104/100*Time!K31/Inputs!$F$248,0) -> 0 | L13: =IF(Time!L20>=Time!$F$12,Waterfall!L33*Inputs!$F$104/100*Time!L31/Inputs!$F$248,0) -> 0 | M13: =IF(Time!M20>=Time!$F$12,Waterfall!M33*Inputs!$F$104/100*Time!M31/Inputs!$F$248,0) -> 0 | N13: =IF(Time!N20>=Time!$F$12,Waterfall!N33*Inputs!$F$104/100*Time!N31/Inputs!$F$248,0) -> 0 | O13: =IF(Time!O20>=Time!$F$12,Waterfall!O33*Inputs!$F$104/100*Time!O31/Inputs!$F$248,0) -> 3.2416808 | P13: =IF(Time!P20>=Time!$F$12,Waterfall!P33*Inputs!$F$104/100*Time!P31/Inputs!$F$248,0) -> 9.9334301 | Q13: =IF(Time!Q20>=Time!$F$12,Waterfall!Q33*Inputs!$F$104/100*Time!Q31/Inputs!$F$248,0) -> 9.588361 | ... BN13: =IF(Time!BN20>=Time!$F$12,Waterfall!BN33*Inputs!$F$104/100*Time!BN31/Inputs!$F$248,0) -> 0
D14: Thin cap: deductible share = min(1, 3 x equity / SHL) | E14: fraction | J14: =IF(Waterfall!J33>0,MIN(1,Inputs!$F$183*(Waterfall!$F$32+MAX(0,Waterfall!I43))/Waterfall!J33),1) -> 1 | K14: =IF(Waterfall!K33>0,MIN(1,Inputs!$F$183*(Waterfall!$F$32+MAX(0,Waterfall!J43))/Waterfall!K33),1) -> 1 | L14: =IF(Waterfall!L33>0,MIN(1,Inputs!$F$183*(Waterfall!$F$32+MAX(0,Waterfall!K43))/Waterfall!L33),1) -> 1 | M14: =IF(Waterfall!M33>0,MIN(1,Inputs!$F$183*(Waterfall!$F$32+MAX(0,Waterfall!L43))/Waterfall!M33),1) -> 1 | N14: =IF(Waterfall!N33>0,MIN(1,Inputs!$F$183*(Waterfall!$F$32+MAX(0,Waterfall!M43))/Waterfall!N33),1) -> 1 | O14: =IF(Waterfall!O33>0,MIN(1,Inputs!$F$183*(Waterfall!$F$32+MAX(0,Waterfall!N43))/Waterfall!O33),1) -> 0.66001776 | P14: =IF(Waterfall!P33>0,MIN(1,Inputs!$F$183*(Waterfall!$F$32+MAX(0,Waterfall!O43))/Waterfall!P33),1) -> 0.78576271 | Q14: =IF(Waterfall!Q33>0,MIN(1,Inputs!$F$183*(Waterfall!$F$32+MAX(0,Waterfall!P43))/Waterfall!Q33),1) -> 0.89462413 | ... BN14: =IF(Waterfall!BN33>0,MIN(1,Inputs!$F$183*(Waterfall!$F$32+MAX(0,Waterfall!BM43))/Waterfall!BN33),1) -> 1
D15: Shareholder loan interest deductible | E15: USD m | G15: =SUM(J15:BN15) -> 218.4466 | J15: =J13*J14 -> 0 | K15: =K13*K14 -> 0 | L15: =L13*L14 -> 0 | M15: =M13*M14 -> 0 | N15: =N13*N14 -> 0 | O15: =O13*O14 -> 2.1395669 | P15: =P13*P14 -> 7.8053189 | Q15: =Q13*Q14 -> 8.5779792 | ... BN15: =BN13*BN14 -> 0
D16: Senior financing costs deductible (all grandfathered) | E16: USD m | G16: =SUM(J16:BN16) -> 318.50754 | J16: =Debt!J112+Debt!J110+Debt!J104-Debt!J103 -> 0 | K16: =Debt!K112+Debt!K110+Debt!K104-Debt!K103 -> 0 | L16: =Debt!L112+Debt!L110+Debt!L104-Debt!L103 -> 0 | M16: =Debt!M112+Debt!M110+Debt!M104-Debt!M103 -> 0 | N16: =Debt!N112+Debt!N110+Debt!N104-Debt!N103 -> 0 | O16: =Debt!O112+Debt!O110+Debt!O104-Debt!O103 -> 0 | P16: =Debt!P112+Debt!P110+Debt!P104-Debt!P103 -> 21.642589 | Q16: =Debt!Q112+Debt!Q110+Debt!Q104-Debt!Q103 -> 20.940936 | ... BN16: =Debt!BN112+Debt!BN110+Debt!BN104-Debt!BN103 -> 0
D17: Non-holiday share of operating months | E17: fraction | J17: =IF(Time!J30>0,(Time!J30-J7)/Time!J30,0) -> 0 | K17: =IF(Time!K30>0,(Time!K30-K7)/Time!K30,0) -> 0 | L17: =IF(Time!L30>0,(Time!L30-L7)/Time!L30,0) -> 0 | M17: =IF(Time!M30>0,(Time!M30-M7)/Time!M30,0) -> 0 | N17: =IF(Time!N30>0,(Time!N30-N7)/Time!N30,0) -> 0 | O17: =IF(Time!O30>0,(Time!O30-O7)/Time!O30,0) -> 0 | P17: =IF(Time!P30>0,(Time!P30-P7)/Time!P30,0) -> 0 | Q17: =IF(Time!Q30>0,(Time!Q30-Q7)/Time!Q30,0) -> 0 | ... BN17: =IF(Time!BN30>0,(Time!BN30-BN7)/Time!BN30,0) -> 0
D18: Taxable income before losses and deferred depreciation | E18: USD m | G18: =SUM(J18:BN18) -> 1178.5707 | J18: =(Operations!J84-J16-J15)*J17-J12 -> 0 | K18: =(Operations!K84-K16-K15)*K17-K12 -> 0 | L18: =(Operations!L84-L16-L15)*L17-L12 -> 0 | M18: =(Operations!M84-M16-M15)*M17-M12 -> 0 | N18: =(Operations!N84-N16-N15)*N17-N12 -> 0 | O18: =(Operations!O84-O16-O15)*O17-O12 -> 0 | P18: =(Operations!P84-P16-P15)*P17-P12 -> 0 | Q18: =(Operations!Q84-Q16-Q15)*Q17-Q12 -> 0 | ... BN18: =(Operations!BN84-BN16-BN15)*BN17-BN12 -> 0
D19: Tax losses used | E19: USD m | G19: =SUM(J19:BN19) -> 2.3474755 | J19: =MIN(I22,MAX(0,J18)) -> 0 | K19: =MIN(J22,MAX(0,K18)) -> 0 | L19: =MIN(K22,MAX(0,L18)) -> 0 | M19: =MIN(L22,MAX(0,M18)) -> 0 | N19: =MIN(M22,MAX(0,N18)) -> 0 | O19: =MIN(N22,MAX(0,O18)) -> 0 | P19: =MIN(O22,MAX(0,P18)) -> 0 | Q19: =MIN(P22,MAX(0,Q18)) -> 0 | ... BN19: =MIN(BM22,MAX(0,BN18)) -> 0
D20: Deferred depreciation used | E20: USD m | G20: =SUM(J20:BN20) -> 225.84219 | J20: =MIN(I21,MAX(0,J18-J19)) -> 0 | K20: =MIN(J21,MAX(0,K18-K19)) -> 0 | L20: =MIN(K21,MAX(0,L18-L19)) -> 0 | M20: =MIN(L21,MAX(0,M18-M19)) -> 0 | N20: =MIN(M21,MAX(0,N18-N19)) -> 0 | O20: =MIN(N21,MAX(0,O18-O19)) -> 0 | P20: =MIN(O21,MAX(0,P18-P19)) -> 0 | Q20: =MIN(P21,MAX(0,Q18-Q19)) -> 0 | ... BN20: =MIN(BM21,MAX(0,BN18-BN19)) -> 0
D21: Deferred depreciation pool, closing | E21: USD m | J21: =I21+J11-J20 -> 0 | K21: =J21+K11-K20 -> 0 | L21: =K21+L11-L20 -> 0 | M21: =L21+M11-M20 -> 0 | N21: =M21+N11-N20 -> 0 | O21: =N21+O11-O20 -> 7.5280731 | P21: =O21+P11-P20 -> 30.112292 | Q21: =P21+Q11-Q20 -> 52.696512 | ... BN21: =BM21+BN11-BN20 -> 0
D22: Tax losses carried forward, closing | E22: USD m | J22: =I22-J19+MAX(0,-J18) -> 0 | K22: =J22-K19+MAX(0,-K18) -> 0 | L22: =K22-L19+MAX(0,-L18) -> 0 | M22: =L22-M19+MAX(0,-M18) -> 0 | N22: =M22-N19+MAX(0,-N18) -> 0 | O22: =N22-O19+MAX(0,-O18) -> 0 | P22: =O22-P19+MAX(0,-P18) -> 0 | Q22: =P22-Q19+MAX(0,-Q18) -> 0 | ... BN22: =BM22-BN19+MAX(0,-BN18) -> 0
D23: Taxable income | E23: USD m | G23: =SUM(J23:BN23) -> 952.72849 | J23: =MAX(0,J18-J19-J20) -> 0 | K23: =MAX(0,K18-K19-K20) -> 0 | L23: =MAX(0,L18-L19-L20) -> 0 | M23: =MAX(0,M18-M19-M20) -> 0 | N23: =MAX(0,N18-N19-N20) -> 0 | O23: =MAX(0,O18-O19-O20) -> 0 | P23: =MAX(0,P18-P19-P20) -> 0 | Q23: =MAX(0,Q18-Q19-Q20) -> 0 | ... BN23: =MAX(0,BN18-BN19-BN20) -> 0
D24: Applicable CIT rate (month-weighted) | E24: % | J24: =IF(J8+J9>0,(J8*Inputs!$F$175+J9*Inputs!$F$174)/(J8+J9)/100,0) -> 0 | K24: =IF(K8+K9>0,(K8*Inputs!$F$175+K9*Inputs!$F$174)/(K8+K9)/100,0) -> 0 | L24: =IF(L8+L9>0,(L8*Inputs!$F$175+L9*Inputs!$F$174)/(L8+L9)/100,0) -> 0 | M24: =IF(M8+M9>0,(M8*Inputs!$F$175+M9*Inputs!$F$174)/(M8+M9)/100,0) -> 0 | N24: =IF(N8+N9>0,(N8*Inputs!$F$175+N9*Inputs!$F$174)/(N8+N9)/100,0) -> 0 | O24: =IF(O8+O9>0,(O8*Inputs!$F$175+O9*Inputs!$F$174)/(O8+O9)/100,0) -> 0 | P24: =IF(P8+P9>0,(P8*Inputs!$F$175+P9*Inputs!$F$174)/(P8+P9)/100,0) -> 0 | Q24: =IF(Q8+Q9>0,(Q8*Inputs!$F$175+Q9*Inputs!$F$174)/(Q8+Q9)/100,0) -> 0 | ... BN24: =IF(BN8+BN9>0,(BN8*Inputs!$F$175+BN9*Inputs!$F$174)/(BN8+BN9)/100,0) -> 0
D25: Corporate income tax | E25: USD m | G25: =SUM(J25:BN25) -> 285.81855 | J25: =J23*J24 -> 0 | K25: =K23*K24 -> 0 | L25: =L23*L24 -> 0 | M25: =M23*M24 -> 0 | N25: =N23*N24 -> 0 | O25: =O23*O24 -> 0 | P25: =P23*P24 -> 0 | Q25: =Q23*Q24 -> 0 | ... BN25: =BN23*BN24 -> 0
D26: Minimum turnover tax | E26: USD m | G26: =SUM(J26:BN26) -> 15.639465 | J26: =IF(Time!J30>0,Inputs!$F$176/100*Operations!J55*(J8+J9)/Time!J30,0) -> 0 | K26: =IF(Time!K30>0,Inputs!$F$176/100*Operations!K55*(K8+K9)/Time!K30,0) -> 0 | L26: =IF(Time!L30>0,Inputs!$F$176/100*Operations!L55*(L8+L9)/Time!L30,0) -> 0 | M26: =IF(Time!M30>0,Inputs!$F$176/100*Operations!M55*(M8+M9)/Time!M30,0) -> 0 | N26: =IF(Time!N30>0,Inputs!$F$176/100*Operations!N55*(N8+N9)/Time!N30,0) -> 0 | O26: =IF(Time!O30>0,Inputs!$F$176/100*Operations!O55*(O8+O9)/Time!O30,0) -> 0 | P26: =IF(Time!P30>0,Inputs!$F$176/100*Operations!P55*(P8+P9)/Time!P30,0) -> 0 | Q26: =IF(Time!Q30>0,Inputs!$F$176/100*Operations!Q55*(Q8+Q9)/Time!Q30,0) -> 0 | ... BN26: =IF(Time!BN30>0,Inputs!$F$176/100*Operations!BN55*(BN8+BN9)/Time!BN30,0) -> 0
D27: Tax paid = max(CIT, MTT) | E27: USD m | G27: =SUM(J27:BN27) -> 291.44161 | J27: =MAX(J25,J26) -> 0 | K27: =MAX(K25,K26) -> 0 | L27: =MAX(L25,L26) -> 0 | M27: =MAX(M25,M26) -> 0 | N27: =MAX(N25,N26) -> 0 | O27: =MAX(O25,O26) -> 0 | P27: =MAX(P25,P26) -> 0 | Q27: =MAX(Q25,Q26) -> 0 | ... BN27: =MAX(BN25,BN26) -> 0
D28: Thin-cap disallowance | E28: USD m | G28: =SUM(J28:BN28) -> 4.2406069 | J28: =J13-J15 -> 0 | K28: =K13-K15 -> 0 | L28: =L13-L15 -> 0 | M28: =M13-M15 -> 0 | N28: =N13-N15 -> 0 | O28: =O13-O15 -> 1.1021139 | P28: =P13-P15 -> 2.1281112 | Q28: =Q13-Q15 -> 1.0103818 | ... BN28: =BN13-BN15 -> 0

Sheet Funding
A1: Case P: Belanou Combined Cycle Power Project, Republic of Kessara
A2: Funding: closed-form gross-up, drawdowns by tranche, IDC, fees, equity
A3: Units in column E; constants in column F; row totals in column G; first period in column J. Inputs: blue on yellow. Links from other sheets: green.
D4: Label | E4: Unit | F4: Constant | G4: Total
D5: Month | J5: 2018-08 | K5: 2018-09 | L5: 2018-10 | M5: 2018-11 | N5: 2018-12 | O5: 2019-01 | P5: 2019-02 | Q5: 2019-03 | R5: 2019-04 | S5: 2019-05 | T5: 2019-06 | U5: 2019-07 | V5: 2019-08 | W5: 2019-09 | X5: 2019-10 | Y5: 2019-11 | Z5: 2019-12 | AA5: 2020-01 | AB5: 2020-02 | AC5: 2020-03 | AD5: 2020-04 | AE5: 2020-05 | AF5: 2020-06 | AG5: 2020-07 | AH5: 2020-08 | AI5: 2020-09 | AJ5: 2020-10 | AK5: 2020-11 | AL5: 2020-12 | AM5: 2021-01 | AN5: 2021-02 | AO5: 2021-03 | AP5: 2021-04 | AQ5: 2021-05 | AR5: 2021-06 | AS5: 2021-07 | AT5: 2021-08 | AU5: 2021-09 | AV5: 2021-10 | AW5: 2021-11 | AX5: 2021-12 | AY5: 2022-01 | AZ5: 2022-02 | BA5: 2022-03 | BB5: 2022-04 | BC5: 2022-05 | BD5: 2022-06 | BE5: 2022-07 | BF5: 2022-08 | BG5: 2022-09 | BH5: 2022-10 | BI5: 2022-11 | BJ5: 2022-12
B7: Constants
D8: Contract debt share of funding g = D/(D+E) | E8: fraction | F8: =Inputs!$F$113/(Inputs!$F$113+Inputs!$F$114) -> 0.7371696
D9: Gearing used in the closed-form gross-up | E9: fraction | F9: =IF(Inputs!$F$51<>1,Funding!$F$8,Inputs!$F$105) -> 0.75
D10: ECA premium gross-up denominator 1 - prem x share x g | E10: factor | F10: =1-Inputs!$F$94/100*Inputs!$F$75*Funding!$F$9 -> 0.9755875
D11: First installment share of remaining profile (A, B, commercial, standby) | E11: fraction | F11: =INDEX(Debt!$J$17:$BN$17,1,Time!$F$13)/INDEX(Debt!$J$18:$BN$18,1,Time!$F$13) -> 0.018900957
D12: DSRA coefficient per USD of E balance | E12: factor | F12: =INDEX(Debt!$J$147:$BN$147,1,Time!$F$13)+(INDEX(Operations!$J$9:$BN$9,1,Time!$F$13)+Inputs!$F$79)/100*INDEX(Time!$J$25:$BN$25,1,Time!$F$13)/Inputs!$F$247*1 -> 0.061154872
D13: DSRA coefficient per USD of A balance | E13: factor | F13: =$F$11+(INDEX(Operations!$J$9:$BN$9,1,Time!$F$13)+Inputs!$F$80)/100*INDEX(Time!$J$25:$BN$25,1,Time!$F$13)/Inputs!$F$247*1 -> 0.053349846
D14: DSRA coefficient per USD of B balance | E14: factor | F14: =$F$11+(INDEX(Operations!$J$9:$BN$9,1,Time!$F$13)+Inputs!$F$81)/100*INDEX(Time!$J$25:$BN$25,1,Time!$F$13)/Inputs!$F$247*1 -> 0.052072068
D15: DSRA coefficient per USD of C balance | E15: factor | F15: =$F$11+(INDEX(Operations!$J$9:$BN$9,1,Time!$F$13)+INDEX(Debt!$J$8:$BN$8,1,Time!$F$13))/100*INDEX(Time!$J$25:$BN$25,1,Time!$F$13)/Inputs!$F$247*(1/(1-Inputs!$F$93/100))+(Inputs!$F$95/100*Inputs!$F$96/100)*INDEX(Time!$J$25:$BN$25,1,Time!$F$13)/Inputs!$F$248 -> 0.06495059
D16: DSRA coefficient per USD of standby balance | E16: factor | F16: =$F$11+INDEX(Debt!$J$14:$BN$14,1,Time!$F$13) -> 0.058542735
D17: DSRA constant (swap net payment) | E17: USD m | F17: =INDEX(Inputs!$J$301:$BN$301,1,Time!$F$13)*(Inputs!$F$97/100*INDEX(Time!$J$24:$BN$24,1,Time!$F$13)-INDEX(Operations!$J$9:$BN$9,1,Time!$F$13)/100*INDEX(Time!$J$25:$BN$25,1,Time!$F$13)/Inputs!$F$247) -> -0.53335739
B18: Closed-form gross-up: debt balance = alpha + beta x T (FC-type cases)
D19: Blended loan rate per month (rho) | E19: factor | J19: =Inputs!$F$75*(Construction!J17+Inputs!$F$79)/100*Construction!J11/Inputs!$F$247*1+Inputs!$F$76*(Construction!J17+Inputs!$F$80)/100*Construction!J11/Inputs!$F$247*1+Inputs!$F$77*(Construction!J17+Inputs!$F$81)/100*Construction!J11/Inputs!$F$247*1+Inputs!$F$78*(Construction!J17+Inputs!$F$82)/100*Construction!J11/Inputs!$F$247*(1/(1-Inputs!$F$93/100))+Inputs!$F$78*(Inputs!$F$95/100*Inputs!$F$96/100)*Construction!J11/Inputs!$F$248 -> 0.0054193369 | K19: =Inputs!$F$75*(Construction!K17+Inputs!$F$79)/100*Construction!K11/Inputs!$F$247*1+Inputs!$F$76*(Construction!K17+Inputs!$F$80)/100*Construction!K11/Inputs!$F$247*1+Inputs!$F$77*(Construction!K17+Inputs!$F$81)/100*Construction!K11/Inputs!$F$247*1+Inputs!$F$78*(Construction!K17+Inputs!$F$82)/100*Construction!K11/Inputs!$F$247*(1/(1-Inputs!$F$93/100))+Inputs!$F$78*(Inputs!$F$95/100*Inputs!$F$96/100)*Construction!K11/Inputs!$F$248 -> 0.0052445195 | L19: =Inputs!$F$75*(Construction!L17+Inputs!$F$79)/100*Construction!L11/Inputs!$F$247*1+Inputs!$F$76*(Construction!L17+Inputs!$F$80)/100*Construction!L11/Inputs!$F$247*1+Inputs!$F$77*(Construction!L17+Inputs!$F$81)/100*Construction!L11/Inputs!$F$247*1+Inputs!$F$78*(Construction!L17+Inputs!$F$82)/100*Construction!L11/Inputs!$F$247*(1/(1-Inputs!$F$93/100))+Inputs!$F$78*(Inputs!$F$95/100*Inputs!$F$96/100)*Construction!L11/Inputs!$F$248 -> 0.0054193369 | M19: =Inputs!$F$75*(Construction!M17+Inputs!$F$79)/100*Construction!M11/Inputs!$F$247*1+Inputs!$F$76*(Construction!M17+Inputs!$F$80)/100*Construction!M11/Inputs!$F$247*1+Inputs!$F$77*(Construction!M17+Inputs!$F$81)/100*Construction!M11/Inputs!$F$247*1+Inputs!$F$78*(Construction!M17+Inputs!$F$82)/100*Construction!M11/Inputs!$F$247*(1/(1-Inputs!$F$93/100))+Inputs!$F$78*(Inputs!$F$95/100*Inputs!$F$96/100)*Construction!M11/Inputs!$F$248 -> 0.0052445195 | N19: =Inputs!$F$75*(Construction!N17+Inputs!$F$79)/100*Construction!N11/Inputs!$F$247*1+Inputs!$F$76*(Construction!N17+Inputs!$F$80)/100*Construction!N11/Inputs!$F$247*1+Inputs!$F$77*(Construction!N17+Inputs!$F$81)/100*Construction!N11/Inputs!$F$247*1+Inputs!$F$78*(Construction!N17+Inputs!$F$82)/100*Construction!N11/Inputs!$F$247*(1/(1-Inputs!$F$93/100))+Inputs!$F$78*(Inputs!$F$95/100*Inputs!$F$96/100)*Construction!N11/Inputs!$F$248 -> 0.0054193369 | O19: =Inputs!$F$75*(Construction!O17+Inputs!$F$79)/100*Construction!O11/Inputs!$F$247*1+Inputs!$F$76*(Construction!O17+Inputs!$F$80)/100*Construction!O11/Inputs!$F$247*1+Inputs!$F$77*(Construction!O17+Inputs!$F$81)/100*Construction!O11/Inputs!$F$247*1+Inputs!$F$78*(Construction!O17+Inputs!$F$82)/100*Construction!O11/Inputs!$F$247*(1/(1-Inputs!$F$93/100))+Inputs!$F$78*(Inputs!$F$95/100*Inputs!$F$96/100)*Construction!O11/Inputs!$F$248 -> 0.0056616535 | P19: =Inputs!$F$75*(Construction!P17+Inputs!$F$79)/100*Construction!P11/Inputs!$F$247*1+Inputs!$F$76*(Construction!P17+Inputs!$F$80)/100*Construction!P11/Inputs!$F$247*1+Inputs!$F$77*(Construction!P17+Inputs!$F$81)/100*Construction!P11/Inputs!$F$247*1+Inputs!$F$78*(Construction!P17+Inputs!$F$82)/100*Construction!P11/Inputs!$F$247*(1/(1-Inputs!$F$93/100))+Inputs!$F$78*(Inputs!$F$95/100*Inputs!$F$96/100)*Construction!P11/Inputs!$F$248 -> 0.0051137516 | Q19: =Inputs!$F$75*(Construction!Q17+Inputs!$F$79)/100*Construction!Q11/Inputs!$F$247*1+Inputs!$F$76*(Construction!Q17+Inputs!$F$80)/100*Construction!Q11/Inputs!$F$247*1+Inputs!$F$77*(Construction!Q17+Inputs!$F$81)/100*Construction!Q11/Inputs!$F$247*1+Inputs!$F$78*(Construction!Q17+Inputs!$F$82)/100*Construction!Q11/Inputs!$F$247*(1/(1-Inputs!$F$93/100))+Inputs!$F$78*(Inputs!$F$95/100*Inputs!$F$96/100)*Construction!Q11/Inputs!$F$248 -> 0.0056616535 | ... BJ19: =Inputs!$F$75*(Construction!BJ17+Inputs!$F$79)/100*Construction!BJ11/Inputs!$F$247*1+Inputs!$F$76*(Construction!BJ17+Inputs!$F$80)/100*Construction!BJ11/Inputs!$F$247*1+Inputs!$F$77*(Construction!BJ17+Inputs!$F$81)/100*Construction!BJ11/Inputs!$F$247*1+Inputs!$F$78*(Construction!BJ17+Inputs!$F$82)/100*Construction!BJ11/Inputs!$F$247*(1/(1-Inputs!$F$93/100))+Inputs!$F$78*(Inputs!$F$95/100*Inputs!$F$96/100)*Construction!BJ11/Inputs!$F$248 -> 0.0059488436
D20: Blended commitment fee per month (kappa) | E20: factor | J20: =Inputs!$F$75*Inputs!$F$85/100*Construction!J11/Inputs!$F$247+Inputs!$F$76*Inputs!$F$86/100*Construction!J11/Inputs!$F$247+Inputs!$F$77*Inputs!$F$87/100*Construction!J11/Inputs!$F$247+Inputs!$F$78*(Inputs!$F$88/100*Inputs!$F$82)/100*Construction!J11/Inputs!$F$247 -> 0.00086817222 | K20: =Inputs!$F$75*Inputs!$F$85/100*Construction!K11/Inputs!$F$247+Inputs!$F$76*Inputs!$F$86/100*Construction!K11/Inputs!$F$247+Inputs!$F$77*Inputs!$F$87/100*Construction!K11/Inputs!$F$247+Inputs!$F$78*(Inputs!$F$88/100*Inputs!$F$82)/100*Construction!K11/Inputs!$F$247 -> 0.00084016667 | L20: =Inputs!$F$75*Inputs!$F$85/100*Construction!L11/Inputs!$F$247+Inputs!$F$76*Inputs!$F$86/100*Construction!L11/Inputs!$F$247+Inputs!$F$77*Inputs!$F$87/100*Construction!L11/Inputs!$F$247+Inputs!$F$78*(Inputs!$F$88/100*Inputs!$F$82)/100*Construction!L11/Inputs!$F$247 -> 0.00086817222 | M20: =Inputs!$F$75*Inputs!$F$85/100*Construction!M11/Inputs!$F$247+Inputs!$F$76*Inputs!$F$86/100*Construction!M11/Inputs!$F$247+Inputs!$F$77*Inputs!$F$87/100*Construction!M11/Inputs!$F$247+Inputs!$F$78*(Inputs!$F$88/100*Inputs!$F$82)/100*Construction!M11/Inputs!$F$247 -> 0.00084016667 | N20: =Inputs!$F$75*Inputs!$F$85/100*Construction!N11/Inputs!$F$247+Inputs!$F$76*Inputs!$F$86/100*Construction!N11/Inputs!$F$247+Inputs!$F$77*Inputs!$F$87/100*Construction!N11/Inputs!$F$247+Inputs!$F$78*(Inputs!$F$88/100*Inputs!$F$82)/100*Construction!N11/Inputs!$F$247 -> 0.00086817222 | O20: =Inputs!$F$75*Inputs!$F$85/100*Construction!O11/Inputs!$F$247+Inputs!$F$76*Inputs!$F$86/100*Construction!O11/Inputs!$F$247+Inputs!$F$77*Inputs!$F$87/100*Construction!O11/Inputs!$F$247+Inputs!$F$78*(Inputs!$F$88/100*Inputs!$F$82)/100*Construction!O11/Inputs!$F$247 -> 0.00086817222 | P20: =Inputs!$F$75*Inputs!$F$85/100*Construction!P11/Inputs!$F$247+Inputs!$F$76*Inputs!$F$86/100*Construction!P11/Inputs!$F$247+Inputs!$F$77*Inputs!$F$87/100*Construction!P11/Inputs!$F$247+Inputs!$F$78*(Inputs!$F$88/100*Inputs!$F$82)/100*Construction!P11/Inputs!$F$247 -> 0.00078415556 | Q20: =Inputs!$F$75*Inputs!$F$85/100*Construction!Q11/Inputs!$F$247+Inputs!$F$76*Inputs!$F$86/100*Construction!Q11/Inputs!$F$247+Inputs!$F$77*Inputs!$F$87/100*Construction!Q11/Inputs!$F$247+Inputs!$F$78*(Inputs!$F$88/100*Inputs!$F$82)/100*Construction!Q11/Inputs!$F$247 -> 0.00086817222 | ... BJ20: =Inputs!$F$75*Inputs!$F$85/100*Construction!BJ11/Inputs!$F$247+Inputs!$F$76*Inputs!$F$86/100*Construction!BJ11/Inputs!$F$247+Inputs!$F$77*Inputs!$F$87/100*Construction!BJ11/Inputs!$F$247+Inputs!$F$78*(Inputs!$F$88/100*Inputs!$F$82)/100*Construction!BJ11/Inputs!$F$247 -> 0.00086817222
D21: Costs independent of facility size | E21: USD m | J21: =J79+Construction!J14*(Construction!J32+Construction!J38+Inputs!$F$107/12+Inputs!J309*(Inputs!$F$97/100/12-Construction!J17/100*Construction!J11/Inputs!$F$247)+Inputs!$F$99*Inputs!$F$100/100*Construction!J11/Inputs!$F$247+Construction!J15*$F$17) -> 108.15662 | K21: =K79+Construction!K14*(Construction!K32+Construction!K38+Inputs!$F$107/12+Inputs!K309*(Inputs!$F$97/100/12-Construction!K17/100*Construction!K11/Inputs!$F$247)+Inputs!$F$99*Inputs!$F$100/100*Construction!K11/Inputs!$F$247+Construction!K15*$F$17) -> 1.5100263 | L21: =L79+Construction!L14*(Construction!L32+Construction!L38+Inputs!$F$107/12+Inputs!L309*(Inputs!$F$97/100/12-Construction!L17/100*Construction!L11/Inputs!$F$247)+Inputs!$F$99*Inputs!$F$100/100*Construction!L11/Inputs!$F$247+Construction!L15*$F$17) -> 2.1406271 | M21: =M79+Construction!M14*(Construction!M32+Construction!M38+Inputs!$F$107/12+Inputs!M309*(Inputs!$F$97/100/12-Construction!M17/100*Construction!M11/Inputs!$F$247)+Inputs!$F$99*Inputs!$F$100/100*Construction!M11/Inputs!$F$247+Construction!M15*$F$17) -> 3.4474578 | N21: =N79+Construction!N14*(Construction!N32+Construction!N38+Inputs!$F$107/12+Inputs!N309*(Inputs!$F$97/100/12-Construction!N17/100*Construction!N11/Inputs!$F$247)+Inputs!$F$99*Inputs!$F$100/100*Construction!N11/Inputs!$F$247+Construction!N15*$F$17) -> 5.3341079 | O21: =O79+Construction!O14*(Construction!O32+Construction!O38+Inputs!$F$107/12+Inputs!O309*(Inputs!$F$97/100/12-Construction!O17/100*Construction!O11/Inputs!$F$247)+Inputs!$F$99*Inputs!$F$100/100*Construction!O11/Inputs!$F$247+Construction!O15*$F$17) -> 7.6796436 | P21: =P79+Construction!P14*(Construction!P32+Construction!P38+Inputs!$F$107/12+Inputs!P309*(Inputs!$F$97/100/12-Construction!P17/100*Construction!P11/Inputs!$F$247)+Inputs!$F$99*Inputs!$F$100/100*Construction!P11/Inputs!$F$247+Construction!P15*$F$17) -> 10.407155 | Q21: =Q79+Construction!Q14*(Construction!Q32+Construction!Q38+Inputs!$F$107/12+Inputs!Q309*(Inputs!$F$97/100/12-Construction!Q17/100*Construction!Q11/Inputs!$F$247)+Inputs!$F$99*Inputs!$F$100/100*Construction!Q11/Inputs!$F$247+Construction!Q15*$F$17) -> 13.325841 | ... BJ21: =BJ79+Construction!BJ14*(Construction!BJ32+Construction!BJ38+Inputs!$F$107/12+Inputs!BJ309*(Inputs!$F$97/100/12-Construction!BJ17/100*Construction!BJ11/Inputs!$F$247)+Inputs!$F$99*Inputs!$F$100/100*Construction!BJ11/Inputs!$F$247+Construction!BJ15*$F$17) -> 0
D22: Balance, constant part (alpha) | E22: USD m | J22: =I22+Construction!J14*$F$9/$F$10*(J21+(J19-J20)*I22) -> 83.147296 | K22: =J22+Construction!K14*$F$9/$F$10*(K21+(K19-K20)*J22) -> 84.589685 | L22: =K22+Construction!L14*$F$9/$F$10*(L21+(L19-L20)*K22) -> 86.531291 | M22: =L22+Construction!M14*$F$9/$F$10*(M21+(M19-M20)*L22) -> 89.474573 | N22: =M22+Construction!N14*$F$9/$F$10*(N21+(N19-N20)*M22) -> 93.888315 | O22: =N22+Construction!O14*$F$9/$F$10*(O21+(O19-O20)*N22) -> 100.13816 | P22: =O22+Construction!P14*$F$9/$F$10*(P21+(P19-P20)*O22) -> 108.47215 | Q22: =P22+Construction!Q14*$F$9/$F$10*(Q21+(Q19-Q20)*P22) -> 119.11635 | ... BJ22: =BI22+Construction!BJ14*$F$9/$F$10*(BJ21+(BJ19-BJ20)*BI22) -> 588.77675
D23: Balance per USD of total funding (beta) | E23: factor | J23: =I23+Construction!J14*$F$9/$F$10*(J19*I23+J20*($F$9-I23)+IF(Construction!J8=1,$F$9*(Inputs!$F$75*Inputs!$F$89/100+Inputs!$F$76*Inputs!$F$90/100+Inputs!$F$77*Inputs!$F$91/100+Inputs!$F$78*Inputs!$F$92/100),0)+Construction!J15*$F$9*(Inputs!$F$75*$F$12+Inputs!$F$76*$F$13+Inputs!$F$77*$F$14+Inputs!$F$78*$F$15)) -> 0.0095643362 | K23: =J23+Construction!K14*$F$9/$F$10*(K19*J23+K20*($F$9-J23)+IF(Construction!K8=1,$F$9*(Inputs!$F$75*Inputs!$F$89/100+Inputs!$F$76*Inputs!$F$90/100+Inputs!$F$77*Inputs!$F$91/100+Inputs!$F$78*Inputs!$F$92/100),0)+Construction!K15*$F$9*(Inputs!$F$75*$F$12+Inputs!$F$76*$F$13+Inputs!$F$77*$F$14+Inputs!$F$78*$F$15)) -> 0.01008114 | L23: =K23+Construction!L14*$F$9/$F$10*(L19*K23+L20*($F$9-K23)+IF(Construction!L8=1,$F$9*(Inputs!$F$75*Inputs!$F$89/100+Inputs!$F$76*Inputs!$F$90/100+Inputs!$F$77*Inputs!$F$91/100+Inputs!$F$78*Inputs!$F$92/100),0)+Construction!L15*$F$9*(Inputs!$F$75*$F$12+Inputs!$F$76*$F$13+Inputs!$F$77*$F$14+Inputs!$F$78*$F$15)) -> 0.010616979 | M23: =L23+Construction!M14*$F$9/$F$10*(M19*L23+M20*($F$9-L23)+IF(Construction!M8=1,$F$9*(Inputs!$F$75*Inputs!$F$89/100+Inputs!$F$76*Inputs!$F$90/100+Inputs!$F$77*Inputs!$F$91/100+Inputs!$F$78*Inputs!$F$92/100),0)+Construction!M15*$F$9*(Inputs!$F$75*$F$12+Inputs!$F$76*$F$13+Inputs!$F$77*$F$14+Inputs!$F$78*$F$15)) -> 0.011137347 | N23: =M23+Construction!N14*$F$9/$F$10*(N19*M23+N20*($F$9-M23)+IF(Construction!N8=1,$F$9*(Inputs!$F$75*Inputs!$F$89/100+Inputs!$F$76*Inputs!$F$90/100+Inputs!$F$77*Inputs!$F$91/100+Inputs!$F$78*Inputs!$F$92/100),0)+Construction!N15*$F$9*(Inputs!$F$75*$F$12+Inputs!$F$76*$F$13+Inputs!$F$77*$F$14+Inputs!$F$78*$F$15)) -> 0.011676881 | O23: =N23+Construction!O14*$F$9/$F$10*(O19*N23+O20*($F$9-N23)+IF(Construction!O8=1,$F$9*(Inputs!$F$75*Inputs!$F$89/100+Inputs!$F$76*Inputs!$F$90/100+Inputs!$F$77*Inputs!$F$91/100+Inputs!$F$78*Inputs!$F$92/100),0)+Construction!O15*$F$9*(Inputs!$F$75*$F$12+Inputs!$F$76*$F$13+Inputs!$F$77*$F$14+Inputs!$F$78*$F$15)) -> 0.012220478 | P23: =O23+Construction!P14*$F$9/$F$10*(P19*O23+P20*($F$9-O23)+IF(Construction!P8=1,$F$9*(Inputs!$F$75*Inputs!$F$89/100+Inputs!$F$76*Inputs!$F$90/100+Inputs!$F$77*Inputs!$F$91/100+Inputs!$F$78*Inputs!$F$92/100),0)+Construction!P15*$F$9*(Inputs!$F$75*$F$12+Inputs!$F$76*$F$13+Inputs!$F$77*$F$14+Inputs!$F$78*$F$15)) -> 0.012713278 | Q23: =P23+Construction!Q14*$F$9/$F$10*(Q19*P23+Q20*($F$9-P23)+IF(Construction!Q8=1,$F$9*(Inputs!$F$75*Inputs!$F$89/100+Inputs!$F$76*Inputs!$F$90/100+Inputs!$F$77*Inputs!$F$91/100+Inputs!$F$78*Inputs!$F$92/100),0)+Construction!Q15*$F$9*(Inputs!$F$75*$F$12+Inputs!$F$76*$F$13+Inputs!$F$77*$F$14+Inputs!$F$78*$F$15)) -> 0.013260695 | ... BJ23: =BI23+Construction!BJ14*$F$9/$F$10*(BJ19*BI23+BJ20*($F$9-BI23)+IF(Construction!BJ8=1,$F$9*(Inputs!$F$75*Inputs!$F$89/100+Inputs!$F$76*Inputs!$F$90/100+Inputs!$F$77*Inputs!$F$91/100+Inputs!$F$78*Inputs!$F$92/100),0)+Construction!BJ15*$F$9*(Inputs!$F$75*$F$12+Inputs!$F$76*$F$13+Inputs!$F$77*$F$14+Inputs!$F$78*$F$15)) -> 0.063333297
D24: Total funding requirement at this gearing, closed form T = alpha/(g - beta) | E24: USD m | F24: =INDEX(Funding!$J$22:$BJ$22,1,Time!$F$14)/(Funding!$F$9-INDEX(Funding!$J$23:$BJ$23,1,Time!$F$14)) -> 857.44182
D25: Senior debt (committed tranches) | E25: USD m | F25: =IF(Inputs!$F$51<>1,Funding!$F$8*Funding!$F$24,Inputs!$F$113) -> 629.94967
D26: Debt share of monthly funding | E26: fraction | F26: =$F$8 -> 0.7371696
B27: Monthly funding schedule (USD m)
D28: ECA-covered tranche: opening balance | E28: USD m | J28: =I61 -> 0 | K28: =J61 -> 26.87475 | L28: =K61 -> 27.426229 | M28: =L61 -> 28.129468 | N28: =M61 -> 29.124119 | O28: =N61 -> 30.556798 | P28: =O61 -> 32.531464 | Q28: =P61 -> 35.10791 | ... BJ28: =BI61 -> 188.9849
D29: ABDB A-loan: opening balance | E29: USD m | J29: =I62 -> 0 | K29: =J62 -> 19.70815 | L29: =K62 -> 20.112568 | M29: =L62 -> 20.628276 | N29: =M62 -> 21.357687 | O29: =N62 -> 22.408319 | P29: =O62 -> 23.856407 | Q29: =P62 -> 25.745801 | ... BJ29: =BI62 -> 138.58893
D30: ABDB B-loan: opening balance | E30: USD m | J30: =I63 -> 0 | K30: =J63 -> 8.9582501 | L30: =K63 -> 9.1420764 | M30: =L63 -> 9.3764893 | N30: =M63 -> 9.7080397 | O30: =N63 -> 10.185599 | P30: =O63 -> 10.843821 | Q30: =P63 -> 11.702637 | ... BJ30: =BI63 -> 62.994967
D31: Commercial tranche: opening balance | E31: USD m | J31: =I64 -> 0 | K31: =J64 -> 34.04135 | L31: =K64 -> 34.73989 | M31: =L64 -> 35.630659 | N31: =M64 -> 36.890551 | O31: =N64 -> 38.705278 | P31: =O64 -> 41.206521 | Q31: =P64 -> 44.470019 | ... BJ31: =BI64 -> 239.38088
D32: Standby facility: opening balance | E32: USD m | J32: =I65 -> 0 | K32: =J65 -> 0 | L32: =K65 -> 0 | M32: =L65 -> 0 | N32: =M65 -> 0 | O32: =N65 -> 0 | P32: =O65 -> 0 | Q32: =P65 -> 0 | ... BJ32: =BI65 -> 1.6334933e-11
D33: ECA-covered tranche: interest | E33: USD m | G33: =SUM(J33:BJ33) -> 12.369812 | J33: =Construction!J14*J28*(Construction!J17+Inputs!$F$79)/100*Construction!J11/Inputs!$F$247*1 -> 0 | K33: =Construction!K14*K28*(Construction!K17+Inputs!$F$79)/100*Construction!K11/Inputs!$F$247*1 -> 0.08667107 | L33: =Construction!L14*L28*(Construction!L17+Inputs!$F$79)/100*Construction!L11/Inputs!$F$247*1 -> 0.091397909 | M33: =Construction!M14*M28*(Construction!M17+Inputs!$F$79)/100*Construction!M11/Inputs!$F$247*1 -> 0.090717534 | N33: =Construction!N14*N28*(Construction!N17+Inputs!$F$79)/100*Construction!N11/Inputs!$F$247*1 -> 0.097056127 | O33: =Construction!O14*O28*(Construction!O17+Inputs!$F$79)/100*Construction!O11/Inputs!$F$247*1 -> 0.10893499 | P33: =Construction!P14*P28*(Construction!P17+Inputs!$F$79)/100*Construction!P11/Inputs!$F$247*1 -> 0.10475131 | Q33: =Construction!Q14*Q28*(Construction!Q17+Inputs!$F$79)/100*Construction!Q11/Inputs!$F$247*1 -> 0.1251597 | ... BJ33: =Construction!BJ14*BJ28*(Construction!BJ17+Inputs!$F$79)/100*Construction!BJ11/Inputs!$F$247*1 -> 0
D34: ABDB A-loan: interest | E34: USD m | G34: =SUM(J34:BJ34) -> 13.856356 | J34: =Construction!J14*J29*(Construction!J17+Inputs!$F$80)/100*Construction!J11/Inputs!$F$247*1 -> 0 | K34: =Construction!K14*K29*(Construction!K17+Inputs!$F$80)/100*Construction!K11/Inputs!$F$247*1 -> 0.10133274 | L34: =Construction!L14*L29*(Construction!L17+Inputs!$F$80)/100*Construction!L11/Inputs!$F$247*1 -> 0.10685919 | M34: =Construction!M14*M29*(Construction!M17+Inputs!$F$80)/100*Construction!M11/Inputs!$F$247*1 -> 0.10606372 | N34: =Construction!N14*N29*(Construction!N17+Inputs!$F$80)/100*Construction!N11/Inputs!$F$247*1 -> 0.11347458 | O34: =Construction!O14*O29*(Construction!O17+Inputs!$F$80)/100*Construction!O11/Inputs!$F$247*1 -> 0.12426658 | P34: =Construction!P14*P29*(Construction!P17+Inputs!$F$80)/100*Construction!P11/Inputs!$F$247*1 -> 0.11949409 | Q34: =Construction!Q14*Q29*(Construction!Q17+Inputs!$F$80)/100*Construction!Q11/Inputs!$F$247*1 -> 0.14277477 | ... BJ34: =Construction!BJ14*BJ29*(Construction!BJ17+Inputs!$F$80)/100*Construction!BJ11/Inputs!$F$247*1 -> 0
D35: ABDB B-loan: interest | E35: USD m | G35: =SUM(J35:BJ35) -> 6.0619227 | J35: =Construction!J14*J30*(Construction!J17+Inputs!$F$81)/100*Construction!J11/Inputs!$F$247*1 -> 0 | K35: =Construction!K14*K30*(Construction!K17+Inputs!$F$81)/100*Construction!K11/Inputs!$F$247*1 -> 0.044194034 | L35: =Construction!L14*L30*(Construction!L17+Inputs!$F$81)/100*Construction!L11/Inputs!$F$247*1 -> 0.046604274 | M35: =Construction!M14*M30*(Construction!M17+Inputs!$F$81)/100*Construction!M11/Inputs!$F$247*1 -> 0.046257347 | N35: =Construction!N14*N30*(Construction!N17+Inputs!$F$81)/100*Construction!N11/Inputs!$F$247*1 -> 0.049489429 | O35: =Construction!O14*O30*(Construction!O17+Inputs!$F$81)/100*Construction!O11/Inputs!$F$247*1 -> 0.054292074 | P35: =Construction!P14*P30*(Construction!P17+Inputs!$F$81)/100*Construction!P11/Inputs!$F$247*1 -> 0.052206976 | Q35: =Construction!Q14*Q30*(Construction!Q17+Inputs!$F$81)/100*Construction!Q11/Inputs!$F$247*1 -> 0.062378304 | ... BJ35: =Construction!BJ14*BJ30*(Construction!BJ17+Inputs!$F$81)/100*Construction!BJ11/Inputs!$F$247*1 -> 0
D36: Commercial tranche: interest | E36: USD m | G36: =SUM(J36:BJ36) -> 28.389806 | J36: =Construction!J14*J31*(Construction!J17+Inputs!$F$82)/100*Construction!J11/Inputs!$F$247*(1/(1-Inputs!$F$93/100)) -> 0 | K36: =Construction!K14*K31*(Construction!K17+Inputs!$F$82)/100*Construction!K11/Inputs!$F$247*(1/(1-Inputs!$F$93/100)) -> 0.20866087 | L36: =Construction!L14*L31*(Construction!L17+Inputs!$F$82)/100*Construction!L11/Inputs!$F$247*(1/(1-Inputs!$F$93/100)) -> 0.22004075 | M36: =Construction!M14*M31*(Construction!M17+Inputs!$F$82)/100*Construction!M11/Inputs!$F$247*(1/(1-Inputs!$F$93/100)) -> 0.21840275 | N36: =Construction!N14*N31*(Construction!N17+Inputs!$F$82)/100*Construction!N11/Inputs!$F$247*(1/(1-Inputs!$F$93/100)) -> 0.23366293 | O36: =Construction!O14*O31*(Construction!O17+Inputs!$F$82)/100*Construction!O11/Inputs!$F$247*(1/(1-Inputs!$F$93/100)) -> 0.25515618 | P36: =Construction!P14*P31*(Construction!P17+Inputs!$F$82)/100*Construction!P11/Inputs!$F$247*(1/(1-Inputs!$F$93/100)) -> 0.24535685 | Q36: =Construction!Q14*Q31*(Construction!Q17+Inputs!$F$82)/100*Construction!Q11/Inputs!$F$247*(1/(1-Inputs!$F$93/100)) -> 0.29315899 | ... BJ36: =Construction!BJ14*BJ31*(Construction!BJ17+Inputs!$F$82)/100*Construction!BJ11/Inputs!$F$247*(1/(1-Inputs!$F$93/100)) -> 0
D37: Standby facility: interest | E37: USD m | G37: =SUM(J37:BJ37) -> 0 | J37: =Construction!J14*J32*(Inputs!$F$102*(Construction!J17+Inputs!$F$82+Inputs!$F$101)/(1-Inputs!$F$93/100)+(1-Inputs!$F$102)*(Construction!J17+Inputs!$F$80+Inputs!$F$101))/100*Construction!J11/Inputs!$F$247 -> 0 | K37: =Construction!K14*K32*(Inputs!$F$102*(Construction!K17+Inputs!$F$82+Inputs!$F$101)/(1-Inputs!$F$93/100)+(1-Inputs!$F$102)*(Construction!K17+Inputs!$F$80+Inputs!$F$101))/100*Construction!K11/Inputs!$F$247 -> 0 | L37: =Construction!L14*L32*(Inputs!$F$102*(Construction!L17+Inputs!$F$82+Inputs!$F$101)/(1-Inputs!$F$93/100)+(1-Inputs!$F$102)*(Construction!L17+Inputs!$F$80+Inputs!$F$101))/100*Construction!L11/Inputs!$F$247 -> 0 | M37: =Construction!M14*M32*(Inputs!$F$102*(Construction!M17+Inputs!$F$82+Inputs!$F$101)/(1-Inputs!$F$93/100)+(1-Inputs!$F$102)*(Construction!M17+Inputs!$F$80+Inputs!$F$101))/100*Construction!M11/Inputs!$F$247 -> 0 | N37: =Construction!N14*N32*(Inputs!$F$102*(Construction!N17+Inputs!$F$82+Inputs!$F$101)/(1-Inputs!$F$93/100)+(1-Inputs!$F$102)*(Construction!N17+Inputs!$F$80+Inputs!$F$101))/100*Construction!N11/Inputs!$F$247 -> 0 | O37: =Construction!O14*O32*(Inputs!$F$102*(Construction!O17+Inputs!$F$82+Inputs!$F$101)/(1-Inputs!$F$93/100)+(1-Inputs!$F$102)*(Construction!O17+Inputs!$F$80+Inputs!$F$101))/100*Construction!O11/Inputs!$F$247 -> 0 | P37: =Construction!P14*P32*(Inputs!$F$102*(Construction!P17+Inputs!$F$82+Inputs!$F$101)/(1-Inputs!$F$93/100)+(1-Inputs!$F$102)*(Construction!P17+Inputs!$F$80+Inputs!$F$101))/100*Construction!P11/Inputs!$F$247 -> 0 | Q37: =Construction!Q14*Q32*(Inputs!$F$102*(Construction!Q17+Inputs!$F$82+Inputs!$F$101)/(1-Inputs!$F$93/100)+(1-Inputs!$F$102)*(Construction!Q17+Inputs!$F$80+Inputs!$F$101))/100*Construction!Q11/Inputs!$F$247 -> 0 | ... BJ37: =Construction!BJ14*BJ32*(Inputs!$F$102*(Construction!BJ17+Inputs!$F$82+Inputs!$F$101)/(1-Inputs!$F$93/100)+(1-Inputs!$F$102)*(Construction!BJ17+Inputs!$F$80+Inputs!$F$101))/100*Construction!BJ11/Inputs!$F$247 -> 0
D38: PRI premium on commercial tranche | E38: USD m | G38: =SUM(J38:BJ38) -> 3.6684243 | J38: =Construction!J14*(Inputs!$F$95/100*Inputs!$F$96/100)*J31*Construction!J11/Inputs!$F$248 -> 0 | K38: =Construction!K14*(Inputs!$F$95/100*Inputs!$F$96/100)*K31*Construction!K11/Inputs!$F$248 -> 0.028958464 | L38: =Construction!L14*(Inputs!$F$95/100*Inputs!$F$96/100)*L31*Construction!L11/Inputs!$F$248 -> 0.030537791 | M38: =Construction!M14*(Inputs!$F$95/100*Inputs!$F$96/100)*M31*Construction!M11/Inputs!$F$248 -> 0.030310465 | N38: =Construction!N14*(Inputs!$F$95/100*Inputs!$F$96/100)*N31*Construction!N11/Inputs!$F$248 -> 0.03242831 | O38: =Construction!O14*(Inputs!$F$95/100*Inputs!$F$96/100)*O31*Construction!O11/Inputs!$F$248 -> 0.03402353 | P38: =Construction!P14*(Inputs!$F$95/100*Inputs!$F$96/100)*P31*Construction!P11/Inputs!$F$248 -> 0.032716849 | Q38: =Construction!Q14*(Inputs!$F$95/100*Inputs!$F$96/100)*Q31*Construction!Q11/Inputs!$F$248 -> 0.039090974 | ... BJ38: =Construction!BJ14*(Inputs!$F$95/100*Inputs!$F$96/100)*BJ31*Construction!BJ11/Inputs!$F$248 -> 0
D39: Swap net payment | E39: USD m | G39: =SUM(J39:BJ39) -> -0.77615528 | J39: =Construction!J14*Inputs!J309*(Inputs!$F$97/100/12-Construction!J17/100*Construction!J11/Inputs!$F$247) -> 0 | K39: =Construction!K14*Inputs!K309*(Inputs!$F$97/100/12-Construction!K17/100*Construction!K11/Inputs!$F$247) -> 0.025501152 | L39: =Construction!L14*Inputs!L309*(Inputs!$F$97/100/12-Construction!L17/100*Construction!L11/Inputs!$F$247) -> 0.020904881 | M39: =Construction!M14*Inputs!M309*(Inputs!$F$97/100/12-Construction!M17/100*Construction!M11/Inputs!$F$247) -> 0.02669174 | N39: =Construction!N14*Inputs!N309*(Inputs!$F$97/100/12-Construction!N17/100*Construction!N11/Inputs!$F$247) -> 0.022199051 | O39: =Construction!O14*Inputs!O309*(Inputs!$F$97/100/12-Construction!O17/100*Construction!O11/Inputs!$F$247) -> 0.0043458557 | P39: =Construction!P14*Inputs!P309*(Inputs!$F$97/100/12-Construction!P17/100*Construction!P11/Inputs!$F$247) -> 0.024796205 | Q39: =Construction!Q14*Inputs!Q309*(Inputs!$F$97/100/12-Construction!Q17/100*Construction!Q11/Inputs!$F$247) -> 0.004993125 | ... BJ39: =Construction!BJ14*Inputs!BJ309*(Inputs!$F$97/100/12-Construction!BJ17/100*Construction!BJ11/Inputs!$F$247) -> 0
D40: Commitment fees, senior tranches | E40: USD m | G40: =SUM(J40:BJ40) -> 9.2544418 | J40: =Construction!J14*((Inputs!$F$75*$F$25-J28)*Inputs!$F$85/100+(Inputs!$F$76*$F$25-J29)*Inputs!$F$86/100+(Inputs!$F$77*$F$25-J30)*Inputs!$F$87/100+(Inputs!$F$78*$F$25-J31)*(Inputs!$F$88/100*Inputs!$F$82)/100)*Construction!J11/Inputs!$F$247 -> 0.54690481 | K40: =Construction!K14*((Inputs!$F$75*$F$25-K28)*Inputs!$F$85/100+(Inputs!$F$76*$F$25-K29)*Inputs!$F$86/100+(Inputs!$F$77*$F$25-K30)*Inputs!$F$87/100+(Inputs!$F$78*$F$25-K31)*(Inputs!$F$88/100*Inputs!$F$82)/100)*Construction!K11/Inputs!$F$247 -> 0.45399849 | L40: =Construction!L14*((Inputs!$F$75*$F$25-L28)*Inputs!$F$85/100+(Inputs!$F$76*$F$25-L29)*Inputs!$F$86/100+(Inputs!$F$77*$F$25-L30)*Inputs!$F$87/100+(Inputs!$F$78*$F$25-L31)*(Inputs!$F$88/100*Inputs!$F$82)/100)*Construction!L11/Inputs!$F$247 -> 0.46753584 | M40: =Construction!M14*((Inputs!$F$75*$F$25-M28)*Inputs!$F$85/100+(Inputs!$F$76*$F$25-M29)*Inputs!$F$86/100+(Inputs!$F$77*$F$25-M30)*Inputs!$F$87/100+(Inputs!$F$78*$F$25-M31)*(Inputs!$F$88/100*Inputs!$F$82)/100)*Construction!M11/Inputs!$F$247 -> 0.45048458 | N40: =Construction!N14*((Inputs!$F$75*$F$25-N28)*Inputs!$F$85/100+(Inputs!$F$76*$F$25-N29)*Inputs!$F$86/100+(Inputs!$F$77*$F$25-N30)*Inputs!$F$87/100+(Inputs!$F$78*$F$25-N31)*(Inputs!$F$88/100*Inputs!$F$82)/100)*Construction!N11/Inputs!$F$247 -> 0.4626223 | O40: =Construction!O14*((Inputs!$F$75*$F$25-O28)*Inputs!$F$85/100+(Inputs!$F$76*$F$25-O29)*Inputs!$F$86/100+(Inputs!$F$77*$F$25-O30)*Inputs!$F$87/100+(Inputs!$F$78*$F$25-O31)*(Inputs!$F$88/100*Inputs!$F$82)/100)*Construction!O11/Inputs!$F$247 -> 0.45847626 | P40: =Construction!P14*((Inputs!$F$75*$F$25-P28)*Inputs!$F$85/100+(Inputs!$F$76*$F$25-P29)*Inputs!$F$86/100+(Inputs!$F$77*$F$25-P30)*Inputs!$F$87/100+(Inputs!$F$78*$F$25-P31)*(Inputs!$F$88/100*Inputs!$F$82)/100)*Construction!P11/Inputs!$F$247 -> 0.40894611 | Q40: =Construction!Q14*((Inputs!$F$75*$F$25-Q28)*Inputs!$F$85/100+(Inputs!$F$76*$F$25-Q29)*Inputs!$F$86/100+(Inputs!$F$77*$F$25-Q30)*Inputs!$F$87/100+(Inputs!$F$78*$F$25-Q31)*(Inputs!$F$88/100*Inputs!$F$82)/100)*Construction!Q11/Inputs!$F$247 -> 0.44530577 | ... BJ40: =Construction!BJ14*((Inputs!$F$75*$F$25-BJ28)*Inputs!$F$85/100+(Inputs!$F$76*$F$25-BJ29)*Inputs!$F$86/100+(Inputs!$F$77*$F$25-BJ30)*Inputs!$F$87/100+(Inputs!$F$78*$F$25-BJ31)*(Inputs!$F$88/100*Inputs!$F$82)/100)*Construction!BJ11/Inputs!$F$247 -> 0
D41: Commitment fee, standby facility | E41: USD m | G41: =SUM(J41:BJ41) -> 0.8165 | J41: =Construction!J14*(Inputs!$F$99-J32)*Inputs!$F$100/100*Construction!J11/Inputs!$F$247 -> 0.023766667 | K41: =Construction!K14*(Inputs!$F$99-K32)*Inputs!$F$100/100*Construction!K11/Inputs!$F$247 -> 0.023 | L41: =Construction!L14*(Inputs!$F$99-L32)*Inputs!$F$100/100*Construction!L11/Inputs!$F$247 -> 0.023766667 | M41: =Construction!M14*(Inputs!$F$99-M32)*Inputs!$F$100/100*Construction!M11/Inputs!$F$247 -> 0.023 | N41: =Construction!N14*(Inputs!$F$99-N32)*Inputs!$F$100/100*Construction!N11/Inputs!$F$247 -> 0.023766667 | O41: =Construction!O14*(Inputs!$F$99-O32)*Inputs!$F$100/100*Construction!O11/Inputs!$F$247 -> 0.023766667 | P41: =Construction!P14*(Inputs!$F$99-P32)*Inputs!$F$100/100*Construction!P11/Inputs!$F$247 -> 0.021466667 | Q41: =Construction!Q14*(Inputs!$F$99-Q32)*Inputs!$F$100/100*Construction!Q11/Inputs!$F$247 -> 0.023766667 | ... BJ41: =Construction!BJ14*(Inputs!$F$99-BJ32)*Inputs!$F$100/100*Construction!BJ11/Inputs!$F$247 -> 0
D42: Upfront and arrangement fees | E42: USD m | G42: =SUM(J42:BJ42) -> 9.9028089 | J42: =IF(Construction!J8=1,Inputs!$F$75*$F$25*Inputs!$F$89/100+Inputs!$F$76*$F$25*Inputs!$F$90/100+Inputs!$F$77*$F$25*Inputs!$F$91/100+Inputs!$F$78*$F$25*Inputs!$F$92/100,0) -> 9.9028089 | K42: =IF(Construction!K8=1,Inputs!$F$75*$F$25*Inputs!$F$89/100+Inputs!$F$76*$F$25*Inputs!$F$90/100+Inputs!$F$77*$F$25*Inputs!$F$91/100+Inputs!$F$78*$F$25*Inputs!$F$92/100,0) -> 0 | L42: =IF(Construction!L8=1,Inputs!$F$75*$F$25*Inputs!$F$89/100+Inputs!$F$76*$F$25*Inputs!$F$90/100+Inputs!$F$77*$F$25*Inputs!$F$91/100+Inputs!$F$78*$F$25*Inputs!$F$92/100,0) -> 0 | M42: =IF(Construction!M8=1,Inputs!$F$75*$F$25*Inputs!$F$89/100+Inputs!$F$76*$F$25*Inputs!$F$90/100+Inputs!$F$77*$F$25*Inputs!$F$91/100+Inputs!$F$78*$F$25*Inputs!$F$92/100,0) -> 0 | N42: =IF(Construction!N8=1,Inputs!$F$75*$F$25*Inputs!$F$89/100+Inputs!$F$76*$F$25*Inputs!$F$90/100+Inputs!$F$77*$F$25*Inputs!$F$91/100+Inputs!$F$78*$F$25*Inputs!$F$92/100,0) -> 0 | O42: =IF(Construction!O8=1,Inputs!$F$75*$F$25*Inputs!$F$89/100+Inputs!$F$76*$F$25*Inputs!$F$90/100+Inputs!$F$77*$F$25*Inputs!$F$91/100+Inputs!$F$78*$F$25*Inputs!$F$92/100,0) -> 0 | P42: =IF(Construction!P8=1,Inputs!$F$75*$F$25*Inputs!$F$89/100+Inputs!$F$76*$F$25*Inputs!$F$90/100+Inputs!$F$77*$F$25*Inputs!$F$91/100+Inputs!$F$78*$F$25*Inputs!$F$92/100,0) -> 0 | Q42: =IF(Construction!Q8=1,Inputs!$F$75*$F$25*Inputs!$F$89/100+Inputs!$F$76*$F$25*Inputs!$F$90/100+Inputs!$F$77*$F$25*Inputs!$F$91/100+Inputs!$F$78*$F$25*Inputs!$F$92/100,0) -> 0 | ... BJ42: =IF(Construction!BJ8=1,Inputs!$F$75*$F$25*Inputs!$F$89/100+Inputs!$F$76*$F$25*Inputs!$F$90/100+Inputs!$F$77*$F$25*Inputs!$F$91/100+Inputs!$F$78*$F$25*Inputs!$F$92/100,0) -> 0
D43: Agency fees during construction | E43: USD m | G43: =SUM(J43:BJ43) -> 0.74375 | J43: =Construction!J14*Inputs!$F$107/12 -> 0.02125 | K43: =Construction!K14*Inputs!$F$107/12 -> 0.02125 | L43: =Construction!L14*Inputs!$F$107/12 -> 0.02125 | M43: =Construction!M14*Inputs!$F$107/12 -> 0.02125 | N43: =Construction!N14*Inputs!$F$107/12 -> 0.02125 | O43: =Construction!O14*Inputs!$F$107/12 -> 0.02125 | P43: =Construction!P14*Inputs!$F$107/12 -> 0.02125 | Q43: =Construction!Q14*Inputs!$F$107/12 -> 0.02125 | ... BJ43: =Construction!BJ14*Inputs!$F$107/12 -> 0
D44: DSRA initial funding (COD month) | E44: USD m | G44: =SUM(J44:BJ44) -> 37.245895 | J44: =Construction!J15*IF(Inputs!$F$34=1,$F$12*Inputs!$F$75*$F$25+$F$13*Inputs!$F$76*$F$25+$F$14*Inputs!$F$77*$F$25+$F$15*Inputs!$F$78*$F$25+$F$17,$F$12*J28+$F$13*J29+$F$14*J30+$F$15*J31+$F$16*J32+$F$17) -> 0 | K44: =Construction!K15*IF(Inputs!$F$34=1,$F$12*Inputs!$F$75*$F$25+$F$13*Inputs!$F$76*$F$25+$F$14*Inputs!$F$77*$F$25+$F$15*Inputs!$F$78*$F$25+$F$17,$F$12*K28+$F$13*K29+$F$14*K30+$F$15*K31+$F$16*K32+$F$17) -> 0 | L44: =Construction!L15*IF(Inputs!$F$34=1,$F$12*Inputs!$F$75*$F$25+$F$13*Inputs!$F$76*$F$25+$F$14*Inputs!$F$77*$F$25+$F$15*Inputs!$F$78*$F$25+$F$17,$F$12*L28+$F$13*L29+$F$14*L30+$F$15*L31+$F$16*L32+$F$17) -> 0 | M44: =Construction!M15*IF(Inputs!$F$34=1,$F$12*Inputs!$F$75*$F$25+$F$13*Inputs!$F$76*$F$25+$F$14*Inputs!$F$77*$F$25+$F$15*Inputs!$F$78*$F$25+$F$17,$F$12*M28+$F$13*M29+$F$14*M30+$F$15*M31+$F$16*M32+$F$17) -> 0 | N44: =Construction!N15*IF(Inputs!$F$34=1,$F$12*Inputs!$F$75*$F$25+$F$13*Inputs!$F$76*$F$25+$F$14*Inputs!$F$77*$F$25+$F$15*Inputs!$F$78*$F$25+$F$17,$F$12*N28+$F$13*N29+$F$14*N30+$F$15*N31+$F$16*N32+$F$17) -> 0 | O44: =Construction!O15*IF(Inputs!$F$34=1,$F$12*Inputs!$F$75*$F$25+$F$13*Inputs!$F$76*$F$25+$F$14*Inputs!$F$77*$F$25+$F$15*Inputs!$F$78*$F$25+$F$17,$F$12*O28+$F$13*O29+$F$14*O30+$F$15*O31+$F$16*O32+$F$17) -> 0 | P44: =Construction!P15*IF(Inputs!$F$34=1,$F$12*Inputs!$F$75*$F$25+$F$13*Inputs!$F$76*$F$25+$F$14*Inputs!$F$77*$F$25+$F$15*Inputs!$F$78*$F$25+$F$17,$F$12*P28+$F$13*P29+$F$14*P30+$F$15*P31+$F$16*P32+$F$17) -> 0 | Q44: =Construction!Q15*IF(Inputs!$F$34=1,$F$12*Inputs!$F$75*$F$25+$F$13*Inputs!$F$76*$F$25+$F$14*Inputs!$F$77*$F$25+$F$15*Inputs!$F$78*$F$25+$F$17,$F$12*Q28+$F$13*Q29+$F$14*Q30+$F$15*Q31+$F$16*Q32+$F$17) -> 0 | ... BJ44: =Construction!BJ15*IF(Inputs!$F$34=1,$F$12*Inputs!$F$75*$F$25+$F$13*Inputs!$F$76*$F$25+$F$14*Inputs!$F$77*$F$25+$F$15*Inputs!$F$78*$F$25+$F$17,$F$12*BJ28+$F$13*BJ29+$F$14*BJ30+$F$15*BJ31+$F$16*BJ32+$F$17) -> 0
D45: Uses before ECA premium | E45: USD m | J45: =Construction!J14*(Construction!J32+Construction!J38)+J33+J34+J35+J36+J37+J38+J39+J40+J41+J42+J43+J44+J79 -> 118.60633 | K45: =Construction!K14*(Construction!K32+Construction!K38)+K33+K34+K35+K36+K37+K38+K39+K40+K41+K42+K43+K44+K79 -> 2.4338419 | L45: =Construction!L14*(Construction!L32+Construction!L38)+L33+L34+L35+L36+L37+L38+L39+L40+L41+L42+L43+L44+L79 -> 3.1036028 | M45: =Construction!M14*(Construction!M32+Construction!M38)+M33+M34+M35+M36+M37+M38+M39+M40+M41+M42+M43+M44+M79 -> 4.3896942 | N45: =Construction!N14*(Construction!N32+Construction!N38)+N33+N34+N35+N36+N37+N38+N39+N40+N41+N42+N43+N44+N79 -> 6.3228416 | O45: =Construction!O14*(Construction!O32+Construction!O38)+O33+O34+O35+O36+O37+O38+O39+O40+O41+O42+O43+O44+O79 -> 8.7147932 | P45: =Construction!P14*(Construction!P32+Construction!P38)+P33+P34+P35+P36+P37+P38+P39+P40+P41+P42+P43+P44+P79 -> 11.370627 | Q45: =Construction!Q14*(Construction!Q32+Construction!Q38)+Q33+Q34+Q35+Q36+Q37+Q38+Q39+Q40+Q41+Q42+Q43+Q44+Q79 -> 14.43371 | ... BJ45: =Construction!BJ14*(Construction!BJ32+Construction!BJ38)+BJ33+BJ34+BJ35+BJ36+BJ37+BJ38+BJ39+BJ40+BJ41+BJ42+BJ43+BJ44+BJ79 -> 0
D46: Headroom on committed senior tranches | E46: USD m | J46: =$F$25-J28-J29-J30-J31 -> 629.94967 | K46: =$F$25-K28-K29-K30-K31 -> 540.36717 | L46: =$F$25-L28-L29-L30-L31 -> 538.52891 | M46: =$F$25-M28-M29-M30-M31 -> 536.18478 | N46: =$F$25-N28-N29-N30-N31 -> 532.86928 | O46: =$F$25-O28-O29-O30-O31 -> 528.09368 | P46: =$F$25-P28-P29-P30-P31 -> 521.51146 | Q46: =$F$25-Q28-Q29-Q30-Q31 -> 512.92331 | ... BJ46: =$F$25-BJ28-BJ29-BJ30-BJ31 -> 0
D47: Senior tranche drawdown (pro rata) | E47: USD m | G47: =SUM(J47:BJ47) -> 629.94967 | J47: =MIN($F$26*J45/(1-Inputs!$F$94/100*Inputs!$F$75*$F$26),J46) -> 89.582501 | K47: =MIN($F$26*K45/(1-Inputs!$F$94/100*Inputs!$F$75*$F$26),K46) -> 1.8382632 | L47: =MIN($F$26*L45/(1-Inputs!$F$94/100*Inputs!$F$75*$F$26),L46) -> 2.3441287 | M47: =MIN($F$26*M45/(1-Inputs!$F$94/100*Inputs!$F$75*$F$26),M46) -> 3.3155042 | N47: =MIN($F$26*N45/(1-Inputs!$F$94/100*Inputs!$F$75*$F$26),N46) -> 4.7755964 | O47: =MIN($F$26*O45/(1-Inputs!$F$94/100*Inputs!$F$75*$F$26),O46) -> 6.5822201 | P47: =MIN($F$26*P45/(1-Inputs!$F$94/100*Inputs!$F$75*$F$26),P46) -> 8.5881524 | Q47: =MIN($F$26*Q45/(1-Inputs!$F$94/100*Inputs!$F$75*$F$26),Q46) -> 10.901676 | ... BJ47: =MIN($F$26*BJ45/(1-Inputs!$F$94/100*Inputs!$F$75*$F$26),BJ46) -> 0
D48: ECA premium (financed) | E48: USD m | G48: =SUM(J48:BJ48) -> 20.504862 | J48: =Inputs!$F$94/100*Inputs!$F$75*J47 -> 2.9159104 | K48: =Inputs!$F$94/100*Inputs!$F$75*K47 -> 0.059835466 | L48: =Inputs!$F$94/100*Inputs!$F$75*L47 -> 0.076301389 | M48: =Inputs!$F$94/100*Inputs!$F$75*M47 -> 0.10791966 | N48: =Inputs!$F$94/100*Inputs!$F$75*N47 -> 0.15544566 | O48: =Inputs!$F$94/100*Inputs!$F$75*O47 -> 0.21425126 | P48: =Inputs!$F$94/100*Inputs!$F$75*P47 -> 0.27954436 | Q48: =Inputs!$F$94/100*Inputs!$F$75*Q47 -> 0.35484956 | ... BJ48: =Inputs!$F$94/100*Inputs!$F$75*BJ47 -> 0
D49: Total uses of funds | E49: USD m | G49: =SUM(J49:BJ49) -> 854.55189 | J49: =J45+J48 -> 121.52224 | K49: =K45+K48 -> 2.4936774 | L49: =L45+L48 -> 3.1799042 | M49: =M45+M48 -> 4.4976139 | N49: =N45+N48 -> 6.4782873 | O49: =O45+O48 -> 8.9290445 | P49: =P45+P48 -> 11.650172 | Q49: =Q45+Q48 -> 14.788559 | ... BJ49: =BJ45+BJ48 -> 0
D50: Funded pro rata from committed debt and equity | E50: USD m | G50: =SUM(J50:BJ50) -> 854.55189 | J50: =J47/$F$26 -> 121.52224 | K50: =K47/$F$26 -> 2.4936774 | L50: =L47/$F$26 -> 3.1799042 | M50: =M47/$F$26 -> 4.4976139 | N50: =N47/$F$26 -> 6.4782873 | O50: =O47/$F$26 -> 8.9290445 | P50: =P47/$F$26 -> 11.650172 | Q50: =Q47/$F$26 -> 14.788559 | ... BJ50: =BJ47/$F$26 -> 0
D51: Remaining uses after committed facilities | E51: USD m | J51: =J49-J50 -> 0 | K51: =K49-K50 -> 0 | L51: =L49-L50 -> 0 | M51: =M49-M50 -> 0 | N51: =N49-N50 -> 0 | O51: =O49-O50 -> 0 | P51: =P49-P50 -> 0 | Q51: =Q49-Q50 -> 0 | ... BJ51: =BJ49-BJ50 -> 0
D52: Delay LDs and DSU proceeds received | E52: USD m | G52: =SUM(J52:BJ52) -> 0 | J52: =IF(AND(Inputs!$F$34<>1,Construction!J8=Inputs!$F$245),Inputs!$F$265+Inputs!$F$266,0) -> 0 | K52: =IF(AND(Inputs!$F$34<>1,Construction!K8=Inputs!$F$245),Inputs!$F$265+Inputs!$F$266,0) -> 0 | L52: =IF(AND(Inputs!$F$34<>1,Construction!L8=Inputs!$F$245),Inputs!$F$265+Inputs!$F$266,0) -> 0 | M52: =IF(AND(Inputs!$F$34<>1,Construction!M8=Inputs!$F$245),Inputs!$F$265+Inputs!$F$266,0) -> 0 | N52: =IF(AND(Inputs!$F$34<>1,Construction!N8=Inputs!$F$245),Inputs!$F$265+Inputs!$F$266,0) -> 0 | O52: =IF(AND(Inputs!$F$34<>1,Construction!O8=Inputs!$F$245),Inputs!$F$265+Inputs!$F$266,0) -> 0 | P52: =IF(AND(Inputs!$F$34<>1,Construction!P8=Inputs!$F$245),Inputs!$F$265+Inputs!$F$266,0) -> 0 | Q52: =IF(AND(Inputs!$F$34<>1,Construction!Q8=Inputs!$F$245),Inputs!$F$265+Inputs!$F$266,0) -> 0 | ... BJ52: =IF(AND(Inputs!$F$34<>1,Construction!BJ8=Inputs!$F$245),Inputs!$F$265+Inputs!$F$266,0) -> 0
D53: LD and DSU proceeds applied | E53: USD m | G53: =SUM(J53:BJ53) -> 0 | J53: =MIN(J51,I54+J52) -> 0 | K53: =MIN(K51,J54+K52) -> 0 | L53: =MIN(L51,K54+L52) -> 0 | M53: =MIN(M51,L54+M52) -> 0 | N53: =MIN(N51,M54+N52) -> 0 | O53: =MIN(O51,N54+O52) -> 0 | P53: =MIN(P51,O54+P52) -> 0 | Q53: =MIN(Q51,P54+Q52) -> 0 | ... BJ53: =MIN(BJ51,BI54+BJ52) -> 0
D54: LD and DSU proceeds held (Proceeds Account) | E54: USD m | J54: =I54+J52-J53 -> 0 | K54: =J54+K52-K53 -> 0 | L54: =K54+L52-L53 -> 0 | M54: =L54+M52-M53 -> 0 | N54: =M54+N52-N53 -> 0 | O54: =N54+O52-O53 -> 0 | P54: =O54+P52-P53 -> 0 | Q54: =P54+Q52-Q53 -> 0 | ... BJ54: =BI54+BJ52-BJ53 -> 0
D55: Standby facility drawdown (75%) | E55: USD m | G55: =SUM(J55:BJ55) -> 1.6334933e-11 | J55: =Inputs!$F$249*(J51-J53) -> 0 | K55: =Inputs!$F$249*(K51-K53) -> 0 | L55: =Inputs!$F$249*(L51-L53) -> 0 | M55: =Inputs!$F$249*(M51-M53) -> 0 | N55: =Inputs!$F$249*(N51-N53) -> 0 | O55: =Inputs!$F$249*(O51-O53) -> 0 | P55: =Inputs!$F$249*(P51-P53) -> 0 | Q55: =Inputs!$F$249*(Q51-Q53) -> 0 | ... BJ55: =Inputs!$F$249*(BJ51-BJ53) -> 0
D56: Contingent equity (25%) | E56: USD m | G56: =SUM(J56:BJ56) -> 5.4449778e-12 | J56: =(1-Inputs!$F$249)*(J51-J53) -> 0 | K56: =(1-Inputs!$F$249)*(K51-K53) -> 0 | L56: =(1-Inputs!$F$249)*(L51-L53) -> 0 | M56: =(1-Inputs!$F$249)*(M51-M53) -> 0 | N56: =(1-Inputs!$F$249)*(N51-N53) -> 0 | O56: =(1-Inputs!$F$249)*(O51-O53) -> 0 | P56: =(1-Inputs!$F$249)*(P51-P53) -> 0 | Q56: =(1-Inputs!$F$249)*(Q51-Q53) -> 0 | ... BJ56: =(1-Inputs!$F$249)*(BJ51-BJ53) -> 0
D57: ECA-covered tranche: drawdown | E57: USD m | G57: =SUM(J57:BJ57) -> 188.9849 | J57: =Inputs!$F$75*J47 -> 26.87475 | K57: =Inputs!$F$75*K47 -> 0.55147895 | L57: =Inputs!$F$75*L47 -> 0.70323861 | M57: =Inputs!$F$75*M47 -> 0.99465126 | N57: =Inputs!$F$75*N47 -> 1.4326789 | O57: =Inputs!$F$75*O47 -> 1.974666 | P57: =Inputs!$F$75*P47 -> 2.5764457 | Q57: =Inputs!$F$75*Q47 -> 3.2705028 | ... BJ57: =Inputs!$F$75*BJ47 -> 0
D58: ABDB A-loan: drawdown | E58: USD m | G58: =SUM(J58:BJ58) -> 138.58893 | J58: =Inputs!$F$76*J47 -> 19.70815 | K58: =Inputs!$F$76*K47 -> 0.40441789 | L58: =Inputs!$F$76*L47 -> 0.51570831 | M58: =Inputs!$F$76*M47 -> 0.72941093 | N58: =Inputs!$F$76*N47 -> 1.0506312 | O58: =Inputs!$F$76*O47 -> 1.4480884 | P58: =Inputs!$F$76*P47 -> 1.8893935 | Q58: =Inputs!$F$76*Q47 -> 2.3983687 | ... BJ58: =Inputs!$F$76*BJ47 -> 0
D59: ABDB B-loan: drawdown | E59: USD m | G59: =SUM(J59:BJ59) -> 62.994967 | J59: =Inputs!$F$77*J47 -> 8.9582501 | K59: =Inputs!$F$77*K47 -> 0.18382632 | L59: =Inputs!$F$77*L47 -> 0.23441287 | M59: =Inputs!$F$77*M47 -> 0.33155042 | N59: =Inputs!$F$77*N47 -> 0.47755964 | O59: =Inputs!$F$77*O47 -> 0.65822201 | P59: =Inputs!$F$77*P47 -> 0.85881524 | Q59: =Inputs!$F$77*Q47 -> 1.0901676 | ... BJ59: =Inputs!$F$77*BJ47 -> 0
D60: Commercial tranche: drawdown | E60: USD m | G60: =SUM(J60:BJ60) -> 239.38088 | J60: =Inputs!$F$78*J47 -> 34.04135 | K60: =Inputs!$F$78*K47 -> 0.69854 | L60: =Inputs!$F$78*L47 -> 0.89076891 | M60: =Inputs!$F$78*M47 -> 1.2598916 | N60: =Inputs!$F$78*N47 -> 1.8147266 | O60: =Inputs!$F$78*O47 -> 2.5012436 | P60: =Inputs!$F$78*P47 -> 3.2634979 | Q60: =Inputs!$F$78*Q47 -> 4.1426369 | ... BJ60: =Inputs!$F$78*BJ47 -> 0
D61: ECA-covered tranche: closing balance | E61: USD m | J61: =J28+J57 -> 26.87475 | K61: =K28+K57 -> 27.426229 | L61: =L28+L57 -> 28.129468 | M61: =M28+M57 -> 29.124119 | N61: =N28+N57 -> 30.556798 | O61: =O28+O57 -> 32.531464 | P61: =P28+P57 -> 35.10791 | Q61: =Q28+Q57 -> 38.378413 | ... BJ61: =BJ28+BJ57 -> 188.9849
D62: ABDB A-loan: closing balance | E62: USD m | J62: =J29+J58 -> 19.70815 | K62: =K29+K58 -> 20.112568 | L62: =L29+L58 -> 20.628276 | M62: =M29+M58 -> 21.357687 | N62: =N29+N58 -> 22.408319 | O62: =O29+O58 -> 23.856407 | P62: =P29+P58 -> 25.745801 | Q62: =Q29+Q58 -> 28.144169 | ... BJ62: =BJ29+BJ58 -> 138.58893
D63: ABDB B-loan: closing balance | E63: USD m | J63: =J30+J59 -> 8.9582501 | K63: =K30+K59 -> 9.1420764 | L63: =L30+L59 -> 9.3764893 | M63: =M30+M59 -> 9.7080397 | N63: =N30+N59 -> 10.185599 | O63: =O30+O59 -> 10.843821 | P63: =P30+P59 -> 11.702637 | Q63: =Q30+Q59 -> 12.792804 | ... BJ63: =BJ30+BJ59 -> 62.994967
D64: Commercial tranche: closing balance | E64: USD m | J64: =J31+J60 -> 34.04135 | K64: =K31+K60 -> 34.73989 | L64: =L31+L60 -> 35.630659 | M64: =M31+M60 -> 36.890551 | N64: =N31+N60 -> 38.705278 | O64: =O31+O60 -> 41.206521 | P64: =P31+P60 -> 44.470019 | Q64: =Q31+Q60 -> 48.612656 | ... BJ64: =BJ31+BJ60 -> 239.38088
D65: Standby facility: closing balance | E65: USD m | J65: =J32+J55 -> 0 | K65: =K32+K55 -> 0 | L65: =L32+L55 -> 0 | M65: =M32+M55 -> 0 | N65: =N32+N55 -> 0 | O65: =O32+O55 -> 0 | P65: =P32+P55 -> 0 | Q65: =Q32+Q55 -> 0 | ... BJ65: =BJ32+BJ55 -> 1.6334933e-11
B66: Equity (USD m)
D67: Equity contributions (incl. LNTP credit in month 1) | E67: USD m | G67: =SUM(J67:BJ67) -> 224.60222 | J67: =J50-J47+J56 -> 31.93974 | K67: =K50-K47+K56 -> 0.65541423 | L67: =L50-L47+L56 -> 0.83577551 | M67: =M50-M47+M56 -> 1.1821097 | N67: =N50-N47+N56 -> 1.7026909 | O67: =O50-O47+O56 -> 2.3468244 | P67: =P50-P47+P56 -> 3.0620193 | Q67: =Q50-Q47+Q56 -> 3.886883 | ... BJ67: =BJ50-BJ47+BJ56 -> 0
D68: Equity contributed in cash | E68: USD m | G68: =SUM(J68:BJ68) -> 210.40222 | J68: =J67-IF(Construction!J8=1,Inputs!$F$68,0) -> 17.73974 | K68: =K67-IF(Construction!K8=1,Inputs!$F$68,0) -> 0.65541423 | L68: =L67-IF(Construction!L8=1,Inputs!$F$68,0) -> 0.83577551 | M68: =M67-IF(Construction!M8=1,Inputs!$F$68,0) -> 1.1821097 | N68: =N67-IF(Construction!N8=1,Inputs!$F$68,0) -> 1.7026909 | O68: =O67-IF(Construction!O8=1,Inputs!$F$68,0) -> 2.3468244 | P68: =P67-IF(Construction!P8=1,Inputs!$F$68,0) -> 3.0620193 | Q68: =Q67-IF(Construction!Q8=1,Inputs!$F$68,0) -> 3.886883 | ... BJ68: =BJ67-IF(Construction!BJ8=1,Inputs!$F$68,0) -> 0
D69: Share capital | E69: USD m | G69: =SUM(J69:BJ69) -> 44.920444 | J69: =(1-Inputs!$F$53)*J67 -> 6.3879479 | K69: =(1-Inputs!$F$53)*K67 -> 0.13108285 | L69: =(1-Inputs!$F$53)*L67 -> 0.1671551 | M69: =(1-Inputs!$F$53)*M67 -> 0.23642193 | N69: =(1-Inputs!$F$53)*N67 -> 0.34053817 | O69: =(1-Inputs!$F$53)*O67 -> 0.46936487 | P69: =(1-Inputs!$F$53)*P67 -> 0.61240387 | Q69: =(1-Inputs!$F$53)*Q67 -> 0.77737659 | ... BJ69: =(1-Inputs!$F$53)*BJ67 -> 0
D70: Shareholder loans advanced | E70: USD m | G70: =SUM(J70:BJ70) -> 179.68178 | J70: =Inputs!$F$53*J67 -> 25.551792 | K70: =Inputs!$F$53*K67 -> 0.52433139 | L70: =Inputs!$F$53*L67 -> 0.66862041 | M70: =Inputs!$F$53*M67 -> 0.94568774 | N70: =Inputs!$F$53*N67 -> 1.3621527 | O70: =Inputs!$F$53*O67 -> 1.8774595 | P70: =Inputs!$F$53*P67 -> 2.4496155 | Q70: =Inputs!$F$53*Q67 -> 3.1095064 | ... BJ70: =Inputs!$F$53*BJ67 -> 0
D71: Shareholder loan interest capitalized (to COD) | E71: USD m | G71: =SUM(J71:BJ71) -> 24.496565 | J71: =IF(Construction!J8<=Time!$F$11,I72*Inputs!$F$104/100*Construction!J11/Inputs!$F$248,0) -> 0 | K71: =IF(Construction!K8<=Time!$F$11,J72*Inputs!$F$104/100*Construction!K11/Inputs!$F$248,0) -> 0.19951399 | L71: =IF(Construction!L8<=Time!$F$11,K72*Inputs!$F$104/100*Construction!L11/Inputs!$F$248,0) -> 0.2120048 | M71: =IF(Construction!M8<=Time!$F$11,L72*Inputs!$F$104/100*Construction!M11/Inputs!$F$248,0) -> 0.21204205 | N71: =IF(Construction!N8<=Time!$F$11,M72*Inputs!$F$104/100*Construction!N11/Inputs!$F$248,0) -> 0.22845125 | O71: =IF(Construction!O8<=Time!$F$11,N72*Inputs!$F$104/100*Construction!O11/Inputs!$F$248,0) -> 0.24128503 | P71: =IF(Construction!P8<=Time!$F$11,O72*Inputs!$F$104/100*Construction!P11/Inputs!$F$248,0) -> 0.23337558 | Q71: =IF(Construction!Q8<=Time!$F$11,P72*Inputs!$F$104/100*Construction!Q11/Inputs!$F$248,0) -> 0.2800278 | ... BJ71: =IF(Construction!BJ8<=Time!$F$11,BI72*Inputs!$F$104/100*Construction!BJ11/Inputs!$F$248,0) -> 0
D72: Shareholder loan balance | E72: USD m | J72: =I72+J71+J70 -> 25.551792 | K72: =J72+K71+K70 -> 26.275637 | L72: =K72+L71+L70 -> 27.156262 | M72: =L72+M71+M70 -> 28.313992 | N72: =M72+N71+N70 -> 29.904596 | O72: =N72+O71+O70 -> 32.023341 | P72: =O72+P71+P70 -> 34.706332 | Q72: =P72+Q71+Q70 -> 38.095866 | ... BJ72: =BI72+BJ71+BJ70 -> 204.17834
D73: Total debt drawdowns (incl. standby) | E73: USD m | G73: =SUM(J73:BJ73) -> 629.94967 | J73: =J47+J55 -> 89.582501 | K73: =K47+K55 -> 1.8382632 | L73: =L47+L55 -> 2.3441287 | M73: =M47+M55 -> 3.3155042 | N73: =N47+N55 -> 4.7755964 | O73: =O47+O55 -> 6.5822201 | P73: =P47+P55 -> 8.5881524 | Q73: =Q47+Q55 -> 10.901676 | ... BJ73: =BJ47+BJ55 -> 0
D74: Financing costs (IDC, fees, premium, VAT interest) | E74: USD m | G74: =SUM(J74:BJ74) -> 106.316 | J74: =J33+J34+J35+J36+J37+J38+J39+J40+J41+J42+J43+J48+Construction!J14*Construction!J38 -> 13.410641 | K74: =K33+K34+K35+K36+K37+K38+K39+K40+K41+K42+K43+K48+Construction!K14*Construction!K38 -> 1.072848 | L74: =L33+L34+L35+L36+L37+L38+L39+L40+L41+L42+L43+L48+Construction!L14*Construction!L38 -> 1.1252297 | M74: =M33+M34+M35+M36+M37+M38+M39+M40+M41+M42+M43+M48+Construction!M14*Construction!M38 -> 1.1406196 | N74: =N33+N34+N35+N36+N37+N38+N39+N40+N41+N42+N43+N48+Construction!N14*Construction!N38 -> 1.2321255 | O74: =O33+O34+O35+O36+O37+O38+O39+O40+O41+O42+O43+O48+Construction!O14*Construction!O38 -> 1.3206502 | P74: =P33+P34+P35+P36+P37+P38+P39+P40+P41+P42+P43+P48+Construction!P14*Construction!P38 -> 1.3320124 | Q74: =Q33+Q34+Q35+Q36+Q37+Q38+Q39+Q40+Q41+Q42+Q43+Q48+Construction!Q14*Construction!Q38 -> 1.5392527 | ... BJ74: =BJ33+BJ34+BJ35+BJ36+BJ37+BJ38+BJ39+BJ40+BJ41+BJ42+BJ43+BJ48+Construction!BJ14*Construction!BJ38 -> 0
D75: Total funding requirement (sum of uses) | E75: USD m | F75: =SUM(Funding!$J$49:$BJ$49) -> 854.55189
D76: Capitalized cost (book and tax) | E76: USD m | F76: =SUM($J$49:$BJ$49)-SUM($J$44:$BJ$44)-SUM(Construction!$J$28:$BJ$28)-SUM($J$79:$BJ$79)+SUM($J$71:$BJ$71)-SUM($J$52:$BJ$52)-Inputs!$F$48*Inputs!$F$267 -> 836.45256
D78: COD-period operating cash shortfall before tax (working capital built in the COD period) | E78: USD m | F78: =MAX(0,-(INDEX(Operations!$J$84:$BN$84,1,Time!$F$12)-INDEX(Operations!$J$96:$BN$96,1,Time!$F$12)+INDEX(Operations!$J$97:$BN$97,1,Time!$F$12)-INDEX(Reserves!$J$7:$BN$7,1,Time!$F$12)+INDEX(Operations!$J$79:$BN$79,1,Time!$F$12))) -> 0
D79: COD working-capital funding (a use in the last funding month; held in the project accounts to COD) | E79: USD m | G79: =SUM(J79:BJ79) -> 0 | J79: =IF(Construction!J8=Time!$F$14,$F$78,0) -> 0 | K79: =IF(Construction!K8=Time!$F$14,$F$78,0) -> 0 | L79: =IF(Construction!L8=Time!$F$14,$F$78,0) -> 0 | M79: =IF(Construction!M8=Time!$F$14,$F$78,0) -> 0 | N79: =IF(Construction!N8=Time!$F$14,$F$78,0) -> 0 | O79: =IF(Construction!O8=Time!$F$14,$F$78,0) -> 0 | P79: =IF(Construction!P8=Time!$F$14,$F$78,0) -> 0 | Q79: =IF(Construction!Q8=Time!$F$14,$F$78,0) -> 0 | ... BJ79: =IF(Construction!BJ8=Time!$F$14,$F$78,0) -> 0

Sheet Debt
A1: Case P: Belanou Combined Cycle Power Project, Republic of Kessara
A2: Debt: tranches, scheduled repayment, waiver, refinancing, swap, sculpting
A3: Units in column E; constants in column F; row totals in column G; first period in column J. Inputs: blue on yellow. Links from other sheets: green.
D4: Label | E4: Unit | F4: Constant | G4: Total
D5: Period ending | J5: 2018H2 | K5: 2019H1 | L5: 2019H2 | M5: 2020H1 | N5: 2020H2 | O5: 2021H1 | P5: 2021H2 | Q5: 2022H1 | R5: 2022H2 | S5: 2023H1 | T5: 2023H2 | U5: 2024H1 | V5: 2024H2 | W5: 2025H1 | X5: 2025H2 | Y5: 2026H1 | Z5: 2026H2 | AA5: 2027H1 | AB5: 2027H2 | AC5: 2028H1 | AD5: 2028H2 | AE5: 2029H1 | AF5: 2029H2 | AG5: 2030H1 | AH5: 2030H2 | AI5: 2031H1 | AJ5: 2031H2 | AK5: 2032H1 | AL5: 2032H2 | AM5: 2033H1 | AN5: 2033H2 | AO5: 2034H1 | AP5: 2034H2 | AQ5: 2035H1 | AR5: 2035H2 | AS5: 2036H1 | AT5: 2036H2 | AU5: 2037H1 | AV5: 2037H2 | AW5: 2038H1 | AX5: 2038H2 | AY5: 2039H1 | AZ5: 2039H2 | BA5: 2040H1 | BB5: 2040H2 | BC5: 2041H1 | BD5: 2041H2 | BE5: 2042H1 | BF5: 2042H2 | BG5: 2043H1 | BH5: 2043H2 | BI5: 2044H1 | BJ5: 2044H2 | BK5: 2045H1 | BL5: 2045H2 | BM5: 2046H1 | BN5: 2046H2
B7: Rates
D8: Commercial margin (step-ups) | E8: % | J8: =IF(Time!J22<Inputs!$F$207,Inputs!$F$82,IF(Time!J22<Inputs!$F$208,Inputs!$F$83,Inputs!$F$84)) -> 4.1 | K8: =IF(Time!K22<Inputs!$F$207,Inputs!$F$82,IF(Time!K22<Inputs!$F$208,Inputs!$F$83,Inputs!$F$84)) -> 4.1 | L8: =IF(Time!L22<Inputs!$F$207,Inputs!$F$82,IF(Time!L22<Inputs!$F$208,Inputs!$F$83,Inputs!$F$84)) -> 4.1 | M8: =IF(Time!M22<Inputs!$F$207,Inputs!$F$82,IF(Time!M22<Inputs!$F$208,Inputs!$F$83,Inputs!$F$84)) -> 4.1 | N8: =IF(Time!N22<Inputs!$F$207,Inputs!$F$82,IF(Time!N22<Inputs!$F$208,Inputs!$F$83,Inputs!$F$84)) -> 4.1 | O8: =IF(Time!O22<Inputs!$F$207,Inputs!$F$82,IF(Time!O22<Inputs!$F$208,Inputs!$F$83,Inputs!$F$84)) -> 4.1 | P8: =IF(Time!P22<Inputs!$F$207,Inputs!$F$82,IF(Time!P22<Inputs!$F$208,Inputs!$F$83,Inputs!$F$84)) -> 4.1 | Q8: =IF(Time!Q22<Inputs!$F$207,Inputs!$F$82,IF(Time!Q22<Inputs!$F$208,Inputs!$F$83,Inputs!$F$84)) -> 4.1 | ... BN8: =IF(Time!BN22<Inputs!$F$207,Inputs!$F$82,IF(Time!BN22<Inputs!$F$208,Inputs!$F$83,Inputs!$F$84)) -> 5.1
D9: Waiver margin uplift | E9: % | J9: =Time!J44*Inputs!$F$269 -> 0 | K9: =Time!K44*Inputs!$F$269 -> 0 | L9: =Time!L44*Inputs!$F$269 -> 0 | M9: =Time!M44*Inputs!$F$269 -> 0 | N9: =Time!N44*Inputs!$F$269 -> 0 | O9: =Time!O44*Inputs!$F$269 -> 0 | P9: =Time!P44*Inputs!$F$269 -> 0 | Q9: =Time!Q44*Inputs!$F$269 -> 0 | ... BN9: =Time!BN44*Inputs!$F$269 -> 0
D10: ECA-covered tranche: rate per period | E10: factor | J10: =(Operations!J9+Inputs!$F$79+J9)/100*Time!J25/Inputs!$F$247 -> 0.01978 | K10: =(Operations!K9+Inputs!$F$79+K9)/100*Time!K25/Inputs!$F$247 -> 0.020815 | L10: =(Operations!L9+Inputs!$F$79+L9)/100*Time!L25/Inputs!$F$247 -> 0.021926667 | M10: =(Operations!M9+Inputs!$F$79+M9)/100*Time!M25/Inputs!$F$247 -> 0.022092778 | N10: =(Operations!N9+Inputs!$F$79+N9)/100*Time!N25/Inputs!$F$247 -> 0.02254 | O10: =(Operations!O9+Inputs!$F$79+O9)/100*Time!O25/Inputs!$F$247 -> 0.022323333 | P10: =(Operations!P9+Inputs!$F$79+P9)/100*Time!P25/Inputs!$F$247 -> 0.022693333 | Q10: =(Operations!Q9+Inputs!$F$79+Q9)/100*Time!Q25/Inputs!$F$247 -> 0.022423889 | ... BN10: =(Operations!BN9+Inputs!$F$79+BN9)/100*Time!BN25/Inputs!$F$247 -> 0.022846667
D11: ABDB A-loan: rate per period | E11: factor | J11: =(Operations!J9+Inputs!$F$80+J9)/100*Time!J25/Inputs!$F$247 -> 0.031535556 | K11: =(Operations!K9+Inputs!$F$80+K9)/100*Time!K25/Inputs!$F$247 -> 0.032378889 | L11: =(Operations!L9+Inputs!$F$80+L9)/100*Time!L25/Inputs!$F$247 -> 0.033682222 | M11: =(Operations!M9+Inputs!$F$80+M9)/100*Time!M25/Inputs!$F$247 -> 0.033720556 | N11: =(Operations!N9+Inputs!$F$80+N9)/100*Time!N25/Inputs!$F$247 -> 0.034295556 | O11: =(Operations!O9+Inputs!$F$80+O9)/100*Time!O25/Inputs!$F$247 -> 0.033887222 | P11: =(Operations!P9+Inputs!$F$80+P9)/100*Time!P25/Inputs!$F$247 -> 0.034448889 | Q11: =(Operations!Q9+Inputs!$F$80+Q9)/100*Time!Q25/Inputs!$F$247 -> 0.033987778 | ... BN11: =(Operations!BN9+Inputs!$F$80+BN9)/100*Time!BN25/Inputs!$F$247 -> 0.034602222
D12: ABDB B-loan: rate per period | E12: factor | J12: =(Operations!J9+Inputs!$F$81+J9)/100*Time!J25/Inputs!$F$247 -> 0.030257778 | K12: =(Operations!K9+Inputs!$F$81+K9)/100*Time!K25/Inputs!$F$247 -> 0.031121944 | L12: =(Operations!L9+Inputs!$F$81+L9)/100*Time!L25/Inputs!$F$247 -> 0.032404444 | M12: =(Operations!M9+Inputs!$F$81+M9)/100*Time!M25/Inputs!$F$247 -> 0.032456667 | N12: =(Operations!N9+Inputs!$F$81+N9)/100*Time!N25/Inputs!$F$247 -> 0.033017778 | O12: =(Operations!O9+Inputs!$F$81+O9)/100*Time!O25/Inputs!$F$247 -> 0.032630278 | P12: =(Operations!P9+Inputs!$F$81+P9)/100*Time!P25/Inputs!$F$247 -> 0.033171111 | Q12: =(Operations!Q9+Inputs!$F$81+Q9)/100*Time!Q25/Inputs!$F$247 -> 0.032730833 | ... BN12: =(Operations!BN9+Inputs!$F$81+BN9)/100*Time!BN25/Inputs!$F$247 -> 0.033324444
D13: Commercial tranche: rate per period | E13: factor | J13: =(Operations!J9+J8+J9)/100*Time!J25/Inputs!$F$247/(1-Inputs!$F$93/100) -> 0.037595062 | K13: =(Operations!K9+K8+K9)/100*Time!K25/Inputs!$F$247/(1-Inputs!$F$93/100) -> 0.038490432 | L13: =(Operations!L9+L8+L9)/100*Time!L25/Inputs!$F$247/(1-Inputs!$F$93/100) -> 0.039980247 | M13: =(Operations!M9+M8+M9)/100*Time!M25/Inputs!$F$247/(1-Inputs!$F$93/100) -> 0.039995062 | N13: =(Operations!N9+N8+N9)/100*Time!N25/Inputs!$F$247/(1-Inputs!$F$93/100) -> 0.040661728 | O13: =(Operations!O9+O8+O9)/100*Time!O25/Inputs!$F$247/(1-Inputs!$F$93/100) -> 0.040166358 | P13: =(Operations!P9+P8+P9)/100*Time!P25/Inputs!$F$247/(1-Inputs!$F$93/100) -> 0.040832099 | Q13: =(Operations!Q9+Q8+Q9)/100*Time!Q25/Inputs!$F$247/(1-Inputs!$F$93/100) -> 0.040278086 | ... BN13: =(Operations!BN9+BN8+BN9)/100*Time!BN25/Inputs!$F$247/(1-Inputs!$F$93/100) -> 0.046681481
