Workbook
Name Scenario: Inputs!$F$8

Sheet Cover
A1: Case R reference model: Mesa Corta Renewables portfolio (ERCOT)
A2: Case R, Mesa Corta Renewables. USD m nominal unless stated. Illustrative prices: not ERCOT settlement data and not a forecast.
B4: Owner: Lattimer Energy Transition Fund II (Lattimer Infrastructure Partners). Platform: Mesa Corta Renewables LLC; HoldCo: Mesa Corta HoldCo LLC; OpCo: Mesa Corta OpCo LLC.
B5: Assets R1-R8 (603.0 MW wind, 401.1 MWac solar, 250.0 MW / 500 MWh storage). Annual periods 2022-2059, first period in column J.
B6: Python mirror: model/case_r.py (computational source of truth). Verification: model/case_r_verification.md.
B7: Model version R-1.1; inputs_case_r.json version 1.1. Workbook saved with scenario 'base'.
B8: Switches on the Inputs sheet: Scenario (1 base, 2 low, 3 high prices and captures), volume case (1 P50, 2 P90 one-year, 3 P90 ten-year, 4 P99 one-year),
B9: refinancing switch (1 = 2025 USPP refinancing and holdco repricing, 0 = status quo), and sensitivity cells. Debt is always sized on the Operations sizing blocks (base, P50 and P99).
B10: Colors: blue on pale yellow = input; green = link from another sheet; black = calculation; Checks sheet shows 0 when passing, red when failing.
B11: Sign convention: costs and outflows stored positive on calculation sheets and subtracted explicitly.
B12: No circular references: debt sculpting uses forward discount-factor products; USPP series are solved backward from 2043; iterative calculation is off.
B13: Every Case R price is Illustrative: Case Bible illustrative price paths; not ERCOT settlement data and not a forecast.

Sheet Inputs
A1: Inputs
A2: Case R, Mesa Corta Renewables. USD m nominal unless stated. Illustrative prices: not ERCOT settlement data and not a forecast.
D4: Year | J4: =Time!J$4 | K4: =Time!K$4 | L4: =Time!L$4 | M4: =Time!M$4 | N4: =Time!N$4 | O4: =Time!O$4 | P4: =Time!P$4 | Q4: =Time!Q$4 | ... AU4: =Time!AU$4
D5: Period end | J5: =Time!J$6 | K5: =Time!K$6 | L5: =Time!L$6 | M5: =Time!M$6 | N5: =Time!N$6 | O5: =Time!O$6 | P5: =Time!P$6 | Q5: =Time!Q$6 | ... AU5: =Time!AU$6
A7: Switches
D8: Scenario (1 base, 2 low, 3 high prices and captures) | E8: index | F8: 1
D9: Volume case (1 P50, 2 P90 one-year, 3 P90 ten-year, 4 P99 one-year) | E9: index | F9: 1
D10: Refinancing switch (1 = 2025 refinancing, 0 = status quo) | E10: flag | F10: 1
D11: Sensitivity: West solar capture shift | E11: points | F11: 0
D12: Sensitivity: battery revenue low case (1 = on) | E12: flag | F12: 0
D13: Sensitivity: curtailment added | E13: % points | F13: 0
D14: Sensitivity: opex factor | E14: factor | F14: 1
D15: Sensitivity: SOFR shift on unhedged debt | E15: % points | F15: 0
D16: Sizing case price scenario (base) | E16: index | F16: 1
D17: Sizing case volume case (P50) | E17: index | F17: 1
D18: P99 sizing test volume case | E18: index | F18: 4
D19: Sensitivity value in sizing cases | E19: number | F19: 0
D20: Opex factor in sizing cases | E20: factor | F20: 1
A22: General
D23: First model year | E23: year | F23: 2022
D24: Price base year for escalation | E24: year | F24: 2022
D25: Opex inflation | E25: % pa | F25: 2.5
D26: Model end date | E26: date | F26: 58440
D27: Days per year for discounting (unit conversion) | E27: days | F27: 365
D28: Large number for MIN tests | E28: number | F28: 1000000000
D29: Debt service below which ratios are not shown | E29: USD m | F29: 0.001
D30: Standard normal z for P90 | E30: number | F30: 1.2816
D31: Standard normal z for P99 | E31: number | F31: 2.3263
D32: Years in the long-horizon P-value | E32: years | F32: 10
A34: Prices and capture (Illustrative)
D35: Hub ratio to North Hub: West Hub | E35: ratio | F35: 0.968
D36: Hub ratio to North Hub: South Hub | E36: ratio | F36: 0.991
D37: Hub ratio to North Hub: Houston Hub | E37: ratio | F37: 1.012
D38: Low case: capture decline multiplier | E38: x | F38: 1.5
D39: Low case: floor adjustment | E39: ratio | F39: -0.04
D40: High case: capture decline multiplier | E40: x | F40: 0.5
D41: Hub capture ratio 2022: west_wind | E41: ratio | F41: 0.74
D42: Hub capture decline: west_wind | E42: points pa | F42: 0.6
D43: Hub capture floor: west_wind | E43: ratio | F43: 0.62
D44: Hub-to-node basis: west_wind | E44: ratio | F44: 0.04
D45: Hub capture ratio 2022: panhandle_wind | E45: ratio | F45: 0.66
D46: Hub capture decline: panhandle_wind | E46: points pa | F46: 0.5
... D71: Curtailment from 2025: coastal_wind | E71: % | F71: 1.5
A73: Price paths (Illustrative)
D74: North Hub ATC, base (Illustrative) | E74: USD/MWh | J74: 74.6 | K74: 61.2 | L74: 30.1 | M74: 39.8 | N74: 44.6 | O74: 47.3 | P74: 49.1 | Q74: 50.4 | R74: 51.8 | S74: 52.84 | T74: 53.9 | U74: 54.98 | V74: 56.08 | W74: 57.2 | X74: 58.34 | Y74: 59.51 | Z74: 60.7 | AA74: 61.91 | AB74: 63.15 | AC74: 64.41 | AD74: 65.7 | AE74: 67.01 | AF74: 68.35 | AG74: 69.72 | AH74: 71.11 | AI74: 72.53 | AJ74: 73.98 | AK74: 75.46 | AL74: 76.97 | AM74: 78.51 | AN74: 80.08 | AO74: 81.68 | AP74: 83.31 | AQ74: 84.98 | AR74: 86.68 | AS74: 88.41 | AT74: 90.18 | AU74: 91.98
D75: North Hub ATC, low (Illustrative) | E75: USD/MWh | J75: 74.6 | K75: 61.2 | L75: 30.1 | M75: 39.8 | N75: 35.2 | O75: 36.4 | P75: 37.3 | Q75: 38 | R75: 38.6 | S75: 38.99 | T75: 39.38 | U75: 39.77 | V75: 40.17 | W75: 40.57 | X75: 40.98 | Y75: 41.39 | Z75: 41.8 | AA75: 42.22 | AB75: 42.64 | AC75: 43.07 | AD75: 43.5 | AE75: 43.94 | AF75: 44.38 | AG75: 44.82 | AH75: 45.27 | AI75: 45.72 | AJ75: 46.18 | AK75: 46.64 | AL75: 47.11 | AM75: 47.58 | AN75: 48.06 | AO75: 48.54 | AP75: 49.03 | AQ75: 49.52 | AR75: 50.02 | AS75: 50.52 | AT75: 51.03 | AU75: 51.54
D76: North Hub ATC, high (Illustrative) | E76: USD/MWh | J76: 74.6 | K76: 61.2 | L76: 30.1 | M76: 39.8 | N76: 56.3 | O76: 60.4 | P76: 63.2 | Q76: 65.1 | R76: 66.9 | S76: 68.77 | T76: 70.7 | U76: 72.68 | V76: 74.72 | W76: 76.81 | X76: 78.96 | Y76: 81.17 | Z76: 83.44 | AA76: 85.78 | AB76: 88.18 | AC76: 90.65 | AD76: 93.19 | AE76: 95.8 | AF76: 98.48 | AG76: 101.24 | AH76: 104.07 | AI76: 106.98 | AJ76: 109.98 | AK76: 113.06 | AL76: 116.23 | AM76: 119.48 | AN76: 122.83 | AO76: 126.27 | AP76: 129.81 | AQ76: 133.44 | AR76: 137.18 | AS76: 141.02 | AT76: 144.97 | AU76: 149.03
D77: Battery merchant revenue, base (Illustrative) | E77: USD/kW-yr | J77: 0 | K77: 142.5 | L77: 61.8 | M77: 52.4 | N77: 57.9 | O77: 58.77 | P77: 59.65 | Q77: 60.54 | R77: 61.45 | S77: 62.37 | T77: 63.31 | U77: 64.26 | V77: 65.22 | W77: 66.2 | X77: 67.19 | Y77: 68.2 | Z77: 69.22 | AA77: 70.26 | AB77: 71.31 | AC77: 72.38 | AD77: 73.47 | AE77: 74.57 | AF77: 75.69 | AG77: 76.83 | AH77: 77.98 | AI77: 79.15 | AJ77: 80.34 | AK77: 81.55 | AL77: 82.77 | AM77: 84.01 | AN77: 85.27 | AO77: 86.55 | AP77: 87.85 | AQ77: 89.17 | AR77: 90.51 | AS77: 91.87 | AT77: 93.25 | AU77: 94.65
D78: Battery merchant revenue, low (Illustrative) | E78: USD/kW-yr | J78: 0 | K78: 142.5 | L78: 61.8 | M78: 52.4 | N78: 39 | O78: 39.19 | P78: 39.39 | Q78: 39.59 | R78: 39.79 | S78: 39.99 | T78: 40.19 | U78: 40.39 | V78: 40.59 | W78: 40.79 | X78: 40.99 | Y78: 41.19 | Z78: 41.4 | AA78: 41.61 | AB78: 41.82 | AC78: 42.03 | AD78: 42.24 | AE78: 42.45 | AF78: 42.66 | AG78: 42.87 | AH78: 43.08 | AI78: 43.3 | AJ78: 43.52 | AK78: 43.74 | AL78: 43.96 | AM78: 44.18 | AN78: 44.4 | AO78: 44.62 | AP78: 44.84 | AQ78: 45.06 | AR78: 45.29 | AS78: 45.52 | AT78: 45.75 | AU78: 45.98
D79: Battery merchant revenue, high (Illustrative) | E79: USD/kW-yr | J79: 0 | K79: 142.5 | L79: 61.8 | M79: 52.4 | N79: 84.5 | O79: 86.61 | P79: 88.78 | Q79: 91 | R79: 93.27 | S79: 95.6 | T79: 97.99 | U79: 100.44 | V79: 102.95 | W79: 105.52 | X79: 108.16 | Y79: 110.86 | Z79: 113.63 | AA79: 116.47 | AB79: 119.38 | AC79: 122.36 | AD79: 125.42 | AE79: 128.56 | AF79: 131.77 | AG79: 135.06 | AH79: 138.44 | AI79: 141.9 | AJ79: 145.45 | AK79: 149.09 | AL79: 152.82 | AM79: 156.64 | AN79: 160.56 | AO79: 164.57 | AP79: 168.68 | AQ79: 172.9 | AR79: 177.22 | AS79: 181.65 | AT79: 186.19 | AU79: 190.84
D80: Term SOFR 3M, annual average (approximate) | E80: % | J80: 2.04 | K80: 5.17 | L80: 5.16 | M80: 4.27 | N80: 3.66 | O80: 3.45 | P80: 3.5 | Q80: 3.5 | R80: 3.5 | S80: 3.5 | T80: 3.5 | U80: 3.5 | V80: 3.5 | W80: 3.5 | X80: 3.5 | Y80: 3.5 | Z80: 3.5 | AA80: 3.5 | AB80: 3.5 | AC80: 3.5 | AD80: 3.5 | AE80: 3.5 | AF80: 3.5 | AG80: 3.5 | AH80: 3.5 | AI80: 3.5 | AJ80: 3.5 | AK80: 3.5 | AL80: 3.5 | AM80: 3.5 | AN80: 3.5 | AO80: 3.5 | AP80: 3.5 | AQ80: 3.5 | AR80: 3.5 | AS80: 3.5 | AT80: 3.5 | AU80: 3.5
D81: R3 PTC rate (2026+ held at 2025 value) | E81: USD/MWh | J81: 26 | K81: 27.5 | L81: 30 | M81: 30 | N81: 30 | O81: 30 | P81: 30 | Q81: 30 | R81: 30 | S81: 30 | T81: 30 | U81: 30 | V81: 30 | W81: 30 | X81: 30 | Y81: 30 | Z81: 30 | AA81: 30 | AB81: 30 | AC81: 30 | AD81: 30 | AE81: 30 | AF81: 30 | AG81: 30 | AH81: 30 | AI81: 30 | AJ81: 30 | AK81: 30 | AL81: 30 | AM81: 30 | AN81: 30 | AO81: 30 | AP81: 30 | AQ81: 30 | AR81: 30 | AS81: 30 | AT81: 30 | AU81: 30
D82: MACRS 5-year rates by recovery year (column J = year 1) | E82: factor | J82: 0.2 | K82: 0.32 | L82: 0.192 | M82: 0.1152 | N82: 0.1152 | O82: 0.0576 | P82: 0 | Q82: 0 | R82: 0 | S82: 0 | T82: 0 | U82: 0 | V82: 0 | W82: 0 | X82: 0 | Y82: 0 | Z82: 0 | AA82: 0 | AB82: 0 | AC82: 0 | AD82: 0 | AE82: 0 | AF82: 0 | AG82: 0 | AH82: 0 | AI82: 0 | AJ82: 0 | AK82: 0 | AL82: 0 | AM82: 0 | AN82: 0 | AO82: 0 | AP82: 0 | AQ82: 0 | AR82: 0 | AS82: 0 | AT82: 0 | AU82: 0
D83: MACRS 15-year rates by recovery year (column J = year 1) | E83: factor | J83: 0.05 | K83: 0.095 | L83: 0.0855 | M83: 0.077 | N83: 0.0693 | O83: 0.0623 | P83: 0.059 | Q83: 0.059 | R83: 0.0591 | S83: 0.059 | T83: 0.0591 | U83: 0.059 | V83: 0.0591 | W83: 0.059 | X83: 0.0591 | Y83: 0.0295 | Z83: 0 | AA83: 0 | AB83: 0 | AC83: 0 | AD83: 0 | AE83: 0 | AF83: 0 | AG83: 0 | AH83: 0 | AI83: 0 | AJ83: 0 | AK83: 0 | AL83: 0 | AM83: 0 | AN83: 0 | AO83: 0 | AP83: 0 | AQ83: 0 | AR83: 0 | AS83: 0 | AT83: 0 | AU83: 0
D84: MACRS 5-year recovery years | E84: years | F84: 6
D85: MACRS 15-year recovery years | E85: years | F85: 16
A87: Assets
D88: R1 capacity | E88: MWac | F88: 201.6
D89: R1 COD | E89: date | F89: 41988
D90: R1 useful life end | E90: date | F90: 52962
D91: R1 ownership start | E91: date | F91: 44642
D92: R1 opex (2022 prices) | E92: USD/kW-yr | F92: 41.5
D93: R1 decommissioning net of salvage (2022) | E93: USD/kW | F93: 62
D94: R1 P50 | E94: GWh/yr | F94: 695.8
D95: R1 P90 one-year | E95: % of P50 | F95: 87.6
D96: R1 P90 ten-year | E96: % of P50 | F96: 92.9
D97: R1 degradation | E97: % pa | F97: 0.2
D98: R1 P50 reference year | E98: year | F98: 2022
D99: R2 capacity | E99: MWac | F99: 248.4
... D187: Augmentation cost escalation | E187: % pa | F187: 2.5
A189: Contracts and hedges
D190: R1 swap volume (7x24) | E190: MW | F190: 40
D191: R1 swap price (West Hub) | E191: USD/MWh | F191: 48.25
D192: R1 swap start | E192: date | F192: 44927
D193: R1 swap end | E193: date | F193: 46752
D194: Hours per day (unit conversion) | E194: hours | F194: 24
D195: R2 PPA price | E195: USD/MWh | F195: 31.4
D196: R2 PPA end | E196: date | F196: 47299
D197: R3 PRS fixed payment | E197: USD m pa | F197: 25.84
D198: R3 PRS start | E198: date | F198: 43831
D199: R3 PRS end | E199: date | F199: 47483
D200: R4 shape hedge volume | E200: GWh pa | F200: 168.4
D201: R4 shape hedge price | E201: USD/MWh | F201: 44.1
... D229: PTC term | E229: years | F229: 10
A231: Operating costs and tax
D232: Wind land lease | E232: % of revenue | F232: 4
D233: Insurance step-up | E233: % | F233: 22
D234: Insurance share of opex | E234: % | F234: 15
D235: Insurance step-up year | E235: year | F235: 2023
D236: Decommissioning surety cost | E236: % of bond pa | F236: 0.6
D237: Texas margin tax rate | E237: % | F237: 0.75
D238: Texas margin tax deemed margin | E238: % of revenue | F238: 70
D239: Asset management cost (2022 prices) | E239: USD m pa | F239: 3.2
D240: Asset management cost start | E240: date | F240: 44642
D241: Federal income tax rate | E241: % | F241: 21
D242: NOL use limit | E242: % of taxable income | F242: 80
D243: Purchase price allocated to 5-year MACRS | E243: % | F243: 85
... D253: ITC basis reduction | E253: share of credit | F253: 0.5
A255: Acquisitions
D256: A1 closing | E256: date | F256: 44642
...

Sheet Time
A1: Time
A2: Case R, Mesa Corta Renewables. USD m nominal unless stated. Illustrative prices: not ERCOT settlement data and not a forecast.
D4: Year | E4: year | J4: =Inputs!$F$23 | K4: =J4+1 | L4: =K4+1 | M4: =L4+1 | N4: =M4+1 | O4: =N4+1 | P4: =O4+1 | Q4: =P4+1 | R4: =Q4+1 | ... AU4: =AT4+1
D5: Period start (prior December 31) | E5: date | J5: =DATE(J4,1,1)-1 | K5: =DATE(K4,1,1)-1 | L5: =DATE(L4,1,1)-1 | M5: =DATE(M4,1,1)-1 | N5: =DATE(N4,1,1)-1 | O5: =DATE(O4,1,1)-1 | P5: =DATE(P4,1,1)-1 | Q5: =DATE(Q4,1,1)-1 | ... AU5: =DATE(AU4,1,1)-1
D6: Period end (December 31) | E6: date | J6: =DATE(J4+1,1,1)-1 | K6: =DATE(K4+1,1,1)-1 | L6: =DATE(L4+1,1,1)-1 | M6: =DATE(M4+1,1,1)-1 | N6: =DATE(N4+1,1,1)-1 | O6: =DATE(O4+1,1,1)-1 | P6: =DATE(P4+1,1,1)-1 | Q6: =DATE(Q4+1,1,1)-1 | ... AU6: =DATE(AU4+1,1,1)-1
D7: Days in period | E7: days | J7: =J6-J5 | K7: =K6-K5 | L7: =L6-L5 | M7: =M6-M5 | N7: =N6-N5 | O7: =O6-O5 | P7: =P6-P5 | Q7: =Q6-Q5 | ... AU7: =AU6-AU5
D8: Years since price base year | E8: years | J8: =J4-Inputs!$F$24 | K8: =K4-Inputs!$F$24 | L8: =L4-Inputs!$F$24 | M8: =M4-Inputs!$F$24 | N8: =N4-Inputs!$F$24 | O8: =O4-Inputs!$F$24 | P8: =P4-Inputs!$F$24 | Q8: =Q4-Inputs!$F$24 | ... AU8: =AU4-Inputs!$F$24
D9: Opex escalation factor | E9: factor | J9: =(1+Inputs!$F$25/100)^J8 | K9: =(1+Inputs!$F$25/100)^K8 | L9: =(1+Inputs!$F$25/100)^L8 | M9: =(1+Inputs!$F$25/100)^M8 | N9: =(1+Inputs!$F$25/100)^N8 | O9: =(1+Inputs!$F$25/100)^O8 | P9: =(1+Inputs!$F$25/100)^P8 | Q9: =(1+Inputs!$F$25/100)^Q8 | ... AU9: =(1+Inputs!$F$25/100)^AU8
D10: Insurance step-up factor | E10: factor | J10: =1+Inputs!$F$234/100*Inputs!$F$233/100*(J4>=Inputs!$F$235) | K10: =1+Inputs!$F$234/100*Inputs!$F$233/100*(K4>=Inputs!$F$235) | L10: =1+Inputs!$F$234/100*Inputs!$F$233/100*(L4>=Inputs!$F$235) | M10: =1+Inputs!$F$234/100*Inputs!$F$233/100*(M4>=Inputs!$F$235) | N10: =1+Inputs!$F$234/100*Inputs!$F$233/100*(N4>=Inputs!$F$235) | O10: =1+Inputs!$F$234/100*Inputs!$F$233/100*(O4>=Inputs!$F$235) | P10: =1+Inputs!$F$234/100*Inputs!$F$233/100*(P4>=Inputs!$F$235) | Q10: =1+Inputs!$F$234/100*Inputs!$F$233/100*(Q4>=Inputs!$F$235) | ... AU10: =1+Inputs!$F$234/100*Inputs!$F$233/100*(AU4>=Inputs!$F$235)

Sheet Operations
A1: Operations: asset yield, hedges, revenue buckets, opex and cash flow
A2: Case R, Mesa Corta Renewables. USD m nominal unless stated. Illustrative prices: not ERCOT settlement data and not a forecast.
D4: Year | J4: =Time!J$4 | K4: =Time!K$4 | L4: =Time!L$4 | M4: =Time!M$4 | N4: =Time!N$4 | O4: =Time!O$4 | P4: =Time!P$4 | Q4: =Time!Q$4 | ... AU4: =Time!AU$4
D5: Period end | J5: =Time!J$6 | K5: =Time!K$6 | L5: =Time!L$6 | M5: =Time!M$6 | N5: =Time!N$6 | O5: =Time!O$6 | P5: =Time!P$6 | Q5: =Time!Q$6 | ... AU5: =Time!AU$6
A7: Yield statistics (normal; sigma_1^2 = sigma_LT^2 + sigma_IAV^2; sigma_10^2 = sigma_LT^2 + sigma_IAV^2/10)
D8: R1 sigma one-year | E8: fraction of P50 | F8: =(1-Inputs!$F$95/100)/Inputs!$F$30
D9: R1 sigma ten-year | E9: fraction of P50 | F9: =(1-Inputs!$F$96/100)/Inputs!$F$30
D10: R1 sigma inter-annual variability | E10: fraction of P50 | F10: =SQRT((Operations!$F$8^2-Operations!$F$9^2)*Inputs!$F$32/(Inputs!$F$32-1))
D11: R1 sigma long-term | E11: fraction of P50 | F11: =SQRT(Operations!$F$9^2-Operations!$F$10^2/Inputs!$F$32)
D12: R1 P99 one-year | E12: % of P50 | F12: =100*(1-Inputs!$F$31*Operations!$F$8)
D13: R1 P99 ten-year | E13: % of P50 | F13: =100*(1-Inputs!$F$31*Operations!$F$9)
D14: R2 sigma one-year | E14: fraction of P50 | F14: =(1-Inputs!$F$106/100)/Inputs!$F$30
D15: R2 sigma ten-year | E15: fraction of P50 | F15: =(1-Inputs!$F$107/100)/Inputs!$F$30
D16: R2 sigma inter-annual variability | E16: fraction of P50 | F16: =SQRT((Operations!$F$14^2-Operations!$F$15^2)*Inputs!$F$32/(Inputs!$F$32-1))
D17: R2 sigma long-term | E17: fraction of P50 | F17: =SQRT(Operations!$F$15^2-Operations!$F$16^2/Inputs!$F$32)
D18: R2 P99 one-year | E18: % of P50 | F18: =100*(1-Inputs!$F$31*Operations!$F$14)
D19: R2 P99 ten-year | E19: % of P50 | F19: =100*(1-Inputs!$F$31*Operations!$F$15)
D20: R3 sigma one-year | E20: fraction of P50 | F20: =(1-Inputs!$F$117/100)/Inputs!$F$30
D21: R3 sigma ten-year | E21: fraction of P50 | F21: =(1-Inputs!$F$118/100)/Inputs!$F$30
D22: R3 sigma inter-annual variability | E22: fraction of P50 | F22: =SQRT((Operations!$F$20^2-Operations!$F$21^2)*Inputs!$F$32/(Inputs!$F$32-1))
D23: R3 sigma long-term | E23: fraction of P50 | F23: =SQRT(Operations!$F$21^2-Operations!$F$22^2/Inputs!$F$32)
D24: R3 P99 one-year | E24: % of P50 | F24: =100*(1-Inputs!$F$31*Operations!$F$20)
D25: R3 P99 ten-year | E25: % of P50 | F25: =100*(1-Inputs!$F$31*Operations!$F$21)
D26: R4 sigma one-year | E26: fraction of P50 | F26: =(1-Inputs!$F$128/100)/Inputs!$F$30
D27: R4 sigma ten-year | E27: fraction of P50 | F27: =(1-Inputs!$F$129/100)/Inputs!$F$30
D28: R4 sigma inter-annual variability | E28: fraction of P50 | F28: =SQRT((Operations!$F$26^2-Operations!$F$27^2)*Inputs!$F$32/(Inputs!$F$32-1))
D29: R4 sigma long-term | E29: fraction of P50 | F29: =SQRT(Operations!$F$27^2-Operations!$F$28^2/Inputs!$F$32)
D30: R4 P99 one-year | E30: % of P50 | F30: =100*(1-Inputs!$F$31*Operations!$F$26)
D31: R4 P99 ten-year | E31: % of P50 | F31: =100*(1-Inputs!$F$31*Operations!$F$27)
D32: R5 sigma one-year | E32: fraction of P50 | F32: =(1-Inputs!$F$139/100)/Inputs!$F$30
D33: R5 sigma ten-year | E33: fraction of P50 | F33: =(1-Inputs!$F$140/100)/Inputs!$F$30
D34: R5 sigma inter-annual variability | E34: fraction of P50 | F34: =SQRT((Operations!$F$32^2-Operations!$F$33^2)*Inputs!$F$32/(Inputs!$F$32-1))
D35: R5 sigma long-term | E35: fraction of P50 | F35: =SQRT(Operations!$F$33^2-Operations!$F$34^2/Inputs!$F$32)
D36: R5 P99 one-year | E36: % of P50 | F36: =100*(1-Inputs!$F$31*Operations!$F$32)
D37: R5 P99 ten-year | E37: % of P50 | F37: =100*(1-Inputs!$F$31*Operations!$F$33)
D38: R8 sigma one-year | E38: fraction of P50 | F38: =(1-Inputs!$F$174/100)/Inputs!$F$30
D39: R8 sigma ten-year | E39: fraction of P50 | F39: =(1-Inputs!$F$175/100)/Inputs!$F$30
D40: R8 sigma inter-annual variability | E40: fraction of P50 | F40: =SQRT((Operations!$F$38^2-Operations!$F$39^2)*Inputs!$F$32/(Inputs!$F$32-1))
D41: R8 sigma long-term | E41: fraction of P50 | F41: =SQRT(Operations!$F$39^2-Operations!$F$40^2/Inputs!$F$32)
D42: R8 P99 one-year | E42: % of P50 | F42: =100*(1-Inputs!$F$31*Operations!$F$38)
D43: R8 P99 ten-year | E43: % of P50 | F43: =100*(1-Inputs!$F$31*Operations!$F$39)
A45: Block L: LIVE case (Inputs switches)
D46: Price scenario index | E46: index | F46: =Inputs!$F$8
D47: Volume case index | E47: index | F47: =Inputs!$F$9
D48: West solar capture shift | E48: points | F48: =Inputs!$F$11
D49: Curtailment added | E49: % points | F49: =Inputs!$F$13
D50: Opex factor | E50: factor | F50: =Inputs!$F$14
D51: Battery revenue curve index | E51: index | F51: =IF(Inputs!$F$12=1,2,Operations!$F$46)
D52: North Hub ATC | E52: USD/MWh | J52: =CHOOSE(Operations!$F$46,Inputs!J74,Inputs!J75,Inputs!J76) | K52: =CHOOSE(Operations!$F$46,Inputs!K74,Inputs!K75,Inputs!K76) | L52: =CHOOSE(Operations!$F$46,Inputs!L74,Inputs!L75,Inputs!L76) | M52: =CHOOSE(Operations!$F$46,Inputs!M74,Inputs!M75,Inputs!M76) | N52: =CHOOSE(Operations!$F$46,Inputs!N74,Inputs!N75,Inputs!N76) | O52: =CHOOSE(Operations!$F$46,Inputs!O74,Inputs!O75,Inputs!O76) | P52: =CHOOSE(Operations!$F$46,Inputs!P74,Inputs!P75,Inputs!P76) | Q52: =CHOOSE(Operations!$F$46,Inputs!Q74,Inputs!Q75,Inputs!Q76) | ... AU52: =CHOOSE(Operations!$F$46,Inputs!AU74,Inputs!AU75,Inputs!AU76)
D53: West Hub ATC | E53: USD/MWh | J53: =Operations!J52*Inputs!$F$35 | K53: =Operations!K52*Inputs!$F$35 | L53: =Operations!L52*Inputs!$F$35 | M53: =Operations!M52*Inputs!$F$35 | N53: =Operations!N52*Inputs!$F$35 | O53: =Operations!O52*Inputs!$F$35 | P53: =Operations!P52*Inputs!$F$35 | Q53: =Operations!Q52*Inputs!$F$35 | ... AU53: =Operations!AU52*Inputs!$F$35
D54: South Hub ATC | E54: USD/MWh | J54: =Operations!J52*Inputs!$F$36 | K54: =Operations!K52*Inputs!$F$36 | L54: =Operations!L52*Inputs!$F$36 | M54: =Operations!M52*Inputs!$F$36 | N54: =Operations!N52*Inputs!$F$36 | O54: =Operations!O52*Inputs!$F$36 | P54: =Operations!P52*Inputs!$F$36 | Q54: =Operations!Q52*Inputs!$F$36 | ... AU54: =Operations!AU52*Inputs!$F$36
D55: Houston Hub ATC | E55: USD/MWh | J55: =Operations!J52*Inputs!$F$37 | K55: =Operations!K52*Inputs!$F$37 | L55: =Operations!L52*Inputs!$F$37 | M55: =Operations!M52*Inputs!$F$37 | N55: =Operations!N52*Inputs!$F$37 | O55: =Operations!O52*Inputs!$F$37 | P55: =Operations!P52*Inputs!$F$37 | Q55: =Operations!Q52*Inputs!$F$37 | ... AU55: =Operations!AU52*Inputs!$F$37
D56: Battery merchant revenue | E56: USD/kW-yr | J56: =CHOOSE(Operations!$F$51,Inputs!J77,Inputs!J78,Inputs!J79) | K56: =CHOOSE(Operations!$F$51,Inputs!K77,Inputs!K78,Inputs!K79) | L56: =CHOOSE(Operations!$F$51,Inputs!L77,Inputs!L78,Inputs!L79) | M56: =CHOOSE(Operations!$F$51,Inputs!M77,Inputs!M78,Inputs!M79) | N56: =CHOOSE(Operations!$F$51,Inputs!N77,Inputs!N78,Inputs!N79) | O56: =CHOOSE(Operations!$F$51,Inputs!O77,Inputs!O78,Inputs!O79) | P56: =CHOOSE(Operations!$F$51,Inputs!P77,Inputs!P78,Inputs!P79) | Q56: =CHOOSE(Operations!$F$51,Inputs!Q77,Inputs!Q78,Inputs!Q79) | ... AU56: =CHOOSE(Operations!$F$51,Inputs!AU77,Inputs!AU78,Inputs!AU79)
D57: Hub capture ratio: west_wind | E57: ratio | J57: =MAX(Inputs!$F$43+CHOOSE(Operations!$F$46,0,Inputs!$F$39,0),Inputs!$F$41-Inputs!$F$42/100*CHOOSE(Operations!$F$46,1,Inputs!$F$38,Inputs!$F$40)*Time!J$8) | K57: =MAX(Inputs!$F$43+CHOOSE(Operations!$F$46,0,Inputs!$F$39,0),Inputs!$F$41-Inputs!$F$42/100*CHOOSE(Operations!$F$46,1,Inputs!$F$38,Inputs!$F$40)*Time!K$8) | L57: =MAX(Inputs!$F$43+CHOOSE(Operations!$F$46,0,Inputs!$F$39,0),Inputs!$F$41-Inputs!$F$42/100*CHOOSE(Operations!$F$46,1,Inputs!$F$38,Inputs!$F$40)*Time!L$8) | M57: =MAX(Inputs!$F$43+CHOOSE(Operations!$F$46,0,Inputs!$F$39,0),Inputs!$F$41-Inputs!$F$42/100*CHOOSE(Operations!$F$46,1,Inputs!$F$38,Inputs!$F$40)*Time!M$8) | N57: =MAX(Inputs!$F$43+CHOOSE(Operations!$F$46,0,Inputs!$F$39,0),Inputs!$F$41-Inputs!$F$42/100*CHOOSE(Operations!$F$46,1,Inputs!$F$38,Inputs!$F$40)*Time!N$8) | O57: =MAX(Inputs!$F$43+CHOOSE(Operations!$F$46,0,Inputs!$F$39,0),Inputs!$F$41-Inputs!$F$42/100*CHOOSE(Operations!$F$46,1,Inputs!$F$38,Inputs!$F$40)*Time!O$8) | P57: =MAX(Inputs!$F$43+CHOOSE(Operations!$F$46,0,Inputs!$F$39,0),Inputs!$F$41-Inputs!$F$42/100*CHOOSE(Operations!$F$46,1,Inputs!$F$38,Inputs!$F$40)*Time!P$8) | Q57: =MAX(Inputs!$F$43+CHOOSE(Operations!$F$46,0,Inputs!$F$39,0),Inputs!$F$41-Inputs!$F$42/100*CHOOSE(Operations!$F$46,1,Inputs!$F$38,Inputs!$F$40)*Time!Q$8) | ... AU57: =MAX(Inputs!$F$43+CHOOSE(Operations!$F$46,0,Inputs!$F$39,0),Inputs!$F$41-Inputs!$F$42/100*CHOOSE(Operations!$F$46,1,Inputs!$F$38,Inputs!$F$40)*Time!AU$8)
D58: Hub capture ratio: panhandle_wind | E58: ratio | J58: =MAX(Inputs!$F$47+CHOOSE(Operations!$F$46,0,Inputs!$F$39,0),Inputs!$F$45-Inputs!$F$46/100*CHOOSE(Operations!$F$46,1,Inputs!$F$38,Inputs!$F$40)*Time!J$8) | K58: =MAX(Inputs!$F$47+CHOOSE(Operations!$F$46,0,Inputs!$F$39,0),Inputs!$F$45-Inputs!$F$46/100*CHOOSE(Operations!$F$46,1,Inputs!$F$38,Inputs!$F$40)*Time!K$8) | L58: =MAX(Inputs!$F$47+CHOOSE(Operations!$F$46,0,Inputs!$F$39,0),Inputs!$F$45-Inputs!$F$46/100*CHOOSE(Operations!$F$46,1,Inputs!$F$38,Inputs!$F$40)*Time!L$8) | M58: =MAX(Inputs!$F$47+CHOOSE(Operations!$F$46,0,Inputs!$F$39,0),Inputs!$F$45-Inputs!$F$46/100*CHOOSE(Operations!$F$46,1,Inputs!$F$38,Inputs!$F$40)*Time!M$8) | N58: =MAX(Inputs!$F$47+CHOOSE(Operations!$F$46,0,Inputs!$F$39,0),Inputs!$F$45-Inputs!$F$46/100*CHOOSE(Operations!$F$46,1,Inputs!$F$38,Inputs!$F$40)*Time!N$8) | O58: =MAX(Inputs!$F$47+CHOOSE(Operations!$F$46,0,Inputs!$F$39,0),Inputs!$F$45-Inputs!$F$46/100*CHOOSE(Operations!$F$46,1,Inputs!$F$38,Inputs!$F$40)*Time!O$8) | P58: =MAX(Inputs!$F$47+CHOOSE(Operations!$F$46,0,Inputs!$F$39,0),Inputs!$F$45-Inputs!$F$46/100*CHOOSE(Operations!$F$46,1,Inputs!$F$38,Inputs!$F$40)*Time!P$8) | Q58: =MAX(Inputs!$F$47+CHOOSE(Operations!$F$46,0,Inputs!$F$39,0),Inputs!$F$45-Inputs!$F$46/100*CHOOSE(Operations!$F$46,1,Inputs!$F$38,Inputs!$F$40)*Time!Q$8) | ... AU58: =MAX(Inputs!$F$47+CHOOSE(Operations!$F$46,0,Inputs!$F$39,0),Inputs!$F$45-Inputs!$F$46/100*CHOOSE(Operations!$F$46,1,Inputs!$F$38,Inputs!$F$40)*Time!AU$8)
D59: Hub capture ratio: west_solar | E59: ratio | J59: =MAX(Inputs!$F$51+CHOOSE(Operations!$F$46,0,Inputs!$F$39,0),Inputs!$F$49-Inputs!$F$50/100*CHOOSE(Operations!$F$46,1,Inputs!$F$38,Inputs!$F$40)*Time!J$8)+Operations!$F$48/100 | K59: =MAX(Inputs!$F$51+CHOOSE(Operations!$F$46,0,Inputs!$F$39,0),Inputs!$F$49-Inputs!$F$50/100*CHOOSE(Operations!$F$46,1,Inputs!$F$38,Inputs!$F$40)*Time!K$8)+Operations!$F$48/100 | L59: =MAX(Inputs!$F$51+CHOOSE(Operations!$F$46,0,Inputs!$F$39,0),Inputs!$F$49-Inputs!$F$50/100*CHOOSE(Operations!$F$46,1,Inputs!$F$38,Inputs!$F$40)*Time!L$8)+Operations!$F$48/100 | M59: =MAX(Inputs!$F$51+CHOOSE(Operations!$F$46,0,Inputs!$F$39,0),Inputs!$F$49-Inputs!$F$50/100*CHOOSE(Operations!$F$46,1,Inputs!$F$38,Inputs!$F$40)*Time!M$8)+Operations!$F$48/100 | N59: =MAX(Inputs!$F$51+CHOOSE(Operations!$F$46,0,Inputs!$F$39,0),Inputs!$F$49-Inputs!$F$50/100*CHOOSE(Operations!$F$46,1,Inputs!$F$38,Inputs!$F$40)*Time!N$8)+Operations!$F$48/100 | O59: =MAX(Inputs!$F$51+CHOOSE(Operations!$F$46,0,Inputs!$F$39,0),Inputs!$F$49-Inputs!$F$50/100*CHOOSE(Operations!$F$46,1,Inputs!$F$38,Inputs!$F$40)*Time!O$8)+Operations!$F$48/100 | P59: =MAX(Inputs!$F$51+CHOOSE(Operations!$F$46,0,Inputs!$F$39,0),Inputs!$F$49-Inputs!$F$50/100*CHOOSE(Operations!$F$46,1,Inputs!$F$38,Inputs!$F$40)*Time!P$8)+Operations!$F$48/100 | Q59: =MAX(Inputs!$F$51+CHOOSE(Operations!$F$46,0,Inputs!$F$39,0),Inputs!$F$49-Inputs!$F$50/100*CHOOSE(Operations!$F$46,1,Inputs!$F$38,Inputs!$F$40)*Time!Q$8)+Operations!$F$48/100 | ... AU59: =MAX(Inputs!$F$51+CHOOSE(Operations!$F$46,0,Inputs!$F$39,0),Inputs!$F$49-Inputs!$F$50/100*CHOOSE(Operations!$F$46,1,Inputs!$F$38,Inputs!$F$40)*Time!AU$8)+Operations!$F$48/100
D60: Hub capture ratio: south_solar | E60: ratio | J60: =MAX(Inputs!$F$55+CHOOSE(Operations!$F$46,0,Inputs!$F$39,0),Inputs!$F$53-Inputs!$F$54/100*CHOOSE(Operations!$F$46,1,Inputs!$F$38,Inputs!$F$40)*Time!J$8) | K60: =MAX(Inputs!$F$55+CHOOSE(Operations!$F$46,0,Inputs!$F$39,0),Inputs!$F$53-Inputs!$F$54/100*CHOOSE(Operations!$F$46,1,Inputs!$F$38,Inputs!$F$40)*Time!K$8) | L60: =MAX(Inputs!$F$55+CHOOSE(Operations!$F$46,0,Inputs!$F$39,0),Inputs!$F$53-Inputs!$F$54/100*CHOOSE(Operations!$F$46,1,Inputs!$F$38,Inputs!$F$40)*Time!L$8) | M60: =MAX(Inputs!$F$55+CHOOSE(Operations!$F$46,0,Inputs!$F$39,0),Inputs!$F$53-Inputs!$F$54/100*CHOOSE(Operations!$F$46,1,Inputs!$F$38,Inputs!$F$40)*Time!M$8) | N60: =MAX(Inputs!$F$55+CHOOSE(Operations!$F$46,0,Inputs!$F$39,0),Inputs!$F$53-Inputs!$F$54/100*CHOOSE(Operations!$F$46,1,Inputs!$F$38,Inputs!$F$40)*Time!N$8) | O60: =MAX(Inputs!$F$55+CHOOSE(Operations!$F$46,0,Inputs!$F$39,0),Inputs!$F$53-Inputs!$F$54/100*CHOOSE(Operations!$F$46,1,Inputs!$F$38,Inputs!$F$40)*Time!O$8) | P60: =MAX(Inputs!$F$55+CHOOSE(Operations!$F$46,0,Inputs!$F$39,0),Inputs!$F$53-Inputs!$F$54/100*CHOOSE(Operations!$F$46,1,Inputs!$F$38,Inputs!$F$40)*Time!P$8) | Q60: =MAX(Inputs!$F$55+CHOOSE(Operations!$F$46,0,Inputs!$F$39,0),Inputs!$F$53-Inputs!$F$54/100*CHOOSE(Operations!$F$46,1,Inputs!$F$38,Inputs!$F$40)*Time!Q$8) | ... AU60: =MAX(Inputs!$F$55+CHOOSE(Operations!$F$46,0,Inputs!$F$39,0),Inputs!$F$53-Inputs!$F$54/100*CHOOSE(Operations!$F$46,1,Inputs!$F$38,Inputs!$F$40)*Time!AU$8)
D61: Hub capture ratio: coastal_wind | E61: ratio | J61: =MAX(Inputs!$F$59+CHOOSE(Operations!$F$46,0,Inputs!$F$39,0),Inputs!$F$57-Inputs!$F$58/100*CHOOSE(Operations!$F$46,1,Inputs!$F$38,Inputs!$F$40)*Time!J$8) | K61: =MAX(Inputs!$F$59+CHOOSE(Operations!$F$46,0,Inputs!$F$39,0),Inputs!$F$57-Inputs!$F$58/100*CHOOSE(Operations!$F$46,1,Inputs!$F$38,Inputs!$F$40)*Time!K$8) | L61: =MAX(Inputs!$F$59+CHOOSE(Operations!$F$46,0,Inputs!$F$39,0),Inputs!$F$57-Inputs!$F$58/100*CHOOSE(Operations!$F$46,1,Inputs!$F$38,Inputs!$F$40)*Time!L$8) | M61: =MAX(Inputs!$F$59+CHOOSE(Operations!$F$46,0,Inputs!$F$39,0),Inputs!$F$57-Inputs!$F$58/100*CHOOSE(Operations!$F$46,1,Inputs!$F$38,Inputs!$F$40)*Time!M$8) | N61: =MAX(Inputs!$F$59+CHOOSE(Operations!$F$46,0,Inputs!$F$39,0),Inputs!$F$57-Inputs!$F$58/100*CHOOSE(Operations!$F$46,1,Inputs!$F$38,Inputs!$F$40)*Time!N$8) | O61: =MAX(Inputs!$F$59+CHOOSE(Operations!$F$46,0,Inputs!$F$39,0),Inputs!$F$57-Inputs!$F$58/100*CHOOSE(Operations!$F$46,1,Inputs!$F$38,Inputs!$F$40)*Time!O$8) | P61: =MAX(Inputs!$F$59+CHOOSE(Operations!$F$46,0,Inputs!$F$39,0),Inputs!$F$57-Inputs!$F$58/100*CHOOSE(Operations!$F$46,1,Inputs!$F$38,Inputs!$F$40)*Time!P$8) | Q61: =MAX(Inputs!$F$59+CHOOSE(Operations!$F$46,0,Inputs!$F$39,0),Inputs!$F$57-Inputs!$F$58/100*CHOOSE(Operations!$F$46,1,Inputs!$F$38,Inputs!$F$40)*Time!Q$8) | ... AU61: =MAX(Inputs!$F$59+CHOOSE(Operations!$F$46,0,Inputs!$F$39,0),Inputs!$F$57-Inputs!$F$58/100*CHOOSE(Operations!$F$46,1,Inputs!$F$38,Inputs!$F$40)*Time!AU$8)
D62: R1 Thatcher Flats Wind (onshore wind)
D63: R1 operating fraction | E63: fraction | J63: =MAX(0,MIN(Inputs!$F$90,Time!J$6)-MAX(Inputs!$F$89,Time!J$5))/Time!J$7 | K63: =MAX(0,MIN(Inputs!$F$90,Time!K$6)-MAX(Inputs!$F$89,Time!K$5))/Time!K$7 | L63: =MAX(0,MIN(Inputs!$F$90,Time!L$6)-MAX(Inputs!$F$89,Time!L$5))/Time!L$7 | M63: =MAX(0,MIN(Inputs!$F$90,Time!M$6)-MAX(Inputs!$F$89,Time!M$5))/Time!M$7 | N63: =MAX(0,MIN(Inputs!$F$90,Time!N$6)-MAX(Inputs!$F$89,Time!N$5))/Time!N$7 | O63: =MAX(0,MIN(Inputs!$F$90,Time!O$6)-MAX(Inputs!$F$89,Time!O$5))/Time!O$7 | P63: =MAX(0,MIN(Inputs!$F$90,Time!P$6)-MAX(Inputs!$F$89,Time!P$5))/Time!P$7 | Q63: =MAX(0,MIN(Inputs!$F$90,Time!Q$6)-MAX(Inputs!$F$89,Time!Q$5))/Time!Q$7 | ... AU63: =MAX(0,MIN(Inputs!$F$90,Time!AU$6)-MAX(Inputs!$F$89,Time!AU$5))/Time!AU$7
D64: R1 owned fraction | E64: fraction | J64: =MAX(0,MIN(Inputs!$F$90,Time!J$6)-MAX(MAX(Inputs!$F$91,Inputs!$F$89),Time!J$5))/Time!J$7 | K64: =MAX(0,MIN(Inputs!$F$90,Time!K$6)-MAX(MAX(Inputs!$F$91,Inputs!$F$89),Time!K$5))/Time!K$7 | L64: =MAX(0,MIN(Inputs!$F$90,Time!L$6)-MAX(MAX(Inputs!$F$91,Inputs!$F$89),Time!L$5))/Time!L$7 | M64: =MAX(0,MIN(Inputs!$F$90,Time!M$6)-MAX(MAX(Inputs!$F$91,Inputs!$F$89),Time!M$5))/Time!M$7 | N64: =MAX(0,MIN(Inputs!$F$90,Time!N$6)-MAX(MAX(Inputs!$F$91,Inputs!$F$89),Time!N$5))/Time!N$7 | O64: =MAX(0,MIN(Inputs!$F$90,Time!O$6)-MAX(MAX(Inputs!$F$91,Inputs!$F$89),Time!O$5))/Time!O$7 | P64: =MAX(0,MIN(Inputs!$F$90,Time!P$6)-MAX(MAX(Inputs!$F$91,Inputs!$F$89),Time!P$5))/Time!P$7 | Q64: =MAX(0,MIN(Inputs!$F$90,Time!Q$6)-MAX(MAX(Inputs!$F$91,Inputs!$F$89),Time!Q$5))/Time!Q$7 | ... AU64: =MAX(0,MIN(Inputs!$F$90,Time!AU$6)-MAX(MAX(Inputs!$F$91,Inputs!$F$89),Time!AU$5))/Time!AU$7
D65: R1 owned share of operating period | E65: fraction | J65: =IF(Operations!J63>0,Operations!J64/Operations!J63,0) | K65: =IF(Operations!K63>0,Operations!K64/Operations!K63,0) | L65: =IF(Operations!L63>0,Operations!L64/Operations!L63,0) | M65: =IF(Operations!M63>0,Operations!M64/Operations!M63,0) | N65: =IF(Operations!N63>0,Operations!N64/Operations!N63,0) | O65: =IF(Operations!O63>0,Operations!O64/Operations!O63,0) | P65: =IF(Operations!P63>0,Operations!P64/Operations!P63,0) | Q65: =IF(Operations!Q63>0,Operations!Q64/Operations!Q63,0) | ... AU65: =IF(Operations!AU63>0,Operations!AU64/Operations!AU63,0)
D66: R1 own hub ATC | E66: USD/MWh | J66: =Operations!J53 | K66: =Operations!K53 | L66: =Operations!L53 | M66: =Operations!M53 | N66: =Operations!N53 | O66: =Operations!O53 | P66: =Operations!P53 | Q66: =Operations!Q53 | ... AU66: =Operations!AU53
D67: R1 volume factor | E67: factor | J67: =CHOOSE(Operations!$F$47,1,Inputs!$F$95/100,Inputs!$F$96/100,Operations!$F$12/100) | K67: =CHOOSE(Operations!$F$47,1,Inputs!$F$95/100,Inputs!$F$96/100,Operations!$F$12/100) | L67: =CHOOSE(Operations!$F$47,1,Inputs!$F$95/100,Inputs!$F$96/100,Operations!$F$12/100) | M67: =CHOOSE(Operations!$F$47,1,Inputs!$F$95/100,Inputs!$F$96/100,Operations!$F$12/100) | N67: =CHOOSE(Operations!$F$47,1,Inputs!$F$95/100,Inputs!$F$96/100,Operations!$F$12/100) | O67: =CHOOSE(Operations!$F$47,1,Inputs!$F$95/100,Inputs!$F$96/100,Operations!$F$12/100) | P67: =CHOOSE(Operations!$F$47,1,Inputs!$F$95/100,Inputs!$F$96/100,Operations!$F$12/100) | Q67: =CHOOSE(Operations!$F$47,1,Inputs!$F$95/100,Inputs!$F$96/100,Operations!$F$12/100) | ... AU67: =CHOOSE(Operations!$F$47,1,Inputs!$F$95/100,Inputs!$F$96/100,Operations!$F$12/100)
D68: R1 degradation factor | E68: factor | J68: =(1-Inputs!$F$97/100)^MAX(0,Time!J$4-Inputs!$F$98) | K68: =(1-Inputs!$F$97/100)^MAX(0,Time!K$4-Inputs!$F$98) | L68: =(1-Inputs!$F$97/100)^MAX(0,Time!L$4-Inputs!$F$98) | M68: =(1-Inputs!$F$97/100)^MAX(0,Time!M$4-Inputs!$F$98) | N68: =(1-Inputs!$F$97/100)^MAX(0,Time!N$4-Inputs!$F$98) | O68: =(1-Inputs!$F$97/100)^MAX(0,Time!O$4-Inputs!$F$98) | P68: =(1-Inputs!$F$97/100)^MAX(0,Time!P$4-Inputs!$F$98) | Q68: =(1-Inputs!$F$97/100)^MAX(0,Time!Q$4-Inputs!$F$98) | ... AU68: =(1-Inputs!$F$97/100)^MAX(0,Time!AU$4-Inputs!$F$98)
D69: R1 curtailment | E69: fraction | J69: =(IF(Time!J$4>=Inputs!$F$61,Inputs!$F$63,Inputs!$F$62+(Inputs!$F$63-Inputs!$F$62)*(Time!J$4-Inputs!$F$23)/(Inputs!$F$61-Inputs!$F$23))+Operations!$F$49)/100 | K69: =(IF(Time!K$4>=Inputs!$F$61,Inputs!$F$63,Inputs!$F$62+(Inputs!$F$63-Inputs!$F$62)*(Time!K$4-Inputs!$F$23)/(Inputs!$F$61-Inputs!$F$23))+Operations!$F$49)/100 | L69: =(IF(Time!L$4>=Inputs!$F$61,Inputs!$F$63,Inputs!$F$62+(Inputs!$F$63-Inputs!$F$62)*(Time!L$4-Inputs!$F$23)/(Inputs!$F$61-Inputs!$F$23))+Operations!$F$49)/100 | M69: =(IF(Time!M$4>=Inputs!$F$61,Inputs!$F$63,Inputs!$F$62+(Inputs!$F$63-Inputs!$F$62)*(Time!M$4-Inputs!$F$23)/(Inputs!$F$61-Inputs!$F$23))+Operations!$F$49)/100 | N69: =(IF(Time!N$4>=Inputs!$F$61,Inputs!$F$63,Inputs!$F$62+(Inputs!$F$63-Inputs!$F$62)*(Time!N$4-Inputs!$F$23)/(Inputs!$F$61-Inputs!$F$23))+Operations!$F$49)/100 | O69: =(IF(Time!O$4>=Inputs!$F$61,Inputs!$F$63,Inputs!$F$62+(Inputs!$F$63-Inputs!$F$62)*(Time!O$4-Inputs!$F$23)/(Inputs!$F$61-Inputs!$F$23))+Operations!$F$49)/100 | P69: =(IF(Time!P$4>=Inputs!$F$61,Inputs!$F$63,Inputs!$F$62+(Inputs!$F$63-Inputs!$F$62)*(Time!P$4-Inputs!$F$23)/(Inputs!$F$61-Inputs!$F$23))+Operations!$F$49)/100 | Q69: =(IF(Time!Q$4>=Inputs!$F$61,Inputs!$F$63,Inputs!$F$62+(Inputs!$F$63-Inputs!$F$62)*(Time!Q$4-Inputs!$F$23)/(Inputs!$F$61-Inputs!$F$23))+Operations!$F$49)/100 | ... AU69: =(IF(Time!AU$4>=Inputs!$F$61,Inputs!$F$63,Inputs!$F$62+(Inputs!$F$63-Inputs!$F$62)*(Time!AU$4-Inputs!$F$23)/(Inputs!$F$61-Inputs!$F$23))+Operations!$F$49)/100
D70: R1 net generation, full year | E70: GWh | J70: =Inputs!$F$94*Operations!J67*Inputs!$F$185/100*Operations!J68*(1-Operations!J69) | K70: =Inputs!$F$94*Operations!K67*Inputs!$F$185/100*Operations!K68*(1-Operations!K69) | L70: =Inputs!$F$94*Operations!L67*Inputs!$F$185/100*Operations!L68*(1-Operations!L69) | M70: =Inputs!$F$94*Operations!M67*Inputs!$F$185/100*Operations!M68*(1-Operations!M69) | N70: =Inputs!$F$94*Operations!N67*Inputs!$F$185/100*Operations!N68*(1-Operations!N69) | O70: =Inputs!$F$94*Operations!O67*Inputs!$F$185/100*Operations!O68*(1-Operations!O69) | P70: =Inputs!$F$94*Operations!P67*Inputs!$F$185/100*Operations!P68*(1-Operations!P69) | Q70: =Inputs!$F$94*Operations!Q67*Inputs!$F$185/100*Operations!Q68*(1-Operations!Q69) | ... AU70: =Inputs!$F$94*Operations!AU67*Inputs!$F$185/100*Operations!AU68*(1-Operations!AU69)
D71: R1 net generation | E71: GWh | G71: =SUM(J71:AU71) | J71: =Operations!J70*Operations!J63 | K71: =Operations!K70*Operations!K63 | L71: =Operations!L70*Operations!L63 | M71: =Operations!M70*Operations!M63 | N71: =Operations!N70*Operations!N63 | O71: =Operations!O70*Operations!O63 | P71: =Operations!P70*Operations!P63 | Q71: =Operations!Q70*Operations!Q63 | ... AU71: =Operations!AU70*Operations!AU63
D72: R1 hub capture ratio | E72: ratio | J72: =Operations!J57 | K72: =Operations!K57 | L72: =Operations!L57 | M72: =Operations!M57 | N72: =Operations!N57 | O72: =Operations!O57 | P72: =Operations!P57 | Q72: =Operations!Q57 | ... AU72: =Operations!AU57
D73: R1 node capture ratio | E73: ratio | J73: =Operations!J72-Inputs!$F$44 | K73: =Operations!K72-Inputs!$F$44 | L73: =Operations!L72-Inputs!$F$44 | M73: =Operations!M72-Inputs!$F$44 | N73: =Operations!N72-Inputs!$F$44 | O73: =Operations!O72-Inputs!$F$44 | P73: =Operations!P72-Inputs!$F$44 | Q73: =Operations!Q72-Inputs!$F$44 | ... AU73: =Operations!AU72-Inputs!$F$44
D74: R1 realized node price | E74: USD/MWh | J74: =Operations!J66*Operations!J73 | K74: =Operations!K66*Operations!K73 | L74: =Operations!L66*Operations!L73 | M74: =Operations!M66*Operations!M73 | N74: =Operations!N66*Operations!N73 | O74: =Operations!O66*Operations!O73 | P74: =Operations!P66*Operations!P73 | Q74: =Operations!Q66*Operations!Q73 | ... AU74: =Operations!AU66*Operations!AU73
D75: R1 swap term fraction | E75: fraction | J75: =MAX(0,MIN(Inputs!$F$193,Time!J$6)-MAX(Inputs!$F$192-1,Time!J$5))/Time!J$7 | K75: =MAX(0,MIN(Inputs!$F$193,Time!K$6)-MAX(Inputs!$F$192-1,Time!K$5))/Time!K$7 | L75: =MAX(0,MIN(Inputs!$F$193,Time!L$6)-MAX(Inputs!$F$192-1,Time!L$5))/Time!L$7 | M75: =MAX(0,MIN(Inputs!$F$193,Time!M$6)-MAX(Inputs!$F$192-1,Time!M$5))/Time!M$7 | N75: =MAX(0,MIN(Inputs!$F$193,Time!N$6)-MAX(Inputs!$F$192-1,Time!N$5))/Time!N$7 | O75: =MAX(0,MIN(Inputs!$F$193,Time!O$6)-MAX(Inputs!$F$192-1,Time!O$5))/Time!O$7 | P75: =MAX(0,MIN(Inputs!$F$193,Time!P$6)-MAX(Inputs!$F$192-1,Time!P$5))/Time!P$7 | Q75: =MAX(0,MIN(Inputs!$F$193,Time!Q$6)-MAX(Inputs!$F$192-1,Time!Q$5))/Time!Q$7 | ... AU75: =MAX(0,MIN(Inputs!$F$193,Time!AU$6)-MAX(Inputs!$F$192-1,Time!AU$5))/Time!AU$7
D76: R1 swap volume | E76: GWh | J76: =Inputs!$F$190*Time!J$7*Inputs!$F$194/1000*Operations!J75 | K76: =Inputs!$F$190*Time!K$7*Inputs!$F$194/1000*Operations!K75 | L76: =Inputs!$F$190*Time!L$7*Inputs!$F$194/1000*Operations!L75 | M76: =Inputs!$F$190*Time!M$7*Inputs!$F$194/1000*Operations!M75 | N76: =Inputs!$F$190*Time!N$7*Inputs!$F$194/1000*Operations!N75 | O76: =Inputs!$F$190*Time!O$7*Inputs!$F$194/1000*Operations!O75 | P76: =Inputs!$F$190*Time!P$7*Inputs!$F$194/1000*Operations!P75 | Q76: =Inputs!$F$190*Time!Q$7*Inputs!$F$194/1000*Operations!Q75 | ... AU76: =Inputs!$F$190*Time!AU$7*Inputs!$F$194/1000*Operations!AU75
D77: R1 swap settlement (receive fixed, pay West Hub) | E77: USD m | G77: =SUM(J77:AU77) | J77: =Operations!J76*(Inputs!$F$191-Operations!J66)/1000 | K77: =Operations!K76*(Inputs!$F$191-Operations!K66)/1000 | L77: =Operations!L76*(Inputs!$F$191-Operations!L66)/1000 | M77: =Operations!M76*(Inputs!$F$191-Operations!M66)/1000 | N77: =Operations!N76*(Inputs!$F$191-Operations!N66)/1000 | O77: =Operations!O76*(Inputs!$F$191-Operations!O66)/1000 | P77: =Operations!P76*(Inputs!$F$191-Operations!P66)/1000 | Q77: =Operations!Q76*(Inputs!$F$191-Operations!Q66)/1000 | ... AU77: =Operations!AU76*(Inputs!$F$191-Operations!AU66)/1000
D78: R1 generation sold at node | E78: GWh | J78: =Operations!J71 | K78: =Operations!K71 | L78: =Operations!L71 | M78: =Operations!M71 | N78: =Operations!N71 | O78: =Operations!O71 | P78: =Operations!P71 | Q78: =Operations!Q71 | ... AU78: =Operations!AU71
D79: R1 contracted revenue | E79: USD m | J79: =0 | K79: =0 | L79: =0 | M79: =0 | N79: =0 | O79: =0 | P79: =0 | Q79: =0 | ... AU79: =0
D80: R1 hedged revenue (swap volume x price) | E80: USD m | J80: =Operations!J76*Inputs!$F$191/1000 | K80: =Operations!K76*Inputs!$F$191/1000 | L80: =Operations!L76*Inputs!$F$191/1000 | M80: =Operations!M76*Inputs!$F$191/1000 | N80: =Operations!N76*Inputs!$F$191/1000 | O80: =Operations!O76*Inputs!$F$191/1000 | P80: =Operations!P76*Inputs!$F$191/1000 | Q80: =Operations!Q76*Inputs!$F$191/1000 | ... AU80: =Operations!AU76*Inputs!$F$191/1000
D81: R1 market revenue at node | E81: USD m | G81: =SUM(J81:AU81) | J81: =Operations!J78*Operations!J74/1000 | K81: =Operations!K78*Operations!K74/1000 | L81: =Operations!L78*Operations!L74/1000 | M81: =Operations!M78*Operations!M74/1000 | N81: =Operations!N78*Operations!N74/1000 | O81: =Operations!O78*Operations!O74/1000 | P81: =Operations!P78*Operations!P74/1000 | Q81: =Operations!Q78*Operations!Q74/1000 | ... AU81: =Operations!AU78*Operations!AU74/1000
D82: R1 total revenue | E82: USD m | G82: =SUM(J82:AU82) | J82: =Operations!J81+Operations!J77 | K82: =Operations!K81+Operations!K77 | L82: =Operations!L81+Operations!L77 | M82: =Operations!M81+Operations!M77 | N82: =Operations!N81+Operations!N77 | O82: =Operations!O81+Operations!O77 | P82: =Operations!P81+Operations!P77 | Q82: =Operations!Q81+Operations!Q77 | ... AU82: =Operations!AU81+Operations!AU77
D83: R1 merchant revenue (total less contracted and hedged) | E83: USD m | J83: =Operations!J82-Operations!J79-Operations!J80 | K83: =Operations!K82-Operations!K79-Operations!K80 | L83: =Operations!L82-Operations!L79-Operations!L80 | M83: =Operations!M82-Operations!M79-Operations!M80 | N83: =Operations!N82-Operations!N79-Operations!N80 | O83: =Operations!O82-Operations!O79-Operations!O80 | P83: =Operations!P82-Operations!P79-Operations!P80 | Q83: =Operations!Q82-Operations!Q79-Operations!Q80 | ... AU83: =Operations!AU82-Operations!AU79-Operations!AU80
D84: R1 opex (O&M, land, insurance, property tax, site) | E84: USD m | J84: =Inputs!$F$92*Inputs!$F$88/1000*Time!J$9*Time!J$10*Operations!J63*Operations!$F$50 | K84: =Inputs!$F$92*Inputs!$F$88/1000*Time!K$9*Time!K$10*Operations!K63*Operations!$F$50 | L84: =Inputs!$F$92*Inputs!$F$88/1000*Time!L$9*Time!L$10*Operations!L63*Operations!$F$50 | M84: =Inputs!$F$92*Inputs!$F$88/1000*Time!M$9*Time!M$10*Operations!M63*Operations!$F$50 | N84: =Inputs!$F$92*Inputs!$F$88/1000*Time!N$9*Time!N$10*Operations!N63*Operations!$F$50 | O84: =Inputs!$F$92*Inputs!$F$88/1000*Time!O$9*Time!O$10*Operations!O63*Operations!$F$50 | P84: =Inputs!$F$92*Inputs!$F$88/1000*Time!P$9*Time!P$10*Operations!P63*Operations!$F$50 | Q84: =Inputs!$F$92*Inputs!$F$88/1000*Time!Q$9*Time!Q$10*Operations!Q63*Operations!$F$50 | ... AU84: =Inputs!$F$92*Inputs!$F$88/1000*Time!AU$9*Time!AU$10*Operations!AU63*Operations!$F$50
D85: R1 wind land lease | E85: USD m | J85: =Inputs!$F$232/100*Operations!J82 | K85: =Inputs!$F$232/100*Operations!K82 | L85: =Inputs!$F$232/100*Operations!L82 | M85: =Inputs!$F$232/100*Operations!M82 | N85: =Inputs!$F$232/100*Operations!N82 | O85: =Inputs!$F$232/100*Operations!O82 | P85: =Inputs!$F$232/100*Operations!P82 | Q85: =Inputs!$F$232/100*Operations!Q82 | ... AU85: =Inputs!$F$232/100*Operations!AU82
D86: R1 decommissioning surety cost | E86: USD m | J86: =Inputs!$F$236/100*Inputs!$F$93*Inputs!$F$88/1000*Time!J$9*Operations!J63 | K86: =Inputs!$F$236/100*Inputs!$F$93*Inputs!$F$88/1000*Time!K$9*Operations!K63 | L86: =Inputs!$F$236/100*Inputs!$F$93*Inputs!$F$88/1000*Time!L$9*Operations!L63 | M86: =Inputs!$F$236/100*Inputs!$F$93*Inputs!$F$88/1000*Time!M$9*Operations!M63 | N86: =Inputs!$F$236/100*Inputs!$F$93*Inputs!$F$88/1000*Time!N$9*Operations!N63 | O86: =Inputs!$F$236/100*Inputs!$F$93*Inputs!$F$88/1000*Time!O$9*Operations!O63 | P86: =Inputs!$F$236/100*Inputs!$F$93*Inputs!$F$88/1000*Time!P$9*Operations!P63 | Q86: =Inputs!$F$236/100*Inputs!$F$93*Inputs!$F$88/1000*Time!Q$9*Operations!Q63 | ... AU86: =Inputs!$F$236/100*Inputs!$F$93*Inputs!$F$88/1000*Time!AU$9*Operations!AU63
D87: R1 Texas margin tax | E87: USD m | J87: =Inputs!$F$237/100*Inputs!$F$238/100*Operations!J82 | K87: =Inputs!$F$237/100*Inputs!$F$238/100*Operations!K82 | L87: =Inputs!$F$237/100*Inputs!$F$238/100*Operations!L82 | M87: =Inputs!$F$237/100*Inputs!$F$238/100*Operations!M82 | N87: =Inputs!$F$237/100*Inputs!$F$238/100*Operations!N82 | O87: =Inputs!$F$237/100*Inputs!$F$238/100*Operations!O82 | P87: =Inputs!$F$237/100*Inputs!$F$238/100*Operations!P82 | Q87: =Inputs!$F$237/100*Inputs!$F$238/100*Operations!Q82 | ... AU87: =Inputs!$F$237/100*Inputs!$F$238/100*Operations!AU82
D88: R1 EBITDA | E88: USD m | G88: =SUM(J88:AU88) | J88: =Operations!J82-Operations!J84-Operations!J85-Operations!J86-Operations!J87 | K88: =Operations!K82-Operations!K84-Operations!K85-Operations!K86-Operations!K87 | L88: =Operations!L82-Operations!L84-Operations!L85-Operations!L86-Operations!L87 | M88: =Operations!M82-Operations!M84-Operations!M85-Operations!M86-Operations!M87 | N88: =Operations!N82-Operations!N84-Operations!N85-Operations!N86-Operations!N87 | O88: =Operations!O82-Operations!O84-Operations!O85-Operations!O86-Operations!O87 | P88: =Operations!P82-Operations!P84-Operations!P85-Operations!P86-Operations!P87 | Q88: =Operations!Q82-Operations!Q84-Operations!Q85-Operations!Q86-Operations!Q87 | ... AU88: =Operations!AU82-Operations!AU84-Operations!AU85-Operations!AU86-Operations!AU87
D89: R1 capex | E89: USD m | J89: =0 | K89: =0 | L89: =0 | M89: =0 | N89: =0 | O89: =0 | P89: =0 | Q89: =0 | ... AU89: =0
D90: R1 decommissioning at end of life | E90: USD m | J90: =IF(Time!J$4=YEAR(Inputs!$F$90),Inputs!$F$93*Inputs!$F$88/1000*Time!J$9,0) | K90: =IF(Time!K$4=YEAR(Inputs!$F$90),Inputs!$F$93*Inputs!$F$88/1000*Time!K$9,0) | L90: =IF(Time!L$4=YEAR(Inputs!$F$90),Inputs!$F$93*Inputs!$F$88/1000*Time!L$9,0) | M90: =IF(Time!M$4=YEAR(Inputs!$F$90),Inputs!$F$93*Inputs!$F$88/1000*Time!M$9,0) | N90: =IF(Time!N$4=YEAR(Inputs!$F$90),Inputs!$F$93*Inputs!$F$88/1000*Time!N$9,0) | O90: =IF(Time!O$4=YEAR(Inputs!$F$90),Inputs!$F$93*Inputs!$F$88/1000*Time!O$9,0) | P90: =IF(Time!P$4=YEAR(Inputs!$F$90),Inputs!$F$93*Inputs!$F$88/1000*Time!P$9,0) | Q90: =IF(Time!Q$4=YEAR(Inputs!$F$90),Inputs!$F$93*Inputs!$F$88/1000*Time!Q$9,0) | ... AU90: =IF(Time!AU$4=YEAR(Inputs!$F$90),Inputs!$F$93*Inputs!$F$88/1000*Time!AU$9,0)
D91: R1 pre-tax cash flow, 100% of asset | E91: USD m | G91: =SUM(J91:AU91) | J91: =Operations!J88-Operations!J89-Operations!J90 | K91: =Operations!K88-Operations!K89-Operations!K90 | L91: =Operations!L88-Operations!L89-Operations!L90 | M91: =Operations!M88-Operations!M89-Operations!M90 | N91: =Operations!N88-Operations!N89-Operations!N90 | O91: =Operations!O88-Operations!O89-Operations!O90 | P91: =Operations!P88-Operations!P89-Operations!P90 | Q91: =Operations!Q88-Operations!Q89-Operations!Q90 | ... AU91: =Operations!AU88-Operations!AU89-Operations!AU90
D92: R1 tax equity cash share | E92: fraction | J92: =0 | K92: =0 | L92: =0 | M92: =0 | N92: =0 | O92: =0 | P92: =0 | Q92: =0 | ... AU92: =0
D93: R1 Mesa share of taxable income | E93: fraction | J93: =1 | K93: =1 | L93: =1 | M93: =1 | N93: =1 | O93: =1 | P93: =1 | Q93: =1 | ... AU93: =1
D94: R1 Mesa share of cash flow | E94: USD m | G94: =SUM(J94:AU94) | J94: =Operations!J91*(1-Operations!J92)*Operations!J65 | K94: =Operations!K91*(1-Operations!K92)*Operations!K65 | L94: =Operations!L91*(1-Operations!L92)*Operations!L65 | M94: =Operations!M91*(1-Operations!M92)*Operations!M65 | N94: =Operations!N91*(1-Operations!N92)*Operations!N65 | O94: =Operations!O91*(1-Operations!O92)*Operations!O65 | P94: =Operations!P91*(1-Operations!P92)*Operations!P65 | Q94: =Operations!Q91*(1-Operations!Q92)*Operations!Q65 | ... AU94: =Operations!AU91*(1-Operations!AU92)*Operations!AU65
D95: R1 Mesa taxable operating income | E95: USD m | J95: =Operations!J91*Operations!J93*Operations!J65 | K95: =Operations!K91*Operations!K93*Operations!K65 | L95: =Operations!L91*Operations!L93*Operations!L65 | M95: =Operations!M91*Operations!M93*Operations!M65 | N95: =Operations!N91*Operations!N93*Operations!N65 | O95: =Operations!O91*Operations!O93*Operations!O65 | P95: =Operations!P91*Operations!P93*Operations!P65 | Q95: =Operations!Q91*Operations!Q93*Operations!Q65 | ... AU95: =Operations!AU91*Operations!AU93*Operations!AU65
D96: R1 Mesa unlevered post-tax cash flow (before price shield) | E96: USD m | J96: =Operations!J94-Inputs!$F$241/100*Operations!J95 | K96: =Operations!K94-Inputs!$F$241/100*Operations!K95 | L96: =Operations!L94-Inputs!$F$241/100*Operations!L95 | M96: =Operations!M94-Inputs!$F$241/100*Operations!M95 | N96: =Operations!N94-Inputs!$F$241/100*Operations!N95 | O96: =Operations!O94-Inputs!$F$241/100*Operations!O95 | P96: =Operations!P94-Inputs!$F$241/100*Operations!P95 | Q96: =Operations!Q94-Inputs!$F$241/100*Operations!Q95 | ... AU96: =Operations!AU94-Inputs!$F$241/100*Operations!AU95
D97: R1 contracted share of revenue | E97: fraction | J97: =IF(Operations!J82=0,0,Operations!J79/Operations!J82) | K97: =IF(Operations!K82=0,0,Operations!K79/Operations!K82) | L97: =IF(Operations!L82=0,0,Operations!L79/Operations!L82) | M97: =IF(Operations!M82=0,0,Operations!M79/Operations!M82) | N97: =IF(Operations!N82=0,0,Operations!N79/Operations!N82) | O97: =IF(Operations!O82=0,0,Operations!O79/Operations!O82) | P97: =IF(Operations!P82=0,0,Operations!P79/Operations!P82) | Q97: =IF(Operations!Q82=0,0,Operations!Q79/Operations!Q82) | ... AU97: =IF(Operations!AU82=0,0,Operations!AU79/Operations!AU82)
D98: R1 hedged share of revenue | E98: fraction | J98: =IF(Operations!J82=0,0,Operations!J80/Operations!J82) | K98: =IF(Operations!K82=0,0,Operations!K80/Operations!K82) | L98: =IF(Operations!L82=0,0,Operations!L80/Operations!L82) | M98: =IF(Operations!M82=0,0,Operations!M80/Operations!M82) | N98: =IF(Operations!N82=0,0,Operations!N80/Operations!N82) | O98: =IF(Operations!O82=0,0,Operations!O80/Operations!O82) | P98: =IF(Operations!P82=0,0,Operations!P80/Operations!P82) | Q98: =IF(Operations!Q82=0,0,Operations!Q80/Operations!Q82) | ... AU98: =IF(Operations!AU82=0,0,Operations!AU80/Operations!AU82)
D99: R1 merchant share of revenue | E99: fraction | J99: =1-Operations!J97-Operations!J98 | K99: =1-Operations!K97-Operations!K98 | L99: =1-Operations!L97-Operations!L98 | M99: =1-Operations!M97-Operations!M98 | N99: =1-Operations!N97-Operations!N98 | O99: =1-Operations!O97-Operations!O98 | P99: =1-Operations!P97-Operations!P98 | Q99: =1-Operations!Q97-Operations!Q98 | ... AU99: =1-Operations!AU97-Operations!AU98
D100: R1 Mesa-share contracted revenue | E100: USD m | J100: =Operations!J79*Operations!J65*(1-Operations!J92) | K100: =Operations!K79*Operations!K65*(1-Operations!K92) | L100: =Operations!L79*Operations!L65*(1-Operations!L92) | M100: =Operations!M79*Operations!M65*(1-Operations!M92) | N100: =Operations!N79*Operations!N65*(1-Operations!N92) | O100: =Operations!O79*Operations!O65*(1-Operations!O92) | P100: =Operations!P79*Operations!P65*(1-Operations!P92) | Q100: =Operations!Q79*Operations!Q65*(1-Operations!Q92) | ... AU100: =Operations!AU79*Operations!AU65*(1-Operations!AU92)
D101: R1 Mesa-share hedged revenue | E101: USD m | J101: =Operations!J80*Operations!J65*(1-Operations!J92) | K101: =Operations!K80*Operations!K65*(1-Operations!K92) | L101: =Operations!L80*Operations!L65*(1-Operations!L92) | M101: =Operations!M80*Operations!M65*(1-Operations!M92) | N101: =Operations!N80*Operations!N65*(1-Operations!N92) | O101: =Operations!O80*Operations!O65*(1-Operations!O92) | P101: =Operations!P80*Operations!P65*(1-Operations!P92) | Q101: =Operations!Q80*Operations!Q65*(1-Operations!Q92) | ... AU101: =Operations!AU80*Operations!AU65*(1-Operations!AU92)
D102: R1 Mesa-share merchant revenue | E102: USD m | J102: =Operations!J83*Operations!J65*(1-Operations!J92) | K102: =Operations!K83*Operations!K65*(1-Operations!K92) | L102: =Operations!L83*Operations!L65*(1-Operations!L92) | M102: =Operations!M83*Operations!M65*(1-Operations!M92) | N102: =Operations!N83*Operations!N65*(1-Operations!N92) | O102: =Operations!O83*Operations!O65*(1-Operations!O92) | P102: =Operations!P83*Operations!P65*(1-Operations!P92) | Q102: =Operations!Q83*Operations!Q65*(1-Operations!Q92) | ... AU102: =Operations!AU83*Operations!AU65*(1-Operations!AU92)
D103: R1 Mesa-share revenue | E103: USD m | J103: =Operations!J82*Operations!J65*(1-Operations!J92) | K103: =Operations!K82*Operations!K65*(1-Operations!K92) | L103: =Operations!L82*Operations!L65*(1-Operations!L92) | M103: =Operations!M82*Operations!M65*(1-Operations!M92) | N103: =Operations!N82*Operations!N65*(1-Operations!N92) | O103: =Operations!O82*Operations!O65*(1-Operations!O92) | P103: =Operations!P82*Operations!P65*(1-Operations!P92) | Q103: =Operations!Q82*Operations!Q65*(1-Operations!Q92) | ... AU103: =Operations!AU82*Operations!AU65*(1-Operations!AU92)
...

Sheet Tax
A1: Tax: depreciation of purchase prices, taxable income, NOL and cash tax
A2: Case R, Mesa Corta Renewables. USD m nominal unless stated. Illustrative prices: not ERCOT settlement data and not a forecast.
D4: Year | J4: =Time!J$4 | K4: =Time!K$4 | L4: =Time!L$4 | M4: =Time!M$4 | N4: =Time!N$4 | O4: =Time!O$4 | P4: =Time!P$4 | Q4: =Time!Q$4 | ... AU4: =Time!AU$4
D5: Period end | J5: =Time!J$6 | K5: =Time!K$6 | L5: =Time!L$6 | M5: =Time!M$6 | N5: =Time!N$6 | O5: =Time!O$6 | P5: =Time!P$6 | Q5: =Time!Q$6 | ... AU5: =Time!AU$6
A7: ITC on R7 and R8 (claimed by the fund and transferred)
D8: R7 ITC | E8: USD m | F8: =Inputs!$F$248/100*Inputs!$F$249/100*Inputs!$F$263
D9: R8 ITC | E9: USD m | F9: =Inputs!$F$250/100*Inputs!$F$251/100*Inputs!$F$264
A11: Tax depreciation (bonus in acquisition year, MACRS half-year on the remainder)
D12: Depreciable basis, A1 | E12: USD m | F12: =Inputs!$F$257
D13: Recovery year index, A1 | E13: years | J13: =Time!J$4-YEAR(Inputs!$F$256) | K13: =Time!K$4-YEAR(Inputs!$F$256) | L13: =Time!L$4-YEAR(Inputs!$F$256) | M13: =Time!M$4-YEAR(Inputs!$F$256) | N13: =Time!N$4-YEAR(Inputs!$F$256) | O13: =Time!O$4-YEAR(Inputs!$F$256) | P13: =Time!P$4-YEAR(Inputs!$F$256) | Q13: =Time!Q$4-YEAR(Inputs!$F$256) | ... AU13: =Time!AU$4-YEAR(Inputs!$F$256)
D14: Tax depreciation, A1 | E14: USD m | G14: =SUM(J14:AU14) | J14: =Tax!$F$12*(Inputs!$F$243/100+Inputs!$F$244/100)*(IF(Tax!J13=0,Inputs!$F$245/100,0)+(1-Inputs!$F$245/100)*IF(AND(Tax!J13>=0,Tax!J13<Inputs!$F$84),INDEX(Inputs!$J$82:$AU$82,Tax!J13+1),0))+Tax!$F$12*Inputs!$F$244/100*(IF(Tax!J13=0,0,0))+Tax!$F$12*Inputs!$F$244/100*(1-Inputs!$F$245/100)*(IF(AND(Tax!J13>=0,Tax!J13<Inputs!$F$85),INDEX(Inputs!$J$83:$AU$83,Tax!J13+1),0)-IF(AND(Tax!J13>=0,Tax!J13<Inputs!$F$84),INDEX(Inputs!$J$82:$AU$82,Tax!J13+1),0)) | K14: =Tax!$F$12*(Inputs!$F$243/100+Inputs!$F$244/100)*(IF(Tax!K13=0,Inputs!$F$245/100,0)+(1-Inputs!$F$245/100)*IF(AND(Tax!K13>=0,Tax!K13<Inputs!$F$84),INDEX(Inputs!$J$82:$AU$82,Tax!K13+1),0))+Tax!$F$12*Inputs!$F$244/100*(IF(Tax!K13=0,0,0))+Tax!$F$12*Inputs!$F$244/100*(1-Inputs!$F$245/100)*(IF(AND(Tax!K13>=0,Tax!K13<Inputs!$F$85),INDEX(Inputs!$J$83:$AU$83,Tax!K13+1),0)-IF(AND(Tax!K13>=0,Tax!K13<Inputs!$F$84),INDEX(Inputs!$J$82:$AU$82,Tax!K13+1),0)) | L14: =Tax!$F$12*(Inputs!$F$243/100+Inputs!$F$244/100)*(IF(Tax!L13=0,Inputs!$F$245/100,0)+(1-Inputs!$F$245/100)*IF(AND(Tax!L13>=0,Tax!L13<Inputs!$F$84),INDEX(Inputs!$J$82:$AU$82,Tax!L13+1),0))+Tax!$F$12*Inputs!$F$244/100*(IF(Tax!L13=0,0,0))+Tax!$F$12*Inputs!$F$244/100*(1-Inputs!$F$245/100)*(IF(AND(Tax!L13>=0,Tax!L13<Inputs!$F$85),INDEX(Inputs!$J$83:$AU$83,Tax!L13+1),0)-IF(AND(Tax!L13>=0,Tax!L13<Inputs!$F$84),INDEX(Inputs!$J$82:$AU$82,Tax!L13+1),0)) | M14: =Tax!$F$12*(Inputs!$F$243/100+Inputs!$F$244/100)*(IF(Tax!M13=0,Inputs!$F$245/100,0)+(1-Inputs!$F$245/100)*IF(AND(Tax!M13>=0,Tax!M13<Inputs!$F$84),INDEX(Inputs!$J$82:$AU$82,Tax!M13+1),0))+Tax!$F$12*Inputs!$F$244/100*(IF(Tax!M13=0,0,0))+Tax!$F$12*Inputs!$F$244/100*(1-Inputs!$F$245/100)*(IF(AND(Tax!M13>=0,Tax!M13<Inputs!$F$85),INDEX(Inputs!$J$83:$AU$83,Tax!M13+1),0)-IF(AND(Tax!M13>=0,Tax!M13<Inputs!$F$84),INDEX(Inputs!$J$82:$AU$82,Tax!M13+1),0)) | N14: =Tax!$F$12*(Inputs!$F$243/100+Inputs!$F$244/100)*(IF(Tax!N13=0,Inputs!$F$245/100,0)+(1-Inputs!$F$245/100)*IF(AND(Tax!N13>=0,Tax!N13<Inputs!$F$84),INDEX(Inputs!$J$82:$AU$82,Tax!N13+1),0))+Tax!$F$12*Inputs!$F$244/100*(IF(Tax!N13=0,0,0))+Tax!$F$12*Inputs!$F$244/100*(1-Inputs!$F$245/100)*(IF(AND(Tax!N13>=0,Tax!N13<Inputs!$F$85),INDEX(Inputs!$J$83:$AU$83,Tax!N13+1),0)-IF(AND(Tax!N13>=0,Tax!N13<Inputs!$F$84),INDEX(Inputs!$J$82:$AU$82,Tax!N13+1),0)) | O14: =Tax!$F$12*(Inputs!$F$243/100+Inputs!$F$244/100)*(IF(Tax!O13=0,Inputs!$F$245/100,0)+(1-Inputs!$F$245/100)*IF(AND(Tax!O13>=0,Tax!O13<Inputs!$F$84),INDEX(Inputs!$J$82:$AU$82,Tax!O13+1),0))+Tax!$F$12*Inputs!$F$244/100*(IF(Tax!O13=0,0,0))+Tax!$F$12*Inputs!$F$244/100*(1-Inputs!$F$245/100)*(IF(AND(Tax!O13>=0,Tax!O13<Inputs!$F$85),INDEX(Inputs!$J$83:$AU$83,Tax!O13+1),0)-IF(AND(Tax!O13>=0,Tax!O13<Inputs!$F$84),INDEX(Inputs!$J$82:$AU$82,Tax!O13+1),0)) | P14: =Tax!$F$12*(Inputs!$F$243/100+Inputs!$F$244/100)*(IF(Tax!P13=0,Inputs!$F$245/100,0)+(1-Inputs!$F$245/100)*IF(AND(Tax!P13>=0,Tax!P13<Inputs!$F$84),INDEX(Inputs!$J$82:$AU$82,Tax!P13+1),0))+Tax!$F$12*Inputs!$F$244/100*(IF(Tax!P13=0,0,0))+Tax!$F$12*Inputs!$F$244/100*(1-Inputs!$F$245/100)*(IF(AND(Tax!P13>=0,Tax!P13<Inputs!$F$85),INDEX(Inputs!$J$83:$AU$83,Tax!P13+1),0)-IF(AND(Tax!P13>=0,Tax!P13<Inputs!$F$84),INDEX(Inputs!$J$82:$AU$82,Tax!P13+1),0)) | Q14: =Tax!$F$12*(Inputs!$F$243/100+Inputs!$F$244/100)*(IF(Tax!Q13=0,Inputs!$F$245/100,0)+(1-Inputs!$F$245/100)*IF(AND(Tax!Q13>=0,Tax!Q13<Inputs!$F$84),INDEX(Inputs!$J$82:$AU$82,Tax!Q13+1),0))+Tax!$F$12*Inputs!$F$244/100*(IF(Tax!Q13=0,0,0))+Tax!$F$12*Inputs!$F$244/100*(1-Inputs!$F$245/100)*(IF(AND(Tax!Q13>=0,Tax!Q13<Inputs!$F$85),INDEX(Inputs!$J$83:$AU$83,Tax!Q13+1),0)-IF(AND(Tax!Q13>=0,Tax!Q13<Inputs!$F$84),INDEX(Inputs!$J$82:$AU$82,Tax!Q13+1),0)) | ... AU14: =Tax!$F$12*(Inputs!$F$243/100+Inputs!$F$244/100)*(IF(Tax!AU13=0,Inputs!$F$245/100,0)+(1-Inputs!$F$245/100)*IF(AND(Tax!AU13>=0,Tax!AU13<Inputs!$F$84),INDEX(Inputs!$J$82:$AU$82,Tax!AU13+1),0))+Tax!$F$12*Inputs!$F$244/100*(IF(Tax!AU13=0,0,0))+Tax!$F$12*Inputs!$F$244/100*(1-Inputs!$F$245/100)*(IF(AND(Tax!AU13>=0,Tax!AU13<Inputs!$F$85),INDEX(Inputs!$J$83:$AU$83,Tax!AU13+1),0)-IF(AND(Tax!AU13>=0,Tax!AU13<Inputs!$F$84),INDEX(Inputs!$J$82:$AU$82,Tax!AU13+1),0))
D15: Depreciable basis, A2 | E15: USD m | F15: =Inputs!$F$260
D16: Recovery year index, A2 | E16: years | J16: =Time!J$4-YEAR(Inputs!$F$259) | K16: =Time!K$4-YEAR(Inputs!$F$259) | L16: =Time!L$4-YEAR(Inputs!$F$259) | M16: =Time!M$4-YEAR(Inputs!$F$259) | N16: =Time!N$4-YEAR(Inputs!$F$259) | O16: =Time!O$4-YEAR(Inputs!$F$259) | P16: =Time!P$4-YEAR(Inputs!$F$259) | Q16: =Time!Q$4-YEAR(Inputs!$F$259) | ... AU16: =Time!AU$4-YEAR(Inputs!$F$259)
D17: Tax depreciation, A2 | E17: USD m | G17: =SUM(J17:AU17) | J17: =Tax!$F$15*(Inputs!$F$243/100+Inputs!$F$244/100)*(IF(Tax!J16=0,Inputs!$F$246/100,0)+(1-Inputs!$F$246/100)*IF(AND(Tax!J16>=0,Tax!J16<Inputs!$F$84),INDEX(Inputs!$J$82:$AU$82,Tax!J16+1),0))+Tax!$F$15*Inputs!$F$244/100*(IF(Tax!J16=0,0,0))+Tax!$F$15*Inputs!$F$244/100*(1-Inputs!$F$246/100)*(IF(AND(Tax!J16>=0,Tax!J16<Inputs!$F$85),INDEX(Inputs!$J$83:$AU$83,Tax!J16+1),0)-IF(AND(Tax!J16>=0,Tax!J16<Inputs!$F$84),INDEX(Inputs!$J$82:$AU$82,Tax!J16+1),0)) | K17: =Tax!$F$15*(Inputs!$F$243/100+Inputs!$F$244/100)*(IF(Tax!K16=0,Inputs!$F$246/100,0)+(1-Inputs!$F$246/100)*IF(AND(Tax!K16>=0,Tax!K16<Inputs!$F$84),INDEX(Inputs!$J$82:$AU$82,Tax!K16+1),0))+Tax!$F$15*Inputs!$F$244/100*(IF(Tax!K16=0,0,0))+Tax!$F$15*Inputs!$F$244/100*(1-Inputs!$F$246/100)*(IF(AND(Tax!K16>=0,Tax!K16<Inputs!$F$85),INDEX(Inputs!$J$83:$AU$83,Tax!K16+1),0)-IF(AND(Tax!K16>=0,Tax!K16<Inputs!$F$84),INDEX(Inputs!$J$82:$AU$82,Tax!K16+1),0)) | L17: =Tax!$F$15*(Inputs!$F$243/100+Inputs!$F$244/100)*(IF(Tax!L16=0,Inputs!$F$246/100,0)+(1-Inputs!$F$246/100)*IF(AND(Tax!L16>=0,Tax!L16<Inputs!$F$84),INDEX(Inputs!$J$82:$AU$82,Tax!L16+1),0))+Tax!$F$15*Inputs!$F$244/100*(IF(Tax!L16=0,0,0))+Tax!$F$15*Inputs!$F$244/100*(1-Inputs!$F$246/100)*(IF(AND(Tax!L16>=0,Tax!L16<Inputs!$F$85),INDEX(Inputs!$J$83:$AU$83,Tax!L16+1),0)-IF(AND(Tax!L16>=0,Tax!L16<Inputs!$F$84),INDEX(Inputs!$J$82:$AU$82,Tax!L16+1),0)) | M17: =Tax!$F$15*(Inputs!$F$243/100+Inputs!$F$244/100)*(IF(Tax!M16=0,Inputs!$F$246/100,0)+(1-Inputs!$F$246/100)*IF(AND(Tax!M16>=0,Tax!M16<Inputs!$F$84),INDEX(Inputs!$J$82:$AU$82,Tax!M16+1),0))+Tax!$F$15*Inputs!$F$244/100*(IF(Tax!M16=0,0,0))+Tax!$F$15*Inputs!$F$244/100*(1-Inputs!$F$246/100)*(IF(AND(Tax!M16>=0,Tax!M16<Inputs!$F$85),INDEX(Inputs!$J$83:$AU$83,Tax!M16+1),0)-IF(AND(Tax!M16>=0,Tax!M16<Inputs!$F$84),INDEX(Inputs!$J$82:$AU$82,Tax!M16+1),0)) | N17: =Tax!$F$15*(Inputs!$F$243/100+Inputs!$F$244/100)*(IF(Tax!N16=0,Inputs!$F$246/100,0)+(1-Inputs!$F$246/100)*IF(AND(Tax!N16>=0,Tax!N16<Inputs!$F$84),INDEX(Inputs!$J$82:$AU$82,Tax!N16+1),0))+Tax!$F$15*Inputs!$F$244/100*(IF(Tax!N16=0,0,0))+Tax!$F$15*Inputs!$F$244/100*(1-Inputs!$F$246/100)*(IF(AND(Tax!N16>=0,Tax!N16<Inputs!$F$85),INDEX(Inputs!$J$83:$AU$83,Tax!N16+1),0)-IF(AND(Tax!N16>=0,Tax!N16<Inputs!$F$84),INDEX(Inputs!$J$82:$AU$82,Tax!N16+1),0)) | O17: =Tax!$F$15*(Inputs!$F$243/100+Inputs!$F$244/100)*(IF(Tax!O16=0,Inputs!$F$246/100,0)+(1-Inputs!$F$246/100)*IF(AND(Tax!O16>=0,Tax!O16<Inputs!$F$84),INDEX(Inputs!$J$82:$AU$82,Tax!O16+1),0))+Tax!$F$15*Inputs!$F$244/100*(IF(Tax!O16=0,0,0))+Tax!$F$15*Inputs!$F$244/100*(1-Inputs!$F$246/100)*(IF(AND(Tax!O16>=0,Tax!O16<Inputs!$F$85),INDEX(Inputs!$J$83:$AU$83,Tax!O16+1),0)-IF(AND(Tax!O16>=0,Tax!O16<Inputs!$F$84),INDEX(Inputs!$J$82:$AU$82,Tax!O16+1),0)) | P17: =Tax!$F$15*(Inputs!$F$243/100+Inputs!$F$244/100)*(IF(Tax!P16=0,Inputs!$F$246/100,0)+(1-Inputs!$F$246/100)*IF(AND(Tax!P16>=0,Tax!P16<Inputs!$F$84),INDEX(Inputs!$J$82:$AU$82,Tax!P16+1),0))+Tax!$F$15*Inputs!$F$244/100*(IF(Tax!P16=0,0,0))+Tax!$F$15*Inputs!$F$244/100*(1-Inputs!$F$246/100)*(IF(AND(Tax!P16>=0,Tax!P16<Inputs!$F$85),INDEX(Inputs!$J$83:$AU$83,Tax!P16+1),0)-IF(AND(Tax!P16>=0,Tax!P16<Inputs!$F$84),INDEX(Inputs!$J$82:$AU$82,Tax!P16+1),0)) | Q17: =Tax!$F$15*(Inputs!$F$243/100+Inputs!$F$244/100)*(IF(Tax!Q16=0,Inputs!$F$246/100,0)+(1-Inputs!$F$246/100)*IF(AND(Tax!Q16>=0,Tax!Q16<Inputs!$F$84),INDEX(Inputs!$J$82:$AU$82,Tax!Q16+1),0))+Tax!$F$15*Inputs!$F$244/100*(IF(Tax!Q16=0,0,0))+Tax!$F$15*Inputs!$F$244/100*(1-Inputs!$F$246/100)*(IF(AND(Tax!Q16>=0,Tax!Q16<Inputs!$F$85),INDEX(Inputs!$J$83:$AU$83,Tax!Q16+1),0)-IF(AND(Tax!Q16>=0,Tax!Q16<Inputs!$F$84),INDEX(Inputs!$J$82:$AU$82,Tax!Q16+1),0)) | ... AU17: =Tax!$F$15*(Inputs!$F$243/100+Inputs!$F$244/100)*(IF(Tax!AU16=0,Inputs!$F$246/100,0)+(1-Inputs!$F$246/100)*IF(AND(Tax!AU16>=0,Tax!AU16<Inputs!$F$84),INDEX(Inputs!$J$82:$AU$82,Tax!AU16+1),0))+Tax!$F$15*Inputs!$F$244/100*(IF(Tax!AU16=0,0,0))+Tax!$F$15*Inputs!$F$244/100*(1-Inputs!$F$246/100)*(IF(AND(Tax!AU16>=0,Tax!AU16<Inputs!$F$85),INDEX(Inputs!$J$83:$AU$83,Tax!AU16+1),0)-IF(AND(Tax!AU16>=0,Tax!AU16<Inputs!$F$84),INDEX(Inputs!$J$82:$AU$82,Tax!AU16+1),0))
D18: Depreciable basis, R7 | E18: USD m | F18: =Inputs!$F$263-Inputs!$F$253*Tax!$F$8
D19: Recovery year index, R7 | E19: years | J19: =Time!J$4-YEAR(Inputs!$F$262) | K19: =Time!K$4-YEAR(Inputs!$F$262) | L19: =Time!L$4-YEAR(Inputs!$F$262) | M19: =Time!M$4-YEAR(Inputs!$F$262) | N19: =Time!N$4-YEAR(Inputs!$F$262) | O19: =Time!O$4-YEAR(Inputs!$F$262) | P19: =Time!P$4-YEAR(Inputs!$F$262) | Q19: =Time!Q$4-YEAR(Inputs!$F$262) | ... AU19: =Time!AU$4-YEAR(Inputs!$F$262)
D20: Tax depreciation, R7 | E20: USD m | G20: =SUM(J20:AU20) | J20: =Tax!$F$18*(Inputs!$F$243/100+Inputs!$F$244/100)*(IF(Tax!J19=0,Inputs!$F$247/100,0)+(1-Inputs!$F$247/100)*IF(AND(Tax!J19>=0,Tax!J19<Inputs!$F$84),INDEX(Inputs!$J$82:$AU$82,Tax!J19+1),0))+Tax!$F$18*Inputs!$F$244/100*(IF(Tax!J19=0,0,0))+Tax!$F$18*Inputs!$F$244/100*(1-Inputs!$F$247/100)*(IF(AND(Tax!J19>=0,Tax!J19<Inputs!$F$85),INDEX(Inputs!$J$83:$AU$83,Tax!J19+1),0)-IF(AND(Tax!J19>=0,Tax!J19<Inputs!$F$84),INDEX(Inputs!$J$82:$AU$82,Tax!J19+1),0)) | K20: =Tax!$F$18*(Inputs!$F$243/100+Inputs!$F$244/100)*(IF(Tax!K19=0,Inputs!$F$247/100,0)+(1-Inputs!$F$247/100)*IF(AND(Tax!K19>=0,Tax!K19<Inputs!$F$84),INDEX(Inputs!$J$82:$AU$82,Tax!K19+1),0))+Tax!$F$18*Inputs!$F$244/100*(IF(Tax!K19=0,0,0))+Tax!$F$18*Inputs!$F$244/100*(1-Inputs!$F$247/100)*(IF(AND(Tax!K19>=0,Tax!K19<Inputs!$F$85),INDEX(Inputs!$J$83:$AU$83,Tax!K19+1),0)-IF(AND(Tax!K19>=0,Tax!K19<Inputs!$F$84),INDEX(Inputs!$J$82:$AU$82,Tax!K19+1),0)) | L20: =Tax!$F$18*(Inputs!$F$243/100+Inputs!$F$244/100)*(IF(Tax!L19=0,Inputs!$F$247/100,0)+(1-Inputs!$F$247/100)*IF(AND(Tax!L19>=0,Tax!L19<Inputs!$F$84),INDEX(Inputs!$J$82:$AU$82,Tax!L19+1),0))+Tax!$F$18*Inputs!$F$244/100*(IF(Tax!L19=0,0,0))+Tax!$F$18*Inputs!$F$244/100*(1-Inputs!$F$247/100)*(IF(AND(Tax!L19>=0,Tax!L19<Inputs!$F$85),INDEX(Inputs!$J$83:$AU$83,Tax!L19+1),0)-IF(AND(Tax!L19>=0,Tax!L19<Inputs!$F$84),INDEX(Inputs!$J$82:$AU$82,Tax!L19+1),0)) | M20: =Tax!$F$18*(Inputs!$F$243/100+Inputs!$F$244/100)*(IF(Tax!M19=0,Inputs!$F$247/100,0)+(1-Inputs!$F$247/100)*IF(AND(Tax!M19>=0,Tax!M19<Inputs!$F$84),INDEX(Inputs!$J$82:$AU$82,Tax!M19+1),0))+Tax!$F$18*Inputs!$F$244/100*(IF(Tax!M19=0,0,0))+Tax!$F$18*Inputs!$F$244/100*(1-Inputs!$F$247/100)*(IF(AND(Tax!M19>=0,Tax!M19<Inputs!$F$85),INDEX(Inputs!$J$83:$AU$83,Tax!M19+1),0)-IF(AND(Tax!M19>=0,Tax!M19<Inputs!$F$84),INDEX(Inputs!$J$82:$AU$82,Tax!M19+1),0)) | N20: =Tax!$F$18*(Inputs!$F$243/100+Inputs!$F$244/100)*(IF(Tax!N19=0,Inputs!$F$247/100,0)+(1-Inputs!$F$247/100)*IF(AND(Tax!N19>=0,Tax!N19<Inputs!$F$84),INDEX(Inputs!$J$82:$AU$82,Tax!N19+1),0))+Tax!$F$18*Inputs!$F$244/100*(IF(Tax!N19=0,0,0))+Tax!$F$18*Inputs!$F$244/100*(1-Inputs!$F$247/100)*(IF(AND(Tax!N19>=0,Tax!N19<Inputs!$F$85),INDEX(Inputs!$J$83:$AU$83,Tax!N19+1),0)-IF(AND(Tax!N19>=0,Tax!N19<Inputs!$F$84),INDEX(Inputs!$J$82:$AU$82,Tax!N19+1),0)) | O20: =Tax!$F$18*(Inputs!$F$243/100+Inputs!$F$244/100)*(IF(Tax!O19=0,Inputs!$F$247/100,0)+(1-Inputs!$F$247/100)*IF(AND(Tax!O19>=0,Tax!O19<Inputs!$F$84),INDEX(Inputs!$J$82:$AU$82,Tax!O19+1),0))+Tax!$F$18*Inputs!$F$244/100*(IF(Tax!O19=0,0,0))+Tax!$F$18*Inputs!$F$244/100*(1-Inputs!$F$247/100)*(IF(AND(Tax!O19>=0,Tax!O19<Inputs!$F$85),INDEX(Inputs!$J$83:$AU$83,Tax!O19+1),0)-IF(AND(Tax!O19>=0,Tax!O19<Inputs!$F$84),INDEX(Inputs!$J$82:$AU$82,Tax!O19+1),0)) | P20: =Tax!$F$18*(Inputs!$F$243/100+Inputs!$F$244/100)*(IF(Tax!P19=0,Inputs!$F$247/100,0)+(1-Inputs!$F$247/100)*IF(AND(Tax!P19>=0,Tax!P19<Inputs!$F$84),INDEX(Inputs!$J$82:$AU$82,Tax!P19+1),0))+Tax!$F$18*Inputs!$F$244/100*(IF(Tax!P19=0,0,0))+Tax!$F$18*Inputs!$F$244/100*(1-Inputs!$F$247/100)*(IF(AND(Tax!P19>=0,Tax!P19<Inputs!$F$85),INDEX(Inputs!$J$83:$AU$83,Tax!P19+1),0)-IF(AND(Tax!P19>=0,Tax!P19<Inputs!$F$84),INDEX(Inputs!$J$82:$AU$82,Tax!P19+1),0)) | Q20: =Tax!$F$18*(Inputs!$F$243/100+Inputs!$F$244/100)*(IF(Tax!Q19=0,Inputs!$F$247/100,0)+(1-Inputs!$F$247/100)*IF(AND(Tax!Q19>=0,Tax!Q19<Inputs!$F$84),INDEX(Inputs!$J$82:$AU$82,Tax!Q19+1),0))+Tax!$F$18*Inputs!$F$244/100*(IF(Tax!Q19=0,0,0))+Tax!$F$18*Inputs!$F$244/100*(1-Inputs!$F$247/100)*(IF(AND(Tax!Q19>=0,Tax!Q19<Inputs!$F$85),INDEX(Inputs!$J$83:$AU$83,Tax!Q19+1),0)-IF(AND(Tax!Q19>=0,Tax!Q19<Inputs!$F$84),INDEX(Inputs!$J$82:$AU$82,Tax!Q19+1),0)) | ... AU20: =Tax!$F$18*(Inputs!$F$243/100+Inputs!$F$244/100)*(IF(Tax!AU19=0,Inputs!$F$247/100,0)+(1-Inputs!$F$247/100)*IF(AND(Tax!AU19>=0,Tax!AU19<Inputs!$F$84),INDEX(Inputs!$J$82:$AU$82,Tax!AU19+1),0))+Tax!$F$18*Inputs!$F$244/100*(IF(Tax!AU19=0,0,0))+Tax!$F$18*Inputs!$F$244/100*(1-Inputs!$F$247/100)*(IF(AND(Tax!AU19>=0,Tax!AU19<Inputs!$F$85),INDEX(Inputs!$J$83:$AU$83,Tax!AU19+1),0)-IF(AND(Tax!AU19>=0,Tax!AU19<Inputs!$F$84),INDEX(Inputs!$J$82:$AU$82,Tax!AU19+1),0))
D21: Depreciable basis, R8 | E21: USD m | F21: =Inputs!$F$264-Inputs!$F$253*Tax!$F$9
D22: Recovery year index, R8 | E22: years | J22: =Time!J$4-YEAR(Inputs!$F$262) | K22: =Time!K$4-YEAR(Inputs!$F$262) | L22: =Time!L$4-YEAR(Inputs!$F$262) | M22: =Time!M$4-YEAR(Inputs!$F$262) | N22: =Time!N$4-YEAR(Inputs!$F$262) | O22: =Time!O$4-YEAR(Inputs!$F$262) | P22: =Time!P$4-YEAR(Inputs!$F$262) | Q22: =Time!Q$4-YEAR(Inputs!$F$262) | ... AU22: =Time!AU$4-YEAR(Inputs!$F$262)
D23: Tax depreciation, R8 | E23: USD m | G23: =SUM(J23:AU23) | J23: =Tax!$F$21*(Inputs!$F$243/100+Inputs!$F$244/100)*(IF(Tax!J22=0,Inputs!$F$247/100,0)+(1-Inputs!$F$247/100)*IF(AND(Tax!J22>=0,Tax!J22<Inputs!$F$84),INDEX(Inputs!$J$82:$AU$82,Tax!J22+1),0))+Tax!$F$21*Inputs!$F$244/100*(IF(Tax!J22=0,0,0))+Tax!$F$21*Inputs!$F$244/100*(1-Inputs!$F$247/100)*(IF(AND(Tax!J22>=0,Tax!J22<Inputs!$F$85),INDEX(Inputs!$J$83:$AU$83,Tax!J22+1),0)-IF(AND(Tax!J22>=0,Tax!J22<Inputs!$F$84),INDEX(Inputs!$J$82:$AU$82,Tax!J22+1),0)) | K23: =Tax!$F$21*(Inputs!$F$243/100+Inputs!$F$244/100)*(IF(Tax!K22=0,Inputs!$F$247/100,0)+(1-Inputs!$F$247/100)*IF(AND(Tax!K22>=0,Tax!K22<Inputs!$F$84),INDEX(Inputs!$J$82:$AU$82,Tax!K22+1),0))+Tax!$F$21*Inputs!$F$244/100*(IF(Tax!K22=0,0,0))+Tax!$F$21*Inputs!$F$244/100*(1-Inputs!$F$247/100)*(IF(AND(Tax!K22>=0,Tax!K22<Inputs!$F$85),INDEX(Inputs!$J$83:$AU$83,Tax!K22+1),0)-IF(AND(Tax!K22>=0,Tax!K22<Inputs!$F$84),INDEX(Inputs!$J$82:$AU$82,Tax!K22+1),0)) | L23: =Tax!$F$21*(Inputs!$F$243/100+Inputs!$F$244/100)*(IF(Tax!L22=0,Inputs!$F$247/100,0)+(1-Inputs!$F$247/100)*IF(AND(Tax!L22>=0,Tax!L22<Inputs!$F$84),INDEX(Inputs!$J$82:$AU$82,Tax!L22+1),0))+Tax!$F$21*Inputs!$F$244/100*(IF(Tax!L22=0,0,0))+Tax!$F$21*Inputs!$F$244/100*(1-Inputs!$F$247/100)*(IF(AND(Tax!L22>=0,Tax!L22<Inputs!$F$85),INDEX(Inputs!$J$83:$AU$83,Tax!L22+1),0)-IF(AND(Tax!L22>=0,Tax!L22<Inputs!$F$84),INDEX(Inputs!$J$82:$AU$82,Tax!L22+1),0)) | M23: =Tax!$F$21*(Inputs!$F$243/100+Inputs!$F$244/100)*(IF(Tax!M22=0,Inputs!$F$247/100,0)+(1-Inputs!$F$247/100)*IF(AND(Tax!M22>=0,Tax!M22<Inputs!$F$84),INDEX(Inputs!$J$82:$AU$82,Tax!M22+1),0))+Tax!$F$21*Inputs!$F$244/100*(IF(Tax!M22=0,0,0))+Tax!$F$21*Inputs!$F$244/100*(1-Inputs!$F$247/100)*(IF(AND(Tax!M22>=0,Tax!M22<Inputs!$F$85),INDEX(Inputs!$J$83:$AU$83,Tax!M22+1),0)-IF(AND(Tax!M22>=0,Tax!M22<Inputs!$F$84),INDEX(Inputs!$J$82:$AU$82,Tax!M22+1),0)) | N23: =Tax!$F$21*(Inputs!$F$243/100+Inputs!$F$244/100)*(IF(Tax!N22=0,Inputs!$F$247/100,0)+(1-Inputs!$F$247/100)*IF(AND(Tax!N22>=0,Tax!N22<Inputs!$F$84),INDEX(Inputs!$J$82:$AU$82,Tax!N22+1),0))+Tax!$F$21*Inputs!$F$244/100*(IF(Tax!N22=0,0,0))+Tax!$F$21*Inputs!$F$244/100*(1-Inputs!$F$247/100)*(IF(AND(Tax!N22>=0,Tax!N22<Inputs!$F$85),INDEX(Inputs!$J$83:$AU$83,Tax!N22+1),0)-IF(AND(Tax!N22>=0,Tax!N22<Inputs!$F$84),INDEX(Inputs!$J$82:$AU$82,Tax!N22+1),0)) | O23: =Tax!$F$21*(Inputs!$F$243/100+Inputs!$F$244/100)*(IF(Tax!O22=0,Inputs!$F$247/100,0)+(1-Inputs!$F$247/100)*IF(AND(Tax!O22>=0,Tax!O22<Inputs!$F$84),INDEX(Inputs!$J$82:$AU$82,Tax!O22+1),0))+Tax!$F$21*Inputs!$F$244/100*(IF(Tax!O22=0,0,0))+Tax!$F$21*Inputs!$F$244/100*(1-Inputs!$F$247/100)*(IF(AND(Tax!O22>=0,Tax!O22<Inputs!$F$85),INDEX(Inputs!$J$83:$AU$83,Tax!O22+1),0)-IF(AND(Tax!O22>=0,Tax!O22<Inputs!$F$84),INDEX(Inputs!$J$82:$AU$82,Tax!O22+1),0)) | P23: =Tax!$F$21*(Inputs!$F$243/100+Inputs!$F$244/100)*(IF(Tax!P22=0,Inputs!$F$247/100,0)+(1-Inputs!$F$247/100)*IF(AND(Tax!P22>=0,Tax!P22<Inputs!$F$84),INDEX(Inputs!$J$82:$AU$82,Tax!P22+1),0))+Tax!$F$21*Inputs!$F$244/100*(IF(Tax!P22=0,0,0))+Tax!$F$21*Inputs!$F$244/100*(1-Inputs!$F$247/100)*(IF(AND(Tax!P22>=0,Tax!P22<Inputs!$F$85),INDEX(Inputs!$J$83:$AU$83,Tax!P22+1),0)-IF(AND(Tax!P22>=0,Tax!P22<Inputs!$F$84),INDEX(Inputs!$J$82:$AU$82,Tax!P22+1),0)) | Q23: =Tax!$F$21*(Inputs!$F$243/100+Inputs!$F$244/100)*(IF(Tax!Q22=0,Inputs!$F$247/100,0)+(1-Inputs!$F$247/100)*IF(AND(Tax!Q22>=0,Tax!Q22<Inputs!$F$84),INDEX(Inputs!$J$82:$AU$82,Tax!Q22+1),0))+Tax!$F$21*Inputs!$F$244/100*(IF(Tax!Q22=0,0,0))+Tax!$F$21*Inputs!$F$244/100*(1-Inputs!$F$247/100)*(IF(AND(Tax!Q22>=0,Tax!Q22<Inputs!$F$85),INDEX(Inputs!$J$83:$AU$83,Tax!Q22+1),0)-IF(AND(Tax!Q22>=0,Tax!Q22<Inputs!$F$84),INDEX(Inputs!$J$82:$AU$82,Tax!Q22+1),0)) | ... AU23: =Tax!$F$21*(Inputs!$F$243/100+Inputs!$F$244/100)*(IF(Tax!AU22=0,Inputs!$F$247/100,0)+(1-Inputs!$F$247/100)*IF(AND(Tax!AU22>=0,Tax!AU22<Inputs!$F$84),INDEX(Inputs!$J$82:$AU$82,Tax!AU22+1),0))+Tax!$F$21*Inputs!$F$244/100*(IF(Tax!AU22=0,0,0))+Tax!$F$21*Inputs!$F$244/100*(1-Inputs!$F$247/100)*(IF(AND(Tax!AU22>=0,Tax!AU22<Inputs!$F$85),INDEX(Inputs!$J$83:$AU$83,Tax!AU22+1),0)-IF(AND(Tax!AU22>=0,Tax!AU22<Inputs!$F$84),INDEX(Inputs!$J$82:$AU$82,Tax!AU22+1),0))
D24: Tax depreciation, total | E24: USD m | G24: =SUM(J24:AU24) | J24: =Tax!J14+Tax!J17+Tax!J20+Tax!J23 | K24: =Tax!K14+Tax!K17+Tax!K20+Tax!K23 | L24: =Tax!L14+Tax!L17+Tax!L20+Tax!L23 | M24: =Tax!M14+Tax!M17+Tax!M20+Tax!M23 | N24: =Tax!N14+Tax!N17+Tax!N20+Tax!N23 | O24: =Tax!O14+Tax!O17+Tax!O20+Tax!O23 | P24: =Tax!P14+Tax!P17+Tax!P20+Tax!P23 | Q24: =Tax!Q14+Tax!Q17+Tax!Q20+Tax!Q23 | ... AU24: =Tax!AU14+Tax!AU17+Tax!AU20+Tax!AU23
D25: Taxable operating income (Mesa shares) less asset management | E25: USD m | J25: =Operations!J95+Operations!J137+Operations!J180+Operations!J223+Operations!J266+Operations!J298+Operations!J331+Operations!J373-Operations!J384 | K25: =Operations!K95+Operations!K137+Operations!K180+Operations!K223+Operations!K266+Operations!K298+Operations!K331+Operations!K373-Operations!K384 | L25: =Operations!L95+Operations!L137+Operations!L180+Operations!L223+Operations!L266+Operations!L298+Operations!L331+Operations!L373-Operations!L384 | M25: =Operations!M95+Operations!M137+Operations!M180+Operations!M223+Operations!M266+Operations!M298+Operations!M331+Operations!M373-Operations!M384 | N25: =Operations!N95+Operations!N137+Operations!N180+Operations!N223+Operations!N266+Operations!N298+Operations!N331+Operations!N373-Operations!N384 | O25: =Operations!O95+Operations!O137+Operations!O180+Operations!O223+Operations!O266+Operations!O298+Operations!O331+Operations!O373-Operations!O384 | P25: =Operations!P95+Operations!P137+Operations!P180+Operations!P223+Operations!P266+Operations!P298+Operations!P331+Operations!P373-Operations!P384 | Q25: =Operations!Q95+Operations!Q137+Operations!Q180+Operations!Q223+Operations!Q266+Operations!Q298+Operations!Q331+Operations!Q373-Operations!Q384 | ... AU25: =Operations!AU95+Operations!AU137+Operations!AU180+Operations!AU223+Operations!AU266+Operations!AU298+Operations!AU331+Operations!AU373-Operations!AU384
A27: Taxable income, NOL and cash tax (Mesa Corta modeled as a taxable blocker)
D28: Interest deducted (opco TL, Redfern, USPP, holdco) | E28: USD m | J28: =Debt!J15+Debt!J24+Debt!J32+Debt!J47+Debt!J54+Debt!J61 | K28: =Debt!K15+Debt!K24+Debt!K32+Debt!K47+Debt!K54+Debt!K61 | L28: =Debt!L15+Debt!L24+Debt!L32+Debt!L47+Debt!L54+Debt!L61 | M28: =Debt!M15+Debt!M24+Debt!M32+Debt!M47+Debt!M54+Debt!M61 | N28: =Debt!N15+Debt!N24+Debt!N32+Debt!N47+Debt!N54+Debt!N61 | O28: =Debt!O15+Debt!O24+Debt!O32+Debt!O47+Debt!O54+Debt!O61 | P28: =Debt!P15+Debt!P24+Debt!P32+Debt!P47+Debt!P54+Debt!P61 | Q28: =Debt!Q15+Debt!Q24+Debt!Q32+Debt!Q47+Debt!Q54+Debt!Q61 | ... AU28: =Debt!AU15+Debt!AU24+Debt!AU32+Debt!AU47+Debt!AU54+Debt!AU61
D29: Taxable income before NOL | E29: USD m | J29: =Tax!J25-Tax!J24-Tax!J28 | K29: =Tax!K25-Tax!K24-Tax!K28 | L29: =Tax!L25-Tax!L24-Tax!L28 | M29: =Tax!M25-Tax!M24-Tax!M28 | N29: =Tax!N25-Tax!N24-Tax!N28 | O29: =Tax!O25-Tax!O24-Tax!O28 | P29: =Tax!P25-Tax!P24-Tax!P28 | Q29: =Tax!Q25-Tax!Q24-Tax!Q28 | ... AU29: =Tax!AU25-Tax!AU24-Tax!AU28
D30: NOL opening | E30: USD m | J30: =I33 | K30: =J33 | L30: =K33 | M30: =L33 | N30: =M33 | O30: =N33 | P30: =O33 | Q30: =P33 | ... AU30: =AT33
D31: NOL used (limited to 80% of taxable income) | E31: USD m | G31: =SUM(J31:AU31) | J31: =MIN(Tax!J30,Inputs!$F$242/100*MAX(Tax!J29,0)) | K31: =MIN(Tax!K30,Inputs!$F$242/100*MAX(Tax!K29,0)) | L31: =MIN(Tax!L30,Inputs!$F$242/100*MAX(Tax!L29,0)) | M31: =MIN(Tax!M30,Inputs!$F$242/100*MAX(Tax!M29,0)) | N31: =MIN(Tax!N30,Inputs!$F$242/100*MAX(Tax!N29,0)) | O31: =MIN(Tax!O30,Inputs!$F$242/100*MAX(Tax!O29,0)) | P31: =MIN(Tax!P30,Inputs!$F$242/100*MAX(Tax!P29,0)) | Q31: =MIN(Tax!Q30,Inputs!$F$242/100*MAX(Tax!Q29,0)) | ... AU31: =MIN(Tax!AU30,Inputs!$F$242/100*MAX(Tax!AU29,0))
D32: Cash tax | E32: USD m | G32: =SUM(J32:AU32) | J32: =Inputs!$F$241/100*(MAX(Tax!J29,0)-Tax!J31) | K32: =Inputs!$F$241/100*(MAX(Tax!K29,0)-Tax!K31) | L32: =Inputs!$F$241/100*(MAX(Tax!L29,0)-Tax!L31) | M32: =Inputs!$F$241/100*(MAX(Tax!M29,0)-Tax!M31) | N32: =Inputs!$F$241/100*(MAX(Tax!N29,0)-Tax!N31) | O32: =Inputs!$F$241/100*(MAX(Tax!O29,0)-Tax!O31) | P32: =Inputs!$F$241/100*(MAX(Tax!P29,0)-Tax!P31) | Q32: =Inputs!$F$241/100*(MAX(Tax!Q29,0)-Tax!Q31) | ... AU32: =Inputs!$F$241/100*(MAX(Tax!AU29,0)-Tax!AU31)
D33: NOL closing | E33: USD m | J33: =Tax!J30-Tax!J31+MAX(-Tax!J29,0) | K33: =Tax!K30-Tax!K31+MAX(-Tax!K29,0) | L33: =Tax!L30-Tax!L31+MAX(-Tax!L29,0) | M33: =Tax!M30-Tax!M31+MAX(-Tax!M29,0) | N33: =Tax!N30-Tax!N31+MAX(-Tax!N29,0) | O33: =Tax!O30-Tax!O31+MAX(-Tax!O29,0) | P33: =Tax!P30-Tax!P31+MAX(-Tax!P29,0) | Q33: =Tax!Q30-Tax!Q31+MAX(-Tax!Q29,0) | ... AU33: =Tax!AU30-Tax!AU31+MAX(-Tax!AU29,0)

Sheet Funding
A1: Funding: debt sizing (base P50 and P99 sizing blocks), sources and uses, 2025 refinancing
A2: Case R, Mesa Corta Renewables. USD m nominal unless stated. Illustrative prices: not ERCOT settlement data and not a forecast.
D4: Year | J4: =Time!J$4 | K4: =Time!K$4 | L4: =Time!L$4 | M4: =Time!M$4 | N4: =Time!N$4 | O4: =Time!O$4 | P4: =Time!P$4 | Q4: =Time!Q$4 | ... AU4: =Time!AU$4
D5: Period end | J5: =Time!J$6 | K5: =Time!K$6 | L5: =Time!L$6 | M5: =Time!M$6 | N5: =Time!N$6 | O5: =Time!O$6 | P5: =Time!P$6 | Q5: =Time!Q$6 | ... AU5: =Time!AU$6
A7: Opco term loan, March 22, 2022 (A1 group, sculpted to December 31, 2040)
D8: Interest period fraction (loan date to notional end) | E8: fraction | J8: =MAX(0,MIN(Inputs!$F$270,Time!J$6)-MAX(Inputs!$F$269,Time!J$5))/Time!J$7 | K8: =MAX(0,MIN(Inputs!$F$270,Time!K$6)-MAX(Inputs!$F$269,Time!K$5))/Time!K$7 | L8: =MAX(0,MIN(Inputs!$F$270,Time!L$6)-MAX(Inputs!$F$269,Time!L$5))/Time!L$7 | M8: =MAX(0,MIN(Inputs!$F$270,Time!M$6)-MAX(Inputs!$F$269,Time!M$5))/Time!M$7 | N8: =MAX(0,MIN(Inputs!$F$270,Time!N$6)-MAX(Inputs!$F$269,Time!N$5))/Time!N$7 | O8: =MAX(0,MIN(Inputs!$F$270,Time!O$6)-MAX(Inputs!$F$269,Time!O$5))/Time!O$7 | P8: =MAX(0,MIN(Inputs!$F$270,Time!P$6)-MAX(Inputs!$F$269,Time!P$5))/Time!P$7 | Q8: =MAX(0,MIN(Inputs!$F$270,Time!Q$6)-MAX(Inputs!$F$269,Time!Q$5))/Time!Q$7 | ... AU8: =MAX(0,MIN(Inputs!$F$270,Time!AU$6)-MAX(Inputs!$F$269,Time!AU$5))/Time!AU$7
D9: Fraction of year before margin step | E9: fraction | J9: =MAX(0,MIN(Inputs!$F$273,Time!J$6)-Time!J$5)/Time!J$7 | K9: =MAX(0,MIN(Inputs!$F$273,Time!K$6)-Time!K$5)/Time!K$7 | L9: =MAX(0,MIN(Inputs!$F$273,Time!L$6)-Time!L$5)/Time!L$7 | M9: =MAX(0,MIN(Inputs!$F$273,Time!M$6)-Time!M$5)/Time!M$7 | N9: =MAX(0,MIN(Inputs!$F$273,Time!N$6)-Time!N$5)/Time!N$7 | O9: =MAX(0,MIN(Inputs!$F$273,Time!O$6)-Time!O$5)/Time!O$7 | P9: =MAX(0,MIN(Inputs!$F$273,Time!P$6)-Time!P$5)/Time!P$7 | Q9: =MAX(0,MIN(Inputs!$F$273,Time!Q$6)-Time!Q$5)/Time!Q$7 | ... AU9: =MAX(0,MIN(Inputs!$F$273,Time!AU$6)-Time!AU$5)/Time!AU$7
D10: Margin | E10: % | J10: =Inputs!$F$272-(Inputs!$F$272-Inputs!$F$271)*Funding!J9 | K10: =Inputs!$F$272-(Inputs!$F$272-Inputs!$F$271)*Funding!K9 | L10: =Inputs!$F$272-(Inputs!$F$272-Inputs!$F$271)*Funding!L9 | M10: =Inputs!$F$272-(Inputs!$F$272-Inputs!$F$271)*Funding!M9 | N10: =Inputs!$F$272-(Inputs!$F$272-Inputs!$F$271)*Funding!N9 | O10: =Inputs!$F$272-(Inputs!$F$272-Inputs!$F$271)*Funding!O9 | P10: =Inputs!$F$272-(Inputs!$F$272-Inputs!$F$271)*Funding!P9 | Q10: =Inputs!$F$272-(Inputs!$F$272-Inputs!$F$271)*Funding!Q9 | ... AU10: =Inputs!$F$272-(Inputs!$F$272-Inputs!$F$271)*Funding!AU9
D11: Hedged share (hedge ratio x fraction of year before swap end) | E11: fraction | J11: =Inputs!$F$279/100*MAX(0,MIN(Inputs!$F$281,Time!J$6)-Time!J$5)/Time!J$7 | K11: =Inputs!$F$279/100*MAX(0,MIN(Inputs!$F$281,Time!K$6)-Time!K$5)/Time!K$7 | L11: =Inputs!$F$279/100*MAX(0,MIN(Inputs!$F$281,Time!L$6)-Time!L$5)/Time!L$7 | M11: =Inputs!$F$279/100*MAX(0,MIN(Inputs!$F$281,Time!M$6)-Time!M$5)/Time!M$7 | N11: =Inputs!$F$279/100*MAX(0,MIN(Inputs!$F$281,Time!N$6)-Time!N$5)/Time!N$7 | O11: =Inputs!$F$279/100*MAX(0,MIN(Inputs!$F$281,Time!O$6)-Time!O$5)/Time!O$7 | P11: =Inputs!$F$279/100*MAX(0,MIN(Inputs!$F$281,Time!P$6)-Time!P$5)/Time!P$7 | Q11: =Inputs!$F$279/100*MAX(0,MIN(Inputs!$F$281,Time!Q$6)-Time!Q$5)/Time!Q$7 | ... AU11: =Inputs!$F$279/100*MAX(0,MIN(Inputs!$F$281,Time!AU$6)-Time!AU$5)/Time!AU$7
D12: All-in sizing rate | E12: % | J12: =Funding!J11*Inputs!$F$280+(1-Funding!J11)*Inputs!J80+Funding!J10 | K12: =Funding!K11*Inputs!$F$280+(1-Funding!K11)*Inputs!K80+Funding!K10 | L12: =Funding!L11*Inputs!$F$280+(1-Funding!L11)*Inputs!L80+Funding!L10 | M12: =Funding!M11*Inputs!$F$280+(1-Funding!M11)*Inputs!M80+Funding!M10 | N12: =Funding!N11*Inputs!$F$280+(1-Funding!N11)*Inputs!N80+Funding!N10 | O12: =Funding!O11*Inputs!$F$280+(1-Funding!O11)*Inputs!O80+Funding!O10 | P12: =Funding!P11*Inputs!$F$280+(1-Funding!P11)*Inputs!P80+Funding!P10 | Q12: =Funding!Q11*Inputs!$F$280+(1-Funding!Q11)*Inputs!Q80+Funding!Q10 | ... AU12: =Funding!AU11*Inputs!$F$280+(1-Funding!AU11)*Inputs!AU80+Funding!AU10
D13: Debt-service capacity by bucket (CFADS / bucket DSCR) | E13: USD m | J13: =Operations!J777/Inputs!$F$275+Operations!J778/Inputs!$F$276+Operations!J779/Inputs!$F$277 | K13: =Operations!K777/Inputs!$F$275+Operations!K778/Inputs!$F$276+Operations!K779/Inputs!$F$277 | L13: =Operations!L777/Inputs!$F$275+Operations!L778/Inputs!$F$276+Operations!L779/Inputs!$F$277 | M13: =Operations!M777/Inputs!$F$275+Operations!M778/Inputs!$F$276+Operations!M779/Inputs!$F$277 | N13: =Operations!N777/Inputs!$F$275+Operations!N778/Inputs!$F$276+Operations!N779/Inputs!$F$277 | O13: =Operations!O777/Inputs!$F$275+Operations!O778/Inputs!$F$276+Operations!O779/Inputs!$F$277 | P13: =Operations!P777/Inputs!$F$275+Operations!P778/Inputs!$F$276+Operations!P779/Inputs!$F$277 | Q13: =Operations!Q777/Inputs!$F$275+Operations!Q778/Inputs!$F$276+Operations!Q779/Inputs!$F$277 | ... AU13: =Operations!AU777/Inputs!$F$275+Operations!AU778/Inputs!$F$276+Operations!AU779/Inputs!$F$277
D14: Debt-service capacity at P99 (P99 CFADS / 1.00x) | E14: USD m | J14: =Operations!J1142/Inputs!$F$278 | K14: =Operations!K1142/Inputs!$F$278 | L14: =Operations!L1142/Inputs!$F$278 | M14: =Operations!M1142/Inputs!$F$278 | N14: =Operations!N1142/Inputs!$F$278 | O14: =Operations!O1142/Inputs!$F$278 | P14: =Operations!P1142/Inputs!$F$278 | Q14: =Operations!Q1142/Inputs!$F$278 | ... AU14: =Operations!AU1142/Inputs!$F$278
D15: Sculpted debt service | E15: USD m | G15: =SUM(J15:AU15) | J15: =IF(Funding!J8>0,MAX(0,MIN(Funding!J13,Funding!J14)),0) | K15: =IF(Funding!K8>0,MAX(0,MIN(Funding!K13,Funding!K14)),0) | L15: =IF(Funding!L8>0,MAX(0,MIN(Funding!L13,Funding!L14)),0) | M15: =IF(Funding!M8>0,MAX(0,MIN(Funding!M13,Funding!M14)),0) | N15: =IF(Funding!N8>0,MAX(0,MIN(Funding!N13,Funding!N14)),0) | O15: =IF(Funding!O8>0,MAX(0,MIN(Funding!O13,Funding!O14)),0) | P15: =IF(Funding!P8>0,MAX(0,MIN(Funding!P13,Funding!P14)),0) | Q15: =IF(Funding!Q8>0,MAX(0,MIN(Funding!Q13,Funding!Q14)),0) | ... AU15: =IF(Funding!AU8>0,MAX(0,MIN(Funding!AU13,Funding!AU14)),0)
D16: Discount factor to loan date | E16: factor | J16: =IF(Time!J$4=Inputs!$F$23,1,I16)/(1+Funding!J12/100*Funding!J8) | K16: =IF(Time!K$4=Inputs!$F$23,1,J16)/(1+Funding!K12/100*Funding!K8) | L16: =IF(Time!L$4=Inputs!$F$23,1,K16)/(1+Funding!L12/100*Funding!L8) | M16: =IF(Time!M$4=Inputs!$F$23,1,L16)/(1+Funding!M12/100*Funding!M8) | N16: =IF(Time!N$4=Inputs!$F$23,1,M16)/(1+Funding!N12/100*Funding!N8) | O16: =IF(Time!O$4=Inputs!$F$23,1,N16)/(1+Funding!O12/100*Funding!O8) | P16: =IF(Time!P$4=Inputs!$F$23,1,O16)/(1+Funding!P12/100*Funding!P8) | Q16: =IF(Time!Q$4=Inputs!$F$23,1,P16)/(1+Funding!Q12/100*Funding!Q8) | ... AU16: =IF(Time!AU$4=Inputs!$F$23,1,AT16)/(1+Funding!AU12/100*Funding!AU8)
D17: Opco term loan amount (PV of sculpted debt service) | E17: USD m | F17: =SUMPRODUCT(Funding!$J$15:$AU$15,Funding!$J$16:$AU$16)
D18: PV of contracted debt-service capacity | E18: USD m | F18: =SUMPRODUCT(Operations!$J$777:$AU$777/Inputs!$F$275,Funding!$J$16:$AU$16,--(Funding!$J$8:$AU$8>0))
D19: PV of hedged debt-service capacity | E19: USD m | F19: =SUMPRODUCT(Operations!$J$778:$AU$778/Inputs!$F$276,Funding!$J$16:$AU$16,--(Funding!$J$8:$AU$8>0))
D20: PV of merchant debt-service capacity | E20: USD m | F20: =SUMPRODUCT(Operations!$J$779:$AU$779/Inputs!$F$277,Funding!$J$16:$AU$16,--(Funding!$J$8:$AU$8>0))
D21: Years in which the P99 test binds | E21: years | F21: =SUMPRODUCT(--(Funding!$J$14:$AU$14<Funding!$J$13:$AU$13),--(Funding!$J$8:$AU$8>0))
D22: Sculpted schedule: opening balance | E22: USD m | J22: =IF(Time!J$4=YEAR(Inputs!$F$269),Funding!$F$17,I25) | K22: =IF(Time!K$4=YEAR(Inputs!$F$269),Funding!$F$17,J25) | L22: =IF(Time!L$4=YEAR(Inputs!$F$269),Funding!$F$17,K25) | M22: =IF(Time!M$4=YEAR(Inputs!$F$269),Funding!$F$17,L25) | N22: =IF(Time!N$4=YEAR(Inputs!$F$269),Funding!$F$17,M25) | O22: =IF(Time!O$4=YEAR(Inputs!$F$269),Funding!$F$17,N25) | P22: =IF(Time!P$4=YEAR(Inputs!$F$269),Funding!$F$17,O25) | Q22: =IF(Time!Q$4=YEAR(Inputs!$F$269),Funding!$F$17,P25) | ... AU22: =IF(Time!AU$4=YEAR(Inputs!$F$269),Funding!$F$17,AT25)
D23: Sculpted schedule: interest | E23: USD m | J23: =Funding!J22*Funding!J12/100*Funding!J8 | K23: =Funding!K22*Funding!K12/100*Funding!K8 | L23: =Funding!L22*Funding!L12/100*Funding!L8 | M23: =Funding!M22*Funding!M12/100*Funding!M8 | N23: =Funding!N22*Funding!N12/100*Funding!N8 | O23: =Funding!O22*Funding!O12/100*Funding!O8 | P23: =Funding!P22*Funding!P12/100*Funding!P8 | Q23: =Funding!Q22*Funding!Q12/100*Funding!Q8 | ... AU23: =Funding!AU22*Funding!AU12/100*Funding!AU8
D24: Sculpted schedule: principal | E24: USD m | G24: =SUM(J24:AU24) | J24: =IF(Funding!J8>0,Funding!J15-Funding!J23,0) | K24: =IF(Funding!K8>0,Funding!K15-Funding!K23,0) | L24: =IF(Funding!L8>0,Funding!L15-Funding!L23,0) | M24: =IF(Funding!M8>0,Funding!M15-Funding!M23,0) | N24: =IF(Funding!N8>0,Funding!N15-Funding!N23,0) | O24: =IF(Funding!O8>0,Funding!O15-Funding!O23,0) | P24: =IF(Funding!P8>0,Funding!P15-Funding!P23,0) | Q24: =IF(Funding!Q8>0,Funding!Q15-Funding!Q23,0) | ... AU24: =IF(Funding!AU8>0,Funding!AU15-Funding!AU23,0)
D25: Sculpted schedule: closing balance | E25: USD m | J25: =Funding!J22-Funding!J24 | K25: =Funding!K22-Funding!K24 | L25: =Funding!L22-Funding!L24 | M25: =Funding!M22-Funding!M24 | N25: =Funding!N22-Funding!N24 | O25: =Funding!O22-Funding!O24 | P25: =Funding!P22-Funding!P24 | Q25: =Funding!Q22-Funding!Q24 | ... AU25: =Funding!AU22-Funding!AU24
D26: Base P50 distributions from A1 group (CFADS less sculpted debt service) | E26: USD m | J26: =Operations!J771-Funding!J15 | K26: =Operations!K771-Funding!K15 | L26: =Operations!L771-Funding!L15 | M26: =Operations!M771-Funding!M15 | N26: =Operations!N771-Funding!N15 | O26: =Operations!O771-Funding!O15 | P26: =Operations!P771-Funding!P15 | Q26: =Operations!Q771-Funding!Q15 | ... AU26: =Operations!AU771-Funding!AU15
A28: Holdco term loan B, March 22, 2022
D29: Interest period fraction to maturity | E29: fraction | J29: =MAX(0,MIN(Inputs!$F$283,Time!J$6)-MAX(Inputs!$F$282,Time!J$5))/Time!J$7 | K29: =MAX(0,MIN(Inputs!$F$283,Time!K$6)-MAX(Inputs!$F$282,Time!K$5))/Time!K$7 | L29: =MAX(0,MIN(Inputs!$F$283,Time!L$6)-MAX(Inputs!$F$282,Time!L$5))/Time!L$7 | M29: =MAX(0,MIN(Inputs!$F$283,Time!M$6)-MAX(Inputs!$F$282,Time!M$5))/Time!M$7 | N29: =MAX(0,MIN(Inputs!$F$283,Time!N$6)-MAX(Inputs!$F$282,Time!N$5))/Time!N$7 | O29: =MAX(0,MIN(Inputs!$F$283,Time!O$6)-MAX(Inputs!$F$282,Time!O$5))/Time!O$7 | P29: =MAX(0,MIN(Inputs!$F$283,Time!P$6)-MAX(Inputs!$F$282,Time!P$5))/Time!P$7 | Q29: =MAX(0,MIN(Inputs!$F$283,Time!Q$6)-MAX(Inputs!$F$282,Time!Q$5))/Time!Q$7 | ... AU29: =MAX(0,MIN(Inputs!$F$283,Time!AU$6)-MAX(Inputs!$F$282,Time!AU$5))/Time!AU$7
D30: Rate (SOFR floored + margin) | E30: % | J30: =MAX(Inputs!J80,Inputs!$F$285)+Inputs!$F$284 | K30: =MAX(Inputs!K80,Inputs!$F$285)+Inputs!$F$284 | L30: =MAX(Inputs!L80,Inputs!$F$285)+Inputs!$F$284 | M30: =MAX(Inputs!M80,Inputs!$F$285)+Inputs!$F$284 | N30: =MAX(Inputs!N80,Inputs!$F$285)+Inputs!$F$284 | O30: =MAX(Inputs!O80,Inputs!$F$285)+Inputs!$F$284 | P30: =MAX(Inputs!P80,Inputs!$F$285)+Inputs!$F$284 | Q30: =MAX(Inputs!Q80,Inputs!$F$285)+Inputs!$F$284 | ... AU30: =MAX(Inputs!AU80,Inputs!$F$285)+Inputs!$F$284
D31: Scheduled amortization per unit of face | E31: factor | J31: =Inputs!$F$287/100*Funding!J29 | K31: =Inputs!$F$287/100*Funding!K29 | L31: =Inputs!$F$287/100*Funding!L29 | M31: =Inputs!$F$287/100*Funding!M29 | N31: =Inputs!$F$287/100*Funding!N29 | O31: =Inputs!$F$287/100*Funding!O29 | P31: =Inputs!$F$287/100*Funding!P29 | Q31: =Inputs!$F$287/100*Funding!Q29 | ... AU31: =Inputs!$F$287/100*Funding!AU29
D32: Scheduled balance per unit of face | E32: factor | J32: =IF(Time!J$4=Inputs!$F$23,1,I32-I31) | K32: =IF(Time!K$4=Inputs!$F$23,1,J32-J31) | L32: =IF(Time!L$4=Inputs!$F$23,1,K32-K31) | M32: =IF(Time!M$4=Inputs!$F$23,1,L32-L31) | N32: =IF(Time!N$4=Inputs!$F$23,1,M32-M31) | O32: =IF(Time!O$4=Inputs!$F$23,1,N32-N31) | P32: =IF(Time!P$4=Inputs!$F$23,1,O32-O31) | Q32: =IF(Time!Q$4=Inputs!$F$23,1,P32-P31) | ... AU32: =IF(Time!AU$4=Inputs!$F$23,1,AT32-AT31)
D33: Debt service per unit of face | E33: factor | J33: =Funding!J32*Funding!J30/100*Funding!J29+Funding!J31 | K33: =Funding!K32*Funding!K30/100*Funding!K29+Funding!K31 | L33: =Funding!L32*Funding!L30/100*Funding!L29+Funding!L31 | M33: =Funding!M32*Funding!M30/100*Funding!M29+Funding!M31 | N33: =Funding!N32*Funding!N30/100*Funding!N29+Funding!N31 | O33: =Funding!O32*Funding!O30/100*Funding!O29+Funding!O31 | P33: =Funding!P32*Funding!P30/100*Funding!P29+Funding!P31 | Q33: =Funding!Q32*Funding!Q30/100*Funding!Q29+Funding!Q31 | ... AU33: =Funding!AU32*Funding!AU30/100*Funding!AU29+Funding!AU31
D34: Coverage test year flag | E34: flag | J34: =(Time!J$4>=Inputs!$F$291)*(Time!J$4<=Inputs!$F$292) | K34: =(Time!K$4>=Inputs!$F$291)*(Time!K$4<=Inputs!$F$292) | L34: =(Time!L$4>=Inputs!$F$291)*(Time!L$4<=Inputs!$F$292) | M34: =(Time!M$4>=Inputs!$F$291)*(Time!M$4<=Inputs!$F$292) | N34: =(Time!N$4>=Inputs!$F$291)*(Time!N$4<=Inputs!$F$292) | O34: =(Time!O$4>=Inputs!$F$291)*(Time!O$4<=Inputs!$F$292) | P34: =(Time!P$4>=Inputs!$F$291)*(Time!P$4<=Inputs!$F$292) | Q34: =(Time!Q$4>=Inputs!$F$291)*(Time!Q$4<=Inputs!$F$292) | ... AU34: =(Time!AU$4>=Inputs!$F$291)*(Time!AU$4<=Inputs!$F$292)
D35: Face supported at 1.75x coverage | E35: USD m | J35: =IF(Funding!J34>0,Funding!J26/(Inputs!$F$289*IF(Funding!J33>0,Funding!J33,1)),Inputs!$F$28) | K35: =IF(Funding!K34>0,Funding!K26/(Inputs!$F$289*IF(Funding!K33>0,Funding!K33,1)),Inputs!$F$28) | L35: =IF(Funding!L34>0,Funding!L26/(Inputs!$F$289*IF(Funding!L33>0,Funding!L33,1)),Inputs!$F$28) | M35: =IF(Funding!M34>0,Funding!M26/(Inputs!$F$289*IF(Funding!M33>0,Funding!M33,1)),Inputs!$F$28) | N35: =IF(Funding!N34>0,Funding!N26/(Inputs!$F$289*IF(Funding!N33>0,Funding!N33,1)),Inputs!$F$28) | O35: =IF(Funding!O34>0,Funding!O26/(Inputs!$F$289*IF(Funding!O33>0,Funding!O33,1)),Inputs!$F$28) | P35: =IF(Funding!P34>0,Funding!P26/(Inputs!$F$289*IF(Funding!P33>0,Funding!P33,1)),Inputs!$F$28) | Q35: =IF(Funding!Q34>0,Funding!Q26/(Inputs!$F$289*IF(Funding!Q33>0,Funding!Q33,1)),Inputs!$F$28) | ... AU35: =IF(Funding!AU34>0,Funding!AU26/(Inputs!$F$289*IF(Funding!AU33>0,Funding!AU33,1)),Inputs!$F$28)
D36: Face supported by coverage (minimum over test years) | E36: USD m | F36: =MIN(Funding!$J$35:$AU$35)
D37: Opco equity value at March 22, 2022: years from valuation date | E37: years | J37: =MAX(0,(Time!J$6-Inputs!$F$256)/Inputs!$F$27) | K37: =MAX(0,(Time!K$6-Inputs!$F$256)/Inputs!$F$27) | L37: =MAX(0,(Time!L$6-Inputs!$F$256)/Inputs!$F$27) | M37: =MAX(0,(Time!M$6-Inputs!$F$256)/Inputs!$F$27) | N37: =MAX(0,(Time!N$6-Inputs!$F$256)/Inputs!$F$27) | O37: =MAX(0,(Time!O$6-Inputs!$F$256)/Inputs!$F$27) | P37: =MAX(0,(Time!P$6-Inputs!$F$256)/Inputs!$F$27) | Q37: =MAX(0,(Time!Q$6-Inputs!$F$256)/Inputs!$F$27) | ... AU37: =MAX(0,(Time!AU$6-Inputs!$F$256)/Inputs!$F$27)
D38: Opco equity value at March 22, 2022: levered discount factor weighted by revenue bucket | E38: factor | J38: =(Time!J$6>=Inputs!$F$256)*(Operations!J774*(1+Inputs!$F$336/100)^(-Funding!J37)+Operations!J775*(1+Inputs!$F$337/100)^(-Funding!J37)+Operations!J776*(1+Inputs!$F$338/100)^(-Funding!J37)) | K38: =(Time!K$6>=Inputs!$F$256)*(Operations!K774*(1+Inputs!$F$336/100)^(-Funding!K37)+Operations!K775*(1+Inputs!$F$337/100)^(-Funding!K37)+Operations!K776*(1+Inputs!$F$338/100)^(-Funding!K37)) | L38: =(Time!L$6>=Inputs!$F$256)*(Operations!L774*(1+Inputs!$F$336/100)^(-Funding!L37)+Operations!L775*(1+Inputs!$F$337/100)^(-Funding!L37)+Operations!L776*(1+Inputs!$F$338/100)^(-Funding!L37)) | M38: =(Time!M$6>=Inputs!$F$256)*(Operations!M774*(1+Inputs!$F$336/100)^(-Funding!M37)+Operations!M775*(1+Inputs!$F$337/100)^(-Funding!M37)+Operations!M776*(1+Inputs!$F$338/100)^(-Funding!M37)) | N38: =(Time!N$6>=Inputs!$F$256)*(Operations!N774*(1+Inputs!$F$336/100)^(-Funding!N37)+Operations!N775*(1+Inputs!$F$337/100)^(-Funding!N37)+Operations!N776*(1+Inputs!$F$338/100)^(-Funding!N37)) | O38: =(Time!O$6>=Inputs!$F$256)*(Operations!O774*(1+Inputs!$F$336/100)^(-Funding!O37)+Operations!O775*(1+Inputs!$F$337/100)^(-Funding!O37)+Operations!O776*(1+Inputs!$F$338/100)^(-Funding!O37)) | P38: =(Time!P$6>=Inputs!$F$256)*(Operations!P774*(1+Inputs!$F$336/100)^(-Funding!P37)+Operations!P775*(1+Inputs!$F$337/100)^(-Funding!P37)+Operations!P776*(1+Inputs!$F$338/100)^(-Funding!P37)) | Q38: =(Time!Q$6>=Inputs!$F$256)*(Operations!Q774*(1+Inputs!$F$336/100)^(-Funding!Q37)+Operations!Q775*(1+Inputs!$F$337/100)^(-Funding!Q37)+Operations!Q776*(1+Inputs!$F$338/100)^(-Funding!Q37)) | ... AU38: =(Time!AU$6>=Inputs!$F$256)*(Operations!AU774*(1+Inputs!$F$336/100)^(-Funding!AU37)+Operations!AU775*(1+Inputs!$F$337/100)^(-Funding!AU37)+Operations!AU776*(1+Inputs!$F$338/100)^(-Funding!AU37))
D39: Opco equity value at levered equity rates | E39: USD m | F39: =SUMPRODUCT(Funding!$J$26:$AU$26,Funding!$J$38:$AU$38)
D40: Cap: 45% of opco equity value | E40: USD m | F40: =Inputs!$F$290/100*Funding!$F$39
D41: Holdco TLB face | E41: USD m | F41: =MIN(Funding!$F$36,Funding!$F$40)
A43: Redfern term loan, August 31, 2023 (toll cash flow only)
D44: Interest period fraction | E44: fraction | J44: =MAX(0,MIN(Inputs!$F$294,Time!J$6)-MAX(Inputs!$F$293,Time!J$5))/Time!J$7 | K44: =MAX(0,MIN(Inputs!$F$294,Time!K$6)-MAX(Inputs!$F$293,Time!K$5))/Time!K$7 | L44: =MAX(0,MIN(Inputs!$F$294,Time!L$6)-MAX(Inputs!$F$293,Time!L$5))/Time!L$7 | M44: =MAX(0,MIN(Inputs!$F$294,Time!M$6)-MAX(Inputs!$F$293,Time!M$5))/Time!M$7 | N44: =MAX(0,MIN(Inputs!$F$294,Time!N$6)-MAX(Inputs!$F$293,Time!N$5))/Time!N$7 | O44: =MAX(0,MIN(Inputs!$F$294,Time!O$6)-MAX(Inputs!$F$293,Time!O$5))/Time!O$7 | P44: =MAX(0,MIN(Inputs!$F$294,Time!P$6)-MAX(Inputs!$F$293,Time!P$5))/Time!P$7 | Q44: =MAX(0,MIN(Inputs!$F$294,Time!Q$6)-MAX(Inputs!$F$293,Time!Q$5))/Time!Q$7 | ... AU44: =MAX(0,MIN(Inputs!$F$294,Time!AU$6)-MAX(Inputs!$F$293,Time!AU$5))/Time!AU$7
D45: R6 annualized cash costs (opex, surety, margin tax) | E45: USD m | J45: =IF(Operations!J647>0,(Operations!J658+Operations!J660+Operations!J661)/Operations!J647,0) | K45: =IF(Operations!K647>0,(Operations!K658+Operations!K660+Operations!K661)/Operations!K647,0) | L45: =IF(Operations!L647>0,(Operations!L658+Operations!L660+Operations!L661)/Operations!L647,0) | M45: =IF(Operations!M647>0,(Operations!M658+Operations!M660+Operations!M661)/Operations!M647,0) | N45: =IF(Operations!N647>0,(Operations!N658+Operations!N660+Operations!N661)/Operations!N647,0) | O45: =IF(Operations!O647>0,(Operations!O658+Operations!O660+Operations!O661)/Operations!O647,0) | P45: =IF(Operations!P647>0,(Operations!P658+Operations!P660+Operations!P661)/Operations!P647,0) | Q45: =IF(Operations!Q647>0,(Operations!Q658+Operations!Q660+Operations!Q661)/Operations!Q647,0) | ... AU45: =IF(Operations!AU647>0,(Operations!AU658+Operations!AU660+Operations!AU661)/Operations!AU647,0)
D46: Toll cash flow for sizing | E46: USD m | J46: =(Inputs!$F$206*Inputs!$F$207*Inputs!$F$143/1000-Funding!J45)*Funding!J44-Operations!J663*(Funding!J44>0) | K46: =(Inputs!$F$206*Inputs!$F$207*Inputs!$F$143/1000-Funding!K45)*Funding!K44-Operations!K663*(Funding!K44>0) | L46: =(Inputs!$F$206*Inputs!$F$207*Inputs!$F$143/1000-Funding!L45)*Funding!L44-Operations!L663*(Funding!L44>0) | M46: =(Inputs!$F$206*Inputs!$F$207*Inputs!$F$143/1000-Funding!M45)*Funding!M44-Operations!M663*(Funding!M44>0) | N46: =(Inputs!$F$206*Inputs!$F$207*Inputs!$F$143/1000-Funding!N45)*Funding!N44-Operations!N663*(Funding!N44>0) | O46: =(Inputs!$F$206*Inputs!$F$207*Inputs!$F$143/1000-Funding!O45)*Funding!O44-Operations!O663*(Funding!O44>0) | P46: =(Inputs!$F$206*Inputs!$F$207*Inputs!$F$143/1000-Funding!P45)*Funding!P44-Operations!P663*(Funding!P44>0) | Q46: =(Inputs!$F$206*Inputs!$F$207*Inputs!$F$143/1000-Funding!Q45)*Funding!Q44-Operations!Q663*(Funding!Q44>0) | ... AU46: =(Inputs!$F$206*Inputs!$F$207*Inputs!$F$143/1000-Funding!AU45)*Funding!AU44-Operations!AU663*(Funding!AU44>0)
D47: Sculpted debt service (toll CF / 1.35x) | E47: USD m | J47: =IF(Funding!J44>0,Funding!J46/Inputs!$F$297,0) | K47: =IF(Funding!K44>0,Funding!K46/Inputs!$F$297,0) | L47: =IF(Funding!L44>0,Funding!L46/Inputs!$F$297,0) | M47: =IF(Funding!M44>0,Funding!M46/Inputs!$F$297,0) | N47: =IF(Funding!N44>0,Funding!N46/Inputs!$F$297,0) | O47: =IF(Funding!O44>0,Funding!O46/Inputs!$F$297,0) | P47: =IF(Funding!P44>0,Funding!P46/Inputs!$F$297,0) | Q47: =IF(Funding!Q44>0,Funding!Q46/Inputs!$F$297,0) | ... AU47: =IF(Funding!AU44>0,Funding!AU46/Inputs!$F$297,0)
D48: All-in rate | E48: % | J48: =Inputs!$F$298/100*Inputs!$F$299+(1-Inputs!$F$298/100)*Inputs!J80+Inputs!$F$295 | K48: =Inputs!$F$298/100*Inputs!$F$299+(1-Inputs!$F$298/100)*Inputs!K80+Inputs!$F$295 | L48: =Inputs!$F$298/100*Inputs!$F$299+(1-Inputs!$F$298/100)*Inputs!L80+Inputs!$F$295 | M48: =Inputs!$F$298/100*Inputs!$F$299+(1-Inputs!$F$298/100)*Inputs!M80+Inputs!$F$295 | N48: =Inputs!$F$298/100*Inputs!$F$299+(1-Inputs!$F$298/100)*Inputs!N80+Inputs!$F$295 | O48: =Inputs!$F$298/100*Inputs!$F$299+(1-Inputs!$F$298/100)*Inputs!O80+Inputs!$F$295 | P48: =Inputs!$F$298/100*Inputs!$F$299+(1-Inputs!$F$298/100)*Inputs!P80+Inputs!$F$295 | Q48: =Inputs!$F$298/100*Inputs!$F$299+(1-Inputs!$F$298/100)*Inputs!Q80+Inputs!$F$295 | ... AU48: =Inputs!$F$298/100*Inputs!$F$299+(1-Inputs!$F$298/100)*Inputs!AU80+Inputs!$F$295
D49: Discount factor | E49: factor | J49: =IF(Time!J$4=Inputs!$F$23,1,I49)/(1+Funding!J48/100*Funding!J44) | K49: =IF(Time!K$4=Inputs!$F$23,1,J49)/(1+Funding!K48/100*Funding!K44) | L49: =IF(Time!L$4=Inputs!$F$23,1,K49)/(1+Funding!L48/100*Funding!L44) | M49: =IF(Time!M$4=Inputs!$F$23,1,L49)/(1+Funding!M48/100*Funding!M44) | N49: =IF(Time!N$4=Inputs!$F$23,1,M49)/(1+Funding!N48/100*Funding!N44) | O49: =IF(Time!O$4=Inputs!$F$23,1,N49)/(1+Funding!O48/100*Funding!O44) | P49: =IF(Time!P$4=Inputs!$F$23,1,O49)/(1+Funding!P48/100*Funding!P44) | Q49: =IF(Time!Q$4=Inputs!$F$23,1,P49)/(1+Funding!Q48/100*Funding!Q44) | ... AU49: =IF(Time!AU$4=Inputs!$F$23,1,AT49)/(1+Funding!AU48/100*Funding!AU44)
D50: Redfern loan amount | E50: USD m | F50: =SUMPRODUCT(Funding!$J$47:$AU$47,Funding!$J$49:$AU$49)
D51: Sculpted schedule: opening balance | E51: USD m | J51: =IF(Time!J$4=YEAR(Inputs!$F$293),Funding!$F$50,I53) | K51: =IF(Time!K$4=YEAR(Inputs!$F$293),Funding!$F$50,J53) | L51: =IF(Time!L$4=YEAR(Inputs!$F$293),Funding!$F$50,K53) | M51: =IF(Time!M$4=YEAR(Inputs!$F$293),Funding!$F$50,L53) | N51: =IF(Time!N$4=YEAR(Inputs!$F$293),Funding!$F$50,M53) | O51: =IF(Time!O$4=YEAR(Inputs!$F$293),Funding!$F$50,N53) | P51: =IF(Time!P$4=YEAR(Inputs!$F$293),Funding!$F$50,O53) | Q51: =IF(Time!Q$4=YEAR(Inputs!$F$293),Funding!$F$50,P53) | ... AU51: =IF(Time!AU$4=YEAR(Inputs!$F$293),Funding!$F$50,AT53)
D52: Sculpted schedule: principal | E52: USD m | G52: =SUM(J52:AU52) | J52: =IF(Funding!J44>0,Funding!J47-Funding!J51*Funding!J48/100*Funding!J44,0) | K52: =IF(Funding!K44>0,Funding!K47-Funding!K51*Funding!K48/100*Funding!K44,0) | L52: =IF(Funding!L44>0,Funding!L47-Funding!L51*Funding!L48/100*Funding!L44,0) | M52: =IF(Funding!M44>0,Funding!M47-Funding!M51*Funding!M48/100*Funding!M44,0) | N52: =IF(Funding!N44>0,Funding!N47-Funding!N51*Funding!N48/100*Funding!N44,0) | O52: =IF(Funding!O44>0,Funding!O47-Funding!O51*Funding!O48/100*Funding!O44,0) | P52: =IF(Funding!P44>0,Funding!P47-Funding!P51*Funding!P48/100*Funding!P44,0) | Q52: =IF(Funding!Q44>0,Funding!Q47-Funding!Q51*Funding!Q48/100*Funding!Q44,0) | ... AU52: =IF(Funding!AU44>0,Funding!AU47-Funding!AU51*Funding!AU48/100*Funding!AU44,0)
D53: Sculpted schedule: closing balance | E53: USD m | J53: =Funding!J51-Funding!J52 | K53: =Funding!K51-Funding!K52 | L53: =Funding!L51-Funding!L52 | M53: =Funding!M51-Funding!M52 | N53: =Funding!N51-Funding!N52 | O53: =Funding!O51-Funding!O52 | P53: =Funding!P51-Funding!P52 | Q53: =Funding!Q51-Funding!Q52 | ... AU53: =Funding!AU51-Funding!AU52
A55: Holdco incremental term loan, February 15, 2024 (R7 and R8)
D56: Interest period fraction to maturity | E56: fraction | J56: =MAX(0,MIN(Inputs!$F$301,Time!J$6)-MAX(Inputs!$F$300,Time!J$5))/Time!J$7 | K56: =MAX(0,MIN(Inputs!$F$301,Time!K$6)-MAX(Inputs!$F$300,Time!K$5))/Time!K$7 | L56: =MAX(0,MIN(Inputs!$F$301,Time!L$6)-MAX(Inputs!$F$300,Time!L$5))/Time!L$7 | M56: =MAX(0,MIN(Inputs!$F$301,Time!M$6)-MAX(Inputs!$F$300,Time!M$5))/Time!M$7 | N56: =MAX(0,MIN(Inputs!$F$301,Time!N$6)-MAX(Inputs!$F$300,Time!N$5))/Time!N$7 | O56: =MAX(0,MIN(Inputs!$F$301,Time!O$6)-MAX(Inputs!$F$300,Time!O$5))/Time!O$7 | P56: =MAX(0,MIN(Inputs!$F$301,Time!P$6)-MAX(Inputs!$F$300,Time!P$5))/Time!P$7 | Q56: =MAX(0,MIN(Inputs!$F$301,Time!Q$6)-MAX(Inputs!$F$300,Time!Q$5))/Time!Q$7 | ... AU56: =MAX(0,MIN(Inputs!$F$301,Time!AU$6)-MAX(Inputs!$F$300,Time!AU$5))/Time!AU$7
D57: Rate (SOFR floored + margin) | E57: % | J57: =MAX(Inputs!J80,Inputs!$F$285)+Inputs!$F$302 | K57: =MAX(Inputs!K80,Inputs!$F$285)+Inputs!$F$302 | L57: =MAX(Inputs!L80,Inputs!$F$285)+Inputs!$F$302 | M57: =MAX(Inputs!M80,Inputs!$F$285)+Inputs!$F$302 | N57: =MAX(Inputs!N80,Inputs!$F$285)+Inputs!$F$302 | O57: =MAX(Inputs!O80,Inputs!$F$285)+Inputs!$F$302 | P57: =MAX(Inputs!P80,Inputs!$F$285)+Inputs!$F$302 | Q57: =MAX(Inputs!Q80,Inputs!$F$285)+Inputs!$F$302 | ... AU57: =MAX(Inputs!AU80,Inputs!$F$285)+Inputs!$F$302
D58: Scheduled amortization per unit of face | E58: factor | J58: =Inputs!$F$304/100*Funding!J56 | K58: =Inputs!$F$304/100*Funding!K56 | L58: =Inputs!$F$304/100*Funding!L56 | M58: =Inputs!$F$304/100*Funding!M56 | N58: =Inputs!$F$304/100*Funding!N56 | O58: =Inputs!$F$304/100*Funding!O56 | P58: =Inputs!$F$304/100*Funding!P56 | Q58: =Inputs!$F$304/100*Funding!Q56 | ... AU58: =Inputs!$F$304/100*Funding!AU56
D59: Scheduled balance per unit of face | E59: factor | J59: =IF(Time!J$4=Inputs!$F$23,1,I59-I58) | K59: =IF(Time!K$4=Inputs!$F$23,1,J59-J58) | L59: =IF(Time!L$4=Inputs!$F$23,1,K59-K58) | M59: =IF(Time!M$4=Inputs!$F$23,1,L59-L58) | N59: =IF(Time!N$4=Inputs!$F$23,1,M59-M58) | O59: =IF(Time!O$4=Inputs!$F$23,1,N59-N58) | P59: =IF(Time!P$4=Inputs!$F$23,1,O59-O58) | Q59: =IF(Time!Q$4=Inputs!$F$23,1,P59-P58) | ... AU59: =IF(Time!AU$4=Inputs!$F$23,1,AT59-AT58)
D60: Debt service per unit of face | E60: factor | J60: =Funding!J59*Funding!J57/100*Funding!J56+Funding!J58 | K60: =Funding!K59*Funding!K57/100*Funding!K56+Funding!K58 | L60: =Funding!L59*Funding!L57/100*Funding!L56+Funding!L58 | M60: =Funding!M59*Funding!M57/100*Funding!M56+Funding!M58 | N60: =Funding!N59*Funding!N57/100*Funding!N56+Funding!N58 | O60: =Funding!O59*Funding!O57/100*Funding!O56+Funding!O58 | P60: =Funding!P59*Funding!P57/100*Funding!P56+Funding!P58 | Q60: =Funding!Q59*Funding!Q57/100*Funding!Q56+Funding!Q58 | ... AU60: =Funding!AU59*Funding!AU57/100*Funding!AU56+Funding!AU58
D61: Coverage test year flag | E61: flag | J61: =(Time!J$4>=Inputs!$F$305)*(Time!J$4<=Inputs!$F$306) | K61: =(Time!K$4>=Inputs!$F$305)*(Time!K$4<=Inputs!$F$306) | L61: =(Time!L$4>=Inputs!$F$305)*(Time!L$4<=Inputs!$F$306) | M61: =(Time!M$4>=Inputs!$F$305)*(Time!M$4<=Inputs!$F$306) | N61: =(Time!N$4>=Inputs!$F$305)*(Time!N$4<=Inputs!$F$306) | O61: =(Time!O$4>=Inputs!$F$305)*(Time!O$4<=Inputs!$F$306) | P61: =(Time!P$4>=Inputs!$F$305)*(Time!P$4<=Inputs!$F$306) | Q61: =(Time!Q$4>=Inputs!$F$305)*(Time!Q$4<=Inputs!$F$306) | ... AU61: =(Time!AU$4>=Inputs!$F$305)*(Time!AU$4<=Inputs!$F$306)
D62: Face supported at 1.75x on R7 and R8 distributions | E62: USD m | J62: =IF(Funding!J61>0,Operations!J773/(Inputs!$F$289*IF(Funding!J60>0,Funding!J60,1)),Inputs!$F$28) | K62: =IF(Funding!K61>0,Operations!K773/(Inputs!$F$289*IF(Funding!K60>0,Funding!K60,1)),Inputs!$F$28) | L62: =IF(Funding!L61>0,Operations!L773/(Inputs!$F$289*IF(Funding!L60>0,Funding!L60,1)),Inputs!$F$28) | M62: =IF(Funding!M61>0,Operations!M773/(Inputs!$F$289*IF(Funding!M60>0,Funding!M60,1)),Inputs!$F$28) | N62: =IF(Funding!N61>0,Operations!N773/(Inputs!$F$289*IF(Funding!N60>0,Funding!N60,1)),Inputs!$F$28) | O62: =IF(Funding!O61>0,Operations!O773/(Inputs!$F$289*IF(Funding!O60>0,Funding!O60,1)),Inputs!$F$28) | P62: =IF(Funding!P61>0,Operations!P773/(Inputs!$F$289*IF(Funding!P60>0,Funding!P60,1)),Inputs!$F$28) | Q62: =IF(Funding!Q61>0,Operations!Q773/(Inputs!$F$289*IF(Funding!Q60>0,Funding!Q60,1)),Inputs!$F$28) | ... AU62: =IF(Funding!AU61>0,Operations!AU773/(Inputs!$F$289*IF(Funding!AU60>0,Funding!AU60,1)),Inputs!$F$28)
D63: Holdco incremental face | E63: USD m | F63: =MIN(Funding!$J$62:$AU$62)
A65: 2025 refinancing: USPP senior secured notes (sized on base P50 and P99 blocks)
D66: Series A amortization years | E66: flag | J66: =(Time!J$4>=Inputs!$F$309)*(Time!J$4<=Inputs!$F$309+Inputs!$F$310-1) | K66: =(Time!K$4>=Inputs!$F$309)*(Time!K$4<=Inputs!$F$309+Inputs!$F$310-1) | L66: =(Time!L$4>=Inputs!$F$309)*(Time!L$4<=Inputs!$F$309+Inputs!$F$310-1) | M66: =(Time!M$4>=Inputs!$F$309)*(Time!M$4<=Inputs!$F$309+Inputs!$F$310-1) | N66: =(Time!N$4>=Inputs!$F$309)*(Time!N$4<=Inputs!$F$309+Inputs!$F$310-1) | O66: =(Time!O$4>=Inputs!$F$309)*(Time!O$4<=Inputs!$F$309+Inputs!$F$310-1) | P66: =(Time!P$4>=Inputs!$F$309)*(Time!P$4<=Inputs!$F$309+Inputs!$F$310-1) | Q66: =(Time!Q$4>=Inputs!$F$309)*(Time!Q$4<=Inputs!$F$309+Inputs!$F$310-1) | ... AU66: =(Time!AU$4>=Inputs!$F$309)*(Time!AU$4<=Inputs!$F$309+Inputs!$F$310-1)
D67: Series B amortization years | E67: flag | J67: =(Time!J$4>=Inputs!$F$309+Inputs!$F$310)*(Time!J$4<=Inputs!$F$309+Inputs!$F$312-1) | K67: =(Time!K$4>=Inputs!$F$309+Inputs!$F$310)*(Time!K$4<=Inputs!$F$309+Inputs!$F$312-1) | L67: =(Time!L$4>=Inputs!$F$309+Inputs!$F$310)*(Time!L$4<=Inputs!$F$309+Inputs!$F$312-1) | M67: =(Time!M$4>=Inputs!$F$309+Inputs!$F$310)*(Time!M$4<=Inputs!$F$309+Inputs!$F$312-1) | N67: =(Time!N$4>=Inputs!$F$309+Inputs!$F$310)*(Time!N$4<=Inputs!$F$309+Inputs!$F$312-1) | O67: =(Time!O$4>=Inputs!$F$309+Inputs!$F$310)*(Time!O$4<=Inputs!$F$309+Inputs!$F$312-1) | P67: =(Time!P$4>=Inputs!$F$309+Inputs!$F$310)*(Time!P$4<=Inputs!$F$309+Inputs!$F$312-1) | Q67: =(Time!Q$4>=Inputs!$F$309+Inputs!$F$310)*(Time!Q$4<=Inputs!$F$309+Inputs!$F$312-1) | ... AU67: =(Time!AU$4>=Inputs!$F$309+Inputs!$F$310)*(Time!AU$4<=Inputs!$F$309+Inputs!$F$312-1)
D68: Series C amortization years | E68: flag | J68: =(Time!J$4>=Inputs!$F$309+Inputs!$F$312)*(Time!J$4<=Inputs!$F$309+Inputs!$F$314-1) | K68: =(Time!K$4>=Inputs!$F$309+Inputs!$F$312)*(Time!K$4<=Inputs!$F$309+Inputs!$F$314-1) | L68: =(Time!L$4>=Inputs!$F$309+Inputs!$F$312)*(Time!L$4<=Inputs!$F$309+Inputs!$F$314-1) | M68: =(Time!M$4>=Inputs!$F$309+Inputs!$F$312)*(Time!M$4<=Inputs!$F$309+Inputs!$F$314-1) | N68: =(Time!N$4>=Inputs!$F$309+Inputs!$F$312)*(Time!N$4<=Inputs!$F$309+Inputs!$F$314-1) | O68: =(Time!O$4>=Inputs!$F$309+Inputs!$F$312)*(Time!O$4<=Inputs!$F$309+Inputs!$F$314-1) | P68: =(Time!P$4>=Inputs!$F$309+Inputs!$F$312)*(Time!P$4<=Inputs!$F$309+Inputs!$F$314-1) | Q68: =(Time!Q$4>=Inputs!$F$309+Inputs!$F$312)*(Time!Q$4<=Inputs!$F$309+Inputs!$F$314-1) | ... AU68: =(Time!AU$4>=Inputs!$F$309+Inputs!$F$312)*(Time!AU$4<=Inputs!$F$309+Inputs!$F$314-1)
D69: Notes outstanding flag | E69: flag | J69: =Funding!J66+Funding!J67+Funding!J68 | K69: =Funding!K66+Funding!K67+Funding!K68 | L69: =Funding!L66+Funding!L67+Funding!L68 | M69: =Funding!M66+Funding!M67+Funding!M68 | N69: =Funding!N66+Funding!N67+Funding!N68 | O69: =Funding!O66+Funding!O67+Funding!O68 | P69: =Funding!P66+Funding!P67+Funding!P68 | Q69: =Funding!Q66+Funding!Q67+Funding!Q68 | ... AU69: =Funding!AU66+Funding!AU67+Funding!AU68
D70: Coupon of the series amortizing in the year | E70: % | J70: =Funding!J66*Inputs!$F$311+Funding!J67*Inputs!$F$313+Funding!J68*Inputs!$F$315 | K70: =Funding!K66*Inputs!$F$311+Funding!K67*Inputs!$F$313+Funding!K68*Inputs!$F$315 | L70: =Funding!L66*Inputs!$F$311+Funding!L67*Inputs!$F$313+Funding!L68*Inputs!$F$315 | M70: =Funding!M66*Inputs!$F$311+Funding!M67*Inputs!$F$313+Funding!M68*Inputs!$F$315 | N70: =Funding!N66*Inputs!$F$311+Funding!N67*Inputs!$F$313+Funding!N68*Inputs!$F$315 | O70: =Funding!O66*Inputs!$F$311+Funding!O67*Inputs!$F$313+Funding!O68*Inputs!$F$315 | P70: =Funding!P66*Inputs!$F$311+Funding!P67*Inputs!$F$313+Funding!P68*Inputs!$F$315 | Q70: =Funding!Q66*Inputs!$F$311+Funding!Q67*Inputs!$F$313+Funding!Q68*Inputs!$F$315 | ... AU70: =Funding!AU66*Inputs!$F$311+Funding!AU67*Inputs!$F$313+Funding!AU68*Inputs!$F$315
D71: Debt-service capacity by bucket | E71: USD m | J71: =Operations!J783/Inputs!$F$316+Operations!J784/Inputs!$F$317+Operations!J785/Inputs!$F$318 | K71: =Operations!K783/Inputs!$F$316+Operations!K784/Inputs!$F$317+Operations!K785/Inputs!$F$318 | L71: =Operations!L783/Inputs!$F$316+Operations!L784/Inputs!$F$317+Operations!L785/Inputs!$F$318 | M71: =Operations!M783/Inputs!$F$316+Operations!M784/Inputs!$F$317+Operations!M785/Inputs!$F$318 | N71: =Operations!N783/Inputs!$F$316+Operations!N784/Inputs!$F$317+Operations!N785/Inputs!$F$318 | O71: =Operations!O783/Inputs!$F$316+Operations!O784/Inputs!$F$317+Operations!O785/Inputs!$F$318 | P71: =Operations!P783/Inputs!$F$316+Operations!P784/Inputs!$F$317+Operations!P785/Inputs!$F$318 | Q71: =Operations!Q783/Inputs!$F$316+Operations!Q784/Inputs!$F$317+Operations!Q785/Inputs!$F$318 | ... AU71: =Operations!AU783/Inputs!$F$316+Operations!AU784/Inputs!$F$317+Operations!AU785/Inputs!$F$318
D72: Debt-service capacity at P99 (1.05x) | E72: USD m | J72: =Operations!J1143/Inputs!$F$319 | K72: =Operations!K1143/Inputs!$F$319 | L72: =Operations!L1143/Inputs!$F$319 | M72: =Operations!M1143/Inputs!$F$319 | N72: =Operations!N1143/Inputs!$F$319 | O72: =Operations!O1143/Inputs!$F$319 | P72: =Operations!P1143/Inputs!$F$319 | Q72: =Operations!Q1143/Inputs!$F$319 | ... AU72: =Operations!AU1143/Inputs!$F$319
D73: Sculpted debt service | E73: USD m | G73: =SUM(J73:AU73) | J73: =IF(Funding!J69>0,MAX(0,MIN(Funding!J71,Funding!J72)),0) | K73: =IF(Funding!K69>0,MAX(0,MIN(Funding!K71,Funding!K72)),0) | L73: =IF(Funding!L69>0,MAX(0,MIN(Funding!L71,Funding!L72)),0) | M73: =IF(Funding!M69>0,MAX(0,MIN(Funding!M71,Funding!M72)),0) | N73: =IF(Funding!N69>0,MAX(0,MIN(Funding!N71,Funding!N72)),0) | O73: =IF(Funding!O69>0,MAX(0,MIN(Funding!O71,Funding!O72)),0) | P73: =IF(Funding!P69>0,MAX(0,MIN(Funding!P71,Funding!P72)),0) | Q73: =IF(Funding!Q69>0,MAX(0,MIN(Funding!Q71,Funding!Q72)),0) | ... AU73: =IF(Funding!AU69>0,MAX(0,MIN(Funding!AU71,Funding!AU72)),0)
D74: Principal, solved backward: (DS - sum of coupons x next-year opening balances) / (1 + coupon of amortizing series) | E74: USD m | G74: =SUM(J74:AU74) | J74: =IF(Funding!J69>0,(Funding!J73-Inputs!$F$311/100*K75-Inputs!$F$313/100*K76-Inputs!$F$315/100*K77)/(1+Funding!J70/100),0) | K74: =IF(Funding!K69>0,(Funding!K73-Inputs!$F$311/100*L75-Inputs!$F$313/100*L76-Inputs!$F$315/100*L77)/(1+Funding!K70/100),0) | L74: =IF(Funding!L69>0,(Funding!L73-Inputs!$F$311/100*M75-Inputs!$F$313/100*M76-Inputs!$F$315/100*M77)/(1+Funding!L70/100),0) | M74: =IF(Funding!M69>0,(Funding!M73-Inputs!$F$311/100*N75-Inputs!$F$313/100*N76-Inputs!$F$315/100*N77)/(1+Funding!M70/100),0) | N74: =IF(Funding!N69>0,(Funding!N73-Inputs!$F$311/100*O75-Inputs!$F$313/100*O76-Inputs!$F$315/100*O77)/(1+Funding!N70/100),0) | O74: =IF(Funding!O69>0,(Funding!O73-Inputs!$F$311/100*P75-Inputs!$F$313/100*P76-Inputs!$F$315/100*P77)/(1+Funding!O70/100),0) | P74: =IF(Funding!P69>0,(Funding!P73-Inputs!$F$311/100*Q75-Inputs!$F$313/100*Q76-Inputs!$F$315/100*Q77)/(1+Funding!P70/100),0) | Q74: =IF(Funding!Q69>0,(Funding!Q73-Inputs!$F$311/100*R75-Inputs!$F$313/100*R76-Inputs!$F$315/100*R77)/(1+Funding!Q70/100),0) | ... AU74: =IF(Funding!AU69>0,(Funding!AU73-Inputs!$F$311/100*AV75-Inputs!$F$313/100*AV76-Inputs!$F$315/100*AV77)/(1+Funding!AU70/100),0)
D75: Series A opening balance | E75: USD m | J75: =K75+Funding!J74*Funding!J66 | K75: =L75+Funding!K74*Funding!K66 | L75: =M75+Funding!L74*Funding!L66 | M75: =N75+Funding!M74*Funding!M66 | N75: =O75+Funding!N74*Funding!N66 | O75: =P75+Funding!O74*Funding!O66 | P75: =Q75+Funding!P74*Funding!P66 | Q75: =R75+Funding!Q74*Funding!Q66 | ... AU75: =AV75+Funding!AU74*Funding!AU66
D76: Series B opening balance | E76: USD m | J76: =K76+Funding!J74*Funding!J67 | K76: =L76+Funding!K74*Funding!K67 | L76: =M76+Funding!L74*Funding!L67 | M76: =N76+Funding!M74*Funding!M67 | N76: =O76+Funding!N74*Funding!N67 | O76: =P76+Funding!O74*Funding!O67 | P76: =Q76+Funding!P74*Funding!P67 | Q76: =R76+Funding!Q74*Funding!Q67 | ... AU76: =AV76+Funding!AU74*Funding!AU67
D77: Series C opening balance | E77: USD m | J77: =K77+Funding!J74*Funding!J68 | K77: =L77+Funding!K74*Funding!K68 | L77: =M77+Funding!L74*Funding!L68 | M77: =N77+Funding!M74*Funding!M68 | N77: =O77+Funding!N74*Funding!N68 | O77: =P77+Funding!O74*Funding!O68 | P77: =Q77+Funding!P74*Funding!P68 | Q77: =R77+Funding!Q74*Funding!Q68 | ... AU77: =AV77+Funding!AU74*Funding!AU68
D78: Notes opening balance | E78: USD m | J78: =(Funding!J75+Funding!J76+Funding!J77)*Funding!J69 | K78: =(Funding!K75+Funding!K76+Funding!K77)*Funding!K69 | L78: =(Funding!L75+Funding!L76+Funding!L77)*Funding!L69 | M78: =(Funding!M75+Funding!M76+Funding!M77)*Funding!M69 | N78: =(Funding!N75+Funding!N76+Funding!N77)*Funding!N69 | O78: =(Funding!O75+Funding!O76+Funding!O77)*Funding!O69 | P78: =(Funding!P75+Funding!P76+Funding!P77)*Funding!P69 | Q78: =(Funding!Q75+Funding!Q76+Funding!Q77)*Funding!Q69 | ... AU78: =(Funding!AU75+Funding!AU76+Funding!AU77)*Funding!AU69
D79: Notes interest | E79: USD m | G79: =SUM(J79:AU79) | J79: =(Inputs!$F$311/100*Funding!J75+Inputs!$F$313/100*Funding!J76+Inputs!$F$315/100*Funding!J77)*Funding!J69 | K79: =(Inputs!$F$311/100*Funding!K75+Inputs!$F$313/100*Funding!K76+Inputs!$F$315/100*Funding!K77)*Funding!K69 | L79: =(Inputs!$F$311/100*Funding!L75+Inputs!$F$313/100*Funding!L76+Inputs!$F$315/100*Funding!L77)*Funding!L69 | M79: =(Inputs!$F$311/100*Funding!M75+Inputs!$F$313/100*Funding!M76+Inputs!$F$315/100*Funding!M77)*Funding!M69 | N79: =(Inputs!$F$311/100*Funding!N75+Inputs!$F$313/100*Funding!N76+Inputs!$F$315/100*Funding!N77)*Funding!N69 | O79: =(Inputs!$F$311/100*Funding!O75+Inputs!$F$313/100*Funding!O76+Inputs!$F$315/100*Funding!O77)*Funding!O69 | P79: =(Inputs!$F$311/100*Funding!P75+Inputs!$F$313/100*Funding!P76+Inputs!$F$315/100*Funding!P77)*Funding!P69 | Q79: =(Inputs!$F$311/100*Funding!Q75+Inputs!$F$313/100*Funding!Q76+Inputs!$F$315/100*Funding!Q77)*Funding!Q69 | ... AU79: =(Inputs!$F$311/100*Funding!AU75+Inputs!$F$313/100*Funding!AU76+Inputs!$F$315/100*Funding!AU77)*Funding!AU69
D80: Series A size | E80: USD m | F80: =SUMIF(Time!$J$4:$AU$4,Inputs!$F$309,Funding!$J$75:$AU$75)
D81: Series B size | E81: USD m | F81: =SUMIF(Time!$J$4:$AU$4,Inputs!$F$309,Funding!$J$76:$AU$76)
D82: Series C size | E82: USD m | F82: =SUMIF(Time!$J$4:$AU$4,Inputs!$F$309,Funding!$J$77:$AU$77)
D83: USPP notes total | E83: USD m | F83: =Funding!$F$80+Funding!$F$81+Funding!$F$82
D84: Series A share | E84: % | F84: =100*Funding!$F$80/Funding!$F$83
D85: Series B share | E85: % | F85: =100*Funding!$F$81/Funding!$F$83
D86: Series C share | E86: % | F86: =100*Funding!$F$82/Funding!$F$83
D87: Issue-weighted blended coupon | E87: % | F87: =(Funding!$F$80*Inputs!$F$311+Funding!$F$81*Inputs!$F$313+Funding!$F$82*Inputs!$F$315)/Funding!$F$83
D88: Discount factor at blended coupon (bucket exhibit) | E88: factor | J88: =(1+Funding!$F$87/100)^(-(Time!J$4-Inputs!$F$307))*Funding!J69 | K88: =(1+Funding!$F$87/100)^(-(Time!K$4-Inputs!$F$307))*Funding!K69 | L88: =(1+Funding!$F$87/100)^(-(Time!L$4-Inputs!$F$307))*Funding!L69 | M88: =(1+Funding!$F$87/100)^(-(Time!M$4-Inputs!$F$307))*Funding!M69 | N88: =(1+Funding!$F$87/100)^(-(Time!N$4-Inputs!$F$307))*Funding!N69 | O88: =(1+Funding!$F$87/100)^(-(Time!O$4-Inputs!$F$307))*Funding!O69 | P88: =(1+Funding!$F$87/100)^(-(Time!P$4-Inputs!$F$307))*Funding!P69 | Q88: =(1+Funding!$F$87/100)^(-(Time!Q$4-Inputs!$F$307))*Funding!Q69 | ... AU88: =(1+Funding!$F$87/100)^(-(Time!AU$4-Inputs!$F$307))*Funding!AU69
D89: PV of contracted capacity at blended coupon | E89: USD m | F89: =SUMPRODUCT(Operations!$J$783:$AU$783/Inputs!$F$316,Funding!$J$88:$AU$88)
D90: PV of hedged capacity at blended coupon | E90: USD m | F90: =SUMPRODUCT(Operations!$J$784:$AU$784/Inputs!$F$317,Funding!$J$88:$AU$88)
D91: PV of merchant capacity at blended coupon | E91: USD m | F91: =SUMPRODUCT(Operations!$J$785:$AU$785/Inputs!$F$318,Funding!$J$88:$AU$88)
D92: Years in which the P99 test binds | E92: years | F92: =SUMPRODUCT(--(Funding!$J$72:$AU$72<Funding!$J$71:$AU$71),--(Funding!$J$69:$AU$69>0))
A94: 2025 holdco repricing (sized on post-refinancing base distributions)
D95: Interest period fraction | E95: fraction | J95: =MAX(0,MIN(Inputs!$F$323,Time!J$6)-MAX(Inputs!$F$308,Time!J$5))/Time!J$7 | K95: =MAX(0,MIN(Inputs!$F$323,Time!K$6)-MAX(Inputs!$F$308,Time!K$5))/Time!K$7 | L95: =MAX(0,MIN(Inputs!$F$323,Time!L$6)-MAX(Inputs!$F$308,Time!L$5))/Time!L$7 | M95: =MAX(0,MIN(Inputs!$F$323,Time!M$6)-MAX(Inputs!$F$308,Time!M$5))/Time!M$7 | N95: =MAX(0,MIN(Inputs!$F$323,Time!N$6)-MAX(Inputs!$F$308,Time!N$5))/Time!N$7 | O95: =MAX(0,MIN(Inputs!$F$323,Time!O$6)-MAX(Inputs!$F$308,Time!O$5))/Time!O$7 | P95: =MAX(0,MIN(Inputs!$F$323,Time!P$6)-MAX(Inputs!$F$308,Time!P$5))/Time!P$7 | Q95: =MAX(0,MIN(Inputs!$F$323,Time!Q$6)-MAX(Inputs!$F$308,Time!Q$5))/Time!Q$7 | ... AU95: =MAX(0,MIN(Inputs!$F$323,Time!AU$6)-MAX(Inputs!$F$308,Time!AU$5))/Time!AU$7
D96: Rate (SOFR floored + margin) | E96: % | J96: =MAX(Inputs!J80,Inputs!$F$285)+Inputs!$F$322 | K96: =MAX(Inputs!K80,Inputs!$F$285)+Inputs!$F$322 | L96: =MAX(Inputs!L80,Inputs!$F$285)+Inputs!$F$322 | M96: =MAX(Inputs!M80,Inputs!$F$285)+Inputs!$F$322 | N96: =MAX(Inputs!N80,Inputs!$F$285)+Inputs!$F$322 | O96: =MAX(Inputs!O80,Inputs!$F$285)+Inputs!$F$322 | P96: =MAX(Inputs!P80,Inputs!$F$285)+Inputs!$F$322 | Q96: =MAX(Inputs!Q80,Inputs!$F$285)+Inputs!$F$322 | ... AU96: =MAX(Inputs!AU80,Inputs!$F$285)+Inputs!$F$322
D97: Scheduled amortization per unit of face | E97: factor | J97: =Inputs!$F$325/100*Funding!J95 | K97: =Inputs!$F$325/100*Funding!K95 | L97: =Inputs!$F$325/100*Funding!L95 | M97: =Inputs!$F$325/100*Funding!M95 | N97: =Inputs!$F$325/100*Funding!N95 | O97: =Inputs!$F$325/100*Funding!O95 | P97: =Inputs!$F$325/100*Funding!P95 | Q97: =Inputs!$F$325/100*Funding!Q95 | ... AU97: =Inputs!$F$325/100*Funding!AU95
D98: Scheduled balance per unit of face | E98: factor | J98: =IF(Time!J$4=Inputs!$F$23,1,I98-I97) | K98: =IF(Time!K$4=Inputs!$F$23,1,J98-J97) | L98: =IF(Time!L$4=Inputs!$F$23,1,K98-K97) | M98: =IF(Time!M$4=Inputs!$F$23,1,L98-L97) | N98: =IF(Time!N$4=Inputs!$F$23,1,M98-M97) | O98: =IF(Time!O$4=Inputs!$F$23,1,N98-N97) | P98: =IF(Time!P$4=Inputs!$F$23,1,O98-O97) | Q98: =IF(Time!Q$4=Inputs!$F$23,1,P98-P97) | ... AU98: =IF(Time!AU$4=Inputs!$F$23,1,AT98-AT97)
D99: Debt service per unit of face | E99: factor | J99: =Funding!J98*Funding!J96/100*Funding!J95+Funding!J97 | K99: =Funding!K98*Funding!K96/100*Funding!K95+Funding!K97 | L99: =Funding!L98*Funding!L96/100*Funding!L95+Funding!L97 | M99: =Funding!M98*Funding!M96/100*Funding!M95+Funding!M97 | N99: =Funding!N98*Funding!N96/100*Funding!N95+Funding!N97 | O99: =Funding!O98*Funding!O96/100*Funding!O95+Funding!O97 | P99: =Funding!P98*Funding!P96/100*Funding!P95+Funding!P97 | Q99: =Funding!Q98*Funding!Q96/100*Funding!Q95+Funding!Q97 | ... AU99: =Funding!AU98*Funding!AU96/100*Funding!AU95+Funding!AU97
D100: Coverage test year flag | E100: flag | J100: =(Time!J$4>=Inputs!$F$326)*(Time!J$4<=Inputs!$F$327) | K100: =(Time!K$4>=Inputs!$F$326)*(Time!K$4<=Inputs!$F$327) | L100: =(Time!L$4>=Inputs!$F$326)*(Time!L$4<=Inputs!$F$327) | M100: =(Time!M$4>=Inputs!$F$326)*(Time!M$4<=Inputs!$F$327) | N100: =(Time!N$4>=Inputs!$F$326)*(Time!N$4<=Inputs!$F$327) | O100: =(Time!O$4>=Inputs!$F$326)*(Time!O$4<=Inputs!$F$327) | P100: =(Time!P$4>=Inputs!$F$326)*(Time!P$4<=Inputs!$F$327) | Q100: =(Time!Q$4>=Inputs!$F$326)*(Time!Q$4<=Inputs!$F$327) | ... AU100: =(Time!AU$4>=Inputs!$F$326)*(Time!AU$4<=Inputs!$F$327)
D101: Base distributions after USPP debt service | E101: USD m | J101: =Operations!J772-Funding!J73 | K101: =Operations!K772-Funding!K73 | L101: =Operations!L772-Funding!L73 | M101: =Operations!M772-Funding!M73 | N101: =Operations!N772-Funding!N73 | O101: =Operations!O772-Funding!O73 | P101: =Operations!P772-Funding!P73 | Q101: =Operations!Q772-Funding!Q73 | ... AU101: =Operations!AU772-Funding!AU73
D102: Face supported at 1.75x | E102: USD m | J102: =IF(Funding!J100>0,Funding!J101/(Inputs!$F$289*IF(Funding!J99>0,Funding!J99,1)),Inputs!$F$28) | K102: =IF(Funding!K100>0,Funding!K101/(Inputs!$F$289*IF(Funding!K99>0,Funding!K99,1)),Inputs!$F$28) | L102: =IF(Funding!L100>0,Funding!L101/(Inputs!$F$289*IF(Funding!L99>0,Funding!L99,1)),Inputs!$F$28) | M102: =IF(Funding!M100>0,Funding!M101/(Inputs!$F$289*IF(Funding!M99>0,Funding!M99,1)),Inputs!$F$28) | N102: =IF(Funding!N100>0,Funding!N101/(Inputs!$F$289*IF(Funding!N99>0,Funding!N99,1)),Inputs!$F$28) | O102: =IF(Funding!O100>0,Funding!O101/(Inputs!$F$289*IF(Funding!O99>0,Funding!O99,1)),Inputs!$F$28) | P102: =IF(Funding!P100>0,Funding!P101/(Inputs!$F$289*IF(Funding!P99>0,Funding!P99,1)),Inputs!$F$28) | Q102: =IF(Funding!Q100>0,Funding!Q101/(Inputs!$F$289*IF(Funding!Q99>0,Funding!Q99,1)),Inputs!$F$28) | ... AU102: =IF(Funding!AU100>0,Funding!AU101/(Inputs!$F$289*IF(Funding!AU99>0,Funding!AU99,1)),Inputs!$F$28)
D103: Repriced holdco face | E103: USD m | F103: =MIN(Funding!$J$102:$AU$102)
A105: Opco debt by asset (pro rata to PV of each asset's own debt-service capacity)
D106: R1 capacity, tl | E106: USD m | J106: =Operations!J465*Operations!J468/Inputs!$F$275+Operations!J465*Operations!J469/Inputs!$F$276+Operations!J465*Operations!J470/Inputs!$F$277 | K106: =Operations!K465*Operations!K468/Inputs!$F$275+Operations!K465*Operations!K469/Inputs!$F$276+Operations!K465*Operations!K470/Inputs!$F$277 | L106: =Operations!L465*Operations!L468/Inputs!$F$275+Operations!L465*Operations!L469/Inputs!$F$276+Operations!L465*Operations!L470/Inputs!$F$277 | M106: =Operations!M465*Operations!M468/Inputs!$F$275+Operations!M465*Operations!M469/Inputs!$F$276+Operations!M465*Operations!M470/Inputs!$F$277 | N106: =Operations!N465*Operations!N468/Inputs!$F$275+Operations!N465*Operations!N469/Inputs!$F$276+Operations!N465*Operations!N470/Inputs!$F$277 | O106: =Operations!O465*Operations!O468/Inputs!$F$275+Operations!O465*Operations!O469/Inputs!$F$276+Operations!O465*Operations!O470/Inputs!$F$277 | P106: =Operations!P465*Operations!P468/Inputs!$F$275+Operations!P465*Operations!P469/Inputs!$F$276+Operations!P465*Operations!P470/Inputs!$F$277 | Q106: =Operations!Q465*Operations!Q468/Inputs!$F$275+Operations!Q465*Operations!Q469/Inputs!$F$276+Operations!Q465*Operations!Q470/Inputs!$F$277 | ... AU106: =Operations!AU465*Operations!AU468/Inputs!$F$275+Operations!AU465*Operations!AU469/Inputs!$F$276+Operations!AU465*Operations!AU470/Inputs!$F$277
D107: PV of capacity, R1 | E107: USD m | F107: =SUMPRODUCT(Funding!$J$106:$AU$106,Funding!$J$16:$AU$16,--(Funding!$J$8:$AU$8>0))
D108: R2 capacity, tl | E108: USD m | J108: =Operations!J507*Operations!J510/Inputs!$F$275+Operations!J507*Operations!J511/Inputs!$F$276+Operations!J507*Operations!J512/Inputs!$F$277 | K108: =Operations!K507*Operations!K510/Inputs!$F$275+Operations!K507*Operations!K511/Inputs!$F$276+Operations!K507*Operations!K512/Inputs!$F$277 | L108: =Operations!L507*Operations!L510/Inputs!$F$275+Operations!L507*Operations!L511/Inputs!$F$276+Operations!L507*Operations!L512/Inputs!$F$277 | M108: =Operations!M507*Operations!M510/Inputs!$F$275+Operations!M507*Operations!M511/Inputs!$F$276+Operations!M507*Operations!M512/Inputs!$F$277 | N108: =Operations!N507*Operations!N510/Inputs!$F$275+Operations!N507*Operations!N511/Inputs!$F$276+Operations!N507*Operations!N512/Inputs!$F$277 | O108: =Operations!O507*Operations!O510/Inputs!$F$275+Operations!O507*Operations!O511/Inputs!$F$276+Operations!O507*Operations!O512/Inputs!$F$277 | P108: =Operations!P507*Operations!P510/Inputs!$F$275+Operations!P507*Operations!P511/Inputs!$F$276+Operations!P507*Operations!P512/Inputs!$F$277 | Q108: =Operations!Q507*Operations!Q510/Inputs!$F$275+Operations!Q507*Operations!Q511/Inputs!$F$276+Operations!Q507*Operations!Q512/Inputs!$F$277 | ... AU108: =Operations!AU507*Operations!AU510/Inputs!$F$275+Operations!AU507*Operations!AU511/Inputs!$F$276+Operations!AU507*Operations!AU512/Inputs!$F$277
...

Sheet Debt
A1: Debt: live schedules (sized amounts held fixed)
A2: Case R, Mesa Corta Renewables. USD m nominal unless stated. Illustrative prices: not ERCOT settlement data and not a forecast.
D4: Year | J4: =Time!J$4 | K4: =Time!K$4 | L4: =Time!L$4 | M4: =Time!M$4 | N4: =Time!N$4 | O4: =Time!O$4 | P4: =Time!P$4 | Q4: =Time!Q$4 | ... AU4: =Time!AU$4
D5: Period end | J5: =Time!J$6 | K5: =Time!K$6 | L5: =Time!L$6 | M5: =Time!M$6 | N5: =Time!N$6 | O5: =Time!O$6 | P5: =Time!P$6 | Q5: =Time!Q$6 | ... AU5: =Time!AU$6
A7: Flags
D8: Post-refinancing flag | E8: flag | J8: =(Inputs!$F$10=1)*(Time!J$4>Inputs!$F$307) | K8: =(Inputs!$F$10=1)*(Time!K$4>Inputs!$F$307) | L8: =(Inputs!$F$10=1)*(Time!L$4>Inputs!$F$307) | M8: =(Inputs!$F$10=1)*(Time!M$4>Inputs!$F$307) | N8: =(Inputs!$F$10=1)*(Time!N$4>Inputs!$F$307) | O8: =(Inputs!$F$10=1)*(Time!O$4>Inputs!$F$307) | P8: =(Inputs!$F$10=1)*(Time!P$4>Inputs!$F$307) | Q8: =(Inputs!$F$10=1)*(Time!Q$4>Inputs!$F$307) | ... AU8: =(Inputs!$F$10=1)*(Time!AU$4>Inputs!$F$307)
D9: Refinancing year flag | E9: flag | J9: =(Inputs!$F$10=1)*(Time!J$4=Inputs!$F$307) | K9: =(Inputs!$F$10=1)*(Time!K$4=Inputs!$F$307) | L9: =(Inputs!$F$10=1)*(Time!L$4=Inputs!$F$307) | M9: =(Inputs!$F$10=1)*(Time!M$4=Inputs!$F$307) | N9: =(Inputs!$F$10=1)*(Time!N$4=Inputs!$F$307) | O9: =(Inputs!$F$10=1)*(Time!O$4=Inputs!$F$307) | P9: =(Inputs!$F$10=1)*(Time!P$4=Inputs!$F$307) | Q9: =(Inputs!$F$10=1)*(Time!Q$4=Inputs!$F$307) | ... AU9: =(Inputs!$F$10=1)*(Time!AU$4=Inputs!$F$307)
D10: SOFR including sensitivity | E10: % | J10: =Inputs!J80+Inputs!$F$15 | K10: =Inputs!K80+Inputs!$F$15 | L10: =Inputs!L80+Inputs!$F$15 | M10: =Inputs!M80+Inputs!$F$15 | N10: =Inputs!N80+Inputs!$F$15 | O10: =Inputs!O80+Inputs!$F$15 | P10: =Inputs!P80+Inputs!$F$15 | Q10: =Inputs!Q80+Inputs!$F$15 | ... AU10: =Inputs!AU80+Inputs!$F$15
A12: Opco term loan
D13: All-in rate (unhedged share at live SOFR) | E13: % | J13: =Funding!J11*Inputs!$F$280+(1-Funding!J11)*Debt!J10+Funding!J10 | K13: =Funding!K11*Inputs!$F$280+(1-Funding!K11)*Debt!K10+Funding!K10 | L13: =Funding!L11*Inputs!$F$280+(1-Funding!L11)*Debt!L10+Funding!L10 | M13: =Funding!M11*Inputs!$F$280+(1-Funding!M11)*Debt!M10+Funding!M10 | N13: =Funding!N11*Inputs!$F$280+(1-Funding!N11)*Debt!N10+Funding!N10 | O13: =Funding!O11*Inputs!$F$280+(1-Funding!O11)*Debt!O10+Funding!O10 | P13: =Funding!P11*Inputs!$F$280+(1-Funding!P11)*Debt!P10+Funding!P10 | Q13: =Funding!Q11*Inputs!$F$280+(1-Funding!Q11)*Debt!Q10+Funding!Q10 | ... AU13: =Funding!AU11*Inputs!$F$280+(1-Funding!AU11)*Debt!AU10+Funding!AU10
D14: Opening balance | E14: USD m | J14: =IF(Time!J$4=YEAR(Inputs!$F$269),Funding!$F$17,I19) | K14: =IF(Time!K$4=YEAR(Inputs!$F$269),Funding!$F$17,J19) | L14: =IF(Time!L$4=YEAR(Inputs!$F$269),Funding!$F$17,K19) | M14: =IF(Time!M$4=YEAR(Inputs!$F$269),Funding!$F$17,L19) | N14: =IF(Time!N$4=YEAR(Inputs!$F$269),Funding!$F$17,M19) | O14: =IF(Time!O$4=YEAR(Inputs!$F$269),Funding!$F$17,N19) | P14: =IF(Time!P$4=YEAR(Inputs!$F$269),Funding!$F$17,O19) | Q14: =IF(Time!Q$4=YEAR(Inputs!$F$269),Funding!$F$17,P19) | ... AU14: =IF(Time!AU$4=YEAR(Inputs!$F$269),Funding!$F$17,AT19)
D15: Interest | E15: USD m | G15: =SUM(J15:AU15) | J15: =Debt!J14*Debt!J13/100*Funding!J8 | K15: =Debt!K14*Debt!K13/100*Funding!K8 | L15: =Debt!L14*Debt!L13/100*Funding!L8 | M15: =Debt!M14*Debt!M13/100*Funding!M8 | N15: =Debt!N14*Debt!N13/100*Funding!N8 | O15: =Debt!O14*Debt!O13/100*Funding!O8 | P15: =Debt!P14*Debt!P13/100*Funding!P8 | Q15: =Debt!Q14*Debt!Q13/100*Funding!Q8 | ... AU15: =Debt!AU14*Debt!AU13/100*Funding!AU8
D16: Scheduled principal | E16: USD m | G16: =SUM(J16:AU16) | J16: =MIN(Debt!J14,Funding!J24)*(1-Debt!J8) | K16: =MIN(Debt!K14,Funding!K24)*(1-Debt!K8) | L16: =MIN(Debt!L14,Funding!L24)*(1-Debt!L8) | M16: =MIN(Debt!M14,Funding!M24)*(1-Debt!M8) | N16: =MIN(Debt!N14,Funding!N24)*(1-Debt!N8) | O16: =MIN(Debt!O14,Funding!O24)*(1-Debt!O8) | P16: =MIN(Debt!P14,Funding!P24)*(1-Debt!P8) | Q16: =MIN(Debt!Q14,Funding!Q24)*(1-Debt!Q8) | ... AU16: =MIN(Debt!AU14,Funding!AU24)*(1-Debt!AU8)
D17: Prepayment from refinancing | E17: USD m | G17: =SUM(J17:AU17) | J17: =Debt!J9*(Debt!J14-Debt!J16) | K17: =Debt!K9*(Debt!K14-Debt!K16) | L17: =Debt!L9*(Debt!L14-Debt!L16) | M17: =Debt!M9*(Debt!M14-Debt!M16) | N17: =Debt!N9*(Debt!N14-Debt!N16) | O17: =Debt!O9*(Debt!O14-Debt!O16) | P17: =Debt!P9*(Debt!P14-Debt!P16) | Q17: =Debt!Q9*(Debt!Q14-Debt!Q16) | ... AU17: =Debt!AU9*(Debt!AU14-Debt!AU16)
D18: Debt service (interest and scheduled principal) | E18: USD m | G18: =SUM(J18:AU18) | J18: =Debt!J15+Debt!J16 | K18: =Debt!K15+Debt!K16 | L18: =Debt!L15+Debt!L16 | M18: =Debt!M15+Debt!M16 | N18: =Debt!N15+Debt!N16 | O18: =Debt!O15+Debt!O16 | P18: =Debt!P15+Debt!P16 | Q18: =Debt!Q15+Debt!Q16 | ... AU18: =Debt!AU15+Debt!AU16
D19: Closing balance | E19: USD m | J19: =Debt!J14-Debt!J16-Debt!J17 | K19: =Debt!K14-Debt!K16-Debt!K17 | L19: =Debt!L14-Debt!L16-Debt!L17 | M19: =Debt!M14-Debt!M16-Debt!M17 | N19: =Debt!N14-Debt!N16-Debt!N17 | O19: =Debt!O14-Debt!O16-Debt!O17 | P19: =Debt!P14-Debt!P16-Debt!P17 | Q19: =Debt!Q14-Debt!Q16-Debt!Q17 | ... AU19: =Debt!AU14-Debt!AU16-Debt!AU17
A21: Redfern term loan
D22: All-in rate | E22: % | J22: =Inputs!$F$298/100*Inputs!$F$299+(1-Inputs!$F$298/100)*Debt!J10+Inputs!$F$295 | K22: =Inputs!$F$298/100*Inputs!$F$299+(1-Inputs!$F$298/100)*Debt!K10+Inputs!$F$295 | L22: =Inputs!$F$298/100*Inputs!$F$299+(1-Inputs!$F$298/100)*Debt!L10+Inputs!$F$295 | M22: =Inputs!$F$298/100*Inputs!$F$299+(1-Inputs!$F$298/100)*Debt!M10+Inputs!$F$295 | N22: =Inputs!$F$298/100*Inputs!$F$299+(1-Inputs!$F$298/100)*Debt!N10+Inputs!$F$295 | O22: =Inputs!$F$298/100*Inputs!$F$299+(1-Inputs!$F$298/100)*Debt!O10+Inputs!$F$295 | P22: =Inputs!$F$298/100*Inputs!$F$299+(1-Inputs!$F$298/100)*Debt!P10+Inputs!$F$295 | Q22: =Inputs!$F$298/100*Inputs!$F$299+(1-Inputs!$F$298/100)*Debt!Q10+Inputs!$F$295 | ... AU22: =Inputs!$F$298/100*Inputs!$F$299+(1-Inputs!$F$298/100)*Debt!AU10+Inputs!$F$295
D23: Opening balance | E23: USD m | J23: =IF(Time!J$4=YEAR(Inputs!$F$293),Funding!$F$50,I28) | K23: =IF(Time!K$4=YEAR(Inputs!$F$293),Funding!$F$50,J28) | L23: =IF(Time!L$4=YEAR(Inputs!$F$293),Funding!$F$50,K28) | M23: =IF(Time!M$4=YEAR(Inputs!$F$293),Funding!$F$50,L28) | N23: =IF(Time!N$4=YEAR(Inputs!$F$293),Funding!$F$50,M28) | O23: =IF(Time!O$4=YEAR(Inputs!$F$293),Funding!$F$50,N28) | P23: =IF(Time!P$4=YEAR(Inputs!$F$293),Funding!$F$50,O28) | Q23: =IF(Time!Q$4=YEAR(Inputs!$F$293),Funding!$F$50,P28) | ... AU23: =IF(Time!AU$4=YEAR(Inputs!$F$293),Funding!$F$50,AT28)
D24: Interest | E24: USD m | G24: =SUM(J24:AU24) | J24: =Debt!J23*Debt!J22/100*Funding!J44 | K24: =Debt!K23*Debt!K22/100*Funding!K44 | L24: =Debt!L23*Debt!L22/100*Funding!L44 | M24: =Debt!M23*Debt!M22/100*Funding!M44 | N24: =Debt!N23*Debt!N22/100*Funding!N44 | O24: =Debt!O23*Debt!O22/100*Funding!O44 | P24: =Debt!P23*Debt!P22/100*Funding!P44 | Q24: =Debt!Q23*Debt!Q22/100*Funding!Q44 | ... AU24: =Debt!AU23*Debt!AU22/100*Funding!AU44
D25: Scheduled principal | E25: USD m | G25: =SUM(J25:AU25) | J25: =MIN(Debt!J23,Funding!J52)*(1-Debt!J8) | K25: =MIN(Debt!K23,Funding!K52)*(1-Debt!K8) | L25: =MIN(Debt!L23,Funding!L52)*(1-Debt!L8) | M25: =MIN(Debt!M23,Funding!M52)*(1-Debt!M8) | N25: =MIN(Debt!N23,Funding!N52)*(1-Debt!N8) | O25: =MIN(Debt!O23,Funding!O52)*(1-Debt!O8) | P25: =MIN(Debt!P23,Funding!P52)*(1-Debt!P8) | Q25: =MIN(Debt!Q23,Funding!Q52)*(1-Debt!Q8) | ... AU25: =MIN(Debt!AU23,Funding!AU52)*(1-Debt!AU8)
D26: Prepayment from refinancing | E26: USD m | J26: =Debt!J9*(Debt!J23-Debt!J25) | K26: =Debt!K9*(Debt!K23-Debt!K25) | L26: =Debt!L9*(Debt!L23-Debt!L25) | M26: =Debt!M9*(Debt!M23-Debt!M25) | N26: =Debt!N9*(Debt!N23-Debt!N25) | O26: =Debt!O9*(Debt!O23-Debt!O25) | P26: =Debt!P9*(Debt!P23-Debt!P25) | Q26: =Debt!Q9*(Debt!Q23-Debt!Q25) | ... AU26: =Debt!AU9*(Debt!AU23-Debt!AU25)
D27: Debt service | E27: USD m | G27: =SUM(J27:AU27) | J27: =Debt!J24+Debt!J25 | K27: =Debt!K24+Debt!K25 | L27: =Debt!L24+Debt!L25 | M27: =Debt!M24+Debt!M25 | N27: =Debt!N24+Debt!N25 | O27: =Debt!O24+Debt!O25 | P27: =Debt!P24+Debt!P25 | Q27: =Debt!Q24+Debt!Q25 | ... AU27: =Debt!AU24+Debt!AU25
D28: Closing balance | E28: USD m | J28: =Debt!J23-Debt!J25-Debt!J26 | K28: =Debt!K23-Debt!K25-Debt!K26 | L28: =Debt!L23-Debt!L25-Debt!L26 | M28: =Debt!M23-Debt!M25-Debt!M26 | N28: =Debt!N23-Debt!N25-Debt!N26 | O28: =Debt!O23-Debt!O25-Debt!O26 | P28: =Debt!P23-Debt!P25-Debt!P26 | Q28: =Debt!Q23-Debt!Q25-Debt!Q26 | ... AU28: =Debt!AU23-Debt!AU25-Debt!AU26
A30: USPP notes (fixed coupons; schedule as sized)
D31: Opening balance | E31: USD m | J31: =Funding!J78*Inputs!$F$10 | K31: =Funding!K78*Inputs!$F$10 | L31: =Funding!L78*Inputs!$F$10 | M31: =Funding!M78*Inputs!$F$10 | N31: =Funding!N78*Inputs!$F$10 | O31: =Funding!O78*Inputs!$F$10 | P31: =Funding!P78*Inputs!$F$10 | Q31: =Funding!Q78*Inputs!$F$10 | ... AU31: =Funding!AU78*Inputs!$F$10
D32: Interest | E32: USD m | G32: =SUM(J32:AU32) | J32: =Funding!J79*Inputs!$F$10 | K32: =Funding!K79*Inputs!$F$10 | L32: =Funding!L79*Inputs!$F$10 | M32: =Funding!M79*Inputs!$F$10 | N32: =Funding!N79*Inputs!$F$10 | O32: =Funding!O79*Inputs!$F$10 | P32: =Funding!P79*Inputs!$F$10 | Q32: =Funding!Q79*Inputs!$F$10 | ... AU32: =Funding!AU79*Inputs!$F$10
D33: Principal | E33: USD m | G33: =SUM(J33:AU33) | J33: =Funding!J74*Inputs!$F$10 | K33: =Funding!K74*Inputs!$F$10 | L33: =Funding!L74*Inputs!$F$10 | M33: =Funding!M74*Inputs!$F$10 | N33: =Funding!N74*Inputs!$F$10 | O33: =Funding!O74*Inputs!$F$10 | P33: =Funding!P74*Inputs!$F$10 | Q33: =Funding!Q74*Inputs!$F$10 | ... AU33: =Funding!AU74*Inputs!$F$10
D34: Debt service | E34: USD m | G34: =SUM(J34:AU34) | J34: =Debt!J32+Debt!J33 | K34: =Debt!K32+Debt!K33 | L34: =Debt!L32+Debt!L33 | M34: =Debt!M32+Debt!M33 | N34: =Debt!N32+Debt!N33 | O34: =Debt!O32+Debt!O33 | P34: =Debt!P32+Debt!P33 | Q34: =Debt!Q32+Debt!Q33 | ... AU34: =Debt!AU32+Debt!AU33
A36: Holdco tranches (sweep from the Waterfall sheet)
D37: Holdco TLB 2022: interest period fraction | E37: fraction | J37: =MAX(0,MIN(Inputs!$F$26,Time!J$6)-MAX(Inputs!$F$282,Time!J$5))/Time!J$7 | K37: =MAX(0,MIN(Inputs!$F$26,Time!K$6)-MAX(Inputs!$F$282,Time!K$5))/Time!K$7 | L37: =MAX(0,MIN(Inputs!$F$26,Time!L$6)-MAX(Inputs!$F$282,Time!L$5))/Time!L$7 | M37: =MAX(0,MIN(Inputs!$F$26,Time!M$6)-MAX(Inputs!$F$282,Time!M$5))/Time!M$7 | N37: =MAX(0,MIN(Inputs!$F$26,Time!N$6)-MAX(Inputs!$F$282,Time!N$5))/Time!N$7 | O37: =MAX(0,MIN(Inputs!$F$26,Time!O$6)-MAX(Inputs!$F$282,Time!O$5))/Time!O$7 | P37: =MAX(0,MIN(Inputs!$F$26,Time!P$6)-MAX(Inputs!$F$282,Time!P$5))/Time!P$7 | Q37: =MAX(0,MIN(Inputs!$F$26,Time!Q$6)-MAX(Inputs!$F$282,Time!Q$5))/Time!Q$7 | ... AU37: =MAX(0,MIN(Inputs!$F$26,Time!AU$6)-MAX(Inputs!$F$282,Time!AU$5))/Time!AU$7
D38: Holdco TLB 2022: rate | E38: % | J38: =MAX(Debt!J10,Inputs!$F$285)+Inputs!$F$284 | K38: =MAX(Debt!K10,Inputs!$F$285)+Inputs!$F$284 | L38: =MAX(Debt!L10,Inputs!$F$285)+Inputs!$F$284 | M38: =MAX(Debt!M10,Inputs!$F$285)+Inputs!$F$284 | N38: =MAX(Debt!N10,Inputs!$F$285)+Inputs!$F$284 | O38: =MAX(Debt!O10,Inputs!$F$285)+Inputs!$F$284 | P38: =MAX(Debt!P10,Inputs!$F$285)+Inputs!$F$284 | Q38: =MAX(Debt!Q10,Inputs!$F$285)+Inputs!$F$284 | ... AU38: =MAX(Debt!AU10,Inputs!$F$285)+Inputs!$F$284
D39: Holdco TLB 2022: face | E39: USD m | F39: =Funding!$F$41
D40: Holdco incremental 2024: interest period fraction | E40: fraction | J40: =MAX(0,MIN(Inputs!$F$26,Time!J$6)-MAX(Inputs!$F$300,Time!J$5))/Time!J$7 | K40: =MAX(0,MIN(Inputs!$F$26,Time!K$6)-MAX(Inputs!$F$300,Time!K$5))/Time!K$7 | L40: =MAX(0,MIN(Inputs!$F$26,Time!L$6)-MAX(Inputs!$F$300,Time!L$5))/Time!L$7 | M40: =MAX(0,MIN(Inputs!$F$26,Time!M$6)-MAX(Inputs!$F$300,Time!M$5))/Time!M$7 | N40: =MAX(0,MIN(Inputs!$F$26,Time!N$6)-MAX(Inputs!$F$300,Time!N$5))/Time!N$7 | O40: =MAX(0,MIN(Inputs!$F$26,Time!O$6)-MAX(Inputs!$F$300,Time!O$5))/Time!O$7 | P40: =MAX(0,MIN(Inputs!$F$26,Time!P$6)-MAX(Inputs!$F$300,Time!P$5))/Time!P$7 | Q40: =MAX(0,MIN(Inputs!$F$26,Time!Q$6)-MAX(Inputs!$F$300,Time!Q$5))/Time!Q$7 | ... AU40: =MAX(0,MIN(Inputs!$F$26,Time!AU$6)-MAX(Inputs!$F$300,Time!AU$5))/Time!AU$7
D41: Holdco incremental 2024: rate | E41: % | J41: =MAX(Debt!J10,Inputs!$F$285)+Inputs!$F$302 | K41: =MAX(Debt!K10,Inputs!$F$285)+Inputs!$F$302 | L41: =MAX(Debt!L10,Inputs!$F$285)+Inputs!$F$302 | M41: =MAX(Debt!M10,Inputs!$F$285)+Inputs!$F$302 | N41: =MAX(Debt!N10,Inputs!$F$285)+Inputs!$F$302 | O41: =MAX(Debt!O10,Inputs!$F$285)+Inputs!$F$302 | P41: =MAX(Debt!P10,Inputs!$F$285)+Inputs!$F$302 | Q41: =MAX(Debt!Q10,Inputs!$F$285)+Inputs!$F$302 | ... AU41: =MAX(Debt!AU10,Inputs!$F$285)+Inputs!$F$302
D42: Holdco incremental 2024: face | E42: USD m | F42: =Funding!$F$63
D43: Repriced holdco TLB 2025: interest period fraction | E43: fraction | J43: =MAX(0,MIN(Inputs!$F$26,Time!J$6)-MAX(Inputs!$F$308,Time!J$5))/Time!J$7 | K43: =MAX(0,MIN(Inputs!$F$26,Time!K$6)-MAX(Inputs!$F$308,Time!K$5))/Time!K$7 | L43: =MAX(0,MIN(Inputs!$F$26,Time!L$6)-MAX(Inputs!$F$308,Time!L$5))/Time!L$7 | M43: =MAX(0,MIN(Inputs!$F$26,Time!M$6)-MAX(Inputs!$F$308,Time!M$5))/Time!M$7 | N43: =MAX(0,MIN(Inputs!$F$26,Time!N$6)-MAX(Inputs!$F$308,Time!N$5))/Time!N$7 | O43: =MAX(0,MIN(Inputs!$F$26,Time!O$6)-MAX(Inputs!$F$308,Time!O$5))/Time!O$7 | P43: =MAX(0,MIN(Inputs!$F$26,Time!P$6)-MAX(Inputs!$F$308,Time!P$5))/Time!P$7 | Q43: =MAX(0,MIN(Inputs!$F$26,Time!Q$6)-MAX(Inputs!$F$308,Time!Q$5))/Time!Q$7 | ... AU43: =MAX(0,MIN(Inputs!$F$26,Time!AU$6)-MAX(Inputs!$F$308,Time!AU$5))/Time!AU$7
D44: Repriced holdco TLB 2025: rate | E44: % | J44: =MAX(Debt!J10,Inputs!$F$285)+Inputs!$F$322 | K44: =MAX(Debt!K10,Inputs!$F$285)+Inputs!$F$322 | L44: =MAX(Debt!L10,Inputs!$F$285)+Inputs!$F$322 | M44: =MAX(Debt!M10,Inputs!$F$285)+Inputs!$F$322 | N44: =MAX(Debt!N10,Inputs!$F$285)+Inputs!$F$322 | O44: =MAX(Debt!O10,Inputs!$F$285)+Inputs!$F$322 | P44: =MAX(Debt!P10,Inputs!$F$285)+Inputs!$F$322 | Q44: =MAX(Debt!Q10,Inputs!$F$285)+Inputs!$F$322 | ... AU44: =MAX(Debt!AU10,Inputs!$F$285)+Inputs!$F$322
D45: Repriced holdco TLB 2025: face | E45: USD m | F45: =Funding!$F$103*Inputs!$F$10
D46: Holdco TLB 2022: opening balance | E46: USD m | J46: =IF(Time!J$4=YEAR(Inputs!$F$282),Debt!$F$39,I52) | K46: =IF(Time!K$4=YEAR(Inputs!$F$282),Debt!$F$39,J52) | L46: =IF(Time!L$4=YEAR(Inputs!$F$282),Debt!$F$39,K52) | M46: =IF(Time!M$4=YEAR(Inputs!$F$282),Debt!$F$39,L52) | N46: =IF(Time!N$4=YEAR(Inputs!$F$282),Debt!$F$39,M52) | O46: =IF(Time!O$4=YEAR(Inputs!$F$282),Debt!$F$39,N52) | P46: =IF(Time!P$4=YEAR(Inputs!$F$282),Debt!$F$39,O52) | Q46: =IF(Time!Q$4=YEAR(Inputs!$F$282),Debt!$F$39,P52) | ... AU46: =IF(Time!AU$4=YEAR(Inputs!$F$282),Debt!$F$39,AT52)
D47: Holdco TLB 2022: interest | E47: USD m | G47: =SUM(J47:AU47) | J47: =Debt!J46*Debt!J38/100*Debt!J37 | K47: =Debt!K46*Debt!K38/100*Debt!K37 | L47: =Debt!L46*Debt!L38/100*Debt!L37 | M47: =Debt!M46*Debt!M38/100*Debt!M37 | N47: =Debt!N46*Debt!N38/100*Debt!N37 | O47: =Debt!O46*Debt!O38/100*Debt!O37 | P47: =Debt!P46*Debt!P38/100*Debt!P37 | Q47: =Debt!Q46*Debt!Q38/100*Debt!Q37 | ... AU47: =Debt!AU46*Debt!AU38/100*Debt!AU37
D48: Holdco TLB 2022: scheduled amortization | E48: USD m | G48: =SUM(J48:AU48) | J48: =MIN(Debt!J46,Inputs!$F$287/100*Debt!$F$39*Debt!J37) | K48: =MIN(Debt!K46,Inputs!$F$287/100*Debt!$F$39*Debt!K37) | L48: =MIN(Debt!L46,Inputs!$F$287/100*Debt!$F$39*Debt!L37) | M48: =MIN(Debt!M46,Inputs!$F$287/100*Debt!$F$39*Debt!M37) | N48: =MIN(Debt!N46,Inputs!$F$287/100*Debt!$F$39*Debt!N37) | O48: =MIN(Debt!O46,Inputs!$F$287/100*Debt!$F$39*Debt!O37) | P48: =MIN(Debt!P46,Inputs!$F$287/100*Debt!$F$39*Debt!P37) | Q48: =MIN(Debt!Q46,Inputs!$F$287/100*Debt!$F$39*Debt!Q37) | ... AU48: =MIN(Debt!AU46,Inputs!$F$287/100*Debt!$F$39*Debt!AU37)
D49: Holdco TLB 2022: excess cash sweep | E49: USD m | J49: =IF(Waterfall!J17>0,Waterfall!J18*Debt!J50/Waterfall!J17,0) | K49: =IF(Waterfall!K17>0,Waterfall!K18*Debt!K50/Waterfall!K17,0) | L49: =IF(Waterfall!L17>0,Waterfall!L18*Debt!L50/Waterfall!L17,0) | M49: =IF(Waterfall!M17>0,Waterfall!M18*Debt!M50/Waterfall!M17,0) | N49: =IF(Waterfall!N17>0,Waterfall!N18*Debt!N50/Waterfall!N17,0) | O49: =IF(Waterfall!O17>0,Waterfall!O18*Debt!O50/Waterfall!O17,0) | P49: =IF(Waterfall!P17>0,Waterfall!P18*Debt!P50/Waterfall!P17,0) | Q49: =IF(Waterfall!Q17>0,Waterfall!Q18*Debt!Q50/Waterfall!Q17,0) | ... AU49: =IF(Waterfall!AU17>0,Waterfall!AU18*Debt!AU50/Waterfall!AU17,0)
D50: Holdco TLB 2022: balance after amortization | E50: USD m | J50: =Debt!J46-Debt!J48 | K50: =Debt!K46-Debt!K48 | L50: =Debt!L46-Debt!L48 | M50: =Debt!M46-Debt!M48 | N50: =Debt!N46-Debt!N48 | O50: =Debt!O46-Debt!O48 | P50: =Debt!P46-Debt!P48 | Q50: =Debt!Q46-Debt!Q48 | ... AU50: =Debt!AU46-Debt!AU48
D51: Holdco TLB 2022: repaid at refinancing | E51: USD m | J51: =Debt!J9*(Debt!J50-Debt!J49) | K51: =Debt!K9*(Debt!K50-Debt!K49) | L51: =Debt!L9*(Debt!L50-Debt!L49) | M51: =Debt!M9*(Debt!M50-Debt!M49) | N51: =Debt!N9*(Debt!N50-Debt!N49) | O51: =Debt!O9*(Debt!O50-Debt!O49) | P51: =Debt!P9*(Debt!P50-Debt!P49) | Q51: =Debt!Q9*(Debt!Q50-Debt!Q49) | ... AU51: =Debt!AU9*(Debt!AU50-Debt!AU49)
D52: Holdco TLB 2022: closing balance | E52: USD m | J52: =Debt!J50-Debt!J49-Debt!J51 | K52: =Debt!K50-Debt!K49-Debt!K51 | L52: =Debt!L50-Debt!L49-Debt!L51 | M52: =Debt!M50-Debt!M49-Debt!M51 | N52: =Debt!N50-Debt!N49-Debt!N51 | O52: =Debt!O50-Debt!O49-Debt!O51 | P52: =Debt!P50-Debt!P49-Debt!P51 | Q52: =Debt!Q50-Debt!Q49-Debt!Q51 | ... AU52: =Debt!AU50-Debt!AU49-Debt!AU51
D53: Holdco incremental 2024: opening balance | E53: USD m | J53: =IF(Time!J$4=YEAR(Inputs!$F$300),Debt!$F$42,I59) | K53: =IF(Time!K$4=YEAR(Inputs!$F$300),Debt!$F$42,J59) | L53: =IF(Time!L$4=YEAR(Inputs!$F$300),Debt!$F$42,K59) | M53: =IF(Time!M$4=YEAR(Inputs!$F$300),Debt!$F$42,L59) | N53: =IF(Time!N$4=YEAR(Inputs!$F$300),Debt!$F$42,M59) | O53: =IF(Time!O$4=YEAR(Inputs!$F$300),Debt!$F$42,N59) | P53: =IF(Time!P$4=YEAR(Inputs!$F$300),Debt!$F$42,O59) | Q53: =IF(Time!Q$4=YEAR(Inputs!$F$300),Debt!$F$42,P59) | ... AU53: =IF(Time!AU$4=YEAR(Inputs!$F$300),Debt!$F$42,AT59)
D54: Holdco incremental 2024: interest | E54: USD m | G54: =SUM(J54:AU54) | J54: =Debt!J53*Debt!J41/100*Debt!J40 | K54: =Debt!K53*Debt!K41/100*Debt!K40 | L54: =Debt!L53*Debt!L41/100*Debt!L40 | M54: =Debt!M53*Debt!M41/100*Debt!M40 | N54: =Debt!N53*Debt!N41/100*Debt!N40 | O54: =Debt!O53*Debt!O41/100*Debt!O40 | P54: =Debt!P53*Debt!P41/100*Debt!P40 | Q54: =Debt!Q53*Debt!Q41/100*Debt!Q40 | ... AU54: =Debt!AU53*Debt!AU41/100*Debt!AU40
D55: Holdco incremental 2024: scheduled amortization | E55: USD m | G55: =SUM(J55:AU55) | J55: =MIN(Debt!J53,Inputs!$F$304/100*Debt!$F$42*Debt!J40) | K55: =MIN(Debt!K53,Inputs!$F$304/100*Debt!$F$42*Debt!K40) | L55: =MIN(Debt!L53,Inputs!$F$304/100*Debt!$F$42*Debt!L40) | M55: =MIN(Debt!M53,Inputs!$F$304/100*Debt!$F$42*Debt!M40) | N55: =MIN(Debt!N53,Inputs!$F$304/100*Debt!$F$42*Debt!N40) | O55: =MIN(Debt!O53,Inputs!$F$304/100*Debt!$F$42*Debt!O40) | P55: =MIN(Debt!P53,Inputs!$F$304/100*Debt!$F$42*Debt!P40) | Q55: =MIN(Debt!Q53,Inputs!$F$304/100*Debt!$F$42*Debt!Q40) | ... AU55: =MIN(Debt!AU53,Inputs!$F$304/100*Debt!$F$42*Debt!AU40)
D56: Holdco incremental 2024: excess cash sweep | E56: USD m | J56: =IF(Waterfall!J17>0,Waterfall!J18*Debt!J57/Waterfall!J17,0) | K56: =IF(Waterfall!K17>0,Waterfall!K18*Debt!K57/Waterfall!K17,0) | L56: =IF(Waterfall!L17>0,Waterfall!L18*Debt!L57/Waterfall!L17,0) | M56: =IF(Waterfall!M17>0,Waterfall!M18*Debt!M57/Waterfall!M17,0) | N56: =IF(Waterfall!N17>0,Waterfall!N18*Debt!N57/Waterfall!N17,0) | O56: =IF(Waterfall!O17>0,Waterfall!O18*Debt!O57/Waterfall!O17,0) | P56: =IF(Waterfall!P17>0,Waterfall!P18*Debt!P57/Waterfall!P17,0) | Q56: =IF(Waterfall!Q17>0,Waterfall!Q18*Debt!Q57/Waterfall!Q17,0) | ... AU56: =IF(Waterfall!AU17>0,Waterfall!AU18*Debt!AU57/Waterfall!AU17,0)
D57: Holdco incremental 2024: balance after amortization | E57: USD m | J57: =Debt!J53-Debt!J55 | K57: =Debt!K53-Debt!K55 | L57: =Debt!L53-Debt!L55 | M57: =Debt!M53-Debt!M55 | N57: =Debt!N53-Debt!N55 | O57: =Debt!O53-Debt!O55 | P57: =Debt!P53-Debt!P55 | Q57: =Debt!Q53-Debt!Q55 | ... AU57: =Debt!AU53-Debt!AU55
D58: Holdco incremental 2024: repaid at refinancing | E58: USD m | J58: =Debt!J9*(Debt!J57-Debt!J56) | K58: =Debt!K9*(Debt!K57-Debt!K56) | L58: =Debt!L9*(Debt!L57-Debt!L56) | M58: =Debt!M9*(Debt!M57-Debt!M56) | N58: =Debt!N9*(Debt!N57-Debt!N56) | O58: =Debt!O9*(Debt!O57-Debt!O56) | P58: =Debt!P9*(Debt!P57-Debt!P56) | Q58: =Debt!Q9*(Debt!Q57-Debt!Q56) | ... AU58: =Debt!AU9*(Debt!AU57-Debt!AU56)
D59: Holdco incremental 2024: closing balance | E59: USD m | J59: =Debt!J57-Debt!J56-Debt!J58 | K59: =Debt!K57-Debt!K56-Debt!K58 | L59: =Debt!L57-Debt!L56-Debt!L58 | M59: =Debt!M57-Debt!M56-Debt!M58 | N59: =Debt!N57-Debt!N56-Debt!N58 | O59: =Debt!O57-Debt!O56-Debt!O58 | P59: =Debt!P57-Debt!P56-Debt!P58 | Q59: =Debt!Q57-Debt!Q56-Debt!Q58 | ... AU59: =Debt!AU57-Debt!AU56-Debt!AU58
D60: Repriced holdco TLB 2025: opening balance | E60: USD m | J60: =IF(AND(Inputs!$F$10=1,Time!J$4=Inputs!$F$307+1),Debt!$F$45,I66) | K60: =IF(AND(Inputs!$F$10=1,Time!K$4=Inputs!$F$307+1),Debt!$F$45,J66) | L60: =IF(AND(Inputs!$F$10=1,Time!L$4=Inputs!$F$307+1),Debt!$F$45,K66) | M60: =IF(AND(Inputs!$F$10=1,Time!M$4=Inputs!$F$307+1),Debt!$F$45,L66) | N60: =IF(AND(Inputs!$F$10=1,Time!N$4=Inputs!$F$307+1),Debt!$F$45,M66) | O60: =IF(AND(Inputs!$F$10=1,Time!O$4=Inputs!$F$307+1),Debt!$F$45,N66) | P60: =IF(AND(Inputs!$F$10=1,Time!P$4=Inputs!$F$307+1),Debt!$F$45,O66) | Q60: =IF(AND(Inputs!$F$10=1,Time!Q$4=Inputs!$F$307+1),Debt!$F$45,P66) | ... AU60: =IF(AND(Inputs!$F$10=1,Time!AU$4=Inputs!$F$307+1),Debt!$F$45,AT66)
D61: Repriced holdco TLB 2025: interest | E61: USD m | G61: =SUM(J61:AU61) | J61: =Debt!J60*Debt!J44/100*Debt!J43 | K61: =Debt!K60*Debt!K44/100*Debt!K43 | L61: =Debt!L60*Debt!L44/100*Debt!L43 | M61: =Debt!M60*Debt!M44/100*Debt!M43 | N61: =Debt!N60*Debt!N44/100*Debt!N43 | O61: =Debt!O60*Debt!O44/100*Debt!O43 | P61: =Debt!P60*Debt!P44/100*Debt!P43 | Q61: =Debt!Q60*Debt!Q44/100*Debt!Q43 | ... AU61: =Debt!AU60*Debt!AU44/100*Debt!AU43
D62: Repriced holdco TLB 2025: scheduled amortization | E62: USD m | G62: =SUM(J62:AU62) | J62: =MIN(Debt!J60,Inputs!$F$325/100*Debt!$F$45*Debt!J43) | K62: =MIN(Debt!K60,Inputs!$F$325/100*Debt!$F$45*Debt!K43) | L62: =MIN(Debt!L60,Inputs!$F$325/100*Debt!$F$45*Debt!L43) | M62: =MIN(Debt!M60,Inputs!$F$325/100*Debt!$F$45*Debt!M43) | N62: =MIN(Debt!N60,Inputs!$F$325/100*Debt!$F$45*Debt!N43) | O62: =MIN(Debt!O60,Inputs!$F$325/100*Debt!$F$45*Debt!O43) | P62: =MIN(Debt!P60,Inputs!$F$325/100*Debt!$F$45*Debt!P43) | Q62: =MIN(Debt!Q60,Inputs!$F$325/100*Debt!$F$45*Debt!Q43) | ... AU62: =MIN(Debt!AU60,Inputs!$F$325/100*Debt!$F$45*Debt!AU43)
D63: Repriced holdco TLB 2025: excess cash sweep | E63: USD m | J63: =IF(Waterfall!J17>0,Waterfall!J18*Debt!J64/Waterfall!J17,0) | K63: =IF(Waterfall!K17>0,Waterfall!K18*Debt!K64/Waterfall!K17,0) | L63: =IF(Waterfall!L17>0,Waterfall!L18*Debt!L64/Waterfall!L17,0) | M63: =IF(Waterfall!M17>0,Waterfall!M18*Debt!M64/Waterfall!M17,0) | N63: =IF(Waterfall!N17>0,Waterfall!N18*Debt!N64/Waterfall!N17,0) | O63: =IF(Waterfall!O17>0,Waterfall!O18*Debt!O64/Waterfall!O17,0) | P63: =IF(Waterfall!P17>0,Waterfall!P18*Debt!P64/Waterfall!P17,0) | Q63: =IF(Waterfall!Q17>0,Waterfall!Q18*Debt!Q64/Waterfall!Q17,0) | ... AU63: =IF(Waterfall!AU17>0,Waterfall!AU18*Debt!AU64/Waterfall!AU17,0)
D64: Repriced holdco TLB 2025: balance after amortization | E64: USD m | J64: =Debt!J60-Debt!J62 | K64: =Debt!K60-Debt!K62 | L64: =Debt!L60-Debt!L62 | M64: =Debt!M60-Debt!M62 | N64: =Debt!N60-Debt!N62 | O64: =Debt!O60-Debt!O62 | P64: =Debt!P60-Debt!P62 | Q64: =Debt!Q60-Debt!Q62 | ... AU64: =Debt!AU60-Debt!AU62
D65: Repriced holdco TLB 2025: repaid at refinancing | E65: USD m | J65: =0 | K65: =0 | L65: =0 | M65: =0 | N65: =0 | O65: =0 | P65: =0 | Q65: =0 | ... AU65: =0
D66: Repriced holdco TLB 2025: closing balance | E66: USD m | J66: =Debt!J64-Debt!J63-Debt!J65 | K66: =Debt!K64-Debt!K63-Debt!K65 | L66: =Debt!L64-Debt!L63-Debt!L65 | M66: =Debt!M64-Debt!M63-Debt!M65 | N66: =Debt!N64-Debt!N63-Debt!N65 | O66: =Debt!O64-Debt!O63-Debt!O65 | P66: =Debt!P64-Debt!P63-Debt!P65 | Q66: =Debt!Q64-Debt!Q63-Debt!Q65 | ... AU66: =Debt!AU64-Debt!AU63-Debt!AU65
D67: Holdco debt service (interest and scheduled amortization) | E67: USD m | G67: =SUM(J67:AU67) | J67: =Debt!J47+Debt!J48+Debt!J54+Debt!J55+Debt!J61+Debt!J62 | K67: =Debt!K47+Debt!K48+Debt!K54+Debt!K55+Debt!K61+Debt!K62 | L67: =Debt!L47+Debt!L48+Debt!L54+Debt!L55+Debt!L61+Debt!L62 | M67: =Debt!M47+Debt!M48+Debt!M54+Debt!M55+Debt!M61+Debt!M62 | N67: =Debt!N47+Debt!N48+Debt!N54+Debt!N55+Debt!N61+Debt!N62 | O67: =Debt!O47+Debt!O48+Debt!O54+Debt!O55+Debt!O61+Debt!O62 | P67: =Debt!P47+Debt!P48+Debt!P54+Debt!P55+Debt!P61+Debt!P62 | Q67: =Debt!Q47+Debt!Q48+Debt!Q54+Debt!Q55+Debt!Q61+Debt!Q62 | ... AU67: =Debt!AU47+Debt!AU48+Debt!AU54+Debt!AU55+Debt!AU61+Debt!AU62

Sheet Waterfall
A1: Waterfall: opco to holdco to fund
A2: Case R, Mesa Corta Renewables. USD m nominal unless stated. Illustrative prices: not ERCOT settlement data and not a forecast.
D4: Year | J4: =Time!J$4 | K4: =Time!K$4 | L4: =Time!L$4 | M4: =Time!M$4 | N4: =Time!N$4 | O4: =Time!O$4 | P4: =Time!P$4 | Q4: =Time!Q$4 | ... AU4: =Time!AU$4
D5: Period end | J5: =Time!J$6 | K5: =Time!K$6 | L5: =Time!L$6 | M5: =Time!M$6 | N5: =Time!N$6 | O5: =Time!O$6 | P5: =Time!P$6 | Q5: =Time!Q$6 | ... AU5: =Time!AU$6
A7: Opco
D8: CFADS (portfolio, Mesa share) | E8: USD m | G8: =SUM(J8:AU8) | J8: =Operations!J401 | K8: =Operations!K401 | L8: =Operations!L401 | M8: =Operations!M401 | N8: =Operations!N401 | O8: =Operations!O401 | P8: =Operations!P401 | Q8: =Operations!Q401 | ... AU8: =Operations!AU401
D9: Opco debt service (term loan, Redfern, USPP) | E9: USD m | G9: =SUM(J9:AU9) | J9: =Debt!J18+Debt!J27+Debt!J34 | K9: =Debt!K18+Debt!K27+Debt!K34 | L9: =Debt!L18+Debt!L27+Debt!L34 | M9: =Debt!M18+Debt!M27+Debt!M34 | N9: =Debt!N18+Debt!N27+Debt!N34 | O9: =Debt!O18+Debt!O27+Debt!O34 | P9: =Debt!P18+Debt!P27+Debt!P34 | Q9: =Debt!Q18+Debt!Q27+Debt!Q34 | ... AU9: =Debt!AU18+Debt!AU27+Debt!AU34
D10: Opco distributions to holdco | E10: USD m | G10: =SUM(J10:AU10) | J10: =Waterfall!J8-Waterfall!J9 | K10: =Waterfall!K8-Waterfall!K9 | L10: =Waterfall!L8-Waterfall!L9 | M10: =Waterfall!M8-Waterfall!M9 | N10: =Waterfall!N8-Waterfall!N9 | O10: =Waterfall!O8-Waterfall!O9 | P10: =Waterfall!P8-Waterfall!P9 | Q10: =Waterfall!Q8-Waterfall!Q9 | ... AU10: =Waterfall!AU8-Waterfall!AU9
D11: Refinancing proceeds distributed by opco | E11: USD m | G11: =SUM(J11:AU11) | J11: =Debt!J9*Funding!$F$179 | K11: =Debt!K9*Funding!$F$179 | L11: =Debt!L9*Funding!$F$179 | M11: =Debt!M9*Funding!$F$179 | N11: =Debt!N9*Funding!$F$179 | O11: =Debt!O9*Funding!$F$179 | P11: =Debt!P9*Funding!$F$179 | Q11: =Debt!Q9*Funding!$F$179 | ... AU11: =Debt!AU9*Funding!$F$179
A13: Holdco
D14: Cash tax | E14: USD m | J14: =Tax!J32 | K14: =Tax!K32 | L14: =Tax!L32 | M14: =Tax!M32 | N14: =Tax!N32 | O14: =Tax!O32 | P14: =Tax!P32 | Q14: =Tax!Q32 | ... AU14: =Tax!AU32
D15: Holdco debt service | E15: USD m | J15: =Debt!J67 | K15: =Debt!K67 | L15: =Debt!L67 | M15: =Debt!M67 | N15: =Debt!N67 | O15: =Debt!O67 | P15: =Debt!P67 | Q15: =Debt!Q67 | ... AU15: =Debt!AU67
D16: Excess cash after tax and holdco debt service | E16: USD m | G16: =SUM(J16:AU16) | J16: =Waterfall!J10-Waterfall!J14-Waterfall!J15 | K16: =Waterfall!K10-Waterfall!K14-Waterfall!K15 | L16: =Waterfall!L10-Waterfall!L14-Waterfall!L15 | M16: =Waterfall!M10-Waterfall!M14-Waterfall!M15 | N16: =Waterfall!N10-Waterfall!N14-Waterfall!N15 | O16: =Waterfall!O10-Waterfall!O14-Waterfall!O15 | P16: =Waterfall!P10-Waterfall!P14-Waterfall!P15 | Q16: =Waterfall!Q10-Waterfall!Q14-Waterfall!Q15 | ... AU16: =Waterfall!AU10-Waterfall!AU14-Waterfall!AU15
D17: Holdco balances after scheduled amortization | E17: USD m | J17: =Debt!J50+Debt!J57+Debt!J64 | K17: =Debt!K50+Debt!K57+Debt!K64 | L17: =Debt!L50+Debt!L57+Debt!L64 | M17: =Debt!M50+Debt!M57+Debt!M64 | N17: =Debt!N50+Debt!N57+Debt!N64 | O17: =Debt!O50+Debt!O57+Debt!O64 | P17: =Debt!P50+Debt!P57+Debt!P64 | Q17: =Debt!Q50+Debt!Q57+Debt!Q64 | ... AU17: =Debt!AU50+Debt!AU57+Debt!AU64
D18: Excess cash sweep (50%, capped at balances) | E18: USD m | G18: =SUM(J18:AU18) | J18: =MIN(Inputs!$F$288/100*MAX(Waterfall!J16,0),Waterfall!J17) | K18: =MIN(Inputs!$F$288/100*MAX(Waterfall!K16,0),Waterfall!K17) | L18: =MIN(Inputs!$F$288/100*MAX(Waterfall!L16,0),Waterfall!L17) | M18: =MIN(Inputs!$F$288/100*MAX(Waterfall!M16,0),Waterfall!M17) | N18: =MIN(Inputs!$F$288/100*MAX(Waterfall!N16,0),Waterfall!N17) | O18: =MIN(Inputs!$F$288/100*MAX(Waterfall!O16,0),Waterfall!O17) | P18: =MIN(Inputs!$F$288/100*MAX(Waterfall!P16,0),Waterfall!P17) | Q18: =MIN(Inputs!$F$288/100*MAX(Waterfall!Q16,0),Waterfall!Q17) | ... AU18: =MIN(Inputs!$F$288/100*MAX(Waterfall!AU16,0),Waterfall!AU17)
D19: Distribution to the fund from operations (floored at zero) | E19: USD m | G19: =SUM(J19:AU19) | J19: =MAX(0,Waterfall!J16-Waterfall!J18) | K19: =MAX(0,Waterfall!K16-Waterfall!K18) | L19: =MAX(0,Waterfall!L16-Waterfall!L18) | M19: =MAX(0,Waterfall!M16-Waterfall!M18) | N19: =MAX(0,Waterfall!N16-Waterfall!N18) | O19: =MAX(0,Waterfall!O16-Waterfall!O18) | P19: =MAX(0,Waterfall!P16-Waterfall!P18) | Q19: =MAX(0,Waterfall!Q16-Waterfall!Q18) | ... AU19: =MAX(0,Waterfall!AU16-Waterfall!AU18)
D20: Holdco repricing net proceeds (new face x OID less tranches repaid) | E20: USD m | G20: =SUM(J20:AU20) | J20: =Debt!J9*(Funding!$F$103*Inputs!$F$324/100-Debt!J51-Debt!J58) | K20: =Debt!K9*(Funding!$F$103*Inputs!$F$324/100-Debt!K51-Debt!K58) | L20: =Debt!L9*(Funding!$F$103*Inputs!$F$324/100-Debt!L51-Debt!L58) | M20: =Debt!M9*(Funding!$F$103*Inputs!$F$324/100-Debt!M51-Debt!M58) | N20: =Debt!N9*(Funding!$F$103*Inputs!$F$324/100-Debt!N51-Debt!N58) | O20: =Debt!O9*(Funding!$F$103*Inputs!$F$324/100-Debt!O51-Debt!O58) | P20: =Debt!P9*(Funding!$F$103*Inputs!$F$324/100-Debt!P51-Debt!P58) | Q20: =Debt!Q9*(Funding!$F$103*Inputs!$F$324/100-Debt!Q51-Debt!Q58) | ... AU20: =Debt!AU9*(Funding!$F$103*Inputs!$F$324/100-Debt!AU51-Debt!AU58)
D21: Recapitalization distribution | E21: USD m | G21: =SUM(J21:AU21) | J21: =Waterfall!J11+Waterfall!J20 | K21: =Waterfall!K11+Waterfall!K20 | L21: =Waterfall!L11+Waterfall!L20 | M21: =Waterfall!M11+Waterfall!M20 | N21: =Waterfall!N11+Waterfall!N20 | O21: =Waterfall!O11+Waterfall!O20 | P21: =Waterfall!P11+Waterfall!P20 | Q21: =Waterfall!Q11+Waterfall!Q20 | ... AU21: =Waterfall!AU11+Waterfall!AU20
D22: Total distribution to the fund | E22: USD m | G22: =SUM(J22:AU22) | J22: =Waterfall!J19+Waterfall!J21 | K22: =Waterfall!K19+Waterfall!K21 | L22: =Waterfall!L19+Waterfall!L21 | M22: =Waterfall!M19+Waterfall!M21 | N22: =Waterfall!N19+Waterfall!N21 | O22: =Waterfall!O19+Waterfall!O21 | P22: =Waterfall!P19+Waterfall!P21 | Q22: =Waterfall!Q19+Waterfall!Q21 | ... AU22: =Waterfall!AU19+Waterfall!AU21

Sheet Ratios
A1: Ratios
A2: Case R, Mesa Corta Renewables. USD m nominal unless stated. Illustrative prices: not ERCOT settlement data and not a forecast.
D4: Year | J4: =Time!J$4 | K4: =Time!K$4 | L4: =Time!L$4 | M4: =Time!M$4 | N4: =Time!N$4 | O4: =Time!O$4 | P4: =Time!P$4 | Q4: =Time!Q$4 | ... AU4: =Time!AU$4
D5: Period end | J5: =Time!J$6 | K5: =Time!K$6 | L5: =Time!L$6 | M5: =Time!M$6 | N5: =Time!N$6 | O5: =Time!O$6 | P5: =Time!P$6 | Q5: =Time!Q$6 | ... AU5: =Time!AU$6
A7: Cover ratios (shown where debt service exceeds the threshold)
D8: Opco term loan DSCR (A1 group CFADS) | E8: x | J8: =IF(Debt!J18>Inputs!$F$29,Operations!J400/Debt!J18,"") | K8: =IF(Debt!K18>Inputs!$F$29,Operations!K400/Debt!K18,"") | L8: =IF(Debt!L18>Inputs!$F$29,Operations!L400/Debt!L18,"") | M8: =IF(Debt!M18>Inputs!$F$29,Operations!M400/Debt!M18,"") | N8: =IF(Debt!N18>Inputs!$F$29,Operations!N400/Debt!N18,"") | O8: =IF(Debt!O18>Inputs!$F$29,Operations!O400/Debt!O18,"") | P8: =IF(Debt!P18>Inputs!$F$29,Operations!P400/Debt!P18,"") | Q8: =IF(Debt!Q18>Inputs!$F$29,Operations!Q400/Debt!Q18,"") | ... AU8: =IF(Debt!AU18>Inputs!$F$29,Operations!AU400/Debt!AU18,"")
D9: Redfern DSCR (R6 Mesa cash flow) | E9: x | J9: =IF(Debt!J27>Inputs!$F$29,Operations!J297/Debt!J27,"") | K9: =IF(Debt!K27>Inputs!$F$29,Operations!K297/Debt!K27,"") | L9: =IF(Debt!L27>Inputs!$F$29,Operations!L297/Debt!L27,"") | M9: =IF(Debt!M27>Inputs!$F$29,Operations!M297/Debt!M27,"") | N9: =IF(Debt!N27>Inputs!$F$29,Operations!N297/Debt!N27,"") | O9: =IF(Debt!O27>Inputs!$F$29,Operations!O297/Debt!O27,"") | P9: =IF(Debt!P27>Inputs!$F$29,Operations!P297/Debt!P27,"") | Q9: =IF(Debt!Q27>Inputs!$F$29,Operations!Q297/Debt!Q27,"") | ... AU9: =IF(Debt!AU27>Inputs!$F$29,Operations!AU297/Debt!AU27,"")
D10: USPP DSCR (portfolio CFADS) | E10: x | J10: =IF(Debt!J34>Inputs!$F$29,Operations!J401/Debt!J34,"") | K10: =IF(Debt!K34>Inputs!$F$29,Operations!K401/Debt!K34,"") | L10: =IF(Debt!L34>Inputs!$F$29,Operations!L401/Debt!L34,"") | M10: =IF(Debt!M34>Inputs!$F$29,Operations!M401/Debt!M34,"") | N10: =IF(Debt!N34>Inputs!$F$29,Operations!N401/Debt!N34,"") | O10: =IF(Debt!O34>Inputs!$F$29,Operations!O401/Debt!O34,"") | P10: =IF(Debt!P34>Inputs!$F$29,Operations!P401/Debt!P34,"") | Q10: =IF(Debt!Q34>Inputs!$F$29,Operations!Q401/Debt!Q34,"") | ... AU10: =IF(Debt!AU34>Inputs!$F$29,Operations!AU401/Debt!AU34,"")
D11: Opco aggregate DSCR | E11: x | J11: =IF(Waterfall!J9>Inputs!$F$29,Operations!J401/Waterfall!J9,"") | K11: =IF(Waterfall!K9>Inputs!$F$29,Operations!K401/Waterfall!K9,"") | L11: =IF(Waterfall!L9>Inputs!$F$29,Operations!L401/Waterfall!L9,"") | M11: =IF(Waterfall!M9>Inputs!$F$29,Operations!M401/Waterfall!M9,"") | N11: =IF(Waterfall!N9>Inputs!$F$29,Operations!N401/Waterfall!N9,"") | O11: =IF(Waterfall!O9>Inputs!$F$29,Operations!O401/Waterfall!O9,"") | P11: =IF(Waterfall!P9>Inputs!$F$29,Operations!P401/Waterfall!P9,"") | Q11: =IF(Waterfall!Q9>Inputs!$F$29,Operations!Q401/Waterfall!Q9,"") | ... AU11: =IF(Waterfall!AU9>Inputs!$F$29,Operations!AU401/Waterfall!AU9,"")
D12: Holdco coverage (opco distributions / holdco debt service) | E12: x | J12: =IF(Debt!J67>Inputs!$F$29,Waterfall!J10/Debt!J67,"") | K12: =IF(Debt!K67>Inputs!$F$29,Waterfall!K10/Debt!K67,"") | L12: =IF(Debt!L67>Inputs!$F$29,Waterfall!L10/Debt!L67,"") | M12: =IF(Debt!M67>Inputs!$F$29,Waterfall!M10/Debt!M67,"") | N12: =IF(Debt!N67>Inputs!$F$29,Waterfall!N10/Debt!N67,"") | O12: =IF(Debt!O67>Inputs!$F$29,Waterfall!O10/Debt!O67,"") | P12: =IF(Debt!P67>Inputs!$F$29,Waterfall!P10/Debt!P67,"") | Q12: =IF(Debt!Q67>Inputs!$F$29,Waterfall!Q10/Debt!Q67,"") | ... AU12: =IF(Debt!AU67>Inputs!$F$29,Waterfall!AU10/Debt!AU67,"")
A14: Summary
D15: Minimum dscr_tl, 2022-2025 | E15: x | F15: =IF(SUMPRODUCT(ISNUMBER(Ratios!$J$8:$AU$8)*(Time!$J$4:$AU$4>=2022)*(Time!$J$4:$AU$4<=2025))=0,"",_xlfn.MINIFS(Ratios!$J$8:$AU$8,Time!$J$4:$AU$4,">="&2022,Time!$J$4:$AU$4,"<="&2025))
D16: Average dscr_tl, 2022-2025 | E16: x | F16: =IFERROR(AVERAGEIFS(Ratios!$J$8:$AU$8,Time!$J$4:$AU$4,">="&2022,Time!$J$4:$AU$4,"<="&2025),"")
D17: Minimum dscr_u, 2026-2043 | E17: x | F17: =IF(SUMPRODUCT(ISNUMBER(Ratios!$J$10:$AU$10)*(Time!$J$4:$AU$4>=2026)*(Time!$J$4:$AU$4<=2043))=0,"",_xlfn.MINIFS(Ratios!$J$10:$AU$10,Time!$J$4:$AU$4,">="&2026,Time!$J$4:$AU$4,"<="&2043))
D18: Average dscr_u, 2026-2043 | E18: x | F18: =IFERROR(AVERAGEIFS(Ratios!$J$10:$AU$10,Time!$J$4:$AU$4,">="&2026,Time!$J$4:$AU$4,"<="&2043),"")
D19: Minimum dscr_rf, 2024-2029 | E19: x | F19: =IF(SUMPRODUCT(ISNUMBER(Ratios!$J$9:$AU$9)*(Time!$J$4:$AU$4>=2024)*(Time!$J$4:$AU$4<=2029))=0,"",_xlfn.MINIFS(Ratios!$J$9:$AU$9,Time!$J$4:$AU$4,">="&2024,Time!$J$4:$AU$4,"<="&2029))
D20: Average dscr_rf, 2024-2029 | E20: x | F20: =IFERROR(AVERAGEIFS(Ratios!$J$9:$AU$9,Time!$J$4:$AU$4,">="&2024,Time!$J$4:$AU$4,"<="&2029),"")
D21: Minimum hc_cov, 2023-2031 | E21: x | F21: =IF(SUMPRODUCT(ISNUMBER(Ratios!$J$12:$AU$12)*(Time!$J$4:$AU$4>=2023)*(Time!$J$4:$AU$4<=2031))=0,"",_xlfn.MINIFS(Ratios!$J$12:$AU$12,Time!$J$4:$AU$4,">="&2023,Time!$J$4:$AU$4,"<="&2031))
D22: Average hc_cov, 2023-2031 | E22: x | F22: =IFERROR(AVERAGEIFS(Ratios!$J$12:$AU$12,Time!$J$4:$AU$4,">="&2023,Time!$J$4:$AU$4,"<="&2031),"")

Sheet Returns
A1: Returns: bid valuations by risk bucket and fund returns
A2: Case R, Mesa Corta Renewables. USD m nominal unless stated. Illustrative prices: not ERCOT settlement data and not a forecast.
D4: Year | J4: =Time!J$4 | K4: =Time!K$4 | L4: =Time!L$4 | M4: =Time!M$4 | N4: =Time!N$4 | O4: =Time!O$4 | P4: =Time!P$4 | Q4: =Time!Q$4 | ... AU4: =Time!AU$4
D5: Period end | J5: =Time!J$6 | K5: =Time!K$6 | L5: =Time!L$6 | M5: =Time!M$6 | N5: =Time!N$6 | O5: =Time!O$6 | P5: =Time!P$6 | Q5: =Time!Q$6 | ... AU5: =Time!AU$6
A7: Unlevered discount factors (bucket rates to 2040, terminal rate after)
D8: Years from valuation date (a1_date) | E8: years | J8: =MAX(0,(Time!J$6-Inputs!$F$256)/Inputs!$F$27) | K8: =MAX(0,(Time!K$6-Inputs!$F$256)/Inputs!$F$27) | L8: =MAX(0,(Time!L$6-Inputs!$F$256)/Inputs!$F$27) | M8: =MAX(0,(Time!M$6-Inputs!$F$256)/Inputs!$F$27) | N8: =MAX(0,(Time!N$6-Inputs!$F$256)/Inputs!$F$27) | O8: =MAX(0,(Time!O$6-Inputs!$F$256)/Inputs!$F$27) | P8: =MAX(0,(Time!P$6-Inputs!$F$256)/Inputs!$F$27) | Q8: =MAX(0,(Time!Q$6-Inputs!$F$256)/Inputs!$F$27) | ... AU8: =MAX(0,(Time!AU$6-Inputs!$F$256)/Inputs!$F$27)
D9: Cash flow on or after valuation date | E9: flag | J9: =--(Time!J$6>=Inputs!$F$256) | K9: =--(Time!K$6>=Inputs!$F$256) | L9: =--(Time!L$6>=Inputs!$F$256) | M9: =--(Time!M$6>=Inputs!$F$256) | N9: =--(Time!N$6>=Inputs!$F$256) | O9: =--(Time!O$6>=Inputs!$F$256) | P9: =--(Time!P$6>=Inputs!$F$256) | Q9: =--(Time!Q$6>=Inputs!$F$256) | ... AU9: =--(Time!AU$6>=Inputs!$F$256)
D10: DF contracted (v1) | E10: factor | J10: =IF(Time!J$4>Inputs!$F$335,(1+Inputs!$F$334/100)^(-Returns!J8),(1+Inputs!$F$330/100)^(-Returns!J8))*Returns!J9 | K10: =IF(Time!K$4>Inputs!$F$335,(1+Inputs!$F$334/100)^(-Returns!K8),(1+Inputs!$F$330/100)^(-Returns!K8))*Returns!K9 | L10: =IF(Time!L$4>Inputs!$F$335,(1+Inputs!$F$334/100)^(-Returns!L8),(1+Inputs!$F$330/100)^(-Returns!L8))*Returns!L9 | M10: =IF(Time!M$4>Inputs!$F$335,(1+Inputs!$F$334/100)^(-Returns!M8),(1+Inputs!$F$330/100)^(-Returns!M8))*Returns!M9 | N10: =IF(Time!N$4>Inputs!$F$335,(1+Inputs!$F$334/100)^(-Returns!N8),(1+Inputs!$F$330/100)^(-Returns!N8))*Returns!N9 | O10: =IF(Time!O$4>Inputs!$F$335,(1+Inputs!$F$334/100)^(-Returns!O8),(1+Inputs!$F$330/100)^(-Returns!O8))*Returns!O9 | P10: =IF(Time!P$4>Inputs!$F$335,(1+Inputs!$F$334/100)^(-Returns!P8),(1+Inputs!$F$330/100)^(-Returns!P8))*Returns!P9 | Q10: =IF(Time!Q$4>Inputs!$F$335,(1+Inputs!$F$334/100)^(-Returns!Q8),(1+Inputs!$F$330/100)^(-Returns!Q8))*Returns!Q9 | ... AU10: =IF(Time!AU$4>Inputs!$F$335,(1+Inputs!$F$334/100)^(-Returns!AU8),(1+Inputs!$F$330/100)^(-Returns!AU8))*Returns!AU9
D11: DF hedged (v1) | E11: factor | J11: =IF(Time!J$4>Inputs!$F$335,(1+Inputs!$F$334/100)^(-Returns!J8),(1+Inputs!$F$331/100)^(-Returns!J8))*Returns!J9 | K11: =IF(Time!K$4>Inputs!$F$335,(1+Inputs!$F$334/100)^(-Returns!K8),(1+Inputs!$F$331/100)^(-Returns!K8))*Returns!K9 | L11: =IF(Time!L$4>Inputs!$F$335,(1+Inputs!$F$334/100)^(-Returns!L8),(1+Inputs!$F$331/100)^(-Returns!L8))*Returns!L9 | M11: =IF(Time!M$4>Inputs!$F$335,(1+Inputs!$F$334/100)^(-Returns!M8),(1+Inputs!$F$331/100)^(-Returns!M8))*Returns!M9 | N11: =IF(Time!N$4>Inputs!$F$335,(1+Inputs!$F$334/100)^(-Returns!N8),(1+Inputs!$F$331/100)^(-Returns!N8))*Returns!N9 | O11: =IF(Time!O$4>Inputs!$F$335,(1+Inputs!$F$334/100)^(-Returns!O8),(1+Inputs!$F$331/100)^(-Returns!O8))*Returns!O9 | P11: =IF(Time!P$4>Inputs!$F$335,(1+Inputs!$F$334/100)^(-Returns!P8),(1+Inputs!$F$331/100)^(-Returns!P8))*Returns!P9 | Q11: =IF(Time!Q$4>Inputs!$F$335,(1+Inputs!$F$334/100)^(-Returns!Q8),(1+Inputs!$F$331/100)^(-Returns!Q8))*Returns!Q9 | ... AU11: =IF(Time!AU$4>Inputs!$F$335,(1+Inputs!$F$334/100)^(-Returns!AU8),(1+Inputs!$F$331/100)^(-Returns!AU8))*Returns!AU9
D12: DF merchant (v1) | E12: factor | J12: =IF(Time!J$4>Inputs!$F$335,(1+Inputs!$F$334/100)^(-Returns!J8),(1+Inputs!$F$332/100)^(-Returns!J8))*Returns!J9 | K12: =IF(Time!K$4>Inputs!$F$335,(1+Inputs!$F$334/100)^(-Returns!K8),(1+Inputs!$F$332/100)^(-Returns!K8))*Returns!K9 | L12: =IF(Time!L$4>Inputs!$F$335,(1+Inputs!$F$334/100)^(-Returns!L8),(1+Inputs!$F$332/100)^(-Returns!L8))*Returns!L9 | M12: =IF(Time!M$4>Inputs!$F$335,(1+Inputs!$F$334/100)^(-Returns!M8),(1+Inputs!$F$332/100)^(-Returns!M8))*Returns!M9 | N12: =IF(Time!N$4>Inputs!$F$335,(1+Inputs!$F$334/100)^(-Returns!N8),(1+Inputs!$F$332/100)^(-Returns!N8))*Returns!N9 | O12: =IF(Time!O$4>Inputs!$F$335,(1+Inputs!$F$334/100)^(-Returns!O8),(1+Inputs!$F$332/100)^(-Returns!O8))*Returns!O9 | P12: =IF(Time!P$4>Inputs!$F$335,(1+Inputs!$F$334/100)^(-Returns!P8),(1+Inputs!$F$332/100)^(-Returns!P8))*Returns!P9 | Q12: =IF(Time!Q$4>Inputs!$F$335,(1+Inputs!$F$334/100)^(-Returns!Q8),(1+Inputs!$F$332/100)^(-Returns!Q8))*Returns!Q9 | ... AU12: =IF(Time!AU$4>Inputs!$F$335,(1+Inputs!$F$334/100)^(-Returns!AU8),(1+Inputs!$F$332/100)^(-Returns!AU8))*Returns!AU9
D13: DF storage_merchant (v1) | E13: factor | J13: =IF(Time!J$4>Inputs!$F$335,(1+Inputs!$F$334/100)^(-Returns!J8),(1+Inputs!$F$333/100)^(-Returns!J8))*Returns!J9 | K13: =IF(Time!K$4>Inputs!$F$335,(1+Inputs!$F$334/100)^(-Returns!K8),(1+Inputs!$F$333/100)^(-Returns!K8))*Returns!K9 | L13: =IF(Time!L$4>Inputs!$F$335,(1+Inputs!$F$334/100)^(-Returns!L8),(1+Inputs!$F$333/100)^(-Returns!L8))*Returns!L9 | M13: =IF(Time!M$4>Inputs!$F$335,(1+Inputs!$F$334/100)^(-Returns!M8),(1+Inputs!$F$333/100)^(-Returns!M8))*Returns!M9 | N13: =IF(Time!N$4>Inputs!$F$335,(1+Inputs!$F$334/100)^(-Returns!N8),(1+Inputs!$F$333/100)^(-Returns!N8))*Returns!N9 | O13: =IF(Time!O$4>Inputs!$F$335,(1+Inputs!$F$334/100)^(-Returns!O8),(1+Inputs!$F$333/100)^(-Returns!O8))*Returns!O9 | P13: =IF(Time!P$4>Inputs!$F$335,(1+Inputs!$F$334/100)^(-Returns!P8),(1+Inputs!$F$333/100)^(-Returns!P8))*Returns!P9 | Q13: =IF(Time!Q$4>Inputs!$F$335,(1+Inputs!$F$334/100)^(-Returns!Q8),(1+Inputs!$F$333/100)^(-Returns!Q8))*Returns!Q9 | ... AU13: =IF(Time!AU$4>Inputs!$F$335,(1+Inputs!$F$334/100)^(-Returns!AU8),(1+Inputs!$F$333/100)^(-Returns!AU8))*Returns!AU9
D14: DF tax shield at contracted rate (v1) | E14: factor | J14: =(1+Inputs!$F$330/100)^(-Returns!J8)*Returns!J9 | K14: =(1+Inputs!$F$330/100)^(-Returns!K8)*Returns!K9 | L14: =(1+Inputs!$F$330/100)^(-Returns!L8)*Returns!L9 | M14: =(1+Inputs!$F$330/100)^(-Returns!M8)*Returns!M9 | N14: =(1+Inputs!$F$330/100)^(-Returns!N8)*Returns!N9 | O14: =(1+Inputs!$F$330/100)^(-Returns!O8)*Returns!O9 | P14: =(1+Inputs!$F$330/100)^(-Returns!P8)*Returns!P9 | Q14: =(1+Inputs!$F$330/100)^(-Returns!Q8)*Returns!Q9 | ... AU14: =(1+Inputs!$F$330/100)^(-Returns!AU8)*Returns!AU9
D15: Years from valuation date (a2_date) | E15: years | J15: =MAX(0,(Time!J$6-Inputs!$F$259)/Inputs!$F$27) | K15: =MAX(0,(Time!K$6-Inputs!$F$259)/Inputs!$F$27) | L15: =MAX(0,(Time!L$6-Inputs!$F$259)/Inputs!$F$27) | M15: =MAX(0,(Time!M$6-Inputs!$F$259)/Inputs!$F$27) | N15: =MAX(0,(Time!N$6-Inputs!$F$259)/Inputs!$F$27) | O15: =MAX(0,(Time!O$6-Inputs!$F$259)/Inputs!$F$27) | P15: =MAX(0,(Time!P$6-Inputs!$F$259)/Inputs!$F$27) | Q15: =MAX(0,(Time!Q$6-Inputs!$F$259)/Inputs!$F$27) | ... AU15: =MAX(0,(Time!AU$6-Inputs!$F$259)/Inputs!$F$27)
D16: Cash flow on or after valuation date | E16: flag | J16: =--(Time!J$6>=Inputs!$F$259) | K16: =--(Time!K$6>=Inputs!$F$259) | L16: =--(Time!L$6>=Inputs!$F$259) | M16: =--(Time!M$6>=Inputs!$F$259) | N16: =--(Time!N$6>=Inputs!$F$259) | O16: =--(Time!O$6>=Inputs!$F$259) | P16: =--(Time!P$6>=Inputs!$F$259) | Q16: =--(Time!Q$6>=Inputs!$F$259) | ... AU16: =--(Time!AU$6>=Inputs!$F$259)
D17: DF contracted (v2) | E17: factor | J17: =IF(Time!J$4>Inputs!$F$335,(1+Inputs!$F$334/100)^(-Returns!J15),(1+Inputs!$F$330/100)^(-Returns!J15))*Returns!J16 | K17: =IF(Time!K$4>Inputs!$F$335,(1+Inputs!$F$334/100)^(-Returns!K15),(1+Inputs!$F$330/100)^(-Returns!K15))*Returns!K16 | L17: =IF(Time!L$4>Inputs!$F$335,(1+Inputs!$F$334/100)^(-Returns!L15),(1+Inputs!$F$330/100)^(-Returns!L15))*Returns!L16 | M17: =IF(Time!M$4>Inputs!$F$335,(1+Inputs!$F$334/100)^(-Returns!M15),(1+Inputs!$F$330/100)^(-Returns!M15))*Returns!M16 | N17: =IF(Time!N$4>Inputs!$F$335,(1+Inputs!$F$334/100)^(-Returns!N15),(1+Inputs!$F$330/100)^(-Returns!N15))*Returns!N16 | O17: =IF(Time!O$4>Inputs!$F$335,(1+Inputs!$F$334/100)^(-Returns!O15),(1+Inputs!$F$330/100)^(-Returns!O15))*Returns!O16 | P17: =IF(Time!P$4>Inputs!$F$335,(1+Inputs!$F$334/100)^(-Returns!P15),(1+Inputs!$F$330/100)^(-Returns!P15))*Returns!P16 | Q17: =IF(Time!Q$4>Inputs!$F$335,(1+Inputs!$F$334/100)^(-Returns!Q15),(1+Inputs!$F$330/100)^(-Returns!Q15))*Returns!Q16 | ... AU17: =IF(Time!AU$4>Inputs!$F$335,(1+Inputs!$F$334/100)^(-Returns!AU15),(1+Inputs!$F$330/100)^(-Returns!AU15))*Returns!AU16
D18: DF hedged (v2) | E18: factor | J18: =IF(Time!J$4>Inputs!$F$335,(1+Inputs!$F$334/100)^(-Returns!J15),(1+Inputs!$F$331/100)^(-Returns!J15))*Returns!J16 | K18: =IF(Time!K$4>Inputs!$F$335,(1+Inputs!$F$334/100)^(-Returns!K15),(1+Inputs!$F$331/100)^(-Returns!K15))*Returns!K16 | L18: =IF(Time!L$4>Inputs!$F$335,(1+Inputs!$F$334/100)^(-Returns!L15),(1+Inputs!$F$331/100)^(-Returns!L15))*Returns!L16 | M18: =IF(Time!M$4>Inputs!$F$335,(1+Inputs!$F$334/100)^(-Returns!M15),(1+Inputs!$F$331/100)^(-Returns!M15))*Returns!M16 | N18: =IF(Time!N$4>Inputs!$F$335,(1+Inputs!$F$334/100)^(-Returns!N15),(1+Inputs!$F$331/100)^(-Returns!N15))*Returns!N16 | O18: =IF(Time!O$4>Inputs!$F$335,(1+Inputs!$F$334/100)^(-Returns!O15),(1+Inputs!$F$331/100)^(-Returns!O15))*Returns!O16 | P18: =IF(Time!P$4>Inputs!$F$335,(1+Inputs!$F$334/100)^(-Returns!P15),(1+Inputs!$F$331/100)^(-Returns!P15))*Returns!P16 | Q18: =IF(Time!Q$4>Inputs!$F$335,(1+Inputs!$F$334/100)^(-Returns!Q15),(1+Inputs!$F$331/100)^(-Returns!Q15))*Returns!Q16 | ... AU18: =IF(Time!AU$4>Inputs!$F$335,(1+Inputs!$F$334/100)^(-Returns!AU15),(1+Inputs!$F$331/100)^(-Returns!AU15))*Returns!AU16
D19: DF merchant (v2) | E19: factor | J19: =IF(Time!J$4>Inputs!$F$335,(1+Inputs!$F$334/100)^(-Returns!J15),(1+Inputs!$F$332/100)^(-Returns!J15))*Returns!J16 | K19: =IF(Time!K$4>Inputs!$F$335,(1+Inputs!$F$334/100)^(-Returns!K15),(1+Inputs!$F$332/100)^(-Returns!K15))*Returns!K16 | L19: =IF(Time!L$4>Inputs!$F$335,(1+Inputs!$F$334/100)^(-Returns!L15),(1+Inputs!$F$332/100)^(-Returns!L15))*Returns!L16 | M19: =IF(Time!M$4>Inputs!$F$335,(1+Inputs!$F$334/100)^(-Returns!M15),(1+Inputs!$F$332/100)^(-Returns!M15))*Returns!M16 | N19: =IF(Time!N$4>Inputs!$F$335,(1+Inputs!$F$334/100)^(-Returns!N15),(1+Inputs!$F$332/100)^(-Returns!N15))*Returns!N16 | O19: =IF(Time!O$4>Inputs!$F$335,(1+Inputs!$F$334/100)^(-Returns!O15),(1+Inputs!$F$332/100)^(-Returns!O15))*Returns!O16 | P19: =IF(Time!P$4>Inputs!$F$335,(1+Inputs!$F$334/100)^(-Returns!P15),(1+Inputs!$F$332/100)^(-Returns!P15))*Returns!P16 | Q19: =IF(Time!Q$4>Inputs!$F$335,(1+Inputs!$F$334/100)^(-Returns!Q15),(1+Inputs!$F$332/100)^(-Returns!Q15))*Returns!Q16 | ... AU19: =IF(Time!AU$4>Inputs!$F$335,(1+Inputs!$F$334/100)^(-Returns!AU15),(1+Inputs!$F$332/100)^(-Returns!AU15))*Returns!AU16
D20: DF storage_merchant (v2) | E20: factor | J20: =IF(Time!J$4>Inputs!$F$335,(1+Inputs!$F$334/100)^(-Returns!J15),(1+Inputs!$F$333/100)^(-Returns!J15))*Returns!J16 | K20: =IF(Time!K$4>Inputs!$F$335,(1+Inputs!$F$334/100)^(-Returns!K15),(1+Inputs!$F$333/100)^(-Returns!K15))*Returns!K16 | L20: =IF(Time!L$4>Inputs!$F$335,(1+Inputs!$F$334/100)^(-Returns!L15),(1+Inputs!$F$333/100)^(-Returns!L15))*Returns!L16 | M20: =IF(Time!M$4>Inputs!$F$335,(1+Inputs!$F$334/100)^(-Returns!M15),(1+Inputs!$F$333/100)^(-Returns!M15))*Returns!M16 | N20: =IF(Time!N$4>Inputs!$F$335,(1+Inputs!$F$334/100)^(-Returns!N15),(1+Inputs!$F$333/100)^(-Returns!N15))*Returns!N16 | O20: =IF(Time!O$4>Inputs!$F$335,(1+Inputs!$F$334/100)^(-Returns!O15),(1+Inputs!$F$333/100)^(-Returns!O15))*Returns!O16 | P20: =IF(Time!P$4>Inputs!$F$335,(1+Inputs!$F$334/100)^(-Returns!P15),(1+Inputs!$F$333/100)^(-Returns!P15))*Returns!P16 | Q20: =IF(Time!Q$4>Inputs!$F$335,(1+Inputs!$F$334/100)^(-Returns!Q15),(1+Inputs!$F$333/100)^(-Returns!Q15))*Returns!Q16 | ... AU20: =IF(Time!AU$4>Inputs!$F$335,(1+Inputs!$F$334/100)^(-Returns!AU15),(1+Inputs!$F$333/100)^(-Returns!AU15))*Returns!AU16
D21: DF tax shield at contracted rate (v2) | E21: factor | J21: =(1+Inputs!$F$330/100)^(-Returns!J15)*Returns!J16 | K21: =(1+Inputs!$F$330/100)^(-Returns!K15)*Returns!K16 | L21: =(1+Inputs!$F$330/100)^(-Returns!L15)*Returns!L16 | M21: =(1+Inputs!$F$330/100)^(-Returns!M15)*Returns!M16 | N21: =(1+Inputs!$F$330/100)^(-Returns!N15)*Returns!N16 | O21: =(1+Inputs!$F$330/100)^(-Returns!O15)*Returns!O16 | P21: =(1+Inputs!$F$330/100)^(-Returns!P15)*Returns!P16 | Q21: =(1+Inputs!$F$330/100)^(-Returns!Q15)*Returns!Q16 | ... AU21: =(1+Inputs!$F$330/100)^(-Returns!AU15)*Returns!AU16
D22: Years from valuation date (a3_date) | E22: years | J22: =MAX(0,(Time!J$6-Inputs!$F$262)/Inputs!$F$27) | K22: =MAX(0,(Time!K$6-Inputs!$F$262)/Inputs!$F$27) | L22: =MAX(0,(Time!L$6-Inputs!$F$262)/Inputs!$F$27) | M22: =MAX(0,(Time!M$6-Inputs!$F$262)/Inputs!$F$27) | N22: =MAX(0,(Time!N$6-Inputs!$F$262)/Inputs!$F$27) | O22: =MAX(0,(Time!O$6-Inputs!$F$262)/Inputs!$F$27) | P22: =MAX(0,(Time!P$6-Inputs!$F$262)/Inputs!$F$27) | Q22: =MAX(0,(Time!Q$6-Inputs!$F$262)/Inputs!$F$27) | ... AU22: =MAX(0,(Time!AU$6-Inputs!$F$262)/Inputs!$F$27)
D23: Cash flow on or after valuation date | E23: flag | J23: =--(Time!J$6>=Inputs!$F$262) | K23: =--(Time!K$6>=Inputs!$F$262) | L23: =--(Time!L$6>=Inputs!$F$262) | M23: =--(Time!M$6>=Inputs!$F$262) | N23: =--(Time!N$6>=Inputs!$F$262) | O23: =--(Time!O$6>=Inputs!$F$262) | P23: =--(Time!P$6>=Inputs!$F$262) | Q23: =--(Time!Q$6>=Inputs!$F$262) | ... AU23: =--(Time!AU$6>=Inputs!$F$262)
D24: DF contracted (v3) | E24: factor | J24: =IF(Time!J$4>Inputs!$F$335,(1+Inputs!$F$334/100)^(-Returns!J22),(1+Inputs!$F$330/100)^(-Returns!J22))*Returns!J23 | K24: =IF(Time!K$4>Inputs!$F$335,(1+Inputs!$F$334/100)^(-Returns!K22),(1+Inputs!$F$330/100)^(-Returns!K22))*Returns!K23 | L24: =IF(Time!L$4>Inputs!$F$335,(1+Inputs!$F$334/100)^(-Returns!L22),(1+Inputs!$F$330/100)^(-Returns!L22))*Returns!L23 | M24: =IF(Time!M$4>Inputs!$F$335,(1+Inputs!$F$334/100)^(-Returns!M22),(1+Inputs!$F$330/100)^(-Returns!M22))*Returns!M23 | N24: =IF(Time!N$4>Inputs!$F$335,(1+Inputs!$F$334/100)^(-Returns!N22),(1+Inputs!$F$330/100)^(-Returns!N22))*Returns!N23 | O24: =IF(Time!O$4>Inputs!$F$335,(1+Inputs!$F$334/100)^(-Returns!O22),(1+Inputs!$F$330/100)^(-Returns!O22))*Returns!O23 | P24: =IF(Time!P$4>Inputs!$F$335,(1+Inputs!$F$334/100)^(-Returns!P22),(1+Inputs!$F$330/100)^(-Returns!P22))*Returns!P23 | Q24: =IF(Time!Q$4>Inputs!$F$335,(1+Inputs!$F$334/100)^(-Returns!Q22),(1+Inputs!$F$330/100)^(-Returns!Q22))*Returns!Q23 | ... AU24: =IF(Time!AU$4>Inputs!$F$335,(1+Inputs!$F$334/100)^(-Returns!AU22),(1+Inputs!$F$330/100)^(-Returns!AU22))*Returns!AU23
D25: DF hedged (v3) | E25: factor | J25: =IF(Time!J$4>Inputs!$F$335,(1+Inputs!$F$334/100)^(-Returns!J22),(1+Inputs!$F$331/100)^(-Returns!J22))*Returns!J23 | K25: =IF(Time!K$4>Inputs!$F$335,(1+Inputs!$F$334/100)^(-Returns!K22),(1+Inputs!$F$331/100)^(-Returns!K22))*Returns!K23 | L25: =IF(Time!L$4>Inputs!$F$335,(1+Inputs!$F$334/100)^(-Returns!L22),(1+Inputs!$F$331/100)^(-Returns!L22))*Returns!L23 | M25: =IF(Time!M$4>Inputs!$F$335,(1+Inputs!$F$334/100)^(-Returns!M22),(1+Inputs!$F$331/100)^(-Returns!M22))*Returns!M23 | N25: =IF(Time!N$4>Inputs!$F$335,(1+Inputs!$F$334/100)^(-Returns!N22),(1+Inputs!$F$331/100)^(-Returns!N22))*Returns!N23 | O25: =IF(Time!O$4>Inputs!$F$335,(1+Inputs!$F$334/100)^(-Returns!O22),(1+Inputs!$F$331/100)^(-Returns!O22))*Returns!O23 | P25: =IF(Time!P$4>Inputs!$F$335,(1+Inputs!$F$334/100)^(-Returns!P22),(1+Inputs!$F$331/100)^(-Returns!P22))*Returns!P23 | Q25: =IF(Time!Q$4>Inputs!$F$335,(1+Inputs!$F$334/100)^(-Returns!Q22),(1+Inputs!$F$331/100)^(-Returns!Q22))*Returns!Q23 | ... AU25: =IF(Time!AU$4>Inputs!$F$335,(1+Inputs!$F$334/100)^(-Returns!AU22),(1+Inputs!$F$331/100)^(-Returns!AU22))*Returns!AU23
D26: DF merchant (v3) | E26: factor | J26: =IF(Time!J$4>Inputs!$F$335,(1+Inputs!$F$334/100)^(-Returns!J22),(1+Inputs!$F$332/100)^(-Returns!J22))*Returns!J23 | K26: =IF(Time!K$4>Inputs!$F$335,(1+Inputs!$F$334/100)^(-Returns!K22),(1+Inputs!$F$332/100)^(-Returns!K22))*Returns!K23 | L26: =IF(Time!L$4>Inputs!$F$335,(1+Inputs!$F$334/100)^(-Returns!L22),(1+Inputs!$F$332/100)^(-Returns!L22))*Returns!L23 | M26: =IF(Time!M$4>Inputs!$F$335,(1+Inputs!$F$334/100)^(-Returns!M22),(1+Inputs!$F$332/100)^(-Returns!M22))*Returns!M23 | N26: =IF(Time!N$4>Inputs!$F$335,(1+Inputs!$F$334/100)^(-Returns!N22),(1+Inputs!$F$332/100)^(-Returns!N22))*Returns!N23 | O26: =IF(Time!O$4>Inputs!$F$335,(1+Inputs!$F$334/100)^(-Returns!O22),(1+Inputs!$F$332/100)^(-Returns!O22))*Returns!O23 | P26: =IF(Time!P$4>Inputs!$F$335,(1+Inputs!$F$334/100)^(-Returns!P22),(1+Inputs!$F$332/100)^(-Returns!P22))*Returns!P23 | Q26: =IF(Time!Q$4>Inputs!$F$335,(1+Inputs!$F$334/100)^(-Returns!Q22),(1+Inputs!$F$332/100)^(-Returns!Q22))*Returns!Q23 | ... AU26: =IF(Time!AU$4>Inputs!$F$335,(1+Inputs!$F$334/100)^(-Returns!AU22),(1+Inputs!$F$332/100)^(-Returns!AU22))*Returns!AU23
D27: DF storage_merchant (v3) | E27: factor | J27: =IF(Time!J$4>Inputs!$F$335,(1+Inputs!$F$334/100)^(-Returns!J22),(1+Inputs!$F$333/100)^(-Returns!J22))*Returns!J23 | K27: =IF(Time!K$4>Inputs!$F$335,(1+Inputs!$F$334/100)^(-Returns!K22),(1+Inputs!$F$333/100)^(-Returns!K22))*Returns!K23 | L27: =IF(Time!L$4>Inputs!$F$335,(1+Inputs!$F$334/100)^(-Returns!L22),(1+Inputs!$F$333/100)^(-Returns!L22))*Returns!L23 | M27: =IF(Time!M$4>Inputs!$F$335,(1+Inputs!$F$334/100)^(-Returns!M22),(1+Inputs!$F$333/100)^(-Returns!M22))*Returns!M23 | N27: =IF(Time!N$4>Inputs!$F$335,(1+Inputs!$F$334/100)^(-Returns!N22),(1+Inputs!$F$333/100)^(-Returns!N22))*Returns!N23 | O27: =IF(Time!O$4>Inputs!$F$335,(1+Inputs!$F$334/100)^(-Returns!O22),(1+Inputs!$F$333/100)^(-Returns!O22))*Returns!O23 | P27: =IF(Time!P$4>Inputs!$F$335,(1+Inputs!$F$334/100)^(-Returns!P22),(1+Inputs!$F$333/100)^(-Returns!P22))*Returns!P23 | Q27: =IF(Time!Q$4>Inputs!$F$335,(1+Inputs!$F$334/100)^(-Returns!Q22),(1+Inputs!$F$333/100)^(-Returns!Q22))*Returns!Q23 | ... AU27: =IF(Time!AU$4>Inputs!$F$335,(1+Inputs!$F$334/100)^(-Returns!AU22),(1+Inputs!$F$333/100)^(-Returns!AU22))*Returns!AU23
D28: DF tax shield at contracted rate (v3) | E28: factor | J28: =(1+Inputs!$F$330/100)^(-Returns!J22)*Returns!J23 | K28: =(1+Inputs!$F$330/100)^(-Returns!K22)*Returns!K23 | L28: =(1+Inputs!$F$330/100)^(-Returns!L22)*Returns!L23 | M28: =(1+Inputs!$F$330/100)^(-Returns!M22)*Returns!M23 | N28: =(1+Inputs!$F$330/100)^(-Returns!N22)*Returns!N23 | O28: =(1+Inputs!$F$330/100)^(-Returns!O22)*Returns!O23 | P28: =(1+Inputs!$F$330/100)^(-Returns!P22)*Returns!P23 | Q28: =(1+Inputs!$F$330/100)^(-Returns!Q22)*Returns!Q23 | ... AU28: =(1+Inputs!$F$330/100)^(-Returns!AU22)*Returns!AU23
A30: A1 valuation at March 22, 2022 (R-F04)
D31: R1 value: contracted | E31: USD m | F31: =SUMPRODUCT(Operations!$J$96:$AU$96,Operations!$J$97:$AU$97,Returns!$J$10:$AU$10)
D32: R1 value: hedged | E32: USD m | F32: =SUMPRODUCT(Operations!$J$96:$AU$96,Operations!$J$98:$AU$98,Returns!$J$11:$AU$11)
D33: R1 value: merchant | E33: USD m | F33: =SUMPRODUCT(Operations!$J$96:$AU$96,Operations!$J$99:$AU$99,Returns!$J$12:$AU$12)
D34: R1 value: total | E34: USD m | F34: =Returns!$F$31+Returns!$F$32+Returns!$F$33
D35: R2 value: contracted | E35: USD m | F35: =SUMPRODUCT(Operations!$J$138:$AU$138,Operations!$J$139:$AU$139,Returns!$J$10:$AU$10)
D36: R2 value: hedged | E36: USD m | F36: =SUMPRODUCT(Operations!$J$138:$AU$138,Operations!$J$140:$AU$140,Returns!$J$11:$AU$11)
D37: R2 value: merchant | E37: USD m | F37: =SUMPRODUCT(Operations!$J$138:$AU$138,Operations!$J$141:$AU$141,Returns!$J$12:$AU$12)
D38: R2 value: total | E38: USD m | F38: =Returns!$F$35+Returns!$F$36+Returns!$F$37
D39: R3 value: contracted | E39: USD m | F39: =SUMPRODUCT(Operations!$J$181:$AU$181,Operations!$J$182:$AU$182,Returns!$J$10:$AU$10)
D40: R3 value: hedged | E40: USD m | F40: =SUMPRODUCT(Operations!$J$181:$AU$181,Operations!$J$183:$AU$183,Returns!$J$11:$AU$11)
D41: R3 value: merchant | E41: USD m | F41: =SUMPRODUCT(Operations!$J$181:$AU$181,Operations!$J$184:$AU$184,Returns!$J$12:$AU$12)
D42: R3 value: total | E42: USD m | F42: =Returns!$F$39+Returns!$F$40+Returns!$F$41
D43: R4 value: contracted | E43: USD m | F43: =SUMPRODUCT(Operations!$J$224:$AU$224,Operations!$J$225:$AU$225,Returns!$J$10:$AU$10)
D44: R4 value: hedged | E44: USD m | F44: =SUMPRODUCT(Operations!$J$224:$AU$224,Operations!$J$226:$AU$226,Returns!$J$11:$AU$11)
D45: R4 value: merchant | E45: USD m | F45: =SUMPRODUCT(Operations!$J$224:$AU$224,Operations!$J$227:$AU$227,Returns!$J$12:$AU$12)
D46: R4 value: total | E46: USD m | F46: =Returns!$F$43+Returns!$F$44+Returns!$F$45
D47: R5 value: contracted | E47: USD m | F47: =SUMPRODUCT(Operations!$J$267:$AU$267,Operations!$J$268:$AU$268,Returns!$J$10:$AU$10)
D48: R5 value: hedged | E48: USD m | F48: =SUMPRODUCT(Operations!$J$267:$AU$267,Operations!$J$269:$AU$269,Returns!$J$11:$AU$11)
D49: R5 value: merchant | E49: USD m | F49: =SUMPRODUCT(Operations!$J$267:$AU$267,Operations!$J$270:$AU$270,Returns!$J$12:$AU$12)
D50: R5 value: total | E50: USD m | F50: =Returns!$F$47+Returns!$F$48+Returns!$F$49
D51: Platform cost after tax | E51: USD m | J51: =-Operations!J384*(1-Inputs!$F$241/100) | K51: =-Operations!K384*(1-Inputs!$F$241/100) | L51: =-Operations!L384*(1-Inputs!$F$241/100) | M51: =-Operations!M384*(1-Inputs!$F$241/100) | N51: =-Operations!N384*(1-Inputs!$F$241/100) | O51: =-Operations!O384*(1-Inputs!$F$241/100) | P51: =-Operations!P384*(1-Inputs!$F$241/100) | Q51: =-Operations!Q384*(1-Inputs!$F$241/100) | ... AU51: =-Operations!AU384*(1-Inputs!$F$241/100)
D52: Platform costs value: contracted | E52: USD m | F52: =SUMPRODUCT(Returns!$J$51:$AU$51,Operations!$J$403:$AU$403,Returns!$J$10:$AU$10)
D53: Platform costs value: hedged | E53: USD m | F53: =SUMPRODUCT(Returns!$J$51:$AU$51,Operations!$J$404:$AU$404,Returns!$J$11:$AU$11)
D54: Platform costs value: merchant | E54: USD m | F54: =SUMPRODUCT(Returns!$J$51:$AU$51,Operations!$J$405:$AU$405,Returns!$J$12:$AU$12)
D55: Platform costs value: total | E55: USD m | F55: =Returns!$F$52+Returns!$F$53+Returns!$F$54
D56: A1 value by bucket: contracted | E56: USD m | F56: =Returns!$F$31+Returns!$F$35+Returns!$F$39+Returns!$F$43+Returns!$F$47+Returns!$F$52
D57: A1 value by bucket: hedged | E57: USD m | F57: =Returns!$F$32+Returns!$F$36+Returns!$F$40+Returns!$F$44+Returns!$F$48+Returns!$F$53
D58: A1 value by bucket: merchant | E58: USD m | F58: =Returns!$F$33+Returns!$F$37+Returns!$F$41+Returns!$F$45+Returns!$F$49+Returns!$F$54
D59: A1 value before purchase-price tax shield | E59: USD m | F59: =Returns!$F$34+Returns!$F$38+Returns!$F$42+Returns!$F$46+Returns!$F$50+Returns!$F$55
D60: PV of A1 tax depreciation per USD of price | E60: factor | F60: =SUMPRODUCT(Tax!$J$14:$AU$14,Returns!$J$14:$AU$14)/Inputs!$F$257
D61: Tax shield at the price paid | E61: USD m | F61: =Inputs!$F$241/100*Returns!$F$60*Inputs!$F$257
D62: A1 enterprise value | E62: USD m | F62: =Returns!$F$59+Returns!$F$61
D63: Value less price | E63: USD m | F63: =Returns!$F$62-Inputs!$F$257
D64: Breakeven price (closed form) | E64: USD m | F64: =Returns!$F$59/(1-Inputs!$F$241/100*Returns!$F$60)
A66: A2 valuation at August 31, 2023 (R-F07)
D67: R6 value: contracted | E67: USD m | F67: =SUMPRODUCT(Operations!$J$299:$AU$299,Operations!$J$300:$AU$300,Returns!$J$17:$AU$17)
D68: R6 value: hedged | E68: USD m | F68: =SUMPRODUCT(Operations!$J$299:$AU$299,Operations!$J$301:$AU$301,Returns!$J$18:$AU$18)
D69: R6 value: merchant | E69: USD m | F69: =SUMPRODUCT(Operations!$J$299:$AU$299,Operations!$J$302:$AU$302,Returns!$J$20:$AU$20)
D70: R6 value: total | E70: USD m | F70: =Returns!$F$67+Returns!$F$68+Returns!$F$69
D71: PV of A2 tax depreciation per USD of price | E71: factor | F71: =SUMPRODUCT(Tax!$J$17:$AU$17,Returns!$J$21:$AU$21)/Inputs!$F$260
D72: Tax shield at the price paid | E72: USD m | F72: =Inputs!$F$241/100*Returns!$F$71*Inputs!$F$260
D73: A2 value | E73: USD m | F73: =Returns!$F$70+Returns!$F$72
D74: Value less price | E74: USD m | F74: =Returns!$F$73-Inputs!$F$260
D75: Breakeven price | E75: USD m | F75: =Returns!$F$70/(1-Inputs!$F$241/100*Returns!$F$71)
A77: A3 valuation at February 15, 2024 (R-F07)
D78: R7 value: contracted | E78: USD m | F78: =SUMPRODUCT(Operations!$J$332:$AU$332,Operations!$J$333:$AU$333,Returns!$J$24:$AU$24)
D79: R7 value: hedged | E79: USD m | F79: =SUMPRODUCT(Operations!$J$332:$AU$332,Operations!$J$334:$AU$334,Returns!$J$25:$AU$25)
D80: R7 value: merchant | E80: USD m | F80: =SUMPRODUCT(Operations!$J$332:$AU$332,Operations!$J$335:$AU$335,Returns!$J$27:$AU$27)
D81: R7 value: total | E81: USD m | F81: =Returns!$F$78+Returns!$F$79+Returns!$F$80
D82: R8 value: contracted | E82: USD m | F82: =SUMPRODUCT(Operations!$J$374:$AU$374,Operations!$J$375:$AU$375,Returns!$J$24:$AU$24)
D83: R8 value: hedged | E83: USD m | F83: =SUMPRODUCT(Operations!$J$374:$AU$374,Operations!$J$376:$AU$376,Returns!$J$25:$AU$25)
D84: R8 value: merchant | E84: USD m | F84: =SUMPRODUCT(Operations!$J$374:$AU$374,Operations!$J$377:$AU$377,Returns!$J$26:$AU$26)
D85: R8 value: total | E85: USD m | F85: =Returns!$F$82+Returns!$F$83+Returns!$F$84
D86: Years from signing to R7 COD | E86: years | F86: =(Inputs!$F$156-Inputs!$F$262)/Inputs!$F$27
D87: Years from signing to R8 COD | E87: years | F87: =(Inputs!$F$168-Inputs!$F$262)/Inputs!$F$27
D88: PV of ITC transfer proceeds | E88: USD m | F88: =Funding!$F$156*(1+Inputs!$F$330/100)^(-Returns!$F$86)+Funding!$F$157*(1+Inputs!$F$330/100)^(-Returns!$F$87)
D89: Tax shield on R7 and R8 basis | E89: USD m | F89: =Inputs!$F$241/100*SUMPRODUCT(Tax!$J$20:$AU$20+Tax!$J$23:$AU$23,Returns!$J$28:$AU$28)
D90: A3 value | E90: USD m | F90: =Returns!$F$81+Returns!$F$85+Returns!$F$88+Returns!$F$89
D91: PV of A3 price payments | E91: USD m | F91: =Funding!$F$154+Inputs!$F$263*(1+Inputs!$F$330/100)^(-Returns!$F$86)+(Inputs!$F$264-Funding!$F$154)*(1+Inputs!$F$330/100)^(-Returns!$F$87)
D92: Value less PV of price | E92: USD m | F92: =Returns!$F$90-Returns!$F$91
A94: Fund cash flows (gross of fund fees and carry)
D95: Years from NAV date | E95: years | J95: =MAX(0,(Time!J$6-Inputs!$F$340)/Inputs!$F$27) | K95: =MAX(0,(Time!K$6-Inputs!$F$340)/Inputs!$F$27) | L95: =MAX(0,(Time!L$6-Inputs!$F$340)/Inputs!$F$27) | M95: =MAX(0,(Time!M$6-Inputs!$F$340)/Inputs!$F$27) | N95: =MAX(0,(Time!N$6-Inputs!$F$340)/Inputs!$F$27) | O95: =MAX(0,(Time!O$6-Inputs!$F$340)/Inputs!$F$27) | P95: =MAX(0,(Time!P$6-Inputs!$F$340)/Inputs!$F$27) | Q95: =MAX(0,(Time!Q$6-Inputs!$F$340)/Inputs!$F$27) | ... AU95: =MAX(0,(Time!AU$6-Inputs!$F$340)/Inputs!$F$27)
D96: NAV discount factor (levered rates by portfolio bucket, after NAV date) | E96: factor | J96: =(Time!J$6>Inputs!$F$340)*(Operations!J409*(1+Inputs!$F$336/100)^(-Returns!J95)+Operations!J410*(1+Inputs!$F$337/100)^(-Returns!J95)+Operations!J411*(1+Inputs!$F$338/100)^(-Returns!J95)) | K96: =(Time!K$6>Inputs!$F$340)*(Operations!K409*(1+Inputs!$F$336/100)^(-Returns!K95)+Operations!K410*(1+Inputs!$F$337/100)^(-Returns!K95)+Operations!K411*(1+Inputs!$F$338/100)^(-Returns!K95)) | L96: =(Time!L$6>Inputs!$F$340)*(Operations!L409*(1+Inputs!$F$336/100)^(-Returns!L95)+Operations!L410*(1+Inputs!$F$337/100)^(-Returns!L95)+Operations!L411*(1+Inputs!$F$338/100)^(-Returns!L95)) | M96: =(Time!M$6>Inputs!$F$340)*(Operations!M409*(1+Inputs!$F$336/100)^(-Returns!M95)+Operations!M410*(1+Inputs!$F$337/100)^(-Returns!M95)+Operations!M411*(1+Inputs!$F$338/100)^(-Returns!M95)) | N96: =(Time!N$6>Inputs!$F$340)*(Operations!N409*(1+Inputs!$F$336/100)^(-Returns!N95)+Operations!N410*(1+Inputs!$F$337/100)^(-Returns!N95)+Operations!N411*(1+Inputs!$F$338/100)^(-Returns!N95)) | O96: =(Time!O$6>Inputs!$F$340)*(Operations!O409*(1+Inputs!$F$336/100)^(-Returns!O95)+Operations!O410*(1+Inputs!$F$337/100)^(-Returns!O95)+Operations!O411*(1+Inputs!$F$338/100)^(-Returns!O95)) | P96: =(Time!P$6>Inputs!$F$340)*(Operations!P409*(1+Inputs!$F$336/100)^(-Returns!P95)+Operations!P410*(1+Inputs!$F$337/100)^(-Returns!P95)+Operations!P411*(1+Inputs!$F$338/100)^(-Returns!P95)) | Q96: =(Time!Q$6>Inputs!$F$340)*(Operations!Q409*(1+Inputs!$F$336/100)^(-Returns!Q95)+Operations!Q410*(1+Inputs!$F$337/100)^(-Returns!Q95)+Operations!Q411*(1+Inputs!$F$338/100)^(-Returns!Q95)) | ... AU96: =(Time!AU$6>Inputs!$F$340)*(Operations!AU409*(1+Inputs!$F$336/100)^(-Returns!AU95)+Operations!AU410*(1+Inputs!$F$337/100)^(-Returns!AU95)+Operations!AU411*(1+Inputs!$F$338/100)^(-Returns!AU95))
D97: NAV before floor | E97: USD m | F97: =SUMPRODUCT(Waterfall!$J$22:$AU$22,Returns!$J$96:$AU$96)
D98: NAV at December 31, 2025 (floored at zero) | E98: USD m | F98: =MAX(0,Returns!$F$97)
D99: Fund equity contributed | E99: USD m | F99: =Funding!$F$150+Funding!$F$153+Funding!$F$168
D100: Fund distributions, life | E100: USD m | F100: =SUM(Waterfall!$J$22:$AU$22)
D101: Fund distributions to 2025 | E101: USD m | F101: =SUMIF(Time!$J$4:$AU$4,"<="&Inputs!$F$307,Waterfall!$J$22:$AU$22)
D102: Lifetime multiple | E102: x | F102: =Returns!$F$100/Returns!$F$99
D103: Multiple to 2025 including NAV | E103: x | F103: =(Returns!$F$101+Returns!$F$98)/Returns!$F$99
D105: Dated fund cash flows (life) | E105: Date | F105: USD m | G105: To 2025 incl. NAV
D106: A1 equity | E106: =Inputs!$F$256 | F106: =-Funding!$F$150 | G106: =F106
D107: A2 equity | E107: =Inputs!$F$259 | F107: =-Funding!$F$153 | G107: =F107
...

Sheet Checks
A1: Checks (0 = pass)
A2: Case R, Mesa Corta Renewables. USD m nominal unless stated. Illustrative prices: not ERCOT settlement data and not a forecast.
D4: Year | J4: =Time!J$4 | K4: =Time!K$4 | L4: =Time!L$4 | M4: =Time!M$4 | N4: =Time!N$4 | O4: =Time!O$4 | P4: =Time!P$4 | Q4: =Time!Q$4 | ... AU4: =Time!AU$4
D5: Period end | J5: =Time!J$6 | K5: =Time!K$6 | L5: =Time!L$6 | M5: =Time!M$6 | N5: =Time!N$6 | O5: =Time!O$6 | P5: =Time!P$6 | Q5: =Time!Q$6 | ... AU5: =Time!AU$6
D8: Opco TL sculpted balance repaid by 2040 | E8: USD m | F8: =ROUND(INDEX(Funding!$J$25:$AU$25,38),6)
D9: Redfern sculpted balance repaid by 2030 | E9: USD m | F9: =ROUND(INDEX(Funding!$J$53:$AU$53,38),6)
D10: USPP principal equals notes issued | E10: USD m | F10: =ROUND(Funding!$F$83-SUM(Debt!$J$33:$AU$33),6)
D11: USPP interest plus principal equals sculpted debt service | E11: USD m | F11: =ROUND(SUMPRODUCT(ABS(Debt!$J$32:$AU$32+Debt!$J$33:$AU$33-Debt!$J$34:$AU$34)),6)
D12: A1 sources equal uses | E12: USD m | F12: =ROUND(Funding!$F$17+Funding!$F$41+Funding!$F$150-Funding!$F$149,6)
D13: A3 sources equal uses | E13: USD m | F13: =ROUND(Funding!$F$63+Funding!$F$156+Funding!$F$157+Funding!$F$168-Funding!$F$167,6)
D14: NOL never negative | E14: USD m | F14: =ROUND(MIN(0,MIN(Tax!$J$33:$AU$33)),6)
D15: Debt balances never negative | E15: USD m | F15: =ROUND(MIN(0,MIN(Debt!$J$14:$AU$14),MIN(Debt!$J$23:$AU$23),MIN(Debt!$J$46:$AU$46),MIN(Debt!$J$53:$AU$53),MIN(Debt!$J$60:$AU$60)),6)
D16: Opco TL repaid when refinanced | E16: USD m | F16: =ROUND(Inputs!$F$10*INDEX(Debt!$J$19:$AU$19,38),6)
D17: R1 revenue buckets sum to revenue | E17: USD m | F17: =ROUND(SUMPRODUCT(ABS(Operations!$J$79:$AU$79+Operations!$J$80:$AU$80+Operations!$J$83:$AU$83-Operations!$J$82:$AU$82)),6)
D18: R2 revenue buckets sum to revenue | E18: USD m | F18: =ROUND(SUMPRODUCT(ABS(Operations!$J$121:$AU$121+Operations!$J$122:$AU$122+Operations!$J$125:$AU$125-Operations!$J$124:$AU$124)),6)
D19: R3 revenue buckets sum to revenue | E19: USD m | F19: =ROUND(SUMPRODUCT(ABS(Operations!$J$163:$AU$163+Operations!$J$164:$AU$164+Operations!$J$167:$AU$167-Operations!$J$166:$AU$166)),6)
D20: R4 revenue buckets sum to revenue | E20: USD m | F20: =ROUND(SUMPRODUCT(ABS(Operations!$J$207:$AU$207+Operations!$J$208:$AU$208+Operations!$J$211:$AU$211-Operations!$J$210:$AU$210)),6)
D21: R5 revenue buckets sum to revenue | E21: USD m | F21: =ROUND(SUMPRODUCT(ABS(Operations!$J$249:$AU$249+Operations!$J$250:$AU$250+Operations!$J$253:$AU$253-Operations!$J$252:$AU$252)),6)
D22: R6 revenue buckets sum to revenue | E22: USD m | F22: =ROUND(SUMPRODUCT(ABS(Operations!$J$283:$AU$283+Operations!$J$284:$AU$284+Operations!$J$286:$AU$286-Operations!$J$285:$AU$285)),6)
D23: R7 revenue buckets sum to revenue | E23: USD m | F23: =ROUND(SUMPRODUCT(ABS(Operations!$J$316:$AU$316+Operations!$J$317:$AU$317+Operations!$J$319:$AU$319-Operations!$J$318:$AU$318)),6)
D24: R8 revenue buckets sum to revenue | E24: USD m | F24: =ROUND(SUMPRODUCT(ABS(Operations!$J$357:$AU$357+Operations!$J$358:$AU$358+Operations!$J$361:$AU$361-Operations!$J$360:$AU$360)),6)
D25: Total of absolute check values (0 = all pass) | E25: USD m | F25: =SUMPRODUCT(ABS(F8:F24))

Sheet Outputs
A1: Outputs dashboard
A2: Case R, Mesa Corta Renewables. USD m nominal unless stated. Illustrative prices: not ERCOT settlement data and not a forecast.
D4: Year | J4: =Time!J$4 | K4: =Time!K$4 | L4: =Time!L$4 | M4: =Time!M$4 | N4: =Time!N$4 | O4: =Time!O$4 | P4: =Time!P$4 | Q4: =Time!Q$4 | ... AU4: =Time!AU$4
D5: Period end | J5: =Time!J$6 | K5: =Time!K$6 | L5: =Time!L$6 | M5: =Time!M$6 | N5: =Time!N$6 | O5: =Time!O$6 | P5: =Time!P$6 | Q5: =Time!Q$6 | ... AU5: =Time!AU$6
A7: Selected case
D8: Scenario (1 base, 2 low, 3 high) | E8: index | F8: =Scenario
D9: Volume case | E9: index | F9: =Inputs!$F$9
D10: Refinancing switch | E10: flag | F10: =Inputs!$F$10
A12: Debt sized at each transaction (base, P50, P99 test)
D13: Opco term loan 2022 | E13: USD m | F13: =Funding!$F$17
D14: Holdco TLB 2022 | E14: USD m | F14: =Funding!$F$41
D15: Redfern loan 2023 | E15: USD m | F15: =Funding!$F$50
D16: Holdco incremental 2024 | E16: USD m | F16: =Funding!$F$63
D17: USPP notes 2025 | E17: USD m | F17: =Funding!$F$83
D18: Series A | E18: USD m | F18: =Funding!$F$80
D19: Series B | E19: USD m | F19: =Funding!$F$81
D20: Series C | E20: USD m | F20: =Funding!$F$82
D21: Blended coupon (%) | E21: % | F21: =Funding!$F$87
D22: Repriced holdco TLB 2025 | E22: USD m | F22: =Funding!$F$103
D23: Net opco refinancing proceeds | E23: USD m | F23: =Funding!$F$179
D24: A1 fund equity | E24: USD m | F24: =Funding!$F$150
D25: A2 fund equity | E25: USD m | F25: =Funding!$F$153
D26: A3 fund equity | E26: USD m | F26: =Funding!$F$168
A28: Returns and valuation (selected case)
D29: Fund gross IRR, life (%) | F29: =Returns!$F$150
D30: Fund gross IRR to 2025 incl. NAV (%) | F30: =Returns!$F$151
D31: NAV at December 31, 2025 | F31: =Returns!$F$98
D32: Lifetime multiple | F32: =Returns!$F$102
D33: A1 enterprise value | F33: =Returns!$F$62
D34: A1 breakeven price | F34: =Returns!$F$64
D35: Minimum USPP DSCR 2026-2043 | F35: =Ratios!$F$17
D36: Average USPP DSCR 2026-2043 | F36: =Ratios!$F$18
D37: Minimum opco TL DSCR 2022-2025 | F37: =Ratios!$F$15
D38: Checks total (0 = pass) | F38: =Checks!$F$25
A40: Key series
D41: Portfolio CFADS | E41: USD m | J41: =Operations!J401 | K41: =Operations!K401 | L41: =Operations!L401 | M41: =Operations!M401 | N41: =Operations!N401 | O41: =Operations!O401 | P41: =Operations!P401 | Q41: =Operations!Q401 | ... AU41: =Operations!AU401
D42: Opco debt service | E42: USD m | J42: =Waterfall!J9 | K42: =Waterfall!K9 | L42: =Waterfall!L9 | M42: =Waterfall!M9 | N42: =Waterfall!N9 | O42: =Waterfall!O9 | P42: =Waterfall!P9 | Q42: =Waterfall!Q9 | ... AU42: =Waterfall!AU9
D43: Holdco debt service | E43: USD m | J43: =Debt!J67 | K43: =Debt!K67 | L43: =Debt!L67 | M43: =Debt!M67 | N43: =Debt!N67 | O43: =Debt!O67 | P43: =Debt!P67 | Q43: =Debt!Q67 | ... AU43: =Debt!AU67
D44: Cash tax | E44: USD m | J44: =Tax!J32 | K44: =Tax!K32 | L44: =Tax!L32 | M44: =Tax!M32 | N44: =Tax!N32 | O44: =Tax!O32 | P44: =Tax!P32 | Q44: =Tax!Q32 | ... AU44: =Tax!AU32
D45: Fund distributions | E45: USD m | J45: =Waterfall!J22 | K45: =Waterfall!K22 | L45: =Waterfall!L22 | M45: =Waterfall!M22 | N45: =Waterfall!N22 | O45: =Waterfall!O22 | P45: =Waterfall!P22 | Q45: =Waterfall!Q22 | ... AU45: =Waterfall!AU22
D46: USPP DSCR | E46: x | J46: =Ratios!J10 | K46: =Ratios!K10 | L46: =Ratios!L10 | M46: =Ratios!M10 | N46: =Ratios!N10 | O46: =Ratios!O10 | P46: =Ratios!P10 | Q46: =Ratios!Q10 | ... AU46: =Ratios!AU10
D47: Holdco coverage | E47: x | J47: =Ratios!J12 | K47: =Ratios!K12 | L47: =Ratios!L12 | M47: =Ratios!M12 | N47: =Ratios!N12 | O47: =Ratios!O12 | P47: =Ratios!P12 | Q47: =Ratios!Q12 | ... AU47: =Ratios!AU12
